Workbook
Name _AnnualCashFlowStatement: CFS!$A$2:$K$42
Name _AnnualIncomeStatement: IS!$A$3:$K$74
Name _AnnualSegmentIncomeStatement: Divisional!$A$2:$K$239
Name _EADSKeyPerformanceMeasures: 'Valuation Summary'!$A$1:$F$86
Name _QuarterlyIncomeStatement: IS!$A$3:$EQ$62
Name _QuarterlySegmentIncomeStatement: Divisional!$A$2:$AV$239
Name africa: 0
Name africaCountries: #REF!
Name allRegions: #REF!
Name americaRegion: #REF!
Name americas: 0.26
Name americasStates: #REF!
Name AppVersion: "GEG-1.0"
Name asiaPacific: 0.3
Name asiaPacificExJapan: 0.06
Name asiaPacificExJapanCountries: #REF!
Name asiaPacificRegion: #REF!
Name asiaPacificStates: #REF!
Name australasia: "NA"
Name BRICS: 0.24
Name centralEasternEurope: 0
Name centralEasternEuropeCountries: #REF!
Name china: 0.24
Name consumerDemandExposure: #REF!
Name consumersExposure: 0
Name countryList: "Country Mapping"
Name DCF_123465: #REF!
Name developedEuropeExUK: 0.4
Name developedEuropeExUKCountries: #REF!
Name domesticAndForeignExposure: #REF!
Name domesticCostExposure: #REF!
Name EEMEA: 0.04
Name endDemandExposure: #REF!
Name europe: 0.4
Name europeRegion: #REF!
Name europeStates: #REF!
Name india: 0
Name instructions: #REF!
Name italy: "NA"
Name japan: 0
Name latinAmerica: 0.02
Name latinAmericaCountries: #REF!
Name Linking_1: #REF!
Name Linking_10: #REF!
Name Linking_100: #REF!
Name Linking_101: #REF!
Name Linking_102: #REF!
Name Linking_103: #REF!
Name Linking_104: #REF!
Name Linking_105: #REF!
Name Linking_106: #REF!
Name Linking_108: #REF!
Name Linking_11: #REF!
Name Linking_116: #REF!
Name Linking_117: #REF!
Name Linking_118: #REF!
Name Linking_119: #REF!
Name Linking_12: #REF!
Name Linking_120: #REF!
Name Linking_121: IS!$A$2:$DG$66

Sheet ImportantDisclosures
A2: 20 Bank Street, Canary Wharf
A3: London E14 4AD
A4: United Kingdom
A5: Tel: +44 (0)20 7425 8000
A7: Authors: Ross Law,Marie-Ange Riggio
A8: Date: 14 Aug 2026
A10: Ticker: AIR.PA
A11: Stock Rating: Overweight
A12: Industry: Aerospace & Defence
A13: Industry View: Attractive
A14: Price as of 14 Aug 2026: 212.90
A15: Target Price: 255.00
... A133: Equal-weight and Not-Rated to hold and Underweight to sell recommendations, respectively.
B135: Coverage Universe | D135: Investment Banking Clients (IBC) | G135: Other Material Investment Services Clients (MISC)
A136: Stock Rating Category | B136: Count | C136: % of Total | D136: Count | E136: % of Total IBC | F136: % of Rating Category | G136: Count | H136: % of Total Other MISC
A137: Overweight/Buy | B137: 1529 | C137: 0.42 | D137: 442 | E137: 0.47 | F137: 0.29 | G137: 750 | H137: 0.43
A138: Equal-weight/Hold | B138: 1582 | C138: 0.43 | D138: 396 | E138: 0.42 | F138: 0.25 | G138: 773 | H138: 0.44
A139: Not-Rated/Hold | B139: 3 | C139: 0 | D139: 1 | E139: 0 | F139: 0.33 | G139: 1 | H139: 0
A140: Underweight/Sell | B140: 560 | C140: 0.15 | D140: 97 | E140: 0.1 | F140: 0.17 | G140: 217 | H140: 0.12
A141: Total | B141: 3674 | D141: 936 | G141: 1741
A143: Data include common stock and ADRs currently assigned ratings. Investment Banking Clients are companies
A144: from whom Morgan Stanley received investment banking compensation in the last 12 months. Due to rounding
A145: off of decimals, the percentages provided in the "% of total" column may not add up to exactly 100
A146: percent.
A148: Analyst Stock Ratings
A150: Overweight (O). The stock's total return is expected to exceed the average total return of the analyst's
A151: industry (or industry team's) coverage universe, on a risk-adjusted basis, over the next 12-18 months.
A153: Equal-weight (E). The stock's total return is expected to be in line with the average total return of
A154: the analyst's industry (or industry team's) coverage universe, on a risk-adjusted basis, over the next
A155: 12-18 months.
A157: Not-Rated (NR). Currently the analyst does not have adequate conviction about the stock's total return
A158: relative to the average total return of the analyst's industry (or industry team's) coverage universe,
... A436: © Copyright 2026 Morgan Stanley

Sheet Valuation Summary
A1: Airbus | AD1: 2022-25 CAGR | AE1: 2022-27 CAGR | AF1: 23-26 CAGR | AG1: 23-28 CAGR
A2: Year End December, EUR
A3: €m | B3: 2004 | C3: 2005 | D3: 2006 | E3: =D3+1 -> 2007 | F3: =E3+1 -> 2008 | G3: =F3+1 -> 2009 | H3: =G3+1 -> 2010 | I3: =H3+1 -> 2011 | J3: =I3+1 -> 2012 | K3: =J3+1 -> 2013 | L3: =K3+1 -> 2014 | ... AB3: =AA3+1 -> 2030
A4: Avg Share Price (€) | B4: 20.691 | C4: 26.146 | D4: 26.3216 | E4: 23.0649 | F4: 14.35 | G4: 12.478 | H4: 16.586 | I4: 21.513 | J4: 27.906 | K4: 43.38 | L4: 49.05 | M4: 58.84 | N4: 70 | O4: 85 | P4: 100 | Q4: 120 | R4: 120 | S4: 102 | T4: 95 | U4: 139.78 | V4: 154.78 | W4: 176.8891 | X4: 212.9 | Y4: =X4 -> 212.9 | Z4: =Y4 -> 212.9 | AA4: =Z4 -> 212.9 | AB4: =AA4 -> 212.9
A5: Avg Basic Shares (m) | B5: 804.08287 | C5: 800.21635 | D5: 804.31566 | E5: 805.5484 | F5: 807.59694 | G5: 811.19011 | H5: 810.69334 | I5: 813.702 | J5: 820.55193 | K5: 794.12781 | L5: =IS!AA70 -> 782.96239 | M5: =IS!AH70 -> 785.6211 | N5: =IS!AO70 -> 773.79884 | O5: =IS!AV70 -> 773.7727 | P5: =IS!BJ70 -> 775.16794 | Q5: =IS!BQ70 -> 777.03986 | R5: =IS!BX70 -> 783.17819 | S5: =IS!CE70 -> 785.32607 | T5: =IS!CL70 -> 787.08058 | U5: =IS!CS70 -> 788.72078 | V5: =IS!CZ70 -> 789.96167 | W5: =IS!DG70 -> 789.57321 | X5: =IS!DN70 -> 786.06495 | Y5: =IS!DU70 -> 781.8688 | Z5: =IS!EB70 -> 776.19772 | AA5: =IS!EI70 -> 771.26635 | AB5: =IS!EP70 -> 768.97269
A6: Market capitalisation | B6: =B4*B5 -> 16637.279 | C6: =C4*C5 -> 20922.457 | D6: =D4*D5 -> 21170.875 | E6: =E4*E5 -> 18579.893 | F6: =F4*F5 -> 11589.016 | G6: =G4*G5 -> 10122.03 | H6: =H4*H5 -> 13446.16 | I6: =I4*I5 -> 17505.171 | ... AB6: =AB4*AB5 -> 163714.28
A7: MS adj. (as for CE ex JV) | B7: =B62+B63+B64+B65+B68+B69+B66 -> 3916 | C7: =C62+C63+C64+C65+C68+C69+C66 -> 3589 | D7: =D62+D63+D64+D65+D68+D69+D66 -> 3400 | E7: =E62+E63+E64+E65+E68+E69+E66 -> -1011 | F7: =F62+F63+F64+F65+F68+F69+F66 -> -4638 | G7: =G62+G63+G64+G65+G68+G69+G66 -> -4476 | H7: =H62+H63+H64+H65+H68+H69+H66 -> -6850 | I7: =I62+I63+I64+I65+I68+I69+I66 -> -6331 | ... AB7: =AB62+AB63+AB64+AB65+AB68+AB69+AB66 -> -35016.022
A8: Dassault associate inv. | B8: -1901 | C8: -2484 | D8: -2896 | E8: -3359 | F8: -2421 | G8: -1921 | H8: -2725 | I8: -3027 | J8: -3223 | K8: -4167 | L8: -3981 | M8: -2443 | N8: -876 | O8: -1071 | P8: -999 | Q8: -968 | R8: -742 | S8: -786 | T8: -1309 | U8: -1483 | V8: -1632 | W8: -2146.5108 | X8: -2441.1154 | Y8: =X8 -> -2441.1154 | Z8: =Y8 -> -2441.1154 | AA8: =Z8 -> -2441.1154 | AB8: =AA8 -> -2441.1154
A9: Enterprise value - MS | B9: =B6+B7+B8 -> 18652.279 | C9: =C6+C7+C8 -> 22027.457 | D9: =D6+D7+D8 -> 21674.875 | E9: =E6+E7+E8 -> 14209.893 | F9: =F6+F7+F8 -> 4530.0161 | G9: =G6+G7+G8 -> 3725.0302 | H9: =H6+H7+H8 -> 3871.1597 | I9: =I6+I7+I8 -> 8147.1711 | ... AB9: =AB6+AB7+AB8 -> 126257.15
A11: Profitability
A12: Revenues | B12: =+IS!E8 -> 31761 | C12: =+IS!F8 -> 34206 | D12: =+IS!G8 -> 39434 | E12: =+IS!H8 -> 39123 | F12: =+IS!I8 -> 43265 | G12: =+IS!J8 -> 42822 | H12: =+IS!K8 -> 45752 | I12: =+IS!L8 -> 49128 | J12: =+IS!M8 -> 56480 | K12: =+IS!T8 -> 57567 | L12: =+IS!AA8 -> 60713 | M12: =+IS!AH8 -> 64450 | N12: =+IS!AO8 -> 66581 | O12: =+IS!AV8 -> 66767 | P12: =+IS!BJ8 -> 63707 | Q12: =+IS!BQ8 -> 70478 | R12: =+IS!BX8 -> 49912 | S12: =+IS!CE8 -> 52149 | T12: =+IS!CL8 -> 58763 | U12: =+IS!CS8 -> 65446 | V12: =+IS!CZ8 -> 69230 | W12: =+IS!DG8 -> 73420 | X12: =+IS!DN8 -> 80558.144 | Y12: =+IS!DU8 -> 89656.987 | Z12: =+IS!EB8 -> 97614.941 | AA12: =+IS!EI8 -> 102018.21 | AB12: =+IS!EP8 -> 105534.12 | AD12: =(W12/T12)^(1/3)-1 -> 0.077052336 | AE12: =(Y12/T12)^(1/5)-1 -> 0.088168215 | AF12: =(X12/U12)^(1/3)-1 -> 0.071705471 | AG12: =(Z12/U12)^(1/5)-1 -> 0.083244862
A13: EBITDA reported | B13: =IS!E18 -> 3836 | C13: =IS!F18 -> 4365 | D13: =IS!G18 -> 2033 | E13: =IS!H18 -> 1751 | F13: =IS!I18 -> 4439 | G13: =IS!J18 -> 1446 | H13: =IS!K18 -> 2769 | I13: =IS!L18 -> 3539 | J13: =IS!M18 -> 4201 | K13: =IS!T18 -> 4512 | L13: =IS!AA18 -> 6147 | M13: =IS!AH18 -> 6528 | N13: =IS!AO18 -> 4508 | O13: =IS!AV18 -> 5719 | P13: =IS!BJ18 -> 7492 | Q13: =IS!BQ18 -> 4266 | R13: =IS!BX18 -> 2321 | S13: =IS!CE18 -> 7667 | T13: =IS!CL18 -> 8041 | U13: =IS!CS18 -> 6845 | V13: =IS!CZ18 -> 8157 | W13: =IS!DG18 -> 9257 | X13: =IS!DN18 -> 11412.544 | Y13: =IS!DU18 -> 13580.968 | Z13: =IS!EB18 -> 16236.925 | AA13: =IS!EI18 -> 17426.398 | AB13: =IS!EP18 -> 18344.759 | AD13: =(W13/T13)^(1/3)-1 -> 0.048061418 | AE13: =(Y13/T13)^(1/5)-1 -> 0.11051425 | AF13: =(X13/U13)^(1/3)-1 -> 0.18577693 | AG13: =(Z13/U13)^(1/5)-1 -> 0.18857356
A14: EBITDA reported ex JV | B14: =IS!E18-IS!E17 -> 3752 | C14: =IS!F18-IS!F17 -> 4140 | D14: =IS!G18-IS!G17 -> 1844 | E14: =IS!H18-IS!H17 -> 1455 | F14: =IS!I18-IS!I17 -> 4228 | G14: =IS!J18-IS!J17 -> 1312 | H14: =IS!K18-IS!K17 -> 2624 | I14: =IS!L18-IS!L17 -> 3347 | J14: =IS!M18-IS!M17 -> 3954 | K14: =IS!T18-IS!T17 -> 4029 | L14: =IS!AA18-IS!AA17 -> 5252 | M14: =IS!AH18-IS!AH17 -> 5458 | N14: =IS!AO18-IS!AO17 -> 4256 | O14: =IS!AV18-IS!AV17 -> 5304 | P14: =IS!BJ18-IS!BJ17 -> 7053 | Q14: =IS!BQ18-IS!BQ17 -> 3963 | R14: =IS!BX18-IS!BX17 -> 2169 | S14: =IS!CE18-IS!CE17 -> 7551 | T14: =IS!CL18-IS!CL17 -> 7849 | U14: =IS!CS18-IS!CS17 -> 6542 | V14: =IS!CZ18-IS!CZ17 -> 7763 | W14: =IS!DG18-IS!DG17 -> 8902 | X14: =IS!DN18-IS!DN17 -> 11023.029 | Y14: =IS!DU18-IS!DU17 -> 13147.459 | Z14: =IS!EB18-IS!EB17 -> 15764.938 | AA14: =IS!EI18-IS!EI17 -> 16933.12 | AB14: =IS!EP18-IS!EP17 -> 17834.481 | AD14: =(W14/T14)^(1/3)-1 -> 0.042856183 | AE14: =(Y14/T14)^(1/5)-1 -> 0.10867819 | AF14: =(X14/U14)^(1/3)-1 -> 0.18995391 | AG14: =(Z14/U14)^(1/5)-1 -> 0.19232965
A15: EBITDA adjusted | B15: =Divisional!G31-IS!F20 -> 1912 | C15: =Divisional!H31-IS!G20 -> 5704 | D15: =Divisional!I31-IS!H20 -> 5029 | E15: =Divisional!J31-IS!I20 -> 3757 | F15: =Divisional!K31-IS!J20 -> 3109 | G15: =Divisional!L31-IS!K20 -> 3324 | H15: =Divisional!M31-IS!L20 -> 4849 | I15: =Divisional!T31-IS!M20 -> 5552 | J15: =Divisional!AA31-IS!T20 -> 5954 | K15: =Divisional!AH31-IS!AA20 -> 6239 | L15: =Divisional!AO31-IS!AH20 -> 6397 | M15: =Divisional!AV31-IS!AO20 -> 6503 | N15: =Divisional!BC31-IS!AV20 -> 5488 | O15: =Divisional!BJ31-IS!BC20 -> 8132 | P15: =Divisional!BQ31-IS!BJ20 -> 9390 | Q15: =Divisional!BX31-IS!BQ20 -> 9873 | R15: =Divisional!CE31-IS!BX20 -> 4537 | S15: =Divisional!CL31-IS!CE20 -> 7190 | T15: =Divisional!CS31-IS!CL20 -> 8343 | U15: =Divisional!CZ31-IS!CS20 -> 8080 | V15: =Divisional!DG31-IS!CZ20 -> 8207 | W15: =Divisional!DN31-IS!DG20 -> 10303 | X15: =Divisional!DU31-IS!DN20 -> 11544.544 | Y15: =Divisional!EB31-IS!DU20 -> 13580.968 | Z15: =Divisional!EI31-IS!EB20 -> 16236.925 | AA15: =Divisional!EP31-IS!EI20 -> 17426.398 | AB15: =Divisional!EW31-IS!EP20 -> 18344.759 | AD15: =(W15/T15)^(1/3)-1 -> 0.072870125 | AE15: =(Y15/T15)^(1/5)-1 -> 0.10235557 | AF15: =(X15/U15)^(1/3)-1 -> 0.12630272 | AG15: =(Z15/U15)^(1/5)-1 -> 0.14978989
A16: EBIT reported | B16: =IS!E22 -> 2432 | C16: =IS!F22 -> 2852 | D16: =IS!G22 -> 399 | E16: =IS!H22 -> 52 | F16: =IS!I22 -> 2830 | G16: =IS!J22 -> -322 | H16: =IS!K22 -> 1231 | I16: =IS!L22 -> 1696 | J16: =IS!M22 -> 2186 | K16: =IS!T22 -> 2624 | L16: =IS!AA22 -> 4040 | M16: =IS!AH22 -> 4086 | N16: =IS!AO22 -> 2258 | O16: =IS!BC22 -> 2665 | P16: =IS!BJ22 -> 5048 | Q16: =IS!BQ22 -> 1339 | R16: =IS!BX22 -> -510 | S16: =IS!CE22 -> 5342 | T16: =IS!CL22 -> 5325 | U16: =IS!CS22 -> 4603 | V16: =IS!CZ22 -> 5304 | W16: =IS!DG22 -> 6082 | X16: =IS!DN22 -> 7779.6032 | Y16: =IS!DU22 -> 9531.4017 | Z16: =IS!EB22 -> 11824.436 | AA16: =IS!EI22 -> 12814.391 | AB16: =IS!EP22 -> 13574.104 | AD16: =(W16/T16)^(1/3)-1 -> 0.045303171 | AE16: =(Y16/T16)^(1/5)-1 -> 0.1234854 | AF16: =(X16/U16)^(1/3)-1 -> 0.19116564 | AG16: =(Z16/U16)^(1/5)-1 -> 0.20766892
A17: EBIT adjusted | B17: 2432 | C17: 2852 | D17: 399 | E17: 52 | F17: 3300 | G17: 2150 | H17: 1340 | I17: 1794 | J17: 2964 | K17: 3574 | L17: =Divisional!AA31 -> 4066 | M17: =Divisional!AH31 -> 4132 | N17: =Divisional!AO31 -> 3955 | O17: =Divisional!BC31 -> 3190 | P17: =Divisional!BJ31 -> 5834 | Q17: =Divisional!BX31 -> 6946 | R17: =Divisional!CE31 -> 1706 | S17: =Divisional!CL31 -> 4865 | T17: =Divisional!CS31 -> 5627 | U17: =Divisional!CZ31 -> 5838 | V17: =Divisional!DG31 -> 5354 | W17: =Divisional!DN31 -> 7128 | X17: =Divisional!DU31 -> 7911.6032 | Y17: =Divisional!EB31 -> 9531.4017 | Z17: =Divisional!EI31 -> 11824.436 | AA17: =Divisional!EP31 -> 12814.391 | AB17: =Divisional!EW31 -> 13574.104 | AD17: =(W17/T17)^(1/3)-1 -> 0.082007469 | AE17: =(Y17/T17)^(1/5)-1 -> 0.11115839 | AF17: =(X17/U17)^(1/3)-1 -> 0.10662413 | AG17: =(Z17/U17)^(1/5)-1 -> 0.15160427
A18: EBIT adjusted ex JV | B18: 2348 | C18: 2642 | D18: 247 | E18: -158 | F18: 3112 | G18: 2035 | H18: 1213 | I18: 1630 | J18: 2723 | K18: 3279 | L18: 3561 | M18: 3818 | N18: 3703 | O18: 3838 | P18: 5395 | Q18: 6643 | R18: 1554 | S18: 4749 | T18: 5435 | U18: 5535 | V18: 4960 | W18: 6773 | X18: 7522.0889 | Y18: 9097.8927 | Z18: 11352.448 | AA18: 12321.113 | AB18: 13063.826 | AD18: =(W18/T18)^(1/3)-1 -> 0.07611952 | AE18: =(Y18/T18)^(1/5)-1 -> 0.10853205 | AF18: =(X18/U18)^(1/3)-1 -> 0.1076612 | AG18: =(Z18/U18)^(1/5)-1 -> 0.15450118
A19: PBT adjusted | B19: =Divisional!E31+IS!E36+IS!E55 -> 2102 | C19: =Divisional!F31+IS!F36+IS!F55 -> 2675 | D19: =Divisional!G31+IS!G36+IS!G55 -> 155 | E19: =Divisional!H31+IS!H36+IS!H55 -> 3333 | F19: =Divisional!I31+IS!I36+IS!I55 -> 2858 | G19: =Divisional!J31+IS!J36+IS!J55 -> 1649 | H19: =Divisional!K31+IS!K36+IS!K55 -> 929 | I19: =Divisional!L31+IS!L36+IS!L55 -> 1507 | J19: =Divisional!M31+IS!M36+IS!M55 -> 2541 | K19: =Divisional!T31+IS!T36+IS!T55 -> 3034 | L19: =Divisional!AA31+IS!AA36+IS!AA55 -> 3629 | M19: =Divisional!AH31+IS!AH36+IS!AH55 -> 3663 | N19: =Divisional!AO31+IS!AO36+IS!AO55 -> 3615 | O19: =Divisional!AV31+IS!AV36+IS!AV55 -> 3864 | P19: =Divisional!BJ31+IS!BJ36+IS!BJ55 -> 5558 | Q19: =Divisional!BQ31+IS!BQ36+IS!BQ55 -> 6789 | R19: =Divisional!CE31+IS!BX36+IS!BX55 -> 1410 | S19: =Divisional!CL31+IS!CE36+IS!CE55 -> 4600 | T19: =Divisional!CS31+IS!CL36+IS!CL55 -> 5403 | U19: =Divisional!CZ31+IS!CS36+IS!CS55 -> 5810 | V19: =Divisional!DG31+IS!CZ36+IS!CZ55 -> 5339 | W19: =Divisional!DN31+IS!DG36+IS!DG55 -> 7336 | X19: =Divisional!DU31+IS!DN36+IS!DN55 -> 7698.6032 | Y19: =Divisional!EB31+IS!DU36+IS!DU55 -> 9364.5096 | Z19: =Divisional!EI31+IS!EB36+IS!EB55 -> 11718.242 | AA19: =Divisional!EP31+IS!EI36+IS!EI55 -> 12818.165 | AB19: =Divisional!EW31+IS!EP36+IS!EP55 -> 13689.91 | AD19: =(W19/T19)^(1/3)-1 -> 0.10732418 | AE19: =(Y19/T19)^(1/5)-1 -> 0.11627196 | AF19: =(X19/U19)^(1/3)-1 -> 0.098361415 | AG19: =(Z19/U19)^(1/5)-1 -> 0.15063417
A20: Net Income adjusted | B20: 1342 | C20: 1769 | D20: 199 | E20: -433 | F20: 1613 | G20: 1219.8971 | H20: 632.5 | I20: 1132 | J20: 1807 | K20: 2236 | L20: =IS!AA57 -> 2601 | M20: =IS!AH57 -> 2662 | N20: =IS!AO57 -> 2562 | O20: =IS!AV57 -> 2836 | P20: =IS!BJ57 -> 4045 | Q20: =IS!BQ57 -> 4715 | R20: =IS!BX57 -> 1068 | S20: =IS!CE57 -> 3397 | T20: =IS!CL57 -> 4055 | U20: =IS!CS57 -> 4417 | V20: =IS!CZ57 -> 3992 | W20: =IS!DG57 -> 5437 | X20: =IS!DN57 -> 6023.9524 | Y20: =IS!DU57 -> 7273.3822 | Z20: =IS!EB57 -> 9038.6817 | AA20: =IS!EI57 -> 9863.6235 | AB20: =IS!EP57 -> 10517.433 | AD20: =(W20/T20)^(1/3)-1 -> 0.10269691 | AE20: =(Y20/T20)^(1/5)-1 -> 0.12395548 | AF20: =(X20/U20)^(1/3)-1 -> 0.10896552 | AG20: =(Z20/U20)^(1/5)-1 -> 0.15397271
A21: EPS adjusted (basic, €) | B21: =IS!E61 -> 1.501807 | C21: =IS!F61 -> 2.11014 | D21: =IS!G61 -> 0.12365248 | E21: =IS!H61 -> -0.55914825 | F21: =IS!I61 -> 1.9480066 | G21: =IS!J61 -> 1.5066057 | H21: =IS!K65 -> 0.7801967 | I21: =IS!L65 -> 1.3932188 | J21: =IS!M65 -> 2.2431642 | K21: =IS!T65 -> 2.811474 | L21: =IS!AA65 -> 3.3641463 | M21: =IS!AH65 -> 3.4100408 | N21: =IS!AO65 -> 3.310938 | O21: =IS!AV65 -> 3.665159 | P21: =IS!BJ65 -> 5.2182241 | Q21: =IS!BQ65 -> 6.0678998 | R21: =IS!BX65 -> 1.3636743 | S21: =IS!CE65 -> 4.3255918 | T21: =IS!CL65 -> 5.1519503 | U21: =IS!CS65 -> 5.6002075 | V21: =IS!CZ65 -> 5.0534097 | W21: =IS!DG65 -> 6.8859986 | X21: =IS!DN65 -> 7.6634283 | Y21: =IS!DU65 -> 9.302561 | Z21: =IS!EB65 -> 11.644819 | AA21: =IS!EI65 -> 12.788868 | AB21: =IS!EP65 -> 13.677252 | AD21: =(W21/T21)^(1/3)-1 -> 0.10153531 | AE21: =(Y21/T21)^(1/5)-1 -> 0.12544992 | AF21: =(X21/U21)^(1/3)-1 -> 0.11021305 | AG21: =(Z21/U21)^(1/5)-1 -> 0.15767251
A22: EPS adjusted (diluted, €) | B22: =IS!E62 -> 1.4961144 | C22: =IS!F62 -> 2.0944336 | D22: =IS!G62 -> 0.123086 | E22: =IS!H62 -> -0.55366009 | F22: =IS!I62 -> 1.9465155 | G22: =IS!J62 -> 1.5038363 | H22: =IS!K66 -> 0.78019637 | I22: =IS!L66 -> 1.3911727 | J22: =IS!M66 -> 2.2399557 | K22: =IS!T66 -> 2.8055937 | L22: =IS!AA66 -> 3.3590266 | M22: =IS!AH66 -> 3.3976262 | N22: =IS!AO66 -> 3.288369 | O22: =IS!AV66 -> 3.6391576 | P22: =IS!BJ66 -> 5.1796351 | Q22: =IS!BQ66 -> 6.0678998 | R22: =IS!BX66 -> 1.3636743 | S22: =IS!CE66 -> 4.3224219 | T22: =IS!CL66 -> 5.1475494 | U22: =IS!CS66 -> 5.5928341 | V22: =IS!CZ66 -> 5.0468332 | W22: =IS!DG66 -> 6.8745153 | X22: =IS!DN66 -> 7.6505916 | Y22: =IS!DU66 -> 9.2868952 | Z22: =IS!EB66 -> 11.625065 | AA22: =IS!EI66 -> 12.767036 | AB22: =IS!EP66 -> 13.653833 | AD22: =(W22/T22)^(1/3)-1 -> 0.1012363 | AE22: =(Y22/T22)^(1/5)-1 -> 0.12526291 | AF22: =(X22/U22)^(1/3)-1 -> 0.11008021 | AG22: =(Z22/U22)^(1/5)-1 -> 0.15758447
A23: DPS (€) | B23: =BS!E261 -> 0.5 | C23: =BS!F261 -> 0.65 | D23: =BS!G261 -> 0.12 | E23: =BS!H261 -> 0.12 | F23: =BS!I261 -> 0.2 | G23: =BS!J261 -> 0 | H23: =BS!K261 -> 0.22 | I23: =BS!L261 -> 0.45 | J23: =BS!M261 -> 0.6 | K23: =BS!T261 -> 0.75 | L23: =BS!AA261 -> 1.2 | M23: =BS!AH261 -> 1.3 | N23: =BS!AO261 -> 1.35 | O23: =BS!AV261 -> 1.5 | P23: =BS!BJ261 -> 1.65 | Q23: =BS!BQ261 -> 0 | R23: =BS!BX261 -> 0 | S23: =BS!CE261 -> 1.5 | T23: =BS!CL261 -> 1.8 | U23: =BS!CS261 -> 2.8 | V23: =BS!CZ261 -> 3 | W23: =BS!DG261 -> 3.2 | X23: =BS!DN261 -> 3.0653713 | Y23: =BS!DU261 -> 3.7210244 | Z23: =BS!EB261 -> 4.6579275 | AA23: =BS!EI261 -> 5.1155472 | AB23: =BS!EP261 -> 5.4709006 | AD23: =(W23/T23)^(1/3)-1 -> 0.21141373 | AE23: =(Y23/T23)^(1/5)-1 -> 0.15631991 | AF23: =(X23/U23)^(1/3)-1 -> 0.030643224 | AG23: =(Z23/U23)^(1/5)-1 -> 0.10715121
A24: FCF | B24: 1714 | C24: 2544 | D24: 2111 | E24: 3354 | F24: 2824 | G24: 606 | H24: 2745 | I24: 2493 | J24: 1449 | K24: -818 | L24: =CFS!AA74 -> 1109 | M24: =CFS!AH74 -> 1175 | N24: =CFS!AO74 -> 1156 | O24: =CFS!AV74 -> 2849 | P24: =CFS!BJ74 -> 2991 | Q24: =CFS!BQ74 -> 3567 | R24: =CFS!BX74 -> -6811 | S24: =CFS!CE58 -> 3425 | T24: =CFS!CL58 -> 4670 | U24: =CFS!CS58 -> 4097 | V24: =CFS!CZ58 -> 4461 | W24: =CFS!DG58 -> 4753 | X24: =CFS!DN58 -> 5119.7231 | Y24: =CFS!DU58 -> 6599.6673 | Z24: =CFS!EB58 -> 9061.9473 | AA24: =CFS!EI58 -> 9848.8051 | AB24: =CFS!EP58 -> 10717.474 | AD24: =(W24/T24)^(1/3)-1 -> 0.0058895845 | AE24: =(Y24/T24)^(1/5)-1 -> 0.071620549 | AF24: =(X24/U24)^(1/3)-1 -> 0.07711028 | AG24: =(Z24/U24)^(1/5)-1 -> 0.17206342
A25: FCF before Customer Financing | N25: =CFS!AO76 -> 1408 | O25: =CFS!BC76 -> 2949 | P25: =CFS!BJ76 -> 2912 | Q25: =CFS!BQ76 -> 3509 | R25: =CFS!BX76 -> -6935 | S25: =CFS!CE60 -> 3397 | T25: =CFS!CL60 -> 4816 | U25: =CFS!CS60 -> 4533 | V25: =CFS!CZ60 -> 4463 | W25: =CFS!DG60 -> 4574 | X25: =CFS!DN60 -> 4996.7231 | Y25: =CFS!DU60 -> 6599.6673 | Z25: =CFS!EB60 -> 9061.9473 | AA25: =CFS!EI60 -> 9848.8051 | AB25: =CFS!EP60 -> 10717.474 | AD25: =(W25/T25)^(1/3)-1 -> -0.017038381 | AE25: =(Y25/T25)^(1/5)-1 -> 0.065042928 | AF25: =(X25/U25)^(1/3)-1 -> 0.032998893 | AG25: =(Z25/U25)^(1/5)-1 -> 0.14859564
A27: Growth
A28: Revenue growth | C28: =C12/B12-1 -> 0.076981203 | D28: =D12/C12-1 -> 0.15283868 | E28: =E12/D12-1 -> -0.0078865953 | F28: =F12/E12-1 -> 0.10587123 | G28: =G12/F12-1 -> -0.010239223 | H28: =H12/G12-1 -> 0.068422773 | I28: =I12/H12-1 -> 0.073789124 | J28: =J12/I12-1 -> 0.14964989 | ... AB28: =AB12/AA12-1 -> 0.034463514
A29: EBITDA adjusted growth | C29: =C15/B15-1 -> 1.9832636 | D29: =D15/C15-1 -> -0.11833801 | E29: =E15/D15-1 -> -0.25293299 | F29: =F15/E15-1 -> -0.17247804 | G29: =G15/F15-1 -> 0.069154069 | H29: =H15/G15-1 -> 0.4587846 | I29: =I15/H15-1 -> 0.14497835 | J29: =J15/I15-1 -> 0.07240634 | ... AB29: =AB15/AA15-1 -> 0.052699414
A30: EBIT adjusted growth | C30: =C17/B17-1 -> 0.17269737 | D30: =D17/C17-1 -> -0.86009818 | E30: =E17/D17-1 -> -0.86967419 | F30: =F17/E17-1 -> 62.461538 | G30: =G17/F17-1 -> -0.34848485 | H30: =H17/G17-1 -> -0.37674419 | I30: =I17/H17-1 -> 0.33880597 | J30: =J17/I17-1 -> 0.65217391 | ... AB30: =AB17/AA17-1 -> 0.059285941
A31: EPS adjusted growth | C31: =C21/B21-1 -> 0.40506737 | D31: =D21/C21-1 -> -0.94140082 | E31: =E21/D21-1 -> -5.5219333 | F31: =F21/E21-1 -> -4.483882 | G31: =G21/F21-1 -> -0.22659106 | H31: =H21/G21-1 -> -0.48214938 | I31: =I21/H21-1 -> 0.78572759 | J31: =J21/I21-1 -> 0.61005886 | ... AB31: =AB21/AA21-1 -> 0.069465375
A33: Margins
A34: EBITDA adjusted Margin (%) | B34: =B15/B12 -> 0.060199616 | C34: =C15/C12 -> 0.16675437 | D34: =D15/D12 -> 0.12752954 | E34: =E15/E12 -> 0.096030468 | F34: =F15/F12 -> 0.071859471 | G34: =G15/G12 -> 0.077623651 | H34: =H15/H12 -> 0.10598444 | I34: =I15/I12 -> 0.11301091 | ... AB34: =AB15/AB12 -> 0.17382776
A35: EBIT adjusted Margin (%) | B35: =B17/B12 -> 0.076571896 | C35: =C17/C12 -> 0.083377185 | D35: =D17/D12 -> 0.010118172 | E35: =E17/E12 -> 0.0013291414 | F35: =F17/F12 -> 0.076274125 | G35: =G17/G12 -> 0.050207837 | H35: =H17/H12 -> 0.029288337 | I35: =I17/I12 -> 0.036516854 | ... AB35: =AB17/AB12 -> 0.1286229
A36: Dividend cover by EPS (x) | B36: =B21/B23 -> 3.0036139 | C36: =C21/C23 -> 3.2463692 | D36: =D21/D23 -> 1.0304373 | E36: =E21/E23 -> -4.6595688 | F36: =F21/F23 -> 9.7400328 | G36: nm | H36: =H21/H23 -> 3.5463486 | I36: =I21/I23 -> 3.0960417 | J36: =J21/J23 -> 3.738607 | K36: =K21/K23 -> 3.748632 | L36: =L21/L23 -> 2.8034552 | M36: =M21/M23 -> 2.6231083 | N36: =N21/N23 -> 2.4525467 | O36: =O21/O23 -> 2.4434393 | P36: =P21/P23 -> 3.16256 | Q36: =IFERROR(Q21/Q23,0) -> 0 | R36: =IFERROR(R21/R23,0) -> 0 | S36: =IFERROR(S21/S23,0) -> 2.8837278 | T36: =IFERROR(T21/T23,0) -> 2.8621946 | U36: =IFERROR(U21/U23,0) -> 2.0000741 | V36: =IFERROR(V21/V23,0) -> 1.6844699 | W36: =IFERROR(W21/W23,0) -> 2.1518745 | X36: =IFERROR(X21/X23,0) -> 2.5 | ... AB36: =IFERROR(AB21/AB23,0) -> 2.5
A37: Payout Ratio (%) | B37: =B23/B22 -> 0.33419903 | C37: =C23/C22 -> 0.31034644 | D37: =D23/D22 -> 0.97492808 | E37: =E23/E22 -> -0.21673948 | F37: =F23/F22 -> 0.1027477 | G37: =G23/G22 -> 0 | H37: =H23/H22 -> 0.28198029 | I37: =I23/I22 -> 0.32346811 | ... AB37: =AB23/AB22 -> 0.40068607
A38: P&L tax | B38: =IS!E40+IS!E56+IS!E24+IS!E26+IS!E50 -> -881 | C38: =IS!F40+IS!F56+IS!F24+IS!F26+IS!F50 -> -965 | D38: =IS!G40+IS!G56+IS!G24+IS!G26+IS!G50 -> 24 | E38: =IS!H40+IS!H56+IS!H24+IS!H26+IS!H50 -> 260 | F38: =IS!I40+IS!I56+IS!I24+IS!I26+IS!I50 -> -761 | G38: =IS!J40+IS!J56+IS!J24+IS!J26+IS!J50 -> -418.10288 | H38: =IS!K40+IS!K56+IS!K24+IS!K26+IS!K50 -> -280.5 | I38: =IS!L40+IS!L56+IS!L24+IS!L26+IS!L50 -> -379 | J38: =IS!M40+IS!M56+IS!M24+IS!M26+IS!M50 -> -702 | K38: =IS!T40+IS!T56+IS!T24+IS!T26+IS!T50 -> -796 | L38: =IS!AA40+IS!AA56+IS!AA24+IS!AA26+IS!AA50 -> -988 | M38: =IS!AH40+IS!AH56+IS!AH24+IS!AH26+IS!AH50 -> -982 | N38: =IS!AO40+IS!AO56+IS!AO24+IS!AO26+IS!AO50 -> -1048 | O38: =IS!AV40+IS!AV56+IS!AV24+IS!AV26+IS!AV50 -> -1024 | P38: =IS!BJ40+IS!BJ56+IS!BJ24+IS!BJ26+IS!BJ50 -> -1556 | Q38: =IS!BQ40+IS!BQ56+IS!BQ24+IS!BQ26+IS!BQ50 -> -2037 | R38: =IS!BX40+IS!BX56+IS!BX24+IS!BX26+IS!BX50 -> -378 | S38: =IS!CE40+IS!CE56+IS!CE24+IS!CE26+IS!CE50 -> -1242 | T38: =IS!CL40+IS!CL56+IS!CL24+IS!CL26+IS!CL50 -> -1459 | U38: =IS!CS40+IS!CS56+IS!CS24+IS!CS26+IS!CS50 -> -1569 | V38: =IS!CZ40+IS!CZ56+IS!CZ24+IS!CZ26+IS!CZ50 -> -1501 | W38: =IS!DG40+IS!DG56+IS!DG24+IS!DG26+IS!DG50 -> -2160 | X38: =IS!DN40+IS!DN56+IS!DN24+IS!DN26+IS!DN50 -> -1924.6508 | Y38: =IS!DU40+IS!DU56+IS!DU24+IS!DU26+IS!DU50 -> -2341.1274 | Z38: =IS!EB40+IS!EB56+IS!EB24+IS!EB26+IS!EB50 -> -2929.5606 | AA38: =IS!EI40+IS!EI56+IS!EI24+IS!EI26+IS!EI50 -> -3204.5412 | AB38: =IS!EP40+IS!EP56+IS!EP24+IS!EP26+IS!EP50 -> -3422.4776
A39: Cash tax | B39: =IS!E40+CFS!E8 -> -127 | C39: =IS!F40+CFS!F8 -> -265 | D39: =IS!G40+CFS!G8 -> -239 | E39: =IS!H40+CFS!H8 -> 36 | F39: =IS!I40+CFS!I8 -> -252 | G39: =IS!J40+CFS!J8 -> 4 | H39: =IS!K40+CFS!K8 -> -140 | I39: =IS!L40+CFS!L8 -> -100 | J39: =IS!M40+CFS!M8 -> -409 | K39: =IS!T40+CFS!T8 -> -243 | L39: =IS!AA40+CFS!AA8 -> -115 | M39: =IS!AH40+CFS!AH8 -> -595 | N39: =IS!AO40+CFS!AO8 -> -559 | O39: =IS!AV40+CFS!AV8 -> -152 | P39: =IS!BJ40+CFS!BJ8 -> -897 | Q39: =IS!BQ40+CFS!BQ8 -> -1476 | R39: =IS!BX40+CFS!BX8 -> 79 | S39: =IS!CE40+CFS!CE8 -> -321 | T39: =IS!CL40+CFS!CL8 -> -790 | U39: =IS!CS40+CFS!CS8 -> -544 | V39: =IS!CZ40+CFS!CZ8 -> -947 | W39: =IS!DG40+CFS!DG8 -> -965 | X39: =IS!DN40+CFS!DN8 -> -1936.9008 | Y39: =IS!DU40+CFS!DU8 -> -2341.1274 | Z39: =IS!EB40+CFS!EB8 -> -2929.5606 | AA39: =IS!EI40+CFS!EI8 -> -3204.5412 | AB39: =IS!EP40+CFS!EP8 -> -3422.4776
A40: P&L tax rate (%) | B40: =-B38/B19 -> 0.41912464 | C40: =-C38/C19 -> 0.36074766 | D40: =-D38/D19 -> -0.15483871 | E40: =-E38/E19 -> -0.078007801 | F40: =-F38/F19 -> 0.26627012 | G40: =-G38/G19 -> 0.25354935 | H40: =-H38/H19 -> 0.30193757 | I40: =-I38/I19 -> 0.25149303 | ... AB40: =-AB38/AB19 -> 0.25
A41: Cash tax rate (%) | B41: =-B39/B19 -> 0.060418649 | C41: =-C39/C19 -> 0.099065421 | D41: =-D39/D19 -> 1.5419355 | E41: =-E39/E19 -> -0.01080108 | F41: =-F39/F19 -> 0.088173548 | G41: =-G39/G19 -> -0.0024257126 | H41: =-H39/H19 -> 0.15069968 | I41: =-I39/I19 -> 0.066357001 | ... AB41: =-AB39/AB19 -> 0.25
A42: FCF margin (%) | B42: =+B24/B12 -> 0.053965555 | C42: =+C24/C12 -> 0.074372917 | D42: =+D24/D12 -> 0.053532485 | E42: =+E24/E12 -> 0.085729622 | F42: =+F24/F12 -> 0.06527216 | G42: =+G24/G12 -> 0.014151604 | H42: =+H24/H12 -> 0.059997377 | I42: =+I24/I12 -> 0.050744993 | ... M42: =+M24/M12 -> 0.018231187 | N42: =+N25/N12 -> 0.021147174 | O42: =+O25/O12 -> 0.044168526 | P42: =+P25/P12 -> 0.045709263 | Q42: =+Q25/Q12 -> 0.049788587 | R42: =+R25/R12 -> -0.13894454 | S42: =+S25/S12 -> 0.065140271 | T42: =+T25/T12 -> 0.081956333 | U42: =+U25/U12 -> 0.069263209 | ... AB42: =+AB25/AB12 -> 0.10155459
A43: Cash conversion (%) | B43: =+B24/B20 -> 1.2771982 | C43: =+C24/C20 -> 1.4381006 | D43: =+D24/D20 -> 10.60804 | E43: =+E24/E20 -> -7.7459584 | F43: =+F24/F20 -> 1.750775 | G43: =+G24/G20 -> 0.4967632 | H43: =+H24/H20 -> 4.3399209 | I43: =+I24/I20 -> 2.2022968 | ... M43: =+M24/M20 -> 0.44139745 | N43: =+N25/N20 -> 0.54957065 | O43: =+O25/O20 -> 1.0398449 | P43: =+P25/P20 -> 0.71990111 | Q43: =+Q25/Q20 -> 0.74422057 | R43: =+R25/R20 -> -6.4934457 | S43: =+S25/S20 -> 1 | T43: =+T25/T20 -> 1.1876695 | U43: =+U25/U20 -> 1.0262622 | ... AB43: =+AB25/AB20 -> 1.01902
A45: Valuation
A46: Price/Book | B46: =B6/B61 -> 1.026359 | C46: =C6/C61 -> 1.5242938 | D46: =D6/D61 -> 1.626652 | E46: =E6/E61 -> 1.419396 | F46: =F6/F61 -> 1.051444 | G46: =G6/G61 -> 0.96080021 | H46: =H6/H61 -> 1.5208867 | I46: =I6/I61 -> 1.9779854 | ... AB46: =AB6/AB61 -> 3.3279842
A47: EV/ Invested Capital | B47: =B9/B71 -> 0.45235191 | C47: =C9/C71 -> 0.570054 | D47: =D9/D71 -> 0.52967609 | E47: =E9/E71 -> 0.34333366 | F47: =F9/F71 -> 0.11489338 | G47: =G9/G71 -> 0.098213199 | H47: =H9/H71 -> 0.09821041 | I47: =I9/I71 -> 0.19880847 | ... AB47: =AB9/AB71 -> 1.3021766
A48: P/E adjusted | B48: =B4/B21 -> 13.777403 | C48: =C4/C21 -> 12.390647 | D48: =D4/D21 -> 212.86755 | E48: =E4/E21 -> -41.250062 | F48: =F4/F21 -> 7.366505 | G48: =G4/G21 -> 8.2821936 | H48: =H4/H21 -> 21.258742 | I48: =I4/I21 -> 15.441222 | ... AB48: =AB4/AB21 -> 15.565993
A49: EV/Sales | B49: =B9/B12 -> 0.58726988 | C49: =C9/C12 -> 0.64396471 | D49: =D9/D12 -> 0.54964942 | E49: =E9/E12 -> 0.36321073 | F49: =F9/F12 -> 0.10470394 | G49: =G9/G12 -> 0.086988703 | H49: =H9/H12 -> 0.084611814 | I49: =I9/I12 -> 0.1658356 | ... AB49: =AB9/AB12 -> 1.1963633
A50: EV/EBITDA adjusted | B50: =B9/B15 -> 9.7553759 | C50: =C9/C15 -> 3.8617561 | D50: =D9/D15 -> 4.3099772 | E50: =E9/E15 -> 3.7822447 | F50: =F9/F15 -> 1.4570653 | G50: =G9/G15 -> 1.1206469 | H50: =H9/H15 -> 0.79834187 | I50: =I9/I15 -> 1.46743 | ... AB50: =AB9/AB15 -> 6.8824641
A51: EV/EBIT adjusted | B51: =B9/B17 -> 7.6695225 | C51: =C9/C17 -> 7.7235122 | D51: =D9/D17 -> 54.322995 | E51: =E9/E17 -> 273.26718 | F51: =F9/F17 -> 1.3727322 | G51: =G9/G17 -> 1.7325722 | H51: =H9/H17 -> 2.8889252 | I51: =I9/I17 -> 4.541344 | ... AB51: =AB9/AB17 -> 9.3013247
A52: Free Cash Flow Yield (%) | B52: =B24/B6 -> 0.10302166 | C52: =C24/C6 -> 0.12159184 | D52: =D24/D6 -> 0.099712458 | E52: =E24/E6 -> 0.18051772 | F52: =F24/F6 -> 0.24367901 | G52: =G24/G6 -> 0.059869412 | H52: =H24/H6 -> 0.20414751 | I52: =I24/I6 -> 0.14241506 | ... M52: =M24/M6 -> 0.025418626 | N52: =N25/N6 -> 0.025994205 | O52: =O25/O6 -> 0.044837609 | P52: =P25/P6 -> 0.037566053 | Q52: =Q25/Q6 -> 0.037632132 | R52: =R25/R6 -> -0.07379121 | S52: =S25/S6 -> 0.042407762 | T52: =T25/T6 -> 0.064408573 | U52: =U25/U6 -> 0.041116619 | ... AB52: =AB25/AB6 -> 0.065464503
A53: Dividend Yield (%) | B53: =B23/B4 -> 0.024165096 | C53: =C23/C4 -> 0.024860399 | D53: =D23/D4 -> 0.0045589934 | E53: =E23/E4 -> 0.0052027106 | F53: =F23/F4 -> 0.013937282 | G53: =G23/G4 -> 0 | H53: =H23/H4 -> 0.013264199 | I53: =I23/I4 -> 0.020917585 | ... AB53: =AB23/AB4 -> 0.025697044
A55: Leverage
A56: Net Debt / (Cash) | B56: -3961 | C56: -5489 | D56: -4229 | E56: -7024 | F56: -9193 | G56: -9797 | H56: -11918 | I56: -11681 | J56: =-CFS!M86 -> -12292 | K56: =-CFS!T86 -> -8454 | L56: =-CFS!AA86 -> -9092 | M56: =-CFS!AH86 -> -10003 | N56: =-CFS!AO86 -> -11113 | O56: =-CFS!AV86 -> -13391 | P56: =-CFS!BJ86 -> -13281 | Q56: =-CFS!BQ86 -> -12534 | R56: =-CFS!BX86 -> -4312 | S56: =-CFS!CE86 -> -7740 | T56: =-CFS!CL86 -> -9431 | U56: =-CFS!CS86 -> -10726 | V56: =-CFS!CZ86 -> -11753 | W56: =-CFS!DG86 -> -12171 | X56: =-CFS!DN86 -> -14013.315 | Y56: =-CFS!DU86 -> -16441.264 | Z56: =-CFS!EB86 -> -20839.961 | AA56: =-CFS!EI86 -> -25321.263 | AB56: =-CFS!EP86 -> -31830.022
A57: Net Debt/EBITDA adjusted | B57: =B56/B15 -> -2.0716527 | C57: =C56/C15 -> -0.96230715 | D57: =D56/D15 -> -0.84092265 | E57: =E56/E15 -> -1.8695768 | F57: =F56/F15 -> -2.9568993 | G57: =G56/G15 -> -2.9473526 | H57: =H56/H15 -> -2.4578264 | I57: =I56/I15 -> -2.1039265 | ... AB57: =AB56/AB15 -> -1.7351016
A58: Net Debt/Equity | B58: =B56/B61 -> -0.24435534 | C58: =C56/C61 -> -0.399898 | D58: =D56/D61 -> -0.32493277 | E58: =E56/E61 -> -0.53659282 | F58: =F56/F61 -> -0.83405915 | G58: =G56/G61 -> -0.92994779 | H58: =H56/H61 -> -1.3480376 | I58: =I56/I61 -> -1.319887 | ... AB58: =AB56/AB61 -> -0.64704073
A60: Returns
A61: Equity | B61: =BS!E56-BS!E51 -> 16210 | C61: =BS!F56-BS!F51 -> 13726 | D61: =BS!G56-BS!G51 -> 13015 | E61: =BS!H56-BS!H51 -> 13090 | F61: =BS!I56-BS!I51 -> 11022 | G61: =BS!J56-BS!J51 -> 10535 | H61: =BS!K56-BS!K51 -> 8841 | I61: =BS!L56-BS!L51 -> 8850 | J61: =BS!M56-BS!M51 -> 10409 | K61: =BS!T56-BS!T51 -> 10864 | L61: =BS!AA56-BS!AA51 -> 7061 | M61: =BS!AH56-BS!AH51 -> 5966 | N61: =BS!AO56-BS!AO51 -> 3657 | O61: =BS!BC56-BS!BC51 -> 10740 | P61: =BS!BJ56-BS!BJ51 -> 9724 | Q61: =BS!BQ56-BS!BQ51 -> 5975 | R61: =BS!BX56-BS!BX51 -> 6445 | S61: =BS!CE56-BS!CE51 -> 9466 | T61: =BS!CL56-BS!CL51 -> 12950 | U61: =BS!CS56-BS!CS51 -> 17695 | V61: =BS!CZ56-BS!CZ51 -> 19606 | W61: =BS!DG56-BS!DG51 -> 26104 | X61: =BS!DN56-BS!DN51 -> 29811.295 | Y61: =BS!DU56-BS!DU51 -> 33187.959 | Z61: =BS!EB56-BS!EB51 -> 37838.39 | AA61: =BS!EI56-BS!EI51 -> 42609.51 | AB61: =BS!EP56-BS!EP51 -> 49193.227
A62: Minorities | B62: =BS!E51 -> 144 | C62: =BS!F51 -> 176 | D62: =BS!G51 -> 137 | E62: =BS!H51 -> 85 | F62: =BS!I51 -> 104 | G62: =BS!J51 -> 106 | H62: =BS!K51 -> 95 | I62: =BS!L51 -> 15 | J62: =BS!M51 -> 25 | K62: =BS!T51 -> 42 | L62: =BS!AA51 -> 18 | M62: =BS!AH51 -> 7 | N62: =BS!AO51 -> -5 | O62: =BS!BC51 -> 2 | P62: =BS!BJ51 -> -5 | Q62: =BS!BQ51 -> 15 | R62: =BS!BX51 -> 11 | S62: =BS!CE51 -> 20 | T62: =BS!CL51 -> 32 | U62: =BS!CS51 -> 35 | V62: =BS!CZ51 -> 90 | W62: =BS!DG51 -> 80 | X62: =BS!DN51 -> -145 | Y62: =BS!DU51 -> -370 | Z62: =BS!EB51 -> -595 | AA62: =BS!EI51 -> -820 | AB62: =BS!EP51 -> -1045
A63: Pensions | B63: =+BS!E39 -> 4535 | C63: =+BS!F39 -> 5128 | D63: =+BS!G39 -> 5751 | E63: =+BS!H39 -> 4542 | F63: =+BS!I39 -> 4442 | G63: =+BS!J39 -> 5139 | H63: =+BS!K39 -> 4983 | I63: =+BS!L39 -> 5504 | J63: =+BS!M39 -> 6024 | K63: =+BS!T39 -> 5866 | L63: =+BS!AA39 -> 7864 | M63: =+BS!AH39 -> 7172 | N63: =+BS!AO39 -> 8656 | O63: =+BS!BC39 -> 8361 | P63: =+BS!BJ39 -> 7072 | Q63: =+BS!BQ39 -> 8353 | R63: =+BS!BX39 -> 9980 | S63: =+BS!CE39 -> 7072 | T63: =+BS!CL39 -> 3509 | U63: =+BS!CS39 -> 2715 | V63: =+BS!CZ39 -> 1821 | W63: =+BS!DG39 -> 1255 | X63: =+BS!DN39 -> 1255 | Y63: =+BS!DU39 -> 1255 | Z63: =+BS!EB39 -> 1255 | AA63: =+BS!EI39 -> 1255 | AB63: =+BS!EP39 -> 1255
A64: Deferred tax | B64: =BS!E42-BS!E16 -> 1591 | C64: =BS!F42-BS!F16 -> -181 | D64: =BS!G42-BS!G16 -> -159 | E64: =BS!H42-BS!H16 -> -517 | F64: =BS!I42-BS!I16 -> -1803 | G64: =BS!J42-BS!J16 -> -1905 | H64: =BS!K42-BS!K16 -> -3055 | I64: =BS!L42-BS!L16 -> -3268 | J64: =BS!M42-BS!M16 -> -3295 | K64: =BS!T42-BS!T16 -> -2279 | L64: =BS!AA42-BS!AA16 -> -4587 | M64: =BS!AH42-BS!AH16 -> -5559 | N64: =BS!AO42-BS!AO16 -> -6265 | O64: =BS!BC42-BS!BC16 -> -3560 | P64: =BS!BJ42-BS!BJ16 -> -3517 | Q64: =BS!BQ42-BS!BQ16 -> -4610 | R64: =BS!BX42-BS!BX16 -> -3572 | S64: =BS!CE42-BS!CE16 -> -4207 | T64: =BS!CL42-BS!CL16 -> -4519 | U64: =BS!CS42-BS!CS16 -> -3087 | V64: =BS!CZ42-BS!CZ16 -> -3234 | W64: =BS!DG42-BS!DG16 -> -1380 | X64: =BS!DN42-BS!DN16 -> -1380 | Y64: =BS!DU42-BS!DU16 -> -1380 | Z64: =BS!EB42-BS!EB16 -> -1380 | AA64: =BS!EI42-BS!EI16 -> -1380 | AB64: =BS!EP42-BS!EP16 -> -1380
A65: Gross interest bearing debt | B65: 5223 | C65: 5097 | D65: 5757 | E65: 4814 | F65: 4504 | G65: 5296 | H65: 4278 | I65: 5104 | J65: =-CFS!M83-CFS!M84 -> 4779 | K65: =-CFS!T83-CFS!T84 -> 5630 | L65: =-CFS!AA83-CFS!AA84 -> 7351 | M65: =-CFS!AH83-CFS!AH84 -> 9125 | N65: =-CFS!AO83-CFS!AO84 -> 10478 | O65: =-CFS!BC83-CFS!BC84 -> 11196 | P65: =-CFS!BJ83-CFS!BJ84 -> 8926 | Q65: =-CFS!BQ83-CFS!BQ84 -> 10148 | R65: =-CFS!BX83-CFS!BX84 -> 17095 | S65: =-CFS!CE83-CFS!CE84 -> 15040 | T65: =-CFS!CL83-CFS!CL84 -> 12773 | U65: =-CFS!CS83-CFS!CS84 -> 13591 | V65: =-CFS!CZ83-CFS!CZ84 -> 14279 | W65: =-CFS!DG83-CFS!DG84 -> 14249 | X65: =-CFS!DN83-CFS!DN84 -> 14249 | Y65: =-CFS!DU83-CFS!DU84 -> 14249 | Z65: =-CFS!EB83-CFS!EB84 -> 14249 | AA65: =-CFS!EI83-CFS!EI84 -> 14249 | AB65: =-CFS!EP83-CFS!EP84 -> 14249
A66: Cash (adjusted) | B66: =-BS!F6-BS!F7-BS!F18 -> -10586 | C66: =-BS!G6-BS!G7-BS!G18 -> -9986 | D66: =-BS!H6-BS!H7-BS!H18 -> -11838 | E66: =-BS!I6-BS!I7-BS!I18 -> -13697 | F66: =-BS!J6-BS!J7-BS!J18 -> -15093 | G66: =-BS!K6-BS!K7-BS!K18 -> -16196 | H66: =-BS!L6-BS!L7-BS!L18 -> -16785 | I66: =-BS!M6-BS!M7-BS!M18 -> -17071 | J66: =-BS!T6-BS!T7-BS!T18 -> -14084 | K66: =-BS!AA6-BS!AA7-BS!AA18 -> -16461 | L66: =-BS!AH6-BS!AH7-BS!AH18 -> -19215 | M66: =-BS!AO6-BS!AO7-BS!AO18 -> -21591 | N66: =-BS!AV6-BS!AV7-BS!AV18 -> -24587 | O66: =-BS!BC6-BS!BC7-BS!BC18 -> -24587 | P66: =-BS!BJ6-BS!BJ7-BS!BJ18 -> -22207 | Q66: =-BS!BQ6-BS!BQ7-BS!BQ18 -> -22682 | R66: =-BS!BX6-BS!BX7-BS!BX18 -> -21407 | S66: =-BS!CE6-BS!CE7-BS!CE18 -> -22683 | T66: =-BS!CL6-BS!CL7-BS!CL18 -> -23598 | U66: =-BS!CS6-BS!CS7-BS!CS18 -> -25278 | V66: =-BS!CZ6-BS!CZ7-BS!CZ18 -> -26864 | W66: =-BS!DG6-BS!DG7-BS!DG18 -> -27218 | X66: =-BS!DN6-BS!DN7-BS!DN18 -> -29062.315 | Y66: =-BS!DU6-BS!DU7-BS!DU18 -> -31490.264 | Z66: =-BS!EB6-BS!EB7-BS!EB18 -> -35888.961 | AA66: =-BS!EI6-BS!EI7-BS!EI18 -> -40370.263 | AB66: =-BS!EP6-BS!EP7-BS!EP18 -> -46879.022
A67: Investments in associates | B67: =-BS!E15 -> -1738 | C67: =-BS!F15 -> -1908 | D67: =-BS!G15 -> -2095 | E67: =-BS!H15 -> -2238 | F67: =-BS!I15 -> -2356 | G67: =-BS!J15 -> -2514 | H67: =-BS!K15 -> -2451 | I67: =-BS!L15 -> -2677 | J67: =-BS!M15 -> -2662 | K67: =-BS!T15 -> -3858 | L67: =-BS!AA15 -> -3391 | M67: =-BS!AH15 -> -1326 | N67: =-BS!AO15 -> -1608 | O67: =-BS!BC15 -> -1617 | P67: =-BS!BJ15 -> -1693 | Q67: =-BS!BQ15 -> -1626 | R67: =-BS!BX15 -> -1578 | S67: =-BS!CE15 -> -1672 | T67: =-BS!CL15 -> -2067 | U67: =-BS!CS15 -> -2228 | V67: =-BS!CZ15 -> -2433 | W67: =-BS!DG15 -> -2360 | X67: =-BS!DN15 -> -2324.8889 | Y67: =-BS!DU15 -> -2285.812 | Z67: =-BS!EB15 -> -2243.2667 | AA67: =-BS!EI15 -> -2198.8022 | AB67: =-BS!EP15 -> -2152.8053
A68: Other investments & l/t financial assets | B68: -2110 | C68: -1938 | D68: -1666 | E68: -1553 | F68: -1712 | G68: -2210 | H68: -2386 | I68: -2352 | J68: -2115 | K68: -1864 | L68: -1769 | M68: -2492 | N68: -3655 | O68: -4204 | P68: -3811 | Q68: -4453 | R68: -3855 | S68: -4001 | T68: -4190 | U68: -4719 | V68: -5077 | W68: -5077 | X68: -5077 | Y68: -5077 | Z68: -5077 | AA68: -5077 | AB68: -5077
A69: EU gov't refundable advances | B69: 5119 | C69: 5293 | D69: 5418 | E69: 5315 | F69: 4920 | G69: 5294 | H69: 6020 | I69: 5737 | J69: 6112 | K69: 6366 | L69: 6528 | M69: 7286 | N69: 7070 | O69: 5901 | P69: 4577 | Q69: 4277 | R69: 3912 | S69: 3861 | T69: 3857 | U69: 3856 | V69: 3861 | W69: 3861 | X69: 3861 | Y69: 3861 | Z69: 3861 | AA69: 3861 | AB69: 3861
A70: MS adjustments | B70: =SUM(B62:B69) -> 2178 | C70: =SUM(C62:C69) -> 1681 | D70: =SUM(D62:D69) -> 1305 | E70: =SUM(E62:E69) -> -3249 | F70: =SUM(F62:F69) -> -6994 | G70: =SUM(G62:G69) -> -6990 | H70: =SUM(H62:H69) -> -9301 | I70: =SUM(I62:I69) -> -9008 | ... AB70: =SUM(AB62:AB69) -> -37168.827
A71: Capital employed | B71: =BS!E24-BS!E35 -> 41234 | C71: =BS!F24-BS!F35 -> 38641 | D71: =BS!G24-BS!G35 -> 40921 | E71: =BS!H24-BS!H35 -> 41388 | F71: =BS!I24-BS!I35 -> 39428 | G71: =BS!J24-BS!J35 -> 37928 | H71: =BS!K24-BS!K35 -> 39417 | I71: =BS!L24-BS!L35 -> 40980 | J71: =BS!M24-BS!M35 -> 43454 | K71: =BS!T24-BS!T35 -> 43923 | L71: =BS!AA24-BS!AA35 -> 47925 | M71: =BS!AH24-BS!AH35 -> 52673 | N71: =BS!AO24-BS!AO35 -> 54441 | O71: =BS!BC24-BS!BC35 -> 53564 | P71: =BS!BJ24-BS!BJ35 -> 54412 | Q71: =BS!BQ24-BS!BQ35 -> 52035 | R71: =BS!BX24-BS!BX35 -> 60324 | S71: =BS!CE24-BS!CE35 -> 59240 | T71: =BS!CL24-BS!CL35 -> 63349 | U71: =BS!CS24-BS!CS35 -> 65121 | V71: =BS!CZ24-BS!CZ35 -> 68590 | W71: =BS!DG24-BS!DG35 -> 71428 | X71: =BS!DN24-BS!DN35 -> 75734.07 | Y71: =BS!DU24-BS!DU35 -> 79538.71 | Z71: =BS!EB24-BS!EB35 -> 84460.554 | AA71: =BS!EI24-BS!EI35 -> 89829.238 | AB71: =BS!EP24-BS!EP35 -> 96958.543
A72: Goodwill | B72: =BS!E66 -> 9460 | C72: =BS!F66 -> 10159 | D72: =BS!G66 -> 9571 | E72: =BS!H66 -> 9519 | F72: =BS!I66 -> 9760 | G72: =BS!J66 -> 9741 | H72: =BS!K66 -> 9809 | I72: =BS!L66 -> 10812 | J72: =BS!M66 -> 11017 | K72: =BS!T66 -> 9872 | L72: =BS!AA66 -> 9979 | M72: =BS!AH66 -> 9907 | N72: =BS!AO66 -> 9425 | O72: =BS!BC66 -> 9141 | P72: =BS!BJ66 -> 13039 | Q72: =BS!BQ66 -> 13019 | R72: =BS!BX66 -> 12999 | S72: =BS!CE66 -> 13028 | T72: =BS!CL66 -> 13165 | U72: =BS!CS66 -> 13141 | V72: =BS!CZ66 -> 13449 | W72: =BS!DG66 -> 13556 | X72: =BS!DN66 -> 13556 | Y72: =BS!DU66 -> 13556 | Z72: =BS!EB66 -> 13556 | AA72: =BS!EI66 -> 13556 | AB72: =BS!EP66 -> 13556
A73: Capital Employed ex goodwill | B73: =B71-B72 -> 31774 | C73: =C71-C72 -> 28482 | D73: =D71-D72 -> 31350 | E73: =E71-E72 -> 31869 | F73: =F71-F72 -> 29668 | G73: =G71-G72 -> 28187 | H73: =H71-H72 -> 29608 | I73: =I71-I72 -> 30168 | ... AB73: =AB71-AB72 -> 83402.543
A75: ROCE reported (avg) | B75: =B17/(AVERAGE(A71:B71)) -> 0.058980453 | C75: =C17/(AVERAGE(B71:C71)) -> 0.071411581 | D75: =D17/(AVERAGE(C71:D71)) -> 0.010029914 | E75: =E17/(AVERAGE(D71:E71)) -> 0.0012635313 | F75: =F17/(AVERAGE(E71:F71)) -> 0.081666997 | G75: =G17/(AVERAGE(F71:G71)) -> 0.055587155 | H75: =H17/(AVERAGE(G71:H71)) -> 0.034649945 | I75: =I17/(AVERAGE(H71:I71)) -> 0.044628531 | ... AB75: =AB17/(AVERAGE(AA71:AB71)) -> 0.14534252
A76: ROCE ex-goodwill (avg) | B76: =B17/(AVERAGE(A73:B73)) -> 0.076540568 | C76: =C17/(AVERAGE(B73:C73)) -> 0.094662772 | D76: =D17/(AVERAGE(C73:D73)) -> 0.013337345 | E76: =E17/(AVERAGE(D73:E73)) -> 0.0016450751 | F76: =F17/(AVERAGE(E73:F73)) -> 0.10725255 | G76: =G17/(AVERAGE(F73:G73)) -> 0.07432374 | H76: =H17/(AVERAGE(G73:H73)) -> 0.046370793 | I76: =I17/(AVERAGE(H73:I73)) -> 0.06002409 | ... AB76: =AB17/(AVERAGE(AA73:AB73)) -> 0.17002082
A77: ROE reported (avg) | B77: =B17/AVERAGE(A61:B61) -> 0.15003085 | C77: =C17/AVERAGE(B61:C61) -> 0.19053982 | D77: =D17/AVERAGE(C61:D61) -> 0.029841816 | E77: =E17/AVERAGE(D61:E61) -> 0.0039839111 | F77: =F17/AVERAGE(E61:F61) -> 0.27372263 | G77: =G17/AVERAGE(F61:G61) -> 0.19947117 | H77: =H17/AVERAGE(G61:H61) -> 0.13831544 | I77: =I17/AVERAGE(H61:I61) -> 0.20281499 | ... AB77: =AB17/AVERAGE(AA61:AB61) -> 0.29572329
A79: Investments
A80: Gross Capital Expenditure | B80: 3673 | C80: 2858 | D80: 2851 | E80: 2062 | F80: 1837 | G80: 1959 | H80: 2542 | I80: 2437 | J80: 3634 | K80: 3129 | L80: =BS!AA108+BS!AA89 -> 2633 | M80: =BS!AH108+BS!AH89 -> 3400 | N80: =BS!AO108+BS!AO89 -> 3315 | O80: =BS!AV108+BS!AV89 -> 2748 | P80: =BS!BJ108+BS!BJ89 -> 2327 | Q80: =BS!BQ108+BS!BQ89 -> 2340 | R80: =BS!BX108+BS!BX89 -> 1759 | S80: =BS!CE108+BS!CE89 -> 1928 | T80: =BS!CL108+BS!CL89 -> 2464 | U80: =BS!CS108+BS!CS89 -> 3051 | V80: =BS!CZ108+BS!CZ89 -> 3669 | W80: =BS!DG108+BS!DG89 -> 3964 | X80: =BS!DN108+BS!DN89 -> 4214.2182 | Y80: =BS!DU108+BS!DU89 -> 4376.9822 | Z80: =BS!EB108+BS!EB89 -> 4577.0666 | AA80: =BS!EI108+BS!EI89 -> 4612.0076 | AB80: =BS!EP108+BS!EP89 -> 4770.6554
A81: Capital Expenditure as a % of Sales | B81: =B80/B12 -> 0.11564497 | C81: =C80/C12 -> 0.083552593 | D81: =D80/D12 -> 0.072298017 | E81: =E80/E12 -> 0.05270557 | F81: =F80/F12 -> 0.042459263 | G81: =G80/G12 -> 0.045747513 | H81: =H80/H12 -> 0.055560413 | I81: =I80/I12 -> 0.049605113 | ... AB81: =AB80/AB12 -> 0.045204864
A82: Capital Expenditure/Depreciation | B82: 2.4260238 | C82: 2.0070225 | D82: 1.7320778 | E82: 1.2002328 | F82: 1.1663492 | G82: 1.1194286 | H82: 1.7665045 | I82: 1.4143935 | J82: 1.7857494 | K82: 1.6390781 | L82: =L80/(BS!AA116+BS!AA96) -> 1.2472762 | M82: =M80/(BS!AH116+BS!AH96) -> 1.4131338 | N82: =N80/(BS!AO116+BS!AO96) -> 1.4655172 | O82: =O80/(BS!AV116+BS!AV96) -> 1.2020997 | P82: =P80/(BS!BJ116+BS!BJ96) -> 0.96958333 | Q82: =Q80/(BS!BQ116+BS!BQ96) -> 0.79945337 | R82: =R80/(BS!BX116+BS!BX96) -> 0.62133522 | S82: =S80/(BS!CE116+BS!CE96) -> 0.82924731 | T82: =T80/(BS!CL116+BS!CL96) -> 0.90721649 | U82: =U80/(BS!CS116+BS!CS96) -> 1.3608385 | V82: =V80/(BS!CZ116+BS!CZ96) -> 1.2860147 | W82: =W80/(BS!DG116+BS!DG96) -> 1.2485039 | X82: =X80/(BS!DN116+BS!DN96) -> 1.160002 | Y82: =Y80/(BS!DU116+BS!DU96) -> 1.080852 | Z82: =Z80/(BS!EB116+BS!EB96) -> 1.0372981 | AA82: =AA80/(BS!EI116+BS!EI96) -> 1 | AB82: =AB80/(BS!EP116+BS!EP96) -> 1
A84: Divisional Revenue
A85: Airbus | B85: =Divisional!E4 -> 20224 | C85: =Divisional!F4 -> 22179 | D85: =Divisional!G4 -> 25190 | E85: =Divisional!H4 -> 25216 | F85: =Divisional!I4 -> 26524 | G85: =Divisional!J4 -> 26370 | H85: =Divisional!K4 -> 27673 | I85: =Divisional!L4 -> 31159 | J85: =Divisional!M4 -> 36943 | K85: =Divisional!T4 -> 39494 | L85: =Divisional!AA4 -> 42280 | M85: =Divisional!AH4 -> 45854 | N85: =Divisional!AO4 -> 49237 | O85: =Divisional!AV4 -> 50958 | P85: =Divisional!BJ4 -> 47970 | Q85: =Divisional!BQ4 -> 54775 | R85: =Divisional!CE4 -> 34250 | S85: =Divisional!CL4 -> 36164 | T85: =Divisional!CS4 -> 41428 | U85: =Divisional!CZ4 -> 47763 | V85: =Divisional!DG4 -> 50646 | W85: =Divisional!DN4 -> 52577 | X85: =Divisional!DU4 -> 58338.759 | Y85: =Divisional!EB4 -> 66232.988 | Z85: =Divisional!EI4 -> 73145.491 | AA85: =Divisional!EP4 -> 76370.601 | AB85: =Divisional!EW4 -> 78628.532
A86: Airbus Helicopters | B86: =Divisional!E5 -> 2786 | C86: =Divisional!F5 -> 3211 | D86: =Divisional!G5 -> 3803 | E86: =Divisional!H5 -> 4172 | F86: =Divisional!I5 -> 4486 | G86: =Divisional!J5 -> 4570 | H86: =Divisional!K5 -> 4830 | I86: =Divisional!L5 -> 5415 | J86: =Divisional!M5 -> 6264 | K86: =Divisional!T5 -> 6297 | L86: =Divisional!AA5 -> 6524 | M86: =Divisional!AH5 -> 6786 | N86: =Divisional!AO5 -> 6652 | O86: =Divisional!AV5 -> 6450 | P86: =Divisional!BJ5 -> 5934 | Q86: =Divisional!BQ5 -> 6007 | R86: =Divisional!CE5 -> 6251 | S86: =Divisional!CL5 -> 6509 | T86: =Divisional!CS5 -> 7048 | U86: =Divisional!CZ5 -> 7337 | V86: =Divisional!DG5 -> 7941 | W86: =Divisional!DN5 -> 8972 | X86: =Divisional!DU5 -> 9371.5052 | Y86: =Divisional!EB5 -> 9789.0023 | Z86: =Divisional!EI5 -> 10225.311 | AA86: =Divisional!EP5 -> 10681.287 | AB86: =Divisional!EW5 -> 11157.829
A87: Airbus Defence & Space | B87: =Divisional!E6 -> 0 | C87: =Divisional!F6 -> 0 | D87: =Divisional!G6 -> 0 | E87: =Divisional!H6 -> 0 | F87: =Divisional!I6 -> 0 | G87: =Divisional!J6 -> 0 | H87: =Divisional!K6 -> 0 | I87: =Divisional!L6 -> 0 | J87: =Divisional!M6 -> 0 | K87: =Divisional!T6 -> 13121 | L87: =Divisional!AA6 -> 13025 | M87: =Divisional!AH6 -> 13080 | N87: =Divisional!AO6 -> 11854 | O87: =Divisional!AV6 -> 10804 | P87: =Divisional!BJ6 -> 11063 | Q87: =Divisional!BQ6 -> 10907 | R87: =Divisional!CE6 -> 10446 | S87: =Divisional!CL6 -> 10186 | T87: =Divisional!CS6 -> 11259 | U87: =Divisional!CZ6 -> 11495 | V87: =Divisional!DG6 -> 12082 | W87: =Divisional!DN6 -> 13405 | X87: =Divisional!DU6 -> 14531.02 | Y87: =Divisional!EB6 -> 15508.245 | Z87: =Divisional!EI6 -> 16283.657 | AA87: =Divisional!EP6 -> 17097.84 | AB87: =Divisional!EW6 -> 17952.732
A88: HQ/Eliminations & other businesses | B88: =Divisional!E12 -> -1620 | C88: =Divisional!F12 -> -1436 | D88: =Divisional!G12 -> -2092 | E88: =Divisional!H12 -> -1754 | F88: =Divisional!I12 -> -1799 | G88: =Divisional!J12 -> -1611 | H88: =Divisional!K12 -> -1553 | I88: =Divisional!L12 -> -1969 | J88: =Divisional!M12 -> -1939 | K88: =Divisional!T12 -> -1345 | L88: =Divisional!AA12 -> -1116 | M88: =Divisional!AH12 -> -1270 | N88: =Divisional!AO12 -> -1162 | O88: =Divisional!AV12 -> -1445 | P88: =Divisional!BJ12 -> -1260 | Q88: =Divisional!BQ12 -> -1211 | R88: =Divisional!CE12 -> -1035 | S88: =Divisional!CL12 -> -710 | T88: =Divisional!CS12 -> -972 | U88: =Divisional!CZ12 -> -1149 | V88: =Divisional!DG12 -> -1439 | W88: =Divisional!DN12 -> -1534 | X88: =Divisional!DU12 -> -1683.1407 | Y88: =Divisional!EB12 -> -1873.2473 | Z88: =Divisional!EI12 -> -2039.5167 | AA88: =Divisional!EP12 -> -2131.5164 | AB88: =Divisional!EW12 -> -2204.976
A90: Divisional EBIT (Adj.)
A91: Airbus | K91: =Divisional!T26 -> 2214 | L91: =Divisional!AA26 -> 2529 | M91: =Divisional!AH26 -> 2780 | N91: =Divisional!AO26 -> 2811 | O91: =Divisional!AV26 -> 3554 | P91: =Divisional!BJ26 -> 4808 | Q91: =Divisional!BQ26 -> 6358 | R91: =Divisional!CE26 -> 618 | S91: =Divisional!CL26 -> 3570 | T91: =Divisional!CS26 -> 4600 | U91: =Divisional!CZ26 -> 4818 | V91: =Divisional!DG26 -> 5093 | W91: =Divisional!DN26 -> 5470 | X91: =Divisional!DU26 -> 5917.678 | Y91: =Divisional!EB26 -> 7312.7601 | Z91: =Divisional!EI26 -> 9368.1627 | AA91: =Divisional!EP26 -> 10185.633 | AB91: =Divisional!EW26 -> 10793.437
A92: Airbus Helicopters | K92: =Divisional!T27 -> 397 | L92: =Divisional!AA27 -> 413 | M92: =Divisional!AH27 -> 427 | N92: =Divisional!AO27 -> 350 | O92: =Divisional!AV27 -> 337 | P92: =Divisional!BJ27 -> 380 | Q92: =Divisional!BQ27 -> 422 | R92: =Divisional!CE27 -> 471 | S92: =Divisional!CL27 -> 535 | T92: =Divisional!CS27 -> 639 | U92: =Divisional!CZ27 -> 735 | V92: =Divisional!DG27 -> 818 | W92: =Divisional!DN27 -> 925 | X92: =Divisional!DU27 -> 963.75376 | Y92: =Divisional!EB27 -> 1055.5232 | Z92: =Divisional!EI27 -> 1153.5804 | AA92: =Divisional!EP27 -> 1234.8607 | AB92: =Divisional!EW27 -> 1289.7011
A93: Airbus Defence & Space | K93: =Divisional!T28 -> 911 | L93: =Divisional!AA28 -> 920 | M93: =Divisional!AH28 -> 1060 | N93: =Divisional!AO28 -> 1002 | O93: =Divisional!AV28 -> 872 | P93: =Divisional!BJ28 -> 935 | Q93: =Divisional!BQ28 -> 565 | R93: =Divisional!CE28 -> 660 | S93: =Divisional!CL28 -> 696 | T93: =Divisional!CS28 -> 384 | U93: =Divisional!CZ28 -> 229 | V93: =Divisional!DG28 -> -566 | W93: =Divisional!DN28 -> 798 | X93: =Divisional!DU28 -> 1017.1714 | Y93: =Divisional!EB28 -> 1163.1183 | Z93: =Divisional!EI28 -> 1302.6925 | AA93: =Divisional!EP28 -> 1393.8973 | AB93: =Divisional!EW28 -> 1490.9659
A94: HQ/Eliminations & other businesses | K94: =Divisional!T30 -> 15 | L94: =Divisional!AA30 -> 204 | M94: =Divisional!AH30 -> -135 | N94: =Divisional!AO30 -> -208 | O94: =Divisional!AV30 -> -510 | P94: =Divisional!BJ30 -> -289 | Q94: =Divisional!BQ30 -> -399 | R94: =Divisional!CE30 -> -43 | S94: =Divisional!CL30 -> 64 | T94: =Divisional!CS30 -> 4 | U94: =Divisional!CZ30 -> 56 | V94: =Divisional!DG30 -> 9 | W94: =Divisional!DN30 -> -65 | X94: =Divisional!DU30 -> 13 | Y94: =Divisional!EB30 -> 0 | Z94: =Divisional!EI30 -> 0 | AA94: =Divisional!EP30 -> 0 | AB94: =Divisional!EW30 -> 0
A96: Divisional EBIT (Adj.) Margin
A97: Airbus | K97: =K91/K85 -> 0.056059148 | L97: =L91/L85 -> 0.059815516 | M97: =M91/M85 -> 0.060627208 | N97: =N91/N85 -> 0.057091212 | O97: =O91/O85 -> 0.069743711 | P97: =P91/P85 -> 0.10022931 | Q97: =Q91/Q85 -> 0.11607485 | R97: =R91/R85 -> 0.018043796 | ... AB97: =AB91/AB85 -> 0.13727125
A98: Airbus Helicopters | K98: =K92/K86 -> 0.063045895 | L98: =L92/L86 -> 0.063304721 | M98: =M92/M86 -> 0.062923666 | N98: =N92/N86 -> 0.052615755 | O98: =O92/O86 -> 0.052248062 | P98: =P92/P86 -> 0.064037749 | Q98: =Q92/Q86 -> 0.070251373 | R98: =R92/R86 -> 0.075347944 | ... AB98: =AB92/AB86 -> 0.1155871
A99: Airbus Defence & Space | K99: =K93/K87 -> 0.069430684 | L99: =L93/L87 -> 0.070633397 | M99: =M93/M87 -> 0.081039755 | N99: =N93/N87 -> 0.084528429 | O99: =O93/O87 -> 0.080710848 | P99: =P93/P87 -> 0.084515954 | Q99: =Q93/Q87 -> 0.051801595 | R99: =R93/R87 -> 0.063182079 | ... AB99: =AB93/AB87 -> 0.083049529

Sheet Divisional
AV1: as rep'd | BC1: IFRS 15 | BJ1: IFRS 15 | BQ1: IFRS 15 | BX1: IFRS 15 | CE1: IFRS 15 | CL1: IFRS 15 | CS1: IFRS 15 | CZ1: IFRS 15 | DG1: IFRS 15 | DH1: 1Q25 | DI1: 2Q25 | DJ1: 3Q25 | DN1: IFRS 15 | DO1: 1Q26 | DP1: 2Q25 | DU1: IFRS 15 | EB1: IFRS 15 | EI1: IFRS 15 | EP1: IFRS 15 | EW1: IFRS 15
B2: 2001 | C2: 2002 | D2: 2003 | E2: 2004 | F2: 2005 | G2: 2006 | H2: 2007 | I2: 2008 | J2: 2009 | K2: 2010 | L2: 2011 | M2: 2012 | N2: Q1 | O2: Q2 | P2: Q3 | Q2: Q4 | R2: H1 | S2: H2 | T2: 2013 | U2: Q1 | V2: Q2 | W2: Q3 | X2: Q4 | Y2: H1 | Z2: H2 | AA2: 2014 | AB2: Q1 | AC2: Q2 | AD2: Q3 | AE2: Q4 | AF2: H1 | AG2: H2 | AH2: 2015 | AI2: Q1 | AJ2: Q2 | AK2: Q3 | AL2: Q4 | AM2: H1 | AN2: H2 | AO2: 2016 | AP2: Q1 | AQ2: Q2 | AR2: Q3 | AS2: Q4 | AT2: H1 | AU2: H2 | AV2: 2017 | AW2: Q1 | AX2: Q2 | AY2: Q3 | AZ2: Q4 | BA2: H1 | BB2: H2 | BC2: 2017 | BD2: Q1 | BE2: Q2 | BF2: Q3 | BG2: Q4 | BH2: H1 | BI2: H2 | BJ2: 2018 | BK2: Q1 | BL2: Q2 | BM2: Q3 | BN2: Q4 | BO2: H1 | BP2: H2 | BQ2: 2019 | BR2: Q1 | BS2: Q2 | BT2: Q3 | BU2: Q4 | BV2: H1 | BW2: H2 | BX2: 2019 rest. | BY2: Q1 | BZ2: Q2 | CA2: Q3 | CB2: Q4 | CC2: H1 | CD2: H2 | CE2: 2020 | CF2: Q1 | CG2: Q2 | CH2: Q3 | CI2: Q4 | CJ2: H1 | CK2: H2 | CL2: 2021 | CM2: Q1 | CN2: Q2 | CO2: Q3 | CP2: Q4 | CQ2: H1 | CR2: H2 | CS2: 2022 | CT2: Q1 | CU2: Q2 | CV2: Q3 | CW2: Q4 | CX2: H1 | CY2: H2 | CZ2: 2023 | DA2: Q1 | DB2: Q2 | DC2: Q3 | DD2: Q4 | DE2: H1 | DF2: H2 | DG2: 2024 | DH2: Q1 | DI2: Q2 | DJ2: Q3 | DK2: Q4 | DL2: H1 | DM2: H2 | DN2: 2025 | DO2: Q1 | DP2: Q2 | DQ2: Q3 | DR2: Q4 | DS2: H1 | DT2: H2 | DU2: 2026e | DV2: Q1 | DW2: Q2 | DX2: Q3 | DY2: Q4 | DZ2: H1 | EA2: H2 | EB2: 2027e | EC2: Q1 | ED2: Q2 | EE2: Q3 | EF2: Q4 | EG2: H1 | EH2: H2 | EI2: 2028e | EJ2: Q1 | EK2: Q2 | EL2: Q3 | EM2: Q4 | EN2: H1 | EO2: H2 | EP2: 2029e | EQ2: Q1 | ER2: Q2 | ES2: Q3 | ET2: Q4 | EU2: H1 | EV2: H2 | EW2: 2030e
A3: Revenue
A4: Airbus | B4: 20549 | C4: 19512 | D4: 19048 | E4: 20224 | F4: 22179 | G4: 25190 | H4: 25216 | I4: 26524 | J4: 26370 | K4: 27673 | L4: 31159 | M4: 36943 | N4: 8759 | O4: =R4-N4 -> 9343 | P4: =27328-R4 -> 9226 | Q4: =S4-P4 -> 12166 | R4: 18102 | S4: =T4-R4 -> 21392 | T4: 39494 | U4: 8937 | V4: =Y4-U4 -> 10492 | W4: =28820-Y4 -> 9391 | X4: =Z4-W4 -> 13460 | Y4: 19429 | Z4: =AA4-Y4 -> 22851 | AA4: 42280 | AB4: 8565 | AC4: =AF4-AB4 -> 12516 | AD4: =31119-AF4 -> 10038 | AE4: =AG4-AD4 -> 14735 | AF4: 21081 | AG4: =AH4-AF4 -> 24773 | AH4: 45854 | AI4: 8668 | AJ4: =AM4-AI4 -> 12393 | AK4: =31511-AM4 -> 10450 | AL4: =AN4-AK4 -> 17726 | AM4: 21061 | AN4: =AO4-AM4 -> 28176 | AO4: 49237 | AP4: 9825 | AQ4: =AT4-AP4 -> 11964 | AR4: 10854 | AS4: =AU4-AR4 -> 18315 | AT4: 21789 | AU4: =AV4-AT4 -> 29169 | AV4: 50958 | AW4: 8166 | AX4: =BA4-AW4 -> 10016 | AY4: =27579-BA4 -> 9397 | AZ4: =BB4-AY4 -> 15907 | BA4: 18182 | BB4: =BC4-BA4 -> 25304 | BC4: 43486 | BD4: 7222 | BE4: 11324 | BF4: =30478-BH4 -> 11932 | BG4: =BI4-BF4 -> 17492 | BH4: =BD4+BE4 -> 18546 | BI4: =BJ4-BH4 -> 29424 | BJ4: 47970 | BK4: 9697 | BL4: 14346 | BM4: 11529 | BN4: =BP4-BM4 -> 19203 | BO4: =BK4+BL4 -> 24043 | BP4: =BQ4-BO4 -> 30732 | BQ4: 54775 | BR4: 9697 | BS4: 14346 | BT4: 11529 | BU4: =BW4-BT4 -> 19203 | BV4: =BR4+BS4 -> 24043 | BW4: =BX4-BV4 -> 30732 | BX4: =BQ4 -> 54775 | BY4: 7569 | BZ4: 4964 | CA4: 7738 | CB4: =CD4-CA4 -> 13979 | CC4: =BY4+BZ4 -> 12533 | CD4: =CE4-CC4 -> 21717 | CE4: 34250 | CF4: 7272 | CG4: =CJ4-CF4 -> 10541 | CH4: 6805 | CI4: =CK4-CH4 -> 11546 | CJ4: 17813 | CK4: =CL4-CJ4 -> 18351 | CL4: 36164 | CM4: 8541 | CN4: 8992 | CO4: 9121 | CP4: =CR4-CO4 -> 14774 | CQ4: =+CM4+CN4 -> 17533 | CR4: =CS4-CQ4 -> 23895 | CS4: 41428 | CT4: 8110 | CU4: =CX4-CT4 -> 12239 | CV4: 11158 | CW4: =CY4-CV4 -> 16256 | CX4: 20349 | CY4: =CZ4-CX4 -> 27414 | CZ4: 47763 | DA4: 9167 | DB4: =DE4-DA4 -> 12048 | DC4: 11664 | DD4: =DF4-DC4 -> 17767 | DE4: 21215 | DF4: =DG4-DE4 -> 29431 | DG4: 50646 | DH4: 9521 | DI4: =DL4-DH4 -> 11308 | DJ4: 13057 | DK4: =DM4-DJ4 -> 18691 | DL4: 20829 | DM4: =DN4-DL4 -> 31748 | DN4: 52577 | DO4: 8436 | DP4: =DS4-DO4 -> 15441 | DQ4: =Airbus!DK11 -> 14465.159 | DR4: =Airbus!DL11 -> 19996.6 | DS4: 23877 | DT4: =Airbus!DN11 -> 34461.759 | DU4: =Airbus!DO11 -> 58338.759 | DV4: =Airbus!DP11 -> 15947.903 | DW4: =Airbus!DQ11 -> 16847.493 | DX4: =Airbus!DR11 -> 16890.459 | DY4: =Airbus!DS11 -> 16547.132 | DZ4: =Airbus!DT11 -> 32795.397 | EA4: =Airbus!DU11 -> 33437.591 | ... EW4: =Airbus!EQ11 -> 78628.532
A5: Airbus Helicopters | B5: =5065*0.55 -> 2785.75 | C5: =3834*0.7 -> 2683.8 | D5: 2586 | E5: 2786 | F5: 3211 | G5: 3803 | H5: 4172 | I5: 4486 | J5: 4570 | K5: 4830 | L5: 5415 | M5: 6264 | N5: 1038 | O5: =R5-N5 -> 1546 | P5: =4132-R5 -> 1548 | Q5: =S5-P5 -> 2165 | R5: 2584 | S5: =T5-R5 -> 3713 | T5: 6297 | U5: 1182 | V5: =Y5-U5 -> 1619 | W5: =4260-Y5 -> 1459 | X5: =Z5-W5 -> 2264 | Y5: 2801 | Z5: =AA5-Y5 -> 3723 | AA5: 6524 | AB5: 1285 | AC5: =AF5-AB5 -> 1665 | AD5: =4423-AF5 -> 1473 | AE5: =AG5-AD5 -> 2363 | AF5: 2950 | AG5: =AH5-AF5 -> 3836 | AH5: 6786 | AI5: 1158 | AJ5: =AM5-AI5 -> 1529 | AK5: =4282-AM5 -> 1595 | AL5: =AN5-AK5 -> 2370 | AM5: 2687 | AN5: =AO5-AM5 -> 3965 | AO5: 6652 | AP5: 1291 | AQ5: =AT5-AP5 -> 1630 | AR5: 1467 | AS5: =AU5-AR5 -> 2062 | AT5: 2921 | AU5: =AV5-AT5 -> 3529 | AV5: 6450 | AW5: 1176 | AX5: =BA5-AW5 -> 1540 | AY5: =4197-BA5 -> 1481 | AZ5: =BB5-AY5 -> 2138 | BA5: 2716 | BB5: =BC5-BA5 -> 3619 | BC5: 6335 | BD5: 961 | BE5: 1427 | BF5: =3755-BH5 -> 1367 | BG5: =BI5-BF5 -> 2179 | BH5: =BD5+BE5 -> 2388 | BI5: =BJ5-BH5 -> 3546 | BJ5: 5934 | BK5: 1007 | BL5: 1364 | BM5: 1341 | BN5: =BP5-BM5 -> 2295 | BO5: =BK5+BL5 -> 2371 | BP5: =BQ5-BO5 -> 3636 | BQ5: 6007 | BR5: 1007 | BS5: 1364 | BT5: 1341 | BU5: =BW5-BT5 -> 2295 | BV5: =BR5+BS5 -> 2371 | BW5: =BX5-BV5 -> 3636 | BX5: =BQ5 -> 6007 | BY5: 1202 | BZ5: 1131 | CA5: 1290 | CB5: =CD5-CA5 -> 2628 | CC5: =BY5+BZ5 -> 2333 | CD5: =CE5-CC5 -> 3918 | CE5: 6251 | CF5: 1177 | CG5: =CJ5-CF5 -> 1417 | CH5: 1543 | CI5: =CK5-CH5 -> 2372 | CJ5: 2594 | CK5: =CL5-CJ5 -> 3915 | CL5: 6509 | CM5: 1265 | CN5: 1479 | CO5: 1771 | CP5: =CR5-CO5 -> 2533 | CQ5: =+CM5+CN5 -> 2744 | CR5: =CS5-CQ5 -> 4304 | CS5: 7048 | CT5: 1598 | CU5: =CX5-CT5 -> 1596 | CV5: 1468 | CW5: =CY5-CV5 -> 2675 | CX5: 3194 | CY5: =CZ5-CX5 -> 4143 | CZ5: 7337 | DA5: 1461 | DB5: =DE5-DA5 -> 1730 | DC5: 1684 | DD5: =DF5-DC5 -> 3066 | DE5: 3191 | DF5: =DG5-DE5 -> 4750 | DG5: 7941 | DH5: 1600 | DI5: =DL5-DH5 -> 2093 | DJ5: 1959 | DK5: =DM5-DJ5 -> 3320 | DL5: 3693 | DM5: =DN5-DL5 -> 5279 | DN5: 8972 | DO5: 1604 | DP5: =DS5-DO5 -> 2076 | DQ5: =Helicopters!DC4 -> 2081.9272 | DR5: =Helicopters!DD4 -> 3609.578 | DS5: 3680 | DT5: =Helicopters!DF4 -> 5691.5052 | DU5: =Helicopters!DG4 -> 9371.5052 | DV5: =Helicopters!DH4 -> 1677.8867 | DW5: =Helicopters!DI4 -> 2169.5092 | DX5: =Helicopters!DJ4 -> 2175.713 | DY5: =Helicopters!DK4 -> 3765.8934 | DZ5: =Helicopters!DL4 -> 3847.3958 | EA5: =Helicopters!DM4 -> 5941.6064 | ... EW5: =Helicopters!EI4 -> 11157.829
A6: Airbus Defence & Space | N6: 2664 | O6: =R6-N6 -> 2900 | P6: =8382-R6 -> 2818 | Q6: =S6-P6 -> 4739 | R6: 5564 | S6: =T6-R6 -> 7557 | T6: 13121 | U6: 2743 | V6: =Y6-U6 -> 2773 | W6: =8197-Y6 -> 2681 | X6: =Z6-W6 -> 4828 | Y6: 5516 | Z6: =AA6-Y6 -> 7509 | AA6: 13025 | AB6: 2603 | AC6: =AF6-AB6 -> 2928 | AD6: =8383-AF6 -> 2852 | AE6: =AG6-AD6 -> 4697 | AF6: 5531 | AG6: =AH6-AF6 -> 7549 | AH6: 13080 | AI6: 2534 | AJ6: =AM6-AI6 -> 2906 | AK6: =7714-AM6 -> 2274 | AL6: =AN6-AK6 -> 4140 | AM6: 5440 | AN6: =AO6-AM6 -> 6414 | AO6: 11854 | AP6: 2114 | AQ6: =AT6-AP6 -> 2511 | AR6: 2108 | AS6: =AU6-AR6 -> 4071 | AT6: 4625 | AU6: =AV6-AT6 -> 6179 | AV6: 10804 | AW6: 2340 | AX6: =BA6-AW6 -> 2560 | AY6: =7052-BA6 -> 2152 | AZ6: =BB6-AY6 -> 3544 | BA6: 4900 | BB6: =BC6-BA6 -> 5696 | BC6: 10596 | BD6: 2217 | BE6: 2435 | BF6: =7051-BH6 -> 2399 | BG6: =BI6-BF6 -> 4012 | BH6: =BD6+BE6 -> 4652 | BI6: =BJ6-BH6 -> 6411 | BJ6: 11063 | BK6: 2112 | BL6: 2903 | BM6: 2691 | BN6: =BP6-BM6 -> 3201 | BO6: =BK6+BL6 -> 5015 | BP6: =BQ6-BO6 -> 5892 | BQ6: 10907 | BR6: 2112 | BS6: 2903 | BT6: 2691 | BU6: =BW6-BT6 -> 3201 | BV6: =BR6+BS6 -> 5015 | BW6: =BX6-BV6 -> 5892 | BX6: =BQ6 -> 10907 | BY6: 2111 | BZ6: 2440 | CA6: 2385 | CB6: =CD6-CA6 -> 3510 | CC6: =BY6+BZ6 -> 4551 | CD6: =CE6-CC6 -> 5895 | CE6: 10446 | CF6: 2115 | CG6: =CJ6-CF6 -> 2423 | CH6: 2343 | CI6: =CK6-CH6 -> 3305 | CJ6: 4538 | CK6: =CL6-CJ6 -> 5648 | CL6: 10186 | CM6: 2453 | CN6: 2603 | CO6: 2537 | CP6: =CR6-CO6 -> 3666 | CQ6: =+CM6+CN6 -> 5056 | CR6: =CS6-CQ6 -> 6203 | CS6: 11259 | CT6: 2299 | CU6: =CX6-CT6 -> 2354 | CV6: 2480 | CW6: =CY6-CV6 -> 4362 | CX6: 4653 | CY6: =CZ6-CX6 -> 6842 | CZ6: 11495 | DA6: 2399 | DB6: =DE6-DA6 -> 2586 | DC6: 2624 | DD6: =DF6-DC6 -> 4473 | DE6: 4985 | DF6: =DG6-DE6 -> 7097 | DG6: 12082 | DH6: 2656 | DI6: =DL6-DH6 -> 3157 | DJ6: 3063 | DK6: =DM6-DJ6 -> 4529 | DL6: 5813 | DM6: =DN6-DL6 -> 7592 | DN6: 13405 | DO6: 2832 | DP6: =DS6-DO6 -> 3484 | DQ6: ='Defence & Space'!CQ4 -> 3343.2645 | DR6: ='Defence & Space'!CR4 -> 4871.7555 | DS6: 6316 | DT6: ='Defence & Space'!CT4 -> 8215.02 | DU6: ='Defence & Space'!CU4 -> 14531.02 | DV6: ='Defence & Space'!CV4 -> 3021.036 | DW6: ='Defence & Space'!CW4 -> 3719.715 | DX6: ='Defence & Space'!CX4 -> 3566.0212 | DY6: ='Defence & Space'!CY4 -> 5201.4723 | DZ6: ='Defence & Space'!CZ4 -> 6740.751 | EA6: ='Defence & Space'!DA4 -> 8767.4935 | ... EW6: ='Defence & Space'!DW4 -> 17952.732
A7: Airbus Military | B7: 547 | C7: 524 | D7: 934 | E7: 1304 | F7: 763 | G7: 2200 | H7: 1140 | I7: 2759 | J7: 2235 | K7: 2684 | L7: 2504 | M7: 2131
A8: Cassidian | B8: 3345 | C8: 4770 | D8: 5165 | E8: 5385 | F8: 5636 | G8: 5864 | H8: 5392 | I8: 5668 | J8: 5363 | K8: 5933 | L8: 5803 | M8: 5740
A9: Astrium | B9: 2439 | C9: 2216 | D9: 2424 | E9: 2592 | F9: 2698 | G9: 3212 | H9: 3550 | I9: 4289 | J9: 4799 | K9: 5003 | L9: 4964 | M9: 5817
A10: Other Businesses | B10: =5065*0.45 -> 2279.25 | C10: =3834*0.3 -> 1150.2 | D10: 1217 | E10: 1090 | F10: 1155 | G10: 1257 | H10: 1407 | I10: 1338 | J10: 1096 | K10: 1182 | L10: 1252 | M10: 1524
A11: Subtotal | B11: =+SUM(B4:B10) -> 31945 | C11: =+SUM(C4:C10) -> 30856 | D11: =+SUM(D4:D10) -> 31374 | E11: =+SUM(E4:E10) -> 33381 | F11: =+SUM(F4:F10) -> 35642 | G11: =+SUM(G4:G10) -> 41526 | H11: =+SUM(H4:H10) -> 40877 | I11: =+SUM(I4:I10) -> 45064 | ... BB11: =+SUM(BB4:BB10) -> 34619 | BC11: =+BC4+BC6+BC5 -> 60417 | BD11: =+SUM(BD4:BD10) -> 10400 | BE11: =+SUM(BE4:BE10) -> 15186 | BF11: =+SUM(BF4:BF10) -> 15698 | BG11: =+SUM(BG4:BG10) -> 23683 | BH11: =+SUM(BH4:BH10) -> 25586 | BI11: =+SUM(BI4:BI10) -> 39381 | BJ11: =+SUM(BJ4:BJ10) -> 64967 | BK11: =+SUM(BK4:BK10) -> 12816 | ... EW11: =+SUM(EW4:EW10) -> 107739.09
A12: HQ/Eliminations & other businesses | B12: -1147 | C12: -955 | D12: -1241 | E12: -1620 | F12: -1436 | G12: -2092 | H12: -1754 | I12: -1799 | J12: =-1639+28 -> -1611 | K12: =-1582+29 -> -1553 | L12: -1969 | M12: -1939 | N12: -367 | O12: =R12-N12 -> -213 | P12: =-895-R12 -> -315 | Q12: =S12-P12 -> -450 | R12: -580 | S12: =T12-R12 -> -765 | T12: -1345 | U12: -214 | V12: =Y12-U12 -> -332 | W12: =-780-Y12 -> -234 | X12: =Z12-W12 -> -336 | Y12: -546 | Z12: =AA12-Y12 -> -570 | AA12: =482-1598 -> -1116 | AB12: -375 | AC12: =AF12-AB12 -> -294 | AD12: =-960-AF12 -> -291 | AE12: =AG12-AD12 -> -310 | AF12: =-792+123 -> -669 | AG12: =AH12-AF12 -> -601 | AH12: =296-1566 -> -1270 | AI12: -177 | AJ12: =AM12-AI12 -> -256 | AK12: =-802-AM12 -> -369 | AL12: =AN12-AK12 -> -360 | AM12: =-588+155 -> -433 | AN12: =AO12-AM12 -> -729 | AO12: =57-1219 -> -1162 | AP12: -242 | AQ12: =AT12-AP12 -> -384 | AR12: -185 | AS12: =AU12-AR12 -> -634 | AT12: -626 | AU12: =AV12-AT12 -> -819 | AV12: -1445 | AW12: -240 | AX12: =BA12-AW12 -> -383 | AY12: =-821-BA12 -> -198 | AZ12: =BB12-AY12 -> -574 | BA12: -623 | BB12: =BC12-BA12 -> -772 | BC12: -1395 | BD12: -281 | BE12: -335 | BF12: =-863-BH12 -> -247 | BG12: =BI12-BF12 -> -397 | BH12: =BD12+BE12 -> -616 | BI12: =BJ12-BH12 -> -644 | BJ12: -1260 | BK12: -267 | BL12: -296 | BM12: -259 | BN12: =BP12-BM12 -> -389 | BO12: =BK12+BL12 -> -563 | BP12: =BQ12-BO12 -> -648 | BQ12: -1211 | BR12: -267 | BS12: -296 | BT12: -259 | BU12: =BW12-BT12 -> -389 | BV12: =BR12+BS12 -> -563 | BW12: =BX12-BV12 -> -648 | BX12: -1211 | BY12: -251 | BZ12: -218 | CA12: -200 | CB12: =CD12-CA12 -> -366 | CC12: =BY12+BZ12 -> -469 | CD12: =CE12-CC12 -> -566 | CE12: -1035 | CF12: -104 | CG12: =CJ12-CF12 -> -204 | CH12: -173 | CI12: =CK12-CH12 -> -229 | CJ12: -308 | CK12: =CL12-CJ12 -> -402 | CL12: -710 | CM12: -259 | CN12: -264 | CO12: -120 | CP12: =CR12-CO12 -> -329 | CQ12: =+CM12+CN12 -> -523 | CR12: =CS12-CQ12 -> -449 | CS12: -972 | CT12: -244 | CU12: =CX12-CT12 -> -289 | CV12: -209 | CW12: =CY12-CV12 -> -407 | CX12: -533 | CY12: =CZ12-CX12 -> -616 | CZ12: -1149 | DA12: -197 | DB12: =DE12-DA12 -> -369 | DC12: -283 | DD12: =DF12-DC12 -> -590 | DE12: -566 | DF12: =DG12-DE12 -> -873 | DG12: -1439 | DH12: -235 | DI12: =DL12-DH12 -> -490 | DJ12: -253 | DK12: =DM12-DJ12 -> -556 | DL12: -725 | DM12: =DN12-DL12 -> -809 | DN12: -1534 | DO12: -221 | DP12: =DS12-DO12 -> -476 | DQ12: =DT12/2 -> -493.07037 | DR12: =DT12-DQ12 -> -493.07037 | DS12: -697 | DT12: =DU12-DS12 -> -986.14073 | DU12: =DN12*(1+((DU11/DN11)-1)) -> -1683.1407 | DV12: =DZ12/2 -> -468.31183 | DW12: =DZ12-DV12 -> -468.31183 | DX12: =EA12/2 -> -468.31183 | DY12: =EA12-DX12 -> -468.31183 | DZ12: =EB12/2 -> -936.62366 | EA12: =EB12-DZ12 -> -936.62366 | EB12: =DU12*(1+((EB11/DU11)-1)) -> -1873.2473 | EC12: =EG12/2 -> -509.87919 | ED12: =EG12-EC12 -> -509.87919 | EE12: =EH12/2 -> -509.87919 | EF12: =EH12-EE12 -> -509.87919 | EG12: =EI12/2 -> -1019.7584 | EH12: =EI12-EG12 -> -1019.7584 | EI12: =EB12*(1+((EI11/EB11)-1)) -> -2039.5167 | EJ12: =EN12/2 -> -532.87911 | EK12: =EN12-EJ12 -> -532.87911 | EL12: =EO12/2 -> -532.87911 | EM12: =EO12-EL12 -> -532.87911 | EN12: =EP12/2 -> -1065.7582 | EO12: =EP12-EN12 -> -1065.7582 | EP12: =EI12*(1+((EP11/EI11)-1)) -> -2131.5164 | EQ12: =EU12/2 -> -551.24399 | ER12: =EU12-EQ12 -> -551.24399 | ES12: =EV12/2 -> -551.24399 | ET12: =EV12-ES12 -> -551.24399 | EU12: =EW12/2 -> -1102.488 | EV12: =EW12-EU12 -> -1102.488 | EW12: =EP12*(1+((EW11/EP11)-1)) -> -2204.976
A13: Total Revenue | B13: =+B11+B12 -> 30798 | C13: =+C11+C12 -> 29901 | D13: =+D11+D12 -> 30133 | E13: =+E11+E12 -> 31761 | F13: =+F11+F12 -> 34206 | G13: =+G11+G12 -> 39434 | H13: =+H11+H12 -> 39123 | I13: =+I11+I12 -> 43265 | ... EW13: =+EW11+EW12 -> 105534.12
A15: Revenue Growth %
A16: =A4 -> Airbus | C16: =C4/B4-1 -> -0.050464743 | D16: =D4/C4-1 -> -0.023780238 | E16: =E4/D4-1 -> 0.061738765 | F16: =F4/E4-1 -> 0.096667326 | G16: =G4/F4-1 -> 0.13575905 | H16: =H4/G4-1 -> 0.0010321556 | I16: =I4/H4-1 -> 0.051871827 | J16: =J4/I4-1 -> -0.0058060624 | ... M16: =M4/L4-1 -> 0.18562855 | T16: =T4/M4-1 -> 0.069052324 | U16: =U4/N4-1 -> 0.020321955 | V16: =V4/O4-1 -> 0.12297977 | W16: =W4/P4-1 -> 0.01788424 | X16: =X4/Q4-1 -> 0.10636199 | Y16: =Y4/R4-1 -> 0.073306817 | Z16: =Z4/S4-1 -> 0.068203067 | AA16: =AA4/T4-1 -> 0.070542361 | ... AV16: =AV4/AO4-1 -> 0.034953389 | AW16: =AW4/AI4-1 -> -0.057914167 | AX16: =AX4/AJ4-1 -> -0.19180182 | AY16: =AY4/AK4-1 -> -0.10076555 | AZ16: =AZ4/AL4-1 -> -0.10261762 | BA16: =BA4/AM4-1 -> -0.13669816 | BB16: =BB4/AN4-1 -> -0.10193072 | BC16: =BC4/AO4-1 -> -0.1168024 | BD16: =BD4/AW4-1 -> -0.11560127 | BE16: =BE4/AX4-1 -> 0.13059105 | BF16: =BF4/AY4-1 -> 0.26976695 | BG16: =BG4/AZ4-1 -> 0.099641667 | BH16: =BH4/BA4-1 -> 0.0200198 | BI16: =BI4/BB4-1 -> 0.16282011 | BJ16: =BJ4/BC4-1 -> 0.10311365 | BK16: =BK4/BD4-1 -> 0.34270285 | ... BQ16: =BQ4/BJ4-1 -> 0.1418595 | BR16: =BR4/BD4-1 -> 0.34270285 | BS16: =BS4/BE4-1 -> 0.26686683 | BT16: =BT4/BF4-1 -> -0.033774723 | BU16: =BU4/BG4-1 -> 0.097816145 | BV16: =BV4/BH4-1 -> 0.29639815 | BW16: =BW4/BI4-1 -> 0.044453507 | BX16: =BX4/BJ4-1 -> 0.1418595 | BY16: =BY4/BR4-1 -> -0.21944931 | BZ16: =BZ4/BS4-1 -> -0.6539802 | CA16: =CA4/BT4-1 -> -0.32882297 | CB16: =CB4/BU4-1 -> -0.27204083 | CC16: =CC4/BV4-1 -> -0.47872562 | CD16: =CD4/BW4-1 -> -0.29334244 | CE16: =CE4/BQ4-1 -> -0.37471474 | CF16: =CF4/BY4-1 -> -0.039239001 | CG16: =CG4/BZ4-1 -> 1.1234891 | CH16: =CH4/CA4-1 -> -0.12057379 | CI16: =CI4/CB4-1 -> -0.17404678 | CJ16: =CJ4/CC4-1 -> 0.4212878 | CK16: =CK4/CD4-1 -> -0.15499378 | CL16: =CL4/CE4-1 -> 0.055883212 | CM16: =CM4/CF4-1 -> 0.17450495 | ... EW16: =EW4/EP4-1 -> 0.029565456
A17: Airbus Helicopters | C17: =C5/B5-1 -> -0.036596967 | D17: =D5/C5-1 -> -0.036440867 | E17: =E5/D5-1 -> 0.07733952 | F17: =F5/E5-1 -> 0.15254846 | G17: =G5/F5-1 -> 0.18436624 | H17: =H5/G5-1 -> 0.097028662 | I17: =I5/H5-1 -> 0.075263663 | J17: =J5/I5-1 -> 0.018724922 | ... M17: =M5/L5-1 -> 0.1567867 | T17: =T5/M5-1 -> 0.0052681992 | U17: =U5/N5-1 -> 0.13872832 | V17: =V5/O5-1 -> 0.047218629 | W17: =W5/P5-1 -> -0.05749354 | X17: =X5/Q5-1 -> 0.045727483 | Y17: =Y5/R5-1 -> 0.083978328 | Z17: =Z5/S5-1 -> 0.00269324 | AA17: =AA5/T5-1 -> 0.036048912 | ... AV17: =AV5/AO5-1 -> -0.030366807 | AW17: =AW5/AI5-1 -> 0.015544041 | AX17: =AX5/AJ5-1 -> 0.0071942446 | AY17: =AY5/AK5-1 -> -0.071473354 | AZ17: =AZ5/AL5-1 -> -0.097890295 | BA17: =BA5/AM5-1 -> 0.010792706 | BB17: =BB5/AN5-1 -> -0.087263556 | BC17: =BC5/AO5-1 -> -0.047654841 | BD17: =BD5/AW5-1 -> -0.18282313 | BE17: =BE5/AX5-1 -> -0.073376623 | BF17: =BF5/AY5-1 -> -0.076975017 | BG17: =BG5/AZ5-1 -> 0.019176801 | BH17: =BH5/BA5-1 -> -0.12076583 | BI17: =BI5/BB5-1 -> -0.020171318 | BJ17: =BJ5/BC5-1 -> -0.063299132 | BK17: =BK5/BD5-1 -> 0.047866805 | ... BQ17: =BQ5/BJ5-1 -> 0.012301989 | BR17: =BR5/BD5-1 -> 0.047866805 | BS17: =BS5/BE5-1 -> -0.044148563 | BT17: =BT5/BF5-1 -> -0.019019751 | BU17: =BU5/BG5-1 -> 0.053235429 | BV17: =BV5/BH5-1 -> -0.007118928 | BW17: =BW5/BI5-1 -> 0.025380711 | BX17: =BX5/BJ5-1 -> 0.012301989 | BY17: =BY5/BR5-1 -> 0.19364449 | BZ17: =BZ5/BS5-1 -> -0.17082111 | CA17: =CA5/BT5-1 -> -0.03803132 | CB17: =CB5/BU5-1 -> 0.14509804 | CC17: =CC5/BV5-1 -> -0.016026993 | CD17: =CD5/BW5-1 -> 0.077557756 | CE17: =CE5/BQ5-1 -> 0.040619278 | CF17: =CF5/BY5-1 -> -0.020798669 | CG17: =CG5/BZ5-1 -> 0.25287356 | CH17: =CH5/CA5-1 -> 0.19612403 | CI17: =CI5/CB5-1 -> -0.097412481 | CJ17: =CJ5/CC5-1 -> 0.11187312 | CK17: =CK5/CD5-1 -> -0.00076569678 | CL17: =CL5/CE5-1 -> 0.041273396 | CM17: =CM5/CF5-1 -> 0.074766355 | ... EW17: =EW5/EP5-1 -> 0.04461466
A18: Airbus Defence & Space | U18: =U6/N6-1 -> 0.029654655 | V18: =V6/O6-1 -> -0.043793103 | W18: =W6/P6-1 -> -0.04861604 | X18: =X6/Q6-1 -> 0.018780333 | Y18: =Y6/R6-1 -> -0.0086268871 | Z18: =Z6/S6-1 -> -0.0063517269 | AA18: =AA6/T6-1 -> -0.0073165155 | AB18: =AB6/U6-1 -> -0.051039008 | ... AV18: =AV6/AO6-1 -> -0.088577695 | AW18: =AW6/AI6-1 -> -0.0765588 | AX18: =AX6/AJ6-1 -> -0.11906401 | AY18: =AY6/AK6-1 -> -0.053649956 | AZ18: =AZ6/AL6-1 -> -0.14396135 | BA18: =BA6/AM6-1 -> -0.099264706 | BB18: =BB6/AN6-1 -> -0.11194263 | BC18: =BC6/AO6-1 -> -0.10612451 | BD18: =BD6/AW6-1 -> -0.052564103 | BE18: =BE6/AX6-1 -> -0.048828125 | BF18: =BF6/AY6-1 -> 0.11477695 | BG18: =BG6/AZ6-1 -> 0.13205418 | BH18: =BH6/BA6-1 -> -0.050612245 | BI18: =BI6/BB6-1 -> 0.12552669 | BJ18: =BJ6/BC6-1 -> 0.044073235 | BK18: =BK6/BD6-1 -> -0.047361299 | ... BQ18: =BQ6/BJ6-1 -> -0.014101058 | BR18: =BR6/BD6-1 -> -0.047361299 | BS18: =BS6/BE6-1 -> 0.19219713 | BT18: =BT6/BF6-1 -> 0.12171738 | BU18: =BU6/BG6-1 -> -0.20214357 | BV18: =BV6/BH6-1 -> 0.078030954 | BW18: =BW6/BI6-1 -> -0.080954609 | BX18: =BX6/BJ6-1 -> -0.014101058 | BY18: =BY6/BR6-1 -> -0.00047348485 | BZ18: =BZ6/BS6-1 -> -0.15949018 | CA18: =CA6/BT6-1 -> -0.11371237 | CB18: =CB6/BU6-1 -> 0.096532334 | CC18: =CC6/BV6-1 -> -0.092522433 | CD18: =CD6/BW6-1 -> 0.00050916497 | CE18: =CE6/BQ6-1 -> -0.042266434 | CF18: =CF6/BY6-1 -> 0.0018948366 | CG18: =CG6/BZ6-1 -> -0.0069672131 | CH18: =CH6/CA6-1 -> -0.017610063 | CI18: =CI6/CB6-1 -> -0.058404558 | CJ18: =CJ6/CC6-1 -> -0.0028565151 | CK18: =CK6/CD6-1 -> -0.041899915 | CL18: =CL6/CE6-1 -> -0.02488991 | CM18: =CM6/CF6-1 -> 0.15981087 | ... EW18: =EW6/EP6-1 -> 0.05
A19: =A7 -> Airbus Military | C19: =C7/B7-1 -> -0.042047532 | D19: =D7/C7-1 -> 0.78244275 | E19: =E7/D7-1 -> 0.39614561 | F19: =F7/E7-1 -> -0.4148773 | G19: =G7/F7-1 -> 1.8833552 | H19: =H7/G7-1 -> -0.48181818 | I19: =I7/H7-1 -> 1.4201754 | J19: =J7/I7-1 -> -0.18992389 | ... M19: =M7/L7-1 -> -0.14896166
A20: =A8 -> Cassidian | C20: =C8/B8-1 -> 0.42600897 | D20: =D8/C8-1 -> 0.082809224 | E20: =E8/D8-1 -> 0.042594385 | F20: =F8/E8-1 -> 0.046610956 | G20: =G8/F8-1 -> 0.040454223 | H20: =H8/G8-1 -> -0.080491132 | I20: =I8/H8-1 -> 0.051186944 | J20: =J8/I8-1 -> -0.053810868 | ... M20: =M8/L8-1 -> -0.010856454
A21: =A9 -> Astrium | C21: =C9/B9-1 -> -0.091430914 | D21: =D9/C9-1 -> 0.093862816 | E21: =E9/D9-1 -> 0.069306931 | F21: =F9/E9-1 -> 0.040895062 | G21: =G9/F9-1 -> 0.19051149 | H21: =H9/G9-1 -> 0.10523039 | I21: =I9/H9-1 -> 0.20816901 | J21: =J9/I9-1 -> 0.11890884 | ... M21: =M9/L9-1 -> 0.17183723
A22: =A10 -> Other Businesses | C22: =C10/B10-1 -> -0.49536032 | D22: =D10/C10-1 -> 0.058076856 | E22: =E10/D10-1 -> -0.10435497 | F22: =F10/E10-1 -> 0.059633028 | G22: =G10/F10-1 -> 0.088311688 | H22: =H10/G10-1 -> 0.11933174 | I22: =I10/H10-1 -> -0.049040512 | J22: =J10/I10-1 -> -0.18086697 | ... M22: =M10/L10-1 -> 0.2172524
A23: Total | C23: =C13/B13-1 -> -0.029125268 | D23: =D13/C13-1 -> 0.0077589378 | E23: =E13/D13-1 -> 0.054027146 | F23: =F13/E13-1 -> 0.076981203 | G23: =G13/F13-1 -> 0.15283868 | H23: =H13/G13-1 -> -0.0078865953 | I23: =I13/H13-1 -> 0.10587123 | J23: =J13/I13-1 -> -0.010239223 | ... M23: =M13/L13-1 -> 0.14964989 | T23: =T13/M13-1 -> 0.019245751 | U23: =U13/N13-1 -> 0.045807839 | V23: =V13/O13-1 -> 0.071891573 | W23: =W13/P13-1 -> 0.0015063644 | X23: =X13/Q13-1 -> 0.085714286 | Y23: =Y13/R13-1 -> 0.059602649 | Z23: =Z13/S13-1 -> 0.050663072 | AA23: =AA13/T13-1 -> 0.054649365 | ... AV23: =AV13/AO13-1 -> 0.0027935898 | AW23: =AW13/AI13-1 -> -0.060822458 | AX23: =AX13/AJ13-1 -> -0.17131306 | AY23: =AY13/AK13-1 -> -0.080143369 | AZ23: =AZ13/AL13-1 -> -0.11982744 | BA23: =BA13/AM13-1 -> -0.12450009 | BB23: =BB13/AN13-1 -> -0.1051922 | BC23: =BC13/AO13-1 -> -0.11353089 | BD23: =BD13/AW13-1 -> -0.11562664 | BE23: =BE13/AX13-1 -> 0.081409743 | BF23: =BF13/AY13-1 -> 0.20409913 | BG23: =BG13/AZ13-1 -> 0.10806567 | BH23: =BH13/BA13-1 -> -0.008142999 | BI23: =BI13/BB13-1 -> 0.14447366 | BJ23: =BJ13/BC13-1 -> 0.079377181 | BK23: =BK13/BD13-1 -> 0.24014231 | ... BQ23: =BQ13/BJ13-1 -> 0.10628345 | BR23: =BR13/BD13-1 -> 0.24014231 | BS23: =BS13/BE13-1 -> 0.23338496 | BT23: =BT13/BF13-1 -> -0.0096433888 | BU23: =BU13/BG13-1 -> 0.043974921 | BV23: =BV13/BH13-1 -> 0.23612335 | BW23: =BW13/BI13-1 -> 0.022588223 | BX23: =BX13/BJ13-1 -> 0.10628345 | BY23: =BY13/BR13-1 -> -0.15284086 | BZ23: =BZ13/BS13-1 -> -0.54594093 | CA23: =CA13/BT13-1 -> -0.26721997 | CB23: =CB13/BU13-1 -> -0.18753599 | CC23: =CC13/BV13-1 -> -0.38612065 | CD23: =CD13/BW13-1 -> -0.21831768 | CE23: =CE13/BQ13-1 -> -0.29180737 | CF23: =CF13/BY13-1 -> -0.016085034 | CG23: =CG13/BZ13-1 -> 0.70458098 | CH23: =CH13/CA13-1 -> -0.061981628 | CI23: =CI13/CB13-1 -> -0.13958787 | CJ23: =CJ13/CC13-1 -> 0.30024277 | CK23: =CK13/CD13-1 -> -0.1114843 | CL23: =CL13/CE13-1 -> 0.044818881 | CM23: =CM13/CF13-1 -> 0.14722753 | ... EW23: =EW13/EP13-1 -> 0.034463514
A25: EBIT Adjusted
A26: Airbus | N26: 608 | O26: =R26-N26 -> 623 | P26: =1712-R26 -> 481 | Q26: =S26-P26 -> 502 | R26: 1231 | S26: =T26-R26 -> 983 | T26: 2214 | U26: 527 | V26: =Y26-U26 -> 760 | W26: =1780-Y26 -> 493 | X26: =Z26-W26 -> 749 | Y26: 1287 | Z26: =AA26-Y26 -> 1242 | AA26: 2529 | AB26: 569 | AC26: =AF26-AB26 -> 964 | AD26: =2226-AF26 -> 693 | AE26: =AG26-AD26 -> 554 | AF26: 1533 | AG26: =AH26-AF26 -> 1247 | AH26: 2780 | AI26: 406 | AJ26: =AM26-AI26 -> 863 | AK26: =1836-AM26 -> 567 | AL26: =AN26-AK26 -> 975 | AM26: 1269 | AN26: =AO26-AM26 -> 1542 | AO26: 2811 | AP26: 281 | AQ26: =AT26-AP26 -> 673 | AR26: 591 | AS26: =AU26-AR26 -> 2009 | AT26: 954 | AU26: =AV26-AT26 -> 2600 | AV26: 3554 | AW26: -103 | AX26: =BA26-AW26 -> 360 | AY26: =806-BA26 -> 549 | AZ26: =BB26-AY26 -> 1577 | BA26: 257 | BB26: =BC26-BA26 -> 2126 | BC26: 2383 | BD26: -41 | BE26: 908 | BF26: =2340-BH26 -> 1473 | BG26: =BI26-BF26 -> 2468 | BH26: =BD26+BE26 -> 867 | BI26: =BJ26-BH26 -> 3941 | BJ26: 4808 | BK26: 536 | BL26: 1802 | BM26: 1495 | BN26: =BP26-BM26 -> 2525 | BO26: =BK26+BL26 -> 2338 | BP26: =BQ26-BO26 -> 4020 | BQ26: 6358 | BR26: =536-73 -> 463 | BS26: =1802-145+73 -> 1730 | BT26: =1495-240+145 -> 1400 | BU26: =BW26-BT26 -> 2354 | BV26: =BR26+BS26 -> 2193 | BW26: =BX26-BV26 -> 3754 | BX26: =BQ26-411 -> 5947 | BY26: 191 | BZ26: -1498 | CA26: 666 | CB26: =CD26-CA26 -> 1259 | CC26: =BY26+BZ26 -> -1307 | CD26: =CE26-CC26 -> 1925 | CE26: 618 | CF26: 533 | CG26: =CJ26-CF26 -> 1758 | CH26: 448 | CI26: =CK26-CH26 -> 831 | CJ26: 2291 | CK26: =CL26-CJ26 -> 1279 | CL26: 3570 | CM26: 1065 | CN26: 1211 | CO26: 599 | CP26: =CR26-CO26 -> 1725 | CQ26: =CM26+CN26 -> 2276 | CR26: =CS26-CQ26 -> 2324 | CS26: 4600 | CT26: 580 | CU26: =CX26-CT26 -> 1676 | CV26: 960 | CW26: =CY26-CV26 -> 1602 | CX26: 2256 | CY26: =CZ26-CX26 -> 2562 | CZ26: 4818 | DA26: 507 | DB26: =DE26-DA26 -> 1447 | DC26: 1074 | DD26: =DF26-DC26 -> 2065 | DE26: 1954 | DF26: =DG26-DE26 -> 3139 | DG26: 5093 | DH26: 494 | DI26: =DL26-DH26 -> 1220 | DJ26: 1556 | DK26: =DM26-DJ26 -> 2200 | DL26: 1714 | DM26: =DN26-DL26 -> 3756 | DN26: 5470 | DO26: 81 | DP26: =DS26-DO26 -> 1906 | DQ26: =Airbus!DK45 -> 1587.1268 | DR26: =Airbus!DL45 -> 2343.5513 | DS26: 1987 | DT26: =Airbus!DN45 -> 3930.678 | DU26: =Airbus!DO45 -> 5917.678 | DV26: =Airbus!DP45 -> 1717.4956 | DW26: =Airbus!DQ45 -> 1876.7178 | DX26: =Airbus!DR45 -> 1879.2567 | DY26: =Airbus!DS45 -> 1839.2901 | DZ26: =Airbus!DT45 -> 3594.2134 | EA26: =Airbus!DU45 -> 3718.5467 | ... EW26: =Airbus!EQ45 -> 10793.437
A27: Airbus Helicopters | N27: 20 | O27: =R27-N27 -> 108 | P27: =217-R27 -> 89 | Q27: =S27-P27 -> 180 | R27: 128 | S27: =T27-R27 -> 269 | T27: 397 | U27: 58 | V27: =Y27-U27 -> 92 | W27: =241-Y27 -> 91 | X27: =Z27-W27 -> 172 | Y27: 150 | Z27: =AA27-Y27 -> 263 | AA27: 413 | AB27: 52 | AC27: =AF27-AB27 -> 110 | AD27: =241-AF27 -> 79 | AE27: =AG27-AD27 -> 186 | AF27: 162 | AG27: =AH27-AF27 -> 265 | AH27: 427 | AI27: 33 | AJ27: =AM27-AI27 -> 111 | AK27: =200-AM27 -> 56 | AL27: =AN27-AK27 -> 150 | AM27: 144 | AN27: =AO27-AM27 -> 206 | AO27: 350 | AP27: -2 | AQ27: =AT27-AP27 -> 95 | AR27: 72 | AS27: =AU27-AR27 -> 172 | AT27: 93 | AU27: =AV27-AT27 -> 244 | AV27: 337 | AW27: -6 | AX27: =BA27-AW27 -> 86 | AY27: =161-BA27 -> 81 | AZ27: =BB27-AY27 -> 86 | BA27: 80 | BB27: =BC27-BA27 -> 167 | BC27: 247 | BD27: -3 | BE27: 138 | BF27: =202-BH27 -> 67 | BG27: =BI27-BF27 -> 178 | BH27: =BD27+BE27 -> 135 | BI27: =BJ27-BH27 -> 245 | BJ27: 380 | BK27: 15 | BL27: 110 | BM27: 80 | BN27: =BP27-BM27 -> 217 | BO27: =BK27+BL27 -> 125 | BP27: =BQ27-BO27 -> 297 | BQ27: 422 | BR27: 15 | BS27: 110 | BT27: 80 | BU27: =BW27-BT27 -> 217 | BV27: =BR27+BS27 -> 125 | BW27: =BX27-BV27 -> 297 | BX27: 422 | BY27: 53 | BZ27: 99 | CA27: 86 | CB27: =CD27-CA27 -> 233 | CC27: =BY27+BZ27 -> 152 | CD27: =CE27-CC27 -> 319 | CE27: 471 | CF27: 62 | CG27: =CJ27-CF27 -> 121 | CH27: 131 | CI27: =CK27-CH27 -> 221 | CJ27: 183 | CK27: =CL27-CJ27 -> 352 | CL27: 535 | CM27: 90 | CN27: 125 | CO27: 165 | CP27: =CR27-CO27 -> 259 | CQ27: =CM27+CN27 -> 215 | CR27: =CS27-CQ27 -> 424 | CS27: 639 | CT27: 156 | CU27: =CX27-CT27 -> 118 | CV27: 143 | CW27: =CY27-CV27 -> 318 | CX27: 274 | CY27: =CZ27-CX27 -> 461 | CZ27: 735 | DA27: 71 | DB27: =DE27-DA27 -> 159 | DC27: 190 | DD27: =DF27-DC27 -> 398 | DE27: 230 | DF27: =DG27-DE27 -> 588 | DG27: 818 | DH27: 78 | DI27: =DL27-DH27 -> 171 | DJ27: 246 | DK27: =DM27-DJ27 -> 430 | DL27: 249 | DM27: =DN27-DL27 -> 676 | DN27: 925 | DO27: 65 | DP27: =DS27-DO27 -> 175 | DQ27: =Helicopters!DC7 -> 260.24091 | DR27: =Helicopters!DD7 -> 463.51285 | DS27: 240 | DT27: =Helicopters!DF7 -> 723.75376 | DU27: =Helicopters!DG7 -> 963.75376 | DV27: =Helicopters!DH7 -> 179.59914 | DW27: =Helicopters!DI7 -> 233.3748 | DX27: =Helicopters!DJ7 -> 234.03693 | DY27: =Helicopters!DK7 -> 408.51238 | DZ27: =Helicopters!DL7 -> 412.97394 | EA27: =Helicopters!DM7 -> 642.5493 | ... EW27: =Helicopters!EI7 -> 1289.7011
A28: Airbus Defence & Space | N28: 84 | O28: =R28-N28 -> 132 | P28: =356-R28 -> 140 | Q28: =S28-P28 -> 555 | R28: 216 | S28: =T28-R28 -> 695 | T28: 911 | U28: 85 | V28: =Y28-U28 -> 138 | W28: =370-Y28 -> 147 | X28: =Z28-W28 -> 550 | Y28: 223 | Z28: =AA28-Y28 -> 697 | AA28: 920 | AB28: 90 | AC28: =AF28-AB28 -> 177 | AD28: =431-AF28 -> 164 | AE28: =AG28-AD28 -> 629 | AF28: 267 | AG28: =AH28-AF28 -> 793 | AH28: 1060 | AI28: 107 | AJ28: =AM28-AI28 -> 215 | AK28: =436-AM28 -> 114 | AL28: =AN28-AK28 -> 566 | AM28: 322 | AN28: =AO28-AM28 -> 680 | AO28: 1002 | AP28: 63 | AQ28: =AT28-AP28 -> 185 | AR28: 109 | AS28: =AU28-AR28 -> 515 | AT28: 248 | AU28: =AV28-AT28 -> 624 | AV28: 872 | AW28: 118 | AX28: =BA28-AW28 -> 180 | AY28: =397-BA28 -> 99 | AZ28: =BB28-AY28 -> 418 | BA28: 298 | BB28: =BC28-BA28 -> 517 | BC28: 815 | BD28: 112 | BE28: 197 | BF28: =409-BH28 -> 100 | BG28: =BI28-BF28 -> 526 | BH28: =BD28+BE28 -> 309 | BI28: =BJ28-BH28 -> 626 | BJ28: 935 | BK28: 101 | BL28: 132 | BM28: 122 | BN28: =BP28-BM28 -> 210 | BO28: =BK28+BL28 -> 233 | BP28: =BQ28-BO28 -> 332 | BQ28: 565 | BR28: 101 | BS28: 132 | BT28: 122 | BU28: =BW28-BT28 -> 210 | BV28: =BR28+BS28 -> 233 | BW28: =BX28-BV28 -> 332 | BX28: =BQ28 -> 565 | BY28: 15 | BZ28: 171 | CA28: 80 | CB28: =CD28-CA28 -> 394 | CC28: =BY28+BZ28 -> 186 | CD28: =CE28-CC28 -> 474 | CE28: 660 | CF28: 59 | CG28: =CJ28-CF28 -> 170 | CH28: 55 | CI28: =CK28-CH28 -> 412 | CJ28: 229 | CK28: =CL28-CJ28 -> 467 | CL28: 696 | CM28: 106 | CN28: 49 | CO28: 76 | CP28: =CR28-CO28 -> 153 | CQ28: =CM28+CN28 -> 155 | CR28: =CS28-CQ28 -> 229 | CS28: 384 | CT28: 36 | CU28: =CX28-CT28 -> 42 | CV28: -79 | CW28: =CY28-CV28 -> 230 | CX28: 78 | CY28: =CZ28-CX28 -> 151 | CZ28: 229 | DA28: -9 | DB28: =DE28-DA28 -> -798 | DC28: 146 | DD28: =DF28-DC28 -> 95 | DE28: -807 | DF28: =DG28-DE28 -> 241 | DG28: -566 | DH28: 77 | DI28: =DL28-DH28 -> 188 | DJ28: 155 | DK28: =DM28-DJ28 -> 378 | DL28: 265 | DM28: =DN28-DL28 -> 533 | DN28: 798 | DO28: 130 | DP28: =DS28-DO28 -> 357 | DQ28: ='Defence & Space'!CQ9 -> 211.79113 | DR28: ='Defence & Space'!CR9 -> 318.38027 | DS28: 487 | DT28: ='Defence & Space'!CT9 -> 530.1714 | DU28: ='Defence & Space'!CU9 -> 1017.1714 | DV28: ='Defence & Space'!CV9 -> 226.5777 | DW28: ='Defence & Space'!CW9 -> 278.97862 | DX28: ='Defence & Space'!CX9 -> 267.45159 | DY28: ='Defence & Space'!CY9 -> 390.11042 | DZ28: ='Defence & Space'!CZ9 -> 505.55633 | EA28: ='Defence & Space'!DA9 -> 657.56201 | ... EW28: ='Defence & Space'!DW9 -> 1490.9659
A29: Subtotal | N29: =SUM(N26:N28) -> 712 | O29: =SUM(O26:O28) -> 863 | P29: =SUM(P26:P28) -> 710 | Q29: =SUM(Q26:Q28) -> 1237 | R29: =SUM(R26:R28) -> 1575 | S29: =SUM(S26:S28) -> 1947 | T29: =T26+T28+T27 -> 3522 | U29: =SUM(U26:U28) -> 670 | V29: =SUM(V26:V28) -> 990 | W29: =SUM(W26:W28) -> 731 | X29: =SUM(X26:X28) -> 1471 | Y29: =SUM(Y26:Y28) -> 1660 | Z29: =SUM(Z26:Z28) -> 2202 | AA29: =AA26+AA28+AA27 -> 3862 | AB29: =SUM(AB26:AB28) -> 711 | AC29: =SUM(AC26:AC28) -> 1251 | AD29: =SUM(AD26:AD28) -> 936 | AE29: =SUM(AE26:AE28) -> 1369 | AF29: =SUM(AF26:AF28) -> 1962 | AG29: =SUM(AG26:AG28) -> 2305 | AH29: =AH26+AH28+AH27 -> 4267 | AI29: =SUM(AI26:AI28) -> 546 | AJ29: =SUM(AJ26:AJ28) -> 1189 | AK29: =SUM(AK26:AK28) -> 737 | AL29: =SUM(AL26:AL28) -> 1691 | AM29: =SUM(AM26:AM28) -> 1735 | AN29: =SUM(AN26:AN28) -> 2428 | AO29: =SUM(AO26:AO28) -> 4163 | AP29: =AP26+AP28+AP27 -> 342 | AQ29: =AQ26+AQ28+AQ27 -> 953 | AR29: =AR26+AR28+AR27 -> 772 | AS29: =AS26+AS28+AS27 -> 2696 | AT29: =AT26+AT28+AT27 -> 1295 | AU29: =AU26+AU28+AU27 -> 3468 | AV29: =AV26+AV28+AV27 -> 4763 | AW29: =AW26+AW28+AW27 -> 9 | ... BB29: =BB26+BB28+BB27 -> 2810 | BC29: =+BC26+BC28+BC27 -> 3445 | BD29: =BD26+BD28+BD27 -> 68 | BE29: =BE26+BE28+BE27 -> 1243 | BF29: =BF26+BF28+BF27 -> 1640 | BG29: =BG26+BG28+BG27 -> 3172 | BH29: =BH26+BH28+BH27 -> 1311 | BI29: =BI26+BI28+BI27 -> 4812 | BJ29: =BJ26+BJ28+BJ27 -> 6123 | BK29: =BK26+BK28+BK27 -> 652 | ... EW29: =EW26+EW28+EW27 -> 13574.104
A30: HQ/Eliminations & other businesses | N30: 22 | O30: =R30-N30 -> 17 | P30: =35-R30 -> -4 | Q30: =S30-P30 -> -20 | R30: 39 | S30: =T30-R30 -> -24 | T30: 15 | U30: 30 | V30: =Y30-U30 -> 79 | W30: =199-Y30 -> 90 | X30: =Z30-W30 -> 5 | Y30: 109 | Z30: =AA30-Y30 -> 95 | AA30: 204 | AB30: -60 | AC30: =AF30-AB30 -> -19 | AD30: =-94-AF30 -> -15 | AE30: =AG30-AD30 -> -41 | AF30: -79 | AG30: =AH30-AF30 -> -56 | AH30: -135 | AI30: -48 | AJ30: =AM30-AI30 -> -8 | AK30: =-64-AM30 -> -8 | AL30: =AN30-AK30 -> -144 | AM30: -56 | AN30: =AO30-AM30 -> -152 | AO30: -208 | AP30: -102 | AQ30: =AT30-AP30 -> -94 | AR30: -75 | AS30: =AU30-AR30 -> -239 | AT30: -196 | AU30: =AV30-AT30 -> -314 | AV30: -510 | AW30: -28 | AX30: =BA30-AW30 -> -54 | AY30: =-156-BA30 -> -74 | AZ30: =BB30-AY30 -> -99 | BA30: -82 | BB30: =BC30-BA30 -> -173 | BC30: -255 | BD30: -54 | BE30: -95 | BF30: =-213-BH30 -> -64 | BG30: =BI30-BF30 -> -76 | BH30: =BD30+BE30 -> -149 | BI30: =BJ30-BH30 -> -140 | BJ30: -289 | BK30: -103 | BL30: -64 | BM30: -93 | BN30: =BP30-BM30 -> -139 | BO30: =BK30+BL30 -> -167 | BP30: =BQ30-BO30 -> -232 | BQ30: -399 | BR30: =-103+73 -> -30 | BS30: =-64+72 -> 8 | BT30: =-93+95 -> 2 | BU30: =BW30-BT30 -> 32 | BV30: =BR30+BS30 -> -22 | BW30: =BX30-BV30 -> 34 | BX30: =BQ30+411 -> 12 | BY30: 22 | BZ30: 2 | CA30: -12 | CB30: =CD30-CA30 -> -55 | CC30: =BY30+BZ30 -> 24 | CD30: =CE30-CC30 -> -67 | CE30: -43 | CF30: 40 | CG30: =CJ30-CF30 -> -40 | CH30: 32 | CI30: =CK30-CH30 -> 32 | CJ30: 0 | CK30: =CL30-CJ30 -> 64 | CL30: 64 | CM30: 2 | CN30: -3 | CO30: -4 | CP30: =CR30-CO30 -> 9 | CQ30: =CM30+CN30 -> -1 | CR30: =CS30-CQ30 -> 5 | CS30: 4 | CT30: 1 | CU30: =CX30-CT30 -> 9 | CV30: -11 | CW30: =CY30-CV30 -> 57 | CX30: 10 | CY30: =CZ30-CX30 -> 46 | CZ30: 56 | DA30: 8 | DB30: =DE30-DA30 -> 6 | DC30: -3 | DD30: =DF30-DC30 -> -2 | DE30: 14 | DF30: =DG30-DE30 -> -5 | DG30: 9 | DH30: -25 | DI30: =DL30-DH30 -> 1 | DJ30: -15 | DK30: =DM30-DJ30 -> -26 | DL30: -24 | DM30: =DN30-DL30 -> -41 | DN30: -65 | DO30: 24 | DP30: =DS30-DO30 -> -11 | DQ30: =DT30/2 -> 0 | DR30: =DT30-DQ30 -> 0 | DS30: 13 | DT30: =DU30-DS30 -> 0 | DU30: 13 | DV30: =DZ30/2 -> 0 | DW30: =DZ30-DV30 -> 0 | DX30: =EA30/2 -> 0 | DY30: =EA30-DX30 -> 0 | DZ30: =EB30/2 -> 0 | EA30: =EB30-DZ30 -> 0 | EB30: 0 | EC30: =EG30/2 -> 0 | ED30: =EG30-EC30 -> 0 | EE30: =EH30/2 -> 0 | EF30: =EH30-EE30 -> 0 | EG30: =EI30/2 -> 0 | EH30: =EI30-EG30 -> 0 | EI30: =EB30 -> 0 | EJ30: =EN30/2 -> 0 | EK30: =EN30-EJ30 -> 0 | EL30: =EO30/2 -> 0 | EM30: =EO30-EL30 -> 0 | EN30: =EP30/2 -> 0 | EO30: =EP30-EN30 -> 0 | EP30: =EI30 -> 0 | EQ30: =EU30/2 -> 0 | ER30: =EU30-EQ30 -> 0 | ES30: =EV30/2 -> 0 | ET30: =EV30-ES30 -> 0 | EU30: =EW30/2 -> 0 | EV30: =EW30-EU30 -> 0 | EW30: =EP30 -> 0
A31: Group EBIT Adjusted (as reported from 2016) | B31: =B60-B39-B38-B37-B36-B35 -> 1694 | C31: =C60-C39-C38-C37-C36-C35 -> 1426 | D31: =D60-D39-D38-D37-D36-D35 -> 1543 | E31: =E60-E39-E38-E37-E36-E35 -> 2432 | F31: =F60-F39-F38-F37-F36-F35 -> 2852 | G31: =G60-G39-G38-G37-G36-G35 -> 399 | H31: =H60-H39-H38-H37-H36-H35 -> 4070 | I31: =I60-I39-I38-I37-I36-I35 -> 3330 | ... M31: =M60-M39-M38-M37-M36-M35 -> 3006 | N31: =N29+N30 -> 734 | O31: =O29+O30 -> 880 | P31: =P29+P30 -> 706 | Q31: =Q29+Q30 -> 1217 | R31: =R29+R30 -> 1614 | S31: =S29+S30 -> 1923 | T31: =T60-T39-T38-T37-T36-T35 -> 3537 | U31: =U29+U30 -> 700 | V31: =V29+V30 -> 1069 | W31: =W29+W30 -> 821 | X31: =X29+X30 -> 1476 | Y31: =Y29+Y30 -> 1769 | Z31: =Z29+Z30 -> 2297 | AA31: =AA60-AA39-AA38-AA37-AA36-AA35 -> 4066 | AB31: =AB29+AB30 -> 651 | AC31: =AC29+AC30 -> 1232 | AD31: =AD29+AD30 -> 921 | AE31: =AE29+AE30 -> 1328 | AF31: =AF29+AF30 -> 1883 | AG31: =AG29+AG30 -> 2249 | AH31: =AH29+AH30 -> 4132 | AI31: =AI29+AI30 -> 498 | ... BB31: =BB29+BB30 -> 2637 | BC31: =+BC29+BC30 -> 3190 | BD31: =BD29+BD30 -> 14 | BE31: =BE29+BE30 -> 1148 | BF31: =BF29+BF30 -> 1576 | BG31: =BG29+BG30 -> 3096 | BH31: =BH29+BH30 -> 1162 | BI31: =BI29+BI30 -> 4672 | BJ31: =BJ29+BJ30 -> 5834 | BK31: =BK29+BK30 -> 549 | ... EW31: =EW29+EW30 -> 13574.104
A32: Margin % | B32: =B31/B13 -> 0.055003572 | C32: =C31/C13 -> 0.047690713 | D32: =D31/D13 -> 0.051206319 | E32: =E31/E13 -> 0.076571896 | F32: =F31/F13 -> 0.083377185 | G32: =G31/G13 -> 0.010118172 | H32: =H31/H13 -> 0.10403088 | I32: =I31/I13 -> 0.076967526 | ... EW32: =EW31/EW13 -> 0.1286229
A34: One-offs by nature
A35: A400M provisions | H35: -1366 | I35: -800 | J35: -1820 | K35: 0 | L35: 0 | U35: 0 | V35: =Y35-U35 -> 0 | W35: =0-U35-V35 -> 0 | X35: =Z35-W35 -> -551 | Y35: 0 | Z35: =AA35-Y35 -> -551 | AA35: -551 | AB35: 0 | AC35: =AF35-AB35 -> -290 | AD35: =-290-AB35-AC35 -> 0 | AE35: =AG35-AD35 -> 0 | AF35: -290 | AG35: =AH35-AF35 -> 0 | AH35: -290 | AI35: 0 | AJ35: =AM35-AI35 -> -1026 | AK35: =-1026-AI35-AJ35 -> 0 | AL35: =AN35-AK35 -> -1184 | AM35: -1026 | AN35: =AO35-AM35 -> -1184 | AO35: -2210 | AP35: 0 | AQ35: =AT35-AP35 -> -70 | AR35: =-150-AP35-AQ35 -> -80 | AS35: =AU35-AR35 -> -1149 | AT35: -70 | AU35: =AV35-AT35 -> -1229 | AV35: -1299 | BD35: 0 | BE35: =BH35-BD35 -> -98 | BF35: =-105-BD35-BE35 -> -7 | BG35: =BI35-BF35 -> -331 | BH35: -98 | BI35: =BJ35-BH35 -> -338 | BJ35: -436 | BK35: 0 | BL35: =BO35-BK35 -> 0 | BM35: 0 | BN35: =BP35-BM35 -> -1212 | BO35: 0 | BP35: =BQ35-BO35 -> -1212 | BQ35: -1212 | BR35: 0 | BS35: =BV35-BR35 -> 0 | BT35: 0 | BU35: =BW35-BT35 -> -1212 | BV35: 0 | BW35: =BX35-BV35 -> -1212 | BX35: -1212 | BY35: 0 | BZ35: =CC35-BY35 -> 0 | CA35: 0 | CB35: =CD35-CA35 -> 0 | CC35: 0 | CD35: =CE35-CC35 -> 0 | CF35: 0 | CG35: =CJ35-CF35 -> 0 | CH35: 0 | CI35: =CK35-CH35 -> -212 | CJ35: 0 | CK35: =CL35-CJ35 -> -212 | CL35: -212 | CM35: 0 | CN35: =CQ35-CM35 -> -218 | CO35: =-219-CM35-CN35 -> -1 | CP35: =CR35-CO35 -> -258 | CQ35: -218 | CR35: =CS35-CQ35 -> -259 | CS35: -477 | CT35: 0 | CU35: =CX35-CT35 -> 0 | CV35: 0 | CW35: =CY35-CV35 -> -41 | CX35: 0 | CY35: =CZ35-CX35 -> -41 | CZ35: -41 | DA35: 0 | DB35: =DE35-DA35 -> 0 | DC35: 0 | DD35: =DF35-DC35 -> -121 | DE35: 0 | DF35: =DG35-DE35 -> -121 | DG35: -121 | DH35: 0 | DI35: =DL35-DH35 -> 0 | DJ35: 0 | DK35: =DM35-DJ35 -> -73 | DL35: 0 | DM35: =DN35-DL35 -> -73 | DN35: -73 | DO35: 0 | DP35: =DS35-DO35 -> 0 | DQ35: =DT35/2 -> 0 | DR35: =DT35-DQ35 -> 0 | DT35: =DU35-DS35 -> 0 | DU35: 0 | DV35: =DZ35/2 -> 0 | DW35: =DZ35-DV35 -> 0 | DX35: =EA35/2 -> 0 | DY35: =EA35-DX35 -> 0 | DZ35: =EB35/2 -> 0 | EA35: =EB35-DZ35 -> 0 | EB35: 0 | EC35: =EG35/2 -> 0 | ED35: =EG35-EC35 -> 0 | EE35: =EH35/2 -> 0 | EF35: =EH35-EE35 -> 0 | EG35: =EI35/2 -> 0 | EH35: =EI35-EG35 -> 0 | EI35: 0 | EJ35: =EN35/2 -> 0 | EK35: =EN35-EJ35 -> 0 | EL35: =EO35/2 -> 0 | EM35: =EO35-EL35 -> 0 | EN35: =EP35/2 -> 0 | EO35: =EP35-EN35 -> 0 | EP35: 0 | EQ35: =EU35/2 -> 0 | ER35: =EU35-EQ35 -> 0 | ES35: =EV35/2 -> 0 | ET35: =EV35-ES35 -> 0 | EU35: =EW35/2 -> 0 | EV35: =EW35-EU35 -> 0 | EW35: 0
A36: A380 provisions | H36: -1028 | I36: -1000 | J36: -240 | K36: 0 | L36: 0 | M36: -251 | T36: -85 | BD36: 0 | BE36: =BH36-BD36 -> 0 | BF36: =0-BD36-BE36 -> 0 | BG36: =BI36-BF36 -> -463 | BH36: 0 | BI36: =BJ36-BH36 -> -463 | BJ36: -463 | BK36: -61 | BL36: =BO36-BK36 -> -75 | BM36: =-158-BK36-BL36 -> -22 | BN36: =BP36-BM36 -> -44 | BO36: -136 | BP36: =BQ36-BO36 -> -66 | BQ36: -202 | BR36: -61 | BS36: =BV36-BR36 -> -75 | BT36: =-158-BR36-BS36 -> -22 | BU36: =BW36-BT36 -> -44 | BV36: -136 | BW36: =BX36-BV36 -> -66 | BX36: -202 | BY36: -33 | BZ36: =CC36-BY36 -> -299 | CA36: =-358-BY36-BZ36 -> -26 | CB36: =CD36-CA36 -> -27 | CC36: -332 | CD36: =CE36-CC36 -> -53 | CE36: -385 | CF36: -29 | CG36: =CJ36-CF36 -> 174 | CH36: =190-CF36-CG36 -> 45 | CI36: =CK36-CH36 -> 84 | CJ36: 145 | CK36: =CL36-CJ36 -> 129 | CL36: 274 | CM36: -11 | CN36: =CQ36-CM36 -> 4 | CO36: =33-CM36-CN36 -> 40 | CP36: =CR36-CO36 -> -5 | CQ36: -7 | CR36: =CS36-CQ36 -> 35 | CS36: 28 | CT36: 0 | CU36: =CX36-CT36 -> 0 | CV36: 0 | CW36: =CY36-CV36 -> 0 | CX36: 0 | CY36: =CZ36-CX36 -> 0 | CZ36: 0 | DA36: 0 | DB36: =DE36-DA36 -> 0 | DC36: 0 | DD36: =DF36-DC36 -> 0 | DE36: 0 | DF36: =DG36-DE36 -> 0 | DG36: 0 | DH36: 0 | DI36: =DL36-DH36 -> 0 | DJ36: 0 | DK36: =DM36-DJ36 -> 0 | DL36: 0 | DM36: =DN36-DL36 -> 0 | DN36: 0 | DO36: 0 | DP36: =DS36-DO36 -> 0 | DQ36: =DT36/2 -> 0 | DR36: =DT36-DQ36 -> 0 | DT36: =DU36-DS36 -> 0 | DU36: 0 | DV36: =DZ36/2 -> 0 | DW36: =DZ36-DV36 -> 0 | DX36: =EA36/2 -> 0 | DY36: =EA36-DX36 -> 0 | DZ36: =EB36/2 -> 0 | EA36: =EB36-DZ36 -> 0 | EB36: 0 | EC36: =EG36/2 -> 0 | ED36: =EG36-EC36 -> 0 | EE36: =EH36/2 -> 0 | EF36: =EH36-EE36 -> 0 | EG36: =EI36/2 -> 0 | EH36: =EI36-EG36 -> 0 | EI36: 0 | EJ36: =EN36/2 -> 0 | EK36: =EN36-EJ36 -> 0 | EL36: =EO36/2 -> 0 | EM36: =EO36-EL36 -> 0 | EN36: =EP36/2 -> 0 | EO36: =EP36-EN36 -> 0 | EP36: 0 | EQ36: =EU36/2 -> 0 | ER36: =EU36-EQ36 -> 0 | ES36: =EV36/2 -> 0 | ET36: =EV36-ES36 -> 0 | EU36: =EW36/2 -> 0 | EV36: =EW36-EU36 -> 0 | EW36: 0
A37: A350XWB provisions | H37: -1000 | I37: 0 | J37: 0 | K37: 0 | L37: -200 | M37: -124 | T37: -434 | AA37: =Airbus!AB53 -> 0 | AJ37: =AM37-AI37 -> -385 | AK37: =-385-AI37-AJ37 -> 0 | AL37: =AN37-AK37 -> 0 | AM37: -385 | AN37: =AO37-AM37 -> 0 | AO37: -385 | CT37: 0 | CU37: =CX37-CT37 -> 0 | CV37: 0 | CW37: =CY37-CV37 -> 0 | CX37: 0 | CY37: =CZ37-CX37 -> 0 | CZ37: 0 | DA37: 0 | DB37: =DE37-DA37 -> 0 | DC37: 0 | DD37: =DF37-DC37 -> 0 | DE37: 0 | DF37: =DG37-DE37 -> 0 | DG37: 0 | DH37: 0 | DI37: =DL37-DH37 -> 0 | DJ37: 0 | DK37: =DM37-DJ37 -> 0 | DL37: 0 | DM37: =DN37-DL37 -> 0 | DN37: 0 | DO37: 0 | DP37: =DS37-DO37 -> 0 | DQ37: =DT37/2 -> 0 | DR37: =DT37-DQ37 -> 0 | DT37: =DU37-DS37 -> 0 | DU37: 0 | DV37: =DZ37/2 -> 0 | DW37: =DZ37-DV37 -> 0 | DX37: =EA37/2 -> 0 | DY37: =EA37-DX37 -> 0 | DZ37: =EB37/2 -> 0 | EA37: =EB37-DZ37 -> 0 | EB37: 0 | EC37: =EG37/2 -> 0 | ED37: =EG37-EC37 -> 0 | EE37: =EH37/2 -> 0 | EF37: =EH37-EE37 -> 0 | EG37: =EI37/2 -> 0 | EH37: =EI37-EG37 -> 0 | EI37: 0 | EJ37: =EN37/2 -> 0 | EK37: =EN37-EJ37 -> 0 | EL37: =EO37/2 -> 0 | EM37: =EO37-EL37 -> 0 | EN37: =EP37/2 -> 0 | EO37: =EP37-EN37 -> 0 | EP37: 0 | EQ37: =EU37/2 -> 0 | ER37: =EU37-EQ37 -> 0 | ES37: =EV37/2 -> 0 | ET37: =EV37-ES37 -> 0 | EU37: =EW37/2 -> 0 | EV37: =EW37-EU37 -> 0 | EW37: 0
A38: Mark to market on LMC | H38: 0 | I38: 850 | J38: -490 | K38: -20 | L38: 70 | M38: -71 | T38: -102 | U38: 19 | V38: =Y38-U38 -> 51 | W38: =-7-U38-V38 -> -77 | X38: =Z38-W38 -> 149 | Y38: 70 | Z38: =AA38-Y38 -> 72 | AA38: 142 | AB38: -150 | AC38: =AF38-AB38 -> 5 | AD38: =-360-AB38-AC38 -> -215 | AE38: =AG38-AD38 -> -275 | AF38: -145 | AG38: =AH38-AF38 -> -490 | AH38: -635 | CT38: 0 | CU38: =CX38-CT38 -> 0 | CV38: 0 | CW38: =CY38-CV38 -> 0 | CX38: 0 | CY38: =CZ38-CX38 -> 0 | CZ38: 0 | DA38: 0 | DB38: =DE38-DA38 -> 0 | DC38: 0 | DD38: =DF38-DC38 -> 0 | DE38: 0 | DF38: =DG38-DE38 -> 0 | DG38: 0 | DH38: 0 | DI38: =DL38-DH38 -> 0 | DJ38: 0 | DK38: =DM38-DJ38 -> 0 | DL38: 0 | DM38: =DN38-DL38 -> 0 | DN38: 0 | DO38: 0 | DP38: =DS38-DO38 -> 0 | DQ38: =DT38/2 -> 0 | DR38: =DT38-DQ38 -> 0 | DT38: =DU38-DS38 -> 0 | DU38: 0 | DV38: =DZ38/2 -> 0 | DW38: =DZ38-DV38 -> 0 | DX38: =EA38/2 -> 0 | DY38: =EA38-DX38 -> 0 | DZ38: =EB38/2 -> 0 | EA38: =EB38-DZ38 -> 0 | EB38: 0 | EC38: =EG38/2 -> 0 | ED38: =EG38-EC38 -> 0 | EE38: =EH38/2 -> 0 | EF38: =EH38-EE38 -> 0 | EG38: =EI38/2 -> 0 | EH38: =EI38-EG38 -> 0 | EI38: 0 | EJ38: =EN38/2 -> 0 | EK38: =EN38-EJ38 -> 0 | EL38: =EO38/2 -> 0 | EM38: =EO38-EL38 -> 0 | EN38: =EP38/2 -> 0 | EO38: =EP38-EN38 -> 0 | EP38: 0 | EQ38: =EU38/2 -> 0 | ER38: =EU38-EQ38 -> 0 | ES38: =EV38/2 -> 0 | ET38: =EV38-ES38 -> 0 | EU38: =EW38/2 -> 0 | EV38: =EW38-EU38 -> 0 | EW38: 0
A39: Other one-offs inc. restructuring charges | H39: -624 | I39: 450 | J39: 80 | K39: -90 | L39: 40 | M39: =-76-100-98-100 -> -374 | T39: -292 | U39: 0 | V39: =Y39-U39 -> 0 | W39: =0-U39-V39 -> 0 | X39: =Z39-W39 -> 383 | Y39: 0 | Z39: =AA39-Y39 -> 383 | AA39: 383 | AB39: =697+43 -> 740 | AC39: =AF39-AB39 -> 41 | AD39: =748+44-AB39-AC39 -> 11 | AE39: =AG39-AD39 -> 87 | AF39: =748+33 -> 781 | AG39: =AH39-AF39 -> 98 | AH39: =90+41+748 -> 879 | AI39: -136 | AJ39: =AM39-AI39 -> 1719 | AK39: =-723+75+1139+868-AI39-AJ39 -> -224 | AL39: =AN39-AK39 -> -461 | AM39: =-509+1139+868+85 -> 1583 | AN39: =AO39-AM39 -> -685 | AO39: =-930-182-33+1175+868 -> 898 | AP39: =560+55-3 -> 612 | AQ39: =AT39-AP39 -> 150 | AR39: =43+604+19-AP39-AQ39 -> -96 | AS39: =AU39-AR39 -> -199 | AT39: =174+560+28 -> 762 | AU39: =AV39-AT39 -> -295 | AV39: =-117-7+7-20+604 -> 467 | BD39: =159+46-20 -> 185 | BE39: =BH39-BD39 -> -129 | BF39: =-23-109+26+156-BD39-BE39 -> -6 | BG39: =BI39-BF39 -> 63 | BH39: =-21-40-40+157 -> 56 | BI39: =BJ39-BH39 -> 57 | BJ39: =-123+188+129-81 -> 113 | BK39: =-190-83-34 -> -307 | BL39: =BO39-BK39 -> 7 | BM39: =-253-221-70-BK39-BL39 -> -244 | BN39: =BP39-BM39 -> -3649 | BO39: =-208-90-2 -> -300 | BP39: =BQ39-BO39 -> -3893 | BQ39: =-3598-221-170-103-101 -> -4193 | BR39: =-190-83-34 -> -307 | BS39: =BV39-BR39 -> 7 | BT39: =-253-221-70-BR39-BS39 -> -244 | BU39: =BW39-BT39 -> -3649 | BV39: =-208-90-2 -> -300 | BW39: =BX39-BV39 -> -3893 | BX39: =-3598-221-170-103-101 -> -4193 | BY39: =-134-35 -> -169 | BZ39: =CC39-BY39 -> -113 | CA39: =-1200-374-128-BY39-BZ39 -> -1420 | CB39: =CD39-CA39 -> -129 | CC39: =-165-117 -> -282 | CD39: =CE39-CC39 -> -1549 | CE39: =-1202-480-149 -> -1831 | CF39: =-177-26 -> -203 | CG39: =CJ39-CF39 -> 82 | CH39: =-165+43-CF39-CG39 -> -1 | CI39: =CK39-CH39 -> 537 | CJ39: =-170+49 -> -121 | CK39: =CL39-CJ39 -> 536 | CL39: =122-38+331 -> 415 | CM39: =190-13 -> 177 | CN39: =CQ39-CM39 -> -18 | CO39: =349-48-44-CM39-CN39 -> 98 | CP39: =CR39-CO39 -> -110 | CQ39: =226-33-34 -> 159 | CR39: =CS39-CQ39 -> -12 | CS39: =308-82-79 -> 147 | CT39: =-360-9-14 -> -383 | CU39: =CX39-CT39 -> -348 | CV39: =-806-57-56-CT39-CU39 -> -188 | CW39: =CY39-CV39 -> -275 | CX39: =-651-34-46 -> -731 | CY39: =CZ39-CX39 -> -463 | CZ39: =-1030-89-75 -> -1194 | DA39: =-13+51-6 -> 32 | DB39: =DE39-DA39 -> 33 | DC39: =-146+51-13-DA39-DB39 -> -173 | DD39: =DF39-DC39 -> 179 | DE39: =19+51-5 -> 65 | DF39: =DG39-DE39 -> 6 | DG39: =101+51-40-41 -> 71 | DH39: =-13-105-33 -> -151 | DI39: =DL39-DH39 -> -436 | DJ39: =-577-105-88-11-DI39-DH39 -> -194 | DK39: =DM39-DJ39 -> -192 | DL39: =-391-105-57-34 -> -587 | DM39: =DN39-DL39 -> -386 | DN39: =-(624+188+105+56) -> -973 | DO39: -76 | DP39: =DS39-DO39 -> 94 | DQ39: -50 | DR39: =DT39-DQ39 -> -100 | DS39: =124-123+60-43 -> 18 | DT39: =DU39-DS39 -> -150 | DU39: -132 | DV39: =DZ39/2 -> 0 | DW39: =DZ39-DV39 -> 0 | DX39: =EA39/2 -> 0 | DY39: =EA39-DX39 -> 0 | DZ39: =EB39/2 -> 0 | EA39: =EB39-DZ39 -> 0 | EB39: 0 | EC39: =EG39/2 -> 0 | ED39: =EG39-EC39 -> 0 | EE39: =EH39/2 -> 0 | EF39: =EH39-EE39 -> 0 | EG39: =EI39/2 -> 0 | EH39: =EI39-EG39 -> 0 | EI39: 0 | EJ39: =EN39/2 -> 0 | EK39: =EN39-EJ39 -> 0 | EL39: =EO39/2 -> 0 | EM39: =EO39-EL39 -> 0 | EN39: =EP39/2 -> 0 | EO39: =EP39-EN39 -> 0 | EP39: 0 | EQ39: =EU39/2 -> 0 | ER39: =EU39-EQ39 -> 0 | ES39: =EV39/2 -> 0 | ET39: =EV39-ES39 -> 0 | EU39: =EW39/2 -> 0 | EV39: =EW39-EU39 -> 0 | EW39: 0
A40: Total | M40: =SUM(M36:M39) -> -820 | T40: =SUM(T35:T39) -> -913 | U40: =SUM(U35:U39) -> 19 | V40: =SUM(V35:V39) -> 51 | W40: =SUM(W35:W39) -> -77 | X40: =SUM(X35:X39) -> -19 | Y40: =SUM(Y35:Y39) -> 70 | Z40: =SUM(Z35:Z39) -> -96 | AA40: =SUM(AA35:AA39) -> -26 | ... AV40: =SUM(AV35:AV39) -> -832 | BD40: =SUM(BD35:BD39) -> 185 | BE40: =SUM(BE35:BE39) -> -227 | BF40: =SUM(BF35:BF39) -> -13 | BG40: =SUM(BG35:BG39) -> -731 | BH40: =SUM(BH35:BH39) -> -42 | BI40: =SUM(BI35:BI39) -> -744 | BJ40: =SUM(BJ35:BJ39) -> -786 | BK40: =SUM(BK35:BK39) -> -368 | ... DQ40: =SUM(DQ35:DQ39) -> -50 | DR40: =DT40-DQ40 -> -100 | DS40: =SUM(DS35:DS39) -> 18 | DT40: =DU40-DS40 -> -150 | DU40: =SUM(DU35:DU39) -> -132 | DV40: =SUM(DV35:DV39) -> 0 | DW40: =DZ40-DV40 -> 0 | DX40: =SUM(DX35:DX39) -> 0 | DY40: =EA40-DX40 -> 0 | DZ40: =SUM(DZ35:DZ39) -> 0 | EA40: =EB40-DZ40 -> 0 | EB40: =SUM(EB35:EB39) -> 0 | EC40: =SUM(EC35:EC39) -> 0 | ED40: =EG40-EC40 -> 0 | EE40: =SUM(EE35:EE39) -> 0 | EF40: =EH40-EE40 -> 0 | EG40: =SUM(EG35:EG39) -> 0 | EH40: =EI40-EG40 -> 0 | EI40: =SUM(EI35:EI39) -> 0 | EJ40: =SUM(EJ35:EJ39) -> 0 | EK40: =EN40-EJ40 -> 0 | EL40: =SUM(EL35:EL39) -> 0 | EM40: =EO40-EL40 -> 0 | EN40: =SUM(EN35:EN39) -> 0 | EO40: =EP40-EN40 -> 0 | EP40: =SUM(EP35:EP39) -> 0 | EQ40: =SUM(EQ35:EQ39) -> 0 | ER40: =EU40-EQ40 -> 0 | ES40: =SUM(ES35:ES39) -> 0 | ET40: =EV40-ES40 -> 0 | EU40: =SUM(EU35:EU39) -> 0 | EV40: =EW40-EU40 -> 0 | EW40: =SUM(EW35:EW39) -> 0
A42: One-offs by division
A43: Airbus | N43: =N51-N26 -> -145 | O43: =O51-O26 -> 9 | P43: =P51-P26 -> -53 | Q43: =Q51-Q26 -> -432 | R43: =R51-R26 -> -136 | S43: =S51-S26 -> -485 | T43: =T51-T26 -> -621 | U43: =U51-U26 -> 19 | ... EW43: =EW51-EW26 -> 0
A44: Airbus Helicopters | N44: =N52-N27 -> 0 | O44: =O52-O27 -> 0 | P44: =P52-P27 -> 0 | Q44: =Q52-Q27 -> 0 | R44: =R52-R27 -> 0 | S44: =S52-S27 -> 0 | T44: =T52-T27 -> 0 | U44: =U52-U27 -> 0 | ... EW44: =EW52-EW27 -> 0
A45: Airbus Defence & Space | N45: =N53-N28 -> 0 | O45: =O53-O28 -> 0 | P45: =P53-P28 -> 0 | Q45: =Q53-Q28 -> -252 | R45: =R53-R28 -> 0 | S45: =S53-S28 -> -252 | T45: =T53-T28 -> -252 | U45: =U53-U28 -> 0 | ... EW45: =EW53-EW28 -> 0
A46: Subtotal | N46: =N43+N45+N44 -> -145 | O46: =O43+O45+O44 -> 9 | P46: =P43+P45+P44 -> -53 | Q46: =Q43+Q45+Q44 -> -684 | R46: =R43+R45+R44 -> -136 | S46: =S43+S45+S44 -> -737 | T46: =T43+T45+T44 -> -873 | U46: =U43+U45+U44 -> 19 | ... EW46: =EW43+EW45+EW44 -> 0
A47: HQ/Eliminations & other businesses | N47: =N59-N30 -> 0 | O47: =R47-N47 -> 0 | P47: =P59-P30 -> 0 | Q47: =S47-P47 -> -40 | R47: =R59-R30 -> 0 | S47: =T47-R47 -> -40 | T47: =T59-T30 -> -40 | U47: =U59-U30 -> 0 | V47: =Y47-U47 -> 0 | W47: =W59-W30 -> 0 | X47: =Z47-W47 -> 343 | Y47: =Y59-Y30 -> 0 | Z47: =AA47-Y47 -> 343 | AA47: =AA59-AA30 -> 343 | AB47: =AB59-AB30 -> 697 | AC47: =AF47-AB47 -> 51 | AD47: =AD59-AD30 -> 0 | AE47: =AG47-AD47 -> 0 | AF47: =AF59-AF30 -> 748 | AG47: =AH47-AF47 -> 0 | AH47: =AH59-AH30 -> 748 | AI47: =AI59-AI30 -> 0 | AJ47: =AM47-AI47 -> 868 | AK47: =AK59-AK30 -> 0 | AL47: =AN47-AK47 -> -160 | AM47: =AM59-AM30 -> 868 | AN47: =AO47-AM47 -> -160 | AO47: =AO59-AO30 -> 708 | AP47: =AP59-AP30 -> 0 | AQ47: =AT47-AP47 -> 0 | AR47: =AR59-AR30 -> 0 | AS47: =AU47-AR47 -> -46 | AT47: =AT59-AT30 -> 0 | AU47: =AV47-AT47 -> -46 | AV47: =AV59-AV30 -> -46 | AW47: =AW59-AW30 -> 0 | AX47: =BA47-AW47 -> 0 | AY47: =AY59-AY30 -> 0 | AZ47: =BB47-AY47 -> -46 | BA47: =BA59-BA30 -> 0 | BB47: =BC47-BA47 -> -46 | BC47: =BC59-BC30 -> -46 | BD47: =BD59-BD30 -> 0 | BE47: =BH47-BD47 -> 0 | BF47: =BF59-BF30 -> 0 | BG47: =BI47-BF47 -> 0 | BH47: =BH59-BH30 -> 0 | BI47: =BJ47-BH47 -> 0 | BJ47: =BJ59-BJ30 -> 0 | BK47: =BK59-BK30 -> 0 | BL47: =BO47-BK47 -> 0 | BM47: =BM59-BM30 -> 0 | BN47: =BP47-BM47 -> 0 | BO47: =BO59-BO30 -> 0 | BP47: =BQ47-BO47 -> 0 | BQ47: =BQ59-BQ30 -> 0 | BR47: =BR59-BR30 -> 0 | BS47: =BV47-BR47 -> 0 | BT47: =BT59-BT30 -> 0 | BU47: =BW47-BT47 -> 0 | BV47: =BV59-BV30 -> 0 | BW47: =BX47-BV47 -> 0 | BX47: =BX59-BX30 -> 0 | BY47: =BY59-BY30 -> 0 | BZ47: =CC47-BY47 -> 0 | CA47: =CA59-CA30 -> 0 | CB47: =CD47-CA47 -> 0 | CC47: =CC59-CC30 -> 0 | CD47: =CE47-CC47 -> 0 | CE47: 0 | CF47: =CF59-CF30 -> 0 | CG47: =CJ47-CF47 -> 0 | CH47: =CH59-CH30 -> 0 | CI47: =CK47-CH47 -> 0 | CJ47: =CJ59-CJ30 -> 0 | CK47: =CL47-CJ47 -> 0 | CL47: 0 | CM47: =CM59-CM30 -> 0 | CN47: =CQ47-CM47 -> 0 | CO47: =CO59-CO30 -> 0 | CP47: =CR47-CO47 -> 0 | CQ47: =CQ59-CQ30 -> 0 | CR47: =CS47-CQ47 -> 0 | CS47: 0 | CT47: =CT59-CT30 -> 0 | CU47: =CX47-CT47 -> 0 | CV47: =CV59-CV30 -> 0 | CW47: =CY47-CV47 -> 0 | CX47: =CX59-CX30 -> 0 | CY47: =CZ47-CX47 -> 0 | CZ47: 0 | DA47: =DA59-DA30 -> 0 | DB47: =DE47-DA47 -> 0 | DC47: =DC59-DC30 -> 0 | DD47: =DF47-DC47 -> 0 | DE47: =DE59-DE30 -> 0 | DF47: =DG47-DE47 -> 0 | DG47: 0 | DH47: 0 | DI47: =DL47-DH47 -> 0 | DJ47: =DJ59-DJ30 -> 0 | DK47: =DM47-DJ47 -> 0 | DL47: =DL59-DL30 -> 0 | DM47: =DN47-DL47 -> 0 | DN47: 0 | DO47: 0 | DP47: =DS47-DO47 -> 0 | DQ47: =DT47/2 -> 0 | DR47: =DT47-DQ47 -> 0 | DS47: =DS59-DS30 -> 0 | DT47: =DU47-DS47 -> 0 | DU47: 0 | DV47: =DZ47/2 -> 0 | DW47: =DZ47-DV47 -> 0 | DX47: =EA47/2 -> 0 | DY47: =EA47-DX47 -> 0 | DZ47: =EB47/2 -> 0 | EA47: =EB47-DZ47 -> 0 | EB47: 0 | EC47: =EG47/2 -> 0 | ED47: =EG47-EC47 -> 0 | EE47: =EH47/2 -> 0 | EF47: =EH47-EE47 -> 0 | EG47: =EI47/2 -> 0 | EH47: =EI47-EG47 -> 0 | EI47: 0 | EJ47: =EN47/2 -> 0 | EK47: =EN47-EJ47 -> 0 | EL47: =EO47/2 -> 0 | EM47: =EO47-EL47 -> 0 | EN47: =EP47/2 -> 0 | EO47: =EP47-EN47 -> 0 | EP47: 0 | EQ47: =EU47/2 -> 0 | ER47: =EU47-EQ47 -> 0 | ES47: =EV47/2 -> 0 | ET47: =EV47-ES47 -> 0 | EU47: =EW47/2 -> 0 | EV47: =EW47-EU47 -> 0 | EW47: 0
A48: Total | N48: =N46+N47 -> -145 | O48: =O46+O47 -> 9 | P48: =P46+P47 -> -53 | Q48: =Q46+Q47 -> -724 | R48: =R46+R47 -> -136 | S48: =S46+S47 -> -777 | T48: =T46+T47 -> -913 | U48: =U46+U47 -> 19 | ... EW48: =EW46+EW47 -> 0
A50: EBIT reported
A51: =A4 -> Airbus | B51: 1655 | C51: 1361 | D51: =1353 -> 1353 | E51: 1919 | F51: 2307 | G51: -572 | H51: -881 | I51: 2306 | J51: 386 | K51: 291 | L51: 543 | M51: 1125 | N51: 463 | O51: =R51-N51 -> 632 | P51: =1523-R51 -> 428 | Q51: =S51-P51 -> 70 | R51: 1095 | S51: =T51-R51 -> 498 | T51: 1593 | U51: 546 | V51: =Y51-U51 -> 811 | W51: =1773-Y51 -> 416 | X51: =Z51-W51 -> 898 | Y51: 1357 | Z51: =AA51-Y51 -> 1314 | AA51: 2671 | AB51: 419 | AC51: =AF51-AB51 -> 1005 | AD51: =1902-AF51 -> 478 | AE51: =AG51-AD51 -> 399 | AF51: 1424 | AG51: =AH51-AF51 -> 877 | AH51: 2301 | AI51: 289 | AJ51: =AM51-AI51 -> 131 | AK51: =773-AM51 -> 353 | AL51: =AN51-AK51 -> 770 | AM51: 420 | AN51: =AO51-AM51 -> 1123 | AO51: 1543 | AP51: 336 | AQ51: =AT51-AP51 -> 742 | AR51: 440 | AS51: =AU51-AR51 -> 1910 | AT51: 1078 | AU51: =AV51-AT51 -> 2350 | AV51: 3428 | AW51: -48 | AX51: =BA51-AW51 -> 429 | AY51: =779-BA51 -> 398 | AZ51: =BB51-AY51 -> 1478 | BA51: 381 | BB51: =BC51-BA51 -> 1876 | BC51: 2257 | BD51: -2 | BE51: 775 | BF51: =2238-BH51 -> 1465 | BG51: =BI51-BF51 -> 2057 | BH51: =BD51+BE51 -> 773 | BI51: =BJ51-BH51 -> 3522 | BJ51: 4295 | BK51: 392 | BL51: =BO51-BK51 -> 1759 | BM51: =3405-BO51 -> 1254 | BN51: =BP51-BM51 -> -1200 | BO51: 2151 | BP51: =BQ51-BO51 -> 54 | BQ51: 2205 | BR51: =392-73 -> 319 | BS51: =BV51-BR51 -> 1687 | BT51: =3405-240-BV51 -> 1159 | BU51: =BW51-BT51 -> -1371 | BV51: =2151-145 -> 2006 | BW51: =BX51-BV51 -> -212 | BX51: =BQ51-411 -> 1794 | BY51: 57 | BZ51: =CC51-BY51 -> -1865 | CA51: -591 | CB51: =CD51-CA51 -> 1069 | CC51: -1808 | CD51: =CE51-CC51 -> 478 | CE51: -1330 | CF51: 343 | CG51: =CJ51-CF51 -> 2044 | CH51: 502 | CI51: =CK51-CH51 -> 1286 | CJ51: 2387 | CK51: =CL51-CJ51 -> 1788 | CL51: 4175 | CM51: 1242 | CN51: 1236 | CO51: 763 | CP51: =CR51-CO51 -> 1559 | CQ51: =+CM51+CN51 -> 2478 | CR51: =CS51-CQ51 -> 2322 | CS51: 4800 | CT51: 197 | CU51: =CX51-CT51 -> 1326 | CV51: 783 | CW51: =CY51-CV51 -> 1304 | CX51: 1523 | CY51: =CZ51-CX51 -> 2087 | CZ51: 3610 | DA51: 500 | DB51: =DE51-DA51 -> 1472 | DC51: 904 | DD51: =DF51-DC51 -> 2257 | DE51: 1972 | DF51: =DG51-DE51 -> 3161 | DG51: 5133 | DH51: 451 | DI51: =DL51-DH51 -> 780 | DJ51: 1325 | DK51: =DM51-DJ51 -> 1999 | DL51: 1231 | DM51: =DN51-DL51 -> 3324 | DN51: 4555 | DO51: 1 | DP51: =DS51-DO51 -> 1949 | DQ51: =Airbus!DK58 -> 1537.1268 | DR51: =Airbus!DL58 -> 2243.5513 | DS51: 1950 | DT51: =Airbus!DN58 -> 3780.678 | DU51: =Airbus!DO58 -> 5730.678 | DV51: =Airbus!DP58 -> 1717.4956 | DW51: =Airbus!DQ58 -> 1876.7178 | DX51: =Airbus!DR58 -> 1879.2567 | DY51: =Airbus!DS58 -> 1839.2901 | DZ51: =Airbus!DT58 -> 3594.2134 | EA51: =Airbus!DU58 -> 3718.5467 | ... EW51: =Airbus!EQ58 -> 10793.437
A52: Airbus Helicopters | B52: =308*0.7 -> 215.6 | C52: =180*0.7 -> 126 | D52: =217*0.7 -> 151.9 | E52: 201 | F52: 212 | G52: 257 | H52: 211 | I52: 293 | J52: 263 | K52: 183 | L52: 259 | M52: 311 | N52: 20 | O52: =R52-N52 -> 108 | P52: =217-R52 -> 89 | Q52: =S52-P52 -> 180 | R52: 128 | S52: =T52-R52 -> 269 | T52: 397 | U52: 58 | V52: =Y52-U52 -> 92 | W52: =241-Y52 -> 91 | X52: =Z52-W52 -> 172 | Y52: 150 | Z52: =AA52-Y52 -> 263 | AA52: 413 | AB52: 52 | AC52: =AF52-AB52 -> 110 | AD52: =241-AF52 -> 79 | AE52: =AG52-AD52 -> 186 | AF52: 162 | AG52: =AH52-AF52 -> 265 | AH52: 427 | AI52: 33 | AJ52: =AM52-AI52 -> 111 | AK52: =200-AM52 -> 56 | AL52: =AN52-AK52 -> 108 | AM52: 144 | AN52: =AO52-AM52 -> 164 | AO52: 308 | AP52: -2 | AQ52: =AT52-AP52 -> 95 | AR52: 72 | AS52: =AU52-AR52 -> 172 | AT52: 93 | AU52: =AV52-AT52 -> 244 | AV52: 337 | AW52: -6 | AX52: =BA52-AW52 -> 86 | AY52: =161-BA52 -> 81 | AZ52: =BB52-AY52 -> 86 | BA52: 80 | BB52: =BC52-BA52 -> 167 | BC52: 247 | BD52: -10 | BE52: 124 | BF52: =179-BH52 -> 65 | BG52: =BI52-BF52 -> 187 | BH52: =BD52+BE52 -> 114 | BI52: =BJ52-BH52 -> 252 | BJ52: 366 | BK52: 9 | BL52: =BO52-BK52 -> 115 | BM52: =203-BO52 -> 79 | BN52: =BP52-BM52 -> 211 | BO52: 124 | BP52: =BQ52-BO52 -> 290 | BQ52: 414 | BR52: 9 | BS52: =BV52-BR52 -> 115 | BT52: =203-BV52 -> 79 | BU52: =BW52-BT52 -> 211 | BV52: 124 | BW52: =BX52-BV52 -> 290 | BX52: 414 | BY52: -53 | BZ52: =CC52-BY52 -> 99 | CA52: 86 | CB52: =CD52-CA52 -> 323 | CC52: 46 | CD52: =CE52-CC52 -> 409 | CE52: 455 | CF52: 62 | CG52: =CJ52-CF52 -> 121 | CH52: 129 | CI52: =CK52-CH52 -> 223 | CJ52: 183 | CK52: =CL52-CJ52 -> 352 | CL52: 535 | CM52: 90 | CN52: 125 | CO52: 165 | CP52: =CR52-CO52 -> 259 | CQ52: =+CM52+CN52 -> 215 | CR52: =CS52-CQ52 -> 424 | CS52: 639 | CT52: 156 | CU52: =CX52-CT52 -> 111 | CV52: 143 | CW52: =CY52-CV52 -> 307 | CX52: 267 | CY52: =CZ52-CX52 -> 450 | CZ52: 717 | DA52: 71 | DB52: =DE52-DA52 -> 159 | DC52: 190 | DD52: =DF52-DC52 -> 398 | DE52: 230 | DF52: =DG52-DE52 -> 588 | DG52: 818 | DH52: 78 | DI52: =DL52-DH52 -> 171 | DJ52: 246 | DK52: =DM52-DJ52 -> 458 | DL52: 249 | DM52: =DN52-DL52 -> 704 | DN52: 953 | DO52: 65 | DP52: =DS52-DO52 -> 175 | DQ52: =Helicopters!DC11 -> 260.24091 | DR52: =Helicopters!DD11 -> 463.51285 | DS52: 240 | DT52: =Helicopters!DF11 -> 723.75376 | DU52: =Helicopters!DG11 -> 963.75376 | DV52: =Helicopters!DH11 -> 179.59914 | DW52: =Helicopters!DI11 -> 233.3748 | DX52: =Helicopters!DJ11 -> 234.03693 | DY52: =Helicopters!DK11 -> 408.51238 | DZ52: =Helicopters!DL11 -> 412.97394 | EA52: =Helicopters!DM11 -> 642.5493 | ... EW52: =Helicopters!EI11 -> 1289.7011
A53: Airbus Defence & Space | N53: 84 | O53: =R53-N53 -> 132 | P53: =356-R53 -> 140 | Q53: =S53-P53 -> 303 | R53: 216 | S53: =T53-R53 -> 443 | T53: 659 | U53: 85 | V53: =Y53-U53 -> 138 | W53: =370-Y53 -> 147 | X53: =Z53-W53 -> 39 | Y53: 223 | Z53: =AA53-Y53 -> 186 | AA53: 409 | AB53: 133 | AC53: =AF53-AB53 -> -159 | AD53: =149-AF53 -> 175 | AE53: =AG53-AD53 -> 596 | AF53: -26 | AG53: =AH53-AF53 -> 771 | AH53: 745 | AI53: 88 | AJ53: =AM53-AI53 -> 387 | AK53: =579-AM53 -> 104 | AL53: =AN53-AK53 -> -672 | AM53: 475 | AN53: =AO53-AM53 -> -568 | AO53: -93 | AP53: 620 | AQ53: =AT53-AP53 -> 196 | AR53: 84 | AS53: =AU53-AR53 -> -688 | AT53: 816 | AU53: =AV53-AT53 -> -604 | AV53: 212 | AW53: 657 | AX53: =BA53-AW53 -> 175 | AY53: =889-BA53 -> 57 | AZ53: =BB53-AY53 -> -427 | BA53: 832 | BB53: =BC53-BA53 -> -370 | BC53: 462 | BD53: 265 | BE53: 117 | BF53: =479-BH53 -> 97 | BG53: =BI53-BF53 -> 197 | BH53: =BD53+BE53 -> 382 | BI53: =BJ53-BH53 -> 294 | BJ53: 676 | BK53: -117 | BL53: =BO53-BK53 -> 102 | BM53: =83-BO53 -> 98 | BN53: =BP53-BM53 -> -964 | BO53: -15 | BP53: =BQ53-BO53 -> -866 | BQ53: -881 | BR53: -117 | BS53: =BV53-BR53 -> 102 | BT53: =83-BV53 -> 98 | BU53: =BW53-BT53 -> -964 | BV53: -15 | BW53: =BX53-BV53 -> -866 | BX53: -881 | BY53: 53 | BZ53: =CC53-BY53 -> 126 | CA53: -109 | CB53: =CD53-CA53 -> 338 | CC53: 179 | CD53: =CE53-CC53 -> 229 | CE53: 408 | CF53: 17 | CG53: =CJ53-CF53 -> 140 | CH53: 47 | CI53: =CK53-CH53 -> 364 | CJ53: 157 | CK53: =CL53-CJ53 -> 411 | CL53: 568 | CM53: 95 | CN53: -208 | CO53: 49 | CP53: =CR53-CO53 -> -54 | CQ53: =+CM53+CN53 -> -113 | CR53: =CS53-CQ53 -> -5 | CS53: -118 | CT53: 36 | CU53: =CX53-CT53 -> 51 | CV53: -90 | CW53: =CY53-CV53 -> 223 | CX53: 87 | CY53: =CZ53-CX53 -> 133 | CZ53: 220 | DA53: 30 | DB53: =DE53-DA53 -> -790 | DC53: 143 | DD53: =DF53-DC53 -> -39 | DE53: -760 | DF53: =DG53-DE53 -> 104 | DG53: -656 | DH53: -31 | DI53: =DL53-DH53 -> 192 | DJ53: 192 | DK53: =DM53-DJ53 -> 286 | DL53: 161 | DM53: =DN53-DL53 -> 478 | DN53: 639 | DO53: 134 | DP53: =DS53-DO53 -> 408 | DQ53: ='Defence & Space'!CQ15 -> 211.79113 | DR53: ='Defence & Space'!CR15 -> 318.38027 | DS53: 542 | DT53: ='Defence & Space'!CT15 -> 530.1714 | DU53: ='Defence & Space'!CU15 -> 1072.1714 | DV53: ='Defence & Space'!CV15 -> 226.5777 | DW53: ='Defence & Space'!CW15 -> 278.97862 | DX53: ='Defence & Space'!CX15 -> 267.45159 | DY53: ='Defence & Space'!CY15 -> 390.11042 | DZ53: ='Defence & Space'!CZ15 -> 505.55633 | EA53: ='Defence & Space'!DA15 -> 657.56201 | ... EW53: ='Defence & Space'!DW15 -> 1490.9659
A54: =A7 -> Airbus Military | B54: 1 | C54: -80 | D54: 30 | E54: 26 | F54: 48 | G54: 75 | H54: -155 | I54: -493 | J54: -1754 | K54: 21 | L54: 49 | M54: 93
A55: =A8 -> Cassidian | B55: -79 | C55: 122 | D55: =171 -> 171 | E55: 226 | F55: 201 | G55: 348 | H55: 345 | I55: 408 | J55: 449 | K55: 457 | L55: 331 | M55: 142
A56: =A9 -> Astrium | B56: -222 | C56: =-268 -> -268 | D56: -400 | E56: 9 | F56: 58 | G56: 130 | H56: 174 | I56: 234 | J56: 261 | K56: 283 | L56: 267 | M56: 312
A57: =A10 -> Other Businesses | B57: =308*0.3 -> 92.4 | C57: =180*0.3 -> 54 | D57: =217*0.3 -> 65.1 | E57: 2 | F57: -171 | G57: -288 | H57: 84 | I57: 43 | J57: 21 | K57: 25 | L57: 59 | M57: 49
A58: Segment Total | B58: =+SUM(B57,B56,B55,B52,B54,B51) -> 1663 | C58: =+SUM(C57,C56,C55,C52,C54,C51) -> 1315 | D58: =+SUM(D57,D56,D55,D52,D54,D51) -> 1371 | E58: =+SUM(E57,E56,E55,E52,E54,E51) -> 2383 | F58: =+SUM(F57,F56,F55,F52,F54,F51) -> 2655 | G58: =+SUM(G57,G56,G55,G52,G54,G51) -> -50 | H58: =+SUM(H57,H56,H55,H52,H54,H51) -> -222 | I58: =+SUM(I57,I56,I55,I52,I54,I51) -> 2791 | ... M58: =+SUM(M57,M56,M55,M52,M54,M51) -> 2032 | N58: =SUM(N51:N56) -> 567 | O58: =SUM(O51:O56) -> 872 | P58: =SUM(P51:P56) -> 657 | Q58: =SUM(Q51:Q56) -> 553 | R58: =SUM(R51:R56) -> 1439 | S58: =SUM(S51:S56) -> 1210 | T58: =+SUM(T51:T57) -> 2649 | U58: =SUM(U51:U56) -> 689 | V58: =SUM(V51:V56) -> 1041 | W58: =SUM(W51:W56) -> 654 | X58: =SUM(X51:X56) -> 1109 | Y58: =SUM(Y51:Y56) -> 1730 | Z58: =SUM(Z51:Z56) -> 1763 | AA58: =SUM(AA51:AA56) -> 3493 | AB58: =SUM(AB51:AB56) -> 604 | ... BB58: =SUM(BB51:BB56) -> 1673 | BC58: =+BC51+BC53+BC52 -> 2966 | BD58: =SUM(BD51:BD56) -> 253 | BE58: =SUM(BE51:BE56) -> 1016 | BF58: =SUM(BF51:BF56) -> 1627 | BG58: =SUM(BG51:BG56) -> 2441 | BH58: =SUM(BH51:BH56) -> 1269 | BI58: =SUM(BI51:BI56) -> 4068 | BJ58: =SUM(BJ51:BJ56) -> 5337 | BK58: =SUM(BK51:BK56) -> 284 | ... EW58: =SUM(EW51:EW56) -> 13574.104
A59: HQ/Eliminations & other businesses | B59: 31 | C59: 111 | D59: 172 | E59: 49 | F59: 197 | G59: 449 | H59: 274 | I59: 39 | J59: 52 | K59: -29 | L59: 188 | M59: 154 | N59: 22 | O59: =R59-N59 -> 17 | P59: =35-R59 -> -4 | Q59: =S59-P59 -> -60 | R59: 39 | S59: =T59-R59 -> -64 | T59: -25 | U59: 30 | V59: =Y59-U59 -> 79 | W59: =199-Y59 -> 90 | X59: =Z59-W59 -> 348 | Y59: 109 | Z59: =AA59-Y59 -> 438 | AA59: 547 | AB59: 637 | AC59: =AF59-AB59 -> 32 | AD59: =654-AF59 -> -15 | AE59: =AG59-AD59 -> -41 | AF59: 669 | AG59: =AH59-AF59 -> -56 | AH59: 613 | AI59: -48 | AJ59: =AM59-AI59 -> 860 | AK59: =804-AM59 -> -8 | AL59: =AN59-AK59 -> -304 | AM59: 812 | AN59: =AO59-AM59 -> -312 | AO59: 500 | AP59: -102 | AQ59: =AT59-AP59 -> -94 | AR59: -75 | AS59: =AU59-AR59 -> -285 | AT59: -196 | AU59: =AV59-AT59 -> -360 | AV59: -556 | AW59: -28 | AX59: =BA59-AW59 -> -54 | AY59: =-156-BA59 -> -74 | AZ59: =BB59-AY59 -> -145 | BA59: -82 | BB59: =BC59-BA59 -> -219 | BC59: -301 | BD59: -54 | BE59: -95 | BF59: =-213-BH59 -> -64 | BG59: =BI59-BF59 -> -76 | BH59: =BD59+BE59 -> -149 | BI59: =BJ59-BH59 -> -140 | BJ59: -289 | BK59: -103 | BL59: =BO59-BK59 -> -64 | BM59: =-260-BO59 -> -93 | BN59: =BP59-BM59 -> -139 | BO59: -167 | BP59: =BQ59-BO59 -> -232 | BQ59: -399 | BR59: =-103+73 -> -30 | BS59: =BV59-BR59 -> 8 | BT59: =-260+240-BV59 -> 2 | BU59: =BW59-BT59 -> 32 | BV59: =-167+145 -> -22 | BW59: =BX59-BV59 -> 34 | BX59: =BQ59+411 -> 12 | BY59: 22 | BZ59: =CC59-BY59 -> 2 | CA59: -12 | CB59: =CD59-CA59 -> -55 | CC59: 24 | CD59: =CE59-CC59 -> -67 | CE59: -43 | CF59: 40 | CG59: =CJ59-CF59 -> -40 | CH59: 32 | CI59: =CK59-CH59 -> 32 | CJ59: 0 | CK59: =CL59-CJ59 -> 64 | CL59: 64 | CM59: 2 | CN59: -3 | CO59: -4 | CP59: =CR59-CO59 -> 9 | CQ59: =+CM59+CN59 -> -1 | CR59: =CS59-CQ59 -> 5 | CS59: 4 | CT59: 1 | CU59: =CX59-CT59 -> 9 | CV59: -11 | CW59: =CY59-CV59 -> 57 | CX59: 10 | CY59: =CZ59-CX59 -> 46 | CZ59: 56 | DA59: 8 | DB59: =DE59-DA59 -> 6 | DC59: -3 | DD59: =DF59-DC59 -> -2 | DE59: 14 | DF59: =DG59-DE59 -> -5 | DG59: 9 | DH59: -25 | DI59: =DL59-DH59 -> 1 | DJ59: -15 | DK59: =DM59-DJ59 -> -26 | DL59: -24 | DM59: =DN59-DL59 -> -41 | DN59: -65 | DO59: 24 | DP59: =DS59-DO59 -> -11 | DQ59: =DQ30+DQ47 -> 0 | DR59: =DR30+DR47 -> 0 | DS59: 13 | DT59: =DT30+DT47 -> 0 | DU59: =DU30+DU47 -> 13 | DV59: =DV30+DV47 -> 0 | DW59: =DW30+DW47 -> 0 | DX59: =DX30+DX47 -> 0 | DY59: =DY30+DY47 -> 0 | DZ59: =DZ30+DZ47 -> 0 | EA59: =EA30+EA47 -> 0 | ... EW59: =EW30+EW47 -> 0
A60: Total EBIT Reported (pre goodwill & except.) | B60: =+B58+B59 -> 1694 | C60: =+C58+C59 -> 1426 | D60: =+D58+D59 -> 1543 | E60: =+E58+E59 -> 2432 | F60: =+F58+F59 -> 2852 | G60: =+G58+G59 -> 399 | H60: =+H58+H59 -> 52 | I60: =+I58+I59 -> 2830 | ... EW60: =+EW58+EW59 -> 13574.104
A62: Reported depreciation & amortisation
A63: =A102 -> Airbus | B63: 1625 | C63: 1614 | D63: 1628 | E63: 1088 | F63: 1131 | G63: 1140 | H63: 1238 | I63: 1042 | J63: 996 | K63: 959 | L63: 1065 | M63: 1205 | T63: 1208 | AA63: 1419 | AH63: 1608 | AO63: 1568 | AV63: 1593 | BC63: 1661 | BJ63: 1794 | BQ63: =Airbus!BR62 -> 2130 | CE63: =Airbus!BY62 -> 1951 | CL63: =Airbus!CF62 -> 1616 | CS63: =Airbus!CM62 -> 1571 | CT63: =Airbus!CN62 -> 363.791 | CU63: =Airbus!CO62 -> 413.698 | CV63: =Airbus!CP62 -> 432.112 | CW63: =Airbus!CQ62 -> 387.399 | CX63: =Airbus!CR62 -> 777.489 | CY63: =Airbus!CS62 -> 819.511 | CZ63: =Airbus!CT62 -> 1597 | ... EW63: =Airbus!EQ62 -> 3538.2839
A64: Airbus Helicopters | C64: =198*0.7 -> 138.6 | D64: =136*0.7 -> 95.2 | E64: 52 | F64: 68 | G64: 74 | H64: 76 | I64: 85 | J64: 86 | K64: 91 | L64: 140 | M64: 134 | T64: 136 | AA64: 157 | AH64: 159 | AO64: 183 | AV64: 209 | BC64: 209 | BJ64: 167 | BQ64: =Helicopters!BJ17 -> 160 | CE64: =Helicopters!BQ17 -> 208 | CL64: =Helicopters!BX17 -> 184 | CS64: =Helicopters!CE17 -> 189 | CT64: =Helicopters!CF17 -> 41.548 | CU64: =Helicopters!CG17 -> 41.496 | CV64: =Helicopters!CH17 -> 38.168 | CW64: =Helicopters!CI17 -> 70.788 | CX64: =Helicopters!CJ17 -> 83.044 | CY64: =Helicopters!CK17 -> 108.956 | CZ64: =Helicopters!CL17 -> 192 | ... EW64: =Helicopters!EI17 -> 334.73488
A65: Airbus Defence & Space | T65: 521 | AA65: 540 | AH65: 654 | AO65: 483 | AV65: 429 | BC65: 429 | BJ65: 457 | BQ65: ='Defence & Space'!AX21 -> 555 | CE65: ='Defence & Space'!BE21 -> 672 | CL65: ='Defence & Space'!BL21 -> 525 | CS65: ='Defence & Space'!BS21 -> 961 | CT65: ='Defence & Space'!BT21 -> 89.661 | CU65: ='Defence & Space'!BU21 -> 91.806 | CV65: ='Defence & Space'!BV21 -> 96.72 | CW65: ='Defence & Space'!BW21 -> 174.813 | CX65: ='Defence & Space'!BX21 -> 181.467 | CY65: ='Defence & Space'!BY21 -> 271.533 | CZ65: ='Defence & Space'!BZ21 -> 453 | ... EW65: ='Defence & Space'!DW21 -> 897.63658
A66: =A105 -> Airbus Military | B66: 21 | C66: 64 | D66: 31 | E66: 34 | F66: 41 | G66: 30 | H66: 28 | I66: 71 | J66: 174 | K66: 35 | L66: 120 | M66: 77
A67: =A106 -> Cassidian | B67: 567 | C67: 241 | D67: 287 | E67: 139 | F67: 146 | G67: 131 | H67: 140 | I67: 149 | J67: 150 | K67: 141 | L67: 167 | M67: 252
A68: =A107 -> Astrium | B68: 121 | C68: 141 | D68: 134 | E68: 110 | F68: 117 | G68: 126 | H68: 166 | I68: 188 | J68: 228 | K68: 218 | L68: 235 | M68: 298
A69: Other Businesses | B69: 278 | C69: =198*0.3 -> 59.4 | D69: =136*0.3 -> 40.8 | E69: 54 | F69: 55 | G69: 88 | H69: 42 | I69: 43 | J69: 31 | K69: 25 | L69: 58 | M69: 45
A70: Segment total | B70: =+SUM(B63:B69) -> 2612 | C70: =+SUM(C63:C69) -> 2258 | D70: =+SUM(D63:D69) -> 2216 | E70: =+SUM(E63:E69) -> 1477 | F70: =SUM(F63:F69) -> 1558 | G70: =SUM(G63:G69) -> 1589 | H70: =SUM(H63:H69) -> 1690 | I70: =SUM(I63:I69) -> 1578 | J70: =SUM(J63:J69) -> 1665 | K70: =SUM(K63:K69) -> 1469 | L70: =+SUM(L63:L69) -> 1785 | M70: =+SUM(M63:M69) -> 2011 | T70: =+SUM(T63:T69) -> 1865 | AA70: =+SUM(AA63:AA69) -> 2116 | AH70: =+SUM(AH63:AH69) -> 2421 | AO70: =+SUM(AO63:AO69) -> 2234 | AV70: =+SUM(AV63:AV69) -> 2231 | BC70: =+SUM(BC63:BC69) -> 2299 | BJ70: =+SUM(BJ63:BJ69) -> 2418 | BQ70: =+SUM(BQ63:BQ69) -> 2845 | CE70: =+SUM(CE63:CE69) -> 2831 | CL70: =+SUM(CL63:CL69) -> 2325 | CS70: =+SUM(CS63:CS69) -> 2721 | CT70: =+SUM(CT63:CT69) -> 495 | CU70: =+SUM(CU63:CU69) -> 547 | CV70: =+SUM(CV63:CV69) -> 567 | CW70: =+SUM(CW63:CW69) -> 633 | CX70: =+SUM(CX63:CX69) -> 1042 | CY70: =+SUM(CY63:CY69) -> 1200 | CZ70: =+SUM(CZ63:CZ69) -> 2242 | ... EW70: =+SUM(EW63:EW69) -> 4770.6554
A71: HQ/Eliminations & other businesses | B71: 158 | C71: =160 -> 160 | D71: 159 | E71: 144 | F71: 95 | G71: 102 | H71: 82 | I71: 89 | J71: 161 | K71: 113 | L71: 99 | M71: 42 | T71: 62 | AA71: 34 | AH71: 45 | AO71: 60 | AV71: 67 | BC71: -1 | BJ71: 26 | BQ71: 82 | CE71: 0 | CL71: 0 | CS71: -5 | CT71: =CX71/2 -> 0 | CU71: =CX71-CT71 -> 0 | CV71: 0 | CW71: =CY71-CV71 -> 0 | CX71: 0 | CY71: =CZ71-CX71 -> 0 | CZ71: 0 | DA71: 0 | DB71: =DE71-DA71 -> 0 | DC71: 0 | DD71: =DF71-DC71 -> 0 | DE71: 0 | DF71: =DG71-DE71 -> 0 | DG71: 0 | DH71: 0 | DI71: =DL71-DH71 -> 0 | DJ71: 0 | DK71: =DM71-DJ71 -> 0 | DL71: 0 | DM71: =DN71-DL71 -> 0 | DN71: 0 | DO71: 0 | DP71: =DS71-DO71 -> 0 | DQ71: =DT71/2 -> 0 | DR71: =DT71-DQ71 -> 0 | DS71: 0 | DT71: =DU71-DS71 -> 0 | DU71: =DN71 -> 0 | DV71: =DZ71/2 -> 0 | DW71: =DZ71-DV71 -> 0 | DX71: =EA71/2 -> 0 | DY71: =EA71-DX71 -> 0 | DZ71: =EB71/2 -> 0 | EA71: =EB71-DZ71 -> 0 | EB71: =DU71 -> 0 | EC71: =EG71/2 -> 0 | ED71: =EG71-EC71 -> 0 | EE71: =EH71/2 -> 0 | EF71: =EH71-EE71 -> 0 | EG71: =EI71/2 -> 0 | EH71: =EI71-EG71 -> 0 | EI71: =EB71 -> 0 | EJ71: =EN71/2 -> 0 | EK71: =EN71-EJ71 -> 0 | EL71: =EO71/2 -> 0 | EM71: =EO71-EL71 -> 0 | EN71: =EP71/2 -> 0 | EO71: =EP71-EN71 -> 0 | EP71: =EI71 -> 0 | EQ71: =EU71/2 -> 0 | ER71: =EU71-EQ71 -> 0 | ES71: =EV71/2 -> 0 | ET71: =EV71-ES71 -> 0 | EU71: =EW71/2 -> 0 | EV71: =EW71-EU71 -> 0 | EW71: =EP71 -> 0
A72: Total | B72: =+B70+B71 -> 2770 | C72: =+C70+C71 -> 2418 | D72: =+D70+D71 -> 2375 | E72: =+E70+E71 -> 1621 | F72: =+F70+F71 -> 1653 | G72: =+G70+G71 -> 1691 | H72: =+H70+H71 -> 1772 | I72: =+I70+I71 -> 1667 | ... M72: =+M70+M71 -> 2053 | N72: 434 | O72: =R72-N72 -> 442 | P72: =1340-R72 -> 464 | Q72: =S72-P72 -> 587 | R72: 876 | S72: =T72-R72 -> 1051 | T72: =+T70+T71 -> 1927 | U72: 471 | V72: =Y72-U72 -> 483 | W72: =1468-Y72 -> 514 | X72: =Z72-W72 -> 682 | Y72: 954 | Z72: =AA72-Y72 -> 1196 | AA72: =+AA70+AA71 -> 2150 | AB72: 525 | AC72: =AF72-AB72 -> 560 | AD72: =1652-AF72 -> 567 | AE72: =AG72-AD72 -> 814 | AF72: 1085 | AG72: =AH72-AF72 -> 1381 | AH72: =+AH70+AH71 -> 2466 | AI72: 512 | AJ72: =AM72-AI72 -> 561 | AK72: =1580-AM72 -> 507 | AL72: =AN72-AK72 -> 714 | AM72: 1073 | AN72: =AO72-AM72 -> 1221 | AO72: =+AO70+AO71 -> 2294 | AP72: 551 | AQ72: =+AT72-AP72 -> 535 | AR72: =1603-AT72 -> 517 | AS72: =AU72-AR72 -> 695 | AT72: 1086 | AU72: =AV72-AT72 -> 1212 | AV72: =+AV70+AV71 -> 2298 | AW72: 551 | AX72: =+BA72-AW72 -> 535 | AY72: =1603-BA72 -> 517 | AZ72: =BB72-AY72 -> 695 | BA72: 1086 | BB72: =BC72-BA72 -> 1212 | BC72: =+BC70+BC71 -> 2298 | BD72: 564 | BE72: =BH72-BD72 -> 598 | BF72: =1684-BH72 -> 522 | BG72: =BI72-BF72 -> 760 | BH72: 1162 | BI72: =BJ72-BH72 -> 1282 | BJ72: =+BJ70+BJ71 -> 2444 | BK72: 720 | BL72: =BO72-BK72 -> 542 | BM72: =1992-BO72 -> 730 | BN72: =BP72-BM72 -> 935 | BO72: 1262 | BP72: =BQ72-BO72 -> 1665 | BQ72: =+BQ70+BQ71 -> 2927 | BY72: 828 | BZ72: =CC72-BY72 -> 593 | CA72: =2044-CC72 -> 623 | CB72: =CD72-CA72 -> 787 | CC72: 1421 | CD72: =CE72-CC72 -> 1410 | CE72: =+CE70+CE71 -> 2831 | CF72: 597 | CG72: =CJ72-CF72 -> 454 | CH72: =1641-CJ72 -> 590 | CI72: =CK72-CH72 -> 684 | CJ72: 1051 | CK72: =CL72-CJ72 -> 1274 | CL72: =+CL70+CL71 -> 2325 | CM72: 585 | CN72: =CQ72-CM72 -> 571 | CO72: =1640-CQ72 -> 484 | CP72: =CR72-CO72 -> 1076 | CQ72: 1156 | CR72: =CS72-CQ72 -> 1560 | CS72: =+CS70+CS71 -> 2716 | CT72: =+CT70+CT71 -> 495 | CU72: =+CU70+CU71 -> 547 | CV72: =+CV70+CV71 -> 567 | CW72: =+CW70+CW71 -> 633 | CX72: =+CX70+CX71 -> 1042 | CY72: =+CY70+CY71 -> 1200 | CZ72: =+CZ70+CZ71 -> 2242 | ... EW72: =+EW70+EW71 -> 4770.6554
A74: Adjustments: (exceptional depreciation / disposals)
A75: =A63 -> Airbus | B75: 390 | C75: 180 | D75: 160 | E75: 126 | F75: 100 | G75: 30 | H75: 23 | I75: 27 | J75: 23 | K75: 27 | L75: 26 | M75: 25 | T75: 26 | AA75: 25 | AH75: 14 | AO75: 2
A76: =A64 -> Airbus Helicopters | B76: 0 | C76: 0 | D76: 0 | E76: 0 | F76: 0 | G76: 0 | H76: 1 | I76: 1 | J76: 1 | K76: 1 | L76: 1 | M76: 1 | T76: 1 | AA76: 0 | AH76: 0 | AO76: 5
A77: Airbus Defence & Space | T77: =1+4+6 -> 11 | AA77: 16 | AH77: 9 | AO77: 0
A78: =A66 -> Airbus Military | B78: 54 | C78: 10 | D78: 10 | E78: 0 | F78: 0 | G78: 4 | H78: 1 | I78: 2 | J78: 2 | K78: 2 | L78: 1 | M78: 1
A79: =A67 -> Cassidian | B79: -936 | C79: 26 | D79: 16 | E79: 0 | F79: 0 | G79: 9 | H79: 10 | I79: 9 | J79: 12 | K79: 7 | L79: 7 | M79: 6
A80: =A68 -> Astrium | B80: -283 | C80: -6 | D80: -8 | E80: 0 | F80: 0 | G80: 3 | H80: 4 | I80: 3 | J80: 4 | K80: 4 | L80: 4 | M80: 4
A81: =A69 -> Other Businesses | B81: -29 | C81: -12 | D81: 10 | E81: 0 | F81: 0 | G81: 0 | H81: 0 | I81: 0 | J81: 0 | K81: =J81 -> 0 | L81: 0 | M81: 0 | T81: 0 | AA81: =T81 -> 0 | AH81: =AA81 -> 0 | AO81: =AH81 -> 0
A82: =A70 -> Segment total | B82: =+SUM(B75:B81) -> -804 | C82: =+SUM(C75:C81) -> 198 | D82: =+SUM(D75:D81) -> 188 | E82: =+SUM(E75:E81) -> 126 | F82: =+SUM(F75:F81) -> 100 | G82: =+SUM(G75:G81) -> 46 | H82: =+SUM(H75:H81) -> 39 | I82: =+SUM(I75:I81) -> 42 | ... M82: =+SUM(M75:M81) -> 37 | T82: =+SUM(T75:T81) -> 38 | AA82: =+SUM(AA75:AA81) -> 41 | AH82: =+SUM(AH75:AH81) -> 23 | AO82: =+SUM(AO75:AO81) -> 7
A83: HQ/Eliminations & other businesses | B83: -1051 | C83: 45 | D83: 41 | E83: =+E84-E82 -> 91 | F83: =+F84-F82 -> 40 | G83: 11 | H83: 34 | I83: 16 | J83: 16 | K83: 3 | L83: 2 | M83: 1 | T83: =+M83 -> 1 | AA83: 2 | AH83: 1 | AO83: 37
A84: Total | B84: =+B82+B83 -> -1855 | C84: =+C82+C83 -> 243 | D84: =+D82+D83 -> 229 | E84: 217 | F84: 140 | G84: =+G82+G83 -> 57 | H84: =+H82+H83 -> 73 | I84: =+I82+I83 -> 58 | J84: =+J82+J83 -> 58 | K84: =+K82+K83 -> 44 | L84: =+L82+L83 -> 41 | M84: =+M82+M83 -> 38 | T84: =+T82+T83 -> 39 | AA84: =+AA82+AA83 -> 43 | AH84: =+AH82+AH83 -> 24 | AO84: =+AO82+AO83 -> 44
A86: Net depreciation & amortisation
A87: =A102 -> Airbus | B87: =+B63-B75 -> 1235 | C87: =+C63-C75 -> 1434 | D87: =+D63-D75 -> 1468 | E87: =+E63-E75 -> 962 | F87: =+F63-F75 -> 1031 | G87: =+G63-G75 -> 1110 | H87: =+H63-H75 -> 1215 | I87: =+I63-I75 -> 1015 | ... M87: =+M63-M75 -> 1180 | T87: =+T63-T75 -> 1182 | AA87: =+AA63-AA75 -> 1394 | AH87: =+AH63-AH75 -> 1594 | AO87: =+AO63-AO75 -> 1566 | AV87: =+AV63-AV75 -> 1593 | BC87: =+BC63-BC75 -> 1661 | BJ87: =+BJ63-BJ75 -> 1794 | BQ87: =+BQ63-BQ75 -> 2130 | CE87: =+CE63-CE75 -> 1951 | CL87: =+CL63-CL75 -> 1616 | CS87: =+CS63-CS75 -> 1571 | CT87: =+CT63-CT75 -> 363.791 | CU87: =+CU63-CU75 -> 413.698 | CV87: =+CV63-CV75 -> 432.112 | CW87: =+CW63-CW75 -> 387.399 | CX87: =+CX63-CX75 -> 777.489 | CY87: =+CY63-CY75 -> 819.511 | CZ87: =+CZ63-CZ75 -> 1597 | ... EW87: =+EW63-EW75 -> 3538.2839
A88: Airbus Helicopters | B88: =+B64-B76 -> 0 | C88: =+C64-C76 -> 138.6 | D88: =+D64-D76 -> 95.2 | E88: =+E64-E76 -> 52 | F88: =+F64-F76 -> 68 | G88: =+G64-G76 -> 74 | H88: =+H64-H76 -> 75 | I88: =+I64-I76 -> 84 | ... M88: =+M64-M76 -> 133 | T88: =+T64-T76 -> 135 | AA88: =+AA64-AA76 -> 157 | AH88: =+AH64-AH76 -> 159 | AO88: =+AO64-AO76 -> 178 | AV88: =+AV64-AV76 -> 209 | BC88: =+BC64-BC76 -> 209 | BJ88: =+BJ64-BJ76 -> 167 | BQ88: =+BQ64-BQ76 -> 160 | CE88: =+CE64-CE76 -> 208 | CL88: =+CL64-CL76 -> 184 | CS88: =+CS64-CS76 -> 189 | CT88: =+CT64-CT76 -> 41.548 | CU88: =+CU64-CU76 -> 41.496 | CV88: =+CV64-CV76 -> 38.168 | CW88: =+CW64-CW76 -> 70.788 | CX88: =+CX64-CX76 -> 83.044 | CY88: =+CY64-CY76 -> 108.956 | CZ88: =+CZ64-CZ76 -> 192 | ... EW88: =+EW64-EW76 -> 334.73488
A89: Airbus Defence & Space | T89: =+T65-T77 -> 510 | AA89: =+AA65-AA77 -> 524 | AH89: =+AH65-AH77 -> 645 | AO89: =+AO65-AO77 -> 483 | AV89: =+AV65-AV77 -> 429 | BC89: =+BC65-BC77 -> 429 | BJ89: =+BJ65-BJ77 -> 457 | BQ89: =+BQ65-BQ77 -> 555 | CE89: =+CE65-CE77 -> 672 | CL89: =+CL65-CL77 -> 525 | CS89: =+CS65-CS77 -> 961 | CT89: =+CT65-CT77 -> 89.661 | CU89: =+CU65-CU77 -> 91.806 | CV89: =+CV65-CV77 -> 96.72 | CW89: =+CW65-CW77 -> 174.813 | CX89: =+CX65-CX77 -> 181.467 | CY89: =+CY65-CY77 -> 271.533 | CZ89: =+CZ65-CZ77 -> 453 | ... EW89: =+EW65-EW77 -> 897.63658
A90: =A105 -> Airbus Military | B90: =+B66-B78 -> -33 | C90: =+C66-C78 -> 54 | D90: =+D66-D78 -> 21 | E90: =+E66-E78 -> 34 | F90: =+F66-F78 -> 41 | G90: =+G66-G78 -> 26 | H90: =+H66-H78 -> 27 | I90: =+I66-I78 -> 69 | ... M90: =+M66-M78 -> 76
A91: =A106 -> Cassidian | B91: =+B67-B79 -> 1503 | C91: =+C67-C79 -> 215 | D91: =+D67-D79 -> 271 | E91: =+E67-E79 -> 139 | F91: =+F67-F79 -> 146 | G91: =+G67-G79 -> 122 | H91: =+H67-H79 -> 130 | I91: =+I67-I79 -> 140 | ... M91: =+M67-M79 -> 246
A92: =A107 -> Astrium | B92: =+B68-B80 -> 404 | C92: =+C68-C80 -> 147 | D92: =+D68-D80 -> 142 | E92: =+E68-E80 -> 110 | F92: =+F68-F80 -> 117 | G92: =+G68-G80 -> 123 | H92: =+H68-H80 -> 162 | I92: =+I68-I80 -> 185 | ... M92: =+M68-M80 -> 294
A93: =A108 -> Other Businesses | B93: =+B69-B81 -> 307 | C93: =+C69-C81 -> 71.4 | D93: =+D69-D81 -> 30.8 | E93: =+E69-E81 -> 54 | F93: =+F69-F81 -> 55 | G93: =+G69-G81 -> 88 | H93: =+H69-H81 -> 42 | I93: =+I69-I81 -> 43 | ... M93: =+M69-M81 -> 45 | T93: =+T69-T81 -> 0 | AA93: =+AA69-AA81 -> 0 | AH93: =+AH69-AH81 -> 0 | AO93: =+AO69-AO81 -> 0 | AV93: =+AV69-AV81 -> 0 | BC93: =+BC69-BC81 -> 0 | BJ93: =+BJ69-BJ81 -> 0 | BQ93: =+BQ69-BQ81 -> 0 | CE93: =+CE69-CE81 -> 0 | CL93: =+CL69-CL81 -> 0 | CS93: =+CS69-CS81 -> 0 | CT93: =+CT69-CT81 -> 0 | CU93: =+CU69-CU81 -> 0 | CV93: =+CV69-CV81 -> 0 | CW93: =+CW69-CW81 -> 0 | CX93: =+CX69-CX81 -> 0 | CY93: =+CY69-CY81 -> 0 | CZ93: =+CZ69-CZ81 -> 0 | ... EW93: =+EW69-EW81 -> 0
A94: =+A109 -> Segment Total | B94: =+SUM(B87:B93) -> 3416 | C94: =+SUM(C87:C93) -> 2060 | D94: =+SUM(D87:D93) -> 2028 | E94: =+SUM(E87:E93) -> 1351 | F94: =+SUM(F87:F93) -> 1458 | G94: =+SUM(G87:G93) -> 1543 | H94: =+SUM(H87:H93) -> 1651 | I94: =+SUM(I87:I93) -> 1536 | ... M94: =+SUM(M87:M93) -> 1974 | T94: =+SUM(T87:T93) -> 1827 | AA94: =+SUM(AA87:AA93) -> 2075 | AH94: =+SUM(AH87:AH93) -> 2398 | AO94: =+SUM(AO87:AO93) -> 2227 | AV94: =+SUM(AV87:AV93) -> 2231 | BC94: =+SUM(BC87:BC93) -> 2299 | BJ94: =+SUM(BJ87:BJ93) -> 2418 | BQ94: =+SUM(BQ87:BQ93) -> 2845 | CE94: =+SUM(CE87:CE93) -> 2831 | CL94: =+SUM(CL87:CL93) -> 2325 | CS94: =+SUM(CS87:CS93) -> 2721 | CT94: =+SUM(CT87:CT93) -> 495 | CU94: =+SUM(CU87:CU93) -> 547 | CV94: =+SUM(CV87:CV93) -> 567 | CW94: =+SUM(CW87:CW93) -> 633 | CX94: =+SUM(CX87:CX93) -> 1042 | CY94: =+SUM(CY87:CY93) -> 1200 | CZ94: =+SUM(CZ87:CZ93) -> 2242 | ... EW94: =+SUM(EW87:EW93) -> 4770.6554
A95: Corporate | B95: =B71-B83 -> 1209 | C95: =C71-C83 -> 115 | D95: =D71-D83 -> 118 | E95: =E71-E83 -> 53 | F95: =F71-F83 -> 55 | G95: =G71-G83 -> 91 | H95: =H71-H83 -> 48 | I95: =I71-I83 -> 73 | ... M95: =M71-M83 -> 41 | T95: =T71-T83 -> 61 | AA95: =AA71-AA83 -> 32 | AH95: =AH71-AH83 -> 44 | AO95: =AO71-AO83 -> 23 | AV95: =AV71-AV83 -> 67 | BC95: =BC71-BC83 -> -1 | BJ95: =BJ71-BJ83 -> 26 | BQ95: =BQ71-BQ83 -> 82 | CE95: =CE71-CE83 -> 0 | CL95: =CL71-CL83 -> 0 | CS95: =CS71-CS83 -> -5 | CT95: =CT71-CT83 -> 0 | CU95: =CU71-CU83 -> 0 | CV95: =CV71-CV83 -> 0 | CW95: =CW71-CW83 -> 0 | CX95: =CX71-CX83 -> 0 | CY95: =CY71-CY83 -> 0 | CZ95: =CZ71-CZ83 -> 0 | ... EW95: =EW71-EW83 -> 0
A96: Consolidated | B96: =+B94+B95 -> 4625 | C96: =+C94+C95 -> 2175 | D96: =+D94+D95 -> 2146 | E96: =+E94+E95 -> 1404 | F96: =+F94+F95 -> 1513 | G96: =+G94+G95 -> 1634 | H96: =+H94+H95 -> 1699 | I96: =+I94+I95 -> 1609 | ... M96: =+M94+M95 -> 2015 | T96: =+T94+T95 -> 1888 | AA96: =+AA94+AA95 -> 2107 | AH96: =+AH94+AH95 -> 2442 | AO96: =+AO94+AO95 -> 2250 | AV96: =+AV94+AV95 -> 2298 | BC96: =+BC94+BC95 -> 2298 | BJ96: =+BJ94+BJ95 -> 2444 | BQ96: =+BQ94+BQ95 -> 2927 | CE96: =+CE94+CE95 -> 2831 | CL96: =+CL94+CL95 -> 2325 | CS96: =+CS94+CS95 -> 2716 | CT96: =+CT94+CT95 -> 495 | CU96: =+CU94+CU95 -> 547 | CV96: =+CV94+CV95 -> 567 | CW96: =+CW94+CW95 -> 633 | CX96: =+CX94+CX95 -> 1042 | CY96: =+CY94+CY95 -> 1200 | CZ96: =+CZ94+CZ95 -> 2242 | ... EW96: =+EW94+EW95 -> 4770.6554
A97: Amortisation of finite intangibles | B97: 0 | C97: 0 | D97: 0 | E97: 0 | F97: 0 | G97: 0 | H97: 0 | I97: 0 | J97: 0 | K97: 0 | L97: 0 | M97: 0 | T97: 0 | AA97: 0 | AH97: 0 | AO97: 0 | AV97: 0 | BC97: 0 | BJ97: 0 | BQ97: 0 | CE97: 0 | CL97: 0 | CS97: 0 | CT97: 0 | CU97: =CX97-CT97 -> 0 | CV97: 0 | CW97: =CY97-CV97 -> 0 | CX97: 0 | CY97: =CZ97-CX97 -> 0 | CZ97: 0 | DA97: 0 | DB97: =DE97-DA97 -> 0 | DC97: 0 | DD97: =DF97-DC97 -> 0 | DE97: 0 | DF97: =DG97-DE97 -> 0 | DG97: 0 | DH97: 0 | DI97: =DL97-DH97 -> 0 | DJ97: =DM97/2 -> 0 | DK97: =DM97-DJ97 -> 0 | DL97: 0 | DM97: =DN97-DL97 -> 0 | DN97: 0 | DO97: 0 | DP97: =DS97-DO97 -> 0 | DQ97: =DT97/2 -> 0 | DR97: =DT97-DQ97 -> 0 | DS97: 0 | DT97: =DU97-DS97 -> 0 | DU97: 0 | DV97: =DZ97/2 -> 0 | DW97: =DZ97-DV97 -> 0 | DX97: =EA97/2 -> 0 | DY97: =EA97-DX97 -> 0 | DZ97: =EB97/2 -> 0 | EA97: =EB97-DZ97 -> 0 | EB97: 0 | EC97: =EG97/2 -> 0 | ED97: =EG97-EC97 -> 0 | EE97: =EH97/2 -> 0 | EF97: =EH97-EE97 -> 0 | EG97: =EI97/2 -> 0 | EH97: =EI97-EG97 -> 0 | EI97: 0 | EJ97: =EN97/2 -> 0 | EK97: =EN97-EJ97 -> 0 | EL97: =EO97/2 -> 0 | EM97: =EO97-EL97 -> 0 | EN97: =EP97/2 -> 0 | EO97: =EP97-EN97 -> 0 | EP97: 0 | EQ97: =EU97/2 -> 0 | ER97: =EU97-EQ97 -> 0 | ES97: =EV97/2 -> 0 | ET97: =EV97-ES97 -> 0 | EU97: =EW97/2 -> 0 | EV97: =EW97-EU97 -> 0 | EW97: 0
A98: Total | B98: =+B96-B97 -> 4625 | C98: =+C96-C97 -> 2175 | D98: =+D96-D97 -> 2146 | E98: =+E96-E97 -> 1404 | F98: =+F96-F97 -> 1513 | G98: =+G96-G97 -> 1634 | H98: =+H96-H97 -> 1699 | I98: =+I96-I97 -> 1609 | ... M98: =+M96-M97 -> 2015 | N98: =N72 -> 434 | O98: =O72 -> 442 | P98: =P72 -> 464 | Q98: =Q72 -> 587 | R98: =R72 -> 876 | S98: =S72 -> 1051 | T98: =+T96-T97 -> 1888 | U98: =U72 -> 471 | V98: =V72 -> 483 | W98: =W72 -> 514 | X98: =X72 -> 682 | Y98: =Y72 -> 954 | Z98: =Z72 -> 1196 | AA98: =+AA96-AA97 -> 2107 | AB98: =AB72 -> 525 | AC98: =AC72 -> 560 | AD98: =AD72 -> 567 | AE98: =AE72 -> 814 | AF98: =AF72 -> 1085 | AG98: =AG72 -> 1381 | AH98: =+AH96-AH97 -> 2442 | AI98: =AI72 -> 512 | AJ98: =AJ72 -> 561 | AK98: =AK72 -> 507 | AL98: =AL72 -> 714 | AM98: =AM72 -> 1073 | AN98: =AN72 -> 1221 | AO98: =AO72-AO84 -> 2250 | AP98: =AP72 -> 551 | AQ98: =AQ72 -> 535 | AR98: =AR72 -> 517 | AS98: =AS72 -> 695 | AT98: =AT72 -> 1086 | AU98: =AU72 -> 1212 | AV98: =+AV96-AV97 -> 2298 | AW98: =AW72 -> 551 | AX98: =AX72 -> 535 | AY98: =AY72 -> 517 | AZ98: =AZ72 -> 695 | BA98: =BA72 -> 1086 | BB98: =BB72 -> 1212 | BC98: =+BC96-BC97 -> 2298 | BD98: =BD72 -> 564 | BE98: =BE72 -> 598 | BF98: =BF72 -> 522 | BG98: =BG72 -> 760 | BH98: =BH72 -> 1162 | BI98: =BI72 -> 1282 | BJ98: =+BJ96-BJ97 -> 2444 | BK98: =BK72 -> 720 | BL98: =BL72 -> 542 | BM98: =BM72 -> 730 | BN98: =BN72 -> 935 | BO98: =BO72 -> 1262 | BP98: =BP72 -> 1665 | BQ98: =+BQ96-BQ97 -> 2927 | BR98: =BK98 -> 720 | BS98: =BL98 -> 542 | BT98: =BM98 -> 730 | BU98: =BN98 -> 935 | BV98: =BO98 -> 1262 | BW98: =BP98 -> 1665 | BX98: =BQ98 -> 2927 | BY98: =BY72 -> 828 | BZ98: =BZ72 -> 593 | CA98: =CA72 -> 623 | CB98: =CB72 -> 787 | CC98: =CC72 -> 1421 | CD98: =CD72 -> 1410 | CE98: =+CE96-CE97 -> 2831 | CF98: =CF72 -> 597 | CG98: =CG72 -> 454 | CH98: =CH72 -> 590 | CI98: =CI72 -> 684 | CJ98: =CJ72 -> 1051 | CK98: =CK72 -> 1274 | CL98: =+CL96-CL97 -> 2325 | CM98: =CM72 -> 585 | CN98: =CN72 -> 571 | CO98: =CO72 -> 484 | CP98: =CP72 -> 1076 | CQ98: =CQ72 -> 1156 | CR98: =CR72 -> 1560 | CS98: =+CS96-CS97 -> 2716 | CT98: =+CT96-CT97 -> 495 | CU98: =+CU96-CU97 -> 547 | CV98: =+CV96-CV97 -> 567 | CW98: =+CW96-CW97 -> 633 | CX98: =+CX96-CX97 -> 1042 | CY98: =+CY96-CY97 -> 1200 | CZ98: =+CZ96-CZ97 -> 2242 | ... EW98: =+EW96-EW97 -> 4770.6554
A99: as a % of sales | J99: =J98/J13 -> 0.041287189 | K99: =K98/K13 -> 0.033616017 | L99: =L98/L13 -> 0.037514248 | M99: =M98/M13 -> 0.035676346 | N99: =N98/N13 -> 0.035885563 | O99: =O98/O13 -> 0.032557454 | P99: =P98/P13 -> 0.034947654 | Q99: =Q98/Q13 -> 0.031525242 | ... BQ99: =BQ98/BQ13 -> 0.04153069 | BR99: =BK99 -> 0.05737509 | BS99: =BL99 -> 0.029589998 | BT99: =BM99 -> 0.047706182 | BU99: =BN99 -> 0.038461538 | BV99: =BO99 -> 0.040886412 | BW99: =BP99 -> 0.042032717 | BX99: =BQ99 -> 0.04153069 | BY99: =BY98/BY13 -> 0.077885429 | BZ99: =BZ98/BZ13 -> 0.071299748 | CA99: =CA98/CA13 -> 0.05556051 | CB99: =CB98/CB13 -> 0.039846084 | CC99: =CC98/CC13 -> 0.074994722 | CD99: =CD98/CD13 -> 0.045536752 | CE99: =CE98/CE13 -> 0.056719827 | CF99: =CF98/CF13 -> 0.05707457 | ... EW99: =EW98/EW13 -> 0.045204864
A101: EBITDA reported
A102: =A16 -> Airbus | B102: =B51+B87 -> 2890 | C102: =C51+C87 -> 2795 | D102: =D51+D87 -> 2821 | E102: =E51+E87 -> 2881 | F102: =F51+F87 -> 3338 | G102: =G51+G87 -> 538 | H102: =H51+H87 -> 334 | I102: =I51+I87 -> 3321 | ... M102: =M51+M87 -> 2305 | T102: =T51+T87 -> 2775 | AA102: =AA51+AA87 -> 4065 | AH102: =AH51+AH87 -> 3895 | AO102: =AO51+AO87 -> 3109 | AV102: =AV51+AV87 -> 5021 | BC102: =BC51+BC87 -> 3918 | BJ102: =BJ51+BJ87 -> 6089 | BQ102: =BQ51+BQ87 -> 4335 | CE102: =CE51+CE87 -> 621 | CL102: =CL51+CL87 -> 5791 | CS102: =CS51+CS87 -> 6371 | CT102: =CT51+CT87 -> 560.791 | CU102: =CU51+CU87 -> 1739.698 | CV102: =CV51+CV87 -> 1215.112 | CW102: =CW51+CW87 -> 1691.399 | CX102: =CX51+CX87 -> 2300.489 | CY102: =CY51+CY87 -> 2906.511 | CZ102: =CZ51+CZ87 -> 5207 | ... EW102: =EW51+EW87 -> 14331.721
A103: Airbus Helicopters | B103: =B52+B88 -> 215.6 | C103: =C52+C88 -> 264.6 | D103: =D52+D88 -> 247.1 | E103: =E52+E88 -> 253 | F103: =F52+F88 -> 280 | G103: =G52+G88 -> 331 | H103: =H52+H88 -> 286 | I103: =I52+I88 -> 377 | ... M103: =M52+M88 -> 444 | T103: =T52+T88 -> 532 | AA103: =AA52+AA88 -> 570 | AH103: =AH52+AH88 -> 586 | AO103: =AO52+AO88 -> 486 | AV103: =AV52+AV88 -> 546 | BC103: =BC52+BC88 -> 456 | BJ103: =BJ52+BJ88 -> 533 | BQ103: =BQ52+BQ88 -> 574 | CE103: =CE52+CE88 -> 663 | CL103: =CL52+CL88 -> 719 | CS103: =CS52+CS88 -> 828 | CT103: =CT52+CT88 -> 197.548 | CU103: =CU52+CU88 -> 152.496 | CV103: =CV52+CV88 -> 181.168 | CW103: =CW52+CW88 -> 377.788 | CX103: =CX52+CX88 -> 350.044 | CY103: =CY52+CY88 -> 558.956 | CZ103: =CZ52+CZ88 -> 909 | ... EW103: =EW52+EW88 -> 1624.436
A104: Airbus Defence & Space | T104: =T53+T89 -> 1169 | AA104: =AA53+AA89 -> 933 | AH104: =AH53+AH89 -> 1390 | AO104: =AO53+AO89 -> 390 | AV104: =AV53+AV89 -> 641 | BC104: =BC53+BC89 -> 891 | BJ104: =BJ53+BJ89 -> 1133 | BQ104: =BQ53+BQ89 -> -326 | CE104: =CE53+CE89 -> 1080 | CL104: =CL53+CL89 -> 1093 | CS104: =CS53+CS89 -> 843 | CT104: =CT53+CT89 -> 125.661 | CU104: =CU53+CU89 -> 142.806 | CV104: =CV53+CV89 -> 6.72 | CW104: =CW53+CW89 -> 397.813 | CX104: =CX53+CX89 -> 268.467 | CY104: =CY53+CY89 -> 404.533 | CZ104: =CZ53+CZ89 -> 673 | ... EW104: =EW53+EW89 -> 2388.6025
A105: =A19 -> Airbus Military | B105: =B54+B90 -> -32 | C105: =C54+C90 -> -26 | D105: =D54+D90 -> 51 | E105: =E54+E90 -> 60 | F105: =F54+F90 -> 89 | G105: =G54+G90 -> 101 | H105: =H54+H90 -> -128 | I105: =I54+I90 -> -424 | ... M105: =M54+M90 -> 169
A106: =A20 -> Cassidian | B106: =B55+B91 -> 1424 | C106: =C55+C91 -> 337 | D106: =D55+D91 -> 442 | E106: =E55+E91 -> 365 | F106: =F55+F91 -> 347 | G106: =G55+G91 -> 470 | H106: =H55+H91 -> 475 | I106: =I55+I91 -> 548 | ... M106: =M55+M91 -> 388
A107: =A21 -> Astrium | B107: =B56+B92 -> 182 | C107: =C56+C92 -> -121 | D107: =D56+D92 -> -258 | E107: =E56+E92 -> 119 | F107: =F56+F92 -> 175 | G107: =G56+G92 -> 253 | H107: =H56+H92 -> 336 | I107: =I56+I92 -> 419 | ... M107: =M56+M92 -> 606
A108: =A22 -> Other Businesses | B108: =B57+B93 -> 399.4 | C108: =C57+C93 -> 125.4 | D108: =D57+D93 -> 95.9 | E108: =E57+E93 -> 56 | F108: =F57+F93 -> -116 | G108: =G57+G93 -> -200 | H108: =H57+H93 -> 126 | I108: =I57+I93 -> 86 | ... M108: =M57+M93 -> 94
A109: Segment Total | B109: =B58+B94 -> 5079 | C109: =C58+C94 -> 3375 | D109: =D58+D94 -> 3399 | E109: =E58+E94 -> 3734 | F109: =F58+F94 -> 4113 | G109: =G58+G94 -> 1493 | H109: =H58+H94 -> 1429 | I109: =I58+I94 -> 4327 | ... K109: =K58+K94 -> 2688 | L109: =+SUM(L102:L108) -> 3254 | M109: =+SUM(M102:M108) -> 4006 | T109: =+SUM(T102:T108) -> 4476 | AA109: =+SUM(AA102:AA108) -> 5568 | AH109: =+SUM(AH102:AH108) -> 5871 | AO109: =+SUM(AO102:AO108) -> 3985 | AV109: =+SUM(AV102:AV108) -> 6208 | BC109: =+SUM(BC102:BC108) -> 5265 | BJ109: =+SUM(BJ102:BJ108) -> 7755 | BQ109: =+SUM(BQ102:BQ108) -> 4583 | CE109: =+SUM(CE102:CE108) -> 2364 | CL109: =+SUM(CL102:CL108) -> 7603 | CS109: =+SUM(CS102:CS108) -> 8042 | CT109: =+SUM(CT102:CT108) -> 884 | CU109: =+SUM(CU102:CU108) -> 2035 | CV109: =+SUM(CV102:CV108) -> 1403 | CW109: =+SUM(CW102:CW108) -> 2467 | CX109: =+SUM(CX102:CX108) -> 2919 | CY109: =+SUM(CY102:CY108) -> 3870 | CZ109: =+SUM(CZ102:CZ108) -> 6789 | ... EW109: =+SUM(EW102:EW108) -> 18344.759
...

Sheet IS
A1: E=Morgan Stanley Estimate | AV1: as reported | AW1: IFRS 15 | AX1: IFRS 15 | AY1: IFRS 15 | AZ1: IFRS 15 | BA1: IFRS 15 | BB1: IFRS 15 | BC1: IFRS 15 | BJ1: IFRS 15
A2: Income Statement | B2: 2001 | C2: 2002 | D2: 2003 | E2: 2004 | F2: 2005 | G2: 2006 | H2: 2007 | I2: 2008 | J2: 2009 | K2: 2010 | L2: 2011 | M2: 2012 | N2: 1Q13 | O2: 2Q13 | P2: 3Q13 | Q2: 4Q13 | R2: 1H13 | S2: 2H13 | T2: 2013 | U2: 1Q14 | V2: 2Q14 | W2: 3Q14 | X2: 4Q14 | Y2: 1H14 | Z2: 2H14 | AA2: 2014 | AB2: 1Q15 | AC2: 2Q15 | AD2: 3Q15 | AE2: 4Q15 | AF2: 1H15 | AG2: 2H15 | AH2: 2015 | AI2: 1Q16 | AJ2: 2Q16 | AK2: 3Q16 | AL2: 4Q16 | AM2: 1H16 | AN2: 2H16 | AO2: 2016 | AP2: 1Q17 | AQ2: 2Q17 | AR2: 3Q17 | AS2: 4Q17 | AT2: 1H17 | AU2: 2H17 | AV2: 2017 | AW2: 1Q17 | AX2: 2Q17 | AY2: 3Q17 | AZ2: 4Q17 | BA2: 1H17 | BB2: 2H17 | BC2: 2017 | BD2: 1Q18 | BE2: 2Q18 | BF2: 3Q18 | BG2: 4Q18 | BH2: 1H18 | BI2: 2H18 | BJ2: 2018 | BK2: 1Q19 | BL2: 2Q19 | BM2: 3Q19 | BN2: 4Q19 | BO2: 1H19 | BP2: 2H19 | BQ2: 2019 | BR2: 1Q20 | BS2: 2Q20 | BT2: 3Q20 | BU2: 4Q20 | BV2: 1H20 | BW2: 2H20 | BX2: 2020 | BY2: 1Q21 | BZ2: 2Q21 | CA2: 3Q21 | CB2: 4Q21 | CC2: 1H21 | CD2: 2H21 | CE2: 2021 | CF2: 1Q22 | CG2: 2Q22 | CH2: 3Q22 | CI2: 4Q22 | CJ2: 1H22 | CK2: 2H22 | CL2: 2022 | CM2: 1Q23 | CN2: 2Q23 | CO2: 3Q23 | CP2: 4Q23 | CQ2: 1H23 | CR2: 2H23 | CS2: 2023 | CT2: 1Q24 | CU2: 2Q24 | CV2: 3Q24 | CW2: 4Q24 | CX2: 1H24 | CY2: 2H24 | CZ2: 2024 | DA2: 1Q25 | DB2: 2Q25 | DC2: 3Q25 | DD2: 4Q25 | DE2: 1H25 | DF2: 2H25 | DG2: 2025 | DH2: 1Q26 | DI2: 2Q26 | DJ2: 3Q26 | DK2: 4Q26 | DL2: 1H26 | DM2: 2H26 | DN2: 2026e | DO2: 1Q27 | DP2: 2Q27 | DQ2: 3Q27 | DR2: 4Q27 | DS2: 1H27 | DT2: 2H27 | DU2: 2027e | DV2: 1Q28 | DW2: 2Q28 | DX2: 3Q28 | DY2: 4Q28 | DZ2: 1H28 | EA2: 2H28 | EB2: 2028e | EC2: 1Q29 | ED2: 2Q29 | EE2: 3Q29 | EF2: 4Q29 | EG2: 1H29 | EH2: 2H29 | EI2: 2029e | EJ2: 1Q30 | EK2: 2Q30 | EL2: 3Q30 | EM2: 4Q30 | EN2: 1H30 | EO2: 2H30 | EP2: 2030e
A8: Revenue | C8: =+Divisional!C13 -> 29901 | D8: =+Divisional!D13 -> 30133 | E8: =+Divisional!E13 -> 31761 | F8: =+Divisional!F13 -> 34206 | G8: =+Divisional!G13 -> 39434 | H8: =+Divisional!H13 -> 39123 | I8: =+Divisional!I13 -> 43265 | J8: =+Divisional!J13 -> 42822 | ... BQ8: =+Divisional!BQ13 -> 70478 | BR8: =+Divisional!BY13 -> 10631 | BS8: =+Divisional!BZ13 -> 8317 | BT8: =+Divisional!CA13 -> 11213 | BU8: =+Divisional!CB13 -> 19751 | BV8: =+Divisional!CC13 -> 18948 | BW8: =+Divisional!CD13 -> 30964 | BX8: =+Divisional!CE13 -> 49912 | BY8: =+Divisional!CF13 -> 10460 | ... EP8: =+Divisional!EW13 -> 105534.12
A9: Cost of sales | N9: -10421 | O9: =R9-N9 -> -11236 | P9: =-33005-R9 -> -11348 | Q9: =S9-P9 -> -14720 | R9: -21657 | S9: =T9-R9 -> -26068 | T9: =+-49613-T20 -> -47725 | U9: -10669 | V9: =Y9-U9 -> -12089 | W9: =-34099-Y9 -> -11341 | X9: =Z9-W9 -> -17677 | Y9: -22758 | Z9: =AA9-Y9 -> -29018 | AA9: -51776 | AB9: -10370 | AC9: =AF9-AB9 -> -14489 | AD9: =-36942-AF9 -> -12083 | AE9: =AG9-AD9 -> -18657 | AF9: -24859 | AG9: =AH9-AF9 -> -30740 | AH9: -55599 | AI9: -10740 | AJ9: =AM9-AI9 -> -15903 | AK9: =-38939-AM9 -> -12296 | AL9: =AN9-AK9 -> -22378 | AM9: -26643 | AN9: =AO9-AM9 -> -34674 | AO9: -61317 | AP9: -11703 | AQ9: =+AT9-AP9 -> -13638 | AR9: -12674 | AS9: =AU9-AR9 -> -21145 | AT9: -25341 | AU9: =AV9-AT9 -> -33819 | AV9: -59160 | AW9: -10437 | AX9: =+BA9-AW9 -> -11953 | AY9: =-33707-BA9 -> -11317 | AZ9: =BB9-AY9 -> -18442 | BA9: -22390 | BB9: =BC9-BA9 -> -29759 | BC9: -52149 | BD9: -9045 | BE9: =BH9-BD9 -> -12685 | BF9: =-34357-BH9 -> -12627 | BG9: =BI9-BF9 -> -20563 | BH9: -21730 | BI9: =BJ9-BH9 -> -33190 | BJ9: -54920 | BK9: -11169 | BL9: -15085 | BM9: =-38985-BO9 -> -12731 | BN9: =BP9-BM9 -> -20988 | BO9: =BK9+BL9 -> -26254 | BP9: =BQ9-BO9 -> -33719 | BQ9: -59973 | BR9: -9430 | BS9: -8566 | BT9: -9528 | BU9: =BW9-BT9 -> -16726 | BV9: =BR9+BS9 -> -17996 | BW9: =BX9-BV9 -> -26254 | BX9: -44250 | BY9: -8981 | BZ9: =CC9-BY9 -> -10895 | CA9: -8730 | CB9: =CD9-CA9 -> -13912 | CC9: -19876 | CD9: =CE9-CC9 -> -22642 | CE9: -42518 | CF9: -9460 | CG9: =CJ9-CF9 -> -10431 | CH9: -11162 | CI9: =CK9-CH9 -> -17139 | CJ9: -19891 | CK9: =CL9-CJ9 -> -28301 | CL9: -48192 | CM9: -10103 | CN9: =CQ9-CM9 -> -13043 | CO9: -12846 | CP9: =CR9-CO9 -> -19410 | CQ9: -23146 | CR9: =CS9-CQ9 -> -32256 | CS9: -55402 | CT9: -10897 | CU9: =CX9-CT9 -> -13755 | CV9: -13222 | CW9: =CY9-CV9 -> -20681 | CX9: -24652 | CY9: =CZ9-CX9 -> -33903 | CZ9: -58555 | DA9: -11664 | DB9: =DE9-DA9 -> -13696 | DC9: -14899 | DD9: =DF9-DC9 -> -22194 | DE9: -25360 | DF9: =DG9-DE9 -> -37093 | DG9: -62453 | DH9: -11095 | DI9: =DL9-DH9 -> -16742 | DJ9: =+DJ10-DJ8 -> -16681.661 | DK9: =DM9-DJ9 -> -23955.761 | DL9: -27837 | DM9: =DN9-DL9 -> -40637.422 | DN9: =+DN10-DN8 -> -68474.422 | DO9: =(DO8/DU8)*DU9 -> -17151.737 | DP9: =DS9-DO9 -> -18928.145 | DQ9: =(DQ8/DU8)*DU9 -> -18839.299 | DR9: =DT9-DQ9 -> -21289.258 | DS9: =(DS8/DU8)*DU9 -> -36079.882 | DT9: =DU9-DS9 -> -40128.557 | DU9: =+DU10-DU8 -> -76208.439 | DV9: =(DV8/EB8)*EB9 -> -18615.797 | DW9: =DZ9-DV9 -> -20556.747 | DX9: =(DX8/EB8)*EB9 -> -20463.867 | DY9: =EA9-DX9 -> -23336.289 | DZ9: =(DZ8/EB8)*EB9 -> -39172.544 | EA9: =EB9-DZ9 -> -43800.156 | EB9: =+EB10-EB8 -> -82972.7 | EC9: =(EC8/EI8)*EI9 -> -19970.651 | ED9: =EG9-EC9 -> -21315.584 | EE9: =(EE8/EI8)*EI9 -> -21217.825 | EF9: =EH9-EE9 -> -24211.42 | EG9: =(EG8/EI8)*EI9 -> -41286.235 | EH9: =EI9-EG9 -> -45429.244 | EI9: =+EI10-EI8 -> -86715.479 | EJ9: =(EJ8/EP8)*EP9 -> -20639.307 | EK9: =EN9-EJ9 -> -22051.693 | EL9: =(EL8/EP8)*EP9 -> -21949.522 | EM9: =EO9-EL9 -> -25063.477 | EN9: =(EN8/EP8)*EP9 -> -42691 | EO9: =EP9-EN9 -> -47012.999 | EP9: =+EP10-EP8 -> -89704
A10: Gross profit | N10: =N8+N9 -> 1673 | O10: =O8+O9 -> 2340 | P10: =P8+P9 -> 1929 | Q10: =Q8+Q9 -> 3900 | R10: =R8+R9 -> 4013 | S10: =S8+S9 -> 5829 | T10: =+T8+T9 -> 9842 | U10: =U8+U9 -> 1979 | V10: =V8+V9 -> 2463 | W10: =W8+W9 -> 1956 | X10: =X8+X9 -> 2539 | Y10: =Y8+Y9 -> 4442 | Z10: =Z8+Z9 -> 4495 | AA10: =+AA8+AA9 -> 8937 | AB10: =AB8+AB9 -> 1708 | AC10: =AC8+AC9 -> 2326 | AD10: =AD8+AD9 -> 1989 | AE10: =AE8+AE9 -> 2828 | AF10: =AF8+AF9 -> 4034 | AG10: =AG8+AG9 -> 4817 | AH10: =+AH8+AH9 -> 8851 | AI10: =AI8+AI9 -> 1443 | AJ10: =AJ8+AJ9 -> 669 | AK10: =AK8+AK9 -> 1654 | AL10: =AL8+AL9 -> 1498 | AM10: =AM8+AM9 -> 2112 | AN10: =AN8+AN9 -> 3152 | AO10: =+AO8+AO9 -> 5264 | AP10: =AP8+AP9 -> 1285 | AQ10: =AQ8+AQ9 -> 2083 | AR10: =AR8+AR9 -> 1570 | AS10: =AS8+AS9 -> 2669 | AT10: =AT8+AT9 -> 3368 | AU10: =AU8+AU9 -> 4239 | AV10: =AV8+AV9 -> 7607 | AW10: =AW8+AW9 -> 1005 | ... DI10: =DI8+DI9 -> 3783 | DJ10: =+DJ11*DJ8 -> 2715.6193 | DK10: =DK8+DK9 -> 4029.1023 | DL10: =DL8+DL9 -> 5339 | DM10: =DM8+DM9 -> 6744.7216 | DN10: =+DN11*DN8 -> 12083.722 | DO10: =DO8+DO9 -> 3026.7771 | DP10: =DP8+DP9 -> 3340.2608 | DQ10: =DQ8+DQ9 -> 3324.5821 | DR10: =DR8+DR9 -> 3756.928 | DS10: =DS8+DS9 -> 6367.038 | DT10: =DT8+DT9 -> 7081.5101 | DU10: =+DU11*DU8 -> 13448.548 | DV10: =DV8+DV9 -> 3285.1406 | DW10: =DW8+DW9 -> 3627.6613 | DX10: =DX8+DX9 -> 3611.2706 | DY10: =DY8+DY9 -> 4118.1687 | DZ10: =DZ8+DZ9 -> 6912.8019 | EA10: =EA8+EA9 -> 7729.4393 | EB10: =+EB11*EB8 -> 14642.241 | EC10: =EC8+EC9 -> 3524.2326 | ED10: =ED8+ED9 -> 3761.5736 | EE10: =EE8+EE9 -> 3744.322 | EF10: =EF8+EF9 -> 4272.6034 | EG10: =EG8+EG9 -> 7285.8062 | EH10: =EH8+EH9 -> 8016.9255 | EI10: =+EI11*EI8 -> 15302.732 | EJ10: =EJ8+EJ9 -> 3642.2307 | EK10: =EK8+EK9 -> 3891.4752 | EL10: =EL8+EL9 -> 3873.4451 | EM10: =EM8+EM9 -> 4422.9666 | EN10: =EN8+EN9 -> 7533.7059 | EO10: =EO8+EO9 -> 8296.4117 | EP10: =+EP11*EP8 -> 15830.118
A11: Gross margin (%) | N11: =+N10/N8 -> 0.13833306 | O11: =+O10/O8 -> 0.17236299 | P11: =+P10/P8 -> 0.14528885 | Q11: =+Q10/Q8 -> 0.2094522 | R11: =+R10/R8 -> 0.15633035 | S11: =+S10/S8 -> 0.18274446 | T11: =+T10/T8 -> 0.170966 | U11: =+U10/U8 -> 0.15646743 | ... DI11: =+DI10/DI8 -> 0.18431181 | DJ11: 0.14 | DK11: =+DK10/DK8 -> 0.14397434 | DL11: =+DL10/DL8 -> 0.16092959 | DM11: =+DM10/DM8 -> 0.14234733 | DN11: 0.15 | DO11: =+DO10/DO8 -> 0.15 | DP11: =+DP10/DP8 -> 0.15 | DQ11: =+DQ10/DQ8 -> 0.15 | DR11: =+DR10/DR8 -> 0.15 | DS11: =+DS10/DS8 -> 0.15 | DT11: =+DT10/DT8 -> 0.15 | DU11: =+DN11 -> 0.15 | DV11: =+DV10/DV8 -> 0.15 | DW11: =+DW10/DW8 -> 0.15 | DX11: =+DX10/DX8 -> 0.15 | DY11: =+DY10/DY8 -> 0.15 | DZ11: =+DZ10/DZ8 -> 0.15 | EA11: =+EA10/EA8 -> 0.15 | EB11: =+DU11 -> 0.15 | EC11: =+EC10/EC8 -> 0.15 | ED11: =+ED10/ED8 -> 0.15 | EE11: =+EE10/EE8 -> 0.15 | EF11: =+EF10/EF8 -> 0.15 | EG11: =+EG10/EG8 -> 0.15 | EH11: =+EH10/EH8 -> 0.15 | EI11: =+EB11 -> 0.15 | EJ11: =+EJ10/EJ8 -> 0.15 | EK11: =+EK10/EK8 -> 0.15 | EL11: =+EL10/EL8 -> 0.15 | EM11: =+EM10/EM8 -> 0.15 | EN11: =+EN10/EN8 -> 0.15 | EO11: =+EO10/EO8 -> 0.15 | EP11: =+EI11 -> 0.15
A13: Operating expenses | C13: =+C18-C15-C8-C17-C14-C16 -> -22047 | D13: =+D18-D15-D8-D17-D14-D16 -> -21652 | E13: =+E18-E15-E8-E17-E14-E16 -> -23901 | F13: =+F18-F15-F8-F17-F14-F16 -> -25877 | G13: =+G18-G15-G8-G17-G14-G16 -> -32967 | H13: =+H18-H15-H8-H17-H14-H16 -> -33018 | I13: =+I18-I15-I8-I17-I14-I16 -> -34240 | J13: =+J18-J15-J8-J17-J14-J16 -> -36557 | ... EP13: =+EP18-EP15-EP8-EP17-EP14-EP16 -> -79495.97
A14: SG&A | C14: -2492 | D14: -2985 | E14: -2296 | F14: -2336 | G14: -2462 | H14: -2275 | I14: -2317 | J14: -2298 | K14: =-1024-1288 -> -2312 | L14: =-981-1427 -> -2408 | M14: -3093 | N14: -664 | O14: =R14-N14 -> -782 | P14: =-2138-R14 -> -692 | Q14: =S14-P14 -> -883 | R14: -1446 | S14: =T14-R14 -> -1575 | T14: -3021 | U14: -666 | V14: =Y14-U14 -> -705 | W14: =-2012-Y14 -> -641 | X14: =Z14-W14 -> -768 | Y14: -1371 | Z14: =AA14-Y14 -> -1409 | AA14: -2780 | AB14: -631 | AC14: =AF14-AB14 -> -761 | AD14: =-2019-AF14 -> -627 | AE14: =AG14-AD14 -> -854 | AF14: -1392 | AG14: =AH14-AF14 -> -1481 | AH14: -2873 | AI14: -651 | AJ14: =AM14-AI14 -> -641 | AK14: =-1895-AM14 -> -603 | AL14: =AN14-AK14 -> -1082 | AM14: -1292 | AN14: =AO14-AM14 -> -1685 | AO14: -2977 | AP14: -644 | AQ14: =+AT14-AP14 -> -678 | AR14: =-1923-AT14 -> -601 | AS14: =AU14-AR14 -> -516 | AT14: -1322 | AU14: =AV14-AT14 -> -1117 | AV14: =-872-1567 -> -2439 | AW14: =-211-412 -> -623 | AX14: =+BA14-AW14 -> -639 | AY14: =-639-1206-BA14 -> -583 | AZ14: =BB14-AY14 -> -594 | BA14: =-462-800 -> -1262 | BB14: =BC14-BA14 -> -1177 | BC14: =-872-1567 -> -2439 | BD14: =-185-357 -> -542 | BE14: =BH14-BD14 -> -552 | BF14: =-622-1093-BH14 -> -621 | BG14: =BI14-BF14 -> -720 | BH14: =-411-683 -> -1094 | BI14: =BJ14-BH14 -> -1341 | BJ14: =-861-1574 -> -2435 | BK14: =-212-372 -> -584 | BL14: =-248-402 -> -650 | BM14: =-214-379 -> -593 | BN14: =BP14-BM14 -> -4298 | BO14: =BK14+BL14 -> -1234 | BP14: =BQ14-BO14 -> -4891 | BQ14: =-908-5217 -> -6125 | BR14: =-200-393 -> -593 | BS14: =-170-370 -> -540 | BT14: =-161-290 -> -451 | BU14: =BW14-BT14 -> -556 | BV14: =BR14+BS14 -> -1133 | BW14: =BX14-BV14 -> -1007 | BX14: =-717-1423 -> -2140 | BY14: =-170-340 -> -510 | BZ14: =CC14-BY14 -> -446 | CA14: =-164-333 -> -497 | CB14: =CD14-CA14 -> -599 | CC14: =-344-612 -> -956 | CD14: =CE14-CC14 -> -1096 | CE14: =-713-1339 -> -2052 | CF14: =-181-330 -> -511 | CG14: =-383-706-CF14 -> -578 | CH14: =-193-338 -> -531 | CI14: =CK14-CH14 -> -620 | CJ14: =+CF14+CG14 -> -1089 | CK14: =CL14-CJ14 -> -1151 | CL14: =-788-1452 -> -2240 | CM14: =-205-382 -> -587 | CN14: =CQ14-CM14 -> -663 | CO14: =-218-405 -> -623 | CP14: =CR14-CO14 -> -648 | CQ14: =-424-826 -> -1250 | CR14: =CS14-CQ14 -> -1271 | CS14: =-867-1654 -> -2521 | CT14: =-226-440 -> -666 | CU14: =CX14-CT14 -> -678 | CV14: =-203-399 -> -602 | CW14: =CY14-CV14 -> -675 | CX14: =-460-884 -> -1344 | CY14: =CZ14-CX14 -> -1277 | CZ14: =-877-1744 -> -2621 | DA14: =-219-446 -> -665 | DB14: =DE14-DA14 -> -638 | DC14: =-191+-358 -> -549 | DD14: =DF14-DC14 -> -726 | DE14: =-428-875 -> -1303 | DF14: =DG14-DE14 -> -1275 | DG14: =-856-1722 -> -2578 | DH14: =-219-446 -> -665 | DI14: =DL14-DH14 -> -692 | DJ14: =DC14*(1+((DJ8/DC8)-1)) -> -597.39185 | DK14: =DM14-DJ14 -> -874.25014 | DL14: =-441-916 -> -1357 | DM14: =DN14-DL14 -> -1471.642 | DN14: =DG14*(1+((DN8/DG8)-1)) -> -2828.642 | DO14: =DH14*(1+((DO8/DH8)-1)) -> -1060.6839 | DP14: =DS14-DO14 -> -675.52511 | DQ14: =DJ14*(1+((DQ8/DJ8)-1)) -> -682.59681 | DR14: =DT14-DQ14 -> -729.32429 | DS14: =DL14*(1+((DS8/DL8)-1)) -> -1736.209 | DT14: =DU14-DS14 -> -1411.9211 | DU14: =DN14*(1+((DU8/DN8)-1)) -> -3148.1301 | DV14: =DO14*(1+((DV8/DO8)-1)) -> -1151.2231 | DW14: =DZ14-DV14 -> -733.8087 | DX14: =DQ14*(1+((DX8/DQ8)-1)) -> -741.45912 | DY14: =EA14-DX14 -> -801.06722 | DZ14: =DS14*(1+((DZ8/DS8)-1)) -> -1885.0318 | EA14: =EB14-DZ14 -> -1542.5263 | EB14: =DU14*(1+((EB8/DU8)-1)) -> -3427.5581 | EC14: =DV14*(1+((EC8/DV8)-1)) -> -1235.0089 | ED14: =EG14-EC14 -> -751.73632 | EE14: =DX14*(1+((EE8/DX8)-1)) -> -768.77698 | EF14: =EH14-EE14 -> -826.64814 | EG14: =DZ14*(1+((EG8/DZ8)-1)) -> -1986.7452 | EH14: =EI14-EG14 -> -1595.4251 | EI14: =EB14*(1+((EI8/EB8)-1)) -> -3582.1704 | EJ14: =EC14*(1+((EJ8/EC8)-1)) -> -1276.3594 | EK14: =EN14-EJ14 -> -777.9849 | EL14: =EE14*(1+((EL8/EE8)-1)) -> -795.28829 | EM14: =EO14-EL14 -> -855.99197 | EN14: =EG14*(1+((EN8/EG8)-1)) -> -2054.3443 | EO14: =EP14-EN14 -> -1651.2803 | EP14: =EI14*(1+((EP8/EI8)-1)) -> -3705.6245
A15: Research & development | C15: =-Divisional!C124 -> -2096 | D15: =-Divisional!D124 -> -2189 | E15: =-Divisional!E124 -> -2126 | F15: =-Divisional!F124 -> -2075 | G15: =-Divisional!G124 -> -2458 | H15: =-Divisional!H124 -> -2608 | I15: =-Divisional!I124 -> -2669 | J15: =-Divisional!J124 -> -2825 | ... BJ15: =-Divisional!BJ124 -> -3217 | BK15: =-Divisional!BR124 -> -654 | BL15: =-Divisional!BS124 -> -769 | BM15: =-Divisional!BT124 -> -727 | BN15: =-Divisional!BU124 -> -1208 | BO15: =-Divisional!BV124 -> -1423 | BP15: =-Divisional!BW124 -> -1935 | BQ15: =-Divisional!BQ124 -> -3358 | BR15: =-Divisional!BY124 -> -663 | BS15: =-Divisional!BZ124 -> -733 | BT15: =-Divisional!CA124 -> -636 | BU15: =-Divisional!CB124 -> -826 | BV15: =-Divisional!CC124 -> -1396 | BW15: =-Divisional!CD124 -> -1462 | BX15: =-Divisional!CE124 -> -2858 | BY15: =-Divisional!CF124 -> -620 | ... CT15: =-Divisional!DA124 -> -743 | CU15: =CX15-CT15 -> -850 | CV15: -758 | CW15: =-Divisional!DD124 -> -899 | CX15: -1593 | CY15: =-Divisional!DF124 -> -1657 | CZ15: =-Divisional!DG124 -> -3250 | DA15: =-Divisional!DH124 -> -673 | DB15: =DE15-DA15 -> -733 | DC15: -739 | DD15: =-Divisional!DK124 -> -1008 | DE15: -1406 | DF15: =-Divisional!DM124 -> -1747 | DG15: =-Divisional!DN124 -> -3153 | DH15: =-Divisional!DO124 -> -730 | DI15: =DL15-DH15 -> -734 | DJ15: =-Divisional!DQ124 -> -781.62798 | DK15: =DM15-DJ15 -> -1263.5988 | DL15: -1464 | DM15: =DN15-DL15 -> -2045.2268 | DN15: =-Divisional!DU124 -> -3509.2268 | DO15: =-Divisional!DV124 -> -915.27196 | DP15: =DS15-DO15 -> -998.62774 | DQ15: =-Divisional!DX124 -> -996.30594 | DR15: =DT15-DQ15 -> -1092.6687 | DS15: =-Divisional!DZ124 -> -1913.8997 | DT15: =DU15-DS15 -> -2088.9746 | DU15: =-Divisional!EB124 -> -4002.8743 | DV15: =-Divisional!EC124 -> -1011.6986 | DW15: =DZ15-DV15 -> -1107.1528 | DX15: =-Divisional!EE124 -> -1103.931 | DY15: =EA15-DX15 -> -1230.5688 | DZ15: =-Divisional!EG124 -> -2118.8514 | EA15: =EB15-DZ15 -> -2334.4998 | EB15: =-Divisional!EI124 -> -4453.3512 | EC15: =-Divisional!EJ124 -> -1102.5675 | ED15: =EG15-EC15 -> -1167.9481 | EE15: =-Divisional!EL124 -> -1163.7049 | EF15: =EH15-EE15 -> -1304.5481 | EG15: =-Divisional!EN124 -> -2270.5156 | EH15: =EI15-EG15 -> -2468.253 | EI15: =-Divisional!EP124 -> -4738.7686 | EJ15: =-Divisional!EQ124 -> -1156.4078 | EK15: =EN15-EJ15 -> -1229.1466 | EL15: =-Divisional!ES124 -> -1223.8285 | EM15: =EO15-EL15 -> -1379.6585 | EN15: =-Divisional!EU124 -> -2385.5544 | EO15: =EP15-EN15 -> -2603.487 | EP15: =-Divisional!EW124 -> -4989.0414
A16: Other income/(expense) | C16: 248 | D16: 196 | E16: 314 | F16: 222 | G16: 297 | H16: 233 | I16: 189 | J16: 170 | K16: =171-102 -> 69 | L16: =359-221 -> 138 | M16: 184 | N16: 61 | O16: =R16-N16 -> 32 | P16: =129-R16 -> 36 | Q16: =S16-P16 -> 143 | R16: 93 | S16: =T16-R16 -> 179 | T16: 272 | U16: 52 | V16: =Y16-U16 -> 112 | W16: =235-Y16 -> 71 | X16: =Z16-W16 -> 95 | Y16: 164 | Z16: =AA16-Y16 -> 166 | AA16: 330 | AB16: 127 | AC16: =AF16-AB16 -> 145 | AD16: =296-AF16 -> 24 | AE16: =AG16-AD16 -> 178 | AF16: 272 | AG16: =AH16-AF16 -> 202 | AH16: 474 | AI16: 85 | AJ16: =AM16-AI16 -> 2269 | AK16: =2422-AM16 -> 68 | AL16: =AN16-AK16 -> 267 | AM16: 2354 | AN16: =AO16-AM16 -> 335 | AO16: 2689 | AP16: 703 | AQ16: =+AT16-AP16 -> 84 | AR16: =916-AT16 -> 129 | AS16: =AU16-AR16 -> -271 | AT16: 787 | AU16: =AV16-AT16 -> -142 | AV16: =981-336 -> 645 | AW16: =703-21 -> 682 | AX16: =+BA16-AW16 -> 45 | AY16: =916-78-BA16 -> 111 | AZ16: =BB16-AY16 -> -193 | BA16: =787-60 -> 727 | BB16: =BC16-BA16 -> -82 | BC16: =981-336 -> 645 | BD16: =256-9 -> 247 | BE16: =BH16-BD16 -> 20 | BF16: =352-78-BH16 -> 7 | BG16: =BI16-BF16 -> 1200 | BH16: =310-43 -> 267 | BI16: =BJ16-BH16 -> 1207 | BJ16: =1656-182 -> 1474 | BK16: =70-21 -> 49 | BL16: =62-42 -> 20 | BM16: =115-53 -> 62 | BN16: =BP16-BM16 -> -117 | BO16: =BK16+BL16 -> 69 | BP16: =BQ16-BO16 -> -55 | BQ16: =370-356 -> 14 | BR16: =29-14 -> 15 | BS16: =39-129 -> -90 | BT16: =31-1232 -> -1201 | BU16: =BW16-BT16 -> -50 | BV16: =BR16+BS16 -> -75 | BW16: =BX16-BV16 -> -1251 | BX16: =132-1458 -> -1326 | BY16: =21-26 -> -5 | BZ16: =CC16-BY16 -> 69 | CA16: =58-24 -> 34 | CB16: =CD16-CA16 -> 295 | CC16: =158-94 -> 64 | CD16: =CE16-CC16 -> 329 | CE16: =594-201 -> 393 | CF16: =22-19 -> 3 | CG16: =55-CF16 -> 52 | CH16: =9-5 -> 4 | CI16: =CK16-CH16 -> -178 | CJ16: =+CF16+CG16 -> 55 | CK16: =CL16-CJ16 -> -174 | CL16: =471-590 -> -119 | CM16: =24-36 -> -12 | CN16: =CQ16-CM16 -> -27 | CO16: =96-15 -> 81 | CP16: =CR16-CO16 -> -8 | CQ16: =34-73 -> -39 | CR16: =CS16-CQ16 -> 73 | CS16: =243-209 -> 34 | CT16: =90-25 -> 65 | CU16: =CX16-CT16 -> 35 | CV16: =63-32 -> 31 | CW16: =CY16-CV16 -> -25 | CX16: =178-78 -> 100 | CY16: =CZ16-CX16 -> 6 | CZ16: =303-197 -> 106 | DA16: =33-121 -> -88 | DB16: =DE16-DA16 -> 26 | DC16: =64+-39 -> 25 | DD16: =DF16-DC16 -> 528 | DE16: =98-160 -> -62 | DF16: =DG16-DE16 -> 553 | DG16: =979-488 -> 491 | DH16: =33-121 -> -88 | DI16: =DL16-DH16 -> 131 | DJ16: =DM16/2 -> 224 | DK16: =DM16-DJ16 -> 224 | DL16: =87-44 -> 43 | DM16: =DN16-DL16 -> 448 | DN16: =DG16 -> 491 | DO16: =DS16/2 -> 122.75 | DP16: =DS16-DO16 -> 122.75 | DQ16: =DT16/2 -> 122.75 | DR16: =DT16-DQ16 -> 122.75 | DS16: =DU16/2 -> 245.5 | DT16: =DU16-DS16 -> 245.5 | DU16: =DN16 -> 491 | DV16: =DZ16/2 -> 122.75 | DW16: =DZ16-DV16 -> 122.75 | DX16: =EA16/2 -> 122.75 | DY16: =EA16-DX16 -> 122.75 | DZ16: =EB16/2 -> 245.5 | EA16: =EB16-DZ16 -> 245.5 | EB16: =DU16 -> 491 | EC16: =EG16/2 -> 122.75 | ED16: =EG16-EC16 -> 122.75 | EE16: =EH16/2 -> 122.75 | EF16: =EH16-EE16 -> 122.75 | EG16: =EI16/2 -> 245.5 | EH16: =EI16-EG16 -> 245.5 | EI16: =EB16 -> 491 | EJ16: =EN16/2 -> 122.75 | EK16: =EN16-EJ16 -> 122.75 | EL16: =EO16/2 -> 122.75 | EM16: =EO16-EL16 -> 122.75 | EN16: =EP16/2 -> 245.5 | EO16: =EP16-EN16 -> 245.5 | EP16: =EI16 -> 491
A17: Income from equity interests | C17: 87 | D17: 186 | E17: 84 | F17: 225 | G17: 189 | H17: 296 | I17: 211 | J17: 134 | K17: 145 | L17: 192 | M17: 247 | N17: 126 | O17: =R17-N17 -> 72 | P17: =319-R17 -> 121 | Q17: =S17-P17 -> 164 | R17: 198 | S17: =T17-R17 -> 285 | T17: 483 | U17: 71 | V17: =Y17-U17 -> 77 | W17: =304-Y17 -> 156 | X17: =Z17-W17 -> 591 | Y17: 148 | Z17: =AA17-Y17 -> 747 | AA17: 895 | AB17: 729 | AC17: =AF17-AB17 -> 73 | AD17: =909-AF17 -> 107 | AE17: =AG17-AD17 -> 161 | AF17: 802 | AG17: =AH17-AF17 -> 268 | AH17: 1070 | AI17: 32 | AJ17: =AM17-AI17 -> -46 | AK17: =78-AM17 -> 92 | AL17: =AN17-AK17 -> 174 | AM17: -14 | AN17: =AO17-AM17 -> 266 | AO17: 252 | AP17: 56 | AQ17: =+AT17-AP17 -> 190 | AR17: 53 | AS17: =AU17-AR17 -> 116 | AT17: 246 | AU17: =AV17-AT17 -> 169 | AV17: =333+82 -> 415 | AW17: =42+17 -> 59 | AX17: =+BA17-AW17 -> 190 | AY17: =197+101-BA17 -> 49 | AZ17: =BB17-AY17 -> 95 | BA17: =149+100 -> 249 | BB17: =BC17-BA17 -> 144 | BC17: =311+82 -> 393 | BD17: =31+5 -> 36 | BE17: =BH17-BD17 -> 74 | BF17: =120+43-BH17 -> 53 | BG17: =BI17-BF17 -> 276 | BH17: =81+29 -> 110 | BI17: =BJ17-BH17 -> 329 | BJ17: =330+109 -> 439 | BK17: =-8-2 -> -10 | BL17: =63+16 -> 79 | BM17: =76+18-BO17 -> 25 | BN17: =BP17-BM17 -> 209 | BO17: =BK17+BL17 -> 69 | BP17: =BQ17-BO17 -> 234 | BQ17: =299+4 -> 303 | BR17: 119 | BS17: =-26 -> -26 | BT17: -23 | BU17: =BW17-BT17 -> 82 | BV17: =BR17+BS17 -> 93 | BW17: =BX17-BV17 -> 59 | BX17: =39+113 -> 152 | BY17: 118 | BZ17: =CC17-BY17 -> 2 | CA17: =-27+4 -> -23 | CB17: =CD17-CA17 -> 19 | CC17: =-1+121 -> 120 | CD17: =CE17-CC17 -> -4 | CE17: =40+76 -> 116 | CF17: =-21+4 -> -17 | CG17: =-62-17+29-CF17 -> -33 | CH17: =34+28 -> 62 | CI17: =CK17-CH17 -> 180 | CJ17: =+CF17+CG17 -> -50 | CK17: =CL17-CJ17 -> 242 | CL17: =134+58 -> 192 | CM17: =9+3 -> 12 | CN17: =CQ17-CM17 -> 78 | CO17: =49+3 -> 52 | CP17: =CR17-CO17 -> 161 | CQ17: =80+10 -> 90 | CR17: =CS17-CQ17 -> 213 | CS17: =267+36 -> 303 | CT17: =22-2 -> 20 | CU17: =CX17-CT17 -> 100 | CV17: =80+16 -> 96 | CW17: =CY17-CV17 -> 178 | CX17: =79+41 -> 120 | CY17: =CZ17-CX17 -> 274 | CZ17: =350+44 -> 394 | DA17: =29-8 -> 21 | DB17: =DE17-DA17 -> 117 | DC17: =46+38 -> 84 | DD17: =DF17-DC17 -> 133 | DE17: =103+35 -> 138 | DF17: =DG17-DE17 -> 217 | DG17: =305+50 -> 355 | DH17: =29-8 -> 21 | DI17: =DL17-DH17 -> 163 | DJ17: =DM17/2 -> 102.75716 | DK17: =DM17-DJ17 -> 102.75716 | DL17: =135+49 -> 184 | DM17: =DN17-DL17 -> 205.51432 | DN17: =DG17*(1+((DN8/DG8)-1)) -> 389.51432 | DO17: =DS17/2 -> 108.37725 | DP17: =DS17-DO17 -> 108.37725 | DQ17: =DT17/2 -> 108.37725 | DR17: =DT17-DQ17 -> 108.37725 | DS17: =DU17/2 -> 216.7545 | DT17: =DU17-DS17 -> 216.7545 | DU17: =DN17*(1+((DU8/DN8)-1)) -> 433.50899 | DV17: =DZ17/2 -> 117.99681 | DW17: =DZ17-DV17 -> 117.99681 | DX17: =EA17/2 -> 117.99681 | DY17: =EA17-DX17 -> 117.99681 | DZ17: =EB17/2 -> 235.99363 | EA17: =EB17-DZ17 -> 235.99363 | EB17: =DU17*(1+((EB8/DU8)-1)) -> 471.98725 | EC17: =EG17/2 -> 123.31948 | ED17: =EG17-EC17 -> 123.31948 | EE17: =EH17/2 -> 123.31948 | EF17: =EH17-EE17 -> 123.31948 | EG17: =EI17/2 -> 246.63896 | EH17: =EI17-EG17 -> 246.63896 | EI17: =EB17*(1+((EI8/EB8)-1)) -> 493.27792 | EJ17: =EN17/2 -> 127.5695 | EK17: =EN17-EJ17 -> 127.5695 | EL17: =EO17/2 -> 127.5695 | EM17: =EO17-EL17 -> 127.5695 | EN17: =EP17/2 -> 255.13901 | EO17: =EP17-EN17 -> 255.13901 | EP17: =EI17*(1+((EP8/EI8)-1)) -> 510.27801
A18: EBITDA reported | C18: =+Divisional!C111 -> 3601 | D18: =+Divisional!D111 -> 3689 | E18: =+Divisional!E111 -> 3836 | F18: =+Divisional!F111 -> 4365 | G18: =+Divisional!G111 -> 2033 | H18: =+Divisional!H111 -> 1751 | I18: =+Divisional!I111 -> 4439 | J18: =+Divisional!J111 -> 1446 | ... BC18: =+Divisional!BC111 -> 4963 | BD18: =BD22-BD20 -> 763 | BE18: =BE22-BE20 -> 1519 | BF18: =BF22-BF20 -> 2085 | BG18: =BG22-BG20 -> 3125 | BH18: =BH22-BH20 -> 2282 | BI18: =BI22-BI20 -> 5210 | BJ18: =BJ22-BJ20 -> 7492 | BK18: =BK22-BK20 -> 901 | ... EP18: =EP22-EP20 -> 18344.759
A20: Depreciation & amortisation | C20: =-Divisional!C96 -> -2175 | D20: =-Divisional!D98 -> -2146 | E20: =-Divisional!E98 -> -1404 | F20: =-Divisional!F98 -> -1513 | G20: =-Divisional!G98 -> -1634 | H20: =-Divisional!H98 -> -1699 | I20: =-Divisional!I98 -> -1609 | J20: =-Divisional!J98 -> -1768 | K20: =-Divisional!K98 -> -1538 | ... BJ20: =-Divisional!BJ98 -> -2444 | BK20: =-Divisional!BR98 -> -720 | BL20: =-Divisional!BS98 -> -542 | BM20: =-Divisional!BT98 -> -730 | BN20: =-Divisional!BU98 -> -935 | BO20: =-Divisional!BV98 -> -1262 | BP20: =-Divisional!BW98 -> -1665 | BQ20: =-Divisional!BQ98 -> -2927 | BR20: =-Divisional!BY98 -> -828 | BS20: =-Divisional!BZ98 -> -593 | BT20: =-Divisional!CA98 -> -623 | BU20: =-Divisional!CB98 -> -787 | BV20: =-Divisional!CC98 -> -1421 | BW20: =-Divisional!CD98 -> -1410 | BX20: =-Divisional!CE98 -> -2831 | BY20: =-Divisional!CF98 -> -597 | ... EP20: =-Divisional!EW98 -> -4770.6554
A22: EBIT reported | C22: =C18+C20 -> 1426 | D22: =D18+D20 -> 1543 | E22: =E18+E20 -> 2432 | F22: =F18+F20 -> 2852 | G22: =G18+G20 -> 399 | H22: =H18+H20 -> 52 | I22: =I18+I20 -> 2830 | J22: =J18+J20 -> -322 | ... M22: =M18+M20 -> 2186 | N22: =Divisional!N60 -> 589 | O22: =Divisional!O60 -> 889 | P22: =Divisional!P60 -> 653 | Q22: =Divisional!Q60 -> 493 | R22: =Divisional!R60 -> 1478 | S22: =Divisional!S60 -> 1146 | T22: =T18+T20 -> 2624 | U22: =Divisional!U60 -> 719 | V22: =Divisional!V60 -> 1120 | W22: =Divisional!W60 -> 744 | X22: =Divisional!X60 -> 1457 | Y22: =Divisional!Y60 -> 1839 | Z22: =Divisional!Z60 -> 2201 | AA22: =AA18+AA20 -> 4040 | AB22: =Divisional!AB60 -> 1241 | AC22: =Divisional!AC60 -> 988 | AD22: =Divisional!AD60 -> 717 | AE22: =Divisional!AE60 -> 1140 | AF22: =Divisional!AF60 -> 2229 | AG22: =Divisional!AG60 -> 1857 | AH22: =AH18+AH20 -> 4086 | AI22: =Divisional!AI60 -> 362 | AJ22: =Divisional!AJ60 -> 1489 | AK22: =Divisional!AK60 -> 505 | AL22: =Divisional!AL60 -> -98 | AM22: =Divisional!AM60 -> 1851 | AN22: =Divisional!AN60 -> 407 | AO22: =AO18+AO20 -> 2258 | AP22: =Divisional!AP60 -> 852 | AQ22: =Divisional!AQ60 -> 939 | AR22: =Divisional!AR60 -> 521 | AS22: =Divisional!AS60 -> 1109 | AT22: =Divisional!AT60 -> 1791 | AU22: =Divisional!AU60 -> 1630 | AV22: =AV18+AV20 -> 3421 | AW22: =Divisional!AW60 -> 575 | AX22: =Divisional!AX60 -> 636 | AY22: =Divisional!AY60 -> 462 | AZ22: =Divisional!AZ60 -> 992 | BA22: =Divisional!BA60 -> 1211 | BB22: =Divisional!BB60 -> 1454 | BC22: =BC18+BC20 -> 2665 | BD22: =Divisional!BD60 -> 199 | BE22: =Divisional!BE60 -> 921 | BF22: =Divisional!BF60 -> 1563 | BG22: =Divisional!BG60 -> 2365 | BH22: =Divisional!BH60 -> 1120 | BI22: =Divisional!BI60 -> 3928 | BJ22: =Divisional!BJ60 -> 5048 | BK22: =Divisional!BR60 -> 181 | BL22: =Divisional!BS60 -> 1912 | BM22: =Divisional!BT60 -> 1338 | BN22: =Divisional!BU60 -> -2092 | BO22: =Divisional!BV60 -> 2093 | BP22: =Divisional!BW60 -> -754 | BQ22: =Divisional!BQ60 -> 1339 | BR22: =Divisional!BY60 -> 79 | BS22: =Divisional!BZ60 -> -1638 | BT22: =Divisional!CA60 -> -626 | BU22: =Divisional!CB60 -> 1675 | BV22: =Divisional!CC60 -> -1559 | BW22: =Divisional!CD60 -> 1049 | BX22: =Divisional!CE60 -> -510 | BY22: =Divisional!CF60 -> 462 | ... EP22: =Divisional!EW60 -> 13574.104
A24: Exceptional depreciation | C24: =-Divisional!C84 -> -243 | D24: =-Divisional!D84 -> -229 | E24: =-Divisional!E84 -> -217 | F24: =-Divisional!F84 -> -140 | G24: =-Divisional!G84 -> -57 | H24: =-Divisional!H84 -> -73 | I24: =-Divisional!I84 -> -58 | J24: =-Divisional!J84 -> -58 | ... M24: =-Divisional!M84 -> -38 | N24: -10 | O24: =R24-N24 -> -9 | P24: =-31-R24 -> -12 | Q24: =S24-P24 -> -8 | R24: -19 | S24: =T24-R24 -> -20 | T24: =-Divisional!T84 -> -39 | U24: -10 | V24: =Y24-U24 -> -10 | W24: =-29-Y24 -> -9 | X24: =Z24-W24 -> -14 | Y24: -20 | Z24: =AA24-Y24 -> -23 | AA24: =-Divisional!AA84 -> -43 | AB24: -9 | AC24: =AF24-AB24 -> -10 | AD24: =-24-AF24 -> -5 | AE24: =AG24-AD24 -> 0 | AF24: -19 | AG24: =AH24-AF24 -> -5 | AH24: =-Divisional!AH84 -> -24
A25: Goodwill amortisation | C25: -936 | D25: -567 | E25: 0 | F25: 0 | G25: -64 | H25: -12 | I25: 0 | J25: 0 | K25: 0 | L25: 0 | M25: 0 | N25: 0 | O25: =R25-N25 -> 0 | P25: 0 | Q25: =S25-P25 -> 0 | R25: 0 | S25: =T25-R25 -> 0 | T25: 0 | U25: 0 | V25: =Y25-U25 -> 0 | W25: 0 | X25: =Z25-W25 -> 0 | Y25: 0 | Z25: =AA25-Y25 -> 0 | AA25: 0 | AB25: 0 | AC25: =AF25-AB25 -> 0 | AD25: 0 | AE25: =AG25-AD25 -> 0 | AF25: 0 | AG25: =AH25-AF25 -> 0 | AH25: 0 | AI25: 0 | AJ25: =AM25-AI25 -> 0 | AK25: 0 | AL25: =AN25-AK25 -> 0 | AM25: 0 | AN25: =AO25-AM25 -> 0 | AO25: 0 | AP25: 0 | AQ25: =AT25-AP25 -> 0 | AR25: 0 | AS25: =AU25-AR25 -> 0 | AT25: 0 | AU25: =AV25-AT25 -> 0 | AV25: 0 | AW25: 0 | AX25: =BA25-AW25 -> 0 | AY25: 0 | AZ25: =BB25-AY25 -> 0 | BA25: 0 | BB25: =BC25-BA25 -> 0 | BC25: 0 | BD25: 0 | BE25: =BH25-BD25 -> 0 | BF25: 0 | BG25: =BI25-BF25 -> 0 | BH25: 0 | BI25: =BJ25-BH25 -> 0 | BJ25: 0 | BK25: 0 | BL25: =BO25-BK25 -> 0 | BM25: 0 | BN25: =BP25-BM25 -> 0 | BO25: 0 | BP25: =BQ25-BO25 -> 0 | BQ25: 0 | BR25: 0 | BS25: =BV25-BR25 -> 0 | BT25: 0 | BU25: =BW25-BT25 -> 0 | BV25: 0 | BW25: =BX25-BV25 -> 0 | BX25: 0 | BY25: 0 | BZ25: =CC25-BY25 -> 0 | CA25: 0 | CB25: =CD25-CA25 -> 0 | CC25: 0 | CD25: =CE25-CC25 -> 0 | CE25: 0 | CF25: 0 | CG25: =CJ25-CF25 -> 0 | CH25: 0 | CI25: =CK25-CH25 -> 0 | CJ25: 0 | CK25: =CL25-CJ25 -> 0 | CL25: 0 | CM25: 0 | CN25: =CQ25-CM25 -> 0 | CO25: 0 | CP25: =CR25-CO25 -> 0 | CQ25: 0 | CR25: =CS25-CQ25 -> 0 | CS25: 0 | CT25: 0 | CU25: =CX25-CT25 -> 0 | CV25: 0 | CW25: =CY25-CV25 -> 0 | CX25: 0 | CY25: =CZ25-CX25 -> 0 | CZ25: 0 | DA25: 0 | DB25: =DE25-DA25 -> 0 | DC25: =DF25/2 -> 0 | DD25: =DF25-DC25 -> 0 | DE25: 0 | DF25: =DG25-DE25 -> 0 | DG25: 0 | DH25: 0 | DI25: =DL25-DH25 -> 0 | DJ25: =DM25/2 -> 0 | DK25: =DM25-DJ25 -> 0 | DL25: 0 | DM25: =DN25-DL25 -> 0 | DN25: 0 | DO25: =DS25/2 -> 0 | DP25: =DS25-DO25 -> 0 | DQ25: =DT25/2 -> 0 | DR25: =DT25-DQ25 -> 0 | DS25: =DU25/2 -> 0 | DT25: =DU25-DS25 -> 0 | DU25: 0 | DV25: =DZ25/2 -> 0 | DW25: =DZ25-DV25 -> 0 | DX25: =EA25/2 -> 0 | DY25: =EA25-DX25 -> 0 | DZ25: =EB25/2 -> 0 | EA25: =EB25-DZ25 -> 0 | EB25: 0 | EC25: =EG25/2 -> 0 | ED25: =EG25-EC25 -> 0 | EE25: =EH25/2 -> 0 | EF25: =EH25-EE25 -> 0 | EG25: =EI25/2 -> 0 | EH25: =EI25-EG25 -> 0 | EI25: 0 | EJ25: =EN25/2 -> 0 | EK25: =EN25-EJ25 -> 0 | EL25: =EO25/2 -> 0 | EM25: =EO25-EL25 -> 0 | EN25: =EP25/2 -> 0 | EO25: =EP25-EN25 -> 0 | EP25: 0
A26: Goodwill impairment | C26: 0 | D26: 0 | E26: 0 | F26: 0 | G26: 0 | H26: 0 | I26: 0 | J26: 0 | K26: 0 | L26: -42 | M26: -17 | N26: 0 | O26: =R26-N26 -> 0 | P26: =0-R26 -> 0 | Q26: =S26-P26 -> -15 | R26: 0 | S26: =T26-R26 -> -15 | T26: -15 | U26: 0 | V26: =Y26-U26 -> 0 | W26: =-5-Y26 -> -5 | X26: =Z26-W26 -> -1 | Y26: 0 | Z26: =AA26-Y26 -> -6 | AA26: -6 | AB26: 0 | AC26: =AF26-AB26 -> 0 | AD26: 0 | AE26: =AG26-AD26 -> 0 | AF26: 0 | AG26: =AH26-AF26 -> 0 | AH26: 0 | AI26: 0 | AJ26: =AM26-AI26 -> 0 | AK26: 0 | AL26: =AN26-AK26 -> 0 | AM26: 0 | AN26: =AO26-AM26 -> 0 | AP26: 0 | AQ26: =AT26-AP26 -> 0 | AR26: 0 | AS26: =AU26-AR26 -> 0 | AT26: 0 | AU26: =AV26-AT26 -> 0 | AV26: 0 | AW26: 0 | AX26: =BA26-AW26 -> 0 | AY26: 0 | AZ26: =BB26-AY26 -> 0 | BA26: 0 | BB26: =BC26-BA26 -> 0 | BC26: 0 | BD26: 0 | BE26: =BH26-BD26 -> 0 | BF26: 0 | BG26: =BI26-BF26 -> 0 | BH26: 0 | BI26: =BJ26-BH26 -> 0 | BJ26: 0 | BK26: 0 | BL26: =BO26-BK26 -> 0 | BM26: 0 | BN26: =BP26-BM26 -> 0 | BO26: 0 | BP26: =BQ26-BO26 -> 0 | BQ26: 0 | BR26: 0 | BS26: =BV26-BR26 -> 0 | BT26: 0 | BU26: =BW26-BT26 -> 0 | BV26: 0 | BW26: =BX26-BV26 -> 0 | BX26: 0 | BY26: 0 | BZ26: =CC26-BY26 -> 0 | CA26: 0 | CB26: =CD26-CA26 -> 0 | CC26: 0 | CD26: =CE26-CC26 -> 0 | CE26: 0 | CF26: 0 | CG26: =CJ26-CF26 -> 0 | CH26: 0 | CI26: =CK26-CH26 -> 0 | CJ26: 0 | CK26: =CL26-CJ26 -> 0 | CL26: 0 | CM26: 0 | CN26: =CQ26-CM26 -> 0 | CO26: 0 | CP26: =CR26-CO26 -> 0 | CQ26: 0 | CR26: =CS26-CQ26 -> 0 | CS26: 0 | CT26: 0 | CU26: =CX26-CT26 -> 0 | CV26: 0 | CW26: =CY26-CV26 -> 0 | CX26: 0 | CY26: =CZ26-CX26 -> 0 | CZ26: 0 | DA26: 0 | DB26: =DE26-DA26 -> 0 | DC26: =DF26/2 -> 0 | DD26: =DF26-DC26 -> 0 | DE26: 0 | DF26: =DG26-DE26 -> 0 | DG26: 0 | DH26: 0 | DI26: =DL26-DH26 -> 0 | DJ26: =DM26/2 -> 0 | DK26: =DM26-DJ26 -> 0 | DL26: 0 | DM26: =DN26-DL26 -> 0 | DN26: 0 | DO26: =DS26/2 -> 0 | DP26: =DS26-DO26 -> 0 | DQ26: =DT26/2 -> 0 | DR26: =DT26-DQ26 -> 0 | DS26: =DU26/2 -> 0 | DT26: =DU26-DS26 -> 0 | DU26: 0 | DV26: =DZ26/2 -> 0 | DW26: =DZ26-DV26 -> 0 | DX26: =EA26/2 -> 0 | DY26: =EA26-DX26 -> 0 | DZ26: =EB26/2 -> 0 | EA26: =EB26-DZ26 -> 0 | EB26: 0 | EC26: =EG26/2 -> 0 | ED26: =EG26-EC26 -> 0 | EE26: =EH26/2 -> 0 | EF26: =EH26-EE26 -> 0 | EG26: =EI26/2 -> 0 | EH26: =EI26-EG26 -> 0 | EI26: 0 | EJ26: =EN26/2 -> 0 | EK26: =EN26-EJ26 -> 0 | EL26: =EO26/2 -> 0 | EM26: =EO26-EL26 -> 0 | EN26: =EP26/2 -> 0 | EO26: =EP26-EN26 -> 0 | EP26: 0
A27: EBIT (reported) | C27: =C22+C24+C25+C26 -> 247 | D27: =D22+D24+D25+D26 -> 747 | E27: =E22+E24+E25+E26 -> 2215 | F27: =F22+F24+F25+F26 -> 2712 | G27: =G22+G24+G25+G26 -> 278 | H27: =H22+H24+H25+H26 -> -33 | I27: =I22+I24+I25+I26 -> 2772 | J27: =J22+J24+J25+J26 -> -380 | ... EP27: =EP22+EP24+EP25+EP26 -> 13574.104
A29: Interest expense | C29: -607 | D29: -203 | E29: -627 | F29: -578 | G29: -575 | H29: -701 | I29: -581 | J29: -503 | K29: -415 | L29: -364 | M29: -522 | N29: =-126 -> -126 | O29: =R29-N29 -> -134 | P29: =-400-R29 -> -140 | Q29: =S29-P29 -> -93 | R29: =-260 -> -260 | S29: =T29-R29 -> -233 | T29: -493 | U29: =-130 -> -130 | V29: =Y29-U29 -> -138 | W29: =-395-Y29 -> -127 | X29: =Z29-W29 -> -67 | Y29: =-268 -> -268 | Z29: =AA29-Y29 -> -194 | AA29: -462 | AB29: =-146 -> -146 | AC29: =AF29-AB29 -> -128 | AD29: =-429-AF29 -> -155 | AE29: =AG29-AD29 -> -122 | AF29: =-274 -> -274 | AG29: =AH29-AF29 -> -277 | AH29: -551 | AI29: =-143 -> -143 | AJ29: =AM29-AI29 -> -91 | AK29: =-389-AM29 -> -155 | AL29: =AN29-AK29 -> -133 | AM29: =-234 -> -234 | AN29: =AO29-AM29 -> -288 | AO29: -522 | AP29: =-127 -> -127 | AQ29: =AT29-AP29 -> -124 | AR29: -134 | AS29: =AU29-AR29 -> -132 | AT29: -251 | AU29: =AV29-AT29 -> -266 | AV29: -517 | AW29: =-127 -> -127 | AX29: =-124 -> -124 | AY29: =-385-BA29 -> -134 | AZ29: =BB29-AY29 -> -132 | BA29: =+AX29+AW29 -> -251 | BB29: =BC29-BA29 -> -266 | BC29: -517 | BD29: =-104 -> -104 | BE29: =BH29-BD29 -> -95 | BF29: =-367-BH29 -> -168 | BG29: =BI29-BF29 -> -73 | BH29: =-199 -> -199 | BI29: =BJ29-BH29 -> -241 | BJ29: -440 | BK29: =-92 -> -92 | BL29: =BO29-BK29 -> -99 | BM29: =-266-BO29 -> -75 | BN29: =BP29-BM29 -> -73 | BO29: =-191 -> -191 | BP29: =BQ29-BO29 -> -148 | BQ29: -339 | BR29: =-98 -> -98 | BS29: =-113 -> -113 | BT29: =-313-BV29 -> -102 | BU29: =BW29-BT29 -> -98 | BV29: =BR29+BS29 -> -211 | BW29: =BX29-BV29 -> -200 | BX29: -411 | BY29: =-96 -> -96 | BZ29: =CC29-BY29 -> -108 | CA29: =-281-BY29-BZ29 -> -77 | CB29: =CD29-CA29 -> -53 | CC29: =-204 -> -204 | CD29: =CE29-CC29 -> -130 | CE29: -334 | CF29: =-78 -> -78 | CG29: =+CJ29-CF29 -> -88 | CH29: =-258-CF29-CG29 -> -92 | CI29: =CK29-CH29 -> -154 | CJ29: =-166 -> -166 | CK29: =CL29-CJ29 -> -246 | CL29: -412 | CM29: =-166 -> -166 | CN29: =CQ29-CM29 -> -170 | CO29: =-195 -> -195 | CP29: =CR29-CO29 -> -222 | CQ29: =-336 -> -336 | CR29: =CS29-CQ29 -> -417 | CS29: -753 | CT29: -213 | CU29: =CX29-CT29 -> -215 | CV29: -212 | CW29: =CY29-CV29 -> -260 | CX29: -428 | CY29: =CZ29-CX29 -> -472 | CZ29: -900 | DA29: -189 | DB29: =DE29-DA29 -> -194 | DC29: -181 | DD29: =DF29-DC29 -> -206 | DE29: -383 | DF29: =DG29-DE29 -> -387 | DG29: -770 | DH29: -175 | DI29: =DL29-DH29 -> -185 | DJ29: =-BS!DJ234 -> -223.45625 | DK29: =-BS!DK234 -> -309.99375 | DL29: -360 | DM29: =-BS!DM234 -> -533.45 | DN29: =-BS!DN234 -> -893.45 | DO29: =-BS!DO234 -> -223.3625 | DP29: =-BS!DP234 -> -223.3625 | DQ29: =-BS!DQ234 -> -223.3625 | DR29: =-BS!DR234 -> -223.3625 | DS29: =-BS!DS234 -> -446.725 | DT29: =-BS!DT234 -> -446.725 | ... EP29: =-BS!EP234 -> -893.45
A30: Interest income | C30: 526 | D30: 186 | E30: 352 | F30: 423 | G30: 454 | H30: 502 | I30: 617 | J30: 356 | K30: 316 | L30: 377 | M30: 237 | N30: 40 | O30: =R30-N30 -> 44 | P30: =137-R30 -> 53 | Q30: =S30-P30 -> 24 | R30: 84 | S30: =T30-R30 -> 77 | T30: 161 | U30: 36 | V30: =Y30-U30 -> 43 | W30: =117-Y30 -> 38 | X30: =Z30-W30 -> 25 | Y30: 79 | Z30: =AA30-Y30 -> 63 | AA30: 142 | AB30: 40 | AC30: =AF30-AB30 -> 45 | AD30: =131-AF30 -> 46 | AE30: =AG30-AD30 -> 52 | AF30: 85 | AG30: =AH30-AF30 -> 98 | AH30: 183 | AI30: 75 | AJ30: =AM30-AI30 -> 62 | AK30: =186-AM30 -> 49 | AL30: =AN30-AK30 -> 61 | AM30: 137 | AN30: =AO30-AM30 -> 110 | AO30: 247 | AP30: 39 | AQ30: =AT30-AP30 -> 42 | AR30: 53 | AS30: =AU30-AR30 -> 55 | AT30: 81 | AU30: =AV30-AT30 -> 108 | AV30: 189 | AW30: 39 | AX30: 42 | AY30: =134-BA30 -> 53 | AZ30: =BB30-AY30 -> 55 | BA30: =+AX30+AW30 -> 81 | BB30: =BC30-BA30 -> 108 | BC30: 189 | BD30: 41 | BE30: =BH30-BD30 -> 46 | BF30: =144-BH30 -> 57 | BG30: =BI30-BF30 -> 64 | BH30: 87 | BI30: =BJ30-BH30 -> 121 | BJ30: 208 | BK30: 56 | BL30: =BO30-BK30 -> 35 | BM30: =143-BO30 -> 52 | BN30: =BP30-BM30 -> 85 | BO30: 91 | BP30: =BQ30-BO30 -> 137 | BQ30: 228 | BR30: 53 | BS30: 29 | BT30: =101-BR30-BS30 -> 19 | BU30: =BW30-BT30 -> 39 | BV30: =BR30+BS30 -> 82 | BW30: =BX30-BV30 -> 58 | BX30: 140 | BY30: 14 | BZ30: =CC30-BY30 -> 18 | CA30: =48-BY30-BZ30 -> 16 | CB30: =CD30-CA30 -> 40 | CC30: 32 | CD30: =CE30-CC30 -> 56 | CE30: 88 | CF30: 2 | CG30: =+CJ30-CF30 -> 28 | CH30: =92-CF30-CG30 -> 62 | CI30: =CK30-CH30 -> 88 | CJ30: 30 | CK30: =CL30-CJ30 -> 150 | CL30: 180 | CM30: 133 | CN30: =CQ30-CM30 -> 145 | CO30: 246 | CP30: =CR30-CO30 -> 204 | CQ30: 278 | CR30: =CS30-CQ30 -> 450 | CS30: 728 | CT30: 217 | CU30: =CX30-CT30 -> 182 | CV30: 183 | CW30: =CY30-CV30 -> 220 | CX30: 399 | CY30: =CZ30-CX30 -> 403 | CZ30: 802 | DA30: 209 | DB30: =DE30-DA30 -> 171 | DC30: 157 | DD30: =DF30-DC30 -> 173 | DE30: 380 | DF30: =DG30-DE30 -> 330 | DG30: 710 | DH30: 176 | DI30: =DL30-DH30 -> 165 | DJ30: =+BS!DJ245 -> 146.1 | DK30: =+BS!DK245 -> 193.35 | DL30: 341 | DM30: =+BS!DM245 -> 339.45 | DN30: =+BS!DN245 -> 680.45 | DO30: =+BS!DO245 -> 181.63947 | DP30: =+BS!DP245 -> 181.63947 | DQ30: =+BS!DQ245 -> 167.10561 | DR30: =+BS!DR245 -> 196.17333 | DS30: =+BS!DS245 -> 363.27894 | DT30: =+BS!DT245 -> 363.27894 | ... EP30: =+BS!EP245 -> 1009.2566
A31: Net interest income (expense) | C31: =+C29+C30 -> -81 | D31: =+D29+D30 -> -17 | E31: =+E29+E30 -> -275 | F31: =+F29+F30 -> -155 | G31: =+G29+G30 -> -121 | H31: =+H29+H30 -> -199 | I31: =+I29+I30 -> 36 | J31: =+J29+J30 -> -147 | ... EP31: =+EP29+EP30 -> 115.80659
A32: Unwinding of discounted provisions | CM32: 0 | CN32: =CQ32-CM32 -> 0 | CO32: 0 | CP32: =CR32-CO32 -> 0 | CQ32: 0 | CR32: =CS32-CQ32 -> 0 | CS32: 0 | CT32: 0 | CU32: =CX32-CT32 -> 0 | CV32: 0 | CW32: =CY32-CV32 -> 0 | CX32: 0 | CY32: =CZ32-CX32 -> 0 | CZ32: 0 | DA32: 0 | DB32: =DE32-DA32 -> 0 | DC32: 0 | DD32: =DF32-DC32 -> 0 | DE32: 0 | DF32: =DG32-DE32 -> 0 | DG32: 0 | DH32: 0 | DI32: =DL32-DH32 -> 0 | DJ32: =DM32/2 -> 0 | DK32: =DM32-DJ32 -> 0 | DL32: 0 | DM32: =DN32-DL32 -> 0 | DN32: =DG32 -> 0 | DO32: =DS32/2 -> 0 | DP32: =DS32-DO32 -> 0 | DQ32: =DT32/2 -> 0 | DR32: =DT32-DQ32 -> 0 | DS32: =DU32/2 -> 0 | DT32: =DU32-DS32 -> 0 | DU32: =DN32 -> 0 | DV32: =DZ32/2 -> 0 | DW32: =DZ32-DV32 -> 0 | DX32: =EA32/2 -> 0 | DY32: =EA32-DX32 -> 0 | DZ32: =EB32/2 -> 0 | EA32: =EB32-DZ32 -> 0 | EB32: =DU32 -> 0 | EC32: =EG32/2 -> 0 | ED32: =EG32-EC32 -> 0 | EE32: =EH32/2 -> 0 | EF32: =EH32-EE32 -> 0 | EG32: =EI32/2 -> 0 | EH32: =EI32-EG32 -> 0 | EI32: =EB32 -> 0 | EJ32: =EN32/2 -> 0 | EK32: =EN32-EJ32 -> 0 | EL32: =EO32/2 -> 0 | EM32: =EO32-EL32 -> 0 | EN32: =EP32/2 -> 0 | EO32: =EP32-EN32 -> 0 | EP32: =EI32 -> 0
A33: Exceptional gains / (losses) on disposals
A34: Other one-off financial results | CT34: 225 | CU34: =CX34-CT34 -> -305 | CV34: =-35-CT34-CU34 -> 45 | CW34: =CY34-CV34 -> 253 | CX34: -80 | CY34: =CZ34-CX34 -> 298 | CZ34: 218 | DA34: 593 | DB34: =DE34-DA34 -> -113 | DC34: -99 | DD34: =DF34-DC34 -> -75 | DE34: 480 | DF34: =DG34-DE34 -> -174 | DG34: 306 | DH34: 453 | DI34: =DL34-DH34 -> -272 | DJ34: 0 | DK34: =DM34-DJ34 -> 0 | DL34: 181 | DM34: =DN34-DL34 -> 0 | DN34: 181
A35: Other financial result | C35: 21 | D35: 148 | E35: -55 | F35: -22 | G35: -123 | H35: -538 | I35: -508 | J35: -445 | K35: -272 | L35: -233 | M35: -168 | N35: -187 | O35: =R35-N35 -> -54 | P35: =-172-R35 -> 69 | Q35: =S35-P35 -> -106 | R35: -241 | S35: =T35-R35 -> -37 | T35: -278 | U35: -13 | V35: =Y35-U35 -> -50 | W35: =-334-Y35 -> -271 | X35: =Z35-W35 -> -124 | Y35: -63 | Z35: =AA35-Y35 -> -395 | AA35: -458 | AB35: -260 | AC35: =AF35-AB35 -> 105 | AD35: =-238-AF35 -> -83 | AE35: =AG35-AD35 -> -81 | AF35: -155 | AG35: =AH35-AF35 -> -164 | AH35: -319 | AI35: 261 | AJ35: =AM35-AI35 -> -312 | AK35: =-139-AM35 -> -88 | AL35: =AN35-AK35 -> -553 | AM35: -51 | AN35: =AO35-AM35 -> -641 | AO35: -692 | AP35: -118 | AQ35: =+AT35-AP35 -> 354 | AR35: 107 | AS35: =AU35-AR35 -> 1134 | AT35: 236 | AU35: =AV35-AT35 -> 1241 | AV35: 1477 | AW35: -118 | AX35: =+BA35-AW35 -> 360 | AY35: =352-BA35 -> 110 | AZ35: =BB35-AY35 -> 1137 | BA35: 242 | BB35: =BC35-BA35 -> 1247 | BC35: 1489 | BD35: 102 | BE35: =BH35-BD35 -> -293 | BF35: =-190-BH35 -> 1 | BG35: =BI35-BF35 -> -341 | BH35: -191 | BI35: =BJ35-BH35 -> -340 | BJ35: -531 | BK35: -7 | BL35: =BO35-BK35 -> -108 | BM35: =-110-BO35 -> 5 | BN35: =BP35-BM35 -> -54 | BO35: =-115 -> -115 | BP35: =BQ35-BO35 -> -49 | BQ35: -164 | BR35: -432 | BS35: 132 | BT35: =-500-BV35 -> -200 | BU35: =BW35-BT35 -> 151 | BV35: =BR35+BS35 -> -300 | BW35: =BX35-BV35 -> -49 | BX35: -349 | BY35: 141 | BZ35: =CC35-BY35 -> 1 | CA35: =61-BY35-BZ35 -> -81 | CB35: =CD35-CA35 -> -130 | CC35: 142 | CD35: =CE35-CC35 -> -211 | CE35: -69 | CF35: 242 | CG35: =+CJ35-CF35 -> 1 | CH35: =-140-CF35-CG35 -> -383 | CI35: =CK35-CH35 -> 122 | CJ35: 243 | CK35: =CL35-CJ35 -> -261 | CL35: -18 | CM35: 182 | CN35: =CQ35-CM35 -> -22 | CO35: 78 | CP35: =CR35-CO35 -> -47 | CQ35: 160 | CR35: =CS35-CQ35 -> 31 | CS35: 191 | CT35: 225 | CU35: =CX35-CT35 -> -304 | CV35: 45 | CW35: =CY35-CV35 -> 253 | CX35: -79 | CY35: =CZ35-CX35 -> 298 | CZ35: 219 | DA35: 601 | DB35: =DE35-DA35 -> -108 | DC35: -92 | DD35: =DF35-DC35 -> -73 | DE35: 493 | DF35: =DG35-DE35 -> -165 | DG35: 328 | DH35: 465 | DI35: =DL35-DH35 -> -260 | DJ35: =DJ32+DJ33+DJ34 -> 0 | DK35: =DM35-DJ35 -> -24 | DL35: 205 | DM35: =DN35-DL35 -> -24 | DN35: =DN32+DN33+DN34 -> 181 | DO35: =DO32+DO33+DO34 -> 0 | DP35: =DS35-DO35 -> 0 | DQ35: =DQ32+DQ33+DQ34 -> 0 | DR35: =DT35-DQ35 -> 0 | DS35: =DS32+DS33+DS34 -> 0 | DT35: =DU35-DS35 -> 0 | DU35: =DU32+DU33+DU34 -> 0 | DV35: =DV32+DV33+DV34 -> 0 | DW35: =DZ35-DV35 -> 0 | DX35: =DX32+DX33+DX34 -> 0 | DY35: =EA35-DX35 -> 0 | DZ35: =DZ32+DZ33+DZ34 -> 0 | EA35: =EB35-DZ35 -> 0 | EB35: =EB32+EB33+EB34 -> 0 | EC35: =EC32+EC33+EC34 -> 0 | ED35: =EG35-EC35 -> 0 | EE35: =EE32+EE33+EE34 -> 0 | EF35: =EH35-EE35 -> 0 | EG35: =EG32+EG33+EG34 -> 0 | EH35: =EI35-EG35 -> 0 | EI35: =EI32+EI33+EI34 -> 0 | EJ35: =EJ32+EJ33+EJ34 -> 0 | EK35: =EN35-EJ35 -> 0 | EL35: =EL32+EL33+EL34 -> 0 | EM35: =EO35-EL35 -> 0 | EN35: =EN32+EN33+EN34 -> 0 | EO35: =EP35-EN35 -> 0 | EP35: =EP32+EP33+EP34 -> 0
A36: Total financial costs | C36: =+C31+C35 -> -60 | D36: =+D31+D35 -> 131 | E36: =+E31+E35 -> -330 | F36: =F35+F31 -> -177 | G36: =G35+G31 -> -244 | H36: =H35+H31 -> -737 | I36: =I35+I31 -> -472 | J36: =J35+J31 -> -592 | K36: =+K31+K35 -> -371 | L36: =+L31+L35 -> -220 | M36: =+M31+M35 -> -453 | N36: =+N31+N35 -> -273 | O36: =+O31+O35 -> -144 | P36: =+P31+P35 -> -18 | Q36: =+Q31+Q35 -> -175 | R36: =+R31+R35 -> -417 | ... EP36: =+EP31+EP35 -> 115.80659
A38: PBT reported | C38: =C27+C36 -> 187 | D38: =D27+D36 -> 878 | E38: =E27+E36 -> 1885 | F38: =F27+F36 -> 2535 | G38: =G27+G36 -> 34 | H38: =H27+H36 -> -770 | I38: =I27+I36 -> 2300 | J38: =J27+J36 -> -972 | ... EP38: =EP27+EP36 -> 13689.91
A40: Provision for income taxes | C40: -453 | D40: -474 | E40: -664 | F40: -825 | G40: 81 | H40: 333 | I40: -703 | J40: 220 | K40: -244 | L40: -356 | M40: -449 | N40: -77 | O40: =R40-N40 -> -206 | P40: =-460-R40 -> -177 | Q40: =S40-P40 -> -17 | R40: -283 | S40: =T40-R40 -> -194 | T40: -477 | U40: -166 | V40: =Y40-U40 -> -260 | W40: =-529-Y40 -> -103 | X40: =Z40-W40 -> -334 | Y40: -426 | Z40: =AA40-Y40 -> -437 | AA40: -863 | AB40: -71 | AC40: =AF40-AB40 -> -264 | AD40: =-484-AF40 -> -149 | AE40: =AG40-AD40 -> -193 | AF40: -335 | AG40: =AH40-AF40 -> -342 | AH40: -677 | AI40: -157 | AJ40: =AM40-AI40 -> 215 | AK40: =-204-AM40 -> -262 | AL40: =AN40-AK40 -> -87 | AM40: 58 | AN40: =AO40-AM40 -> -349 | AO40: -291 | AP40: -37 | AQ40: =+AT40-AP40 -> -317 | AR40: -199 | AS40: =AU40-AR40 -> -1140 | AT40: -354 | AU40: =AV40-AT40 -> -1339 | AV40: -1693 | AW40: 41 | AX40: =+BA40-AW40 -> -233 | AY40: =-376-BA40 -> -184 | AZ40: =BB40-AY40 -> -1086 | BA40: -192 | BB40: =BC40-BA40 -> -1270 | BC40: -1462 | BD40: 46 | BE40: =BH40-BD40 -> -370 | BF40: =-810-BH40 -> -486 | BG40: =BI40-BF40 -> -464 | BH40: -324 | BI40: =BJ40-BH40 -> -950 | BJ40: -1274 | BK40: -94 | BL40: =BO40-BK40 -> -583 | BM40: =-1024-BO40 -> -347 | BN40: =BP40-BM40 -> -1365 | BO40: -677 | BP40: =BQ40-BO40 -> -1712 | BQ40: -2389 | BR40: -94 | BS40: 158 | BT40: =197-BV40 -> 133 | BU40: =BW40-BT40 -> -236 | BV40: =BR40+BS40 -> 64 | BW40: =BX40-BV40 -> -103 | BX40: -39 | BY40: -175 | BZ40: =CC40-BY40 -> -318 | CA40: =-676-BY40-BZ40 -> -183 | CB40: =CD40-CA40 -> -177 | CC40: -493 | CD40: =CE40-CC40 -> -360 | CE40: -853 | CF40: -402 | CG40: =+CJ40-CF40 -> -440 | CH40: =-768-CF40-CG40 -> 74 | CI40: =CK40-CH40 -> -171 | CJ40: -842 | CK40: =CL40-CJ40 -> -97 | CL40: -939 | CM40: -101 | CN40: =CQ40-CM40 -> -436 | CO40: -192 | CP40: =CR40-CO40 -> -427 | CQ40: -537 | CR40: =CS40-CQ40 -> -619 | CS40: -1156 | CT40: -286 | CU40: =CX40-CT40 -> -329 | CV40: -312 | CW40: =CY40-CV40 -> -420 | CX40: -615 | CY40: =CZ40-CX40 -> -732 | CZ40: -1347 | DA40: -349 | DB40: =DE40-DA40 -> -314 | DC40: -547 | DD40: =DF40-DC40 -> -180 | DE40: -663 | DF40: =DG40-DE40 -> -727 | DG40: -1390 | DH40: -139 | DI40: =DL40-DH40 -> -613 | DJ40: =(DJ38/DN38)*DN40 -> -482.95064 | DK40: =DM40-DJ40 -> -701.95016 | DL40: -752 | DM40: =DN40-DL40 -> -1184.9008 | DN40: =DN38*-DN41 -> -1936.9008 | DO40: =(DO38/DU38)*DU40 -> -520.48735 | DP40: =DS40-DO40 -> -586.83705 | DQ40: =(DQ38/DU38)*DU40 -> -581.12207 | DR40: =DT40-DQ40 -> -652.68093 | DS40: =(DS38/DU38)*DU40 -> -1107.3244 | DT40: =DU40-DS40 -> -1233.803 | DU40: =DU38*-DU41 -> -2341.1274 | DV40: =(DV38/EB38)*EB40 -> -657.27101 | DW40: =DZ40-DV40 -> -727.75009 | DX40: =(DX38/EB38)*EB40 -> -723.18469 | DY40: =EA40-DX40 -> -821.35476 | DZ40: =(DZ38/EB38)*EB40 -> -1385.0211 | EA40: =EB40-DZ40 -> -1544.5394 | EB40: =EB38*-EB41 -> -2929.5606 | EC40: =(EC38/EI38)*EI40 -> -753.00744 | ED40: =EG40-EC40 -> -784.728 | EE40: =(EE38/EI38)*EI40 -> -779.94236 | EF40: =EH40-EE40 -> -886.86337 | EG40: =(EG38/EI38)*EI40 -> -1537.7354 | EH40: =EI40-EG40 -> -1666.8057 | EI40: =EI38*-EI41 -> -3204.5412 | EJ40: =(EJ38/EP38)*EP40 -> -805.00747 | EK40: =EN40-EJ40 -> -838.54672 | EL40: =(EL38/EP38)*EP40 -> -836.39497 | EM40: =EO40-EL40 -> -942.52846 | EN40: =(EN38/EP38)*EP40 -> -1643.5542 | EO40: =EP40-EN40 -> -1778.9234 | EP40: =EP38*-EP41 -> -3422.4776
A41: Effective tax rate | C41: =-C40/(C38-C25-C26) -> 0.40338379 | D41: =-D40/(D38-D25-D26) -> 0.32802768 | E41: =-E40/(E38-E25-E26) -> 0.35225464 | F41: =-F40/(F38-F25-F26) -> 0.32544379 | G41: 0.31 | H41: =-H40/(H38-H25-H26) -> 0.43931398 | I41: =-I40/(I38-I25-I26) -> 0.30565217 | J41: =-J40/(J38-J25-J26) -> 0.22633745 | K41: =-K40/(K38-K25-K26) -> 0.29901961 | L41: =-L40/(L38-L25-L26) -> 0.24808362 | M41: =-M40/(M38-M25-M26) -> 0.26489676 | N41: =-N40/(N38-N25-N26) -> 0.25163399 | O41: =-O40/(O38-O25-O26) -> 0.2798913 | ... DM41: =-DM40/(DM38-DM25-DM26) -> 0.24600341 | DN41: 0.25 | DO41: =-DO40/(DO38-DO25-DO26) -> 0.25 | DP41: =-DP40/(DP38-DP25-DP26) -> 0.25 | DQ41: =-DQ40/(DQ38-DQ25-DQ26) -> 0.25 | DR41: =-DR40/(DR38-DR25-DR26) -> 0.25 | DS41: =-DS40/(DS38-DS25-DS26) -> 0.25 | DT41: =-DT40/(DT38-DT25-DT26) -> 0.25 | DU41: =DN41 -> 0.25 | DV41: =-DV40/(DV38-DV25-DV26) -> 0.25 | DW41: =-DW40/(DW38-DW25-DW26) -> 0.25 | DX41: =-DX40/(DX38-DX25-DX26) -> 0.25 | DY41: =-DY40/(DY38-DY25-DY26) -> 0.25 | DZ41: =-DZ40/(DZ38-DZ25-DZ26) -> 0.25 | EA41: =-EA40/(EA38-EA25-EA26) -> 0.25 | EB41: =DU41 -> 0.25 | EC41: =-EC40/(EC38-EC25-EC26) -> 0.25 | ED41: =-ED40/(ED38-ED25-ED26) -> 0.25 | EE41: =-EE40/(EE38-EE25-EE26) -> 0.25 | EF41: =-EF40/(EF38-EF25-EF26) -> 0.25 | EG41: =-EG40/(EG38-EG25-EG26) -> 0.25 | EH41: =-EH40/(EH38-EH25-EH26) -> 0.25 | EI41: =EB41 -> 0.25 | EJ41: =-EJ40/(EJ38-EJ25-EJ26) -> 0.25 | EK41: =-EK40/(EK38-EK25-EK26) -> 0.25 | EL41: =-EL40/(EL38-EL25-EL26) -> 0.25 | EM41: =-EM40/(EM38-EM25-EM26) -> 0.25 | EN41: =-EN40/(EN38-EN25-EN26) -> 0.25 | EO41: =-EO40/(EO38-EO25-EO26) -> 0.25 | EP41: =EI41 -> 0.25
A42: Earnings before minorities | C42: =+C38+C40 -> -266 | D42: =+D38+D40 -> 404 | E42: =+E38+E40 -> 1221 | F42: =+F38+F40 -> 1710 | G42: =+G38+G40 -> 115 | H42: =+H38+H40 -> -437 | I42: =+I38+I40 -> 1597 | J42: =+J38+J40 -> -752 | ... EP42: =+EP38+EP40 -> 10267.433
D43: =(D42-C42)/$D$73 -> 0.83649908
A44: Minority interests | C44: -33 | D44: -66 | E44: -18 | F44: -34 | G44: -16 | H44: -9 | I44: -25 | J44: -11 | K44: -19 | L44: -4 | M44: -1 | N44: -2 | O44: =R44-N44 -> 1 | P44: =-2-R44 -> -1 | Q44: =S44-P44 -> -8 | R44: -1 | S44: =T44-R44 -> -9 | T44: -10 | U44: 3 | V44: =Y44-U44 -> -9 | W44: =-9-Y44 -> -3 | X44: =Z44-W44 -> 2 | Y44: -6 | Z44: =AA44-Y44 -> -1 | AA44: -7 | AB44: -3 | AC44: =AF44-AB44 -> -4 | AD44: =-2-AF44 -> 5 | AE44: =AG44-AD44 -> 0 | AF44: -7 | AG44: =AH44-AF44 -> 5 | AH44: -2 | AI44: 1 | AJ44: =AM44-AI44 -> -1 | AK44: =1-AM44 -> 1 | AL44: =AN44-AK44 -> -6 | AM44: 0 | AN44: =AO44-AM44 -> -5 | AO44: -5 | AP44: -1 | AQ44: =+AT44-AP44 -> 1 | AR44: 0 | AS44: =AU44-AR44 -> -4 | AT44: 0 | AU44: =AV44-AT44 -> -4 | AV44: -4 | AW44: -1 | AX44: =+BA44-AW44 -> 1 | AY44: =0-BA44 -> 0 | AZ44: =BB44-AY44 -> -3 | BA44: 0 | BB44: =BC44-BA44 -> -3 | BC44: -3 | BD44: -1 | BE44: =BH44-BD44 -> 4 | BF44: =-7-BH44 -> -10 | BG44: =BI44-BF44 -> 50 | BH44: 3 | BI44: =BJ44-BH44 -> 40 | BJ44: 43 | BK44: -4 | BL44: =BO44-BK44 -> 0 | BM44: =12-BO44 -> 16 | BN44: =BP44-BM44 -> -49 | BO44: -4 | BP44: =BQ44-BO44 -> -33 | BQ44: -37 | BR44: 11 | BS44: =BV44-BR44 -> -6 | BT44: =14-BV44 -> 9 | BU44: =BW44-BT44 -> 22 | BV44: 5 | BW44: =BX44-BV44 -> 31 | BX44: 36 | BY44: 16 | BZ44: =CC44-BY44 -> 11 | CA44: =46-BY44-BZ44 -> 19 | CB44: =CD44-CA44 -> -7 | CC44: 27 | CD44: =CE44-CC44 -> 12 | CE44: 39 | CF44: 26 | CG44: =+CJ44-CF44 -> 31 | CH44: =90-CF44-CG44 -> 33 | CI44: =CK44-CH44 -> 21 | CJ44: 57 | CK44: =CL44-CJ44 -> 54 | CL44: 111 | CM44: 28 | CN44: =CQ44-CM44 -> 46 | CO44: 44 | CP44: =CR44-CO44 -> 58 | CQ44: 74 | CR44: =CS44-CQ44 -> 102 | CS44: 176 | CT44: 43 | CU44: =CX44-CT44 -> 49 | CV44: 45 | CW44: =CY44-CV44 -> 17 | CX44: 92 | CY44: =CZ44-CX44 -> 62 | CZ44: 154 | DA44: 48 | DB44: =DE44-DA44 -> 33 | DC44: 31 | DD44: =DF44-DC44 -> 149 | DE44: 81 | DF44: =DG44-DE44 -> 180 | DG44: 261 | DH44: 35 | DI44: =DL44-DH44 -> 29 | DJ44: =DM44/2 -> 93 | DK44: =DM44-DJ44 -> 93 | DL44: 64 | DM44: =DN44-DL44 -> 186 | DN44: 250 | DO44: =DS44/2 -> 62.5 | DP44: =DS44-DO44 -> 62.5 | DQ44: =DT44/2 -> 62.5 | DR44: =DT44-DQ44 -> 62.5 | DS44: =DU44/2 -> 125 | DT44: =DU44-DS44 -> 125 | DU44: =DN44 -> 250 | DV44: =DZ44/2 -> 62.5 | DW44: =DZ44-DV44 -> 62.5 | DX44: =EA44/2 -> 62.5 | DY44: =EA44-DX44 -> 62.5 | DZ44: =EB44/2 -> 125 | EA44: =EB44-DZ44 -> 125 | EB44: =DU44 -> 250 | EC44: =EG44/2 -> 62.5 | ED44: =EG44-EC44 -> 62.5 | EE44: =EH44/2 -> 62.5 | EF44: =EH44-EE44 -> 62.5 | EG44: =EI44/2 -> 125 | EH44: =EI44-EG44 -> 125 | EI44: =EB44 -> 250 | EJ44: =EN44/2 -> 62.5 | EK44: =EN44-EJ44 -> 62.5 | EL44: =EO44/2 -> 62.5 | EM44: =EO44-EL44 -> 62.5 | EN44: =EP44/2 -> 125 | EO44: =EP44-EN44 -> 125 | EP44: =EI44 -> 250
A46: Net income (loss) reported | C46: =+C42+C44 -> -299 | D46: =+D42+D44 -> 338 | E46: =+E42+E44 -> 1203 | F46: =+F42+F44 -> 1676 | G46: =+G42+G44 -> 99 | H46: =+H42+H44 -> -446 | I46: =+I42+I44 -> 1572 | J46: =+J42+J44 -> -763 | ... EP46: =+EP42+EP44 -> 10517.433
A47: Reported Basic EPS | C47: =+C46/C70 -> -0.37183649 | D47: =+D46/D70 -> 0.42199506 | E47: =+E46/E70 -> 1.501807 | F47: =+F46/F70 -> 2.11014 | G47: =+G46/G70 -> 0.12365248 | H47: =+H46/H70 -> -0.55914825 | I47: =+I46/I70 -> 1.9480066 | J47: =+J46/J70 -> -0.94232548 | ... EP47: =+EP46/EP70 -> 13.677252
A48: Reported Diluted EPS | C48: =+C46/C73 -> -0.37183649 | D48: =+D46/D73 -> 0.42199506 | E48: =+E46/E73 -> 1.4961144 | F48: =+F46/F73 -> 2.0944336 | G48: =+G46/G73 -> 0.123086 | H48: =+H46/H73 -> -0.55366009 | I48: =+I46/I73 -> 1.9465155 | J48: =+J46/J73 -> -0.94059332 | ... AU48: =+AU46/AU73 -> 1.7566489 | AV48: =(AV46+7)/AV73 -> 3.6956185 | AW48: =+AW46/AW73 -> 0.52559256 | AX48: =+AX46/AX73 -> 0.8752033 | AY48: =+AY46/AY73 -> 0.39366372 | AZ48: =+AZ46/AZ73 -> 1.2347188 | BA48: =+BA46/BA73 -> 1.4010379 | BB48: =+BB46/BB73 -> 1.6284263 | BC48: =(BC46+7)/BC73 -> 3.0386196 | BD48: =+BD46/BD73 -> 0.36279283 | BE48: =+BE46/BE73 -> 0.27322012 | BF48: =+BF46/BF73 -> 1.2239545 | BG48: =+BG46/BG73 -> 2.0467137 | BH48: =+BH46/BH73 -> 0.63603985 | BI48: =+BI46/BI73 -> 3.2708458 | BJ48: =(BJ46+7)/BJ73 -> 3.9196201 | BK48: =+BK46/BK73 -> 0.051176663 | BL48: =+BL46/BL73 -> 1.4779038 | BM48: =+BM46/BM73 -> 1.2619957 | BN48: =+BN46/BN73 -> -4.6683705 | BO48: =+BO46/BO73 -> 1.5302289 | BP48: =+BP46/BP73 -> -3.3154376 | BQ48: =+BQ46/BQ73 -> -1.7528058 | BR48: =+BR46/BR73 -> -0.61485459 | ... EP48: =+EP46/EP73 -> 13.653833
A50: Reconciliation (For NI Reported and NI pre goodwill imp & exc) | K50: 29.5 | L50: 71 | M50: 43 | N50: 7 | O50: =R50-N50 -> 6 | P50: =22-R50 -> 9 | Q50: =S50-P50 -> 20 | R50: 13 | S50: =T50-R50 -> 29 | T50: 42 | U50: 7 | V50: =Y50-U50 -> 7 | W50: =25-Y50 -> 11 | X50: =Z50-W50 -> 8 | Y50: 14 | Z50: =AA50-Y50 -> 19 | AA50: 33 | AB50: 6 | AC50: =AF50-AB50 -> 7 | AD50: =17-AF50 -> 4 | AE50: =AG50-AD50 -> 0 | AF50: 13 | AG50: =AH50-AF50 -> 4 | AH50: 17 | AI50: =-AI24-AI26 -> 0 | AJ50: =-AJ24-AJ26 -> 0 | AK50: =-AK24-AK26 -> 0 | AL50: =-AL24-AL26 -> 0 | AM50: =-AM24-AM26 -> 0 | AN50: =-AN24-AN26 -> 0 | AO50: =-AO24-AO26 -> 0 | AP50: =-AP24-AP26 -> 0 | ... DB50: =-DB24-DB26 -> 0 | DC50: =DF50/2 -> 0 | DD50: =-DD24-DD26 -> 0 | DE50: =-DE24-DE26 -> 0 | DF50: =-DF24-DF26 -> 0 | DG50: =-DG24-DG26 -> 0 | DH50: =-DH24-DH26 -> 0 | DI50: =-DI24-DI26 -> 0 | DJ50: =DM50/2 -> 0 | DK50: =-DK24-DK26 -> 0 | DL50: =-DL24-DL26 -> 0 | DM50: =-DM24-DM26 -> 0 | DN50: =-DN24-DN26 -> 0 | DO50: =DS50/2 -> 0 | DP50: =-DP24-DP26 -> 0 | DQ50: =DT50/2 -> 0 | DR50: =-DR24-DR26 -> 0 | DS50: =DU50/2 -> 0 | DT50: =-DT24-DT26 -> 0 | DU50: =-DU24-DU26 -> 0 | DV50: =DZ50/2 -> 0 | DW50: =-DW24-DW26 -> 0 | DX50: =EA50/2 -> 0 | DY50: =-DY24-DY26 -> 0 | DZ50: =EB50/2 -> 0 | EA50: =-EA24-EA26 -> 0 | EB50: =-EB24-EB26 -> 0 | EC50: =EG50/2 -> 0 | ED50: =-ED24-ED26 -> 0 | EE50: =EH50/2 -> 0 | EF50: =-EF24-EF26 -> 0 | EG50: =EI50/2 -> 0 | EH50: =-EH24-EH26 -> 0 | EI50: =-EI24-EI26 -> 0 | EJ50: =EN50/2 -> 0 | EK50: =-EK24-EK26 -> 0 | EL50: =EO50/2 -> 0 | EM50: =-EM24-EM26 -> 0 | EN50: =EP50/2 -> 0 | EO50: =-EO24-EO26 -> 0 | EP50: =-EP24-EP26 -> 0
A51: Net Income (pre goodwill impairments and exceptionals) | K51: =K46+K50 -> 582.5 | L51: =L46+L50 -> 1104 | M51: =M46+M50 -> 1271 | N51: =N46+N50 -> 234 | O51: =O46+O50 -> 537 | P51: =P46+P50 -> 454 | Q51: =Q46+Q50 -> 290 | R51: =R46+R50 -> 771 | ... EP51: =EP46+EP50 -> 10517.433
A53: Adjustments to net income:
A54: One-offs in EBIT (adj. from reported to clean) | J54: 2470 | K54: 113 | L54: 98 | M54: 820 | N54: =-Divisional!N48 -> 145 | O54: =-Divisional!O48 -> -9 | P54: =-Divisional!P48 -> 53 | Q54: =-Divisional!Q48 -> 724 | R54: =-Divisional!R48 -> 136 | S54: =-Divisional!S48 -> 777 | T54: =519+292+102 -> 913 | U54: =-Divisional!U48 -> -19 | V54: =-Divisional!V48 -> -51 | W54: =-Divisional!W48 -> 77 | X54: =-Divisional!X48 -> 19 | Y54: =-Divisional!Y48 -> -70 | Z54: =-Divisional!Z48 -> 96 | AA54: =511-343-142 -> 26 | AB54: =-Divisional!AB48 -> -590 | AC54: =-Divisional!AC48 -> 244 | AD54: =-Divisional!AD48 -> 204 | AE54: =-Divisional!AE48 -> 188 | AF54: =-Divisional!AF48 -> -346 | AG54: =-Divisional!AG48 -> 392 | AH54: 46 | AI54: =-Divisional!AI48 -> 136 | AJ54: =-Divisional!AJ48 -> -308 | AK54: =-Divisional!AK48 -> 224 | AL54: =-Divisional!AL48 -> 1645 | AM54: =-Divisional!AM48 -> -172 | AN54: =-Divisional!AN48 -> 1869 | AO54: 1697 | AP54: =-Divisional!AP48 -> -612 | AQ54: =-Divisional!AQ48 -> -80 | AR54: =-Divisional!AR48 -> 176 | AS54: =-Divisional!AS48 -> 1348 | AT54: =-Divisional!AT48 -> -692 | AU54: =-Divisional!AU48 -> 1524 | AV54: 832 | AW54: =-Divisional!AW48 -> -594 | AX54: =-Divisional!AX48 -> -64 | AY54: =-Divisional!AY48 -> 193 | AZ54: =-Divisional!AZ48 -> 990 | BA54: =-Divisional!BA48 -> -658 | BB54: =-Divisional!BB48 -> 1183 | BC54: =46+472+7 -> 525 | BD54: =-Divisional!BD48 -> -185 | BE54: =-Divisional!BE48 -> 227 | BF54: =-Divisional!BF48 -> 13 | BG54: =-Divisional!BG48 -> 731 | BH54: =-Divisional!BH48 -> 42 | BI54: =-Divisional!BI48 -> 744 | BJ54: 786 | BK54: =-Divisional!BR48 -> 368 | BL54: =-Divisional!BS48 -> 68 | BM54: =-Divisional!BT48 -> 266 | BN54: =-Divisional!BU48 -> 4905 | BO54: =-Divisional!BV48 -> 436 | BP54: =-Divisional!BW48 -> 5171 | BQ54: =-Divisional!BQ48 -> 5607 | BR54: =-Divisional!BY48 -> 202 | BS54: =-Divisional!BZ48 -> 412 | BT54: =-Divisional!CA48 -> 1446 | BU54: =-Divisional!CB48 -> 156 | BV54: =-Divisional!CC48 -> 614 | BW54: =-Divisional!CD48 -> 1602 | BX54: =-Divisional!CE48 -> 2216 | BY54: =-Divisional!CF48 -> 232 | ... EP54: =-Divisional!EW48 -> 0
A55: One offs in Financial result | J55: 93 | K55: -41 | L55: -59 | M55: -12 | N55: 150 | O55: =R55-N55 -> 22 | P55: =71-R55 -> -101 | Q55: =S55-P55 -> 36 | R55: 172 | S55: =T55-R55 -> -65 | T55: 107 | U55: -28 | V55: =Y55-U55 -> -1 | W55: =178-Y55 -> 207 | X55: =Z55-W55 -> 163 | Y55: -29 | Z55: =AA55-Y55 -> 370 | AA55: 341 | AB55: 229 | AC55: =AF55-AB55 -> -129 | AD55: =156-AF55 -> 56 | AE55: =AG55-AD55 -> 62 | AF55: 100 | AG55: =AH55-AF55 -> 118 | AH55: 218 | AI55: -284 | AJ55: =AM55-AI55 -> 291 | AK55: =73-AM55 -> 66 | AL55: =AN55-AK55 -> 554 | AM55: 7 | AN55: =AO55-AM55 -> 620 | AO55: 627 | AP55: 97 | AQ55: =+AT55-AP55 -> -374 | AR55: =-403-AT55 -> -126 | AS55: =AU55-AR55 -> -1135 | AT55: -277 | AU55: =AV55-AT55 -> -1261 | AV55: -1538 | AW55: 97 | AX55: =+BA55-AW55 -> -374 | AY55: =-403-BA55 -> -126 | AZ55: =BB55-AY55 -> -1135 | BA55: =-140-137 -> -277 | BB55: =BC55-BA55 -> -1261 | BC55: -1538 | BD55: -117 | BE55: =BH55-BD55 -> 282 | BF55: =154-BH55 -> -11 | BG55: =BI55-BF55 -> 333 | BH55: 165 | BI55: =BJ55-BH55 -> 322 | BJ55: 487 | BK55: -5 | BL55: =BO55-BK55 -> 94 | BM55: =72-BO55 -> -17 | BN55: =BP55-BM55 -> 46 | BO55: 89 | BP55: =BQ55-BO55 -> 29 | BQ55: 118 | BR55: 423 | BS55: =BV55-BR55 -> -136 | BT55: =476-BV55 -> 189 | BU55: =BW55-BT55 -> -152 | BV55: 287 | BW55: =BX55-BV55 -> 37 | BX55: 324 | BY55: -148 | BZ55: =CC55-BY55 -> -8 | CA55: =-82-BY55-BZ55 -> 74 | CB55: =CD55-CA55 -> 132 | CC55: -156 | CD55: =CE55-CC55 -> 206 | CE55: 50 | CF55: -243 | CG55: =+CJ55-CF55 -> 3 | CH55: =114-CF55-CG55 -> 354 | CI55: =CK55-CH55 -> -88 | CJ55: -240 | CK55: =CL55-CJ55 -> 266 | CL55: 26 | CM55: -181 | CN55: =CQ55-CM55 -> 24 | CO55: =-231-CM55-CN55 -> -74 | CP55: =CR55-CO55 -> 37 | CQ55: -157 | CR55: =CS55-CQ55 -> -37 | CS55: -194 | CT55: -225 | CU55: =CX55-CT55 -> 305 | CV55: =35-CT55-CU55 -> -45 | CW55: =CY55-CV55 -> -171 | CX55: 80 | CY55: =CZ55-CX55 -> -216 | CZ55: -136 | DA55: -593 | DB55: =DE55-DA55 -> 113 | DC55: 99 | DD55: =DF55-DC55 -> 321 | DE55: -480 | DF55: =DG55-DE55 -> 420 | DG55: =710-770 -> -60 | DH55: -453 | DI55: =DL55-DH55 -> 272 | DJ55: =-DJ34-DJ33 -> 0 | DK55: =DM55-DJ55 -> 0 | DL55: -181 | DM55: =DN55-DL55 -> 0 | DN55: =-DN34-DN33 -> -181 | DO55: =-DO34-DO33 -> 0 | DP55: =DS55-DO55 -> 0 | DQ55: =-DQ34-DQ33 -> 0 | DR55: =DT55-DQ55 -> 0 | DS55: =-DS34-DS33 -> 0 | DT55: =DU55-DS55 -> 0 | DU55: =-DU34-DU33 -> 0 | DV55: =-DV34-DV33 -> 0 | DW55: =DZ55-DV55 -> 0 | DX55: =-DX34-DX33 -> 0 | DY55: =EA55-DX55 -> 0 | DZ55: =-DZ34-DZ33 -> 0 | EA55: =EB55-DZ55 -> 0 | EB55: =-EB34-EB33 -> 0 | EC55: =-EC34-EC33 -> 0 | ED55: =EG55-EC55 -> 0 | EE55: =-EE34-EE33 -> 0 | EF55: =EH55-EE55 -> 0 | EG55: =-EG34-EG33 -> 0 | EH55: =EI55-EG55 -> 0 | EI55: =-EI34-EI33 -> 0 | EJ55: =-EJ34-EJ33 -> 0 | EK55: =EN55-EJ55 -> 0 | EL55: =-EL34-EL33 -> 0 | EM55: =EO55-EL55 -> 0 | EN55: =-EN34-EN33 -> 0 | EO55: =EP55-EN55 -> 0 | EP55: =-EP34-EP33 -> 0
