Workbook
Name _div08: [1]OVERVIEW!$AY$74
Name _div09: [1]OVERVIEW!$AZ$74
Name _div10: [1]OVERVIEW!$BA$74
Name _ShH3: #REF!
Name A_ALL_AIR.PA: #REF!
Name A_ALL_AIR.PA: #REF!
Name A_ALL_AIR.PA_: #REF!
Name A_ALL_AIR.PA_: #REF!
Name A_ALL_BAES.L_: #REF!
Name A_ALL_BAES.L_: #REF!
Name A_ALL_COB.L: '[4]COB.L_Annotation_Sheet'!$A$1:$AV$348
Name A_ALL_COB.L: #REF!
Name A_ALL_KEYWORDS_TYPE_ScalarContributed_EQTY_200000267: [5]ATCOa.ST_Annotation_Sheet!$562:$564,[5]ATCOa.ST_Annotation_Sheet!$510:$519
Name A_ALL_KEYWORDS_TYPE_ScalarContributed_EQTY_200003162: [6]BAES.L_Annotation_Sheet!$339:$345,[6]BAES.L_Annotation_Sheet!$384:$386
Name A_ALL_KEYWORDS_TYPE_ScalarContributed_EQTY_200003162: #REF!,#REF!
Name A_ALL_KEYWORDS_TYPE_ScalarContributed_EQTY_200003170: #REF!,#REF!
Name A_ALL_KEYWORDS_TYPE_ScalarContributed_EQTY_200003173: #REF!,#REF!
Name A_ALL_KEYWORDS_TYPE_ScalarContributed_EQTY_200003183: #REF!,#REF!
Name A_ALL_KEYWORDS_TYPE_ScalarContributed_EQTY_200003821: #REF!,#REF!
Name A_ALL_KEYWORDS_TYPE_ScalarContributed_EQTY_200004285: #REF!,#REF!
Name A_ALL_KEYWORDS_TYPE_ScalarContributed_EQTY_200005121: [8]EAD.PA_Annotation_Sheet!$339:$348,[8]EAD.PA_Annotation_Sheet!$387:$389
Name A_ALL_KEYWORDS_TYPE_ScalarContributed_EQTY_200007513: #REF!,#REF!
Name A_ALL_KEYWORDS_TYPE_ScalarContributed_EQTY_200009618: #REF!,#REF!
Name A_ALL_KEYWORDS_TYPE_ScalarContributed_EQTY_200009619: '[4]COB.L_Annotation_Sheet'!$298:$305,'[4]COB.L_Annotation_Sheet'!$346:$348
Name A_ALL_KEYWORDS_TYPE_ScalarContributed_EQTY_200009619: #REF!,#REF!
Name A_ALL_KEYWORDS_TYPE_ScalarContributed_EQTY_200009620: [9]MGGT.L_Annotation_Sheet!$344:$350,[9]MGGT.L_Annotation_Sheet!$389:$391
Name A_ALL_KEYWORDS_TYPE_ScalarContributed_EQTY_200009620: #REF!,#REF!
Name A_ALL_KEYWORDS_TYPE_ScalarContributed_EQTY_200011295: #REF!,#REF!
Name A_ALL_KEYWORDS_TYPE_ScalarContributed_ISSR_208001092: #REF!,#REF!
Name A_ALL_KEYWORDS_TYPE_ScalarContributed_ISSR_208001095: #REF!,#REF!
Name A_ALL_KEYWORDS_TYPE_ScalarContributed_ISSR_208001100: #REF!,#REF!
Name A_ALL_KEYWORDS_TYPE_ScalarContributed_ISSR_208001219: #REF!,#REF!,#REF!,#REF!,#REF!,#REF!,#REF!,#REF!
Name A_ALL_KEYWORDS_TYPE_ScalarContributed_ISSR_208001433: #REF!,#REF!
Name A_ALL_KEYWORDS_TYPE_ScalarContributed_ISSR_208001433: [10]AIR.PA_Annotation_Sheet!$9:$9,[10]AIR.PA_Annotation_Sheet!$42:$42
Name A_ALL_KEYWORDS_TYPE_ScalarContributed_ISSR_208006659: #REF!,#REF!,#REF!
Name A_ALL_KEYWORDS_TYPE_ScalarContributed_ISSR_208007415: #REF!,#REF!
Name A_ALL_KEYWORDS_TYPE_ScalarContributed_ISSR_208008646: #REF!,#REF!
Name A_ALL_KEYWORDS_TYPE_ScalarReference_EQTY_200007513: #REF!
Name A_ALL_KEYWORDS_TYPE_ScalarReference_EQTY_200007513: #REF!
Name A_ALL_KEYWORDS_TYPE_ScalarReference_ISSR_208002861: #REF!
Name A_ALL_KEYWORDS_TYPE_ScalarReference_ISSR_208002861: #REF!
Name A_ALL_KEYWORDS_TYPE_Vector_EQTY_200000267: [5]ATCOa.ST_Annotation_Sheet!$537:$552,[5]ATCOa.ST_Annotation_Sheet!$554:$556,[5]ATCOa.ST_Annotation_Sheet!$558:$558,[5]ATCOa.ST_Annotation_Sheet!$560:$560,[5]ATCOa.ST_Annotation_Sheet!$521:$535
Name A_ALL_KEYWORDS_TYPE_Vector_EQTY_200003162: [6]BAES.L_Annotation_Sheet!$347:$357,[6]BAES.L_Annotation_Sheet!$359:$374,[6]BAES.L_Annotation_Sheet!$376:$378,[6]BAES.L_Annotation_Sheet!$380:$380,[6]BAES.L_Annotation_Sheet!$382:$382
Name A_ALL_KEYWORDS_TYPE_Vector_EQTY_200003162: #REF!,#REF!,#REF!,#REF!,#REF!
Name A_ALL_KEYWORDS_TYPE_Vector_EQTY_200003169: #REF!,#REF!,#REF!,#REF!,#REF!
Name A_ALL_KEYWORDS_TYPE_Vector_EQTY_200003170: #REF!,#REF!,#REF!,#REF!,#REF!
Name A_ALL_KEYWORDS_TYPE_Vector_EQTY_200003173: #REF!,#REF!,#REF!,#REF!,#REF!
Name A_ALL_KEYWORDS_TYPE_Vector_EQTY_200003183: #REF!,#REF!,#REF!,#REF!,#REF!
Name A_ALL_KEYWORDS_TYPE_Vector_EQTY_200003821: #REF!,#REF!,#REF!,#REF!,#REF!
Name A_ALL_KEYWORDS_TYPE_Vector_EQTY_200004285: #REF!,#REF!,#REF!,#REF!,#REF!
Name A_ALL_KEYWORDS_TYPE_Vector_EQTY_200005121: #REF!,#REF!,#REF!,#REF!,#REF!
Name A_ALL_KEYWORDS_TYPE_Vector_EQTY_200005121: [8]EAD.PA_Annotation_Sheet!$350:$360,[8]EAD.PA_Annotation_Sheet!$362:$377,[8]EAD.PA_Annotation_Sheet!$379:$381,[8]EAD.PA_Annotation_Sheet!$383:$383,[8]EAD.PA_Annotation_Sheet!$385:$385
Name A_ALL_KEYWORDS_TYPE_Vector_EQTY_200007513: #REF!,#REF!,#REF!,#REF!,#REF!
Name A_ALL_KEYWORDS_TYPE_Vector_EQTY_200008448: #REF!,#REF!,#REF!,#REF!,#REF!
Name A_ALL_KEYWORDS_TYPE_Vector_EQTY_200009618: #REF!,#REF!,#REF!,#REF!,#REF!
Name A_ALL_KEYWORDS_TYPE_Vector_EQTY_200009619: '[4]COB.L_Annotation_Sheet'!$307:$317,'[4]COB.L_Annotation_Sheet'!$320:$336,'[4]COB.L_Annotation_Sheet'!$338:$340,'[4]COB.L_Annotation_Sheet'!$342:$342,'[4]COB.L_Annotation_Sheet'!$344:$344
Name A_ALL_KEYWORDS_TYPE_Vector_EQTY_200009619: #REF!,#REF!,#REF!,#REF!,#REF!
Name A_ALL_KEYWORDS_TYPE_Vector_EQTY_200009620: [9]MGGT.L_Annotation_Sheet!$352:$362,[9]MGGT.L_Annotation_Sheet!$364:$379,[9]MGGT.L_Annotation_Sheet!$381:$383,[9]MGGT.L_Annotation_Sheet!$385:$385,[9]MGGT.L_Annotation_Sheet!$387:$387
Name A_ALL_KEYWORDS_TYPE_Vector_EQTY_200009620: #REF!,#REF!,#REF!,#REF!,#REF!
Name A_ALL_KEYWORDS_TYPE_Vector_EQTY_200011295: #REF!,#REF!,#REF!,#REF!,#REF!

Sheet __FDSCACHE__
B1: This sheet contains FactSet XML data for use with this workbook's =FDS codes. Modifying the worksheet's contents may damage the workbook's =FDS functionality.

Sheet Cover Page
A2: GOLDMAN SACHS
A3: GLOBAL INVESTMENT RESEARCH
A4: Multi-Industry
B6: AIR.PA
B7: Published as of | C7: 46260 | I7: Rating Suspended
B9: Team Contacts:
B10: Primary Analyst
B11: Sam Burgess, sam.burgess@gs.com, +44 20 7774-9651 Goldman Sachs International
B12: Supporting Analysts
B13: Jubril Moronfolu, jubril.x.moronfolu@gs.com, +44 20 7051-0985 Goldman Sachs International
B14: Milind Sikchi, milind.sikchi@gs.com, +1 332 245-7985, Goldman Sachs International

Sheet DCF Valuation
B2: 12m forward date:
B3: 46625
C5: 2026 | D5: 2027 | E5: =D5+1 -> 2028 | F5: =E5+1 -> 2029 | G5: =F5+1 -> 2030 | H5: =G5+1 -> 2031 | I5: =H5+1 -> 2032 | J5: =I5+1 -> 2033 | K5: =J5+1 -> 2034 | L5: =K5+1 -> 2035 | M5: =L5+1 -> 2036
B6: Calendar year | D6: =DATE(YEAR(B3),6,1) -> 46539 | E6: =EDATE(DATE(YEAR(D6),6,1),12) -> 46905 | F6: =EDATE(DATE(YEAR(E6),6,1),12) -> 47270 | G6: =EDATE(DATE(YEAR(F6),6,1),12) -> 47635 | H6: =EDATE(DATE(YEAR(G6),6,1),12) -> 48000 | I6: =EDATE(DATE(YEAR(H6),6,1),12) -> 48366 | J6: =EDATE(DATE(YEAR(I6),6,1),12) -> 48731 | K6: =EDATE(DATE(YEAR(J6),6,1),12) -> 49096 | L6: =EDATE(DATE(YEAR(K6),6,1),12) -> 49461 | M6: =EDATE(DATE(YEAR(L6),6,1),12) -> 49827
B7: Adj. EBIT | C7: ='DCF Feed'!B4 -> 7612.6223 | D7: ='DCF Feed'!C4 -> 9281.3937 | E7: ='DCF Feed'!D4 -> 11593.857 | F7: ='DCF Feed'!E4 -> 13254.654 | G7: ='DCF Feed'!F4 -> 14127.451 | H7: ='DCF Feed'!G4 -> 14752.725 | I7: =H7*(1+I8) -> 15785.415 | J7: =I7*(1+J8) -> 16732.54 | K7: =J7*(1+K8) -> 17569.167 | L7: =K7*(1+L8) -> 18271.934 | M7: =L7*(1+M8) -> 18820.092
B8: YoY growth | D8: =D7/C7-1 -> 0.21921111 | E8: =E7/D7-1 -> 0.24915041 | F8: =F7/E7-1 -> 0.14324808 | G8: =G7/F7-1 -> 0.065848287 | H8: =H7/G7-1 -> 0.044259502 | I8: =$D$21 -> 0.07 | J8: =I8+(($M$8-$I$8)/4) -> 0.06 | K8: =J8+(($M$8-$I$8)/4) -> 0.05 | L8: =K8+(($M$8-$I$8)/4) -> 0.04 | M8: =$D$39 -> 0.03
B9: Tax Rate | C9: =-'DCF Feed'!B11 -> 0.26995769 | D9: =-'DCF Feed'!C11 -> 0.26995769 | E9: =-'DCF Feed'!D11 -> 0.26995769 | F9: =-'DCF Feed'!E11 -> 0.26995769 | G9: =-'DCF Feed'!F11 -> 0.26995769 | H9: =-'DCF Feed'!G11 -> 0.26995769 | I9: =H9 -> 0.26995769 | J9: =I9 -> 0.26995769 | K9: =J9 -> 0.26995769 | L9: =K9 -> 0.26995769 | M9: =L9 -> 0.26995769
B10: NOPAT | C10: =C7*(1-C9) -> 5557.5364 | D10: =D7*(1-D9) -> 6775.8102 | E10: =E7*(1-E9) -> 8464.006 | F10: =F7*(1-F9) -> 9676.4586 | G10: =G7*(1-G9) -> 10313.637 | H10: =H7*(1-H9) -> 10770.113 | I10: =I7*(1-I9) -> 11524.021 | J10: =J7*(1-J9) -> 12215.462 | ... M10: =M7*(1-M9) -> 13739.464
B11: D&A | C11: =INDEX('Income Statement'!153:153, MATCH(C5,'Income Statement'!2:2,0)) -> 3211.5501 | D11: =INDEX('Income Statement'!153:153, MATCH(D5,'Income Statement'!2:2,0)) -> 3469.6347 | E11: =INDEX('Income Statement'!153:153, MATCH(E5,'Income Statement'!2:2,0)) -> 3062.0877 | F11: =INDEX('Income Statement'!153:153, MATCH(F5,'Income Statement'!2:2,0)) -> 3424.6146 | G11: =INDEX('Income Statement'!153:153, MATCH(G5,'Income Statement'!2:2,0)) -> 3697.5801 | H11: =INDEX('Income Statement'!153:153, MATCH(H5,'Income Statement'!2:2,0)) -> 3879.6435
B12: Change in working capital | C12: =INDEX('Cash Flow Statement'!23:23, MATCH(C5,'Cash Flow Statement'!2:2,0)) -> 286.29731 | D12: =INDEX('Cash Flow Statement'!23:23, MATCH(D5,'Cash Flow Statement'!2:2,0)) -> 1076.5364 | E12: =INDEX('Cash Flow Statement'!23:23, MATCH(E5,'Cash Flow Statement'!2:2,0)) -> 2094.6614 | F12: =INDEX('Cash Flow Statement'!23:23, MATCH(F5,'Cash Flow Statement'!2:2,0)) -> 2770.782 | G12: =INDEX('Cash Flow Statement'!23:23, MATCH(G5,'Cash Flow Statement'!2:2,0)) -> 2833.2116 | H12: =INDEX('Cash Flow Statement'!23:23, MATCH(H5,'Cash Flow Statement'!2:2,0)) -> 986.59515
B13: Capex & Intangibles | C13: =INDEX('Cash Flow Statement'!73:73, MATCH(C5,'Cash Flow Statement'!2:2,0)) -> -4175.2212 | D13: =INDEX('Cash Flow Statement'!73:73, MATCH(D5,'Cash Flow Statement'!2:2,0)) -> -4567.2086 | E13: =INDEX('Cash Flow Statement'!73:73, MATCH(E5,'Cash Flow Statement'!2:2,0)) -> -5029.5828 | F13: =INDEX('Cash Flow Statement'!73:73, MATCH(F5,'Cash Flow Statement'!2:2,0)) -> -5340.9763 | G13: =INDEX('Cash Flow Statement'!73:73, MATCH(G5,'Cash Flow Statement'!2:2,0)) -> -5495.0067 | H13: =INDEX('Cash Flow Statement'!73:73, MATCH(H5,'Cash Flow Statement'!2:2,0)) -> -5587.5175
B14: Sustainable FCF | C14: =C10+C11+C12+C13 -> 4880.1627 | D14: =D10+D11+D12+D13 -> 6754.7727 | E14: =E10+E11+E12+E13 -> 8591.1724 | F14: =F10+F11+F12+F13 -> 10530.879 | G14: =G10+G11+G12+G13 -> 11349.422 | H14: =H10+H11+H12+H13 -> 10048.834 | I14: =I10*I15 -> 10560.886 | J14: =J10*J15 -> 10991.69 | K14: =K10*K15 -> 11328.283 | L14: =L10*L15 -> 11559.903 | M14: =M10*M15 -> 11678.544
B15: Cash Conversion (Sustainable FCF/NOPAT) | C15: =C14/C10 -> 0.87811619 | D15: =D14/D10 -> 0.99689521 | E15: =E14/E10 -> 1.0150244 | F15: =F14/F10 -> 1.0882989 | G15: =G14/G10 -> 1.1004287 | H15: =H14/H10 -> 0.9330296 | I15: =H15+(($M$15-$H$15)/5) -> 0.91642368 | J15: =I15+(($M$15-$H$15)/5) -> 0.89981776 | K15: =J15+(($M$15-$H$15)/5) -> 0.88321184 | L15: =K15+(($M$15-$H$15)/5) -> 0.86660592 | M15: =$D$22 -> 0.85
B16: WACC | D16: =$D$38 -> 0.08952 | E16: =$D$38 -> 0.08952 | F16: =$D$38 -> 0.08952 | G16: =$D$38 -> 0.08952 | H16: =$D$38 -> 0.08952 | I16: =$D$38 -> 0.08952 | J16: =$D$38 -> 0.08952 | K16: =$D$38 -> 0.08952 | ... M16: =$D$38 -> 0.08952
B17: Discount Factor | D17: =1/(1+$D$38)^((D6-$B$3)/365) -> 1.0204065 | E17: =1/(1+$D$38)^((E6-$B$3)/365) -> 0.93634524 | F17: =1/(1+$D$38)^((F6-$B$3)/365) -> 0.85941078 | G17: =1/(1+$D$38)^((G6-$B$3)/365) -> 0.78879762 | H17: =1/(1+$D$38)^((H6-$B$3)/365) -> 0.72398636 | I17: =1/(1+$D$38)^((I6-$B$3)/365) -> 0.66434422 | J17: =1/(1+$D$38)^((J6-$B$3)/365) -> 0.60975863 | K17: =1/(1+$D$38)^((K6-$B$3)/365) -> 0.55965804 | ... M17: =1/(1+$D$38)^((M6-$B$3)/365) -> 0.47135739
B18: Discounted FCF | D18: =D14*D17 -> 6892.6141 | E18: =E14*E17 -> 8044.3033 | F18: =F14*F17 -> 9050.3509 | G18: =G14*G17 -> 8952.3969 | H18: =H14*H17 -> 7275.2191 | I18: =I14*I17 -> 7016.0635 | J18: =J14*J17 -> 6702.2779 | K18: =K14*K17 -> 6339.9648 | ... M18: =M14*M17 -> 5504.768 | N18: =SUM(C18:M18) -> 71715.98
B20: Assumption
B21: Mid-term Adj. EBIT growth rate | C21: % | D21: 0.07
B22: Cash Conversion LT | C22: % | D22: 0.85
B24: DCF Valuation
B25: Risk free rate | C25: % | D25: 0.04
B26: Equity Risk premium | C26: % | D26: 0.04
B28: Beta | C28: x | D28: 1.238
B29: Cost of equity | C29: % | D29: =D25+D28*(D26) -> 0.08952
B31: Cost of debt | C31: % | D31: ='Income Statement'!V130 -> 0.052
B32: Tax | C32: % | D32: =C9 -> 0.26995769
B33: Post tax cost of debt | C33: % | D33: =D31*(1-D32) -> 0.0379622
B35: MV Equity / (MV Equity + Net Debt) | C35: % | D35: 1
B36: Net Debt / (MV Equity + Net Debt) | C36: % | D36: 0
B38: WACC | C38: % | D38: =(D29*D35)+(D36*D33) -> 0.08952
B39: Terminal growth rate | C39: % | D39: 0.03
B41: DCF Valuation
B42: Sum of discounted cash flows | C42: EUR (mn) | D42: =N18 -> 71715.98
B43: Undiscounted value of TV | C43: EUR (mn) | D43: =M14*(1+D39)/(D38-D39) -> 202098.46
B44: Discounted value of TV | C44: EUR (mn) | D44: =D43*M17 -> 95260.603
B45: Enterprise value | C45: EUR (mn) | D45: =D42+D44 -> 166976.58
B46: Net cash (debt) and lease | C46: EUR (mn) | D46: ='DCF Feed'!C8 -> 16271.149
B47: Pension underfunding | C47: EUR (mn) | D47: ='DCF Feed'!C9 -> 356
B48: Pension tax shield | C48: EUR (mn) | D48: =-D47*(D32) -> -96.104937
B49: Equity value | C49: EUR (mn) | D49: =SUM(D45:D48) -> 183507.63
B50: Number of shares | C50: Million | D50: ='DCF Feed'!C13 -> 775.10265
B51: Equity value per share | C51: EUR | D51: =MROUND(D49/D50,10) -> 240

Sheet DCF Feed
A1: EURm | B1: 2026 | C1: =B1+1 -> 2027 | D1: =C1+1 -> 2028 | E1: =D1+1 -> 2029 | F1: =E1+1 -> 2030 | G1: =F1+1 -> 2031 | H1: CAGR 26-31
A2: Sales | B2: =INDEX('Income Statement'!$14:$14,MATCH('DCF Feed'!B1,'Income Statement'!$4:$4,0)) -> 80292.715 | C2: =INDEX('Income Statement'!$14:$14,MATCH('DCF Feed'!C1,'Income Statement'!$4:$4,0)) -> 91344.172 | D2: =INDEX('Income Statement'!$14:$14,MATCH('DCF Feed'!D1,'Income Statement'!$4:$4,0)) -> 102644.55 | E2: =INDEX('Income Statement'!$14:$14,MATCH('DCF Feed'!E1,'Income Statement'!$4:$4,0)) -> 111270.34 | F2: =INDEX('Income Statement'!$14:$14,MATCH('DCF Feed'!F1,'Income Statement'!$4:$4,0)) -> 116915.04 | G2: =INDEX('Income Statement'!$14:$14,MATCH('DCF Feed'!G1,'Income Statement'!$4:$4,0)) -> 121467.77 | H2: =(G2/B2)^(1/5)-1 -> 0.086318022
A3: Growth | C3: =C2/B2-1 -> 0.1376396 | D3: =D2/C2-1 -> 0.12371206 | E3: =E2/D2-1 -> 0.08403556 | F3: =F2/E2-1 -> 0.050729576 | G3: =G2/F2-1 -> 0.038940547
A4: EBIT | B4: =INDEX('Income Statement'!$84:$84,MATCH('DCF Feed'!B1,'Income Statement'!$4:$4,0)) -> 7612.6223 | C4: =INDEX('Income Statement'!$84:$84,MATCH('DCF Feed'!C1,'Income Statement'!$4:$4,0)) -> 9281.3937 | D4: =INDEX('Income Statement'!$84:$84,MATCH('DCF Feed'!D1,'Income Statement'!$4:$4,0)) -> 11593.857 | E4: =INDEX('Income Statement'!$84:$84,MATCH('DCF Feed'!E1,'Income Statement'!$4:$4,0)) -> 13254.654 | F4: =INDEX('Income Statement'!$84:$84,MATCH('DCF Feed'!F1,'Income Statement'!$4:$4,0)) -> 14127.451 | G4: =INDEX('Income Statement'!$84:$84,MATCH('DCF Feed'!G1,'Income Statement'!$4:$4,0)) -> 14752.725 | H4: =(G4/B4)^(1/5)-1 -> 0.14147812
A5: Growth | C5: =C4/B4-1 -> 0.21921111 | D5: =D4/C4-1 -> 0.24915041 | E5: =E4/D4-1 -> 0.14324808 | F5: =F4/E4-1 -> 0.065848287 | G5: =G4/F4-1 -> 0.044259502
A6: GS Defined Op Cash Flow | B6: =INDEX('Cash Flow Statement'!75:75, MATCH('DCF Feed'!B1,'Cash Flow Statement'!2:2,0)) -> 6164.9986 | C6: =INDEX('Cash Flow Statement'!75:75, MATCH('DCF Feed'!C1,'Cash Flow Statement'!2:2,0)) -> 8652.0938 | D6: =INDEX('Cash Flow Statement'!75:75, MATCH('DCF Feed'!D1,'Cash Flow Statement'!2:2,0)) -> 11095.947 | E6: =INDEX('Cash Flow Statement'!75:75, MATCH('DCF Feed'!E1,'Cash Flow Statement'!2:2,0)) -> 13466.345 | F6: =INDEX('Cash Flow Statement'!75:75, MATCH('DCF Feed'!F1,'Cash Flow Statement'!2:2,0)) -> 14501.97 | G6: =INDEX('Cash Flow Statement'!75:75, MATCH('DCF Feed'!G1,'Cash Flow Statement'!2:2,0)) -> 13350.717 | H6: =(G6/B6)^(1/5)-1 -> 0.1671168
A7: Cash Conversion | C7: =C6/C4 -> 0.93219769 | D7: =D6/D4 -> 0.95705404 | E7: =E6/E4 -> 1.0159711 | F7: =F6/F4 -> 1.02651 | G7: =G6/G4 -> 0.90496616 | H7: =AVERAGE(C7:G7) -> 0.9673398
A8: Net Cash (debt) | B8: =INDEX('Balance Sheet'!65:65,MATCH('DCF Feed'!B$1,'Balance Sheet'!$2:$2,0)) -> 14247.337 | C8: =INDEX('Balance Sheet'!65:65,MATCH('DCF Feed'!C1,'Balance Sheet'!$2:$2,0)) -> 16271.149 | D8: =INDEX('Balance Sheet'!65:65,MATCH('DCF Feed'!D1,'Balance Sheet'!$2:$2,0)) -> 19589.53 | E8: =INDEX('Balance Sheet'!65:65,MATCH('DCF Feed'!E1,'Balance Sheet'!$2:$2,0)) -> 26112.194 | F8: =INDEX('Balance Sheet'!65:65,MATCH('DCF Feed'!F1,'Balance Sheet'!$2:$2,0)) -> 33061.678 | G8: =INDEX('Balance Sheet'!65:65,MATCH('DCF Feed'!G1,'Balance Sheet'!$2:$2,0)) -> 38198.225
A9: Pension underfunding | B9: =INDEX('Balance Sheet'!119:119,MATCH('DCF Feed'!B$1,'Balance Sheet'!$2:$2,0)) -> -144 | C9: =INDEX('Balance Sheet'!119:119,MATCH('DCF Feed'!C1,'Balance Sheet'!$2:$2,0)) -> 356 | D9: =INDEX('Balance Sheet'!119:119,MATCH('DCF Feed'!D1,'Balance Sheet'!$2:$2,0)) -> 856 | E9: =INDEX('Balance Sheet'!119:119,MATCH('DCF Feed'!E1,'Balance Sheet'!$2:$2,0)) -> 1356 | F9: =INDEX('Balance Sheet'!119:119,MATCH('DCF Feed'!F1,'Balance Sheet'!$2:$2,0)) -> 1856 | G9: =INDEX('Balance Sheet'!119:119,MATCH('DCF Feed'!G1,'Balance Sheet'!$2:$2,0)) -> 2356
A10: Launch Aid | B10: =INDEX('Balance Sheet'!125:125,MATCH('DCF Feed'!B$1,'Balance Sheet'!$2:$2,0)) -> -3874.5338 | C10: =INDEX('Balance Sheet'!125:125,MATCH('DCF Feed'!C$1,'Balance Sheet'!$2:$2,0)) -> -3886.3152 | D10: =INDEX('Balance Sheet'!125:125,MATCH('DCF Feed'!D$1,'Balance Sheet'!$2:$2,0)) -> -3900.3517 | E10: =INDEX('Balance Sheet'!125:125,MATCH('DCF Feed'!E$1,'Balance Sheet'!$2:$2,0)) -> -3916.3786 | F10: =INDEX('Balance Sheet'!125:125,MATCH('DCF Feed'!F$1,'Balance Sheet'!$2:$2,0)) -> -3934.1658 | G10: =INDEX('Balance Sheet'!125:125,MATCH('DCF Feed'!G$1,'Balance Sheet'!$2:$2,0)) -> -3953.5131
A11: Tax rate (adjusted) | B11: =INDEX('Income Statement'!97:97,MATCH('DCF Feed'!B1,'Income Statement'!2:2,0)) -> -0.26995769 | C11: =INDEX('Income Statement'!97:97,MATCH('DCF Feed'!C1,'Income Statement'!2:2,0)) -> -0.26995769 | D11: =INDEX('Income Statement'!97:97,MATCH('DCF Feed'!D1,'Income Statement'!2:2,0)) -> -0.26995769 | E11: =INDEX('Income Statement'!97:97,MATCH('DCF Feed'!E1,'Income Statement'!2:2,0)) -> -0.26995769 | F11: =INDEX('Income Statement'!97:97,MATCH('DCF Feed'!F1,'Income Statement'!2:2,0)) -> -0.26995769 | G11: =INDEX('Income Statement'!97:97,MATCH('DCF Feed'!G1,'Income Statement'!2:2,0)) -> -0.26995769
A12: Other
A13: Number of shares (mn) | B13: =INDEX('Income Statement'!114:114,MATCH('DCF Feed'!B$1,'Income Statement'!$2:$2,0))/1000 -> 785.62897 | C13: =INDEX('Income Statement'!114:114,MATCH('DCF Feed'!C$1,'Income Statement'!$2:$2,0))/1000 -> 775.10265 | D13: =INDEX('Income Statement'!114:114,MATCH('DCF Feed'!D$1,'Income Statement'!$2:$2,0))/1000 -> 764.57634 | E13: =INDEX('Income Statement'!114:114,MATCH('DCF Feed'!E$1,'Income Statement'!$2:$2,0))/1000 -> 764.57634 | F13: =INDEX('Income Statement'!114:114,MATCH('DCF Feed'!F$1,'Income Statement'!$2:$2,0))/1000 -> 764.57634 | G13: =INDEX('Income Statement'!114:114,MATCH('DCF Feed'!G$1,'Income Statement'!$2:$2,0))/1000 -> 764.57634
A25: Goldman Sachs adjusted EV | B25: ='Income Statement'!B2 -> 2006 | C25: ='Income Statement'!C2 -> 2007 | D25: ='Income Statement'!D2 -> 2008 | E25: ='Income Statement'!E2 -> 2009 | F25: ='Income Statement'!F2 -> 2010 | G25: ='Income Statement'!G2 -> 2011 | H25: ='Income Statement'!H2 -> 2012 | I25: ='Income Statement'!I2 -> 2013 | ... P25: ='Income Statement'!P2 -> 2020 | Q25: ='Income Statement'!Q$2 -> 2021 | R25: ='Income Statement'!R$2 -> 2022 | S25: ='Income Statement'!S$2 -> 2023 | T25: ='Income Statement'!T$2 -> 2024 | U25: ='Income Statement'!U$2 -> 2025 | V25: ='Income Statement'!V$2 -> 2026 | W25: ='Income Statement'!W$2 -> 2027 | X25: ='Income Statement'!X$2 -> 2028 | ... Z25: ='Income Statement'!Z$2 -> 2030
A26: Avg. no. of shares (m) | B26: ='Income Statement'!B113/1000 -> 800.18516 | C26: ='Income Statement'!C113/1000 -> 803.12822 | D26: ='Income Statement'!D113/1000 -> 806.9788 | E26: ='Income Statement'!E113/1000 -> 809.69863 | F26: ='Income Statement'!F113/1000 -> 810.69334 | G26: ='Income Statement'!G113/1000 -> 812.50729 | H26: ='Income Statement'!H113/1000 -> 819.37826 | I26: ='Income Statement'!I113/1000 -> 792.46686 | ... Z26: ='Income Statement'!Z113/1000 -> 763.25742
A27: Share price - average | B27: 26.32 | C27: 23.06 | D27: 14.34 | E27: 12.48 | F27: 16.59 | G27: 21.497 | H27: 27.8623 | I27: 41.2545 | J27: ='Income Statement'!J120 -> 55.8 | K27: ='Income Statement'!K120 -> 55.8 | L27: ='Income Statement'!L120 -> 110 | M27: =L27 -> 110 | N27: ='Income Statement'!N120 -> 109.68 | O27: 137 | P27: =O27 -> 137 | Q27: =P27 -> 137 | R27: =Q27 -> 137 | S27: =R27 -> 137 | T27: =S27 -> 137 | U27: =T27 -> 137 | V27: =U27 -> 137 | W27: =V27 -> 137 | ... Z27: =Y27 -> 137
A28: GS target Price | I28: =I27*1.35 -> 55.693575 | J28: =I28 -> 55.693575 | K28: =J28 -> 55.693575 | L28: =K28 -> 55.693575 | M28: =L28 -> 55.693575 | N28: =M28 -> 55.693575 | O28: =N28 -> 55.693575 | P28: =O28 -> 55.693575 | Q28: =P28 -> 55.693575 | ... Z28: =Y28 -> 55.693575
A29: Enterprise value calculation
A30: Market value - average | B30: =B27*B26 -> 21060.874 | C30: =C27*C26 -> 18520.137 | D30: =D27*D26 -> 11572.076 | E30: =E27*E26 -> 10105.039 | F30: =F27*F26 -> 13449.402 | G30: =G27*G26 -> 17466.469 | H30: =H27*H26 -> 22829.763 | I30: =I27*I26 -> 32692.824 | ... Z30: =Z27*Z26 -> 104566.27
A31: Market value of minorities - average | B31: =B30/SUM('Balance Sheet'!B49:B53)*'Balance Sheet'!B$54+2750 -> 2976.6002 | C31: =C30/SUM('Balance Sheet'!C49:C53)*'Balance Sheet'!C$54 -> 120.26063 | D31: =D30/SUM('Balance Sheet'!D49:D53)*'Balance Sheet'!D$54 -> 109.19034 | E31: =E30/SUM('Balance Sheet'!E49:E53)*'Balance Sheet'!E$54 -> 101.67386 | F31: =F30/SUM('Balance Sheet'!F49:F53)*'Balance Sheet'!F$54 -> 144.51909 | G31: =G30/SUM('Balance Sheet'!G49:G53)*'Balance Sheet'!G$54 -> 29.604185 | H31: =H30/SUM('Balance Sheet'!H49:H53)*'Balance Sheet'!H$54 -> 37.30712 | I31: =I30/SUM('Balance Sheet'!I49:I53)*'Balance Sheet'!I$54 -> 127.67155 | J31: =J30/SUM('Balance Sheet'!J49:J53)*'Balance Sheet'!J$54 -> 111.37338 | ... Z31: =Z30/SUM('Balance Sheet'!Z49:Z53)*'Balance Sheet'!Z$54 -> 181.20953
A32: Company Defined Net Debt (Cash) | B32: ='Balance Sheet'!B65 -> 4229 | C32: ='Balance Sheet'!C65 -> 7024 | D32: ='Balance Sheet'!D65 -> 9193 | E32: ='Balance Sheet'!E65 -> 9797 | F32: ='Balance Sheet'!F65 -> 11918 | G32: ='Balance Sheet'!G65 -> 11681 | H32: ='Balance Sheet'!H65 -> 12292 | I32: ='Balance Sheet'!I65 -> 9054 | ... Z32: ='Balance Sheet'!Z65 -> 33061.678
A33: Net Pension Deficit | B33: ='Balance Sheet'!B119 -> -4986 | C33: ='Balance Sheet'!C119 -> -4174 | D33: ='Balance Sheet'!D119 -> -3958 | E33: ='Balance Sheet'!E119 -> -5306 | F33: ='Balance Sheet'!F119 -> -5221 | G33: ='Balance Sheet'!G119 -> -5821 | H33: ='Balance Sheet'!H119 -> -6433 | I33: ='Balance Sheet'!I119 -> -6615 | ... Z33: ='Balance Sheet'!Z119 -> 1856
A34: Other Adjustments | B34: =SUM(B35:B41) -> -9508.4283 | C34: =SUM(C35:C41) -> -7625.7939 | D34: =SUM(D35:D41) -> -8414.2227 | E34: =SUM(E35:E41) -> -8368.2639 | F34: =SUM(F35:F41) -> -8004.6498 | G34: =SUM(G35:G41) -> -11452.389 | H34: =SUM(H35:H41) -> -8672 | I34: =SUM(I35:I41) -> -9930 | ... Z34: =SUM(Z35:Z41) -> -1208.6189
A35: Excess customer advances | B35: =B87 -> -12484 | C35: =C87 -> -13470 | D35: =D87 -> -14082 | E35: =E87 -> -15703 | F35: =F87 -> -15249 | G35: =G87 -> -16522 | H35: =H87 -> -17352 | I35: =I87 -> -18890 | ... Z35: =Z87 -> 0
A36: Launch aid | B36: =-'Balance Sheet'!B125 -> 5418 | C36: =-'Balance Sheet'!C125 -> 5315 | D36: =-'Balance Sheet'!D125 -> 4920 | E36: =-'Balance Sheet'!E125 -> 5294 | F36: =-'Balance Sheet'!F125 -> 6020 | G36: =-'Balance Sheet'!G125 -> 5737 | H36: =-'Balance Sheet'!H125 -> 6112 | I36: =-'Balance Sheet'!I125 -> 6112 | ... Z36: =-'Balance Sheet'!Z125 -> 3934.1658
A37: Net customer financing exposure | B37: =B60 -> 526 | C37: =C60 -> 440 | D37: =D60 -> 415 | E37: =E60 -> 429 | F37: =F60 -> 427 | G37: =G60 -> 363 | H37: =H60 -> 181 | I37: =I60 -> 181 | ... Z37: =Z60 -> 4
A38: Provisions/obligations for aircraft leassing
A39: Less Investments | B39: =B64 -> -3900.4283 | C39: =C64 -> -3309.7939 | D39: =D64 -> -3150.2227 | E39: =E64 -> -2836.2639 | F39: =F64 -> -4148.6498 | G39: =G64 -> -4575.3887 | H39: =H64 -> -1518 | I39: =I64 -> -1354 | ... Z39: =Z64 -> -9367.7847
A40: Cash provisions to be utilised | B40: =B74 -> 1990 | C40: =C74 -> 4258 | D40: =D74 -> 4220 | E40: =E74 -> 5100 | F40: =F74 -> 5478 | G40: =G74 -> 4000 | H40: =H74 -> 4250 | I40: =I74 -> 4250 | ... Z40: =Z74 -> 4250
A41: Non-recourse Debt (adjustment) | B41: =B80 -> -1058 | C41: =C80 -> -859 | D41: =D80 -> -737 | E41: =E80 -> -652 | F41: =F80 -> -532 | G41: =G80 -> -455 | H41: =H80 -> -345 | I41: =I80 -> -229 | ... Z41: =Z80 -> -29
A42: EV - average | B42: =SUM(B30:B34) -> 13772.045 | C42: =SUM(C30:C34) -> 13864.604 | D42: =SUM(D30:D34) -> 8502.0437 | E42: =SUM(E30:E34) -> 6329.4489 | F42: =SUM(F30:F34) -> 12286.272 | G42: =SUM(G30:G34) -> 11903.685 | H42: =SUM(H30:H34) -> 20054.07 | I42: =SUM(I30:I34) -> 25329.496 | ... Z42: =SUM(Z30:Z34) -> 138456.54
A43: as a multiple of Company defined EBIT | B43: =B42/'Income Statement'!B84 -> 34.516405 | C43: =C42/'Income Statement'!C84 -> 266.62699 | D43: =D42/'Income Statement'!D84 -> 3.0042557 | E43: =E42/'Income Statement'!E84 -> -19.656674 | F43: =F42/'Income Statement'!F84 -> 9.9807244 | G43: =G42/'Income Statement'!G84 -> 7.018682 | H43: =H42/'Income Statement'!H84 -> 9.3535775 | I43: =I42/'Income Statement'!I84 -> 9.5187883 | J43: =J42/'Income Statement'!J151 -> 8.4519613 | K43: =K42/'Income Statement'!K151 -> 7.5021955 | L43: =L42/'Income Statement'!L151 -> 17.912894 | M43: =M42/'Income Statement'!M151 -> 16.418323 | N43: =N42/'Income Statement'!N151 -> 11.999778 | O43: =O42/'Income Statement'!O151 -> 16.381185 | P43: =P42/'Income Statement'!P151 -> 61.407701 | Q43: =Q42/'Income Statement'!Q151 -> 22.837203 | ... Z43: =Z42/'Income Statement'!Z151 -> 9.8005322
A44: on GS target Price | H44: =(H42-H30+H30/H27*H28)/'Income Statement'!H84 -> -1.2946329 | I44: =(I42-I30+I30/I27*I28)/'Income Statement'!I84 -> 13.818859 | J44: =(J42-J30+J30/J27*J28)/'Income Statement'!J84 -> 8.4314677 | K44: =(K42-K30+K30/K27*K28)/'Income Statement'!K84 -> 7.4818426 | L44: =(L42-L30+L30/L27*L28)/'Income Statement'!L84 -> 7.2877995 | M44: =(M42-M30+M30/M27*M28)/'Income Statement'!M84 -> 6.5380432 | N44: =(N42-N30+N30/N27*N28)/'Income Statement'!N84 -> 4.826561 | O44: =(O42-O30+O30/O27*O28)/'Income Statement'!O84 -> 7.2855424 | ... Z44: =(Z42-Z30+Z30/Z27*Z28)/'Income Statement'!Z84 -> 5.4078265
A45: Implied P/E | B45: =B27/'Income Statement'!B201 -> #DIV/0! | C45: =C27/'Income Statement'!C201 -> #DIV/0! | D45: =D27/'Income Statement'!D201 -> #DIV/0! | E45: =E27/'Income Statement'!E201 -> #DIV/0! | F45: =F27/'Income Statement'!F201 -> #DIV/0! | G45: =G27/'Income Statement'!G201 -> #DIV/0! | H45: =H27/'Income Statement'!H201 -> #DIV/0! | I45: =I28/'Income Statement'!I201 -> #DIV/0! | J45: =J28/'Income Statement'!J201 -> #DIV/0! | K45: =K28/'Income Statement'!K201 -> #DIV/0! | L45: =L28/'Income Statement'!L201 -> #DIV/0! | M45: =M28/'Income Statement'!M201 -> #DIV/0! | N45: =N28/'Income Statement'!N201 -> #DIV/0! | O45: =O28/'Income Statement'!O201 -> #DIV/0! | P45: =P28/'Income Statement'!P201 -> #DIV/0! | ... Z45: =Z28/'Income Statement'!Z201 -> #DIV/0!
A60: Net vendor financing (assets)/liablities | B60: =B61 -> 526 | C60: =C61 -> 440 | D60: =D61 -> 415 | E60: =E61 -> 429 | F60: =F61 -> 427 | G60: =G61 -> 363 | H60: =H61 -> 181 | I60: =I61 -> 181 | ... Z60: =Z61 -> 4
A61: Off-balance sheet aircraft financing commitments | B61: 526 | C61: 440 | D61: 415 | E61: 429 | F61: 427 | G61: =267+56+40 -> 363 | H61: =124+45+12 -> 181 | I61: =H61 -> 181 | J61: =71+9 -> 80 | K61: =60+8 -> 68 | L61: =182+21 -> 203 | M61: =144+4 -> 148 | N61: 38 | O61: 104 | P61: 14 | Q61: 67 | R61: 8 | S61: 8 | T61: 4 | U61: =T61 -> 4 | V61: =U61 -> 4 | W61: =V61 -> 4 | X61: =W61 -> 4 | Y61: =X61 -> 4 | Z61: =Y61 -> 4 | AB61: Customer Financing Exposure slide on FY results PPT. We use the Off-balance sheet number as the rest is already captured within Net Debt
A62: Less: customer financing collateral value | B62: -791 | C62: -622 | D62: -697 | E62: -972 | F62: -926 | G62: =-627-86-53 -> -766 | H62: =-741-61-48 -> -850 | I62: =H62 -> -850 | J62: =-743-20 -> -763 | K62: =-922-20 -> -942 | L62: =-1157-60 -> -1217 | M62: =-953-64 -> -1017 | N62: -597 | O62: -560 | P62: -279 | Q62: =P62 -> -279 | R62: =Q62 -> -279 | S62: =R62 -> -279 | T62: =S62 -> -279 | U62: =T62 -> -279 | V62: =U62 -> -279 | W62: =V62 -> -279 | X62: =W62 -> -279 | ... Z62: =Y62 -> -279 | AB62: Some people would argue that the collateral should be added back into EV as it's a liquid asset. We don't think so as otherwise other types of debt could be removed, depending on what they had been used to purchase
A64: Less Investments | B64: =B65+B67 -> -3900.4283 | C64: =C65+C67 -> -3309.7939 | D64: =D65+D67 -> -3150.2227 | E64: =E65+E67 -> -2836.2639 | F64: =F65+F67 -> -4148.6498 | G64: =G65+G67 -> -4575.3887 | H64: =H65+H67 -> -1518 | I64: =I65+I67 -> -1354 | ... Z64: =Z65+Z67 -> -9367.7847
A65: Less: Market value of Dassault Aviation | B65: -2911.4283 | C65: -2484.7939 | D65: -2433.2227 | E65: -1936.2639 | F65: -2742.6498 | G65: -3047.3887 | K65: -2188.8009 | L65: 0 | M65: =L65 -> 0 | N65: =M65 -> 0 | O65: =N65 -> 0 | P65: =O65 -> 0 | Q65: =P65 -> 0 | R65: =Q65 -> 0 | S65: =R65 -> 0 | T65: =S65 -> 0 | ... Z65: =Y65 -> 0
A66: Dassault Share price | H66: 744.1 | I66: 872 | J66: 1280.5
A67: Less: book value of other investments | B67: =-(B68-B69)-(B70-B71-B72) -> -989 | C67: =-(C68-C69)-(C70-C71-C72) -> -825 | D67: =-(D68-D69)-(D70-D71-D72) -> -717 | E67: =-(E68-E69)-(E70-E71-E72) -> -900 | F67: =-(F68-F69)-(F70-F71-F72) -> -1406 | G67: =-(G68-G69)-(G70-G71-G72) -> -1528 | H67: =-(H68-H69)-(H70-H71-H72) -> -1518 | I67: =-(I68-I69)-(I70-I71-I72) -> -1354 | ... Z67: =-(Z68-Z69)-(Z70-Z71-Z72) -> -9367.7847
A68: Associates | B68: ='Balance Sheet'!B7 -> 2095 | C68: ='Balance Sheet'!C7 -> 2238 | D68: ='Balance Sheet'!D7 -> 2356 | E68: ='Balance Sheet'!E7 -> 2514 | F68: ='Balance Sheet'!F7 -> 2451 | G68: ='Balance Sheet'!G7 -> 2677 | H68: ='Balance Sheet'!H7 -> 2662 | I68: ='Balance Sheet'!I7 -> 2902 | ... Z68: ='Balance Sheet'!Z7 -> 4129.5834 | AB68: Investments in associates accounted for under the equity method, within Consolidated Statements of Financial Position. Page 55 2012 FS
A69: of which, Dassault Aviation | B69: 1985 | C69: 2121 | D69: 2243 | E69: 2380 | F69: 2318 | G69: 2552 | H69: 2519 | I69: 2747 | J69: 2429 | K69: 1253 | L69: 12 | M69: 0 | N69: 0 | O69: =N69 -> 0 | P69: =O69 -> 0 | Q69: =P69 -> 0 | R69: =Q69 -> 0 | S69: =R69 -> 0 | T69: =S69 -> 0 | U69: =T69 -> 0 | V69: =U69 -> 0 | ... Z69: =Y69 -> 0 | AB69: Carrying amount of the investment at 31 December within Investments in Associates, Page 55 2012 FS
A70: Other investments and long-term financial assets | B70: ='Balance Sheet'!B8 -> 1666 | C70: ='Balance Sheet'!C8 -> 1553 | D70: ='Balance Sheet'!D8 -> 1712 | E70: ='Balance Sheet'!E8 -> 2210 | F70: ='Balance Sheet'!F8 -> 2386 | G70: ='Balance Sheet'!G8 -> 2352 | H70: ='Balance Sheet'!H8 -> 2115 | I70: ='Balance Sheet'!I8 -> 1864 | ... Z70: ='Balance Sheet'!Z8 -> 5470 | AB70: Total non-current other investments and other long-term financial assets within Investments in Associates, Page 55 2012 FS
A71: of which, aircraft financing loans (loans to customers) | B71: 157 | C71: 267 | D71: 406 | E71: 690 | F71: 486 | G71: 421 | H71: 364 | I71: 335 | J71: 426 | K71: 553 | L71: 732 | M71: 695 | N71: 502 | O71: 349 | P71: 224 | Q71: 77 | R71: 49 | S71: 85 | T71: 97 | U71: =AVERAGE(T71)/AVERAGE(S70)*U$70 -> 112.43696 | V71: =AVERAGE(U71)/AVERAGE(T70)*V$70 -> 121.14047 | W71: =AVERAGE(V71)/AVERAGE(U70)*W$70 -> 121.14047 | X71: =AVERAGE(W71)/AVERAGE(V70)*X$70 -> 121.14047 | Y71: =AVERAGE(X71)/AVERAGE(W70)*Y$70 -> 121.14047 | Z71: =AVERAGE(Y71)/AVERAGE(X70)*Z$70 -> 121.14047 | AB71: Total net book value of loans. Page 57 2012 FS. We exclude these as it is already accounted for in the net exposure calculation in Net Vendor Financing
A72: of which, finance lease receivables from aircraft financing | B72: 630 | C72: 578 | D72: 702 | E72: 754 | F72: 627 | G72: 528 | H72: 376 | I72: 330 | J72: 17 | K72: =AVERAGE(J72)/AVERAGE(I70)*K$70 -> 22.727468 | L72: 219 | M72: 80 | N72: 9 | O72: 9 | P72: 13 | Q72: 65 | R72: 62 | S72: =AVERAGE(R72)/AVERAGE(Q70)*S$70 -> 73.126218 | T72: =AVERAGE(S72)/AVERAGE(R70)*T$70 -> 88.606637 | U72: =AVERAGE(T72)/AVERAGE(S70)*U$70 -> 102.70784 | V72: =AVERAGE(U72)/AVERAGE(T70)*V$70 -> 110.65824 | W72: =AVERAGE(V72)/AVERAGE(U70)*W$70 -> 110.65824 | X72: =AVERAGE(W72)/AVERAGE(V70)*X$70 -> 110.65824 | Y72: =AVERAGE(X72)/AVERAGE(W70)*Y$70 -> 110.65824 | Z72: =AVERAGE(Y72)/AVERAGE(X70)*Z$70 -> 110.65824 | AB72: Total net book value of finance lease receivables. Page 256 of 2017 AR. We exclude these as it is already accounted for in the net exposure calculation in Net Vendor Financing
A74: Cash provisions to be utilised | B74: 1990 | C74: 4258 | D74: 4220 | E74: 5100 | F74: 5478 | G74: 4000 | H74: 4250 | I74: =$H74 -> 4250 | J74: 4900 | K74: =$H74 -> 4250 | L74: =$H74 -> 4250 | M74: =$H74 -> 4250 | N74: =$H74 -> 4250 | O74: =$H74 -> 4250 | P74: =$H74 -> 4250 | Q74: =$H74 -> 4250 | R74: =$H74 -> 4250 | ... Z74: =$H74 -> 4250
A75: Change in provisions and current tax assets / liabilities | H75: =-(H77-G77) -> 419 | I75: =H75 -> 419 | J75: =I75 -> 419 | K75: =J75 -> 419 | L75: =K75 -> 419 | M75: =L75 -> 419 | N75: =M75 -> 419 | O75: =N75 -> 419 | P75: =O75 -> 419 | ... Z75: =Y75 -> 419
A76: Total provisions
A77: of which, other provisions (excludes Pension related provisions already dealt with above) | B77: -5747 | C77: -6953 | D77: -6611 | E77: -7762 | F77: -7782 | G77: =-(9164+G78) -> -8205 | H77: =-(9428+H78) -> -8624 | I77: =H77 -> -8624 | J77: =-(7862+J78) -> -7175 | K77: =-(7465+K78) -> -6847 | L77: =-(8313+L78) -> -7719 | M77: =-(8367+M78) -> -7838 | N77: =-(11816+N78) -> -11517 | O77: =-(10561+O78) -> -10405 | P77: =-(10563+P78) -> -10469 | Q77: =-(8209+Q78) -> -8115 | R77: ='Balance Sheet'!R29+'Balance Sheet'!R38-'Balance Sheet'!R120 -> -7514 | S77: ='Balance Sheet'!S29+'Balance Sheet'!S38-'Balance Sheet'!S120 -> -7113 | T77: ='Balance Sheet'!T29+'Balance Sheet'!T38-'Balance Sheet'!T120 -> -7116 | U77: ='Balance Sheet'!U29+'Balance Sheet'!U38-'Balance Sheet'!U120 -> -7024 | V77: ='Balance Sheet'!V29+'Balance Sheet'!V38-'Balance Sheet'!V120 -> -7524 | W77: ='Balance Sheet'!W29+'Balance Sheet'!W38-'Balance Sheet'!W120 -> -8024 | X77: ='Balance Sheet'!X29+'Balance Sheet'!X38-'Balance Sheet'!X120 -> -8524 | Y77: ='Balance Sheet'!Y29+'Balance Sheet'!Y38-'Balance Sheet'!Y120 -> -9024 | Z77: ='Balance Sheet'!Z29+'Balance Sheet'!Z38-'Balance Sheet'!Z120 -> -9524 | AB77: Other provisions in Provisions
A78: of which, Aircraft financing risks | B78: -1064 | C78: -812 | D78: -905 | E78: -952 | F78: -976 | G78: -959 | H78: -804 | I78: =H78 -> -804 | J78: -687 | K78: -618 | L78: -594 | M78: -529 | N78: -299 | O78: -156 | P78: -94 | Q78: =P78 -> -94 | R78: =Q78 -> -94 | S78: =R78 -> -94 | T78: =S78 -> -94 | U78: =T78 -> -94 | V78: =U78 -> -94 | W78: =V78 -> -94 | X78: =W78 -> -94 | ... Z78: =Y78 -> -94 | AB78: Aircraft financing risks within Note to Other Provisions
A80: Other Adjustments | B80: =SUM(B81) -> -1058 | C80: =SUM(C81) -> -859 | D80: =SUM(D81) -> -737 | E80: =SUM(E81) -> -652 | F80: =SUM(F81) -> -532 | G80: =SUM(G81) -> -455 | H80: =SUM(H81) -> -345 | I80: =SUM(I81) -> -229 | ... Z80: =SUM(Z81) -> -29
A81: Non-recourse debt (Cash) | B81: -1058 | C81: -859 | D81: -737 | E81: -652 | F81: -532 | G81: -455 | H81: -345 | I81: -229 | J81: -46 | K81: -94 | L81: -45 | M81: -29 | N81: =M81 -> -29 | O81: =N81 -> -29 | P81: =O81 -> -29 | Q81: =P81 -> -29 | R81: =Q81 -> -29 | S81: =R81 -> -29 | T81: =S81 -> -29 | U81: =T81 -> -29 | ... Z81: =Y81 -> -29 | AB81: Non recourse Airbus financing liabilities, page 256 AR 17. This needs to be removed from Net Debt as it's a financial liability for which EADS doesn't bear the risk (but is included in Net Debt)
A83: Market Value adjustment for minorities | B83: =B85-B84 -> 86.600238 | C83: =C85-C84 -> 35.260628 | D83: =D85-D84 -> 5.1903379 | E83: =E85-E84 -> -4.3261391 | F83: =F85-F84 -> 49.519086 | G83: =G85-G84 -> 14.604185 | H83: =H85-H84 -> 20.30712 | I83: =I85-I84 -> 84.67155 | ... Z83: =Z85-Z84 -> 101.20953
A84: Balance sheet minorities | B84: ='Balance Sheet'!B$54+2750 -> 2890 | C84: ='Balance Sheet'!C$54 -> 85 | D84: ='Balance Sheet'!D$54 -> 104 | E84: ='Balance Sheet'!E$54 -> 106 | F84: ='Balance Sheet'!F$54 -> 95 | G84: ='Balance Sheet'!G$54 -> 15 | H84: ='Balance Sheet'!H$54 -> 17 | I84: ='Balance Sheet'!I$54 -> 43 | J84: ='Balance Sheet'!J$54 -> 18 | ... Z84: ='Balance Sheet'!Z$54 -> 80
A85: Market Value of minorities minorities | B85: =B31 -> 2976.6002 | C85: =C31 -> 120.26063 | D85: =D31 -> 109.19034 | E85: =E31 -> 101.67386 | F85: =F31 -> 144.51909 | G85: =G31 -> 29.604185 | H85: =H31 -> 37.30712 | I85: =I31 -> 127.67155 | ... Z85: =Z31 -> 181.20953
A87: Est. Excess customer advances | B87: =-SUM(B91:B92) -> -12484 | C87: =-SUM(C91:C92) -> -13470 | D87: =-SUM(D91:D92) -> -14082 | E87: =-SUM(E91:E92) -> -15703 | F87: =-SUM(F91:F92) -> -15249 | G87: =-SUM(G91:G92) -> -16522 | H87: =-SUM(H91:H92) -> -17352 | I87: =-SUM(I91:I92) -> -18890 | ... N87: =-SUM(N91:N92) -> -25037 | O87: =MAX(-SUM(O91:O92),0) -> 0 | P87: =MAX(-SUM(P91:P92),0) -> 0 | Q87: =MAX(-SUM(Q91:Q92),0) -> 0 | R87: =MAX(-SUM(R91:R92),0) -> 0 | S87: =MAX(-SUM(S91:S92),0) -> 0 | T87: =MAX(-SUM(T91:T92),0) -> 0 | U87: =MAX(-SUM(U91:U92),0) -> 0 | V87: =MAX(-SUM(V91:V92),0) -> 0 | ... Z87: =MAX(-SUM(Z91:Z92),0) -> 0
A88: Assumed Margin retianed on advances (Underlying EBITDA margin) | B88: =#REF! -> #REF! | C88: =#REF! -> #REF! | D88: =#REF! -> #REF! | E88: =#REF! -> #REF! | F88: =#REF! -> #REF! | G88: =#REF! -> #REF! | H88: 0.1 | I88: 0.1 | J88: =$I88 -> 0.1 | K88: =$I88 -> 0.1 | L88: =$I88 -> 0.1 | M88: =$I88 -> 0.1 | N88: =$I88 -> 0.1 | O88: =$I88 -> 0.1 | P88: =$I88 -> 0.1 | Q88: =$I88 -> 0.1 | ... Z88: =$I88 -> 0.1 | AB88: We assume 10% here, for Narrow bodies the operating leverage contribution is higher (18-19%), but for wide bodies it is just below 10%.
A89: Inventory | B89: ='Balance Sheet'!B16 -> 16892 | C89: ='Balance Sheet'!C16 -> 18906 | D89: ='Balance Sheet'!D16 -> 19452 | E89: ='Balance Sheet'!E16 -> 21577 | F89: ='Balance Sheet'!F16 -> 20862 | G89: ='Balance Sheet'!G16 -> 22563 | H89: ='Balance Sheet'!H16 -> 23216 | I89: ='Balance Sheet'!I16 -> 25060 | ... Z89: ='Balance Sheet'!Z16 -> 58522.854
A90: Raw mat and supplies | B90: 1283 | C90: 1596 | D90: 1706 | E90: 1736 | F90: 1654 | G90: 1980 | H90: 2397 | I90: 2650 | J90: 2717 | K90: 2753 | L90: 2780 | M90: 2651 | N90: 3273 | O90: 3279 | P90: 3328 | Q90: 3068 | R90: 3744 | S90: 4286 | T90: 5067 | U90: =SUM($F90:$H90)/SUM($F$89:$H$89)*U$89 -> 3771.6714 | V90: =SUM($F90:$H90)/SUM($F$89:$H$89)*V$89 -> 3956.1515 | W90: =SUM($F90:$H90)/SUM($F$89:$H$89)*W$89 -> 4481.7857 | X90: =SUM($F90:$H90)/SUM($F$89:$H$89)*X$89 -> 4945.2596 | Y90: =SUM($F90:$H90)/SUM($F$89:$H$89)*Y$89 -> 5210.272 | Z90: =SUM($F90:$H90)/SUM($F$89:$H$89)*Z$89 -> 5296.3091
A91: WIP | B91: 11260 | C91: 12253 | D91: 12253 | E91: 13899 | F91: 13631 | G91: 14803 | H91: 15464 | I91: 16771 | J91: 17255 | K91: 20435 | L91: 21058 | M91: 22652 | N91: 21643 | O91: 20519 | P91: 18730 | Q91: 17542 | R91: 19255 | S91: 19558 | T91: 20925 | U91: =SUM($F91:$H91)/SUM($F$89:$H$89)*U$89 -> 27452.965 | V91: =SUM($F91:$H91)/SUM($F$89:$H$89)*V$89 -> 28795.745 | W91: =SUM($F91:$H91)/SUM($F$89:$H$89)*W$89 -> 32621.693 | X91: =SUM($F91:$H91)/SUM($F$89:$H$89)*X$89 -> 35995.192 | Y91: =SUM($F91:$H91)/SUM($F$89:$H$89)*Y$89 -> 37924.145 | Z91: =SUM($F91:$H91)/SUM($F$89:$H$89)*Z$89 -> 38550.386 | AD91: ='Balance Sheet'!#REF!-'Balance Sheet'!#REF! -> #REF! | AE91: ='Balance Sheet'!#REF!-'Balance Sheet'!#REF! -> #REF! | AF91: ='Balance Sheet'!#REF!-'Balance Sheet'!#REF! -> #REF! | AG91: ='Balance Sheet'!#REF!-'Balance Sheet'!#REF! -> #REF! | AH91: ='Balance Sheet'!#REF!-'Balance Sheet'!#REF! -> #REF! | AI91: ='Balance Sheet'!#REF!-'Balance Sheet'!#REF! -> #REF!
A92: Finished goods for resale | B92: 1224 | C92: 1217 | D92: 1829 | E92: 1804 | F92: 1618 | G92: 1719 | H92: 1888 | I92: 2119 | J92: 2196 | K92: 2355 | L92: 2750 | M92: 2853 | N92: 3394 | O92: 4112 | P92: 5228 | Q92: 4556 | R92: 4158 | S92: 3896 | T92: 5054 | U92: =SUM($F92:$H92)/SUM($F$89:$H$89)*U$89 -> 3267.6145 | V92: =SUM($F92:$H92)/SUM($F$89:$H$89)*V$89 -> 3427.4402 | W92: =SUM($F92:$H92)/SUM($F$89:$H$89)*W$89 -> 3882.8271 | X92: =SUM($F92:$H92)/SUM($F$89:$H$89)*X$89 -> 4284.361 | Y92: =SUM($F92:$H92)/SUM($F$89:$H$89)*Y$89 -> 4513.9564 | Z92: =SUM($F92:$H92)/SUM($F$89:$H$89)*Z$89 -> 4588.4953 | AC92: Advance payments received/ Contract Assets and Liabilities | AD92: 1700.3 | AE92: 3066.1 | AF92: 3355.1 | AG92: 2739.1 | AH92: 2426.4 | AI92: 2613
A93: Advance to suppliers | B93: 3125 | C93: 3840 | D93: 3664 | E93: 4138 | F93: 3959 | G93: 4061 | H93: 3467 | I93: 3520 | J93: 3187 | K93: 3508 | L93: 3100 | M93: 3308 | N93: 3581 | O93: 3640 | P93: 3115 | Q93: 3372 | R93: 5045 | S93: 6001 | T93: 6699 | U93: =SUM($F93:$H93)/SUM($F$89:$H$89)*U$89 -> 7183.7489 | V93: =SUM($F93:$H93)/SUM($F$89:$H$89)*V$89 -> 7535.1206 | W93: =SUM($F93:$H93)/SUM($F$89:$H$89)*W$89 -> 8536.2747 | X93: =SUM($F93:$H93)/SUM($F$89:$H$89)*X$89 -> 9419.0344 | Y93: =SUM($F93:$H93)/SUM($F$89:$H$89)*Y$89 -> 9923.7929 | Z93: =SUM($F93:$H93)/SUM($F$89:$H$89)*Z$89 -> 10087.664
A95: Customer Advances | R95: 0.43 | S95: 0.42 | T95: 0.42 | U95: 0.42 | V95: 0.42 | W95: 0.42 | X95: 0.42 | Y95: 0.42 | Z95: 0.42

Sheet Income Statement
A1: ='DCF Valuation'!D51 -> 240
A2: Airbus | B2: 2006 | C2: 2007 | D2: 2008 | E2: 2009 | F2: 2010 | G2: 2011 | H2: 2012 | I2: 2013 | J2: 2014 | K2: 2015 | L2: 2016 | M2: 2017 | N2: 2018 | O2: 2019 | P2: 2020 | Q2: 2021 | R2: 2022 | S2: 2023 | T2: 2024 | U2: 2025 | V2: =U2+1 -> 2026 | W2: =V2+1 -> 2027 | X2: =W2+1 -> 2028 | Y2: =X2+1 -> 2029 | Z2: =Y2+1 -> 2030 | AA2: =Z2+1 -> 2031
A4: Divisional Summary | B4: =B2 -> 2006 | C4: =C2 -> 2007 | D4: =D2 -> 2008 | E4: =E2 -> 2009 | F4: =F2 -> 2010 | G4: =G2 -> 2011 | H4: =H2 -> 2012 | I4: =I2 -> 2013 | ... T4: =T2 -> 2024 | U4: =U$2 -> 2025 | V4: =V$2 -> 2026 | W4: =W$2 -> 2027 | X4: =X$2 -> 2028 | Y4: =Y$2 -> 2029 | Z4: =Z$2 -> 2030 | AA4: =AA$2 -> 2031
A5: Sales
A6: Airbus Division | B6: =#REF! -> #REF! | C6: =#REF! -> #REF! | D6: =#REF! -> #REF! | E6: =#REF! -> #REF! | F6: =#REF! -> #REF! | G6: =#REF! -> #REF! | H6: =#REF! -> #REF! | I6: =#REF! -> #REF!
A7: Airbus Commercial | B7: ='Airbus Commercial'!B2 -> work | C7: ='Airbus Commercial'!C2 -> 25216 | D7: ='Airbus Commercial'!D2 -> 26524 | E7: ='Airbus Commercial'!E2 -> 26370 | F7: ='Airbus Commercial'!F2 -> 27673 | G7: ='Airbus Commercial'!G2 -> 31159 | H7: ='Airbus Commercial'!H2 -> 37624 | I7: ='Airbus Commercial'!I2 -> 39889 | ... U7: ='Airbus Commercial'!U2 -> 52577 | V7: =U7*(1+V17) -> 57945.622 | W7: =V7*(1+W17) -> 67784.666 | X7: =W7*(1+X17) -> 77835.508 | Y7: =X7*(1+Y17) -> 84850.404 | Z7: =Y7*(1+Z17) -> 88711.401 | AA7: =Z7*(1+AA17) -> 91335.261
A8: Airbus Military | B8: ='Airbus Defence & Space'!B39 -> 0 | C8: ='Airbus Defence & Space'!C39 -> 0 | D8: ='Airbus Defence & Space'!D39 -> 0 | E8: ='Airbus Defence & Space'!E39 -> 0 | F8: ='Airbus Defence & Space'!F39 -> 0 | G8: ='Airbus Defence & Space'!G39 -> 0 | H8: ='Airbus Defence & Space'!H39 -> 5632.4 | I8: =#REF! -> #REF! | V8: =U8*(1+V18) -> 0 | W8: =V8*(1+W18) -> 0 | X8: =W8*(1+X18) -> 0 | Y8: =X8*(1+Y18) -> 0 | Z8: =Y8*(1+Z18) -> 0 | AA8: =Z8*(1+AA18) -> 0
A9: Airbus Helicopters | B9: ='Airbus Helicopters'!B2 -> 3803 | C9: ='Airbus Helicopters'!C2 -> 4172 | D9: ='Airbus Helicopters'!D2 -> 4486 | E9: ='Airbus Helicopters'!E2 -> 4570 | F9: ='Airbus Helicopters'!F2 -> 4830 | G9: ='Airbus Helicopters'!G2 -> 5415 | H9: ='Airbus Helicopters'!H2 -> 6264 | I9: ='Airbus Helicopters'!I2 -> 6297 | ... U9: ='Airbus Helicopters'!U2 -> 8972 | V9: =U9*(1+V19) -> 9641.0962 | W9: =V9*(1+W19) -> 10139.801 | X9: =W9*(1+X19) -> 10619.327 | Y9: =X9*(1+Y19) -> 11105.228 | Z9: =Y9*(1+Z19) -> 11598.105 | AA9: =Z9*(1+AA19) -> 12098.144
A10: Astrium | B10: ='Airbus Defence & Space'!B53 -> 0 | C10: ='Airbus Defence & Space'!C53 -> 0 | D10: ='Airbus Defence & Space'!D53 -> 0 | E10: ='Airbus Defence & Space'!E53 -> 0 | F10: ='Airbus Defence & Space'!F53 -> 0 | G10: ='Airbus Defence & Space'!G53 -> 0 | H10: ='Airbus Defence & Space'!H53 -> 5817 | I10: ='Airbus Defence & Space'!I53 -> 5784 | V10: =U10*(1+V20) -> 0 | W10: =V10*(1+W20) -> 0 | X10: =W10*(1+X20) -> 0 | Y10: =X10*(1+Y20) -> 0 | Z10: =Y10*(1+Z20) -> 0 | AA10: =Z10*(1+AA20) -> 0
A11: Cassidian | B11: ='Airbus Defence & Space'!B46 -> 0 | C11: ='Airbus Defence & Space'!C46 -> 0 | D11: ='Airbus Defence & Space'!D46 -> 0 | E11: ='Airbus Defence & Space'!E46 -> 0 | F11: ='Airbus Defence & Space'!F46 -> 0 | G11: ='Airbus Defence & Space'!G46 -> 0 | H11: ='Airbus Defence & Space'!H46 -> 5740 | I11: ='Airbus Defence & Space'!I46 -> 5976 | V11: =U11*(1+V21) -> 0 | W11: =V11*(1+W21) -> 0 | X11: =W11*(1+X21) -> 0 | Y11: =X11*(1+Y21) -> 0 | Z11: =Y11*(1+Z21) -> 0 | AA11: =Z11*(1+AA21) -> 0
A12: Airbus Defence & Space | H12: ='Airbus Defence & Space'!H2 -> 13520 | I12: ='Airbus Defence & Space'!I2 -> 17982 | J12: ='Airbus Defence & Space'!J2 -> 13025 | K12: ='Airbus Defence & Space'!K2 -> 13080 | L12: ='Airbus Defence & Space'!L2 -> 11854 | M12: ='Airbus Defence & Space'!M2 -> 10804 | N12: ='Airbus Defence & Space'!N2 -> 11063 | O12: ='Airbus Defence & Space'!O2 -> 10907 | ... U12: ='Airbus Defence & Space'!U2 -> 13405 | V12: =U12*(1+V22) -> 14277.666 | W12: =V12*(1+W22) -> 15207.698 | X12: =W12*(1+X22) -> 16198.901 | Y12: =X12*(1+Y22) -> 17492.739 | Z12: =Y12*(1+Z22) -> 18894.053 | AA12: =Z12*(1+AA22) -> 20412.006
A13: other | B13: =#REF! -> #REF! | C13: =#REF! -> #REF! | D13: =#REF! -> #REF! | E13: =#REF! -> #REF! | F13: =#REF! -> #REF! | G13: =#REF! -> #REF! | H13: -614 | I13: -1352 | J13: -1116 | K13: -1270 | L13: -1162 | M13: -1445 | N13: -1260 | O13: -1211 | P13: -1035 | Q13: -710 | R13: -972 | S13: -1149 | T13: -1439 | U13: -1439 | V13: =U13/SUM(U7:U12)*SUM(V7:V12) -> -1571.6686 | W13: =V13/SUM(V7:V12)*SUM(W7:W12) -> -1787.9924 | X13: =W13/SUM(W7:W12)*SUM(X7:X12) -> -2009.1887 | Y13: =X13/SUM(X7:X12)*SUM(Y7:Y12) -> -2178.0319 | Z13: =Y13/SUM(Y7:Y12)*SUM(Z7:Z12) -> -2288.5226 | AA13: =Z13/SUM(Z7:Z12)*SUM(AA7:AA12) -> -2377.6389
A14: Group | B14: =SUM(B7:B13) -> #REF! | C14: =SUM(C7:C13) -> #REF! | D14: =SUM(D7:D13) -> #REF! | E14: =SUM(E7:E13) -> #REF! | F14: =SUM(F7:F13) -> #REF! | G14: =SUM(G7:G13)-2000+31 -> #REF! | H14: 56480 | I14: =I7+I9+I12+I13 -> 62816 | J14: =J7+J9+J12+J13 -> 60713 | K14: =K7+K9+K12+K13 -> 64450 | L14: =L7+L9+L12+L13 -> 66581 | M14: =M7+M9+M12+M13 -> 66767 | N14: =N7+N9+N12+N13 -> 63707 | O14: =O7+O9+O12+O13 -> 70478 | P14: =P7+P9+P12+P13 -> 49912 | ... AA14: =AA7+AA9+AA12+AA13 -> 121467.77
A16: Sales Growth
A17: Airbus Commercial | C17: =C7/B7-1 -> #VALUE! | D17: =D7/C7-1 -> 0.051871827 | E17: =E7/D7-1 -> -0.0058060624 | F17: =F7/E7-1 -> 0.049412211 | G17: =G7/F7-1 -> 0.12597116 | H17: =H7/G7-1 -> 0.20748419 | I17: =I7/H7-1 -> 0.060200936 | J17: =J7/I7-1 -> 0.059941337 | ... U17: =U7/T7-1 -> 0.038127394 | V17: ='Airbus Commercial'!V3 -> 0.1021097 | W17: ='Airbus Commercial'!W3 -> 0.16979788 | X17: ='Airbus Commercial'!X3 -> 0.14827605 | Y17: ='Airbus Commercial'!Y3 -> 0.090124629 | Z17: ='Airbus Commercial'!Z3 -> 0.045503571 | AA17: ='Airbus Commercial'!AA3 -> 0.029577488
A18: Airbus Military | C18: =C8/B8-1 -> #DIV/0! | D18: =D8/C8-1 -> #DIV/0! | E18: =E8/D8-1 -> #DIV/0! | F18: =F8/E8-1 -> #DIV/0! | G18: =G8/F8-1 -> #DIV/0! | H18: =H8/G8-1 -> #DIV/0! | I18: =I8/H8-1 -> #REF!
A19: Airbus Helicopters | C19: =C9/B9-1 -> 0.097028662 | D19: =D9/C9-1 -> 0.075263663 | E19: =E9/D9-1 -> 0.018724922 | F19: =F9/E9-1 -> 0.056892779 | G19: =G9/F9-1 -> 0.12111801 | H19: =H9/G9-1 -> 0.1567867 | I19: =I9/H9-1 -> 0.0052681992 | J19: =J9/I9-1 -> 0.036048912 | ... U19: =U9/T9-1 -> 0.12983251 | V19: ='Airbus Helicopters'!V3 -> 0.074576037 | W19: ='Airbus Helicopters'!W3 -> 0.051726993 | X19: ='Airbus Helicopters'!X3 -> 0.047291422 | Y19: ='Airbus Helicopters'!Y3 -> 0.045756289 | Z19: ='Airbus Helicopters'!Z3 -> 0.044382472 | AA19: ='Airbus Helicopters'!AA3 -> 0.043113818
A20: Astrium | C20: =C10/B10-1 -> #DIV/0! | D20: =D10/C10-1 -> #DIV/0! | E20: =E10/D10-1 -> #DIV/0! | F20: =F10/E10-1 -> #DIV/0! | G20: =G10/F10-1 -> #DIV/0! | H20: =H10/G10-1 -> #DIV/0! | I20: =I10/H10-1 -> -0.0056730273
A21: Cassidian | C21: =C11/B11-1 -> #DIV/0! | D21: =D11/C11-1 -> #DIV/0! | E21: =E11/D11-1 -> #DIV/0! | F21: =F11/E11-1 -> #DIV/0! | G21: =G11/F11-1 -> #DIV/0! | H21: =H11/G11-1 -> #DIV/0! | I21: =I11/H11-1 -> 0.041114983
A22: Airbus Defence & Space | I22: =I12/H12-1 -> 0.33002959 | J22: =J12/I12-1 -> -0.27566455 | K22: =K12/J12-1 -> 0.0042226488 | L22: =L12/K12-1 -> -0.093730887 | M22: =M12/L12-1 -> -0.088577695 | N22: =N12/M12-1 -> 0.023972603 | O22: =O12/N12-1 -> -0.014101058 | P22: =P12/O12-1 -> -0.042266434 | ... U22: =U12/T12-1 -> 0.10950174 | V22: ='Airbus Defence & Space'!V3 -> 0.0651 | W22: ='Airbus Defence & Space'!W3 -> 0.065138954 | X22: ='Airbus Defence & Space'!X3 -> 0.065177751 | Y22: ='Airbus Defence & Space'!Y3 -> 0.07987196 | Z22: ='Airbus Defence & Space'!Z3 -> 0.080108317 | AA22: ='Airbus Defence & Space'!AA3 -> 0.080340246
A23: other | C23: =C13/B13-1 -> #REF! | D23: =D13/C13-1 -> #REF! | E23: =E13/D13-1 -> #REF! | F23: =F13/E13-1 -> #REF! | G23: =G13/F13-1 -> #REF! | H23: =H13/G13-1 -> #REF! | I23: =I13/H13-1 -> 1.2019544 | J23: =J13/I13-1 -> -0.17455621 | ... U23: =U13/T13-1 -> 0 | V23: =-(V13/U13-1) -> -0.092194995 | W23: =-(W13/V13-1) -> -0.1376396 | X23: =-(X13/W13-1) -> -0.12371206 | Y23: =-(Y13/X13-1) -> -0.08403556 | Z23: =-(Z13/Y13-1) -> -0.050729576 | AA23: =-(AA13/Z13-1) -> -0.038940547
A24: Group | C24: =C14/B14-1 -> #REF! | D24: =D14/C14-1 -> #REF! | E24: =E14/D14-1 -> #REF! | F24: =F14/E14-1 -> #REF! | G24: =G14/F14-1 -> #REF! | H24: =H14/G14-1 -> #REF! | I24: =I14/H14-1 -> 0.1121813 | J24: =J14/I14-1 -> -0.033478732 | ... AA24: =AA14/Z14-1 -> 0.038940547
A26: Company defined EBIT Adjusted
A27: Airbus Commercial | D27: 2100 | E27: 1070 | F27: 295 | G27: ='Airbus Commercial'!G7 -> 485 | H27: ='Airbus Commercial'!H7 -> 1669 | I27: ='Airbus Commercial'!I7 -> 2216 | J27: ='Airbus Commercial'!J7 -> 2529 | K27: ='Airbus Commercial'!K7 -> 2766 | L27: ='Airbus Commercial'!L7 -> 2811 | M27: ='Airbus Commercial'!M7 -> 3554 | N27: ='Airbus Commercial'!N7 -> 4808 | ... U27: ='Airbus Commercial'!U7 -> 5470 | V27: =V7*V35 -> 5757.7436 | W27: =W7*W35 -> 7168.2228 | X27: =X7*X35 -> 9291.9898 | Y27: =Y7*Y35 -> 10716.437 | Z27: =Z7*Z35 -> 11317.255 | AA27: =AA7*AA35 -> 11676.606
A28: Airbus Helicopters | D28: 293 | E28: 263 | F28: 303 | G28: ='Airbus Helicopters'!G4 -> 259 | H28: ='Airbus Helicopters'!H4 -> 309 | I28: ='Airbus Helicopters'!I4 -> 397 | J28: ='Airbus Helicopters'!J4 -> 413 | K28: ='Airbus Helicopters'!K4 -> 427 | L28: ='Airbus Helicopters'!L4 -> 350 | M28: ='Airbus Helicopters'!M4 -> 337 | N28: ='Airbus Helicopters'!N4 -> 380 | ... U28: ='Airbus Helicopters'!U4 -> 925 | V28: =V37*V9 -> 989.36564 | W28: =W37*W9 -> 1055.2531 | X28: =X37*X9 -> 1124.5583 | Y28: =Y37*Y9 -> 1197.5089 | Z28: =Z37*Z9 -> 1290.4173 | AA28: =AA37*AA9 -> 1341.8893
A29: Airbus Defence & Space | H29: ='Airbus Defence & Space'!H4 -> 720 | I29: ='Airbus Defence & Space'!I4 -> 942 | J29: ='Airbus Defence & Space'!J4 -> 920 | K29: ='Airbus Defence & Space'!K4 -> 1051 | L29: ='Airbus Defence & Space'!L4 -> 1002 | M29: ='Airbus Defence & Space'!M4 -> 872 | N29: ='Airbus Defence & Space'!N4 -> 935 | O29: ='Airbus Defence & Space'!O4 -> 565 | ... U29: ='Airbus Defence & Space'!U4 -> 798 | V29: =V12*V40 -> 930.51314 | W29: =W12*W40 -> 1092.9178 | X29: =X12*X40 -> 1212.3087 | Y29: =Y12*Y40 -> 1375.709 | Z29: =Z12*Z40 -> 1554.7785 | AA29: =AA12*AA40 -> 1769.2296
A30: other | D30: =D31-SUM(D29,D28,D27) -> 937 | E30: =E31-SUM(E29,E28,E27) -> 815 | F30: =F31-SUM(F29,F28,F27) -> 743 | G30: =G31-SUM(G29,G28,G27) -> 1050 | H30: =H31-SUM(H29,H28,H27) -> 266 | I30: =I31-SUM(I29,I28,I27) -> 19 | J30: =J31-SUM(J29,J28,J27) -> 204 | K30: =K31-SUM(K29,K28,K27) -> -136 | L30: -208 | M30: -510 | N30: -289 | O30: -399 | P30: -43 | Q30: 64 | R30: 4 | S30: 56 | T30: 9 | U30: -65 | V30: =U30 -> -65 | W30: =V30+30 -> -35 | X30: =W30 -> -35 | Y30: =X30 -> -35 | Z30: =Y30 -> -35 | AA30: =Z30 -> -35
A31: Group | B31: 3556 | C31: 3614 | D31: 3330 | E31: 2148 | F31: 1341 | G31: 1794 | H31: 2964 | I31: 3574 | J31: 4066 | K31: 4108 | L31: =SUM(L27,L28,L29,L30) -> 3955 | M31: =SUM(M27,M28,M29,M30) -> 4253 | N31: =SUM(N27,N28,N29,N30) -> 5834 | O31: =SUM(O27,O28,O29,O30) -> 6946 | P31: =SUM(P27,P28,P29,P30) -> 1706 | Q31: =SUM(Q27,Q28,Q29,Q30) -> 4865 | R31: =SUM(R27,R28,R29,R30) -> 5627 | S31: =SUM(S27,S28,S29,S30) -> 5838 | ... AA31: =SUM(AA27,AA28,AA29,AA30) -> 14752.725
A33: EBIT margin
A34: Airbus Division | F34: =#REF!/F6 -> #REF! | G34: =#REF!/G6 -> #REF! | H34: =#REF!/H6 -> #REF! | I34: =#REF!/I6 -> #REF!
A35: Airbus Commercial | D35: =D27/D7 -> 0.079173579 | E35: =E27/E7 -> 0.040576413 | F35: =F27/F7 -> 0.01066021 | G35: =G27/G7 -> 0.015565326 | H35: =H27/H7 -> 0.044359983 | I35: =I27/I7 -> 0.055554163 | J35: =J27/J7 -> 0.059815516 | K35: =K27/K7 -> 0.060321891 | ... U35: =U27/U7 -> 0.10403789 | V35: ='Airbus Commercial'!V5 -> 0.0993646 | W35: ='Airbus Commercial'!W5 -> 0.10574992 | X35: ='Airbus Commercial'!X5 -> 0.11937983 | Y35: ='Airbus Commercial'!Y5 -> 0.126298 | Z35: ='Airbus Commercial'!Z5 -> 0.12757385 | AA35: ='Airbus Commercial'!AA5 -> 0.12784335
A36: Airbus Military | D36: =#REF!/D8 -> #REF! | E36: =#REF!/E8 -> #REF! | F36: =#REF!/F8 -> #REF! | G36: =#REF!/G8 -> #REF! | H36: =#REF!/H8 -> #REF! | I36: =#REF!/I8 -> #REF! | J36: =#REF!/J8 -> #REF! | K36: =#REF!/K8 -> #REF! | ... AA36: =#REF!/AA8 -> #REF!
A37: Airbus Helicopters | D37: =D28/D9 -> 0.065314311 | E37: =E28/E9 -> 0.057549234 | F37: =F28/F9 -> 0.062732919 | G37: =G28/G9 -> 0.047830102 | H37: =H28/H9 -> 0.049329502 | I37: =I28/I9 -> 0.063045895 | J37: =J28/J9 -> 0.063304721 | K37: =K28/K9 -> 0.062923666 | ... U37: =U28/U9 -> 0.10309853 | V37: ='Airbus Helicopters'!V5 -> 0.10261962 | W37: ='Airbus Helicopters'!W5 -> 0.1040704 | X37: ='Airbus Helicopters'!X5 -> 0.10589733 | Y37: ='Airbus Helicopters'!Y5 -> 0.1078329 | Z37: ='Airbus Helicopters'!Z5 -> 0.11126104 | AA37: ='Airbus Helicopters'!AA5 -> 0.11091695
A38: Astrium | D38: =#REF!/D10 -> #REF! | E38: =#REF!/E10 -> #REF! | F38: =#REF!/F10 -> #REF! | G38: =#REF!/G10 -> #REF! | H38: =#REF!/H10 -> #REF! | I38: =#REF!/I10 -> #REF! | J38: =#REF!/J10 -> #REF! | K38: =#REF!/K10 -> #REF! | ... AA38: =#REF!/AA10 -> #REF!
A39: Cassidian | D39: =#REF!/D11 -> #REF! | E39: =#REF!/E11 -> #REF! | F39: =#REF!/F11 -> #REF! | G39: =#REF!/G11 -> #REF! | H39: =#REF!/H11 -> #REF! | I39: =#REF!/I11 -> #REF! | J39: =#REF!/J11 -> #REF! | K39: =#REF!/K11 -> #REF! | ... AA39: =#REF!/AA11 -> #REF!
A40: Airbus Defence & Space | H40: =H29/H12 -> 0.053254438 | I40: =I29/I12 -> 0.052385719 | J40: =J29/J12 -> 0.070633397 | K40: =K29/K12 -> 0.080351682 | L40: =L29/L12 -> 0.084528429 | M40: =M29/M12 -> 0.080710848 | N40: =N29/N12 -> 0.084515954 | O40: =O29/O12 -> 0.051801595 | ... U40: =U29/U12 -> 0.059530026 | V40: ='Airbus Defence & Space'!V6 -> 0.065172639 | W40: ='Airbus Defence & Space'!W6 -> 0.07186609 | X40: ='Airbus Defence & Space'!X6 -> 0.074838947 | Y40: ='Airbus Defence & Space'!Y6 -> 0.078644574 | Z40: ='Airbus Defence & Space'!Z6 -> 0.082289306 | AA40: ='Airbus Defence & Space'!AA6 -> 0.086675932
A41: other | D41: =D30/D13 -> #REF! | E41: =E30/E13 -> #REF! | F41: =F30/F13 -> #REF! | G41: =G30/G13 -> #REF! | H41: =H30/H13 -> -0.43322476 | I41: =I30/I13 -> -0.014053254 | J41: =J30/J13 -> -0.1827957 | K41: =K30/K13 -> 0.10708661 | ... AA41: =AA30/AA13 -> 0.014720486
A42: Group | B42: =B31/B14 -> #REF! | C42: =C31/C14 -> #REF! | D42: =D31/D14 -> #REF! | E42: =E31/E14 -> #REF! | F42: =F31/F14 -> #REF! | G42: =G31/G14 -> #REF! | H42: =H31/H14 -> 0.052478754 | I42: =I31/I14 -> 0.056896332 | ... AA42: =AA31/AA14 -> 0.12145382
A44: EBIT Growth
A45: Airbus Commercial | C45: =IFERROR(C27/B27-1,"") | D45: =IFERROR(D27/C27-1,"") | E45: =IFERROR(E27/D27-1,"") -> -0.49047619 | F45: =IFERROR(F27/E27-1,"") -> -0.72429907 | G45: =IFERROR(G27/F27-1,"") -> 0.6440678 | H45: =IFERROR(H27/G27-1,"") -> 2.4412371 | I45: =IFERROR(I27/H27-1,"") -> 0.32774116 | J45: =IFERROR(J27/I27-1,"") -> 0.14124549 | ... AA45: =IFERROR(AA27/Z27-1,"") -> 0.031752475
A46: Airbus Helicopters | C46: =IFERROR(C28/B28-1,"") | D46: =IFERROR(D28/C28-1,"") | E46: =IFERROR(E28/D28-1,"") -> -0.10238908 | F46: =IFERROR(F28/E28-1,"") -> 0.15209125 | G46: =IFERROR(G28/F28-1,"") -> -0.14521452 | H46: =IFERROR(H28/G28-1,"") -> 0.19305019 | I46: =IFERROR(I28/H28-1,"") -> 0.28478964 | J46: =IFERROR(J28/I28-1,"") -> 0.040302267 | ... AA46: =IFERROR(AA28/Z28-1,"") -> 0.039887848
A47: Astrium | C47: =IFERROR(#REF!/#REF!-1,"") | D47: =IFERROR(#REF!/#REF!-1,"") | E47: =IFERROR(#REF!/#REF!-1,"") | F47: =IFERROR(#REF!/#REF!-1,"") | G47: =IFERROR(#REF!/#REF!-1,"") | H47: =IFERROR(#REF!/#REF!-1,"") | I47: =IFERROR(#REF!/#REF!-1,"") | J47: =IFERROR(#REF!/#REF!-1,"") | ... AA47: =IFERROR(#REF!/#REF!-1,"")
A48: Cassidian | C48: =IFERROR(#REF!/#REF!-1,"") | D48: =IFERROR(#REF!/#REF!-1,"") | E48: =IFERROR(#REF!/#REF!-1,"") | F48: =IFERROR(#REF!/#REF!-1,"") | G48: =IFERROR(#REF!/#REF!-1,"") | H48: =IFERROR(#REF!/#REF!-1,"") | I48: =IFERROR(#REF!/#REF!-1,"") | J48: =IFERROR(#REF!/#REF!-1,"") | ... AA48: =IFERROR(#REF!/#REF!-1,"")
A49: Airbus Defence & Space | I49: =I29/H29-1 -> 0.30833333 | J49: =J29/I29-1 -> -0.023354565 | K49: =K29/J29-1 -> 0.1423913 | L49: =L29/K29-1 -> -0.046622265 | M49: =M29/L29-1 -> -0.12974052 | N49: =N29/M29-1 -> 0.072247706 | O49: =O29/N29-1 -> -0.39572193 | P49: =P29/O29-1 -> 0.16814159 | ... AA49: =AA29/Z29-1 -> 0.13793032
A50: other | C50: =IFERROR(C30/B30-1,"") | D50: =IFERROR(D30/C30-1,"") | E50: =IFERROR(E30/D30-1,"") -> -0.13020277 | F50: =IFERROR(F30/E30-1,"") -> -0.088343558 | G50: =IFERROR(G30/F30-1,"") -> 0.41318977 | H50: =IFERROR(H30/G30-1,"") -> -0.74666667 | I50: =IFERROR(I30/H30-1,"") -> -0.92857143 | J50: =IFERROR(J30/I30-1,"") -> 9.7368421 | ... AA50: =IFERROR(AA30/Z30-1,"") -> 0
A51: Group | C51: =IFERROR(C31/B31-1,"") -> 0.016310461 | D51: =IFERROR(D31/C31-1,"") -> -0.078583287 | E51: =IFERROR(E31/D31-1,"") -> -0.35495495 | F51: =IFERROR(F31/E31-1,"") -> -0.37569832 | G51: =IFERROR(G31/F31-1,"") -> 0.33780761 | H51: =IFERROR(H31/G31-1,"") -> 0.65217391 | I51: =IFERROR(I31/H31-1,"") -> 0.20580297 | J51: =IFERROR(J31/I31-1,"") -> 0.13766088 | ... AA51: =IFERROR(AA31/Z31-1,"") -> 0.044259502
A53: Airbus Commercial sales excl A350 | I53: ='Airbus Commercial'!#REF! -> #REF! | J53: ='Airbus Commercial'!#REF! -> #REF! | K53: ='Airbus Commercial'!#REF! -> #REF! | L53: ='Airbus Commercial'!#REF! -> #REF! | M53: ='Airbus Commercial'!#REF! -> #REF! | N53: ='Airbus Commercial'!#REF! -> #REF! | O53: ='Airbus Commercial'!#REF! -> #REF! | P53: ='Airbus Commercial'!#REF! -> #REF! | Q53: ='Airbus Commercial'!#REF! -> #REF!
A54: Airbus Commercial EBIT pre one-offs excl A350 | I54: ='Airbus Commercial'!#REF! -> #REF! | J54: ='Airbus Commercial'!#REF! -> #REF! | K54: ='Airbus Commercial'!#REF! -> #REF! | L54: ='Airbus Commercial'!#REF! -> #REF! | M54: ='Airbus Commercial'!#REF! -> #REF! | N54: ='Airbus Commercial'!#REF! -> #REF! | O54: ='Airbus Commercial'!#REF! -> #REF! | P54: ='Airbus Commercial'!#REF! -> #REF! | Q54: ='Airbus Commercial'!#REF! -> #REF!
A55: margin | I55: =I54/I53 -> #REF! | J55: =J54/J53 -> #REF! | K55: =K54/K53 -> #REF! | L55: =L54/L53 -> #REF! | M55: =M54/M53 -> #REF! | N55: =N54/N53 -> #REF! | O55: =O54/O53 -> #REF! | P55: =P54/P53 -> #REF! | Q55: =Q54/Q53 -> #REF!
A56: profit growth | J56: =J54/I54-1 -> #REF! | K56: =K54/J54-1 -> #REF! | L56: =L54/K54-1 -> #REF! | M56: =M54/L54-1 -> #REF! | N56: =N54/M54-1 -> #REF! | O56: =O54/N54-1 -> #REF! | P56: =P54/O54-1 -> #REF! | Q56: =Q54/P54-1 -> #REF!
A57: Income Statement | B57: =B$2 -> 2006 | C57: =C$2 -> 2007 | D57: =D$2 -> 2008 | E57: =E$2 -> 2009 | F57: =F$2 -> 2010 | G57: =G$2 -> 2011 | H57: =H$2 -> 2012 | I57: =I$2 -> 2013 | ... AA57: =AA$2 -> 2031
A58: Sales | B58: 39434 | C58: 39123 | D58: 43265 | E58: 42822 | F58: 45752 | G58: 49128 | H58: 56480 | I58: =I14 -> 62816 | J58: 60713 | K58: 64450 | L58: =L14 -> 66581 | M58: =M14 -> 66767 | N58: =N14 -> 63707 | O58: =O14 -> 70478 | P58: =P14 -> 49912 | Q58: =Q14 -> 52149 | R58: =R14 -> 58763 | S58: =S14 -> 65446 | ... AA58: =AA14 -> 121467.77
A59: YoY growth (%) | C59: =C58/B58-1 -> -0.0078865953 | D59: =D58/C58-1 -> 0.10587123 | E59: =E58/D58-1 -> -0.010239223 | F59: =F58/E58-1 -> 0.068422773 | G59: =G58/F58-1 -> 0.073789124 | H59: =H58/G58-1 -> 0.14964989 | I59: =I58/H58-1 -> 0.1121813 | J59: =J58/I58-1 -> -0.033478732 | ... AA59: =AA58/Z58-1 -> 0.038940547
A60: Cost of sales | B60: -34722 | C60: -34802 | D60: -35907 | E60: -38383 | F60: -39528 | G60: -42285 | H60: -48582 | I60: -50895 | J60: -51776 | K60: -55599 | L60: -61317 | M60: -59160 | N60: -54920 | O60: =-59973 -> -59973 | P60: -44250 | Q60: -42518 | R60: -48192 | S60: -55402 | T60: -58555 | U60: -62453 | V60: =V62-V58 -> -67352.372 | W60: =W62-W58 -> -76285.047 | X60: =X62-X58 -> -84800.188 | Y60: =Y62-Y58 -> -91245.51 | Z60: =Z62-Z58 -> -95982.214 | AA60: =AA62-AA58 -> -99647.029
A61: as a % of sales | Q61: =-Q60/Q58 -> 0.81531765 | R61: =-R60/R58 -> 0.82010789 | S61: =-S60/S58 -> 0.84652996 | T61: =-T60/T58 -> 0.84580384 | U61: =-U60/U58 -> 0.84952731 | V61: =-V60/V58 -> 0.83883541 | W61: =-W60/W58 -> 0.83513863 | X61: =-X60/X58 -> 0.82615385 | ... AA61: =-AA60/AA58 -> 0.82035776
A62: Gross Profit | B62: =B58+B60 -> 4712 | C62: =C58+C60 -> 4321 | D62: =D58+D60 -> 7358 | E62: =E58+E60 -> 4439 | F62: =F58+F60 -> 6224 | G62: =G58+G60 -> 6843 | H62: =H58+H60 -> 7898 | I62: =I58+I60 -> 11921 | ... L62: =L58+L60 -> 5264 | M62: 7607 | N62: 8787 | O62: =10505 -> 10505 | P62: 5662 | Q62: 9631 | R62: =10571 -> 10571 | S62: 10044 | T62: 10675 | U62: 10967 | V62: =V76-V64-V66-V68-V70-V72-V74-V75 -> 12940.343 | W62: =W76-W64-W66-W68-W70-W72-W74-W75 -> 15059.125 | X62: =X76-X64-X66-X68-X70-X72-X74-X75 -> 17844.359 | Y62: =Y76-Y64-Y66-Y68-Y70-Y72-Y74-Y75 -> 20024.83 | Z62: =Z76-Z64-Z66-Z68-Z70-Z72-Z74-Z75 -> 20932.822 | AA62: =AA76-AA64-AA66-AA68-AA70-AA72-AA74-AA75 -> 21820.743
A63: Gross margin (%) | B63: =B62/B$58 -> 0.11949079 | C63: =C62/C$58 -> 0.11044654 | D63: =D62/D$58 -> 0.17006818 | E63: =E62/E$58 -> 0.10366167 | F63: =F62/F$58 -> 0.13603777 | G63: =G62/G$58 -> 0.1392892 | H63: =H62/H$58 -> 0.13983711 | I63: =I62/I$58 -> 0.18977649 | ... AA63: =AA62/AA$58 -> 0.17964224
A64: Selling expenses | B64: -914 | C64: -864 | D64: -933 | E64: -924 | F64: -1024 | G64: -981 | H64: -1197 | I64: -1217 | J64: -1063 | K64: -1065 | L64: -997 | M64: -872 | N64: -861 | O64: -908 | P64: -717 | Q64: -713 | R64: -788 | S64: -867 | T64: -877 | U64: -856 | V64: =V65*V$58 -> -934.91892 | W64: =W65*W$58 -> -1063.6008 | X64: =X65*X$58 -> -1195.181 | Y64: =Y65*Y$58 -> -1295.6187 | Z64: =Z65*Z$58 -> -1361.3449 | AA64: =AA65*AA$58 -> -1414.3564
A65: as a % of sales | B65: =B64/B$58 -> -0.023177968 | C65: =C64/C$58 -> -0.022084196 | D65: =D64/D$58 -> -0.021564775 | E65: =E64/E$58 -> -0.021577694 | F65: =F64/F$58 -> -0.022381535 | G65: =G64/G$58 -> -0.019968246 | H65: =H64/H$58 -> -0.021193343 | I65: =I64/I$58 -> -0.019374045 | ... U65: =U64/U$58 -> -0.011643882 | V65: =U65 -> -0.011643882 | W65: =V65 -> -0.011643882 | X65: =W65 -> -0.011643882 | Y65: =X65 -> -0.011643882 | Z65: =Y65 -> -0.011643882 | AA65: =Z65 -> -0.011643882
A66: Administrative expenses | B66: -1360 | C66: -1314 | D66: -1253 | E66: -1272 | F66: -1288 | G66: -1427 | H66: -1672 | I66: -1696 | J66: -1538 | K66: -1586 | L66: -1726 | M66: -1567 | N66: -1574 | O66: -5217 | P66: -1423 | Q66: -1339 | R66: -1452 | S66: -1654 | T66: -1744 | U66: -1722 | V66: =V58*V67 -> -1766.4397 | W66: =W58*W67 -> -2009.5718 | X66: =X58*X67 -> -2258.18 | Y66: =Y58*Y67 -> -2447.9475 | Z66: =Z58*Z67 -> -2572.1308 | AA66: =AA58*AA67 -> -2672.291
A67: as a % of sales | B67: =B66/B$58 -> -0.034488005 | C67: =C66/C$58 -> -0.033586381 | D67: =D66/D$58 -> -0.028961054 | E67: =E66/E$58 -> -0.029704358 | F67: =F66/F$58 -> -0.028151775 | G67: =G66/G$58 -> -0.029046572 | H67: =H66/H$58 -> -0.029603399 | I67: =I66/I58 -> -0.026999491 | J67: =J66/J58 -> -0.025332301 | K67: =K66/K58 -> -0.024608223 | L67: =L66/L58 -> -0.025923311 | M67: =M66/M58 -> -0.023469678 | N67: =N66/N58 -> -0.024706861 | O67: =O66/O58 -> -0.074023099 | P67: =P66/P58 -> -0.028510178 | ... U67: =U66/U58 -> -0.023423791 | V67: -0.022 | W67: =V67 -> -0.022 | X67: =W67 -> -0.022 | Y67: =X67 -> -0.022 | Z67: =Y67 -> -0.022 | AA67: =Z67 -> -0.022
A68: R&D expenses | B68: =-2458 -> -2458 | C68: -2608 | D68: -2669 | E68: -2825 | F68: -2939 | G68: -3152 | H68: -3142 | I68: -3160 | J68: -3391 | K68: -3460 | L68: -2970 | M68: -2807 | N68: -3217 | O68: -3358 | P68: -2858 | Q68: -2746 | R68: -3079 | S68: -3257 | T68: -3250 | U68: -3153 | V68: =V58*V69 -> -3532.8795 | W68: =W58*W69 -> -3700.9006 | X68: =X58*X69 -> -3885.7706 | Y68: =Y58*Y69 -> -4190.5029 | Z68: =Z58*Z69 -> -4092.0263 | AA68: =AA58*AA69 -> -4251.372
A69: as a % of sales | B69: =B68/B$58 -> -0.062331998 | C69: =C68/C$58 -> -0.066661555 | D69: =D68/D$58 -> -0.061689587 | E69: =E68/E$58 -> -0.065970763 | F69: =F68/F$58 -> -0.064237629 | G69: =G68/G$58 -> -0.064158932 | H69: =H68/H$58 -> -0.055630312 | I69: =I68/I$58 -> -0.050305655 | ... U69: =U68/U$58 -> -0.042889206 | V69: -0.044 | W69: -0.040516002 | X69: -0.037856571 | Y69: -0.037660556 | Z69: -0.035 | AA69: -0.035
A70: Other Income | B70: 297 | C70: 233 | D70: 189 | E70: 170 | F70: 171 | G70: 359 | H70: 184 | I70: 236 | J70: 330 | K70: 474 | L70: 2689 | M70: 981 | N70: 1656 | O70: 370 | P70: 132 | Q70: 594 | R70: 471 | S70: 243 | T70: 303 | U70: 979 | V70: =V71*V$58 -> 1069.2589 | W70: =W71*W$58 -> 1216.4313 | X70: =X71*X$58 -> 1366.9185 | Y70: =Y71*Y$58 -> 1481.7882 | Z70: =Z71*Z$58 -> 1556.9587 | AA70: =AA71*AA$58 -> 1617.5876
A71: as a % of sales | B71: =B70/B$58 -> 0.0075315717 | C71: =C70/C$58 -> 0.005955576 | D71: =D70/D$58 -> 0.0043684271 | E71: =E70/E$58 -> 0.003969922 | F71: =F70/F$58 -> 0.0037375415 | G71: =G70/G$58 -> 0.0073074418 | H71: =H70/H$58 -> 0.0032577904 | I71: =I70/I$58 -> 0.0037570046 | ... U71: =U70/U$58 -> 0.01331701 | V71: =U71 -> 0.01331701 | W71: =V71 -> 0.01331701 | X71: =W71 -> 0.01331701 | Y71: =X71 -> 0.01331701 | Z71: =Y71 -> 0.01331701 | AA71: =Z71 -> 0.01331701
A72: Other expenses | B72: -188 | C72: -97 | D72: -131 | E72: -102 | F72: -102 | G72: -221 | H72: -229 | I72: -263 | J72: -179 | K72: -222 | L72: -254 | M72: -336 | N72: -182 | O72: -356 | P72: -1458 | Q72: -201 | R72: -590 | S72: -209 | T72: -197 | U72: -488 | V72: =V73*V$58 -> -532.99116 | W72: =W73*W$58 -> -606.35185 | X72: =X73*X$58 -> -681.36488 | Y72: =Y73*Y$58 -> -738.62376 | Z72: =Z73*Z$58 -> -776.09383 | AA72: =AA73*AA$58 -> -806.31535
A73: as a % of sales | B73: =B72/B$58 -> -0.0047674596 | C73: =C72/C$58 -> -0.00247936 | D73: =D72/D$58 -> -0.0030278516 | E73: =E72/E$58 -> -0.0023819532 | F73: =F72/F$58 -> -0.0022294107 | G73: =G72/G$58 -> -0.004498453 | H73: =H72/H$58 -> -0.0040545326 | I73: =I72/I$58 -> -0.0041868314 | ... U73: =U72/U$58 -> -0.0066381011 | V73: =U73 -> -0.0066381011 | W73: =V73 -> -0.0066381011 | X73: =W73 -> -0.0066381011 | Y73: =X73 -> -0.0066381011 | Z73: =Y73 -> -0.0066381011 | AA73: =Z73 -> -0.0066381011
A74: Share of profit from associates accounted for under the equity method | B74: 152 | C74: 210 | D74: 188 | E74: 115 | F74: 127 | G74: 164 | H74: 247 | I74: 346 | J74: =895-J75 -> 840 | K74: =1070-K75 -> 1016 | L74: 231 | M74: 333 | N74: 330 | O74: 299 | P74: 39 | Q74: 40 | R74: 134 | S74: 267 | T74: 350 | U74: 305 | V74: =U74*(1.05) -> 320.25 | W74: =V74*(1.05) -> 336.2625 | X74: =W74*(1.05) -> 353.07563 | Y74: =X74*(1.05) -> 370.72941 | Z74: =Y74*(1.05) -> 389.26588 | AA74: =Z74*(1.05) -> 408.72917
A75: Other income from investments | B75: 37 | C75: 86 | D75: 23 | E75: 19 | F75: 18 | G75: 28 | H75: 0 | I75: 0 | J75: 55 | K75: 54 | L75: 21 | M75: 82 | N75: 109 | O75: 4 | P75: 113 | Q75: 76 | R75: 58 | S75: 36 | T75: 44 | U75: 50 | V75: 50 | W75: 50 | X75: 50 | Y75: 50 | Z75: 50 | AA75: 50
A76: EBIT (Reported) | B76: =B62+B64+B66+B68+B70+B72+B74+B75 -> 278 | C76: =C62+C64+C66+C68+C70+C72+C74+C75 -> -33 | D76: =D62+D64+D66+D68+D70+D72+D74+D75 -> 2772 | E76: =E62+E64+E66+E68+E70+E72+E74+E75 -> -380 | F76: =F62+F64+F66+F68+F70+F72+F74+F75 -> 1187 | G76: =G62+G64+G66+G68+G70+G72+G74+G75 -> 1613 | H76: =H62+H64+H66+H68+H70+H72+H74+H75 -> 2089 | I76: =I62+I64+I66+I68+I70+I72+I74+I75 -> 6167 | ... U76: =U62+U64+U66+U68+U70+U72+U74+U75 -> 6082 | V76: =V31 -> 7612.6223 | W76: =W31 -> 9281.3937 | X76: =X31 -> 11593.857 | Y76: =Y31 -> 13254.654 | Z76: =Z31 -> 14127.451 | AA76: =AA31 -> 14752.725
A77: add back one-offs (negatives = deductions, positives = addbacks) | B77: =SUM(B78:B83) -> 3157 | C77: =SUM(C78:C83) -> 3562 | D77: =SUM(D78:D83) -> 500 | E77: =SUM(E78:E83) -> 2470 | F77: =SUM(F78:F83) -> 110 | G77: =SUM(G78:G83) -> 98 | H77: =SUM(H78:H83) -> 820 | I77: =SUM(I78:I83) -> 913 | ... AA77: =SUM(AA78:AA83) -> 0
A78: of which A400M charges | B78: 352 | C78: 1088 | D78: 800 | E78: 1820 | J78: 560 | K78: 290 | L78: 2210 | M78: 1299 | N78: 436 | O78: 1212 | Q78: 212 | R78: 477 | S78: 41 | T78: 121 | Z78: ,
A79: of which A380 provisions | B79: 2300 | C79: 1000 | D79: 1000 | E79: 240 | G79: 200 | H79: 251 | I79: 85 | L79: 0 | M79: 0 | N79: 463 | O79: 202 | P79: 385 | Q79: -274 | R79: -28 | S79: 0 | T79: 0 | U79: 0 | V79: 0 | W79: 0 | X79: 0 | Y79: 0 | Z79: 0 | AA79: 0
A80: of which A350 provisions | B80: 505 | C80: 850 | H80: 124 | I80: 434 | L80: 385 | M80: 0 | N80: 0 | O80: 0 | P80: 0 | Q80: 0 | R80: 0 | S80: 0 | T80: 0 | U80: 0 | V80: 0 | W80: 0 | X80: 0 | Y80: 0 | Z80: 0 | AA80: 0
A81: operational impact adjustments from all divisions | U81: =296+154-28 -> 422
A82: of which mark-to-mkt on provisions for LMCs | D82: -900 | E82: 50 | F82: -30
A83: of which other EADS defined one-offs/other | C83: 624 | D83: -400 | E83: 360 | F83: 140 | G83: -102 | H83: 445 | I83: =102+292 -> 394 | J83: =-142-343 -> -485 | K83: =635-748-41-90 -> -244 | L83: =930+33+182-1175-868 -> -898 | M83: =117+7-7+20-604 -> -467 | N83: =123-188-129+81 -> -113 | O83: =3598+221+170+103+101 -> 4193 | P83: =1202+480+149 -> 1831 | Q83: =-(331-38+122) -> -415 | R83: =-(-79-82+308) -> -147 | S83: =1030+75+89 -> 1194 | T83: =-101-51+40+41 -> -71 | U83: 624
A84: EBIT Adjusted (Company defined) | B84: =B151-B77 -> 399 | C84: =C151-C77 -> 52 | D84: =D151-D77 -> 2830 | E84: =E151-E77 -> -322 | F84: =F151-F77 -> 1231 | G84: =G151-G77 -> 1696 | H84: =H151-H77 -> 2144 | I84: =I151-I77 -> 2661 | J84: =J76+J77 -> 4066 | K84: =K76+K77 -> 4108 | L84: =L76+L77 -> 3955 | M84: =M76+M77 -> 4253 | N84: =N76+N77 -> 5834 | O84: =O76+O77 -> 6946 | P84: =P76+P77 -> 1706 | Q84: =Q76+Q77 -> 4865 | ... AA84: =AA76+AA77 -> 14752.725
A85: Adj. EBIT margin (%) | B85: =B76/B$58 -> 0.007049754 | C85: =C76/C$58 -> -0.0008434936 | D85: =D76/D$58 -> 0.064070265 | E85: =E76/E$58 -> -0.0088739433 | F85: =F76/F$58 -> 0.025944221 | G85: =G76/G$58 -> 0.032832601 | H85: =H76/H$58 -> 0.036986544 | I85: =I76/I$58 -> 0.098175624 | ... AA85: =AA76/AA$58 -> 0.12145382
A86: Financing (expense)/gain | B86: =SUM(B87:B89) -> -244 | C86: =SUM(C87:C89) -> -737 | D86: =SUM(D87:D89) -> -472 | E86: =SUM(E87:E89) -> -592 | F86: =SUM(F87:F89) -> -371 | G86: =SUM(G87:G89) -> -220 | H86: =SUM(H87:H89) -> -453 | I86: =SUM(I87:I89) -> -630 | ... L86: =SUM(L87:L89) -> -967 | M86: 1149 | N86: =SUM(N87:N89) -> -763 | O86: =SUM(O87:O89) -> -275 | P86: =SUM(P87:P89) -> -620 | Q86: =SUM(Q87:Q89) -> -315 | R86: =SUM(R87:R89) -> -250 | S86: =SUM(S87:S89) -> 166 | T86: =SUM(T87:T89) -> 121 | U86: =SUM(U87:U89) -> 268 | ... AA86: =SUM(AA87:AA89) -> 753.47344
A87: interest income | B87: 454 | C87: 502 | D87: 617 | E87: 356 | F87: 316 | G87: 377 | H87: 237 | I87: 168 | J87: 142 | K87: 183 | L87: 247 | M87: 189 | N87: 208 | O87: 228 | P87: 140 | Q87: 88 | R87: 180 | S87: 728 | T87: 802 | U87: 710 | V87: =V134 -> 649.888 | W87: =W134 -> 673.03517 | X87: =X134 -> 701.74226 | Y87: =Y134 -> 770.42669 | Z87: =Z134 -> 1014.2026 | AA87: =AA134 -> 1274.6244
A88: interest expense | B88: -575 | C88: -701 | D88: -581 | E88: -503 | F88: -415 | G88: -364 | H88: -522 | I88: -497 | J88: -462 | K88: -551 | L88: -522 | M88: -517 | N88: -440 | O88: -339 | P88: -411 | Q88: -334 | R88: -412 | S88: -753 | T88: -900 | U88: -770 | V88: =V133 -> -740.948 | W88: =W133 -> -689.95 | X88: =X133 -> -649.296 | Y88: =Y133 -> -609.73 | Z88: =Z133 -> -558.269 | AA88: =AA133 -> -521.151
A89: other financing costs | B89: -123 | C89: -538 | D89: -508 | E89: -445 | F89: -272 | G89: -233 | H89: -168 | I89: -301 | J89: -458 | K89: -319 | L89: -692 | M89: 1477 | N89: -531 | O89: -164 | P89: -349 | Q89: -69 | R89: -18 | S89: 191 | T89: 219 | U89: 328
A90: Reported profit/(loss) before tax | B90: =B76+B86 -> 34 | C90: =C76+C86 -> -770 | D90: =D76+D86 -> 2300 | E90: =E76+E86 -> -972 | F90: =F76+F86 -> 816 | G90: =G76+G86 -> 1393 | H90: =H76+H86 -> 1636 | I90: =I76+I86 -> 5537 | ... AA90: =AA76+AA86 -> 15506.198
A91: as a % of sales | B91: =B90/B$58 -> 0.00086220013 | C91: =C90/C$58 -> -0.019681517 | D91: =D90/D$58 -> 0.053160753 | E91: =E90/E$58 -> -0.022698613 | F91: =F90/F$58 -> 0.017835286 | G91: =G90/G$58 -> 0.028354503 | H91: =H90/H$58 -> 0.028966006 | I91: =I90/I$58 -> 0.088146332 | ... AA91: =AA90/AA$58 -> 0.12765689
A92: Adj. total interest income/(expense) | J92: -437 | K92: -469 | L92: -340 | M92: -377 | N92: -276 | O92: -157 | P92: -296 | Q92: -265 | R92: -224 | S92: -28 | T92: -97 | U92: =710-770+22 -> -38 | V92: =V86 -> -91.06 | W92: =W86 -> -16.914826 | X92: =X86 -> 52.446265 | Y92: =Y86 -> 160.69669 | Z92: =Z86 -> 455.93357 | AA92: =AA86 -> 753.47344
A93: Adjusted profit/(loss) before tax | J93: =J84+J92 -> 3629 | K93: =K84+K92 -> 3639 | L93: =L84+L92 -> 3615 | M93: =M84+M92 -> 3876 | N93: =N84+N92 -> 5558 | O93: =O84+O92 -> 6789 | P93: =P84+P92 -> 1410 | Q93: =Q84+Q92 -> 4600 | ... AA93: =AA84+AA92 -> 15506.198
A94: Reported tax | B94: 81 | C94: 333 | D94: -703 | E94: 220 | F94: -244 | G94: -356 | H94: -438 | I94: -502 | J94: -863 | K94: -677 | L94: -291 | M94: -1693 | N94: -1274 | O94: -2389 | P94: -39 | Q94: -853 | R94: -939 | S94: -1156 | T94: -1347 | U94: -1390 | V94: =V97*V90 -> -2030.5036 | W94: =W97*W90 -> -2501.0173 | X94: =X97*X90 -> -3144.009 | Y94: =Y97*Y90 -> -3621.5772 | Z94: =Z97*Z90 -> -3936.8967 | AA94: =AA97*AA90 -> -4186.0174
A95: Underlying Tax | J95: -988 | K95: -975 | L95: -1048 | M95: -1276.7 | N95: -1556 | O95: -2037 | P95: -381 | Q95: -1242 | R95: -1459 | S95: -1569 | T95: -1419 | U95: -1914 | V95: =V93*V97 -> -2030.5036 | W95: =W93*W97 -> -2501.0173 | X95: =X93*X97 -> -3144.009 | Y95: =Y93*Y97 -> -3621.5772 | Z95: =Z93*Z97 -> -3936.8967 | AA95: =AA93*AA97 -> -4186.0174
A96: Reported tax rate | B96: =B94/B90 -> 2.3823529 | C96: =C94/C90 -> -0.43246753 | D96: =D94/D90 -> -0.30565217 | E96: =E94/E90 -> -0.22633745 | F96: =F94/F90 -> -0.29901961 | G96: =G94/G90 -> -0.25556353 | H96: =H94/H90 -> -0.26772616 | I96: =I94/I90 -> -0.090662814 | ... U96: =U94/U90 -> -0.21889764
A97: Adjusted tax rate | J97: =J95/J93 -> -0.27225131 | K97: =K95/K93 -> -0.26793075 | L97: =L95/L93 -> -0.28990318 | M97: =M95/M93 -> -0.32938596 | N97: =N95/N93 -> -0.27995682 | O97: =O95/O93 -> -0.30004419 | P97: =P95/P93 -> -0.27021277 | Q97: =Q95/Q93 -> -0.27 | ... U97: =U95/U93 -> -0.26995769 | V97: =U97 -> -0.26995769 | W97: =V97 -> -0.26995769 | X97: =W97 -> -0.26995769 | Y97: =X97 -> -0.26995769 | Z97: =Y97 -> -0.26995769 | AA97: =Z97 -> -0.26995769
A98: Reported (Loss)/profit after tax for the year from continuing operations | B98: =B94+B90 -> 115 | C98: =C94+C90 -> -437 | D98: =D94+D90 -> 1597 | E98: =E94+E90 -> -752 | F98: =F94+F90 -> 572 | G98: =G94+G90 -> 1037 | H98: =H94+H90 -> 1198 | I98: =I94+I90 -> 5035 | ... AA98: =AA94+AA90 -> 11320.181
A99: Adjusted (Loss)/profit after tax for the year from continuing operations | J99: =J93+J95 -> 2641 | K99: =K93+K95 -> 2664 | L99: =L93+L95 -> 2567 | M99: =M93+M95 -> 2599.3 | N99: =N93+N95 -> 4002 | O99: =O93+O95 -> 4752 | P99: =P93+P95 -> 1029 | Q99: =Q93+Q95 -> 3358 | ... AA99: =AA93+AA95 -> 11320.181
A101: Reported net income (attributable to shareholders) | B101: =B98-B103 -> 99 | C101: =C98-C103 -> -446 | D101: =D98-D103 -> 1572 | E101: =E98-E103 -> -763 | F101: =F98-F103 -> 553 | G101: =G98-G103 -> 1033 | H101: =H98-H103 -> 1197 | I101: =I98-I103 -> 5025 | ... L101: =L98-L103 -> 995 | M101: 2873 | N101: 3054 | O101: -1362 | P101: -1133 | Q101: =Q98-Q103 -> 4213 | R101: =R98-R103 -> 4247 | S101: =S98-S103 -> 3788.5 | T101: =T98-T103 -> 4232 | U101: =U98-U103 -> 5221 | V101: =V98-V103 -> 5752.0588 | W101: =W98-W103 -> 7024.4616 | X101: =X98-X103 -> 8763.294 | ... AA101: =AA98-AA103 -> 11581.181
A102: Adjusted net income (attributable to shareholders) | J102: =J99-J103 -> 2634 | K102: =K99-K103 -> 2662 | L102: =L99-L103 -> 2562 | M102: =M99-M103 -> 2595.3 | N102: =N99-N103 -> 4045 | O102: =O99-O103 -> 4715 | P102: =P99-P103 -> 1065 | Q102: =Q99-Q103 -> 3397 | ... AA102: =AA99-AA103 -> 11581.181
A103: Attributable to Non-controlling interests | B103: 16 | C103: 9 | D103: 25 | E103: 11 | F103: 19 | G103: 4 | H103: 1 | I103: 10 | J103: 7 | K103: 2 | L103: 5 | M103: 4 | N103: -43 | O103: 37 | P103: -36 | Q103: -39 | R103: -111 | S103: -175.5 | T103: -154 | U103: -261 | V103: =U103 -> -261 | W103: =V103 -> -261 | X103: =W103 -> -261 | Y103: =X103 -> -261 | Z103: =Y103 -> -261 | AA103: =Z103 -> -261
A105: Earning per shares (EPS)
A106: Reported EPS - Basic | B106: =B101/B113*1000 -> 0.12372136 | C106: =C101/C113*1000 -> -0.55532851 | D106: =D101/D113*1000 -> 1.9480066 | E106: =E101/E113*1000 -> -0.94232591 | F106: =F101/F113*1000 -> 0.68213216 | G106: =G101/G113*1000 -> 1.2713732 | H106: =H101/H113*1000 -> 1.4608637 | I106: =I101/I113*1000 -> 6.3409592 | ... AA106: =AA101/AA113*1000 -> 15.173361
A107: Reported EPS - Diluted | B107: =B101/B114*1000 -> 0.123086 | C107: =C101/C114*1000 -> -0.55366009 | D107: =D101/D114*1000 -> 1.9465155 | E107: =E101/E114*1000 -> -0.94059332 | F107: =F101/F114*1000 -> 0.6819281 | G107: =G101/G114*1000 -> 1.2695067 | H107: =H101/H114*1000 -> 1.4587742 | I107: =I101/I114*1000 -> 6.3276968 | ... AA107: =AA101/AA114*1000 -> 15.147187
A108: Underlying EPS - Basic | J108: =J$102/J113*1000 -> 3.3641463 | K108: =K$102/K113*1000 -> 3.3884019 | L108: =L$102/L113*1000 -> 3.310938 | M108: =M$102/M113*1000 -> 3.3540858 | N108: =N$102/N113*1000 -> 5.2182241 | O108: =O$102/O113*1000 -> 6.0678998 | P108: =P$102/P113*1000 -> 1.3598438 | Q108: =Q$102/Q113*1000 -> 4.3255918 | ... AA108: =AA$102/AA113*1000 -> 15.173361
...

Sheet Cash Flow Statement
A1: ='DCF Valuation'!D51 -> 240
A2: Cash Flow Statement | B2: ='Income Statement'!B2 -> 2006 | C2: ='Income Statement'!C2 -> 2007 | D2: ='Income Statement'!D2 -> 2008 | E2: ='Income Statement'!E2 -> 2009 | F2: ='Income Statement'!F2 -> 2010 | G2: ='Income Statement'!G2 -> 2011 | H2: ='Income Statement'!H2 -> 2012 | I2: ='Income Statement'!I2 -> 2013 | ... T2: ='Income Statement'!T2 -> 2024 | U2: =T2+1 -> 2025 | V2: =U2+1 -> 2026 | W2: =V2+1 -> 2027 | X2: =W2+1 -> 2028 | Y2: =X2+1 -> 2029 | Z2: =Y2+1 -> 2030 | AA2: =Z2+1 -> 2031
A4: Net Income | B4: ='Income Statement'!B101 -> 99 | C4: ='Income Statement'!C101 -> -446 | D4: ='Income Statement'!D101 -> 1572 | E4: ='Income Statement'!E101 -> -763 | F4: ='Income Statement'!F101 -> 553 | G4: ='Income Statement'!G101 -> 1033 | H4: ='Income Statement'!H101 -> 1197 | I4: ='Income Statement'!I101 -> 5025 | ... AA4: ='Income Statement'!AA101 -> 11581.181
A5: Profit to Non-controlling interests | B5: 16 | C5: 9 | D5: 25 | E5: 11 | F5: 19 | G5: 4 | H5: 1 | I5: ='Income Statement'!I103 -> 10 | J5: ='Income Statement'!J103 -> 7 | K5: ='Income Statement'!K103 -> 2 | L5: ='Income Statement'!L103 -> 5 | M5: ='Income Statement'!M103 -> 4 | N5: ='Income Statement'!N103 -> -43 | O5: ='Income Statement'!O103 -> 37 | P5: ='Income Statement'!P103 -> -36 | ... AA5: ='Income Statement'!AA103 -> -261
A6: Interest income | B6: -454 | C6: -502 | D6: -617 | E6: -356 | F6: -316 | G6: -377 | H6: -237 | I6: =-'Income Statement'!I87 -> -168 | J6: =-'Income Statement'!J87 -> -142 | K6: =-'Income Statement'!K87 -> -183 | L6: =-'Income Statement'!L87 -> -247 | M6: =-'Income Statement'!M87 -> -189 | N6: =-'Income Statement'!N87 -> -208 | O6: =-'Income Statement'!O87 -> -228 | P6: =-'Income Statement'!P87 -> -140 | ... AA6: =-'Income Statement'!AA87 -> -1274.6244
A7: Interest expense | B7: 575 | C7: 701 | D7: 581 | E7: 503 | F7: 415 | G7: 364 | H7: 522 | I7: =-'Income Statement'!I88 -> 497 | J7: =-'Income Statement'!J88 -> 462 | K7: =-'Income Statement'!K88 -> 551 | L7: =-'Income Statement'!L88 -> 522 | M7: =-'Income Statement'!M88 -> 517 | N7: =-'Income Statement'!N88 -> 440 | O7: =-'Income Statement'!O88 -> 339 | P7: =-'Income Statement'!P88 -> 411 | ... AA7: =-'Income Statement'!AA88 -> 521.151
A8: Interest received | B8: 380 | C8: 480 | D8: 657 | E8: 382 | F8: 332 | G8: 417 | H8: 198 | I8: 119 | J8: 99 | K8: 131 | L8: 139 | M8: 149 | N8: 186 | O8: 151 | P8: 82 | Q8: 111 | R8: 250 | S8: 690 | T8: 681 | U8: 607 | V8: ='Income Statement'!V87 -> 649.888 | W8: ='Income Statement'!W87 -> 673.03517 | X8: ='Income Statement'!X87 -> 701.74226 | Y8: ='Income Statement'!Y87 -> 770.42669 | Z8: ='Income Statement'!Z87 -> 1014.2026 | AA8: ='Income Statement'!AA87 -> 1274.6244
A9: Interest paid | B9: -271 | C9: -370 | D9: -471 | E9: -331 | F9: -278 | G9: -307 | H9: -351 | I9: -323 | J9: -303 | K9: -388 | L9: -378 | M9: -501 | N9: -292 | O9: -187 | P9: -205 | Q9: -330 | R9: -322 | S9: -606 | T9: -786 | U9: -651 | V9: ='Income Statement'!V88 -> -740.948 | W9: ='Income Statement'!W88 -> -689.95 | X9: ='Income Statement'!X88 -> -649.296 | Y9: ='Income Statement'!Y88 -> -609.73 | Z9: ='Income Statement'!Z88 -> -558.269 | AA9: ='Income Statement'!AA88 -> -521.151
A10: Income tax expense | B10: -81 | C10: -333 | D10: 703 | E10: -220 | F10: 244 | G10: 356 | H10: 449 | I10: =-'Income Statement'!I94 -> 502 | J10: =-'Income Statement'!J94 -> 863 | K10: 677 | L10: =-'Income Statement'!L94 -> 291 | M10: =-'Income Statement'!M94 -> 1693 | N10: =-'Income Statement'!N94 -> 1274 | O10: =-'Income Statement'!O94 -> 2389 | P10: =-'Income Statement'!P94 -> 39 | Q10: =-'Income Statement'!Q94 -> 853 | R10: =-'Income Statement'!R94 -> 939 | S10: =-'Income Statement'!S94 -> 1156 | ... AA10: =-'Income Statement'!AA94 -> 4186.0174
A11: Income taxes paid | B11: -239 | C11: 36 | D11: -252 | E11: 4 | F11: -140 | G11: -100 | H11: -219 | I11: ='Income Statement'!I189 -> 0 | J11: -115 | K11: -595 | L11: -559 | M11: -152 | N11: -897 | O11: -1476 | P11: 79 | Q11: -321 | R11: -790 | S11: -544 | T11: -947 | U11: -965 | V11: ='Income Statement'!V94 -> -2030.5036 | W11: ='Income Statement'!W94 -> -2501.0173 | X11: ='Income Statement'!X94 -> -3144.009 | Y11: ='Income Statement'!Y94 -> -3621.5772 | Z11: ='Income Statement'!Z94 -> -3936.8967 | AA11: ='Income Statement'!AA94 -> -4186.0174
A12: Depreciation | B12: =1691-B14 -> 1554 | C12: =1772-C14 -> 1574 | D12: =1667-D14 -> 1543 | E12: =1826-E14 -> 1483 | F12: =1582-F14 -> 1403 | G12: =1884-G14 -> 1493 | H12: =2053-H14 -> 1618 | I12: =1968-I14 -> 1484.2011 | J12: =2150-J14 -> 1682.3981 | K12: =2466-K14 -> 1969.6163 | L12: =2294-L14 -> 1781.2037 | M12: =2298-M14 -> 1783.7712 | N12: =2444-N14 -> 1899.4259 | O12: =2927-O14 -> 2455 | P12: =2831-P14 -> 2439 | Q12: =2325-Q14 -> 2008 | R12: =2716-R14 -> 2410 | S12: =2242-S14 -> 2106 | T12: =2853-T14 -> 2001 | U12: =3133-U14 -> 2281 | V12: =V13*'Income Statement'!U$58 -> 2281 | W12: =W13*'Income Statement'!V$58 -> 2411.0041 | X12: =X13*'Income Statement'!W$58 -> 2651.5095 | Y12: =Y13*'Income Statement'!X$58 -> 2979.5332 | Z12: =Z13*'Income Statement'!Y$58 -> 3229.92 | AA12: =AA13*'Income Statement'!Z$58 -> 3393.7724
A13: as a % of sales | B13: =B12/'Income Statement'!B$58 -> 0.039407618 | C13: =C12/'Income Statement'!C$58 -> 0.040232089 | D13: =D12/'Income Statement'!D$58 -> 0.035663932 | E13: =E12/'Income Statement'!E$58 -> 0.034631731 | F13: =F12/'Income Statement'!F$58 -> 0.030665326 | G13: =G12/'Income Statement'!G$58 -> 0.030390002 | H13: =H12/'Income Statement'!H$58 -> 0.028647309 | I13: =I12/'Income Statement'!I$58 -> 0.023627756 | ... U13: =U12/'Income Statement'!U$58 -> 0.031027681 | V13: =U13 -> 0.031027681 | W13: =V13-0.1% -> 0.030027681 | X13: =W13-0.1% -> 0.029027681 | Y13: =X13 -> 0.029027681 | Z13: =Y13 -> 0.029027681 | AA13: =Z13 -> 0.029027681
A14: Amortisation | B14: 137 | C14: 198 | D14: 124 | E14: 343 | F14: 179 | G14: 391 | H14: 435 | I14: =I15*'Income Statement'!I$58 -> 483.79887 | J14: =J15*'Income Statement'!J$58 -> 467.60189 | K14: =K15*'Income Statement'!K$58 -> 496.38368 | L14: =L15*'Income Statement'!L$58 -> 512.7963 | M14: =M15*'Income Statement'!M$58 -> 514.22884 | N14: =N15*'Income Statement'!N$58 -> 544.5741 | O14: 472 | P14: 392 | Q14: 317 | R14: 306 | S14: 136 | T14: 852 | U14: 852 | V14: =V15*'Income Statement'!V$58 -> 930.55014 | W14: =W15*'Income Statement'!W$58 -> 1058.6307 | X14: =X15*'Income Statement'!X$58 -> 410.57819 | Y14: =Y15*'Income Statement'!Y$58 -> 445.08136 | Z14: =Z15*'Income Statement'!Z$58 -> 467.66015 | AA14: =AA15*'Income Statement'!AA$58 -> 485.87109
A15: as a % of sales | B15: =B14/'Income Statement'!B$58 -> 0.0034741594 | C15: =C14/'Income Statement'!C$58 -> 0.0050609616 | D15: =D14/'Income Statement'!D$58 -> 0.002866058 | E15: =E14/'Income Statement'!E$58 -> 0.0080099015 | F15: =F14/'Income Statement'!F$58 -> 0.0039123973 | G15: =G14/'Income Statement'!G$58 -> 0.0079588015 | H15: =H14/'Income Statement'!H$58 -> 0.0077018414 | I15: =$H15 -> 0.0077018414 | J15: =$H15 -> 0.0077018414 | K15: =$H15 -> 0.0077018414 | L15: =$H15 -> 0.0077018414 | M15: =$H15 -> 0.0077018414 | N15: =M15*(('Income Statement'!N14+7000)/'Income Statement'!N14) -> 0.0085481046 | O15: =N15 -> 0.0085481046 | P15: =O15 -> 0.0085481046 | Q15: =Q14/'Income Statement'!Q58 -> 0.0060787359 | R15: =R14/'Income Statement'!R58 -> 0.0052073584 | S15: =S14/'Income Statement'!S58 -> 0.0020780491 | T15: =T14/'Income Statement'!T58 -> 0.012306803 | U15: =U14/'Income Statement'!U58 -> 0.011589472 | V15: =U15 -> 0.011589472 | W15: =V15 -> 0.011589472 | X15: 0.004 | Y15: =X15 -> 0.004 | Z15: =Y15 -> 0.004 | AA15: =Z15 -> 0.004
A16: Valuation adjustments | B16: 163 | C16: 582 | D16: 924 | E16: -254 | F16: -366 | G16: -408 | H16: 318 | I16: 16 | J16: 562 | K16: 487 | L16: 1132 | M16: -1755 | N16: -1849 | O16: 600 | P16: 95 | Q16: -863 | R16: -569 | S16: -541 | T16: -640 | U16: -393
A17: Results on disposals on non-current assets | B17: -336 | C17: -125 | D17: -31 | E17: -31 | F17: -75 | G17: -29 | H17: -21 | I17: -58 | J17: -93 | K17: -234 | L17: -1870 | M17: -773 | N17: -261 | O17: -77 | P17: 9 | Q17: -116 | R17: 25 | S17: 64 | T17: 70 | U17: 17
A18: Results of equity investments | B18: -152 | C18: -210 | D18: -188 | E18: -115 | F18: -127 | G18: -164 | H18: -241 | I18: -295 | J18: -840 | K18: -1016 | L18: =-'Income Statement'!L74 -> -231 | M18: =-'Income Statement'!M74 -> -333 | N18: =-'Income Statement'!N74 -> -330 | O18: =-'Income Statement'!O74 -> -299 | P18: =-'Income Statement'!P74 -> -39 | Q18: =-'Income Statement'!Q74 -> -40 | R18: =-'Income Statement'!R74 -> -134 | S18: =-'Income Statement'!S74 -> -267 | ... AA18: =-'Income Statement'!AA74 -> -408.72917
A19: Movement in provisions | B19: 2150 | C19: 2268 | D19: 1 | E19: 1767 | F19: -219 | G19: 230 | H19: 1114 | I19: 605 | J19: 415 | K19: -54 | L19: 1321 | M19: 805 | N19: 1952 | O19: 475 | P19: 1138 | Q19: -1934 | R19: -1016 | S19: -114 | T19: 166 | U19: 314
A20: Change in inventory | B20: -1942 | C20: -2998 | D20: -1210 | E20: -1961 | F20: 705 | G20: -1640 | H20: -1526 | I20: ='Balance Sheet'!H16-'Balance Sheet'!I16 -> -1844 | J20: -3252 | K20: -4133 | L20: -3477 | M20: -2572 | N20: -671 | O20: 117 | P20: 152 | Q20: 2405 | R20: -3218 | S20: -1854 | T20: -3522 | U20: -3989 | V20: =-('Balance Sheet'!V16-'Balance Sheet'!U16) -> -2038.4576 | W20: =-('Balance Sheet'!W16-'Balance Sheet'!V16) -> -5808.1229 | X20: =-('Balance Sheet'!X16-'Balance Sheet'!W16) -> -5121.2667 | Y20: =-('Balance Sheet'!Y16-'Balance Sheet'!X16) -> -2928.3196 | Z20: =-('Balance Sheet'!Z16-'Balance Sheet'!Y16) -> -950.68753 | AA20: =-('Balance Sheet'!AA16-'Balance Sheet'!Z16) -> -2098.0301
A21: Change in receivables | B21: -7 | C21: -148 | D21: -845 | E21: -478 | F21: -345 | G21: 447 | H21: -260 | I21: ='Balance Sheet'!H18-'Balance Sheet'!I18 -> -451 | J21: -700 | K21: -1378 | L21: -1215 | M21: 621 | N21: -881 | O21: 29 | P21: 351 | Q21: 379 | R21: -115 | S21: 258 | T21: -105 | U21: -707 | V21: =-('Balance Sheet'!V18-'Balance Sheet'!U18) -> -1145.4012 | W21: =-('Balance Sheet'!W18-'Balance Sheet'!V18) -> -908.33892 | X21: =-('Balance Sheet'!X18-'Balance Sheet'!W18) -> -647.58004 | Y21: =-('Balance Sheet'!Y18-'Balance Sheet'!X18) -> -380.48665 | Z21: =-('Balance Sheet'!Z18-'Balance Sheet'!Y18) -> -433.01786 | AA21: =-('Balance Sheet'!AA18-'Balance Sheet'!Z18) -> -349.25094
A22: Change in trade liabilities | B22: 686 | C22: 44 | D22: 757 | E22: 192 | F22: -40 | G22: 806 | H22: 754 | I22: =-('Balance Sheet'!I40-'Balance Sheet'!H40) -> 451 | J22: 130 | K22: 1603 | L22: 2398 | M22: 1419 | N22: 2294 | O22: -1625 | P22: -5523 | Q22: 194 | R22: 3309 | S22: 1421 | T22: -1182 | U22: 2791 | V22: =-('Balance Sheet'!V40-'Balance Sheet'!U40) -> 120.25097 | W22: =-('Balance Sheet'!W40-'Balance Sheet'!V40) -> 2330.7839 | X22: =-('Balance Sheet'!X40-'Balance Sheet'!W40) -> 2278.2652 | Y22: =-('Balance Sheet'!Y40-'Balance Sheet'!X40) -> 1816.2658 | Z22: =-('Balance Sheet'!Z40-'Balance Sheet'!Y40) -> 1427.0092 | AA22: =-('Balance Sheet'!AA40-'Balance Sheet'!Z40) -> 1183.6736
A23: Change in working capital | Q23: =Q20+Q21+Q22+Q24+Q25 -> 1067 | R23: =R20+R21+R22+R24+R25 -> 1421 | S23: =S20+S21+S22+S24+S25 -> 1205 | T23: =T20+T21+T22+T24+T25 -> 1337 | U23: =U20+U21+U22+U24+U25 -> 100 | V23: =V20+V21+V22+V24+V25 -> 286.29731 | W23: =W20+W21+W22+W24+W25 -> 1076.5364 | X23: =X20+X21+X22+X24+X25 -> 2094.6614 | ... AA23: =AA20+AA21+AA22+AA24+AA25 -> 986.59515
A24: Advance payments received/ Contract Assets and Liabilities | B24: 1564 | C24: 4817 | D24: 2435 | E24: 2925 | F24: 1698 | G24: 1965 | H24: 1243 | I24: ='Balance Sheet'!#REF!-'Balance Sheet'!#REF! -> #REF! | J24: 1715 | K24: 3752 | L24: 4628 | M24: 1268 | N24: -684 | O24: 1297 | P24: 848 | Q24: -2326 | R24: 3300 | S24: 2277 | T24: 7135 | U24: 3250 | V24: ='Balance Sheet'!U43-'Balance Sheet'!V43 -> 3349.9051 | W24: ='Balance Sheet'!V43-'Balance Sheet'!W43 -> 5462.2143 | X24: ='Balance Sheet'!W43-'Balance Sheet'!X43 -> 5585.243 | Y24: ='Balance Sheet'!X43-'Balance Sheet'!Y43 -> 4263.3225 | Z24: ='Balance Sheet'!Y43-'Balance Sheet'!Z43 -> 2789.9078 | AA24: ='Balance Sheet'!Z43-'Balance Sheet'!AA43 -> 2250.2026
A25: Other assets and liabilities | B25: -444 | C25: -540 | D25: -982 | E25: -257 | F25: 738 | G25: -327 | H25: -141 | J25: -387 | K25: -417 | L25: -837 | M25: -470 | N25: -691 | O25: 2398 | P25: -4065 | Q25: 415 | R25: -1855 | S25: -897 | T25: -989 | U25: -1245
A26: Other | B26: =B27-SUM(B4:B12,B14,B16:B25) -> 1160 | C26: =C27-SUM(C4:C12,C14,C16:C25) -> 61 | D26: =D27-SUM(D4:D12,D14,D16:D25) -> -327 | E26: =E27-SUM(E4:E12,E14,E16:E25) -> -406 | F26: =F27-SUM(F4:F12,F14,F16:F25) -> 63 | G26: =G27-SUM(G4:G12,G14,G16:G25) -> 135 | H26: =H27-SUM(H4:H12,H14,H16:H25) -> -1013 | I26: =I27-SUM(I4:I12,I14,I16:I25) -> #REF! | J26: =J27-SUM(J4:J12,J14,J16:J25) -> -354 | K26: -217 | L26: -290 | M26: =-'Cash Flow Statement'!M83 -> -458 | N26: =-2519 -> -2519 | O26: -1752 | P26: -314 | Q26: -533 | R26: -600 | S26: -668 | T26: -505 | U26: -272 | V26: -450 | W26: =U26 -> -272 | X26: =W26 -> -272 | Y26: =X26 -> -272 | Z26: =Y26 -> -272 | AA26: =Z26 -> -272
A27: Cashflow from Operating activities | B27: 4558 | C27: 5098 | D27: 4399 | E27: 2438 | F27: 4443 | G27: 4289 | H27: 3840 | I27: 1931 | J27: 2560 | K27: =SUM(K4:K12,K14,K16:K26) -> 3750 | L27: =SUM(L4:L12,L14,L16:L26) -> 4621 | M27: =SUM(M4:M12,M14,M16:M26) -> 4444 | N27: =SUM(N4:N12,N14,N16:N26) -> 2318 | O27: =SUM(O4:O12,O14,O16:O26) -> 3753 | P27: =SUM(P4:P12,P14,P16:P26) -> -5420 | Q27: =SUM(Q4:Q12,Q14,Q16:Q19,Q23,Q26) -> 4639 | R27: =SUM(R4:R12,R14,R16:R19,R23,R26) -> 6288 | S27: =SUM(S4:S12,S14,S16:S19,S23,S26) -> 6255 | T27: =SUM(T4:T12,T14,T16:T19,T23,T26) -> 7402 | U27: =SUM(U4:U12,U14,U16:U19,U23,U26) -> 7995 | V27: =SUM(V4:V12,V14,V16:V19,V23,V26) -> 8218.6562 | W27: =SUM(W4:W12,W14,W16:W19,W23,W26) -> 10701.37 | X27: =SUM(X4:X12,X14,X16:X19,X23,X26) -> 13033.968 | ... AA27: =SUM(AA4:AA12,AA14,AA16:AA19,AA23,AA26) -> 15505.69
A28: Purchases of intangible assets, PP&E & Investment property | B28: -2708 | C28: -2028 | D28: -1837 | E28: -1957 | F28: -2250 | G28: -2197 | H28: -3270 | I28: -2949 | J28: -2548 | K28: -2924 | L28: -3060 | M28: -2558 | N28: -2285 | O28: -2340 | P28: -1759 | Q28: -1928 | R28: -2464 | S28: -3051 | T28: -3669 | U28: -3964 | V28: =-V29*'Income Statement'!V$58 -> -4175.2212 | W28: =-W29*'Income Statement'!W$58 -> -4567.2086 | X28: =-X29*'Income Statement'!X$58 -> -5029.5828 | Y28: =-Y29*'Income Statement'!Y$58 -> -5340.9763 | Z28: =-Z29*'Income Statement'!Z$58 -> -5495.0067 | AA28: =-AA29*'Income Statement'!AA$58 -> -5587.5175
A29: as a % of sales | B29: =-B28/'Income Statement'!B$58 -> 0.068671705 | C29: =-C28/'Income Statement'!C$58 -> 0.051836516 | D29: =-D28/'Income Statement'!D$58 -> 0.042459263 | E29: =-E28/'Income Statement'!E$58 -> 0.045700808 | F29: =-F28/'Income Statement'!F$58 -> 0.049178178 | G29: =-G28/'Income Statement'!G$58 -> 0.044719915 | H29: =-H28/'Income Statement'!H$58 -> 0.057896601 | I29: =-I28/'Income Statement'!I$58 -> 0.046946638 | ... U29: =-U28/'Income Statement'!U$58 -> 0.053920969 | V29: 0.052 | W29: =V29-0.2% -> 0.05 | X29: =W29-0.1% -> 0.049 | Y29: =X29-0.1% -> 0.048 | Z29: =Y29-0.1% -> 0.047 | AA29: =Z29-0.1% -> 0.046
A30: Proceeds from disposals of intangible assets, PP&E & Investment Property | B30: 76 | C30: 162 | D30: 35 | E30: 75 | F30: 45 | G30: 79 | H30: 73 | I30: 60 | J30: 232 | K30: 78 | L30: 72 | M30: 177 | N30: 213 | O30: 112 | P30: 228 | Q30: 212 | R30: 101 | S30: 75 | T30: 98 | U30: 69 | V30: =V31*'Income Statement'!V14 -> 75.361455 | W30: =W31*'Income Statement'!W14 -> 85.734175 | X30: =X31*'Income Statement'!X14 -> 96.340526 | Y30: =Y31*'Income Statement'!Y14 -> 104.43656 | Z30: =Z31*'Income Statement'!Z14 -> 109.73458 | AA30: =AA31*'Income Statement'!AA14 -> 114.0077
A31: as a % of sales | B31: =B30/'Income Statement'!B$58 -> 0.0019272709 | C31: =C30/'Income Statement'!C$58 -> 0.0041407867 | D31: =D30/'Income Statement'!D$58 -> 0.00080896799 | E31: =E30/'Income Statement'!E$58 -> 0.0017514362 | F31: =F30/'Income Statement'!F$58 -> 0.00098356356 | G31: =G30/'Income Statement'!G$58 -> 0.0016080443 | H31: =H30/'Income Statement'!H$58 -> 0.0012924929 | I31: =I30/'Income Statement'!I$58 -> 0.00095517066 | ... U31: =U30/'Income Statement'!U$58 -> 0.00093858396 | V31: =U31 -> 0.00093858396 | W31: =V31 -> 0.00093858396 | X31: =W31 -> 0.00093858396 | Y31: =X31 -> 0.00093858396 | Z31: =Y31 -> 0.00093858396 | AA31: =Z31 -> 0.00093858396
A32: Acquisitions of subsidiaries, JVs, businesses and non-controlling interests (net of cash) | B32: -82 | C32: 0 | D32: -265 | E32: -21 | F32: -38 | G32: -1535 | H32: -201 | I32: -16 | J32: -47 | K32: -13 | L32: -120 | M32: -23 | N32: 129 | O32: 8 | P32: -481 | Q32: -25 | R32: -188 | S32: -65 | T32: -246 | U32: 122
A33: Proceeds from disposals of subsidiaries (net of cash) | B33: 86 | C33: 29 | D33: 2 | E33: 13 | F33: 12 | G33: 18 | H33: 0 | I33: 0 | J33: -34 | K33: 127 | L33: 731 | M33: 377 | N33: 0 | O33: 0 | P33: 0 | Q33: 0 | R33: 0 | S33: 0 | T33: 0 | U33: 27
A34: Payments for investments in associates, other investments and other long-term financial assets | B34: -194 | C34: -132 | D34: -122 | E34: -136 | F34: -190 | G34: =-312 -> -312 | H34: -328 | I34: -292 | J34: -36 | K34: -258 | L34: -691 | M34: -913 | N34: -707 | O34: -952 | P34: -565 | Q34: -577 | R34: -777 | S34: -960 | T34: -871 | U34: -879
A35: Proceeds from disposals of associates, other investments and other long-term financial assets | B35: 116 | C35: 186 | D35: 180 | E35: 43 | F35: 91 | G35: 77 | H35: 232 | I35: 157 | J35: 1083 | K35: 1731 | L35: 182 | M35: 532 | N35: 597 | O35: 358 | P35: 408 | Q35: 396 | R35: 459 | S35: 509 | T35: 530 | U35: 1083
A36: Dividends paid by companies valued at equity | B36: 46 | C36: 39 | D36: 50 | E36: 27 | F36: 41 | G36: 50 | H36: 46 | I36: 52 | J36: 143 | K36: 34 | L36: 192 | M36: 218 | N36: 191 | O36: 210 | P36: -8 | Q36: 79 | R36: 100 | S36: 150 | T36: 196 | U36: 387 | V36: ='Income Statement'!V74*0.7 -> 224.175 | W36: ='Income Statement'!W74*0.7 -> 235.38375 | X36: ='Income Statement'!X74*0.7 -> 247.15294 | Y36: ='Income Statement'!Y74*0.7 -> 259.51058 | Z36: ='Income Statement'!Z74*0.7 -> 272.48611 | AA36: ='Income Statement'!AA74*0.7 -> 286.11042
A37: Payments for investments in securities | B37: 3357 | C37: -2641 | D37: -2676 | E37: -821 | F37: -10751 | G37: -11091 | H37: -3237 | J37: -5526 | K37: -7151 | L37: -2280 | M37: -3767 | N37: -2010 | O37: -2861 | P37: -337 | Q37: -3049 | R37: -1851 | S37: -2700 | T37: -4460 | U37: -5205
A38: Proceeds from disposals of securities | E38: 0 | F38: 7604 | G38: 10713 | H38: 6659 | I38: 1272 | J38: 3510 | K38: 4790 | L38: 2617 | M38: 2534 | N38: 1917 | O38: 2464 | P38: 6640 | Q38: 1863 | R38: 1507 | S38: 1914 | T38: 1769 | U38: 3678
A39: Other | B39: =B40-SUM(B28:B38) -> 69.929401 | C39: =C40-SUM(C28:C38) -> -552.05598 | D39: =D40-SUM(D28:D38) -> -319.04327 | E39: =E40-SUM(E28:E38) -> -70.047452 | F39: =F40-SUM(F28:F38) -> -0.050161742 | G39: =G40-SUM(G28:G38) -> -0.04632796 | H39: =H40-SUM(H28:H38) -> -0.059189093 | I39: =I40-SUM(I28,I30,I33:I38,I32) -> -26 | J39: =J40-SUM(J28,J30,J33:J38,J32) -> 0 | K39: =K40-SUM(K28,K30,K33:K38,K32) -> 127 | L39: 1527 | M39: 893 | N39: 320 | O39: 137 | Q39: 310 | R39: 0
A40: Cashflow from Investing activities | B40: 767 | C40: -4937 | D40: -4952 | E40: -2847 | F40: -5436 | G40: -4198 | H40: -26 | I40: -1742 | J40: -3223 | K40: -3459 | L40: =SUM(L28,L30,L33:L39,L32) -> -830 | M40: =SUM(M28,M30,M33:M39,M32) -> -2530 | N40: =SUM(N28,N30,N33:N39,N32) -> -1635 | O40: =SUM(O28,O30,O33:O39,O32) -> -2864 | P40: =SUM(P28,P30,P33:P39,P32) -> 4126 | Q40: =SUM(Q28,Q30,Q33:Q39,Q32) -> -2719 | R40: =SUM(R28,R30,R33:R39,R32) -> -3113 | S40: =SUM(S28,S30,S33:S39,S32) -> -4128 | ... AA40: =SUM(AA28,AA30,AA33:AA39,AA32) -> -5187.3994
A41: Proceeds from the issue of share capital | I41: 0 | J41: 0 | L41: 0 | M41: 0 | N41: 0 | O41: 0 | P41: 0 | Q41: 0 | R41: 0 | S41: 0 | T41: 0 | U41: 0
A42: Purchase of own shares | I42: -1915 | K42: -264 | L42: -736 | M42: 0 | N42: 0 | O42: 0 | P42: 0 | Q42: 0 | R42: 0 | S42: 0 | T42: 0 | U42: 0 | V42: -1000 | W42: -2000 | X42: -2000
A43: Increase in financing liabilities | B43: 1170 | C43: 206 | D43: 471 | E43: 1114 | F43: 99 | G43: 813 | H43: 380 | I43: 1679 | J43: 2038 | K43: 1254 | L43: 3297 | M43: 1703 | N43: 103 | O43: 402 | P43: 7102 | Q43: 0 | R43: 171 | S43: 247 | T43: 851 | U43: 244
A44: Repayment of financing liabilities | B44: -325 | C44: -792 | D44: -628 | E44: -208 | F44: -1160 | G44: -399 | H44: -505 | I44: -534 | J44: -1108 | K44: -262 | L44: -1725 | M44: -419 | N44: -2411 | O44: -562 | P44: -445 | Q44: -2295 | R44: -1348 | S44: -52 | T44: -1283 | U44: -858
A45: Cash distribution to Airbus group NV shareholders | B45: -520 | C45: -97 | D45: -97 | E45: -162 | F45: 0 | G45: -178 | H45: -369 | I45: -467 | J45: -587 | K45: -945 | L45: -1008 | M45: -1043 | N45: -1161 | O45: -1280 | P45: 0 | Q45: 0 | R45: -1181 | S45: -1421 | T45: -2215 | U45: -2372 | V45: ='Income Statement'!U116 -> -2526.6343 | W45: ='Income Statement'!V116 -> -2703.4676 | X45: ='Income Statement'!W116 -> -3301.497 | Y45: ='Income Statement'!X116 -> -4118.7482 | Z45: ='Income Statement'!Y116 -> -4725.7438 | AA45: ='Income Statement'!Z116 -> -5453.7438
A46: Year end dividend from prior year | B46: 0.65 | C46: 0.12 | D46: 0.12 | E46: 0.2 | F46: 0 | G46: 0.22 | H46: 0.45 | I46: ='Income Statement'!H117 -> 0.45034146 | J46: ='Income Statement'!I117 -> 0.58929909 | K46: =J46*(1+'Income Statement'!J119) -> 0.74971673 | L46: =K46*(1+'Income Statement'!K119) -> 1.2028699 | M46: ='Income Statement'!L117 -> 1.3026641 | N46: ='Income Statement'!M117 -> 1.3479411 | O46: ='Income Statement'!N117 -> 1.49774 | P46: ='Income Statement'!O117 -> 1.6472771 | Q46: ='Income Statement'!P117 -> 0 | R46: ='Income Statement'!Q117 -> 1.5038339 | S46: ='Income Statement'!R117 -> 1.805406 | T46: ='Income Statement'!S117 -> 2.8083449 | ... AA46: ='Income Statement'!Z117 -> 7.1453531
A47: Dividends paid to non-controlling interests | B47: -16 | C47: -1 | D47: -10 | E47: -4 | F47: -7 | G47: -5 | H47: -10 | I47: -2 | J47: -2 | K47: -3 | L47: -4 | M47: -3 | N47: 0 | O47: 0 | P47: 0 | Q47: 0 | R47: -1 | S47: 0 | T47: -1 | U47: -2
A48: Changes in capital and non-controlling interests | B48: 94 | C48: 46 | D48: 24 | E48: 17 | F48: -48 | G48: -65 | H48: 144 | I48: 171 | J48: 52 | K48: 195 | L48: 60 | M48: 83 | N48: 117 | O48: 194 | P48: 89 | Q48: 138 | R48: 145 | S48: 146 | T48: 126 | U48: 0
A49: Change in treasury shares | B49: -35 | C49: 0 | D49: 39 | E49: -5 | F49: -3 | G49: -1 | H49: -5 | J49: 102 | K49: 0 | N49: -49 | O49: -31 | P49: -4 | Q49: -22 | R49: -36 | S49: -334 | T49: -276 | U49: -565
A50: Other | B50: =B51-SUM(B43:B45,B47:B49) -> -2879 | C50: =C51-SUM(C43:C45,C47:C49) -> 0 | D50: =D51-SUM(D43:D45,D47:D49) -> 0 | E50: =E51-SUM(E43:E45,E47:E49) -> 0 | F50: =F51-SUM(F43:F45,F47:F49) -> 0 | G50: =G51-SUM(G43:G45,G47:G49) -> 0 | H50: =H51-SUM(H43:H45,H47:H49) -> 0 | I50: =I51-SUM(I41:I45,I47:I49) -> 0 | J50: =J51-SUM(J43:J45,J47:J49) -> 0 | K50: =K51-SUM(K41:K45,K47:K49) -> 0 | L50: =L51-SUM(L41:L45,L47:L49) -> 0 | M50: =M51-SUM(M41:M45,M47:M49) -> 0 | N50: 179 | O50: 319 | P50: 91 | Q50: 0 | R50: 135 | S50: 138 | T50: 228 | U50: 82 | V50: =V51-SUM(V41:V45,V47:V49) -> 0 | W50: =W51-SUM(W41:W45,W47:W49) -> 0 | X50: =X51-SUM(X41:X45,X47:X49) -> 0 | Y50: =Y51-SUM(Y41:Y45,Y47:Y49) -> 0 | Z50: =Z51-SUM(Z41:Z45,Z47:Z49) -> 0 | AA50: =AA51-SUM(AA41:AA45,AA47:AA49) -> 0
A51: Cashflow from Financing activities | B51: -2511 | C51: -638 | D51: -201 | E51: 752 | F51: -1119 | G51: 165 | H51: -365 | I51: -1068 | J51: =SUM(J41:J45,J47:J49) -> 495 | K51: =SUM(K41:K45,K47:K49) -> -25 | L51: =SUM(L41:L45,L47:L49) -> -116 | M51: =SUM(M41:M45,M47:M49) -> 321 | N51: =SUM(N41:N45,N47:N50) -> -3222 | O51: =SUM(O41:O45,O47:O50) -> -958 | P51: =SUM(P41:P45,P47:P50) -> 6833 | Q51: =SUM(Q41:Q45,Q47:Q49) -> -2179 | R51: =SUM(R41:R45,R47:R50) -> -2115 | S51: =SUM(S41:S45,S47:S50) -> -1276 | T51: =SUM(T41:T45,T47:T50) -> -2570 | U51: =SUM(U41:U45,U47:U50) -> -3471 | V51: =SUM(V41:V45,V47:V49) -> -3526.6343 | W51: =SUM(W41:W45,W47:W49) -> -4703.4676 | X51: =SUM(X41:X45,X47:X49) -> -5301.497 | Y51: =SUM(Y41:Y45,Y47:Y49) -> -4118.7482 | Z51: =SUM(Z41:Z45,Z47:Z49) -> -4725.7438 | AA51: =SUM(AA41:AA45,AA47:AA49) -> -5453.7438
A52: Change in Cash | B52: =B51+B40+B27 -> 2814 | C52: =C51+C40+C27 -> -477 | D52: =D51+D40+D27 -> -754 | E52: =E51+E40+E27 -> 343 | F52: =F51+F40+F27 -> -2112 | G52: =G51+G40+G27 -> 256 | H52: =H51+H40+H27 -> 3449 | I52: =I51+I40+I27 -> -879 | ... AA52: =AA51+AA40+AA27 -> 4864.547
A53: FX | B53: -57 | C53: -117 | D53: -50 | E53: -50 | F53: 104 | G53: -2 | H53: 23 | I53: -112 | J53: 256 | K53: 171 | L53: 60 | M53: -374 | N53: -54 | O53: -45 | P53: -414 | Q53: 392 | R53: 191 | S53: -201 | T53: 358 | U53: -712
A54: Change in Overdraft
A55: Other
A56: Cash at the beginning of the year | B56: 5386 | C56: 8143 | D56: 7549 | E56: 6745 | F56: 7038 | G56: 5030 | H56: 5284 | I56: =H57 -> 8756 | J56: =I57 -> 7765 | K56: =J57 -> 7271 | L56: =K57 -> 7489 | M56: =L57 -> 10160 | N56: =M57 -> 12021 | O56: =N57 -> 9428 | P56: =O57 -> 9314 | ... AA56: =Z57 -> 32682.678
A57: Cash at the end of the year | B57: =SUM(B52:B56) -> 8143 | C57: =SUM(C52:C56) -> 7549 | D57: =SUM(D52:D56) -> 6745 | E57: =SUM(E52:E56) -> 7038 | F57: =SUM(F52:F56) -> 5030 | G57: =SUM(G52:G56) -> 5284 | H57: =SUM(H52:H56) -> 8756 | I57: =SUM(I52:I56) -> 7765 | J57: 7271 | K57: 7489 | L57: =10143+17 -> 10160 | M57: =SUM(M52:M56) -> 12021 | N57: =SUM(N52:N56) -> 9428 | O57: =SUM(O52:O56) -> 9314 | P57: =SUM(P52:P56) -> 14439 | Q57: =SUM(Q52:Q56) -> 14572 | R57: =SUM(R52:R56) -> 15823 | S57: =SUM(S52:S56) -> 16473 | T57: =SUM(T52:T56) -> 15010 | ... AA57: =SUM(AA52:AA56) -> 37547.225
A58: Overdraft
A59: Disposals | T59: 7
A60: Cash at the end of year prior to held for sale | T60: =T57-T59 -> 15003
A61: ='Cash Flow Statement'!A89 -> FCF excluding the impact of customer financing | B61: ='Cash Flow Statement'!B89 -> 0 | C61: ='Cash Flow Statement'!C89 -> 0 | D61: ='Cash Flow Statement'!D89 -> 2824 | E61: ='Cash Flow Statement'!E89 -> 606 | F61: ='Cash Flow Statement'!F89 -> 2745 | G61: ='Cash Flow Statement'!G89 -> 2493 | H61: ='Cash Flow Statement'!H89 -> 1449 | ... AA61: ='Cash Flow Statement'!AA89 -> 10476.283
A62: FCF per share | O62: =O61/'Income Statement'!O113*1000 -> 4.5158559 | P62: =P61/'Income Statement'!P113*1000 -> -8.8549452 | Q62: =Q61/'Income Statement'!Q113*1000 -> 4.4758478 | R62: =R61/'Income Statement'!R113*1000 -> 5.946024 | S62: =S61/'Income Statement'!S113*1000 -> 5.7460132 | T62: =T61/'Income Statement'!T113*1000 -> 5.6496412 | U62: =U61/'Income Statement'!U113*1000 -> 6.0944317 | V62: =V61/'Income Statement'!V113*1000 -> 6.0149809 | ... AA62: =AA61/'Income Statement'!AA113*1000 -> 13.725753
A64: GS Op Cash (EBIT Equivalent) | B64: =B2 -> 2006 | C64: =C2 -> 2007 | D64: =D2 -> 2008 | E64: =E2 -> 2009 | F64: =F2 -> 2010 | G64: =G2 -> 2011 | H64: =H2 -> 2012 | I64: =I2 -> 2013 | ... AA64: =AA2 -> 2031
A65: Cash provided by operating activities | Q65: =Q27 -> 4639 | R65: =R27 -> 6288 | S65: =S27 -> 6255 | T65: =T27 -> 7402 | U65: =U27 -> 7995 | V65: =V27 -> 8218.6562 | W65: =W27 -> 10701.37 | X65: =X27 -> 13033.968 | ... AA65: =AA27 -> 15505.69
A66: add back:
A67: Interest paid | Q67: =-Q9 -> 330 | R67: =-R9 -> 322 | S67: =-S9 -> 606 | T67: =-T9 -> 786 | U67: =-U9 -> 651 | V67: =-V9 -> 740.948 | W67: =-W9 -> 689.95 | X67: =-X9 -> 649.296 | ... AA67: =-AA9 -> 521.151
A68: Tax paid | Q68: =-Q11 -> 321 | R68: =-R11 -> 790 | S68: =-S11 -> 544 | T68: =-T11 -> 947 | U68: =-U11 -> 965 | V68: =-V11 -> 2030.5036 | W68: =-W11 -> 2501.0173 | X68: =-X11 -> 3144.009 | ... AA68: =-AA11 -> 4186.0174
A70: Less: Interest received | Q70: =-Q8 -> -111 | R70: =-R8 -> -250 | S70: =-S8 -> -690 | T70: =-T8 -> -681 | U70: =-U8 -> -607 | V70: =-V8 -> -649.888 | W70: =-W8 -> -673.03517 | X70: =-X8 -> -701.74226 | ... AA70: =-AA8 -> -1274.6244
A72: Deduct:
A73: Purchase of PP&E | Q73: =Q28 -> -1928 | R73: =R28 -> -2464 | S73: =S28 -> -3051 | T73: =T28 -> -3669 | U73: =U28 -> -3964 | V73: =V28 -> -4175.2212 | W73: =W28 -> -4567.2086 | X73: =X28 -> -5029.5828 | ... AA73: =AA28 -> -5587.5175
A74: Purchase of intangible assets
A75: Operating cash flow | Q75: =SUM(Q65:Q74) -> 3251 | R75: =SUM(R65:R74) -> 4686 | S75: =SUM(S65:S74) -> 3664 | T75: =SUM(T65:T74) -> 4785 | U75: =SUM(U65:U74) -> 5040 | V75: =SUM(V65:V74) -> 6164.9986 | W75: =SUM(W65:W74) -> 8652.0938 | X75: =SUM(X65:X74) -> 11095.947 | ... AA75: =SUM(AA65:AA74) -> 13350.717
A76: Underlying EBIT | Q76: ='Income Statement'!Q31 -> 4865 | R76: ='Income Statement'!R31 -> 5627 | S76: ='Income Statement'!S31 -> 5838 | T76: ='Income Statement'!T31 -> 5354 | U76: ='Income Statement'!U31 -> 7128 | V76: ='Income Statement'!V31 -> 7612.6223 | W76: ='Income Statement'!W31 -> 9281.3937 | X76: ='Income Statement'!X31 -> 11593.857 | ... AA76: ='Income Statement'!AA31 -> 14752.725
A77: Cash conversion | Q77: =Q75/Q76 -> 0.66824255 | R77: =R75/R76 -> 0.83277057 | S77: =S75/S76 -> 0.6276122 | T77: =T75/T76 -> 0.89372432 | U77: =U75/U76 -> 0.70707071 | V77: =V75/V76 -> 0.80983902 | W77: =W75/W76 -> 0.93219769 | X77: =X75/X76 -> 0.95705404 | ... AA77: =AA75/AA76 -> 0.90496616
A79: Free Cash Flow analysis | B79: =B64 -> 2006 | C79: =C64 -> 2007 | D79: =D64 -> 2008 | E79: =E64 -> 2009 | F79: =F64 -> 2010 | G79: =G64 -> 2011 | H79: =H64 -> 2012 | I79: =I64 -> 2013 | ... AA79: =AA64 -> 2031
A80: Cash Provided by Operating Activities | D80: ='Cash Flow Statement'!D27 -> 4399 | E80: ='Cash Flow Statement'!E27 -> 2438 | F80: ='Cash Flow Statement'!F27 -> 4443 | G80: ='Cash Flow Statement'!G27 -> 4289 | H80: ='Cash Flow Statement'!H27 -> 3840 | I80: ='Cash Flow Statement'!I27 -> 1931 | J80: ='Cash Flow Statement'!J27+187 -> 2747 | K80: ='Cash Flow Statement'!K27+106 -> 3856 | L80: ='Cash Flow Statement'!L27-311 -> 4310 | M80: ='Cash Flow Statement'!M27+7 -> 4451 | N80: ='Cash Flow Statement'!N27 -> 2318 | O80: ='Cash Flow Statement'!O27 -> 3753 | P80: ='Cash Flow Statement'!P27 -> -5420 | Q80: ='Cash Flow Statement'!Q27 -> 4639 | R80: ='Cash Flow Statement'!R27 -> 6288 | S80: ='Cash Flow Statement'!S27 -> 6255 | T80: ='Cash Flow Statement'!T27 -> 7402 | U80: ='Cash Flow Statement'!U27 -> 7995 | ... AA80: ='Cash Flow Statement'!AA27 -> 15505.69
A81: Cash used for Investing activites | D81: ='Cash Flow Statement'!D40 -> -4952 | E81: ='Cash Flow Statement'!E40 -> -2847 | F81: ='Cash Flow Statement'!F40 -> -5436 | G81: ='Cash Flow Statement'!G40 -> -4198 | H81: ='Cash Flow Statement'!H40 -> -26 | I81: ='Cash Flow Statement'!I40 -> -1742 | J81: ='Cash Flow Statement'!J40 -> -3223 | K81: ='Cash Flow Statement'!K40 -> -3459 | ... AA81: ='Cash Flow Statement'!AA40 -> -5187.3994
A82: Less changes in Securities | D82: =-('Cash Flow Statement'!D37+'Cash Flow Statement'!D38) -> 2676 | E82: =-('Cash Flow Statement'!E37+'Cash Flow Statement'!E38) -> 821 | F82: =-('Cash Flow Statement'!F37+'Cash Flow Statement'!F38) -> 3147 | G82: =-('Cash Flow Statement'!G37+'Cash Flow Statement'!G38) -> 378 | H82: =-('Cash Flow Statement'!H37+'Cash Flow Statement'!H38) -> -3422 | I82: =-('Cash Flow Statement'!I37+'Cash Flow Statement'!I38) -> -1272 | J82: =-('Cash Flow Statement'!J37+'Cash Flow Statement'!J38) -> 2016 | K82: =-('Cash Flow Statement'!K37+'Cash Flow Statement'!K38) -> 2361 | L82: =-('Cash Flow Statement'!L37+'Cash Flow Statement'!L38) -> -337 | M82: =-('Cash Flow Statement'!M37+'Cash Flow Statement'!M38)+123 -> 1356 | N82: =-('Cash Flow Statement'!N37+'Cash Flow Statement'!N38) -> 93 | O82: =-('Cash Flow Statement'!O37+'Cash Flow Statement'!O38) -> 397 | P82: =-('Cash Flow Statement'!P37+'Cash Flow Statement'!P38) -> -6303 | Q82: =-('Cash Flow Statement'!Q37+'Cash Flow Statement'!Q38) -> 1186 | R82: =-('Cash Flow Statement'!R37+'Cash Flow Statement'!R38) -> 344 | S82: =-('Cash Flow Statement'!S37+'Cash Flow Statement'!S38) -> 786 | T82: =-('Cash Flow Statement'!T37+'Cash Flow Statement'!T38) -> 2691 | U82: =-('Cash Flow Statement'!U37+'Cash Flow Statement'!U38) -> 1527 | ... AA82: =-('Cash Flow Statement'!AA37+'Cash Flow Statement'!AA38) -> 0
A83: Less Contribution to Plan Assets (Pension) | B83: 0 | C83: 303 | D83: 436 | E83: 173 | F83: 553 | G83: 489 | H83: 856 | I83: 223 | J83: 462 | K83: 217 | L83: 290 | M83: 458 | N83: =-N26 -> 2519 | O83: =-O26 -> 1752 | P83: =-P26 -> 314 | Q83: =-Q26 -> 533 | R83: =-R26 -> 600 | S83: =-S26 -> 668 | T83: =-T26 -> 505 | U83: =-U26 -> 272 | ... AA83: =-AA26 -> 272
A84: Less Acquisitions | B84: =-'Cash Flow Statement'!B32 -> 82 | C84: =-'Cash Flow Statement'!C32 -> 0 | D84: =-'Cash Flow Statement'!D32 -> 265 | E84: =-'Cash Flow Statement'!E32 -> 21 | F84: =-'Cash Flow Statement'!F32 -> 38 | G84: =-'Cash Flow Statement'!G32 -> 1535 | H84: =-'Cash Flow Statement'!H32 -> 201 | I84: =-'Cash Flow Statement'!I32 -> 16 | J84: -893 | K84: -1650 | L84: -2025 | M84: -886 | N84: =2912-SUM(N80:N83) -> -383 | O84: =3509-SUM(O80:O83) -> 471 | P84: =-6935-SUM(P80:P83) -> 348 | Q84: =3515-SUM(Q80:Q83) -> -124 | R84: =4680-SUM(R80:R83) -> 561 | S84: =4532-SUM(S80:S83) -> 951 | T84: =4463-SUM(T80:T83) -> 518 | U84: =-'Cash Flow Statement'!U35-'Cash Flow Statement'!U34-'Cash Flow Statement'!U33-'Cash Flow Statement'!U30 -> -300 | V84: =-'Cash Flow Statement'!V35-'Cash Flow Statement'!V34-'Cash Flow Statement'!V33-'Cash Flow Statement'!V30 -> -75.361455 | W84: =-'Cash Flow Statement'!W35-'Cash Flow Statement'!W34-'Cash Flow Statement'!W33-'Cash Flow Statement'!W30 -> -85.734175 | X84: =-'Cash Flow Statement'!X35-'Cash Flow Statement'!X34-'Cash Flow Statement'!X33-'Cash Flow Statement'!X30 -> -96.340526 | Y84: =-'Cash Flow Statement'!Y35-'Cash Flow Statement'!Y34-'Cash Flow Statement'!Y33-'Cash Flow Statement'!Y30 -> -104.43656 | Z84: =-'Cash Flow Statement'!Z35-'Cash Flow Statement'!Z34-'Cash Flow Statement'!Z33-'Cash Flow Statement'!Z30 -> -109.73458 | AA84: =-'Cash Flow Statement'!AA35-'Cash Flow Statement'!AA34-'Cash Flow Statement'!AA33-'Cash Flow Statement'!AA30 -> -114.0077
A85: Of which M&A
A86: Company Defined FCF | D86: =SUM(D80:D84) -> 2824 | E86: =SUM(E80:E84) -> 606 | F86: =SUM(F80:F84) -> 2745 | G86: =SUM(G80:G84) -> 2493 | H86: =SUM(H80:H84) -> 1449 | I86: =SUM(I80:I84) -> -844 | J86: =SUM(J80:J84)-108 -> 1001 | K86: =SUM(K80:K84) -> 1325 | L86: =SUM(L80:L84) -> 1408 | M86: =SUM(M80:M84)+100 -> 2949 | N86: =SUM(N80:N84) -> 2912 | O86: =SUM(O80:O84) -> 3509 | P86: =SUM(P80:P84) -> -6935 | Q86: =SUM(Q80:Q84) -> 3515 | R86: =SUM(R80:R84) -> 4680 | S86: =SUM(S80:S85) -> 4532 | T86: =SUM(T80:T85) -> 4463 | U86: =SUM(U80:U85) -> 4812 | V86: =SUM(V80:V85) -> 4717.61 | W86: =SUM(W80:W85) -> 6641.5454 | X86: =SUM(X80:X85) -> 8523.5377 | Y86: =SUM(Y80:Y85) -> 10536.975 | Z86: =SUM(Z80:Z85) -> 11565.493 | AA86: =SUM(AA80:AA85) -> 10476.283
A87: cash conversion (vs. Net Income) | J87: =J86/'Income Statement'!J102 -> 0.38003037 | K87: =K86/'Income Statement'!K102 -> 0.49774606 | L87: =L86/'Income Statement'!L102 -> 0.54957065 | M87: =M86/'Income Statement'!M102 -> 1.1362848 | N87: =N86/'Income Statement'!N102 -> 0.71990111 | O87: =O86/'Income Statement'!O102 -> 0.74422057 | P87: =P86/'Income Statement'!P102 -> -6.5117371 | Q87: =Q86/'Income Statement'!Q102 -> 1.0347365 | ... AA87: =AA86/'Income Statement'!AA102 -> 0.90459543
A89: FCF excluding the impact of customer financing | B89: 0 | C89: 0 | D89: 2824 | E89: 606 | F89: 2745 | G89: 2493 | H89: 1449 | I89: -844 | J89: =J86 -> 1001 | K89: 1325 | L89: 1408 | M89: =M86 -> 2949 | N89: =N86 -> 2912 | O89: =O86 -> 3509 | P89: =P86 -> -6935 | Q89: =Q86 -> 3515 | R89: =R86 -> 4680 | S89: =S86 -> 4532 | T89: =T86 -> 4463 | ... AA89: =AA86 -> 10476.283
A90: A400M Cash drag | O90: -889 | P90: -552.25 | Q90: -530.25 | R90: -217.25 | S90: -530.25 | T90: -330.25
A91: A220 Cash Drag | O91: -343.18947 | P91: -316.24126 | Q91: -347.69878 | R91: -262.32158 | S91: -183.27931 | T91: -77.426508
A92: Adjusted FCF | O92: =O89-O90-O91 -> 4741.1895 | P92: =P89-P90-P91 -> -6066.5087 | Q92: =Q89-Q90-Q91 -> 4392.9488 | R92: =R89-R90-R91 -> 5159.5716 | S92: =S89-S90-S91 -> 5245.5293 | T92: =T89-T90-T91 -> 4870.6765 | U92: =U89-U90-U91 -> 4812 | V92: =V89-V90-V91 -> 4717.61 | ... AA92: =AA89-AA90-AA91 -> 10476.283
A93: Adjusted Cash conversion | O93: =O92/'Income Statement'!O102 -> 1.0055545 | P93: =P92/'Income Statement'!P102 -> -5.6962523 | Q93: =Q92/'Income Statement'!Q102 -> 1.2931848 | R93: =R92/'Income Statement'!R102 -> 1.2723974 | S93: =S92/'Income Statement'!S102 -> 1.1877118 | T93: =T92/'Income Statement'!T102 -> 1.2201093 | U93: =U92/'Income Statement'!U102 -> 0.8850469 | V93: =V92/'Income Statement'!V102 -> 0.82016026 | ... AA93: =AA92/'Income Statement'!AA102 -> 0.90459543
A95: Use of Cash Analysis | B95: =B79 -> 2006 | C95: =C79 -> 2007 | D95: =D79 -> 2008 | E95: =E79 -> 2009 | F95: =F79 -> 2010 | G95: =G79 -> 2011 | H95: =H79 -> 2012 | I95: =I79 -> 2013 | ... T95: =T79 -> 2024 | U95: ='Income Statement'!U$2 -> 2025 | V95: ='Income Statement'!V$2 -> 2026 | W95: ='Income Statement'!W$2 -> 2027 | X95: ='Income Statement'!X$2 -> 2028 | Y95: ='Income Statement'!Y$2 -> 2029 | Z95: ='Income Statement'!Z$2 -> 2030 | AA95: ='Income Statement'!AA$2 -> 2031
A96: Cash Flow from Operations | B96: ='Cash Flow Statement'!B27-B97+'Income Statement'!B140-'Income Statement'!B141 -> #REF! | C96: ='Cash Flow Statement'!C27-C97+'Income Statement'!C140-'Income Statement'!C141 -> #REF! | D96: ='Cash Flow Statement'!D27-D97+'Income Statement'!D140-'Income Statement'!D141 -> #REF! | E96: ='Cash Flow Statement'!E27-E97+'Income Statement'!E140-'Income Statement'!E141 -> #REF! | F96: ='Cash Flow Statement'!F27-F97+'Income Statement'!F140-'Income Statement'!F141 -> #REF! | G96: ='Cash Flow Statement'!G27-G97+'Income Statement'!G140-'Income Statement'!G141 -> #REF! | H96: ='Cash Flow Statement'!H27-H97+'Income Statement'!H140-'Income Statement'!H141 -> #REF! | I96: ='Cash Flow Statement'!I27-I97+'Income Statement'!I140-'Income Statement'!I141 -> #REF! | ... AA96: ='Cash Flow Statement'!AA27-AA97+'Income Statement'!AA140-'Income Statement'!AA141 -> 27530.562
A97: Working Capital | B97: =-'Balance Sheet'!#REF! -> #REF! | C97: =-'Balance Sheet'!#REF! -> #REF! | D97: =-'Balance Sheet'!#REF! -> #REF! | E97: =-'Balance Sheet'!#REF! -> #REF! | F97: =-'Balance Sheet'!#REF! -> #REF! | G97: =-'Balance Sheet'!#REF! -> #REF! | H97: =-'Balance Sheet'!#REF! -> #REF! | I97: =-'Balance Sheet'!#REF! -> #REF! | ... P97: =-'Balance Sheet'!#REF! -> #REF! | Q97: ='Balance Sheet'!Q155 -> -1041 | R97: ='Balance Sheet'!R155 -> -796 | S97: ='Balance Sheet'!S155 -> 172 | T97: ='Balance Sheet'!T155 -> -923 | U97: ='Balance Sheet'!U155 -> 1997 | V97: ='Balance Sheet'!V155 -> 1710.7027 | W97: ='Balance Sheet'!W155 -> 634.16631 | X97: ='Balance Sheet'!X155 -> -1460.4951 | ... AA97: ='Balance Sheet'!AA155 -> -8051.0839
A98: R&D | B98: =-'Income Statement'!B143 -> -2862 | C98: =-'Income Statement'!C143 -> -2655 | D98: =-'Income Statement'!D143 -> -2700 | E98: =-'Income Statement'!E143 -> -2732 | F98: =-'Income Statement'!F143 -> -3050 | G98: =-'Income Statement'!G143 -> -3133 | H98: =-'Income Statement'!H143 -> -3459 | I98: =-'Income Statement'!I143 -> -3410 | ... AA98: =-'Income Statement'!AA143 -> -4562.0017
A99: Acquisitions | B99: ='Cash Flow Statement'!B32+'Cash Flow Statement'!B33 -> 4 | C99: ='Cash Flow Statement'!C32+'Cash Flow Statement'!C33 -> 29 | D99: ='Cash Flow Statement'!D32+'Cash Flow Statement'!D33 -> -263 | E99: ='Cash Flow Statement'!E32+'Cash Flow Statement'!E33 -> -8 | F99: ='Cash Flow Statement'!F32+'Cash Flow Statement'!F33 -> -26 | G99: ='Cash Flow Statement'!G32+'Cash Flow Statement'!G33 -> -1517 | H99: ='Cash Flow Statement'!H32+'Cash Flow Statement'!H33 -> -201 | I99: ='Cash Flow Statement'!I32+'Cash Flow Statement'!I33 -> -16 | ... AA99: ='Cash Flow Statement'!AA32+'Cash Flow Statement'!AA33 -> 0
A100: Dividends | B100: ='Cash Flow Statement'!B45+'Cash Flow Statement'!B47 -> -536 | C100: ='Cash Flow Statement'!C45+'Cash Flow Statement'!C47 -> -98 | D100: ='Cash Flow Statement'!D45+'Cash Flow Statement'!D47 -> -107 | E100: ='Cash Flow Statement'!E45+'Cash Flow Statement'!E47 -> -166 | F100: ='Cash Flow Statement'!F45+'Cash Flow Statement'!F47 -> -7 | G100: ='Cash Flow Statement'!G45+'Cash Flow Statement'!G47 -> -183 | H100: ='Cash Flow Statement'!H45+'Cash Flow Statement'!H47 -> -379 | I100: ='Cash Flow Statement'!I45+'Cash Flow Statement'!I47 -> -469 | ... AA100: ='Cash Flow Statement'!AA45+'Cash Flow Statement'!AA47 -> -5453.7438
A101: Buybacks | B101: ='Cash Flow Statement'!B42 -> 0 | C101: ='Cash Flow Statement'!C42 -> 0 | D101: ='Cash Flow Statement'!D42 -> 0 | E101: ='Cash Flow Statement'!E42 -> 0 | F101: ='Cash Flow Statement'!F42 -> 0 | G101: ='Cash Flow Statement'!G42 -> 0 | H101: ='Cash Flow Statement'!H42 -> 0 | I101: ='Cash Flow Statement'!I42 -> -1915 | ... AA101: ='Cash Flow Statement'!AA42 -> 0
A102: Investment | B102: ='Cash Flow Statement'!B28+'Cash Flow Statement'!B30+'Income Statement'!B142 -> -2221 | C102: ='Cash Flow Statement'!C28+'Cash Flow Statement'!C30+'Income Statement'!C142 -> -1773 | D102: ='Cash Flow Statement'!D28+'Cash Flow Statement'!D30+'Income Statement'!D142 -> -1715 | E102: ='Cash Flow Statement'!E28+'Cash Flow Statement'!E30+'Income Statement'!E142 -> -1829 | F102: ='Cash Flow Statement'!F28+'Cash Flow Statement'!F30+'Income Statement'!F142 -> -2060 | G102: ='Cash Flow Statement'!G28+'Cash Flow Statement'!G30+'Income Statement'!G142 -> -2021 | H102: ='Cash Flow Statement'!H28+'Cash Flow Statement'!H30+'Income Statement'!H142 -> -2709 | I102: ='Cash Flow Statement'!I28+'Cash Flow Statement'!I30+'Income Statement'!I142 -> -2468 | ... AA102: ='Cash Flow Statement'!AA28+'Cash Flow Statement'!AA30+'Income Statement'!AA142 -> -4885.2962
A103: Net Change in Debt (lower = debt paydown) | B103: ='Cash Flow Statement'!B43+'Cash Flow Statement'!B44 -> 845 | C103: ='Cash Flow Statement'!C43+'Cash Flow Statement'!C44 -> -586 | D103: ='Cash Flow Statement'!D43+'Cash Flow Statement'!D44 -> -157 | E103: ='Cash Flow Statement'!E43+'Cash Flow Statement'!E44 -> 906 | F103: ='Cash Flow Statement'!F43+'Cash Flow Statement'!F44 -> -1061 | G103: ='Cash Flow Statement'!G43+'Cash Flow Statement'!G44 -> 414 | H103: ='Cash Flow Statement'!H43+'Cash Flow Statement'!H44 -> -125 | I103: ='Cash Flow Statement'!I41+'Cash Flow Statement'!I44 -> -534 | J103: ='Cash Flow Statement'!J43+'Cash Flow Statement'!J44 -> 930 | K103: ='Cash Flow Statement'!K43+'Cash Flow Statement'!K44 -> 992 | L103: ='Cash Flow Statement'!L43+'Cash Flow Statement'!L44 -> 1572 | M103: ='Cash Flow Statement'!M43+'Cash Flow Statement'!M44 -> 1284 | N103: ='Cash Flow Statement'!N43+'Cash Flow Statement'!N44 -> -2308 | O103: ='Cash Flow Statement'!O43+'Cash Flow Statement'!O44 -> -160 | P103: ='Cash Flow Statement'!P43+'Cash Flow Statement'!P44 -> 6657 | Q103: ='Cash Flow Statement'!Q43+'Cash Flow Statement'!Q44 -> -2295 | ... AA103: ='Cash Flow Statement'!AA43+'Cash Flow Statement'!AA44 -> 0
A104: Other | B104: =B105-SUM(B96:B103) -> #REF! | C104: =C105-SUM(C96:C103) -> #REF! | D104: =D105-SUM(D96:D103) -> #REF! | E104: =E105-SUM(E96:E103) -> #REF! | F104: =F105-SUM(F96:F103) -> #REF! | G104: =G105-SUM(G96:G103) -> #REF! | H104: =H105-SUM(H96:H103) -> #REF! | I104: =I105-SUM(I96:I103) -> #REF! | ... AA104: =AA105-SUM(AA96:AA103) -> 286.11042
A105: Net Change in Cash | B105: ='Cash Flow Statement'!B52 -> 2814 | C105: ='Cash Flow Statement'!C52 -> -477 | D105: ='Cash Flow Statement'!D52 -> -754 | E105: ='Cash Flow Statement'!E52 -> 343 | F105: ='Cash Flow Statement'!F52 -> -2112 | G105: ='Cash Flow Statement'!G52 -> 256 | H105: ='Cash Flow Statement'!H52 -> 3449 | I105: ='Cash Flow Statement'!I52 -> -879 | ... AA105: ='Cash Flow Statement'!AA52 -> 4864.547
A107: Working Capital - as a % of Cash flow from Operations | B107: =B97/B$96 -> #REF! | C107: =C97/C$96 -> #REF! | D107: =D97/D$96 -> #REF! | E107: =E97/E$96 -> #REF! | F107: =F97/F$96 -> #REF! | G107: =G97/G$96 -> #REF! | H107: =H97/H$96 -> #REF! | I107: =I97/I$96 -> #REF! | ... AA107: =AA97/AA$96 -> -0.29244168
A108: R&D - as a % of Cash flow from Operations | B108: =B98/B$96 -> #REF! | C108: =C98/C$96 -> #REF! | D108: =D98/D$96 -> #REF! | E108: =E98/E$96 -> #REF! | F108: =F98/F$96 -> #REF! | G108: =G98/G$96 -> #REF! | H108: =H98/H$96 -> #REF! | I108: =I98/I$96 -> #REF! | ... AA108: =AA98/AA$96 -> -0.16570681
...

Sheet Balance Sheet
A1: ='DCF Valuation'!D51 -> 240
A2: Balance Sheet | B2: ='Income Statement'!B2 -> 2006 | C2: ='Income Statement'!C2 -> 2007 | D2: ='Income Statement'!D2 -> 2008 | E2: ='Income Statement'!E2 -> 2009 | F2: ='Income Statement'!F2 -> 2010 | G2: ='Income Statement'!G2 -> 2011 | H2: ='Income Statement'!H2 -> 2012 | I2: ='Income Statement'!I2 -> 2013 | ... P2: ='Income Statement'!P2 -> 2020 | Q2: =P2+1 -> 2021 | R2: =Q2+1 -> 2022 | S2: =R2+1 -> 2023 | T2: =S2+1 -> 2024 | U2: 2025 | V2: =U2+1 -> 2026 | W2: =V2+1 -> 2027 | X2: =W2+1 -> 2028 | Y2: =X2+1 -> 2029 | Z2: =Y2+1 -> 2030 | AA2: =Z2+1 -> 2031
A4: Intangible assets | B4: 10855 | C4: 10832 | D4: 11171 | E4: 11060 | F4: 11299 | G4: 12786 | H4: 13429 | I4: 13653 | J4: 12758 | K4: 12555 | L4: 12068 | M4: 11629 | N4: 16726 | O4: 16591 | P4: 16199 | Q4: 16367 | R4: 16768 | S4: 16929 | T4: 17179 | U4: 16847 | V4: =U4-'Cash Flow Statement'!V14-(0.25*'Cash Flow Statement'!V28)-(0.75*'Cash Flow Statement'!V30) -> 16903.734 | W4: =V4-'Cash Flow Statement'!W14-(0.25*'Cash Flow Statement'!W28)-(0.75*'Cash Flow Statement'!W30) -> 16922.605 | X4: =W4-'Cash Flow Statement'!X14-(0.25*'Cash Flow Statement'!X28)-(0.75*'Cash Flow Statement'!X30) -> 17697.167 | Y4: =X4-'Cash Flow Statement'!Y14-(0.25*'Cash Flow Statement'!Y28)-(0.75*'Cash Flow Statement'!Y30) -> 18509.002 | Z4: =Y4-'Cash Flow Statement'!Z14-(0.25*'Cash Flow Statement'!Z28)-(0.75*'Cash Flow Statement'!Z30) -> 19332.793 | AA4: =Z4-'Cash Flow Statement'!AA14-(0.25*'Cash Flow Statement'!AA28)-(0.75*'Cash Flow Statement'!AA30) -> 20158.295
A5: PP&E | B5: 14178 | C5: 13393 | D5: 12156 | E5: 12508 | F5: 13427 | G5: 14146 | H5: 15196 | I5: 15856 | J5: 16321 | K5: 17127 | L5: 16913 | M5: 16610 | N5: 16773 | O5: 17294 | P5: 16674 | Q5: 16536 | R5: 16505 | S5: 17201 | T5: 19112 | U5: 20893 | V5: =U5-'Cash Flow Statement'!V12-(0.75*'Cash Flow Statement'!V28)-(0.25*'Cash Flow Statement'!V30) -> 21724.576 | W5: =V5-'Cash Flow Statement'!W12-(0.75*'Cash Flow Statement'!W28)-(0.25*'Cash Flow Statement'!W30) -> 22717.544 | X5: =W5-'Cash Flow Statement'!X12-(0.75*'Cash Flow Statement'!X28)-(0.25*'Cash Flow Statement'!X30) -> 23814.137 | Y5: =X5-'Cash Flow Statement'!Y12-(0.75*'Cash Flow Statement'!Y28)-(0.25*'Cash Flow Statement'!Y30) -> 24814.227 | Z5: =Y5-'Cash Flow Statement'!Z12-(0.75*'Cash Flow Statement'!Z28)-(0.25*'Cash Flow Statement'!Z30) -> 25678.128 | AA5: =Z5-'Cash Flow Statement'!AA12-(0.75*'Cash Flow Statement'!AA28)-(0.25*'Cash Flow Statement'!AA30) -> 26446.492
A6: Investment property | B6: 137 | C6: 96 | D6: 87 | E6: 78 | F6: 77 | G6: 74 | H6: 72 | I6: 69 | J6: 67 | K6: 66 | L6: 5 | M6: 3 | N6: =M6 -> 3 | O6: 2 | P6: 2 | Q6: 41 | R6: 37 | S6: 35 | T6: 35 | U6: 68 | V6: =U6 -> 68 | W6: =V6 -> 68 | X6: =W6 -> 68 | Y6: =X6 -> 68 | Z6: =Y6 -> 68 | AA6: =Z6 -> 68
A7: Investments in associates accounted for under the equity method | B7: 2095 | C7: 2238 | D7: 2356 | E7: 2514 | F7: 2451 | G7: 2677 | H7: 2662 | I7: 2902 | J7: 3391 | K7: 1326 | L7: 1608 | M7: 1678 | N7: 1693 | O7: 1626 | P7: 1578 | Q7: 1672 | R7: 2067 | S7: 2228 | T7: 2433 | U7: 2360 | V7: =U7+'Cash Flow Statement'!V33-'Cash Flow Statement'!V18-'Cash Flow Statement'!V34-'Cash Flow Statement'!V35 -> 2680.25 | W7: =V7+'Cash Flow Statement'!W33-'Cash Flow Statement'!W18-'Cash Flow Statement'!W34-'Cash Flow Statement'!W35 -> 3016.5125 | X7: =W7+'Cash Flow Statement'!X33-'Cash Flow Statement'!X18-'Cash Flow Statement'!X34-'Cash Flow Statement'!X35 -> 3369.5881 | Y7: =X7+'Cash Flow Statement'!Y33-'Cash Flow Statement'!Y18-'Cash Flow Statement'!Y34-'Cash Flow Statement'!Y35 -> 3740.3175 | Z7: =Y7+'Cash Flow Statement'!Z33-'Cash Flow Statement'!Z18-'Cash Flow Statement'!Z34-'Cash Flow Statement'!Z35 -> 4129.5834 | AA7: =Z7+'Cash Flow Statement'!AA33-'Cash Flow Statement'!AA18-'Cash Flow Statement'!AA34-'Cash Flow Statement'!AA35 -> 4538.3126
A8: Other investments and other long-term financial assets | B8: 1666 | C8: 1553 | D8: 1712 | E8: 2210 | F8: 2386 | G8: 2352 | H8: 2115 | I8: 1864 | J8: 1769 | K8: 2492 | L8: 3655 | M8: 4204 | N8: 3811 | O8: 4453 | P8: 3855 | Q8: 4001 | R8: 4190 | S8: 4719 | T8: 5077 | U8: 5470 | V8: =U8 -> 5470 | W8: =V8 -> 5470 | X8: =W8 -> 5470 | Y8: =X8 -> 5470 | Z8: =Y8 -> 5470 | AA8: =Z8 -> 5470
A9: Non-current other financial assets | B9: 4231 | C9: 2510 | D9: 1612 | E9: 1607 | F9: 871 | G9: 631 | H9: 1386 | I9: 2076 | J9: 586 | K9: 1096 | L9: 976 | M9: 2980 | N9: 1108 | O9: 1033 | P9: 3483 | Q9: 691 | R9: 781 | S9: 922 | T9: 697 | U9: 1070 | V9: =U9 -> 1070 | W9: =V9 -> 1070 | X9: =W9 -> 1070 | Y9: =X9 -> 1070 | Z9: =Y9 -> 1070 | AA9: =Z9 -> 1070
A10: Non-current other assets | C10: 1033 | D10: 1034 | E10: 1176 | F10: 1104 | G10: 1253 | H10: 1415 | I10: 1653 | J10: 1822 | K10: 2166 | L10: 2358 | M10: 2295 | N10: 888 | O10: 522 | P10: 483 | Q10: 901 | R10: 1872 | S10: 1854 | T10: 2650 | U10: 2762 | V10: =U10 -> 2762 | W10: =V10 -> 2762 | X10: =W10 -> 2762 | Y10: =X10 -> 2762 | Z10: =Y10 -> 2762 | AA10: =Z10 -> 2762
A11: Deferred tax assets | B11: 2624 | C11: 2705 | D11: 2756 | E11: 2656 | F11: 4250 | G11: 4318 | H11: 4532 | I11: 3840 | J11: 5717 | K11: 6759 | L11: 7557 | M11: 3598 | N11: 4835 | O11: 5008 | P11: 4023 | Q11: 4323 | R11: 4683 | S11: 3448 | T11: 3505 | U11: 1808 | V11: =U11 -> 1808 | W11: =V11 -> 1808 | X11: =W11 -> 1808 | Y11: =X11 -> 1808 | Z11: =Y11 -> 1808 | AA11: =Z11 -> 1808
A12: Non-current securities | B12: 1294 | C12: 2691 | D12: 3040 | E12: 3983 | F12: 5332 | G12: 7229 | H12: 5987 | I12: 4300 | J12: 5989 | K12: 9851 | L12: 9897 | M12: 10944 | N12: 10662 | O12: 11066 | P12: 5350 | Q12: 6794 | R12: 6013 | S12: 7508 | T12: 9032 | U12: 9997 | V12: =U12 -> 9997 | W12: =V12 -> 9997 | X12: =W12 -> 9997 | Y12: =X12 -> 9997 | Z12: =Y12 -> 9997 | AA12: =Z12 -> 9997
A13: Non-current contract assets | B13: =B14-SUM(B4:B12) -> 0 | C13: =C14-SUM(C4:C12) -> 0 | D13: =D14-SUM(D4:D12) -> 0 | E13: =E14-SUM(E4:E12) -> 0 | F13: =F14-SUM(F4:F12) -> 0 | G13: =G14-SUM(G4:G12) -> 0 | H13: =H14-SUM(H4:H12) -> 0 | I13: =I14-SUM(I4:I12) -> 0 | J13: 750 | K13: 1779 | L13: =1148-17 -> 1131 | M13: =202-17 -> 185 | N13: 65 | O13: 91 | P13: 48 | Q13: 27 | R13: 26 | S13: 26 | T13: 61 | U13: 17 | V13: 5 | W13: =V13 -> 5 | X13: =W13 -> 5 | Y13: =X13 -> 5 | Z13: =Y13 -> 5 | AA13: =Z13 -> 5
A14: Non-Current assets | B14: 37080 | C14: 37051 | D14: 35924 | E14: 37792 | F14: 41197 | G14: 45466 | H14: 46794 | I14: 46213 | J14: =SUM(J4:J13) -> 49170 | K14: =SUM(K4:K13) -> 55217 | L14: =SUM(L4:L13) -> 56168 | M14: =SUM(M4:M13) -> 54126 | N14: =SUM(N4:N13) -> 56564 | O14: =SUM(O4:O13) -> 57686 | P14: =SUM(P4:P13) -> 51695 | Q14: =SUM(Q4:Q13) -> 51353 | ... AA14: =SUM(AA4:AA13) -> 72323.1
Q15: =Q16/'Income Statement'!Q14 -> 0.54723964 | R15: =R16/'Income Statement'!R14 -> 0.54799789 | S15: =S16/'Income Statement'!S14 -> 0.51555481 | T15: =T16/'Income Statement'!T14 -> 0.54521161 | U15: =U16/'Income Statement'!U14 -> 0.56690471 | V15: =V16/'Income Statement'!V14 -> 0.54443865 | W15: =W16/'Income Statement'!W14 -> 0.5421537 | X15: =X16/'Income Statement'!X14 -> 0.53235996 | ... AA15: =AA16/'Income Statement'!AA14 -> 0.4990697
A16: Inventories | B16: 16892 | C16: 18906 | D16: 19452 | E16: 21577 | F16: 20862 | G16: 22563 | H16: 23216 | I16: 25060 | J16: 25355 | K16: 29051 | L16: 29688 | M16: 31464 | N16: 31891 | O16: 31550 | P16: 30401 | Q16: 28538 | R16: 32202 | S16: 33741 | T16: 37745 | U16: 41676 | V16: =-V17/365*'Income Statement'!V60 -> 43714.458 | W16: =-W17/365*'Income Statement'!W60 -> 49522.58 | X16: =-X17/365*'Income Statement'!X60 -> 54643.847 | Y16: =-Y17/365*'Income Statement'!Y60 -> 57572.167 | Z16: =-Z17/365*'Income Statement'!Z60 -> 58522.854 | AA16: =-AA17/365*'Income Statement'!AA60 -> 60620.884
A17: DIO | B17: =-AVERAGE(A16:B16)*365/'Income Statement'!B60 -> 177.56984 | C17: =-AVERAGE(B16:C16)*365/'Income Statement'!C60 -> 187.72298 | D17: =-AVERAGE(C16:D16)*365/'Income Statement'!D60 -> 194.95739 | E17: =-AVERAGE(D16:E16)*365/'Income Statement'!E60 -> 195.08096 | F17: =-AVERAGE(E16:F16)*365/'Income Statement'!F60 -> 195.94003 | G17: =-AVERAGE(F16:G16)*365/'Income Statement'!G60 -> 187.42018 | H17: =-AVERAGE(G16:H16)*365/'Income Statement'!H60 -> 171.97043 | I17: =-AVERAGE(H16:I16)*365/'Income Statement'!I60 -> 173.10875 | ... U17: =-AVERAGE(T16:U16)*365/'Income Statement'!U60 -> 232.08385 | V17: 236.9 | W17: 236.95 | X17: 235.2 | Y17: 230.3 | Z17: 222.55 | AA17: =Z17-0.5 -> 222.05
A18: Receivables | B18: 4852 | C18: 4639 | D18: 5267 | E18: 5587 | F18: 6632 | G18: 6394 | H18: 6788 | I18: 7239 | J18: 6798 | K18: 7877 | L18: 8101 | M18: 8358 | N18: 6078 | O18: 5674 | P18: 5132 | Q18: 4957 | R18: 4953 | S18: 4725 | T18: 5293 | U18: 5454 | V18: =V19/365*'Income Statement'!V58 -> 6599.4012 | W18: =W19/365*'Income Statement'!W58 -> 7507.7402 | X18: =X19/365*'Income Statement'!X58 -> 8155.3202 | Y18: =Y19/365*'Income Statement'!Y58 -> 8535.8069 | Z18: =Z19/365*'Income Statement'!Z58 -> 8968.8247 | AA18: =AA19/365*'Income Statement'!AA58 -> 9318.0757
A19: DSO | B19: =AVERAGE(A18:B18)*365/'Income Statement'!B58 -> 44.909976 | C19: =AVERAGE(B18:C18)*365/'Income Statement'!C58 -> 44.273381 | D19: =AVERAGE(C18:D18)*365/'Income Statement'!D58 -> 41.785392 | E19: =AVERAGE(D18:E18)*365/'Income Statement'!E58 -> 46.257881 | F19: =AVERAGE(E18:F18)*365/'Income Statement'!F58 -> 48.740328 | G19: =AVERAGE(F18:G18)*365/'Income Statement'!G58 -> 48.388801 | H19: =AVERAGE(G18:H18)*365/'Income Statement'!H58 -> 42.594104 | I19: =AVERAGE(H18:I18)*365/'Income Statement'!I58 -> 40.752794 | ... U19: =AVERAGE(T18:U18)*365/'Income Statement'!U58 -> 26.679283 | V19: 30 | W19: 30 | X19: =W19-1 -> 29 | Y19: =X19-1 -> 28 | Z19: =Y19 -> 28 | AA19: =Z19 -> 28
A20: Current portion of other long-term financial assets | B20: 103 | C20: 166 | D20: 177 | E20: 230 | F20: 111 | G20: 172 | H20: 287 | I20: 181 | J20: 167 | K20: 178 | L20: 522 | M20: 529 | N20: 489 | O20: 449 | P20: 468 | Q20: 537 | R20: 665 | S20: 795 | T20: 897 | U20: 734 | V20: =U20 -> 734 | W20: =V20 -> 734 | X20: =W20 -> 734 | Y20: =X20 -> 734 | Z20: =Y20 -> 734 | AA20: =Z20 -> 734
A21: Current other financial assets | B21: 4014 | C21: 3855 | D21: 2495 | E21: 2043 | F21: 1575 | G21: 1739 | H21: 1448 | I21: 1557 | J21: 1164 | K21: 1402 | L21: 1257 | M21: 1979 | N21: 1811 | O21: 2060 | P21: 2432 | Q21: 1451 | R21: 2542 | S21: 1851 | T21: 2004 | U21: 2557 | V21: =U21 -> 2557 | W21: =V21 -> 2557 | X21: =W21 -> 2557 | Y21: =X21 -> 2557 | Z21: =Y21 -> 2557 | AA21: =Z21 -> 2557
A22: Current other assets | C22: 1317 | D22: 1466 | E22: 1698 | F22: 1712 | G22: 2253 | H22: 2046 | I22: 2074 | J22: 2389 | K22: 2819 | L22: 2576 | M22: 2907 | N22: =4246+789 -> 5035 | O22: =2423+1167 -> 3590 | P22: =2216+1074 -> 3290 | Q22: =2393+1377 -> 3770 | R22: =2850+1501 -> 4351 | S22: =2697+1823 -> 4520 | T22: =1474+3463 -> 4937 | U22: =1639+3760 -> 5399 | V22: =U22 -> 5399 | W22: =V22 -> 5399 | X22: =W22 -> 5399 | Y22: =X22 -> 5399 | Z22: =Y22 -> 5399 | AA22: =Z22 -> 5399
A23: Current tax assets | B23: 428 | C23: 375 | D23: 452 | E23: 267 | F23: 234 | G23: 339 | H23: 458 | I23: 632 | J23: 605 | K23: 860 | L23: 1110 | M23: 914 | N23: 1451 | O23: 1784 | P23: 620 | Q23: 552 | R23: 704 | S23: 546 | T23: 663 | U23: 543 | V23: =U23 -> 543 | W23: =V23 -> 543 | X23: =W23 -> 543 | Y23: =X23 -> 543 | Z23: =Y23 -> 543 | AA23: =Z23 -> 543
A24: Current securities | B24: 549 | C24: 1598 | D24: 3912 | E24: 4072 | F24: 5834 | G24: 4272 | H24: 2328 | I24: 2590 | J24: 3183 | K24: 1788 | L24: 1551 | M24: 1627 | N24: 2132 | O24: 2302 | P24: 1618 | Q24: 1317 | R24: 1762 | S24: 1301 | T24: 2829 | U24: 3093 | V24: =U24 -> 3093 | W24: =V24 -> 3093 | X24: =W24 -> 3093 | Y24: =X24 -> 3093 | Z24: =Y24 -> 3093 | AA24: =Z24 -> 3093
A25: Cash & Cash equivalents | B25: 8143 | C25: 7549 | D25: 6745 | E25: 7038 | F25: 5030 | G25: 5284 | H25: 8756 | I25: ='Cash Flow Statement'!I57 -> 7765 | J25: ='Cash Flow Statement'!J57 -> 7271 | K25: ='Cash Flow Statement'!K57 -> 7489 | L25: ='Cash Flow Statement'!L57 -> 10160 | M25: ='Cash Flow Statement'!M57 -> 12021 | N25: ='Cash Flow Statement'!N57 -> 9428 | O25: ='Cash Flow Statement'!O57 -> 9314 | P25: ='Cash Flow Statement'!P57 -> 14439 | ... R25: ='Cash Flow Statement'!R57 -> 15823 | S25: ='Cash Flow Statement'!S57-4 -> 16469 | T25: ='Cash Flow Statement'!T60 -> 15003 | U25: 14128 | V25: ='Cash Flow Statement'!V57 -> 14956.337 | W25: ='Cash Flow Statement'!W57 -> 16708.149 | X25: ='Cash Flow Statement'!X57 -> 19754.53 | Y25: ='Cash Flow Statement'!Y57 -> 26005.194 | Z25: ='Cash Flow Statement'!Z57 -> 32682.678 | AA25: ='Cash Flow Statement'!AA57 -> 37547.225
A26: Assets and disposal group of assets classified as held for sale | B26: =B27-SUM(B16,B18,B20:B25) -> 76 | C26: =C27-SUM(C16,C18,C20:C25) -> 0 | D26: =D27-SUM(D16,D18,D20:D25) -> 263 | E26: =E27-SUM(E16,E18,E20:E25) -> 0 | F26: =F27-SUM(F16,F18,F20:F25) -> 0 | G26: =G27-SUM(G16,G18,G20:G25) -> 0 | H26: =H27-SUM(H16,H18,H20:H25) -> 0 | I26: =I27-SUM(I16,I18,I20:I25) -> 0 | J26: 0 | K26: 0 | M26: 12 | N26: =336-17 -> 319 | S26: 53 | T26: 61 | U26: 63 | V26: =U26 -> 63 | W26: =V26 -> 63 | X26: =W26 -> 63 | Y26: =X26 -> 63 | Z26: =Y26 -> 63 | AA26: =Z26 -> 63
A27: Current assets | B27: 35057 | C27: 38405 | D27: 40229 | E27: 42512 | F27: 41990 | G27: 43016 | H27: 45327 | I27: 47098 | J27: =SUM(J16,J18,J20:J26) -> 46932 | K27: =SUM(K16,K18,K20:K26) -> 51464 | L27: =SUM(L16,L18,L20:L26) -> 54965 | M27: =SUM(M16,M18,M20:M26) -> 59811 | N27: =SUM(N16,N18,N20:N26) -> 58634 | O27: =SUM(O16,O18,O20:O26) -> 56723 | P27: =SUM(P16,P18,P20:P26) -> 58400 | Q27: =SUM(Q16,Q18,Q20:Q26) -> 55694 | ... AA27: =SUM(AA16,AA18,AA20:AA26) -> 119875.19
A29: Non-current Provisions | B29: -8911 | C29: -8055 | D29: -7479 | E29: -8137 | F29: -8213 | G29: -9144 | H29: -9850 | I29: -10046 | J29: -10400 | K29: -9871 | L29: -10826 | M29: -10153 | N29: -11571 | O29: -12542 | P29: -13998 | Q29: -10771 | R29: -6896 | S29: -5667 | T29: -4630 | U29: -3976 | V29: =U29 -> -3976 | W29: =V29 -> -3976 | X29: =W29 -> -3976 | Y29: =X29 -> -3976 | Z29: =Y29 -> -3976 | AA29: =Z29 -> -3976
A30: Long-term financing liabilities | B30: -3561 | C30: -3090 | D30: -3046 | E30: -2867 | F30: -2870 | G30: -3628 | H30: -3506 | I30: -3956 | J30: -6278 | K30: -6335 | L30: -8791 | M30: -8984 | N30: -7463 | O30: -8189 | P30: -14082 | Q30: -13094 | R30: -10631 | S30: -10202 | T30: -10355 | U30: -9063 | V30: =U30-'Cash Flow Statement'!V44-'Cash Flow Statement'!V26 -> -8613 | W30: =V30-'Cash Flow Statement'!W44-'Cash Flow Statement'!W26 -> -8341 | X30: =W30-'Cash Flow Statement'!X44-'Cash Flow Statement'!X26 -> -8069 | Y30: =X30-'Cash Flow Statement'!Y44-'Cash Flow Statement'!Y26 -> -7797 | Z30: =Y30-'Cash Flow Statement'!Z44-'Cash Flow Statement'!Z26 -> -7525 | AA30: =Z30-'Cash Flow Statement'!AA44-'Cash Flow Statement'!AA26 -> -7253
A31: Non-current other financial liabilities | B31: -11722 | C31: -5653 | D31: -7499 | E31: -6175 | F31: -8624 | G31: -8193 | H31: -7458 | I31: -7158 | J31: -9922 | K31: -14038 | L31: -13313 | M31: -6948 | N31: -8009 | O31: -7498 | P31: -5657 | Q31: -6562 | R31: -10117 | S31: -6715 | T31: -7576 | U31: -4809 | V31: =U31 -> -4809 | W31: =V31 -> -4809 | X31: =W31 -> -4809 | Y31: =X31 -> -4809 | Z31: =Y31 -> -4809 | AA31: =Z31 -> -4809
A32: Non-current other liabilities | C32: -8474 | D32: -8907 | E32: -9091 | F32: -9264 | G32: -9817 | H32: -10524 | I32: -10790 | J32: -12849 | K32: -15256 | L32: -16279 | M32: -17190 | N32: =-15832-460 -> -16292 | O32: =-16980-384 -> -17364 | P32: =-19212-436 -> -19648 | Q32: =-18620-583 -> -19203 | R32: =-22044-498 -> -22542 | S32: =-23961-450 -> -24411 | T32: =-25572-463 -> -26035 | U32: =-26484-477 -> -26961 | V32: =U32 -> -26961 | W32: =V32 -> -26961 | X32: =W32 -> -26961 | Y32: =X32 -> -26961 | Z32: =Y32 -> -26961 | AA32: =Z32 -> -26961
A33: Deferred tax liabilities | B33: -2465 | C33: -2188 | D33: -953 | E33: -751 | F33: -1195 | G33: -1043 | H33: -1502 | I33: -1487 | J33: -1130 | K33: -1200 | L33: -1292 | M33: -981 | N33: -1318 | O33: -398 | P33: -451 | Q33: -116 | R33: -164 | S33: -361 | T33: -271 | U33: -428 | V33: =U33-('Cash Flow Statement'!V10+'Cash Flow Statement'!V11) -> -428 | W33: =V33-('Cash Flow Statement'!W10+'Cash Flow Statement'!W11) -> -428 | X33: =W33-('Cash Flow Statement'!X10+'Cash Flow Statement'!X11) -> -428 | Y33: =X33-('Cash Flow Statement'!Y10+'Cash Flow Statement'!Y11) -> -428 | Z33: =Y33-('Cash Flow Statement'!Z10+'Cash Flow Statement'!Z11) -> -428 | AA33: =Z33-('Cash Flow Statement'!AA10+'Cash Flow Statement'!AA11) -> -428
A34: Non-current deferred income | B34: -1110 | C34: -753 | D34: -418 | E34: -266 | F34: -315 | G34: -290 | H34: -212 | I34: -239 | J34: -267 | L34: -288 | M34: -199 | N34: -40 | O34: -54 | P34: -32 | Q34: -8 | R34: -17 | S34: -35 | T34: -27 | U34: -7 | V34: =U34 -> -7 | W34: =V34 -> -7 | X34: =W34 -> -7 | Y34: =X34 -> -7 | Z34: =Y34 -> -7 | AA34: =Z34 -> -7
A35: Other | B35: 0 | C35: 0 | D35: 0 | E35: 0 | F35: 0 | G35: 0 | H35: 0 | I35: 0 | J35: -680 | K35: -231 | L35: -991 | M35: -106 | N35: -432 | O35: 0 | P35: -300 | Q35: 0 | R35: 0 | S35: 0 | T35: 0 | U35: =T35 -> 0 | V35: =U35 -> 0 | W35: =V35 -> 0 | X35: =W35 -> 0 | Y35: =X35 -> 0 | Z35: =Y35 -> 0 | AA35: =Z35 -> 0
A36: Non-Current Liabilities | B36: -27769 | C36: -28213 | D36: -28302 | E36: -27287 | F36: -30481 | G36: -32115 | H36: -33052 | I36: -33676 | J36: =SUM(J29:J35) -> -41526 | K36: =SUM(K29:K35) -> -46931 | L36: =SUM(L29:L35) -> -51780 | M36: =SUM(M29:M35) -> -44561 | N36: =SUM(N29:N35) -> -45125 | O36: =SUM(O29:O35) -> -46045 | P36: =SUM(P29:P35) -> -54168 | Q36: =SUM(Q29:Q35) -> -49754 | ... AA36: =SUM(AA29:AA35) -> -43434
A38: Current provisions | B38: -3552 | C38: -4378 | D38: -4583 | E38: -5883 | F38: -5766 | G38: -5856 | H38: -6039 | I38: -5323 | J38: -5712 | K38: -5209 | L38: -6143 | M38: -6575 | N38: -7317 | O38: -6372 | P38: -6545 | Q38: -4510 | R38: -4127 | S38: -4161 | T38: -4307 | U38: -4369 | V38: =U38 -> -4369 | W38: =V38 -> -4369 | X38: =W38 -> -4369 | Y38: =X38 -> -4369 | Z38: =Y38 -> -4369 | AA38: =Z38 -> -4369
A39: Short-term financing liabilities | B39: -2196 | C39: -1724 | D39: -1458 | E39: -2429 | F39: -1408 | G39: -1476 | H39: -1273 | I39: -1645 | J39: -1073 | K39: -2790 | L39: -1687 | M39: -2212 | N39: -1463 | O39: -1959 | P39: -3013 | Q39: -1946 | R39: -2142 | S39: -3389 | T39: -3924 | U39: -5186 | V39: =U39 -> -5186 | W39: =V39 -> -5186 | X39: =W39 -> -5186 | Y39: =X39 -> -5186 | Z39: =Y39 -> -5186 | AA39: =Z39 -> -5186
A40: Trade liabilities | B40: -7461 | C40: -7398 | D40: -7824 | E40: -8217 | F40: -8546 | G40: -9630 | H40: -9921 | I40: -10372 | J40: -10183 | K40: -11763 | L40: -12532 | M40: -13444 | N40: -16237 | O40: -14808 | P40: -8722 | Q40: -9693 | R40: -13261 | S40: -14323 | T40: -13791 | U40: -15878 | V40: =V41/365*'Income Statement'!V60 -> -15998.251 | W40: =W41/365*'Income Statement'!W60 -> -18329.035 | X40: =X41/365*'Income Statement'!X60 -> -20607.3 | Y40: =Y41/365*'Income Statement'!Y60 -> -22423.566 | Z40: =Z41/365*'Income Statement'!Z60 -> -23850.575 | AA40: =AA41/365*'Income Statement'!AA60 -> -25034.249
A41: DPO | B41: =AVERAGE(A40:B40)*365/'Income Statement'!B60 -> 78.430534 | C41: =AVERAGE(B40:C40)*365/'Income Statement'!C60 -> 77.919875 | D41: =AVERAGE(C40:D40)*365/'Income Statement'!D60 -> 77.366948 | E41: =AVERAGE(D40:E40)*365/'Income Statement'!E60 -> 76.270289 | F41: =AVERAGE(E40:F40)*365/'Income Statement'!F60 -> 77.394442 | G41: =AVERAGE(F40:G40)*365/'Income Statement'!G60 -> 78.446731 | H41: =AVERAGE(G40:H40)*365/'Income Statement'!H60 -> 73.444022 | I41: =AVERAGE(H40:I40)*365/'Income Statement'!I60 -> 72.766922 | ... U41: =AVERAGE(T40:U40)*365/'Income Statement'!U60 -> 86.698677 | V41: =U41 -> 86.698677 | W41: =V41+1 -> 87.698677 | X41: =W41+1 -> 88.698677 | Y41: =X41+1 -> 89.698677 | Z41: =Y41+1 -> 90.698677 | AA41: =Z41+1 -> 91.698677
A42: Current other financial liabilities | B42: -17239 | C42: -1514 | D42: -1714 | E42: -1200 | F42: -1234 | G42: -1687 | H42: -1715 | I42: -1467 | J42: -3480 | K42: -5021 | L42: -5761 | M42: -2185 | N42: -2462 | O42: -2647 | P42: -1769 | Q42: -2532 | R42: -4073 | S42: -2569 | T42: -3050 | U42: -1000 | V42: =U42 -> -1000 | W42: =V42 -> -1000 | X42: =W42 -> -1000 | Y42: =X42 -> -1000 | Z42: =Y42 -> -1000 | AA42: =Z42 -> -1000
A43: Current other liabilities | C43: -18169 | D43: -19968 | E43: -23547 | F43: -25772 | G43: -27670 | H43: -28183 | I43: -28159 | J43: -25222 | K43: -27037 | L43: -27535 | M43: -29193 | N43: =-5288-26229 -> -31517 | O43: =-26426-6817 -> -33243 | P43: =-24675-3160 -> -27835 | Q43: =-23906-3532 -> -27438 | R43: =-23869-3803 -> -27672 | S43: =-24537-3507 -> -28044 | T43: =-30136-4022 -> -34158 | U43: =-32112-4223 -> -36335 | V43: =U43*(1+'Income Statement'!V24) -> -39684.905 | W43: =V43*(1+'Income Statement'!W24) -> -45147.119 | X43: =W43*(1+'Income Statement'!X24) -> -50732.362 | Y43: =X43*(1+'Income Statement'!Y24) -> -54995.685 | Z43: =Y43*(1+'Income Statement'!Z24) -> -57785.593 | AA43: =Z43*(1+'Income Statement'!AA24) -> -60035.795
A44: Current tax liabilties | B44: -218 | C44: -179 | D44: -201 | E44: -220 | F44: -254 | G44: -308 | H44: -458 | I44: -616 | J44: -738 | K44: -908 | L44: -1126 | M44: -1481 | N44: -732 | O44: -2780 | P44: -1311 | Q44: -1057 | R44: -817 | S44: -740 | T44: -593 | U44: -133 | V44: =U44 -> -133 | W44: =V44 -> -133 | X44: =W44 -> -133 | Y44: =X44 -> -133 | Z44: =Y44 -> -133 | AA44: =Z44 -> -133
A45: Current deferred income | B45: -486 | C45: -706 | D45: -822 | E45: -880 | F45: -790 | G45: -875 | H45: -1057 | I45: -999 | J45: -1089 | K45: -1049 | L45: -917 | M45: -935 | N45: -626 | O45: -565 | P45: -576 | Q45: -631 | R45: -503 | S45: -450 | T45: -725 | U45: -528 | V45: =U45 -> -528 | W45: =V45 -> -528 | X45: =W45 -> -528 | Y45: =X45 -> -528 | Z45: =Y45 -> -528 | AA45: =Z45 -> -528
A46: Other | B46: -64 | C46: 0 | D46: -155 | E46: 0 | F46: 0 | G46: 0 | H46: -3 | I46: 0 | J46: 0 | K46: 0 | L46: 0 | M46: 0 | N46: 0 | O46: 0 | P46: 300 | Q46: 0 | R46: 0 | S46: -74 | T46: -75 | U46: -82 | V46: =U46 -> -82 | W46: =V46 -> -82 | X46: =W46 -> -82 | Y46: =X46 -> -82 | Z46: =Y46 -> -82 | AA46: =Z46 -> -82
A47: Current Liabilities | B47: -31216 | C47: -34068 | D47: -36725 | E47: -42376 | F47: -43770 | G47: -47502 | H47: -48649 | I47: -48581 | J47: =SUM(J38:J40,J42:J46) -> -47497 | K47: =SUM(K38:K40,K42:K46) -> -53777 | L47: =SUM(L38:L40,L42:L46) -> -55701 | M47: =SUM(M38:M40,M42:M46) -> -56025 | N47: =SUM(N38:N40,N42:N46) -> -60354 | O47: =SUM(O38:O40,O42:O46) -> -62374 | P47: =SUM(P38:P40,P42:P46) -> -49471 | Q47: =SUM(Q38:Q40,Q42:Q46) -> -47807 | ... AA47: =SUM(AA38:AA40,AA42:AA46) -> -96368.044
A49: Capital Stock | B49: 813 | C49: 814 | D49: 815 | E49: 816 | F49: 816 | G49: 820 | H49: 827 | I49: 783 | J49: 785 | K49: 785 | L49: 773 | M49: 775 | N49: 777 | O49: 784 | P49: 785 | Q49: 787 | R49: 789 | S49: 791 | T49: 793 | U49: 793 | V49: =U49 -> 793 | W49: =V49 -> 793 | X49: =W49 -> 793 | Y49: =X49 -> 793 | Z49: =Y49 -> 793 | AA49: =Z49 -> 793
A50: Share Premium | B50: 8160 | C50: 7968 | D50: 7836 | E50: 7683 | F50: 7645 | G50: 7519 | H50: =8147-H51 -> 7247 | I50: 5049 | J50: 4500 | K50: 3484 | L50: 2745 | M50: 2826 | N50: 2941 | O50: 3555 | P50: 3599 | Q50: 3712 | R50: 3837 | S50: 3983 | T50: 4002 | U50: 4002 | V50: =U50+'Cash Flow Statement'!V42 -> 3002 | W50: =V50+'Cash Flow Statement'!W42 -> 1002 | X50: =W50+'Cash Flow Statement'!X42 -> -998 | Y50: =X50+'Cash Flow Statement'!Y42 -> -998 | Z50: =Y50+'Cash Flow Statement'!Z42 -> -998 | AA50: =Z50+'Cash Flow Statement'!AA42 -> -998
A51: Retained Earnings | B51: -567 | C51: -562 | D51: 722 | E51: -501 | F51: 46 | G51: 471 | H51: 900 | I51: 2300 | J51: 2989 | K51: 6316 | L51: 4987 | M51: 7007 | N51: 5923 | O51: 2241 | P51: 250 | Q51: 6834 | R51: 13408 | S51: 15616 | T51: 18687 | U51: 22334 | V51: =U51+'Income Statement'!V98+'Cash Flow Statement'!V45+'Cash Flow Statement'!V16+'Cash Flow Statement'!V36 -> 25522.599 | W51: =V51+'Income Statement'!W98+'Cash Flow Statement'!W45+'Cash Flow Statement'!W16+'Cash Flow Statement'!W36 -> 29817.977 | X51: =W51+'Income Statement'!X98+'Cash Flow Statement'!X45+'Cash Flow Statement'!X16+'Cash Flow Statement'!X36 -> 35265.927 | Y51: =X51+'Income Statement'!Y98+'Cash Flow Statement'!Y45+'Cash Flow Statement'!Y16+'Cash Flow Statement'!Y36 -> 41200.464 | Z51: =Y51+'Income Statement'!Z98+'Cash Flow Statement'!Z45+'Cash Flow Statement'!Z16+'Cash Flow Statement'!Z36 -> 47393.694 | AA51: =Z51+'Income Statement'!AA98+'Cash Flow Statement'!AA45+'Cash Flow Statement'!AA16+'Cash Flow Statement'!AA36 -> 53546.241
A52: Accumulated other comprehensive income | B52: 4955 | C52: 5076 | D52: 1758 | E52: 2646 | F52: 446 | G52: 153 | H52: 1513 | I52: 2929 | J52: -1205 | K52: -4316 | L52: -4845 | M52: 2742 | N52: 134 | O52: -523 | P52: 1853 | Q52: -1822 | R52: -5016 | S52: -2305 | T52: =-4553-253+1520 -> -3286 | U52: -70 | V52: =U52 -> -70 | W52: =V52 -> -70 | X52: =W52 -> -70 | Y52: =X52 -> -70 | Z52: =Y52 -> -70 | AA52: =Z52 -> -70
A53: Treasury shares | B53: -349 | C53: -206 | D53: -109 | E53: -109 | F53: -112 | G53: -113 | H53: -84 | I53: -50 | J53: -8 | K53: -303 | L53: -3 | M53: -2 | N53: -51 | O53: -82 | P53: -42 | Q53: -45 | R53: -68 | S53: -390 | T53: -590 | U53: -955 | V53: =U53 -> -955 | W53: =V53 -> -955 | X53: =W53 -> -955 | Y53: =X53 -> -955 | Z53: =Y53 -> -955 | AA53: =Z53 -> -955
A54: Non-controlling interests | B54: =B55-SUM(B49:B53) -> 140 | C54: =C55-SUM(C49:C53) -> 85 | D54: =D55-SUM(D49:D53) -> 104 | E54: =E55-SUM(E49:E53) -> 106 | F54: =F55-SUM(F49:F53) -> 95 | G54: =G55-SUM(G49:G53) -> 15 | H54: =H55-SUM(H49:H53) -> 17 | I54: =I55-SUM(I49:I53) -> 43 | J54: 18 | K54: 7 | L54: -5 | M54: 3 | N54: -5 | O54: 15 | P54: 11 | Q54: 20 | R54: 32 | S54: 35 | T54: 90 | U54: 80 | V54: =U54 -> 80 | W54: =V54 -> 80 | X54: =W54 -> 80 | Y54: =X54 -> 80 | Z54: =Y54 -> 80 | AA54: =Z54 -> 80
A55: Total Equity | B55: 13152 | C55: 13175 | D55: 11126 | E55: 10641 | F55: 8936 | G55: 8865 | H55: 10420 | I55: 11054 | J55: =SUM(J49:J54) -> 7079 | K55: =SUM(K49:K54) -> 5973 | L55: =SUM(L49:L54) -> 3652 | M55: =SUM(M49:M54) -> 13351 | N55: =SUM(N49:N54) -> 9719 | O55: =SUM(O49:O54) -> 5990 | P55: =SUM(P49:P54) -> 6456 | Q55: =SUM(Q49:Q54) -> 9486 | ... AA55: =SUM(AA49:AA54) -> 52396.241
A56: balance sheet check | B56: =B14+B27+B36+B47-B55 -> 0 | C56: =C14+C27+C36+C47-C55 -> 0 | D56: =D14+D27+D36+D47-D55 -> 0 | E56: =E14+E27+E36+E47-E55 -> 0 | F56: =F14+F27+F36+F47-F55 -> 0 | G56: =G14+G27+G36+G47-G55 -> 0 | H56: =H14+H27+H36+H47-H55 -> 0 | I56: =I14+I27+I36+I47-I55 -> 0 | ... AA56: =AA14+AA27+AA36+AA47-AA55 -> 0
J57: =J56-I56 -> 0 | K57: =K56-J56 -> 0 | L57: =L56-K56 -> 0 | M57: =M56-L56 -> 0 | N57: =N56-M56 -> 0 | O57: =O56-N56 -> 0 | P57: =P56-O56 -> 0 | Q57: =Q56-P56 -> 0 | ... AA57: =AA56-Z56 -> 0
A59: Net Debt Analysis | B59: =B2 -> 2006 | C59: =C2 -> 2007 | D59: =D2 -> 2008 | E59: =E2 -> 2009 | F59: =F2 -> 2010 | G59: =G2 -> 2011 | H59: =H2 -> 2012 | I59: =I2 -> 2013 | ... AA59: =AA2 -> 2031
A60: Cash | B60: ='Balance Sheet'!B25 -> 8143 | C60: ='Balance Sheet'!C25 -> 7549 | D60: ='Balance Sheet'!D25 -> 6745 | E60: ='Balance Sheet'!E25 -> 7038 | F60: ='Balance Sheet'!F25 -> 5030 | G60: ='Balance Sheet'!G25 -> 5284 | H60: ='Balance Sheet'!H25 -> 8756 | I60: ='Balance Sheet'!I25 -> 7765 | ... AA60: ='Balance Sheet'!AA25 -> 37547.225
A61: Current Securities | B61: ='Balance Sheet'!B24 -> 549 | C61: ='Balance Sheet'!C24 -> 1598 | D61: ='Balance Sheet'!D24 -> 3912 | E61: ='Balance Sheet'!E24 -> 4072 | F61: ='Balance Sheet'!F24 -> 5834 | G61: ='Balance Sheet'!G24 -> 4272 | H61: ='Balance Sheet'!H24 -> 2328 | I61: ='Balance Sheet'!I24 -> 2590 | ... AA61: ='Balance Sheet'!AA24 -> 3093
A62: Non-current Securities | B62: ='Balance Sheet'!B12 -> 1294 | C62: ='Balance Sheet'!C12 -> 2691 | D62: ='Balance Sheet'!D12 -> 3040 | E62: ='Balance Sheet'!E12 -> 3983 | F62: ='Balance Sheet'!F12 -> 5332 | G62: ='Balance Sheet'!G12 -> 7229 | H62: ='Balance Sheet'!H12 -> 5987 | I62: ='Balance Sheet'!I12 -> 4300 | ... AA62: ='Balance Sheet'!AA12 -> 9997
A63: Short Term Debt | B63: ='Balance Sheet'!B39 -> -2196 | C63: ='Balance Sheet'!C39 -> -1724 | D63: ='Balance Sheet'!D39 -> -1458 | E63: ='Balance Sheet'!E39 -> -2429 | F63: ='Balance Sheet'!F39 -> -1408 | G63: ='Balance Sheet'!G39 -> -1476 | H63: ='Balance Sheet'!H39 -> -1273 | I63: ='Balance Sheet'!I39 -> -1645 | ... AA63: ='Balance Sheet'!AA39 -> -5186
A64: Long Term Debt | B64: ='Balance Sheet'!B30 -> -3561 | C64: ='Balance Sheet'!C30 -> -3090 | D64: ='Balance Sheet'!D30 -> -3046 | E64: ='Balance Sheet'!E30 -> -2867 | F64: ='Balance Sheet'!F30 -> -2870 | G64: ='Balance Sheet'!G30 -> -3628 | H64: ='Balance Sheet'!H30 -> -3506 | I64: ='Balance Sheet'!I30 -> -3956 | ... AA64: ='Balance Sheet'!AA30 -> -7253
A65: (Net Debt)/Net cash | B65: =SUM(B60:B64) -> 4229 | C65: =SUM(C60:C64) -> 7024 | D65: =SUM(D60:D64) -> 9193 | E65: =SUM(E60:E64) -> 9797 | F65: =SUM(F60:F64) -> 11918 | G65: =SUM(G60:G64) -> 11681 | H65: =SUM(H60:H64) -> 12292 | I65: =SUM(I60:I64) -> 9054 | ... P65: =SUM(P60:P64) -> 4312 | Q65: =SUM(Q60:Q64)+97 -> 7740 | R65: =SUM(R60:R64)-1394 -> 9431 | S65: =SUM(S60:S64)-961 -> 10726 | T65: =SUM(T60:T64)-832 -> 11753 | U65: =SUM(U60:U64)-798 -> 12171 | V65: =SUM(V60:V64) -> 14247.337 | W65: =SUM(W60:W64) -> 16271.149 | X65: =SUM(X60:X64) -> 19589.53 | Y65: =SUM(Y60:Y64) -> 26112.194 | Z65: =SUM(Z60:Z64) -> 33061.678 | AA65: =SUM(AA60:AA64) -> 38198.225
A67: EBITDA | B67: ='Income Statement'!B76+'Cash Flow Statement'!B12+'Cash Flow Statement'!B14 -> 1969 | C67: ='Income Statement'!C76+'Cash Flow Statement'!C12+'Cash Flow Statement'!C14 -> 1739 | D67: ='Income Statement'!D76+'Cash Flow Statement'!D12+'Cash Flow Statement'!D14 -> 4439 | E67: ='Income Statement'!E76+'Cash Flow Statement'!E12+'Cash Flow Statement'!E14 -> 1446 | F67: ='Income Statement'!F76+'Cash Flow Statement'!F12+'Cash Flow Statement'!F14 -> 2769 | G67: ='Income Statement'!G76+'Cash Flow Statement'!G12+'Cash Flow Statement'!G14 -> 3497 | H67: ='Income Statement'!H76+'Cash Flow Statement'!H12+'Cash Flow Statement'!H14 -> 4142 | I67: ='Income Statement'!I76+'Cash Flow Statement'!I12+'Cash Flow Statement'!I14 -> 8135 | ... Z67: ='Income Statement'!Z76+'Cash Flow Statement'!Z12+'Cash Flow Statement'!Z14 -> 17825.031 | AA67: ='Income Statement'!AA76+'Cash Flow Statement'!AB12+'Cash Flow Statement'!AB14 -> 14752.725
A69: Y/E Net Debt/EBITDA | B69: =B65/B67 -> 2.1477908 | C69: =C65/C67 -> 4.0391029 | D69: =D65/D67 -> 2.0709619 | E69: =E65/E67 -> 6.775242 | F69: =F65/F67 -> 4.3040809 | G69: =G65/G67 -> 3.3402917 | H69: =H65/H67 -> 2.9676485 | I69: =I65/I67 -> 1.1129687 | ... AA69: =AA65/AA67 -> 2.5892319
A71: ROIC Analysis | B71: =B2 -> 2006 | C71: =C2 -> 2007 | D71: =D2 -> 2008 | E71: =E2 -> 2009 | F71: =F2 -> 2010 | G71: =G2 -> 2011 | H71: =H2 -> 2012 | I71: =I2 -> 2013 | ... AA71: =AA2 -> 2031
A72: Adj. EBIT | J72: ='Income Statement'!J93 -> 3629 | K72: ='Income Statement'!K93 -> 3639 | L72: ='Income Statement'!L93 -> 3615 | M72: ='Income Statement'!M93 -> 3876 | N72: ='Income Statement'!N93 -> 5558 | O72: ='Income Statement'!O93 -> 6789 | P72: ='Income Statement'!P93 -> 1410 | Q72: ='Income Statement'!Q93 -> 4600 | ... AA72: ='Income Statement'!AA93 -> 15506.198
A73: Underlying Tax | J73: ='Income Statement'!J95 -> -988 | K73: ='Income Statement'!K95 -> -975 | L73: ='Income Statement'!L95 -> -1048 | M73: ='Income Statement'!M95 -> -1276.7 | N73: ='Income Statement'!N95 -> -1556 | O73: ='Income Statement'!O95 -> -2037 | P73: ='Income Statement'!P95 -> -381 | Q73: ='Income Statement'!Q95 -> -1242 | ... AA73: ='Income Statement'!AA95 -> -4186.0174
A74: NOPAT | J74: =J72+J73 -> 2641 | K74: =K72+K73 -> 2664 | L74: =L72+L73 -> 2567 | M74: =M72+M73 -> 2599.3 | N74: =N72+N73 -> 4002 | O74: =O72+O73 -> 4752 | P74: =P72+P73 -> 1029 | Q74: =Q72+Q73 -> 3358 | ... AA74: =AA72+AA73 -> 11320.181
A75: Average Invested Capital | J75: =SUM(J76:J79) -> 24255.398 | K75: =SUM(K76:K79) -> 24404.616 | L75: =SUM(L76:L79) -> 23333.204 | M75: =SUM(M76:M79) -> 21674.771 | N75: =SUM(N76:N79) -> 24268.426 | O75: =SUM(O76:O79) -> 21095 | P75: =SUM(P76:P79) -> 28740 | Q75: =SUM(Q76:Q79) -> 28433 | ... AA75: =SUM(AA76:AA79) -> 33564.703
A76: Net Intangibles | J76: =J4-'Cash Flow Statement'!J14 -> 12290.398 | K76: =K4-'Cash Flow Statement'!K14 -> 12058.616 | L76: =L4-'Cash Flow Statement'!L14 -> 11555.204 | M76: =M4-'Cash Flow Statement'!M14 -> 11114.771 | N76: =N4-'Cash Flow Statement'!N14 -> 16181.426 | O76: =O4-'Cash Flow Statement'!O14 -> 16119 | P76: =P4-'Cash Flow Statement'!P14 -> 15807 | Q76: =Q4-'Cash Flow Statement'!Q14 -> 16050 | ... Z76: =Z4-'Cash Flow Statement'!Z14 -> 18865.133 | AA76: =AA4-'Cash Flow Statement'!AB14 -> 20158.295
A77: PP&E | J77: =J5 -> 16321 | K77: =K5 -> 17127 | L77: =L5 -> 16913 | M77: =M5 -> 16610 | N77: =N5 -> 16773 | O77: =O5 -> 17294 | P77: =P5 -> 16674 | Q77: =Q5 -> 16536 | ... AA77: =AA5 -> 26446.492
A78: Current assets (excluding Cash & Equivalents) | J78: =J27-J25 -> 39661 | K78: =K27-K25 -> 43975 | L78: =L27-L25 -> 44805 | M78: =M27-M25 -> 47790 | N78: =N27-N25 -> 49206 | O78: =O27-O25 -> 47409 | P78: =P27-P25 -> 43961 | Q78: =Q27-Q25 -> 41122 | ... AA78: =AA27-AA25 -> 82327.96
A79: Current Liabilities (excluding Financial Liabilities) | J79: =J47-J42 -> -44017 | K79: =K47-K42 -> -48756 | L79: =L47-L42 -> -49940 | M79: =M47-M42 -> -53840 | N79: =N47-N42 -> -57892 | O79: =O47-O42 -> -59727 | P79: =P47-P42 -> -47702 | Q79: =Q47-Q42 -> -45275 | ... AA79: =AA47-AA42 -> -95368.044
A80: Other Assets | J80: 0 | K80: 0 | L80: 0 | M80: 0 | N80: 0 | O80: 0 | P80: 0 | Q80: 0 | R80: 0 | S80: 0 | T80: 0 | U80: 0 | V80: 0 | W80: 0 | X80: 0 | Y80: 0 | Z80: 0 | AA80: 0
A81: ROIC (%) | J81: =J74/J75 -> 0.10888298 | K81: =K74/K75 -> 0.10915968 | L81: =L74/L75 -> 0.1100149 | M81: =M74/M75 -> 0.11992283 | N81: =N74/N75 -> 0.16490563 | O81: =O74/O75 -> 0.22526665 | P81: =P74/P75 -> 0.035803758 | Q81: =Q74/(AVERAGE(P75:Q75)) -> 0.11746804 | R81: =R74/(AVERAGE(Q75:R75)) -> 0.13134189 | S81: =S74/(AVERAGE(R75:S75)) -> 0.13687489 | T81: =T74/(AVERAGE(S75:T75)) -> 0.12254151 | U81: =U74/(AVERAGE(T75:U75)) -> 0.15639588 | V81: =V74/(AVERAGE(U75:V75)) -> 0.16075596 | W81: =W74/(AVERAGE(V75:W75)) -> 0.19705291 | X81: =X74/(AVERAGE(W75:X75)) -> 0.24688012 | ... AA81: =AA74/(AVERAGE(Z75:AA75)) -> 0.34275288
A83: IFRS 16 | B83: =B2 -> 2006 | C83: =C2 -> 2007 | D83: =D2 -> 2008 | E83: =E2 -> 2009 | F83: =F2 -> 2010 | G83: =G2 -> 2011 | H83: =H2 -> 2012 | I83: =I2 -> 2013 | ... AA83: =AA2 -> 2031
A84: Long Term Leases | O84: 1298 | P84: 1538 | Q84: 1491 | R84: 1492 | S84: 1396 | T84: 1696 | U84: =U85*'Income Statement'!U14 -> 1800.9741 | V84: =V85*'Income Statement'!V14 -> 1967.0149 | W84: =W85*'Income Statement'!W14 -> 2237.7541 | X84: =X85*'Income Statement'!X14 -> 2514.5913 | Y84: =Y85*'Income Statement'!Y14 -> 2725.9063 | Z84: =Z85*'Income Statement'!Z14 -> 2864.1904 | AA84: =AA85*'Income Statement'!AA14 -> 2975.7235
A85: % of sales | O85: =O84/'Income Statement'!O14 -> 0.018417095 | P85: =P84/'Income Statement'!P14 -> 0.030814233 | Q85: =Q84/'Income Statement'!Q14 -> 0.028591152 | R85: =R84/'Income Statement'!R14 -> 0.025390126 | S85: =S84/'Income Statement'!S14 -> 0.021330563 | T85: =T84/'Income Statement'!T14 -> 0.02449805 | U85: =T85 -> 0.02449805 | V85: =U85 -> 0.02449805 | W85: =V85 -> 0.02449805 | X85: =W85 -> 0.02449805 | Y85: =X85 -> 0.02449805 | Z85: =Y85 -> 0.02449805 | AA85: =Z85 -> 0.02449805
A86: Short Term Leases | O86: 262 | P86: 260 | Q86: 245 | R86: 242 | S86: 221 | T86: 253 | U86: =U87*'Income Statement'!U14 -> 268.65947 | V86: =V87*'Income Statement'!V14 -> 293.42853 | W86: =W87*'Income Statement'!W14 -> 333.81591 | X86: =X87*'Income Statement'!X14 -> 375.11296 | Y86: =Y87*'Income Statement'!Y14 -> 406.63579 | Z86: =Z87*'Income Statement'!Z14 -> 427.26425 | AA86: =AA87*'Income Statement'!AA14 -> 443.90216
A87: % of sales | O87: =O86/'Income Statement'!O14 -> 0.0037174721 | P87: =P86/'Income Statement'!P14 -> 0.0052091681 | Q87: =Q86/'Income Statement'!Q14 -> 0.0046980767 | R87: =R86/'Income Statement'!R14 -> 0.0041182377 | S87: =S86/'Income Statement'!S14 -> 0.0033768298 | T87: =T86/'Income Statement'!T14 -> 0.003654485 | U87: =T87 -> 0.003654485 | V87: =U87 -> 0.003654485 | W87: =V87 -> 0.003654485 | X87: =W87 -> 0.003654485 | Y87: =X87 -> 0.003654485 | Z87: =Y87 -> 0.003654485 | AA87: =Z87 -> 0.003654485
A88: Total | O88: =O84+O86 -> 1560 | P88: =P84+P86 -> 1798 | Q88: =Q84+Q86 -> 1736 | R88: =R84+R86 -> 1734 | S88: =S84+S86 -> 1617 | T88: =T84+T86 -> 1949 | U88: =U84+U86 -> 2069.6336 | V88: =V84+V86 -> 2260.4435 | ... AA88: =AA84+AA86 -> 3419.6257
A90: Net Debt Ex Leases | O90: ='Balance Sheet'!O65-O88 -> 10974 | P90: ='Balance Sheet'!P65-P88 -> 2514 | Q90: ='Balance Sheet'!Q65-Q88 -> 6004 | R90: ='Balance Sheet'!R65-R88 -> 7697 | S90: ='Balance Sheet'!S65-S88 -> 9109 | T90: ='Balance Sheet'!T65-T88 -> 9804 | U90: ='Balance Sheet'!U65-U88 -> 10101.366 | V90: ='Balance Sheet'!V65-V88 -> 11986.894 | ... AA90: ='Balance Sheet'!AA65-AA88 -> 34778.599
A92: RoU Asset | O92: 1543 | P92: 1804 | Q92: 1698 | R92: 1746 | S92: 1641 | T92: 2020 | U92: =U93*'Income Statement'!U14 -> 2145.0282 | V92: =V93*'Income Statement'!V14 -> 2342.789 | W92: =W93*'Income Statement'!W14 -> 2665.2496 | X92: =X93*'Income Statement'!X14 -> 2994.9731 | Y92: =Y93*'Income Statement'!Y14 -> 3246.6573 | Z92: =Z93*'Income Statement'!Z14 -> 3411.3589 | AA92: =AA93*'Income Statement'!AA14 -> 3544.199
A93: % sales | O93: =O92/'Income Statement'!O14 -> 0.021893357 | P93: =P92/'Income Statement'!P14 -> 0.036143613 | Q93: =Q92/'Income Statement'!Q14 -> 0.032560548 | R93: =R92/'Income Statement'!R14 -> 0.029712574 | S93: =S92/'Income Statement'!S14 -> 0.025074107 | T93: =T92/'Income Statement'!T14 -> 0.029178102 | U93: =T93 -> 0.029178102 | V93: =U93 -> 0.029178102 | W93: =V93 -> 0.029178102 | X93: =W93 -> 0.029178102 | Y93: =X93 -> 0.029178102 | Z93: =Y93 -> 0.029178102 | AA93: =Z93 -> 0.029178102
A94: Depreciation on RoU Asset | O94: 271 | P94: 246 | Q94: 260 | R94: 224 | S94: 218 | T94: 230 | U94: =U95*'Income Statement'!U14 -> 244.23588 | V94: =V95*'Income Statement'!V14 -> 266.75321 | W94: =W95*'Income Statement'!W14 -> 303.46901 | X94: =X95*'Income Statement'!X14 -> 341.01179 | Y94: =Y95*'Income Statement'!Y14 -> 369.6689 | Z94: =Z95*'Income Statement'!Z14 -> 388.42205 | AA94: =AA95*'Income Statement'!AA14 -> 403.54742
A95: % sales | O95: =O94/'Income Statement'!O14 -> 0.0038451715 | P95: =P94/'Income Statement'!P14 -> 0.0049286745 | Q95: =Q94/'Income Statement'!Q14 -> 0.004985714 | R95: =R94/'Income Statement'!R14 -> 0.0038119225 | S95: =S94/'Income Statement'!S14 -> 0.0033309904 | T95: =T94/'Income Statement'!T14 -> 0.0033222591 | U95: =T95 -> 0.0033222591 | V95: =U95 -> 0.0033222591 | W95: =V95 -> 0.0033222591 | X95: =W95 -> 0.0033222591 | Y95: =X95 -> 0.0033222591 | Z95: =Y95 -> 0.0033222591 | AA95: =Z95 -> 0.0033222591
A96: Lease Principal | O96: -294 | P96: -331 | Q96: -400 | R96: -262 | S96: -267 | T96: -324 | U96: =T96 -> -324 | V96: =U96 -> -324 | W96: =V96 -> -324 | X96: =W96 -> -324 | Y96: =X96 -> -324 | Z96: =Y96 -> -324 | AA96: =Z96 -> -324
A97: Lease Interest | O97: -14 | P97: -22 | Q97: -22 | R97: -31 | S97: -37 | T97: -50 | U97: =T97 -> -50 | V97: =U97 -> -50 | W97: =V97 -> -50 | X97: =W97 -> -50 | Y97: =X97 -> -50 | Z97: =Y97 -> -50 | AA97: =Z97 -> -50
A99: Debt Maturity | B99: =B2 -> 2006 | C99: 2007 | D99: 2008 | E99: 2009 | F99: 2010 | G99: 2011 | H99: 2012 | I99: 2013 | J99: 2014 | K99: 2015 | L99: 2016 | M99: 2017 | N99: 2018 | O99: 2019 | P99: 2020 | Q99: 2021 | R99: ='Income Statement'!R2 -> 2022 | S99: ='Income Statement'!S2 -> 2023 | T99: ='Income Statement'!T2 -> 2024 | U99: =U2 -> 2025 | V99: =V2 -> 2026 | W99: =W2 -> 2027 | X99: =X2 -> 2028 | Y99: =Y2 -> 2029 | Z99: =Z2 -> 2030 | AA99: =AA2 -> 2031
A100: EMTN 15 years, €500 mn, Coupon or Interest rate 5.5% | B100: 500 | N100: 512
A101: EMTN 7 years, € 1 bn, 4.625% | B101: 1000 | L101: 999
A102: EMTN 10 years, €1 bn, 2.375% | B102: 1000 | T102: 1038
A103: EMTN 15 years,€500 mn, 2.125% | B103: 500 | W103: 523 | X103: 523 | Y103: 523 | Z103: 523 | AA103: 523
A104: USD Bond 10 years, $1bn, 2.7% | B104: 1000 | S104: 848
A105: Convertible bond 7 years, €500 mn,0.00% | B105: 500 | R105: 477
A106: EMTN 10 years, €600 mn, 0.875% | W106: 594 | X106: 594 | Y106: 594 | Z106: 594 | AA106: 594
A107: EMTN 15 years, €900 mn, 1.375% | W107: 865 | X107: 865 | Y107: 865 | Z107: 865 | AA107: 865
A108: Exchangeable bonds 5 years, €1.078 bn, 0% | Q108: 1061
A109: USD Bond 10 years, $750 mn, 3.15% | W109: 632 | X109: 632 | Y109: 632 | Z109: 632 | AA109: 632
A110: USD Bond 30 years, $750 mn, 3.95% | W110: 621 | X110: 621 | Y110: 621 | Z110: 621 | AA110: 621
A111: DBJ 10 years, $300mn, 3M US-Libor +1.15% | B111: 300 | Q111: 87
A112: EIB 10 years, $720.75mn, 3M US-Libor +0.85% | B112: 720.75 | Q112: 0
...

Sheet Interims
B1: 2011 | C1: 2011 | D1: 2011 | E1: 2011 | F1: 2011 | G1: 2011 | H1: 2011 | I1: 2011 | J1: 2012 | K1: 2012 | L1: 2012 | M1: 2012 | N1: 2012 | O1: 2012 | P1: 2012 | Q1: 2012 | R1: 2013 | S1: 2013 | T1: 2013 | U1: 2013 | V1: 2013 | W1: 2013 | X1: 2013 | Y1: 2013 | Z1: 2014 | AA1: 2014 | AB1: 2014 | AC1: 2014 | AD1: 2014 | AE1: 2014 | AF1: 2014 | AG1: 2014 | AH1: 2015 | AI1: =AH1 -> 2015 | AJ1: =AI1 -> 2015 | AK1: =AJ1 -> 2015 | AL1: =AK1 -> 2015 | AM1: =AL1 -> 2015 | AN1: =AM1 -> 2015 | AO1: =AN1 -> 2015 | AP1: 2016 | AQ1: =AP1 -> 2016 | AR1: =AQ1 -> 2016 | AS1: =AR1 -> 2016 | AT1: =AS1 -> 2016 | AU1: =AT1 -> 2016 | AV1: =AU1 -> 2016 | AW1: =AV1 -> 2016 | AX1: 2017 | AY1: =AX1 -> 2017 | AZ1: =AY1 -> 2017 | BA1: =AZ1 -> 2017 | BB1: =BA1 -> 2017 | BC1: =BB1 -> 2017 | BD1: =BC1 -> 2017 | BE1: =BD1 -> 2017 | BF1: 2017 | BG1: =BF1 -> 2017 | BH1: =BG1 -> 2017 | BI1: =BH1 -> 2017 | BJ1: =BI1 -> 2017 | BK1: =BJ1 -> 2017 | BL1: =BK1 -> 2017 | BM1: =BL1 -> 2017 | BN1: =BF1+1 -> 2018 | BO1: =BG1+1 -> 2018 | BP1: =BH1+1 -> 2018 | BQ1: =BI1+1 -> 2018 | BR1: =BJ1+1 -> 2018 | BS1: =BK1+1 -> 2018 | BT1: =BL1+1 -> 2018 | BU1: =BM1+1 -> 2018 | ... DS1: =DK1+1 -> 2025 | DT1: 2025 | DU1: =DM1+1 -> 2025 | DV1: =DN1+1 -> 2025 | DW1: =DO1+1 -> 2025 | DX1: =DP1+1 -> 2025 | DY1: =DQ1+1 -> 2025 | DZ1: =DR1+1 -> 2026 | EA1: =DS1+1 -> 2026 | EB1: =DT1+1 -> 2026 | ... EG1: =DY1+1 -> 2026
B2: Q1 | C2: Q2 | D2: H1 | E2: Q3 | F2: 9M | G2: Q4 | H2: H2 | I2: FY | J2: Q1 | K2: Q2 | L2: H1 | M2: Q3 | N2: 9M | O2: Q4 | P2: H2 | Q2: FY | R2: Q1 | S2: Q2 | T2: H1 | U2: Q3 | V2: 9M | W2: Q4 | X2: H2 | Y2: FY | Z2: Q1 | AA2: Q2 | AB2: H1 | AC2: Q3 | AD2: 9M | AE2: Q4 | AF2: H2 | AG2: FY | AH2: Q1 | AI2: Q2 | AJ2: H1 | AK2: Q3 | AL2: 9M | AM2: Q4 | AN2: H2 | AO2: FY | AP2: Q1 | AQ2: Q2 | AR2: H1 | AS2: Q3 | AT2: 9M | AU2: Q4 | AV2: H2 | AW2: FY | AX2: Q1 | AY2: Q2 | AZ2: H1 | BA2: Q3 | BB2: 9M | BC2: Q4 | BD2: H2 | BE2: FY | BF2: Q1 | BG2: Q2 | BH2: H1 | BI2: Q3 | BJ2: 9M | BK2: Q4 | BL2: H2 | BM2: FY | BN2: Q1 | BO2: Q2 | BP2: H1 | BQ2: Q3 | BR2: 9M | BS2: Q4 | BT2: H2 | BU2: FY | BV2: =BN2 -> Q1 | BW2: =BO2 -> Q2 | BX2: =BP2 -> H1 | BY2: =BQ2 -> Q3 | BZ2: =BR2 -> 9M | CA2: =BS2 -> Q4 | CB2: =BT2 -> H2 | CC2: =BU2 -> FY | ... DS2: =DK2 -> Q2 | DT2: H1 | DU2: =DM2 -> Q3 | DV2: =DN2 -> 9M | DW2: =DO2 -> Q4 | DX2: =DP2 -> H2 | DY2: =DQ2 -> FY | DZ2: =DR2 -> Q1 | EA2: =DS2 -> Q2 | EB2: =DT2 -> H1 | ... EG2: =DY2 -> FY
BF3: IFRS 15 | BG3: IFRS 15 | BH3: IFRS 15 | BI3: IFRS 15 | BJ3: IFRS 15 | BK3: IFRS 15 | BL3: IFRS 15 | BM3: IFRS 15 | DU3: 2025E
A4: Divisional Summary | B4: =B1&" "&B2 -> 2011 Q1 | C4: =C1&" "&C2 -> 2011 Q2 | D4: =D1&" "&D2 -> 2011 H1 | E4: =E1&" "&E2 -> 2011 Q3 | F4: =F1&" "&F2 -> 2011 9M | G4: =G1&" "&G2 -> 2011 Q4 | H4: =H1&" "&H2 -> 2011 H2 | I4: =I1&" "&I2 -> 2011 FY | ... EG4: =EG1&" "&EG2 -> 2026 FY
A5: Sales
A6: Airbus Commercial | B6: 6707 | C6: =D6-B6 -> 7757 | D6: 14464 | E6: =F6-D6 -> 6656 | F6: 21120 | G6: =I6-F6 -> 10039 | H6: =G6+E6 -> 16695 | I6: ='Income Statement'!G7 -> 31159 | J6: 7609 | K6: =L6-J6 -> 9255 | L6: 16864 | M6: =N6-L6 -> 8291 | N6: 25155 | O6: =Q6-N6 -> 12469 | P6: =O6+M6 -> 20760 | Q6: ='Income Statement'!H7 -> 37624 | R6: 8822 | S6: =M6-R6 -> -531 | T6: 18235 | U6: =V6-M6 -> 19261 | V6: 27552 | W6: =Y6-V6 -> 12337 | X6: =W6+U6 -> 31598 | Y6: ='Income Statement'!I7 -> 39889 | AA6: =AB6-Z6 -> 0 | AC6: =AD6-AB6 -> 0 | AE6: =AG6-AD6 -> 42280 | AF6: =AE6+AC6 -> 42280 | AG6: ='Income Statement'!J7 -> 42280 | AI6: =AJ6-AH6 -> 0 | AK6: =AL6-AJ6 -> 0 | AM6: =AO6-AL6 -> 41428 | AN6: =AM6+AK6 -> 41428 | AO6: ='Income Statement'!R7 -> 41428 | AQ6: =AR6-AP6 -> 0 | AS6: =AM6-AR6 -> 41428 | AU6: =AW6-AM6 -> -41428 | AV6: =AU6+AS6 -> 0 | AW6: ='Income Statement'!AF7 -> 0 | AY6: =AZ6-AX6 -> 0 | BA6: =BB6-AZ6 -> 0 | BC6: =BE6-BB6 -> 0 | BD6: =BC6+BA6 -> 0 | BE6: ='Income Statement'!AN7 -> 0 | BO6: =BP6-BN6 -> 0 | BQ6: =BR6-BP6 -> 0 | BS6: =BU6-BR6 -> 0 | BT6: =BS6+BQ6 -> 0 | BU6: ='Income Statement'!AV7 -> 0 | BW6: =BX6-BV6 -> 0 | BY6: =BZ6-BX6 -> 0 | CA6: =CC6-BZ6 -> 0 | CB6: =CA6+BY6 -> 0 | CC6: ='Income Statement'!BD7 -> 0 | CE6: =CF6-CD6 -> 0 | CG6: =CH6-CF6 -> 0 | CI6: =CK6-CH6 -> 0 | CJ6: =CI6+CG6 -> 0 | CK6: ='Income Statement'!BL7 -> 0 | CS6: ='Income Statement'!BT7 -> 0 | DA6: ='Income Statement'!CB7 -> 0 | DI6: ='Income Statement'!CJ7 -> 0 | DQ6: ='Income Statement'!CR7 -> 0
A7: Airbus MiliMary | B7: 434 | C7: =D7-B7 -> 678 | D7: 1112 | E7: =F7-D7 -> 635 | F7: 1747 | G7: =I7-F7 -> -1747 | H7: =G7+E7 -> -1112 | I7: ='Income Statement'!G8 -> 0 | J7: 425 | K7: =L7-J7 -> 418 | L7: 843 | M7: =N7-L7 -> 351 | N7: 1194 | O7: =Q7-N7 -> 4438.4 | P7: =O7+M7 -> 4789.4 | Q7: ='Income Statement'!H8 -> 5632.4 | R7: 615 | S7: =M7-R7 -> -264 | T7: 1067 | U7: =V7-M7 -> 1418 | V7: 1769 | W7: =Y7-V7 -> #REF! | X7: =W7+U7 -> #REF! | Y7: ='Income Statement'!I8 -> #REF! | AA7: =AB7-Z7 -> 0 | AC7: =AD7-AB7 -> 0 | AE7: =AG7-AD7 -> 0 | AF7: =AE7+AC7 -> 0 | AG7: ='Income Statement'!J8 -> 0 | AI7: =AJ7-AH7 -> 0 | AK7: =AL7-AJ7 -> 0 | AM7: =AO7-AL7 -> 0 | AN7: =AM7+AK7 -> 0 | AO7: ='Income Statement'!R8 -> 0 | AQ7: =AR7-AP7 -> 0 | AS7: =AM7-AR7 -> 0 | AU7: =AW7-AM7 -> 0 | AV7: =AU7+AS7 -> 0 | AW7: ='Income Statement'!AF8 -> 0 | AY7: =AZ7-AX7 -> 0 | BA7: =BB7-AZ7 -> 0 | BC7: =BE7-BB7 -> 0 | BD7: =BC7+BA7 -> 0 | BE7: ='Income Statement'!AN8 -> 0 | BO7: =BP7-BN7 -> 0 | BQ7: =BR7-BP7 -> 0 | BS7: =BU7-BR7 -> 0 | BT7: =BS7+BQ7 -> 0 | BU7: ='Income Statement'!AV8 -> 0 | BW7: =BX7-BV7 -> 0 | BY7: =BZ7-BX7 -> 0 | CA7: =CC7-BZ7 -> 0 | CB7: =CA7+BY7 -> 0 | CC7: ='Income Statement'!BD8 -> 0 | CE7: =CF7-CD7 -> 0 | CG7: =CH7-CF7 -> 0 | CI7: =CK7-CH7 -> 0 | CJ7: =CI7+CG7 -> 0 | CK7: ='Income Statement'!BL8 -> 0 | CS7: ='Income Statement'!BT8 -> 0 | DA7: ='Income Statement'!CB8 -> 0 | DI7: ='Income Statement'!CJ8 -> 0 | DQ7: ='Income Statement'!CR8 -> 0
A8: EurocopMer | B8: 823 | C8: =D8-B8 -> 1348 | D8: 2171 | E8: =F8-D8 -> 1287 | F8: 3458 | G8: =I8-F8 -> 1957 | H8: =G8+E8 -> 3244 | I8: ='Income Statement'!G9 -> 5415 | J8: 1199 | K8: =L8-J8 -> 1572 | L8: 2771 | M8: =N8-L8 -> 1345 | N8: 4116 | O8: =Q8-N8 -> 2148 | P8: =O8+M8 -> 3493 | Q8: ='Income Statement'!H9 -> 6264 | R8: 1038 | S8: =M8-R8 -> 307 | T8: 2584 | U8: =V8-M8 -> 2787 | V8: 4132 | W8: =Y8-V8 -> 2165 | X8: =W8+U8 -> 4952 | Y8: ='Income Statement'!I9 -> 6297 | AA8: =AB8-Z8 -> 0 | AC8: =AD8-AB8 -> 0 | AE8: =AG8-AD8 -> 6524 | AF8: =AE8+AC8 -> 6524 | AG8: ='Income Statement'!J9 -> 6524 | AI8: =AJ8-AH8 -> 0 | AK8: =AL8-AJ8 -> 0 | AM8: =AO8-AL8 -> 7048 | AN8: =AM8+AK8 -> 7048 | AO8: ='Income Statement'!R9 -> 7048 | AQ8: =AR8-AP8 -> 0 | AS8: =AM8-AR8 -> 7048 | AU8: =AW8-AM8 -> -7048 | AV8: =AU8+AS8 -> 0 | AW8: ='Income Statement'!AF9 -> 0 | AY8: =AZ8-AX8 -> 0 | BA8: =BB8-AZ8 -> 0 | BC8: =BE8-BB8 -> 0 | BD8: =BC8+BA8 -> 0 | BE8: ='Income Statement'!AN9 -> 0 | BO8: =BP8-BN8 -> 0 | BQ8: =BR8-BP8 -> 0 | BS8: =BU8-BR8 -> 0 | BT8: =BS8+BQ8 -> 0 | BU8: ='Income Statement'!AV9 -> 0 | BW8: =BX8-BV8 -> 0 | BY8: =BZ8-BX8 -> 0 | CA8: =CC8-BZ8 -> 0 | CB8: =CA8+BY8 -> 0 | CC8: ='Income Statement'!BD9 -> 0 | CE8: =CF8-CD8 -> 0 | CG8: =CH8-CF8 -> 0 | CI8: =CK8-CH8 -> 0 | CJ8: =CI8+CG8 -> 0 | CK8: ='Income Statement'!BL9 -> 0 | CS8: ='Income Statement'!BT9 -> 0 | DA8: ='Income Statement'!CB9 -> 0 | DI8: ='Income Statement'!CJ9 -> 0 | DQ8: ='Income Statement'!CR9 -> 0
A9: AsMrium | B9: 1171 | C9: =D9-B9 -> 1176 | D9: 2347 | E9: =F9-D9 -> 1093 | F9: 3440 | G9: =I9-F9 -> -3440 | H9: =G9+E9 -> -2347 | I9: ='Income Statement'!G10 -> 0 | J9: 1325 | K9: =L9-J9 -> 1336 | L9: 2661 | M9: =N9-L9 -> 1273 | N9: 3934 | O9: =Q9-N9 -> 1883 | P9: =O9+M9 -> 3156 | Q9: ='Income Statement'!H10 -> 5817 | R9: 1369 | S9: =M9-R9 -> -96 | T9: 2808 | U9: =V9-M9 -> 2741 | V9: 4014 | W9: =Y9-V9 -> 1770 | X9: =W9+U9 -> 4511 | Y9: ='Income Statement'!I10 -> 5784 | AA9: =AB9-Z9 -> 0 | AC9: =AD9-AB9 -> 0 | AE9: =AG9-AD9 -> 0 | AF9: =AE9+AC9 -> 0 | AG9: ='Income Statement'!J10 -> 0 | AI9: =AJ9-AH9 -> 0 | AK9: =AL9-AJ9 -> 0 | AM9: =AO9-AL9 -> 0 | AN9: =AM9+AK9 -> 0 | AO9: ='Income Statement'!R10 -> 0 | AQ9: =AR9-AP9 -> 0 | AS9: =AM9-AR9 -> 0 | AU9: =AW9-AM9 -> 0 | AV9: =AU9+AS9 -> 0 | AW9: ='Income Statement'!AF10 -> 0 | AY9: =AZ9-AX9 -> 0 | BA9: =BB9-AZ9 -> 0 | BC9: =BE9-BB9 -> 0 | BD9: =BC9+BA9 -> 0 | BE9: ='Income Statement'!AN10 -> 0 | BO9: =BP9-BN9 -> 0 | BQ9: =BR9-BP9 -> 0 | BS9: =BU9-BR9 -> 0 | BT9: =BS9+BQ9 -> 0 | BU9: ='Income Statement'!AV10 -> 0 | BW9: =BX9-BV9 -> 0 | BY9: =BZ9-BX9 -> 0 | CA9: =CC9-BZ9 -> 0 | CB9: =CA9+BY9 -> 0 | CC9: ='Income Statement'!BD10 -> 0 | CE9: =CF9-CD9 -> 0 | CG9: =CH9-CF9 -> 0 | CI9: =CK9-CH9 -> 0 | CJ9: =CI9+CG9 -> 0 | CK9: ='Income Statement'!BL10 -> 0 | CS9: ='Income Statement'!BT10 -> 0 | DA9: ='Income Statement'!CB10 -> 0 | DI9: ='Income Statement'!CJ10 -> 0 | DQ9: ='Income Statement'!CR10 -> 0
A10: Cassidian | B10: 878 | C10: =D10-B10 -> 1255 | D10: 2133 | E10: =F10-D10 -> 1286 | F10: 3419 | G10: =I10-F10 -> -3419 | H10: =G10+E10 -> -2133 | I10: ='Income Statement'!G11 -> 0 | J10: 925 | K10: =L10-J10 -> 1261 | L10: 2186 | M10: =N10-L10 -> 1298 | N10: 3484 | O10: =Q10-N10 -> 2256 | P10: =O10+M10 -> 3554 | Q10: ='Income Statement'!H11 -> 5740 | R10: 941 | S10: =M10-R10 -> 357 | T10: 2286 | U10: =V10-M10 -> 2200 | V10: 3498 | W10: =Y10-V10 -> 2478 | X10: =W10+U10 -> 4678 | Y10: ='Income Statement'!I11 -> 5976 | AA10: =AB10-Z10 -> 0 | AC10: =AD10-AB10 -> 0 | AE10: =AG10-AD10 -> 0 | AF10: =AE10+AC10 -> 0 | AG10: ='Income Statement'!J11 -> 0 | AI10: =AJ10-AH10 -> 0 | AK10: =AL10-AJ10 -> 0 | AM10: =AO10-AL10 -> 0 | AN10: =AM10+AK10 -> 0 | AO10: ='Income Statement'!R11 -> 0 | AQ10: =AR10-AP10 -> 0 | AS10: =AM10-AR10 -> 0 | AU10: =AW10-AM10 -> 0 | AV10: =AU10+AS10 -> 0 | AW10: ='Income Statement'!AF11 -> 0 | AY10: =AZ10-AX10 -> 0 | BA10: =BB10-AZ10 -> 0 | BC10: =BE10-BB10 -> 0 | BD10: =BC10+BA10 -> 0 | BE10: ='Income Statement'!AN11 -> 0 | BO10: =BP10-BN10 -> 0 | BQ10: =BR10-BP10 -> 0 | BS10: =BU10-BR10 -> 0 | BT10: =BS10+BQ10 -> 0 | BU10: ='Income Statement'!AV11 -> 0 | BW10: =BX10-BV10 -> 0 | BY10: =BZ10-BX10 -> 0 | CA10: =CC10-BZ10 -> 0 | CB10: =CA10+BY10 -> 0 | CC10: ='Income Statement'!BD11 -> 0 | CE10: =CF10-CD10 -> 0 | CG10: =CH10-CF10 -> 0 | CI10: =CK10-CH10 -> 0 | CJ10: =CI10+CG10 -> 0 | CK10: ='Income Statement'!BL11 -> 0 | CS10: ='Income Statement'!BT11 -> 0 | DA10: ='Income Statement'!CB11 -> 0 | DI10: ='Income Statement'!CJ11 -> 0 | DQ10: ='Income Statement'!CR11 -> 0
A11: oMher | B11: 246 | C11: =D11-B11 -> 278 | D11: 524 | E11: =F11-D11 -> 309 | F11: 833 | G11: =I11-F11 -> #REF! | H11: =G11+E11 -> #REF! | I11: ='Income Statement'!G13 -> #REF! | J11: 197 | K11: =L11-J11 -> 134 | L11: 331 | M11: =N11-L11 -> 130 | N11: 461 | O11: =Q11-N11 -> -1075 | P11: =O11+M11 -> -945 | Q11: ='Income Statement'!H13 -> -614 | R11: 78 | S11: =M11-R11 -> 52 | T11: 205 | U11: =V11-M11 -> 166 | V11: 296 | W11: =Y11-V11 -> -1648 | X11: =W11+U11 -> -1482 | Y11: ='Income Statement'!I13 -> -1352 | AA11: =AB11-Z11 -> 0 | AC11: =AD11-AB11 -> 0 | AE11: =AG11-AD11 -> -1116 | AF11: =AE11+AC11 -> -1116 | AG11: ='Income Statement'!J13 -> -1116 | AI11: =AJ11-AH11 -> 0 | AK11: =AL11-AJ11 -> 0 | AM11: =AO11-AL11 -> -972 | AN11: =AM11+AK11 -> -972 | AO11: ='Income Statement'!R13 -> -972 | AQ11: =AR11-AP11 -> 0 | AS11: =AM11-AR11 -> -972 | AU11: =AW11-AM11 -> 972 | AV11: =AU11+AS11 -> 0 | AW11: ='Income Statement'!AF13 -> 0 | AY11: =AZ11-AX11 -> 0 | BA11: =BB11-AZ11 -> 0 | BC11: =BE11-BB11 -> 0 | BD11: =BC11+BA11 -> 0 | BE11: ='Income Statement'!AN13 -> 0 | BO11: =BP11-BN11 -> 0 | BQ11: =BR11-BP11 -> 0 | BS11: =BU11-BR11 -> 0 | BT11: =BS11+BQ11 -> 0 | BU11: ='Income Statement'!AV13 -> 0 | BW11: =BX11-BV11 -> 0 | BY11: =BZ11-BX11 -> 0 | CA11: =CC11-BZ11 -> 0 | CB11: =CA11+BY11 -> 0 | CC11: ='Income Statement'!BD13 -> 0 | CE11: =CF11-CD11 -> 0 | CG11: =CH11-CF11 -> 0 | CI11: =CK11-CH11 -> 0 | CJ11: =CI11+CG11 -> 0 | CK11: ='Income Statement'!BL13 -> 0 | CS11: ='Income Statement'!BT13 -> 0 | DA11: ='Income Statement'!CB13 -> 0 | DI11: ='Income Statement'!CJ13 -> 0 | DQ11: ='Income Statement'!CR13 -> 0
A12: InMernal revenues | B12: =B14-SUM(B6:B11,B13) -> -128 | C12: =D12-B12 -> -136 | D12: =D14-SUM(D6:D11,D13) -> -264 | E12: =F12-D12 -> -192 | F12: =F14-SUM(F6:F11,F13) -> -456 | G12: =I12-F12 -> #REF! | H12: =G12+E12 -> #REF! | I12: ='Income Statement'!#REF! -> #REF! | J12: =J14-SUM(J6:J11,J13) -> 39 | K12: =L12-J12 -> -110 | L12: =L14-SUM(L6:L11,L13) -> -71 | M12: =N12-L12 -> -51 | N12: =N14-SUM(N6:N11,N13) -> -122 | O12: =Q12-N12 -> #REF! | P12: =O12+M12 -> #REF! | Q12: ='Income Statement'!#REF! -> #REF! | R12: =R14-SUM(R6:R11,R13) -> -256 | S12: =M12-R12 -> 205 | T12: =M14-SUM(M6:M11,M13) -> -51 | U12: =V12-M12 -> -470 | V12: =V14-SUM(V6:V11,V13) -> -521 | W12: =Y12-V12 -> #REF! | X12: =W12+U12 -> #REF! | Y12: ='Income Statement'!#REF! -> #REF! | AA12: =AB12-Z12 -> 0 | AC12: =AD12-AB12 -> 0 | AE12: =AG12-AD12 -> #REF! | AF12: =AE12+AC12 -> #REF! | AG12: ='Income Statement'!#REF! -> #REF! | AI12: =AJ12-AH12 -> 0 | AK12: =AL12-AJ12 -> 0 | AM12: =AO12-AL12 -> #REF! | AN12: =AM12+AK12 -> #REF! | AO12: ='Income Statement'!#REF! -> #REF! | AQ12: =AR12-AP12 -> 0 | AS12: =AM12-AR12 -> #REF! | AU12: =AW12-AM12 -> #REF! | AV12: =AU12+AS12 -> #REF! | AW12: ='Income Statement'!#REF! -> #REF! | AY12: =AZ12-AX12 -> 0 | BA12: =BB12-AZ12 -> 0 | BC12: =BE12-BB12 -> #REF! | BD12: =BC12+BA12 -> #REF! | BE12: ='Income Statement'!#REF! -> #REF! | BO12: =BP12-BN12 -> 0 | BQ12: =BR12-BP12 -> 0 | BS12: =BU12-BR12 -> #REF! | BT12: =BS12+BQ12 -> #REF! | BU12: ='Income Statement'!#REF! -> #REF! | BW12: =BX12-BV12 -> 0 | BY12: =BZ12-BX12 -> 0 | CA12: =CC12-BZ12 -> #REF! | CB12: =CA12+BY12 -> #REF! | CC12: ='Income Statement'!#REF! -> #REF! | CE12: =CF12-CD12 -> 0 | CG12: =CH12-CF12 -> 0 | CI12: =CK12-CH12 -> #REF! | CJ12: =CI12+CG12 -> #REF! | CK12: ='Income Statement'!#REF! -> #REF! | CS12: ='Income Statement'!#REF! -> #REF! | DA12: ='Income Statement'!#REF! -> #REF! | DI12: ='Income Statement'!#REF! -> #REF! | DQ12: ='Income Statement'!#REF! -> #REF!
A13: HQ/ConsolidaMion | B13: -277 | C13: =D13-B13 -> -274 | D13: -551 | E13: =F13-D13 -> -323 | F13: -874 | G13: =I13-F13 -> #REF! | H13: =G13+E13 -> #REF! | I13: ='Income Statement'!#REF! -> #REF! | J13: -315 | K13: =L13-J13 -> -336 | L13: -651 | M13: =N13-L13 -> -313 | N13: -964 | O13: =Q13-N13 -> #REF! | P13: =O13+M13 -> #REF! | Q13: ='Income Statement'!#REF! -> #REF! | R13: -220 | S13: =M13-R13 -> -93 | T13: -475 | U13: =V13-M13 -> -461 | V13: -774 | W13: =Y13-V13 -> #REF! | X13: =W13+U13 -> #REF! | Y13: ='Income Statement'!#REF! -> #REF! | AA13: =AB13-Z13 -> 0 | AC13: =AD13-AB13 -> 0 | AE13: =AG13-AD13 -> #REF! | AF13: =AE13+AC13 -> #REF! | AG13: ='Income Statement'!#REF! -> #REF! | AI13: =AJ13-AH13 -> 0 | AK13: =AL13-AJ13 -> 0 | AM13: =AO13-AL13 -> #REF! | AN13: =AM13+AK13 -> #REF! | AO13: ='Income Statement'!#REF! -> #REF! | AQ13: =AR13-AP13 -> 0 | AS13: =AM13-AR13 -> #REF! | AU13: =AW13-AM13 -> #REF! | AV13: =AU13+AS13 -> #REF! | AW13: ='Income Statement'!#REF! -> #REF! | AY13: =AZ13-AX13 -> 0 | BA13: =BB13-AZ13 -> 0 | BC13: =BE13-BB13 -> #REF! | BD13: =BC13+BA13 -> #REF! | BE13: ='Income Statement'!#REF! -> #REF! | BO13: =BP13-BN13 -> 0 | BQ13: =BR13-BP13 -> 0 | BS13: =BU13-BR13 -> #REF! | BT13: =BS13+BQ13 -> #REF! | BU13: ='Income Statement'!#REF! -> #REF! | BW13: =BX13-BV13 -> 0 | BY13: =BZ13-BX13 -> 0 | CA13: =CC13-BZ13 -> #REF! | CB13: =CA13+BY13 -> #REF! | CC13: ='Income Statement'!#REF! -> #REF! | CE13: =CF13-CD13 -> 0 | CG13: =CH13-CF13 -> 0 | CI13: =CK13-CH13 -> #REF! | CJ13: =CI13+CG13 -> #REF! | CK13: ='Income Statement'!#REF! -> #REF! | CS13: ='Income Statement'!#REF! -> #REF! | DA13: ='Income Statement'!#REF! -> #REF! | DI13: ='Income Statement'!#REF! -> #REF! | DQ13: ='Income Statement'!#REF! -> #REF!
A14: Group | B14: 9854 | C14: =SUM(C6:C13) -> 12082 | D14: 21936 | E14: =SUM(E6:E13) -> 10751 | F14: 32687 | G14: =SUM(G6:G13) -> #REF! | H14: =SUM(H6:H13) -> #REF! | I14: =SUM(I6:I13) -> #REF! | J14: 11404 | K14: =SUM(K6:K13) -> 13530 | L14: 24934 | M14: =SUM(M6:M13) -> 12324 | N14: 37258 | O14: =SUM(O6:O13) -> #REF! | P14: =SUM(P6:P13) -> #REF! | Q14: =SUM(Q6:Q13) -> #REF! | R14: 12387 | S14: =SUM(S6:S13) -> -63 | T14: 26332 | U14: =SUM(U6:U13) -> 27642 | V14: 39966 | W14: =SUM(W6:W13) -> #REF! | X14: =SUM(X6:X13) -> #REF! | Y14: =SUM(Y6:Y13) -> #REF! | Z14: =SUM(Z6:Z13) -> 0 | AA14: =SUM(AA6:AA13) -> 0 | AB14: =SUM(AB6:AB13) -> 0 | AC14: =SUM(AC6:AC13) -> 0 | AD14: =SUM(AD6:AD13) -> 0 | ... AS14: =SUM(AS6:AS13) -> #REF! | AT14: =SUM(AM6:AM13) -> #REF! | AU14: =SUM(AU6:AU13) -> #REF! | AV14: =SUM(AV6:AV13) -> #REF! | AW14: =SUM(AW6:AW13) -> #REF! | AX14: =SUM(AX6:AX13) -> 0 | AY14: =SUM(AY6:AY13) -> 0 | AZ14: =SUM(AZ6:AZ13) -> 0 | BA14: =SUM(BA6:BA13) -> 0 | BB14: =SUM(BB6:BB13) -> 0 | ... BE14: =SUM(BE6:BE13) -> #REF! | BN14: =SUM(BN6:BN13) -> 0 | BO14: =SUM(BO6:BO13) -> 0 | BP14: =SUM(BP6:BP13) -> 0 | BQ14: =SUM(BQ6:BQ13) -> 0 | BR14: =SUM(BR6:BR13) -> 0 | BS14: =SUM(BS6:BS13) -> #REF! | BT14: =SUM(BT6:BT13) -> #REF! | BU14: =SUM(BU6:BU13) -> #REF! | ... CK14: =SUM(CK6:CK13) -> #REF! | CS14: =SUM(CS6:CS13) -> #REF! | DA14: =SUM(DA6:DA13) -> #REF! | DI14: =SUM(DI6:DI13) -> #REF! | DQ14: =SUM(DQ6:DQ13) -> #REF!
A16: Sales GrowMh
A17: Airbus Commercial | J17: =IFERROR(J6/B6-1,0) -> 0.13448636 | K17: =IFERROR(K6/C6-1,0) -> 0.1931159 | L17: =IFERROR(L6/D6-1,0) -> 0.1659292 | M17: =IFERROR(M6/E6-1,0) -> 0.24564303 | N17: =IFERROR(N6/F6-1,0) -> 0.19105114 | O17: =IFERROR(O6/G6-1,0) -> 0.24205598 | P17: =IFERROR(P6/H6-1,0) -> 0.24348607 | Q17: =IFERROR(Q6/I6-1,0) -> 0.20748419 | ... S17: =IFERROR(S6/K6-1,0) -> -1.0573744 | T17: =IFERROR(M6/L6-1,0) -> -0.50836101 | U17: =IFERROR(U6/M6-1,0) -> 1.3231215 | V17: =IFERROR(V6/N6-1,0) -> 0.095289207 | W17: =IFERROR(W6/O6-1,0) -> -0.010586254 | X17: =IFERROR(X6/P6-1,0) -> 0.52206166 | Y17: =IFERROR(Y6/Q6-1,0) -> 0.060200936 | Z17: =IFERROR(Z6/R6-1,0) -> -1 | AA17: =IFERROR(AA6/S6-1,0) -> -1 | AB17: =IFERROR(AB6/M6-1,0) -> -1 | AC17: =IFERROR(AC6/U6-1,0) -> -1 | AD17: =IFERROR(AD6/V6-1,0) -> -1 | AE17: =IFERROR(AE6/W6-1,0) -> 2.4270892 | AF17: =IFERROR(AF6/X6-1,0) -> 0.33805937 | AG17: =IFERROR(AG6/Y6-1,0) -> 0.059941337 | AH17: =IFERROR(AH6/Z6-1,0) -> 0 | AI17: =IFERROR(AI6/AA6-1,0) -> 0 | AJ17: =IFERROR(AJ6/AB6-1,0) -> 0 | ... AS17: =IFERROR(AS6/AK6-1,0) -> 0 | AT17: =IFERROR(AM6/AL6-1,0) -> 0 | AU17: =IFERROR(AU6/AM6-1,0) -> -2 | AV17: =IFERROR(AV6/AN6-1,0) -> -1 | AW17: =IFERROR(AW6/AO6-1,0) -> -1 | AX17: =IFERROR(AX6/AP6-1,0) -> 0 | AY17: =IFERROR(AY6/AQ6-1,0) -> 0 | AZ17: =IFERROR(AZ6/AR6-1,0) -> 0 | BA17: =IFERROR(BA6/AS6-1,0) -> -1 | BB17: =IFERROR(BB6/AM6-1,0) -> -1 | BC17: =IFERROR(BC6/AU6-1,0) -> -1 | BD17: =IFERROR(BD6/AV6-1,0) -> 0 | BE17: =IFERROR(BE6/AW6-1,0) -> 0 | BN17: =IFERROR(BN6/AX6-1,0) -> 0 | BO17: =IFERROR(BO6/AY6-1,0) -> 0 | BP17: =IFERROR(BP6/AZ6-1,0) -> 0 | BQ17: =IFERROR(BQ6/BA6-1,0) -> 0 | BR17: =IFERROR(BR6/AU6-1,0) -> -1 | BS17: =IFERROR(BS6/BC6-1,0) -> 0 | BT17: =IFERROR(BT6/BD6-1,0) -> 0 | BU17: =IFERROR(BU6/BE6-1,0) -> 0 | BV17: =IFERROR(BV6/BN6-1,0) -> 0 | BW17: =IFERROR(BW6/BO6-1,0) -> 0 | BX17: =IFERROR(BX6/BP6-1,0) -> 0 | BY17: =IFERROR(BY6/BQ6-1,0) -> 0 | BZ17: =IFERROR(BZ6/BC6-1,0) -> 0 | CA17: =IFERROR(CA6/BS6-1,0) -> 0 | CB17: =IFERROR(CB6/BT6-1,0) -> 0 | CC17: =IFERROR(CC6/BU6-1,0) -> 0 | CD17: =IFERROR(CD6/BV6-1,0) -> 0 | CE17: =IFERROR(CE6/BW6-1,0) -> 0 | CF17: =IFERROR(CF6/BX6-1,0) -> 0 | CG17: =IFERROR(CG6/BY6-1,0) -> 0 | CH17: =IFERROR(CH6/BS6-1,0) -> 0 | CI17: =IFERROR(CI6/CA6-1,0) -> 0 | CJ17: =IFERROR(CJ6/CB6-1,0) -> 0 | CK17: =IFERROR(CK6/CC6-1,0) -> 0 | CS17: =IFERROR(CS6/CK6-1,0) -> 0 | DA17: =IFERROR(DA6/CS6-1,0) -> 0 | DI17: =IFERROR(DI6/DA6-1,0) -> 0 | DQ17: =IFERROR(DQ6/DI6-1,0) -> 0
A18: Airbus MiliMary | J18: =IFERROR(J7/B7-1,0) -> -0.020737327 | K18: =IFERROR(K7/C7-1,0) -> -0.38348083 | L18: =IFERROR(L7/D7-1,0) -> -0.24190647 | M18: =IFERROR(M7/E7-1,0) -> -0.44724409 | N18: =IFERROR(N7/F7-1,0) -> -0.31654264 | O18: =IFERROR(O7/G7-1,0) -> -3.5405839 | P18: =IFERROR(P7/H7-1,0) -> -5.3070144 | Q18: =IFERROR(Q7/I7-1,0) -> 0 | ... S18: =IFERROR(S7/K7-1,0) -> -1.6315789 | T18: =IFERROR(M7/L7-1,0) -> -0.58362989 | U18: =IFERROR(U7/M7-1,0) -> 3.039886 | V18: =IFERROR(V7/N7-1,0) -> 0.48157454 | W18: =IFERROR(W7/O7-1,0) -> 0 | X18: =IFERROR(X7/P7-1,0) -> 0 | Y18: =IFERROR(Y7/Q7-1,0) -> 0 | Z18: =IFERROR(Z7/R7-1,0) -> -1 | AA18: =IFERROR(AA7/S7-1,0) -> -1 | AB18: =IFERROR(AB7/M7-1,0) -> -1 | AC18: =IFERROR(AC7/U7-1,0) -> -1 | AD18: =IFERROR(AD7/V7-1,0) -> -1 | AE18: =IFERROR(AE7/W7-1,0) -> 0 | AF18: =IFERROR(AF7/X7-1,0) -> 0 | AG18: =IFERROR(AG7/Y7-1,0) -> 0 | AH18: =IFERROR(AH7/Z7-1,0) -> 0 | AI18: =IFERROR(AI7/AA7-1,0) -> 0 | AJ18: =IFERROR(AJ7/AB7-1,0) -> 0 | ... AS18: =IFERROR(AS7/AK7-1,0) -> 0 | AT18: =IFERROR(AM7/AL7-1,0) -> 0 | AU18: =IFERROR(AU7/AM7-1,0) -> 0 | AV18: =IFERROR(AV7/AN7-1,0) -> 0 | AW18: =IFERROR(AW7/AO7-1,0) -> 0 | AX18: =IFERROR(AX7/AP7-1,0) -> 0 | AY18: =IFERROR(AY7/AQ7-1,0) -> 0 | AZ18: =IFERROR(AZ7/AR7-1,0) -> 0 | BA18: =IFERROR(BA7/AS7-1,0) -> 0 | BB18: =IFERROR(BB7/AM7-1,0) -> 0 | BC18: =IFERROR(BC7/AU7-1,0) -> 0 | BD18: =IFERROR(BD7/AV7-1,0) -> 0 | BE18: =IFERROR(BE7/AW7-1,0) -> 0 | BN18: =IFERROR(BN7/AX7-1,0) -> 0 | BO18: =IFERROR(BO7/AY7-1,0) -> 0 | BP18: =IFERROR(BP7/AZ7-1,0) -> 0 | BQ18: =IFERROR(BQ7/BA7-1,0) -> 0 | BR18: =IFERROR(BR7/AU7-1,0) -> 0 | BS18: =IFERROR(BS7/BC7-1,0) -> 0 | BT18: =IFERROR(BT7/BD7-1,0) -> 0 | BU18: =IFERROR(BU7/BE7-1,0) -> 0 | BV18: =IFERROR(BV7/BN7-1,0) -> 0 | BW18: =IFERROR(BW7/BO7-1,0) -> 0 | BX18: =IFERROR(BX7/BP7-1,0) -> 0 | BY18: =IFERROR(BY7/BQ7-1,0) -> 0 | BZ18: =IFERROR(BZ7/BC7-1,0) -> 0 | CA18: =IFERROR(CA7/BS7-1,0) -> 0 | CB18: =IFERROR(CB7/BT7-1,0) -> 0 | CC18: =IFERROR(CC7/BU7-1,0) -> 0 | CD18: =IFERROR(CD7/BV7-1,0) -> 0 | CE18: =IFERROR(CE7/BW7-1,0) -> 0 | CF18: =IFERROR(CF7/BX7-1,0) -> 0 | CG18: =IFERROR(CG7/BY7-1,0) -> 0 | CH18: =IFERROR(CH7/BS7-1,0) -> 0 | CI18: =IFERROR(CI7/CA7-1,0) -> 0 | CJ18: =IFERROR(CJ7/CB7-1,0) -> 0 | CK18: =IFERROR(CK7/CC7-1,0) -> 0 | CS18: =IFERROR(CS7/CK7-1,0) -> 0 | DA18: =IFERROR(DA7/CS7-1,0) -> 0 | DI18: =IFERROR(DI7/DA7-1,0) -> 0 | DQ18: =IFERROR(DQ7/DI7-1,0) -> 0
A19: EurocopMer | J19: =IFERROR(J8/B8-1,0) -> 0.45686513 | K19: =IFERROR(K8/C8-1,0) -> 0.16617211 | L19: =IFERROR(L8/D8-1,0) -> 0.27637034 | M19: =IFERROR(M8/E8-1,0) -> 0.045066045 | N19: =IFERROR(N8/F8-1,0) -> 0.1902834 | O19: =IFERROR(O8/G8-1,0) -> 0.097598365 | P19: =IFERROR(P8/H8-1,0) -> 0.07675709 | Q19: =IFERROR(Q8/I8-1,0) -> 0.1567867 | ... S19: =IFERROR(S8/K8-1,0) -> -0.80470738 | T19: =IFERROR(M8/L8-1,0) -> -0.51461566 | U19: =IFERROR(U8/M8-1,0) -> 1.072119 | V19: =IFERROR(V8/N8-1,0) -> 0.0038872692 | W19: =IFERROR(W8/O8-1,0) -> 0.0079143389 | X19: =IFERROR(X8/P8-1,0) -> 0.41769253 | Y19: =IFERROR(Y8/Q8-1,0) -> 0.0052681992 | Z19: =IFERROR(Z8/R8-1,0) -> -1 | AA19: =IFERROR(AA8/S8-1,0) -> -1 | AB19: =IFERROR(AB8/M8-1,0) -> -1 | AC19: =IFERROR(AC8/U8-1,0) -> -1 | AD19: =IFERROR(AD8/V8-1,0) -> -1 | AE19: =IFERROR(AE8/W8-1,0) -> 2.0133949 | AF19: =IFERROR(AF8/X8-1,0) -> 0.3174475 | AG19: =IFERROR(AG8/Y8-1,0) -> 0.036048912 | AH19: =IFERROR(AH8/Z8-1,0) -> 0 | AI19: =IFERROR(AI8/AA8-1,0) -> 0 | AJ19: =IFERROR(AJ8/AB8-1,0) -> 0 | ... AS19: =IFERROR(AS8/AK8-1,0) -> 0 | AT19: =IFERROR(AM8/AL8-1,0) -> 0 | AU19: =IFERROR(AU8/AM8-1,0) -> -2 | AV19: =IFERROR(AV8/AN8-1,0) -> -1 | AW19: =IFERROR(AW8/AO8-1,0) -> -1 | AX19: =IFERROR(AX8/AP8-1,0) -> 0 | AY19: =IFERROR(AY8/AQ8-1,0) -> 0 | AZ19: =IFERROR(AZ8/AR8-1,0) -> 0 | BA19: =IFERROR(BA8/AS8-1,0) -> -1 | BB19: =IFERROR(BB8/AM8-1,0) -> -1 | BC19: =IFERROR(BC8/AU8-1,0) -> -1 | BD19: =IFERROR(BD8/AV8-1,0) -> 0 | BE19: =IFERROR(BE8/AW8-1,0) -> 0 | BN19: =IFERROR(BN8/AX8-1,0) -> 0 | BO19: =IFERROR(BO8/AY8-1,0) -> 0 | BP19: =IFERROR(BP8/AZ8-1,0) -> 0 | BQ19: =IFERROR(BQ8/BA8-1,0) -> 0 | BR19: =IFERROR(BR8/AU8-1,0) -> -1 | BS19: =IFERROR(BS8/BC8-1,0) -> 0 | BT19: =IFERROR(BT8/BD8-1,0) -> 0 | BU19: =IFERROR(BU8/BE8-1,0) -> 0 | BV19: =IFERROR(BV8/BN8-1,0) -> 0 | BW19: =IFERROR(BW8/BO8-1,0) -> 0 | BX19: =IFERROR(BX8/BP8-1,0) -> 0 | BY19: =IFERROR(BY8/BQ8-1,0) -> 0 | BZ19: =IFERROR(BZ8/BC8-1,0) -> 0 | CA19: =IFERROR(CA8/BS8-1,0) -> 0 | CB19: =IFERROR(CB8/BT8-1,0) -> 0 | CC19: =IFERROR(CC8/BU8-1,0) -> 0 | CD19: =IFERROR(CD8/BV8-1,0) -> 0 | CE19: =IFERROR(CE8/BW8-1,0) -> 0 | CF19: =IFERROR(CF8/BX8-1,0) -> 0 | CG19: =IFERROR(CG8/BY8-1,0) -> 0 | CH19: =IFERROR(CH8/BS8-1,0) -> 0 | CI19: =IFERROR(CI8/CA8-1,0) -> 0 | CJ19: =IFERROR(CJ8/CB8-1,0) -> 0 | CK19: =IFERROR(CK8/CC8-1,0) -> 0 | CS19: =IFERROR(CS8/CK8-1,0) -> 0 | DA19: =IFERROR(DA8/CS8-1,0) -> 0 | DI19: =IFERROR(DI8/DA8-1,0) -> 0 | DQ19: =IFERROR(DQ8/DI8-1,0) -> 0
A20: AsMrium | J20: =IFERROR(J9/B9-1,0) -> 0.13151153 | K20: =IFERROR(K9/C9-1,0) -> 0.13605442 | L20: =IFERROR(L9/D9-1,0) -> 0.13378781 | M20: =IFERROR(M9/E9-1,0) -> 0.16468435 | N20: =IFERROR(N9/F9-1,0) -> 0.14360465 | O20: =IFERROR(O9/G9-1,0) -> -1.5473837 | P20: =IFERROR(P9/H9-1,0) -> -2.3446954 | Q20: =IFERROR(Q9/I9-1,0) -> 0 | ... S20: =IFERROR(S9/K9-1,0) -> -1.0718563 | T20: =IFERROR(M9/L9-1,0) -> -0.52160842 | U20: =IFERROR(U9/M9-1,0) -> 1.1531815 | V20: =IFERROR(V9/N9-1,0) -> 0.020335536 | W20: =IFERROR(W9/O9-1,0) -> -0.060010621 | X20: =IFERROR(X9/P9-1,0) -> 0.42934094 | Y20: =IFERROR(Y9/Q9-1,0) -> -0.0056730273 | Z20: =IFERROR(Z9/R9-1,0) -> -1 | AA20: =IFERROR(AA9/S9-1,0) -> -1 | AB20: =IFERROR(AB9/M9-1,0) -> -1 | AC20: =IFERROR(AC9/U9-1,0) -> -1 | AD20: =IFERROR(AD9/V9-1,0) -> -1 | AE20: =IFERROR(AE9/W9-1,0) -> -1 | AF20: =IFERROR(AF9/X9-1,0) -> -1 | AG20: =IFERROR(AG9/Y9-1,0) -> -1 | AH20: =IFERROR(AH9/Z9-1,0) -> 0 | AI20: =IFERROR(AI9/AA9-1,0) -> 0 | AJ20: =IFERROR(AJ9/AB9-1,0) -> 0 | ... AS20: =IFERROR(AS9/AK9-1,0) -> 0 | AT20: =IFERROR(AM9/AL9-1,0) -> 0 | AU20: =IFERROR(AU9/AM9-1,0) -> 0 | AV20: =IFERROR(AV9/AN9-1,0) -> 0 | AW20: =IFERROR(AW9/AO9-1,0) -> 0 | AX20: =IFERROR(AX9/AP9-1,0) -> 0 | AY20: =IFERROR(AY9/AQ9-1,0) -> 0 | AZ20: =IFERROR(AZ9/AR9-1,0) -> 0 | BA20: =IFERROR(BA9/AS9-1,0) -> 0 | BB20: =IFERROR(BB9/AM9-1,0) -> 0 | BC20: =IFERROR(BC9/AU9-1,0) -> 0 | BD20: =IFERROR(BD9/AV9-1,0) -> 0 | BE20: =IFERROR(BE9/AW9-1,0) -> 0 | BN20: =IFERROR(BN9/AX9-1,0) -> 0 | BO20: =IFERROR(BO9/AY9-1,0) -> 0 | BP20: =IFERROR(BP9/AZ9-1,0) -> 0 | BQ20: =IFERROR(BQ9/BA9-1,0) -> 0 | BR20: =IFERROR(BR9/AU9-1,0) -> 0 | BS20: =IFERROR(BS9/BC9-1,0) -> 0 | BT20: =IFERROR(BT9/BD9-1,0) -> 0 | BU20: =IFERROR(BU9/BE9-1,0) -> 0 | BV20: =IFERROR(BV9/BN9-1,0) -> 0 | BW20: =IFERROR(BW9/BO9-1,0) -> 0 | BX20: =IFERROR(BX9/BP9-1,0) -> 0 | BY20: =IFERROR(BY9/BQ9-1,0) -> 0 | BZ20: =IFERROR(BZ9/BC9-1,0) -> 0 | CA20: =IFERROR(CA9/BS9-1,0) -> 0 | CB20: =IFERROR(CB9/BT9-1,0) -> 0 | CC20: =IFERROR(CC9/BU9-1,0) -> 0 | CD20: =IFERROR(CD9/BV9-1,0) -> 0 | CE20: =IFERROR(CE9/BW9-1,0) -> 0 | CF20: =IFERROR(CF9/BX9-1,0) -> 0 | CG20: =IFERROR(CG9/BY9-1,0) -> 0 | CH20: =IFERROR(CH9/BS9-1,0) -> 0 | CI20: =IFERROR(CI9/CA9-1,0) -> 0 | CJ20: =IFERROR(CJ9/CB9-1,0) -> 0 | CK20: =IFERROR(CK9/CC9-1,0) -> 0 | CS20: =IFERROR(CS9/CK9-1,0) -> 0 | DA20: =IFERROR(DA9/CS9-1,0) -> 0 | DI20: =IFERROR(DI9/DA9-1,0) -> 0 | DQ20: =IFERROR(DQ9/DI9-1,0) -> 0
A21: Cassidian | J21: =IFERROR(J10/B10-1,0) -> 0.053530752 | K21: =IFERROR(K10/C10-1,0) -> 0.0047808765 | L21: =IFERROR(L10/D10-1,0) -> 0.024847632 | M21: =IFERROR(M10/E10-1,0) -> 0.0093312597 | N21: =IFERROR(N10/F10-1,0) -> 0.019011407 | O21: =IFERROR(O10/G10-1,0) -> -1.6598421 | P21: =IFERROR(P10/H10-1,0) -> -2.6661978 | Q21: =IFERROR(Q10/I10-1,0) -> 0 | ... S21: =IFERROR(S10/K10-1,0) -> -0.71689136 | T21: =IFERROR(M10/L10-1,0) -> -0.40622141 | U21: =IFERROR(U10/M10-1,0) -> 0.69491525 | V21: =IFERROR(V10/N10-1,0) -> 0.0040183697 | W21: =IFERROR(W10/O10-1,0) -> 0.098404255 | X21: =IFERROR(X10/P10-1,0) -> 0.31626337 | Y21: =IFERROR(Y10/Q10-1,0) -> 0.041114983 | Z21: =IFERROR(Z10/R10-1,0) -> -1 | AA21: =IFERROR(AA10/S10-1,0) -> -1 | AB21: =IFERROR(AB10/M10-1,0) -> -1 | AC21: =IFERROR(AC10/U10-1,0) -> -1 | AD21: =IFERROR(AD10/V10-1,0) -> -1 | AE21: =IFERROR(AE10/W10-1,0) -> -1 | AF21: =IFERROR(AF10/X10-1,0) -> -1 | AG21: =IFERROR(AG10/Y10-1,0) -> -1 | AH21: =IFERROR(AH10/Z10-1,0) -> 0 | AI21: =IFERROR(AI10/AA10-1,0) -> 0 | AJ21: =IFERROR(AJ10/AB10-1,0) -> 0 | ... AS21: =IFERROR(AS10/AK10-1,0) -> 0 | AT21: =IFERROR(AM10/AL10-1,0) -> 0 | AU21: =IFERROR(AU10/AM10-1,0) -> 0 | AV21: =IFERROR(AV10/AN10-1,0) -> 0 | AW21: =IFERROR(AW10/AO10-1,0) -> 0 | AX21: =IFERROR(AX10/AP10-1,0) -> 0 | AY21: =IFERROR(AY10/AQ10-1,0) -> 0 | AZ21: =IFERROR(AZ10/AR10-1,0) -> 0 | BA21: =IFERROR(BA10/AS10-1,0) -> 0 | BB21: =IFERROR(BB10/AM10-1,0) -> 0 | BC21: =IFERROR(BC10/AU10-1,0) -> 0 | BD21: =IFERROR(BD10/AV10-1,0) -> 0 | BE21: =IFERROR(BE10/AW10-1,0) -> 0 | BN21: =IFERROR(BN10/AX10-1,0) -> 0 | BO21: =IFERROR(BO10/AY10-1,0) -> 0 | BP21: =IFERROR(BP10/AZ10-1,0) -> 0 | BQ21: =IFERROR(BQ10/BA10-1,0) -> 0 | BR21: =IFERROR(BR10/AU10-1,0) -> 0 | BS21: =IFERROR(BS10/BC10-1,0) -> 0 | BT21: =IFERROR(BT10/BD10-1,0) -> 0 | BU21: =IFERROR(BU10/BE10-1,0) -> 0 | BV21: =IFERROR(BV10/BN10-1,0) -> 0 | BW21: =IFERROR(BW10/BO10-1,0) -> 0 | BX21: =IFERROR(BX10/BP10-1,0) -> 0 | BY21: =IFERROR(BY10/BQ10-1,0) -> 0 | BZ21: =IFERROR(BZ10/BC10-1,0) -> 0 | CA21: =IFERROR(CA10/BS10-1,0) -> 0 | CB21: =IFERROR(CB10/BT10-1,0) -> 0 | CC21: =IFERROR(CC10/BU10-1,0) -> 0 | CD21: =IFERROR(CD10/BV10-1,0) -> 0 | CE21: =IFERROR(CE10/BW10-1,0) -> 0 | CF21: =IFERROR(CF10/BX10-1,0) -> 0 | CG21: =IFERROR(CG10/BY10-1,0) -> 0 | CH21: =IFERROR(CH10/BS10-1,0) -> 0 | CI21: =IFERROR(CI10/CA10-1,0) -> 0 | CJ21: =IFERROR(CJ10/CB10-1,0) -> 0 | CK21: =IFERROR(CK10/CC10-1,0) -> 0 | CS21: =IFERROR(CS10/CK10-1,0) -> 0 | DA21: =IFERROR(DA10/CS10-1,0) -> 0 | DI21: =IFERROR(DI10/DA10-1,0) -> 0 | DQ21: =IFERROR(DQ10/DI10-1,0) -> 0
A22: oMher | J22: =IFERROR(J11/B11-1,0) -> -0.19918699 | K22: =IFERROR(K11/C11-1,0) -> -0.51798561 | L22: =IFERROR(L11/D11-1,0) -> -0.36832061 | M22: =IFERROR(M11/E11-1,0) -> -0.57928803 | N22: =IFERROR(N11/F11-1,0) -> -0.44657863 | O22: =IFERROR(O11/G11-1,0) -> 0 | P22: =IFERROR(P11/H11-1,0) -> 0 | Q22: =IFERROR(Q11/I11-1,0) -> 0 | ... S22: =IFERROR(S11/K11-1,0) -> -0.6119403 | T22: =IFERROR(M11/L11-1,0) -> -0.60725076 | U22: =IFERROR(U11/M11-1,0) -> 0.27692308 | V22: =IFERROR(V11/N11-1,0) -> -0.35791757 | W22: =IFERROR(W11/O11-1,0) -> 0.53302326 | X22: =IFERROR(X11/P11-1,0) -> 0.56825397 | Y22: =IFERROR(Y11/Q11-1,0) -> 1.2019544 | Z22: =IFERROR(Z11/R11-1,0) -> -1 | AA22: =IFERROR(AA11/S11-1,0) -> -1 | AB22: =IFERROR(AB11/M11-1,0) -> -1 | AC22: =IFERROR(AC11/U11-1,0) -> -1 | AD22: =IFERROR(AD11/V11-1,0) -> -1 | AE22: =IFERROR(AE11/W11-1,0) -> -0.32281553 | AF22: =IFERROR(AF11/X11-1,0) -> -0.24696356 | AG22: =IFERROR(AG11/Y11-1,0) -> -0.17455621 | AH22: =IFERROR(AH11/Z11-1,0) -> 0 | AI22: =IFERROR(AI11/AA11-1,0) -> 0 | AJ22: =IFERROR(AJ11/AB11-1,0) -> 0 | ... AS22: =IFERROR(AS11/AK11-1,0) -> 0 | AT22: =IFERROR(AM11/AL11-1,0) -> 0 | AU22: =IFERROR(AU11/AM11-1,0) -> -2 | AV22: =IFERROR(AV11/AN11-1,0) -> -1 | AW22: =IFERROR(AW11/AO11-1,0) -> -1 | AX22: =IFERROR(AX11/AP11-1,0) -> 0 | AY22: =IFERROR(AY11/AQ11-1,0) -> 0 | AZ22: =IFERROR(AZ11/AR11-1,0) -> 0 | BA22: =IFERROR(BA11/AS11-1,0) -> -1 | BB22: =IFERROR(BB11/AM11-1,0) -> -1 | BC22: =IFERROR(BC11/AU11-1,0) -> -1 | BD22: =IFERROR(BD11/AV11-1,0) -> 0 | BE22: =IFERROR(BE11/AW11-1,0) -> 0 | BN22: =IFERROR(BN11/AX11-1,0) -> 0 | BO22: =IFERROR(BO11/AY11-1,0) -> 0 | BP22: =IFERROR(BP11/AZ11-1,0) -> 0 | BQ22: =IFERROR(BQ11/BA11-1,0) -> 0 | BR22: =IFERROR(BR11/AU11-1,0) -> -1 | BS22: =IFERROR(BS11/BC11-1,0) -> 0 | BT22: =IFERROR(BT11/BD11-1,0) -> 0 | BU22: =IFERROR(BU11/BE11-1,0) -> 0 | BV22: =IFERROR(BV11/BN11-1,0) -> 0 | BW22: =IFERROR(BW11/BO11-1,0) -> 0 | BX22: =IFERROR(BX11/BP11-1,0) -> 0 | BY22: =IFERROR(BY11/BQ11-1,0) -> 0 | BZ22: =IFERROR(BZ11/BC11-1,0) -> 0 | CA22: =IFERROR(CA11/BS11-1,0) -> 0 | CB22: =IFERROR(CB11/BT11-1,0) -> 0 | CC22: =IFERROR(CC11/BU11-1,0) -> 0 | CD22: =IFERROR(CD11/BV11-1,0) -> 0 | CE22: =IFERROR(CE11/BW11-1,0) -> 0 | CF22: =IFERROR(CF11/BX11-1,0) -> 0 | CG22: =IFERROR(CG11/BY11-1,0) -> 0 | CH22: =IFERROR(CH11/BS11-1,0) -> 0 | CI22: =IFERROR(CI11/CA11-1,0) -> 0 | CJ22: =IFERROR(CJ11/CB11-1,0) -> 0 | CK22: =IFERROR(CK11/CC11-1,0) -> 0 | CS22: =IFERROR(CS11/CK11-1,0) -> 0 | DA22: =IFERROR(DA11/CS11-1,0) -> 0 | DI22: =IFERROR(DI11/DA11-1,0) -> 0 | DQ22: =IFERROR(DQ11/DI11-1,0) -> 0
A23: Group | J23: =IFERROR(J14/B14-1,0) -> 0.15729653 | K23: =IFERROR(K14/C14-1,0) -> 0.11984771 | L23: =IFERROR(L14/D14-1,0) -> 0.13667031 | M23: =IFERROR(M14/E14-1,0) -> 0.14631197 | N23: =IFERROR(N14/F14-1,0) -> 0.13984153 | O23: =IFERROR(O14/G14-1,0) -> 0 | P23: =IFERROR(P14/H14-1,0) -> 0 | Q23: =IFERROR(Q14/I14-1,0) -> 0 | ... S23: =IFERROR(S14/K14-1,0) -> -1.0046563 | T23: =IFERROR(M14/L14-1,0) -> -0.50573514 | U23: =IFERROR(U14/M14-1,0) -> 1.2429406 | V23: =IFERROR(V14/N14-1,0) -> 0.072682377 | W23: =IFERROR(W14/O14-1,0) -> 0 | X23: =IFERROR(X14/P14-1,0) -> 0 | Y23: =IFERROR(Y14/Q14-1,0) -> 0 | Z23: =IFERROR(Z14/R14-1,0) -> -1 | AA23: =IFERROR(AA14/S14-1,0) -> -1 | AB23: =IFERROR(AB14/M14-1,0) -> -1 | AC23: =IFERROR(AC14/U14-1,0) -> -1 | AD23: =IFERROR(AD14/V14-1,0) -> -1 | AE23: =IFERROR(AE14/W14-1,0) -> 0 | AF23: =IFERROR(AF14/X14-1,0) -> 0 | AG23: =IFERROR(AG14/Y14-1,0) -> 0 | AH23: =IFERROR(AH14/Z14-1,0) -> 0 | AI23: =IFERROR(AI14/AA14-1,0) -> 0 | AJ23: =IFERROR(AJ14/AB14-1,0) -> 0 | ... AS23: =IFERROR(AS14/AK14-1,0) -> 0 | AT23: =IFERROR(AM14/AL14-1,0) -> 0 | AU23: =IFERROR(AU14/AM14-1,0) -> 0 | AV23: =IFERROR(AV14/AN14-1,0) -> 0 | AW23: =IFERROR(AW14/AO14-1,0) -> 0 | AX23: =IFERROR(AX14/AP14-1,0) -> 0 | AY23: =IFERROR(AY14/AQ14-1,0) -> 0 | AZ23: =IFERROR(AZ14/AR14-1,0) -> 0 | BA23: =IFERROR(BA14/AS14-1,0) -> 0 | BB23: =IFERROR(BB14/AM14-1,0) -> 0 | BC23: =IFERROR(BC14/AU14-1,0) -> 0 | BD23: =IFERROR(BD14/AV14-1,0) -> 0 | BE23: =IFERROR(BE14/AW14-1,0) -> 0 | BN23: =IFERROR(BN14/AX14-1,0) -> 0 | BO23: =IFERROR(BO14/AY14-1,0) -> 0 | BP23: =IFERROR(BP14/AZ14-1,0) -> 0 | BQ23: =IFERROR(BQ14/BA14-1,0) -> 0 | BR23: =IFERROR(BR14/AU14-1,0) -> 0 | BS23: =IFERROR(BS14/BC14-1,0) -> 0 | BT23: =IFERROR(BT14/BD14-1,0) -> 0 | BU23: =IFERROR(BU14/BE14-1,0) -> 0 | BV23: =IFERROR(BV14/BN14-1,0) -> 0 | BW23: =IFERROR(BW14/BO14-1,0) -> 0 | BX23: =IFERROR(BX14/BP14-1,0) -> 0 | BY23: =IFERROR(BY14/BQ14-1,0) -> 0 | BZ23: =IFERROR(BZ14/BC14-1,0) -> 0 | CA23: =IFERROR(CA14/BS14-1,0) -> 0 | CB23: =IFERROR(CB14/BT14-1,0) -> 0 | CC23: =IFERROR(CC14/BU14-1,0) -> 0 | CD23: =IFERROR(CD14/BV14-1,0) -> 0 | CE23: =IFERROR(CE14/BW14-1,0) -> 0 | CF23: =IFERROR(CF14/BX14-1,0) -> 0 | CG23: =IFERROR(CG14/BY14-1,0) -> 0 | CH23: =IFERROR(CH14/BS14-1,0) -> 0 | CI23: =IFERROR(CI14/CA14-1,0) -> 0 | CJ23: =IFERROR(CJ14/CB14-1,0) -> 0 | CK23: =IFERROR(CK14/CC14-1,0) -> 0 | CS23: =IFERROR(CS14/CK14-1,0) -> 0 | DA23: =IFERROR(DA14/CS14-1,0) -> 0 | DI23: =IFERROR(DI14/DA14-1,0) -> 0 | DQ23: =IFERROR(DQ14/DI14-1,0) -> 0
A25: Company defined EBIM before one offs
