Workbook
Name _div08: #REF!
Name _div09: #REF!
Name _div10: #REF!
Name _ShH3: #REF!
Name A_ALL_AIR.PA: #REF!
Name A_ALL_AIR.PA: #REF!
Name A_ALL_AIR.PA_: #REF!
Name A_ALL_AIR.PA_: #REF!
Name A_ALL_AIR.PA_: #REF!
Name A_ALL_AIR.PA_: #REF!
Name A_ALL_AIR.PA_: #REF!
Name A_ALL_AIR.PA_: #REF!
Name A_ALL_AIR.PA_: #REF!
Name A_ALL_BAES.L_: #REF!
Name A_ALL_BAES.L_: #REF!
Name A_ALL_BAES.L_: #REF!
Name A_ALL_BAES.L_: #REF!
Name A_ALL_BAES.L_: #REF!
Name A_ALL_BAES.L_: #REF!
Name A_ALL_BAES.L_: #REF!
Name A_ALL_COB.L: #REF!
Name A_ALL_COB.L: #REF!
Name A_ALL_COB.L: #REF!
Name A_ALL_KEYWORDS_TYPE_ScalarContributed_EQTY_200000267: #REF!,#REF!
Name A_ALL_KEYWORDS_TYPE_ScalarContributed_EQTY_200003162: #REF!,#REF!
Name A_ALL_KEYWORDS_TYPE_ScalarContributed_EQTY_200003162: #REF!,#REF!
Name A_ALL_KEYWORDS_TYPE_ScalarContributed_EQTY_200003162: #REF!,#REF!
Name A_ALL_KEYWORDS_TYPE_ScalarContributed_EQTY_200003170: #REF!,#REF!
Name A_ALL_KEYWORDS_TYPE_ScalarContributed_EQTY_200003170: #REF!,#REF!
Name A_ALL_KEYWORDS_TYPE_ScalarContributed_EQTY_200003170: #REF!,#REF!
Name A_ALL_KEYWORDS_TYPE_ScalarContributed_EQTY_200003173: #REF!,#REF!
Name A_ALL_KEYWORDS_TYPE_ScalarContributed_EQTY_200003173: #REF!,#REF!
Name A_ALL_KEYWORDS_TYPE_ScalarContributed_EQTY_200003173: #REF!,#REF!
Name A_ALL_KEYWORDS_TYPE_ScalarContributed_EQTY_200003183: #REF!,#REF!
Name A_ALL_KEYWORDS_TYPE_ScalarContributed_EQTY_200003183: #REF!,#REF!
Name A_ALL_KEYWORDS_TYPE_ScalarContributed_EQTY_200003183: #REF!,#REF!
Name A_ALL_KEYWORDS_TYPE_ScalarContributed_EQTY_200003821: #REF!,#REF!
Name A_ALL_KEYWORDS_TYPE_ScalarContributed_EQTY_200003821: #REF!,#REF!
Name A_ALL_KEYWORDS_TYPE_ScalarContributed_EQTY_200003821: #REF!,#REF!
Name A_ALL_KEYWORDS_TYPE_ScalarContributed_EQTY_200004285: #REF!,#REF!
Name A_ALL_KEYWORDS_TYPE_ScalarContributed_EQTY_200004285: #REF!,#REF!
Name A_ALL_KEYWORDS_TYPE_ScalarContributed_EQTY_200005121: #REF!,#REF!
Name A_ALL_KEYWORDS_TYPE_ScalarContributed_EQTY_200005121: #REF!,#REF!
Name A_ALL_KEYWORDS_TYPE_ScalarContributed_EQTY_200005121: #REF!,#REF!
Name A_ALL_KEYWORDS_TYPE_ScalarContributed_EQTY_200007513: #REF!,#REF!
Name A_ALL_KEYWORDS_TYPE_ScalarContributed_EQTY_200007513: #REF!,#REF!
Name A_ALL_KEYWORDS_TYPE_ScalarContributed_EQTY_200007513: #REF!,#REF!
Name A_ALL_KEYWORDS_TYPE_ScalarContributed_EQTY_200008448: #REF!,#REF!,#REF!
Name A_ALL_KEYWORDS_TYPE_ScalarContributed_EQTY_200009618: #REF!,#REF!
Name A_ALL_KEYWORDS_TYPE_ScalarContributed_EQTY_200009618: #REF!,#REF!
Name A_ALL_KEYWORDS_TYPE_ScalarContributed_EQTY_200009618: #REF!,#REF!
Name A_ALL_KEYWORDS_TYPE_ScalarContributed_EQTY_200009619: #REF!,#REF!
Name A_ALL_KEYWORDS_TYPE_ScalarContributed_EQTY_200009619: #REF!,#REF!
Name A_ALL_KEYWORDS_TYPE_ScalarContributed_EQTY_200009619: #REF!,#REF!
Name A_ALL_KEYWORDS_TYPE_ScalarContributed_EQTY_200009620: #REF!,#REF!
Name A_ALL_KEYWORDS_TYPE_ScalarContributed_EQTY_200009620: #REF!,#REF!
Name A_ALL_KEYWORDS_TYPE_ScalarContributed_EQTY_200009620: #REF!,#REF!
Name A_ALL_KEYWORDS_TYPE_ScalarContributed_EQTY_200011295: #REF!,#REF!
Name A_ALL_KEYWORDS_TYPE_ScalarContributed_EQTY_200011295: #REF!,#REF!
Name A_ALL_KEYWORDS_TYPE_ScalarContributed_ISSR_208000023: #REF!,#REF!,#REF!,#REF!,#REF!,#REF!,#REF!,#REF!,#REF!,#REF!

Sheet _QP_SAF.PA
A1: 1311101 | F1: 1998 | G1: 1999 | H1: 2000 | I1: 2001 | J1: 2002 | K1: 2003 | L1: 2004 | M1: 2005 | N1: 2006 H1 | O1: 2006 H2 | P1: 2006 | Q1: 2007 H1 | R1: 2007 H2 | S1: 2007 | T1: 2008 H1 | U1: 2008 H2 | V1: 2008 | W1: 2009 H1 | X1: 2009 H2 | Y1: 2009 | Z1: 2010 H1 | AA1: 2010 H2 | AB1: 2010 | AC1: 2011 H1 | AD1: 2011 H2 | AE1: 2011 | AF1: 2012 | AG1: 2013 | AH1: 2014 | AI1: 2015 | AJ1: 2016
A2: AUTO-GENERATED BY TIGR NUMBERS SUBMISSION. DO NOT MODIFY OR DELETE!
B4: ACC_END_DATE | D4: EUR | F4: 36160 | G4: 36525 | H4: 36891 | I4: 37256 | J4: 37621 | K4: 37986 | L4: 38352 | M4: 38717 | N4: 38898 | O4: 39082 | P4: 39082 | Q4: 39263 | R4: 39447 | S4: 39447 | T4: 39629 | U4: 39813 | V4: 39813 | W4: 39994 | X4: 40178 | Y4: 40178 | Z4: 40359 | AA4: 40543 | AB4: 40543 | AC4: 40724 | AD4: 40908 | AE4: 40908 | AF4: 41274 | AG4: 41639 | AH4: 42004 | AI4: 42369 | AJ4: 42735
B5: EURO_LIST | D5: EUR
B6: EURO_CONVICTION | D6: EUR
B7: LEGAL_RATING | D7: EUR | E7: Coverage Suspended
B8: TARGET_PRICE | D8: EUR
B9: TP_PERIOD | D9: EUR
B10: NUM_SH1 | D10: EUR | E10: 404.73546
B11: FREE_FLOAT | D11: EUR | E11: 0.466
B12: BVPS_PUB | D12: EUR | M12: 10.963251 | P12: 10.404538 | S12: 10.40214 | V12: 9.3517537 | Y12: 10.900213 | AB12: 10.862539 | AE12: 11.912824
B13: DPS_PUB | D13: EUR | M13: 0.35968671 | P13: 0.22060785 | S13: 0.40045121 | V13: 0.25 | Y13: 0.38 | AB13: 0.5 | AE13: 0.62
B14: EBITDA_PUB | D14: EUR | M14: 1019 | P14: 884 | S14: 1069 | V14: 1182 | Y14: 1107 | AB14: 1313.5 | AE14: 1681
B15: EPS_PUB | D15: EUR | M15: 1.2240036 | P15: 0.4320298 | S15: 0.98837802 | V15: 0.63154612 | Y15: 0.94172621 | AB15: 1.2714211 | AE15: 1.5911628
B16: EV_ADJ_PUB | D16: EUR | F16: 0 | G16: 0 | H16: 0 | I16: 0 | J16: 0 | K16: 0 | M16: 486.3324 | N16: 0 | O16: 0 | P16: 838.35458 | Q16: 0 | S16: 1109.3546 | V16: 1064.3546 | Y16: 1044.3546 | AB16: 1100.3546 | AE16: 1144.3546
B17: NET_DEBT_PUB | D17: EUR | M17: 473 | P17: 419 | S17: 169 | V17: 635 | W17: -690 | X17: 498 | Y17: 498 | AB17: -24 | AE17: 997
B18: NI_PUB | D18: EUR | M18: 501 | P18: 177 | S18: 406 | V18: 256 | W18: 207 | X18: 169 | Y18: 376 | Z18: 261 | AA18: 247 | AB18: 508 | AC18: 317.05748 | AD18: 321.616 | AE18: 644
B19: EBIT_PUB | D19: EUR | M19: 762 | P19: 465 | S19: 706 | V19: 798 | W19: 347 | X19: 351 | Y19: 698 | Z19: 428 | AA19: 450 | AB19: 878 | AC19: 554.05748 | AD19: 632.616 | AE19: 1189
B20: PTP_PUB | D20: EUR | M20: 678 | P20: 391 | S20: 645 | V20: 605 | W20: 265 | X20: 227 | Y20: 492 | Z20: 337 | AA20: 369 | AB20: 706 | AC20: 442.05748 | AD20: 510.616 | AE20: 955
B21: REVS_PUB | D21: EUR | M21: 10577 | P21: 11329 | S21: 12003 | V21: 10329 | W21: 5149 | X21: 5299 | Y21: 10448 | Z21: 5197 | AA21: 5563 | AB21: 10760 | AC21: 5622 | AD21: 6114 | AE21: 11736
B22: EQ_PUB | D22: EUR | M22: 4736 | P22: 4512 | S22: 4505 | V22: 3874 | Y22: 4501 | AB22: 4705 | AE22: 5122
B23: SALES | D23: EUR | M23: 10577 | P23: 11329 | S23: 12003 | V23: 10329 | Y23: 10448 | AB23: 10760 | AE23: 11736
B24: COST_GD_SD | D24: EUR
B25: SEL_GL_AD | D25: EUR | F25: 0 | G25: 0 | H25: 0 | I25: 0 | J25: 0 | K25: 0 | L25: 0 | M25: 0 | N25: 0 | O25: 0 | P25: 0 | Q25: 0 | S25: 0
B26: OP_COST | D26: EUR | F26: 0 | G26: 0 | H26: 0 | I26: 0 | J26: 0 | K26: 0 | M26: -9558 | N26: 0 | O26: 0 | P26: -10445 | Q26: 0 | S26: -10934 | V26: -8708 | Y26: -8847 | AB26: -9040.5 | AE26: -9560
B27: RD_EXP | D27: EUR
B28: OTH_OP_INC_EXP | D28: EUR | F28: 0 | G28: 0 | H28: 0 | I28: 0 | J28: 0 | K28: 0 | N28: 0 | O28: 0 | Q28: 0 | V28: -439 | Y28: -494 | AB28: -406 | AE28: -495
B29: TOT_OPS_EXP_DDA | D29: EUR | M29: -9815 | P29: -10864 | S29: -11297 | V29: -9531 | Y29: -9750 | AB29: -9882 | AE29: -10547
B30: TOT_OPS_EXP | D30: EUR | M30: -9558 | P30: -10445 | S30: -10934 | V30: -9147 | Y30: -9341 | AB30: -9446.5 | AE30: -10055
B31: EBITDA_CALC | D31: EUR | M31: 1019 | P31: 884 | S31: 1069 | V31: 1182 | Y31: 1107 | AB31: 1313.5 | AE31: 1681
B32: DEPREC | D32: EUR | F32: 0 | G32: 0 | H32: 0 | I32: 0 | J32: 0 | K32: 0 | M32: -257 | N32: 0 | O32: 0 | P32: -306 | Q32: 0 | S32: -287 | V32: -278 | Y32: -279 | AB32: -291 | AE32: -321
B33: GOODWILL_AMORT | D33: EUR | F33: 0 | G33: 0 | H33: 0 | I33: 0 | J33: 0 | K33: 0 | N33: 0 | O33: 0 | P33: -113 | Q33: 0 | S33: -76 | V33: -106 | Y33: -130 | AB33: -144.5 | AE33: -171
B34: EBIT | D34: EUR | M34: 762 | P34: 465 | S34: 706 | V34: 798 | Y34: 698 | AB34: 878 | AE34: 1189
B35: INT_INC_IND | D35: EUR
B36: INT_EXP_IND | D36: EUR
B37: NET_INT_EXP | D37: EUR | M37: -87 | P37: -78 | S37: -65 | V37: -203 | Y37: -174 | AB37: -168 | AE37: -215
B38: ASSOCIATE | D38: EUR | F38: 0 | G38: 0 | H38: 0 | I38: 0 | J38: 0 | K38: 0 | L38: 0 | M38: 3 | N38: 0 | O38: 0 | P38: 4 | Q38: 0 | S38: 4 | V38: 10 | Y38: 3 | AB38: 9 | AE38: 10
B39: PROFIT_ON_DISP | D39: EUR | F39: 0 | G39: 0 | H39: 0 | I39: 0 | J39: 0 | K39: 0 | L39: 0 | M39: 0 | N39: 0 | O39: 0 | P39: 0 | Q39: 0 | S39: 0
B40: OTH_COST_INC | D40: EUR | F40: 0 | G40: 0 | H40: 0 | I40: 0 | J40: 0 | K40: 0 | L40: 0 | M40: 0 | N40: 0 | O40: 0 | P40: 0 | Q40: 0 | S40: 0 | AB40: -13 | AE40: -29
B41: PT_PROF | D41: EUR | M41: 678 | P41: 391 | S41: 645 | V41: 605 | Y41: 527 | AB41: 706 | AE41: 955
B42: PROV_INC_TAX | D42: EUR | M42: -170 | P42: -199 | S42: -224 | V42: -101 | Y42: -98 | AB42: -173 | AE42: -289
B43: INC_MINORITY | D43: EUR | F43: 0 | G43: 0 | H43: 0 | I43: 0 | J43: 0 | K43: 0 | M43: -7 | N43: 0 | O43: 0 | P43: -15 | Q43: 0 | S43: -15 | V43: -15 | Y43: -14 | AB43: -20 | AE43: -25
B44: NI_PRE_PREF | D44: EUR | M44: 501 | P44: 177 | S44: 406 | V44: 489 | Y44: 415 | AB44: 513 | AE44: 641
B45: PREF_DIV | D45: EUR | F45: 0 | G45: 0 | H45: 0 | I45: 0 | J45: 0 | K45: 0 | L45: 0 | M45: 0 | N45: 0 | O45: 0 | P45: 0 | Q45: 0 | S45: 0
B46: NET_EARNING | D46: EUR | M46: 501 | P46: 177 | S46: 406 | V46: 489 | Y46: 415 | AB46: 513 | AE46: 641
B47: TAX_EXC | D47: EUR | F47: 0 | G47: 0 | H47: 0 | I47: 0 | J47: 0 | K47: 0 | N47: 0 | O47: 0 | Q47: 0 | V47: -233
B48: NET_INC | D48: EUR | M48: 501 | P48: 177 | S48: 406 | V48: 256 | Y48: 415 | AB48: 513 | AE48: 641
B49: EPS | D49: EUR | M49: 1.2240036 | P49: 0.4320298 | S49: 0.98837802 | V49: 1.2063518 | Y49: 1.0394053 | AB49: 1.2839351 | AE49: 1.5837505
B50: EPS_FUL_DIL | D50: EUR | M50: 1.2207229 | P50: 0.43086725 | S50: 0.98780596 | V50: 1.2063518 | Y50: 1.0347028 | AB50: 1.2712729 | AE50: 1.5774982
B51: EPS_POST_BASIC | D51: EUR | M51: 1.2240036 | P51: 0.4320298 | S51: 0.98837802 | V51: 0.63154612 | Y51: 1.0394053 | AB51: 1.2839351 | AE51: 1.5837505
B52: FULLY_DIL_EPS | D52: EUR | M52: 1.2207229 | P52: 0.43086725 | S52: 0.98780596 | V52: 0.63154612 | Y52: 1.0347028 | AB52: 1.2712729 | AE52: 1.5774982
B53: COMMON_DIV_PAID | D53: EUR | M53: -150 | P53: -92 | S53: -167 | V53: -104 | Y53: -158 | AB53: -202 | AE53: -260
B54: DPS | D54: EUR | F54: 0 | G54: 0 | H54: 0 | I54: 0 | J54: 0 | K54: 0 | M54: 0.35968671 | N54: 0 | O54: 0 | P54: 0.22060785 | Q54: 0 | S54: 0.40045121 | V54: 0.25 | Y54: 0.38 | AB54: 0.5 | AE54: 0.62
B55: SH1 | D55: EUR | M55: 409.31254 | P55: 409.69396 | S55: 410.77401 | V55: 405.3544 | Y55: 399.26679 | AB55: 399.55292 | AE55: 404.73546
B56: DILUTE_SHARES | D56: EUR | M56: 410.41254 | P56: 410.79938 | S56: 411.0119 | V56: 405.3544 | Y56: 401.08134 | AB56: 403.53256 | AE56: 406.33962
B57: NON_OP_ADD | D57: EUR | M57: 417.02958 | P57: 417.02958 | S57: 417.02958 | V57: 399.17647 | Y57: 399.35 | AB57: 417.02958 | AE57: 417.02958
B58: ORG_NI | D58: EUR
B59: ORG_EPS | D59: EUR
B60: ORG_REV | D60: EUR
B61: ORG_REV_GRTH | D61: EUR
B62: LEASE_PAY | D62: EUR | F62: 0 | G62: 0 | H62: 0 | I62: 0 | J62: 0 | K62: 0 | L62: 0 | M62: 0 | N62: 0 | O62: 0 | P62: 0 | Q62: 0 | S62: 0
B63: LEASE_DEEM_INT | D63: EUR | F63: 0.333333 | G63: 0.333333 | H63: 0.333333 | I63: 0.333333 | J63: 0.333333 | K63: 0.333333 | L63: 0.333333 | M63: 0.333333 | N63: 0.333333 | O63: 0.333333 | P63: 0.333333 | Q63: 0.333333 | S63: 0.333333
B64: LEASE_DEEM_DEPR | D64: EUR | F64: 0.666667 | G64: 0.666667 | H64: 0.666667 | I64: 0.666667 | J64: 0.666667 | K64: 0.666667 | L64: 0.666667 | M64: 0.666667 | N64: 0.666667 | O64: 0.666667 | P64: 0.666667 | Q64: 0.666667 | S64: 0.666667
B65: NET_INT_CH | D65: EUR | F65: 0 | G65: 0 | H65: 0 | I65: 0 | J65: 0 | K65: 0 | N65: 0 | O65: 0 | Q65: 0
B66: ASSOCIATE_OP | D66: EUR | F66: 0 | G66: 0 | H66: 0 | I66: 0 | J66: 0 | K66: 0 | L66: 0 | M66: 0 | N66: 0 | O66: 0 | P66: 0 | Q66: 0 | S66: 0
B67: GW_AMORT | D67: EUR
B68: OTH_INT_AMORT | D68: EUR | F68: 0 | G68: 0 | H68: 0 | I68: 0 | J68: 0 | K68: 0 | L68: 0 | M68: 0 | N68: 0 | O68: 0 | P68: 0 | Q68: 0 | S68: 0
B69: MARGIN_TAX_RATE | D69: EUR | F69: 0 | G69: 0 | H69: 0 | I69: 0 | J69: 0 | K69: 0 | M69: 0.25073746 | N69: 0 | O69: 0 | P69: 0.50895141 | Q69: 0 | S69: 0.34728682 | V69: 0.16694215 | Y69: 0.19918699 | AB69: 0.24504249 | AE69: 0.3026178
B70: CASH_EQ | D70: EUR | F70: 0 | G70: 0 | H70: 0 | I70: 0 | J70: 0 | K70: 0 | M70: 936 | N70: 0 | O70: 0 | P70: 743 | Q70: 0 | S70: 730 | V70: 919 | Y70: 2080 | AB70: 2062 | AE70: 1431
B71: DEBTORS | D71: EUR | M71: 4052 | P71: 4218 | S71: 3926 | V71: 3881 | Y71: 3994 | AB71: 3921 | AE71: 5005
B72: STOCKS | D72: EUR | F72: 0 | G72: 0 | H72: 0 | I72: 0 | J72: 0 | K72: 0 | M72: 2904 | N72: 0 | O72: 0 | P72: 3240 | Q72: 0 | S72: 3420 | V72: 3673 | Y72: 3382 | AB72: 3508 | AE72: 3799
B73: OTH_CUR_ASS | D73: EUR | F73: 0 | G73: 0 | H73: 0 | I73: 0 | J73: 0 | K73: 0 | M73: 213 | N73: 0 | O73: 0 | P73: 219 | Q73: 0 | S73: 210 | V73: 330 | Y73: 309 | AB73: 444 | AE73: 494
B74: CUR_ASS | D74: EUR | F74: 0 | G74: 0 | H74: 0 | I74: 0 | J74: 0 | K74: 0 | M74: 8105 | N74: 0 | O74: 0 | P74: 8420 | Q74: 0 | S74: 8286 | V74: 8803 | Y74: 9765 | AB74: 9935 | AE74: 10729
B75: GR_FIX_ASS | D75: EUR | M75: 4772 | P75: 4871 | S75: 4881 | V75: 5238 | Y75: 5436 | AB75: 5750 | AE75: 6434
B76: ACC_DDA | D76: EUR | M76: -2974 | P76: -3045 | S76: -3034 | V76: -3131 | Y76: -3235 | AB76: -3497 | AE76: -3948
B77: NET_FIX_ASS | D77: EUR | F77: 0 | G77: 0 | H77: 0 | I77: 0 | J77: 0 | K77: 0 | M77: 1798 | N77: 0 | O77: 0 | P77: 1826 | Q77: 0 | S77: 1847 | V77: 2107 | Y77: 2201 | AB77: 2253 | AE77: 2486
B78: GR_INTANG | D78: EUR | F78: 0 | G78: 0 | H78: 0 | I78: 0 | J78: 0 | K78: 0 | M78: 4977 | N78: 0 | O78: 0 | P78: 5404 | Q78: 0 | S78: 5591 | V78: 6187 | Y78: 7048 | AB78: 7339 | AE78: 8923
B79: ACC_AMORT | D79: EUR | F79: 0 | G79: 0 | H79: 0 | I79: 0 | J79: 0 | K79: 0 | M79: -438 | P79: -759 | S79: -1049 | V79: -1319 | Y79: -1705 | AB79: -1911 | AE79: -2299
B80: NET_INTANG | D80: EUR | F80: 0 | G80: 0 | H80: 0 | I80: 0 | J80: 0 | K80: 0 | M80: 4539 | N80: 0 | O80: 0 | P80: 4645 | Q80: 0 | S80: 4542 | V80: 4868 | Y80: 5343 | AB80: 5428 | AE80: 6624
B81: FIX_ASS_INV | D81: EUR | F81: 0 | G81: 0 | H81: 0 | I81: 0 | J81: 0 | K81: 0 | L81: 0 | M81: 37 | N81: 0 | O81: 0 | P81: 32 | Q81: 0 | S81: 34 | V81: 244 | Y81: 238 | AB81: 236 | AE81: 253
B82: INV_SECUR | D82: EUR | F82: 0 | G82: 0 | H82: 0 | I82: 0 | J82: 0 | K82: 0 | N82: 0 | O82: 0 | Q82: 0
B83: OTH_LT_ASS | D83: EUR | F83: 0 | G83: 0 | H83: 0 | I83: 0 | J83: 0 | K83: 0 | M83: 1064 | N83: 0 | O83: 0 | P83: 1005 | Q83: 0 | S83: 1466 | V83: 814 | Y83: 622 | AB83: 659 | AE83: 610
B84: TOT_ASSET | D84: EUR | M84: 15543 | N84: 0 | O84: 0 | P84: 15928 | Q84: 0 | S84: 16175 | V84: 16836 | Y84: 18169 | AB84: 18511 | AE84: 20702
B85: ACC_PAY_GQ | D85: EUR | F85: 0 | G85: 0 | H85: 0 | I85: 0 | J85: 0 | K85: 0 | M85: 5898 | N85: 0 | O85: 0 | P85: 6390 | Q85: 0 | S85: 6517 | V85: 6786 | Y85: 6805 | AB85: 7236 | AE85: 8348
B86: SHORT_T_DEBT | D86: EUR | F86: 0 | G86: 0 | H86: 0 | I86: 0 | J86: 0 | K86: 0 | M86: 877 | N86: 0 | O86: 0 | P86: 699 | Q86: 0 | S86: 502 | V86: 1136 | Y86: 1367 | AB86: 568 | AE86: 998
B87: OTH_CUR_LIABS | D87: EUR | F87: 0 | G87: 0 | H87: 0 | I87: 0 | J87: 0 | K87: 0 | M87: 1156 | N87: 0 | O87: 0 | P87: 1274 | Q87: 0 | S87: 1771 | V87: 2089 | Y87: 1234 | AB87: 1637 | AE87: 1814
B88: SHORT_TERM_LIABS | D88: EUR | M88: 7931 | P88: 8363 | S88: 8790 | V88: 10011 | Y88: 9406 | AB88: 9441 | AE88: 11160
B89: LT_DEBT | D89: EUR | F89: 0 | G89: 0 | H89: 0 | I89: 0 | J89: 0 | K89: 0 | M89: 532 | N89: 0 | O89: 0 | P89: 463 | Q89: 0 | S89: 397 | V89: 418 | Y89: 1208 | AB89: 1483 | AE89: 1447
B90: OTH_LT_CRED_GQ | D90: EUR | F90: 0 | G90: 0 | H90: 0 | I90: 0 | J90: 0 | K90: 0 | M90: 2344 | N90: 0 | O90: 0 | P90: 2590 | Q90: 0 | S90: 2483 | V90: 2533 | Y90: 3054 | AB90: 2882 | AE90: 2973
B91: TOT_LT_LIAB | D91: EUR | M91: 2876 | P91: 3053 | S91: 2880 | V91: 2951 | Y91: 4262 | AB91: 4365 | AE91: 4420
B92: TOT_LIAB | D92: EUR | F92: 0 | G92: 0 | H92: 0 | I92: 0 | J92: 0 | K92: 0 | M92: 10807 | N92: 0 | O92: 0 | P92: 11416 | Q92: 0 | S92: 11670 | V92: 12962 | Y92: 13668 | AB92: 13806 | AE92: 15580
B93: PREF_SH | D93: EUR | F93: 0 | G93: 0 | H93: 0 | I93: 0 | J93: 0 | K93: 0 | L93: 0 | M93: 0 | N93: 0 | O93: 0 | P93: 0 | Q93: 0 | S93: 0
B94: ORD_SH_FUND | D94: EUR | F94: 0 | G94: 0 | H94: 0 | I94: 0 | J94: 0 | K94: 0 | M94: 4572 | N94: 0 | O94: 0 | P94: 4339 | Q94: 0 | S94: 4338 | V94: 3733 | Y94: 4353 | AB94: 4530 | AE94: 4968
B95: MINORITIES | D95: EUR | F95: 0 | G95: 0 | H95: 0 | I95: 0 | J95: 0 | K95: 0 | M95: 164 | N95: 0 | O95: 0 | P95: 173 | Q95: 0 | S95: 167 | V95: 141 | Y95: 148 | AB95: 175 | AE95: 154
B96: EQ | D96: EUR | M96: 4736 | P96: 4512 | S96: 4505 | V96: 3874 | Y96: 4501 | AB96: 4705 | AE96: 5122
B97: TOT_LIAB_EQ | D97: EUR | M97: 15543 | P97: 15928 | S97: 16175 | V97: 16836 | Y97: 18169 | AB97: 18511 | AE97: 20702
B98: BVPS | D98: EUR | M98: 10.963251 | P98: 10.404538 | S98: 10.40214 | V98: 9.3517537 | Y98: 10.900213 | AB98: 10.862539 | AE98: 11.912824
B99: NET_DEBT | D99: EUR | F99: 0 | G99: 0 | H99: 0 | I99: 0 | J99: 0 | K99: 0 | M99: 473 | N99: 0 | O99: 0 | P99: 419 | Q99: 0 | S99: 169 | V99: 635 | Y99: 498 | AB99: -24 | AE99: 997
B100: CAP_LEASES | D100: EUR | F100: 0 | G100: 0 | H100: 0 | I100: 0 | J100: 0 | K100: 0 | L100: 0 | M100: 0 | N100: 0 | O100: 0 | P100: 0 | Q100: 0 | S100: 0
B101: DEF_INC_TAX | D101: EUR | F101: 0 | G101: 0 | H101: 0 | I101: 0 | J101: 0 | K101: 0 | L101: 0 | M101: 0 | N101: 0 | O101: 0 | P101: 0 | Q101: 0 | S101: 0
...

Sheet Cover Page
A2: GOLDMAN SACHS
A3: GLOBAL INVESTMENT RESEARCH
A4: Multi-Industry
B6: SAF.PA
B7: Published as of | C7: 45919 | I7: Rating Suspended
B9: Team Contacts:
B10: Primary Analysts
B11: Sam Burgess, sam.burgess@gs.com, +44 20 7774-9651 Goldman Sachs International
B12: Supporting Analyst
B13: Jubril Moronfolu, jubril.x.moronfolu@gs.com, +44 20 7051-0985 Goldman Sachs International
B14: Milind Sikchi, milind.sikchi@gs.com, +1 332 245-7985, Goldman Sachs International

Sheet DCF Valuation
B4: Calendar year | C4: 2026 | D4: 2027 | E4: 2028 | F4: 2029 | G4: 2030 | H4: 2031 | I4: 2032 | J4: 2033 | K4: 2034 | L4: 2035 | O4: Adj. EBIT
B5: Adj. EBIT | C5: ='DCF Feed'!C4 -> 6014.9129 | D5: ='DCF Feed'!D4 -> 6844.9824 | E5: ='DCF Feed'!E4 -> 7604.1887 | F5: ='DCF Feed'!F4 -> 8050.4884 | G5: ='DCF Feed'!G4 -> 8490.6102 | O5: 3 | P5: 2025
B6: Tax Rate | C6: =-'DCF Feed'!C10 -> 0.25 | D6: =-'DCF Feed'!D10 -> 0.25 | E6: =-'DCF Feed'!E10 -> 0.25 | F6: =-'DCF Feed'!F10 -> 0.25 | G6: =-'DCF Feed'!G10 -> 0.25 | O6: =12-O5 -> 9 | P6: =+P5+1 -> 2026
B7: NOPAT | C7: =C5*(1-C6) -> 4511.1846 | D7: =D5*(1-D6) -> 5133.7368 | E7: =E5*(1-E6) -> 5703.1415 | F7: =F5*(1-F6) -> 6037.8663 | G7: =G5*(1-G6) -> 6367.9577
B8: D&A | C8: =INDEX('Income Statement'!192:192, MATCH('DCF Valuation'!C4,'Income Statement'!3:3,0)) -> 1819.1631 | D8: =INDEX('Income Statement'!192:192, MATCH('DCF Valuation'!D4,'Income Statement'!3:3,0)) -> 1935.1626 | E8: =INDEX('Income Statement'!192:192, MATCH('DCF Valuation'!E4,'Income Statement'!3:3,0)) -> 2098.9075 | F8: =INDEX('Income Statement'!192:192, MATCH('DCF Valuation'!F4,'Income Statement'!3:3,0)) -> 2201.9772 | G8: =INDEX('Income Statement'!192:192, MATCH('DCF Valuation'!G4,'Income Statement'!3:3,0)) -> 2308.5662 | O8: =(#REF!*0.3)+(C5*0.9) -> #REF!
B9: Change in working capital | C9: =INDEX('Cashflow Statement'!22:22, MATCH('DCF Valuation'!C4,'Cashflow Statement'!2:2,0)) -> 228.01264 | D9: =INDEX('Cashflow Statement'!22:22, MATCH('DCF Valuation'!D4,'Cashflow Statement'!2:2,0)) -> -54.587281 | E9: =INDEX('Cashflow Statement'!22:22, MATCH('DCF Valuation'!E4,'Cashflow Statement'!2:2,0)) -> -501.92972 | F9: =INDEX('Cashflow Statement'!22:22, MATCH('DCF Valuation'!F4,'Cashflow Statement'!2:2,0)) -> -444.89697 | G9: =INDEX('Cashflow Statement'!22:22, MATCH('DCF Valuation'!G4,'Cashflow Statement'!2:2,0)) -> -599.47322
B10: Capex & Intangibles | C10: =(INDEX('Cashflow Statement'!69:69, MATCH('DCF Valuation'!C4,'Cashflow Statement'!2:2,0)))+INDEX('Cashflow Statement'!70:70, MATCH('DCF Valuation'!C4,'Cashflow Statement'!2:2,0)) -> -2103.4318 | D10: =(INDEX('Cashflow Statement'!69:69, MATCH('DCF Valuation'!D4,'Cashflow Statement'!2:2,0)))+INDEX('Cashflow Statement'!70:70, MATCH('DCF Valuation'!D4,'Cashflow Statement'!2:2,0)) -> -2076.8236 | E10: =(INDEX('Cashflow Statement'!69:69, MATCH('DCF Valuation'!E4,'Cashflow Statement'!2:2,0)))+INDEX('Cashflow Statement'!70:70, MATCH('DCF Valuation'!E4,'Cashflow Statement'!2:2,0)) -> -1999.0147 | F10: =(INDEX('Cashflow Statement'!69:69, MATCH('DCF Valuation'!F4,'Cashflow Statement'!2:2,0)))+INDEX('Cashflow Statement'!70:70, MATCH('DCF Valuation'!F4,'Cashflow Statement'!2:2,0)) -> -1853.0033 | G10: =(INDEX('Cashflow Statement'!69:69, MATCH('DCF Valuation'!G4,'Cashflow Statement'!2:2,0)))+INDEX('Cashflow Statement'!70:70, MATCH('DCF Valuation'!G4,'Cashflow Statement'!2:2,0)) -> -1688.3971
B11: Sustainable FCF | C11: =C7+C8+C9+C10 -> 4454.9286 | D11: =D7+D8+D9+D10 -> 4937.4884 | E11: =E7+E8+E9+E10 -> 5301.1047 | F11: =F7+F8+F9+F10 -> 5941.9433 | G11: =G7+G8+G9+G10 -> 6388.6536 | H11: =G11*(1+H12) -> 6737.9225 | I11: =H11*(1+I12) -> 7064.7296 | J11: =I11*(1+J12) -> 7363.8157 | K11: =J11*(1+K12) -> 7630.1468 | L11: =K11*(1+L12) -> 7859.0512
B12: Annual growth | D12: ='DCF Feed'!D5 -> 0.13800192 | E12: ='DCF Feed'!E5 -> 0.11091429 | F12: ='DCF Feed'!F5 -> 0.058691293 | G12: ='DCF Feed'!G5 -> 0.054670199 | H12: =G12 -> 0.054670199 | I12: =H12+(($L$12-$H$12)/4) -> 0.048502649 | J12: =I12+(($L$12-$H$12)/4) -> 0.042335099 | K12: =J12+(($L$12-$H$12)/4) -> 0.03616755 | L12: =$D$33 -> 0.03
B13: WACC | D13: =$D$32 -> 0.07325 | E13: =$D$32 -> 0.07325 | F13: =$D$32 -> 0.07325 | G13: =$D$32 -> 0.07325 | H13: =$D$32 -> 0.07325 | I13: =$D$32 -> 0.07325 | J13: =$D$32 -> 0.07325 | K13: =$D$32 -> 0.07325 | L13: =$D$32 -> 0.07325
B14: Discount Factor | D14: 1 | E14: =D14+1 -> 2 | F14: =E14+1 -> 3 | G14: =F14+1 -> 4 | H14: =G14+1 -> 5 | I14: =H14+1 -> 6 | J14: =I14+1 -> 7 | K14: =J14+1 -> 8 | L14: =K14+1 -> 9
B15: Discounted FCF | D15: =D11/((1+D13)^D14) -> 4600.5017 | E15: =E11/((1+E13)^E14) -> 4602.1905 | F15: =F11/((1+F13)^F14) -> 4806.4653 | G15: =G11/((1+G13)^G14) -> 4815.1049 | H15: =H11/((1+H13)^H14) -> 4731.7471 | I15: =I11/((1+I13)^I14) -> 4622.641 | J15: =J11/((1+J13)^J14) -> 4489.4861 | K15: =K11/((1+K13)^K14) -> 4334.3674 | L15: =L11/((1+L13)^L14) -> 4159.7003 | M15: =SUM(C15:L15) -> 41162.204
B18: DCF Valuation
B19: Risk free rate | C19: % | D19: 0.035
B20: Equity Risk premium | C20: % | D20: 0.045
B22: Beta | C22: x | D22: 0.85
B23: Cost of equity | C23: % | D23: =D19+D22*(D20) -> 0.07325
B25: Cost of debt | C25: % | D25: 0.04
B26: Tax | C26: % | D26: =C6 -> 0.25
B27: Post tax cost of debt | C27: % | D27: =D25*(1-D26) -> 0.03
B29: MV Equity / (MV Equity + Net Debt) | C29: % | D29: 1
B30: Net Debt / (MV Equity + Net Debt) | C30: % | D30: 0
B32: WACC | C32: % | D32: =(D23*D29)+(D30*D27) -> 0.07325
B33: Terminal growth rate | C33: % | D33: 0.03
B35: DCF Valuation
B36: Sum of discounted cash flows | C36: EUR (mn) | D36: =M15 -> 41162.204
B37: Undiscounted value of TV | C37: EUR (mn) | D37: =L11/(D32-D33) -> 181712.17
B38: Discounted value of TV | C38: EUR (mn) | D38: =D37/(1+L13)^L14 -> 96178.043
B39: Enterprise value | C39: EUR (mn) | D39: =D36+D38 -> 137340.25
B40: Net cash (debt) and lease | C40: EUR (mn) | D40: ='DCF Feed'!C8 -> 3382.4906
B41: Pension underfunding | C41: EUR (mn) | D41: ='DCF Feed'!C9 -> -23
B42: Pension tax shield | C42: EUR (mn) | D42: =-D41*(D26) -> 5.75
B43: Equity value | C43: EUR (mn) | D43: =SUM(D39:D42) -> 140705.49
B44: Number of shares | C44: million | D44: ='DCF Feed'!C12 -> 411.74891
B45: Equity value per share | C45: EUR | D45: =ROUND(D43/D44,-1) -> 340

Sheet Sheet5

Sheet Sheet4

Sheet MigrationOutput_QP_SAF.PA
B2: Congratulations! You have successfully migrated | F2: =HYPERLINK("[cleanSafran model WIP.xlsx]SAF.PA_Exchange_Sheet!$A$1","SAF.PA_Exchange_Sheet") -> SAF.PA_Exchange_Sheet
B3: Please review non-migrated data on: | F3: =HYPERLINK("[cleanSafran model WIP.xlsx]QP_SAF.PA_migrated!$A$1","QP_SAF.PA_migrated") -> QP_SAF.PA_migrated
B5: Final cleanup Items
B6: Keyword | C6: Description | E6: Action

Sheet QP_SAF.PA_migrated
A1: Quantum submission sheet for SAF.PA | F1: 1998 | G1: 1999 | H1: 2000 | I1: 2001 | J1: 2002 | K1: 2003 | L1: 2004 | M1: 2005 | N1: 2006 H1 | O1: 2006 H2 | P1: 2006 | Q1: 2007 H1 | R1: 2007 H2 | S1: 2007 | T1: 2008 H1 | U1: 2008 H2 | V1: 2008 | W1: 2009 H1 | X1: 2009 H2 | Y1: 2009 | Z1: 2010 H1 | AA1: 2010 H2 | AB1: 2010 | AC1: 2011 H1 | AD1: 2011 H2 | AE1: 2011 | AF1: 2012 | AG1: 2013 | AH1: 2014 | AI1: 2015 | AJ1: 2016 | AK1: 2017 | AL1: 2018 | AM1: 2019 | AN1: 2020
F2: Actual | G2: Actual | H2: Actual | I2: Actual | J2: Actual | K2: Actual | L2: Actual | M2: Actual | N2: Actual | O2: Actual | P2: Actual | Q2: Actual | R2: Actual | S2: Actual | T2: Actual | U2: Actual | V2: Actual | W2: Actual | X2: Actual | Y2: Actual | Z2: Actual | AA2: Actual | AB2: Actual | AC2: Actual | AD2: Actual | AE2: Actual | AF2: Actual | AG2: Estimate | AH2: Estimate | AI2: Estimate | AJ2: Estimate | AK2: Estimate | AL2: Estimate | AM2: Estimate | AN2: Estimate
F3: 36160 | G3: 36525 | H3: 36891 | I3: 37256 | J3: 37621 | K3: 37986 | L3: 38352 | M3: 38717 | N3: 38898 | O3: 39082 | P3: 39082 | Q3: 39263 | R3: 39447 | S3: 39447 | T3: 39629 | U3: 39813 | V3: 39813 | W3: 39994 | X3: 40178 | Y3: 40178 | Z3: 40359 | AA3: 40543 | AB3: 40543 | AC3: 40724 | AD3: 40908 | AE3: 40908 | AF3: 41274 | AG3: 41639 | AH3: 42004 | AI3: 42369 | AJ3: 42735 | AK3: 43100 | AL3: 43465 | AM3: 43830 | AN3: 44196
A5: Reference data | D5: #0
B6: Ticker | C6: Ticker_1 | E6: SAF.PA
B7: Company name | C7: Company name | E7: Safran
B8: Interim type | C8: Interim type | E8: Semiannual
B9: Reporting currency | C9: Reporting currency | E9: EUR
B10: Publishing currency | C10: Publishing currency | E10: EUR
B11: Pricing currency | C11: Pricing currency_1 | E11: EUR
A13: General Information | D13: #10
B14: Pan Europe Investment List | C14: EURO_LIST
B15: Pan Europe Conviction List | C15: EURO_CONVICTION
B16: Legal rating | C16: LEGAL_RATING
B17: Target price | C17: TARGET_PRICE | D17: EUR
B18: Target price period | C18: TP_PERIOD
B19: Current shares outstanding (mn) | C19: NUM_SH1
B20: Free float | C20: FREE_FLOAT
A22: Publishing Items | D22: #20
B23: Book value per share, BVPS (Pub) | C23: BVPS_PUB | D23: EUR | AK23: =AK116/AK75 -> #REF! | AL23: =AL116/AL75 -> #REF! | AM23: =AM116/AM75 -> #REF! | AN23: =AN116/AN75 -> #REF!
B24: DPS, dividend per share (Pub) | C24: DPS_PUB | D24: EUR | AK24: =#REF! -> #REF! | AL24: =#REF! -> #REF! | AM24: =#REF! -> #REF! | AN24: =#REF! -> #REF!
B25: EBITDA (Pub) | C25: EBITDA_PUB | D25: EUR | AK25: =#REF! -> #REF! | AL25: =#REF! -> #REF! | AM25: =#REF! -> #REF! | AN25: =#REF! -> #REF! | AO25: CH: GS A&D standard EBITDA (company defined underlying EBIT exclusing any additional depreciation, amortisation or impairments)
B26: EPS (Pub) | C26: EPS_PUB | D26: EUR | AK26: =#REF! -> #REF! | AL26: =#REF! -> #REF! | AM26: =#REF! -> #REF! | AN26: =#REF! -> #REF!
B27: EV adjustment (Pub) | C27: EV_ADJ_PUB | D27: EUR
B28: Long-term EPS growth estimate (Pub)
B29: Net debt (Pub) | C29: NET_DEBT_PUB | D29: EUR | AK29: =#REF! -> #REF! | AL29: =#REF! -> #REF! | AM29: =#REF! -> #REF! | AN29: =#REF! -> #REF!
B30: Net income (Pub) | C30: NI_PUB | D30: EUR | AK30: =#REF! -> #REF! | AL30: =#REF! -> #REF! | AM30: =#REF! -> #REF! | AN30: =#REF! -> #REF!
B31: EBIT, operating profit (Pub) | C31: EBIT_PUB | D31: EUR | AK31: =#REF! -> #REF! | AL31: =#REF! -> #REF! | AM31: =#REF! -> #REF! | AN31: =#REF! -> #REF!
B32: Pre-tax profit (Pub) | C32: PTP_PUB | D32: EUR | AK32: =#REF! -> #REF! | AL32: =#REF! -> #REF! | AM32: =#REF! -> #REF! | AN32: =#REF! -> #REF!
B33: Sales, revenue (Pub) | C33: REVS_PUB | D33: EUR | AK33: =#REF! -> #REF! | AL33: =#REF! -> #REF! | AM33: =#REF! -> #REF! | AN33: =#REF! -> #REF!
B34: Total shareholders' equity (Pub) | C34: EQ_PUB | D34: EUR | AK34: =AK116 -> #REF! | AL34: =AL116 -> #REF! | AM34: =AM116 -> #REF! | AN34: =AN116 -> #REF!
A36: Other & Corporate Income Statement | D36: #29
B37: EBITDA (Pub) | D37: EUR | M37: 724
B38: Pre-tax profit (Pub) | D38: EUR | M38: 383
B39: Net income (Pub) | D39: EUR | M39: 279.96755
B40: EPS (Pub) | D40: EUR | M40: 0.68399457
A42: Income Statement | D42: #30
B43: Sales, net revenue | C43: SALES | D43: EUR | AK43: =#REF! -> #REF! | AL43: =#REF! -> #REF! | AM43: =#REF! -> #REF! | AN43: =#REF! -> #REF!
B44: Cost of goods sold, COGS | C44: COST_GD_SD | D44: EUR
B45: SG&A, selling, general and admin. expense | C45: SEL_GL_AD | D45: EUR
B46: Total operating expense | C46: OP_COST | D46: EUR | AK46: =AK51-AK48-AK43 -> #REF! | AL46: =AL51-AL48-AL43 -> #REF! | AM46: =AM51-AM48-AM43 -> #REF! | AN46: =AN51-AN48-AN43 -> #REF!
B47: R&D expense | C47: RD_EXP | D47: EUR | AK47: =-#REF! -> #REF! | AL47: =-#REF! -> #REF! | AM47: =-#REF! -> #REF! | AN47: =-#REF! -> #REF!
B48: Other operating income/(expense) (incl. leases) | C48: OTH_OP_INC_EXP | D48: EUR
B49: Total operating expense (incl. D&A) | C49: TOT_OPS_EXP_DDA | D49: EUR | AK49: =AK46+AK48+AK52+AK53 -> #REF! | AL49: =AL46+AL48+AL52+AL53 -> #REF! | AM49: =AM46+AM48+AM52+AM53 -> #REF! | AN49: =AN46+AN48+AN52+AN53 -> #REF!
B50: Total operating expense (excl. D&A) | C50: TOT_OPS_EXP | D50: EUR | AK50: =AK46+AK48 -> #REF! | AL50: =AL46+AL48 -> #REF! | AM50: =AM46+AM48 -> #REF! | AN50: =AN46+AN48 -> #REF!
B51: EBITDA | C51: EBITDA_CALC | D51: EUR | AK51: =AK25 -> #REF! | AL51: =AL25 -> #REF! | AM51: =AM25 -> #REF! | AN51: =AN25 -> #REF!
B52: Depreciation | C52: DEPREC | D52: EUR | AK52: =-#REF! -> #REF! | AL52: =-#REF! -> #REF! | AM52: =-#REF! -> #REF! | AN52: =-#REF! -> #REF!
B53: Amortization | C53: GOODWILL_AMORT | D53: EUR | AK53: =-#REF!-#REF! -> #REF! | AL53: =-#REF!-#REF! -> #REF! | AM53: =-#REF!-#REF! -> #REF! | AN53: =-#REF!-#REF! -> #REF! | AO53: CH: This includes impairment charges (to reconcile between GS EBITDA (which excludes impairments) and company defined underlying EBIT which includes impairment charges)
B54: EBIT, operating profit | C54: EBIT | D54: EUR | AK54: =AK51+AK52+AK53 -> #REF! | AL54: =AL51+AL52+AL53 -> #REF! | AM54: =AM51+AM52+AM53 -> #REF! | AN54: =AN51+AN52+AN53 -> #REF!
B55: Interest income | C55: INT_INC_IND | D55: EUR
B56: Interest expense | C56: INT_EXP_IND | D56: EUR
B57: Net interest income/(expense) | C57: NET_INT_EXP | D57: EUR | AK57: =#REF! -> #REF! | AL57: =#REF! -> #REF! | AM57: =#REF! -> #REF! | AN57: =#REF! -> #REF!
B58: Income/(loss) from unconsolidated subs & associates | C58: ASSOCIATE | D58: EUR | AK58: =#REF! -> #REF! | AL58: =#REF! -> #REF! | AM58: =#REF! -> #REF! | AN58: =#REF! -> #REF!
B59: Profit/(loss) on disposals of assets, pre-tax | C59: PROFIT_ON_DISP | D59: EUR
B60: Other non-ops income/(expense) | C60: OTH_COST_INC | D60: EUR
B61: Pre-tax profit | C61: PT_PROF | D61: EUR | AK61: =AK54+AK57+AK58 -> #REF! | AL61: =AL54+AL57+AL58 -> #REF! | AM61: =AM54+AM57+AM58 -> #REF! | AN61: =AN54+AN57+AN58 -> #REF!
B62: Provision for income tax | C62: PROV_INC_TAX | D62: EUR | AK62: =#REF! -> #REF! | AL62: =#REF! -> #REF! | AM62: =#REF! -> #REF! | AN62: =#REF! -> #REF!
B63: Minority interest | C63: INC_MINORITY | D63: EUR | AK63: =#REF! -> #REF! | AL63: =#REF! -> #REF! | AM63: =#REF! -> #REF! | AN63: =#REF! -> #REF!
B64: Net income (pre-preferred dividends) | C64: NI_PRE_PREF | D64: EUR | AK64: =AK61+AK62+AK63 -> #REF! | AL64: =AL61+AL62+AL63 -> #REF! | AM64: =AM61+AM62+AM63 -> #REF! | AN64: =AN61+AN62+AN63 -> #REF!
B65: Preferred dividends | C65: PREF_DIV | D65: EUR
B66: Net income (pre-exceptionals) | C66: NET_EARNING | D66: EUR | AK66: =AK64+AK65 -> #REF! | AL66: =AL64+AL65 -> #REF! | AM66: =AM64+AM65 -> #REF! | AN66: =AN64+AN65 -> #REF!
B67: Post-tax exceptionals | C67: TAX_EXC | D67: EUR | AK67: =#REF! -> #REF! | AL67: =#REF! -> #REF! | AM67: =#REF! -> #REF! | AN67: =#REF! -> #REF! | AO67: CH: Income from discontinued operations
B68: Net income (post-exceptionals) | C68: NET_INC | D68: EUR | AK68: =AK66+AK67 -> #REF! | AL68: =AL66+AL67 -> #REF! | AM68: =AM66+AM67 -> #REF! | AN68: =AN66+AN67 -> #REF!
B69: EPS (pre-exceptionals, basic) | C69: EPS | D69: EUR | AK69: =AK66/AK75 -> #REF! | AL69: =AL66/AL75 -> #REF! | AM69: =AM66/AM75 -> #REF! | AN69: =AN66/AN75 -> #REF!
B70: EPS (pre-exceptionals, diluted) | C70: EPS_FUL_DIL | D70: EUR | AK70: =AK66/AK76 -> #REF! | AL70: =AL66/AL76 -> #REF! | AM70: =AM66/AM76 -> #REF! | AN70: =AN66/AN76 -> #REF!
B71: EPS (post-exceptionals, basic) | C71: EPS_POST_BASIC | D71: EUR | AK71: =AK68/AK75 -> #REF! | AL71: =AL68/AL75 -> #REF! | AM71: =AM68/AM75 -> #REF! | AN71: =AN68/AN75 -> #REF!
B72: EPS (post-exceptionals, diluted) | C72: FULLY_DIL_EPS | D72: EUR | AK72: =AK68/AK76 -> #REF! | AL72: =AL68/AL76 -> #REF! | AM72: =AM68/AM76 -> #REF! | AN72: =AN68/AN76 -> #REF!
B73: Common dividends paid | C73: COMMON_DIV_PAID | D73: EUR | AK73: =-(#REF!*#REF!)/1000 -> #REF! | AL73: =-(#REF!*#REF!)/1000 -> #REF! | AM73: =-(#REF!*#REF!)/1000 -> #REF! | AN73: =-(#REF!*#REF!)/1000 -> #REF!
B74: DPS, dividend per share | C74: DPS | D74: EUR | AK74: =#REF! -> #REF! | AL74: =#REF! -> #REF! | AM74: =#REF! -> #REF! | AN74: =#REF! -> #REF!
B75: Weighted average shares outstanding, basic | C75: SH1 | AK75: =#REF!/1000 -> #REF! | AL75: =#REF!/1000 -> #REF! | AM75: =#REF!/1000 -> #REF! | AN75: =#REF!/1000 -> #REF!
B76: Diluted average shares outstanding (mn) | C76: DILUTE_SHARES | AK76: =#REF!/1000 -> #REF! | AL76: =#REF!/1000 -> #REF! | AM76: =#REF!/1000 -> #REF! | AN76: =#REF!/1000 -> #REF!
B77: Period-end shares outstanding | C77: NON_OP_ADD | AK77: =#REF!/1000 -> #REF! | AL77: =#REF!/1000 -> #REF! | AM77: =#REF!/1000 -> #REF! | AN77: =#REF!/1000 -> #REF!
A79: Additional Income Statement Items | D79: #31
B80: Lease payments | C80: LEASE_PAY | D80: EUR
B81: Lease payments (deemed interest portion) | C81: LEASE_DEEM_INT | D81: EUR
B82: Lease payments (deemed depreciation portion) | C82: LEASE_DEEM_DEPR | D82: EUR
B83: Gross interest charge | C83: NET_INT_CH | D83: EUR
B84: Income from associates (operating) | C84: ASSOCIATE_OP | D84: EUR
B85: Goodwill amortization | C85: GW_AMORT | D85: EUR
B86: Other intangible amortization | C86: OTH_INT_AMORT | D86: EUR
B87: Marginal tax rate | C87: MARGIN_TAX_RATE | AK87: =1-#REF! -> #REF! | AL87: =1-#REF! -> #REF! | AM87: =1-#REF! -> #REF! | AN87: =1-#REF! -> #REF!
A89: Balance Sheet | D89: #40
B90: Cash & cash equivalents | C90: CASH_EQ | D90: EUR | AK90: =#REF! -> #REF! | AL90: =#REF! -> #REF! | AM90: =#REF! -> #REF! | AN90: =#REF! -> #REF!
B91: Accounts receivable | C91: DEBTORS | D91: EUR | AK91: =#REF! -> #REF! | AL91: =#REF! -> #REF! | AM91: =#REF! -> #REF! | AN91: =#REF! -> #REF!
B92: Inventory | C92: STOCKS | D92: EUR | AK92: =#REF! -> #REF! | AL92: =#REF! -> #REF! | AM92: =#REF! -> #REF! | AN92: =#REF! -> #REF!
B93: Other current assets | C93: OTH_CUR_ASS | D93: EUR | AK93: =AK94-AK92-AK91 -> #REF! | AL93: =AL94-AL92-AL91 -> #REF! | AM93: =AM94-AM92-AM91 -> #REF! | AN93: =AN94-AN92-AN91 -> #REF!
B94: Total current assets | C94: CUR_ASS | D94: EUR | AK94: =#REF! -> #REF! | AL94: =#REF! -> #REF! | AM94: =#REF! -> #REF! | AN94: =#REF! -> #REF!
B95: Gross fixed assets, PP&E | C95: GR_FIX_ASS | D95: EUR | AK95: =#REF! -> #REF! | AL95: =#REF! -> #REF! | AM95: =#REF! -> #REF! | AN95: =#REF! -> #REF!
B96: Accumulated depreciation | C96: ACC_DDA | D96: EUR | AK96: =AK97-AK95 -> #REF! | AL96: =AL97-AL95 -> #REF! | AM96: =AM97-AM95 -> #REF! | AN96: =AN97-AN95 -> #REF!
B97: Net PP&E | C97: NET_FIX_ASS | D97: EUR | AK97: =#REF! -> #REF! | AL97: =#REF! -> #REF! | AM97: =#REF! -> #REF! | AN97: =#REF! -> #REF!
B98: Gross intangibles | C98: GR_INTANG | D98: EUR | AK98: =#REF! -> #REF! | AL98: =#REF! -> #REF! | AM98: =#REF! -> #REF! | AN98: =#REF! -> #REF!
B99: Accumulated amortization | C99: ACC_AMORT | D99: EUR | AK99: =AK100-AK98 -> #REF! | AL99: =AL100-AL98 -> #REF! | AM99: =AM100-AM98 -> #REF! | AN99: =AN100-AN98 -> #REF!
B100: Net intangible assets | C100: NET_INTANG | D100: EUR | AK100: =#REF! -> #REF! | AL100: =#REF! -> #REF! | AM100: =#REF! -> #REF! | AN100: =#REF! -> #REF!
B101: Equity method investments | C101: FIX_ASS_INV | D101: EUR | AK101: =#REF! -> #REF! | AL101: =#REF! -> #REF! | AM101: =#REF! -> #REF! | AN101: =#REF! -> #REF!
B102: Investments in securities | C102: INV_SECUR | D102: EUR
B103: Other long-term assets | C103: OTH_LT_ASS | D103: EUR | AK103: =AK104-AK97-AK100-AK101-AK102-AK94 -> #REF! | AL103: =AL104-AL97-AL100-AL101-AL102-AL94 -> #REF! | AM103: =AM104-AM97-AM100-AM101-AM102-AM94 -> #REF! | AN103: =AN104-AN97-AN100-AN101-AN102-AN94 -> #REF!
B104: Total assets | C104: TOT_ASSET | D104: EUR | AK104: =AK94+#REF! -> #REF! | AL104: =AL94+#REF! -> #REF! | AM104: =AM94+#REF! -> #REF! | AN104: =AN94+#REF! -> #REF!
B105: Accounts payable | C105: ACC_PAY_GQ | D105: EUR | AK105: =-#REF! -> #REF! | AL105: =-#REF! -> #REF! | AM105: =-#REF! -> #REF! | AN105: =-#REF! -> #REF!
B106: Short-term debt | C106: SHORT_T_DEBT | D106: EUR | AK106: =-#REF! -> #REF! | AL106: =-#REF! -> #REF! | AM106: =-#REF! -> #REF! | AN106: =-#REF! -> #REF!
B107: Other current liabilities | C107: OTH_CUR_LIABS | D107: EUR
...

Sheet DCF
B1: =C34 -> 300 | Z1: SAF.PA
B2: Valuation date | C2: 45918
B3: Explicit growth (EBIT) | C3: ='DCF Feed'!H4 -> 0.1039199
B4: Mid-term growth | C4: 0.1
B5: Long term growth | C5: 0.03
B6: Discount rate | C6: 0.09
B7: Tax rate | C7: =-'DCF Feed'!E10 -> 0.25
B8: Cash conversion | C8: 1.05
B9: EV/EBIT | C9: =N19*(1-C7) -> 22.912496
B12: Calendar year | C12: =YEAR(TODAY()) -> 2025 | D12: =C12+1 -> 2026 | E12: =D12+1 -> 2027 | F12: =E12+1 -> 2028 | G12: =F12+1 -> 2029 | H12: =G12+1 -> 2030 | I12: =H12+1 -> 2031 | J12: =I12+1 -> 2032 | K12: =J12+1 -> 2033 | ... M12: =L12+1 -> 2035 | N12: Terminal value
C13: 0 | D13: =C13+1 -> 1 | E13: =D13+1 -> 2 | F13: =E13+1 -> 3 | G13: =F13+1 -> 4 | H13: =G13+1 -> 5 | I13: =H13+1 -> 6 | J13: =I13+1 -> 7 | K13: =J13+1 -> 8 | ... M13: =L13+1 -> 10
B14: =C2+365 -> 46283 | C14: 45809 | D14: =C14+365 -> 46174 | E14: =D14+365 -> 46539 | F14: =E14+365 -> 46904 | G14: =F14+365 -> 47269 | H14: =G14+365 -> 47634 | I14: =H14+365 -> 47999 | J14: =I14+365 -> 48364 | K14: =J14+365 -> 48729 | ... M14: =L14+365 -> 49459
B15: Cumulative growth | C15: 1 | D15: =C15*(1+D16) -> 1.1613904 | E15: =D15*(1+E16) -> 1.3216646 | F15: =E15*(1+F16) -> 1.468256 | G15: =F15*(1+G16) -> 1.5544299 | H15: =C15*(1+C3)^5 -> 1.6394109 | I15: =H15*(1+I16) -> 1.803352 | J15: =I15*(1+J16) -> 1.9521285 | K15: =J15*(1+K16) -> 2.0790169 | L15: =K15*(1+L16) -> 2.1777702 | M15: =L15*(1+M16) -> 2.2431033 | N15: =M15/(C6-C5) -> 37.385054
B16: Annual growth | D16: =INDEX('DCF Feed'!5:5,MATCH(DCF!D12,'DCF Feed'!1:1,0)) -> 0.16139044 | E16: =INDEX('DCF Feed'!5:5,MATCH(DCF!E12,'DCF Feed'!1:1,0)) -> 0.13800192 | F16: =INDEX('DCF Feed'!5:5,MATCH(DCF!F12,'DCF Feed'!1:1,0)) -> 0.11091429 | G16: =INDEX('DCF Feed'!5:5,MATCH(DCF!G12,'DCF Feed'!1:1,0)) -> 0.058691293 | H16: =INDEX('DCF Feed'!5:5,MATCH(DCF!H12,'DCF Feed'!1:1,0)) -> 0.054670199 | I16: =$C$4 -> 0.1 | J16: =I16+(($M$16-$I$16)/4) -> 0.0825 | K16: =J16+(($M$16-$I$16)/4) -> 0.065 | L16: =K16+(($M$16-$I$16)/4) -> 0.0475 | M16: =$C$5 -> 0.03
B17: Cash conversion | D17: =INDEX('DCF Feed'!7:7,MATCH(DCF!D12,'DCF Feed'!1:1,0)) -> 0.95509426 | E17: =INDEX('DCF Feed'!7:7,MATCH(DCF!E12,'DCF Feed'!1:1,0)) -> 0.97572869 | F17: =INDEX('DCF Feed'!7:7,MATCH(DCF!F12,'DCF Feed'!1:1,0)) -> 0.95005885 | G17: =INDEX('DCF Feed'!7:7,MATCH(DCF!G12,'DCF Feed'!1:1,0)) -> 0.99026338 | H17: =INDEX('DCF Feed'!7:7,MATCH(DCF!H12,'DCF Feed'!1:1,0)) -> 1.00393 | I17: =$C$8 -> 1.05 | J17: =$C$8 -> 1.05 | K17: =$C$8 -> 1.05 | L17: =$C$8 -> 1.05 | M17: =$C$8 -> 1.05
B18: Discounted value | D18: =1/(1+$C$6)^((D14-$B$14)/365) -> 1.0260693 | E18: =1/(1+$C$6)^((E14-$B$14)/365) -> 0.94134795 | F18: =1/(1+$C$6)^((F14-$B$14)/365) -> 0.86362197 | G18: =1/(1+$C$6)^((G14-$B$14)/365) -> 0.79231374 | H18: =1/(1+$C$6)^((H14-$B$14)/365) -> 0.72689334 | I18: =1/(1+$C$6)^((I14-$B$14)/365) -> 0.66687462 | J18: =1/(1+$C$6)^((J14-$B$14)/365) -> 0.61181158 | K18: =1/(1+$C$6)^((K14-$B$14)/365) -> 0.56129503 | ... M18: =1/(1+$C$6)^((M14-$B$14)/365) -> 0.47243079
B19: PV | D19: =D15*D17*D18 -> 1.1381543 | E19: =E15*E17*E18 -> 1.2139492 | F19: =F15*F17*F18 -> 1.2046919 | G19: =G15*G17*G18 -> 1.2196046 | H19: =H15*H17*H18 -> 1.1963601 | I19: =I15*I17*I18 -> 1.2627401 | J19: =J15*J17*J18 -> 1.2540516 | K19: =K15*K17*K18 -> 1.2252889 | L19: =L15*L17*L18 -> 1.1775139 | M19: =(M15+N15)*M17*M18 -> 19.65764 | N19: =SUM(D19:M19) -> 30.549995
B24: Year | C24: =C12 -> 2025
B25: Target EV/EBIT | C25: =C9 -> 22.912496
B26: EBIT | C26: =INDEX('DCF Feed'!4:4,MATCH(DCF!$C$24,'DCF Feed'!$1:$1,0)) -> 5179.0618
B27: Target EV | C27: =C25*C26 -> 118665.23
B28: Net Cash (Debt) | C28: ='DCF Feed'!B8 -> 2168.7677
B29: Other
B30: Pension underfunding | C30: =INDEX('DCF Feed'!9:9,MATCH(DCF!C24,'DCF Feed'!1:1,0)) -> -23
B31: Pension tax shield | C31: =-C30*C7 -> 5.75
B32: Target Market Cap | C32: =SUM(C27:C31) -> 120816.75
B33: Number of shares | C33: ='DCF Feed'!E12 -> 402.77548
B34: Target price | C34: =MROUND(C32/C33,1) -> 300
B35: Current Share Price | C35: Error: RTD method of WorksheetFunction class failed
B36: Upside/(Downside) | C36: =C34/C35-1 -> #VALUE!
B39: Share Price | D39: WACC
C40: =$C$34 -> 300 | D40: =E40-0.5% -> 0.08 | E40: =F40-0.5% -> 0.085 | F40: 0.09 | G40: =F40+0.5% -> 0.095 | H40: =G40+0.5% -> 0.1
B41: 5Yr EBIT CAGR | C41: =C42-2% -> 0.0639199 | D41: 307 | E41: 280 | F41: 258 | G41: 239 | H41: 223
C42: =C43-2% -> 0.0839199 | D42: 331 | E42: 302 | F42: 278 | G42: 258 | H42: 240
B43: Explicit PROF Grow | C43: 0.1039199 | D43: 358 | E43: 326 | F43: 300 | G43: 278 | H43: 258
C44: =C43+2% -> 0.1239199 | D44: 387 | E44: 352 | F44: 323 | G44: 299 | H44: 278
C45: =C44+2% -> 0.1439199 | D45: 418 | E45: 380 | F45: 348 | G45: 322 | H45: 299
D48: Cash Conversion Ratio | F48: CC
C49: =$C$34 -> 300 | D49: =E49-10% -> 0.85 | E49: =F49-10% -> 0.95 | F49: 1.05 | G49: =F49+10% -> 1.15 | H49: =G49+10% -> 1.25
B50: 5Yr EBIT CAGR | C50: =C51-3% -> 0.0439199 | D50: 205 | E50: 222 | F50: 239 | G50: 256 | H50: 274
C51: =C52-3% -> 0.0739199 | D51: 229 | E51: 248 | F51: 268 | G51: 288 | H51: 307
B52: Explicit PROF Grow | C52: 0.1039199 | D52: 255 | E52: 277 | F52: 300 | G52: 323 | H52: 345
C53: =C52+3% -> 0.1339199 | D53: 284 | E53: 310 | F53: 336 | G53: 361 | H53: 387
C54: =C53+3% -> 0.1639199 | D54: 316 | E54: 346 | F54: 375 | G54: 405 | H54: 434

Sheet DCF Feed
A1: €mn | B1: 2025 | C1: =B1+1 -> 2026 | D1: =C1+1 -> 2027 | E1: =D1+1 -> 2028 | F1: =E1+1 -> 2029 | G1: =F1+1 -> 2030 | H1: 5yr. CAGR
A2: Sales | B2: =INDEX('Income Statement'!39:39,MATCH(B1,'Income Statement'!38:38,0)) -> 30995.967 | C2: =INDEX('Income Statement'!39:39,MATCH(C1,'Income Statement'!38:38,0)) -> 34520.707 | D2: =INDEX('Income Statement'!39:39,MATCH(D1,'Income Statement'!38:38,0)) -> 38170.591 | E2: =INDEX('Income Statement'!39:39,MATCH(E1,'Income Statement'!38:38,0)) -> 41400.419 | F2: =INDEX('Income Statement'!39:39,MATCH(F1,'Income Statement'!38:38,0)) -> 43433.442 | G2: =INDEX('Income Statement'!39:39,MATCH(G1,'Income Statement'!38:38,0)) -> 45535.884 | H2: =(G2/B2)^(1/5)-1 -> 0.079965089
A3: Sales growth | C3: =C2/B2-1 -> 0.11371608 | D3: =D2/C2-1 -> 0.10573028 | E3: =E2/D2-1 -> 0.084615614 | F3: =F2/E2-1 -> 0.049106341 | G3: =G2/F2-1 -> 0.048406068
A4: Adj. EBIT | B4: =INDEX('Income Statement'!74:74,MATCH(B1,'Income Statement'!$38:$38,0)) -> 5179.0618 | C4: =INDEX('Income Statement'!74:74,MATCH(C1,'Income Statement'!$38:$38,0)) -> 6014.9129 | D4: =INDEX('Income Statement'!74:74,MATCH(D1,'Income Statement'!$38:$38,0)) -> 6844.9824 | E4: =INDEX('Income Statement'!74:74,MATCH(E1,'Income Statement'!$38:$38,0)) -> 7604.1887 | F4: =INDEX('Income Statement'!74:74,MATCH(F1,'Income Statement'!$38:$38,0)) -> 8050.4884 | G4: =INDEX('Income Statement'!74:74,MATCH(G1,'Income Statement'!$38:$38,0)) -> 8490.6102 | H4: =(G4/B4)^(1/5)-1 -> 0.1039199
A5: Growth | C5: =C4/B4-1 -> 0.16139044 | D5: =D4/C4-1 -> 0.13800192 | E5: =E4/D4-1 -> 0.11091429 | F5: =F4/E4-1 -> 0.058691293 | G5: =G4/F4-1 -> 0.054670199
A6: GS Defined Op Cash Flow | B6: =INDEX('Cashflow Statement'!71:71, MATCH('DCF Feed'!B1,'Cashflow Statement'!2:2,0)) -> 4768.3913 | C6: =INDEX('Cashflow Statement'!71:71, MATCH('DCF Feed'!C1,'Cashflow Statement'!2:2,0)) -> 5744.8087 | D6: =INDEX('Cashflow Statement'!71:71, MATCH('DCF Feed'!D1,'Cashflow Statement'!2:2,0)) -> 6678.8457 | E6: =INDEX('Cashflow Statement'!71:71, MATCH('DCF Feed'!E1,'Cashflow Statement'!2:2,0)) -> 7224.4268 | F6: =INDEX('Cashflow Statement'!71:71, MATCH('DCF Feed'!F1,'Cashflow Statement'!2:2,0)) -> 7972.1038 | G6: =INDEX('Cashflow Statement'!71:71, MATCH('DCF Feed'!G1,'Cashflow Statement'!2:2,0)) -> 8523.9782 | H6: =(G6/B6)^(1/5)-1 -> 0.12319222
A7: Cash Conversion | B7: =B6/B4 -> 0.92070562 | C7: =C6/C4 -> 0.95509426 | D7: =D6/D4 -> 0.97572869 | E7: =E6/E4 -> 0.95005885 | F7: =F6/F4 -> 0.99026338 | G7: =G6/G4 -> 1.00393 | H7: =AVERAGE(B7:G7) -> 0.96596346
A8: Net Cash (Debt) | B8: =INDEX('Balance Sheet'!$93:$93,MATCH('DCF Feed'!B1,'Balance Sheet'!$88:$88,0)) -> 2168.7677 | C8: =INDEX('Balance Sheet'!93:93,MATCH('DCF Feed'!C1,'Balance Sheet'!88:88,0)) -> 3382.4906 | D8: =INDEX('Balance Sheet'!93:93,MATCH('DCF Feed'!D1,'Balance Sheet'!88:88,0)) -> 4867.2613 | E8: =INDEX('Balance Sheet'!93:93,MATCH('DCF Feed'!E1,'Balance Sheet'!88:88,0)) -> 6676.9131 | F8: =INDEX('Balance Sheet'!93:93,MATCH('DCF Feed'!F1,'Balance Sheet'!88:88,0)) -> 10162.36 | G8: =INDEX('Balance Sheet'!93:93,MATCH('DCF Feed'!G1,'Balance Sheet'!88:88,0)) -> 13985.148
A9: Pension underfunding | B9: =INDEX('Balance Sheet'!$140:$140,MATCH('DCF Feed'!B1,'Balance Sheet'!$88:$88,0)) -> -23 | C9: =INDEX('Balance Sheet'!$140:$140,MATCH('DCF Feed'!C1,'Balance Sheet'!$88:$88,0)) -> -23 | D9: =INDEX('Balance Sheet'!$140:$140,MATCH('DCF Feed'!D1,'Balance Sheet'!$88:$88,0)) -> -23 | E9: =INDEX('Balance Sheet'!$140:$140,MATCH('DCF Feed'!E1,'Balance Sheet'!$88:$88,0)) -> -23 | F9: =INDEX('Balance Sheet'!$140:$140,MATCH('DCF Feed'!F1,'Balance Sheet'!$88:$88,0)) -> -23 | G9: =INDEX('Balance Sheet'!$140:$140,MATCH('DCF Feed'!G1,'Balance Sheet'!$88:$88,0)) -> -23
A10: Tax rate (adjusted) | B10: =INDEX('Income Statement'!91:91,MATCH(B1,'Income Statement'!$38:$38,0)) -> -0.32 | C10: =INDEX('Income Statement'!91:91,MATCH(C1,'Income Statement'!$38:$38,0)) -> -0.25 | D10: =INDEX('Income Statement'!91:91,MATCH(D1,'Income Statement'!$38:$38,0)) -> -0.25 | E10: =INDEX('Income Statement'!91:91,MATCH(E1,'Income Statement'!$38:$38,0)) -> -0.25 | F10: =INDEX('Income Statement'!91:91,MATCH(F1,'Income Statement'!$38:$38,0)) -> -0.25 | G10: =INDEX('Income Statement'!91:91,MATCH(G1,'Income Statement'!$38:$38,0)) -> -0.25
A11: Other
A12: No. of shares | B12: =INDEX('Income Statement'!117:117,MATCH(B1,'Income Statement'!$38:$38,0))/1000 -> 416.23563 | C12: =INDEX('Income Statement'!117:117,MATCH(C1,'Income Statement'!$38:$38,0))/1000 -> 411.74891 | D12: =INDEX('Income Statement'!117:117,MATCH(D1,'Income Statement'!$38:$38,0))/1000 -> 407.2622 | E12: =INDEX('Income Statement'!117:117,MATCH(E1,'Income Statement'!$38:$38,0))/1000 -> 402.77548 | F12: =INDEX('Income Statement'!117:117,MATCH(F1,'Income Statement'!$38:$38,0))/1000 -> 402.77548 | G12: =INDEX('Income Statement'!117:117,MATCH(G1,'Income Statement'!$38:$38,0))/1000 -> 402.77548

Sheet Income Statement
A1: ='DCF Valuation'!D45 -> 340
A2: Divisional Summary
A3: Revenues | B3: =B38 -> 2000 | C3: =C38 -> 2001 | D3: =D38 -> 2002 | E3: =E38 -> 2003 | F3: =F38 -> 2004 | G3: =G38 -> 2005 | H3: =H38 -> 2006 | I3: =I38 -> 2007 | ... Z3: =Z38 -> 2024 | AA3: =Z3+1 -> 2025 | AB3: =AA3+1 -> 2026 | AC3: =AB3+1 -> 2027 | AD3: =AC3+1 -> 2028 | AE3: =AD3+1 -> 2029 | AF3: =AE3+1 -> 2030
A4: Adjusted Revenues
A5: Aerospace Propulsion | H5: 5073 | I5: 5917 | J5: 5803 | K5: 5673 | L5: 5604 | M5: 6110 | N5: 7005 | O5: ='Aerospace Propulsion Division'!O6 -> 7589 | P5: ='Aerospace Propulsion Division'!P6 -> 8153 | Q5: ='Aerospace Propulsion Division'!Q6 -> 9319 | R5: ='Aerospace Propulsion Division'!R6 -> 9391 | S5: ='Aerospace Propulsion Division'!S6 -> 9357 | T5: ='Aerospace Propulsion Division'!T6 -> 10579 | U5: ='Aerospace Propulsion Division'!U6 -> 12045 | V5: ='Aerospace Propulsion Division'!V6 -> 7663 | ... Z5: ='Aerospace Propulsion Division'!Z6 -> 13652 | AA5: =Z5*(1+AA12) -> 15370.63 | AB5: =AA5*(1+AB12) -> 17237.134 | AC5: =AB5*(1+AC12) -> 19144.031 | AD5: =AC5*(1+AD12) -> 20696.681 | AE5: =AD5*(1+AE12) -> 21724.522 | AF5: =AE5*(1+AF12) -> 22805.291 | AG5: =(AD5/Z5)^(1/4)-1 -> 0.10962467
A6: Equipment & Defense | T6: ='Equipment and Defense'!T6 -> 7942 | U6: ='Equipment and Defense'!U6 -> 9256 | V6: ='Equipment and Defense'!V6 -> 6893 | W6: ='Equipment and Defense'!W6 -> 6325 | X6: ='Equipment and Defense'!X6 -> 7535 | Y6: ='Equipment and Defense'!Y6 -> 8835 | Z6: ='Equipment and Defense'!Z6 -> 10618 | AA6: =Z6*(1+AA13) -> 12191.477 | AB6: =AA6*(1+AB13) -> 13490.448 | AC6: =AB6*(1+AC13) -> 14881.972 | AD6: =AC6*(1+AD13) -> 16221.876 | AE6: =AD6*(1+AE13) -> 17082.303 | AF6: =AE6*(1+AF13) -> 17972.921
A7: Aircraft Interiors | T7: ='Aircraft Interiors Division'!H6 -> 2511 | U7: ='Aircraft Interiors Division'!I6 -> 3321 | V7: ='Aircraft Interiors Division'!J6 -> 1922 | W7: ='Aircraft Interiors Division'!K6 -> 1475 | X7: ='Aircraft Interiors Division'!L6 -> 1978 | Y7: ='Aircraft Interiors Division'!M6 -> 2477 | Z7: ='Aircraft Interiors Division'!N6 -> 3037 | AA7: =Z7*(1+AA14) -> 3423.86 | AB7: =AA7*(1+AB14) -> 3783.125 | AC7: =AB7*(1+AC14) -> 4134.5881 | AD7: =AC7*(1+AD14) -> 4471.8616 | AE7: =AD7*(1+AE14) -> 4616.6169 | AF7: =AE7*(1+AF14) -> 4747.6719
A8: Other | H8: =H9-H5 -> 6256 | I8: =I9-I5 -> 4305 | J8: =J9-J5 -> 4526 | K8: =K9-K5 -> 4775 | L8: =L9-L5 -> 5156 | M8: =M9-M5 -> 5626 | N8: =N9-N5 -> 6555 | O8: =O9-O5 -> 6774 | ... S8: =S9-S5 -> 6596 | T8: 18 | U8: 18 | V8: 20 | W8: 18 | X8: 16 | Y8: 11 | Z8: 10 | AA8: =Z8 -> 10 | AB8: =AA8 -> 10 | AC8: =AB8 -> 10 | AD8: =AC8 -> 10 | AE8: =AD8 -> 10 | AF8: =AE8 -> 10
A9: Group | H9: 11329 | I9: 10222 | J9: 10329 | K9: 10448 | L9: 10760 | M9: 11736 | N9: 13560 | O9: 14363 | P9: 15355 | Q9: 17414 | R9: 15781 | S9: 15953 | T9: =SUM(T5,T6,T7,T8) -> 21050 | U9: =SUM(U5,U6,U7,U8) -> 24640 | V9: =SUM(V5,V6,V7,V8) -> 16498 | W9: =SUM(W5,W6,W7,W8) -> 15257 | X9: =SUM(X5,X6,X7,X8) -> 19035 | Y9: =SUM(Y5,Y6,Y7,Y8) -> 23199 | Z9: =SUM(Z5,Z6,Z7,Z8) -> 27317 | AA9: =SUM(AA5,AA6,AA7,AA8) -> 30995.967 | ... AF9: =SUM(AF5,AF6,AF7,AF8) -> 45535.884 | AG9: Below on Revenues for all years
A11: Revenue Growth
A12: Aerospace Propulsion | I12: =I5/H5-1 -> 0.16637098 | J12: =J5/I5-1 -> -0.01926652 | K12: =K5/J5-1 -> -0.022402206 | L12: =L5/K5-1 -> -0.012162877 | M12: =M5/L5-1 -> 0.090292648 | N12: =N5/M5-1 -> 0.14648118 | O12: =O5/N5-1 -> 0.083369022 | P12: =P5/O5-1 -> 0.074318092 | ... Z12: =Z5/Y5-1 -> 0.1495453 | AA12: ='Aerospace Propulsion Division'!AA7 -> 0.12588853 | AB12: ='Aerospace Propulsion Division'!AB7 -> 0.12143315 | AC12: ='Aerospace Propulsion Division'!AC7 -> 0.11062724 | AD12: ='Aerospace Propulsion Division'!AD7 -> 0.081103612 | AE12: ='Aerospace Propulsion Division'!AE7 -> 0.049662117 | AF12: ='Aerospace Propulsion Division'!AF7 -> 0.049748801
A13: Equipment & Defense | U13: =U6/T6-1 -> 0.16544951 | V13: =V6/U6-1 -> -0.25529386 | W13: =W6/V6-1 -> -0.082402437 | X13: =X6/W6-1 -> 0.19130435 | Y13: =Y6/X6-1 -> 0.1725282 | Z13: =Z6/Y6-1 -> 0.20181098 | AA13: ='Equipment and Defense'!AA7 -> 0.14818956 | AB13: ='Equipment and Defense'!AB7 -> 0.10654745 | AC13: ='Equipment and Defense'!AC7 -> 0.10314887 | AD13: ='Equipment and Defense'!AD7 -> 0.090035408 | AE13: ='Equipment and Defense'!AE7 -> 0.053041139 | AF13: ='Equipment and Defense'!AF7 -> 0.052136895
A14: Aircraft Interiors | U14: =U7/T7-1 -> 0.32258065 | V14: =V7/U7-1 -> -0.42125866 | W14: =W7/V7-1 -> -0.23257024 | X14: =X7/W7-1 -> 0.34101695 | Y14: =Y7/X7-1 -> 0.25227503 | Z14: =Z7/Y7-1 -> 0.22607994 | AA14: ='Aircraft Interiors Division'!O7 -> 0.12738229 | AB14: ='Aircraft Interiors Division'!P7 -> 0.10492982 | AC14: ='Aircraft Interiors Division'!Q7 -> 0.092902847 | AD14: ='Aircraft Interiors Division'!R7 -> 0.081573672 | AE14: ='Aircraft Interiors Division'!S7 -> 0.032370256 | AF14: ='Aircraft Interiors Division'!T7 -> 0.028387668
A15: Other | K15: =K8/J8-1 -> 0.055015466 | L15: =L8/K8-1 -> 0.079790576 | M15: =M8/L8-1 -> 0.091155935 | N15: =N8/M8-1 -> 0.1651262 | O15: =O8/N8-1 -> 0.033409611 | P15: =P8/O8-1 -> 0.063182758 | Q15: =Q8/P8-1 -> 0.12399334 | R15: =R8/Q8-1 -> -0.21062384 | ... AF15: =AF8/AE8-1 -> 0
A16: Group | I16: =I9/H9-1 -> -0.097713832 | J16: =J9/I9-1 -> 0.010467619 | K16: =K9/J9-1 -> 0.01152096 | L16: =L9/K9-1 -> 0.029862175 | M16: =M9/L9-1 -> 0.09070632 | N16: =N9/M9-1 -> 0.15541922 | O16: =O9/N9-1 -> 0.059218289 | P16: =P9/O9-1 -> 0.069066351 | ... AF16: =AF9/AE9-1 -> 0.048406068
A18: Adj. EBIT
A19: Aerospace Propulsion | H19: 561 | I19: 636 | J19: 584 | K19: 628 | L19: 663 | M19: 909 | N19: 1076 | O19: ='Aerospace Propulsion Division'!O19 -> 0 | P19: ='Aerospace Propulsion Division'!P19 -> 0 | Q19: ='Aerospace Propulsion Division'!Q19 -> 0 | R19: ='Aerospace Propulsion Division'!R19 -> 0 | S19: 1516 | T19: ='Aerospace Propulsion Division'!T19 -> 2030 | U19: ='Aerospace Propulsion Division'!U19 -> 2485 | V19: ='Aerospace Propulsion Division'!V19 -> 1192 | W19: ='Aerospace Propulsion Division'!W19 -> 1342 | X19: ='Aerospace Propulsion Division'!X19 -> 1710 | Y19: ='Aerospace Propulsion Division'!Y19 -> 2390 | Z19: ='Aerospace Propulsion Division'!Z19 -> 2819 | AA19: =AA5*AA26 -> 3498.7921 | AB19: =AB5*AB26 -> 3987.5039 | AC19: =AC5*AC26 -> 4435.8248 | AD19: =AD5*AD26 -> 4851.2678 | AE19: =AE5*AE26 -> 5134.0822 | AF19: =AF5*AF26 -> 5445.7704 | AG19: =(AF19/AA19)^(1/5)-1 -> 0.092517087
A20: Equipment & Defense | S20: 619 | T20: ='Equipment and Defense'!T14 -> 992 | U20: ='Equipment and Defense'!U14 -> 1209 | V20: ='Equipment and Defense'!V14 -> 687 | W20: ='Equipment and Defense'!W14 -> 650 | X20: ='Equipment and Defense'!X14 -> 874 | Y20: ='Equipment and Defense'!Y14 -> 992 | Z20: ='Equipment and Defense'!Z14 -> 1298 | AA20: =AA6*AA27 -> 1601.9438 | AB20: =AB6*AB27 -> 1858.4703 | AC20: =AC6*AC27 -> 2134.7102 | AD20: =AD6*AD27 -> 2389.6485 | AE20: =AE6*AE27 -> 2524.2429 | AF20: =AF6*AF27 -> 2640.3034
A21: Aircraft Interiors | S21: 93 | T21: ='Aircraft Interiors Division'!H19 -> 81 | U21: ='Aircraft Interiors Division'!I19 -> 188 | V21: ='Aircraft Interiors Division'!J19 -> -174 | W21: ='Aircraft Interiors Division'!K19 -> -167 | X21: ='Aircraft Interiors Division'!L19 -> -140 | Y21: ='Aircraft Interiors Division'!M19 -> -116 | Z21: ='Aircraft Interiors Division'!N19 -> 27 | AA21: =AA7*AA28 -> 106.69282 | AB21: =AB7*AB28 -> 200.53141 | AC21: =AC7*AC28 -> 309.38034 | AD21: =AD7*AD28 -> 401.1613 | AE21: =AE7*AE28 -> 431.91276 | AF21: =AF7*AF28 -> 446.20993
A22: Other | H22: -16 | I22: -23 | J22: 82 | K22: -67 | L22: -95 | M22: -119 | N22: -142 | O22: -158 | P22: -175 | Q22: -82 | R22: -25 | S22: -36 | T22: -80 | U22: -62 | V22: -19 | W22: -20 | X22: -36 | Y22: -100 | Z22: -25 | AA22: =Z22*(AA9/Z9) -> -28.366921 | AB22: =AA22*(AB9/AA9) -> -31.592696 | AC22: =AB22*(AC9/AB9) -> -34.933 | AD22: =AC22*(AD9/AC9) -> -37.888878 | AE22: =AD22*(AE9/AD9) -> -39.749462 | AF22: =AE22*(AF9/AE9) -> -41.673577
A23: Group | H23: =SUM(H19:H22) -> 545 | I23: =SUM(I19:I22) -> 613 | J23: =SUM(J19:J22) -> 666 | K23: =SUM(K19:K22) -> 561 | L23: =SUM(L19:L22) -> 568 | M23: =SUM(M19:M22) -> 790 | N23: =SUM(N19:N22) -> 934 | O23: =SUM(O19:O22) -> -158 | ... S23: =SUM(S19:S22) -> 2192 | T23: =SUM(T19,T20,T21,T22) -> 3023 | U23: =SUM(U19,U20,U21,U22) -> 3820 | V23: =SUM(V19,V20,V21,V22) -> 1686 | W23: =SUM(W19,W20,W21,W22) -> 1805 | X23: =SUM(X19,X20,X21,X22) -> 2408 | Y23: =SUM(Y19,Y20,Y21,Y22) -> 3166 | Z23: =SUM(Z19,Z20,Z21,Z22) -> 4119 | AA23: =SUM(AA19,AA20,AA21,AA22) -> 5179.0618 | ... AF23: =SUM(AF19,AF20,AF21,AF22) -> 8490.6102 | AG23: 5-51.bn FY25 new guidance
AG24: Below cons on all years
A25: Adj. EBIT Margin
A26: Aerospace Propulsion | H26: =H19/H5 -> 0.11058545 | I26: =I19/I5 -> 0.1074869 | J26: =J19/J5 -> 0.1006376 | K26: =K19/K5 -> 0.11069981 | L26: =L19/L5 -> 0.11830835 | M26: =M19/M5 -> 0.1487725 | N26: =N19/N5 -> 0.15360457 | O26: =O19/O5 -> 0 | ... Z26: =Z19/Z5 -> 0.20648989 | AA26: ='Aerospace Propulsion Division'!AA20 -> 0.22762841 | AB26: ='Aerospace Propulsion Division'!AB20 -> 0.23133218 | AC26: ='Aerospace Propulsion Division'!AC20 -> 0.23170799 | AD26: ='Aerospace Propulsion Division'!AD20 -> 0.23439835 | AE26: ='Aerospace Propulsion Division'!AE20 -> 0.23632659 | AF26: ='Aerospace Propulsion Division'!AF20 -> 0.23879417
A27: Equipment & Defense | T27: =T20/T6 -> 0.12490557 | U27: =U20/U6 -> 0.13061798 | V27: =V20/V6 -> 0.099666328 | W27: =W20/W6 -> 0.1027668 | X27: =X20/X6 -> 0.11599204 | Y27: =Y20/Y6 -> 0.1122807 | Z27: =Z20/Z6 -> 0.12224524 | AA27: ='Equipment and Defense'!AA15 -> 0.13139866 | AB27: ='Equipment and Defense'!AB15 -> 0.13776194 | AC27: ='Equipment and Defense'!AC15 -> 0.1434427 | AD27: ='Equipment and Defense'!AD15 -> 0.14731024 | AE27: ='Equipment and Defense'!AE15 -> 0.14776947 | AF27: ='Equipment and Defense'!AF15 -> 0.14690452
A28: Aircraft Interiors | T28: =T21/T7 -> 0.032258065 | U28: =U21/U7 -> 0.056609455 | V28: =V21/V7 -> -0.090530697 | W28: =W21/W7 -> -0.11322034 | X28: =X21/X7 -> -0.070778564 | Y28: =Y21/Y7 -> -0.046830844 | Z28: =Z21/Z7 -> 0.0088903523 | AA28: ='Aircraft Interiors Division'!O20 -> 0.031161559 | AB28: ='Aircraft Interiors Division'!P20 -> 0.053006815 | AC28: ='Aircraft Interiors Division'!Q20 -> 0.074827367 | AD28: ='Aircraft Interiors Division'!R20 -> 0.089707897 | AE28: ='Aircraft Interiors Division'!S20 -> 0.093556118 | AF28: ='Aircraft Interiors Division'!T20 -> 0.093984998
A29: Group | H29: =H23/H9 -> 0.048106629 | I29: =I23/I9 -> 0.059968695 | J29: =J23/J9 -> 0.064478652 | K29: =K23/K9 -> 0.053694487 | L29: =L23/L9 -> 0.052788104 | M29: =M23/M9 -> 0.067314247 | N29: =N23/N9 -> 0.068879056 | O29: =O23/O9 -> -0.011000487 | ... AF29: =AF23/AF9 -> 0.18645976
A31: Adj. EBIT growth
A32: Aerospace Propulsion | I32: =I19/H19-1 -> 0.13368984 | J32: =J19/I19-1 -> -0.081761006 | K32: =K19/J19-1 -> 0.075342466 | L32: =L19/K19-1 -> 0.055732484 | M32: =M19/L19-1 -> 0.37104072 | N32: =N19/M19-1 -> 0.18371837 | O32: =O19/N19-1 -> -1 | P32: =P19/O19-1 -> #DIV/0! | ... AF32: =AF19/AE19-1 -> 0.060709632
A33: Equipment & Defense | U33: =U20/T20-1 -> 0.21875 | V33: =V20/U20-1 -> -0.43176179 | W33: =W20/V20-1 -> -0.053857351 | X33: =X20/W20-1 -> 0.34461538 | Y33: =Y20/X20-1 -> 0.13501144 | Z33: =Z20/Y20-1 -> 0.30846774 | AA33: =AA20/Z20-1 -> 0.23416315 | AB33: =AB20/AA20-1 -> 0.16013453 | ... AF33: =AF20/AE20-1 -> 0.045978341
A34: Aircraft Interiors | U34: =U21/T21-1 -> 1.3209877 | V34: =V21/U21-1 -> -1.9255319 | W34: =W21/V21-1 -> -0.040229885 | X34: =-(X21/W21-1) -> 0.16167665 | Y34: =-(Y21/X21-1) -> 0.17142857 | Z34: =-(Z21/Y21-1) -> 1.2327586 | AA34: =(AA21/Z21-1) -> 2.9515858 | AB34: =AB21/AA21-1 -> 0.87952118 | AC34: =AC21/AB21-1 -> 0.54280242 | AD34: =AD21/AC21-1 -> 0.29666061 | AE34: =AE21/AD21-1 -> 0.076656091 | AF34: =AF21/AE21-1 -> 0.033101997
A35: Group | I35: =I23/H23-1 -> 0.12477064 | J35: =J23/I23-1 -> 0.086460033 | K35: =K23/J23-1 -> -0.15765766 | L35: =L23/K23-1 -> 0.012477718 | M35: =M23/L23-1 -> 0.39084507 | N35: =N23/M23-1 -> 0.18227848 | O35: =O23/N23-1 -> -1.1691649 | P35: =P23/O23-1 -> 0.10759494 | ... AF35: =AF23/AE23-1 -> 0.054670199
A38: Income Statement (consolidated) | B38: 2000 | C38: 2001 | D38: 2002 | E38: 2003 | F38: 2004 | G38: 2005 | H38: 2006 | I38: 2007 | J38: 2008 | K38: 2009 | L38: 2010 | M38: 2011 | N38: 2012 | O38: 2013 | P38: 2014 | Q38: 2015 | R38: 2016 | S38: 2017 | T38: 2018 | U38: 2019 | V38: 2020 | W38: 2021 | X38: 2022 | Y38: 2023 | Z38: 2024 | AA38: =Z38+1 -> 2025 | AB38: =AA38+1 -> 2026 | AC38: =AB38+1 -> 2027 | AD38: =AC38+1 -> 2028 | AE38: =AD38+1 -> 2029 | AF38: =AE38+1 -> 2030
A39: Adjusted Revenues | H39: =H9 -> 11329 | I39: =I9 -> 10222 | J39: =J9 -> 10329 | K39: =K9 -> 10448 | L39: =L9 -> 10760 | M39: =M9 -> 11736 | N39: =N9 -> 13560 | O39: =O9 -> 14363 | ... AF39: =AF9 -> 45535.884
A40: Adjustments | L40: 268 | M40: -78 | N40: 55 | O40: 127 | P40: -311 | Q40: -1192 | R40: 701 | S40: 423 | T40: -25 | U40: 458 | V40: 133 | W40: -124 | X40: 488 | Y40: 452 | Z40: 399 | AA40: 0 | AB40: =AA40 -> 0 | AC40: =AB40 -> 0 | AD40: =AC40 -> 0 | AE40: =AD40 -> 0 | AF40: =AE40 -> 0
A41: Sales (Reported) | H41: 10841 | I41: 9714 | J41: 10281 | K41: 10559 | L41: 11028 | M41: 11658 | N41: 13615 | O41: 14490 | P41: 15044 | Q41: 16222 | R41: 16482 | S41: 16376 | T41: 21025 | U41: 25098 | V41: 16631 | W41: 15133 | X41: 19523 | Y41: 23651 | Z41: 27716 | AA41: ='Income Statement'!AA9 -> 30995.967 | AB41: ='Income Statement'!AB9 -> 34520.707 | AC41: ='Income Statement'!AC9 -> 38170.591 | AD41: ='Income Statement'!AD9 -> 41400.419 | AE41: ='Income Statement'!AE9 -> 43433.442 | AF41: ='Income Statement'!AF9 -> 45535.884
A42: growth | I42: =I41/H41-1 -> -0.1039572 | J42: =J41/I41-1 -> 0.058369364 | K42: =K41/J41-1 -> 0.027040171 | L42: =L41/K41-1 -> 0.044417085 | M42: =M41/L41-1 -> 0.057127312 | N42: =N41/M41-1 -> 0.16786756 | O42: =O41/N41-1 -> 0.064267352 | P42: =P41/O41-1 -> 0.038233264 | ... AF42: =AF41/AE41-1 -> 0.048406068
A43: Other Income | H43: 74 | I43: 66 | J43: 127 | K43: 156 | L43: 200 | M43: 216 | N43: 209 | O43: 264 | P43: 291 | Q43: 285 | R43: 277 | S43: 280 | T43: 321 | U43: 297 | V43: 267 | W43: 373 | X43: 440 | Y43: 474 | Z43: 438 | AA43: =AA44*AA41 -> 489.8338 | AB43: =AB44*AB41 -> 545.53577 | AC43: =AC44*AC41 -> 603.21543 | AD43: =AD44*AD41 -> 654.25687 | AE43: =AE44*AE41 -> 686.38503 | AF43: =AF44*AF41 -> 719.61023
A44: as a % of sales | H44: =H43/H$41 -> 0.0068259386 | I44: =I43/I$41 -> 0.0067943175 | J44: =J43/J$41 -> 0.012352884 | K44: =K43/K$41 -> 0.014774126 | L44: =L43/L$41 -> 0.018135655 | M44: =M43/M$41 -> 0.018528049 | N44: =N43/N$41 -> 0.015350716 | O44: =O43/O$41 -> 0.018219462 | ... Z44: =Z43/Z$41 -> 0.015803146 | AA44: =Z44 -> 0.015803146 | AB44: =AA44 -> 0.015803146 | AC44: =AB44 -> 0.015803146 | AD44: =AC44 -> 0.015803146 | AE44: =AD44 -> 0.015803146 | AF44: =AE44 -> 0.015803146
A45: Changes in Inventories of finished goods and Work-in-progress | H45: 360 | I45: 316 | J45: 276 | K45: -268 | L45: -43 | M45: 125 | N45: 340 | O45: -32 | P45: 255 | Q45: 257 | R45: 308 | S45: 195 | T45: 3 | U45: 453 | V45: -865 | W45: -199 | X45: 1204 | Y45: 1000 | Z45: 989 | AA45: =AA46*AA$41 -> 1106.0402 | AB45: =AB46*AB$41 -> 1231.8148 | AC45: =AC46*AC$41 -> 1362.0549 | AD45: =AD46*AD$41 -> 1477.306 | AE45: =AE46*AE$41 -> 1549.8511 | AF45: =AF46*AF$41 -> 1624.8733
A46: as a % of sales | H46: =H45/H$41 -> 0.033207269 | I46: =I45/I$41 -> 0.032530369 | J46: =J45/J$41 -> 0.026845638 | K46: =K45/K$41 -> -0.025381191 | L46: =L45/L$41 -> -0.0038991658 | M46: =M45/M$41 -> 0.010722251 | N46: =N45/N$41 -> 0.024972457 | O46: =O45/O$41 -> -0.0022084196 | ... Z46: =Z45/Z$41 -> 0.03568336 | AA46: =Z46 -> 0.03568336 | AB46: =AA46 -> 0.03568336 | AC46: =AB46 -> 0.03568336 | AD46: =AC46 -> 0.03568336 | AE46: =AD46 -> 0.03568336 | AF46: =AE46 -> 0.03568336
A47: Capitalised production | H47: 350 | I47: 277 | J47: 298 | K47: 242 | L47: 243 | M47: 371 | N47: 642 | O47: 911 | P47: 998 | Q47: 946 | R47: 624 | S47: 522 | T47: 447 | U47: 438 | V47: 329 | W47: 372 | X47: 382 | Y47: 480 | Z47: 526 | AA47: =AA48*AA$41 -> 588.24789 | AB47: =AB48*AB$41 -> 655.14114 | AC47: =AC48*AC$41 -> 724.40939 | AD47: =AD48*AD$41 -> 785.70574 | AE47: =AE48*AE$41 -> 824.28887 | AF47: =AF48*AF$41 -> 864.18946
A48: as a % of sales | H48: =H47/H$41 -> 0.032284845 | I48: =I47/I$41 -> 0.028515545 | J48: =J47/J$41 -> 0.028985507 | K48: =K47/K$41 -> 0.022918837 | L48: =L47/L$41 -> 0.02203482 | M48: =M47/M$41 -> 0.03182364 | N48: =N47/N$41 -> 0.047153874 | O48: =O47/O$41 -> 0.062870945 | ... Z48: =Z47/Z$41 -> 0.018978208 | AA48: =Z48 -> 0.018978208 | AB48: =AA48 -> 0.018978208 | AC48: =AB48 -> 0.018978208 | AD48: =AC48 -> 0.018978208 | AE48: =AD48 -> 0.018978208 | AF48: =AE48 -> 0.018978208
A49: Raw materials and Consumables used | H49: -7341 | I49: -6098 | J49: -6475 | K49: -5948 | L49: -6254 | M49: -6834 | N49: -8160 | O49: -8648 | P49: -9048 | Q49: -9275 | R49: -9340 | S49: -9449 | T49: -12440 | U49: -14448 | V49: -8450 | W49: -7999 | X49: -11724 | Y49: -14072 | Z49: -15960 | AA49: =AA50*AA$41 -> -17848.738 | AB49: =AB50*AB$41 -> -19878.427 | AC49: =AC50*AC$41 -> -21980.179 | AD49: =AD50*AD$41 -> -23840.045 | AE49: =AE50*AE$41 -> -25010.742 | AF49: =AF50*AF$41 -> -26221.414
A50: as a % of sales | H50: =H49/H$41 -> -0.67715155 | I50: =I49/I$41 -> -0.62775376 | J50: =J49/J$41 -> -0.62980255 | K50: =K49/K$41 -> -0.56331092 | L50: =L49/L$41 -> -0.56710192 | M50: =M49/M$41 -> -0.5862069 | N50: =N49/N$41 -> -0.59933896 | O50: =O49/O$41 -> -0.5968254 | ... Z50: =Z49/Z$41 -> -0.57584067 | AA50: =Z50 -> -0.57584067 | AB50: =AA50 -> -0.57584067 | AC50: =AB50 -> -0.57584067 | AD50: =AC50 -> -0.57584067 | AE50: =AD50 -> -0.57584067 | AF50: =AE50 -> -0.57584067
A51: Personnel Costs | H51: -3170 | I51: -3032 | J51: -3133 | K51: -3276 | L51: -3459 | M51: -3808 | N51: -4205 | O51: -4506 | P51: -4744 | Q51: -4524 | R51: -4406 | S51: -4353 | T51: -5665 | U51: -6349 | V51: -5028 | W51: -4919 | X51: -5792 | Y51: -6767 | Z51: -7801 | AA51: =AA23-SUM(AA41+AA43+AA45+AA47+AA49+AA53+AA55+AA58+AA60+AA62) -> -8226.5038 | AB51: =AB23-SUM(AB41+AB43+AB45+AB47+AB49+AB53+AB55+AB58+AB60+AB62) -> -8915.081 | AC51: =AC23-SUM(AC41+AC43+AC45+AC47+AC49+AC53+AC55+AC58+AC60+AC62) -> -9663.564 | AD51: =AD23-SUM(AD41+AD43+AD45+AD47+AD49+AD53+AD55+AD58+AD60+AD62) -> -10301.238 | AE51: =AE23-SUM(AE41+AE43+AE45+AE47+AE49+AE53+AE55+AE58+AE60+AE62) -> -10734.209 | AF51: =AF23-SUM(AF41+AF43+AF45+AF47+AF49+AF53+AF55+AF58+AF60+AF62) -> -11203.38
A52: as a % of sales | H52: =H51/H$41 -> -0.29240845 | I52: =I51/I$41 -> -0.31212683 | J52: =J51/J$41 -> -0.30473689 | K52: =K51/K$41 -> -0.31025665 | L52: =L51/L$41 -> -0.31365615 | M52: =M51/M$41 -> -0.32664265 | N52: =N51/N$41 -> -0.30885053 | O52: =O51/O$41 -> -0.31097308 | P52: =P51/P41 -> -0.31534166 | Q52: =Q51/Q41 -> -0.27888053 | R52: =R51/R41 -> -0.26732193 | S52: =S51/S41 -> -0.26581583 | T52: =T51/T41 -> -0.26944114 | U52: =U51/U41 -> -0.25296836 | V52: =V51/V41 -> -0.30232698 | W52: =W51/W41 -> -0.32505121 | ... AF52: =AF51/AF41 -> -0.2460341
A53: Taxes | H53: -229 | I53: -207 | J53: -221 | K53: -238 | L53: -217 | M53: -235 | N53: -270 | O53: -276 | P53: -275 | Q53: -277 | R53: -286 | S53: -284 | T53: -295 | U53: -388 | V53: -326 | W53: -257 | X53: -290 | Y53: -308 | Z53: -337 | AA53: =AA54*AA$41 -> -376.88125 | AB53: =AB54*AB$41 -> -419.73871 | AC53: =AC54*AC$41 -> -464.11781 | AD53: =AD54*AD$41 -> -503.38942 | AE53: =AE54*AE$41 -> -528.10903 | AF53: =AF54*AF$41 -> -553.67271
A54: as a % of sales | H54: =H53/H$41 -> -0.021123513 | I54: =I53/I$41 -> -0.02130945 | J54: =J53/J$41 -> -0.021495963 | K54: =K53/K$41 -> -0.022540013 | L54: =L53/L$41 -> -0.019677185 | M54: =M53/M$41 -> -0.020157832 | N54: =N53/N$41 -> -0.019831069 | O54: =O53/O$41 -> -0.019047619 | ... Z54: =Z53/Z$41 -> -0.012159042 | AA54: =Z54 -> -0.012159042 | AB54: =AA54 -> -0.012159042 | AC54: =AB54 -> -0.012159042 | AD54: =AC54 -> -0.012159042 | AE54: =AD54 -> -0.012159042 | AF54: =AE54 -> -0.012159042
A55: Depreciation, Amortization and increase in provision (net of use) | H55: =-583-284 -> -867 | I55: -718 | J55: -595 | K55: -606 | L55: -575 | M55: -579 | N55: -854 | O55: -790 | P55: -894 | Q55: -763 | R55: -634 | S55: -1012 | T55: -1176 | U55: -1600 | V55: -1212 | W55: -1509 | X55: -1174 | Y55: -1282 | Z55: -1578 | AA55: =AA56*AA$41 -> -1764.7437 | AB55: =AB56*AB$41 -> -1965.4234 | AC55: =AC56*AC$41 -> -2173.2282 | AD55: =AD56*AD$41 -> -2357.1172 | AE55: =AE56*AE$41 -> -2472.8666 | AF55: =AF56*AF$41 -> -2592.5684
A56: as a % of sales | H56: =H55/H$41 -> -0.079974172 | I56: =I55/I$41 -> -0.073913939 | J56: =J55/J$41 -> -0.057873748 | K56: =K55/K$41 -> -0.057391798 | L56: =L55/L$41 -> -0.052140007 | M56: =M55/M$41 -> -0.049665466 | N56: =N55/N$41 -> -0.062724936 | O56: =O55/O$41 -> -0.054520359 | ... Z56: =Z55/Z$41 -> -0.056934623 | AA56: =Z56 -> -0.056934623 | AB56: =AA56 -> -0.056934623 | AC56: =AB56 -> -0.056934623 | AD56: =AC56 -> -0.056934623 | AE56: =AD56 -> -0.056934623 | AF56: =AE56 -> -0.056934623
A57: Of which provisions | R57: -92 | S57: 224 | T57: -33 | U57: 137 | V57: -235 | W57: 129 | X57: -199 | Y57: -54 | Z57: 172 | AA57: =AA55+'Cashflow Statement'!AA5+'Cashflow Statement'!AA7 -> -192.35482 | AB57: =AB55+'Cashflow Statement'!AB5+'Cashflow Statement'!AB7 -> -146.2603 | AC57: =AC55+'Cashflow Statement'!AC5+'Cashflow Statement'!AC7 -> -238.06563 | AD57: =AD55+'Cashflow Statement'!AD5+'Cashflow Statement'!AD7 -> -258.2097 | AE57: =AE55+'Cashflow Statement'!AE5+'Cashflow Statement'!AE7 -> -270.88943 | AF57: =AF55+'Cashflow Statement'!AF5+'Cashflow Statement'!AF7 -> -284.00212
A58: Asset impairment | H58: -157 | I58: -178 | J58: -40 | K58: -34 | L58: 7 | M58: -65 | N58: -29 | O58: -82 | P58: -59 | Q58: -179 | R58: -237 | S58: -60 | T58: 62 | U58: 57 | V58: -149 | W58: 78 | X58: -252 | Y58: -50 | Z58: 18 | AA58: =AA59*AA$41 -> 20.130156 | AB58: =AB59*AB$41 -> 22.419278 | AC58: =AC59*AC$41 -> 24.789675 | AD58: =AD59*AD$41 -> 26.887269 | AE58: =AE59*AE$41 -> 28.207604 | AF58: =AF59*AF$41 -> 29.573023
A59: as a % of sales | H59: =H58/H$41 -> -0.014482059 | I59: =I58/I$41 -> -0.018324068 | J59: =J58/J$41 -> -0.0038906721 | K59: =K58/K$41 -> -0.0032200019 | L59: =L58/L$41 -> 0.00063474791 | M59: =M58/M$41 -> -0.0055755704 | N59: =N58/N$41 -> -0.0021300037 | O59: =O58/O$41 -> -0.0056590752 | ... Z59: =Z58/Z$41 -> 0.00064944436 | AA59: =Z59 -> 0.00064944436 | AB59: =AA59 -> 0.00064944436 | AC59: =AB59 -> 0.00064944436 | AD59: =AC59 -> 0.00064944436 | AE59: =AD59 -> 0.00064944436 | AF59: =AE59 -> 0.00064944436
A60: Other recurring operating income and expense | H60: -47 | I60: -11 | J60: 85 | K60: 42 | L60: 21 | M60: 15 | N60: -45 | O60: -36 | P60: -113 | Q60: 118 | R60: 115 | S60: 159 | T60: -191 | U60: 102 | V60: 148 | W60: 156 | X60: 103 | Y60: 84 | Z60: 39 | AA60: =AA61*AA$41 -> 43.615338 | AB60: =AB61*AB$41 -> 48.575103 | AC60: =AC61*AC$41 -> 53.710963 | AD60: =AD61*AD$41 -> 58.255749 | AE60: =AE61*AE$41 -> 61.116475 | AF60: =AF61*AF$41 -> 64.074884
A61: as a % of sales | H61: =H60/H$41 -> -0.0043353934 | I61: =I60/I$41 -> -0.0011323862 | J61: =J60/J$41 -> 0.0082676782 | K61: =K60/K$41 -> 0.0039776494 | L61: =L60/L$41 -> 0.0019042437 | M61: =M60/M$41 -> 0.0012866701 | N61: =N60/N$41 -> -0.0033051781 | O61: =O60/O$41 -> -0.002484472 | ... Z61: =Z60/Z$41 -> 0.0014071295 | AA61: =Z61 -> 0.0014071295 | AB61: =AA61 -> 0.0014071295 | AC61: =AB61 -> 0.0014071295 | AD61: =AC61 -> 0.0014071295 | AE61: =AD61 -> 0.0014071295 | AF61: =AE61 -> 0.0014071295
A62: Share in profit from joint ventures | P62: 45 | Q62: 44 | R62: 87 | S62: 144 | T62: 189 | U62: 164 | V62: 48 | W62: 40 | X62: 73 | Y62: 99 | Z62: 136 | AA62: =AA63*AA$41 -> 152.09451 | AB62: =AB63*AB$41 -> 169.3901 | AC62: =AC63*AC$41 -> 187.29977 | AD62: =AD63*AD$41 -> 203.14825 | AE62: =AE63*AE$41 -> 213.12412 | AF62: =AF63*AF$41 -> 223.44062
A63: as a % of sales | P63: =P62/P$41 -> 0.0029912257 | Q63: =Q62/Q$41 -> 0.0027123659 | R63: =R62/R$41 -> 0.0052784856 | S63: =S62/S$41 -> 0.0087933561 | T63: =T62/T$41 -> 0.0089892985 | U63: =U62/U$41 -> 0.0065343852 | V63: =V62/V$41 -> 0.0028861764 | W63: =W62/W$41 -> 0.00264323 | ... Z63: =Z62/Z$41 -> 0.004906913 | AA63: =Z63 -> 0.004906913 | AB63: =AA63 -> 0.004906913 | AC63: =AB63 -> 0.004906913 | AD63: =AC63 -> 0.004906913 | AE63: =AD63 -> 0.004906913 | AF63: =AE63 -> 0.004906913
A64: Recurring operating Income (EBITA) | H64: =H41+H43+H45+H47+H49+H51+H53+H55+H58+H60 -> -186 | I64: =I41+I43+I45+I47+I49+I51+I53+I55+I58+I60 -> 129 | J64: =J41+J43+J45+J47+J49+J51+J53+J55+J58+J60 -> 603 | K64: =K41+K43+K45+K47+K49+K51+K53+K55+K58+K60 -> 629 | L64: =L41+L43+L45+L47+L49+L51+L53+L55+L58+L60 -> 951 | M64: =M41+M43+M45+M47+M49+M51+M53+M55+M58+M60 -> 864 | N64: =N41+N43+N45+N47+N49+N51+N53+N55+N58+N60 -> 1243 | O64: =O41+O43+O45+O47+O49+O51+O53+O55+O58+O60 -> 1295 | P64: =P41+P43+P45+P47+P49+P51+P53+P55+P58+P60+P62 -> 1500 | Q64: =Q41+Q43+Q45+Q47+Q49+Q51+Q53+Q55+Q58+Q60+Q62 -> 2854 | R64: =R41+R43+R45+R47+R49+R51+R53+R55+R58+R60+R62 -> 2990 | S64: =S41+S43+S45+S47+S49+S51+S53+S55+S58+S60+S62 -> 2518 | T64: =T41+T43+T45+T47+T49+T51+T53+T55+T58+T60+T62 -> 2280 | U64: =U41+U43+U45+U47+U49+U51+U53+U55+U58+U60+U62 -> 3824 | V64: =V41+V43+V45+V47+V49+V51+V53+V55+V58+V60+V62 -> 1393 | W64: =W41+W43+W45+W47+W49+W51+W53+W55+W58+W60+W62 -> 1269 | ... AF64: =AF41+AF43+AF45+AF47+AF49+AF51+AF53+AF55+AF58+AF60+AF62 -> 8490.6102
A65: EBITA Margin | Q65: =Q64/Q$41 -> 0.17593392 | R65: =R64/R$41 -> 0.18141002 | S65: =S64/S$41 -> 0.1537616 | T65: =T64/T$41 -> 0.10844233 | U65: =U64/U$41 -> 0.15236274 | V65: =V64/V$41 -> 0.083759245 | W65: =W64/W$41 -> 0.083856473 | X65: =X64/X$41 -> 0.12769554 | ... AF65: =AF64/AF$41 -> 0.18645976
A66: Remeasurement of revenue | R66: -722 | S66: -463 | T66: 11 | U66: -449 | V66: -134 | W66: 136 | X66: -478 | Y66: -455 | Z66: -404
A67: Deferred hedging gain/loss | R67: 10 | S67: 7 | T67: -2 | U67: -1 | V67: 5 | W67: 5 | X67: 3 | Y67: -7 | Z67: 10
A68: Amortization of intangible assets from meger | R68: 70 | S68: 67 | T68: 56 | U68: 51 | V68: 46 | W68: 39 | X68: 38 | Y68: 38 | Z68: 41
A69: PPA Impacts/Other Business combinations | R69: 56 | S69: 63 | T69: 678 | U69: 395 | V69: 376 | W69: 356 | X69: 352 | Y69: 281 | Z69: 286
A70: Adj. Recurring operating income (Adj EBITA) | R70: =R64+SUM(R66:R69) -> 2404 | S70: =S64+SUM(S66:S69) -> 2192 | T70: =T64+SUM(T66:T69) -> 3023 | U70: =U64+SUM(U66:U69) -> 3820 | V70: =V64+SUM(V66:V69) -> 1686 | W70: =W64+SUM(W66:W69) -> 1805 | X70: =X64+SUM(X66:X69) -> 2408 | Y70: =Y64+SUM(Y66:Y69) -> 3166 | ... AF70: =AF64+SUM(AF66:AF69) -> 8490.6102
A71: Adj. EBITA Margin | Q71: =Q70/Q39 -> 0 | R71: =R70/R39 -> 0.15233509 | S71: =S70/S39 -> 0.13740362 | T71: =T70/T39 -> 0.14361045 | U71: =U70/U39 -> 0.15503247 | V71: =V70/V39 -> 0.10219421 | W71: =W70/W39 -> 0.11830635 | X71: =X70/X39 -> 0.12650381 | ... AF71: =AF70/AF39 -> 0.18645976
A72: other non-recurring operating income and expenses | K72: -35 | L72: -13 | M72: -29 | N72: -56 | O72: 185 | P72: -107 | Q72: -778 | R72: 349 | S72: -90 | T72: -115 | U72: 13 | V72: -466 | W72: -405 | X72: -450 | Y72: -511 | Z72: 6 | AA72: 0 | AB72: 0 | AC72: 0 | AD72: 0 | AE72: 0 | AF72: 0
A73: Reported EBIT | P73: =P64+P72 -> 1393 | Q73: =Q64+Q72 -> 2076 | R73: =R64+R72 -> 3339 | S73: =S64+S72 -> 2428 | T73: =T64+T72 -> 2165 | U73: =U64+U72 -> 3837 | V73: =V64+V72 -> 927 | W73: =W64+W72 -> 864 | ... AF73: =AF64+AF72 -> 8490.6102
A74: Adj. EBIT | R74: =R70+R72 -> 2753 | S74: =S70+S72 -> 2102 | T74: =T70+T72 -> 2908 | U74: =U70+U72 -> 3833 | V74: =V70+V72 -> 1220 | W74: =W70+W72 -> 1400 | X74: =X70+X72 -> 1958 | Y74: =Y70+Y72 -> 2655 | ... AF74: =AF70+AF72 -> 8490.6102
A75: Financing expense | H75: =H76+H77+H78 -> 312 | I75: =I76+I77+I78 -> 34 | J75: =J76+J77+J78 -> -716 | K75: =K76+K77+K78 -> 296 | L75: =L76+L77+L78 -> -703 | M75: =M76+M77+M78 -> -150 | N75: =N76+N77+N78 -> 533 | O75: =SUM(O76:O78) -> 439 | P75: =SUM(P76:P78) -> -1771 | Q75: =SUM(Q76:Q78) -> -3408 | R75: =SUM(R76:R78) -> -1052 | S75: =SUM(S76:S78) -> 3012 | T75: =SUM(T76:T78) -> -476 | U75: =SUM(U76:U78) -> -363 | V75: =SUM(V76:V78) -> -357 | ... AF75: =SUM(AF76:AF78) -> 242.18511
A76: Net Interest expense | H76: -22 | I76: -10 | J76: -19 | K76: -38 | L76: -36 | M76: -42 | N76: -54 | O76: -42 | P76: -42 | Q76: -29 | R76: -51 | S76: -57 | T76: -67 | U76: -33 | V76: -58 | W76: -85 | X76: -56 | Y76: 112 | Z76: 157 | AA76: =AA120 -> 113.985 | AB76: =AB120 -> 126.92821 | AC76: =AC120 -> 143.85053 | AD76: =AD120 -> 168.32129 | AE76: =AE120 -> 195.66533 | AF76: =AF120 -> 242.18511
A77: FX | K77: 479 | L77: -531 | M77: 19 | N77: 709 | O77: 551 | P77: -1654 | Q77: -3270 | R77: -943 | S77: 3071 | T77: -351 | U77: -283 | V77: -257 | W77: -497 | X77: -5072 | Y77: 1850 | Z77: -5180
A78: Other | H78: 334 | I78: 44 | J78: -697 | K78: -145 | L78: -136 | M78: -127 | N78: -122 | O78: -70 | P78: -75 | Q78: -109 | R78: -58 | S78: -2 | T78: -58 | U78: -47 | V78: -42 | W78: -14 | X78: -35 | Y78: -4 | Z78: -28
A79: Adj. Financial expense | R79: -144 | S79: 7 | T79: -211 | U79: -89 | V79: -7 | W79: =W75+SUM(W80:W81) -> -204 | X79: =X75+SUM(X80:X81) -> -186 | Y79: =Y75+SUM(Y80:Y81) -> 174 | Z79: =Z75+SUM(Z80:Z81) -> 23 | AA79: =AA75+SUM(AA80:AA81) -> 113.985 | AB79: =AB75+SUM(AB80:AB81) -> 126.92821 | AC79: =AC75+SUM(AC80:AC81) -> 143.85053 | AD79: =AD75+SUM(AD80:AD81) -> 168.32129 | ... AF79: =AF75+SUM(AF80:AF81) -> 242.18511
A80: Remeasurement of revenue | W80: -136 | X80: 478 | Y80: 455 | Z80: 404
A81: Deferred hedging gain/loss | W81: 528 | X81: 4499 | Y81: -2239 | Z81: 4670
A82: check
A83: Share in profit from associates | H83: 4 | I83: 4 | J83: 10 | K83: 3 | L83: 9 | M83: 10 | N83: 19 | O83: 15 | P83: 18 | Q83: 0 | R83: 0 | S83: 0 | T83: 0 | U83: 0 | V83: 0 | W83: 0 | X83: =W83*1.05 -> 0 | Y83: 0 | Z83: 0 | AA83: =Z83*1.05 -> 0 | AB83: =AA83*1.05 -> 0 | AC83: =AB83*1.05 -> 0 | AD83: =AC83*1.05 -> 0 | AE83: =AD83*1.05 -> 0 | AF83: =AE83*1.05 -> 0
A84: PBT | H84: =H64+H72+H75 -> 126 | I84: =I64+I72+I75 -> 163 | J84: =J64+J72+J75 -> -113 | K84: =K64+K72+K75 -> 890 | L84: =L64+L72+L75 -> 235 | M84: =M64+M72+M75 -> 685 | N84: =N64+N72+N75 -> 1720 | O84: =O64+O72+O75 -> 1919 | ... AF84: =AF64+AF72+AF75 -> 8732.7953
A85: Adj. PBT | R85: =R70+R72+R79 -> 2609 | S85: =S70+S72+S79 -> 2109 | T85: =T70+T72+T79 -> 2697 | U85: =U70+U72+U79 -> 3744 | V85: =V70+V72+V79 -> 1213 | W85: =W70+W72+W79 -> 1196 | X85: =X70+X72+X79 -> 1772 | Y85: =Y70+Y72+Y79 -> 2829 | ... AF85: =AF70+AF72+AF79 -> 8732.7953
A86: Tax benefit (expense) | H86: -109 | I86: -25 | J86: 142 | K86: -235 | L86: -14 | M86: -201 | N86: -433 | O86: -650 | P86: 292 | Q86: 505 | R86: -398 | S86: -1660 | T86: -348 | U86: -962 | V86: -184 | W86: -200 | X86: 694 | Y86: -1236 | Z86: 284 | AA86: =AA87*AA84 -> -1811.2806 | AB86: =AB87*AB84 -> -1849.3083 | AC86: =AC87*AC84 -> -1817.0966 | AD86: =AD87*AD84 -> -2020.8526 | AE86: =AE87*AE84 -> -2144 | AF86: =AF87*AF84 -> -2270.5268
A87: Reported tax rate | H87: =H86/H84 -> -0.86507937 | I87: =I86/I84 -> -0.15337423 | J87: =J86/J84 -> -1.2566372 | K87: =K86/K84 -> -0.26404494 | L87: =L86/L84 -> -0.059574468 | M87: =M86/M84 -> -0.29343066 | N87: =N86/N84 -> -0.25174419 | O87: =O86/O84 -> -0.33871808 | P87: -0.25 | Q87: =P87 -> -0.25 | R87: =R86/R84 -> -0.17402711 | S87: =S86/S84 -> -0.30514706 | T87: =T86/T84 -> -0.20603908 | U87: =U86/U84 -> -0.27691422 | V87: =V86/V84 -> -0.32280702 | W87: =W86/W84 -> -0.74626866 | X87: =X86/X84 -> -0.2224359 | Y87: =Y86/Y84 -> -0.25988225 | Z87: =Z86/Z84 -> -0.330617 | AA87: -0.3422 | AB87: -0.3011 | AC87: -0.26 | AD87: -0.26 | AE87: -0.26 | AF87: -0.26
A88: Adj. Tax benefit (expense) | R88: =-498 -> -498 | S88: -485 | T88: -638 | U88: -1012 | V88: -334 | W88: =W86+SUM(W89:W90) -> -412 | X88: =X86+SUM(X89:X90) -> -557 | Y88: =Y86+SUM(Y89:Y90) -> -724 | Z88: =Z86+SUM(Z89:Z90) -> -987 | AA88: =AA85*AA91 -> -1693.775 | AB88: =AB85*AB91 -> -1535.4603 | AC88: =AC85*AC91 -> -1747.2082 | AD88: =AD85*AD91 -> -1943.1275 | AE88: =AE85*AE91 -> -2061.5384 | AF88: =AF85*AF91 -> -2183.1988
A89: Remeasurement of revenue | W89: -138 | X89: -1163 | Y89: 581 | Z89: -1209
A90: Other | W90: =-11+-63 -> -74 | X90: =-10+-78 -> -88 | Y90: =-10+-59 -> -69 | Z90: =-11+-51 -> -62
A91: Adj. tax rate | R91: =R88/R85 -> -0.19087773 | S91: =S88/S85 -> -0.22996681 | T91: =T88/T85 -> -0.23655914 | U91: =U88/U85 -> -0.27029915 | V91: =V88/V85 -> -0.27535037 | W91: =W88/W85 -> -0.34448161 | X91: =X88/X85 -> -0.31433409 | Y91: =Y88/Y85 -> -0.25592082 | Z91: =Z88/Z85 -> -0.237946 | AA91: -0.32 | AB91: -0.25 | AC91: -0.25 | AD91: =AC91 -> -0.25 | AE91: =AD91 -> -0.25 | AF91: =AE91 -> -0.25
A92: Net Income (Reported) | H92: =H84+H86+H83 -> 21 | I92: =I84+I86+I83 -> 142 | J92: =J84+J86+J83 -> 39 | K92: =K84+K86+K83 -> 658 | L92: =L84+L86+L83 -> 230 | M92: =M84+M86+M83 -> 494 | N92: =N84+N86+N83 -> 1306 | O92: =O84+O86+O83 -> 1284 | P92: =P84+P86+P83 -> -68 | Q92: =Q84+Q86+Q83+421 -> -406 | R92: =R84+R86+R83 -> 1889 | S92: =S84+S86+S83 -> 3780 | T92: =T84+T86+T83 -> 1341 | U92: =U84+U86+U83 -> 2512 | V92: =V84+V86+V83 -> 386 | W92: =W84+W86+W83 -> 68 | X92: =X84+X86+X83 -> -2426 | Y92: =Y84+Y86+Y83 -> 3520 | ... AF92: =AF84+AF86+AF83 -> 6462.2685
A93: Adj. Net Income | R93: =R85+R88+R83 -> 2111 | S93: =S85+S88+S83 -> 1624 | T93: =T85+T88+T83 -> 2059 | U93: =U85+U88+U83 -> 2732 | V93: =V85+V88+V83 -> 879 | W93: =W85+W88+W83 -> 784 | X93: =X85+X88+X83 -> 1215 | Y93: =Y85+Y88+Y83 -> 2105 | ... AF93: =AF85+AF88+AF83 -> 6549.5965
A94: Net Income from discontinued operations | H94: 0 | I94: -96 | J94: -233 | K94: -4 | L94: -5 | M94: 3 | N94: 0 | O94: 0 | P94: 0 | Q94: 29 | R94: 74 | S94: 831 | T94: 0 | U94: 0 | V94: 0 | W94: 0 | X94: 0 | Y94: 0 | Z94: 0 | AA94: 0 | AB94: 0 | AC94: 0 | AD94: 0 | AE94: 0 | AF94: 0
A95: Non Controlling Interest | H95: -12 | I95: -7 | J95: -11 | K95: 13 | L95: 18 | M95: 19 | N95: 24 | O95: 29 | P95: 58 | Q95: 47 | R95: 55 | S95: 61 | T95: 58 | U95: 65 | V95: 34 | W95: 25 | X95: 33 | Y95: 76 | Z95: 92 | AA95: =AA39*AA96 -> 102.88746 | AB95: =AB39*AB96 -> 114.58742 | AC95: =AC39*AC96 -> 126.70278 | AD95: =AD39*AD96 -> 137.42382 | AE95: =AE39*AE96 -> 144.1722 | AF95: =AF39*AF96 -> 151.15101
A96: as a % of sales | W96: =W95/W41 -> 0.0016520188 | X96: =X95/X41 -> 0.001690314 | Y96: =Y95/Y41 -> 0.0032133948 | Z96: =Z95/Z41 -> 0.0033193823 | AA96: =Z96 -> 0.0033193823 | AB96: =AA96 -> 0.0033193823 | AC96: =AB96 -> 0.0033193823 | AD96: =AC96 -> 0.0033193823 | AE96: =AD96 -> 0.0033193823 | AF96: =AE96 -> 0.0033193823
A97: Net Income attributable to owners of the parent | H97: =H92+H94-H95 -> 33 | I97: =I92+I94-I95 -> 53 | J97: =J92+J94-J95 -> -183 | K97: =K92+K94-K95 -> 641 | L97: =L92+L94-L95 -> 207 | M97: =M92+M94-M95 -> 478 | N97: =N92+N94-N95 -> 1282 | O97: =O92+O94-O95 -> 1255 | ... AF97: =AF92+AF94-AF95 -> 6311.1175
A98: Adj. Net Income attributable to owners of the parent | H98: =H93+H94-H95 -> 12 | I98: =I93+I94-I95 -> -89 | J98: =J93+J94-J95 -> -222 | K98: =K93+K94-K95 -> -17 | L98: =L93+L94-L95 -> -23 | M98: =M93+M94-M95 -> -16 | N98: =N93+N94-N95 -> -24 | O98: =O93+O94-O95 -> -29 | ... R98: =R93+R94-R95 -> 2130 | S98: =S93+S94-S95-1 -> 2393 | T98: =T93+T94-T95 -> 2001 | U98: =U93+U94-U95 -> 2667 | V98: =V93+V94-V95 -> 845 | W98: =W93+W94-W95 -> 759 | X98: =X93+X94-X95 -> 1182 | Y98: =Y93+Y94-Y95-1 -> 2028 | Z98: =Z93+Z94-Z95 -> 3069 | AA98: =AA93+AA94-AA95 -> 3496.3843 | AB98: =AB93+AB94-AB95 -> 4491.7934 | AC98: =AC93+AC94-AC95 -> 5114.9219 | AD98: =AD93+AD94-AD95 -> 5691.9587 | AE98: =AE93+AE94-AE95 -> 6040.4431 | AF98: =AF93+AF94-AF95 -> 6398.4455
A100: Reported EPS - Basic | H100: 0.02 | I100: 0.09 | J100: -0.51 | K100: 1.61 | L100: 0.52 | M100: 1.18 | N100: 3.09 | O100: =((O92-O95)/O116)*1000 -> 3.0147055 | P100: =((P92-P95)/P116)*1000 -> -0.30258395 | Q100: =((Q92-Q95)/Q116)*1000 -> -1.0848506 | R100: =((R92-R95)/R116)*1000 -> 4.405211 | S100: =((S92-S95)/S116)*1000 -> 9.0654021 | T100: =((T92-T95)/T116)*1000 -> 2.9774074 | U100: =((U92-U95)/U116)*1000 -> 5.694361 | V100: =((V92-V95)/V116)*1000 -> 0.82622178 | ... AF100: =((AF92-AF95)/AF116)*1000 -> 15.849009
A101: Reported EPS - Diluted | H101: 0.02 | I101: 0.09 | J101: -0.51 | K101: 1.6 | L101: 0.51 | M101: 1.18 | N101: 3.08 | O101: =((O92-O95)/O117)*1000 -> 3.0137463 | P101: =((P92-P95)/P117)*1000 -> -0.30258395 | Q101: =((Q92-Q95)/Q117)*1000 -> -1.0848506 | R101: =((R92-R95)/R117)*1000 -> 4.3293625 | S101: =((S92-S95)/S117)*1000 -> 8.9073951 | T101: =((T92-T95)/T117)*1000 -> 2.940397 | U101: =((U92-U95)/U117)*1000 -> 5.6255883 | V101: =((V92-V95)/V117)*1000 -> 0.79916361 | ... X101: =((X92-X95)/X117)*1000 -> -5.5866058 | Y101: =((Y92-Y95+36)/Y117)*1000 -> 8.0672538 | Z101: =(((Z92-Z95)/Z117)*1000)-0.01 -> -1.5953686 | AA101: =((AA92-AA95)/AA117)*1000 -> 8.1177065 | AB101: =((AB92-AB95)/AB117)*1000 -> 10.146828 | AC101: =((AC92-AC95)/AC117)*1000 -> 12.38768 | AD101: =((AD92-AD95)/AD117)*1000 -> 13.938867 | AE101: =((AE92-AE95)/AE117)*1000 -> 14.792315 | AF101: =((AF92-AF95)/AF117)*1000 -> 15.669071
A102: Continuing EPS - Basic | H102: 0.02 | I102: -0.24 | J102: -0.58 | K102: 1.62 | L102: 0.53 | M102: 1.17 | N102: 3.14 | O102: =((O92-O94-O95)/O116)*1000 -> 3.0147055 | P102: =((P92-P94-P95)/P116)*1000 -> -0.30258395 | Q102: =((Q92-Q94-Q95)/Q116)*1000 -> -1.1543002 | R102: =((R92-R94-R95)/R116)*1000 -> 4.2274653 | S102: =((S92-S94-S95)/S116)*1000 -> 7.0397637 | T102: =((T92-T94-T95)/T116)*1000 -> 2.9774074 | U102: =((U92-U94-U95)/U116)*1000 -> 5.694361 | V102: =((V92-V94-V95)/V116)*1000 -> 0.82622178 | ... AF102: =((AF92-AF94-AF95)/AF116)*1000 -> 15.849009
A103: Continuing EPS - Diluted | H103: 0.02 | I103: -0.24 | J103: -0.58 | K103: 1.61 | L103: 0.52 | M103: 1.17 | N103: 3.13 | O103: =((O92-O94-O95)/O117)*1000 -> 3.0137463 | P103: =((P92-P94-P95)/P117)*1000 -> -0.30258395 | Q103: =((Q92-Q94-Q95)/Q117)*1000 -> -1.1543002 | R103: =((R92-R94-R95)/R117)*1000 -> 4.1546772 | S103: =((S92-S94-S95)/S117)*1000 -> 6.9170629 | T103: =((T92-T94-T95)/T117)*1000 -> 2.940397 | U103: =((U92-U94-U95)/U117)*1000 -> 5.6255883 | V103: =((V92-V94-V95)/V117)*1000 -> 0.79916361 | ... X103: =((X92-X94-X95)/X117)*1000 -> -5.5866058 | Y103: =((Y92-Y94-Y95+36)/Y117)*1000 -> 8.0672538 | Z103: =(((Z92-Z94-Z95)/Z117)*1000)-0.01 -> -1.5953686 | AA103: =((AA92-AA94-AA95)/AA117)*1000 -> 8.1177065 | AB103: =((AB92-AB94-AB95)/AB117)*1000 -> 10.146828 | AC103: =((AC92-AC94-AC95)/AC117)*1000 -> 12.38768 | AD103: =((AD92-AD94-AD95)/AD117)*1000 -> 13.938867 | AE103: =((AE92-AE94-AE95)/AE117)*1000 -> 14.792315 | AF103: =((AF92-AF94-AF95)/AF117)*1000 -> 15.669071
A104: Adj. Reported EPS - Basic | Q104: =(Q93-Q95)/Q116*1000 -> -0.11255624 | R104: =(R93-R95)/R116*1000 -> 4.9384481 | S104: =(S93-S95-S94)/S116*1000 -> 1.7843168 | T104: =(T93-T95-20)/T116*1000 -> 4.5972284 | U104: =(U93-U95-2)/U116*1000 -> 6.2016641 | V104: =(V93-V95)/V116*1000 -> 1.9834017 | W104: =(W93-W95)/W116*1000 -> 1.778974 | X104: =(X93-X95-4)/X116*1000 -> 2.760847 | Y104: =(Y93-Y95)/Y116*1000 -> 4.856443 | Z104: =(Z93-Z95)/Z116*1000 -> 7.374753 | AA104: =(AA93-AA95)/AA116*1000 -> 8.4933209 | AB104: =(AB93-AB95)/AB116*1000 -> 11.031574 | AC104: =(AC93-AC95)/AC116*1000 -> 12.701904 | AD104: =(AD93-AD95)/AD116*1000 -> 14.294126 | AE104: =(AE93-AE95)/AE116*1000 -> 15.169269 | AF104: =(AF93-AF95)/AF116*1000 -> 16.068315
A105: Adj. Reported EPS - Diluted | Q105: =(Q93-Q95)/Q117*1000 -> -0.11255624 | R105: =(R93-R95)/R117*1000 -> 4.8534184 | S105: =(S93-S95-S94)/S117*1000 -> 1.7532168 | T105: =(T93-T95-20)/T117*1000 -> 4.540083 | U105: =(U93-U95)/U117*1000 -> 6.1313624 | V105: =(V93-V95)/V117*1000 -> 1.9184467 | W105: =(W93-W95+1)/W117*1000 -> 1.7269312 | X105: =(X93-X95-4)/X117*1000 -> 2.6763 | Y105: =(Y93-Y95)/Y117*1000 -> 4.7035799 | Z105: =(Z93-Z95)/Z117*1000 -> 7.294597 | AA105: =(AA93-AA95)/AA117*1000 -> 8.4000121 | AB105: =(AB93-AB95)/AB117*1000 -> 10.909059 | AC105: =(AC93-AC95)/AC117*1000 -> 12.559285 | AD105: =(AD93-AD95)/AD117*1000 -> 14.13184 | AE105: =(AE93-AE95)/AE117*1000 -> 14.997048 | AF105: =(AF93-AF95)/AF117*1000 -> 15.885886
A106: Adj. Continuing EPS - Basic | Q106: =(Q93-Q94-Q95)/Q116*1000 -> -0.18200583 | R106: =(R93-R94-R95)/R116*1000 -> 4.7607024 | S106: =(S93-S95)/S116*1000 -> 3.8099552 | T106: =(T93-T94-T95-20)/T116*1000 -> 4.5972284 | U106: =(U93-U94-U95-2)/U116*1000 -> 6.2016641 | V106: =(V93-V94-V95)/V116*1000 -> 1.9834017 | W106: =(W93-W94-W95)/W116*1000 -> 1.778974 | X106: =(X93-X94-X95-4)/X116*1000 -> 2.760847 | Y106: =(Y93-Y94-Y95)/Y116*1000 -> 4.856443 | Z106: =(Z93-Z94-Z95)/Z116*1000 -> 7.374753 | AA106: =(AA93-AA94-AA95)/AA116*1000 -> 8.4933209 | AB106: =(AB93-AB94-AB95)/AB116*1000 -> 11.031574 | AC106: =(AC93-AC94-AC95)/AC116*1000 -> 12.701904 | AD106: =(AD93-AD94-AD95)/AD116*1000 -> 14.294126 | AE106: =(AE93-AE94-AE95)/AE116*1000 -> 15.169269 | AF106: =(AF93-AF94-AF95)/AF116*1000 -> 16.068315
...

Sheet Cashflow Statement
A1: ='DCF Valuation'!D45 -> 340
A2: Cash Flow Statement | B2: 2000 | C2: 2001 | D2: 2002 | E2: 2003 | F2: 2004 | G2: 2005 | H2: 2006 | I2: 2007 | J2: 2008 | K2: 2009 | L2: 2010 | M2: 2011 | N2: 2012 | O2: 2013 | P2: 2014 | Q2: 2015 | R2: 2016 | S2: 2017 | T2: 2018 | U2: 2019 | V2: 2020 | W2: 2021 | X2: 2022 | Y2: 2023 | Z2: 2024 | AA2: =Z2+1 -> 2025 | AB2: =AA2+1 -> 2026 | AC2: =AB2+1 -> 2027 | AD2: =AC2+1 -> 2028 | AE2: =AD2+1 -> 2029 | AF2: =AE2+1 -> 2030 | AG2: Comments
A4: Reported Net Income | H4: ='Income Statement'!H92+'Income Statement'!H94-'Income Statement'!H95 -> 33 | I4: ='Income Statement'!I92+'Income Statement'!I94-'Income Statement'!I95 -> 53 | J4: ='Income Statement'!J92+'Income Statement'!J94-'Income Statement'!J95 -> -183 | K4: ='Income Statement'!K92+'Income Statement'!K94-'Income Statement'!K95 -> 641 | L4: ='Income Statement'!L92+'Income Statement'!L94-'Income Statement'!L95 -> 207 | M4: ='Income Statement'!M92+'Income Statement'!M94-'Income Statement'!M95 -> 478 | N4: ='Income Statement'!N92+'Income Statement'!N94-'Income Statement'!N95 -> 1282 | O4: ='Income Statement'!O92+'Income Statement'!O94-'Income Statement'!O95 -> 1255 | ... AF4: ='Income Statement'!AF92+'Income Statement'!AF94-'Income Statement'!AF95 -> 6311.1175
A5: Depreciation | H5: =575-H7 -> 298 | I5: =513-I7 -> 281 | J5: =540-J7 -> 273 | K5: =573-K7 -> 274 | L5: 291 | M5: =695-M7-M9-M10 -> 321 | N5: =962-N7-N9-N10 -> 340 | O5: =941-O7-O9-O10 -> 363 | P5: 366 | Q5: =741*(P5/(P5+P7)) -> 331.54768 | R5: =726*(Q5/(Q5+Q7)) -> 324.83619 | S5: =788*(R5/(R5+R7)) -> 352.57702 | T5: =1209*(S5/(S5+S7)) -> 540.94621 | U5: =1463*(T5/(T5+T7)) -> 654.59413 | V5: =1447*(U5/(U5+U7)) -> 647.43521 | W5: =1380*(V5/(V5+V7)) -> 617.45721 | X5: =1373*(W5/(W5+W7)) -> 614.32518 | Y5: =1336*(X5/(X5+X7)) -> 597.77017 | Z5: =1406*(Y5/(Y5+Y7)) -> 629.09046 | AA5: =AA6*'Income Statement'!AA$41 -> 703.53829 | AB5: =AB6*'Income Statement'!AB$41 -> 783.5419 | AC5: =AC6*'Income Statement'!AC$41 -> 866.38601 | AD5: =AD6*'Income Statement'!AD$41 -> 939.6958 | AE5: =AE6*'Income Statement'!AE$41 -> 985.84082 | AF5: =AF6*'Income Statement'!AF$41 -> 1033.5615
A6: as a % of sales | H6: =H5/'Income Statement'!H$41 -> 0.027488239 | I6: =I5/'Income Statement'!I$41 -> 0.028927321 | J6: =J5/'Income Statement'!J$41 -> 0.026553837 | K6: =K5/'Income Statement'!K$41 -> 0.025949427 | L6: =L5/'Income Statement'!L$41 -> 0.026387378 | M6: =M5/'Income Statement'!M$41 -> 0.02753474 | N6: =N5/'Income Statement'!N$41 -> 0.024972457 | O6: =O5/'Income Statement'!O$41 -> 0.02505176 | ... Q6: =Q5/'Income Statement'!Q$41 -> 0.02043815 | R6: =$I6 -> 0.028927321 | S6: =R6 -> 0.028927321 | T6: =T5/'Income Statement'!T41 -> 0.025728714 | U6: =U5/'Income Statement'!U41 -> 0.026081526 | V6: =V5/'Income Statement'!V41 -> 0.038929421 | W6: =W5/'Income Statement'!W41 -> 0.040802036 | X6: =X5/'Income Statement'!X41 -> 0.031466741 | Y6: =Y5/'Income Statement'!Y41 -> 0.025274626 | Z6: =Z5/'Income Statement'!Z41 -> 0.022697736 | AA6: =Z6 -> 0.022697736 | AB6: =AA6 -> 0.022697736 | AC6: =AB6 -> 0.022697736 | AD6: =AC6 -> 0.022697736 | AE6: =AD6 -> 0.022697736 | AF6: =AE6 -> 0.022697736
A7: Amortisation | H7: 277 | I7: 232 | J7: 267 | K7: 299 | L7: 315 | M7: 341 | N7: 381 | O7: 399 | P7: 452 | Q7: =741-Q5 -> 409.45232 | R7: =726-R5 -> 401.16381 | S7: =788-S5 -> 435.42298 | T7: =1209-T5 -> 668.05379 | U7: =1463-U5 -> 808.40587 | V7: =1447-V5 -> 799.56479 | W7: =1380-W5 -> 762.54279 | X7: =1373-X5 -> 758.67482 | Y7: =1336-Y5 -> 738.22983 | Z7: =1406-Z5 -> 776.90954 | AA7: =AA8*'Income Statement'!AA$41 -> 868.85057 | AB7: =AB8*'Income Statement'!AB$41 -> 1035.6212 | AC7: =AC8*'Income Statement'!AC$41 -> 1068.7765 | AD7: =AD8*'Income Statement'!AD$41 -> 1159.2117 | AE7: =AE8*'Income Statement'!AE$41 -> 1216.1364 | AF7: =AF8*'Income Statement'!AF$41 -> 1275.0048
A8: as a % of sales | H8: =H7/'Income Statement'!H$41 -> 0.025551148 | I8: =I7/'Income Statement'!I$41 -> 0.023883055 | J8: =J7/'Income Statement'!J$41 -> 0.025970236 | K8: =K7/'Income Statement'!K$41 -> 0.028317075 | L8: =L7/'Income Statement'!L$41 -> 0.028563656 | M8: =M7/'Income Statement'!M$41 -> 0.0292503 | N8: =N7/'Income Statement'!N$41 -> 0.027983841 | O8: =O7/'Income Statement'!O$41 -> 0.027536232 | ... Q8: =Q7/'Income Statement'!Q$41 -> 0.025240557 | R8: =AVERAGE(M8:Q8) -> 0.028011226 | S8: =R8 -> 0.028011226 | T8: =T7/'Income Statement'!T41 -> 0.031774259 | U8: =U7/'Income Statement'!U41 -> 0.032209972 | V8: =V7/'Income Statement'!V41 -> 0.048076772 | W8: =W7/'Income Statement'!W41 -> 0.0503894 | X8: =X7/'Income Statement'!X41 -> 0.038860565 | Y8: =Y7/'Income Statement'!Y41 -> 0.031213472 | Z8: =Z7/'Income Statement'!Z41 -> 0.028031084 | AA8: =Z8 -> 0.028031084 | AB8: 0.03 | AC8: 0.028 | AD8: 0.028 | AE8: 0.028 | AF8: 0.028
A9: Impairment | H9: 129 | I9: 210 | J9: -10 | K9: 177 | L9: -3 | M9: 62 | N9: 54 | O9: 103 | P9: 137 | Q9: 1004 | R9: 243 | S9: 60 | T9: -19 | U9: -42 | V9: 377 | W9: 91 | X9: 411 | Y9: 148 | Z9: 0 | AA9: =Z9 -> 0 | AB9: =AA9 -> 0 | AC9: =AB9 -> 0 | AD9: =AC9 -> 0 | AE9: =AD9 -> 0 | AF9: =AE9 -> 0
A10: Change in Provisions | H10: 247 | I10: 178 | J10: 160 | K10: 25 | L10: 46 | M10: -29 | N10: 187 | O10: 76 | P10: 205 | Q10: 114 | R10: -42 | S10: 178 | T10: 45 | U10: 168 | V10: -259 | W10: 171 | X10: -169 | Y10: -51 | Z10: 285 | AA10: 100 | AB10: 100 | AC10: 100 | AD10: 100 | AE10: 100 | AF10: 100
A11: Share of profit in associates (net of dividends received) | H11: 4 | I11: 4 | J11: -4 | K11: -2 | L11: -9 | M11: -10 | N11: -19 | O11: =-'Income Statement'!O83 -> -15 | P11: -36 | Q11: -20 | R11: -63 | S11: -100 | T11: -124 | U11: -87 | V11: 22 | W11: 702 | X11: 11 | Y11: -83 | Z11: -120 | AA11: =-'Income Statement'!AA83 -> 0 | AB11: =-'Income Statement'!AB83 -> 0 | AC11: =-'Income Statement'!AC83 -> 0 | AD11: =-'Income Statement'!AD83 -> 0 | AE11: =-'Income Statement'!AE83 -> 0 | AF11: =-'Income Statement'!AF83 -> 0
A12: Change in fair value of derivatives | H12: 135 | I12: 368 | J12: 546 | K12: -546 | L12: 310 | M12: 2 | N12: -779 | O12: -432 | P12: 1934 | Q12: 2475 | R12: 81 | S12: -3608 | T12: 316 | U12: -152 | V12: 209 | W12: 538 | X12: 4207 | Y12: -2161 | Z12: 4684
A13: Capital gains on asset disposals | H13: -39 | I13: 7 | J13: -127 | K13: 6 | L13: 31 | M13: 16 | N13: 10 | O13: -382 | P13: -12 | Q13: -453 | R13: -364 | S13: -20 | T13: 12 | U13: -41 | V13: 20 | W13: -57 | X13: 289 | Y13: 344 | Z13: -47
A14: Profit/(Loss) before tax from discontinued operations | H14: 0 | I14: -36 | J14: 308 | K14: -1 | L14: 5 | M14: -4 | N14: -1 | Q14: -26 | R14: -110 | S14: -997
A15: Profit attributable to non-controlling interests | H15: 12 | I15: 7 | J15: 11 | K15: 13 | L15: 18 | M15: 19 | N15: 24 | O15: 29 | P15: ='Income Statement'!P95 -> 58 | Q15: ='Income Statement'!Q95 -> 47 | R15: 55 | S15: 60 | T15: 58 | U15: 65 | V15: ='Income Statement'!V95 -> 34 | W15: ='Income Statement'!W95 -> 25 | X15: ='Income Statement'!X95 -> 33 | Y15: ='Income Statement'!Y95 -> 76 | Z15: ='Income Statement'!Z95 -> 92 | AA15: ='Income Statement'!AA95 -> 102.88746 | AB15: ='Income Statement'!AB95 -> 114.58742 | AC15: ='Income Statement'!AC95 -> 126.70278 | ... AF15: ='Income Statement'!AF95 -> 151.15101
A16: Co-detailed Other | H16: =7-19 -> -12 | I16: =22+4 -> 26 | J16: =25+6 -> 31 | K16: =-24+7 -> -17 | L16: =4+6 -> 10 | M16: 4 | N16: 222 | O16: 457 | P16: -510 | Q16: -821 | R16: 217 | S16: 1150 | T16: 318 | U16: 221 | V16: -328 | W16: -707 | X16: -880 | Y16: 459 | Z16: -907
A17: Cash Tax adjustment | H17: =-202-'Income Statement'!H86 -> -93 | I17: =-212-'Income Statement'!I86 -> -187 | J17: =-257-'Income Statement'!J86 -> -399 | K17: =-73-'Income Statement'!K86 -> 162 | L17: =-103-'Income Statement'!L86 -> -89 | M17: 42 | N17: 337 | O17: -14 | AA17: 330 | AB17: -130 | AC17: -200
A18: Change in Inventory and Work in Progress | H18: -461 | I18: -421 | J18: -337 | K18: 387 | L18: 55 | M18: -134 | N18: -388 | O18: 45 | P18: -185 | Q18: -280 | R18: -347 | S18: -280 | T18: -393 | U18: -590 | V18: 1016 | W18: 296 | X18: -1545 | Y18: -1494 | Z18: -1452 | AA18: =-('Balance Sheet'!AA18-'Balance Sheet'!Z18) -> -558.08419 | AB18: =-('Balance Sheet'!AB18-'Balance Sheet'!AA18) -> -80.744285 | AC18: =-('Balance Sheet'!AC18-'Balance Sheet'!AB18) -> -709.71164 | AD18: =-('Balance Sheet'!AD18-'Balance Sheet'!AC18) -> -917.19435 | AE18: =-('Balance Sheet'!AE18-'Balance Sheet'!AD18) -> -714.37538 | AF18: =-('Balance Sheet'!AF18-'Balance Sheet'!AE18) -> -675.51688
A19: Change in operating receivables and payables | H19: 254 | I19: 318 | J19: 228 | K19: -45 | L19: 185 | M19: 216 | N19: 228 | O19: 178 | P19: -58 | Q19: 210 | R19: 219 | S19: 890 | T19: -280 | U19: -563 | V19: 41 | W19: -53 | X19: -81 | Y19: 478 | Z19: 549 | AA19: =-'Balance Sheet'!AA80-'Balance Sheet'!AA81 -> 692.32885 | AB19: =-'Balance Sheet'!AB80-'Balance Sheet'!AB81 -> 308.75692 | AC19: =-'Balance Sheet'!AC80-'Balance Sheet'!AC81 -> 655.12436 | AD19: =-'Balance Sheet'!AD80-'Balance Sheet'!AD81 -> 415.26463 | AE19: =-'Balance Sheet'!AE80-'Balance Sheet'!AE81 -> 269.47841 | AF19: =-'Balance Sheet'!AF80-'Balance Sheet'!AF81 -> 76.043666
A20: Change in contract assets and liabilities | S20: =86+10 -> 96 | T20: =746+2 -> 748 | U20: =218+11 -> 229 | V20: =-982-17 -> -999 | W20: =131-43 -> 88 | X20: =2451-118 -> 2333 | Y20: =2073-103 -> 1970 | Z20: =1004-89 -> 915 | AA20: =-('Balance Sheet'!AA44-'Balance Sheet'!Z44)-('Balance Sheet'!AA25-'Balance Sheet'!Z25) -> 0 | AB20: =-('Balance Sheet'!AB44-'Balance Sheet'!AA44)-('Balance Sheet'!AB25-'Balance Sheet'!AA25) -> 0 | AC20: =-('Balance Sheet'!AC44-'Balance Sheet'!AB44)-('Balance Sheet'!AC25-'Balance Sheet'!AB25) -> 0 | AD20: =-('Balance Sheet'!AD44-'Balance Sheet'!AC44)-('Balance Sheet'!AD25-'Balance Sheet'!AC25) -> 0 | AE20: =-('Balance Sheet'!AE44-'Balance Sheet'!AD44)-('Balance Sheet'!AE25-'Balance Sheet'!AD25) -> 0 | AF20: =-('Balance Sheet'!AF44-'Balance Sheet'!AE44)-('Balance Sheet'!AF25-'Balance Sheet'!AE25) -> 0
A21: Change in other receivables and payables | H21: 58 | I21: -10 | J21: 18 | K21: -5 | L21: 77 | M21: -35 | N21: 75 | O21: -68 | P21: 132 | Q21: 75 | R21: -40 | S21: -15 | T21: -102 | U21: 27 | V21: -66 | W21: -81 | X21: 22 | Y21: -196 | Z21: -5
A22: Change in Working Capital | W22: =W18+W19+W20+W21 -> 250 | X22: =X18+X19+X20+X21 -> 729 | Y22: =Y18+Y19+Y20+Y21 -> 758 | Z22: =Z18+Z19+Z20+Z21 -> 7 | AA22: =AA18+AA19+AA20+AA21 -> 134.24466 | AB22: =AB18+AB19+AB20+AB21 -> 228.01264 | AC22: =AC18+AC19+AC20+AC21 -> -54.587281 | AD22: =AD18+AD19+AD20+AD21 -> -501.92972 | ... AF22: =AF18+AF19+AF20+AF21 -> -599.47322
A23: Other | H23: =H24-SUM(H4:H21) -> 11.946961 | I23: =I24-SUM(I4:I21) -> 77.94719 | J23: =J24-SUM(J4:J21) -> -156.05252 | K23: =K24-SUM(K4:K21) -> 39.945733 | L23: =L24-SUM(L4:L21) -> -19.054951 | M23: =M24-SUM(M4:M5,M7,M9:M21) -> -52 | N23: =N24-SUM(N4:N5,N7,N9:N21) -> -336 | O23: =O24-SUM(O4:O5,O7,O9:O21) -> 145 | P23: =P24-SUM(P4:P5,P7,P9:P21) -> 0 | Q23: =Q24-SUM(Q4:Q5,Q7,Q9:Q21) -> -11 | R23: =R24-SUM(R4:R5,R7,R9:R21) -> 0 | S23: =S24-SUM(S4:S5,S7,S9:S21) -> 0 | T23: =T24-SUM(T4:T5,T7,T9:T21) -> 0 | ... AF23: =AF24-SUM(AF4:AF5,AF7,AF9:AF21) -> 0
A24: Cash flow from Operations | H24: 854 | I24: =1013+95 -> 1108 | J24: =720-94 -> 626 | K24: =1403+5 -> 1408 | L24: =1459-29 -> 1430 | M24: =1247-10 -> 1237 | N24: 1617 | O24: 2139 | P24: 2357 | Q24: 2631 | R24: =SUM(R4:R5,R7,R9:R21) -> 2483 | S24: =SUM(S4:S5,S7,S9:S21) -> 2752 | T24: =SUM(T4:T5,T7,T9:T21) -> 3071 | U24: =SUM(U4:U5,U7,U9:U21) -> 3145 | V24: =SUM(V4:V5,V7,V9:V21) -> 1866 | W24: =SUM(W4:W5,W7,W9:W17)+W22 -> 2436 | X24: =SUM(X4:X5,X7,X9:X17)+X22 -> 3545 | Y24: =SUM(Y4:Y5,Y7,Y9:Y17)+Y22 -> 4270 | Z24: =SUM(Z4:Z5,Z7,Z9:Z17)+Z22 -> 4733 | AA24: =SUM(AA4:AA5,AA7,AA9:AA17)+AA22 -> 5618.3997 | AB24: =SUM(AB4:AB5,AB7,AB9:AB21) -> 6309.7085 | AC24: =SUM(AC4:AC5,AC7,AC9:AC21) -> 6952.3116 | AD24: =SUM(AD4:AD5,AD7,AD9:AD21) -> 7448.6352 | AE24: =SUM(AE4:AE5,AE7,AE9:AE21) -> 7959.234 | AF24: =SUM(AF4:AF5,AF7,AF9:AF21) -> 8271.3616
A26: Purchase of Intangible assets (net of disposals) | H26: -343 | I26: -252 | J26: -230 | K26: -292 | L26: -254 | M26: -363 | N26: -634 | O26: =-720-215 -> -935 | P26: =-676-267 -> -943 | Q26: =-495-502 -> -997 | R26: -324 | S26: =-225-349 -> -574 | T26: =-183-327 -> -510 | U26: =-333-134 -> -467 | V26: =-287-57 -> -344 | W26: =-316-53 -> -369 | X26: =-283-98 -> -381 | Y26: =-323-179 -> -502 | Z26: =-328-172 -> -500 | AA26: =Z26-50 -> -550 | AB26: =AA26 -> -550 | AC26: =AB26 -> -550 | AD26: =AC26 -> -550 | AE26: =AD26 -> -550 | AF26: =AE26 -> -550 | AG26: pretty flat over CMD plan
A27: as a % of sales | H27: =H26/'Income Statement'!H$41 -> -0.031639148 | I27: =I26/'Income Statement'!I$41 -> -0.025941939 | J27: =J26/'Income Statement'!J$41 -> -0.022371365 | K27: =K26/'Income Statement'!K$41 -> -0.027654134 | L27: =L26/'Income Statement'!L$41 -> -0.023032281 | M27: =M26/'Income Statement'!M$41 -> -0.031137416 | N27: =N26/'Income Statement'!N$41 -> -0.046566287 | O27: =O26/'Income Statement'!O$41 -> -0.06452726 | ... AF27: =AF26/'Income Statement'!AF$41 -> -0.012078386
A28: Purchase of PP&E (net of disposals) | H28: -346 | I28: -387 | J28: -441 | K28: -293 | L28: -271 | M28: -352 | N28: -419 | O28: -492 | P28: -674 | Q28: -705 | R28: -704 | S28: -740 | T28: -780 | U28: -695 | V28: -449 | W28: -387 | X28: -498 | Y28: -823 | Z28: -1044 | AA28: =AA29*'Income Statement'!AA$41 -> -1549.7983 | AB28: =AB29*'Income Statement'!AB$41 -> -1553.4318 | AC28: =AC29*'Income Statement'!AC$41 -> -1526.8236 | AD28: =AD29*'Income Statement'!AD$41 -> -1449.0147 | AE28: =AE29*'Income Statement'!AE$41 -> -1303.0033 | AF28: =AF29*'Income Statement'!AF$41 -> -1138.3971 | AG28: Use of Cash Analysis
A29: as a % of sales | H29: =H28/'Income Statement'!H$41 -> -0.031915875 | I29: =I28/'Income Statement'!I$41 -> -0.039839407 | J29: =J28/'Income Statement'!J$41 -> -0.04289466 | K29: =K28/'Income Statement'!K$41 -> -0.02774884 | L29: =L28/'Income Statement'!L$41 -> -0.024573812 | M29: =M28/'Income Statement'!M$41 -> -0.030193858 | N29: =N28/'Income Statement'!N$41 -> -0.030774881 | O29: =O28/'Income Statement'!O$41 -> -0.033954451 | ... Z29: =Z28/'Income Statement'!Z$41 -> -0.037667773 | AA29: -0.05 | AB29: =AA29+0.005 -> -0.045 | AC29: =AB29+0.005 -> -0.04 | AD29: =AC29+0.005 -> -0.035 | AE29: =AD29+0.005 -> -0.03 | AF29: =AE29+0.005 -> -0.025 | AG29: CMD'24 p77: c.4% tangible capex with a peak @5% in 2025
A30: Proceeds/(Payments) from Investments | H30: =-53+14 -> -39 | I30: -68 | J30: -221 | K30: -560 | L30: -122 | M30: -1176 | N30: -193 | O30: =-733+353 -> -380 | P30: =-272+5 -> -267 | Q30: =622-39 -> 583 | R30: -810 | S30: -54 | T30: -4172 | U30: -29 | V30: -21 | W30: -33 | X30: -490 | Y30: -328 | Z30: -344 | AA30: =Z30 -> -344 | AB30: =AA30 -> -344 | AC30: =AB30 -> -344 | AD30: =AC30 -> -344 | AE30: =AD30 -> -344 | AF30: =AE30 -> -344
A31: of which additions to PP&E | R31: =R30*0.5 -> -405 | S31: =S30*0.5 -> -27 | T31: =T30*0.5 -> -2086 | U31: =U30*0.5 -> -14.5 | V31: =V30*0.5 -> -10.5 | W31: =W30*0.5 -> -16.5 | X31: =X30*0.5 -> -245 | Y31: =Y30*0.5 -> -164 | ... AF31: =AF30*0.5 -> -172 | AG31: historical goodwill/purchase price has been 50/50
A32: of which additions to Intangibles (Goodwill) | R32: =R30-R31 -> -405 | S32: =S30-S31 -> -27 | T32: =T30-T31 -> -2086 | U32: =U30-U31 -> -14.5 | V32: =V30-V31 -> -10.5 | W32: =W30-W31 -> -16.5 | X32: =X30-X31 -> -245 | Y32: =Y30-Y31 -> -164 | ... AF32: =AF30-AF31 -> -172
A33: Proceeds/(Payments) from Financial Assets | H33: 13 | I33: -26 | J33: 109 | K33: -9 | L33: -53 | M33: -6 | N33: -86 | O33: -35 | P33: -70 | Q33: -61 | R33: 5 | S33: -1974 | T33: 1950 | U33: 39 | V33: 14 | W33: -212 | X33: -167 | Y33: -202 | Z33: -73
A34: Other | H34: =H35-SUM(H26,H28,H30:H33) -> 9 | I34: =I35-SUM(I26,I28,I30:I33) -> -34 | J34: =J35-SUM(J26,J28,J30:J33) -> -12 | K34: =K35-SUM(K26,K28,K30:K33) -> 0 | L34: =L35-SUM(L26,L28,L30:L33) -> 1 | M34: =M35-SUM(M26,M28,M30:M33) -> -2 | N34: =N35-SUM(N26,N28,N30:N33) -> 0 | O34: =O35-SUM(O26,O28,O30,O33) -> 0 | P34: =P35-SUM(P26,P28,P30,P33) -> 0 | Q34: =Q35-SUM(Q26,Q28,Q30,Q33) -> 0 | R34: =-364+2 -> -362 | S34: =3060 -> 3060 | T34: =18 -> 18 | U34: 47 | V34: 1 | W34: 263 | X34: 248 | Y34: 151 | Z34: 113 | AA34: =AA35-SUM(AA26,AA28,AA30,AA33) -> 0 | AB34: =AB35-SUM(AB26,AB28,AB30,AB33) -> 0 | AC34: =AC35-SUM(AC26,AC28,AC30,AC33) -> 0 | AD34: =AD35-SUM(AD26,AD28,AD30,AD33) -> 0 | AE34: =AE35-SUM(AE26,AE28,AE30,AE33) -> 0 | AF34: =AF35-SUM(AF26,AF28,AF30,AF33) -> 0
A35: Cash flow from Investing | H35: -706 | I35: =-734-33 -> -767 | J35: =-788-7 -> -795 | K35: -1154 | L35: -699 | M35: =-1897-2 -> -1899 | N35: -1332 | O35: -1842 | P35: -1954 | Q35: -1180 | R35: =SUM(R26,R28,R30,R33,R34) -> -2195 | S35: =SUM(S26,S28,S30,S33,S34) -> -282 | T35: =SUM(T26,T28,T30,T33,T34) -> -3494 | U35: =SUM(U26,U28,U30,U33,U34) -> -1105 | V35: =SUM(V26,V28,V30,V33,V34) -> -799 | W35: =SUM(W26,W28,W30,W33,W34) -> -738 | X35: =SUM(X26,X28,X30,X33,X34) -> -1288 | Y35: =SUM(Y26,Y28,Y30,Y33,Y34) -> -1704 | Z35: =SUM(Z26,Z28,Z30,Z33,Z34) -> -1848 | AA35: =SUM(AA26,AA28,AA30,AA33) -> -2443.7983 | AB35: =SUM(AB26,AB28,AB30,AB33) -> -2447.4318 | AC35: =SUM(AC26,AC28,AC30,AC33) -> -2420.8236 | AD35: =SUM(AD26,AD28,AD30,AD33) -> -2343.0147 | AE35: =SUM(AE26,AE28,AE30,AE33) -> -2197.0033 | AF35: =SUM(AF26,AF28,AF30,AF33) -> -2032.3971
A37: Change in Share Capital | H37: 8 | I37: 19 | J37: 0 | K37: 1 | L37: 6 | M37: 1 | N37: 0 | Q37: -5 | R37: -9 | S37: -4 | T37: -1 | U37: =2-9 -> -7 | V37: 0 | W37: 1 | X37: 0 | Y37: 2 | Z37: 0
A38: Acquisitions and disposals of treasury shares | I38: 0 | J38: -151 | K38: 5 | L38: 0 | M38: 180 | N38: 118 | O38: 2 | P38: -1 | R38: -38 | S38: -449 | T38: -539 | U38: -1299 | V38: 96 | W38: -73 | X38: -270 | Y38: -1535 | Z38: -1320
A39: Repayment of borrowings and long-term debt | H39: -129 | I39: -86 | J39: -93 | K39: -218 | L39: -138 | M39: -254 | N39: -119 | O39: -111 | P39: -850 | Q39: -79 | R39: -73 | S39: -66 | T39: -1895 | U39: -875 | V39: -778 | W39: -1367 | X39: -654 | Y39: -311 | Z39: -863
A40: Increase in borrowings | H40: 67 | I40: 24 | J40: 136 | K40: 794 | L40: 324 | M40: 32 | N40: 917 | O40: 9 | P40: 209 | Q40: 12 | R40: 682 | S40: 1058 | T40: 1480 | U40: 24 | V40: 1595 | W40: 2146 | X40: 510 | Y40: 17 | Z40: 56 | AA40: 0 | AB40: 0 | AC40: 0 | AD40: 0 | AE40: 0 | AF40: 0
A41: Change in repayable advances | H41: =71-46 -> 25 | I41: =41-57 -> -16 | J41: =112-31 -> 81 | K41: =-36+69 -> 33 | L41: =-35+17 -> -18 | M41: -15 | N41: -9 | O41: -27 | P41: 3 | Q41: -14 | R41: -24 | S41: -25 | T41: -10 | U41: -27 | V41: -10 | W41: -12 | X41: -17 | Y41: -5 | Z41: -21
A42: Change in short term borrowings | H42: -151 | I42: -97 | J42: 465 | K42: 381 | L42: -802 | M42: 390 | N42: -122 | O42: -191 | P42: 809 | Q42: -631 | R42: 10 | S42: 449 | T42: -472 | U42: 1261 | V42: -831 | W42: -775 | X42: -159 | Y42: -161 | Z42: 45
A43: Dividends Paid | H43: -148 | I43: -90 | J43: -197 | K43: -68 | L43: -152 | M43: -304 | N43: -283 | O43: -471 | P43: -500 | Q43: -517 | R43: -612 | S43: -340 | T43: -695 | U43: -785 | V43: 0 | W43: -183 | X43: -213 | Y43: -564 | Z43: -911 | AA43: =-((AA44*'Income Statement'!Z116)+(AA45*'Income Statement'!AA116))/1000 -> -1206.8336 | AB43: =-((AB44*'Income Statement'!AA116)+(AB45*'Income Statement'!AB116))/1000 -> -1398.5537 | AC43: =-((AC44*'Income Statement'!AB116)+(AC45*'Income Statement'!AC116))/1000 -> -1796.7174 | AD43: =-((AD44*'Income Statement'!AC116)+(AD45*'Income Statement'!AD116))/1000 -> -2045.9688 | AE43: =-((AE44*'Income Statement'!AD116)+(AE45*'Income Statement'!AE116))/1000 -> -2276.7835 | AF43: =-((AF44*'Income Statement'!AE116)+(AF45*'Income Statement'!AF116))/1000 -> -2416.1772
A44: Final From Previous Year (€) | J44: 0.4 | K44: 0.25 | L44: 0.38 | M44: 0.5 | N44: 0.37 | O44: ='Income Statement'!N109-N45 -> 0.65 | P44: ='Income Statement'!O109-O45 -> 0.64 | Q44: 0.64 | R44: ='Income Statement'!Q109-Q45 -> 0.78 | S44: ='Income Statement'!R109-R45 -> 0.92 | T44: ='Income Statement'!S109-S45 -> 1.6 | U44: ='Income Statement'!T109-T45 -> 1.82 | V44: ='Income Statement'!U109-U45 -> 0 | W44: ='Income Statement'!V109-V45 -> 0.43 | X44: ='Income Statement'!W109-W45 -> 0.5 | Y44: ='Income Statement'!X109-X45 -> 1.35 | ... AF44: ='Income Statement'!AE109-AE45 -> 6.0677075
A45: Interim from Reported Year (€) | J45: 0.08 | K45: 0 | L45: 0 | M45: 0.25 | N45: 0.31 | O45: 0.48 | P45: ='Income Statement'!P109-Q44 -> 0.56 | Q45: 0.6 | R45: =Q45*(1+'Income Statement'!R111) -> 0.6
A46: Dividends paid to non-controlling interests | H46: -7 | I46: -6 | J46: -5 | K46: -5 | L46: -9 | M46: -13 | N46: -17 | O46: -10 | P46: -11 | Q46: -23 | R46: -30 | S46: -32 | T46: -26 | U46: -32 | V46: -4 | W46: -5 | X46: -12 | Y46: -19 | Z46: -59
A47: Share Buybacks | H47: 0 | I47: 0 | J47: 0 | K47: 0 | L47: 0 | M47: 0 | N47: 0 | O47: 0 | AA47: =-5000/4 -> -1250 | AB47: =-5000/4 -> -1250 | AC47: =-5000/4 -> -1250 | AD47: =-5000/4 -> -1250
A48: Other | H48: =H49-SUM(H37:H43,H46) -> 0 | I48: =I49-SUM(I37:I43,I46) -> -63 | J48: =J49-SUM(J37:J43,J46) -> 135 | K48: =K49-SUM(K37:K43,K46) -> -31 | L48: =L49-SUM(L37:L43,L46) -> 28 | M48: =M49-SUM(M37:M43,M46) -> 11 | N48: =N49-SUM(N37:N43,N46) -> 0 | O48: =O49-SUM(O37:O43,O46:O47) -> 0 | P48: =P49-SUM(P37:P43,P46:P47) -> 0 | Q48: =Q49-SUM(Q37:Q43,Q46:Q47) -> 0 | R48: =R49-SUM(R37:R43,R46:R47) -> 0 | S48: =S49-SUM(S37:S43,S46:S47) -> 0 | T48: =T49-SUM(T37:T43,T46:T47) -> 0 | U48: =U49-SUM(U37:U43,U46:U47) -> 0 | V48: =V49-SUM(V37:V43,V46:V47) -> 0 | ... X48: =X49-SUM(X37:X43,X46:X47) -> 0 | Y48: =Y49-SUM(Y37:Y43,Y46) -> 0 | Z48: =Z49-SUM(Z37:Z43,Z46) -> 0 | AA48: =AA49-SUM(AA37:AA43,AA46:AA47) -> 0 | AB48: =AB49-SUM(AB37:AB43,AB46:AB47) -> 0 | AC48: =AC49-SUM(AC37:AC43,AC46:AC47) -> 0 | AD48: =AD49-SUM(AD37:AD43,AD46:AD47) -> 0 | AE48: =AE49-SUM(AE37:AE43,AE46:AE47) -> 0 | AF48: =AF49-SUM(AF37:AF43,AF46:AF47) -> 0
A49: Cash flow from Financing | H49: -335 | I49: =-316+1 -> -315 | J49: =369+2 -> 371 | K49: =893-1 -> 892 | L49: -761 | M49: 28 | N49: 485 | O49: -799 | P49: -341 | Q49: -1257 | R49: =SUM(R37:R43,R46:R47) -> -94 | S49: =SUM(S37:S43,S46:S47) -> 591 | T49: =SUM(T37:T43,T46:T47) -> -2158 | U49: =SUM(U37:U43,U46:U47) -> -1740 | V49: =SUM(V37:V43,V46:V47) -> 68 | W49: =SUM(W37:W43,W46:W47) -> -268 | X49: =SUM(X37:X43,X46:X47) -> -815 | Y49: =SUM(Y37:Y43,Y46) -> -2576 | Z49: =SUM(Z37:Z43,Z46) -> -3073 | AA49: =SUM(AA37:AA43,AA46:AA47) -> -2456.8336 | AB49: =SUM(AB37:AB43,AB46:AB47) -> -2648.5537 | AC49: =SUM(AC37:AC43,AC46:AC47) -> -3046.7174 | AD49: =SUM(AD37:AD43,AD46:AD47) -> -3295.9688 | AE49: =SUM(AE37:AE43,AE46:AE47) -> -2276.7835 | AF49: =SUM(AF37:AF43,AF46:AF47) -> -2416.1772
A51: Change in Cash | H51: =H24+H35+H49 -> -187 | I51: =I24+I35+I49 -> 26 | J51: =J24+J35+J49 -> 202 | K51: =K24+K35+K49 -> 1146 | L51: =L24+L35+L49 -> -30 | M51: =M24+M35+M49 -> -634 | N51: =N24+N35+N49 -> 770 | O51: =O24+O35+O49 -> -502 | P51: =P24+P35+P49 -> 62 | Q51: =Q24+Q35+Q49+121-88-21 -> 206 | R51: =R24+R35+R49+(171-111-8) -> 246 | S51: =S24+S35+S49+(14-52-198) -> 2825 | T51: =T24+T35+T49 -> -2581 | U51: =U24+U35+U49 -> 300 | V51: =V24+V35+V49 -> 1135 | W51: =W24+W35+W49 -> 1430 | X51: =X24+X35+X49 -> 1442 | Y51: =Y24+Y35+Y49 -> -10 | Z51: =Z24+Z35+Z49 -> -188 | AA51: =AA24+AA35+AA49 -> 717.7677 | ... AF51: =AF24+AF35+AF49 -> 3822.7872
A52: FX | H52: -6 | I52: -2 | J52: -2 | K52: 4 | L52: 12 | M52: 3 | N52: -8 | O52: -19 | P52: 24 | Q52: 6 | R52: 15 | S52: -17 | T52: -3 | U52: 2 | V52: -20 | W52: 70 | X52: -2 | Y52: -1 | Z52: 26
A53: Other | I53: -37 | J53: -11 | K53: 11 | O53: -125 | S53: 180
A54: Cash at the beginning of the year | H54: 936 | I54: 743 | J54: 730 | K54: 919 | L54: 2080 | M54: 2062 | N54: 1431 | O54: =N55 -> 2193 | P54: =O55 -> 1547 | Q54: =P55 -> 1633 | R54: =Q55+186 -> 1845 | S54: =R55 -> 1926 | T54: =S55 -> 4914 | U54: =T55 -> 2330 | V54: =U55 -> 2632 | W54: =V55 -> 3747 | X54: =W55 -> 5247 | Y54: =X55 -> 6687 | Z54: =Y55 -> 6676 | ... AF54: =AE55 -> 15225.36
A55: Cash at the end of the year | H55: =SUM(H51:H54) -> 743 | I55: =SUM(I51:I54) -> 730 | J55: =SUM(J51:J54) -> 919 | K55: =SUM(K51:K54) -> 2080 | L55: =SUM(L51:L54) -> 2062 | M55: =SUM(M51:M54) -> 1431 | N55: =SUM(N51:N54) -> 2193 | O55: =SUM(O51:O54) -> 1547 | P55: =SUM(P51:P54) -> 1633 | Q55: =SUM(Q51:Q54)-186 -> 1659 | R55: =SUM(R51:R54)-180 -> 1926 | S55: =SUM(S51:S54) -> 4914 | T55: =SUM(T51:T54) -> 2330 | U55: =SUM(U51:U54) -> 2632 | V55: =SUM(V51:V54) -> 3747 | W55: =SUM(W51:W54) -> 5247 | X55: =SUM(X51:X54) -> 6687 | Y55: =SUM(Y51:Y54) -> 6676 | Z55: =SUM(Z51:Z54) -> 6514 | ... AF55: =SUM(AF51:AF54) -> 19048.148
A57: Company defined FCF | H57: =H24+SUM(H26,H28) -> 165 | I57: =I24+SUM(I26,I28)-95 -> 374 | J57: =J24+SUM(J26,J28)+94 -> 49 | K57: =K24+SUM(K26,K28)-5 -> 818 | L57: =L24+SUM(L26,L28)+29 -> 934 | M57: =M24+SUM(M26,M28)+10 -> 532 | N57: =N24+SUM(N26,N28)+1 -> 565 | O57: =O24+SUM(O26,O28) -> 712 | P57: =P24+SUM(P26,P28) -> 740 | Q57: =Q24+SUM(Q26,Q28) -> 929 | R57: =R24+SUM(R26,R28) -> 1455 | S57: =S24+SUM(S26,S28) -> 1438 | T57: =T24+SUM(T26,T28) -> 1781 | U57: =U24+SUM(U26,U28) -> 1983 | V57: =V24+SUM(V26,V28) -> 1073 | ... AF57: =AF24+SUM(AF26,AF28) -> 6582.9645 | AG57: Company guide to 15-17bn cumulative FCF; 3.4-3.6bn FY25 | AH57: =SUM(Z57:AD57) -> 21238.987 | AI57: =3189+3227+4114+4700+5319 -> 20549
A58: % of underlying EBITA | O58: -4.5063291 | P58: -4.2285714 | Q58: -11.329268 | R58: -58.2 | S58: -39.944444 | T58: 0.58914985 | U58: 0.51910995 | V58: 0.63641756 | W58: 0.93074792 | X58: 1.1071429 | Y58: 0.93019583 | Z58: 0.77421704 | AA58: =AA57/'Income Statement'!AA70 -> 0.67938972 | AB58: =AB57/'Income Statement'!AB70 -> 0.699308 | AC58: =AC57/'Income Statement'!AC70 -> 0.71227181 | AD58: =AD57/'Income Statement'!AD70 -> 0.71666035 | AE58: =AE57/'Income Statement'!AE70 -> 0.75849196 | AF58: =AF57/'Income Statement'!AF70 -> 0.77532289 | AG58: Below Cons on FCF on all years
A59: FCF per share | T59: =T57/'Income Statement'!T116*1000 -> 4.1330963 | U59: =U57/'Income Statement'!U116*1000 -> 4.6145966 | V59: =V57/'Income Statement'!V116*1000 -> 2.5185681 | W59: =W57/'Income Statement'!W116*1000 -> 3.9376499 | X59: =X57/'Income Statement'!X116*1000 -> 6.2482326 | Y59: =Y57/'Income Statement'!Y116*1000 -> 7.0489032 | Z59: =Z57/'Income Statement'!Z116*1000 -> 7.6631109 | AA59: =AA57/'Income Statement'!AA116*1000 -> 8.5472898 | ... AF59: =AF57/'Income Statement'!AF116*1000 -> 16.531694
A61: Unlevered op cash flow, post tax, post capex | B61: =B2 -> 2000 | C61: =C2 -> 2001 | D61: =D2 -> 2002 | E61: =E2 -> 2003 | F61: =F2 -> 2004 | G61: =G2 -> 2005 | H61: =H2 -> 2006 | I61: =I2 -> 2007 | ... Z61: =Z2 -> 2024 | AA61: =Z61+1 -> 2025 | AB61: =AA61+1 -> 2026 | AC61: =AB61+1 -> 2027 | AD61: =AC61+1 -> 2028 | AE61: =AD61+1 -> 2029 | AF61: =AE61+1 -> 2030
A62: Cash provided by operating activities | W62: =W24 -> 2436 | X62: =X24 -> 3545 | Y62: =Y24 -> 4270 | Z62: =Z24 -> 4733 | AA62: =AA24 -> 5618.3997 | AB62: =AB24 -> 6309.7085 | AC62: =AC24 -> 6952.3116 | AD62: =AD24 -> 7448.6352 | ... AF62: =AF24 -> 8271.3616
A63: add back:
A64: Tax paid/(Tax refund) | W64: 302 | X64: 233 | Y64: 988 | Z64: 935 | AA64: =-AA17-'Income Statement'!AA88 -> 1363.775 | AB64: =-AB17-'Income Statement'!AB88 -> 1665.4603 | AC64: =-AC17-'Income Statement'!AC88 -> 1947.2082 | AD64: =-AD17-'Income Statement'!AD88 -> 1943.1275 | AE64: =-AE17-'Income Statement'!AE88 -> 2061.5384 | AF64: =-AF17-'Income Statement'!AF88 -> 2183.1988
A65: Interest Paid | W65: 79 | X65: 87 | Y65: 116 | Z65: =-'Income Statement'!Z121 -> 92 | AA65: =-'Income Statement'!AA121 -> 121.825 | AB65: =-'Income Statement'!AB121 -> 105.072 | AC65: =-'Income Statement'!AC121 -> 105.072 | AD65: =-'Income Statement'!AD121 -> 105.072 | AE65: =-'Income Statement'!AE121 -> 105.072 | AF65: =-'Income Statement'!AF121 -> 105.072
A66: Less: Interest income | W66: =-'Income Statement'!W122 -> -15 | X66: =-'Income Statement'!X122 -> -38 | Y66: -229 | Z66: =-'Income Statement'!Z122 -> -249 | AA66: =-'Income Statement'!AA122 -> -235.81 | AB66: =-'Income Statement'!AB122 -> -232.00021 | AC66: =-'Income Statement'!AC122 -> -248.92253 | AD66: =-'Income Statement'!AD122 -> -273.39329 | AE66: =-'Income Statement'!AE122 -> -300.73733 | AF66: =-'Income Statement'!AF122 -> -347.25711
A68: Deduct:
A69: Purchase of PP&E | W69: =W28 -> -387 | X69: =X28 -> -498 | Y69: =Y28 -> -823 | Z69: =Z28 -> -1044 | AA69: =AA28 -> -1549.7983 | AB69: =AB28 -> -1553.4318 | AC69: =AC28 -> -1526.8236 | AD69: =AD28 -> -1449.0147 | ... AF69: =AF28 -> -1138.3971
A70: Purchase of intangible assets | W70: =W26 -> -369 | X70: =X26 -> -381 | Y70: =Y26 -> -502 | Z70: =Z26 -> -500 | AA70: =AA26 -> -550 | AB70: =AB26 -> -550 | AC70: =AC26 -> -550 | AD70: =AD26 -> -550 | ... AF70: =AF26 -> -550
A71: Operating cash flow | W71: =SUM(W62:W70) -> 2046 | X71: =SUM(X62:X70) -> 2948 | Y71: =SUM(Y62:Y70) -> 3820 | Z71: =SUM(Z62:Z70) -> 3967 | AA71: =SUM(AA62:AA70) -> 4768.3913 | AB71: =SUM(AB62:AB70) -> 5744.8087 | AC71: =SUM(AC62:AC70) -> 6678.8457 | AD71: =SUM(AD62:AD70) -> 7224.4268 | ... AF71: =SUM(AF62:AF70) -> 8523.9782
A72: EBIT | W72: ='Income Statement'!W74 -> 1400 | X72: ='Income Statement'!X74 -> 1958 | Y72: ='Income Statement'!Y74 -> 2655 | Z72: ='Income Statement'!Z74 -> 4125 | AA72: ='Income Statement'!AA74 -> 5179.0618 | AB72: ='Income Statement'!AB74 -> 6014.9129 | AC72: ='Income Statement'!AC74 -> 6844.9824 | AD72: ='Income Statement'!AD74 -> 7604.1887 | ... AF72: ='Income Statement'!AF74 -> 8490.6102
A73: Cash Conversion | W73: =W71/W72 -> 1.4614286 | X73: =X71/X72 -> 1.505618 | Y73: =Y71/Y72 -> 1.4387947 | Z73: =Z71/Z72 -> 0.96169697 | AA73: =AA71/AA72 -> 0.92070562 | AB73: =AB71/AB72 -> 0.95509426 | AC73: =AC71/AC72 -> 0.97572869 | AD73: =AD71/AD72 -> 0.95005885 | ... AF73: =AF71/AF72 -> 1.00393

Sheet Balance Sheet
A1: ='DCF Valuation'!D45 -> 340
A2: Balance Sheet | B2: 2000 | C2: 2001 | D2: 2002 | E2: 2003 | F2: 2004 | G2: 2005 | H2: 2006 | I2: 2007 | J2: 2008 | K2: 2009 | L2: 2010 | M2: 2011 | N2: 2012 | O2: 2013 | P2: 2014 | Q2: 2015 | R2: 2016 | S2: 2017 | T2: 2018 | U2: 2019 | V2: 2020 | W2: 2021 | X2: 2022 | Y2: 2023 | Z2: 2024 | AA2: 2025E | AB2: 2026E | AC2: 2027E | AD2: 2028E | AE2: 2029E | AF2: 2030E | AI2: Comments
A4: Goodwill | H4: 1589 | I4: 1561 | J4: 1756 | K4: 2126 | L4: 2298 | M4: 3126 | N4: 3078 | O4: 3399 | P4: 3420 | Q4: 3590 | R4: 1864 | S4: 1831 | T4: 5173 | U4: 5199 | V4: 5060 | W4: 5068 | X4: 4994 | Y4: 4706 | Z4: 4937 | AA4: =Z4-'Cashflow Statement'!AA32-'Cashflow Statement'!AA9 -> 5109 | AB4: =AA4-'Cashflow Statement'!AB32-'Cashflow Statement'!AB9 -> 5281 | AC4: =AB4-'Cashflow Statement'!AC32-'Cashflow Statement'!AC9 -> 5453 | AD4: =AC4-'Cashflow Statement'!AD32-'Cashflow Statement'!AD9 -> 5625 | AE4: =AD4-'Cashflow Statement'!AE32-'Cashflow Statement'!AE9 -> 5797 | AF4: =AE4-'Cashflow Statement'!AF32-'Cashflow Statement'!AF9 -> 5969
A5: Intangible Assets | H5: 3056 | I5: 2981 | J5: 3112 | K5: 3217 | L5: 3130 | M5: 3498 | N5: 3872 | O5: =4641-200 -> 4441 | P5: 5536 | Q5: 5321 | R5: 5178 | S5: 5596 | T5: 9757 | U5: 9479 | V5: 8676 | W5: 8382 | X5: 8096 | Y5: 7830 | Z5: 7947 | AA5: =Z5-'Cashflow Statement'!AA7-'Cashflow Statement'!AA26 -> 7628.1494 | AB5: =AA5-'Cashflow Statement'!AB7-'Cashflow Statement'!AB26 -> 7142.5282 | AC5: =AB5-'Cashflow Statement'!AC7-'Cashflow Statement'!AC26 -> 6623.7517 | AD5: =AC5-'Cashflow Statement'!AD7-'Cashflow Statement'!AD26 -> 6014.54 | AE5: =AD5-'Cashflow Statement'!AE7-'Cashflow Statement'!AE26 -> 5348.4036 | AF5: =AE5-'Cashflow Statement'!AF7-'Cashflow Statement'!AF26 -> 4623.3988
A6: PP&E | H6: 1826 | I6: 1847 | J6: 2107 | K6: 2201 | L6: 2253 | M6: 2486 | N6: 2604 | O6: =2740-98 -> 2642 | P6: 2928 | Q6: 3272 | R6: 3169 | S6: 3518 | T6: 4454 | U6: 4398 | V6: 4055 | W6: 3937 | X6: 3847 | Y6: 4121 | Z6: 4629 | AA6: =Z6-'Cashflow Statement'!AA5-'Cashflow Statement'!AA28-'Cashflow Statement'!AA31 -> 5647.2601 | AB6: =AA6-'Cashflow Statement'!AB5-'Cashflow Statement'!AB28-'Cashflow Statement'!AB31 -> 6589.15 | AC6: =AB6-'Cashflow Statement'!AC5-'Cashflow Statement'!AC28-'Cashflow Statement'!AC31 -> 7421.5876 | AD6: =AC6-'Cashflow Statement'!AD5-'Cashflow Statement'!AD28-'Cashflow Statement'!AD31 -> 8102.9064 | AE6: =AD6-'Cashflow Statement'!AE5-'Cashflow Statement'!AE28-'Cashflow Statement'!AE31 -> 8592.0689 | AF6: =AE6-'Cashflow Statement'!AF5-'Cashflow Statement'!AF28-'Cashflow Statement'!AF31 -> 8868.9045
A7: Non-current financial assets | H7: 364 | I7: 286 | J7: 203 | K7: 220 | L7: 215 | M7: 246 | N7: 281 | O7: 384 | P7: 446 | Q7: 419 | R7: 382 | S7: 324 | T7: 416 | U7: 429 | V7: 431 | W7: 688 | X7: 752 | Y7: 997 | Z7: 1073 | AA7: =Z7 -> 1073 | AB7: =AA7 -> 1073 | AC7: =AB7 -> 1073 | AD7: =AC7 -> 1073 | AE7: =AD7 -> 1073 | AF7: =AE7 -> 1073
A8: Investments in associates | H8: 32 | I8: 34 | J8: 244 | K8: 238 | L8: 236 | M8: 253 | N8: 281 | O8: 680 | P8: 771 | Q8: 765 | R8: 2175 | S8: 2127 | T8: 2253 | U8: 2211 | V8: 2126 | W8: 1969 | X8: 1974 | Y8: 1928 | Z8: 1894 | AA8: =Z8 -> 1894 | AB8: =AA8 -> 1894 | AC8: =AB8 -> 1894 | AD8: =AC8 -> 1894 | AE8: =AD8 -> 1894 | AF8: =AE8 -> 1894
A9: Non-current derivatives | M9: 20 | N9: 62 | O9: 0 | P9: 29 | Q9: 35 | R9: 28 | S9: 16 | T9: 13 | U9: 33 | V9: 52 | W9: 23 | X9: 18 | Y9: 0 | Z9: 4 | AA9: =Z9 -> 4 | AB9: =AA9 -> 4 | AC9: =AB9 -> 4 | AD9: =AC9 -> 4 | AE9: =AD9 -> 4 | AF9: =AE9 -> 4
A10: Deferred tax assets | H10: 120 | I10: 158 | J10: 295 | K10: 263 | L10: 194 | M10: 251 | N10: 243 | O10: 201 | P10: 228 | Q10: 984 | R10: 1351 | S10: 251 | T10: 391 | U10: 251 | V10: 316 | W10: 449 | X10: 1576 | Y10: 1122 | Z10: 2349 | AA10: =Z10 -> 2349 | AB10: =AA10 -> 2349 | AC10: =AB10 -> 2349 | AD10: =AC10 -> 2349 | AE10: =AD10 -> 2349 | AF10: =AE10 -> 2349
A11: Right of use Asset | U11: 732 | V11: 623 | W11: 606 | X11: 566 | Y11: 582 | Z11: 653 | AA11: =Z11 -> 653 | AB11: =AA11 -> 653 | AC11: =AB11 -> 653 | AD11: =AC11 -> 653 | AE11: =AD11 -> 653 | AF11: =AE11 -> 653
A12: Other non-current financial assets | H12: 16 | I12: 10 | J12: 9 | K12: 1 | L12: 12 | M12: 12 | N12: 13 | O12: 0 | P12: 0 | Q12: =P12 -> 0 | R12: =Q12 -> 0 | S12: =R12 -> 0 | T12: 4 | U12: =T12 -> 4 | V12: 4 | W12: 11 | X12: 8 | Y12: 7 | Z12: 3 | AA12: =Z12 -> 3 | AB12: =AA12 -> 3 | AC12: =AB12 -> 3 | AD12: =AC12 -> 3 | AE12: =AD12 -> 3 | AF12: =AE12 -> 3
A13: Other | H13: =H14-SUM(H4:H12) -> 0 | I13: =I14-SUM(I4:I12) -> 0 | J13: =J14-SUM(J4:J12) -> 0 | K13: =K14-SUM(K4:K12) -> 0 | L13: =L14-SUM(L4:L12) -> 0 | M13: =M14-SUM(M4:M12) -> 0 | N13: =N14-SUM(N4:N12) -> 0 | O13: =O14-SUM(O4:O12) -> 0 | ... Z13: =Z14-SUM(Z4:Z12) -> 0 | AA13: 0 | AB13: 0 | AC13: 0 | AD13: 0 | AE13: 0 | AF13: 0
A14: Non-current assets | H14: 7003 | I14: 6877 | J14: 7726 | K14: 8266 | L14: 8338 | M14: 9892 | N14: 10434 | O14: =(3399+7083+680+585) -> 11747 | P14: 13358 | Q14: 14386 | R14: =SUM(R4:R12) -> 14147 | S14: =SUM(S4:S12) -> 13663 | T14: =SUM(T4:T12) -> 22461 | U14: =SUM(U4:U12) -> 22736 | V14: =SUM(V4:V12) -> 21343 | W14: =SUM(W4:W12) -> 21133 | X14: =SUM(X4:X12) -> 21831 | Y14: =SUM(Y4:Y12) -> 21293 | Z14: =SUM(Z4:Z12) -> 23489 | AA14: =SUM(AA4:AA13) -> 24360.409 | AB14: =SUM(AB4:AB13) -> 24988.678 | AC14: =SUM(AC4:AC13) -> 25474.339 | AD14: =SUM(AD4:AD13) -> 25718.446 | AE14: =SUM(AE4:AE13) -> 25713.472 | AF14: =SUM(AF4:AF13) -> 25437.303
A16: Current financial assets | H16: 108 | I16: 107 | J16: 108 | K16: 75 | L16: 110 | M16: 101 | N16: 176 | O16: 198 | P16: 221 | Q16: 247 | R16: 147 | S16: 2113 | T16: 185 | U16: 143 | V16: 126 | W16: 104 | X16: 242 | Y16: 270 | Z16: 243 | AA16: =Z16 -> 243 | AB16: =AA16 -> 243 | AC16: =AB16 -> 243 | AD16: =AC16 -> 243 | AE16: =AD16 -> 243 | AF16: =AE16 -> 243
A17: Current derivatives | H17: 397 | I17: 126 | J17: 138 | K17: 63 | L17: 128 | M17: 259 | N17: 585 | O17: 864 | P17: 377 | Q17: 373 | R17: 592 | S17: 566 | T17: 740 | U17: 674 | V17: 694 | W17: 705 | X17: 540 | Y17: 1577 | Z17: 952 | AA17: =Z17 -> 952 | AB17: =AA17 -> 952 | AC17: =AB17 -> 952 | AD17: =AC17 -> 952 | AE17: =AD17 -> 952 | AF17: =AE17 -> 952
A18: Inventories and work-in-progress | H18: 3240 | I18: 3240 | J18: 3673 | K18: 3382 | L18: 3508 | M18: 3799 | N18: 4131 | O18: 3998 | P18: 4265 | Q18: 4518 | R18: 4247 | S18: 3954 | T18: 5558 | U18: 6312 | V18: 5190 | W18: 5063 | X18: 6408 | Y18: 7903 | Z18: 9491 | AA18: =-AA19*'Income Statement'!AA49/365 -> 10049.084 | AB18: =-AB19*'Income Statement'!AB49/365 -> 10129.828 | AC18: =-AC19*'Income Statement'!AC49/365 -> 10839.54 | AD18: =-AD19*'Income Statement'!AD49/365 -> 11756.734 | AE18: =-AE19*'Income Statement'!AE49/365 -> 12471.11 | AF18: =-AF19*'Income Statement'!AF49/365 -> 13146.627
A19: DIO | W19: =-W18/'Income Statement'!W49*365 -> 231.02825 | X19: =-X18/'Income Statement'!X49*365 -> 199.49846 | Y19: =-Y18/'Income Statement'!Y49*365 -> 204.98827 | Z19: =-Z18/'Income Statement'!Z49*365 -> 217.05608 | AA19: 205.5 | AB19: 186 | AC19: 180 | AD19: 180 | AE19: 182 | AF19: 183
A20: Trade and Other receivables | H20: 4218 | I20: 3926 | J20: 3881 | K20: 4158 | L20: 4219 | M20: 5005 | N20: 5025 | O20: 4967 | P20: 5827 | Q20: 6515 | R20: 6252 | S20: 4952 | T20: 6580 | U20: 7639 | V20: 5769 | W20: 6504 | X20: 7904 | Y20: 9417 | Z20: 10572 | AA20: ='Income Statement'!AA39*'Balance Sheet'!AA21/365 -> 11039.659 | AB20: ='Income Statement'!AB39*'Balance Sheet'!AB21/365 -> 12295.046 | AC20: ='Income Statement'!AC39*'Balance Sheet'!AC21/365 -> 13385.851 | AD20: ='Income Statement'!AD39*'Balance Sheet'!AD21/365 -> 14178.226 | AE20: ='Income Statement'!AE39*'Balance Sheet'!AE21/365 -> 14874.466 | AF20: ='Income Statement'!AF39*'Balance Sheet'!AF21/365 -> 15594.481
A21: DSO | W21: =W20/'Income Statement'!W39*365 -> 155.59809 | X21: =X20/'Income Statement'!X39*365 -> 151.56081 | Y21: =Y20/'Income Statement'!Y39*365 -> 148.16177 | Z21: =Z20/'Income Statement'!Z39*365 -> 141.25929 | AA21: 130 | AB21: 130 | AC21: 128 | AD21: 125 | AE21: 125 | AF21: 125
A22: Tax assets | H22: 68 | I22: 27 | J22: 127 | K22: 145 | L22: 146 | M22: 215 | N22: 421 | O22: 392 | P22: 452 | Q22: 623 | R22: 513 | S22: 596 | T22: 752 | U22: 458 | V22: 481 | W22: 555 | X22: 358 | Y22: 422 | Z22: 364 | AA22: =Z22 -> 364 | AB22: =AA22 -> 364 | AC22: =AB22 -> 364 | AD22: =AC22 -> 364 | AE22: =AD22 -> 364 | AF22: =AE22 -> 364
A23: Cash and Cash equivalents | H23: 743 | I23: 730 | J23: 919 | K23: 2080 | L23: 2062 | M23: 1431 | N23: 2193 | O23: 1547 | P23: 1633 | Q23: 1845 | R23: 1926 | S23: 4914 | T23: 2330 | U23: 2632 | V23: 3747 | W23: 5247 | X23: 6687 | Y23: 6676 | Z23: 6514 | AA23: ='Cashflow Statement'!AA55 -> 7231.7677 | AB23: ='Cashflow Statement'!AB55 -> 8445.4906 | AC23: ='Cashflow Statement'!AC55 -> 9930.2613 | AD23: ='Cashflow Statement'!AD55 -> 11739.913 | AE23: ='Cashflow Statement'!AE55 -> 15225.36 | AF23: ='Cashflow Statement'!AF55 -> 19048.148
A24: Contract costs | S24: 261 | T24: 470 | U24: 471 | V24: 486 | W24: 552 | X24: 664 | Y24: 753 | Z24: 884 | AA24: =Z24 -> 884 | AB24: =AA24 -> 884 | AC24: =AB24 -> 884 | AD24: =AC24 -> 884 | AE24: =AD24 -> 884 | AF24: =AE24 -> 884
A25: Contract assets | S25: 1366 | T25: 1544 | U25: 1743 | V25: 1695 | W25: 1853 | X25: 1982 | Y25: 2157 | Z25: 2503 | AA25: =Z25 -> 2503 | AB25: =AA25 -> 2503 | AC25: =AB25 -> 2503 | AD25: =AC25 -> 2503 | AE25: =AD25 -> 2503 | AF25: =AE25 -> 2503
A26: Other | H26: =H27-SUM(H16:H23) -> 151 | I26: =I27-SUM(I16:I23) -> 1142 | J26: =J27-SUM(J16:J23) -> 264 | K26: =K27-SUM(K16:K23) -> 0 | L26: =L27-SUM(L16:L23) -> 0 | M26: =M27-SUM(M16:M23) -> 0 | N26: =N27-SUM(N16:N23) -> 0 | O26: =O27-SUM(O16:O23) -> -15 | ... Q26: =Q27-SUM(Q16:Q23) -> 0 | R26: 3234 | S26: 0 | T26: =S26 -> 0 | U26: 0 | X26: 212 | Y26: 0 | Z26: 0 | AA26: =Z26 -> 0 | AB26: =AA26 -> 0 | AC26: =AB26 -> 0 | AD26: =AC26 -> 0 | AE26: =AD26 -> 0 | AF26: =AE26 -> 0
A27: Current Assets | H27: 8925 | I27: =8519+779 -> 9298 | J27: =9049+61 -> 9110 | K27: 9903 | L27: 10173 | M27: 10810 | N27: 12531 | O27: =(864+3998+4967+1547+575) -> 11951 | P27: 12775 | Q27: 14121 | R27: =SUM(R16:R26) -> 16911 | S27: =SUM(S16:S26) -> 18722 | T27: =SUM(T16:T26) -> 18159 | U27: =SUM(U16:U26) -> 20072 | V27: =SUM(V16:V26) -> 18188 | W27: =SUM(W16:W26)-W19-W21 -> 20583 | X27: =SUM(X16:X26)-X19-X21 -> 24997 | Y27: =SUM(Y16:Y26)-Y19-Y21 -> 29175 | Z27: =SUM(Z16:Z26)-Z19-Z21 -> 31523 | AA27: =SUM(AA16:AA26)-AA19-AA21 -> 33266.511 | AB27: =SUM(AB16:AB26)-AB19-AB21 -> 35816.365 | AC27: =SUM(AC16:AC26)-AC19-AC21 -> 39101.652 | AD27: =SUM(AD16:AD26)-AD19-AD21 -> 42620.873 | ... AF27: =SUM(AF16:AF26)-AF19-AF21 -> 52735.255
A29: Provisions | H29: -976 | I29: -1052 | J29: -1078 | K29: -1315 | L29: -1310 | M29: -1374 | N29: -1823 | O29: =-1751+10 -> -1741 | P29: -1870 | Q29: -1802 | R29: -1706 | S29: -1263 | T29: -1588 | U29: -2093 | V29: -1942 | W29: -1798 | X29: -1549 | Y29: -1547 | Z29: -1835 | AA29: =Z29-'Cashflow Statement'!AA10 -> -1935 | AB29: =AA29-'Cashflow Statement'!AB10 -> -2035 | AC29: =AB29-'Cashflow Statement'!AC10 -> -2135 | AD29: =AC29-'Cashflow Statement'!AD10 -> -2235 | AE29: =AD29-'Cashflow Statement'!AE10 -> -2335 | AF29: =AE29-'Cashflow Statement'!AF10 -> -2435
A30: Borrowings subject to specific conditions | H30: -573 | I30: -590 | J30: -698 | K30: -696 | L30: -701 | M30: -682 | N30: -670 | O30: -670 | P30: -713 | Q30: -708 | R30: -699 | S30: -569 | T30: -585 | U30: -505 | V30: -426 | W30: -327 | X30: -302 | Y30: -292 | Z30: -287 | AA30: =Z30 -> -287 | AB30: =AA30 -> -287 | AC30: =AB30 -> -287 | AD30: =AC30 -> -287 | AE30: =AD30 -> -287 | AF30: =AE30 -> -287
A31: Non-current interest-bearing financial liabilities | H31: -463 | I31: -397 | J31: -418 | K31: -1208 | L31: -1483 | M31: -1447 | N31: -2259 | O31: =-1295-6 -> -1301 | P31: -1658 | Q31: -1752 | R31: -2392 | S31: -3246 | T31: -3384 | U31: -3239 | V31: -4082 | W31: -5094 | X31: -5378 | Y31: -4691 | Z31: -3788 | AA31: =Z31-'Cashflow Statement'!AA39 -> -3788 | AB31: =AA31-'Cashflow Statement'!AB39 -> -3788 | AC31: =AB31-'Cashflow Statement'!AC39 -> -3788 | AD31: =AC31-'Cashflow Statement'!AD39 -> -3788 | AE31: =AD31-'Cashflow Statement'!AE39 -> -3788 | AF31: =AE31-'Cashflow Statement'!AF39 -> -3788
A32: Non-current derivatives | M32: -5 | N32: -12 | O32: -36 | R32: 0 | S32: =R32 -> 0 | T32: -7 | U32: -5 | V32: -18 | W32: -8 | X32: -18 | Y32: -8 | Z32: -15 | AA32: =Z32 -> -15 | AB32: =AA32 -> -15 | AC32: =AB32 -> -15 | AD32: =AC32 -> -15 | AE32: =AD32 -> -15 | AF32: =AE32 -> -15
A33: Deferred tax liabilities | H33: -929 | I33: -745 | J33: -618 | K33: -833 | L33: -685 | M33: -718 | N33: -981 | O33: -1293 | P33: -728 | Q33: -677 | R33: -987 | S33: -674 | T33: -1662 | U33: -1340 | V33: -1285 | W33: -1275 | X33: -1164 | Y33: -1022 | Z33: -911 | AA33: =Z33-('Cashflow Statement'!AA17) -> -1241 | AB33: =AA33-('Cashflow Statement'!AB17) -> -1111 | AC33: =AB33-('Cashflow Statement'!AC17) -> -911 | AD33: =AC33-('Cashflow Statement'!AD17) -> -911 | AE33: =AD33-('Cashflow Statement'!AE17) -> -911 | AF33: =AE33-('Cashflow Statement'!AF17) -> -911
A34: Other non-current financial liabilities | H34: -112 | I34: -96 | J34: -139 | K34: -208 | L34: -186 | M34: -199 | N34: -81 | O34: =-119+8 -> -111 | P34: -101 | Q34: -26 | R34: -5 | S34: -8 | T34: -2 | U34: -2 | V34: -2 | W34: -116 | X34: -75 | Y34: -43 | Z34: -11 | AA34: =Z34 -> -11 | AB34: =AA34 -> -11 | AC34: =AB34 -> -11 | AD34: =AC34 -> -11 | AE34: =AD34 -> -11 | AF34: =AE34 -> -11
A35: Other | H35: =H36-SUM(H29:H34) -> 0 | I35: =I36-SUM(I29:I34) -> 0 | J35: =J36-SUM(J29:J34) -> 0 | K35: =K36-SUM(K29:K34) -> 0 | L35: =L36-SUM(L29:L34) -> 0 | M35: =M36-SUM(M29:M34) -> 0 | N35: =N36-SUM(N29:N34) -> 0 | O35: =O36-SUM(O29:O34) -> 13 | ... R35: =R36-SUM(R29:R34) -> 0 | S35: 0 | T35: 0 | U35: =U36-SUM(U29:U34) -> 0 | V35: =V36-SUM(V29:V34) -> 0 | W35: =W36-SUM(W29:W34) -> 0 | X35: -49 | Y35: 0 | Z35: =Y35 -> 0 | AA35: =Z35 -> 0 | AB35: =AA35 -> 0 | AC35: =AB35 -> 0 | AD35: =AC35 -> 0 | AE35: =AD35 -> 0 | AF35: =AE35 -> 0
A36: Non-current liabilities | H36: -3053 | I36: -2880 | J36: -2951 | K36: -4260 | L36: -4365 | M36: -4425 | N36: -5826 | O36: -5139 | P36: -5070 | Q36: -4965 | R36: =SUM(R29:R34) -> -5789 | S36: =SUM(S29:S34) -> -5760 | T36: =SUM(T29:T34) -> -7228 | U36: =SUM(U29:U34) -> -7184 | V36: =SUM(V29:V34) -> -7755 | W36: =SUM(W29:W34) -> -8618 | X36: =SUM(X29:X35) -> -8535 | Y36: =SUM(Y29:Y35) -> -7603 | Z36: =SUM(Z29:Z35) -> -6847 | AA36: =SUM(AA29:AA35) -> -7277 | AB36: =SUM(AB29:AB35) -> -7247 | AC36: =SUM(AC29:AC35) -> -7147 | AD36: =SUM(AD29:AD35) -> -7247 | AE36: =SUM(AE29:AE35) -> -7347 | AF36: =SUM(AF29:AF35) -> -7447
A38: Provisions | H38: -1101 | I38: -1133 | J38: -1278 | K38: -1039 | L38: -1114 | M38: -1064 | N38: -1064 | O38: =-1224+7 -> -1217 | P38: -1459 | Q38: -1654 | R38: -1558 | S38: -925 | T38: -1189 | U38: -990 | V38: -905 | W38: -1058 | X38: -1018 | Y38: -1064 | Z38: -1173 | AA38: =Z38 -> -1173 | AB38: =AA38 -> -1173 | AC38: =AB38 -> -1173 | AD38: =AC38 -> -1173 | AE38: =AD38 -> -1173 | AF38: =AE38 -> -1173
A39: Interest-bearing current financial liabilities | H39: -699 | I39: =-502 -> -502 | J39: -1136 | K39: -1367 | L39: -568 | M39: -998 | N39: -916 | O39: -1435 | P39: -1507 | Q39: -876 | R39: -945 | S39: -1390 | T39: -2221 | U39: -3540 | V39: -2509 | W39: -1720 | X39: -1277 | Y39: -1608 | Z39: -988 | AA39: =Z39 -> -988 | AB39: =AA39 -> -988 | AC39: =AB39 -> -988 | AD39: =AC39 -> -988 | AE39: =AD39 -> -988 | AF39: =AE39 -> -988
A40: Trade and other payables | H40: -6390 | I40: -6517 | J40: -6786 | K40: -6936 | L40: -7236 | M40: -8348 | N40: -8767 | O40: -8668 | P40: -9638 | Q40: -10602 | R40: -10242 | S40: -4409 | T40: -5650 | U40: -6164 | V40: -4353 | W40: -4950 | X40: -6298 | Y40: -8097 | Z40: -9802 | AA40: =AA41*'Income Statement'!AA49/365 -> -10961.988 | AB40: =AB41*'Income Statement'!AB49/365 -> -12526.132 | AC40: =AC41*'Income Statement'!AC49/365 -> -14272.061 | AD40: =AD41*'Income Statement'!AD49/365 -> -15479.7 | AE40: =AE41*'Income Statement'!AE49/365 -> -16445.42 | AF40: =AF41*'Income Statement'!AF49/365 -> -17241.478
A41: DPO | W41: =W40/'Income Statement'!W49*365 -> 225.87198 | X41: =X40/'Income Statement'!X49*365 -> 196.07387 | Y41: =Y40/'Income Statement'!Y49*365 -> 210.02025 | Z41: =Z40/'Income Statement'!Z49*365 -> 224.16855 | AA41: 224.16855 | AB41: 230 | AC41: 237 | AD41: 237 | AE41: 240 | AF41: 240
A42: Tax liabilities | H42: -21 | I42: -43 | J42: -39 | K42: -53 | L42: -72 | M42: -92 | N42: -156 | O42: -202 | P42: -220 | Q42: -287 | R42: -179 | S42: -214 | T42: -210 | U42: -111 | V42: -118 | W42: -109 | X42: -105 | Y42: -104 | Z42: -105 | AA42: =Z42 -> -105 | AB42: =AA42 -> -105 | AC42: =AB42 -> -105 | AD42: =AC42 -> -105 | AE42: =AD42 -> -105 | AF42: =AE42 -> -105
A43: Current derivatives | H43: -2 | I43: -4 | J43: -577 | K43: -13 | L43: -451 | M43: -653 | N43: -213 | O43: -150 | P43: -1636 | Q43: -4108 | R43: -4385 | S43: -805 | T43: -1255 | U43: -1033 | V43: -1244 | W43: -1788 | X43: -5848 | Y43: -4735 | Z43: -8803 | AA43: =Z43 -> -8803 | AB43: =AA43 -> -8803 | AC43: =AB43 -> -8803 | AD43: =AC43 -> -8803 | AE43: =AD43 -> -8803 | AF43: =AE43 -> -8803
A44: Contract liabilities | S44: -9090 | T44: -10453 | U44: -10923 | V44: -9838 | W44: -10141 | X44: -12756 | Y44: -15029 | Z44: -16421 | AA44: =Z44 -> -16421 | AB44: =AA44 -> -16421 | AC44: =AB44 -> -16421 | AD44: =AC44 -> -16421 | AE44: =AD44 -> -16421 | AF44: =AE44 -> -16421
A45: RPFH cash advances
A46: Other | H46: =H47-SUM(H38:H43) -> -150 | I46: =I47-SUM(I38:I43) -> -591 | J46: =J47-SUM(J38:J43) -> -195 | K46: =K47-SUM(K38:K43) -> 0 | L46: =L47-SUM(L38:L43) -> 0 | M46: =M47-SUM(M38:M43) -> 0 | N46: =N47-SUM(N38:N43) -> -26 | O46: =-64+3 -> -61 | P46: -125 | Q46: -122 | R46: =-357-794 -> -1151 | S46: -144 | T46: -113 | U46: -115 | V46: -59 | W46: -62 | X46: -125 | Y46: -140 | Z46: -148 | AA46: =Z46 -> -148 | AB46: =AA46 -> -148 | AC46: =AB46 -> -148 | AD46: =AC46 -> -148 | AE46: =AD46 -> -148 | AF46: =AE46 -> -148
A47: Current liabilities | H47: -8363 | I47: =-8338-452 -> -8790 | J47: =-9972-39 -> -10011 | K47: -9408 | L47: -9441 | M47: -11155 | N47: -11142 | O47: -11746 | P47: -14585 | Q47: -17649 | R47: =SUM(R38:R46) -> -18460 | S47: =SUM(S38:S46) -> -16977 | T47: =SUM(T38:T46) -> -21091 | U47: =SUM(U38:U46) -> -22876 | V47: =SUM(V38:V46) -> -19026 | W47: =SUM(W38:W40,W42:W44,W46) -> -19828 | X47: =SUM(X38:X40,X42:X44,X46) -> -27427 | Y47: =SUM(Y38:Y40,Y42:Y44,Y46) -> -30777 | Z47: =SUM(Z38:Z40,Z42:Z44,Z46) -> -37440 | AA47: =SUM(AA38:AA40,AA42:AA44,AA46) -> -38599.988 | AB47: =SUM(AB38:AB40,AB42:AB44,AB46) -> -40164.132 | AC47: =SUM(AC38:AC40,AC42:AC44,AC46) -> -41910.061 | AD47: =SUM(AD38:AD40,AD42:AD44,AD46) -> -43117.7 | ... AF47: =SUM(AF38:AF40,AF42:AF44,AF46) -> -44879.478
A49: Share capital | H49: 83 | I49: 83 | J49: 83 | K49: 83 | L49: 83 | M49: 83 | N49: 83 | O49: =N49 -> 83 | P49: =O49 -> 83 | Q49: 83 | R49: =Q49 -> 83 | S49: 83 | T49: 87 | U49: 85 | V49: 85 | W49: 85 | X49: 85 | Y49: 85 | Z49: 85 | AA49: =Z49 -> 85 | AB49: =AA49 -> 85 | AC49: =AB49 -> 85 | AD49: =AC49 -> 85 | AE49: =AD49 -> 85 | AF49: =AE49 -> 85
A50: Retained Earnings | H50: 4296 | I50: 4189 | J50: 3902 | K50: 3619 | L50: 4214 | M50: 4387 | N50: 4444 | O50: =5138-1 -> 5137 | P50: 6246 | Q50: 5927 | R50: 4495 | S50: 4686 | T50: 10585 | U50: 9839 | V50: 11912 | W50: 12713 | X50: 12785 | Y50: 8048 | Z50: 10758 | AA50: =Z50+'Income Statement'!Z92+'Income Statement'!Z94-'Income Statement'!Z95-'Income Statement'!AA83+'Cashflow Statement'!AA43+'Cashflow Statement'!AA47 -> 7634.1664 | AB50: =AA50+'Income Statement'!AA92+'Income Statement'!AA94-'Income Statement'!AA95-'Income Statement'!AB83+'Cashflow Statement'!AB43+'Cashflow Statement'!AB47 -> 8364.4913 | AC50: =AB50+'Income Statement'!AB92+'Income Statement'!AB94-'Income Statement'!AB95-'Income Statement'!AC83+'Cashflow Statement'!AC43+'Cashflow Statement'!AC47 -> 9495.7193 | AD50: =AC50+'Income Statement'!AC92+'Income Statement'!AC94-'Income Statement'!AC95-'Income Statement'!AD83+'Cashflow Statement'!AD43+'Cashflow Statement'!AD47 -> 11244.784 | AE50: =AD50+'Income Statement'!AD92+'Income Statement'!AD94-'Income Statement'!AD95-'Income Statement'!AE83+'Cashflow Statement'!AE43+'Cashflow Statement'!AE47 -> 14582.234 | AF50: =AE50+'Income Statement'!AE92+'Income Statement'!AE94-'Income Statement'!AE95-'Income Statement'!AF83+'Cashflow Statement'!AF43+'Cashflow Statement'!AF47 -> 18124.039
A51: Net unrealised gain on available-for-sale financial assets | H51: 27 | I51: 27 | J51: -15 | K51: 10 | L51: 26 | M51: 20 | N51: 25 | O51: 29 | P51: 50 | Q51: 41 | R51: 35 | S51: 28 | T51: 0 | U51: 0 | Y51: =X51 -> 0 | Z51: 0 | AA51: =Z51 -> 0 | AB51: =AA51 -> 0 | AC51: =AB51 -> 0 | AD51: =AC51 -> 0 | AE51: =AD51 -> 0 | AF51: =AE51 -> 0
A52: Profit for the period | H52: 9 | I52: 39 | J52: -205 | K52: 641 | L52: 207 | M52: ='Cashflow Statement'!M4 -> 478 | N52: ='Cashflow Statement'!N4 -> 1282 | O52: ='Cashflow Statement'!O4 -> 1255 | P52: -126 | Q52: -424 | R52: ='Cashflow Statement'!R4 -> 1908 | S52: 4550 | T52: 1283 | U52: 2447 | V52: 352 | W52: 43 | X52: -2459 | Y52: 3444 | Z52: -667 | AA52: ='Cashflow Statement'!AA4 -> 3378.8787 | AB52: ='Cashflow Statement'!AB4 -> 4177.9453 | AC52: ='Cashflow Statement'!AC4 -> 5045.0336 | AD52: ='Cashflow Statement'!AD4 -> 5614.2336 | AE52: ='Cashflow Statement'!AE4 -> 5957.9816 | AF52: ='Cashflow Statement'!AF4 -> 6311.1175
A53: Non-controlling interests | H53: 173 | I53: 167 | J53: 141 | K53: 148 | L53: 175 | M53: 154 | N53: 163 | O53: 178 | P53: 225 | Q53: 266 | R53: 288 | S53: 301 | T53: 346 | U53: 377 | V53: 401 | W53: 429 | X53: 455 | Y53: 511 | Z53: 549 | AA53: =Z53+'Income Statement'!AA95 -> 651.88746 | AB53: =AA53+'Income Statement'!AB95 -> 766.47489 | AC53: =AB53+'Income Statement'!AC95 -> 893.17767 | AD53: =AC53+'Income Statement'!AD95 -> 1030.6015 | AE53: =AD53+'Income Statement'!AE95 -> 1174.7737 | AF53: =AE53+'Income Statement'!AF95 -> 1325.9247
A54: Total Equity | H54: =SUM(H49:H53)-76 -> 4512 | I54: =SUM(I49:I53) -> 4505 | J54: =SUM(J49:J53)-32 -> 3874 | K54: =SUM(K49:K53) -> 4501 | L54: =SUM(L49:L53) -> 4705 | M54: =SUM(M49:M53) -> 5122 | N54: =SUM(N49:N53) -> 5997 | O54: 6813 | P54: =SUM(P49:P53) -> 6478 | Q54: 5893 | R54: =SUM(R49:R53) -> 6809 | S54: =SUM(S49:S53) -> 9648 | T54: =SUM(T49:T53) -> 12301 | U54: =SUM(U49:U53) -> 12748 | V54: =SUM(V49:V53) -> 12750 | W54: =SUM(W49:W53) -> 13270 | X54: =SUM(X49:X53) -> 10866 | Y54: =SUM(Y49:Y53) -> 12088 | ... AF54: =SUM(AF49:AF53) -> 25846.081
A56: balance sheet check | H56: =H14+H27+H36+H47-H54 -> 0 | I56: =I14+I27+I36+I47-I54 -> 0 | J56: =J14+J27+J36+J47-J54 -> 0 | K56: =K14+K27+K36+K47-K54 -> 0 | L56: =L14+L27+L36+L47-L54 -> 0 | M56: =M14+M27+M36+M47-M54 -> 0 | N56: =N14+N27+N36+N47-N54 -> 0 | O56: =O14+O27+O36+O47-O54 -> 0 | ... AF56: =AF14+AF27+AF36+AF47-AF54 -> 0
A58: Working capital analysis
A59: Inventory | H59: =H18 -> 3240 | I59: =I18 -> 3240 | J59: =J18 -> 3673 | K59: =K18 -> 3382 | L59: =L18 -> 3508 | M59: =M18 -> 3799 | N59: =N18 -> 4131 | O59: =O18 -> 3998 | ... AF59: =AF18 -> 13146.627
A60: Receivables | H60: =H20 -> 4218 | I60: =I20 -> 3926 | J60: =J20 -> 3881 | K60: =K20 -> 4158 | L60: =L20 -> 4219 | M60: =M20 -> 5005 | N60: =N20 -> 5025 | O60: =O20 -> 4967 | ... AF60: =AF20 -> 15594.481
A61: Current Tax assets | H61: ='Balance Sheet'!H22 -> 68 | I61: ='Balance Sheet'!I22 -> 27 | J61: ='Balance Sheet'!J22 -> 127 | K61: ='Balance Sheet'!K22 -> 145 | L61: ='Balance Sheet'!L22 -> 146 | M61: ='Balance Sheet'!M22 -> 215 | N61: ='Balance Sheet'!N22 -> 421 | O61: ='Balance Sheet'!O22 -> 392 | ... AF61: ='Balance Sheet'!AF22 -> 364
A62: Contract Assets | S62: ='Balance Sheet'!S25 -> 1366 | T62: ='Balance Sheet'!T25 -> 1544 | U62: ='Balance Sheet'!U25 -> 1743 | V62: ='Balance Sheet'!V25 -> 1695 | W62: ='Balance Sheet'!W25 -> 1853 | X62: ='Balance Sheet'!X25 -> 1982 | Y62: ='Balance Sheet'!Y25 -> 2157 | Z62: ='Balance Sheet'!Z25 -> 2503 | AA62: =AA76*'Income Statement'!AA$41 -> 2799.21 | AB62: =AB76*'Income Statement'!AB$41 -> 3117.5252 | AC62: =AC76*'Income Statement'!AC$41 -> 3447.142 | AD62: =AD76*'Income Statement'!AD$41 -> 3738.8241 | AE62: =AE76*'Income Statement'!AE$41 -> 3922.4241 | AF62: =AF76*'Income Statement'!AF$41 -> 4112.2932
A63: Other | H63: ='Balance Sheet'!H26 -> 151 | I63: ='Balance Sheet'!I26-779 -> 363 | J63: ='Balance Sheet'!J26-61 -> 203 | K63: ='Balance Sheet'!K26 -> 0 | L63: ='Balance Sheet'!L26 -> 0 | M63: ='Balance Sheet'!M26 -> 0 | N63: ='Balance Sheet'!N26 -> 0 | O63: ='Balance Sheet'!O26 -> -15 | P63: ='Balance Sheet'!P26 -> 0 | Q63: ='Balance Sheet'!Q26 -> 0 | R63: ='Balance Sheet'!R26-3234 -> 0 | S63: ='Balance Sheet'!S26 -> 0 | T63: ='Balance Sheet'!T26 -> 0 | U63: ='Balance Sheet'!U26 -> 0 | V63: ='Balance Sheet'!V26 -> 0 | W63: ='Balance Sheet'!W26 -> 0 | X63: ='Balance Sheet'!X26 -> 212 | Y63: ='Balance Sheet'!Y26 -> 0 | Z63: ='Balance Sheet'!Z26 -> 0 | ... AF63: ='Balance Sheet'!AF26 -> 0
A64: Operating Current Assets | H64: =SUM(H59:H63) -> 7677 | I64: =SUM(I59:I63) -> 7556 | J64: =SUM(J59:J63) -> 7884 | K64: =SUM(K59:K63) -> 7685 | L64: =SUM(L59:L63) -> 7873 | M64: =SUM(M59:M63) -> 9019 | N64: =SUM(N59:N63) -> 9577 | O64: =SUM(O59:O63) -> 9342 | ... AF64: =SUM(AF59:AF63) -> 33217.401
A66: Payables | H66: =H40 -> -6390 | I66: =I40 -> -6517 | J66: =J40 -> -6786 | K66: =K40 -> -6936 | L66: =L40 -> -7236 | M66: =M40 -> -8348 | N66: =N40 -> -8767 | O66: =O40 -> -8668 | ... AF66: =AF40 -> -17241.478
A67: Provisions | H67: ='Balance Sheet'!H38 -> -1101 | I67: ='Balance Sheet'!I38 -> -1133 | J67: ='Balance Sheet'!J38 -> -1278 | K67: ='Balance Sheet'!K38 -> -1039 | L67: ='Balance Sheet'!L38 -> -1114 | M67: ='Balance Sheet'!M38 -> -1064 | N67: ='Balance Sheet'!N38 -> -1064 | O67: ='Balance Sheet'!O38 -> -1217 | ... AF67: ='Balance Sheet'!AF38 -> -1173
A68: Current tax liabilities | H68: ='Balance Sheet'!H42 -> -21 | I68: ='Balance Sheet'!I42 -> -43 | J68: ='Balance Sheet'!J42 -> -39 | K68: ='Balance Sheet'!K42 -> -53 | L68: ='Balance Sheet'!L42 -> -72 | M68: ='Balance Sheet'!M42 -> -92 | N68: ='Balance Sheet'!N42 -> -156 | O68: ='Balance Sheet'!O42 -> -202 | ... AF68: ='Balance Sheet'!AF42 -> -105
A69: Contract Liabilities | S69: ='Balance Sheet'!S44 -> -9090 | T69: ='Balance Sheet'!T44 -> -10453 | U69: ='Balance Sheet'!U44 -> -10923 | V69: ='Balance Sheet'!V44 -> -9838 | W69: ='Balance Sheet'!W44 -> -10141 | X69: ='Balance Sheet'!X44 -> -12756 | Y69: ='Balance Sheet'!Y44 -> -15029 | Z69: ='Balance Sheet'!Z44 -> -16421 | AA69: =AA44 -> -16421 | AB69: =AB44 -> -16421 | AC69: =AC44 -> -16421 | AD69: =AD44 -> -16421 | AE69: =AE44 -> -16421 | AF69: =AF44 -> -16421 | AI69: We include LEAP RPFH deferred income in contract liabilities
A70: Other | H70: ='Balance Sheet'!H46+'Balance Sheet'!H43 -> -152 | I70: ='Balance Sheet'!I46+'Balance Sheet'!I43+452 -> -143 | J70: ='Balance Sheet'!J46+'Balance Sheet'!J43+39 -> -733 | K70: ='Balance Sheet'!K46+'Balance Sheet'!K43 -> -13 | L70: ='Balance Sheet'!L46+'Balance Sheet'!L43 -> -451 | M70: ='Balance Sheet'!M46+'Balance Sheet'!M43 -> -653 | N70: ='Balance Sheet'!N46+'Balance Sheet'!N43 -> -239 | O70: ='Balance Sheet'!O46+'Balance Sheet'!O43 -> -211 | P70: ='Balance Sheet'!P46+'Balance Sheet'!P43 -> -1761 | Q70: ='Balance Sheet'!Q46+'Balance Sheet'!Q43 -> -4230 | R70: ='Balance Sheet'!R46+'Balance Sheet'!R43+794 -> -4742 | S70: ='Balance Sheet'!S46+'Balance Sheet'!S43+794 -> -155 | T70: ='Balance Sheet'!T46+'Balance Sheet'!T43 -> -1368 | U70: ='Balance Sheet'!U46+'Balance Sheet'!U43 -> -1148 | V70: ='Balance Sheet'!V46+'Balance Sheet'!V43 -> -1303 | W70: ='Balance Sheet'!W46+'Balance Sheet'!W43 -> -1850 | X70: ='Balance Sheet'!X46+'Balance Sheet'!X43 -> -5973 | Y70: ='Balance Sheet'!Y46+'Balance Sheet'!Y43 -> -4875 | Z70: ='Balance Sheet'!Z46+'Balance Sheet'!Z43 -> -8951 | AA70: ='Balance Sheet'!AA46+'Balance Sheet'!AA43 -> -8951 | ... AF70: ='Balance Sheet'!AF46+'Balance Sheet'!AF43 -> -8951
A71: Operating Current Liabilities | H71: =SUM(H66:H70) -> -7664 | I71: =SUM(I66:I70) -> -7836 | J71: =SUM(J66:J70) -> -8836 | K71: =SUM(K66:K70) -> -8041 | L71: =SUM(L66:L70) -> -8873 | M71: =SUM(M66:M70) -> -10157 | N71: =SUM(N66:N70) -> -10226 | O71: =SUM(O66:O70) -> -10298 | ... AF71: =SUM(AF66:AF70) -> -43891.478
S72: =SUM(S66:S69)+SUM(S59:S62) -> -3770 | T72: =SUM(T66:T69)+SUM(T59:T62) -> -3068 | U72: =SUM(U66:U69)+SUM(U59:U62) -> -2036 | V72: =SUM(V66:V69)+SUM(V59:V62) -> -2079 | W72: =SUM(W66:W69)+SUM(W59:W62) -> -2283 | X72: =SUM(X66:X69)+SUM(X59:X62) -> -3525 | Y72: =SUM(Y66:Y69)+SUM(Y59:Y62) -> -4395 | Z72: =SUM(Z66:Z69)+SUM(Z59:Z62) -> -4571 | ... AF72: =SUM(AF66:AF69)+SUM(AF59:AF62) -> -1723.0769
A73: Working Capital | H73: =H71+H64 -> 13 | I73: =I71+I64 -> -280 | J73: =J71+J64 -> -952 | K73: =K71+K64 -> -356 | L73: =L71+L64 -> -1000 | M73: =M71+M64 -> -1138 | N73: =N71+N64 -> -649 | O73: =O71+O64 -> -956 | ... AF73: =AF71+AF64 -> -10674.077
A74: y/y change | H74: =H73-115 -> -102 | I74: =I73-H73 -> -293 | J74: =J73-I73 -> -672 | K74: =K73-J73 -> 596 | L74: =L73-K73 -> -644 | M74: =M73-L73 -> -138 | N74: =N73-M73 -> 489 | O74: =O73-N73 -> -307 | P74: =P73-O73 -> -1578 | ... AF74: =AF73-AE73 -> 789.34234
AI75: FCF line to check
A76: Contract assets - as a % of sales | S76: =S62/'Income Statement'!S$41 -> 0.083414753 | T76: =T62/'Income Statement'!T$41 -> 0.073436385 | U76: =U62/'Income Statement'!U$41 -> 0.069447765 | V76: =V62/'Income Statement'!V$41 -> 0.1019181 | W76: =W62/'Income Statement'!W$41 -> 0.12244763 | X76: =X62/'Income Statement'!X$41 -> 0.10152128 | Y76: =Y62/'Income Statement'!Y$41 -> 0.091201218 | Z76: =Z62/'Income Statement'!Z$41 -> 0.090308847 | AA76: =Z76 -> 0.090308847 | AB76: =AA76 -> 0.090308847 | AC76: =AB76 -> 0.090308847 | AD76: =AC76 -> 0.090308847 | AE76: =AD76 -> 0.090308847 | AF76: =AE76 -> 0.090308847
A77: Contract liabilities - as a % of sales | S77: =S69/'Income Statement'!S$41 -> -0.55508061 | T77: =T69/'Income Statement'!T$41 -> -0.49717004 | U77: =U69/'Income Statement'!U$41 -> -0.43521396 | V77: =V69/'Income Statement'!V$41 -> -0.59154591 | W77: =W69/'Income Statement'!W$41 -> -0.67012489 | X77: =X69/'Income Statement'!X$41 -> -0.65338319 | Y77: =Y69/'Income Statement'!Y$41 -> -0.63544882 | Z77: =Z69/'Income Statement'!Z$41 -> -0.59247366 | AA77: -0.54 | AB77: =AA77+0.025 -> -0.515 | AC77: =AB77+0.025 -> -0.49 | AD77: =AC77+0.025 -> -0.465 | AE77: =AD77+0.025 -> -0.44 | AF77: =AE77+0.025 -> -0.415 | AI77: CMD'21 p63: "Increasing advance payments from Rafale programs over 2021 23, decreasing elsewhere."
A79: LEAP impact | U79: -800 | V79: 0 | W79: 0 | X79: 0
A80: Change in Receivables | I80: =I60-H60 -> -292 | J80: =J60-I60 -> -45 | K80: =K60-J60 -> 277 | L80: =L60-K60 -> 61 | M80: =M60-L60 -> 786 | N80: =N60-M60 -> 20 | O80: =O60-N60 -> -58 | P80: =P60-O60 -> 860 | ... AF80: =AF60-AE60 -> 720.01443
A81: Change in Payables | I81: =I66-H66 -> -127 | J81: =J66-I66 -> -269 | K81: =K66-J66 -> -150 | L81: =L66-K66 -> -300 | M81: =M66-L66 -> -1112 | N81: =N66-M66 -> -419 | O81: =O66-N66 -> 99 | P81: =P66-O66 -> -970 | ... AF81: =AF66-AE66 -> -796.0581
A82: Change in Contract Assets | T82: =T62-S62 -> 178 | U82: =U62-T62 -> 199 | V82: =V62-U62 -> -48 | W82: =W62-V62 -> 158 | X82: =X62-W62 -> 129 | Y82: =Y62-X62 -> 175 | Z82: =Z62-Y62 -> 346 | AA82: =AA62-Z62 -> 296.21003 | ... AF82: =AF62-AE62 -> 189.86913
A83: Change in Contract Liabilities | T83: =T69-S69 -> -1363 | U83: =U69-T69 -> -470 | V83: =V69-U69 -> 1085 | W83: =W69-V69 -> -303 | X83: =X69-W69 -> -2615 | Y83: =Y69-X69 -> -2273 | Z83: =Z69-Y69 -> -1392 | AA83: =AA69-Z69 -> 0 | ... AF83: =AF69-AE69 -> 0
AA84: ='Cashflow Statement'!AA57 -> 3518.6013 | AB84: ='Cashflow Statement'!AB57 -> 4206.2767 | AC84: ='Cashflow Statement'!AC57 -> 4875.488 | AD84: ='Cashflow Statement'!AD57 -> 5449.6206 | AE84: ='Cashflow Statement'!AE57 -> 6106.2307 | AF84: ='Cashflow Statement'!AF57 -> 6582.9645
A85: Deferred income | T85: 3905 | U85: 4313 | V85: 4142 | W85: 4450 | X85: 5101 | Y85: 5818 | Z85: 6459
A86: ow RPFH | V86: 3600
A87: ow RTDI | V87: =V85-V86 -> 542 | W87: =V87*1.1 -> 596.2 | X87: =W87*1.1 -> 655.82 | Y87: =X87*1.1 -> 721.402 | Z87: =Y87*1.1 -> 793.5422 | AA87: =Z87*1.1 -> 872.89642
A88: Leverage Anaylsis | B88: =B2 -> 2000 | C88: =C2 -> 2001 | D88: =D2 -> 2002 | E88: =E2 -> 2003 | F88: =F2 -> 2004 | G88: =G2 -> 2005 | H88: =H2 -> 2006 | I88: =I2 -> 2007 | ... Z88: =Z2 -> 2024 | AA88: =Z88+1 -> 2025 | AB88: =AA88+1 -> 2026 | AC88: =AB88+1 -> 2027 | AD88: =AC88+1 -> 2028 | AE88: =AD88+1 -> 2029 | AF88: =AE88+1 -> 2030
A89: =A30 -> Borrowings subject to specific conditions | I89: =I30 -> -590 | J89: =J30 -> -698 | K89: =K30 -> -696 | L89: =L30 -> -701 | M89: =M30 -> -682 | N89: =N30 -> -670 | O89: =O30 -> -670 | P89: =P30 -> -713 | ... AF89: =AF30 -> -287
A90: =A31 -> Non-current interest-bearing financial liabilities | I90: =I31 -> -397 | J90: =J31 -> -418 | K90: =K31 -> -1208 | L90: =L31 -> -1483 | M90: =M31 -> -1447 | N90: =N31 -> -2259 | O90: =O31 -> -1301 | P90: =P31 -> -1658 | ... AF90: =AF31 -> -3788
A91: =A39 -> Interest-bearing current financial liabilities | I91: =I39 -> -502 | J91: =J39 -> -1136 | K91: =K39 -> -1367 | L91: =L39 -> -568 | M91: =M39 -> -998 | N91: =N39 -> -916 | O91: =O39 -> -1435 | P91: =P39 -> -1507 | ... AF91: =AF39 -> -988
A92: =A23 -> Cash and Cash equivalents | I92: =I23 -> 730 | J92: =J23 -> 919 | K92: =K23 -> 2080 | L92: =L23 -> 2062 | M92: =M23 -> 1431 | N92: =N23 -> 2193 | O92: =O23 -> 1547 | P92: =P23 -> 1633 | ... AF92: =AF23 -> 19048.148
A93: Period End (Net Debt)/Net Cash | I93: =SUM(I89:I92) -> -759 | J93: =SUM(J89:J92) -> -1333 | K93: =SUM(K89:K92) -> -1191 | L93: =SUM(L89:L92) -> -690 | M93: =SUM(M89:M92) -> -1696 | N93: =SUM(N89:N92) -> -1652 | O93: =SUM(O89:O92) -> -1859 | P93: =SUM(P89:P92) -> -2245 | ... AF93: =SUM(AF89:AF92) -> 13985.148
A94: Period Average (Net Debt)/Net Cash | I94: =AVERAGE(H93:I93) -> -759 | J94: =AVERAGE(I93:J93) -> -1046 | K94: =AVERAGE(J93:K93) -> -1262 | L94: =AVERAGE(K93:L93) -> -940.5 | M94: =AVERAGE(L93:M93) -> -1193 | N94: =AVERAGE(M93:N93) -> -1674 | O94: =AVERAGE(N93:O93) -> -1755.5 | P94: =AVERAGE(O93:P93) -> -2052 | ... AF94: =AVERAGE(AE93:AF93) -> 12073.754
A96: EBITDA | R96: ='Income Statement'!R193 -> 3130 | S96: ='Income Statement'!S193 -> 2980 | T96: ='Income Statement'!T193 -> 4232 | U96: ='Income Statement'!U193 -> 5283 | V96: ='Income Statement'!V193 -> 3133 | W96: ='Income Statement'!W193 -> 3185 | X96: ='Income Statement'!X193 -> 3781 | Y96: ='Income Statement'!Y193 -> 4502 | ... AF96: ='Income Statement'!AF193 -> 10799.176
A98: Y/E Net Debt/Adj. EBITDA | R98: =R93/R96 -> -0.67412141 | S98: =S93/S96 -> -0.097651007 | T98: =T93/T96 -> -0.9120983 | U98: =U93/U96 -> -0.88056029 | V98: =V93/V96 -> -1.0437281 | W98: =W93/W96 -> -0.59466248 | X98: =X93/X96 -> -0.07140968 | Y98: =Y93/Y96 -> 0.018880498 | ... AF98: =AF93/AF96 -> 1.2950198
A99: Average Net Debt/Adj. EBITDA | R99: =R94/R96 -> -0.57523962 | S99: =S94/S96 -> -0.40285235 | T99: =T94/T96 -> -0.49043006 | U99: =U94/U96 -> -0.80560288 | V99: =V94/V96 -> -1.2642834 | W99: =W94/W96 -> -0.81067504 | X99: =X94/X96 -> -0.28616768 | Y99: =Y94/Y96 -> -0.020546424 | ... AF99: =AF94/AF96 -> 1.1180254
A101: ROIC Analysis | B101: =B2 -> 2000 | C101: =C2 -> 2001 | D101: =D2 -> 2002 | E101: =E2 -> 2003 | F101: =F2 -> 2004 | G101: =G2 -> 2005 | H101: =H2 -> 2006 | I101: =I2 -> 2007 | ... Z101: =Z2 -> 2024 | AA101: =Z101+1 -> 2025 | AB101: =AA101+1 -> 2026 | AC101: =AB101+1 -> 2027 | AD101: =AC101+1 -> 2028 | AE101: =AD101+1 -> 2029 | AF101: =AE101+1 -> 2030
A102: Adj. EBITA | S102: ='Income Statement'!S70 -> 2192 | T102: ='Income Statement'!T70 -> 3023 | U102: ='Income Statement'!U70 -> 3820 | V102: ='Income Statement'!V70 -> 1686 | W102: ='Income Statement'!W70 -> 1805 | X102: ='Income Statement'!X70 -> 2408 | Y102: ='Income Statement'!Y70 -> 3166 | Z102: ='Income Statement'!Z70 -> 4119 | ... AF102: ='Income Statement'!AF70 -> 8490.6102
A103: Underlying Tax | S103: ='Income Statement'!S88 -> -485 | T103: ='Income Statement'!T88 -> -638 | U103: ='Income Statement'!U88 -> -1012 | V103: ='Income Statement'!V88 -> -334 | W103: ='Income Statement'!W88 -> -412 | X103: ='Income Statement'!X88 -> -557 | Y103: ='Income Statement'!Y88 -> -724 | Z103: ='Income Statement'!Z88 -> -987 | ... AF103: ='Income Statement'!AF88 -> -2183.1988
A104: NOPAT | S104: =S102+S103 -> 1707 | T104: =T102+T103 -> 2385 | U104: =U102+U103 -> 2808 | V104: =V102+V103 -> 1352 | W104: =W102+W103 -> 1393 | X104: =X102+X103 -> 1851 | Y104: =Y102+Y103 -> 2442 | Z104: =Z102+Z103 -> 3132 | ... AF104: =AF102+AF103 -> 6307.4114
A105: Invested Capital | S105: =SUM(S106:S110) -> 9655.577 | T105: =SUM(T106:T110) -> 16863.946 | U105: =SUM(U106:U110) -> 17361.594 | V105: =SUM(V106:V110) -> 15820.435 | W105: =SUM(W106:W110) -> 14910.457 | X105: =SUM(X106:X110) -> 9568.3252 | Y105: =SUM(Y106:Y110) -> 10312.77 | Z105: =SUM(Z106:Z110) -> 6466.0905 | ... AF105: =SUM(AF106:AF110) -> 9154.9285
A106: Net Intangibles | H106: =H4+H5-'Cashflow Statement'!H7 -> 4368 | I106: =I4+I5-'Cashflow Statement'!I7 -> 4310 | J106: =J4+J5-'Cashflow Statement'!J7 -> 4601 | K106: =K4+K5-'Cashflow Statement'!K7 -> 5044 | L106: =L4+L5-'Cashflow Statement'!L7 -> 5113 | M106: =M4+M5-'Cashflow Statement'!M7 -> 6283 | N106: =N4+N5-'Cashflow Statement'!N7 -> 6569 | O106: =O4+O5-'Cashflow Statement'!O7 -> 7441 | ... AF106: =AF4+AF5-'Cashflow Statement'!AF7 -> 9317.3941
A107: PP&E | H107: =H6 -> 1826 | I107: =I6 -> 1847 | J107: =J6 -> 2107 | K107: =K6 -> 2201 | L107: =L6 -> 2253 | M107: =M6 -> 2486 | N107: =N6 -> 2604 | O107: =O6 -> 2642 | ... AF107: =AF6 -> 8868.9045
A108: Current assets (excluding Cash & Equivalents) | H108: =H27-H23 -> 8182 | I108: =I27-I23 -> 8568 | J108: =J27-J23 -> 8191 | K108: =K27-K23 -> 7823 | L108: =L27-L23 -> 8111 | M108: =M27-M23 -> 9379 | N108: =N27-N23 -> 10338 | O108: =O27-O23 -> 10404 | ... AF108: =AF27-AF23 -> 33687.108
A109: Current Liabilities (excluding Financial Liabilities) | H109: =H47-H39-H38 -> -6563 | I109: =I47-I39-I38 -> -7155 | J109: =J47-J39-J38 -> -7597 | K109: =K47-K39-K38 -> -7002 | L109: =L47-L39-L38 -> -7759 | M109: =M47-M39-M38 -> -9093 | N109: =N47-N39-N38 -> -9162 | O109: =O47-O39-O38 -> -9094 | ... AF109: =AF47-AF39-AF38 -> -42718.478
A110: Other current assets | H110: =H26 -> 151 | I110: =I26 -> 1142 | J110: =J26 -> 264 | K110: =K26 -> 0 | L110: =L26 -> 0 | M110: =M26 -> 0 | N110: =N26 -> 0 | O110: =O26 -> -15 | ... AF110: =AF26 -> 0
A111: ROIC (%) | S111: =S104/S105 -> 0.17678902 | T111: =T104/T105 -> 0.14142597 | U111: =U104/U105 -> 0.1617363 | V111: =V104/V105 -> 0.08545909 | W111: =W104/W105 -> 0.093424365 | X111: =X104/AVERAGE(W105:X105) -> 0.15123301 | Y111: =Y104/AVERAGE(X105:Y105) -> 0.24566051 | Z111: =Z104/AVERAGE(Y105:Z105) -> 0.3733269 | AA111: =AA104/AVERAGE(Z105:AA105) -> 0.51339514 | AB111: =AB104/AVERAGE(AA105:AB105) -> 0.61973122 | AC111: =AC104/AVERAGE(AB105:AC105) -> 0.67090575 | AD111: =AD104/AVERAGE(AC105:AD105) -> 0.6920872 | AE111: =AE104/AVERAGE(AD105:AE105) -> 0.6884647 | AF111: =AF104/AVERAGE(AE105:AF105) -> 0.69905948
A113: IFRS 16 Exchange Sheet Metrics (updated annually with AR) | B113: =B2 -> 2000 | C113: =C2 -> 2001 | D113: =D2 -> 2002 | E113: =E2 -> 2003 | F113: =F2 -> 2004 | G113: =G2 -> 2005 | H113: =H2 -> 2006 | I113: =I2 -> 2007 | ... Z113: =Z2 -> 2024 | AA113: =Z113+1 -> 2025 | AB113: =AA113+1 -> 2026 | AC113: =AB113+1 -> 2027 | AD113: =AC113+1 -> 2028 | AE113: =AD113+1 -> 2029 | AF113: =AE113+1 -> 2030
...

Sheet Multiples
I1: Historical / GSe PT | J1: ='Income Statement'!V112 -> 90 | K1: ='Income Statement'!W112 -> 107.66 | L1: ='Income Statement'!X112 -> 105.3 | M1: =135.8*0.5+154*0.5 -> 144.9 | N1: 171 | O1: 208 | P1: 240
B2: Safran Target Price Calculation | F2: EBIT, IC, ROIC | I2: SAF.PA | J2: 2020 | K2: =J2+1 -> 2021 | L2: =K2+1 -> 2022 | M2: =L2+1 -> 2023 | N2: =M2+1 -> 2024 | O2: =N2+1 -> 2025 | P2: =O2+1 -> 2026 | Q2: =P2+1 -> 2027 | R2: =Q2+1 -> 2028 | ... T2: =S2+1 -> 2030 | V2: Notes
B3: Implied LT growth rate | D3: 0.058 | F3: 12 | G3: 2026 | I3: Price | J3: 211.5 | K3: =J3 -> 211.5 | L3: =K3 -> 211.5 | M3: =L3 -> 211.5 | N3: =M3 -> 211.5 | O3: =DCF!C35 -> Error: RTD method of WorksheetFunction class failed | P3: =O3 -> Error: RTD method of WorksheetFunction class failed | Q3: =P3 -> Error: RTD method of WorksheetFunction class failed | R3: =Q3 -> Error: RTD method of WorksheetFunction class failed | S3: =R3 -> Error: RTD method of WorksheetFunction class failed | T3: =S3 -> Error: RTD method of WorksheetFunction class failed | X3: Safran TP % change
B4: {=_xlfn.IFS(AND(F3>0,F4=0),"ROIC "&F3&"M "&G3&" GSe",AND(F3>0,F4>0),"ROIC "&F3&"M "&G3&"/"&F4&"M "&G4&" GSe",AND(F3=0,F4>0),"ROIC "&F4&"M "&G4&" GSe")} -> ROIC 12M 2026 GSe | D4: =(INDEX(OpMod!163:163,MATCH(Multiples!G3,OpMod!$8:$8,0))*Multiples!F3+INDEX(OpMod!163:163,MATCH(Multiples!G4,OpMod!$8:$8,0))*Multiples!F4)/12 -> 0.59567017 | F4: =12-F3 -> 0 | G4: =G3+1 -> 2027 | I4: Number of shares | J4: ='Income Statement'!V116/1000 -> 426.03573 | K4: ='Income Statement'!W116/1000 -> 426.65042 | L4: ='Income Statement'!X116/1000 -> 426.68066 | M4: ='Income Statement'!Y116/1000 -> 417.79549 | N4: ='Income Statement'!Z116/1000 -> 416.14953 | O4: ='Income Statement'!AA116/1000 -> 411.66281 | P4: ='Income Statement'!AB116/1000 -> 407.17609 | Q4: ='Income Statement'!AC116/1000 -> 402.68937 | ... T4: ='Income Statement'!AF116/1000 -> 398.20265 | AA4: 24m fwd ROIC
B5: WACC GSe | D5: 0.09 | I5: Market cap | J5: =J3*J4 -> 90106.557 | K5: =K3*K4 -> 90236.565 | L5: =L3*L4 -> 90242.959 | M5: =M3*M4 -> 88363.747 | N5: =N3*N4 -> 88015.626 | O5: =O3*O4 -> #VALUE! | P5: =P3*P4 -> #VALUE! | Q5: =Q3*Q4 -> #VALUE! | ... T5: =T3*T4 -> #VALUE! | Y5: =D20/D30-1 -> #VALUE! | Z5: 0.21 | AA5: 0.22 | AB5: 0.23 | AC5: 0.24 | AD5: 0.25 | AE5: 0.26
B6: {=_xlfn.IFS(AND(F3>0,F4=0),"ROIC/WACC "&F3&"M "&G3&" GSe",AND(F3>0,F4>0),"ROIC/WACC "&F3&"M "&G3&"/"&F4&"M "&G4&" GSe",AND(F3=0,F4>0),"ROIC/WACC "&F4&"M "&G4&" GSe")} -> ROIC/WACC 12M 2026 GSe | D6: =+D4/D5 -> 6.6185574 | F6: M&A EBIT, EV adjustments | I6: EV | J6: =J38 -> 95763.521 | K6: =K38 -> 94734.243 | L6: =L38 -> 94148.917 | M6: =M38 -> 91823.055 | N6: =N38 -> 91003.11 | O6: =O38 -> #VALUE! | P6: =P38 -> #VALUE! | Q6: =Q38 -> #VALUE! | ... T6: =T38 -> #VALUE! | Y6: 0.05 | Z6: #VALUE! | AA6: #VALUE! | AB6: #VALUE! | AC6: #VALUE! | AD6: #VALUE! | AE6: #VALUE!
F7: =F3 -> 12 | G7: =G3-1 -> 2025 | I7: Net debt | J7: =J45 -> 2792 | K7: =K45 -> 1544 | L7: =L45 -> -14 | M7: =M45 -> -374 | N7: =N45 -> -1738 | O7: =-'DCF Feed'!B8 -> -2168.7677 | P7: =-'DCF Feed'!C8 -> -3382.4906 | Q7: =-'DCF Feed'!D8 -> -4867.2613 | R7: =-'DCF Feed'!E8 -> -6676.9131 | S7: =-'DCF Feed'!F8 -> -10162.36 | T7: =-'DCF Feed'!G8 -> -13985.148 | Y7: =+Y6+0.001 -> 0.051 | Z7: #VALUE! | AA7: #VALUE! | AB7: #VALUE! | AC7: #VALUE! | AD7: #VALUE! | AE7: #VALUE!
B8: {=_xlfn.IFS(AND(F3>0,F4=0),"Invested Capital "&F3&"M "&G3&" GSe",AND(F3>0,F4>0),"Invested Capital "&F3&"M "&G3&"/"&F4&"M "&G4&" GSe",AND(F3=0,F4>0),"Invested Capital "&F4&"M "&G4&" GSe")} -> Invested Capital 12M 2026 GSe | D8: =(INDEX(OpMod!131:131,MATCH(Multiples!G3,OpMod!$8:$8,0))*Multiples!F3+INDEX(OpMod!131:131,MATCH(Multiples!G4,OpMod!$8:$8,0))*Multiples!F4)/12 -> 0 | F8: =12-F7 -> 0 | G8: =G7+1 -> 2026 | X8: Implied LT | Y8: =+Y7+0.001 -> 0.052 | Z8: #VALUE! | AA8: #VALUE! | AB8: #VALUE! | AC8: #VALUE! | AD8: #VALUE! | AE8: #VALUE! | AF8: WIP Safran TP % change
B9: Multiplier | D9: =+(D10/D8)/D6 -> #DIV/0! | I9: Sales | J9: ='Income Statement'!V9 -> 16498 | K9: ='Income Statement'!W9 -> 15257 | L9: ='Income Statement'!X9 -> 19035 | M9: ='Income Statement'!Y9 -> 23199 | N9: ='Income Statement'!Z9 -> 27317 | O9: ='Income Statement'!AA9 -> 30995.967 | P9: ='Income Statement'!AB9 -> 34520.707 | Q9: ='Income Statement'!AC9 -> 38170.591 | ... T9: ='Income Statement'!AF9 -> 45535.884 | V9: REVS_PUB | X9: Growth | Y9: =+Y8+0.001 -> 0.053 | Z9: #VALUE! | AA9: #VALUE! | AB9: #VALUE! | AC9: #VALUE! | AD9: #VALUE! | AE9: #VALUE!
B10: EV implied by EV/IC-ROIC/WACC | D10: =+(D4-D3)/(D5-D3)*D8 -> 0 | I10: Adj. EBITDA | J10: ='Income Statement'!V193 -> 3133 | K10: ='Income Statement'!W193 -> 3185 | L10: ='Income Statement'!X193 -> 3781 | M10: ='Income Statement'!Y193 -> 4502 | N10: ='Income Statement'!Z193 -> 5525 | O10: ='Income Statement'!AA193 -> 6751.4506 | P10: ='Income Statement'!AB193 -> 7834.076 | Q10: ='Income Statement'!AC193 -> 8780.1449 | ... T10: ='Income Statement'!AF193 -> 10799.176 | V10: EBITDA_PUB | Y10: =+Y9+0.001 -> 0.054 | Z10: #VALUE! | AA10: #VALUE! | AB10: #VALUE! | AC10: #VALUE! | AD10: #VALUE! | AE10: #VALUE!
H11: =(R11/N11)^(0.25)-1 -> 0.16564223 | I11: Adj. EBIT | J11: ='Income Statement'!V23 -> 1686 | K11: ='Income Statement'!W23 -> 1805 | L11: ='Income Statement'!X23 -> 2408 | M11: ='Income Statement'!Y23 -> 3166 | N11: ='Income Statement'!Z23 -> 4119 | O11: ='Income Statement'!AA23 -> 5179.0618 | P11: ='Income Statement'!AB23 -> 6014.9129 | Q11: ='Income Statement'!AC23 -> 6844.9824 | ... T11: ='Income Statement'!AF23 -> 8490.6102 | V11: EBIT_PUB | Y11: =+Y10+0.001 -> 0.055 | Z11: #VALUE! | AA11: #VALUE! | AB11: #VALUE! | AC11: #VALUE! | AD11: #VALUE! | AE11: #VALUE!
B12: {=_xlfn.IFS(AND(F7>0,F8=0),"Net debt (cash) "&F7&"M "&G7&" GSe",AND(F7>0,F8>0),"Net debt (cash) "&F7&"M "&G7&"/"&F8&"M "&G8&" GSe",AND(F7=0,F8>0),"Net debt (cash) "&F8&"M "&G8&" GSe")} -> Net debt (cash) 12M 2025 GSe | D12: =(INDEX($L$27:$S$27,MATCH(Multiples!G7,$L$2:$S$2,0))*Multiples!F7+INDEX($L$27:$S$27,MATCH(Multiples!G8,$L$2:$S$2,0))*Multiples!F8)/12 -> -2168.7677 | H12: =(R12/N12)^(0.25)-1 -> 0.17991991 | I12: EPS | J12: ='Income Statement'!V104 -> 1.9834017 | K12: ='Income Statement'!W104 -> 1.778974 | L12: ='Income Statement'!X104 -> 2.760847 | M12: ='Income Statement'!Y104 -> 4.856443 | N12: ='Income Statement'!Z104 -> 7.374753 | O12: ='Income Statement'!AA104 -> 8.4933209 | P12: ='Income Statement'!AB104 -> 11.031574 | Q12: ='Income Statement'!AC104 -> 12.701904 | ... T12: ='Income Statement'!AF104 -> 16.068315 | V12: EPS_PUB | Y12: =+Y11+0.001 -> 0.056 | Z12: #VALUE! | AA12: #VALUE! | AB12: #VALUE! | AC12: #VALUE! | AD12: #VALUE! | AE12: #VALUE!
B13: {=_xlfn.IFS(AND(F7>0,F8=0),"Pension liabilities "&F7&"M "&G7&" GSe",AND(F7>0,F8>0),"Pension liabilities "&F7&"M "&G7&"/"&F8&"M "&G8&" GSe",AND(F7=0,F8>0),"Pension liabilities "&F8&"M "&G8&" GSe")} -> Pension liabilities 12M 2025 GSe | D13: =(INDEX($L$28:$S$28,MATCH(Multiples!G7,$L$2:$S$2,0))*Multiples!F7+INDEX($L$28:$S$28,MATCH(Multiples!G8,$L$2:$S$2,0))*Multiples!F8)/12 -> -23 | I13: DPS | J13: ='Income Statement'!V109 -> 0.43 | K13: ='Income Statement'!W109 -> 0.5 | L13: ='Income Statement'!X109 -> 1.35 | M13: ='Income Statement'!Y109 -> 2.2 | N13: ='Income Statement'!Z109 -> 2.9 | O13: ='Income Statement'!AA109 -> 3.3973284 | P13: ='Income Statement'!AB109 -> 4.4126298 | Q13: ='Income Statement'!AC109 -> 5.0807618 | ... T13: ='Income Statement'!AF109 -> 6.4273258 | V13: DPS_PUB | Y13: =+Y12+0.001 -> 0.057 | Z13: #VALUE! | AA13: #VALUE! | AB13: #VALUE! | AC13: #VALUE! | AD13: #VALUE! | AE13: #VALUE!
B14: {=_xlfn.IFS(AND(F7>0,F8=0),"Minority interests "&F7&"M "&G7&" GSe",AND(F7>0,F8>0),"Minority interests "&F7&"M "&G7&"/"&F8&"M "&G8&" GSe",AND(F7=0,F8>0),"Minority interests "&F8&"M "&G8&" GSe")} -> Minority interests 12M 2025 GSe | D14: =(INDEX($L$29:$S$29,MATCH(Multiples!G7,$L$2:$S$2,0))*Multiples!F7+INDEX($L$29:$S$29,MATCH(Multiples!G8,$L$2:$S$2,0))*Multiples!F8)/12 -> #VALUE! | I14: FCF | J14: ='Cashflow Statement'!V57 -> 1073 | K14: ='Cashflow Statement'!W57 -> 1680 | L14: ='Cashflow Statement'!X57 -> 2666 | M14: ='Cashflow Statement'!Y57 -> 2945 | N14: ='Cashflow Statement'!Z57 -> 3189 | O14: ='Cashflow Statement'!AA57 -> 3518.6013 | P14: ='Cashflow Statement'!AB57 -> 4206.2767 | Q14: ='Cashflow Statement'!AC57 -> 4875.488 | ... T14: ='Cashflow Statement'!AF57 -> 6582.9645
B15: {=_xlfn.IFS(AND(F7>0,F8=0),"Other EV adj. "&F7&"M "&G7&" GSe",AND(F7>0,F8>0),"Other EV adj. "&F7&"M "&G7&"/"&F8&"M "&G8&" GSe",AND(F7=0,F8>0),"Other EV adj. "&F8&"M "&G8&" GSe")} -> Other EV adj. 12M 2025 GSe | D15: =(INDEX($L$30:$S$30,MATCH(Multiples!G7,$L$2:$S$2,0))*Multiples!F7+INDEX($L$30:$S$30,MATCH(Multiples!G8,$L$2:$S$2,0))*Multiples!F8)/12 -> -3210 | F15: div | G15: 0.02 | I15: FCF per share | J15: =J14/J4 -> 2.5185681 | K15: =K14/K4 -> 3.9376499 | L15: =L14/L4 -> 6.2482326 | M15: =M14/M4 -> 7.0489032 | N15: =N14/N4 -> 7.6631109 | O15: =O14/O4 -> 8.5472898 | P15: =P14/P4 -> 10.330363 | Q15: =Q14/Q4 -> 12.107317 | ... T15: =T14/T4 -> 16.531694
B16: {=_xlfn.IFS(AND(F7>0,F8=0),"EV Adjustments "&F7&"M "&G7&" GSe",AND(F7>0,F8>0),"EV Adjustments "&F7&"M "&G7&"/"&F8&"M "&G8&" GSe",AND(F7=0,F8>0),"EV Adjustments "&F8&"M "&G8&" GSe")} -> EV Adjustments 12M 2025 GSe | D16: =SUM(D12:D15) -> #VALUE! | F16: bb | G16: 0.025
F17: EPS | G17: 0.15 | I17: P/E | J17: =J3/J12 -> 106.63498 | K17: =K3/K12 -> 118.88875 | L17: =L3/L12 -> 76.606926 | M17: =M3/M12 -> 43.550393 | N17: =N3/N12 -> 28.678927 | O17: =O3/O12 -> #VALUE! | P17: =P3/P12 -> #VALUE! | Q17: =Q3/Q12 -> #VALUE! | ... T17: =T3/T12 -> #VALUE!
B18: Market Cap implied by EV/IC-ROIC/WACC | D18: =+D10-D16 -> #VALUE! | F18: TSR | G18: =SUM(G15:G17) -> 0.195 | I18: FCF yield | J18: =J15/J3 -> 0.011908123 | K18: =K15/K3 -> 0.01861773 | L18: =L15/L3 -> 0.029542471 | M18: =M15/M3 -> 0.033328148 | N18: =N15/N3 -> 0.036232203 | O18: =O15/O3 -> #VALUE! | P18: =P15/P3 -> #VALUE! | Q18: =Q15/Q3 -> #VALUE! | ... T18: =T15/T3 -> #VALUE! | X18: Safran TP % change
B19: NOSH | D19: =(INDEX(OpMod!#REF!,MATCH(Multiples!G3,OpMod!$8:$8,0))*Multiples!F3+INDEX(OpMod!#REF!,MATCH(Multiples!G4,OpMod!$8:$8,0))*Multiples!F4)/12/1000 -> #REF! | I19: Dividend yield | J19: =J13/J3 -> 0.0020330969 | K19: =K13/K3 -> 0.0023640662 | L19: =L13/L3 -> 0.0063829787 | M19: =M13/M3 -> 0.010401891 | N19: =N13/N3 -> 0.013711584 | O19: =O13/O3 -> #VALUE! | P19: =P13/P3 -> #VALUE! | Q19: =Q13/Q3 -> #VALUE! | ... T19: =T13/T3 -> #VALUE! | AA19: WACC
B20: GS Target Price | D20: =ROUND(D18/D19,0) -> #VALUE! | I20: EV/Sales | J20: =J6/J9 -> 5.8045534 | K20: =K6/K9 -> 6.2092314 | L20: =L6/L9 -> 4.9460949 | M20: =M6/M9 -> 3.9580609 | N20: =N6/N9 -> 3.3313728 | O20: =O6/O9 -> #VALUE! | P20: =P6/P9 -> #VALUE! | Q20: =Q6/Q9 -> #VALUE! | ... T20: =T6/T9 -> #VALUE! | Y20: =D20/D30-1 -> #VALUE! | Z20: 0.075 | AA20: 0.08 | AB20: 0.085 | AC20: 0.09 | AD20: 0.095 | AE20: 0.1
I21: EV/EBIT | J21: =J6/J11 -> 56.799242 | K21: =K6/K11 -> 52.484345 | L21: =L6/L11 -> 39.098387 | M21: =M6/M11 -> 29.00286 | N21: =N6/N11 -> 22.093496 | O21: =O6/O11 -> #VALUE! | P21: =P6/P11 -> #VALUE! | Q21: =Q6/Q11 -> #VALUE! | ... T21: =T6/T11 -> #VALUE! | Y21: 0.05 | Z21: #VALUE! | AA21: #VALUE! | AB21: #VALUE! | AC21: #VALUE! | AD21: #VALUE! | AE21: #VALUE!
B22: {=_xlfn.IFS(AND(F3>0,F4=0),"EBIT "&F3&"M "&G3&" GSe",AND(F3>0,F4>0),"EBIT "&F3&"M "&G3&"/"&F4&"M "&G4&" GSe",AND(F3=0,F4>0),"EBIT "&F4&"M "&G4&" GSe")} -> EBIT 12M 2026 GSe | D22: =(INDEX($L$11:$S$11,MATCH(Multiples!G3,$L$2:$S$2,0))*Multiples!F3+INDEX($L$11:$S$11,MATCH(Multiples!G4,$L$2:$S$2,0))*Multiples!F4)/12 -> 6014.9129 | I22: EV/EBITDA | J22: =J6/J10 -> 30.566078 | K22: =K6/K10 -> 29.743875 | L22: =L6/L10 -> 24.900533 | M22: =M6/M10 -> 20.396058 | N22: =N6/N10 -> 16.471151 | O22: =O6/O10 -> #VALUE! | P22: =P6/P10 -> #VALUE! | Q22: =Q6/Q10 -> #VALUE! | ... T22: =T6/T10 -> #VALUE! | Y22: 0.0506 | Z22: #VALUE! | AA22: #VALUE! | AB22: #VALUE! | AC22: #VALUE! | AD22: #VALUE! | AE22: #VALUE! | AF22: Safran TP % change if were
B23: Implied EV/EBIT | D23: =D10/D22 -> 0 | I23: Net Debt/EBITDA | J23: =J45/J10 -> 0.89115863 | K23: =K27/K10 -> 0.48477237 | L23: =L27/L10 -> -0.0037027241 | M23: =M27/M10 -> -0.083074189 | N23: =N27/N10 -> -0.31457014 | O23: =O27/O10 -> -0.32122988 | P23: =P27/P10 -> -0.43176638 | Q23: =Q27/Q10 -> -0.55434863 | R23: =R27/R10 -> -0.68812191 | ... T23: =T27/T10 -> -1.2950198 | X23: Implied LT | Y23: 0.052 | Z23: #VALUE! | AA23: #VALUE! | AB23: #VALUE! | AC23: #VALUE! | AD23: #VALUE! | AE23: #VALUE! | AF23: to not change implied LT growth
B24: {=_xlfn.IFS(AND(F3>0,F4=0),"EPS "&F3&"M "&G3&" GSe",AND(F3>0,F4>0),"EPS "&F3&"M "&G3&"/"&F4&"M "&G4&" GSe",AND(F3=0,F4>0),"EPS "&F4&"M "&G4&" GSe")} -> EPS 12M 2026 GSe | D24: =(INDEX($L$12:$S$12,MATCH(Multiples!G3,$L$2:$S$2,0))*Multiples!F3+INDEX($L$12:$S$12,MATCH(Multiples!G4,$L$2:$S$2,0))*Multiples!F4)/12 -> 11.031574 | J24: =J6/J11 -> 56.799242 | K24: =K6/K11 -> 52.484345 | L24: =L6/L11 -> 39.098387 | M24: =M6/M11 -> 29.00286 | N24: =N6/N11 -> 22.093496 | O24: =O6/O11 -> #VALUE! | P24: =P6/P11 -> #VALUE! | Q24: =Q6/Q11 -> #VALUE! | ... T24: =T6/T11 -> #VALUE! | X24: Growth | Y24: 0.053 | Z24: #VALUE! | AA24: #VALUE! | AB24: #VALUE! | AC24: #VALUE! | AD24: #VALUE! | AE24: #VALUE!
B25: Implied P/E | D25: =D20/D24 -> #VALUE! | I25: EV breakout | Y25: 0.054 | Z25: #VALUE! | AA25: #VALUE! | AB25: #VALUE! | AC25: #VALUE! | AD25: #VALUE! | AE25: #VALUE!
I26: Market cap | J26: =J5 -> 90106.557 | K26: =K5 -> 90236.565 | L26: =L5 -> 90242.959 | M26: =M5 -> 88363.747 | N26: =N5 -> 88015.626 | O26: =O5 -> #VALUE! | P26: =P5 -> #VALUE! | Q26: =Q5 -> #VALUE! | ... T26: =T5 -> #VALUE! | V26: ADAPTCAPIHISTO | Y26: 0.055 | Z26: #VALUE! | AA26: #VALUE! | AB26: #VALUE! | AC26: #VALUE! | AD26: #VALUE! | AE26: #VALUE!
B27: Upside/Downside | D27: =D20/D31-1 -> #VALUE! | I27: Net debt (cash) | J27: =J45 -> 2792 | K27: =K45 -> 1544 | L27: =L45 -> -14 | M27: =M45 -> -374 | N27: =N45 -> -1738 | O27: =O7 -> -2168.7677 | P27: =P7 -> -3382.4906 | Q27: =Q7 -> -4867.2613 | R27: =R7 -> -6676.9131 | S27: =S7 -> -10162.36 | T27: =T7 -> -13985.148 | V27: NET_DEBT_PUB | Y27: 0.056 | Z27: #VALUE! | AA27: #VALUE! | AB27: #VALUE! | AC27: #VALUE! | AD27: #VALUE! | AE27: #VALUE!
B28: PT Change | D28: =D20/D30-1 -> #VALUE! | I28: Pension liabilities | J28: =K28 -> -61 | K28: ='Balance Sheet'!W140 -> -61 | L28: ='Balance Sheet'!X140 -> -24 | M28: ='Balance Sheet'!Y140 -> -67 | N28: ='Balance Sheet'!Z140 -> -23 | O28: ='Balance Sheet'!AA140 -> -23 | P28: ='Balance Sheet'!AB140 -> -23 | Q28: ='Balance Sheet'!AC140 -> -23 | R28: ='Balance Sheet'!AD140 -> -23 | ... T28: ='Balance Sheet'!AF140 -> -23 | V28: UNF_PENS_LIAB_OTH | Y28: 0.057 | Z28: #VALUE! | AA28: #VALUE! | AB28: #VALUE! | AC28: #VALUE! | AD28: #VALUE! | AE28: #VALUE!
I29: Minority interests | J29: ='Balance Sheet'!V53*J26/SUM('Balance Sheet'!V49:V52) -> 2925.964 | K29: ='Balance Sheet'!W53*K26/SUM('Balance Sheet'!W49:W52) -> 3014.6785 | L29: ='Balance Sheet'!X53*L26/SUM('Balance Sheet'!X49:X52) -> 3943.958 | M29: ='Balance Sheet'!Y53*M26/SUM('Balance Sheet'!Y49:Y52) -> 3900.3088 | N29: ='Balance Sheet'!Z53*N26/SUM('Balance Sheet'!Z49:Z52) -> 4748.4845 | O29: ='Balance Sheet'!AA53*Multiples!O26/(SUM('Balance Sheet'!AA49:AA52)) -> #VALUE! | P29: ='Balance Sheet'!AB53*Multiples!P26/(SUM('Balance Sheet'!AB49:AB52)) -> #VALUE! | Q29: ='Balance Sheet'!AC53*Multiples!Q26/(SUM('Balance Sheet'!AC49:AC52)) -> #VALUE! | R29: ='Balance Sheet'!AD53*Multiples!R26/(SUM('Balance Sheet'!AD49:AD52)) -> #VALUE! | S29: ='Balance Sheet'!AE53*Multiples!S26/(SUM('Balance Sheet'!AE49:AE52)) -> #VALUE! | T29: ='Balance Sheet'!AF53*Multiples!T26/(SUM('Balance Sheet'!AF49:AF52)) -> #VALUE! | V29: BAL_MINO_INT | AE29: Moving our implied LT growth rate from 5.1% to 5.7% is equivalent to not changing WACC
B30: Old PT | D30: Error: RTD method of WorksheetFunction class failed | I30: Other EV adjustments | J30: =SUM(J31:J37) -> -2900 | K30: =SUM(K31:K37) -> -2858 | L30: =SUM(L31:L37) -> -2240 | M30: =SUM(M31:M37) -> -2194 | N30: =SUM(N31:N37) -> -2211 | O30: =SUM(O31:O37) -> -3210 | P30: =SUM(P31:P37) -> -3210 | Q30: =SUM(Q31:Q37) -> -3210 | ... T30: =SUM(T31:T37) -> -3210 | V30: EV_ADJ_PUB
B31: Last Price | D31: Error: RTD method of WorksheetFunction class failed | I31: Excess customer advances | J31: =OpMod!X289 -> 209 | K31: =OpMod!Y289 -> 230 | L31: =OpMod!Z289 -> 1030 | M31: =OpMod!AA289 -> 1293 | N31: =OpMod!AB289 -> 1286 | O31: =OpMod!AC289 -> 0 | P31: =OpMod!AD289 -> 0 | Q31: =OpMod!AE289 -> 0 | ... T31: =OpMod!AH289 -> 0
I32: Launch Aid/risk sharing partner liablities | J32: =OpMod!X290 -> -426 | K32: =OpMod!Y290 -> -327 | L32: =OpMod!Z290 -> -302 | M32: =OpMod!AA290 -> -292 | N32: =OpMod!AB290 -> -287 | O32: 0 | P32: 0 | Q32: 0 | R32: 0 | S32: 0 | T32: 0
I33: Net vendor financing assets/liablities | J33: =OpMod!X291 -> 0 | K33: =OpMod!Y291 -> 0 | L33: =OpMod!Z291 -> 0 | M33: =OpMod!AA291 -> 0 | N33: =OpMod!AB291 -> 0 | O33: =OpMod!AC291 -> 0 | P33: =OpMod!AD291 -> 0 | Q33: =OpMod!AE291 -> 0 | ... T33: =OpMod!AH291 -> 0 | X33: Safran TP % change
I34: Provisions/obligations for aircraft leassing | J34: =OpMod!X292 -> 0 | K34: =OpMod!Y292 -> 0 | L34: =OpMod!Z292 -> 0 | M34: =OpMod!AA292 -> 0 | N34: =OpMod!AB292 -> 0 | O34: =OpMod!AC292 -> 0 | P34: =OpMod!AD292 -> 0 | Q34: =OpMod!AE292 -> 0 | ... T34: =OpMod!AH292 -> 0 | AA34: ROIC
I35: Less Investments | J35: =OpMod!X293 -> -2683 | K35: =OpMod!Y293 -> -2761 | L35: =OpMod!Z293 -> -2968 | M35: =OpMod!AA293 -> -3195 | N35: =OpMod!AB293 -> -3210 | O35: =OpMod!AC293 -> -3210 | P35: =OpMod!AD293 -> -3210 | Q35: =OpMod!AE293 -> -3210 | ... T35: =OpMod!AH293 -> -3210 | Y35: =D20/D30-1 -> #VALUE! | Z35: 0.16 | AA35: 0.18 | AB35: 0.20968442 | AC35: 0.22 | AD35: 0.24 | AE35: 0.26
I36: Cash provisions to be utilised | J36: =OpMod!X294 -> 0 | K36: =OpMod!Y294 -> 0 | L36: =OpMod!Z294 -> 0 | M36: =OpMod!AA294 -> 0 | N36: =OpMod!AB294 -> 0 | O36: =OpMod!AC294 -> 0 | P36: =OpMod!AD294 -> 0 | Q36: =OpMod!AE294 -> 0 | ... T36: =OpMod!AH294 -> 0 | Y36: 0.075 | Z36: #VALUE! | AA36: #VALUE! | AB36: #VALUE! | AC36: #VALUE! | AD36: #VALUE! | AE36: #VALUE!
I37: Others | J37: =OpMod!X295 -> 0 | K37: =OpMod!Y295 -> 0 | L37: =OpMod!Z295 -> 0 | M37: =OpMod!AA295 -> 0 | N37: =OpMod!AB295 -> 0 | O37: =OpMod!AC295 -> 0 | P37: =OpMod!AD295 -> 0 | Q37: =OpMod!AE295 -> 0 | ... T37: =OpMod!AH295 -> 0 | Y37: 0.08 | Z37: #VALUE! | AA37: #VALUE! | AB37: #VALUE! | AC37: #VALUE! | AD37: #VALUE! | AE37: #VALUE!
I38: Implied EV | J38: =SUM(J26:J29) -> 95763.521 | K38: =SUM(K26:K29) -> 94734.243 | L38: =SUM(L26:L29) -> 94148.917 | M38: =SUM(M26:M29) -> 91823.055 | N38: =SUM(N26:N29) -> 91003.11 | O38: =SUM(O26:O29) -> #VALUE! | P38: =SUM(P26:P29) -> #VALUE! | Q38: =SUM(Q26:Q29) -> #VALUE! | ... T38: =SUM(T26:T29) -> #VALUE! | V38: EV_PUB | Y38: 0.085 | Z38: #VALUE! | AA38: #VALUE! | AB38: #VALUE! | AC38: #VALUE! | AD38: #VALUE! | AE38: #VALUE!
X39: WACC | Y39: 0.09 | Z39: #VALUE! | AA39: #VALUE! | AB39: #VALUE! | AC39: #VALUE! | AD39: #VALUE! | AE39: #VALUE!
I40: Net debt breakout | Y40: 0.095 | Z40: #VALUE! | AA40: #VALUE! | AB40: #VALUE! | AC40: #VALUE! | AD40: #VALUE! | AE40: #VALUE!
I41: Cash | J41: =OpMod!X274 -> 3747 | K41: =OpMod!Y274 -> 5247 | L41: =OpMod!Z274 -> 6687 | M41: =OpMod!AA274 -> 6676 | N41: =OpMod!AB274 -> 6514 | O41: =OpMod!AC274 -> 7231.7677 | P41: =OpMod!AD274 -> 8445.4906 | Q41: =OpMod!AE274 -> 9930.2613 | ... T41: =OpMod!AH274 -> 19048.148 | Y41: 0.1 | Z41: #VALUE! | AA41: #VALUE! | AB41: #VALUE! | AC41: #VALUE! | AD41: #VALUE! | AE41: #VALUE!
I42: Short Term Debt | J42: =OpMod!X275 -> -2509 | K42: =OpMod!Y275 -> -1720 | L42: =OpMod!Z275 -> -1277 | M42: =OpMod!AA275 -> -1608 | N42: =OpMod!AB275 -> -988 | O42: =OpMod!AC275 -> -988 | P42: =OpMod!AD275 -> -988 | Q42: =OpMod!AE275 -> -988 | ... T42: =OpMod!AH275 -> -988 | Y42: 0.105 | Z42: #VALUE! | AA42: #VALUE! | AB42: #VALUE! | AC42: #VALUE! | AD42: #VALUE! | AE42: #VALUE!
I43: Long Term Debt | J43: =OpMod!X276 -> -4082 | K43: =OpMod!Y276 -> -5094 | L43: =OpMod!Z276 -> -5378 | M43: =OpMod!AA276 -> -4691 | N43: =OpMod!AB276 -> -3788 | O43: =OpMod!AC276 -> -3788 | P43: =OpMod!AD276 -> -3788 | Q43: =OpMod!AE276 -> -3788 | ... T43: =OpMod!AH276 -> -3788 | Y43: 0.11 | Z43: #VALUE! | AA43: #VALUE! | AB43: #VALUE! | AC43: #VALUE! | AD43: #VALUE! | AE43: #VALUE!
I44: FV of interest rate derivatives (hedging borrowings) | J44: =OpMod!X277 -> 52 | K44: =OpMod!Y277 -> 23 | L44: =OpMod!Z277 -> -18 | M44: =OpMod!AA277 -> -3 | N44: =OpMod!AB277 -> 0 | O44: =OpMod!AC277 -> 0 | P44: =OpMod!AD277 -> 0 | Q44: =OpMod!AE277 -> 0 | ... T44: =OpMod!AH277 -> 0
I45: Net Debt | J45: =OpMod!X273 -> 2792 | K45: =OpMod!Y273 -> 1544 | L45: =OpMod!Z273 -> -14 | M45: =OpMod!AA273 -> -374 | N45: =OpMod!AB273 -> -1738 | O45: =OpMod!AC273 -> -2455.7677 | P45: =OpMod!AD273 -> -3669.4906 | Q45: =OpMod!AE273 -> -5154.2613 | ... T45: =OpMod!AH273 -> -14272.148 | V45: NET_DEBT_PUB
I47: Rf | J47: 0.009 | K47: 0.0151 | L47: 0.0387 | M47: 0.039 | N47: 0.0375 | O47: 0.0375 | P47: 0.0375 | Q47: 0.0375 | R47: 0.0375 | S47: 0.0375 | T47: 0.0375
I48: ERP | J48: 0.04 | K48: 0.04 | L48: 0.04 | M48: 0.04 | N48: 0.04 | O48: 0.04 | P48: 0.04 | Q48: 0.04 | R48: 0.04 | S48: 0.04 | T48: 0.04 | X48: Safran TP % upside
I49: SAF Beta | J49: 2 | K49: =J49 -> 2 | L49: =K49 -> 2 | M49: =L49 -> 2 | N49: =M49 -> 2 | O49: =N49 -> 2 | P49: =O49 -> 2 | Q49: =P49 -> 2 | R49: =Q49 -> 2 | ... T49: =S49 -> 2 | AA49: WACC
I50: COE | J50: =J47+J49*J48 -> 0.089 | K50: =K47+K49*K48 -> 0.0951 | L50: =L47+L49*L48 -> 0.1187 | M50: =M47+M49*M48 -> 0.119 | N50: =N47+N49*N48 -> 0.1175 | O50: =O47+O49*O48 -> 0.1175 | P50: =P47+P49*P48 -> 0.1175 | Q50: =Q47+Q49*Q48 -> 0.1175 | ... T50: =T47+T49*T48 -> 0.1175 | Y50: =D20/108.04-1 -> #VALUE! | Z50: 0.075 | AA50: 0.08 | AB50: 0.085 | AC50: 0.09 | AD50: 0.095 | AE50: 0.1
P51: =((1+L57)*(1+M57)*(1+N57)*(1+O57))^0.25-1 -> 0.25629404 | Q51: =((1+M57)*(1+N57)*(1+O57))^(1/3)-1 -> 0.21262625 | Y51: 0.05 | Z51: #VALUE! | AA51: #VALUE! | AB51: #VALUE! | AC51: #VALUE! | AD51: #VALUE! | AE51: #VALUE!
I52: GS modelled returns | J52: =J2 -> 2020 | K52: =J52+1 -> 2021 | L52: =K52+1 -> 2022 | M52: =L52+1 -> 2023 | N52: =M52+1 -> 2024 | O52: =N52+1 -> 2025 | P52: =O52+1 -> 2026 | Q52: =P52+1 -> 2027 | R52: =Q52+1 -> 2028 | ... T52: =S52+1 -> 2030 | Y52: 0.0506 | Z52: #VALUE! | AA52: #VALUE! | AB52: #VALUE! | AC52: #VALUE! | AD52: #VALUE! | AE52: #VALUE! | AF52: Safran TP % upside if were
I53: 2yr fwd Price return | J53: =(L1/J1)^0.5-1 -> 0.081665383 | K53: =(M1/K1)^0.5-1 -> 0.16013093 | L53: =(N1/L1)^0.5-1 -> 0.27433576 | M53: =(O1/M1)^0.5-1 -> 0.19811216 | N53: =(P1/N1)^0.5-1 -> 0.18469776 | O53: =(Q1/O1)^0.5-1 -> -1 | P53: =(R1/P1)^0.5-1 -> -1 | Q53: =(S1/Q1)^0.5-1 -> #DIV/0! | R53: =(U1/R1)^0.5-1 -> #DIV/0! | S53: =(V1/S1)^0.5-1 -> #DIV/0! | T53: =(W1/T1)^0.5-1 -> #DIV/0! | X53: Implied LT | Y53: 0.052 | Z53: #VALUE! | AA53: #VALUE! | AB53: #VALUE! | AC53: #VALUE! | AD53: #VALUE! | AE53: #VALUE! | AF53: to not change implied LT growth
I54: 1yr fwd Dividend | J54: =K13/J1 -> 0.0055555556 | K54: =L13/K1 -> 0.012539476 | L54: =M13/L1 -> 0.020892688 | M54: =N13/M1 -> 0.020013803 | N54: =O13/N1 -> 0.019867417 | O54: =P13/O1 -> 0.021214566 | P54: =Q13/P1 -> 0.021169841 | Q54: =R13/Q1 -> #DIV/0! | R54: =S13/R1 -> #DIV/0! | S54: =U13/S1 -> #DIV/0! | T54: =V13/T1 -> #VALUE! | X54: Growth | Y54: 0.053 | Z54: #VALUE! | AA54: #VALUE! | AB54: #VALUE! | AC54: #VALUE! | AD54: #VALUE! | AE54: #VALUE!
I55: 1yr fwd Buyback | J55: 0 | K55: 0 | L55: =OpMod!AA205/(OpMod!Z204*('Income Statement'!Y116/1000)) -> 0 | M55: =OpMod!AB205/(OpMod!AA204*('Income Statement'!Z116/1000)) -> 0 | N55: =OpMod!AC205/(OpMod!AB204*('Income Statement'!AA116/1000)) -> 0.015095781 | O55: =OpMod!AD205/(OpMod!AC204*('Income Statement'!AB116/1000)) -> 0.012279699 | P55: =OpMod!AE205/(OpMod!AD204*('Income Statement'!AC116/1000)) -> 0.010347099 | Q55: =OpMod!AF205/(OpMod!AE204*('Income Statement'!AD116/1000)) -> 0.0093425749 | R55: =OpMod!AG205/(OpMod!AF204*('Income Statement'!AE116/1000)) -> 0.0083415847 | S55: =OpMod!AH205/(OpMod!AG204*('Income Statement'!AF116/1000)) -> 0.0074418852 | T55: =OpMod!AI205/(OpMod!AH204*('Income Statement'!#REF!/1000)) -> #REF! | Y55: 0.054 | Z55: #VALUE! | AA55: #VALUE! | AB55: #VALUE! | AC55: #VALUE! | AD55: #VALUE! | AE55: #VALUE!
I56: 1yr fwd price return | J56: =(K1/J1)-1 -> 0.19622222 | K56: =(L1/K1)-1 -> -0.021920862 | L56: =(M1/L1)-1 -> 0.37606838 | M56: =(N1/M1)-1 -> 0.18012422 | N56: =(O1/N1)-1 -> 0.21637427 | O56: =(P1/O1)-1 -> 0.15384615 | P56: =(Q1/P1)-1 -> -1 | Q56: =(R1/Q1)-1 -> #DIV/0! | R56: =(S1/R1)-1 -> #DIV/0! | S56: =(U1/S1)-1 -> #DIV/0! | T56: =(V1/T1)-1 -> #DIV/0! | Y56: 0.055 | Z56: #VALUE! | AA56: #VALUE! | AB56: #VALUE! | AC56: #VALUE! | AD56: #VALUE! | AE56: #VALUE!
I57: 1yr fwd total return | J57: =SUM(J54:J56) -> 0.20177778 | K57: =SUM(K54:K56) -> -0.0093813858 | L57: =SUM(L54:L56) -> 0.39696106 | M57: =SUM(M54:M56) -> 0.20013803 | N57: =SUM(N54:N56) -> 0.25133747 | O57: =SUM(O54:O56) -> 0.18734042 | P57: =SUM(P54:P56) -> -0.96848306 | Q57: =SUM(Q54:Q56) -> #DIV/0! | ... T57: =SUM(T54:T56) -> #VALUE! | Y57: 0.056 | Z57: #VALUE! | AA57: #VALUE! | AB57: #VALUE! | AC57: #VALUE! | AD57: #VALUE! | AE57: #VALUE!
I58: Returns vs WACC | J58: =J57-$D$5 -> 0.11177778 | K58: =K57-$D$5 -> -0.099381386 | L58: =L57-$D$5 -> 0.30696106 | M58: =M57-$D$5 -> 0.11013803 | N58: =N57-$D$5 -> 0.16133747 | O58: =O57-$D$5 -> 0.09734042 | P58: =P57-$D$5 -> -1.0584831 | Q58: =Q57-$D$5 -> #DIV/0! | ... T58: =T57-$D$5 -> #VALUE! | Y58: 0.057 | Z58: #VALUE! | AA58: #VALUE! | AB58: #VALUE! | AC58: #VALUE! | AD58: #VALUE! | AE58: #VALUE!
I59: Returns vs CoE | J59: =J57-J50 -> 0.11277778 | K59: =K57-K50 -> -0.10448139 | L59: =L57-L50 -> 0.27826106 | M59: =M57-M50 -> 0.081138026 | N59: =N57-N50 -> 0.13383747 | O59: =O57-O50 -> 0.06984042 | P59: =P57-P50 -> -1.0859831 | Q59: =Q57-Q50 -> #DIV/0! | ... T59: =T57-T50 -> #VALUE! | AE59: Moving our implied LT growth rate from 5.1% to 5.7% is equivalent to not changing WACC
X61: Safran EPS % change
AA62: Mid-point of FX corridor
Y63: =O12/9.27-1 -> -0.083784154 | Z63: =AA63-0.01 -> 1.11 | AA63: =AB63-0.01 -> 1.12 | AB63: =AC63-0.01 -> 1.13 | AC63: 1.14 | AD63: =AE63-0.01 -> 1.14 | AE63: 1.15
O64: =OpMod!AB205 -> 0 | P64: =OpMod!AB517/(OpMod!AB516*(OpMod!AB217/1000))
O65: =(OpMod!AB204) -> 201.14664
O66: ='Income Statement'!Z116 -> 416149.53 | X66: Implied LT
X67: Growth

Sheet Exhibit 3 Statements
B2: Income Statement (€ mn) | C2: 2015 | D2: 2016E | E2: 2017 | F2: 2018 | G2: =F2+1 -> 2019 | H2: =G2+1 -> 2020 | I2: =H2+1 -> 2021 | J2: =I2+1 -> 2022 | K2: =J2+1 -> 2023 | L2: =K2+1 -> 2024 | M2: =L2+1 -> 2025 | N2: =M2+1 -> 2026 | ... R2: =Q2+1 -> 2030
B3: Adj. Revenues | C3: ='Income Statement'!Q39 -> 17414 | D3: ='Income Statement'!R39 -> 15781 | E3: ='Income Statement'!S39 -> 15953 | F3: ='Income Statement'!T39 -> 21050 | G3: ='Income Statement'!U39 -> 24640 | H3: ='Income Statement'!V39 -> 16498 | I3: ='Income Statement'!W39 -> 15257 | J3: ='Income Statement'!X39 -> 19035 | ... R3: ='Income Statement'!AF39 -> 45535.884
B4: Reported Revenues | F4: ='Income Statement'!T41 -> 21025 | G4: ='Income Statement'!U41 -> 25098 | H4: ='Income Statement'!V41 -> 16631 | I4: ='Income Statement'!W41 -> 15133 | J4: ='Income Statement'!X41 -> 19523 | K4: ='Income Statement'!Y41 -> 23651 | L4: ='Income Statement'!Z41 -> 27716 | M4: ='Income Statement'!AA41 -> 30995.967 | ... R4: ='Income Statement'!AF41 -> 45535.884
B5: Other Income | C5: ='Income Statement'!Q43 -> 285 | D5: ='Income Statement'!R43 -> 277 | E5: ='Income Statement'!S43 -> 280 | F5: ='Income Statement'!T43 -> 321 | G5: ='Income Statement'!U43 -> 297 | H5: ='Income Statement'!V43 -> 267 | I5: ='Income Statement'!W43 -> 373 | J5: ='Income Statement'!X43 -> 440 | ... R5: ='Income Statement'!AF43 -> 719.61023
B6: Changes in Inventories of finished goods and WIP | C6: ='Income Statement'!Q45 -> 257 | D6: ='Income Statement'!R45 -> 308 | E6: ='Income Statement'!S45 -> 195 | F6: ='Income Statement'!T45 -> 3 | G6: ='Income Statement'!U45 -> 453 | H6: ='Income Statement'!V45 -> -865 | I6: ='Income Statement'!W45 -> -199 | J6: ='Income Statement'!X45 -> 1204 | ... R6: ='Income Statement'!AF45 -> 1624.8733
B7: Capitalised production | C7: ='Income Statement'!Q47 -> 946 | D7: ='Income Statement'!R47 -> 624 | E7: ='Income Statement'!S47 -> 522 | F7: ='Income Statement'!T47 -> 447 | G7: ='Income Statement'!U47 -> 438 | H7: ='Income Statement'!V47 -> 329 | I7: ='Income Statement'!W47 -> 372 | J7: ='Income Statement'!X47 -> 382 | ... R7: ='Income Statement'!AF47 -> 864.18946
B8: Raw materials and Consumables used | C8: ='Income Statement'!Q49 -> -9275 | D8: ='Income Statement'!R49 -> -9340 | E8: ='Income Statement'!S49 -> -9449 | F8: ='Income Statement'!T49 -> -12440 | G8: ='Income Statement'!U49 -> -14448 | H8: ='Income Statement'!V49 -> -8450 | I8: ='Income Statement'!W49 -> -7999 | J8: ='Income Statement'!X49 -> -11724 | ... R8: ='Income Statement'!AF49 -> -26221.414
B9: Personnel Costs | C9: ='Income Statement'!Q51 -> -4524 | D9: ='Income Statement'!R51 -> -4406 | E9: ='Income Statement'!S51 -> -4353 | F9: ='Income Statement'!T51 -> -5665 | G9: ='Income Statement'!U51 -> -6349 | H9: ='Income Statement'!V51 -> -5028 | I9: ='Income Statement'!W51 -> -4919 | J9: ='Income Statement'!X51 -> -5792 | ... R9: ='Income Statement'!AF51 -> -11203.38
B10: Taxes | C10: ='Income Statement'!Q53 -> -277 | D10: ='Income Statement'!R53 -> -286 | E10: ='Income Statement'!S53 -> -284 | F10: ='Income Statement'!T53 -> -295 | G10: ='Income Statement'!U53 -> -388 | H10: ='Income Statement'!V53 -> -326 | I10: ='Income Statement'!W53 -> -257 | J10: ='Income Statement'!X53 -> -290 | ... R10: ='Income Statement'!AF53 -> -553.67271
B11: Depreciation, Amortization and provision | C11: ='Income Statement'!Q55 -> -763 | D11: ='Income Statement'!R55 -> -634 | E11: ='Income Statement'!S55 -> -1012 | F11: ='Income Statement'!T55 -> -1176 | G11: ='Income Statement'!U55 -> -1600 | H11: ='Income Statement'!V55 -> -1212 | I11: ='Income Statement'!W55 -> -1509 | J11: ='Income Statement'!X55 -> -1174 | ... R11: ='Income Statement'!AF55 -> -2592.5684
B12: Asset impairment | C12: ='Income Statement'!Q58 -> -179 | D12: ='Income Statement'!R58 -> -237 | E12: ='Income Statement'!S58 -> -60 | F12: ='Income Statement'!T58 -> 62 | G12: ='Income Statement'!U58 -> 57 | H12: ='Income Statement'!V58 -> -149 | I12: ='Income Statement'!W58 -> 78 | J12: ='Income Statement'!X58 -> -252 | ... R12: ='Income Statement'!AF58 -> 29.573023
B13: Other recurring operating income and expense | C13: ='Income Statement'!Q60 -> 118 | D13: ='Income Statement'!R60 -> 115 | E13: ='Income Statement'!S60 -> 159 | F13: ='Income Statement'!T60 -> -191 | G13: ='Income Statement'!U60 -> 102 | H13: ='Income Statement'!V60 -> 148 | I13: ='Income Statement'!W60 -> 156 | J13: ='Income Statement'!X60 -> 103 | ... R13: ='Income Statement'!AF60 -> 64.074884
B14: Share in profit from joint ventures | C14: ='Income Statement'!Q62 -> 44 | D14: ='Income Statement'!R62 -> 87 | E14: ='Income Statement'!S62 -> 144 | F14: ='Income Statement'!T62 -> 189 | G14: ='Income Statement'!U62 -> 164 | H14: ='Income Statement'!V62 -> 48 | I14: ='Income Statement'!W62 -> 40 | J14: ='Income Statement'!X62 -> 73 | ... R14: ='Income Statement'!AF62 -> 223.44062
B15: EBITA | C15: ='Income Statement'!Q70 -> 0 | D15: ='Income Statement'!R70 -> 2404 | E15: ='Income Statement'!S70 -> 2192 | F15: ='Income Statement'!T64 -> 2280 | G15: ='Income Statement'!U64 -> 3824 | H15: ='Income Statement'!V64 -> 1393 | I15: ='Income Statement'!W64 -> 1269 | J15: ='Income Statement'!X64 -> 2493 | K15: ='Income Statement'!Y64 -> 3309 | L15: ='Income Statement'!Z64 -> 4186 | M15: ='Income Statement'!AA64 -> 5179.0618 | ... R15: ='Income Statement'!AF64 -> 8490.6102
B16: Total Adjustments | F16: =SUM('Income Statement'!T66:T69) -> 743 | G16: =SUM('Income Statement'!U66:U69) -> -4 | H16: =SUM('Income Statement'!V66:V69) -> 293 | I16: =SUM('Income Statement'!W66:W69) -> 536 | J16: =SUM('Income Statement'!X66:X69) -> -85 | K16: =SUM('Income Statement'!Y66:Y69) -> -143 | L16: =SUM('Income Statement'!Z66:Z69) -> -67 | M16: =SUM('Income Statement'!AA66:AA69) -> 0 | ... R16: =SUM('Income Statement'!AF66:AF69) -> 0
B17: Adj. EBITA | F17: ='Income Statement'!T70 -> 3023 | G17: ='Income Statement'!U70 -> 3820 | H17: ='Income Statement'!V70 -> 1686 | I17: ='Income Statement'!W70 -> 1805 | J17: ='Income Statement'!X70 -> 2408 | K17: ='Income Statement'!Y70 -> 3166 | L17: ='Income Statement'!Z70 -> 4119 | M17: ='Income Statement'!AA70 -> 5179.0618 | ... R17: ='Income Statement'!AF70 -> 8490.6102
B18: Other non-recurring operating income and expenses | C18: ='Income Statement'!Q72 -> -778 | D18: ='Income Statement'!R72 -> 349 | E18: ='Income Statement'!S72 -> -90 | F18: ='Income Statement'!T72 -> -115 | G18: ='Income Statement'!U72 -> 13 | H18: ='Income Statement'!V72 -> -466 | I18: ='Income Statement'!W72 -> -405 | J18: ='Income Statement'!X72 -> -450 | ... R18: ='Income Statement'!AF72 -> 0
B19: EBIT | F19: ='Income Statement'!T73 -> 2165 | G19: ='Income Statement'!U73 -> 3837 | H19: ='Income Statement'!V73 -> 927 | I19: ='Income Statement'!W73 -> 864 | J19: ='Income Statement'!X73 -> 2043 | K19: ='Income Statement'!Y73 -> 2798 | L19: ='Income Statement'!Z73 -> 4192 | M19: ='Income Statement'!AA73 -> 5179.0618 | ... R19: ='Income Statement'!AF73 -> 8490.6102
B20: Adj. EBIT | F20: ='Income Statement'!T74 -> 2908 | G20: ='Income Statement'!U74 -> 3833 | H20: ='Income Statement'!V74 -> 1220 | I20: ='Income Statement'!W74 -> 1400 | J20: ='Income Statement'!X74 -> 1958 | K20: ='Income Statement'!Y74 -> 2655 | L20: ='Income Statement'!Z74 -> 4125 | M20: ='Income Statement'!AA74 -> 5179.0618 | ... R20: ='Income Statement'!AF74 -> 8490.6102
B21: Net financing expense | F21: ='Income Statement'!T75 -> -476 | G21: ='Income Statement'!U75 -> -363 | H21: ='Income Statement'!V75 -> -357 | I21: ='Income Statement'!W75 -> -596 | J21: ='Income Statement'!X75 -> -5163 | K21: ='Income Statement'!Y75 -> 1958 | L21: ='Income Statement'!Z75 -> -5051 | M21: ='Income Statement'!AA75 -> 113.985 | ... R21: ='Income Statement'!AF75 -> 242.18511
B22: Adj. net financing expense | C22: ='Income Statement'!Q79 -> 0 | D22: ='Income Statement'!R79 -> -144 | E22: ='Income Statement'!S79 -> 7 | F22: ='Income Statement'!T79 -> -211 | G22: ='Income Statement'!U79 -> -89 | H22: ='Income Statement'!V79 -> -7 | I22: ='Income Statement'!W79 -> -204 | J22: ='Income Statement'!X79 -> -186 | ... R22: ='Income Statement'!AF79 -> 242.18511
B23: PBT | C23: ='Income Statement'!Q85 -> 0 | D23: ='Income Statement'!R85 -> 2609 | E23: ='Income Statement'!S85 -> 2109 | F23: ='Income Statement'!T84 -> 1689 | G23: ='Income Statement'!U84 -> 3474 | H23: ='Income Statement'!V84 -> 570 | I23: ='Income Statement'!W84 -> 268 | J23: ='Income Statement'!X84 -> -3120 | K23: ='Income Statement'!Y84 -> 4756 | L23: ='Income Statement'!Z84 -> -859 | M23: ='Income Statement'!AA84 -> 5293.0468 | ... R23: ='Income Statement'!AF84 -> 8732.7953
B24: Adj. PBT | F24: ='Income Statement'!T85 -> 2697 | G24: ='Income Statement'!U85 -> 3744 | H24: ='Income Statement'!V85 -> 1213 | I24: ='Income Statement'!W85 -> 1196 | J24: ='Income Statement'!X85 -> 1772 | K24: ='Income Statement'!Y85 -> 2829 | L24: ='Income Statement'!Z85 -> 4148 | M24: ='Income Statement'!AA85 -> 5293.0468 | ... R24: ='Income Statement'!AF85 -> 8732.7953
B25: Tax benefit/(expense) | C25: ='Income Statement'!Q88 -> 0 | D25: ='Income Statement'!R88 -> -498 | E25: ='Income Statement'!S88 -> -485 | F25: ='Income Statement'!T86 -> -348 | G25: ='Income Statement'!U86 -> -962 | H25: ='Income Statement'!V86 -> -184 | I25: ='Income Statement'!W86 -> -200 | J25: ='Income Statement'!X86 -> 694 | K25: ='Income Statement'!Y86 -> -1236 | L25: ='Income Statement'!Z86 -> 284 | M25: ='Income Statement'!AA86 -> -1811.2806 | ... R25: ='Income Statement'!AF86 -> -2270.5268
B26: Adj. Tax benefit/(expense) | F26: ='Income Statement'!T88 -> -638 | G26: ='Income Statement'!U88 -> -1012 | H26: ='Income Statement'!V88 -> -334 | I26: ='Income Statement'!W88 -> -412 | J26: ='Income Statement'!X88 -> -557 | K26: ='Income Statement'!Y88 -> -724 | L26: ='Income Statement'!Z88 -> -987 | M26: ='Income Statement'!AA88 -> -1693.775 | ... R26: ='Income Statement'!AF88 -> -2183.1988
B27: Net Income | C27: ='Income Statement'!Q93 -> 0 | D27: ='Income Statement'!R93 -> 2111 | E27: ='Income Statement'!S93 -> 1624 | F27: ='Income Statement'!T92 -> 1341 | G27: ='Income Statement'!U92 -> 2512 | H27: ='Income Statement'!V92 -> 386 | I27: ='Income Statement'!W92 -> 68 | J27: ='Income Statement'!X92 -> -2426 | K27: ='Income Statement'!Y92 -> 3520 | L27: ='Income Statement'!Z92 -> -575 | M27: ='Income Statement'!AA92 -> 3481.7662 | ... R27: ='Income Statement'!AF92 -> 6462.2685
B28: Adj. Net Income | C28: ='Income Statement'!Q94 -> 29 | D28: ='Income Statement'!R94 -> 74 | E28: ='Income Statement'!S94 -> 831 | F28: ='Income Statement'!T93 -> 2059 | G28: ='Income Statement'!U93 -> 2732 | H28: ='Income Statement'!V93 -> 879 | I28: ='Income Statement'!W93 -> 784 | J28: ='Income Statement'!X93 -> 1215 | K28: ='Income Statement'!Y93 -> 2105 | L28: ='Income Statement'!Z93 -> 3161 | M28: ='Income Statement'!AA93 -> 3599.2718 | ... R28: ='Income Statement'!AF93 -> 6549.5965
B29: Non Controlling Interest | C29: ='Income Statement'!Q95 -> 47 | D29: ='Income Statement'!R95 -> 55 | E29: ='Income Statement'!S95 -> 61 | F29: ='Income Statement'!T95 -> 58 | G29: ='Income Statement'!U95 -> 65 | H29: ='Income Statement'!V95 -> 34 | I29: ='Income Statement'!W95 -> 25 | J29: ='Income Statement'!X95 -> 33 | ... R29: ='Income Statement'!AF95 -> 151.15101
B30: Net Income attributable to owners of the parent | F30: ='Income Statement'!T97 -> 1283 | G30: ='Income Statement'!U97 -> 2447 | H30: ='Income Statement'!V97 -> 352 | I30: ='Income Statement'!W97 -> 43 | J30: ='Income Statement'!X97 -> -2459 | K30: ='Income Statement'!Y97 -> 3444 | L30: ='Income Statement'!Z97 -> -667 | M30: ='Income Statement'!AA97 -> 3378.8787 | ... R30: ='Income Statement'!AF97 -> 6311.1175
B31: Adj. Net Income attributable to owners of the parent | F31: ='Income Statement'!T98 -> 2001 | G31: ='Income Statement'!U98 -> 2667 | H31: ='Income Statement'!V98 -> 845 | I31: ='Income Statement'!W98 -> 759 | J31: ='Income Statement'!X98 -> 1182 | K31: ='Income Statement'!Y98 -> 2028 | L31: ='Income Statement'!Z98 -> 3069 | M31: ='Income Statement'!AA98 -> 3496.3843 | ... R31: ='Income Statement'!AF98 -> 6398.4455
B32: Continuing EPS - Basic | C32: ='Income Statement'!Q106 -> -0.18200583 | D32: ='Income Statement'!R106 -> 4.7607024 | E32: ='Income Statement'!S106 -> 3.8099552 | F32: ='Income Statement'!T102 -> 2.9774074 | G32: ='Income Statement'!U102 -> 5.694361 | H32: ='Income Statement'!V102 -> 0.82622178 | I32: ='Income Statement'!W102 -> 0.10078509 | J32: ='Income Statement'!X102 -> -5.7630923 | K32: ='Income Statement'!Y102 -> 8.2432675 | L32: ='Income Statement'!Z102 -> -1.6027893 | M32: ='Income Statement'!AA102 -> 8.2078794 | ... R32: ='Income Statement'!AF102 -> 15.849009
B33: Adj. Continuing EPS - Basic | C33: ='Income Statement'!Q107 -> -0.18200583 | D33: ='Income Statement'!R107 -> 4.6787331 | E33: ='Income Statement'!S107 -> 3.743549 | F33: ='Income Statement'!T106 -> 4.5972284 | G33: ='Income Statement'!U106 -> 6.2016641 | H33: ='Income Statement'!V106 -> 1.9834017 | I33: ='Income Statement'!W106 -> 1.778974 | J33: ='Income Statement'!X106 -> 2.760847 | K33: ='Income Statement'!Y106 -> 4.856443 | L33: ='Income Statement'!Z106 -> 7.374753 | M33: ='Income Statement'!AA106 -> 8.4933209 | ... R33: ='Income Statement'!AF106 -> 16.068315
B35: Average Share Count (thousands) | C35: ='Income Statement'!Q116 -> 417569.03 | D35: ='Income Statement'!R116 -> 416325.12 | E35: ='Income Statement'!S116 -> 410241.04 | F35: ='Income Statement'!T116 -> 430911.81 | G35: ='Income Statement'!U116 -> 429723.37 | H35: ='Income Statement'!V116 -> 426035.73 | I35: ='Income Statement'!W116 -> 426650.42 | J35: ='Income Statement'!X116 -> 426680.66 | ... R35: ='Income Statement'!AF116 -> 398202.65
B36: Average Share count - diluted (thousands) | C36: ='Income Statement'!Q117 -> 417569.03 | D36: ='Income Statement'!R117 -> 423618.95 | E36: ='Income Statement'!S117 -> 417518.25 | F36: ='Income Statement'!T117 -> 436335.63 | G36: ='Income Statement'!U117 -> 434976.73 | H36: ='Income Statement'!V117 -> 440460.49 | I36: ='Income Statement'!W117 -> 440087.03 | J36: ='Income Statement'!X117 -> 440159.93 | ... R36: ='Income Statement'!AF117 -> 402775.48
B37: DPS | C37: ='Income Statement'!Q109 -> 1.38 | D37: ='Income Statement'!R109 -> 1.52 | E37: ='Income Statement'!S109 -> 1.6 | F37: ='Income Statement'!T109 -> 1.82 | G37: ='Income Statement'!U109 -> 0 | H37: ='Income Statement'!V109 -> 0.43 | I37: ='Income Statement'!W109 -> 0.5 | J37: ='Income Statement'!X109 -> 1.35 | ... R37: ='Income Statement'!AF109 -> 6.4273258
B38: Payout ratio (as % of underlying EPS) | C38: ='Income Statement'!Q110 -> -0.55783665 | D38: ='Income Statement'!R110 -> -0.8551543 | E38: ='Income Statement'!S110 -> -0.92972474 | F38: ='Income Statement'!T110 -> 0.39589071 | G38: ='Income Statement'!U110 -> 0 | H38: ='Income Statement'!V110 -> 0.21705612 | I38: ='Income Statement'!W110 -> 0.28069107 | J38: ='Income Statement'!X110 -> 0.48898038 | ... R38: ='Income Statement'!AF110 -> 0.4
B40: Cash Flow Statement (€ mn) | C40: =C2 -> 2015 | D40: =D2 -> 2016E | E40: =E2 -> 2017 | F40: =F2 -> 2018 | G40: =G2 -> 2019 | H40: =H2 -> 2020 | I40: =I2 -> 2021 | J40: =J2 -> 2022 | ... R40: =R2 -> 2030
B41: ='Cashflow Statement'!A4 -> Reported Net Income | C41: ='Cashflow Statement'!Q4 -> -424 | D41: ='Cashflow Statement'!R4 -> 1908 | E41: ='Cashflow Statement'!S4 -> 4550 | F41: ='Cashflow Statement'!T4 -> 1283 | G41: ='Cashflow Statement'!U4 -> 2447 | H41: ='Cashflow Statement'!V4 -> 352 | I41: ='Cashflow Statement'!W4 -> 43 | J41: ='Cashflow Statement'!X4 -> -2459 | ... R41: ='Cashflow Statement'!AF4 -> 6311.1175
