Workbook
Name _div08: #REF!
Name _div09: #REF!
Name _div10: #REF!
Name _ShH3: #REF!
Name A_ALL_AIR.PA: #REF!
Name A_ALL_AIR.PA: #REF!
Name A_ALL_AIR.PA_: #REF!
Name A_ALL_AIR.PA_: #REF!
Name A_ALL_AIR.PA_: #REF!
Name A_ALL_AIR.PA_: #REF!
Name A_ALL_AIR.PA_: #REF!
Name A_ALL_BAES.L_: #REF!
Name A_ALL_BAES.L_: #REF!
Name A_ALL_BAES.L_: #REF!
Name A_ALL_BAES.L_: #REF!
Name A_ALL_BAES.L_: #REF!
Name A_ALL_COB.L: #REF!
Name A_ALL_COB.L: #REF!
Name A_ALL_COB.L: #REF!
Name A_ALL_KEYWORDS_TYPE_ScalarContributed_EQTY_200000267: #REF!,#REF!
Name A_ALL_KEYWORDS_TYPE_ScalarContributed_EQTY_200003162: #REF!,#REF!
Name A_ALL_KEYWORDS_TYPE_ScalarContributed_EQTY_200003162: #REF!,#REF!
Name A_ALL_KEYWORDS_TYPE_ScalarContributed_EQTY_200003162: #REF!,#REF!
Name A_ALL_KEYWORDS_TYPE_ScalarContributed_EQTY_200003170: #REF!,#REF!
Name A_ALL_KEYWORDS_TYPE_ScalarContributed_EQTY_200003170: #REF!,#REF!
Name A_ALL_KEYWORDS_TYPE_ScalarContributed_EQTY_200003170: #REF!,#REF!
Name A_ALL_KEYWORDS_TYPE_ScalarContributed_EQTY_200003173: #REF!,#REF!
Name A_ALL_KEYWORDS_TYPE_ScalarContributed_EQTY_200003173: #REF!,#REF!
Name A_ALL_KEYWORDS_TYPE_ScalarContributed_EQTY_200003173: #REF!,#REF!
Name A_ALL_KEYWORDS_TYPE_ScalarContributed_EQTY_200003183: #REF!,#REF!
Name A_ALL_KEYWORDS_TYPE_ScalarContributed_EQTY_200003183: #REF!,#REF!
Name A_ALL_KEYWORDS_TYPE_ScalarContributed_EQTY_200003183: #REF!,#REF!
Name A_ALL_KEYWORDS_TYPE_ScalarContributed_EQTY_200003821: #REF!,#REF!
Name A_ALL_KEYWORDS_TYPE_ScalarContributed_EQTY_200003821: #REF!,#REF!
Name A_ALL_KEYWORDS_TYPE_ScalarContributed_EQTY_200003821: #REF!,#REF!
Name A_ALL_KEYWORDS_TYPE_ScalarContributed_EQTY_200004285: #REF!,#REF!
Name A_ALL_KEYWORDS_TYPE_ScalarContributed_EQTY_200004285: #REF!,#REF!
Name A_ALL_KEYWORDS_TYPE_ScalarContributed_EQTY_200005121: #REF!,#REF!
Name A_ALL_KEYWORDS_TYPE_ScalarContributed_EQTY_200005121: #REF!,#REF!
Name A_ALL_KEYWORDS_TYPE_ScalarContributed_EQTY_200005121: #REF!,#REF!
Name A_ALL_KEYWORDS_TYPE_ScalarContributed_EQTY_200007513: #REF!,#REF!
Name A_ALL_KEYWORDS_TYPE_ScalarContributed_EQTY_200007513: #REF!,#REF!
Name A_ALL_KEYWORDS_TYPE_ScalarContributed_EQTY_200007513: #REF!,#REF!
Name A_ALL_KEYWORDS_TYPE_ScalarContributed_EQTY_200008448: #REF!,#REF!,#REF!
Name A_ALL_KEYWORDS_TYPE_ScalarContributed_EQTY_200008448: #REF!,#REF!,#REF!
Name A_ALL_KEYWORDS_TYPE_ScalarContributed_EQTY_200009618: #REF!,#REF!
Name A_ALL_KEYWORDS_TYPE_ScalarContributed_EQTY_200009618: #REF!,#REF!
Name A_ALL_KEYWORDS_TYPE_ScalarContributed_EQTY_200009618: #REF!,#REF!
Name A_ALL_KEYWORDS_TYPE_ScalarContributed_EQTY_200009619: #REF!,#REF!
Name A_ALL_KEYWORDS_TYPE_ScalarContributed_EQTY_200009619: #REF!,#REF!
Name A_ALL_KEYWORDS_TYPE_ScalarContributed_EQTY_200009619: #REF!,#REF!
Name A_ALL_KEYWORDS_TYPE_ScalarContributed_EQTY_200009620: #REF!,#REF!
Name A_ALL_KEYWORDS_TYPE_ScalarContributed_EQTY_200009620: #REF!,#REF!
Name A_ALL_KEYWORDS_TYPE_ScalarContributed_EQTY_200009620: #REF!,#REF!
Name A_ALL_KEYWORDS_TYPE_ScalarContributed_EQTY_200011295: #REF!,#REF!
Name A_ALL_KEYWORDS_TYPE_ScalarContributed_EQTY_200011295: #REF!,#REF!
Name A_ALL_KEYWORDS_TYPE_ScalarContributed_ISSR_208000023: #REF!,#REF!,#REF!,#REF!,#REF!,#REF!,#REF!,#REF!,#REF!,#REF!
Name A_ALL_KEYWORDS_TYPE_ScalarContributed_ISSR_208001092: #REF!,#REF!
Name A_ALL_KEYWORDS_TYPE_ScalarContributed_ISSR_208001092: #REF!,#REF!
Name A_ALL_KEYWORDS_TYPE_ScalarContributed_ISSR_208001095: #REF!,#REF!

Sheet _QP_SAF.PA
A1: 1311101 | F1: 1998 | G1: 1999 | H1: 2000 | I1: 2001 | J1: 2002 | K1: 2003 | L1: 2004 | M1: 2005 | N1: 2006 H1 | O1: 2006 H2 | P1: 2006 | Q1: 2007 H1 | R1: 2007 H2 | S1: 2007 | T1: 2008 H1 | U1: 2008 H2 | V1: 2008 | W1: 2009 H1 | X1: 2009 H2 | Y1: 2009 | Z1: 2010 H1 | AA1: 2010 H2 | AB1: 2010 | AC1: 2011 H1 | AD1: 2011 H2 | AE1: 2011 | AF1: 2012 | AG1: 2013 | AH1: 2014 | AI1: 2015 | AJ1: 2016
A2: AUTO-GENERATED BY TIGR NUMBERS SUBMISSION. DO NOT MODIFY OR DELETE!
B4: ACC_END_DATE | D4: EUR | F4: 36160 | G4: 36525 | H4: 36891 | I4: 37256 | J4: 37621 | K4: 37986 | L4: 38352 | M4: 38717 | N4: 38898 | O4: 39082 | P4: 39082 | Q4: 39263 | R4: 39447 | S4: 39447 | T4: 39629 | U4: 39813 | V4: 39813 | W4: 39994 | X4: 40178 | Y4: 40178 | Z4: 40359 | AA4: 40543 | AB4: 40543 | AC4: 40724 | AD4: 40908 | AE4: 40908 | AF4: 41274 | AG4: 41639 | AH4: 42004 | AI4: 42369 | AJ4: 42735
B5: EURO_LIST | D5: EUR
B6: EURO_CONVICTION | D6: EUR
B7: LEGAL_RATING | D7: EUR | E7: Coverage Suspended
B8: TARGET_PRICE | D8: EUR
B9: TP_PERIOD | D9: EUR
B10: NUM_SH1 | D10: EUR | E10: 404.73546
B11: FREE_FLOAT | D11: EUR | E11: 0.466
B12: BVPS_PUB | D12: EUR | M12: 10.963251 | P12: 10.404538 | S12: 10.40214 | V12: 9.3517537 | Y12: 10.900213 | AB12: 10.862539 | AE12: 11.912824
B13: DPS_PUB | D13: EUR | M13: 0.35968671 | P13: 0.22060785 | S13: 0.40045121 | V13: 0.25 | Y13: 0.38 | AB13: 0.5 | AE13: 0.62
B14: EBITDA_PUB | D14: EUR | M14: 1019 | P14: 884 | S14: 1069 | V14: 1182 | Y14: 1107 | AB14: 1313.5 | AE14: 1681
B15: EPS_PUB | D15: EUR | M15: 1.2240036 | P15: 0.4320298 | S15: 0.98837802 | V15: 0.63154612 | Y15: 0.94172621 | AB15: 1.2714211 | AE15: 1.5911628
B16: EV_ADJ_PUB | D16: EUR | F16: 0 | G16: 0 | H16: 0 | I16: 0 | J16: 0 | K16: 0 | M16: 486.3324 | N16: 0 | O16: 0 | P16: 838.35458 | Q16: 0 | S16: 1109.3546 | V16: 1064.3546 | Y16: 1044.3546 | AB16: 1100.3546 | AE16: 1144.3546
B17: NET_DEBT_PUB | D17: EUR | M17: 473 | P17: 419 | S17: 169 | V17: 635 | W17: -690 | X17: 498 | Y17: 498 | AB17: -24 | AE17: 997
B18: NI_PUB | D18: EUR | M18: 501 | P18: 177 | S18: 406 | V18: 256 | W18: 207 | X18: 169 | Y18: 376 | Z18: 261 | AA18: 247 | AB18: 508 | AC18: 317.05748 | AD18: 321.616 | AE18: 644
B19: EBIT_PUB | D19: EUR | M19: 762 | P19: 465 | S19: 706 | V19: 798 | W19: 347 | X19: 351 | Y19: 698 | Z19: 428 | AA19: 450 | AB19: 878 | AC19: 554.05748 | AD19: 632.616 | AE19: 1189
B20: PTP_PUB | D20: EUR | M20: 678 | P20: 391 | S20: 645 | V20: 605 | W20: 265 | X20: 227 | Y20: 492 | Z20: 337 | AA20: 369 | AB20: 706 | AC20: 442.05748 | AD20: 510.616 | AE20: 955
B21: REVS_PUB | D21: EUR | M21: 10577 | P21: 11329 | S21: 12003 | V21: 10329 | W21: 5149 | X21: 5299 | Y21: 10448 | Z21: 5197 | AA21: 5563 | AB21: 10760 | AC21: 5622 | AD21: 6114 | AE21: 11736
B22: EQ_PUB | D22: EUR | M22: 4736 | P22: 4512 | S22: 4505 | V22: 3874 | Y22: 4501 | AB22: 4705 | AE22: 5122
B23: SALES | D23: EUR | M23: 10577 | P23: 11329 | S23: 12003 | V23: 10329 | Y23: 10448 | AB23: 10760 | AE23: 11736
B24: COST_GD_SD | D24: EUR
B25: SEL_GL_AD | D25: EUR | F25: 0 | G25: 0 | H25: 0 | I25: 0 | J25: 0 | K25: 0 | L25: 0 | M25: 0 | N25: 0 | O25: 0 | P25: 0 | Q25: 0 | S25: 0
B26: OP_COST | D26: EUR | F26: 0 | G26: 0 | H26: 0 | I26: 0 | J26: 0 | K26: 0 | M26: -9558 | N26: 0 | O26: 0 | P26: -10445 | Q26: 0 | S26: -10934 | V26: -8708 | Y26: -8847 | AB26: -9040.5 | AE26: -9560
B27: RD_EXP | D27: EUR
B28: OTH_OP_INC_EXP | D28: EUR | F28: 0 | G28: 0 | H28: 0 | I28: 0 | J28: 0 | K28: 0 | N28: 0 | O28: 0 | Q28: 0 | V28: -439 | Y28: -494 | AB28: -406 | AE28: -495
B29: TOT_OPS_EXP_DDA | D29: EUR | M29: -9815 | P29: -10864 | S29: -11297 | V29: -9531 | Y29: -9750 | AB29: -9882 | AE29: -10547
B30: TOT_OPS_EXP | D30: EUR | M30: -9558 | P30: -10445 | S30: -10934 | V30: -9147 | Y30: -9341 | AB30: -9446.5 | AE30: -10055
B31: EBITDA_CALC | D31: EUR | M31: 1019 | P31: 884 | S31: 1069 | V31: 1182 | Y31: 1107 | AB31: 1313.5 | AE31: 1681
B32: DEPREC | D32: EUR | F32: 0 | G32: 0 | H32: 0 | I32: 0 | J32: 0 | K32: 0 | M32: -257 | N32: 0 | O32: 0 | P32: -306 | Q32: 0 | S32: -287 | V32: -278 | Y32: -279 | AB32: -291 | AE32: -321
B33: GOODWILL_AMORT | D33: EUR | F33: 0 | G33: 0 | H33: 0 | I33: 0 | J33: 0 | K33: 0 | N33: 0 | O33: 0 | P33: -113 | Q33: 0 | S33: -76 | V33: -106 | Y33: -130 | AB33: -144.5 | AE33: -171
B34: EBIT | D34: EUR | M34: 762 | P34: 465 | S34: 706 | V34: 798 | Y34: 698 | AB34: 878 | AE34: 1189
B35: INT_INC_IND | D35: EUR
B36: INT_EXP_IND | D36: EUR
B37: NET_INT_EXP | D37: EUR | M37: -87 | P37: -78 | S37: -65 | V37: -203 | Y37: -174 | AB37: -168 | AE37: -215
B38: ASSOCIATE | D38: EUR | F38: 0 | G38: 0 | H38: 0 | I38: 0 | J38: 0 | K38: 0 | L38: 0 | M38: 3 | N38: 0 | O38: 0 | P38: 4 | Q38: 0 | S38: 4 | V38: 10 | Y38: 3 | AB38: 9 | AE38: 10
B39: PROFIT_ON_DISP | D39: EUR | F39: 0 | G39: 0 | H39: 0 | I39: 0 | J39: 0 | K39: 0 | L39: 0 | M39: 0 | N39: 0 | O39: 0 | P39: 0 | Q39: 0 | S39: 0
B40: OTH_COST_INC | D40: EUR | F40: 0 | G40: 0 | H40: 0 | I40: 0 | J40: 0 | K40: 0 | L40: 0 | M40: 0 | N40: 0 | O40: 0 | P40: 0 | Q40: 0 | S40: 0 | AB40: -13 | AE40: -29
B41: PT_PROF | D41: EUR | M41: 678 | P41: 391 | S41: 645 | V41: 605 | Y41: 527 | AB41: 706 | AE41: 955
B42: PROV_INC_TAX | D42: EUR | M42: -170 | P42: -199 | S42: -224 | V42: -101 | Y42: -98 | AB42: -173 | AE42: -289
B43: INC_MINORITY | D43: EUR | F43: 0 | G43: 0 | H43: 0 | I43: 0 | J43: 0 | K43: 0 | M43: -7 | N43: 0 | O43: 0 | P43: -15 | Q43: 0 | S43: -15 | V43: -15 | Y43: -14 | AB43: -20 | AE43: -25
B44: NI_PRE_PREF | D44: EUR | M44: 501 | P44: 177 | S44: 406 | V44: 489 | Y44: 415 | AB44: 513 | AE44: 641
B45: PREF_DIV | D45: EUR | F45: 0 | G45: 0 | H45: 0 | I45: 0 | J45: 0 | K45: 0 | L45: 0 | M45: 0 | N45: 0 | O45: 0 | P45: 0 | Q45: 0 | S45: 0
B46: NET_EARNING | D46: EUR | M46: 501 | P46: 177 | S46: 406 | V46: 489 | Y46: 415 | AB46: 513 | AE46: 641
B47: TAX_EXC | D47: EUR | F47: 0 | G47: 0 | H47: 0 | I47: 0 | J47: 0 | K47: 0 | N47: 0 | O47: 0 | Q47: 0 | V47: -233
B48: NET_INC | D48: EUR | M48: 501 | P48: 177 | S48: 406 | V48: 256 | Y48: 415 | AB48: 513 | AE48: 641
B49: EPS | D49: EUR | M49: 1.2240036 | P49: 0.4320298 | S49: 0.98837802 | V49: 1.2063518 | Y49: 1.0394053 | AB49: 1.2839351 | AE49: 1.5837505
B50: EPS_FUL_DIL | D50: EUR | M50: 1.2207229 | P50: 0.43086725 | S50: 0.98780596 | V50: 1.2063518 | Y50: 1.0347028 | AB50: 1.2712729 | AE50: 1.5774982
B51: EPS_POST_BASIC | D51: EUR | M51: 1.2240036 | P51: 0.4320298 | S51: 0.98837802 | V51: 0.63154612 | Y51: 1.0394053 | AB51: 1.2839351 | AE51: 1.5837505
B52: FULLY_DIL_EPS | D52: EUR | M52: 1.2207229 | P52: 0.43086725 | S52: 0.98780596 | V52: 0.63154612 | Y52: 1.0347028 | AB52: 1.2712729 | AE52: 1.5774982
B53: COMMON_DIV_PAID | D53: EUR | M53: -150 | P53: -92 | S53: -167 | V53: -104 | Y53: -158 | AB53: -202 | AE53: -260
B54: DPS | D54: EUR | F54: 0 | G54: 0 | H54: 0 | I54: 0 | J54: 0 | K54: 0 | M54: 0.35968671 | N54: 0 | O54: 0 | P54: 0.22060785 | Q54: 0 | S54: 0.40045121 | V54: 0.25 | Y54: 0.38 | AB54: 0.5 | AE54: 0.62
B55: SH1 | D55: EUR | M55: 409.31254 | P55: 409.69396 | S55: 410.77401 | V55: 405.3544 | Y55: 399.26679 | AB55: 399.55292 | AE55: 404.73546
B56: DILUTE_SHARES | D56: EUR | M56: 410.41254 | P56: 410.79938 | S56: 411.0119 | V56: 405.3544 | Y56: 401.08134 | AB56: 403.53256 | AE56: 406.33962
B57: NON_OP_ADD | D57: EUR | M57: 417.02958 | P57: 417.02958 | S57: 417.02958 | V57: 399.17647 | Y57: 399.35 | AB57: 417.02958 | AE57: 417.02958
B58: ORG_NI | D58: EUR
B59: ORG_EPS | D59: EUR
B60: ORG_REV | D60: EUR
B61: ORG_REV_GRTH | D61: EUR
B62: LEASE_PAY | D62: EUR | F62: 0 | G62: 0 | H62: 0 | I62: 0 | J62: 0 | K62: 0 | L62: 0 | M62: 0 | N62: 0 | O62: 0 | P62: 0 | Q62: 0 | S62: 0
B63: LEASE_DEEM_INT | D63: EUR | F63: 0.333333 | G63: 0.333333 | H63: 0.333333 | I63: 0.333333 | J63: 0.333333 | K63: 0.333333 | L63: 0.333333 | M63: 0.333333 | N63: 0.333333 | O63: 0.333333 | P63: 0.333333 | Q63: 0.333333 | S63: 0.333333
B64: LEASE_DEEM_DEPR | D64: EUR | F64: 0.666667 | G64: 0.666667 | H64: 0.666667 | I64: 0.666667 | J64: 0.666667 | K64: 0.666667 | L64: 0.666667 | M64: 0.666667 | N64: 0.666667 | O64: 0.666667 | P64: 0.666667 | Q64: 0.666667 | S64: 0.666667
B65: NET_INT_CH | D65: EUR | F65: 0 | G65: 0 | H65: 0 | I65: 0 | J65: 0 | K65: 0 | N65: 0 | O65: 0 | Q65: 0
B66: ASSOCIATE_OP | D66: EUR | F66: 0 | G66: 0 | H66: 0 | I66: 0 | J66: 0 | K66: 0 | L66: 0 | M66: 0 | N66: 0 | O66: 0 | P66: 0 | Q66: 0 | S66: 0
B67: GW_AMORT | D67: EUR
B68: OTH_INT_AMORT | D68: EUR | F68: 0 | G68: 0 | H68: 0 | I68: 0 | J68: 0 | K68: 0 | L68: 0 | M68: 0 | N68: 0 | O68: 0 | P68: 0 | Q68: 0 | S68: 0
B69: MARGIN_TAX_RATE | D69: EUR | F69: 0 | G69: 0 | H69: 0 | I69: 0 | J69: 0 | K69: 0 | M69: 0.25073746 | N69: 0 | O69: 0 | P69: 0.50895141 | Q69: 0 | S69: 0.34728682 | V69: 0.16694215 | Y69: 0.19918699 | AB69: 0.24504249 | AE69: 0.3026178
B70: CASH_EQ | D70: EUR | F70: 0 | G70: 0 | H70: 0 | I70: 0 | J70: 0 | K70: 0 | M70: 936 | N70: 0 | O70: 0 | P70: 743 | Q70: 0 | S70: 730 | V70: 919 | Y70: 2080 | AB70: 2062 | AE70: 1431
B71: DEBTORS | D71: EUR | M71: 4052 | P71: 4218 | S71: 3926 | V71: 3881 | Y71: 3994 | AB71: 3921 | AE71: 5005
B72: STOCKS | D72: EUR | F72: 0 | G72: 0 | H72: 0 | I72: 0 | J72: 0 | K72: 0 | M72: 2904 | N72: 0 | O72: 0 | P72: 3240 | Q72: 0 | S72: 3420 | V72: 3673 | Y72: 3382 | AB72: 3508 | AE72: 3799
B73: OTH_CUR_ASS | D73: EUR | F73: 0 | G73: 0 | H73: 0 | I73: 0 | J73: 0 | K73: 0 | M73: 213 | N73: 0 | O73: 0 | P73: 219 | Q73: 0 | S73: 210 | V73: 330 | Y73: 309 | AB73: 444 | AE73: 494
B74: CUR_ASS | D74: EUR | F74: 0 | G74: 0 | H74: 0 | I74: 0 | J74: 0 | K74: 0 | M74: 8105 | N74: 0 | O74: 0 | P74: 8420 | Q74: 0 | S74: 8286 | V74: 8803 | Y74: 9765 | AB74: 9935 | AE74: 10729
B75: GR_FIX_ASS | D75: EUR | M75: 4772 | P75: 4871 | S75: 4881 | V75: 5238 | Y75: 5436 | AB75: 5750 | AE75: 6434
B76: ACC_DDA | D76: EUR | M76: -2974 | P76: -3045 | S76: -3034 | V76: -3131 | Y76: -3235 | AB76: -3497 | AE76: -3948
B77: NET_FIX_ASS | D77: EUR | F77: 0 | G77: 0 | H77: 0 | I77: 0 | J77: 0 | K77: 0 | M77: 1798 | N77: 0 | O77: 0 | P77: 1826 | Q77: 0 | S77: 1847 | V77: 2107 | Y77: 2201 | AB77: 2253 | AE77: 2486
B78: GR_INTANG | D78: EUR | F78: 0 | G78: 0 | H78: 0 | I78: 0 | J78: 0 | K78: 0 | M78: 4977 | N78: 0 | O78: 0 | P78: 5404 | Q78: 0 | S78: 5591 | V78: 6187 | Y78: 7048 | AB78: 7339 | AE78: 8923
B79: ACC_AMORT | D79: EUR | F79: 0 | G79: 0 | H79: 0 | I79: 0 | J79: 0 | K79: 0 | M79: -438 | P79: -759 | S79: -1049 | V79: -1319 | Y79: -1705 | AB79: -1911 | AE79: -2299
B80: NET_INTANG | D80: EUR | F80: 0 | G80: 0 | H80: 0 | I80: 0 | J80: 0 | K80: 0 | M80: 4539 | N80: 0 | O80: 0 | P80: 4645 | Q80: 0 | S80: 4542 | V80: 4868 | Y80: 5343 | AB80: 5428 | AE80: 6624
B81: FIX_ASS_INV | D81: EUR | F81: 0 | G81: 0 | H81: 0 | I81: 0 | J81: 0 | K81: 0 | L81: 0 | M81: 37 | N81: 0 | O81: 0 | P81: 32 | Q81: 0 | S81: 34 | V81: 244 | Y81: 238 | AB81: 236 | AE81: 253
B82: INV_SECUR | D82: EUR | F82: 0 | G82: 0 | H82: 0 | I82: 0 | J82: 0 | K82: 0 | N82: 0 | O82: 0 | Q82: 0
B83: OTH_LT_ASS | D83: EUR | F83: 0 | G83: 0 | H83: 0 | I83: 0 | J83: 0 | K83: 0 | M83: 1064 | N83: 0 | O83: 0 | P83: 1005 | Q83: 0 | S83: 1466 | V83: 814 | Y83: 622 | AB83: 659 | AE83: 610
B84: TOT_ASSET | D84: EUR | M84: 15543 | N84: 0 | O84: 0 | P84: 15928 | Q84: 0 | S84: 16175 | V84: 16836 | Y84: 18169 | AB84: 18511 | AE84: 20702
B85: ACC_PAY_GQ | D85: EUR | F85: 0 | G85: 0 | H85: 0 | I85: 0 | J85: 0 | K85: 0 | M85: 5898 | N85: 0 | O85: 0 | P85: 6390 | Q85: 0 | S85: 6517 | V85: 6786 | Y85: 6805 | AB85: 7236 | AE85: 8348
B86: SHORT_T_DEBT | D86: EUR | F86: 0 | G86: 0 | H86: 0 | I86: 0 | J86: 0 | K86: 0 | M86: 877 | N86: 0 | O86: 0 | P86: 699 | Q86: 0 | S86: 502 | V86: 1136 | Y86: 1367 | AB86: 568 | AE86: 998
B87: OTH_CUR_LIABS | D87: EUR | F87: 0 | G87: 0 | H87: 0 | I87: 0 | J87: 0 | K87: 0 | M87: 1156 | N87: 0 | O87: 0 | P87: 1274 | Q87: 0 | S87: 1771 | V87: 2089 | Y87: 1234 | AB87: 1637 | AE87: 1814
B88: SHORT_TERM_LIABS | D88: EUR | M88: 7931 | P88: 8363 | S88: 8790 | V88: 10011 | Y88: 9406 | AB88: 9441 | AE88: 11160
B89: LT_DEBT | D89: EUR | F89: 0 | G89: 0 | H89: 0 | I89: 0 | J89: 0 | K89: 0 | M89: 532 | N89: 0 | O89: 0 | P89: 463 | Q89: 0 | S89: 397 | V89: 418 | Y89: 1208 | AB89: 1483 | AE89: 1447
B90: OTH_LT_CRED_GQ | D90: EUR | F90: 0 | G90: 0 | H90: 0 | I90: 0 | J90: 0 | K90: 0 | M90: 2344 | N90: 0 | O90: 0 | P90: 2590 | Q90: 0 | S90: 2483 | V90: 2533 | Y90: 3054 | AB90: 2882 | AE90: 2973
B91: TOT_LT_LIAB | D91: EUR | M91: 2876 | P91: 3053 | S91: 2880 | V91: 2951 | Y91: 4262 | AB91: 4365 | AE91: 4420
B92: TOT_LIAB | D92: EUR | F92: 0 | G92: 0 | H92: 0 | I92: 0 | J92: 0 | K92: 0 | M92: 10807 | N92: 0 | O92: 0 | P92: 11416 | Q92: 0 | S92: 11670 | V92: 12962 | Y92: 13668 | AB92: 13806 | AE92: 15580
B93: PREF_SH | D93: EUR | F93: 0 | G93: 0 | H93: 0 | I93: 0 | J93: 0 | K93: 0 | L93: 0 | M93: 0 | N93: 0 | O93: 0 | P93: 0 | Q93: 0 | S93: 0
B94: ORD_SH_FUND | D94: EUR | F94: 0 | G94: 0 | H94: 0 | I94: 0 | J94: 0 | K94: 0 | M94: 4572 | N94: 0 | O94: 0 | P94: 4339 | Q94: 0 | S94: 4338 | V94: 3733 | Y94: 4353 | AB94: 4530 | AE94: 4968
B95: MINORITIES | D95: EUR | F95: 0 | G95: 0 | H95: 0 | I95: 0 | J95: 0 | K95: 0 | M95: 164 | N95: 0 | O95: 0 | P95: 173 | Q95: 0 | S95: 167 | V95: 141 | Y95: 148 | AB95: 175 | AE95: 154
B96: EQ | D96: EUR | M96: 4736 | P96: 4512 | S96: 4505 | V96: 3874 | Y96: 4501 | AB96: 4705 | AE96: 5122
B97: TOT_LIAB_EQ | D97: EUR | M97: 15543 | P97: 15928 | S97: 16175 | V97: 16836 | Y97: 18169 | AB97: 18511 | AE97: 20702
B98: BVPS | D98: EUR | M98: 10.963251 | P98: 10.404538 | S98: 10.40214 | V98: 9.3517537 | Y98: 10.900213 | AB98: 10.862539 | AE98: 11.912824
B99: NET_DEBT | D99: EUR | F99: 0 | G99: 0 | H99: 0 | I99: 0 | J99: 0 | K99: 0 | M99: 473 | N99: 0 | O99: 0 | P99: 419 | Q99: 0 | S99: 169 | V99: 635 | Y99: 498 | AB99: -24 | AE99: 997
B100: CAP_LEASES | D100: EUR | F100: 0 | G100: 0 | H100: 0 | I100: 0 | J100: 0 | K100: 0 | L100: 0 | M100: 0 | N100: 0 | O100: 0 | P100: 0 | Q100: 0 | S100: 0
B101: DEF_INC_TAX | D101: EUR | F101: 0 | G101: 0 | H101: 0 | I101: 0 | J101: 0 | K101: 0 | L101: 0 | M101: 0 | N101: 0 | O101: 0 | P101: 0 | Q101: 0 | S101: 0
...

Sheet Cover Page
A2: GOLDMAN SACHS
A3: GLOBAL INVESTMENT RESEARCH
A4: Multi-Industry
B6: SAF.PA
B7: Published as of | C7: 45968 | I7: Rating Suspended
B9: Team Contacts:
B10: Primary Analysts
B11: Sam Burgess, sam.burgess@gs.com, +44 20 7774-9651 Goldman Sachs International
B12: Supporting Analyst
B13: Jubril Moronfolu, jubril.x.moronfolu@gs.com, +44 20 7051-0985 Goldman Sachs International
B14: Milind Sikchi, milind.sikchi@gs.com, +1 332 245-7985, Goldman Sachs International

Sheet DCF Valuation
B4: Calendar year | C4: 2026 | D4: 2027 | E4: 2028 | F4: 2029 | G4: 2030 | H4: 2031 | I4: 2032 | J4: 2033 | K4: 2034 | L4: 2035
B5: Adj. EBIT | C5: ='DCF Feed'!C4 -> 6143.3638 | D5: ='DCF Feed'!D4 -> 6980.0222 | E5: ='DCF Feed'!E4 -> 7702.6228 | F5: ='DCF Feed'!F4 -> 8235.9281 | G5: ='DCF Feed'!G4 -> 8787.0465
B6: Tax Rate | C6: =-'DCF Feed'!C10 -> 0.25 | D6: =-'DCF Feed'!D10 -> 0.25 | E6: =-'DCF Feed'!E10 -> 0.25 | F6: =-'DCF Feed'!F10 -> 0.25 | G6: =-'DCF Feed'!G10 -> 0.25
B7: NOPAT | C7: =C5*(1-C6) -> 4607.5228 | D7: =D5*(1-D6) -> 5235.0166 | E7: =E5*(1-E6) -> 5776.9671 | F7: =F5*(1-F6) -> 6176.946 | G7: =G5*(1-G6) -> 6590.2848
B8: D&A | C8: =INDEX('Income Statement'!192:192, MATCH('DCF Valuation'!C4,'Income Statement'!3:3,0)) -> 1878.871 | D8: =INDEX('Income Statement'!192:192, MATCH('DCF Valuation'!D4,'Income Statement'!3:3,0)) -> 1989.0011 | E8: =INDEX('Income Statement'!192:192, MATCH('DCF Valuation'!E4,'Income Statement'!3:3,0)) -> 2143.6064 | F8: =INDEX('Income Statement'!192:192, MATCH('DCF Valuation'!F4,'Income Statement'!3:3,0)) -> 2262.166 | G8: =INDEX('Income Statement'!192:192, MATCH('DCF Valuation'!G4,'Income Statement'!3:3,0)) -> 2371.9984
B9: Change in working capital | C9: =INDEX('Cashflow Statement'!22:22, MATCH('DCF Valuation'!C4,'Cashflow Statement'!2:2,0)) -> 254.32099 | D9: =INDEX('Cashflow Statement'!22:22, MATCH('DCF Valuation'!D4,'Cashflow Statement'!2:2,0)) -> -104.50791 | E9: =INDEX('Cashflow Statement'!22:22, MATCH('DCF Valuation'!E4,'Cashflow Statement'!2:2,0)) -> -454.17326 | F9: =INDEX('Cashflow Statement'!22:22, MATCH('DCF Valuation'!F4,'Cashflow Statement'!2:2,0)) -> -643.49968 | G9: =INDEX('Cashflow Statement'!22:22, MATCH('DCF Valuation'!G4,'Cashflow Statement'!2:2,0)) -> -903.4025
B10: Capex & Intangibles | C10: =(INDEX('Cashflow Statement'!69:69, MATCH('DCF Valuation'!C4,'Cashflow Statement'!2:2,0)))+INDEX('Cashflow Statement'!70:70, MATCH('DCF Valuation'!C4,'Cashflow Statement'!2:2,0)) -> -2154.4179 | D10: =(INDEX('Cashflow Statement'!69:69, MATCH('DCF Valuation'!D4,'Cashflow Statement'!2:2,0)))+INDEX('Cashflow Statement'!70:70, MATCH('DCF Valuation'!D4,'Cashflow Statement'!2:2,0)) -> -2119.3017 | E10: =(INDEX('Cashflow Statement'!69:69, MATCH('DCF Valuation'!E4,'Cashflow Statement'!2:2,0)))+INDEX('Cashflow Statement'!70:70, MATCH('DCF Valuation'!E4,'Cashflow Statement'!2:2,0)) -> -2029.8732 | F10: =(INDEX('Cashflow Statement'!69:69, MATCH('DCF Valuation'!F4,'Cashflow Statement'!2:2,0)))+INDEX('Cashflow Statement'!70:70, MATCH('DCF Valuation'!F4,'Cashflow Statement'!2:2,0)) -> -1888.6195 | G10: =(INDEX('Cashflow Statement'!69:69, MATCH('DCF Valuation'!G4,'Cashflow Statement'!2:2,0)))+INDEX('Cashflow Statement'!70:70, MATCH('DCF Valuation'!G4,'Cashflow Statement'!2:2,0)) -> -1719.6767
B11: Sustainable FCF | C11: =C7+C8+C9+C10 -> 4586.2969 | D11: =D7+D8+D9+D10 -> 5000.2081 | E11: =E7+E8+E9+E10 -> 5436.527 | F11: =F7+F8+F9+F10 -> 5906.9928 | G11: =G7+G8+G9+G10 -> 6339.204 | H11: =G11*(1+H12) -> 6763.4006 | I11: =H11*(1+I12) -> 7153.5627 | J11: =I11*(1+J12) -> 7500.2114 | K11: =J11*(1+K12) -> 7794.4379 | L11: =K11*(1+L12) -> 8028.271
B12: Annual growth | D12: ='DCF Feed'!D5 -> 0.13618897 | E12: ='DCF Feed'!E5 -> 0.10352412 | F12: ='DCF Feed'!F5 -> 0.069236834 | G12: ='DCF Feed'!G5 -> 0.066916368 | H12: =G12 -> 0.066916368 | I12: =H12+(($L$12-$H$12)/4) -> 0.057687276 | J12: =I12+(($L$12-$H$12)/4) -> 0.048458184 | K12: =J12+(($L$12-$H$12)/4) -> 0.039229092 | L12: =$D$33 -> 0.03
B13: WACC | D13: =$D$32 -> 0.0746 | E13: =$D$32 -> 0.0746 | F13: =$D$32 -> 0.0746 | G13: =$D$32 -> 0.0746 | H13: =$D$32 -> 0.0746 | I13: =$D$32 -> 0.0746 | J13: =$D$32 -> 0.0746 | K13: =$D$32 -> 0.0746 | L13: =$D$32 -> 0.0746
B14: Discount Factor | D14: 1 | E14: =D14+1 -> 2 | F14: =E14+1 -> 3 | G14: =F14+1 -> 4 | H14: =G14+1 -> 5 | I14: =H14+1 -> 6 | J14: =I14+1 -> 7 | K14: =J14+1 -> 8 | L14: =K14+1 -> 9
B15: Discounted FCF | D15: =D11/((1+D13)^D14) -> 4653.0878 | E15: =E11/((1+E13)^E14) -> 4707.907 | F15: =F11/((1+F13)^F14) -> 4760.2081 | G15: =G11/((1+G13)^G14) -> 4753.8709 | H15: =H11/((1+H13)^H14) -> 4719.8797 | I15: =I11/((1+I13)^I14) -> 4645.5953 | J15: =J11/((1+J13)^J14) -> 4532.5818 | K15: =K11/((1+K13)^K14) -> 4383.39 | L15: =L11/((1+L13)^L14) -> 4201.4626 | M15: =SUM(C15:L15) -> 41357.983
B18: DCF Valuation
B19: Risk free rate | C19: % | D19: 0.035
B20: Equity Risk premium | C20: % | D20: 0.045
B22: Beta | C22: x | D22: 0.88
B23: Cost of equity | C23: % | D23: =D19+D22*(D20) -> 0.0746
B25: Cost of debt | C25: % | D25: 0.04
B26: Tax | C26: % | D26: =C6 -> 0.25
B27: Post tax cost of debt | C27: % | D27: =D25*(1-D26) -> 0.03
B29: MV Equity / (MV Equity + Net Debt) | C29: % | D29: 1
B30: Net Debt / (MV Equity + Net Debt) | C30: % | D30: 0
B32: WACC | C32: % | D32: =(D23*D29)+(D30*D27) -> 0.0746
B33: Terminal growth rate | C33: % | D33: 0.03
B35: DCF Valuation
B36: Sum of discounted cash flows | C36: EUR (mn) | D36: =M15 -> 41357.983
B37: Undiscounted value of TV | C37: EUR (mn) | D37: =L11/(D32-D33) -> 180006.08
B38: Discounted value of TV | C38: EUR (mn) | D38: =D37/(1+L13)^L14 -> 94203.196
B39: Enterprise value | C39: EUR (mn) | D39: =D36+D38 -> 135561.18
B40: Net cash (debt) and lease | C40: EUR (mn) | D40: ='DCF Feed'!C8 -> 3593.3944
B41: Pension underfunding | C41: EUR (mn) | D41: ='DCF Feed'!C9 -> -23
B42: Pension tax shield | C42: EUR (mn) | D42: =-D41*(D26) -> 5.75
B43: Equity value | C43: EUR (mn) | D43: =SUM(D39:D42) -> 139137.32
B44: Number of shares | C44: million | D44: ='DCF Feed'!C12 -> 411.74891
B45: Equity value per share | C45: EUR | D45: =ROUND(D43/D44,-1) -> 340

Sheet Sheet5

Sheet Sheet4

Sheet MigrationOutput_QP_SAF.PA
B2: Congratulations! You have successfully migrated | F2: =HYPERLINK("[cleanSafran model WIP.xlsx]SAF.PA_Exchange_Sheet!$A$1","SAF.PA_Exchange_Sheet") -> SAF.PA_Exchange_Sheet
B3: Please review non-migrated data on: | F3: =HYPERLINK("[cleanSafran model WIP.xlsx]QP_SAF.PA_migrated!$A$1","QP_SAF.PA_migrated") -> QP_SAF.PA_migrated
B5: Final cleanup Items
B6: Keyword | C6: Description | E6: Action

Sheet QP_SAF.PA_migrated
A1: Quantum submission sheet for SAF.PA | F1: 1998 | G1: 1999 | H1: 2000 | I1: 2001 | J1: 2002 | K1: 2003 | L1: 2004 | M1: 2005 | N1: 2006 H1 | O1: 2006 H2 | P1: 2006 | Q1: 2007 H1 | R1: 2007 H2 | S1: 2007 | T1: 2008 H1 | U1: 2008 H2 | V1: 2008 | W1: 2009 H1 | X1: 2009 H2 | Y1: 2009 | Z1: 2010 H1 | AA1: 2010 H2 | AB1: 2010 | AC1: 2011 H1 | AD1: 2011 H2 | AE1: 2011 | AF1: 2012 | AG1: 2013 | AH1: 2014 | AI1: 2015 | AJ1: 2016 | AK1: 2017 | AL1: 2018 | AM1: 2019 | AN1: 2020
F2: Actual | G2: Actual | H2: Actual | I2: Actual | J2: Actual | K2: Actual | L2: Actual | M2: Actual | N2: Actual | O2: Actual | P2: Actual | Q2: Actual | R2: Actual | S2: Actual | T2: Actual | U2: Actual | V2: Actual | W2: Actual | X2: Actual | Y2: Actual | Z2: Actual | AA2: Actual | AB2: Actual | AC2: Actual | AD2: Actual | AE2: Actual | AF2: Actual | AG2: Estimate | AH2: Estimate | AI2: Estimate | AJ2: Estimate | AK2: Estimate | AL2: Estimate | AM2: Estimate | AN2: Estimate
F3: 36160 | G3: 36525 | H3: 36891 | I3: 37256 | J3: 37621 | K3: 37986 | L3: 38352 | M3: 38717 | N3: 38898 | O3: 39082 | P3: 39082 | Q3: 39263 | R3: 39447 | S3: 39447 | T3: 39629 | U3: 39813 | V3: 39813 | W3: 39994 | X3: 40178 | Y3: 40178 | Z3: 40359 | AA3: 40543 | AB3: 40543 | AC3: 40724 | AD3: 40908 | AE3: 40908 | AF3: 41274 | AG3: 41639 | AH3: 42004 | AI3: 42369 | AJ3: 42735 | AK3: 43100 | AL3: 43465 | AM3: 43830 | AN3: 44196
A5: Reference data | D5: #0
B6: Ticker | C6: Ticker_1 | E6: SAF.PA
B7: Company name | C7: Company name | E7: Safran
B8: Interim type | C8: Interim type | E8: Semiannual
B9: Reporting currency | C9: Reporting currency | E9: EUR
B10: Publishing currency | C10: Publishing currency | E10: EUR
B11: Pricing currency | C11: Pricing currency_1 | E11: EUR
A13: General Information | D13: #10
B14: Pan Europe Investment List | C14: EURO_LIST
B15: Pan Europe Conviction List | C15: EURO_CONVICTION
B16: Legal rating | C16: LEGAL_RATING
B17: Target price | C17: TARGET_PRICE | D17: EUR
B18: Target price period | C18: TP_PERIOD
B19: Current shares outstanding (mn) | C19: NUM_SH1
B20: Free float | C20: FREE_FLOAT
A22: Publishing Items | D22: #20
B23: Book value per share, BVPS (Pub) | C23: BVPS_PUB | D23: EUR | AK23: =AK116/AK75 -> #REF! | AL23: =AL116/AL75 -> #REF! | AM23: =AM116/AM75 -> #REF! | AN23: =AN116/AN75 -> #REF!
B24: DPS, dividend per share (Pub) | C24: DPS_PUB | D24: EUR | AK24: =#REF! -> #REF! | AL24: =#REF! -> #REF! | AM24: =#REF! -> #REF! | AN24: =#REF! -> #REF!
B25: EBITDA (Pub) | C25: EBITDA_PUB | D25: EUR | AK25: =#REF! -> #REF! | AL25: =#REF! -> #REF! | AM25: =#REF! -> #REF! | AN25: =#REF! -> #REF! | AO25: CH: GS A&D standard EBITDA (company defined underlying EBIT exclusing any additional depreciation, amortisation or impairments)
B26: EPS (Pub) | C26: EPS_PUB | D26: EUR | AK26: =#REF! -> #REF! | AL26: =#REF! -> #REF! | AM26: =#REF! -> #REF! | AN26: =#REF! -> #REF!
B27: EV adjustment (Pub) | C27: EV_ADJ_PUB | D27: EUR
B28: Long-term EPS growth estimate (Pub)
B29: Net debt (Pub) | C29: NET_DEBT_PUB | D29: EUR | AK29: =#REF! -> #REF! | AL29: =#REF! -> #REF! | AM29: =#REF! -> #REF! | AN29: =#REF! -> #REF!
B30: Net income (Pub) | C30: NI_PUB | D30: EUR | AK30: =#REF! -> #REF! | AL30: =#REF! -> #REF! | AM30: =#REF! -> #REF! | AN30: =#REF! -> #REF!
B31: EBIT, operating profit (Pub) | C31: EBIT_PUB | D31: EUR | AK31: =#REF! -> #REF! | AL31: =#REF! -> #REF! | AM31: =#REF! -> #REF! | AN31: =#REF! -> #REF!
B32: Pre-tax profit (Pub) | C32: PTP_PUB | D32: EUR | AK32: =#REF! -> #REF! | AL32: =#REF! -> #REF! | AM32: =#REF! -> #REF! | AN32: =#REF! -> #REF!
B33: Sales, revenue (Pub) | C33: REVS_PUB | D33: EUR | AK33: =#REF! -> #REF! | AL33: =#REF! -> #REF! | AM33: =#REF! -> #REF! | AN33: =#REF! -> #REF!
B34: Total shareholders' equity (Pub) | C34: EQ_PUB | D34: EUR | AK34: =AK116 -> #REF! | AL34: =AL116 -> #REF! | AM34: =AM116 -> #REF! | AN34: =AN116 -> #REF!
A36: Other & Corporate Income Statement | D36: #29
B37: EBITDA (Pub) | D37: EUR | M37: 724
B38: Pre-tax profit (Pub) | D38: EUR | M38: 383
B39: Net income (Pub) | D39: EUR | M39: 279.96755
B40: EPS (Pub) | D40: EUR | M40: 0.68399457
A42: Income Statement | D42: #30
B43: Sales, net revenue | C43: SALES | D43: EUR | AK43: =#REF! -> #REF! | AL43: =#REF! -> #REF! | AM43: =#REF! -> #REF! | AN43: =#REF! -> #REF!
B44: Cost of goods sold, COGS | C44: COST_GD_SD | D44: EUR
B45: SG&A, selling, general and admin. expense | C45: SEL_GL_AD | D45: EUR
B46: Total operating expense | C46: OP_COST | D46: EUR | AK46: =AK51-AK48-AK43 -> #REF! | AL46: =AL51-AL48-AL43 -> #REF! | AM46: =AM51-AM48-AM43 -> #REF! | AN46: =AN51-AN48-AN43 -> #REF!
B47: R&D expense | C47: RD_EXP | D47: EUR | AK47: =-#REF! -> #REF! | AL47: =-#REF! -> #REF! | AM47: =-#REF! -> #REF! | AN47: =-#REF! -> #REF!
B48: Other operating income/(expense) (incl. leases) | C48: OTH_OP_INC_EXP | D48: EUR
B49: Total operating expense (incl. D&A) | C49: TOT_OPS_EXP_DDA | D49: EUR | AK49: =AK46+AK48+AK52+AK53 -> #REF! | AL49: =AL46+AL48+AL52+AL53 -> #REF! | AM49: =AM46+AM48+AM52+AM53 -> #REF! | AN49: =AN46+AN48+AN52+AN53 -> #REF!
B50: Total operating expense (excl. D&A) | C50: TOT_OPS_EXP | D50: EUR | AK50: =AK46+AK48 -> #REF! | AL50: =AL46+AL48 -> #REF! | AM50: =AM46+AM48 -> #REF! | AN50: =AN46+AN48 -> #REF!
B51: EBITDA | C51: EBITDA_CALC | D51: EUR | AK51: =AK25 -> #REF! | AL51: =AL25 -> #REF! | AM51: =AM25 -> #REF! | AN51: =AN25 -> #REF!
B52: Depreciation | C52: DEPREC | D52: EUR | AK52: =-#REF! -> #REF! | AL52: =-#REF! -> #REF! | AM52: =-#REF! -> #REF! | AN52: =-#REF! -> #REF!
B53: Amortization | C53: GOODWILL_AMORT | D53: EUR | AK53: =-#REF!-#REF! -> #REF! | AL53: =-#REF!-#REF! -> #REF! | AM53: =-#REF!-#REF! -> #REF! | AN53: =-#REF!-#REF! -> #REF! | AO53: CH: This includes impairment charges (to reconcile between GS EBITDA (which excludes impairments) and company defined underlying EBIT which includes impairment charges)
B54: EBIT, operating profit | C54: EBIT | D54: EUR | AK54: =AK51+AK52+AK53 -> #REF! | AL54: =AL51+AL52+AL53 -> #REF! | AM54: =AM51+AM52+AM53 -> #REF! | AN54: =AN51+AN52+AN53 -> #REF!
B55: Interest income | C55: INT_INC_IND | D55: EUR
B56: Interest expense | C56: INT_EXP_IND | D56: EUR
B57: Net interest income/(expense) | C57: NET_INT_EXP | D57: EUR | AK57: =#REF! -> #REF! | AL57: =#REF! -> #REF! | AM57: =#REF! -> #REF! | AN57: =#REF! -> #REF!
B58: Income/(loss) from unconsolidated subs & associates | C58: ASSOCIATE | D58: EUR | AK58: =#REF! -> #REF! | AL58: =#REF! -> #REF! | AM58: =#REF! -> #REF! | AN58: =#REF! -> #REF!
B59: Profit/(loss) on disposals of assets, pre-tax | C59: PROFIT_ON_DISP | D59: EUR
B60: Other non-ops income/(expense) | C60: OTH_COST_INC | D60: EUR
B61: Pre-tax profit | C61: PT_PROF | D61: EUR | AK61: =AK54+AK57+AK58 -> #REF! | AL61: =AL54+AL57+AL58 -> #REF! | AM61: =AM54+AM57+AM58 -> #REF! | AN61: =AN54+AN57+AN58 -> #REF!
B62: Provision for income tax | C62: PROV_INC_TAX | D62: EUR | AK62: =#REF! -> #REF! | AL62: =#REF! -> #REF! | AM62: =#REF! -> #REF! | AN62: =#REF! -> #REF!
B63: Minority interest | C63: INC_MINORITY | D63: EUR | AK63: =#REF! -> #REF! | AL63: =#REF! -> #REF! | AM63: =#REF! -> #REF! | AN63: =#REF! -> #REF!
B64: Net income (pre-preferred dividends) | C64: NI_PRE_PREF | D64: EUR | AK64: =AK61+AK62+AK63 -> #REF! | AL64: =AL61+AL62+AL63 -> #REF! | AM64: =AM61+AM62+AM63 -> #REF! | AN64: =AN61+AN62+AN63 -> #REF!
B65: Preferred dividends | C65: PREF_DIV | D65: EUR
B66: Net income (pre-exceptionals) | C66: NET_EARNING | D66: EUR | AK66: =AK64+AK65 -> #REF! | AL66: =AL64+AL65 -> #REF! | AM66: =AM64+AM65 -> #REF! | AN66: =AN64+AN65 -> #REF!
B67: Post-tax exceptionals | C67: TAX_EXC | D67: EUR | AK67: =#REF! -> #REF! | AL67: =#REF! -> #REF! | AM67: =#REF! -> #REF! | AN67: =#REF! -> #REF! | AO67: CH: Income from discontinued operations
B68: Net income (post-exceptionals) | C68: NET_INC | D68: EUR | AK68: =AK66+AK67 -> #REF! | AL68: =AL66+AL67 -> #REF! | AM68: =AM66+AM67 -> #REF! | AN68: =AN66+AN67 -> #REF!
B69: EPS (pre-exceptionals, basic) | C69: EPS | D69: EUR | AK69: =AK66/AK75 -> #REF! | AL69: =AL66/AL75 -> #REF! | AM69: =AM66/AM75 -> #REF! | AN69: =AN66/AN75 -> #REF!
B70: EPS (pre-exceptionals, diluted) | C70: EPS_FUL_DIL | D70: EUR | AK70: =AK66/AK76 -> #REF! | AL70: =AL66/AL76 -> #REF! | AM70: =AM66/AM76 -> #REF! | AN70: =AN66/AN76 -> #REF!
B71: EPS (post-exceptionals, basic) | C71: EPS_POST_BASIC | D71: EUR | AK71: =AK68/AK75 -> #REF! | AL71: =AL68/AL75 -> #REF! | AM71: =AM68/AM75 -> #REF! | AN71: =AN68/AN75 -> #REF!
B72: EPS (post-exceptionals, diluted) | C72: FULLY_DIL_EPS | D72: EUR | AK72: =AK68/AK76 -> #REF! | AL72: =AL68/AL76 -> #REF! | AM72: =AM68/AM76 -> #REF! | AN72: =AN68/AN76 -> #REF!
B73: Common dividends paid | C73: COMMON_DIV_PAID | D73: EUR | AK73: =-(#REF!*#REF!)/1000 -> #REF! | AL73: =-(#REF!*#REF!)/1000 -> #REF! | AM73: =-(#REF!*#REF!)/1000 -> #REF! | AN73: =-(#REF!*#REF!)/1000 -> #REF!
B74: DPS, dividend per share | C74: DPS | D74: EUR | AK74: =#REF! -> #REF! | AL74: =#REF! -> #REF! | AM74: =#REF! -> #REF! | AN74: =#REF! -> #REF!
B75: Weighted average shares outstanding, basic | C75: SH1 | AK75: =#REF!/1000 -> #REF! | AL75: =#REF!/1000 -> #REF! | AM75: =#REF!/1000 -> #REF! | AN75: =#REF!/1000 -> #REF!
B76: Diluted average shares outstanding (mn) | C76: DILUTE_SHARES | AK76: =#REF!/1000 -> #REF! | AL76: =#REF!/1000 -> #REF! | AM76: =#REF!/1000 -> #REF! | AN76: =#REF!/1000 -> #REF!
B77: Period-end shares outstanding | C77: NON_OP_ADD | AK77: =#REF!/1000 -> #REF! | AL77: =#REF!/1000 -> #REF! | AM77: =#REF!/1000 -> #REF! | AN77: =#REF!/1000 -> #REF!
A79: Additional Income Statement Items | D79: #31
B80: Lease payments | C80: LEASE_PAY | D80: EUR
B81: Lease payments (deemed interest portion) | C81: LEASE_DEEM_INT | D81: EUR
B82: Lease payments (deemed depreciation portion) | C82: LEASE_DEEM_DEPR | D82: EUR
B83: Gross interest charge | C83: NET_INT_CH | D83: EUR
B84: Income from associates (operating) | C84: ASSOCIATE_OP | D84: EUR
B85: Goodwill amortization | C85: GW_AMORT | D85: EUR
B86: Other intangible amortization | C86: OTH_INT_AMORT | D86: EUR
B87: Marginal tax rate | C87: MARGIN_TAX_RATE | AK87: =1-#REF! -> #REF! | AL87: =1-#REF! -> #REF! | AM87: =1-#REF! -> #REF! | AN87: =1-#REF! -> #REF!
A89: Balance Sheet | D89: #40
B90: Cash & cash equivalents | C90: CASH_EQ | D90: EUR | AK90: =#REF! -> #REF! | AL90: =#REF! -> #REF! | AM90: =#REF! -> #REF! | AN90: =#REF! -> #REF!
B91: Accounts receivable | C91: DEBTORS | D91: EUR | AK91: =#REF! -> #REF! | AL91: =#REF! -> #REF! | AM91: =#REF! -> #REF! | AN91: =#REF! -> #REF!
B92: Inventory | C92: STOCKS | D92: EUR | AK92: =#REF! -> #REF! | AL92: =#REF! -> #REF! | AM92: =#REF! -> #REF! | AN92: =#REF! -> #REF!
B93: Other current assets | C93: OTH_CUR_ASS | D93: EUR | AK93: =AK94-AK92-AK91 -> #REF! | AL93: =AL94-AL92-AL91 -> #REF! | AM93: =AM94-AM92-AM91 -> #REF! | AN93: =AN94-AN92-AN91 -> #REF!
B94: Total current assets | C94: CUR_ASS | D94: EUR | AK94: =#REF! -> #REF! | AL94: =#REF! -> #REF! | AM94: =#REF! -> #REF! | AN94: =#REF! -> #REF!
B95: Gross fixed assets, PP&E | C95: GR_FIX_ASS | D95: EUR | AK95: =#REF! -> #REF! | AL95: =#REF! -> #REF! | AM95: =#REF! -> #REF! | AN95: =#REF! -> #REF!
B96: Accumulated depreciation | C96: ACC_DDA | D96: EUR | AK96: =AK97-AK95 -> #REF! | AL96: =AL97-AL95 -> #REF! | AM96: =AM97-AM95 -> #REF! | AN96: =AN97-AN95 -> #REF!
B97: Net PP&E | C97: NET_FIX_ASS | D97: EUR | AK97: =#REF! -> #REF! | AL97: =#REF! -> #REF! | AM97: =#REF! -> #REF! | AN97: =#REF! -> #REF!
B98: Gross intangibles | C98: GR_INTANG | D98: EUR | AK98: =#REF! -> #REF! | AL98: =#REF! -> #REF! | AM98: =#REF! -> #REF! | AN98: =#REF! -> #REF!
B99: Accumulated amortization | C99: ACC_AMORT | D99: EUR | AK99: =AK100-AK98 -> #REF! | AL99: =AL100-AL98 -> #REF! | AM99: =AM100-AM98 -> #REF! | AN99: =AN100-AN98 -> #REF!
B100: Net intangible assets | C100: NET_INTANG | D100: EUR | AK100: =#REF! -> #REF! | AL100: =#REF! -> #REF! | AM100: =#REF! -> #REF! | AN100: =#REF! -> #REF!
B101: Equity method investments | C101: FIX_ASS_INV | D101: EUR | AK101: =#REF! -> #REF! | AL101: =#REF! -> #REF! | AM101: =#REF! -> #REF! | AN101: =#REF! -> #REF!
B102: Investments in securities | C102: INV_SECUR | D102: EUR
B103: Other long-term assets | C103: OTH_LT_ASS | D103: EUR | AK103: =AK104-AK97-AK100-AK101-AK102-AK94 -> #REF! | AL103: =AL104-AL97-AL100-AL101-AL102-AL94 -> #REF! | AM103: =AM104-AM97-AM100-AM101-AM102-AM94 -> #REF! | AN103: =AN104-AN97-AN100-AN101-AN102-AN94 -> #REF!
B104: Total assets | C104: TOT_ASSET | D104: EUR | AK104: =AK94+#REF! -> #REF! | AL104: =AL94+#REF! -> #REF! | AM104: =AM94+#REF! -> #REF! | AN104: =AN94+#REF! -> #REF!
B105: Accounts payable | C105: ACC_PAY_GQ | D105: EUR | AK105: =-#REF! -> #REF! | AL105: =-#REF! -> #REF! | AM105: =-#REF! -> #REF! | AN105: =-#REF! -> #REF!
B106: Short-term debt | C106: SHORT_T_DEBT | D106: EUR | AK106: =-#REF! -> #REF! | AL106: =-#REF! -> #REF! | AM106: =-#REF! -> #REF! | AN106: =-#REF! -> #REF!
B107: Other current liabilities | C107: OTH_CUR_LIABS | D107: EUR
...

Sheet DCF
B1: =C34 -> 309 | Z1: SAF.PA
B2: Valuation date | C2: 45918
B3: Explicit growth (EBIT) | C3: ='DCF Feed'!H4 -> 0.10989743
B4: Mid-term growth | C4: 0.1
B5: Long term growth | C5: 0.03
B6: Discount rate | C6: 0.09
B7: Tax rate | C7: =-'DCF Feed'!E10 -> 0.25
B8: Cash conversion | C8: 1.05
B9: EV/EBIT | C9: =N19*(1-C7) -> 23.443403
B12: Calendar year | C12: =YEAR(TODAY()) -> 2025 | D12: =C12+1 -> 2026 | E12: =D12+1 -> 2027 | F12: =E12+1 -> 2028 | G12: =F12+1 -> 2029 | H12: =G12+1 -> 2030 | I12: =H12+1 -> 2031 | J12: =I12+1 -> 2032 | K12: =J12+1 -> 2033 | ... M12: =L12+1 -> 2035 | N12: Terminal value
C13: 0 | D13: =C13+1 -> 1 | E13: =D13+1 -> 2 | F13: =E13+1 -> 3 | G13: =F13+1 -> 4 | H13: =G13+1 -> 5 | I13: =H13+1 -> 6 | J13: =I13+1 -> 7 | K13: =J13+1 -> 8 | ... M13: =L13+1 -> 10
B14: =C2+365 -> 46283 | C14: 45809 | D14: =C14+365 -> 46174 | E14: =D14+365 -> 46539 | F14: =E14+365 -> 46904 | G14: =F14+365 -> 47269 | H14: =G14+365 -> 47634 | I14: =H14+365 -> 47999 | J14: =I14+365 -> 48364 | K14: =J14+365 -> 48729 | ... M14: =L14+365 -> 49459
B15: Cumulative growth | C15: 1 | D15: =C15*(1+D16) -> 1.1775451 | E15: =D15*(1+E16) -> 1.3379137 | F15: =E15*(1+F16) -> 1.4764201 | G15: =F15*(1+G16) -> 1.5786428 | H15: =C15*(1+C3)^5 -> 1.6842798 | I15: =H15*(1+I16) -> 1.8527078 | J15: =I15*(1+J16) -> 2.0055562 | K15: =J15*(1+K16) -> 2.1359173 | L15: =K15*(1+L16) -> 2.2373734 | M15: =L15*(1+M16) -> 2.3044946 | N15: =M15/(C6-C5) -> 38.408243
B16: Annual growth | D16: =INDEX('DCF Feed'!5:5,MATCH(DCF!D12,'DCF Feed'!1:1,0)) -> 0.1775451 | E16: =INDEX('DCF Feed'!5:5,MATCH(DCF!E12,'DCF Feed'!1:1,0)) -> 0.13618897 | F16: =INDEX('DCF Feed'!5:5,MATCH(DCF!F12,'DCF Feed'!1:1,0)) -> 0.10352412 | G16: =INDEX('DCF Feed'!5:5,MATCH(DCF!G12,'DCF Feed'!1:1,0)) -> 0.069236834 | H16: =INDEX('DCF Feed'!5:5,MATCH(DCF!H12,'DCF Feed'!1:1,0)) -> 0.066916368 | I16: =$C$4 -> 0.1 | J16: =I16+(($M$16-$I$16)/4) -> 0.0825 | K16: =J16+(($M$16-$I$16)/4) -> 0.065 | L16: =K16+(($M$16-$I$16)/4) -> 0.0475 | M16: =$C$5 -> 0.03
B17: Cash conversion | D17: =INDEX('DCF Feed'!7:7,MATCH(DCF!D12,'DCF Feed'!1:1,0)) -> 0.96065356 | E17: =INDEX('DCF Feed'!7:7,MATCH(DCF!E12,'DCF Feed'!1:1,0)) -> 0.97047348 | F17: =INDEX('DCF Feed'!7:7,MATCH(DCF!F12,'DCF Feed'!1:1,0)) -> 0.958557 | G17: =INDEX('DCF Feed'!7:7,MATCH(DCF!G12,'DCF Feed'!1:1,0)) -> 0.96911592 | H17: =INDEX('DCF Feed'!7:7,MATCH(DCF!H12,'DCF Feed'!1:1,0)) -> 0.97251994 | I17: =$C$8 -> 1.05 | J17: =$C$8 -> 1.05 | K17: =$C$8 -> 1.05 | L17: =$C$8 -> 1.05 | M17: =$C$8 -> 1.05
B18: Discounted value | D18: =1/(1+$C$6)^((D14-$B$14)/365) -> 1.0260693 | E18: =1/(1+$C$6)^((E14-$B$14)/365) -> 0.94134795 | F18: =1/(1+$C$6)^((F14-$B$14)/365) -> 0.86362197 | G18: =1/(1+$C$6)^((G14-$B$14)/365) -> 0.79231374 | H18: =1/(1+$C$6)^((H14-$B$14)/365) -> 0.72689334 | I18: =1/(1+$C$6)^((I14-$B$14)/365) -> 0.66687462 | J18: =1/(1+$C$6)^((J14-$B$14)/365) -> 0.61181158 | K18: =1/(1+$C$6)^((K14-$B$14)/365) -> 0.56129503 | ... M18: =1/(1+$C$6)^((M14-$B$14)/365) -> 0.47243079
B19: PV | D19: =D15*D17*D18 -> 1.1607028 | E19: =E15*E17*E18 -> 1.2222554 | F19: =F15*F17*F18 -> 1.2222262 | G19: =G15*G17*G18 -> 1.2121511 | H19: =H15*H17*H18 -> 1.1906481 | I19: =I15*I17*I18 -> 1.2973 | J19: =J15*J17*J18 -> 1.2883736 | K19: =K15*K17*K18 -> 1.2588238 | L19: =L15*L17*L18 -> 1.2097412 | M19: =(M15+N15)*M17*M18 -> 20.195649 | N19: =SUM(D19:M19) -> 31.257871
B24: Year | C24: =C12 -> 2025
B25: Target EV/EBIT | C25: =C9 -> 23.443403
B26: EBIT | C26: =INDEX('DCF Feed'!4:4,MATCH(DCF!$C$24,'DCF Feed'!$1:$1,0)) -> 5217.0943
B27: Target EV | C27: =C25*C26 -> 122306.44
B28: Net Cash (Debt) | C28: ='DCF Feed'!B8 -> 2263.3518
B29: Other
B30: Pension underfunding | C30: =INDEX('DCF Feed'!9:9,MATCH(DCF!C24,'DCF Feed'!1:1,0)) -> -23
B31: Pension tax shield | C31: =-C30*C7 -> 5.75
B32: Target Market Cap | C32: =SUM(C27:C31) -> 124552.55
B33: Number of shares | C33: ='DCF Feed'!E12 -> 402.77548
B34: Target price | C34: =MROUND(C32/C33,1) -> 309
B35: Current Share Price | C35: Error: RTD method of WorksheetFunction class failed
B36: Upside/(Downside) | C36: =C34/C35-1 -> #VALUE!
B39: Share Price | D39: WACC
C40: =$C$34 -> 309 | D40: =E40-0.5% -> 0.08 | E40: =F40-0.5% -> 0.085 | F40: 0.09 | G40: =F40+0.5% -> 0.095 | H40: =G40+0.5% -> 0.1
B41: 5Yr EBIT CAGR | C41: =C42-2% -> 0.0639199 | D41: 309 | E41: 282 | F41: 260 | G41: 241 | H41: 225
C42: =C43-2% -> 0.0839199 | D42: 334 | E42: 305 | F42: 281 | G42: 260 | H42: 242
B43: Explicit PROF Grow | C43: 0.1039199 | D43: 361 | E43: 329 | F43: 302 | G43: 280 | H43: 261
C44: =C43+2% -> 0.1239199 | D44: 390 | E44: 355 | F44: 326 | G44: 301 | H44: 280
C45: =C44+2% -> 0.1439199 | D45: 421 | E45: 383 | F45: 351 | G45: 324 | H45: 301
D48: Cash Conversion Ratio | F48: CC
C49: =$C$34 -> 309 | D49: =E49-10% -> 0.85 | E49: =F49-10% -> 0.95 | F49: 1.05 | G49: =F49+10% -> 1.15 | H49: =G49+10% -> 1.25
B50: 5Yr EBIT CAGR | C50: =C51-3% -> 0.0439199 | D50: 207 | E50: 224 | F50: 241 | G50: 259 | H50: 276
C51: =C52-3% -> 0.0739199 | D51: 231 | E51: 250 | F51: 270 | G51: 290 | H51: 310
B52: Explicit PROF Grow | C52: 0.1039199 | D52: 257 | E52: 280 | F52: 302 | G52: 325 | H52: 348
C53: =C52+3% -> 0.1339199 | D53: 286 | E53: 312 | F53: 338 | G53: 364 | H53: 390
C54: =C53+3% -> 0.1639199 | D54: 319 | E54: 349 | F54: 378 | G54: 408 | H54: 437

Sheet DCF Feed
A1: €mn | B1: 2025 | C1: =B1+1 -> 2026 | D1: =C1+1 -> 2027 | E1: =D1+1 -> 2028 | F1: =E1+1 -> 2029 | G1: =F1+1 -> 2030 | H1: 5yr. CAGR
A2: Sales | B2: =INDEX('Income Statement'!39:39,MATCH(B1,'Income Statement'!38:38,0)) -> 31556.569 | C2: =INDEX('Income Statement'!39:39,MATCH(C1,'Income Statement'!38:38,0)) -> 35653.732 | D2: =INDEX('Income Statement'!39:39,MATCH(D1,'Income Statement'!38:38,0)) -> 39232.543 | E2: =INDEX('Income Statement'!39:39,MATCH(E1,'Income Statement'!38:38,0)) -> 42282.093 | F2: =INDEX('Income Statement'!39:39,MATCH(F1,'Income Statement'!38:38,0)) -> 44620.651 | G2: =INDEX('Income Statement'!39:39,MATCH(G1,'Income Statement'!38:38,0)) -> 46787.067 | H2: =(G2/B2)^(1/5)-1 -> 0.081950044
A3: Sales growth | C3: =C2/B2-1 -> 0.12983551 | D3: =D2/C2-1 -> 0.10037691 | E3: =E2/D2-1 -> 0.077730101 | F3: =F2/E2-1 -> 0.055308477 | G3: =G2/F2-1 -> 0.048551861
A4: Adj. EBIT | B4: =INDEX('Income Statement'!74:74,MATCH(B1,'Income Statement'!$38:$38,0)) -> 5217.0943 | C4: =INDEX('Income Statement'!74:74,MATCH(C1,'Income Statement'!$38:$38,0)) -> 6143.3638 | D4: =INDEX('Income Statement'!74:74,MATCH(D1,'Income Statement'!$38:$38,0)) -> 6980.0222 | E4: =INDEX('Income Statement'!74:74,MATCH(E1,'Income Statement'!$38:$38,0)) -> 7702.6228 | F4: =INDEX('Income Statement'!74:74,MATCH(F1,'Income Statement'!$38:$38,0)) -> 8235.9281 | G4: =INDEX('Income Statement'!74:74,MATCH(G1,'Income Statement'!$38:$38,0)) -> 8787.0465 | H4: =(G4/B4)^(1/5)-1 -> 0.10989743
A5: Growth | C5: =C4/B4-1 -> 0.1775451 | D5: =D4/C4-1 -> 0.13618897 | E5: =E4/D4-1 -> 0.10352412 | F5: =F4/E4-1 -> 0.069236834 | G5: =G4/F4-1 -> 0.066916368
A6: GS Defined Op Cash Flow | B6: =INDEX('Cashflow Statement'!71:71, MATCH('DCF Feed'!B1,'Cashflow Statement'!2:2,0)) -> 4875.1458 | C6: =INDEX('Cashflow Statement'!71:71, MATCH('DCF Feed'!C1,'Cashflow Statement'!2:2,0)) -> 5901.6443 | D6: =INDEX('Cashflow Statement'!71:71, MATCH('DCF Feed'!D1,'Cashflow Statement'!2:2,0)) -> 6773.9264 | E6: =INDEX('Cashflow Statement'!71:71, MATCH('DCF Feed'!E1,'Cashflow Statement'!2:2,0)) -> 7383.403 | F6: =INDEX('Cashflow Statement'!71:71, MATCH('DCF Feed'!F1,'Cashflow Statement'!2:2,0)) -> 7981.569 | G6: =INDEX('Cashflow Statement'!71:71, MATCH('DCF Feed'!G1,'Cashflow Statement'!2:2,0)) -> 8545.5779 | H6: =(G6/B6)^(1/5)-1 -> 0.11879564
A7: Cash Conversion | B7: =B6/B4 -> 0.93445614 | C7: =C6/C4 -> 0.96065356 | D7: =D6/D4 -> 0.97047348 | E7: =E6/E4 -> 0.958557 | F7: =F6/F4 -> 0.96911592 | G7: =G6/G4 -> 0.97251994 | H7: =AVERAGE(B7:G7) -> 0.96096268
A8: Net Cash (Debt) | B8: =INDEX('Balance Sheet'!$93:$93,MATCH('DCF Feed'!B1,'Balance Sheet'!$88:$88,0)) -> 2263.3518 | C8: =INDEX('Balance Sheet'!93:93,MATCH('DCF Feed'!C1,'Balance Sheet'!88:88,0)) -> 3593.3944 | D8: =INDEX('Balance Sheet'!93:93,MATCH('DCF Feed'!D1,'Balance Sheet'!88:88,0)) -> 5128.5417 | E8: =INDEX('Balance Sheet'!93:93,MATCH('DCF Feed'!E1,'Balance Sheet'!88:88,0)) -> 7063.3546 | F8: =INDEX('Balance Sheet'!93:93,MATCH('DCF Feed'!F1,'Balance Sheet'!88:88,0)) -> 10517.022 | G8: =INDEX('Balance Sheet'!93:93,MATCH('DCF Feed'!G1,'Balance Sheet'!88:88,0)) -> 14268.618
A9: Pension underfunding | B9: =INDEX('Balance Sheet'!$140:$140,MATCH('DCF Feed'!B1,'Balance Sheet'!$88:$88,0)) -> -23 | C9: =INDEX('Balance Sheet'!$140:$140,MATCH('DCF Feed'!C1,'Balance Sheet'!$88:$88,0)) -> -23 | D9: =INDEX('Balance Sheet'!$140:$140,MATCH('DCF Feed'!D1,'Balance Sheet'!$88:$88,0)) -> -23 | E9: =INDEX('Balance Sheet'!$140:$140,MATCH('DCF Feed'!E1,'Balance Sheet'!$88:$88,0)) -> -23 | F9: =INDEX('Balance Sheet'!$140:$140,MATCH('DCF Feed'!F1,'Balance Sheet'!$88:$88,0)) -> -23 | G9: =INDEX('Balance Sheet'!$140:$140,MATCH('DCF Feed'!G1,'Balance Sheet'!$88:$88,0)) -> -23
A10: Tax rate (adjusted) | B10: =INDEX('Income Statement'!91:91,MATCH(B1,'Income Statement'!$38:$38,0)) -> -0.32 | C10: =INDEX('Income Statement'!91:91,MATCH(C1,'Income Statement'!$38:$38,0)) -> -0.25 | D10: =INDEX('Income Statement'!91:91,MATCH(D1,'Income Statement'!$38:$38,0)) -> -0.25 | E10: =INDEX('Income Statement'!91:91,MATCH(E1,'Income Statement'!$38:$38,0)) -> -0.25 | F10: =INDEX('Income Statement'!91:91,MATCH(F1,'Income Statement'!$38:$38,0)) -> -0.25 | G10: =INDEX('Income Statement'!91:91,MATCH(G1,'Income Statement'!$38:$38,0)) -> -0.25
A11: Other
A12: No. of shares | B12: =INDEX('Income Statement'!117:117,MATCH(B1,'Income Statement'!$38:$38,0))/1000 -> 416.23563 | C12: =INDEX('Income Statement'!117:117,MATCH(C1,'Income Statement'!$38:$38,0))/1000 -> 411.74891 | D12: =INDEX('Income Statement'!117:117,MATCH(D1,'Income Statement'!$38:$38,0))/1000 -> 407.2622 | E12: =INDEX('Income Statement'!117:117,MATCH(E1,'Income Statement'!$38:$38,0))/1000 -> 402.77548 | F12: =INDEX('Income Statement'!117:117,MATCH(F1,'Income Statement'!$38:$38,0))/1000 -> 402.77548 | G12: =INDEX('Income Statement'!117:117,MATCH(G1,'Income Statement'!$38:$38,0))/1000 -> 402.77548

Sheet Income Statement
A1: ='DCF Valuation'!D45 -> 340
A2: Divisional Summary
A3: Revenues | B3: =B38 -> 2000 | C3: =C38 -> 2001 | D3: =D38 -> 2002 | E3: =E38 -> 2003 | F3: =F38 -> 2004 | G3: =G38 -> 2005 | H3: =H38 -> 2006 | I3: =I38 -> 2007 | ... Z3: =Z38 -> 2024 | AA3: =Z3+1 -> 2025 | AB3: =AA3+1 -> 2026 | AC3: =AB3+1 -> 2027 | AD3: =AC3+1 -> 2028 | AE3: =AD3+1 -> 2029 | AF3: =AE3+1 -> 2030
A4: Adjusted Revenues
A5: Aerospace Propulsion | H5: 5073 | I5: 5917 | J5: 5803 | K5: 5673 | L5: 5604 | M5: 6110 | N5: 7005 | O5: ='Aerospace Propulsion Division'!O6 -> 7589 | P5: ='Aerospace Propulsion Division'!P6 -> 8153 | Q5: ='Aerospace Propulsion Division'!Q6 -> 9319 | R5: ='Aerospace Propulsion Division'!R6 -> 9391 | S5: ='Aerospace Propulsion Division'!S6 -> 9357 | T5: ='Aerospace Propulsion Division'!T6 -> 10579 | U5: ='Aerospace Propulsion Division'!U6 -> 12045 | V5: ='Aerospace Propulsion Division'!V6 -> 7663 | ... Z5: ='Aerospace Propulsion Division'!Z6 -> 13652 | AA5: =Z5*(1+AA12) -> 15834.377 | AB5: =AA5*(1+AB12) -> 17806.597 | AC5: =AB5*(1+AC12) -> 19932.222 | AD5: =AC5*(1+AD12) -> 21615.123 | AE5: =AD5*(1+AE12) -> 22915.426 | AF5: =AE5*(1+AF12) -> 24191.629
A6: Equipment & Defense | T6: ='Equipment and Defense'!T6 -> 7942 | U6: ='Equipment and Defense'!U6 -> 9256 | V6: ='Equipment and Defense'!V6 -> 6893 | W6: ='Equipment and Defense'!W6 -> 6325 | X6: ='Equipment and Defense'!X6 -> 7535 | Y6: ='Equipment and Defense'!Y6 -> 8835 | Z6: ='Equipment and Defense'!Z6 -> 10618 | AA6: =Z6*(1+AA13) -> 12288.332 | AB6: =AA6*(1+AB13) -> 14054.01 | AC6: =AB6*(1+AC13) -> 15155.733 | AD6: =AC6*(1+AD13) -> 16185.108 | AE6: =AD6*(1+AE13) -> 17078.608 | AF6: =AE6*(1+AF13) -> 17837.766
A7: Aircraft Interiors | T7: ='Aircraft Interiors Division'!H6 -> 2511 | U7: ='Aircraft Interiors Division'!I6 -> 3321 | V7: ='Aircraft Interiors Division'!J6 -> 1922 | W7: ='Aircraft Interiors Division'!K6 -> 1475 | X7: ='Aircraft Interiors Division'!L6 -> 1978 | Y7: ='Aircraft Interiors Division'!M6 -> 2477 | Z7: ='Aircraft Interiors Division'!N6 -> 3037 | AA7: =Z7*(1+AA14) -> 3423.86 | AB7: =AA7*(1+AB14) -> 3783.125 | AC7: =AB7*(1+AC14) -> 4134.5881 | AD7: =AC7*(1+AD14) -> 4471.8616 | AE7: =AD7*(1+AE14) -> 4616.6169 | AF7: =AE7*(1+AF14) -> 4747.6719
A8: Other | H8: =H9-H5 -> 6256 | I8: =I9-I5 -> 4305 | J8: =J9-J5 -> 4526 | K8: =K9-K5 -> 4775 | L8: =L9-L5 -> 5156 | M8: =M9-M5 -> 5626 | N8: =N9-N5 -> 6555 | O8: =O9-O5 -> 6774 | ... S8: =S9-S5 -> 6596 | T8: 18 | U8: 18 | V8: 20 | W8: 18 | X8: 16 | Y8: 11 | Z8: 10 | AA8: =Z8 -> 10 | AB8: =AA8 -> 10 | AC8: =AB8 -> 10 | AD8: =AC8 -> 10 | AE8: =AD8 -> 10 | AF8: =AE8 -> 10
A9: Group | H9: 11329 | I9: 10222 | J9: 10329 | K9: 10448 | L9: 10760 | M9: 11736 | N9: 13560 | O9: 14363 | P9: 15355 | Q9: 17414 | R9: 15781 | S9: 15953 | T9: =SUM(T5,T6,T7,T8) -> 21050 | U9: =SUM(U5,U6,U7,U8) -> 24640 | V9: =SUM(V5,V6,V7,V8) -> 16498 | W9: =SUM(W5,W6,W7,W8) -> 15257 | X9: =SUM(X5,X6,X7,X8) -> 19035 | Y9: =SUM(Y5,Y6,Y7,Y8) -> 23199 | Z9: =SUM(Z5,Z6,Z7,Z8) -> 27317 | AA9: =SUM(AA5,AA6,AA7,AA8) -> 31556.569 | ... AF9: =SUM(AF5,AF6,AF7,AF8) -> 46787.067
A11: Revenue Growth
A12: Aerospace Propulsion | I12: =I5/H5-1 -> 0.16637098 | J12: =J5/I5-1 -> -0.01926652 | K12: =K5/J5-1 -> -0.022402206 | L12: =L5/K5-1 -> -0.012162877 | M12: =M5/L5-1 -> 0.090292648 | N12: =N5/M5-1 -> 0.14648118 | O12: =O5/N5-1 -> 0.083369022 | P12: =P5/O5-1 -> 0.074318092 | ... Z12: =Z5/Y5-1 -> 0.1495453 | AA12: ='Aerospace Propulsion Division'!AA7 -> 0.15985768 | AB12: ='Aerospace Propulsion Division'!AB7 -> 0.12455304 | AC12: ='Aerospace Propulsion Division'!AC7 -> 0.11937292 | AD12: ='Aerospace Propulsion Division'!AD7 -> 0.084431186 | AE12: ='Aerospace Propulsion Division'!AE7 -> 0.060157086 | AF12: ='Aerospace Propulsion Division'!AF7 -> 0.055691852
A13: Equipment & Defense | U13: =U6/T6-1 -> 0.16544951 | V13: =V6/U6-1 -> -0.25529386 | W13: =W6/V6-1 -> -0.082402437 | X13: =X6/W6-1 -> 0.19130435 | Y13: =Y6/X6-1 -> 0.1725282 | Z13: =Z6/Y6-1 -> 0.20181098 | AA13: ='Equipment and Defense'!AA7 -> 0.15731132 | AB13: ='Equipment and Defense'!AB7 -> 0.1436874 | AC13: ='Equipment and Defense'!AC7 -> 0.078392078 | AD13: ='Equipment and Defense'!AD7 -> 0.067919832 | AE13: ='Equipment and Defense'!AE7 -> 0.05520507 | AF13: ='Equipment and Defense'!AF7 -> 0.04445082
A14: Aircraft Interiors | U14: =U7/T7-1 -> 0.32258065 | V14: =V7/U7-1 -> -0.42125866 | W14: =W7/V7-1 -> -0.23257024 | X14: =X7/W7-1 -> 0.34101695 | Y14: =Y7/X7-1 -> 0.25227503 | Z14: =Z7/Y7-1 -> 0.22607994 | AA14: ='Aircraft Interiors Division'!O7 -> 0.12738229 | AB14: ='Aircraft Interiors Division'!P7 -> 0.10492982 | AC14: ='Aircraft Interiors Division'!Q7 -> 0.092902847 | AD14: ='Aircraft Interiors Division'!R7 -> 0.081573672 | AE14: ='Aircraft Interiors Division'!S7 -> 0.032370256 | AF14: ='Aircraft Interiors Division'!T7 -> 0.028387668
A15: Other | K15: =K8/J8-1 -> 0.055015466 | L15: =L8/K8-1 -> 0.079790576 | M15: =M8/L8-1 -> 0.091155935 | N15: =N8/M8-1 -> 0.1651262 | O15: =O8/N8-1 -> 0.033409611 | P15: =P8/O8-1 -> 0.063182758 | Q15: =Q8/P8-1 -> 0.12399334 | R15: =R8/Q8-1 -> -0.21062384 | ... AF15: =AF8/AE8-1 -> 0
A16: Group | I16: =I9/H9-1 -> -0.097713832 | J16: =J9/I9-1 -> 0.010467619 | K16: =K9/J9-1 -> 0.01152096 | L16: =L9/K9-1 -> 0.029862175 | M16: =M9/L9-1 -> 0.09070632 | N16: =N9/M9-1 -> 0.15541922 | O16: =O9/N9-1 -> 0.059218289 | P16: =P9/O9-1 -> 0.069066351 | ... AF16: =AF9/AE9-1 -> 0.048551861
A18: Adj. EBIT
A19: Aerospace Propulsion | H19: 561 | I19: 636 | J19: 584 | K19: 628 | L19: 663 | M19: 909 | N19: 1076 | O19: ='Aerospace Propulsion Division'!O19 -> 0 | P19: ='Aerospace Propulsion Division'!P19 -> 0 | Q19: ='Aerospace Propulsion Division'!Q19 -> 0 | R19: ='Aerospace Propulsion Division'!R19 -> 0 | S19: 1516 | T19: ='Aerospace Propulsion Division'!T19 -> 2030 | U19: ='Aerospace Propulsion Division'!U19 -> 2485 | V19: ='Aerospace Propulsion Division'!V19 -> 1192 | W19: ='Aerospace Propulsion Division'!W19 -> 1342 | X19: ='Aerospace Propulsion Division'!X19 -> 1710 | Y19: ='Aerospace Propulsion Division'!Y19 -> 2390 | Z19: ='Aerospace Propulsion Division'!Z19 -> 2819 | AA19: =AA5*AA26 -> 3573.1909 | AB19: =AB5*AB26 -> 4022.7156 | AC19: =AC5*AC26 -> 4530.2242 | AD19: =AD5*AD26 -> 4955.689 | AE19: =AE5*AE26 -> 5298.5022 | AF19: =AF5*AF26 -> 5689.8015
A20: Equipment & Defense | S20: 619 | T20: ='Equipment and Defense'!T14 -> 992 | U20: ='Equipment and Defense'!U14 -> 1209 | V20: ='Equipment and Defense'!V14 -> 687 | W20: ='Equipment and Defense'!W14 -> 650 | X20: ='Equipment and Defense'!X14 -> 874 | Y20: ='Equipment and Defense'!Y14 -> 992 | Z20: ='Equipment and Defense'!Z14 -> 1298 | AA20: =AA6*AA27 -> 1566.0906 | AB20: =AB6*AB27 -> 1952.7463 | AC20: =AC6*AC27 -> 2176.3225 | AD20: =AD6*AD27 -> 2384.4683 | AE20: =AE6*AE27 -> 2546.349 | AF20: =AF6*AF27 -> 2693.8536
A21: Aircraft Interiors | S21: 93 | T21: ='Aircraft Interiors Division'!H19 -> 81 | U21: ='Aircraft Interiors Division'!I19 -> 188 | V21: ='Aircraft Interiors Division'!J19 -> -174 | W21: ='Aircraft Interiors Division'!K19 -> -167 | X21: ='Aircraft Interiors Division'!L19 -> -140 | Y21: ='Aircraft Interiors Division'!M19 -> -116 | Z21: ='Aircraft Interiors Division'!N19 -> 27 | AA21: =AA7*AA28 -> 106.69282 | AB21: =AB7*AB28 -> 200.53141 | AC21: =AC7*AC28 -> 309.38034 | AD21: =AD7*AD28 -> 401.1613 | AE21: =AE7*AE28 -> 431.91276 | AF21: =AF7*AF28 -> 446.20993
A22: Other | H22: -16 | I22: -23 | J22: 82 | K22: -67 | L22: -95 | M22: -119 | N22: -142 | O22: -158 | P22: -175 | Q22: -82 | R22: -25 | S22: -36 | T22: -80 | U22: -62 | V22: -19 | W22: -20 | X22: -36 | Y22: -100 | Z22: -25 | AA22: =Z22*(AA9/Z9) -> -28.879973 | AB22: =AA22*(AB9/AA9) -> -32.629619 | AC22: =AB22*(AC9/AB9) -> -35.904879 | AD22: =AC22*(AD9/AC9) -> -38.695769 | AE22: =AD22*(AE9/AD9) -> -40.835973 | AF22: =AE22*(AF9/AE9) -> -42.818635
A23: Group | H23: =SUM(H19:H22) -> 545 | I23: =SUM(I19:I22) -> 613 | J23: =SUM(J19:J22) -> 666 | K23: =SUM(K19:K22) -> 561 | L23: =SUM(L19:L22) -> 568 | M23: =SUM(M19:M22) -> 790 | N23: =SUM(N19:N22) -> 934 | O23: =SUM(O19:O22) -> -158 | ... S23: =SUM(S19:S22) -> 2192 | T23: =SUM(T19,T20,T21,T22) -> 3023 | U23: =SUM(U19,U20,U21,U22) -> 3820 | V23: =SUM(V19,V20,V21,V22) -> 1686 | W23: =SUM(W19,W20,W21,W22) -> 1805 | X23: =SUM(X19,X20,X21,X22) -> 2408 | Y23: =SUM(Y19,Y20,Y21,Y22) -> 3166 | Z23: =SUM(Z19,Z20,Z21,Z22) -> 4119 | AA23: =SUM(AA19,AA20,AA21,AA22) -> 5217.0943 | ... AF23: =SUM(AF19,AF20,AF21,AF22) -> 8787.0465
A25: Adj. EBIT Margin
A26: Aerospace Propulsion | H26: =H19/H5 -> 0.11058545 | I26: =I19/I5 -> 0.1074869 | J26: =J19/J5 -> 0.1006376 | K26: =K19/K5 -> 0.11069981 | L26: =L19/L5 -> 0.11830835 | M26: =M19/M5 -> 0.1487725 | N26: =N19/N5 -> 0.15360457 | O26: =O19/O5 -> 0 | ... Z26: =Z19/Z5 -> 0.20648989 | AA26: ='Aerospace Propulsion Division'!AA20 -> 0.22566034 | AB26: ='Aerospace Propulsion Division'!AB20 -> 0.22591154 | AC26: ='Aerospace Propulsion Division'!AC20 -> 0.22728144 | AD26: ='Aerospace Propulsion Division'!AD20 -> 0.22926952 | AE26: ='Aerospace Propulsion Division'!AE20 -> 0.23121989 | AF26: ='Aerospace Propulsion Division'!AF20 -> 0.23519712
A27: Equipment & Defense | T27: =T20/T6 -> 0.12490557 | U27: =U20/U6 -> 0.13061798 | V27: =V20/V6 -> 0.099666328 | W27: =W20/W6 -> 0.1027668 | X27: =X20/X6 -> 0.11599204 | Y27: =Y20/Y6 -> 0.1122807 | Z27: =Z20/Z6 -> 0.12224524 | AA27: ='Equipment and Defense'!AA15 -> 0.12744534 | AB27: ='Equipment and Defense'!AB15 -> 0.13894585 | AC27: ='Equipment and Defense'!AC15 -> 0.14359731 | AD27: ='Equipment and Defense'!AD15 -> 0.14732483 | AE27: ='Equipment and Defense'!AE15 -> 0.14909582 | AF27: ='Equipment and Defense'!AF15 -> 0.15101968
A28: Aircraft Interiors | T28: =T21/T7 -> 0.032258065 | U28: =U21/U7 -> 0.056609455 | V28: =V21/V7 -> -0.090530697 | W28: =W21/W7 -> -0.11322034 | X28: =X21/X7 -> -0.070778564 | Y28: =Y21/Y7 -> -0.046830844 | Z28: =Z21/Z7 -> 0.0088903523 | AA28: ='Aircraft Interiors Division'!O20 -> 0.031161559 | AB28: ='Aircraft Interiors Division'!P20 -> 0.053006815 | AC28: ='Aircraft Interiors Division'!Q20 -> 0.074827367 | AD28: ='Aircraft Interiors Division'!R20 -> 0.089707897 | AE28: ='Aircraft Interiors Division'!S20 -> 0.093556118 | AF28: ='Aircraft Interiors Division'!T20 -> 0.093984998
A29: Group | H29: =H23/H9 -> 0.048106629 | I29: =I23/I9 -> 0.059968695 | J29: =J23/J9 -> 0.064478652 | K29: =K23/K9 -> 0.053694487 | L29: =L23/L9 -> 0.052788104 | M29: =M23/M9 -> 0.067314247 | N29: =N23/N9 -> 0.068879056 | O29: =O23/O9 -> -0.011000487 | ... AF29: =AF23/AF9 -> 0.1878093
A31: Adj. EBIT growth
A32: Aerospace Propulsion | I32: =I19/H19-1 -> 0.13368984 | J32: =J19/I19-1 -> -0.081761006 | K32: =K19/J19-1 -> 0.075342466 | L32: =L19/K19-1 -> 0.055732484 | M32: =M19/L19-1 -> 0.37104072 | N32: =N19/M19-1 -> 0.18371837 | O32: =O19/N19-1 -> -1 | P32: =P19/O19-1 -> #DIV/0! | ... AF32: =AF19/AE19-1 -> 0.073850922
A33: Equipment & Defense | U33: =U20/T20-1 -> 0.21875 | V33: =V20/U20-1 -> -0.43176179 | W33: =W20/V20-1 -> -0.053857351 | X33: =X20/W20-1 -> 0.34461538 | Y33: =Y20/X20-1 -> 0.13501144 | Z33: =Z20/Y20-1 -> 0.30846774 | AA33: =AA20/Z20-1 -> 0.20654126 | AB33: =AB20/AA20-1 -> 0.24689236 | ... AF33: =AF20/AE20-1 -> 0.057927884
A34: Aircraft Interiors | U34: =U21/T21-1 -> 1.3209877 | V34: =V21/U21-1 -> -1.9255319 | W34: =W21/V21-1 -> -0.040229885 | X34: =-(X21/W21-1) -> 0.16167665 | Y34: =-(Y21/X21-1) -> 0.17142857 | Z34: =-(Z21/Y21-1) -> 1.2327586 | AA34: =(AA21/Z21-1) -> 2.9515858 | AB34: =AB21/AA21-1 -> 0.87952118 | AC34: =AC21/AB21-1 -> 0.54280242 | AD34: =AD21/AC21-1 -> 0.29666061 | AE34: =AE21/AD21-1 -> 0.076656091 | AF34: =AF21/AE21-1 -> 0.033101997
A35: Group | I35: =I23/H23-1 -> 0.12477064 | J35: =J23/I23-1 -> 0.086460033 | K35: =K23/J23-1 -> -0.15765766 | L35: =L23/K23-1 -> 0.012477718 | M35: =M23/L23-1 -> 0.39084507 | N35: =N23/M23-1 -> 0.18227848 | O35: =O23/N23-1 -> -1.1691649 | P35: =P23/O23-1 -> 0.10759494 | ... AF35: =AF23/AE23-1 -> 0.066916368
A38: Income Statement (consolidated) | B38: 2000 | C38: 2001 | D38: 2002 | E38: 2003 | F38: 2004 | G38: 2005 | H38: 2006 | I38: 2007 | J38: 2008 | K38: 2009 | L38: 2010 | M38: 2011 | N38: 2012 | O38: 2013 | P38: 2014 | Q38: 2015 | R38: 2016 | S38: 2017 | T38: 2018 | U38: 2019 | V38: 2020 | W38: 2021 | X38: 2022 | Y38: 2023 | Z38: 2024 | AA38: =Z38+1 -> 2025 | AB38: =AA38+1 -> 2026 | AC38: =AB38+1 -> 2027 | AD38: =AC38+1 -> 2028 | AE38: =AD38+1 -> 2029 | AF38: =AE38+1 -> 2030
A39: Adjusted Revenues | H39: =H9 -> 11329 | I39: =I9 -> 10222 | J39: =J9 -> 10329 | K39: =K9 -> 10448 | L39: =L9 -> 10760 | M39: =M9 -> 11736 | N39: =N9 -> 13560 | O39: =O9 -> 14363 | ... AF39: =AF9 -> 46787.067
A40: Adjustments | L40: 268 | M40: -78 | N40: 55 | O40: 127 | P40: -311 | Q40: -1192 | R40: 701 | S40: 423 | T40: -25 | U40: 458 | V40: 133 | W40: -124 | X40: 488 | Y40: 452 | Z40: 399 | AA40: 0 | AB40: =AA40 -> 0 | AC40: =AB40 -> 0 | AD40: =AC40 -> 0 | AE40: =AD40 -> 0 | AF40: =AE40 -> 0
A41: Sales (Reported) | H41: 10841 | I41: 9714 | J41: 10281 | K41: 10559 | L41: 11028 | M41: 11658 | N41: 13615 | O41: 14490 | P41: 15044 | Q41: 16222 | R41: 16482 | S41: 16376 | T41: 21025 | U41: 25098 | V41: 16631 | W41: 15133 | X41: 19523 | Y41: 23651 | Z41: 27716 | AA41: ='Income Statement'!AA9 -> 31556.569 | AB41: ='Income Statement'!AB9 -> 35653.732 | AC41: ='Income Statement'!AC9 -> 39232.543 | AD41: ='Income Statement'!AD9 -> 42282.093 | AE41: ='Income Statement'!AE9 -> 44620.651 | AF41: ='Income Statement'!AF9 -> 46787.067
A42: growth | I42: =I41/H41-1 -> -0.1039572 | J42: =J41/I41-1 -> 0.058369364 | K42: =K41/J41-1 -> 0.027040171 | L42: =L41/K41-1 -> 0.044417085 | M42: =M41/L41-1 -> 0.057127312 | N42: =N41/M41-1 -> 0.16786756 | O42: =O41/N41-1 -> 0.064267352 | P42: =P41/O41-1 -> 0.038233264 | ... AF42: =AF41/AE41-1 -> 0.048551861
A43: Other Income | H43: 74 | I43: 66 | J43: 127 | K43: 156 | L43: 200 | M43: 216 | N43: 209 | O43: 264 | P43: 291 | Q43: 285 | R43: 277 | S43: 280 | T43: 321 | U43: 297 | V43: 267 | W43: 373 | X43: 440 | Y43: 474 | Z43: 438 | AA43: =AA44*AA41 -> 498.69307 | AB43: =AB44*AB41 -> 563.44114 | AC43: =AC44*AC41 -> 619.99762 | AD43: =AD44*AD41 -> 668.19009 | AE43: =AE44*AE41 -> 705.14667 | AF43: =AF44*AF41 -> 739.38285
A44: as a % of sales | H44: =H43/H$41 -> 0.0068259386 | I44: =I43/I$41 -> 0.0067943175 | J44: =J43/J$41 -> 0.012352884 | K44: =K43/K$41 -> 0.014774126 | L44: =L43/L$41 -> 0.018135655 | M44: =M43/M$41 -> 0.018528049 | N44: =N43/N$41 -> 0.015350716 | O44: =O43/O$41 -> 0.018219462 | ... Z44: =Z43/Z$41 -> 0.015803146 | AA44: =Z44 -> 0.015803146 | AB44: =AA44 -> 0.015803146 | AC44: =AB44 -> 0.015803146 | AD44: =AC44 -> 0.015803146 | AE44: =AD44 -> 0.015803146 | AF44: =AE44 -> 0.015803146
A45: Changes in Inventories of finished goods and Work-in-progress | H45: 360 | I45: 316 | J45: 276 | K45: -268 | L45: -43 | M45: 125 | N45: 340 | O45: -32 | P45: 255 | Q45: 257 | R45: 308 | S45: 195 | T45: 3 | U45: 453 | V45: -865 | W45: -199 | X45: 1204 | Y45: 1000 | Z45: 989 | AA45: =AA46*AA$41 -> 1126.0444 | AB45: =AB46*AB$41 -> 1272.2449 | AC45: =AC46*AC$41 -> 1399.949 | AD45: =AD46*AD$41 -> 1508.7671 | AE45: =AE46*AE$41 -> 1592.2147 | AF45: =AF46*AF$41 -> 1669.5197
A46: as a % of sales | H46: =H45/H$41 -> 0.033207269 | I46: =I45/I$41 -> 0.032530369 | J46: =J45/J$41 -> 0.026845638 | K46: =K45/K$41 -> -0.025381191 | L46: =L45/L$41 -> -0.0038991658 | M46: =M45/M$41 -> 0.010722251 | N46: =N45/N$41 -> 0.024972457 | O46: =O45/O$41 -> -0.0022084196 | ... Z46: =Z45/Z$41 -> 0.03568336 | AA46: =Z46 -> 0.03568336 | AB46: =AA46 -> 0.03568336 | AC46: =AB46 -> 0.03568336 | AD46: =AC46 -> 0.03568336 | AE46: =AD46 -> 0.03568336 | AF46: =AE46 -> 0.03568336
A47: Capitalised production | H47: 350 | I47: 277 | J47: 298 | K47: 242 | L47: 243 | M47: 371 | N47: 642 | O47: 911 | P47: 998 | Q47: 946 | R47: 624 | S47: 522 | T47: 447 | U47: 438 | V47: 329 | W47: 372 | X47: 382 | Y47: 480 | Z47: 526 | AA47: =AA48*AA$41 -> 598.88711 | AB47: =AB48*AB$41 -> 676.64392 | AC47: =AC48*AC$41 -> 744.56335 | AD47: =AD48*AD$41 -> 802.43833 | AE47: =AE48*AE$41 -> 846.81997 | AF47: =AF48*AF$41 -> 887.93466
A48: as a % of sales | H48: =H47/H$41 -> 0.032284845 | I48: =I47/I$41 -> 0.028515545 | J48: =J47/J$41 -> 0.028985507 | K48: =K47/K$41 -> 0.022918837 | L48: =L47/L$41 -> 0.02203482 | M48: =M47/M$41 -> 0.03182364 | N48: =N47/N$41 -> 0.047153874 | O48: =O47/O$41 -> 0.062870945 | ... Z48: =Z47/Z$41 -> 0.018978208 | AA48: =Z48 -> 0.018978208 | AB48: =AA48 -> 0.018978208 | AC48: =AB48 -> 0.018978208 | AD48: =AC48 -> 0.018978208 | AE48: =AD48 -> 0.018978208 | AF48: =AE48 -> 0.018978208
A49: Raw materials and Consumables used | H49: -7341 | I49: -6098 | J49: -6475 | K49: -5948 | L49: -6254 | M49: -6834 | N49: -8160 | O49: -8648 | P49: -9048 | Q49: -9275 | R49: -9340 | S49: -9449 | T49: -12440 | U49: -14448 | V49: -8450 | W49: -7999 | X49: -11724 | Y49: -14072 | Z49: -15960 | AA49: =AA50*AA$41 -> -18171.556 | AB49: =AB50*AB$41 -> -20530.869 | AC49: =AC50*AC$41 -> -22591.694 | AD49: =AD50*AD$41 -> -24347.749 | AE49: =AE50*AE$41 -> -25694.386 | AF49: =AF50*AF$41 -> -26941.896
A50: as a % of sales | H50: =H49/H$41 -> -0.67715155 | I50: =I49/I$41 -> -0.62775376 | J50: =J49/J$41 -> -0.62980255 | K50: =K49/K$41 -> -0.56331092 | L50: =L49/L$41 -> -0.56710192 | M50: =M49/M$41 -> -0.5862069 | N50: =N49/N$41 -> -0.59933896 | O50: =O49/O$41 -> -0.5968254 | ... Z50: =Z49/Z$41 -> -0.57584067 | AA50: =Z50 -> -0.57584067 | AB50: =AA50 -> -0.57584067 | AC50: =AB50 -> -0.57584067 | AD50: =AC50 -> -0.57584067 | AE50: =AD50 -> -0.57584067 | AF50: =AE50 -> -0.57584067
A51: Personnel Costs | H51: -3170 | I51: -3032 | J51: -3133 | K51: -3276 | L51: -3459 | M51: -3808 | N51: -4205 | O51: -4506 | P51: -4744 | Q51: -4524 | R51: -4406 | S51: -4353 | T51: -5665 | U51: -6349 | V51: -5028 | W51: -4919 | X51: -5792 | Y51: -6767 | Z51: -7801 | AA51: =AA23-SUM(AA41+AA43+AA45+AA47+AA49+AA53+AA55+AA58+AA60+AA62) -> -8430.9281 | AB51: =AB23-SUM(AB41+AB43+AB45+AB47+AB49+AB53+AB55+AB58+AB60+AB62) -> -9276.6565 | AC51: =AC23-SUM(AC41+AC43+AC45+AC47+AC49+AC53+AC55+AC58+AC60+AC62) -> -9987.8122 | AD51: =AD23-SUM(AD41+AD43+AD45+AD47+AD49+AD53+AD55+AD58+AD60+AD62) -> -10584.123 | AE51: =AE23-SUM(AE41+AE43+AE45+AE47+AE49+AE53+AE55+AE58+AE60+AE62) -> -11062.23 | AF51: =AF23-SUM(AF41+AF43+AF45+AF47+AF49+AF53+AF55+AF58+AF60+AF62) -> -11448.073
A52: as a % of sales | H52: =H51/H$41 -> -0.29240845 | I52: =I51/I$41 -> -0.31212683 | J52: =J51/J$41 -> -0.30473689 | K52: =K51/K$41 -> -0.31025665 | L52: =L51/L$41 -> -0.31365615 | M52: =M51/M$41 -> -0.32664265 | N52: =N51/N$41 -> -0.30885053 | O52: =O51/O$41 -> -0.31097308 | P52: =P51/P41 -> -0.31534166 | Q52: =Q51/Q41 -> -0.27888053 | R52: =R51/R41 -> -0.26732193 | S52: =S51/S41 -> -0.26581583 | T52: =T51/T41 -> -0.26944114 | U52: =U51/U41 -> -0.25296836 | V52: =V51/V41 -> -0.30232698 | W52: =W51/W41 -> -0.32505121 | ... AF52: =AF51/AF41 -> -0.24468456
A53: Taxes | H53: -229 | I53: -207 | J53: -221 | K53: -238 | L53: -217 | M53: -235 | N53: -270 | O53: -276 | P53: -275 | Q53: -277 | R53: -286 | S53: -284 | T53: -295 | U53: -388 | V53: -326 | W53: -257 | X53: -290 | Y53: -308 | Z53: -337 | AA53: =AA54*AA$41 -> -383.69763 | AB53: =AB54*AB$41 -> -433.51521 | AC53: =AC54*AC$41 -> -477.03013 | AD53: =AD54*AD$41 -> -514.10973 | AE53: =AE54*AE$41 -> -542.54436 | AF53: =AF54*AF$41 -> -568.88589
A54: as a % of sales | H54: =H53/H$41 -> -0.021123513 | I54: =I53/I$41 -> -0.02130945 | J54: =J53/J$41 -> -0.021495963 | K54: =K53/K$41 -> -0.022540013 | L54: =L53/L$41 -> -0.019677185 | M54: =M53/M$41 -> -0.020157832 | N54: =N53/N$41 -> -0.019831069 | O54: =O53/O$41 -> -0.019047619 | ... Z54: =Z53/Z$41 -> -0.012159042 | AA54: =Z54 -> -0.012159042 | AB54: =AA54 -> -0.012159042 | AC54: =AB54 -> -0.012159042 | AD54: =AC54 -> -0.012159042 | AE54: =AD54 -> -0.012159042 | AF54: =AE54 -> -0.012159042
A55: Depreciation, Amortization and increase in provision (net of use) | H55: =-583-284 -> -867 | I55: -718 | J55: -595 | K55: -606 | L55: -575 | M55: -579 | N55: -854 | O55: -790 | P55: -894 | Q55: -763 | R55: -634 | S55: -1012 | T55: -1176 | U55: -1600 | V55: -1212 | W55: -1509 | X55: -1174 | Y55: -1282 | Z55: -1578 | AA55: =AA56*AA$41 -> -1796.6613 | AB55: =AB56*AB$41 -> -2029.9318 | AC55: =AC56*AC$41 -> -2233.69 | AD55: =AD56*AD$41 -> -2407.315 | AE55: =AE56*AE$41 -> -2540.4599 | AF55: =AF56*AF$41 -> -2663.804
A56: as a % of sales | H56: =H55/H$41 -> -0.079974172 | I56: =I55/I$41 -> -0.073913939 | J56: =J55/J$41 -> -0.057873748 | K56: =K55/K$41 -> -0.057391798 | L56: =L55/L$41 -> -0.052140007 | M56: =M55/M$41 -> -0.049665466 | N56: =N55/N$41 -> -0.062724936 | O56: =O55/O$41 -> -0.054520359 | ... Z56: =Z55/Z$41 -> -0.056934623 | AA56: =Z56 -> -0.056934623 | AB56: =AA56 -> -0.056934623 | AC56: =AB56 -> -0.056934623 | AD56: =AC56 -> -0.056934623 | AE56: =AD56 -> -0.056934623 | AF56: =AE56 -> -0.056934623
A57: Of which provisions | R57: -92 | S57: 224 | T57: -33 | U57: 137 | V57: -235 | W57: 129 | X57: -199 | Y57: -54 | Z57: 172 | AA57: =AA55+'Cashflow Statement'!AA5+'Cashflow Statement'!AA7 -> -195.83381 | AB57: =AB55+'Cashflow Statement'!AB5+'Cashflow Statement'!AB7 -> -151.0608 | AC57: =AC55+'Cashflow Statement'!AC5+'Cashflow Statement'!AC7 -> -244.6889 | AD57: =AD55+'Cashflow Statement'!AD5+'Cashflow Statement'!AD7 -> -263.7086 | AE57: =AE55+'Cashflow Statement'!AE5+'Cashflow Statement'!AE7 -> -278.29392 | AF57: =AF55+'Cashflow Statement'!AF5+'Cashflow Statement'!AF7 -> -291.80561
A58: Asset impairment | H58: -157 | I58: -178 | J58: -40 | K58: -34 | L58: 7 | M58: -65 | N58: -29 | O58: -82 | P58: -59 | Q58: -179 | R58: -237 | S58: -60 | T58: 62 | U58: 57 | V58: -149 | W58: 78 | X58: -252 | Y58: -50 | Z58: 18 | AA58: =AA59*AA$41 -> 20.494236 | AB58: =AB59*AB$41 -> 23.155115 | AC58: =AC59*AC$41 -> 25.479354 | AD58: =AD59*AD$41 -> 27.459867 | AE58: =AE59*AE$41 -> 28.97863 | AF58: =AF59*AF$41 -> 30.385597
A59: as a % of sales | H59: =H58/H$41 -> -0.014482059 | I59: =I58/I$41 -> -0.018324068 | J59: =J58/J$41 -> -0.0038906721 | K59: =K58/K$41 -> -0.0032200019 | L59: =L58/L$41 -> 0.00063474791 | M59: =M58/M$41 -> -0.0055755704 | N59: =N58/N$41 -> -0.0021300037 | O59: =O58/O$41 -> -0.0056590752 | ... Z59: =Z58/Z$41 -> 0.00064944436 | AA59: =Z59 -> 0.00064944436 | AB59: =AA59 -> 0.00064944436 | AC59: =AB59 -> 0.00064944436 | AD59: =AC59 -> 0.00064944436 | AE59: =AD59 -> 0.00064944436 | AF59: =AE59 -> 0.00064944436
A60: Other recurring operating income and expense | H60: -47 | I60: -11 | J60: 85 | K60: 42 | L60: 21 | M60: 15 | N60: -45 | O60: -36 | P60: -113 | Q60: 118 | R60: 115 | S60: 159 | T60: -191 | U60: 102 | V60: 148 | W60: 156 | X60: 103 | Y60: 84 | Z60: 39 | AA60: =AA61*AA$41 -> 44.404177 | AB60: =AB61*AB$41 -> 50.169416 | AC60: =AC61*AC$41 -> 55.205267 | AD60: =AD61*AD$41 -> 59.496378 | AE60: =AE61*AE$41 -> 62.787032 | AF60: =AF61*AF$41 -> 65.83546
A61: as a % of sales | H61: =H60/H$41 -> -0.0043353934 | I61: =I60/I$41 -> -0.0011323862 | J61: =J60/J$41 -> 0.0082676782 | K61: =K60/K$41 -> 0.0039776494 | L61: =L60/L$41 -> 0.0019042437 | M61: =M60/M$41 -> 0.0012866701 | N61: =N60/N$41 -> -0.0033051781 | O61: =O60/O$41 -> -0.002484472 | ... Z61: =Z60/Z$41 -> 0.0014071295 | AA61: =Z61 -> 0.0014071295 | AB61: =AA61 -> 0.0014071295 | AC61: =AB61 -> 0.0014071295 | AD61: =AC61 -> 0.0014071295 | AE61: =AD61 -> 0.0014071295 | AF61: =AE61 -> 0.0014071295
A62: Share in profit from joint ventures | P62: 45 | Q62: 44 | R62: 87 | S62: 144 | T62: 189 | U62: 164 | V62: 48 | W62: 40 | X62: 73 | Y62: 99 | Z62: 136 | AA62: =AA63*AA$41 -> 154.84534 | AB62: =AB63*AB$41 -> 174.94976 | AC62: =AC63*AC$41 -> 192.51068 | AD62: =AD63*AD$41 -> 207.47455 | AE62: =AE63*AE$41 -> 218.94965 | AF62: =AF63*AF$41 -> 229.58006
A63: as a % of sales | P63: =P62/P$41 -> 0.0029912257 | Q63: =Q62/Q$41 -> 0.0027123659 | R63: =R62/R$41 -> 0.0052784856 | S63: =S62/S$41 -> 0.0087933561 | T63: =T62/T$41 -> 0.0089892985 | U63: =U62/U$41 -> 0.0065343852 | V63: =V62/V$41 -> 0.0028861764 | W63: =W62/W$41 -> 0.00264323 | ... Z63: =Z62/Z$41 -> 0.004906913 | AA63: =Z63 -> 0.004906913 | AB63: =AA63 -> 0.004906913 | AC63: =AB63 -> 0.004906913 | AD63: =AC63 -> 0.004906913 | AE63: =AD63 -> 0.004906913 | AF63: =AE63 -> 0.004906913
A64: Recurring operating Income (EBITA) | H64: =H41+H43+H45+H47+H49+H51+H53+H55+H58+H60 -> -186 | I64: =I41+I43+I45+I47+I49+I51+I53+I55+I58+I60 -> 129 | J64: =J41+J43+J45+J47+J49+J51+J53+J55+J58+J60 -> 603 | K64: =K41+K43+K45+K47+K49+K51+K53+K55+K58+K60 -> 629 | L64: =L41+L43+L45+L47+L49+L51+L53+L55+L58+L60 -> 951 | M64: =M41+M43+M45+M47+M49+M51+M53+M55+M58+M60 -> 864 | N64: =N41+N43+N45+N47+N49+N51+N53+N55+N58+N60 -> 1243 | O64: =O41+O43+O45+O47+O49+O51+O53+O55+O58+O60 -> 1295 | P64: =P41+P43+P45+P47+P49+P51+P53+P55+P58+P60+P62 -> 1500 | Q64: =Q41+Q43+Q45+Q47+Q49+Q51+Q53+Q55+Q58+Q60+Q62 -> 2854 | R64: =R41+R43+R45+R47+R49+R51+R53+R55+R58+R60+R62 -> 2990 | S64: =S41+S43+S45+S47+S49+S51+S53+S55+S58+S60+S62 -> 2518 | T64: =T41+T43+T45+T47+T49+T51+T53+T55+T58+T60+T62 -> 2280 | U64: =U41+U43+U45+U47+U49+U51+U53+U55+U58+U60+U62 -> 3824 | V64: =V41+V43+V45+V47+V49+V51+V53+V55+V58+V60+V62 -> 1393 | W64: =W41+W43+W45+W47+W49+W51+W53+W55+W58+W60+W62 -> 1269 | ... AF64: =AF41+AF43+AF45+AF47+AF49+AF51+AF53+AF55+AF58+AF60+AF62 -> 8787.0465
A65: EBITA Margin | Q65: =Q64/Q$41 -> 0.17593392 | R65: =R64/R$41 -> 0.18141002 | S65: =S64/S$41 -> 0.1537616 | T65: =T64/T$41 -> 0.10844233 | U65: =U64/U$41 -> 0.15236274 | V65: =V64/V$41 -> 0.083759245 | W65: =W64/W$41 -> 0.083856473 | X65: =X64/X$41 -> 0.12769554 | ... AF65: =AF64/AF$41 -> 0.1878093
A66: Remeasurement of revenue | R66: -722 | S66: -463 | T66: 11 | U66: -449 | V66: -134 | W66: 136 | X66: -478 | Y66: -455 | Z66: -404
A67: Deferred hedging gain/loss | R67: 10 | S67: 7 | T67: -2 | U67: -1 | V67: 5 | W67: 5 | X67: 3 | Y67: -7 | Z67: 10
A68: Amortization of intangible assets from meger | R68: 70 | S68: 67 | T68: 56 | U68: 51 | V68: 46 | W68: 39 | X68: 38 | Y68: 38 | Z68: 41
A69: PPA Impacts/Other Business combinations | R69: 56 | S69: 63 | T69: 678 | U69: 395 | V69: 376 | W69: 356 | X69: 352 | Y69: 281 | Z69: 286
A70: Adj. Recurring operating income (Adj EBITA) | R70: =R64+SUM(R66:R69) -> 2404 | S70: =S64+SUM(S66:S69) -> 2192 | T70: =T64+SUM(T66:T69) -> 3023 | U70: =U64+SUM(U66:U69) -> 3820 | V70: =V64+SUM(V66:V69) -> 1686 | W70: =W64+SUM(W66:W69) -> 1805 | X70: =X64+SUM(X66:X69) -> 2408 | Y70: =Y64+SUM(Y66:Y69) -> 3166 | ... AF70: =AF64+SUM(AF66:AF69) -> 8787.0465
A71: Adj. EBITA Margin | Q71: =Q70/Q39 -> 0 | R71: =R70/R39 -> 0.15233509 | S71: =S70/S39 -> 0.13740362 | T71: =T70/T39 -> 0.14361045 | U71: =U70/U39 -> 0.15503247 | V71: =V70/V39 -> 0.10219421 | W71: =W70/W39 -> 0.11830635 | X71: =X70/X39 -> 0.12650381 | ... AF71: =AF70/AF39 -> 0.1878093
A72: other non-recurring operating income and expenses | K72: -35 | L72: -13 | M72: -29 | N72: -56 | O72: 185 | P72: -107 | Q72: -778 | R72: 349 | S72: -90 | T72: -115 | U72: 13 | V72: -466 | W72: -405 | X72: -450 | Y72: -511 | Z72: 6 | AA72: 0 | AB72: 0 | AC72: 0 | AD72: 0 | AE72: 0 | AF72: 0
A73: Reported EBIT | P73: =P64+P72 -> 1393 | Q73: =Q64+Q72 -> 2076 | R73: =R64+R72 -> 3339 | S73: =S64+S72 -> 2428 | T73: =T64+T72 -> 2165 | U73: =U64+U72 -> 3837 | V73: =V64+V72 -> 927 | W73: =W64+W72 -> 864 | ... AF73: =AF64+AF72 -> 8787.0465
A74: Adj. EBIT | R74: =R70+R72 -> 2753 | S74: =S70+S72 -> 2102 | T74: =T70+T72 -> 2908 | U74: =U70+U72 -> 3833 | V74: =V70+V72 -> 1220 | W74: =W70+W72 -> 1400 | X74: =X70+X72 -> 1958 | Y74: =Y70+Y72 -> 2655 | ... AF74: =AF70+AF72 -> 8787.0465
A75: Financing expense | H75: =H76+H77+H78 -> 312 | I75: =I76+I77+I78 -> 34 | J75: =J76+J77+J78 -> -716 | K75: =K76+K77+K78 -> 296 | L75: =L76+L77+L78 -> -703 | M75: =M76+M77+M78 -> -150 | N75: =N76+N77+N78 -> 533 | O75: =SUM(O76:O78) -> 439 | P75: =SUM(P76:P78) -> -1771 | Q75: =SUM(Q76:Q78) -> -3408 | R75: =SUM(R76:R78) -> -1052 | S75: =SUM(S76:S78) -> 3012 | T75: =SUM(T76:T78) -> -476 | U75: =SUM(U76:U78) -> -363 | V75: =SUM(V76:V78) -> -357 | ... AF75: =SUM(AF76:AF78) -> 251.729
A76: Net Interest expense | H76: -22 | I76: -10 | J76: -19 | K76: -38 | L76: -36 | M76: -42 | N76: -54 | O76: -42 | P76: -42 | Q76: -29 | R76: -51 | S76: -57 | T76: -67 | U76: -33 | V76: -58 | W76: -85 | X76: -56 | Y76: 112 | Z76: 157 | AA76: =AA120 -> 113.985 | AB76: =AB120 -> 128.5246 | AC76: =AC120 -> 148.70105 | AD76: =AD120 -> 175.34642 | AE76: =AE120 -> 204.65438 | AF76: =AF120 -> 251.729
A77: FX | K77: 479 | L77: -531 | M77: 19 | N77: 709 | O77: 551 | P77: -1654 | Q77: -3270 | R77: -943 | S77: 3071 | T77: -351 | U77: -283 | V77: -257 | W77: -497 | X77: -5072 | Y77: 1850 | Z77: -5180
A78: Other | H78: 334 | I78: 44 | J78: -697 | K78: -145 | L78: -136 | M78: -127 | N78: -122 | O78: -70 | P78: -75 | Q78: -109 | R78: -58 | S78: -2 | T78: -58 | U78: -47 | V78: -42 | W78: -14 | X78: -35 | Y78: -4 | Z78: -28
A79: Adj. Financial expense | R79: -144 | S79: 7 | T79: -211 | U79: -89 | V79: -7 | W79: =W75+SUM(W80:W81) -> -204 | X79: =X75+SUM(X80:X81) -> -186 | Y79: =Y75+SUM(Y80:Y81) -> 174 | Z79: =Z75+SUM(Z80:Z81) -> 23 | AA79: =AA75+SUM(AA80:AA81) -> 113.985 | AB79: =AB75+SUM(AB80:AB81) -> 128.5246 | AC79: =AC75+SUM(AC80:AC81) -> 148.70105 | AD79: =AD75+SUM(AD80:AD81) -> 175.34642 | ... AF79: =AF75+SUM(AF80:AF81) -> 251.729
A80: Remeasurement of revenue | W80: -136 | X80: 478 | Y80: 455 | Z80: 404
A81: Deferred hedging gain/loss | W81: 528 | X81: 4499 | Y81: -2239 | Z81: 4670
A82: check
A83: Share in profit from associates | H83: 4 | I83: 4 | J83: 10 | K83: 3 | L83: 9 | M83: 10 | N83: 19 | O83: 15 | P83: 18 | Q83: 0 | R83: 0 | S83: 0 | T83: 0 | U83: 0 | V83: 0 | W83: 0 | X83: =W83*1.05 -> 0 | Y83: 0 | Z83: 0 | AA83: =Z83*1.05 -> 0 | AB83: =AA83*1.05 -> 0 | AC83: =AB83*1.05 -> 0 | AD83: =AC83*1.05 -> 0 | AE83: =AD83*1.05 -> 0 | AF83: =AE83*1.05 -> 0
A84: PBT | H84: =H64+H72+H75 -> 126 | I84: =I64+I72+I75 -> 163 | J84: =J64+J72+J75 -> -113 | K84: =K64+K72+K75 -> 890 | L84: =L64+L72+L75 -> 235 | M84: =M64+M72+M75 -> 685 | N84: =N64+N72+N75 -> 1720 | O84: =O64+O72+O75 -> 1919 | ... AF84: =AF64+AF72+AF75 -> 9038.7755
A85: Adj. PBT | R85: =R70+R72+R79 -> 2609 | S85: =S70+S72+S79 -> 2109 | T85: =T70+T72+T79 -> 2697 | U85: =U70+U72+U79 -> 3744 | V85: =V70+V72+V79 -> 1213 | W85: =W70+W72+W79 -> 1196 | X85: =X70+X72+X79 -> 1772 | Y85: =Y70+Y72+Y79 -> 2829 | ... AF85: =AF70+AF72+AF79 -> 9038.7755
A86: Tax benefit (expense) | H86: -109 | I86: -25 | J86: 142 | K86: -235 | L86: -14 | M86: -201 | N86: -433 | O86: -650 | P86: 292 | Q86: 505 | R86: -398 | S86: -1660 | T86: -348 | U86: -962 | V86: -184 | W86: -200 | X86: 694 | Y86: -1236 | Z86: 284 | AA86: =AA87*AA84 -> -1824.2953 | AB86: =AB87*AB84 -> -1888.4656 | AC86: =AC87*AC84 -> -1853.468 | AD86: =AD87*AD84 -> -2048.272 | AE86: =AE87*AE84 -> -2194.5514 | AF86: =AF87*AF84 -> -2350.0816
A87: Reported tax rate | H87: =H86/H84 -> -0.86507937 | I87: =I86/I84 -> -0.15337423 | J87: =J86/J84 -> -1.2566372 | K87: =K86/K84 -> -0.26404494 | L87: =L86/L84 -> -0.059574468 | M87: =M86/M84 -> -0.29343066 | N87: =N86/N84 -> -0.25174419 | O87: =O86/O84 -> -0.33871808 | P87: -0.25 | Q87: =P87 -> -0.25 | R87: =R86/R84 -> -0.17402711 | S87: =S86/S84 -> -0.30514706 | T87: =T86/T84 -> -0.20603908 | U87: =U86/U84 -> -0.27691422 | V87: =V86/V84 -> -0.32280702 | W87: =W86/W84 -> -0.74626866 | X87: =X86/X84 -> -0.2224359 | Y87: =Y86/Y84 -> -0.25988225 | Z87: =Z86/Z84 -> -0.330617 | AA87: -0.3422 | AB87: -0.3011 | AC87: -0.26 | AD87: -0.26 | AE87: -0.26 | AF87: -0.26
A88: Adj. Tax benefit (expense) | R88: =-498 -> -498 | S88: -485 | T88: -638 | U88: -1012 | V88: -334 | W88: =W86+SUM(W89:W90) -> -412 | X88: =X86+SUM(X89:X90) -> -557 | Y88: =Y86+SUM(Y89:Y90) -> -724 | Z88: =Z86+SUM(Z89:Z90) -> -987 | AA88: =AA85*AA91 -> -1705.9454 | AB88: =AB85*AB91 -> -1567.9721 | AC88: =AC85*AC91 -> -1782.1808 | AD88: =AD85*AD91 -> -1969.4923 | AE88: =AE85*AE91 -> -2110.1456 | AF88: =AF85*AF91 -> -2259.6939
A89: Remeasurement of revenue | W89: -138 | X89: -1163 | Y89: 581 | Z89: -1209
A90: Other | W90: =-11+-63 -> -74 | X90: =-10+-78 -> -88 | Y90: =-10+-59 -> -69 | Z90: =-11+-51 -> -62
A91: Adj. tax rate | R91: =R88/R85 -> -0.19087773 | S91: =S88/S85 -> -0.22996681 | T91: =T88/T85 -> -0.23655914 | U91: =U88/U85 -> -0.27029915 | V91: =V88/V85 -> -0.27535037 | W91: =W88/W85 -> -0.34448161 | X91: =X88/X85 -> -0.31433409 | Y91: =Y88/Y85 -> -0.25592082 | Z91: =Z88/Z85 -> -0.237946 | AA91: -0.32 | AB91: -0.25 | AC91: -0.25 | AD91: =AC91 -> -0.25 | AE91: =AD91 -> -0.25 | AF91: =AE91 -> -0.25
A92: Net Income (Reported) | H92: =H84+H86+H83 -> 21 | I92: =I84+I86+I83 -> 142 | J92: =J84+J86+J83 -> 39 | K92: =K84+K86+K83 -> 658 | L92: =L84+L86+L83 -> 230 | M92: =M84+M86+M83 -> 494 | N92: =N84+N86+N83 -> 1306 | O92: =O84+O86+O83 -> 1284 | P92: =P84+P86+P83 -> -68 | Q92: =Q84+Q86+Q83+421 -> -406 | R92: =R84+R86+R83 -> 1889 | S92: =S84+S86+S83 -> 3780 | T92: =T84+T86+T83 -> 1341 | U92: =U84+U86+U83 -> 2512 | V92: =V84+V86+V83 -> 386 | W92: =W84+W86+W83 -> 68 | X92: =X84+X86+X83 -> -2426 | Y92: =Y84+Y86+Y83 -> 3520 | ... AF92: =AF84+AF86+AF83 -> 6688.6938
A93: Adj. Net Income | R93: =R85+R88+R83 -> 2111 | S93: =S85+S88+S83 -> 1624 | T93: =T85+T88+T83 -> 2059 | U93: =U85+U88+U83 -> 2732 | V93: =V85+V88+V83 -> 879 | W93: =W85+W88+W83 -> 784 | X93: =X85+X88+X83 -> 1215 | Y93: =Y85+Y88+Y83 -> 2105 | ... AF93: =AF85+AF88+AF83 -> 6779.0816
A94: Net Income from discontinued operations | H94: 0 | I94: -96 | J94: -233 | K94: -4 | L94: -5 | M94: 3 | N94: 0 | O94: 0 | P94: 0 | Q94: 29 | R94: 74 | S94: 831 | T94: 0 | U94: 0 | V94: 0 | W94: 0 | X94: 0 | Y94: 0 | Z94: 0 | AA94: 0 | AB94: 0 | AC94: 0 | AD94: 0 | AE94: 0 | AF94: 0
A95: Non Controlling Interest | H95: -12 | I95: -7 | J95: -11 | K95: 13 | L95: 18 | M95: 19 | N95: 24 | O95: 29 | P95: 58 | Q95: 47 | R95: 55 | S95: 61 | T95: 58 | U95: 65 | V95: 34 | W95: 25 | X95: 33 | Y95: 76 | Z95: 92 | AA95: =AA39*AA96 -> 104.74832 | AB95: =AB39*AB96 -> 118.34837 | AC95: =AC39*AC96 -> 130.22781 | AD95: =AD39*AD96 -> 140.35043 | AE95: =AE39*AE96 -> 148.113 | AF95: =AF39*AF96 -> 155.30416
A96: as a % of sales | W96: =W95/W41 -> 0.0016520188 | X96: =X95/X41 -> 0.001690314 | Y96: =Y95/Y41 -> 0.0032133948 | Z96: =Z95/Z41 -> 0.0033193823 | AA96: =Z96 -> 0.0033193823 | AB96: =AA96 -> 0.0033193823 | AC96: =AB96 -> 0.0033193823 | AD96: =AC96 -> 0.0033193823 | AE96: =AD96 -> 0.0033193823 | AF96: =AE96 -> 0.0033193823
A97: Net Income attributable to owners of the parent | H97: =H92+H94-H95 -> 33 | I97: =I92+I94-I95 -> 53 | J97: =J92+J94-J95 -> -183 | K97: =K92+K94-K95 -> 641 | L97: =L92+L94-L95 -> 207 | M97: =M92+M94-M95 -> 478 | N97: =N92+N94-N95 -> 1282 | O97: =O92+O94-O95 -> 1255 | ... AF97: =AF92+AF94-AF95 -> 6533.3897
A98: Adj. Net Income attributable to owners of the parent | H98: =H93+H94-H95 -> 12 | I98: =I93+I94-I95 -> -89 | J98: =J93+J94-J95 -> -222 | K98: =K93+K94-K95 -> -17 | L98: =L93+L94-L95 -> -23 | M98: =M93+M94-M95 -> -16 | N98: =N93+N94-N95 -> -24 | O98: =O93+O94-O95 -> -29 | ... R98: =R93+R94-R95 -> 2130 | S98: =S93+S94-S95-1 -> 2393 | T98: =T93+T94-T95 -> 2001 | U98: =U93+U94-U95 -> 2667 | V98: =V93+V94-V95 -> 845 | W98: =W93+W94-W95 -> 759 | X98: =X93+X94-X95 -> 1182 | Y98: =Y93+Y94-Y95-1 -> 2028 | Z98: =Z93+Z94-Z95 -> 3069 | AA98: =AA93+AA94-AA95 -> 3520.3856 | AB98: =AB93+AB94-AB95 -> 4585.5679 | AC98: =AC93+AC94-AC95 -> 5216.3146 | AD98: =AD93+AD94-AD95 -> 5768.1265 | AE98: =AE93+AE94-AE95 -> 6182.3238 | AF98: =AF93+AF94-AF95 -> 6623.7774
A100: Reported EPS - Basic | H100: 0.02 | I100: 0.09 | J100: -0.51 | K100: 1.61 | L100: 0.52 | M100: 1.18 | N100: 3.09 | O100: =((O92-O95)/O116)*1000 -> 3.0147055 | P100: =((P92-P95)/P116)*1000 -> -0.30258395 | Q100: =((Q92-Q95)/Q116)*1000 -> -1.0848506 | R100: =((R92-R95)/R116)*1000 -> 4.405211 | S100: =((S92-S95)/S116)*1000 -> 9.0654021 | T100: =((T92-T95)/T116)*1000 -> 2.9774074 | U100: =((U92-U95)/U116)*1000 -> 5.694361 | V100: =((V92-V95)/V116)*1000 -> 0.82622178 | ... AF100: =((AF92-AF95)/AF116)*1000 -> 16.407198
A101: Reported EPS - Diluted | H101: 0.02 | I101: 0.09 | J101: -0.51 | K101: 1.6 | L101: 0.51 | M101: 1.18 | N101: 3.08 | O101: =((O92-O95)/O117)*1000 -> 3.0137463 | P101: =((P92-P95)/P117)*1000 -> -0.30258395 | Q101: =((Q92-Q95)/Q117)*1000 -> -1.0848506 | R101: =((R92-R95)/R117)*1000 -> 4.3293625 | S101: =((S92-S95)/S117)*1000 -> 8.9073951 | T101: =((T92-T95)/T117)*1000 -> 2.940397 | U101: =((U92-U95)/U117)*1000 -> 5.6255883 | V101: =((V92-V95)/V117)*1000 -> 0.79916361 | ... X101: =((X92-X95)/X117)*1000 -> -5.5866058 | Y101: =((Y92-Y95+36)/Y117)*1000 -> 8.0672538 | Z101: =(((Z92-Z95)/Z117)*1000)-0.01 -> -1.5953686 | AA101: =((AA92-AA95)/AA117)*1000 -> 8.1733407 | AB101: =((AB92-AB95)/AB117)*1000 -> 10.358435 | AC101: =((AC92-AC95)/AC117)*1000 -> 12.633206 | AD101: =((AD92-AD95)/AD117)*1000 -> 14.125356 | AE101: =((AE92-AE95)/AE117)*1000 -> 15.139745 | AF101: =((AF92-AF95)/AF117)*1000 -> 16.220922
A102: Continuing EPS - Basic | H102: 0.02 | I102: -0.24 | J102: -0.58 | K102: 1.62 | L102: 0.53 | M102: 1.17 | N102: 3.14 | O102: =((O92-O94-O95)/O116)*1000 -> 3.0147055 | P102: =((P92-P94-P95)/P116)*1000 -> -0.30258395 | Q102: =((Q92-Q94-Q95)/Q116)*1000 -> -1.1543002 | R102: =((R92-R94-R95)/R116)*1000 -> 4.2274653 | S102: =((S92-S94-S95)/S116)*1000 -> 7.0397637 | T102: =((T92-T94-T95)/T116)*1000 -> 2.9774074 | U102: =((U92-U94-U95)/U116)*1000 -> 5.694361 | V102: =((V92-V94-V95)/V116)*1000 -> 0.82622178 | ... AF102: =((AF92-AF94-AF95)/AF116)*1000 -> 16.407198
A103: Continuing EPS - Diluted | H103: 0.02 | I103: -0.24 | J103: -0.58 | K103: 1.61 | L103: 0.52 | M103: 1.17 | N103: 3.13 | O103: =((O92-O94-O95)/O117)*1000 -> 3.0137463 | P103: =((P92-P94-P95)/P117)*1000 -> -0.30258395 | Q103: =((Q92-Q94-Q95)/Q117)*1000 -> -1.1543002 | R103: =((R92-R94-R95)/R117)*1000 -> 4.1546772 | S103: =((S92-S94-S95)/S117)*1000 -> 6.9170629 | T103: =((T92-T94-T95)/T117)*1000 -> 2.940397 | U103: =((U92-U94-U95)/U117)*1000 -> 5.6255883 | V103: =((V92-V94-V95)/V117)*1000 -> 0.79916361 | ... X103: =((X92-X94-X95)/X117)*1000 -> -5.5866058 | Y103: =((Y92-Y94-Y95+36)/Y117)*1000 -> 8.0672538 | Z103: =(((Z92-Z94-Z95)/Z117)*1000)-0.01 -> -1.5953686 | AA103: =((AA92-AA94-AA95)/AA117)*1000 -> 8.1733407 | AB103: =((AB92-AB94-AB95)/AB117)*1000 -> 10.358435 | AC103: =((AC92-AC94-AC95)/AC117)*1000 -> 12.633206 | AD103: =((AD92-AD94-AD95)/AD117)*1000 -> 14.125356 | AE103: =((AE92-AE94-AE95)/AE117)*1000 -> 15.139745 | AF103: =((AF92-AF94-AF95)/AF117)*1000 -> 16.220922
A104: Adj. Reported EPS - Basic | Q104: =(Q93-Q95)/Q116*1000 -> -0.11255624 | R104: =(R93-R95)/R116*1000 -> 4.9384481 | S104: =(S93-S95-S94)/S116*1000 -> 1.7843168 | T104: =(T93-T95-20)/T116*1000 -> 4.5972284 | U104: =(U93-U95-2)/U116*1000 -> 6.2016641 | V104: =(V93-V95)/V116*1000 -> 1.9834017 | W104: =(W93-W95)/W116*1000 -> 1.778974 | X104: =(X93-X95-4)/X116*1000 -> 2.760847 | Y104: =(Y93-Y95)/Y116*1000 -> 4.856443 | Z104: =(Z93-Z95)/Z116*1000 -> 7.374753 | AA104: =(AA93-AA95)/AA116*1000 -> 8.5516241 | AB104: =(AB93-AB95)/AB116*1000 -> 11.261879 | AC104: =(AC93-AC95)/AC116*1000 -> 12.953693 | AD104: =(AD93-AD95)/AD116*1000 -> 14.485405 | AE104: =(AE93-AE95)/AE116*1000 -> 15.525572 | AF104: =(AF93-AF95)/AF116*1000 -> 16.634187
A105: Adj. Reported EPS - Diluted | Q105: =(Q93-Q95)/Q117*1000 -> -0.11255624 | R105: =(R93-R95)/R117*1000 -> 4.8534184 | S105: =(S93-S95-S94)/S117*1000 -> 1.7532168 | T105: =(T93-T95-20)/T117*1000 -> 4.540083 | U105: =(U93-U95)/U117*1000 -> 6.1313624 | V105: =(V93-V95)/V117*1000 -> 1.9184467 | W105: =(W93-W95+1)/W117*1000 -> 1.7269312 | X105: =(X93-X95-4)/X117*1000 -> 2.6763 | Y105: =(Y93-Y95)/Y117*1000 -> 4.7035799 | Z105: =(Z93-Z95)/Z117*1000 -> 7.294597 | AA105: =(AA93-AA95)/AA117*1000 -> 8.4576747 | AB105: =(AB93-AB95)/AB117*1000 -> 11.136806 | AC105: =(AC93-AC95)/AC117*1000 -> 12.808247 | AD105: =(AD93-AD95)/AD117*1000 -> 14.320948 | AE105: =(AE93-AE95)/AE117*1000 -> 15.349306 | AF105: =(AF93-AF95)/AF117*1000 -> 16.445335
A106: Adj. Continuing EPS - Basic | Q106: =(Q93-Q94-Q95)/Q116*1000 -> -0.18200583 | R106: =(R93-R94-R95)/R116*1000 -> 4.7607024 | S106: =(S93-S95)/S116*1000 -> 3.8099552 | T106: =(T93-T94-T95-20)/T116*1000 -> 4.5972284 | U106: =(U93-U94-U95-2)/U116*1000 -> 6.2016641 | V106: =(V93-V94-V95)/V116*1000 -> 1.9834017 | W106: =(W93-W94-W95)/W116*1000 -> 1.778974 | X106: =(X93-X94-X95-4)/X116*1000 -> 2.760847 | Y106: =(Y93-Y94-Y95)/Y116*1000 -> 4.856443 | Z106: =(Z93-Z94-Z95)/Z116*1000 -> 7.374753 | AA106: =(AA93-AA94-AA95)/AA116*1000 -> 8.5516241 | AB106: =(AB93-AB94-AB95)/AB116*1000 -> 11.261879 | AC106: =(AC93-AC94-AC95)/AC116*1000 -> 12.953693 | AD106: =(AD93-AD94-AD95)/AD116*1000 -> 14.485405 | AE106: =(AE93-AE94-AE95)/AE116*1000 -> 15.525572 | AF106: =(AF93-AF94-AF95)/AF116*1000 -> 16.634187
A107: Adj. Continuing EPS - Diluted | Q107: =(Q93-Q94-Q95)/Q117*1000 -> -0.18200583 | R107: =(R93-R94-R95)/R117*1000 -> 4.6787331 | S107: =(S93-S95)/S117*1000 -> 3.743549 | T107: =(T93-T94-T95-20)/T117*1000 -> 4.540083 | U107: =(U93-U94-U95)/U117*1000 -> 6.1313624 | V107: =(V93-V94-V95)/V117*1000 -> 1.9184467 | W107: =(W93-W94-W95+1)/W117*1000 -> 1.7269312 | X107: =(X93-X94-X95-4)/X117*1000 -> 2.6763 | Y107: =(Y93-Y94-Y95)/Y117*1000 -> 4.7035799 | Z107: =(Z93-Z94-Z95)/Z117*1000 -> 7.294597 | AA107: =(AA93-AA94-AA95)/AA117*1000 -> 8.4576747 | AB107: =(AB93-AB94-AB95)/AB117*1000 -> 11.136806 | AC107: =(AC93-AC94-AC95)/AC117*1000 -> 12.808247 | AD107: =(AD93-AD94-AD95)/AD117*1000 -> 14.320948 | AE107: =(AE93-AE94-AE95)/AE117*1000 -> 15.349306 | AF107: =(AF93-AF94-AF95)/AF117*1000 -> 16.445335
...

Sheet Balance Sheet
A1: ='DCF Valuation'!D45 -> 340
A2: Balance Sheet | B2: 2000 | C2: 2001 | D2: 2002 | E2: 2003 | F2: 2004 | G2: 2005 | H2: 2006 | I2: 2007 | J2: 2008 | K2: 2009 | L2: 2010 | M2: 2011 | N2: 2012 | O2: 2013 | P2: 2014 | Q2: 2015 | R2: 2016 | S2: 2017 | T2: 2018 | U2: 2019 | V2: 2020 | W2: 2021 | X2: 2022 | Y2: 2023 | Z2: 2024 | AA2: 2025E | AB2: 2026E | AC2: 2027E | AD2: 2028E | AE2: 2029E | AF2: 2030E | AI2: Comments
A4: Goodwill | H4: 1589 | I4: 1561 | J4: 1756 | K4: 2126 | L4: 2298 | M4: 3126 | N4: 3078 | O4: 3399 | P4: 3420 | Q4: 3590 | R4: 1864 | S4: 1831 | T4: 5173 | U4: 5199 | V4: 5060 | W4: 5068 | X4: 4994 | Y4: 4706 | Z4: 4937 | AA4: =Z4-'Cashflow Statement'!AA32-'Cashflow Statement'!AA9 -> 5109 | AB4: =AA4-'Cashflow Statement'!AB32-'Cashflow Statement'!AB9 -> 5281 | AC4: =AB4-'Cashflow Statement'!AC32-'Cashflow Statement'!AC9 -> 5453 | AD4: =AC4-'Cashflow Statement'!AD32-'Cashflow Statement'!AD9 -> 5625 | AE4: =AD4-'Cashflow Statement'!AE32-'Cashflow Statement'!AE9 -> 5797 | AF4: =AE4-'Cashflow Statement'!AF32-'Cashflow Statement'!AF9 -> 5969
A5: Intangible Assets | H5: 3056 | I5: 2981 | J5: 3112 | K5: 3217 | L5: 3130 | M5: 3498 | N5: 3872 | O5: =4641-200 -> 4441 | P5: 5536 | Q5: 5321 | R5: 5178 | S5: 5596 | T5: 9757 | U5: 9479 | V5: 8676 | W5: 8382 | X5: 8096 | Y5: 7830 | Z5: 7947 | AA5: =Z5-'Cashflow Statement'!AA7-'Cashflow Statement'!AA26 -> 7612.4352 | AB5: =AA5-'Cashflow Statement'!AB7-'Cashflow Statement'!AB26 -> 7092.8232 | AC5: =AB5-'Cashflow Statement'!AC7-'Cashflow Statement'!AC26 -> 6544.312 | AD5: =AC5-'Cashflow Statement'!AD7-'Cashflow Statement'!AD26 -> 5910.4134 | AE5: =AD5-'Cashflow Statement'!AE7-'Cashflow Statement'!AE26 -> 5211.0352 | AF5: =AE5-'Cashflow Statement'!AF7-'Cashflow Statement'!AF26 -> 4450.9973
A6: PP&E | H6: 1826 | I6: 1847 | J6: 2107 | K6: 2201 | L6: 2253 | M6: 2486 | N6: 2604 | O6: =2740-98 -> 2642 | P6: 2928 | Q6: 3272 | R6: 3169 | S6: 3518 | T6: 4454 | U6: 4398 | V6: 4055 | W6: 3937 | X6: 3847 | Y6: 4121 | Z6: 4629 | AA6: =Z6-'Cashflow Statement'!AA5-'Cashflow Statement'!AA28-'Cashflow Statement'!AA31 -> 5662.5658 | AB6: =AA6-'Cashflow Statement'!AB5-'Cashflow Statement'!AB28-'Cashflow Statement'!AB31 -> 6629.7247 | AC6: =AB6-'Cashflow Statement'!AC5-'Cashflow Statement'!AC28-'Cashflow Statement'!AC31 -> 7480.5365 | AD6: =AC6-'Cashflow Statement'!AD5-'Cashflow Statement'!AD28-'Cashflow Statement'!AD31 -> 8172.7019 | AE6: =AD6-'Cashflow Statement'!AE5-'Cashflow Statement'!AE28-'Cashflow Statement'!AE31 -> 8670.5337 | AF6: =AE6-'Cashflow Statement'!AF5-'Cashflow Statement'!AF28-'Cashflow Statement'!AF31 -> 8950.2498
A7: Non-current financial assets | H7: 364 | I7: 286 | J7: 203 | K7: 220 | L7: 215 | M7: 246 | N7: 281 | O7: 384 | P7: 446 | Q7: 419 | R7: 382 | S7: 324 | T7: 416 | U7: 429 | V7: 431 | W7: 688 | X7: 752 | Y7: 997 | Z7: 1073 | AA7: =Z7 -> 1073 | AB7: =AA7 -> 1073 | AC7: =AB7 -> 1073 | AD7: =AC7 -> 1073 | AE7: =AD7 -> 1073 | AF7: =AE7 -> 1073
A8: Investments in associates | H8: 32 | I8: 34 | J8: 244 | K8: 238 | L8: 236 | M8: 253 | N8: 281 | O8: 680 | P8: 771 | Q8: 765 | R8: 2175 | S8: 2127 | T8: 2253 | U8: 2211 | V8: 2126 | W8: 1969 | X8: 1974 | Y8: 1928 | Z8: 1894 | AA8: =Z8 -> 1894 | AB8: =AA8 -> 1894 | AC8: =AB8 -> 1894 | AD8: =AC8 -> 1894 | AE8: =AD8 -> 1894 | AF8: =AE8 -> 1894
A9: Non-current derivatives | M9: 20 | N9: 62 | O9: 0 | P9: 29 | Q9: 35 | R9: 28 | S9: 16 | T9: 13 | U9: 33 | V9: 52 | W9: 23 | X9: 18 | Y9: 0 | Z9: 4 | AA9: =Z9 -> 4 | AB9: =AA9 -> 4 | AC9: =AB9 -> 4 | AD9: =AC9 -> 4 | AE9: =AD9 -> 4 | AF9: =AE9 -> 4
A10: Deferred tax assets | H10: 120 | I10: 158 | J10: 295 | K10: 263 | L10: 194 | M10: 251 | N10: 243 | O10: 201 | P10: 228 | Q10: 984 | R10: 1351 | S10: 251 | T10: 391 | U10: 251 | V10: 316 | W10: 449 | X10: 1576 | Y10: 1122 | Z10: 2349 | AA10: =Z10 -> 2349 | AB10: =AA10 -> 2349 | AC10: =AB10 -> 2349 | AD10: =AC10 -> 2349 | AE10: =AD10 -> 2349 | AF10: =AE10 -> 2349
A11: Right of use Asset | U11: 732 | V11: 623 | W11: 606 | X11: 566 | Y11: 582 | Z11: 653 | AA11: =Z11 -> 653 | AB11: =AA11 -> 653 | AC11: =AB11 -> 653 | AD11: =AC11 -> 653 | AE11: =AD11 -> 653 | AF11: =AE11 -> 653
A12: Other non-current financial assets | H12: 16 | I12: 10 | J12: 9 | K12: 1 | L12: 12 | M12: 12 | N12: 13 | O12: 0 | P12: 0 | Q12: =P12 -> 0 | R12: =Q12 -> 0 | S12: =R12 -> 0 | T12: 4 | U12: =T12 -> 4 | V12: 4 | W12: 11 | X12: 8 | Y12: 7 | Z12: 3 | AA12: =Z12 -> 3 | AB12: =AA12 -> 3 | AC12: =AB12 -> 3 | AD12: =AC12 -> 3 | AE12: =AD12 -> 3 | AF12: =AE12 -> 3
A13: Other | H13: =H14-SUM(H4:H12) -> 0 | I13: =I14-SUM(I4:I12) -> 0 | J13: =J14-SUM(J4:J12) -> 0 | K13: =K14-SUM(K4:K12) -> 0 | L13: =L14-SUM(L4:L12) -> 0 | M13: =M14-SUM(M4:M12) -> 0 | N13: =N14-SUM(N4:N12) -> 0 | O13: =O14-SUM(O4:O12) -> 0 | ... Z13: =Z14-SUM(Z4:Z12) -> 0 | AA13: 0 | AB13: 0 | AC13: 0 | AD13: 0 | AE13: 0 | AF13: 0
A14: Non-current assets | H14: 7003 | I14: 6877 | J14: 7726 | K14: 8266 | L14: 8338 | M14: 9892 | N14: 10434 | O14: =(3399+7083+680+585) -> 11747 | P14: 13358 | Q14: 14386 | R14: =SUM(R4:R12) -> 14147 | S14: =SUM(S4:S12) -> 13663 | T14: =SUM(T4:T12) -> 22461 | U14: =SUM(U4:U12) -> 22736 | V14: =SUM(V4:V12) -> 21343 | W14: =SUM(W4:W12) -> 21133 | X14: =SUM(X4:X12) -> 21831 | Y14: =SUM(Y4:Y12) -> 21293 | Z14: =SUM(Z4:Z12) -> 23489 | AA14: =SUM(AA4:AA13) -> 24360.001 | AB14: =SUM(AB4:AB13) -> 24979.548 | AC14: =SUM(AC4:AC13) -> 25453.848 | AD14: =SUM(AD4:AD13) -> 25684.115 | AE14: =SUM(AE4:AE13) -> 25654.569 | AF14: =SUM(AF4:AF13) -> 25346.247
A16: Current financial assets | H16: 108 | I16: 107 | J16: 108 | K16: 75 | L16: 110 | M16: 101 | N16: 176 | O16: 198 | P16: 221 | Q16: 247 | R16: 147 | S16: 2113 | T16: 185 | U16: 143 | V16: 126 | W16: 104 | X16: 242 | Y16: 270 | Z16: 243 | AA16: =Z16 -> 243 | AB16: =AA16 -> 243 | AC16: =AB16 -> 243 | AD16: =AC16 -> 243 | AE16: =AD16 -> 243 | AF16: =AE16 -> 243
A17: Current derivatives | H17: 397 | I17: 126 | J17: 138 | K17: 63 | L17: 128 | M17: 259 | N17: 585 | O17: 864 | P17: 377 | Q17: 373 | R17: 592 | S17: 566 | T17: 740 | U17: 674 | V17: 694 | W17: 705 | X17: 540 | Y17: 1577 | Z17: 952 | AA17: =Z17 -> 952 | AB17: =AA17 -> 952 | AC17: =AB17 -> 952 | AD17: =AC17 -> 952 | AE17: =AD17 -> 952 | AF17: =AE17 -> 952
A18: Inventories and work-in-progress | H18: 3240 | I18: 3240 | J18: 3673 | K18: 3382 | L18: 3508 | M18: 3799 | N18: 4131 | O18: 3998 | P18: 4265 | Q18: 4518 | R18: 4247 | S18: 3954 | T18: 5558 | U18: 6312 | V18: 5190 | W18: 5063 | X18: 6408 | Y18: 7903 | Z18: 9491 | AA18: =-AA19*'Income Statement'!AA49/365 -> 10156.157 | AB18: =-AB19*'Income Statement'!AB49/365 -> 10293.559 | AC18: =-AC19*'Income Statement'!AC49/365 -> 11141.109 | AD18: =-AD19*'Income Statement'!AD49/365 -> 12007.109 | AE18: =-AE19*'Income Statement'!AE49/365 -> 12811.995 | AF18: =-AF19*'Income Statement'!AF49/365 -> 13507.855
A19: DIO | W19: =-W18/'Income Statement'!W49*365 -> 231.02825 | X19: =-X18/'Income Statement'!X49*365 -> 199.49846 | Y19: =-Y18/'Income Statement'!Y49*365 -> 204.98827 | Z19: =-Z18/'Income Statement'!Z49*365 -> 217.05608 | AA19: 204 | AB19: 183 | AC19: 180 | AD19: 180 | AE19: 182 | AF19: 183
A20: Trade and Other receivables | H20: 4218 | I20: 3926 | J20: 3881 | K20: 4158 | L20: 4219 | M20: 5005 | N20: 5025 | O20: 4967 | P20: 5827 | Q20: 6515 | R20: 6252 | S20: 4952 | T20: 6580 | U20: 7639 | V20: 5769 | W20: 6504 | X20: 7904 | Y20: 9417 | Z20: 10572 | AA20: ='Income Statement'!AA39*'Balance Sheet'!AA21/365 -> 11152.869 | AB20: ='Income Statement'!AB39*'Balance Sheet'!AB21/365 -> 12503.226 | AC20: ='Income Statement'!AC39*'Balance Sheet'!AC21/365 -> 13435.802 | AD20: ='Income Statement'!AD39*'Balance Sheet'!AD21/365 -> 14364.327 | AE20: ='Income Statement'!AE39*'Balance Sheet'!AE21/365 -> 15158.796 | AF20: ='Income Statement'!AF39*'Balance Sheet'!AF21/365 -> 15894.784
A21: DSO | W21: =W20/'Income Statement'!W39*365 -> 155.59809 | X21: =X20/'Income Statement'!X39*365 -> 151.56081 | Y21: =Y20/'Income Statement'!Y39*365 -> 148.16177 | Z21: =Z20/'Income Statement'!Z39*365 -> 141.25929 | AA21: 129 | AB21: 128 | AC21: 125 | AD21: 124 | AE21: =AD21 -> 124 | AF21: =AE21 -> 124
A22: Tax assets | H22: 68 | I22: 27 | J22: 127 | K22: 145 | L22: 146 | M22: 215 | N22: 421 | O22: 392 | P22: 452 | Q22: 623 | R22: 513 | S22: 596 | T22: 752 | U22: 458 | V22: 481 | W22: 555 | X22: 358 | Y22: 422 | Z22: 364 | AA22: =Z22 -> 364 | AB22: =AA22 -> 364 | AC22: =AB22 -> 364 | AD22: =AC22 -> 364 | AE22: =AD22 -> 364 | AF22: =AE22 -> 364
A23: Cash and Cash equivalents | H23: 743 | I23: 730 | J23: 919 | K23: 2080 | L23: 2062 | M23: 1431 | N23: 2193 | O23: 1547 | P23: 1633 | Q23: 1845 | R23: 1926 | S23: 4914 | T23: 2330 | U23: 2632 | V23: 3747 | W23: 5247 | X23: 6687 | Y23: 6676 | Z23: 6514 | AA23: ='Cashflow Statement'!AA55 -> 7326.3518 | AB23: ='Cashflow Statement'!AB55 -> 8656.3944 | AC23: ='Cashflow Statement'!AC55 -> 10191.542 | AD23: ='Cashflow Statement'!AD55 -> 12126.355 | AE23: ='Cashflow Statement'!AE55 -> 15580.022 | AF23: ='Cashflow Statement'!AF55 -> 19331.618
A24: Contract costs | S24: 261 | T24: 470 | U24: 471 | V24: 486 | W24: 552 | X24: 664 | Y24: 753 | Z24: 884 | AA24: =Z24 -> 884 | AB24: =AA24 -> 884 | AC24: =AB24 -> 884 | AD24: =AC24 -> 884 | AE24: =AD24 -> 884 | AF24: =AE24 -> 884
A25: Contract assets | S25: 1366 | T25: 1544 | U25: 1743 | V25: 1695 | W25: 1853 | X25: 1982 | Y25: 2157 | Z25: 2503 | AA25: =Z25 -> 2503 | AB25: =AA25 -> 2503 | AC25: =AB25 -> 2503 | AD25: =AC25 -> 2503 | AE25: =AD25 -> 2503 | AF25: =AE25 -> 2503
A26: Other | H26: =H27-SUM(H16:H23) -> 151 | I26: =I27-SUM(I16:I23) -> 1142 | J26: =J27-SUM(J16:J23) -> 264 | K26: =K27-SUM(K16:K23) -> 0 | L26: =L27-SUM(L16:L23) -> 0 | M26: =M27-SUM(M16:M23) -> 0 | N26: =N27-SUM(N16:N23) -> 0 | O26: =O27-SUM(O16:O23) -> -15 | ... Q26: =Q27-SUM(Q16:Q23) -> 0 | R26: 3234 | S26: 0 | T26: =S26 -> 0 | U26: 0 | X26: 212 | Y26: 0 | Z26: 0 | AA26: =Z26 -> 0 | AB26: =AA26 -> 0 | AC26: =AB26 -> 0 | AD26: =AC26 -> 0 | AE26: =AD26 -> 0 | AF26: =AE26 -> 0
A27: Current Assets | H27: 8925 | I27: =8519+779 -> 9298 | J27: =9049+61 -> 9110 | K27: 9903 | L27: 10173 | M27: 10810 | N27: 12531 | O27: =(864+3998+4967+1547+575) -> 11951 | P27: 12775 | Q27: 14121 | R27: =SUM(R16:R26) -> 16911 | S27: =SUM(S16:S26) -> 18722 | T27: =SUM(T16:T26) -> 18159 | U27: =SUM(U16:U26) -> 20072 | V27: =SUM(V16:V26) -> 18188 | W27: =SUM(W16:W26)-W19-W21 -> 20583 | X27: =SUM(X16:X26)-X19-X21 -> 24997 | Y27: =SUM(Y16:Y26)-Y19-Y21 -> 29175 | Z27: =SUM(Z16:Z26)-Z19-Z21 -> 31523 | AA27: =SUM(AA16:AA26)-AA19-AA21 -> 33581.378 | AB27: =SUM(AB16:AB26)-AB19-AB21 -> 36399.18 | AC27: =SUM(AC16:AC26)-AC19-AC21 -> 39714.454 | AD27: =SUM(AD16:AD26)-AD19-AD21 -> 43443.791 | ... AF27: =SUM(AF16:AF26)-AF19-AF21 -> 53680.256
A29: Provisions | H29: -976 | I29: -1052 | J29: -1078 | K29: -1315 | L29: -1310 | M29: -1374 | N29: -1823 | O29: =-1751+10 -> -1741 | P29: -1870 | Q29: -1802 | R29: -1706 | S29: -1263 | T29: -1588 | U29: -2093 | V29: -1942 | W29: -1798 | X29: -1549 | Y29: -1547 | Z29: -1835 | AA29: =Z29-'Cashflow Statement'!AA10 -> -1935 | AB29: =AA29-'Cashflow Statement'!AB10 -> -2035 | AC29: =AB29-'Cashflow Statement'!AC10 -> -2135 | AD29: =AC29-'Cashflow Statement'!AD10 -> -2235 | AE29: =AD29-'Cashflow Statement'!AE10 -> -2335 | AF29: =AE29-'Cashflow Statement'!AF10 -> -2435
A30: Borrowings subject to specific conditions | H30: -573 | I30: -590 | J30: -698 | K30: -696 | L30: -701 | M30: -682 | N30: -670 | O30: -670 | P30: -713 | Q30: -708 | R30: -699 | S30: -569 | T30: -585 | U30: -505 | V30: -426 | W30: -327 | X30: -302 | Y30: -292 | Z30: -287 | AA30: =Z30 -> -287 | AB30: =AA30 -> -287 | AC30: =AB30 -> -287 | AD30: =AC30 -> -287 | AE30: =AD30 -> -287 | AF30: =AE30 -> -287
A31: Non-current interest-bearing financial liabilities | H31: -463 | I31: -397 | J31: -418 | K31: -1208 | L31: -1483 | M31: -1447 | N31: -2259 | O31: =-1295-6 -> -1301 | P31: -1658 | Q31: -1752 | R31: -2392 | S31: -3246 | T31: -3384 | U31: -3239 | V31: -4082 | W31: -5094 | X31: -5378 | Y31: -4691 | Z31: -3788 | AA31: =Z31-'Cashflow Statement'!AA39 -> -3788 | AB31: =AA31-'Cashflow Statement'!AB39 -> -3788 | AC31: =AB31-'Cashflow Statement'!AC39 -> -3788 | AD31: =AC31-'Cashflow Statement'!AD39 -> -3788 | AE31: =AD31-'Cashflow Statement'!AE39 -> -3788 | AF31: =AE31-'Cashflow Statement'!AF39 -> -3788
A32: Non-current derivatives | M32: -5 | N32: -12 | O32: -36 | R32: 0 | S32: =R32 -> 0 | T32: -7 | U32: -5 | V32: -18 | W32: -8 | X32: -18 | Y32: -8 | Z32: -15 | AA32: =Z32 -> -15 | AB32: =AA32 -> -15 | AC32: =AB32 -> -15 | AD32: =AC32 -> -15 | AE32: =AD32 -> -15 | AF32: =AE32 -> -15
A33: Deferred tax liabilities | H33: -929 | I33: -745 | J33: -618 | K33: -833 | L33: -685 | M33: -718 | N33: -981 | O33: -1293 | P33: -728 | Q33: -677 | R33: -987 | S33: -674 | T33: -1662 | U33: -1340 | V33: -1285 | W33: -1275 | X33: -1164 | Y33: -1022 | Z33: -911 | AA33: =Z33-('Cashflow Statement'!AA17) -> -1241 | AB33: =AA33-('Cashflow Statement'!AB17) -> -1111 | AC33: =AB33-('Cashflow Statement'!AC17) -> -911 | AD33: =AC33-('Cashflow Statement'!AD17) -> -911 | AE33: =AD33-('Cashflow Statement'!AE17) -> -911 | AF33: =AE33-('Cashflow Statement'!AF17) -> -911
A34: Other non-current financial liabilities | H34: -112 | I34: -96 | J34: -139 | K34: -208 | L34: -186 | M34: -199 | N34: -81 | O34: =-119+8 -> -111 | P34: -101 | Q34: -26 | R34: -5 | S34: -8 | T34: -2 | U34: -2 | V34: -2 | W34: -116 | X34: -75 | Y34: -43 | Z34: -11 | AA34: =Z34 -> -11 | AB34: =AA34 -> -11 | AC34: =AB34 -> -11 | AD34: =AC34 -> -11 | AE34: =AD34 -> -11 | AF34: =AE34 -> -11
A35: Other | H35: =H36-SUM(H29:H34) -> 0 | I35: =I36-SUM(I29:I34) -> 0 | J35: =J36-SUM(J29:J34) -> 0 | K35: =K36-SUM(K29:K34) -> 0 | L35: =L36-SUM(L29:L34) -> 0 | M35: =M36-SUM(M29:M34) -> 0 | N35: =N36-SUM(N29:N34) -> 0 | O35: =O36-SUM(O29:O34) -> 13 | ... R35: =R36-SUM(R29:R34) -> 0 | S35: 0 | T35: 0 | U35: =U36-SUM(U29:U34) -> 0 | V35: =V36-SUM(V29:V34) -> 0 | W35: =W36-SUM(W29:W34) -> 0 | X35: -49 | Y35: 0 | Z35: =Y35 -> 0 | AA35: =Z35 -> 0 | AB35: =AA35 -> 0 | AC35: =AB35 -> 0 | AD35: =AC35 -> 0 | AE35: =AD35 -> 0 | AF35: =AE35 -> 0
A36: Non-current liabilities | H36: -3053 | I36: -2880 | J36: -2951 | K36: -4260 | L36: -4365 | M36: -4425 | N36: -5826 | O36: -5139 | P36: -5070 | Q36: -4965 | R36: =SUM(R29:R34) -> -5789 | S36: =SUM(S29:S34) -> -5760 | T36: =SUM(T29:T34) -> -7228 | U36: =SUM(U29:U34) -> -7184 | V36: =SUM(V29:V34) -> -7755 | W36: =SUM(W29:W34) -> -8618 | X36: =SUM(X29:X35) -> -8535 | Y36: =SUM(Y29:Y35) -> -7603 | Z36: =SUM(Z29:Z35) -> -6847 | AA36: =SUM(AA29:AA35) -> -7277 | AB36: =SUM(AB29:AB35) -> -7247 | AC36: =SUM(AC29:AC35) -> -7147 | AD36: =SUM(AD29:AD35) -> -7247 | AE36: =SUM(AE29:AE35) -> -7347 | AF36: =SUM(AF29:AF35) -> -7447
A38: Provisions | H38: -1101 | I38: -1133 | J38: -1278 | K38: -1039 | L38: -1114 | M38: -1064 | N38: -1064 | O38: =-1224+7 -> -1217 | P38: -1459 | Q38: -1654 | R38: -1558 | S38: -925 | T38: -1189 | U38: -990 | V38: -905 | W38: -1058 | X38: -1018 | Y38: -1064 | Z38: -1173 | AA38: =Z38 -> -1173 | AB38: =AA38 -> -1173 | AC38: =AB38 -> -1173 | AD38: =AC38 -> -1173 | AE38: =AD38 -> -1173 | AF38: =AE38 -> -1173
A39: Interest-bearing current financial liabilities | H39: -699 | I39: =-502 -> -502 | J39: -1136 | K39: -1367 | L39: -568 | M39: -998 | N39: -916 | O39: -1435 | P39: -1507 | Q39: -876 | R39: -945 | S39: -1390 | T39: -2221 | U39: -3540 | V39: -2509 | W39: -1720 | X39: -1277 | Y39: -1608 | Z39: -988 | AA39: =Z39 -> -988 | AB39: =AA39 -> -988 | AC39: =AB39 -> -988 | AD39: =AC39 -> -988 | AE39: =AD39 -> -988 | AF39: =AE39 -> -988
A40: Trade and other payables | H40: -6390 | I40: -6517 | J40: -6786 | K40: -6936 | L40: -7236 | M40: -8348 | N40: -8767 | O40: -8668 | P40: -9638 | Q40: -10602 | R40: -10242 | S40: -4409 | T40: -5650 | U40: -6164 | V40: -4353 | W40: -4950 | X40: -6298 | Y40: -8097 | Z40: -9802 | AA40: =AA41*'Income Statement'!AA49/365 -> -11251.429 | AB40: =AB41*'Income Statement'!AB49/365 -> -12993.509 | AC40: =AC41*'Income Statement'!AC49/365 -> -14669.127 | AD40: =AD41*'Income Statement'!AD49/365 -> -16009.479 | AE40: =AE41*'Income Statement'!AE49/365 -> -16965.334 | AF40: =AF41*'Income Statement'!AF49/365 -> -17493.779
A41: DPO | W41: =W40/'Income Statement'!W49*365 -> 225.87198 | X41: =X40/'Income Statement'!X49*365 -> 196.07387 | Y41: =Y40/'Income Statement'!Y49*365 -> 210.02025 | Z41: =Z40/'Income Statement'!Z49*365 -> 224.16855 | AA41: 226 | AB41: 231 | AC41: 237 | AD41: 240 | AE41: 241 | AF41: 237
A42: Tax liabilities | H42: -21 | I42: -43 | J42: -39 | K42: -53 | L42: -72 | M42: -92 | N42: -156 | O42: -202 | P42: -220 | Q42: -287 | R42: -179 | S42: -214 | T42: -210 | U42: -111 | V42: -118 | W42: -109 | X42: -105 | Y42: -104 | Z42: -105 | AA42: =Z42 -> -105 | AB42: =AA42 -> -105 | AC42: =AB42 -> -105 | AD42: =AC42 -> -105 | AE42: =AD42 -> -105 | AF42: =AE42 -> -105
A43: Current derivatives | H43: -2 | I43: -4 | J43: -577 | K43: -13 | L43: -451 | M43: -653 | N43: -213 | O43: -150 | P43: -1636 | Q43: -4108 | R43: -4385 | S43: -805 | T43: -1255 | U43: -1033 | V43: -1244 | W43: -1788 | X43: -5848 | Y43: -4735 | Z43: -8803 | AA43: =Z43 -> -8803 | AB43: =AA43 -> -8803 | AC43: =AB43 -> -8803 | AD43: =AC43 -> -8803 | AE43: =AD43 -> -8803 | AF43: =AE43 -> -8803
A44: Contract liabilities | S44: -9090 | T44: -10453 | U44: -10923 | V44: -9838 | W44: -10141 | X44: -12756 | Y44: -15029 | Z44: -16421 | AA44: =Z44 -> -16421 | AB44: =AA44 -> -16421 | AC44: =AB44 -> -16421 | AD44: =AC44 -> -16421 | AE44: =AD44 -> -16421 | AF44: =AE44 -> -16421
A45: RPFH cash advances
A46: Other | H46: =H47-SUM(H38:H43) -> -150 | I46: =I47-SUM(I38:I43) -> -591 | J46: =J47-SUM(J38:J43) -> -195 | K46: =K47-SUM(K38:K43) -> 0 | L46: =L47-SUM(L38:L43) -> 0 | M46: =M47-SUM(M38:M43) -> 0 | N46: =N47-SUM(N38:N43) -> -26 | O46: =-64+3 -> -61 | P46: -125 | Q46: -122 | R46: =-357-794 -> -1151 | S46: -144 | T46: -113 | U46: -115 | V46: -59 | W46: -62 | X46: -125 | Y46: -140 | Z46: -148 | AA46: =Z46 -> -148 | AB46: =AA46 -> -148 | AC46: =AB46 -> -148 | AD46: =AC46 -> -148 | AE46: =AD46 -> -148 | AF46: =AE46 -> -148
A47: Current liabilities | H47: -8363 | I47: =-8338-452 -> -8790 | J47: =-9972-39 -> -10011 | K47: -9408 | L47: -9441 | M47: -11155 | N47: -11142 | O47: -11746 | P47: -14585 | Q47: -17649 | R47: =SUM(R38:R46) -> -18460 | S47: =SUM(S38:S46) -> -16977 | T47: =SUM(T38:T46) -> -21091 | U47: =SUM(U38:U46) -> -22876 | V47: =SUM(V38:V46) -> -19026 | W47: =SUM(W38:W40,W42:W44,W46) -> -19828 | X47: =SUM(X38:X40,X42:X44,X46) -> -27427 | Y47: =SUM(Y38:Y40,Y42:Y44,Y46) -> -30777 | Z47: =SUM(Z38:Z40,Z42:Z44,Z46) -> -37440 | AA47: =SUM(AA38:AA40,AA42:AA44,AA46) -> -38889.429 | AB47: =SUM(AB38:AB40,AB42:AB44,AB46) -> -40631.509 | AC47: =SUM(AC38:AC40,AC42:AC44,AC46) -> -42307.127 | AD47: =SUM(AD38:AD40,AD42:AD44,AD46) -> -43647.479 | ... AF47: =SUM(AF38:AF40,AF42:AF44,AF46) -> -45131.779
A49: Share capital | H49: 83 | I49: 83 | J49: 83 | K49: 83 | L49: 83 | M49: 83 | N49: 83 | O49: =N49 -> 83 | P49: =O49 -> 83 | Q49: 83 | R49: =Q49 -> 83 | S49: 83 | T49: 87 | U49: 85 | V49: 85 | W49: 85 | X49: 85 | Y49: 85 | Z49: 85 | AA49: =Z49 -> 85 | AB49: =AA49 -> 85 | AC49: =AB49 -> 85 | AD49: =AC49 -> 85 | AE49: =AD49 -> 85 | AF49: =AE49 -> 85
A50: Retained Earnings | H50: 4296 | I50: 4189 | J50: 3902 | K50: 3619 | L50: 4214 | M50: 4387 | N50: 4444 | O50: =5138-1 -> 5137 | P50: 6246 | Q50: 5927 | R50: 4495 | S50: 4686 | T50: 10585 | U50: 9839 | V50: 11912 | W50: 12713 | X50: 12785 | Y50: 8048 | Z50: 10758 | AA50: =Z50+'Income Statement'!Z92+'Income Statement'!Z94-'Income Statement'!Z95-'Income Statement'!AA83+'Cashflow Statement'!AA43+'Cashflow Statement'!AA47 -> 7634.1664 | AB50: =AA50+'Income Statement'!AA92+'Income Statement'!AA94-'Income Statement'!AA95-'Income Statement'!AB83+'Cashflow Statement'!AB43+'Cashflow Statement'!AB47 -> 8378.0478 | AC50: =AB50+'Income Statement'!AB92+'Income Statement'!AB94-'Income Statement'!AB95-'Income Statement'!AC83+'Cashflow Statement'!AC43+'Cashflow Statement'!AC47 -> 9581.8229 | AD50: =AC50+'Income Statement'!AC92+'Income Statement'!AC94-'Income Statement'!AC95-'Income Statement'!AD83+'Cashflow Statement'!AD43+'Cashflow Statement'!AD47 -> 11416.406 | AE50: =AD50+'Income Statement'!AD92+'Income Statement'!AD94-'Income Statement'!AD95-'Income Statement'!AE83+'Cashflow Statement'!AE43+'Cashflow Statement'!AE47 -> 14827.343 | AF50: =AE50+'Income Statement'!AE92+'Income Statement'!AE94-'Income Statement'!AE95-'Income Statement'!AF83+'Cashflow Statement'!AF43+'Cashflow Statement'!AF47 -> 18483.243
A51: Net unrealised gain on available-for-sale financial assets | H51: 27 | I51: 27 | J51: -15 | K51: 10 | L51: 26 | M51: 20 | N51: 25 | O51: 29 | P51: 50 | Q51: 41 | R51: 35 | S51: 28 | T51: 0 | U51: 0 | Y51: =X51 -> 0 | Z51: 0 | AA51: =Z51 -> 0 | AB51: =AA51 -> 0 | AC51: =AB51 -> 0 | AD51: =AC51 -> 0 | AE51: =AD51 -> 0 | AF51: =AE51 -> 0
A52: Profit for the period | H52: 9 | I52: 39 | J52: -205 | K52: 641 | L52: 207 | M52: ='Cashflow Statement'!M4 -> 478 | N52: ='Cashflow Statement'!N4 -> 1282 | O52: ='Cashflow Statement'!O4 -> 1255 | P52: -126 | Q52: -424 | R52: ='Cashflow Statement'!R4 -> 1908 | S52: 4550 | T52: 1283 | U52: 2447 | V52: 352 | W52: 43 | X52: -2459 | Y52: 3444 | Z52: -667 | AA52: ='Cashflow Statement'!AA4 -> 3402.0356 | AB52: ='Cashflow Statement'!AB4 -> 4265.0744 | AC52: ='Cashflow Statement'!AC4 -> 5145.0274 | AD52: ='Cashflow Statement'!AD4 -> 5689.3468 | AE52: ='Cashflow Statement'!AE4 -> 6097.918 | AF52: ='Cashflow Statement'!AF4 -> 6533.3897
A53: Non-controlling interests | H53: 173 | I53: 167 | J53: 141 | K53: 148 | L53: 175 | M53: 154 | N53: 163 | O53: 178 | P53: 225 | Q53: 266 | R53: 288 | S53: 301 | T53: 346 | U53: 377 | V53: 401 | W53: 429 | X53: 455 | Y53: 511 | Z53: 549 | AA53: =Z53+'Income Statement'!AA95 -> 653.74832 | AB53: =AA53+'Income Statement'!AB95 -> 772.09668 | AC53: =AB53+'Income Statement'!AC95 -> 902.32449 | AD53: =AC53+'Income Statement'!AD95 -> 1042.6749 | AE53: =AD53+'Income Statement'!AE95 -> 1190.7879 | AF53: =AE53+'Income Statement'!AF95 -> 1346.0921
A54: Total Equity | H54: =SUM(H49:H53)-76 -> 4512 | I54: =SUM(I49:I53) -> 4505 | J54: =SUM(J49:J53)-32 -> 3874 | K54: =SUM(K49:K53) -> 4501 | L54: =SUM(L49:L53) -> 4705 | M54: =SUM(M49:M53) -> 5122 | N54: =SUM(N49:N53) -> 5997 | O54: 6813 | P54: =SUM(P49:P53) -> 6478 | Q54: 5893 | R54: =SUM(R49:R53) -> 6809 | S54: =SUM(S49:S53) -> 9648 | T54: =SUM(T49:T53) -> 12301 | U54: =SUM(U49:U53) -> 12748 | V54: =SUM(V49:V53) -> 12750 | W54: =SUM(W49:W53) -> 13270 | X54: =SUM(X49:X53) -> 10866 | Y54: =SUM(Y49:Y53) -> 12088 | ... AF54: =SUM(AF49:AF53) -> 26447.725
A56: balance sheet check | H56: =H14+H27+H36+H47-H54 -> 0 | I56: =I14+I27+I36+I47-I54 -> 0 | J56: =J14+J27+J36+J47-J54 -> 0 | K56: =K14+K27+K36+K47-K54 -> 0 | L56: =L14+L27+L36+L47-L54 -> 0 | M56: =M14+M27+M36+M47-M54 -> 0 | N56: =N14+N27+N36+N47-N54 -> 0 | O56: =O14+O27+O36+O47-O54 -> 0 | ... AF56: =AF14+AF27+AF36+AF47-AF54 -> 0
A58: Working capital analysis
A59: Inventory | H59: =H18 -> 3240 | I59: =I18 -> 3240 | J59: =J18 -> 3673 | K59: =K18 -> 3382 | L59: =L18 -> 3508 | M59: =M18 -> 3799 | N59: =N18 -> 4131 | O59: =O18 -> 3998 | ... AF59: =AF18 -> 13507.855
A60: Receivables | H60: =H20 -> 4218 | I60: =I20 -> 3926 | J60: =J20 -> 3881 | K60: =K20 -> 4158 | L60: =L20 -> 4219 | M60: =M20 -> 5005 | N60: =N20 -> 5025 | O60: =O20 -> 4967 | ... AF60: =AF20 -> 15894.784
A61: Current Tax assets | H61: ='Balance Sheet'!H22 -> 68 | I61: ='Balance Sheet'!I22 -> 27 | J61: ='Balance Sheet'!J22 -> 127 | K61: ='Balance Sheet'!K22 -> 145 | L61: ='Balance Sheet'!L22 -> 146 | M61: ='Balance Sheet'!M22 -> 215 | N61: ='Balance Sheet'!N22 -> 421 | O61: ='Balance Sheet'!O22 -> 392 | ... AF61: ='Balance Sheet'!AF22 -> 364
A62: Contract Assets | S62: ='Balance Sheet'!S25 -> 1366 | T62: ='Balance Sheet'!T25 -> 1544 | U62: ='Balance Sheet'!U25 -> 1743 | V62: ='Balance Sheet'!V25 -> 1695 | W62: ='Balance Sheet'!W25 -> 1853 | X62: ='Balance Sheet'!X25 -> 1982 | Y62: ='Balance Sheet'!Y25 -> 2157 | Z62: ='Balance Sheet'!Z25 -> 2503 | AA62: =AA76*'Income Statement'!AA$41 -> 2849.8373 | AB62: =AB76*'Income Statement'!AB$41 -> 3219.8474 | AC62: =AC76*'Income Statement'!AC$41 -> 3543.0457 | AD62: =AD76*'Income Statement'!AD$41 -> 3818.447 | AE62: =AE76*'Income Statement'!AE$41 -> 4029.6395 | AF62: =AF76*'Income Statement'!AF$41 -> 4225.286
A63: Other | H63: ='Balance Sheet'!H26 -> 151 | I63: ='Balance Sheet'!I26-779 -> 363 | J63: ='Balance Sheet'!J26-61 -> 203 | K63: ='Balance Sheet'!K26 -> 0 | L63: ='Balance Sheet'!L26 -> 0 | M63: ='Balance Sheet'!M26 -> 0 | N63: ='Balance Sheet'!N26 -> 0 | O63: ='Balance Sheet'!O26 -> -15 | P63: ='Balance Sheet'!P26 -> 0 | Q63: ='Balance Sheet'!Q26 -> 0 | R63: ='Balance Sheet'!R26-3234 -> 0 | S63: ='Balance Sheet'!S26 -> 0 | T63: ='Balance Sheet'!T26 -> 0 | U63: ='Balance Sheet'!U26 -> 0 | V63: ='Balance Sheet'!V26 -> 0 | W63: ='Balance Sheet'!W26 -> 0 | X63: ='Balance Sheet'!X26 -> 212 | Y63: ='Balance Sheet'!Y26 -> 0 | Z63: ='Balance Sheet'!Z26 -> 0 | ... AF63: ='Balance Sheet'!AF26 -> 0
A64: Operating Current Assets | H64: =SUM(H59:H63) -> 7677 | I64: =SUM(I59:I63) -> 7556 | J64: =SUM(J59:J63) -> 7884 | K64: =SUM(K59:K63) -> 7685 | L64: =SUM(L59:L63) -> 7873 | M64: =SUM(M59:M63) -> 9019 | N64: =SUM(N59:N63) -> 9577 | O64: =SUM(O59:O63) -> 9342 | ... AF64: =SUM(AF59:AF63) -> 33991.925
A66: Payables | H66: =H40 -> -6390 | I66: =I40 -> -6517 | J66: =J40 -> -6786 | K66: =K40 -> -6936 | L66: =L40 -> -7236 | M66: =M40 -> -8348 | N66: =N40 -> -8767 | O66: =O40 -> -8668 | ... AF66: =AF40 -> -17493.779
A67: Provisions | H67: ='Balance Sheet'!H38 -> -1101 | I67: ='Balance Sheet'!I38 -> -1133 | J67: ='Balance Sheet'!J38 -> -1278 | K67: ='Balance Sheet'!K38 -> -1039 | L67: ='Balance Sheet'!L38 -> -1114 | M67: ='Balance Sheet'!M38 -> -1064 | N67: ='Balance Sheet'!N38 -> -1064 | O67: ='Balance Sheet'!O38 -> -1217 | ... AF67: ='Balance Sheet'!AF38 -> -1173
A68: Current tax liabilities | H68: ='Balance Sheet'!H42 -> -21 | I68: ='Balance Sheet'!I42 -> -43 | J68: ='Balance Sheet'!J42 -> -39 | K68: ='Balance Sheet'!K42 -> -53 | L68: ='Balance Sheet'!L42 -> -72 | M68: ='Balance Sheet'!M42 -> -92 | N68: ='Balance Sheet'!N42 -> -156 | O68: ='Balance Sheet'!O42 -> -202 | ... AF68: ='Balance Sheet'!AF42 -> -105
A69: Contract Liabilities | S69: ='Balance Sheet'!S44 -> -9090 | T69: ='Balance Sheet'!T44 -> -10453 | U69: ='Balance Sheet'!U44 -> -10923 | V69: ='Balance Sheet'!V44 -> -9838 | W69: ='Balance Sheet'!W44 -> -10141 | X69: ='Balance Sheet'!X44 -> -12756 | Y69: ='Balance Sheet'!Y44 -> -15029 | Z69: ='Balance Sheet'!Z44 -> -16421 | AA69: =AA44 -> -16421 | AB69: =AB44 -> -16421 | AC69: =AC44 -> -16421 | AD69: =AD44 -> -16421 | AE69: =AE44 -> -16421 | AF69: =AF44 -> -16421 | AI69: We include LEAP RPFH deferred income in contract liabilities
A70: Other | H70: ='Balance Sheet'!H46+'Balance Sheet'!H43 -> -152 | I70: ='Balance Sheet'!I46+'Balance Sheet'!I43+452 -> -143 | J70: ='Balance Sheet'!J46+'Balance Sheet'!J43+39 -> -733 | K70: ='Balance Sheet'!K46+'Balance Sheet'!K43 -> -13 | L70: ='Balance Sheet'!L46+'Balance Sheet'!L43 -> -451 | M70: ='Balance Sheet'!M46+'Balance Sheet'!M43 -> -653 | N70: ='Balance Sheet'!N46+'Balance Sheet'!N43 -> -239 | O70: ='Balance Sheet'!O46+'Balance Sheet'!O43 -> -211 | P70: ='Balance Sheet'!P46+'Balance Sheet'!P43 -> -1761 | Q70: ='Balance Sheet'!Q46+'Balance Sheet'!Q43 -> -4230 | R70: ='Balance Sheet'!R46+'Balance Sheet'!R43+794 -> -4742 | S70: ='Balance Sheet'!S46+'Balance Sheet'!S43+794 -> -155 | T70: ='Balance Sheet'!T46+'Balance Sheet'!T43 -> -1368 | U70: ='Balance Sheet'!U46+'Balance Sheet'!U43 -> -1148 | V70: ='Balance Sheet'!V46+'Balance Sheet'!V43 -> -1303 | W70: ='Balance Sheet'!W46+'Balance Sheet'!W43 -> -1850 | X70: ='Balance Sheet'!X46+'Balance Sheet'!X43 -> -5973 | Y70: ='Balance Sheet'!Y46+'Balance Sheet'!Y43 -> -4875 | Z70: ='Balance Sheet'!Z46+'Balance Sheet'!Z43 -> -8951 | AA70: ='Balance Sheet'!AA46+'Balance Sheet'!AA43 -> -8951 | ... AF70: ='Balance Sheet'!AF46+'Balance Sheet'!AF43 -> -8951
A71: Operating Current Liabilities | H71: =SUM(H66:H70) -> -7664 | I71: =SUM(I66:I70) -> -7836 | J71: =SUM(J66:J70) -> -8836 | K71: =SUM(K66:K70) -> -8041 | L71: =SUM(L66:L70) -> -8873 | M71: =SUM(M66:M70) -> -10157 | N71: =SUM(N66:N70) -> -10226 | O71: =SUM(O66:O70) -> -10298 | ... AF71: =SUM(AF66:AF70) -> -44143.779
S72: =SUM(S66:S69)+SUM(S59:S62) -> -3770 | T72: =SUM(T66:T69)+SUM(T59:T62) -> -3068 | U72: =SUM(U66:U69)+SUM(U59:U62) -> -2036 | V72: =SUM(V66:V69)+SUM(V59:V62) -> -2079 | W72: =SUM(W66:W69)+SUM(W59:W62) -> -2283 | X72: =SUM(X66:X69)+SUM(X59:X62) -> -3525 | Y72: =SUM(Y66:Y69)+SUM(Y59:Y62) -> -4395 | Z72: =SUM(Z66:Z69)+SUM(Z59:Z62) -> -4571 | ... AF72: =SUM(AF66:AF69)+SUM(AF59:AF62) -> -1200.854
A73: Working Capital | H73: =H71+H64 -> 13 | I73: =I71+I64 -> -280 | J73: =J71+J64 -> -952 | K73: =K71+K64 -> -356 | L73: =L71+L64 -> -1000 | M73: =M71+M64 -> -1138 | N73: =N71+N64 -> -649 | O73: =O71+O64 -> -956 | ... AF73: =AF71+AF64 -> -10151.854
A74: y/y change | H74: =H73-115 -> -102 | I74: =I73-H73 -> -293 | J74: =J73-I73 -> -672 | K74: =K73-J73 -> 596 | L74: =L73-K73 -> -644 | M74: =M73-L73 -> -138 | N74: =N73-M73 -> 489 | O74: =O73-N73 -> -307 | P74: =P73-O73 -> -1578 | ... AF74: =AF73-AE73 -> 1099.049
AI75: FCF line to check
A76: Contract assets - as a % of sales | S76: =S62/'Income Statement'!S$41 -> 0.083414753 | T76: =T62/'Income Statement'!T$41 -> 0.073436385 | U76: =U62/'Income Statement'!U$41 -> 0.069447765 | V76: =V62/'Income Statement'!V$41 -> 0.1019181 | W76: =W62/'Income Statement'!W$41 -> 0.12244763 | X76: =X62/'Income Statement'!X$41 -> 0.10152128 | Y76: =Y62/'Income Statement'!Y$41 -> 0.091201218 | Z76: =Z62/'Income Statement'!Z$41 -> 0.090308847 | AA76: =Z76 -> 0.090308847 | AB76: =AA76 -> 0.090308847 | AC76: =AB76 -> 0.090308847 | AD76: =AC76 -> 0.090308847 | AE76: =AD76 -> 0.090308847 | AF76: =AE76 -> 0.090308847
A77: Contract liabilities - as a % of sales | S77: =S69/'Income Statement'!S$41 -> -0.55508061 | T77: =T69/'Income Statement'!T$41 -> -0.49717004 | U77: =U69/'Income Statement'!U$41 -> -0.43521396 | V77: =V69/'Income Statement'!V$41 -> -0.59154591 | W77: =W69/'Income Statement'!W$41 -> -0.67012489 | X77: =X69/'Income Statement'!X$41 -> -0.65338319 | Y77: =Y69/'Income Statement'!Y$41 -> -0.63544882 | Z77: =Z69/'Income Statement'!Z$41 -> -0.59247366 | AA77: -0.54 | AB77: =AA77+0.025 -> -0.515 | AC77: =AB77+0.025 -> -0.49 | AD77: =AC77+0.025 -> -0.465 | AE77: =AD77+0.025 -> -0.44 | AF77: =AE77+0.025 -> -0.415 | AI77: CMD'21 p63: "Increasing advance payments from Rafale programs over 2021 23, decreasing elsewhere."
A79: LEAP impact | U79: -800 | V79: 0 | W79: 0 | X79: 0
A80: Change in Receivables | I80: =I60-H60 -> -292 | J80: =J60-I60 -> -45 | K80: =K60-J60 -> 277 | L80: =L60-K60 -> 61 | M80: =M60-L60 -> 786 | N80: =N60-M60 -> 20 | O80: =O60-N60 -> -58 | P80: =P60-O60 -> 860 | ... AF80: =AF60-AE60 -> 735.98778
A81: Change in Payables | I81: =I66-H66 -> -127 | J81: =J66-I66 -> -269 | K81: =K66-J66 -> -150 | L81: =L66-K66 -> -300 | M81: =M66-L66 -> -1112 | N81: =N66-M66 -> -419 | O81: =O66-N66 -> 99 | P81: =P66-O66 -> -970 | ... AF81: =AF66-AE66 -> -528.44488
A82: Change in Contract Assets | T82: =T62-S62 -> 178 | U82: =U62-T62 -> 199 | V82: =V62-U62 -> -48 | W82: =W62-V62 -> 158 | X82: =X62-W62 -> 129 | Y82: =Y62-X62 -> 175 | Z82: =Z62-Y62 -> 346 | AA82: =AA62-Z62 -> 346.83732 | ... AF82: =AF62-AE62 -> 195.6465
A83: Change in Contract Liabilities | T83: =T69-S69 -> -1363 | U83: =U69-T69 -> -470 | V83: =V69-U69 -> 1085 | W83: =W69-V69 -> -303 | X83: =X69-W69 -> -2615 | Y83: =Y69-X69 -> -2273 | Z83: =Z69-Y69 -> -1392 | AA83: =AA69-Z69 -> 0 | ... AF83: =AF69-AE69 -> 0
AA84: ='Cashflow Statement'!AA57 -> 3613.1854 | AB84: ='Cashflow Statement'!AB57 -> 4332.1968 | AC84: ='Cashflow Statement'!AC57 -> 4940.4467 | AD84: ='Cashflow Statement'!AD57 -> 5589.2572 | AE84: ='Cashflow Statement'!AE57 -> 6076.0778 | AF84: ='Cashflow Statement'!AF57 -> 6537.613
A85: Deferred income | T85: 3905 | U85: 4313 | V85: 4142 | W85: 4450 | X85: 5101 | Y85: 5818 | Z85: 6459
A86: ow RPFH | V86: 3600
A87: ow RTDI | V87: =V85-V86 -> 542 | W87: =V87*1.1 -> 596.2 | X87: =W87*1.1 -> 655.82 | Y87: =X87*1.1 -> 721.402 | Z87: =Y87*1.1 -> 793.5422 | AA87: =Z87*1.1 -> 872.89642
A88: Leverage Anaylsis | B88: =B2 -> 2000 | C88: =C2 -> 2001 | D88: =D2 -> 2002 | E88: =E2 -> 2003 | F88: =F2 -> 2004 | G88: =G2 -> 2005 | H88: =H2 -> 2006 | I88: =I2 -> 2007 | ... Z88: =Z2 -> 2024 | AA88: =Z88+1 -> 2025 | AB88: =AA88+1 -> 2026 | AC88: =AB88+1 -> 2027 | AD88: =AC88+1 -> 2028 | AE88: =AD88+1 -> 2029 | AF88: =AE88+1 -> 2030
A89: =A30 -> Borrowings subject to specific conditions | I89: =I30 -> -590 | J89: =J30 -> -698 | K89: =K30 -> -696 | L89: =L30 -> -701 | M89: =M30 -> -682 | N89: =N30 -> -670 | O89: =O30 -> -670 | P89: =P30 -> -713 | ... AF89: =AF30 -> -287
A90: =A31 -> Non-current interest-bearing financial liabilities | I90: =I31 -> -397 | J90: =J31 -> -418 | K90: =K31 -> -1208 | L90: =L31 -> -1483 | M90: =M31 -> -1447 | N90: =N31 -> -2259 | O90: =O31 -> -1301 | P90: =P31 -> -1658 | ... AF90: =AF31 -> -3788
A91: =A39 -> Interest-bearing current financial liabilities | I91: =I39 -> -502 | J91: =J39 -> -1136 | K91: =K39 -> -1367 | L91: =L39 -> -568 | M91: =M39 -> -998 | N91: =N39 -> -916 | O91: =O39 -> -1435 | P91: =P39 -> -1507 | ... AF91: =AF39 -> -988
A92: =A23 -> Cash and Cash equivalents | I92: =I23 -> 730 | J92: =J23 -> 919 | K92: =K23 -> 2080 | L92: =L23 -> 2062 | M92: =M23 -> 1431 | N92: =N23 -> 2193 | O92: =O23 -> 1547 | P92: =P23 -> 1633 | ... AF92: =AF23 -> 19331.618
A93: Period End (Net Debt)/Net Cash | I93: =SUM(I89:I92) -> -759 | J93: =SUM(J89:J92) -> -1333 | K93: =SUM(K89:K92) -> -1191 | L93: =SUM(L89:L92) -> -690 | M93: =SUM(M89:M92) -> -1696 | N93: =SUM(N89:N92) -> -1652 | O93: =SUM(O89:O92) -> -1859 | P93: =SUM(P89:P92) -> -2245 | ... AF93: =SUM(AF89:AF92) -> 14268.618
A94: Period Average (Net Debt)/Net Cash | I94: =AVERAGE(H93:I93) -> -759 | J94: =AVERAGE(I93:J93) -> -1046 | K94: =AVERAGE(J93:K93) -> -1262 | L94: =AVERAGE(K93:L93) -> -940.5 | M94: =AVERAGE(L93:M93) -> -1193 | N94: =AVERAGE(M93:N93) -> -1674 | O94: =AVERAGE(N93:O93) -> -1755.5 | P94: =AVERAGE(O93:P93) -> -2052 | ... AF94: =AVERAGE(AE93:AF93) -> 12392.82
A96: EBITDA | R96: ='Income Statement'!R193 -> 3130 | S96: ='Income Statement'!S193 -> 2980 | T96: ='Income Statement'!T193 -> 4232 | U96: ='Income Statement'!U193 -> 5283 | V96: ='Income Statement'!V193 -> 3133 | W96: ='Income Statement'!W193 -> 3185 | X96: ='Income Statement'!X193 -> 3781 | Y96: ='Income Statement'!Y193 -> 4502 | ... AF96: ='Income Statement'!AF193 -> 11159.045
A98: Y/E Net Debt/Adj. EBITDA | R98: =R93/R96 -> -0.67412141 | S98: =S93/S96 -> -0.097651007 | T98: =T93/T96 -> -0.9120983 | U98: =U93/U96 -> -0.88056029 | V98: =V93/V96 -> -1.0437281 | W98: =W93/W96 -> -0.59466248 | X98: =X93/X96 -> -0.07140968 | Y98: =Y93/Y96 -> 0.018880498 | ... AF98: =AF93/AF96 -> 1.2786594
A99: Average Net Debt/Adj. EBITDA | R99: =R94/R96 -> -0.57523962 | S99: =S94/S96 -> -0.40285235 | T99: =T94/T96 -> -0.49043006 | U99: =U94/U96 -> -0.80560288 | V99: =V94/V96 -> -1.2642834 | W99: =W94/W96 -> -0.81067504 | X99: =X94/X96 -> -0.28616768 | Y99: =Y94/Y96 -> -0.020546424 | ... AF99: =AF94/AF96 -> 1.1105628
A101: ROIC Analysis | B101: =B2 -> 2000 | C101: =C2 -> 2001 | D101: =D2 -> 2002 | E101: =E2 -> 2003 | F101: =F2 -> 2004 | G101: =G2 -> 2005 | H101: =H2 -> 2006 | I101: =I2 -> 2007 | ... Z101: =Z2 -> 2024 | AA101: =Z101+1 -> 2025 | AB101: =AA101+1 -> 2026 | AC101: =AB101+1 -> 2027 | AD101: =AC101+1 -> 2028 | AE101: =AD101+1 -> 2029 | AF101: =AE101+1 -> 2030
A102: Adj. EBITA | S102: ='Income Statement'!S70 -> 2192 | T102: ='Income Statement'!T70 -> 3023 | U102: ='Income Statement'!U70 -> 3820 | V102: ='Income Statement'!V70 -> 1686 | W102: ='Income Statement'!W70 -> 1805 | X102: ='Income Statement'!X70 -> 2408 | Y102: ='Income Statement'!Y70 -> 3166 | Z102: ='Income Statement'!Z70 -> 4119 | ... AF102: ='Income Statement'!AF70 -> 8787.0465
A103: Underlying Tax | S103: ='Income Statement'!S88 -> -485 | T103: ='Income Statement'!T88 -> -638 | U103: ='Income Statement'!U88 -> -1012 | V103: ='Income Statement'!V88 -> -334 | W103: ='Income Statement'!W88 -> -412 | X103: ='Income Statement'!X88 -> -557 | Y103: ='Income Statement'!Y88 -> -724 | Z103: ='Income Statement'!Z88 -> -987 | ... AF103: ='Income Statement'!AF88 -> -2259.6939
A104: NOPAT | S104: =S102+S103 -> 1707 | T104: =T102+T103 -> 2385 | U104: =U102+U103 -> 2808 | V104: =V102+V103 -> 1352 | W104: =W102+W103 -> 1393 | X104: =X102+X103 -> 1851 | Y104: =Y102+Y103 -> 2442 | Z104: =Z102+Z103 -> 3132 | ... AF104: =AF102+AF103 -> 6527.3526
A105: Invested Capital | S105: =SUM(S106:S110) -> 9655.577 | T105: =SUM(T106:T110) -> 16863.946 | U105: =SUM(U106:U110) -> 17361.594 | V105: =SUM(V106:V110) -> 15820.435 | W105: =SUM(W106:W110) -> 14910.457 | X105: =SUM(X106:X110) -> 9568.3252 | Y105: =SUM(Y106:Y110) -> 10312.77 | Z105: =SUM(Z106:Z110) -> 6466.0905 | ... AF105: =SUM(AF106:AF110) -> 9438.0692
A106: Net Intangibles | H106: =H4+H5-'Cashflow Statement'!H7 -> 4368 | I106: =I4+I5-'Cashflow Statement'!I7 -> 4310 | J106: =J4+J5-'Cashflow Statement'!J7 -> 4601 | K106: =K4+K5-'Cashflow Statement'!K7 -> 5044 | L106: =L4+L5-'Cashflow Statement'!L7 -> 5113 | M106: =M4+M5-'Cashflow Statement'!M7 -> 6283 | N106: =N4+N5-'Cashflow Statement'!N7 -> 6569 | O106: =O4+O5-'Cashflow Statement'!O7 -> 7441 | ... AF106: =AF4+AF5-'Cashflow Statement'!AF7 -> 9109.9594
A107: PP&E | H107: =H6 -> 1826 | I107: =I6 -> 1847 | J107: =J6 -> 2107 | K107: =K6 -> 2201 | L107: =L6 -> 2253 | M107: =M6 -> 2486 | N107: =N6 -> 2604 | O107: =O6 -> 2642 | ... AF107: =AF6 -> 8950.2498
A108: Current assets (excluding Cash & Equivalents) | H108: =H27-H23 -> 8182 | I108: =I27-I23 -> 8568 | J108: =J27-J23 -> 8191 | K108: =K27-K23 -> 7823 | L108: =L27-L23 -> 8111 | M108: =M27-M23 -> 9379 | N108: =N27-N23 -> 10338 | O108: =O27-O23 -> 10404 | ... AF108: =AF27-AF23 -> 34348.639
A109: Current Liabilities (excluding Financial Liabilities) | H109: =H47-H39-H38 -> -6563 | I109: =I47-I39-I38 -> -7155 | J109: =J47-J39-J38 -> -7597 | K109: =K47-K39-K38 -> -7002 | L109: =L47-L39-L38 -> -7759 | M109: =M47-M39-M38 -> -9093 | N109: =N47-N39-N38 -> -9162 | O109: =O47-O39-O38 -> -9094 | ... AF109: =AF47-AF39-AF38 -> -42970.779
A110: Other current assets | H110: =H26 -> 151 | I110: =I26 -> 1142 | J110: =J26 -> 264 | K110: =K26 -> 0 | L110: =L26 -> 0 | M110: =M26 -> 0 | N110: =N26 -> 0 | O110: =O26 -> -15 | ... AF110: =AF26 -> 0
A111: ROIC (%) | S111: =S104/S105 -> 0.17678902 | T111: =T104/T105 -> 0.14142597 | U111: =U104/U105 -> 0.1617363 | V111: =V104/V105 -> 0.08545909 | W111: =W104/W105 -> 0.093424365 | X111: =X104/AVERAGE(W105:X105) -> 0.15123301 | Y111: =Y104/AVERAGE(X105:Y105) -> 0.24566051 | Z111: =Z104/AVERAGE(Y105:Z105) -> 0.3733269 | AA111: =AA104/AVERAGE(Z105:AA105) -> 0.52047385 | AB111: =AB104/AVERAGE(AA105:AB105) -> 0.64296129 | AC111: =AC104/AVERAGE(AB105:AC105) -> 0.69479016 | AD111: =AD104/AVERAGE(AC105:AD105) -> 0.71169078 | AE111: =AE104/AVERAGE(AD105:AE105) -> 0.70987258 | AF111: =AF104/AVERAGE(AE105:AF105) -> 0.71174934
A113: IFRS 16 Exchange Sheet Metrics (updated annually with AR) | B113: =B2 -> 2000 | C113: =C2 -> 2001 | D113: =D2 -> 2002 | E113: =E2 -> 2003 | F113: =F2 -> 2004 | G113: =G2 -> 2005 | H113: =H2 -> 2006 | I113: =I2 -> 2007 | ... Z113: =Z2 -> 2024 | AA113: =Z113+1 -> 2025 | AB113: =AA113+1 -> 2026 | AC113: =AB113+1 -> 2027 | AD113: =AC113+1 -> 2028 | AE113: =AD113+1 -> 2029 | AF113: =AE113+1 -> 2030
...

Sheet Cashflow Statement
A1: ='Balance Sheet'!A1 -> 340
A2: Cash Flow Statement | B2: 2000 | C2: 2001 | D2: 2002 | E2: 2003 | F2: 2004 | G2: 2005 | H2: 2006 | I2: 2007 | J2: 2008 | K2: 2009 | L2: 2010 | M2: 2011 | N2: 2012 | O2: 2013 | P2: 2014 | Q2: 2015 | R2: 2016 | S2: 2017 | T2: 2018 | U2: 2019 | V2: 2020 | W2: 2021 | X2: 2022 | Y2: 2023 | Z2: 2024 | AA2: =Z2+1 -> 2025 | AB2: =AA2+1 -> 2026 | AC2: =AB2+1 -> 2027 | AD2: =AC2+1 -> 2028 | AE2: =AD2+1 -> 2029 | AF2: =AE2+1 -> 2030 | AG2: Comments
A4: Reported Net Income | H4: ='Income Statement'!H92+'Income Statement'!H94-'Income Statement'!H95 -> 33 | I4: ='Income Statement'!I92+'Income Statement'!I94-'Income Statement'!I95 -> 53 | J4: ='Income Statement'!J92+'Income Statement'!J94-'Income Statement'!J95 -> -183 | K4: ='Income Statement'!K92+'Income Statement'!K94-'Income Statement'!K95 -> 641 | L4: ='Income Statement'!L92+'Income Statement'!L94-'Income Statement'!L95 -> 207 | M4: ='Income Statement'!M92+'Income Statement'!M94-'Income Statement'!M95 -> 478 | N4: ='Income Statement'!N92+'Income Statement'!N94-'Income Statement'!N95 -> 1282 | O4: ='Income Statement'!O92+'Income Statement'!O94-'Income Statement'!O95 -> 1255 | ... AF4: ='Income Statement'!AF92+'Income Statement'!AF94-'Income Statement'!AF95 -> 6533.3897
A5: Depreciation | H5: =575-H7 -> 298 | I5: =513-I7 -> 281 | J5: =540-J7 -> 273 | K5: =573-K7 -> 274 | L5: 291 | M5: =695-M7-M9-M10 -> 321 | N5: =962-N7-N9-N10 -> 340 | O5: =941-O7-O9-O10 -> 363 | P5: 366 | Q5: =741*(P5/(P5+P7)) -> 331.54768 | R5: =726*(Q5/(Q5+Q7)) -> 324.83619 | S5: =788*(R5/(R5+R7)) -> 352.57702 | T5: =1209*(S5/(S5+S7)) -> 540.94621 | U5: =1463*(T5/(T5+T7)) -> 654.59413 | V5: =1447*(U5/(U5+U7)) -> 647.43521 | W5: =1380*(V5/(V5+V7)) -> 617.45721 | X5: =1373*(W5/(W5+W7)) -> 614.32518 | Y5: =1336*(X5/(X5+X7)) -> 597.77017 | Z5: =1406*(Y5/(Y5+Y7)) -> 629.09046 | AA5: =AA6*'Income Statement'!AA$41 -> 716.26268 | AB5: =AB6*'Income Statement'!AB$41 -> 809.25901 | AC5: =AC6*'Income Statement'!AC$41 -> 890.48993 | AD5: =AD6*'Income Statement'!AD$41 -> 959.7078 | AE5: =AE6*'Income Statement'!AE$41 -> 1012.7878 | AF5: =AF6*'Income Statement'!AF$41 -> 1061.9605
A6: as a % of sales | H6: =H5/'Income Statement'!H$41 -> 0.027488239 | I6: =I5/'Income Statement'!I$41 -> 0.028927321 | J6: =J5/'Income Statement'!J$41 -> 0.026553837 | K6: =K5/'Income Statement'!K$41 -> 0.025949427 | L6: =L5/'Income Statement'!L$41 -> 0.026387378 | M6: =M5/'Income Statement'!M$41 -> 0.02753474 | N6: =N5/'Income Statement'!N$41 -> 0.024972457 | O6: =O5/'Income Statement'!O$41 -> 0.02505176 | ... Q6: =Q5/'Income Statement'!Q$41 -> 0.02043815 | R6: =$I6 -> 0.028927321 | S6: =R6 -> 0.028927321 | T6: =T5/'Income Statement'!T41 -> 0.025728714 | U6: =U5/'Income Statement'!U41 -> 0.026081526 | V6: =V5/'Income Statement'!V41 -> 0.038929421 | W6: =W5/'Income Statement'!W41 -> 0.040802036 | X6: =X5/'Income Statement'!X41 -> 0.031466741 | Y6: =Y5/'Income Statement'!Y41 -> 0.025274626 | Z6: =Z5/'Income Statement'!Z41 -> 0.022697736 | AA6: =Z6 -> 0.022697736 | AB6: =AA6 -> 0.022697736 | AC6: =AB6 -> 0.022697736 | AD6: =AC6 -> 0.022697736 | AE6: =AD6 -> 0.022697736 | AF6: =AE6 -> 0.022697736
A7: Amortisation | H7: 277 | I7: 232 | J7: 267 | K7: 299 | L7: 315 | M7: 341 | N7: 381 | O7: 399 | P7: 452 | Q7: =741-Q5 -> 409.45232 | R7: =726-R5 -> 401.16381 | S7: =788-S5 -> 435.42298 | T7: =1209-T5 -> 668.05379 | U7: =1463-U5 -> 808.40587 | V7: =1447-V5 -> 799.56479 | W7: =1380-W5 -> 762.54279 | X7: =1373-X5 -> 758.67482 | Y7: =1336-Y5 -> 738.22983 | Z7: =1406-Z5 -> 776.90954 | AA7: =AA8*'Income Statement'!AA$41 -> 884.56484 | AB7: =AB8*'Income Statement'!AB$41 -> 1069.612 | AC7: =AC8*'Income Statement'!AC$41 -> 1098.5112 | AD7: =AD8*'Income Statement'!AD$41 -> 1183.8986 | AE7: =AE8*'Income Statement'!AE$41 -> 1249.3782 | AF7: =AF8*'Income Statement'!AF$41 -> 1310.0379
A8: as a % of sales | H8: =H7/'Income Statement'!H$41 -> 0.025551148 | I8: =I7/'Income Statement'!I$41 -> 0.023883055 | J8: =J7/'Income Statement'!J$41 -> 0.025970236 | K8: =K7/'Income Statement'!K$41 -> 0.028317075 | L8: =L7/'Income Statement'!L$41 -> 0.028563656 | M8: =M7/'Income Statement'!M$41 -> 0.0292503 | N8: =N7/'Income Statement'!N$41 -> 0.027983841 | O8: =O7/'Income Statement'!O$41 -> 0.027536232 | ... Q8: =Q7/'Income Statement'!Q$41 -> 0.025240557 | R8: =AVERAGE(M8:Q8) -> 0.028011226 | S8: =R8 -> 0.028011226 | T8: =T7/'Income Statement'!T41 -> 0.031774259 | U8: =U7/'Income Statement'!U41 -> 0.032209972 | V8: =V7/'Income Statement'!V41 -> 0.048076772 | W8: =W7/'Income Statement'!W41 -> 0.0503894 | X8: =X7/'Income Statement'!X41 -> 0.038860565 | Y8: =Y7/'Income Statement'!Y41 -> 0.031213472 | Z8: =Z7/'Income Statement'!Z41 -> 0.028031084 | AA8: =Z8 -> 0.028031084 | AB8: 0.03 | AC8: 0.028 | AD8: 0.028 | AE8: 0.028 | AF8: 0.028
A9: Impairment | H9: 129 | I9: 210 | J9: -10 | K9: 177 | L9: -3 | M9: 62 | N9: 54 | O9: 103 | P9: 137 | Q9: 1004 | R9: 243 | S9: 60 | T9: -19 | U9: -42 | V9: 377 | W9: 91 | X9: 411 | Y9: 148 | Z9: 0 | AA9: =Z9 -> 0 | AB9: =AA9 -> 0 | AC9: =AB9 -> 0 | AD9: =AC9 -> 0 | AE9: =AD9 -> 0 | AF9: =AE9 -> 0
A10: Change in Provisions | H10: 247 | I10: 178 | J10: 160 | K10: 25 | L10: 46 | M10: -29 | N10: 187 | O10: 76 | P10: 205 | Q10: 114 | R10: -42 | S10: 178 | T10: 45 | U10: 168 | V10: -259 | W10: 171 | X10: -169 | Y10: -51 | Z10: 285 | AA10: 100 | AB10: 100 | AC10: 100 | AD10: 100 | AE10: 100 | AF10: 100
A11: Share of profit in associates (net of dividends received) | H11: 4 | I11: 4 | J11: -4 | K11: -2 | L11: -9 | M11: -10 | N11: -19 | O11: =-'Income Statement'!O83 -> -15 | P11: -36 | Q11: -20 | R11: -63 | S11: -100 | T11: -124 | U11: -87 | V11: 22 | W11: 702 | X11: 11 | Y11: -83 | Z11: -120 | AA11: =-'Income Statement'!AA83 -> 0 | AB11: =-'Income Statement'!AB83 -> 0 | AC11: =-'Income Statement'!AC83 -> 0 | AD11: =-'Income Statement'!AD83 -> 0 | AE11: =-'Income Statement'!AE83 -> 0 | AF11: =-'Income Statement'!AF83 -> 0
A12: Change in fair value of derivatives | H12: 135 | I12: 368 | J12: 546 | K12: -546 | L12: 310 | M12: 2 | N12: -779 | O12: -432 | P12: 1934 | Q12: 2475 | R12: 81 | S12: -3608 | T12: 316 | U12: -152 | V12: 209 | W12: 538 | X12: 4207 | Y12: -2161 | Z12: 4684
A13: Capital gains on asset disposals | H13: -39 | I13: 7 | J13: -127 | K13: 6 | L13: 31 | M13: 16 | N13: 10 | O13: -382 | P13: -12 | Q13: -453 | R13: -364 | S13: -20 | T13: 12 | U13: -41 | V13: 20 | W13: -57 | X13: 289 | Y13: 344 | Z13: -47
A14: Profit/(Loss) before tax from discontinued operations | H14: 0 | I14: -36 | J14: 308 | K14: -1 | L14: 5 | M14: -4 | N14: -1 | Q14: -26 | R14: -110 | S14: -997
A15: Profit attributable to non-controlling interests | H15: 12 | I15: 7 | J15: 11 | K15: 13 | L15: 18 | M15: 19 | N15: 24 | O15: 29 | P15: ='Income Statement'!P95 -> 58 | Q15: ='Income Statement'!Q95 -> 47 | R15: 55 | S15: 60 | T15: 58 | U15: 65 | V15: ='Income Statement'!V95 -> 34 | W15: ='Income Statement'!W95 -> 25 | X15: ='Income Statement'!X95 -> 33 | Y15: ='Income Statement'!Y95 -> 76 | Z15: ='Income Statement'!Z95 -> 92 | AA15: ='Income Statement'!AA95 -> 104.74832 | AB15: ='Income Statement'!AB95 -> 118.34837 | AC15: ='Income Statement'!AC95 -> 130.22781 | ... AF15: ='Income Statement'!AF95 -> 155.30416
A16: Co-detailed Other | H16: =7-19 -> -12 | I16: =22+4 -> 26 | J16: =25+6 -> 31 | K16: =-24+7 -> -17 | L16: =4+6 -> 10 | M16: 4 | N16: 222 | O16: 457 | P16: -510 | Q16: -821 | R16: 217 | S16: 1150 | T16: 318 | U16: 221 | V16: -328 | W16: -707 | X16: -880 | Y16: 459 | Z16: -907
A17: Cash Tax adjustment | H17: =-202-'Income Statement'!H86 -> -93 | I17: =-212-'Income Statement'!I86 -> -187 | J17: =-257-'Income Statement'!J86 -> -399 | K17: =-73-'Income Statement'!K86 -> 162 | L17: =-103-'Income Statement'!L86 -> -89 | M17: 42 | N17: 337 | O17: -14 | AA17: 330 | AB17: -130 | AC17: -200
A18: Change in Inventory and Work in Progress | H18: -461 | I18: -421 | J18: -337 | K18: 387 | L18: 55 | M18: -134 | N18: -388 | O18: 45 | P18: -185 | Q18: -280 | R18: -347 | S18: -280 | T18: -393 | U18: -590 | V18: 1016 | W18: 296 | X18: -1545 | Y18: -1494 | Z18: -1452 | AA18: =-('Balance Sheet'!AA18-'Balance Sheet'!Z18) -> -665.1571 | AB18: =-('Balance Sheet'!AB18-'Balance Sheet'!AA18) -> -137.40176 | AC18: =-('Balance Sheet'!AC18-'Balance Sheet'!AB18) -> -847.5505 | AD18: =-('Balance Sheet'!AD18-'Balance Sheet'!AC18) -> -865.99955 | AE18: =-('Balance Sheet'!AE18-'Balance Sheet'!AD18) -> -804.88606 | AF18: =-('Balance Sheet'!AF18-'Balance Sheet'!AE18) -> -695.85961
A19: Change in operating receivables and payables | H19: 254 | I19: 318 | J19: 228 | K19: -45 | L19: 185 | M19: 216 | N19: 228 | O19: 178 | P19: -58 | Q19: 210 | R19: 219 | S19: 890 | T19: -280 | U19: -563 | V19: 41 | W19: -53 | X19: -81 | Y19: 478 | Z19: 549 | AA19: =-'Balance Sheet'!AA80-'Balance Sheet'!AA81 -> 868.55949 | AB19: =-'Balance Sheet'!AB80-'Balance Sheet'!AB81 -> 391.72276 | AC19: =-'Balance Sheet'!AC80-'Balance Sheet'!AC81 -> 743.04259 | AD19: =-'Balance Sheet'!AD80-'Balance Sheet'!AD81 -> 411.8263 | AE19: =-'Balance Sheet'!AE80-'Balance Sheet'!AE81 -> 161.38638 | AF19: =-'Balance Sheet'!AF80-'Balance Sheet'!AF81 -> -207.54289
A20: Change in contract assets and liabilities | S20: =86+10 -> 96 | T20: =746+2 -> 748 | U20: =218+11 -> 229 | V20: =-982-17 -> -999 | W20: =131-43 -> 88 | X20: =2451-118 -> 2333 | Y20: =2073-103 -> 1970 | Z20: =1004-89 -> 915 | AA20: =-('Balance Sheet'!AA44-'Balance Sheet'!Z44)-('Balance Sheet'!AA25-'Balance Sheet'!Z25) -> 0 | AB20: =-('Balance Sheet'!AB44-'Balance Sheet'!AA44)-('Balance Sheet'!AB25-'Balance Sheet'!AA25) -> 0 | AC20: =-('Balance Sheet'!AC44-'Balance Sheet'!AB44)-('Balance Sheet'!AC25-'Balance Sheet'!AB25) -> 0 | AD20: =-('Balance Sheet'!AD44-'Balance Sheet'!AC44)-('Balance Sheet'!AD25-'Balance Sheet'!AC25) -> 0 | AE20: =-('Balance Sheet'!AE44-'Balance Sheet'!AD44)-('Balance Sheet'!AE25-'Balance Sheet'!AD25) -> 0 | AF20: =-('Balance Sheet'!AF44-'Balance Sheet'!AE44)-('Balance Sheet'!AF25-'Balance Sheet'!AE25) -> 0
A21: Change in other receivables and payables | H21: 58 | I21: -10 | J21: 18 | K21: -5 | L21: 77 | M21: -35 | N21: 75 | O21: -68 | P21: 132 | Q21: 75 | R21: -40 | S21: -15 | T21: -102 | U21: 27 | V21: -66 | W21: -81 | X21: 22 | Y21: -196 | Z21: -5
A22: Change in Working Capital | W22: =W18+W19+W20+W21 -> 250 | X22: =X18+X19+X20+X21 -> 729 | Y22: =Y18+Y19+Y20+Y21 -> 758 | Z22: =Z18+Z19+Z20+Z21 -> 7 | AA22: =AA18+AA19+AA20+AA21 -> 203.40239 | AB22: =AB18+AB19+AB20+AB21 -> 254.32099 | AC22: =AC18+AC19+AC20+AC21 -> -104.50791 | AD22: =AD18+AD19+AD20+AD21 -> -454.17326 | ... AF22: =AF18+AF19+AF20+AF21 -> -903.4025
A23: Other | H23: =H24-SUM(H4:H21) -> 11.946961 | I23: =I24-SUM(I4:I21) -> 77.94719 | J23: =J24-SUM(J4:J21) -> -156.05252 | K23: =K24-SUM(K4:K21) -> 39.945733 | L23: =L24-SUM(L4:L21) -> -19.054951 | M23: =M24-SUM(M4:M5,M7,M9:M21) -> -52 | N23: =N24-SUM(N4:N5,N7,N9:N21) -> -336 | O23: =O24-SUM(O4:O5,O7,O9:O21) -> 145 | P23: =P24-SUM(P4:P5,P7,P9:P21) -> 0 | Q23: =Q24-SUM(Q4:Q5,Q7,Q9:Q21) -> -11 | R23: =R24-SUM(R4:R5,R7,R9:R21) -> 0 | S23: =S24-SUM(S4:S5,S7,S9:S21) -> 0 | T23: =T24-SUM(T4:T5,T7,T9:T21) -> 0 | ... AF23: =AF24-SUM(AF4:AF5,AF7,AF9:AF21) -> 0
A24: Cash flow from Operations | H24: 854 | I24: =1013+95 -> 1108 | J24: =720-94 -> 626 | K24: =1403+5 -> 1408 | L24: =1459-29 -> 1430 | M24: =1247-10 -> 1237 | N24: 1617 | O24: 2139 | P24: 2357 | Q24: 2631 | R24: =SUM(R4:R5,R7,R9:R21) -> 2483 | S24: =SUM(S4:S5,S7,S9:S21) -> 2752 | T24: =SUM(T4:T5,T7,T9:T21) -> 3071 | U24: =SUM(U4:U5,U7,U9:U21) -> 3145 | V24: =SUM(V4:V5,V7,V9:V21) -> 1866 | W24: =SUM(W4:W5,W7,W9:W17)+W22 -> 2436 | X24: =SUM(X4:X5,X7,X9:X17)+X22 -> 3545 | Y24: =SUM(Y4:Y5,Y7,Y9:Y17)+Y22 -> 4270 | Z24: =SUM(Z4:Z5,Z7,Z9:Z17)+Z22 -> 4733 | AA24: =SUM(AA4:AA5,AA7,AA9:AA17)+AA22 -> 5741.0139 | AB24: =SUM(AB4:AB5,AB7,AB9:AB21) -> 6486.6147 | AC24: =SUM(AC4:AC5,AC7,AC9:AC21) -> 7059.7484 | AD24: =SUM(AD4:AD5,AD7,AD9:AD21) -> 7619.1304 | AE24: =SUM(AE4:AE5,AE7,AE9:AE21) -> 7964.6973 | AF24: =SUM(AF4:AF5,AF7,AF9:AF21) -> 8257.2897
A26: Purchase of Intangible assets (net of disposals) | H26: -343 | I26: -252 | J26: -230 | K26: -292 | L26: -254 | M26: -363 | N26: -634 | O26: =-720-215 -> -935 | P26: =-676-267 -> -943 | Q26: =-495-502 -> -997 | R26: -324 | S26: =-225-349 -> -574 | T26: =-183-327 -> -510 | U26: =-333-134 -> -467 | V26: =-287-57 -> -344 | W26: =-316-53 -> -369 | X26: =-283-98 -> -381 | Y26: =-323-179 -> -502 | Z26: =-328-172 -> -500 | AA26: =Z26-50 -> -550 | AB26: =AA26 -> -550 | AC26: =AB26 -> -550 | AD26: =AC26 -> -550 | AE26: =AD26 -> -550 | AF26: =AE26 -> -550 | AG26: pretty flat over CMD plan
A27: as a % of sales | H27: =H26/'Income Statement'!H$41 -> -0.031639148 | I27: =I26/'Income Statement'!I$41 -> -0.025941939 | J27: =J26/'Income Statement'!J$41 -> -0.022371365 | K27: =K26/'Income Statement'!K$41 -> -0.027654134 | L27: =L26/'Income Statement'!L$41 -> -0.023032281 | M27: =M26/'Income Statement'!M$41 -> -0.031137416 | N27: =N26/'Income Statement'!N$41 -> -0.046566287 | O27: =O26/'Income Statement'!O$41 -> -0.06452726 | ... AF27: =AF26/'Income Statement'!AF$41 -> -0.011755385
A28: Purchase of PP&E (net of disposals) | H28: -346 | I28: -387 | J28: -441 | K28: -293 | L28: -271 | M28: -352 | N28: -419 | O28: -492 | P28: -674 | Q28: -705 | R28: -704 | S28: -740 | T28: -780 | U28: -695 | V28: -449 | W28: -387 | X28: -498 | Y28: -823 | Z28: -1044 | AA28: =AA29*'Income Statement'!AA$41 -> -1577.8284 | AB28: =AB29*'Income Statement'!AB$41 -> -1604.4179 | AC28: =AC29*'Income Statement'!AC$41 -> -1569.3017 | AD28: =AD29*'Income Statement'!AD$41 -> -1479.8732 | AE28: =AE29*'Income Statement'!AE$41 -> -1338.6195 | AF28: =AF29*'Income Statement'!AF$41 -> -1169.6767 | AG28: Use of Cash Analysis
A29: as a % of sales | H29: =H28/'Income Statement'!H$41 -> -0.031915875 | I29: =I28/'Income Statement'!I$41 -> -0.039839407 | J29: =J28/'Income Statement'!J$41 -> -0.04289466 | K29: =K28/'Income Statement'!K$41 -> -0.02774884 | L29: =L28/'Income Statement'!L$41 -> -0.024573812 | M29: =M28/'Income Statement'!M$41 -> -0.030193858 | N29: =N28/'Income Statement'!N$41 -> -0.030774881 | O29: =O28/'Income Statement'!O$41 -> -0.033954451 | ... Z29: =Z28/'Income Statement'!Z$41 -> -0.037667773 | AA29: -0.05 | AB29: =AA29+0.005 -> -0.045 | AC29: =AB29+0.005 -> -0.04 | AD29: =AC29+0.005 -> -0.035 | AE29: =AD29+0.005 -> -0.03 | AF29: =AE29+0.005 -> -0.025 | AG29: CMD'24 p77: c.4% tangible capex with a peak @5% in 2025
A30: Proceeds/(Payments) from Investments | H30: =-53+14 -> -39 | I30: -68 | J30: -221 | K30: -560 | L30: -122 | M30: -1176 | N30: -193 | O30: =-733+353 -> -380 | P30: =-272+5 -> -267 | Q30: =622-39 -> 583 | R30: -810 | S30: -54 | T30: -4172 | U30: -29 | V30: -21 | W30: -33 | X30: -490 | Y30: -328 | Z30: -344 | AA30: =Z30 -> -344 | AB30: =AA30 -> -344 | AC30: =AB30 -> -344 | AD30: =AC30 -> -344 | AE30: =AD30 -> -344 | AF30: =AE30 -> -344
A31: of which additions to PP&E | R31: =R30*0.5 -> -405 | S31: =S30*0.5 -> -27 | T31: =T30*0.5 -> -2086 | U31: =U30*0.5 -> -14.5 | V31: =V30*0.5 -> -10.5 | W31: =W30*0.5 -> -16.5 | X31: =X30*0.5 -> -245 | Y31: =Y30*0.5 -> -164 | ... AF31: =AF30*0.5 -> -172 | AG31: historical goodwill/purchase price has been 50/50
A32: of which additions to Intangibles (Goodwill) | R32: =R30-R31 -> -405 | S32: =S30-S31 -> -27 | T32: =T30-T31 -> -2086 | U32: =U30-U31 -> -14.5 | V32: =V30-V31 -> -10.5 | W32: =W30-W31 -> -16.5 | X32: =X30-X31 -> -245 | Y32: =Y30-Y31 -> -164 | ... AF32: =AF30-AF31 -> -172
A33: Proceeds/(Payments) from Financial Assets | H33: 13 | I33: -26 | J33: 109 | K33: -9 | L33: -53 | M33: -6 | N33: -86 | O33: -35 | P33: -70 | Q33: -61 | R33: 5 | S33: -1974 | T33: 1950 | U33: 39 | V33: 14 | W33: -212 | X33: -167 | Y33: -202 | Z33: -73
A34: Other | H34: =H35-SUM(H26,H28,H30:H33) -> 9 | I34: =I35-SUM(I26,I28,I30:I33) -> -34 | J34: =J35-SUM(J26,J28,J30:J33) -> -12 | K34: =K35-SUM(K26,K28,K30:K33) -> 0 | L34: =L35-SUM(L26,L28,L30:L33) -> 1 | M34: =M35-SUM(M26,M28,M30:M33) -> -2 | N34: =N35-SUM(N26,N28,N30:N33) -> 0 | O34: =O35-SUM(O26,O28,O30,O33) -> 0 | P34: =P35-SUM(P26,P28,P30,P33) -> 0 | Q34: =Q35-SUM(Q26,Q28,Q30,Q33) -> 0 | R34: =-364+2 -> -362 | S34: =3060 -> 3060 | T34: =18 -> 18 | U34: 47 | V34: 1 | W34: 263 | X34: 248 | Y34: 151 | Z34: 113 | AA34: =AA35-SUM(AA26,AA28,AA30,AA33) -> 0 | AB34: =AB35-SUM(AB26,AB28,AB30,AB33) -> 0 | AC34: =AC35-SUM(AC26,AC28,AC30,AC33) -> 0 | AD34: =AD35-SUM(AD26,AD28,AD30,AD33) -> 0 | AE34: =AE35-SUM(AE26,AE28,AE30,AE33) -> 0 | AF34: =AF35-SUM(AF26,AF28,AF30,AF33) -> 0
A35: Cash flow from Investing | H35: -706 | I35: =-734-33 -> -767 | J35: =-788-7 -> -795 | K35: -1154 | L35: -699 | M35: =-1897-2 -> -1899 | N35: -1332 | O35: -1842 | P35: -1954 | Q35: -1180 | R35: =SUM(R26,R28,R30,R33,R34) -> -2195 | S35: =SUM(S26,S28,S30,S33,S34) -> -282 | T35: =SUM(T26,T28,T30,T33,T34) -> -3494 | U35: =SUM(U26,U28,U30,U33,U34) -> -1105 | V35: =SUM(V26,V28,V30,V33,V34) -> -799 | W35: =SUM(W26,W28,W30,W33,W34) -> -738 | X35: =SUM(X26,X28,X30,X33,X34) -> -1288 | Y35: =SUM(Y26,Y28,Y30,Y33,Y34) -> -1704 | Z35: =SUM(Z26,Z28,Z30,Z33,Z34) -> -1848 | AA35: =SUM(AA26,AA28,AA30,AA33) -> -2471.8284 | AB35: =SUM(AB26,AB28,AB30,AB33) -> -2498.4179 | AC35: =SUM(AC26,AC28,AC30,AC33) -> -2463.3017 | AD35: =SUM(AD26,AD28,AD30,AD33) -> -2373.8732 | AE35: =SUM(AE26,AE28,AE30,AE33) -> -2232.6195 | AF35: =SUM(AF26,AF28,AF30,AF33) -> -2063.6767
A37: Change in Share Capital | H37: 8 | I37: 19 | J37: 0 | K37: 1 | L37: 6 | M37: 1 | N37: 0 | Q37: -5 | R37: -9 | S37: -4 | T37: -1 | U37: =2-9 -> -7 | V37: 0 | W37: 1 | X37: 0 | Y37: 2 | Z37: 0
A38: Acquisitions and disposals of treasury shares | I38: 0 | J38: -151 | K38: 5 | L38: 0 | M38: 180 | N38: 118 | O38: 2 | P38: -1 | R38: -38 | S38: -449 | T38: -539 | U38: -1299 | V38: 96 | W38: -73 | X38: -270 | Y38: -1535 | Z38: -1320
A39: Repayment of borrowings and long-term debt | H39: -129 | I39: -86 | J39: -93 | K39: -218 | L39: -138 | M39: -254 | N39: -119 | O39: -111 | P39: -850 | Q39: -79 | R39: -73 | S39: -66 | T39: -1895 | U39: -875 | V39: -778 | W39: -1367 | X39: -654 | Y39: -311 | Z39: -863
A40: Increase in borrowings | H40: 67 | I40: 24 | J40: 136 | K40: 794 | L40: 324 | M40: 32 | N40: 917 | O40: 9 | P40: 209 | Q40: 12 | R40: 682 | S40: 1058 | T40: 1480 | U40: 24 | V40: 1595 | W40: 2146 | X40: 510 | Y40: 17 | Z40: 56 | AA40: 0 | AB40: 0 | AC40: 0 | AD40: 0 | AE40: 0 | AF40: 0
A41: Change in repayable advances | H41: =71-46 -> 25 | I41: =41-57 -> -16 | J41: =112-31 -> 81 | K41: =-36+69 -> 33 | L41: =-35+17 -> -18 | M41: -15 | N41: -9 | O41: -27 | P41: 3 | Q41: -14 | R41: -24 | S41: -25 | T41: -10 | U41: -27 | V41: -10 | W41: -12 | X41: -17 | Y41: -5 | Z41: -21
A42: Change in short term borrowings | H42: -151 | I42: -97 | J42: 465 | K42: 381 | L42: -802 | M42: 390 | N42: -122 | O42: -191 | P42: 809 | Q42: -631 | R42: 10 | S42: 449 | T42: -472 | U42: 1261 | V42: -831 | W42: -775 | X42: -159 | Y42: -161 | Z42: 45
A43: Dividends Paid | H43: -148 | I43: -90 | J43: -197 | K43: -68 | L43: -152 | M43: -304 | N43: -283 | O43: -471 | P43: -500 | Q43: -517 | R43: -612 | S43: -340 | T43: -695 | U43: -785 | V43: 0 | W43: -183 | X43: -213 | Y43: -564 | Z43: -911 | AA43: =-((AA44*'Income Statement'!Z116)+(AA45*'Income Statement'!AA116))/1000 -> -1206.8336 | AB43: =-((AB44*'Income Statement'!AA116)+(AB45*'Income Statement'!AB116))/1000 -> -1408.1542 | AC43: =-((AC44*'Income Statement'!AB116)+(AC45*'Income Statement'!AC116))/1000 -> -1811.2993 | AD43: =-((AD44*'Income Statement'!AC116)+(AD45*'Income Statement'!AD116))/1000 -> -2060.4443 | AE43: =-((AE44*'Income Statement'!AD116)+(AE45*'Income Statement'!AE116))/1000 -> -2278.41 | AF43: =-((AF44*'Income Statement'!AE116)+(AF45*'Income Statement'!AF116))/1000 -> -2442.0179
A44: Final From Previous Year (€) | J44: 0.4 | K44: 0.25 | L44: 0.38 | M44: 0.5 | N44: 0.37 | O44: ='Income Statement'!N109-N45 -> 0.65 | P44: ='Income Statement'!O109-O45 -> 0.64 | Q44: 0.64 | R44: ='Income Statement'!Q109-Q45 -> 0.78 | S44: ='Income Statement'!R109-R45 -> 0.92 | T44: ='Income Statement'!S109-S45 -> 1.6 | U44: ='Income Statement'!T109-T45 -> 1.82 | V44: ='Income Statement'!U109-U45 -> 0 | W44: ='Income Statement'!V109-V45 -> 0.43 | X44: ='Income Statement'!W109-W45 -> 0.5 | Y44: ='Income Statement'!X109-X45 -> 1.35 | ... AF44: ='Income Statement'!AE109-AE45 -> 6.1326008
A45: Interim from Reported Year (€) | J45: 0.08 | K45: 0 | L45: 0 | M45: 0.25 | N45: 0.31 | O45: 0.48 | P45: ='Income Statement'!P109-Q44 -> 0.56 | Q45: 0.6 | R45: =Q45*(1+'Income Statement'!R111) -> 0.6
A46: Dividends paid to non-controlling interests | H46: -7 | I46: -6 | J46: -5 | K46: -5 | L46: -9 | M46: -13 | N46: -17 | O46: -10 | P46: -11 | Q46: -23 | R46: -30 | S46: -32 | T46: -26 | U46: -32 | V46: -4 | W46: -5 | X46: -12 | Y46: -19 | Z46: -59
A47: Share Buybacks | H47: 0 | I47: 0 | J47: 0 | K47: 0 | L47: 0 | M47: 0 | N47: 0 | O47: 0 | AA47: =-5000/4 -> -1250 | AB47: =-5000/4 -> -1250 | AC47: =-5000/4 -> -1250 | AD47: =-5000/4 -> -1250
A48: Other | H48: =H49-SUM(H37:H43,H46) -> 0 | I48: =I49-SUM(I37:I43,I46) -> -63 | J48: =J49-SUM(J37:J43,J46) -> 135 | K48: =K49-SUM(K37:K43,K46) -> -31 | L48: =L49-SUM(L37:L43,L46) -> 28 | M48: =M49-SUM(M37:M43,M46) -> 11 | N48: =N49-SUM(N37:N43,N46) -> 0 | O48: =O49-SUM(O37:O43,O46:O47) -> 0 | P48: =P49-SUM(P37:P43,P46:P47) -> 0 | Q48: =Q49-SUM(Q37:Q43,Q46:Q47) -> 0 | R48: =R49-SUM(R37:R43,R46:R47) -> 0 | S48: =S49-SUM(S37:S43,S46:S47) -> 0 | T48: =T49-SUM(T37:T43,T46:T47) -> 0 | U48: =U49-SUM(U37:U43,U46:U47) -> 0 | V48: =V49-SUM(V37:V43,V46:V47) -> 0 | ... X48: =X49-SUM(X37:X43,X46:X47) -> 0 | Y48: =Y49-SUM(Y37:Y43,Y46) -> 0 | Z48: =Z49-SUM(Z37:Z43,Z46) -> 0 | AA48: =AA49-SUM(AA37:AA43,AA46:AA47) -> 0 | AB48: =AB49-SUM(AB37:AB43,AB46:AB47) -> 0 | AC48: =AC49-SUM(AC37:AC43,AC46:AC47) -> 0 | AD48: =AD49-SUM(AD37:AD43,AD46:AD47) -> 0 | AE48: =AE49-SUM(AE37:AE43,AE46:AE47) -> 0 | AF48: =AF49-SUM(AF37:AF43,AF46:AF47) -> 0
A49: Cash flow from Financing | H49: -335 | I49: =-316+1 -> -315 | J49: =369+2 -> 371 | K49: =893-1 -> 892 | L49: -761 | M49: 28 | N49: 485 | O49: -799 | P49: -341 | Q49: -1257 | R49: =SUM(R37:R43,R46:R47) -> -94 | S49: =SUM(S37:S43,S46:S47) -> 591 | T49: =SUM(T37:T43,T46:T47) -> -2158 | U49: =SUM(U37:U43,U46:U47) -> -1740 | V49: =SUM(V37:V43,V46:V47) -> 68 | W49: =SUM(W37:W43,W46:W47) -> -268 | X49: =SUM(X37:X43,X46:X47) -> -815 | Y49: =SUM(Y37:Y43,Y46) -> -2576 | Z49: =SUM(Z37:Z43,Z46) -> -3073 | AA49: =SUM(AA37:AA43,AA46:AA47) -> -2456.8336 | AB49: =SUM(AB37:AB43,AB46:AB47) -> -2658.1542 | AC49: =SUM(AC37:AC43,AC46:AC47) -> -3061.2993 | AD49: =SUM(AD37:AD43,AD46:AD47) -> -3310.4443 | AE49: =SUM(AE37:AE43,AE46:AE47) -> -2278.41 | AF49: =SUM(AF37:AF43,AF46:AF47) -> -2442.0179
A51: Change in Cash | H51: =H24+H35+H49 -> -187 | I51: =I24+I35+I49 -> 26 | J51: =J24+J35+J49 -> 202 | K51: =K24+K35+K49 -> 1146 | L51: =L24+L35+L49 -> -30 | M51: =M24+M35+M49 -> -634 | N51: =N24+N35+N49 -> 770 | O51: =O24+O35+O49 -> -502 | P51: =P24+P35+P49 -> 62 | Q51: =Q24+Q35+Q49+121-88-21 -> 206 | R51: =R24+R35+R49+(171-111-8) -> 246 | S51: =S24+S35+S49+(14-52-198) -> 2825 | T51: =T24+T35+T49 -> -2581 | U51: =U24+U35+U49 -> 300 | V51: =V24+V35+V49 -> 1135 | W51: =W24+W35+W49 -> 1430 | X51: =X24+X35+X49 -> 1442 | Y51: =Y24+Y35+Y49 -> -10 | Z51: =Z24+Z35+Z49 -> -188 | AA51: =AA24+AA35+AA49 -> 812.35179 | ... AF51: =AF24+AF35+AF49 -> 3751.5951
A52: FX | H52: -6 | I52: -2 | J52: -2 | K52: 4 | L52: 12 | M52: 3 | N52: -8 | O52: -19 | P52: 24 | Q52: 6 | R52: 15 | S52: -17 | T52: -3 | U52: 2 | V52: -20 | W52: 70 | X52: -2 | Y52: -1 | Z52: 26
A53: Other | I53: -37 | J53: -11 | K53: 11 | O53: -125 | S53: 180
A54: Cash at the beginning of the year | H54: 936 | I54: 743 | J54: 730 | K54: 919 | L54: 2080 | M54: 2062 | N54: 1431 | O54: =N55 -> 2193 | P54: =O55 -> 1547 | Q54: =P55 -> 1633 | R54: =Q55+186 -> 1845 | S54: =R55 -> 1926 | T54: =S55 -> 4914 | U54: =T55 -> 2330 | V54: =U55 -> 2632 | W54: =V55 -> 3747 | X54: =W55 -> 5247 | Y54: =X55 -> 6687 | Z54: =Y55 -> 6676 | ... AF54: =AE55 -> 15580.022
A55: Cash at the end of the year | H55: =SUM(H51:H54) -> 743 | I55: =SUM(I51:I54) -> 730 | J55: =SUM(J51:J54) -> 919 | K55: =SUM(K51:K54) -> 2080 | L55: =SUM(L51:L54) -> 2062 | M55: =SUM(M51:M54) -> 1431 | N55: =SUM(N51:N54) -> 2193 | O55: =SUM(O51:O54) -> 1547 | P55: =SUM(P51:P54) -> 1633 | Q55: =SUM(Q51:Q54)-186 -> 1659 | R55: =SUM(R51:R54)-180 -> 1926 | S55: =SUM(S51:S54) -> 4914 | T55: =SUM(T51:T54) -> 2330 | U55: =SUM(U51:U54) -> 2632 | V55: =SUM(V51:V54) -> 3747 | W55: =SUM(W51:W54) -> 5247 | X55: =SUM(X51:X54) -> 6687 | Y55: =SUM(Y51:Y54) -> 6676 | Z55: =SUM(Z51:Z54) -> 6514 | ... AF55: =SUM(AF51:AF54) -> 19331.618
A57: Company defined FCF | H57: =H24+SUM(H26,H28) -> 165 | I57: =I24+SUM(I26,I28)-95 -> 374 | J57: =J24+SUM(J26,J28)+94 -> 49 | K57: =K24+SUM(K26,K28)-5 -> 818 | L57: =L24+SUM(L26,L28)+29 -> 934 | M57: =M24+SUM(M26,M28)+10 -> 532 | N57: =N24+SUM(N26,N28)+1 -> 565 | O57: =O24+SUM(O26,O28) -> 712 | P57: =P24+SUM(P26,P28) -> 740 | Q57: =Q24+SUM(Q26,Q28) -> 929 | R57: =R24+SUM(R26,R28) -> 1455 | S57: =S24+SUM(S26,S28) -> 1438 | T57: =T24+SUM(T26,T28) -> 1781 | U57: =U24+SUM(U26,U28) -> 1983 | V57: =V24+SUM(V26,V28) -> 1073 | ... AF57: =AF24+SUM(AF26,AF28) -> 6537.613 | AG57: Company guide to 15-17bn cumulative FCF; 3.4-3.6bn FY25 | AH57: =SUM(Z57:AD57) -> 21664.086 | AI57: =3189+3227+4114+4700+5319 -> 20549
A58: % of underlying EBITA | O58: -4.5063291 | P58: -4.2285714 | Q58: -11.329268 | R58: -58.2 | S58: -39.944444 | T58: 0.58914985 | U58: 0.51910995 | V58: 0.63641756 | W58: 0.93074792 | X58: 1.1071429 | Y58: 0.93019583 | Z58: 0.77421704 | AA58: =AA57/'Income Statement'!AA70 -> 0.69256663 | AB58: =AB57/'Income Statement'!AB70 -> 0.70518318 | AC58: =AC57/'Income Statement'!AC70 -> 0.70779814 | AD58: =AD57/'Income Statement'!AD70 -> 0.72563038 | AE58: =AE57/'Income Statement'!AE70 -> 0.73775266 | AF58: =AF57/'Income Statement'!AF70 -> 0.74400574 | AG58: Below Cons on FCF on all years
A59: FCF per share | T59: =T57/'Income Statement'!T116*1000 -> 4.1330963 | U59: =U57/'Income Statement'!U116*1000 -> 4.6145966 | V59: =V57/'Income Statement'!V116*1000 -> 2.5185681 | W59: =W57/'Income Statement'!W116*1000 -> 3.9376499 | X59: =X57/'Income Statement'!X116*1000 -> 6.2482326 | Y59: =Y57/'Income Statement'!Y116*1000 -> 7.0489032 | Z59: =Z57/'Income Statement'!Z116*1000 -> 7.6631109 | AA59: =AA57/'Income Statement'!AA116*1000 -> 8.7770509 | ... AF59: =AF57/'Income Statement'!AF116*1000 -> 16.417804
A61: Unlevered op cash flow, post tax, post capex | B61: =B2 -> 2000 | C61: =C2 -> 2001 | D61: =D2 -> 2002 | E61: =E2 -> 2003 | F61: =F2 -> 2004 | G61: =G2 -> 2005 | H61: =H2 -> 2006 | I61: =I2 -> 2007 | ... Z61: =Z2 -> 2024 | AA61: =Z61+1 -> 2025 | AB61: =AA61+1 -> 2026 | AC61: =AB61+1 -> 2027 | AD61: =AC61+1 -> 2028 | AE61: =AD61+1 -> 2029 | AF61: =AE61+1 -> 2030
A62: Cash provided by operating activities | W62: =W24 -> 2436 | X62: =X24 -> 3545 | Y62: =Y24 -> 4270 | Z62: =Z24 -> 4733 | AA62: =AA24 -> 5741.0139 | AB62: =AB24 -> 6486.6147 | AC62: =AC24 -> 7059.7484 | AD62: =AD24 -> 7619.1304 | ... AF62: =AF24 -> 8257.2897
A63: add back:
A64: Tax paid/(Tax refund) | W64: 302 | X64: 233 | Y64: 988 | Z64: 935 | AA64: =-AA17-'Income Statement'!AA88 -> 1375.9454 | AB64: =-AB17-'Income Statement'!AB88 -> 1697.9721 | AC64: =-AC17-'Income Statement'!AC88 -> 1982.1808 | AD64: =-AD17-'Income Statement'!AD88 -> 1969.4923 | AE64: =-AE17-'Income Statement'!AE88 -> 2110.1456 | AF64: =-AF17-'Income Statement'!AF88 -> 2259.6939
A65: Interest Paid | W65: 79 | X65: 87 | Y65: 116 | Z65: =-'Income Statement'!Z121 -> 92 | AA65: =-'Income Statement'!AA121 -> 121.825 | AB65: =-'Income Statement'!AB121 -> 105.072 | AC65: =-'Income Statement'!AC121 -> 105.072 | AD65: =-'Income Statement'!AD121 -> 105.072 | AE65: =-'Income Statement'!AE121 -> 105.072 | AF65: =-'Income Statement'!AF121 -> 105.072
A66: Less: Interest income | W66: =-'Income Statement'!W122 -> -15 | X66: =-'Income Statement'!X122 -> -38 | Y66: -229 | Z66: =-'Income Statement'!Z122 -> -249 | AA66: =-'Income Statement'!AA122 -> -235.81 | AB66: =-'Income Statement'!AB122 -> -233.5966 | AC66: =-'Income Statement'!AC122 -> -253.77305 | AD66: =-'Income Statement'!AD122 -> -280.41842 | AE66: =-'Income Statement'!AE122 -> -309.72638 | AF66: =-'Income Statement'!AF122 -> -356.801
A68: Deduct:
A69: Purchase of PP&E | W69: =W28 -> -387 | X69: =X28 -> -498 | Y69: =Y28 -> -823 | Z69: =Z28 -> -1044 | AA69: =AA28 -> -1577.8284 | AB69: =AB28 -> -1604.4179 | AC69: =AC28 -> -1569.3017 | AD69: =AD28 -> -1479.8732 | ... AF69: =AF28 -> -1169.6767
A70: Purchase of intangible assets | W70: =W26 -> -369 | X70: =X26 -> -381 | Y70: =Y26 -> -502 | Z70: =Z26 -> -500 | AA70: =AA26 -> -550 | AB70: =AB26 -> -550 | AC70: =AC26 -> -550 | AD70: =AD26 -> -550 | ... AF70: =AF26 -> -550
A71: Operating cash flow | W71: =SUM(W62:W70) -> 2046 | X71: =SUM(X62:X70) -> 2948 | Y71: =SUM(Y62:Y70) -> 3820 | Z71: =SUM(Z62:Z70) -> 3967 | AA71: =SUM(AA62:AA70) -> 4875.1458 | AB71: =SUM(AB62:AB70) -> 5901.6443 | AC71: =SUM(AC62:AC70) -> 6773.9264 | AD71: =SUM(AD62:AD70) -> 7383.403 | ... AF71: =SUM(AF62:AF70) -> 8545.5779
A72: EBIT | W72: ='Income Statement'!W74 -> 1400 | X72: ='Income Statement'!X74 -> 1958 | Y72: ='Income Statement'!Y74 -> 2655 | Z72: ='Income Statement'!Z74 -> 4125 | AA72: ='Income Statement'!AA74 -> 5217.0943 | AB72: ='Income Statement'!AB74 -> 6143.3638 | AC72: ='Income Statement'!AC74 -> 6980.0222 | AD72: ='Income Statement'!AD74 -> 7702.6228 | ... AF72: ='Income Statement'!AF74 -> 8787.0465
A73: Cash Conversion | W73: =W71/W72 -> 1.4614286 | X73: =X71/X72 -> 1.505618 | Y73: =Y71/Y72 -> 1.4387947 | Z73: =Z71/Z72 -> 0.96169697 | AA73: =AA71/AA72 -> 0.93445614 | AB73: =AB71/AB72 -> 0.96065356 | AC73: =AC71/AC72 -> 0.97047348 | AD73: =AD71/AD72 -> 0.958557 | ... AF73: =AF71/AF72 -> 0.97251994

Sheet Interim (New)
B1: 2011 | C1: 2011 | D1: 2011 | E1: 2011 | F1: 2011 | G1: 2011 | H1: 2011 | I1: 2011 | J1: 2012 | K1: 2012 | L1: 2012 | M1: 2012 | N1: 2012 | O1: 2012 | P1: 2012 | Q1: 2012 | R1: 2013 | S1: 2013 | T1: 2013 | U1: 2013 | V1: 2013 | W1: 2013 | X1: 2013 | Y1: 2013 | Z1: 2014 | AA1: 2014 | AB1: 2014 | AC1: 2014 | AD1: 2014 | AE1: 2014 | AF1: 2014 | AG1: 2014 | AH1: 2015 | AI1: =AH1 -> 2015 | AJ1: =AI1 -> 2015 | AK1: =AJ1 -> 2015 | AL1: =AK1 -> 2015 | AM1: =AL1 -> 2015 | AN1: =AM1 -> 2015 | AO1: =AN1 -> 2015 | AP1: 2016 | AQ1: =AP1 -> 2016 | AR1: =AQ1 -> 2016 | AS1: =AR1 -> 2016 | AT1: =AS1 -> 2016 | AU1: =AT1 -> 2016 | AV1: =AU1 -> 2016 | AW1: =AV1 -> 2016 | AX1: 2017 | AY1: =AX1 -> 2017 | AZ1: =AY1 -> 2017 | BA1: =AZ1 -> 2017 | BB1: =BA1 -> 2017 | BC1: =BB1 -> 2017 | BD1: =BC1 -> 2017 | BE1: =BD1 -> 2017 | BF1: 2018 | BG1: =BF1 -> 2018 | BH1: =BG1 -> 2018 | BI1: =BH1 -> 2018 | BJ1: =BI1 -> 2018 | BK1: =BJ1 -> 2018 | BL1: =BK1 -> 2018 | BM1: =BL1 -> 2018 | BN1: =BF1+1 -> 2019 | BO1: =BG1+1 -> 2019 | BP1: =BH1+1 -> 2019 | BQ1: =BI1+1 -> 2019 | BR1: =BJ1+1 -> 2019 | BS1: =BK1+1 -> 2019 | BT1: =BL1+1 -> 2019 | BU1: =BM1+1 -> 2019 | ... EG1: =DY1+1 -> 2027 | EJ1: Source | EM1: Company-Wide Outlook • Safran upgraded its full-year 2025 guidance across all metrics—revenue, EBIT, and free cash flow—reflecting strong execution and demand. • The company expects continued profitable growth and robust cash generation, supported by aftermarket strength and LEAP engine ramp-up. • Tariff impacts are being mitigated, with residual EBIT impact expected to be €100–150M in 2025 and around €100M annually going forward. • Share buyback program continues, with €1.4B in shares to be cancelled by year-end 2025 Propulsion • LEAP engine deliveries are expected to grow over 20% vs. 2024, with catch-up on delays nearly complete. Q3 numbers - Record 511 units in Q3 (+40% YoY); 1,240 delivered YTD (+21% YoY) • LEAP-related services are forecasted to grow in the low to mid-20% range, though with no additional EBIT due to fixed profit recognition • Civil aftermarket remains a key growth driver, especially CFM56 and high-thrust engines Equipment & Defense • Continued growth expected, driven by strong OE demand and defense momentum • Collins acquisition to contribute ~€650M (Aug - Dec) in revenue for FY25 with mid-single digit margins (pre-integration costs) • Integration is progressing well, with synergy opportunities already being explored across Safran’s systems teams Aircraft Interiors • Growth expected to continue, especially in cabin systems, supported by aircraft production ramp-up. • Seat business remains challenged by certification delays, but pricing improvements on recent wins should support margin recovery over the next two years. • Safran maintains seats as a core business, with no divestment planned • Safran reiterated plans to divest ~30% of ex-Zodiac portfolio (mostly interiors), but seats are not part of current divestment scope LEAP Engine & Production Capacity • Morocco Assembly Line: First LEAP engines from the Casablanca line expected in early 2028, with full ramp-up to 350 engines/year by 2030. • Rate 75 Discussions: Ongoing talks with Airbus; full-year rate 75 not confirmed for 2027, but capacity planning is underway. • Catch-Up Status: Confident in catching up on LEAP delivery delays by end-October or early November. Aftermarket & Services • LEAP RPFH Contracts: These now form the majority of services revenue. Growth is driven by more shop visits and performance restorations, but EBIT remains unchanged due to fixed profit recognition. • Spare Parts Breakdown: Growth driven by volume, pricing (mid- to high-single digit increases), and higher work scope—especially for high-thrust engines and CFM56.
B2: Q1 | C2: Q2 | D2: H1 | E2: Q3 | F2: 9M | G2: Q4 | H2: H2 | I2: FY | J2: Q1 | K2: Q2 | L2: H1 | M2: Q3 | N2: 9M | O2: Q4 | P2: H2 | Q2: FY | R2: Q1 | S2: Q2 | T2: H1 | U2: Q3 | V2: 9M | W2: Q4 | X2: H2 | Y2: FY | Z2: Q1 | AA2: Q2 | AB2: H1 | AC2: Q3 | AD2: 9M | AE2: Q4 | AF2: H2 | AG2: FY | AH2: Q1 | AI2: Q2 | AJ2: H1 | AK2: Q3 | AL2: 9M | AM2: Q4 | AN2: H2 | AO2: FY | AP2: Q1 | AQ2: Q2 | AR2: H1 | AS2: Q3 | AT2: 9M | AU2: Q4 | AV2: H2 | AW2: FY | AX2: Q1 | AY2: Q2 | AZ2: H1 | BA2: Q3 | BB2: 9M | BC2: Q4 | BD2: H2 | BE2: FY | BF2: Q1 | BG2: Q2 | BH2: H1 | BI2: Q3 | BJ2: 9M | BK2: Q4 | BL2: H2 | BM2: FY | BN2: Q1 | BO2: Q2 | BP2: H1 | BQ2: Q3 | BR2: 9M | BS2: Q4 | BT2: H2 | BU2: FY | BV2: =BN2 -> Q1 | BW2: =BO2 -> Q2 | BX2: =BP2 -> H1 | BY2: =BQ2 -> Q3 | BZ2: =BR2 -> 9M | CA2: =BS2 -> Q4 | CB2: =BT2 -> H2 | CC2: =BU2 -> FY | ... EG2: =DY2 -> FY | EJ2: Q3'25 transcript ->
A4: Divisional Summary | B4: =B1&" "&B2 -> 2011 Q1 | C4: =C1&" "&C2 -> 2011 Q2 | D4: =D1&" "&D2 -> 2011 H1 | E4: =E1&" "&E2 -> 2011 Q3 | F4: =F1&" "&F2 -> 2011 9M | G4: =G1&" "&G2 -> 2011 Q4 | H4: =H1&" "&H2 -> 2011 H2 | I4: =I1&" "&I2 -> 2011 FY | ... EG4: =EG1&" "&EG2 -> 2027 FY
A5: Adjusted Revenues
A6: Aerospace Propulsion | B6: 1423 | C6: 1554 | D6: =B6+C6 -> 2977 | E6: 1459 | F6: =D6+E6 -> 4436 | G6: 1674 | H6: =G6+E6 -> 3133 | I6: =H6+D6 -> 6110 | J6: 1585 | K6: 1681 | L6: =J6+K6 -> 3266 | M6: 1635 | N6: =L6+M6 -> 4901 | O6: 2104 | P6: =O6+M6 -> 3739 | Q6: =P6+L6 -> 7005 | R6: 1785 | S6: 1886 | T6: =R6+S6 -> 3671 | U6: 1771 | V6: =T6+U6 -> 5442 | W6: 2147 | X6: =W6+U6 -> 3918 | Y6: =X6+T6 -> 7589 | Z6: 1825 | AA6: 1938 | AB6: =Z6+AA6 -> 3763 | AC6: 1944 | AD6: =AB6+AC6 -> 5707 | AE6: 2446 | AF6: =AE6+AC6 -> 4390 | AG6: =AF6+AB6 -> 8153 | AH6: 2070 | AI6: 2416 | AJ6: =AH6+AI6 -> 4486 | AK6: 2220 | AL6: =AJ6+AK6 -> 6706 | AM6: 2613 | AN6: =AM6+AK6 -> 4833 | AO6: =AN6+AJ6 -> 9319 | AP6: 2301 | AQ6: 2556 | AR6: =AP6+AQ6 -> 4857 | AS6: 2056 | AT6: =AR6+AS6 -> 6913 | AU6: 2478 | AV6: =AU6+AS6 -> 4534 | AW6: =AV6+AR6 -> 9391 | AX6: 2360 | AY6: 2331 | AZ6: =AX6+AY6 -> 4691 | BA6: 2303 | BB6: =AZ6+BA6 -> 6994 | BC6: 2363 | BD6: =BC6+BA6 -> 4666 | BE6: =BD6+AZ6 -> 9357 | BF6: 2319 | BG6: 2486 | BH6: =BF6+BG6 -> 4805 | BI6: 2524 | BJ6: =BH6+BI6 -> 7329 | BK6: 3250 | BL6: =BK6+BI6 -> 5774 | BM6: =BL6+BH6 -> 10579 | BN6: 2771 | BO6: 3131 | BP6: =BN6+BO6 -> 5902 | BQ6: 2987 | BR6: =BP6+BQ6 -> 8889 | BS6: 3156 | BT6: =BS6+BQ6 -> 6143 | BU6: =BT6+BP6 -> 12045 | BV6: 2497 | BW6: 1550 | BX6: =BV6+BW6 -> 4047 | BY6: 1559 | BZ6: =BX6+BY6 -> 5606 | CA6: 2057 | CB6: =CA6+BY6 -> 3616 | CC6: =CB6+BX6 -> 7663 | CD6: 1561 | CE6: 1688 | CF6: =CD6+CE6 -> 3249 | CG6: 1812 | CH6: =CF6+CG6 -> 5061 | CI6: 2378 | CJ6: =CI6+CG6 -> 4190 | CK6: =INDEX('Income Statement'!5:5, MATCH('Interim (New)'!CK$1,'Income Statement'!$3:$3,0)) -> 7439 | CL6: 1942 | CM6: 2234 | CN6: =CL6+CM6 -> 4176 | CO6: 2503 | CP6: =CN6+CO6 -> 6679 | CQ6: 2827 | CR6: =CQ6+CO6 -> 5330 | CS6: =INDEX('Income Statement'!5:5, MATCH('Interim (New)'!CS$1,'Income Statement'!$3:$3,0)) -> 9506 | CT6: 2714 | CU6: 2963 | CV6: =CT6+CU6 -> 5677 | CW6: 3083 | CX6: =CV6+CW6 -> 8760 | CY6: 3116 | CZ6: =CY6+CW6 -> 6199 | DA6: =INDEX('Income Statement'!5:5, MATCH('Interim (New)'!DA$1,'Income Statement'!$3:$3,0)) -> 11876 | DB6: 3097 | DC6: 3364 | DD6: =DB6+DC6 -> 6461 | DE6: 3339 | DF6: =DD6+DE6 -> 9800 | DG6: 3852 | DH6: =DG6+DE6 -> 7191 | DI6: =INDEX('Income Statement'!5:5, MATCH('Interim (New)'!DI$1,'Income Statement'!$3:$3,0)) -> 13652 | DJ6: 3684 | DK6: 3857 | DL6: =DJ6+DK6 -> 7541 | DM6: 4044 | DN6: =DL6+DM6 -> 11585 | DO6: =DQ6-DN6 -> 4249.3771 | DP6: =DM6+DO6 -> 8293.3771 | DQ6: =INDEX('Income Statement'!5:5, MATCH('Interim (New)'!DQ$1,'Income Statement'!$3:$3,0)) -> 15834.377 | DR6: =(DB6/$DI$6)*$DY$6 -> 4039.4836 | DS6: =(DC6/$DI$6)*$DY$6 -> 4387.7375 | DT6: =(DD6/$DI$6)*$DY$6 -> 8427.2211 | DU6: =(DE6/$DI$6)*$DY$6 -> 4355.1294 | DV6: =(DF6/$DI$6)*$DY$6 -> 12782.35 | DW6: =(DG6/$DI$6)*$DY$6 -> 5024.2463 | DX6: =(DH6/$DI$6)*$DY$6 -> 9379.3757 | DY6: =INDEX('Income Statement'!5:5, MATCH('Interim (New)'!DY$1,'Income Statement'!$3:$3,0)) -> 17806.597
A7: Aircraft Equipment | B7: 729 | C7: 775 | D7: =B7+C7 -> 1504 | E7: 697 | F7: =D7+E7 -> 2201 | G7: 896 | H7: =G7+E7 -> 1593 | I7: =H7+D7 -> 3097 | J7: 883 | K7: 904 | L7: =J7+K7 -> 1787 | M7: 850 | N7: =L7+M7 -> 2637 | O7: 1054 | P7: =O7+M7 -> 1904 | Q7: =P7+L7 -> 3691 | R7: 915 | S7: 1030 | T7: =R7+S7 -> 1945 | U7: 982 | V7: =T7+U7 -> 2927 | W7: 1164 | X7: =W7+U7 -> 2146 | Y7: =X7+T7 -> 4091 | Z7: 1016 | AA7: 1121 | AB7: =Z7+AA7 -> 2137 | AC7: 1021 | AD7: =AB7+AC7 -> 3158 | AE7: 1288 | AF7: =AE7+AC7 -> 2309 | AG7: =AF7+AB7 -> 4446 | AH7: 1172 | AI7: 1242 | AJ7: =AH7+AI7 -> 2414 | AK7: 1180 | AL7: =AJ7+AK7 -> 3594 | AM7: 1349 | AN7: =AM7+AK7 -> 2529 | AO7: =AN7+AJ7 -> 4943 | AP7: 1219 | AQ7: 1323 | AR7: =AP7+AQ7 -> 2542 | AS7: 1208 | AT7: =AR7+AS7 -> 3750 | AU7: 1395 | AV7: =AU7+AS7 -> 2603 | AW7: =AV7+AR7 -> 5145 | AX7: 1335 | AY7: 1380 | AZ7: =AX7+AY7 -> 2715 | BA7: 1225 | BB7: =AZ7+BA7 -> 3940 | BC7: 1320 | BD7: =BC7+BA7 -> 2545 | BE7: =BD7+AZ7 -> 5260 | BF7: 1230 | BG7: 1294 | BH7: =BF7+BG7 -> 2524 | BI7: 1312 | BJ7: =BH7+BI7 -> 3836 | BK7: 1432 | BL7: =BK7+BI7 -> 2744 | BM7: =BL7+BH7 -> 5268 | BN7: 1422 | BO7: 1611.002 | BP7: =BN7+BO7 -> 3033.002 | BQ7: 1576.5842 | BR7: =BP7+BQ7 -> 4609.5862 | BS7: 1720.784 | BT7: =BS7+BQ7 -> 3297.3682 | BU7: =BT7+BP7 -> 6330.3702 | BV7: 937.11726 | BW7: 1061.6721 | BX7: =BV7+BW7 -> 1998.7894 | BY7: 1038.9904 | BZ7: =BX7+BY7 -> 3037.7797 | CA7: 1134.02 | CB7: =CA7+BY7 -> 2173.0103 | CC7: =CB7+BX7 -> 4171.7997 | CD7: 830.18233 | CE7: 940.52416 | CF7: =CD7+CE7 -> 1770.7065 | CG7: 920.43063 | CH7: =CF7+CG7 -> 2691.1371 | CI7: 1004.6164 | CJ7: =CI7+CG7 -> 1925.047 | CL7: 1081.9079
A8: Defence | B8: 292 | C8: 332 | D8: =B8+C8 -> 624 | E8: 251 | F8: =D8+E8 -> 875 | G8: 389 | H8: =G8+E8 -> 640 | I8: =H8+D8 -> 1264 | J8: 307 | K8: 333 | L8: =J8+K8 -> 640 | M8: 276 | N8: =L8+M8 -> 916 | O8: 399 | P8: =O8+M8 -> 675 | Q8: =P8+L8 -> 1315 | R8: 292 | S8: 274 | T8: =R8+S8 -> 566 | U8: 258 | V8: =T8+U8 -> 824 | W8: 373 | X8: =W8+U8 -> 631 | Y8: =X8+T8 -> 1197 | Z8: 257 | AA8: 327 | AB8: =Z8+AA8 -> 584 | AC8: 256 | AD8: =AB8+AC8 -> 840 | AE8: 381 | AF8: =AE8+AC8 -> 637 | AG8: =AF8+AB8 -> 1221 | AH8: 278 | AI8: 338 | AJ8: =AH8+AI8 -> 616 | AK8: 266 | AL8: =AJ8+AK8 -> 882 | AM8: 384 | AN8: =AM8+AK8 -> 650 | AO8: =AN8+AJ8 -> 1266 | AP8: 269 | AQ8: 315 | AR8: =AP8+AQ8 -> 584 | AS8: 253 | AT8: =AR8+AS8 -> 837 | AU8: 401 | AV8: =AU8+AS8 -> 654 | AW8: =AV8+AR8 -> 1238 | AX8: 284 | AY8: 340 | AZ8: =AX8+AY8 -> 624 | BA8: 281 | BB8: =AZ8+BA8 -> 905 | BC8: 411 | BD8: =BC8+BA8 -> 692 | BE8: =BD8+AZ8 -> 1316 | BF8: 298 | BG8: 353 | BH8: =BF8+BG8 -> 651 | BI8: 309 | BJ8: =BH8+BI8 -> 960 | BK8: 426 | BL8: =BK8+BI8 -> 735 | BM8: =BL8+BH8 -> 1386 | BN8: 360 | BO8: 330 | BP8: =BN8+BO8 -> 690 | BQ8: 632.74673 | BR8: =BP8+BQ8 -> 1322.7467 | BS8: 586.96886 | BT8: =BS8+BQ8 -> 1219.7156 | BU8: =BT8+BP8 -> 1909.7156 | BV8: 360 | BW8: 330 | BX8: =BV8+BW8 -> 690 | BY8: 632.74673 | BZ8: =BX8+BY8 -> 1322.7467 | CA8: 586.96886 | CB8: =CA8+BY8 -> 1219.7156 | CC8: =CB8+BX8 -> 1909.7156 | CD8: 363.6 | CE8: 333.3 | CF8: =CD8+CE8 -> 696.9 | CG8: 639.07419 | CH8: =CF8+CG8 -> 1335.9742 | CI8: 592.83855 | CJ8: =CI8+CG8 -> 1231.9127 | CL8: 426.74058
A9: Aerosystems | BF9: 113.5 | BG9: 423.5 | BH9: =BF9+BG9 -> 537 | BI9: 431 | BJ9: =BH9+BI9 -> 968 | BK9: 320 | BL9: =BJ9+BK9 -> 1288 | BM9: =BK9+BL9 -> 1608 | BN9: 419 | BO9: 88.957114 | BP9: =BN9+BO9 -> 507.95711 | BQ9: 308.9857 | BR9: =BP9+BQ9 -> 816.94282 | BS9: 198.97141 | BT9: =BS9+BQ9 -> 507.95711 | BU9: =BT9+BP9 -> 1015.9142 | BV9: 334.68583 | BW9: 71.056528 | BX9: =BV9+BW9 -> 405.74236 | BY9: 246.80939 | BZ9: =BX9+BY9 -> 652.55175 | CA9: 158.93296 | CB9: =CA9+BY9 -> 405.74236 | CC9: =CB9+BX9 -> 811.48471 | CD9: 288.88438 | CE9: 61.332507 | CF9: =CD9+CE9 -> 350.21689 | CG9: 213.03375 | CH9: =CF9+CG9 -> 563.25064 | CI9: 137.18313 | CJ9: =CI9+CG9 -> 350.21689 | CL9: 207.35155
A10: Equipment & Defense | BF10: 1641.5 | BG10: 2070.5 | BH10: =BF10+BG10 -> 3712 | BI10: 2052 | BJ10: =BH10+BI10 -> 5764 | BK10: 2178 | BL10: =BJ10+BK10 -> 7942 | BM10: =BK10+BL10 -> 10120 | BN10: 2201 | BO10: 2352 | BP10: =BN10+BO10 -> 4553 | BQ10: 2298 | BR10: =BP10+BQ10 -> 6851 | BS10: 2405 | BT10: =BS10+BQ10 -> 4703 | BU10: =BT10+BP10 -> 9256 | BV10: 2187 | BW10: 1451 | BX10: =BV10+BW10 -> 3638 | BY10: 1461 | BZ10: =BX10+BY10 -> 5099 | CA10: 1794 | CB10: =CA10+BY10 -> 3255 | CC10: =CB10+BX10 -> 6893 | CD10: 1464 | CE10: 1508 | CF10: =CD10+CE10 -> 2972 | CG10: 1535 | CH10: =CF10+CG10 -> 4507 | CI10: 1818 | CJ10: =CI10+CG10 -> 3353 | CK10: =INDEX('Income Statement'!6:6, MATCH('Interim (New)'!CK$1,'Income Statement'!$3:$3,0)) -> 6325 | CL10: 1716 | CM10: 1790 | CN10: =CL10+CM10 -> 3506 | CO10: 1820 | CP10: =CN10+CO10 -> 5326 | CQ10: 2209 | CR10: =CQ10+CO10 -> 4029 | CS10: =INDEX('Income Statement'!6:6, MATCH('Interim (New)'!CS$1,'Income Statement'!$3:$3,0)) -> 7535 | CT10: 1966 | CU10: 2134 | CV10: =CT10+CU10 -> 4100 | CW10: 2134 | CX10: =CV10+CW10 -> 6234 | CY10: 2601 | CZ10: =CY10+CW10 -> 4735 | DA10: =INDEX('Income Statement'!6:6, MATCH('Interim (New)'!DA$1,'Income Statement'!$3:$3,0)) -> 8835 | DB10: 2444 | DC10: 2726 | DD10: =DB10+DC10 -> 5170 | DE10: 2527 | DF10: =DD10+DE10 -> 7697 | DG10: 2921 | DH10: =DG10+DE10 -> 5448 | DI10: =INDEX('Income Statement'!6:6, MATCH('Interim (New)'!DI$1,'Income Statement'!$3:$3,0)) -> 10618 | DJ10: 2783 | DK10: 2826 | DL10: =DJ10+DK10 -> 5609 | DM10: 3004 | DN10: =DL10+DM10 -> 8613 | DO10: =DQ10-DN10 -> 3675.3316 | DP10: =DM10+DO10 -> 6679.3316 | DQ10: =INDEX('Income Statement'!6:6, MATCH('Interim (New)'!DQ$1,'Income Statement'!$3:$3,0)) -> 12288.332 | DR10: =(DB10/$DI$10)*$DY$10 -> 3234.8842 | DS10: =(DC10/$DI$10)*$DY$10 -> 3608.1401 | DT10: =(DD10/$DI$10)*$DY$10 -> 6843.0243 | DU10: =(DE10/$DI$10)*$DY$10 -> 3344.7432 | DV10: =(DF10/$DI$10)*$DY$10 -> 10187.767 | DW10: =(DG10/$DI$10)*$DY$10 -> 3866.2425 | DX10: =(DH10/$DI$10)*$DY$10 -> 7210.9857 | DY10: =INDEX('Income Statement'!6:6, MATCH('Interim (New)'!DY$1,'Income Statement'!$3:$3,0)) -> 14054.01
A11: Aircraft Interiors | BF11: 255.5 | BG11: 724.5 | BH11: =BF11+BG11 -> 980 | BI11: 769 | BJ11: =BH11+BI11 -> 1749 | BK11: 762 | BL11: =BJ11+BK11 -> 2511 | BM11: =BK11+BL11 -> 3273 | BN11: 806 | BO11: 834 | BP11: =BN11+BO11 -> 1640 | BQ11: 805 | BR11: =BP11+BQ11 -> 2445 | BS11: 876 | BT11: =BS11+BQ11 -> 1681 | BU11: =BT11+BP11 -> 3321 | BV11: 694 | BW11: 378 | BX11: =BV11+BW11 -> 1072 | BY11: 357 | BZ11: =BX11+BY11 -> 1429 | CA11: 493 | CB11: =CA11+BY11 -> 850 | CC11: =CB11+BX11 -> 1922 | CD11: 313 | CE11: 333 | CF11: =CD11+CE11 -> 646 | CG11: 385 | CH11: =CF11+CG11 -> 1031 | CI11: 444 | CJ11: =CI11+CG11 -> 829 | CK11: =INDEX('Income Statement'!7:7, MATCH('Interim (New)'!CK$1,'Income Statement'!$3:$3,0)) -> 1475 | CL11: 409 | CM11: 461 | CN11: =CL11+CM11 -> 870 | CO11: 522 | CP11: =CN11+CO11 -> 1392 | CQ11: 586 | CR11: =CQ11+CO11 -> 1108 | CS11: =INDEX('Income Statement'!7:7, MATCH('Interim (New)'!CS$1,'Income Statement'!$3:$3,0)) -> 1978 | CT11: 584 | CU11: 579 | CV11: =CT11+CU11 -> 1163 | CW11: 605 | CX11: =CV11+CW11 -> 1768 | CY11: 709 | CZ11: =CY11+CW11 -> 1314 | DA11: =INDEX('Income Statement'!7:7, MATCH('Interim (New)'!DA$1,'Income Statement'!$3:$3,0)) -> 2477 | DB11: 676 | DC11: 735 | DD11: =DB11+DC11 -> 1411 | DE11: 771 | DF11: =DD11+DE11 -> 2182 | DG11: 855 | DH11: =DG11+DE11 -> 1626 | DI11: =INDEX('Income Statement'!7:7, MATCH('Interim (New)'!DI$1,'Income Statement'!$3:$3,0)) -> 3037 | DJ11: 788 | DK11: 828 | DL11: =DJ11+DK11 -> 1616 | DM11: 802 | DN11: =DL11+DM11 -> 2418 | DO11: =DQ11-DN11 -> 1005.86 | DP11: =DM11+DO11 -> 1807.86 | DQ11: =INDEX('Income Statement'!7:7, MATCH('Interim (New)'!DQ$1,'Income Statement'!$3:$3,0)) -> 3423.86 | DR11: =(DB11/$DI$11)*$DY$11 -> 842.07853 | DS11: =(DC11/$DI$11)*$DY$11 -> 915.57355 | DT11: =(DD11/$DI$11)*$DY$11 -> 1757.6521 | DU11: =(DE11/$DI$11)*$DY$11 -> 960.41797 | DV11: =(DF11/$DI$11)*$DY$11 -> 2718.0701 | DW11: =(DG11/$DI$11)*$DY$11 -> 1065.0549 | DX11: =(DH11/$DI$11)*$DY$11 -> 2025.4729 | DY11: =INDEX('Income Statement'!7:7, MATCH('Interim (New)'!DY$1,'Income Statement'!$3:$3,0)) -> 3783.125
A12: Security | B12: 233 | C12: 276 | D12: =B12+C12 -> 509 | E12: 317 | F12: =D12+E12 -> 826 | G12: 423 | H12: =G12+E12 -> 740 | I12: =H12+D12 -> 1249 | J12: 332 | K12: 387 | L12: =J12+K12 -> 719 | M12: 371 | N12: =L12+M12 -> 1090 | O12: 456 | P12: =O12+M12 -> 827 | Q12: =P12+L12 -> 1546 | R12: 340 | S12: 384 | T12: =R12+S12 -> 724 | U12: 349 | V12: =T12+U12 -> 1073 | W12: 409 | X12: =W12+U12 -> 758 | Y12: =X12+T12 -> 1482 | Z12: 345 | AA12: 377 | AB12: =Z12+AA12 -> 722 | AC12: 368 | AD12: =AB12+AC12 -> 1090 | AE12: 440 | AF12: =AE12+AC12 -> 808 | AG12: =AF12+AB12 -> 1530 | AH12: 414 | AI12: 471 | AJ12: =AH12+AI12 -> 885 | AK12: 474 | AL12: =AJ12+AK12 -> 1359 | AM12: 519 | AN12: =AM12+AK12 -> 993 | AO12: =AN12+AJ12 -> 1878 | AP12: 449 | AQ12: 500 | AR12: =AP12+AQ12 -> 949 | AS12: 470 | AT12: =AR12+AS12 -> 1419 | AV12: =AU12+AS12 -> 470 | AW12: =AV12+AR12 -> 1419
A13: Other | B13: 4 | C13: -4 | E13: 12 | F13: =D13+E13 -> 12 | G13: 4 | H13: =G13+E13 -> 16 | I13: =H13+D13 -> 16 | J13: 1 | K13: 0 | M13: 2 | N13: =L13+M13 -> 2 | O13: 0 | P13: =O13+M13 -> 2 | Q13: =P13+L13 -> 2 | R13: 1 | S13: 0 | U13: 1 | V13: =T13+U13 -> 1 | W13: 2 | X13: =W13+U13 -> 3 | Y13: =X13+T13 -> 3 | Z13: 0 | AA13: 2 | AC13: 0 | AD13: =AB13+AC13 -> 0 | AE13: 3 | AF13: =AE13+AC13 -> 3 | AG13: =AF13+AB13 -> 3 | AH13: 1 | AI13: 1 | AK13: 1 | AL13: =AJ13+AK13 -> 1 | AM13: 5 | AN13: =AM13+AK13 -> 6 | AO13: =AN13+AJ13 -> 6 | AP13: 2 | AQ13: 2 | AS13: 0 | AT13: =AR13+AS13 -> 0 | AU13: 0 | AV13: =AU13+AS13 -> 0 | AW13: =AV13+AR13 -> 0 | AX13: 3 | AY13: 5 | AZ13: =AX13+AY13 -> 8 | BA13: 6 | BB13: =AZ13+BA13 -> 14 | BC13: 6 | BD13: =BC13+BA13 -> 12 | BE13: =BD13+AZ13 -> 20 | BF13: 6 | BG13: 4 | BH13: =BF13+BG13 -> 10 | BI13: 3 | BJ13: =BH13+BI13 -> 13 | BK13: 5 | BL13: =BK13+BI13 -> 8 | BM13: =BL13+BH13 -> 18 | BN13: 3 | BO13: 5 | BP13: =BO13+BK13 -> 10 | BQ13: 5 | BR13: =BP13+BQ13 -> 15 | BS13: 6 | BT13: =BS13+BQ13 -> 11 | BU13: =BT13+BP13 -> 21 | BV13: 5 | BW13: 5 | BX13: =BV13+BW13 -> 10 | BY13: 5 | BZ13: =BX13+BY13 -> 15 | CA13: 5 | CB13: =CA13+BY13 -> 10 | CC13: =CB13+BX13 -> 20 | CD13: 4 | CE13: 5 | CF13: =CD13+CE13 -> 9 | CG13: 2 | CH13: =CF13+CG13 -> 11 | CI13: 7 | CJ13: =CI13+CG13 -> 9 | CK13: =INDEX('Income Statement'!8:8, MATCH('Interim (New)'!CK$1,'Income Statement'!$3:$3,0)) -> 18 | CL13: 4 | CM13: 4 | CN13: =CL13+CM13 -> 8 | CO13: 4 | CP13: =CN13+CO13 -> 12 | CQ13: 4 | CR13: =CQ13+CO13 -> 8 | CS13: =INDEX('Income Statement'!8:8, MATCH('Interim (New)'!CS$1,'Income Statement'!$3:$3,0)) -> 16 | CT13: 2 | CU13: 3 | CV13: =CT13+CU13 -> 5 | CW13: 3 | CX13: =CV13+CW13 -> 8 | CY13: 3 | CZ13: =CY13+CW13 -> 6 | DA13: =INDEX('Income Statement'!8:8, MATCH('Interim (New)'!DA$1,'Income Statement'!$3:$3,0)) -> 11 | DB13: 3 | DC13: 2 | DD13: =DB13+DC13 -> 5 | DE13: 2 | DF13: =DD13+DE13 -> 7 | DG13: 2 | DH13: =DG13+DE13 -> 4 | DI13: =INDEX('Income Statement'!8:8, MATCH('Interim (New)'!DI$1,'Income Statement'!$3:$3,0)) -> 10 | DJ13: 2 | DK13: 2 | DL13: =DJ13+DK13 -> 4 | DM13: 2 | DN13: =DL13+DM13 -> 6 | DO13: =DQ13-DN13 -> 4 | DP13: =DM13+DO13 -> 6 | DQ13: =INDEX('Income Statement'!8:8, MATCH('Interim (New)'!DQ$1,'Income Statement'!$3:$3,0)) -> 10 | DR13: =(DB13/$DI$13)*$DY$13 -> 3 | DS13: =(DC13/$DI$13)*$DY$13 -> 2 | DT13: =(DD13/$DI$13)*$DY$13 -> 5 | DU13: =(DE13/$DI$13)*$DY$13 -> 2 | DV13: =(DF13/$DI$13)*$DY$13 -> 7 | DW13: =(DG13/$DI$13)*$DY$13 -> 2 | DX13: =(DH13/$DI$13)*$DY$13 -> 4 | DY13: =INDEX('Income Statement'!8:8, MATCH('Interim (New)'!DY$1,'Income Statement'!$3:$3,0)) -> 10
A14: Defence Security
A15: Communications
A16: Group | B16: =SUM(B6:B15) -> 2681 | C16: =SUM(C6:C15) -> 2933 | D16: =B16+C16 -> 5614 | E16: =SUM(E6:E15) -> 2736 | F16: =D16+E16 -> 8350 | G16: =SUM(G6:G15) -> 3386 | H16: =G16+E16 -> 6122 | I16: =H16+D16 -> 11736 | J16: =SUM(J6:J15) -> 3108 | K16: =SUM(K6:K15) -> 3305 | L16: =J16+K16 -> 6413 | M16: =SUM(M6:M15) -> 3134 | N16: =L16+M16 -> 9547 | O16: =SUM(O6:O15) -> 4013 | P16: =O16+M16 -> 7147 | Q16: =P16+L16 -> 13560 | R16: =SUM(R6:R15) -> 3333 | S16: =SUM(S6:S15) -> 3574 | T16: =R16+S16 -> 6907 | U16: =SUM(U6:U15) -> 3361 | V16: =T16+U16 -> 10268 | W16: =SUM(W6:W15) -> 4095 | X16: =W16+U16 -> 7456 | Y16: =X16+T16 -> 14363 | Z16: =SUM(Z6:Z15) -> 3443 | AA16: =SUM(AA6:AA15) -> 3765 | AB16: =Z16+AA16 -> 7208 | AC16: =SUM(AC6:AC15) -> 3589 | AD16: =AB16+AC16 -> 10797 | AE16: =SUM(AE6:AE15) -> 4558 | AF16: =AE16+AC16 -> 8147 | AG16: =AF16+AB16 -> 15355 | AH16: =SUM(AH6:AH15) -> 3935 | AI16: =SUM(AI6:AI15) -> 4468 | AJ16: =AH16+AI16 -> 8403 | AK16: =SUM(AK6:AK15) -> 4141 | AL16: =AJ16+AK16 -> 12544 | AM16: =SUM(AM6:AM15) -> 4870 | AN16: =AM16+AK16 -> 9011 | AO16: =AN16+AJ16 -> 17414 | AP16: =SUM(AP6:AP15)-AP12 -> 3791 | AQ16: =SUM(AQ6:AQ15)-AQ12 -> 4196 | AR16: =AP16+AQ16 -> 7987 | AS16: =SUM(AS6:AS15)-AS12 -> 3517 | AT16: =AR16+AS16 -> 11504 | AU16: =SUM(AU6:AU15)-AU12 -> 4274 | AV16: =AU16+AS16 -> 7791 | AW16: =AV16+AR16 -> 15778 | AX16: =SUM(AX6:AX15) -> 3982 | AY16: =SUM(AY6:AY15) -> 4056 | AZ16: =AX16+AY16 -> 8038 | BA16: =SUM(BA6:BA15) -> 3815 | BB16: =AZ16+BA16 -> 11853 | BC16: =SUM(BC6:BC15) -> 4100 | BD16: =BC16+BA16 -> 7915 | BE16: =BD16+AZ16 -> 15953 | BF16: =SUM(BF10:BF15,BF6) -> 4222 | BG16: =SUM(BG10:BG15,BG6) -> 5285 | BH16: =BF16+BG16 -> 9507 | BI16: =SUM(BI10:BI15,BI6) -> 5348 | BJ16: =BH16+BI16 -> 14855 | BK16: =SUM(BK10:BK15,BK6) -> 6195 | BL16: =BK16+BI16 -> 11543 | BM16: =BL16+BH16 -> 21050 | BN16: =SUM(BN10:BN15,BN6) -> 5781 | BO16: =SUM(BO10:BO15,BO6) -> 6322 | BP16: =BN16+BO16 -> 12103 | BQ16: =SUM(BQ10:BQ15,BQ6) -> 6095 | BR16: =BP16+BQ16 -> 18198 | BS16: =SUM(BS10:BS15,BS6) -> 6443 | BT16: =BS16+BQ16 -> 12538 | BU16: =BT16+BP16 -> 24641 | BV16: =SUM(BV10:BV15,BV6) -> 5383 | BW16: =SUM(BW10:BW15,BW6) -> 3384 | BX16: =BV16+BW16 -> 8767 | BY16: =SUM(BY10:BY15,BY6) -> 3382 | BZ16: =BX16+BY16 -> 12149 | CA16: =SUM(CA10:CA15,CA6) -> 4349 | CB16: =CA16+BY16 -> 7731 | CC16: =CB16+BX16 -> 16498 | CD16: =SUM(CD10:CD15,CD6) -> 3342 | CE16: =SUM(CE10:CE15,CE6) -> 3534 | CF16: =CD16+CE16 -> 6876 | CG16: =SUM(CG10:CG15,CG6) -> 3734 | CH16: =CF16+CG16 -> 10610 | CI16: =SUM(CI10:CI15,CI6) -> 4647 | CJ16: =CI16+CG16 -> 8381 | CK16: =INDEX('Income Statement'!9:9, MATCH('Interim (New)'!CK$1,'Income Statement'!$3:$3,0)) -> 15257 | CL16: =SUM(CL10:CL15,CL6) -> 4071 | CM16: 4489 | CN16: =CL16+CM16 -> 8560 | CO16: =SUM(CO10:CO15,CO6) -> 4849 | CP16: =CN16+CO16 -> 13409 | CQ16: 5626 | CR16: =CQ16+CO16 -> 10475 | CS16: =INDEX('Income Statement'!9:9, MATCH('Interim (New)'!CS$1,'Income Statement'!$3:$3,0)) -> 19035 | CT16: =SUM(CT10:CT15,CT6) -> 5266 | CU16: 5679 | CV16: =CT16+CU16 -> 10945 | CW16: =SUM(CW10:CW15,CW6) -> 5825 | CX16: =CV16+CW16 -> 16770 | CY16: 6429 | CZ16: =CY16+CW16 -> 12254 | DA16: =INDEX('Income Statement'!9:9, MATCH('Interim (New)'!DA$1,'Income Statement'!$3:$3,0)) -> 23199 | DB16: =SUM(DB10:DB15,DB6) -> 6220 | DC16: 6827 | DD16: =DB16+DC16 -> 13047 | DE16: =SUM(DE10:DE15,DE6) -> 6639 | DF16: =DD16+DE16 -> 19686 | DG16: 7630 | DH16: =DG16+DE16 -> 14269 | DI16: =INDEX('Income Statement'!9:9, MATCH('Interim (New)'!DI$1,'Income Statement'!$3:$3,0)) -> 27317 | DJ16: =SUM(DJ10:DJ15,DJ6) -> 7257 | DK16: =SUM(DK10:DK15,DK6)-1 -> 7512 | DL16: =SUM(DL10:DL15,DL6)-1 -> 14769 | DM16: =SUM(DM10:DM15,DM6) -> 7852 | DN16: =SUM(DN10:DN15,DN6) -> 22622 | DO16: =SUM(DO10:DO15,DO6) -> 8934.5686 | DP16: =SUM(DP10:DP15,DP6) -> 16786.569 | DQ16: =INDEX('Income Statement'!9:9, MATCH('Interim (New)'!DQ$1,'Income Statement'!$3:$3,0)) -> 31556.569 | DR16: =(DB16/$DI$16)*$DY$16 -> 8118.2491 | DS16: =(DC16/$DI$16)*$DY$16 -> 8910.4963 | DT16: =(DD16/$DI$16)*$DY$16 -> 17028.745 | DU16: =(DE16/$DI$16)*$DY$16 -> 8665.1215 | DV16: =(DF16/$DI$16)*$DY$16 -> 25693.867 | DW16: =(DG16/$DI$16)*$DY$16 -> 9958.5596 | DX16: =(DH16/$DI$16)*$DY$16 -> 18623.681 | DY16: =INDEX('Income Statement'!9:9, MATCH('Interim (New)'!DY$1,'Income Statement'!$3:$3,0)) -> 35653.732
A18: Revenue Growth
A19: Aerospace Propulsion | CD19: =CD6/BV6-1 -> -0.37484982 | CE19: =CE6/BW6-1 -> 0.089032258 | CF19: =CF6/BX6-1 -> -0.1971831 | CG19: =CG6/BY6-1 -> 0.16228352 | CH19: =CH6/BZ6-1 -> -0.097217267 | CI19: =CI6/CA6-1 -> 0.1560525 | CJ19: =CJ6/CB6-1 -> 0.15873894 | CK19: =CK6/CC6-1 -> -0.029231372 | ... DY19: =DY6/DQ6-1 -> 0.12455304
A20: Aircraft Equipment | CD20: =CD7/BV7-1 -> -0.11411052 | CL20: =CL7/CD7-1 -> 0.30321718
A21: Defence | CD21: =CD8/BV8-1 -> 0.01 | CL21: =CL8/CD8-1 -> 0.17365395
A22: Aerosystems | CD22: =CD9/BV9-1 -> -0.13684909 | CL22: =CL9/CD9-1 -> -0.28223343
A23: Equipment & Defense | CD23: =CD10/BV10-1 -> -0.33058985 | CE23: =CE10/BW10-1 -> 0.039283253 | CF23: =CF10/BX10-1 -> -0.18306762 | CG23: =CG10/BY10-1 -> 0.05065024 | CH23: =CH10/BZ10-1 -> -0.1161012 | CI23: =CI10/CA10-1 -> 0.013377926 | CJ23: =CJ10/CB10-1 -> 0.030107527 | CK23: =CK10/CC10-1 -> -0.082402437 | ... DY23: =DY10/DQ10-1 -> 0.1436874
A24: Aircraft Interiors | CD24: =CD11/BV11-1 -> -0.54899135 | CE24: =CE11/BW11-1 -> -0.11904762 | CF24: =CF11/BX11-1 -> -0.39738806 | CG24: =CG11/BY11-1 -> 0.078431373 | CH24: =CH11/BZ11-1 -> -0.27851645 | CI24: =CI11/CA11-1 -> -0.099391481 | CJ24: =CJ11/CB11-1 -> -0.024705882 | CK24: =CK11/CC11-1 -> -0.23257024 | ... DY24: =DY11/DQ11-1 -> 0.10492982
A25: Security
A26: Other | CD26: =CD13/BV13-1 -> -0.2 | CE26: =CE13/BW13-1 -> 0 | CF26: =CF13/BX13-1 -> -0.1 | CG26: =CG13/BY13-1 -> -0.6 | CH26: =CH13/BZ13-1 -> -0.26666667 | CI26: =CI13/CA13-1 -> 0.4 | CJ26: =CJ13/CB13-1 -> -0.1 | CK26: =CK13/CC13-1 -> -0.1 | ... DY26: =DY13/DQ13-1 -> 0
A27: Defence Security
A28: Communications
A29: Group | B29: =SUM(B19:B28) -> 0 | C29: =SUM(C19:C28) -> 0 | D29: =B29+C29 -> 0 | E29: =SUM(E19:E28) -> 0 | F29: =D29+E29 -> 0 | G29: =SUM(G19:G28) -> 0 | H29: =G29+E29 -> 0 | I29: =H29+D29 -> 0 | J29: =SUM(J19:J28) -> 0 | K29: =SUM(K19:K28) -> 0 | L29: =J29+K29 -> 0 | M29: =SUM(M19:M28) -> 0 | N29: =L29+M29 -> 0 | O29: =SUM(O19:O28) -> 0 | P29: =O29+M29 -> 0 | Q29: =P29+L29 -> 0 | R29: =SUM(R19:R28) -> 0 | S29: =SUM(S19:S28) -> 0 | T29: =R29+S29 -> 0 | U29: =SUM(U19:U28) -> 0 | V29: =T29+U29 -> 0 | W29: =SUM(W19:W28) -> 0 | X29: =W29+U29 -> 0 | Y29: =X29+T29 -> 0 | Z29: =SUM(Z19:Z28) -> 0 | AA29: =SUM(AA19:AA28) -> 0 | AB29: =Z29+AA29 -> 0 | AC29: =SUM(AC19:AC28) -> 0 | AD29: =AB29+AC29 -> 0 | AE29: =SUM(AE19:AE28) -> 0 | AF29: =AE29+AC29 -> 0 | AH29: =SUM(AH19:AH28) -> 0 | AI29: =SUM(AI19:AI28) -> 0 | AJ29: =AH29+AI29 -> 0 | AK29: =SUM(AK19:AK28) -> 0 | AL29: =AJ29+AK29 -> 0 | AM29: =SUM(AM19:AM28) -> 0 | AN29: =AM29+AK29 -> 0 | AO29: =AN29+AJ29 -> 0 | AP29: =SUM(AP19:AP28)-AP25 -> 0 | AQ29: =SUM(AQ19:AQ28)-AQ25 -> 0 | AR29: =AP29+AQ29 -> 0 | AS29: =SUM(AS19:AS28)-AS25 -> 0 | AT29: =AR29+AS29 -> 0 | AU29: =SUM(AU19:AU28)-AU25 -> 0 | AV29: =AU29+AS29 -> 0 | AW29: =AV29+AR29 -> 0 | AX29: =SUM(AX19:AX28) -> 0 | AY29: =SUM(AY19:AY28) -> 0 | AZ29: =AX29+AY29 -> 0 | BA29: =SUM(BA19:BA28) -> 0 | BB29: =AZ29+BA29 -> 0 | BC29: =SUM(BC19:BC28) -> 0 | BD29: =BC29+BA29 -> 0 | BE29: =BD29+AZ29 -> 0 | BF29: =SUM(BF23:BF28,BF19) -> 0 | BG29: =SUM(BG23:BG28,BG19) -> 0 | BH29: =BF29+BG29 -> 0 | BI29: =SUM(BI23:BI28,BI19) -> 0 | BJ29: =BH29+BI29 -> 0 | BK29: =SUM(BK23:BK28,BK19) -> 0 | BL29: =BK29+BI29 -> 0 | BM29: =BL29+BH29 -> 0 | BN29: =SUM(BN23:BN28,BN19) -> 0 | BO29: =SUM(BO23:BO28,BO19) -> 0 | BP29: =BN29+BO29 -> 0 | BQ29: =SUM(BQ23:BQ28,BQ19) -> 0 | BR29: =BP29+BQ29 -> 0 | BS29: =SUM(BS23:BS28,BS19) -> 0 | BT29: =BS29+BQ29 -> 0 | BU29: =BT29+BP29 -> 0 | BV29: =SUM(BV23:BV28,BV19) -> 0 | BW29: =SUM(BW23:BW28,BW19) -> 0 | BX29: =BV29+BW29 -> 0 | BY29: =SUM(BY23:BY28,BY19) -> 0 | BZ29: =BX29+BY29 -> 0 | CA29: =SUM(CA23:CA28,CA19) -> 0 | CB29: =CA29+BY29 -> 0 | CC29: =CB29+BX29 -> 0 | CD29: =(CD16/BV16)-1 -> -0.3791566 | CE29: =(CE16/BW16)-1 -> 0.044326241 | CF29: =(CF16/BX16)-1 -> -0.21569522 | CG29: =(CG16/BY16)-1 -> 0.10408043 | CH29: =(CH16/BZ16)-1 -> -0.12667709 | CI29: =(CI16/CA16)-1 -> 0.068521499 | CJ29: =(CJ16/CB16)-1 -> 0.084077092 | CK29: =(CK16/CC16)-1 -> -0.075221239 | ... DY29: =(DY16/DQ16)-1 -> 0.12983551
A30: Group organic
A32: Seasonality
A33: Aerospace Propulsion | CD33: =CD6/$CK$6 -> 0.20984003 | CE33: =CE6/$CK$6 -> 0.22691222 | CF33: =CF6/$CK$6 -> 0.43675225 | CG33: =CG6/$CK$6 -> 0.24358113 | CH33: =CH6/$CK$6 -> 0.68033338 | CI33: =CI6/$CK$6 -> 0.31966662 | CJ33: =CJ6/$CK$6 -> 0.56324775 | CK33: =CK6/$CK$6 -> 1 | CL33: =CL6/$CS$6 -> 0.20429203 | CM33: =CM6/$CS$6 -> 0.23500947 | CN33: =CN6/$CS$6 -> 0.43930149 | CO33: =CO6/$CS$6 -> 0.26330738 | CP33: =CP6/$CS$6 -> 0.70260888 | CQ33: =CQ6/$CS$6 -> 0.29739112 | CR33: =CR6/$CS$6 -> 0.56069851 | CS33: =CS6/$CS$6 -> 1 | CT33: =CT6/$DA$6 -> 0.22852812 | CU33: =CU6/$DA$6 -> 0.24949478 | CV33: =CV6/$DA$6 -> 0.4780229 | CW33: =CW6/$DA$6 -> 0.25959919 | CX33: =CX6/$DA$6 -> 0.73762209 | CY33: =CY6/$DA$6 -> 0.26237791 | CZ33: =CZ6/$DA$6 -> 0.5219771 | DA33: =DA6/$DA$6 -> 1 | DB33: =DB6/$DI$6 -> 0.22685321 | DC33: =DC6/$DI$6 -> 0.24641078 | DD33: =DD6/$DI$6 -> 0.47326399 | DE33: =DE6/$DI$6 -> 0.24457955 | DF33: =DF6/$DI$6 -> 0.71784354 | DG33: =DG6/$DI$6 -> 0.28215646 | DH33: =DH6/$DI$6 -> 0.52673601 | DI33: =DI6/$DI$6 -> 1 | DJ33: =DJ6/$DQ$6 -> 0.23265835 | DK33: =DK6/$DQ$6 -> 0.24358394 | DL33: =DL6/$DQ$6 -> 0.47624229 | DM33: =DM6/$DQ$6 -> 0.25539369 | DN33: =DN6/$DQ$6 -> 0.73163598 | DO33: =DO6/$DQ$6 -> 0.26836402 | DP33: =DP6/$DQ$6 -> 0.52375771 | DQ33: =DQ6/$DQ$6 -> 1
A34: Equipment & Defense | CD34: =CD10/$CK$10 -> 0.23146245 | CE34: =CE10/$CK$10 -> 0.23841897 | CF34: =CF10/$CK$10 -> 0.46988142 | CG34: =CG10/$CK$10 -> 0.24268775 | CH34: =CH10/$CK$10 -> 0.71256917 | CI34: =CI10/$CK$10 -> 0.28743083 | CJ34: =CJ10/$CK$10 -> 0.53011858 | CK34: =CK10/$CK$10 -> 1 | CL34: =CL10/$CS$10 -> 0.22773723 | CM34: =CM10/$CS$10 -> 0.23755806 | CN34: =CN10/$CS$10 -> 0.46529529 | CO34: =CO10/$CS$10 -> 0.24153948 | CP34: =CP10/$CS$10 -> 0.70683477 | CQ34: =CQ10/$CS$10 -> 0.29316523 | CR34: =CR10/$CS$10 -> 0.53470471 | CS34: =CS10/$CS$10 -> 1 | CT34: =CT10/$DA$10 -> 0.22252405 | CU34: =CU10/$DA$10 -> 0.24153933 | CV34: =CV10/$DA$10 -> 0.46406338 | CW34: =CW10/$DA$10 -> 0.24153933 | CX34: =CX10/$DA$10 -> 0.70560272 | CY34: =CY10/$DA$10 -> 0.29439728 | CZ34: =CZ10/$DA$10 -> 0.53593662 | DA34: =DA10/$DA$10 -> 1 | DB34: =DB10/$DI$10 -> 0.23017517 | DC34: =DC10/$DI$10 -> 0.25673385 | DD34: =DD10/$DI$10 -> 0.48690902 | DE34: =DE10/$DI$10 -> 0.23799209 | DF34: =DF10/$DI$10 -> 0.72490111 | DG34: =DG10/$DI$10 -> 0.27509889 | DH34: =DH10/$DI$10 -> 0.51309098 | DI34: =DI10/$DI$10 -> 1 | DJ34: =DJ10/$DQ$10 -> 0.22647501 | DK34: =DK10/$DQ$10 -> 0.22997426 | DL34: =DL10/$DQ$10 -> 0.45644927 | DM34: =DM10/$DQ$10 -> 0.24445955 | DN34: =DN10/$DQ$10 -> 0.70090882 | DO34: =DO10/$DQ$10 -> 0.29909118 | DP34: =DP10/$DQ$10 -> 0.54355073 | DQ34: =DQ10/$DQ$10 -> 1
A35: Aircraft Interiors | CD35: =CD11/$CK$11 -> 0.21220339 | CE35: =CE11/$CK$11 -> 0.22576271 | CF35: =CF11/$CK$11 -> 0.4379661 | CG35: =CG11/$CK$11 -> 0.26101695 | CH35: =CH11/$CK$11 -> 0.69898305 | CI35: =CI11/$CK$11 -> 0.30101695 | CJ35: =CJ11/$CK$11 -> 0.5620339 | CK35: =CK11/$CK$11 -> 1 | CL35: =CL11/$CS$11 -> 0.20677452 | CM35: =CM11/$CS$11 -> 0.2330637 | CN35: =CN11/$CS$11 -> 0.43983822 | CO35: =CO11/$CS$11 -> 0.26390293 | CP35: =CP11/$CS$11 -> 0.70374115 | CQ35: =CQ11/$CS$11 -> 0.29625885 | CR35: =CR11/$CS$11 -> 0.56016178 | CS35: =CS11/$CS$11 -> 1 | CT35: =CT11/$DA$11 -> 0.23576908 | CU35: =CU11/$DA$11 -> 0.2337505 | CV35: =CV11/$DA$11 -> 0.46951958 | CW35: =CW11/$DA$11 -> 0.24424707 | CX35: =CX11/$DA$11 -> 0.71376665 | CY35: =CY11/$DA$11 -> 0.28623335 | CZ35: =CZ11/$DA$11 -> 0.53048042 | DA35: =DA11/$DA$11 -> 1 | DB35: =DB11/$DI$11 -> 0.22258808 | DC35: =DC11/$DI$11 -> 0.24201515 | DD35: =DD11/$DI$11 -> 0.46460323 | DE35: =DE11/$DI$11 -> 0.25386895 | DF35: =DF11/$DI$11 -> 0.71847218 | DG35: =DG11/$DI$11 -> 0.28152782 | DH35: =DH11/$DI$11 -> 0.53539677 | DI35: =DI11/$DI$11 -> 1 | DJ35: =DJ11/$DQ$11 -> 0.2301496 | DK35: =DK11/$DQ$11 -> 0.24183232 | DL35: =DL11/$DQ$11 -> 0.47198192 | DM35: =DM11/$DQ$11 -> 0.23423855 | DN35: =DN11/$DQ$11 -> 0.70622046 | DO35: =DO11/$DQ$11 -> 0.29377954 | DP35: =DP11/$DQ$11 -> 0.52801808 | DQ35: =DQ11/$DQ$11 -> 1
A36: Other | CD36: =CD13/$CK$13 -> 0.22222222 | CE36: =CE13/$CK$13 -> 0.27777778 | CF36: =CF13/$CK$13 -> 0.5 | CG36: =CG13/$CK$13 -> 0.11111111 | CH36: =CH13/$CK$13 -> 0.61111111 | CI36: =CI13/$CK$13 -> 0.38888889 | CJ36: =CJ13/$CK$13 -> 0.5 | CK36: =CK13/$CK$13 -> 1 | CL36: =CL13/$CS$13 -> 0.25 | CM36: =CM13/$CS$13 -> 0.25 | CN36: =CN13/$CS$13 -> 0.5 | CO36: =CO13/$CS$13 -> 0.25 | CP36: =CP13/$CS$13 -> 0.75 | CQ36: =CQ13/$CS$13 -> 0.25 | CR36: =CR13/$CS$13 -> 0.5 | CS36: =CS13/$CS$13 -> 1 | CT36: =CT13/$DA$13 -> 0.18181818 | CU36: =CU13/$DA$13 -> 0.27272727 | CV36: =CV13/$DA$13 -> 0.45454545 | CW36: =CW13/$DA$13 -> 0.27272727 | CX36: =CX13/$DA$13 -> 0.72727273 | CY36: =CY13/$DA$13 -> 0.27272727 | CZ36: =CZ13/$DA$13 -> 0.54545455 | DA36: =DA13/$DA$13 -> 1 | DB36: =DB13/$DI$13 -> 0.3 | DC36: =DC13/$DI$13 -> 0.2 | DD36: =DD13/$DI$13 -> 0.5 | DE36: =DE13/$DI$13 -> 0.2 | DF36: =DF13/$DI$13 -> 0.7 | DG36: =DG13/$DI$13 -> 0.2 | DH36: =DH13/$DI$13 -> 0.4 | DI36: =DI13/$DI$13 -> 1 | DJ36: =DJ13/$DQ$13 -> 0.2 | DK36: =DK13/$DQ$13 -> 0.2 | DL36: =DL13/$DQ$13 -> 0.4 | DM36: =DM13/$DQ$13 -> 0.2 | DN36: =DN13/$DQ$13 -> 0.6 | DO36: =DO13/$DQ$13 -> 0.4 | DP36: =DP13/$DQ$13 -> 0.6 | DQ36: =DQ13/$DQ$13 -> 1
A37: Group | CD37: =CD16/$CK$16 -> 0.21904699 | CE37: =CE16/$CK$16 -> 0.23163138 | CF37: =CF16/$CK$16 -> 0.45067838 | CG37: =CG16/$CK$16 -> 0.24474012 | CH37: =CH16/$CK$16 -> 0.6954185 | CI37: =CI16/$CK$16 -> 0.3045815 | CJ37: =CJ16/$CK$16 -> 0.54932162 | CK37: =CK16/$CK$16 -> 1 | CL37: =CL16/$CS$16 -> 0.21386919 | CM37: =CM16/$CS$16 -> 0.23582874 | CN37: =CN16/$CS$16 -> 0.44969792 | CO37: =CO16/$CS$16 -> 0.25474127 | CP37: =CP16/$CS$16 -> 0.70443919 | CQ37: =CQ16/$CS$16 -> 0.29556081 | CR37: =CR16/$CS$16 -> 0.55030208 | CS37: =CS16/$CS$16 -> 1 | CT37: =CT16/$DA$16 -> 0.22699254 | CU37: =CU16/$DA$16 -> 0.24479503 | CV37: =CV16/$DA$16 -> 0.47178758 | CW37: =CW16/$DA$16 -> 0.25108841 | CX37: =CX16/$DA$16 -> 0.72287599 | CY37: =CY16/$DA$16 -> 0.27712401 | CZ37: =CZ16/$DA$16 -> 0.52821242 | DA37: =DA16/$DA$16 -> 1 | DB37: =DB16/$DI$16 -> 0.22769704 | DC37: =DC16/$DI$16 -> 0.24991763 | DD37: =DD16/$DI$16 -> 0.47761467 | DE37: =DE16/$DI$16 -> 0.24303547 | DF37: =DF16/$DI$16 -> 0.72065014 | DG37: =DG16/$DI$16 -> 0.27931325 | DH37: =DH16/$DI$16 -> 0.52234872 | DI37: =DI16/$DI$16 -> 1 | DJ37: =DJ16/$DQ$16 -> 0.22996797 | DK37: =DK16/$DQ$16 -> 0.2380487 | DL37: =DL16/$DQ$16 -> 0.46801666 | DM37: =DM16/$DQ$16 -> 0.248823 | DN37: =DN16/$DQ$16 -> 0.71687135 | DO37: =DO16/$DQ$16 -> 0.28312865 | DP37: =DP16/$DQ$16 -> 0.53195165 | DQ37: =DQ16/$DQ$16 -> 1
A39: Underlying EBITA
A40: Aerospace Propulsion | D40: 424 | H40: 485 | L40: 512 | P40: 564 | T40: 631 | X40: 727 | AB40: 727 | AF40: 906 | AJ40: 944 | AN40: 889 | AR40: 942 | AV40: 844 | AZ40: 849 | BD40: 667 | BH40: 915 | BL40: 1115 | BP40: 1227 | BT40: 1258 | BX40: 699 | CB40: 493 | CF40: 504 | CJ40: 838 | CK40: =INDEX('Income Statement'!19:19, MATCH('Interim (New)'!CK$1,'Income Statement'!$3:$3,0)) -> 1342 | CN40: 723 | CR40: 987 | CS40: =INDEX('Income Statement'!19:19, MATCH('Interim (New)'!CS$1,'Income Statement'!$3:$3,0)) -> 1710 | CV40: 1051 | CZ40: 1339 | DA40: =INDEX('Income Statement'!19:19, MATCH('Interim (New)'!DA$1,'Income Statement'!$3:$3,0)) -> 2390 | DD40: 1285 | DH40: 1534 | DI40: =INDEX('Income Statement'!19:19, MATCH('Interim (New)'!DI$1,'Income Statement'!$3:$3,0)) -> 2819 | DL40: 1758 | DP40: =DQ40-DL40 -> 1815.1909 | DQ40: =INDEX('Income Statement'!19:19, MATCH('Interim (New)'!DQ$1,'Income Statement'!$3:$3,0)) -> 3573.1909 | DT40: =(DD40/DI40)*DY40 -> 1833.6962 | DX40: =DY40-DT40 -> 2189.0194 | DY40: =INDEX('Income Statement'!19:19, MATCH('Interim (New)'!DY$1,'Income Statement'!$3:$3,0)) -> 4022.7156
A41: Aircraft Equipment | D41: 99 | H41: 103 | L41: 134 | P41: 152 | T41: 174 | X41: 202 | AB41: 197 | AF41: 229 | AJ41: 199 | AN41: 267 | AR41: 271 | AV41: 296 | AZ41: 327 | BD41: 292 | BH41: 300 | BL41: 369
A42: Defence | D42: 31 | H42: 27 | L42: 45 | P42: 34 | T42: 45 | X42: 39 | AB42: 43 | AF42: 28 | AJ42: 15 | AN42: 49 | AR42: 22 | AV42: 54 | AZ42: 40 | BD42: 53 | BH42: 45 | BL42: 73
A43: Aerosystems | BH43: 97 | BL43: 108
A44: Equipment & Defense | BH44: 442 | BL44: 550 | BP44: 588 | BT44: 621 | BX44: 343 | CB44: 344 | CF44: 270 | CJ44: 380 | CK44: =INDEX('Income Statement'!20:20, MATCH('Interim (New)'!CK$1,'Income Statement'!$3:$3,0)) -> 650 | CN44: 411 | CR44: 463 | CS44: =INDEX('Income Statement'!20:20, MATCH('Interim (New)'!CS$1,'Income Statement'!$3:$3,0)) -> 874 | CV44: 466 | CZ44: 526 | DA44: =INDEX('Income Statement'!20:20, MATCH('Interim (New)'!DA$1,'Income Statement'!$3:$3,0)) -> 992 | DD44: 657 | DH44: 641 | DI44: =INDEX('Income Statement'!20:20, MATCH('Interim (New)'!DI$1,'Income Statement'!$3:$3,0)) -> 1298 | DL44: 703 | DP44: =DQ44-DL44 -> 863.09055 | DQ44: =INDEX('Income Statement'!20:20, MATCH('Interim (New)'!DQ$1,'Income Statement'!$3:$3,0)) -> 1566.0906 | DT44: =(DD44/DI44)*DY44 -> 988.40859 | DX44: =DY44-DT44 -> 964.33776 | DY44: =INDEX('Income Statement'!20:20, MATCH('Interim (New)'!DY$1,'Income Statement'!$3:$3,0)) -> 1952.7463
A45: Aircraft Interiors | BH45: 32 | BL45: 49 | BP45: 85 | BT45: 103 | BX45: -101 | CB45: -73 | CF45: -110 | CJ45: -57 | CK45: =INDEX('Income Statement'!21:21, MATCH('Interim (New)'!CK$1,'Income Statement'!$3:$3,0)) -> -167 | CN45: -82 | CR45: -58 | CS45: =INDEX('Income Statement'!21:21, MATCH('Interim (New)'!CS$1,'Income Statement'!$3:$3,0)) -> -140 | CV45: -100 | CZ45: -16 | DA45: =INDEX('Income Statement'!21:21, MATCH('Interim (New)'!DA$1,'Income Statement'!$3:$3,0)) -> -116 | DD45: 10 | DH45: 17 | DI45: =INDEX('Income Statement'!21:21, MATCH('Interim (New)'!DI$1,'Income Statement'!$3:$3,0)) -> 27 | DL45: 27 | DP45: =DQ45-DL45 -> 79.692816 | DQ45: =INDEX('Income Statement'!21:21, MATCH('Interim (New)'!DQ$1,'Income Statement'!$3:$3,0)) -> 106.69282 | DT45: =(DD45/DI45)*DY45 -> 74.270891 | DX45: =DY45-DT45 -> 126.26052 | DY45: =INDEX('Income Statement'!21:21, MATCH('Interim (New)'!DY$1,'Income Statement'!$3:$3,0)) -> 200.53141
A46: Security | D46: 59 | H46: 80 | L46: 66 | P46: 79 | T46: 65 | X46: 55 | AB46: 64 | AF46: 70 | AJ46: 66 | AN46: 85 | AR46: 79 | AV46: -79 | DT46: =(DD46/DI46)*DY46 -> #DIV/0!
A47: Other | D47: -59 | H47: -60 | L47: -76 | P47: -66 | T47: -68 | X47: -90 | AB47: -75 | AF47: -100 | AJ47: -53 | AN47: -29 | AR47: -5 | AV47: -20 | AZ47: 2 | BD47: -38 | BH47: -3 | BL47: -77 | BP47: -17 | BT47: -45 | BX47: 6 | CB47: -25 | CF47: -5 | CJ47: -15 | CK47: =INDEX('Income Statement'!22:22, MATCH('Interim (New)'!CK$1,'Income Statement'!$3:$3,0)) -> -20 | CN47: -5 | CR47: -31 | CS47: =INDEX('Income Statement'!22:22, MATCH('Interim (New)'!CS$1,'Income Statement'!$3:$3,0)) -> -36 | CV47: -20 | CZ47: -80 | DA47: =INDEX('Income Statement'!22:22, MATCH('Interim (New)'!DA$1,'Income Statement'!$3:$3,0)) -> -100 | DD47: 22 | DH47: -47 | DI47: =INDEX('Income Statement'!22:22, MATCH('Interim (New)'!DI$1,'Income Statement'!$3:$3,0)) -> -25 | DL47: 22 | DP47: =DQ47-DL47 -> -50.879973 | DQ47: =INDEX('Income Statement'!22:22, MATCH('Interim (New)'!DQ$1,'Income Statement'!$3:$3,0)) -> -28.879973 | DT47: 22 | DX47: =DY47-DT47 -> -54.629619 | DY47: =INDEX('Income Statement'!22:22, MATCH('Interim (New)'!DY$1,'Income Statement'!$3:$3,0)) -> -32.629619
A48: Defence Security
A49: Communications
A50: Group | D50: =SUM(D40:D47) -> 554 | H50: =SUM(H40:H47) -> 635 | L50: =SUM(L40:L47) -> 681 | P50: =SUM(P40:P47) -> 763 | T50: =SUM(T40:T47) -> 847 | X50: =SUM(X40:X47) -> 933 | AB50: =SUM(AB40:AB47) -> 956 | AF50: =SUM(AF40:AF47) -> 1133 | AJ50: =SUM(AJ40:AJ47) -> 1171 | AN50: =SUM(AN40:AN47) -> 1261 | AR50: =SUM(AR40:AR47) -> 1309 | AV50: =SUM(AV40:AV47) -> 1095 | AZ50: =SUM(AZ40:AZ47) -> 1218 | BD50: =SUM(BD40:BD47) -> 974 | BH50: =SUM(BH40:BH47) -> 1828 | BL50: =SUM(BL40:BL47) -> 2187 | BP50: =SUM(BP40:BP47) -> 1883 | BT50: =SUM(BT40:BT47) -> 1937 | BX50: =SUM(BX40:BX47) -> 947 | CB50: =SUM(CB40:CB47) -> 739 | CF50: =SUM(CF40:CF47) -> 659 | CJ50: =SUM(CJ40:CJ47) -> 1146 | CK50: =INDEX('Income Statement'!23:23, MATCH('Interim (New)'!CK$1,'Income Statement'!$3:$3,0)) -> 1805 | CN50: =SUM(CN40:CN47) -> 1047 | CR50: =SUM(CR40:CR47) -> 1361 | CS50: =INDEX('Income Statement'!23:23, MATCH('Interim (New)'!CS$1,'Income Statement'!$3:$3,0)) -> 2408 | CV50: =SUM(CV40:CV47) -> 1397 | CZ50: =SUM(CZ40:CZ47) -> 1769 | DA50: =INDEX('Income Statement'!23:23, MATCH('Interim (New)'!DA$1,'Income Statement'!$3:$3,0)) -> 3166 | DD50: =SUM(DD40:DD47) -> 1974 | DH50: =SUM(DH40:DH47) -> 2145 | DI50: =INDEX('Income Statement'!23:23, MATCH('Interim (New)'!DI$1,'Income Statement'!$3:$3,0)) -> 4119 | DL50: =SUM(DL40:DL47) -> 2510 | DP50: =SUM(DP40:DP47) -> 2707.0943 | DQ50: =INDEX('Income Statement'!23:23, MATCH('Interim (New)'!DQ$1,'Income Statement'!$3:$3,0)) -> 5217.0943 | DT50: =DT40+DT44+DT45+DT47 -> 2918.3757 | DX50: =DY50-DT50 -> 3224.9881 | DY50: =INDEX('Income Statement'!23:23, MATCH('Interim (New)'!DY$1,'Income Statement'!$3:$3,0)) -> 6143.3638
A52: Underlying EBITA margin
A53: Aerospace Propulsion | CF53: =CF40/CF6 -> 0.15512465 | CJ53: =CJ40/CJ6 -> 0.2 | CK53: =CK40/CK6 -> 0.18040059 | CN53: =CN40/CN6 -> 0.17313218 | CR53: =CR40/CR6 -> 0.18517824 | CS53: =CS40/CS6 -> 0.17988639 | CV53: =CV40/CV6 -> 0.18513299 | CZ53: =CZ40/CZ6 -> 0.21600258 | DA53: =DA40/DA6 -> 0.20124621 | DD53: =DD40/DD6 -> 0.19888562 | DH53: =DH40/DH6 -> 0.21332221 | DI53: =DI40/DI6 -> 0.20648989 | DL53: =DL40/DL6 -> 0.23312558 | DP53: =DP40/DP6 -> 0.21887234 | DQ53: =DQ40/DQ6 -> 0.22566034 | DT53: =DT40/DT6 -> 0.21759204 | DX53: =DX40/DX6 -> 0.23338647 | DY53: =DY40/DY6 -> 0.22591154
A54: Aircraft Equipment
A55: Defence
A56: Aerosystems
