Workbook
Name A_ALL_KEYWORDS_TYPE_ScalarContributed_EQTY_200001648: #REF!,#REF!,#REF!,#REF!,#REF!
Name A_ALL_KEYWORDS_TYPE_ScalarContributed_ISSR_208000604: #REF!,#REF!
Name A_ALL_KEYWORDS_TYPE_ScalarReference_EQTY_200001648: #REF!
Name A_ALL_KEYWORDS_TYPE_ScalarReference_ISSR_208000604: #REF!
Name A_ALL_KEYWORDS_TYPE_Vector_EQTY_200001648: #REF!,#REF!,#REF!,#REF!,#REF!,#REF!,#REF!
Name A_ALL_KEYWORDS_TYPE_Vector_ISSR_208000604: #REF!,#REF!,#REF!,#REF!,#REF!,#REF!,#REF!,#REF!,#REF!
Name A_ALL_RTX: #REF!
Name A_ALL_SECTION_KEYWORDS_EQTY_200001648_1314: #REF!
Name A_ALL_SECTION_KEYWORDS_EQTY_200001648_1319: #REF!
Name A_ALL_SECTION_KEYWORDS_EQTY_200001648_131E: #REF!
Name A_ALL_SECTION_KEYWORDS_EQTY_200001648_131O: #REF!
Name A_ALL_SECTION_KEYWORDS_EQTY_200001648_13A: #REF!
Name A_ALL_SECTION_KEYWORDS_EQTY_200001648_13K: #REF!
Name A_ALL_SECTION_KEYWORDS_EQTY_200001648_13U: #REF!
Name A_ALL_SECTION_KEYWORDS_EQTY_200001648_13V: #REF!
Name A_ALL_SECTION_KEYWORDS_EQTY_200001648_13W: #REF!
Name A_ALL_SECTION_KEYWORDS_EQTY_200001648_Reference_Data: #REF!
Name A_ALL_SECTION_KEYWORDS_ISSR_208000604_1314: #REF!
Name A_ALL_SECTION_KEYWORDS_ISSR_208000604_13168: #REF!
Name A_ALL_SECTION_KEYWORDS_ISSR_208000604_1316S: #REF!
Name A_ALL_SECTION_KEYWORDS_ISSR_208000604_1316T: #REF!
Name A_ALL_SECTION_KEYWORDS_ISSR_208000604_1316U: #REF!
Name A_ALL_SECTION_KEYWORDS_ISSR_208000604_1319: #REF!
Name A_ALL_SECTION_KEYWORDS_ISSR_208000604_131E: #REF!
Name A_ALL_SECTION_KEYWORDS_ISSR_208000604_131J: #REF!
Name A_ALL_SECTION_KEYWORDS_ISSR_208000604_131O: #REF!
Name A_ALL_SECTION_KEYWORDS_ISSR_208000604_136E: #REF!,#REF!
Name A_ALL_SECTION_KEYWORDS_ISSR_208000604_13A: #REF!
Name A_ALL_SECTION_KEYWORDS_ISSR_208000604_13U: #REF!
Name A_ALL_SECTION_KEYWORDS_ISSR_208000604_13V: #REF!
Name A_ALL_SECTION_KEYWORDS_ISSR_208000604_Reference_Data: #REF!
Name A_ALL_SECTIONS_EQTY_200001648: #REF!,#REF!,#REF!,#REF!,#REF!,#REF!,#REF!,#REF!,#REF!,#REF!
Name A_ALL_UTX_: #REF!
Name A_CURRENCY_EQTY_200001648_PRI: #REF!
Name A_CURRENCY_EQTY_200001648_PUB: #REF!
Name A_CURRENCY_EQTY_200001648_REP: #REF!
Name A_CURRENCY_ISSR_208000604_REP: #REF!
Name A_KEYWORD_EQTY_200001648_AMER_LIST: #REF!
Name A_KEYWORD_EQTY_200001648_BETA_ANALYST: #REF!
Name A_KEYWORD_EQTY_200001648_BVPS: #REF!
Name A_KEYWORD_EQTY_200001648_BVPS_PUB: #REF!
Name A_KEYWORD_EQTY_200001648_CEEE_EPS: #REF!
Name A_KEYWORD_EQTY_200001648_CF_NI_PRE_PREF: #REF!
Name A_KEYWORD_EQTY_200001648_COMMON_DIV_PAID: #REF!
Name A_KEYWORD_EQTY_200001648_CURRENCY_ISO: #REF!
Name A_KEYWORD_EQTY_200001648_DILUTE_SHARES: #REF!
Name A_KEYWORD_EQTY_200001648_DPS: #REF!
Name A_KEYWORD_EQTY_200001648_DPS_PUB: #REF!
Name A_KEYWORD_EQTY_200001648_EBIT_PUB: #REF!
Name A_KEYWORD_EQTY_200001648_EBITDA_PUB: #REF!
Name A_KEYWORD_EQTY_200001648_EPS: #REF!
Name A_KEYWORD_EQTY_200001648_EPS_EX_ESO_B: #REF!
Name A_KEYWORD_EQTY_200001648_EPS_EX_ESO_D: #REF!
Name A_KEYWORD_EQTY_200001648_EPS_FUL_DIL: #REF!
Name A_KEYWORD_EQTY_200001648_EPS_POST_BASIC: #REF!
Name A_KEYWORD_EQTY_200001648_EPS_PUB: #REF!
Name A_KEYWORD_EQTY_200001648_EPS_PUB_EX_ESO: #REF!
Name A_KEYWORD_EQTY_200001648_EQ_PUB: #REF!
Name A_KEYWORD_EQTY_200001648_ESO_POST_TAX: #REF!
Name A_KEYWORD_EQTY_200001648_ESO_YEAR: #REF!

Sheet __FDSCACHE__
B1: This sheet contains FactSet XML data for use with this workbook's =FDS codes. Modifying the worksheet's contents may damage the workbook's =FDS functionality.

Sheet Cover
D7: Raytheon Technologies (RTX) Model
D8: 45951
B16: Noah Poponak, CFA
B17: (212) 357-0954
B18: noah.poponak@gs.com
B20: Anthony Valentini, CFA
B21: (212) 934-0385
B22: anthony.valentini@gs.com
B24: Connor Dessert
B25: (212) 357-6166
B26: connor.dessert@gs.com
B28: Will Ortmayer
B29: (801) 744-0681
B30: will.ortmayer@gs.com

Sheet Data
B3: RTX Raw Data | C3: 1997 | D3: 1998 | E3: 1999 | F3: 2000 | G3: 2001 | H3: 2002 | I3: 2003 | J3: 1Q04 | K3: 2Q04 | L3: 3Q04 | M3: 4Q04 | N3: 2004 | O3: 1Q05 | P3: 2Q05 | Q3: 3Q05 | R3: 4Q05 | S3: 2005 | T3: 1Q06 | U3: 2Q06 | V3: 3Q06 | W3: 4Q06 | X3: 2006 | Y3: 1Q07 | Z3: 2Q07 | AA3: 3Q07 | AB3: 4Q07 | AC3: 2007 | AD3: 1Q08 | AE3: 2Q08 | AF3: 3Q08 | AG3: 4Q08 | AH3: 2008 | AI3: 1Q09 | AJ3: 2Q09 | AK3: 3Q09 | AL3: 4Q09 | AM3: 2009 | AN3: 1Q10 | AO3: 2Q10 | AP3: 3Q10 | AQ3: 4Q10 | AR3: 2010 | AS3: 1Q11 | AT3: 2Q11 | AU3: 3Q11 | AV3: 4Q11 | AW3: 2011 | AX3: 1Q12 | AY3: 2Q12 | AZ3: 3Q12 | BA3: 4Q12 | BB3: 2012 | BC3: 1Q13 | BD3: 2Q13 | BE3: 3Q13 | BF3: 4Q13 | BG3: 2013 | BH3: 1Q14 | BI3: 2Q14 | BJ3: 3Q14 | BK3: 4Q14 | BL3: 2014 | BM3: 1Q15 | BN3: 2Q15 | BO3: 3Q15 | BP3: 4Q15 | BQ3: 2015 | BR3: 1Q16 | BS3: 2Q16 | BT3: 3Q16 | BU3: 4Q16 | BV3: 2016 | BW3: 1Q17 | BX3: 2Q17 | BY3: 3Q17 | BZ3: 4Q17 | CA3: 2017 | CB3: 1Q18 | CC3: 2Q18 | CD3: 3Q18 | CE3: 4Q18 | CF3: 2018 | CG3: 1Q19 | CH3: 2Q19 | CI3: 3Q19 | CJ3: 4Q19 | CK3: 2019 | CL3: 1Q20 | CM3: 2Q20 | CN3: 3Q20 | CO3: 4Q20 | CP3: 2020 | CQ3: 1Q21 | CR3: 2Q21 | CS3: 3Q21 | CT3: 4Q21 | CU3: 2021 | CV3: 1Q22 | CW3: 2Q22 | CX3: 3Q22 | CY3: 4Q22 | CZ3: 2022 | DA3: 1Q23 | DB3: 2Q23 | DC3: 3Q23 | DD3: 4Q23 | DE3: 2023 | DF3: 1Q24 | DG3: 2Q24 | DH3: 3Q24 | DI3: 4Q24 | DJ3: 2024 | DK3: 1Q25 | DL3: 2Q25 | DM3: 3Q25 | DN3: 4Q25 | DO3: 2025 | DP3: 1Q26 | DQ3: 2Q26 | DR3: 3Q26 | DS3: 4Q26 | DT3: 2026 | DU3: 2027 | DV3: 2028
B4: ($ mn) | C4: 35795 | D4: 36160 | E4: 36525 | F4: 36891 | G4: 37256 | H4: 37621 | I4: 37986 | J4: 38076 | K4: 38168 | L4: 38260 | M4: 38352 | N4: 38352 | O4: 38441 | P4: 38533 | Q4: 38625 | R4: 38717 | S4: 38717 | T4: 38806 | U4: 38898 | V4: 38990 | W4: 39082 | X4: 39082 | Y4: 39171 | Z4: 39263 | AA4: 39355 | AB4: 39447 | AC4: 39447 | AD4: 39537 | AE4: 39629 | AF4: 39721 | AG4: 39813 | AH4: 39813 | AI4: 39902 | AJ4: 39994 | AK4: 40086 | AL4: 40178 | AM4: 40178 | AN4: 40267 | AO4: 40359 | AP4: 40451 | AQ4: 40543 | AR4: 40543 | AS4: 40632 | AT4: 40724 | AU4: 40816 | AV4: 40908 | AW4: 40908 | AX4: 40998 | AY4: 41090 | AZ4: 41182 | BA4: 41274 | BB4: 41274 | BC4: 41363 | BD4: 41455 | BE4: 41547 | BF4: 41639 | BG4: 41639 | BH4: 41728 | BI4: 41820 | BJ4: 41912 | BK4: 42004 | BL4: 42004 | BM4: 42093 | BN4: 42185 | BO4: 42277 | BP4: 42369 | BQ4: 42369 | BR4: 42459 | BS4: 42551 | BT4: 42643 | BU4: 42735 | BV4: 42735 | BW4: 42824 | BX4: 42916 | BY4: 43008 | BZ4: 43100 | CA4: 43100 | CB4: 43189 | CC4: 43281 | CD4: 43373 | CE4: 43465 | CF4: 43465 | CG4: 43554 | CH4: 43646 | CI4: 43738 | CJ4: 43830 | CK4: 43830 | CL4: 43920 | CM4: 44012 | CN4: 44104 | CO4: 44196 | CP4: 44196 | CQ4: 44285 | CR4: 44377 | CS4: 44469 | CT4: 44561 | CU4: 44561 | CV4: 44650 | CW4: 44742 | CX4: 44834 | CY4: 44926 | CZ4: 44926 | DA4: 45015 | DB4: 45107 | DC4: 45199 | DD4: 45291 | DE4: 45291 | DF4: 45381 | DG4: 45473 | DH4: 45565 | DI4: 45657 | DJ4: 45657 | DK4: 45746 | DL4: 45838 | DM4: 45930 | DN4: 46022 | DO4: 46022 | DP4: 46111 | DQ4: 46203 | DR4: 46295 | DS4: 46387 | DT4: 46387 | DU4: 46752 | DV4: 47118
B6: Income Statement
B7: Product sales | CF7: 53157 | CG7: 13651.4 | CH7: 14208.6 | CI7: 14350.14 | CJ7: 14935.86 | CN7: 11469 | CQ7: 11664
B8: Service sales | CF8: 16015 | CG8: 4013.1 | CH8: 4176.9 | CI8: 4361.49 | CJ8: 4539.51 | CN8: 3278 | CQ8: 3587
B9: Net sales | CF9: =CF7+CF8 -> 69172 | CG9: 17664.5 | CH9: 18385.5 | CI9: 18711.63 | CJ9: 19475.37 | CK9: =SUM(CG9:CJ9) -> 74237 | CL9: 18451 | CM9: 14470 | CN9: =CN7+CN8 -> 14747 | CO9: 16419 | CP9: =SUM(CL9:CO9) -> 64087 | CQ9: =CQ7+CQ8 -> 15251 | CR9: 15880 | CS9: 16213 | CT9: 17044 | CV9: 15716 | CW9: 16314 | CX9: 16951 | CY9: 18093 | DA9: 17214 | DB9: 18315 | DC9: 13464 | DD9: 19927 | DF9: 19305 | DG9: 19721 | DH9: 20089 | DI9: 21623 | DK9: 20306 | DL9: 21581 | DM9: 22478
B10: Cost of products sold | CF10: 42281 | CG10: 10703.07 | CH10: 11139.93 | CI10: 11715.41 | CJ10: 12193.59 | CM10: 9620 | CN10: 10322 | CQ10: 9974
B11: Cost of services sold | CF11: 10602 | CG11: 2651.39 | CH11: 2759.61 | CI11: 2912.07 | CJ11: 3030.93 | CM11: 2594 | CN11: 2682 | CQ11: 2563
B12: Cost of goods sold | CF12: =CF10+CF11 -> 52883 | CG12: 13354.46 | CH12: 13899.54 | CI12: 14627.48 | CJ12: 15224.52 | CK12: =SUM(CG12:CJ12) -> 57106 | CM12: =CM10+CM11 -> 12214 | CN12: =CN10+CN11 -> 13004 | CO12: 14266 | CQ12: =CQ10+CQ11 -> 12537 | CR12: 12655 | CS12: 13089 | CT12: 13616 | CV12: 12560 | CW12: 12856 | CX12: 13464 | CY12: 14526 | DA12: 13645 | DB12: 14518 | DC12: 12750 | DD12: 15918 | DF12: 15744 | DG12: 16141 | DH12: 16055 | DI12: 17388 | DK12: 16190 | DL12: 17205 | DM12: 17898
B13: Research and development | CF13: 3252 | CG13: 779.1 | CH13: 810.9 | CI13: 782.04 | CJ13: 813.96 | CK13: =SUM(CG13:CJ13) -> 3186 | CM13: 695 | CN13: 642 | CO13: 710 | CQ13: 589 | CR13: 657 | CS13: 676 | CT13: 810 | CV13: 635 | CW13: 698 | CX13: 662 | CY13: 716 | DA13: 607 | DB13: 729 | DC13: 712 | DD13: 757 | DF13: 669 | DG13: 706 | DH13: 751 | DI13: 808 | DK13: 637 | DL13: 697 | DM13: 684
B14: Selling and administrative expenses | CF14: 5553 | CG14: 1368.08 | CH14: 1423.92 | CI14: 1450.89 | CJ14: 1510.11 | CK14: =SUM(CG14:CJ14) -> 5753 | CM14: 1811 | CN14: 1401 | CO14: 1351 | CQ14: 1220 | CR14: 1368 | CS14: 1229 | CT14: 1407 | CV14: 1469 | CW14: 1424 | CX14: 1391 | CY14: 1379 | DA14: 1398 | DB14: 1635 | DC14: 1401 | DD14: 1445 | DF14: 1394 | DG14: 1449 | DH14: 1389 | DI14: 1574 | DK14: 1448 | DL14: 1573 | DM14: 1436
B15: Charges & other | CM15: -3183 | CT15: -617
B16: Other income (expense), net | CF16: 337 | CG16: 97.02 | CH16: 100.98 | CI16: 75.95 | CJ16: 79.05 | CK16: =SUM(CG16:CJ16) -> 353 | CM16: 82 | CN16: 734 | CO16: 50 | CQ16: 108 | CR16: 82 | CS16: 124 | CT16: =109 -> 109 | CV16: 28 | CW16: 17 | CX16: 46 | CY16: 29 | DA16: 88 | DB16: 25 | DC16: 3 | DD16: -30 | DF16: 372 | DG16: -896 | DH16: 134 | DI16: 258 | DK16: 4 | DL16: 40 | DM16: 63
B17: EBIT | CF17: =CF9-CF12-CF13-CF14+CF16 -> 7821 | CG17: 2259.88 | CH17: 2352.12 | CI17: 1927.17 | CJ17: 2005.83 | CK17: =CK9-CK12-CK13-CK14+CK16 -> 8545 | CL17: 2187 | CM17: -3617 | CN17: =CN9-CN12-CN13-CN14+CN15+CN16 -> 434 | CO17: =CO9-CO12-CO13-CO14+CO15+CO16 -> 142 | CP17: =SUM(CL17:CO17) -> -854 | CQ17: =CQ9-CQ12-CQ13-CQ14+CQ15+CQ16 -> 1013 | CR17: =CR9-CR12-CR13-CR14+CR15+CR16 -> 1282 | CS17: =CS9-CS12-CS13-CS14+CS15+CS16 -> 1343 | CT17: =CT9-CT12-CT13-CT14+CT15+CT16 -> 703 | CV17: =CV9-CV12-CV13-CV14+CV15+CV16 -> 1080 | CW17: =CW9-CW12-CW13-CW14+CW15+CW16 -> 1353 | CX17: =CX9-CX12-CX13-CX14+CX15+CX16 -> 1480 | CY17: =CY9-CY12-CY13-CY14+CY15+CY16 -> 1501 | DA17: =DA9-DA12-DA13-DA14+DA15+DA16 -> 1652 | DB17: =DB9-DB12-DB13-DB14+DB15+DB16 -> 1458 | DC17: =DC9-DC12-DC13-DC14+DC15+DC16 -> -1396 | DD17: =DD9-DD12-DD13-DD14+DD15+DD16 -> 1777 | DF17: =DF9-DF12-DF13-DF14+DF15+DF16 -> 1870 | DG17: =DG9-DG12-DG13-DG14+DG15+DG16 -> 529 | DH17: =DH9-DH12-DH13-DH14+DH15+DH16 -> 2028 | DI17: =DI9-DI12-DI13-DI14+DI15+DI16 -> 2111 | DK17: =DK9-DK12-DK13-DK14+DK15+DK16 -> 2035 | DL17: =DL9-DL12-DL13-DL14+DL15+DL16 -> 2146 | DM17: =DM9-DM12-DM13-DM14+DM15+DM16 -> 2523
B18: Non-service pension (benefit) cost | CF18: -1305 | CG18: -315.07 | CH18: -327.93 | CI18: -278.81 | CJ18: -290.19 | CK18: =SUM(CG18:CJ18) -> -1212 | CL18: -276 | CM18: -225 | CN18: -253 | CO18: -244 | CP18: =SUM(CL18:CO18) -> -998 | CQ18: -491 | CR18: -490 | CS18: -491 | CT18: -472 | CV18: -480 | CW18: -474 | CX18: -468 | CY18: -467 | DA18: -444 | DB18: -447 | DC18: -443 | DD18: -446 | DF18: -386 | DG18: -374 | DH18: -374 | DI18: -384 | DK18: -366 | DL18: -351 | DM18: -364
B19: Interest expense (income), net | CF19: 1001 | CG19: 253.82 | CH19: 264.18 | CI19: 274.89 | CJ19: 286.11 | CK19: =SUM(CG19:CJ19) -> 1079 | CL19: 252 | CM19: 337 | CN19: 350 | CO19: 349 | CP19: =SUM(CL19:CO19) -> 1288 | CQ19: 346 | CR19: 342 | CS19: 358 | CT19: 308 | CV19: 318 | CW19: 329 | CX19: 311 | CY19: 318 | DA19: 315 | DB19: 333 | DC19: 369 | DD19: 488 | DF19: 405 | DG19: 475 | DH19: 496 | DI19: 486 | DK19: 443 | DL19: 457 | DM19: 449
B20: EBT | CF20: =CF17-CF18-CF19 -> 8125 | CG20: 2321.13 | CH20: 2415.87 | CI20: 1931.09 | CJ20: 2009.91 | CK20: =CK17-CK18-CK19 -> 8678 | CL20: =CL17-CL18-CL19 -> 2211 | CM20: =CM17-CM18-CM19 -> -3729 | CN20: =CN17-CN18-CN19 -> 337 | CO20: =CO17-CO18-CO19 -> 37 | CP20: =SUM(CL20:CO20) -> -1144 | CQ20: =CQ17-CQ18-CQ19 -> 1158 | CR20: =CR17-CR18-CR19 -> 1430 | CS20: =CS17-CS18-CS19 -> 1476 | CT20: =CT17-CT18-CT19 -> 867 | CV20: =CV17-CV18-CV19 -> 1242 | CW20: =CW17-CW18-CW19 -> 1498 | CX20: =CX17-CX18-CX19 -> 1637 | CY20: =CY17-CY18-CY19 -> 1650 | DA20: =DA17-DA18-DA19 -> 1781 | DB20: =DB17-DB18-DB19 -> 1572 | DC20: =DC17-DC18-DC19 -> -1322 | DD20: =DD17-DD18-DD19 -> 1735 | DF20: =DF17-DF18-DF19 -> 1851 | DG20: =DG17-DG18-DG19 -> 428 | DH20: =DH17-DH18-DH19 -> 1906 | DI20: =DI17-DI18-DI19 -> 2009 | DK20: =DK17-DK18-DK19 -> 1958 | DL20: =DL17-DL18-DL19 -> 2040 | DM20: =DM17-DM18-DM19 -> 2438
B21: Income tax expense (income) | CF21: 1808 | CG21: 296.94 | CH21: 309.06 | CI21: 299.88 | CJ21: 312.12 | CK21: =SUM(CG21:CJ21) -> 1218 | CL21: 419 | CM21: -23 | CN21: 152 | CO21: -178 | CP21: =SUM(CL21:CO21) -> 370 | CQ21: 345 | CR21: 342 | CS21: 3 | CT21: 96 | CV21: 116 | CW21: 160 | CX21: 242 | CY21: 182 | DA21: 300 | DB21: 213 | DC21: -389 | DD21: 262 | DF21: 108 | DG21: 253 | DH21: 371 | DI21: 449 | DK21: 333 | DL21: 315 | DM21: 432
B22: Net income, continuing ops.
B23: Discontinued ops. & non recurring items: | CM23: 9 | CN23: =13-100 -> -87 | CO23: =-14+3 -> -11 | CP23: =SUM(CL23:CO23) -> -89 | CQ23: -20 | CR23: -8 | CS23: -73 | CT23: -21
B24: Net income | CF24: =CF20-CF21 -> 6317 | CG24: 2024.19 | CH24: 2106.81 | CI24: 1631.21 | CJ24: 1697.79 | CK24: =CK20-CK21 -> 7460 | CL24: =CL20-CL21 -> 1792 | CM24: =CM20-CM21 -> -3706 | CN24: =CN20-CN21 -> 185 | CO24: =CO20-CO21 -> 215 | CP24: =SUM(CL24:CO24) -> -1514 | CQ24: =CQ20-CQ21 -> 813 | CR24: =CR20-CR21 -> 1088 | CS24: =CS20-CS21 -> 1473 | CT24: =CT20-CT21 -> 771 | CV24: =CV20-CV21 -> 1126 | CW24: =CW20-CW21 -> 1338 | CX24: =CX20-CX21 -> 1395 | CY24: =CY20-CY21 -> 1468 | DA24: =DA20-DA21 -> 1481 | DB24: =DB20-DB21 -> 1359 | DC24: =DC20-DC21 -> -933 | DD24: =DD20-DD21 -> 1473 | DF24: =DF20-DF21 -> 1743 | DG24: =DG20-DG21 -> 175 | DH24: =DH20-DH21 -> 1535 | DI24: =DI20-DI21 -> 1560 | DK24: =DK20-DK21 -> 1625 | DL24: =DL20-DL21 -> 1725 | DM24: =DM20-DM21 -> 2006
B25: Non controlling interest | CF25: 163 | CG25: 41.16 | CH25: 42.84 | CI25: 60.27 | CJ25: 62.73 | CK25: =SUM(CG25:CJ25) -> 207 | CL25: 56 | CM25: 24 | CN25: 34 | CO25: 69 | CP25: =SUM(CL25:CO25) -> 183 | CQ25: 41 | CR25: 48 | CS25: 73 | CT25: 86 | CV25: 23 | CW25: 34 | CX25: 8 | CY25: 46 | DA25: 55 | DB25: 32 | DC25: 51 | DD25: 47 | DF25: 34 | DG25: 64 | DH25: 63 | DI25: 78 | DK25: 90 | DL25: 68 | DM25: 88
B26: Net income attributable to shareholders | CF26: =CF24-CF25 -> 6154 | CG26: 1983.03 | CH26: 2063.97 | CI26: 1570.94 | CJ26: 1635.06 | CK26: =CK24-CK25 -> 7253 | CL26: =CL24-CL25 -> 1736 | CM26: =CM24-CM25 -> -3730 | CN26: =CN24-CN25 -> 151 | CO26: =CO24-CO25 -> 146 | CP26: =SUM(CL26:CO26) -> -1697 | CQ26: =CQ24-CQ25 -> 772 | CR26: =CR24-CR25 -> 1040 | CS26: =CS24-CS25 -> 1400 | CT26: =CT24-CT25 -> 685 | CV26: =CV24-CV25 -> 1103 | CW26: =CW24-CW25 -> 1304 | CX26: =CX24-CX25 -> 1387 | CY26: =CY24-CY25 -> 1422 | DA26: =DA24-DA25 -> 1426 | DB26: =DB24-DB25 -> 1327 | DC26: =DC24-DC25 -> -984 | DD26: =DD24-DD25 -> 1426 | DF26: =DF24-DF25 -> 1709 | DG26: =DG24-DG25 -> 111 | DH26: =DH24-DH25 -> 1472 | DI26: =DI24-DI25 -> 1482 | DK26: =DK24-DK25 -> 1535 | DL26: =DL24-DL25 -> 1657 | DM26: =DM24-DM25 -> 1918
B28: Net income, continuing ops. attributable to shareholders
B29: =+B23 -> Discontinued ops. & non recurring items:
B30: =+B26 -> Net income attributable to shareholders
B32: Basic EPS, continuing ops. | CF32: =CF26/CF41 -> 4.2491197 | CG32: 1.32 | CH32: 1.37 | CI32: 1.04 | CJ32: 1.09 | CK32: =CK26/CK41 -> 4.8237563 | CL32: =CL26/CL41 -> 1.1521869 | CM32: =CM26/CM41 -> -2.4845134 | CN32: =CN26/CN41 -> 0.099900761 | CO32: =CO26/CO41 -> 0.096541691 | CP32: =CP26/CP41 -> -1.1225772 | CQ32: =CQ26/CQ41 -> 0.51088611 | CR32: =CR26/CR41 -> 0.69038768 | ... CT32: =CT26/CT41 -> 0.45957732 | CV32: =CV26/CV41 -> 0.74186172 | CW32: =CW26/CW41 -> 0.8815576 | CX32: =CX26/CX41 -> 0.94347323 | CY32: =CY26/CY41 -> 0.9703173 | DA32: =DA26/DA41 -> 0.97524278 | DB32: =DB26/DB41 -> 0.91046312 | DC32: =DC26/DC41 -> -0.67951108 | DD32: =DD26/DD41 -> 1.0524762 | DF32: =DF26/DF41 -> 1.2855423 | DG32: =DG26/DG41 -> 0.083345848 | DH32: =DH26/DH41 -> 1.1041104 | DI32: =DI26/DI41 -> 1.1106115 | DK32: =DK26/DK41 -> 1.1480069 | DL32: =DL26/DL41 -> 1.2360137 | DM32: =DM26/DM41 -> 1.4280396
B33: Discontinued ops. & non recurring items
B34: Basic EPS, reported
B36: Diluted EPS, continuing ops. | CF36: =CF26/CF42 -> 4.2173794 | CG36: 1.31 | CH36: 1.36 | CI36: 1.03 | CJ36: 1.08 | CK36: =CK26/CK42 -> 4.784932 | CL36: =CL26/CL42 -> 1.1436854 | CM36: =CM26/CM42 -> -2.4845134 | CN36: =CN26/CN42 -> 0.099722626 | CO36: =CO26/CO42 -> 0.0963442 | CP36: =CP26/CP42 -> -1.1225772 | CQ36: =CQ26/CQ42 -> 0.50987385 | CR36: =CR26/CR42 -> 0.68714899 | ... CT36: =CT26/CT42 -> 0.45660579 | CV36: =CV26/CV42 -> 0.73636424 | CW36: =CW26/CW42 -> 0.87540279 | CX36: =CX26/CX42 -> 0.93760562 | CY36: =CY26/CY42 -> 0.96321886 | DA36: =DA26/DA42 -> 0.9673043 | DB36: =DB26/DB42 -> 0.90352012 | DC36: =DC26/DC42 -> -0.67596345 | DD36: =DD26/DD42 -> 1.0472204 | DF36: =DF26/DF42 -> 1.2779481 | DG36: =DG26/DG42 -> 0.082706207 | DH36: =DH26/DH42 -> 1.0934482 | DI36: =DI26/DI42 -> 1.098673 | DK36: =DK26/DK42 -> 1.135523 | DL36: =DL26/DL42 -> 1.2237814 | DM36: =DM26/DM42 -> 1.4119552
B37: Discontinued ops. & non recurring items
B38: Diluted EPS, reported
B40: Common shares outstanding
B41: Basic | CF41: 1448.3 | CG41: 1501.7 | CH41: 1501.7 | CI41: 1505.5 | CJ41: 1505.5 | CK41: 1503.6 | CL41: 1506.7 | CM41: 1501.3 | CN41: 1511.5 | CO41: 1512.3 | CP41: 1511.7 | CQ41: 1511.1 | CR41: 1506.4 | CS41: 1497.9 | CT41: 1490.5 | CV41: 1486.8 | CW41: 1479.2 | CX41: 1470.1 | CY41: 1465.5 | DA41: 1462.2 | DB41: 1457.5 | DC41: 1448.1 | DD41: 1354.9 | DF41: 1329.4 | DG41: 1331.8 | DH41: 1333.2 | DI41: 1334.4 | DK41: 1337.1 | DL41: 1340.6 | DM41: 1343.1
B42: Diluted | CF42: 1459.2 | CG42: 1512.5 | CH42: 1512.5 | CI42: 1519.1 | CJ42: 1519.1 | CK42: 1515.8 | CL42: 1517.9 | CM42: 1501.3 | CN42: 1514.2 | CO42: 1515.4 | CP42: 1511.7 | CQ42: 1514.1 | CR42: 1513.5 | CS42: 1505.9 | CT42: 1500.2 | CV42: 1497.9 | CW42: 1489.6 | CX42: 1479.3 | CY42: 1476.3 | DA42: 1474.2 | DB42: 1468.7 | DC42: 1455.7 | DD42: 1361.7 | DF42: 1337.3 | DG42: 1342.1 | DH42: 1346.2 | DI42: 1348.9 | DK42: 1351.8 | DL42: 1354 | DM42: 1358.4
CW45: =71-53 -> 18
B46: Balance Sheet
B48: Assets
B49: Cash and cash equivalents | CH49: 6480 | CJ49: 4937 | CK49: =CJ49 -> 4937 | CM49: 6975 | CN49: 10001 | CO49: 8802 | CP49: =CO49 -> 8802 | CQ49: 8579 | CR49: 8051 | CS49: 7476 | CT49: 7832 | CU49: =CT49 -> 7832 | CV49: 6040 | CW49: 4767 | CX49: 5381 | CY49: 6220 | CZ49: =CY49 -> 6220 | DA49: 5893 | DB49: 5391 | DC49: 5456 | DD49: 6587 | DE49: =DD49 -> 6587 | DF49: 5607 | DG49: 6011 | DH49: 6682 | DI49: 5578 | DJ49: =DI49 -> 5578 | DK49: 5157 | DL49: 4782 | DM49: 5966
B50: Accounts receivable, net | CH50: 9633 | CJ50: 8743 | CK50: =CJ50 -> 8743 | CM50: 9496 | CN50: 10115 | CO50: 9254 | CP50: =CO50 -> 9254 | CQ50: 10037 | CR50: 8912 | CS50: 9538 | CT50: 9661 | CU50: =CT50 -> 9661 | CV50: 9076 | CW50: 10394 | CX50: 9233 | CY50: 9108 | CZ50: =CY50 -> 9108 | DA50: 10069 | DB50: 9903 | DC50: 10058 | DD50: 10838 | DE50: =DD50 -> 10838 | DF50: 10280 | DG50: 10252 | DH50: 10097 | DI50: 10976 | DJ50: =DI50 -> 10976 | DK50: 11426 | DL50: 12385 | DM50: 12837
B51: Contract assets, current | CH51: 8969 | CJ51: 4462 | CK51: =CJ51 -> 4462 | CM51: 9943 | CN51: 9617 | CO51: 9931 | CP51: =CO51 -> 9931 | CQ51: 10238 | CR51: 10485 | CS51: 10899 | CT51: 11361 | CU51: =CT51 -> 11361 | CV51: 11566 | CW51: 11836 | CX51: 12297 | CY51: 11534 | CZ51: =CY51 -> 11534 | DA51: 12729 | DB51: 12970 | DC51: 12696 | DD51: 12139 | DE51: =DD51 -> 12139 | DF51: 13104 | DG51: 13581 | DH51: 14684 | DI51: 14570 | DJ51: =DI51 -> 14570 | DK51: 15241 | DL51: 15686 | DM51: 16604
B52: Inventories and contracts in progress, net | CH52: 9554 | CJ52: 9047 | CK52: =CJ52 -> 9047 | CM52: 10256 | CN52: 9843 | CO52: 9411 | CP52: =CO52 -> 9411 | CQ52: 9498 | CR52: 9548 | CS52: 9426 | CT52: 9178 | CU52: =CT52 -> 9178 | CV52: 9749 | CW52: 10142 | CX52: 10443 | CY52: 10617 | CZ52: =CY52 -> 10617 | DA52: 11327 | DB52: 11997 | DC52: 12050 | DD52: 11777 | DE52: =DD52 -> 11777 | DF52: 12386 | DG52: 13047 | DH52: 13465 | DI52: 12768 | DJ52: =DI52 -> 12768 | DK52: 13618 | DL52: 14012 | DM52: 13806
B53: Other assets, current | CH53: 1450 | CJ53: =31823+2565 -> 34388 | CK53: =CJ53 -> 34388 | CM53: =135+5469 -> 5604 | CN53: =56+3879 -> 3935 | CO53: =64+5914 -> 5978 | CP53: =CO53 -> 5978 | CQ53: 4200 | CR53: 3883 | CS53: 4653 | CT53: 4018 | CU53: =CT53 -> 4018 | CV53: 4309 | CW53: 4323 | CX53: 4467 | CY53: 4964 | CZ53: =CY53 -> 4964 | DA53: 5486 | DB53: 5654 | DC53: 6258 | DD53: 7076 | DE53: =DD53 -> 7076 | DF53: 6646 | DG53: 6334 | DH53: 6836 | DI53: 7241 | DJ53: =DI53 -> 7241 | DK53: 7474 | DL53: 7792 | DM53: 7905
B54: Total current assets | CH54: =SUM(CH49:CH53) -> 36086 | CJ54: =SUM(CJ49:CJ53) -> 61577 | CK54: =CJ54 -> 61577 | CM54: =SUM(CM49:CM53) -> 42274 | CN54: =SUM(CN49:CN53) -> 43511 | CO54: =SUM(CO49:CO53) -> 43376 | CP54: =CO54 -> 43376 | CQ54: =SUM(CQ49:CQ53) -> 42552 | CR54: =SUM(CR49:CR53) -> 40879 | CS54: =SUM(CS49:CS53) -> 41992 | CT54: =SUM(CT49:CT53) -> 42050 | CU54: =CT54 -> 42050 | CV54: =SUM(CV49:CV53) -> 40740 | CW54: =SUM(CW49:CW53) -> 41462 | CX54: =SUM(CX49:CX53) -> 41821 | CY54: =SUM(CY49:CY53) -> 42443 | CZ54: =CY54 -> 42443 | DA54: =SUM(DA49:DA53) -> 45504 | DB54: =SUM(DB49:DB53) -> 45915 | DC54: =SUM(DC49:DC53) -> 46518 | DD54: =SUM(DD49:DD53) -> 48417 | DE54: =DD54 -> 48417 | DF54: =SUM(DF49:DF53) -> 48023 | DG54: =SUM(DG49:DG53) -> 49225 | DH54: =SUM(DH49:DH53) -> 51764 | DI54: =SUM(DI49:DI53) -> 51133 | DJ54: =DI54 -> 51133 | DK54: =SUM(DK49:DK53) -> 52916 | DL54: =SUM(DL49:DL53) -> 54657 | DM54: =SUM(DM49:DM53) -> 57118
B55: Customer financing assets | CH55: 3281 | CJ55: 3463 | CK55: =CJ55 -> 3463 | CM55: 3363 | CN55: 3314 | CO55: 3144 | CP55: =CO55 -> 3144 | CQ55: 3079 | CR55: 3063 | CS55: 2960 | CT55: 2848 | CU55: =CT55 -> 2848 | CV55: 2766 | CW55: 2675 | CX55: 2618 | CY55: 2603 | CZ55: =CY55 -> 2603 | DA55: 2543 | DB55: 2457 | DC55: 2452 | DD55: 2392 | DE55: =DD55 -> 2392 | DF55: 2359 | DG55: 2320 | DH55: 2306 | DI55: 2246 | DJ55: =DI55 -> 2246 | DK55: 2135 | DL55: 2104 | DM55: 2071
B56: Future income tax benefits | CH56: 930 | CJ56: 0 | CK56: =CJ56 -> 0 | CM56: 732 | CN56: 699 | CP56: =CO56 -> 0 | CU56: =CT56 -> 0 | CZ56: =CY56 -> 0 | DE56: =DD56 -> 0 | DF56: 0 | DJ56: =DI56 -> 0
B57: Fixed assets, net | CH57: 14596 | CJ57: 10322 | CK57: =CJ57 -> 10322 | CM57: 14805 | CN57: 14730 | CO57: 14962 | CP57: =CO57 -> 14962 | CQ57: 14742 | CR57: 14665 | CS57: 14517 | CT57: 14972 | CU57: =CT57 -> 14972 | CV57: 14837 | CW57: 14741 | CX57: 14668 | CY57: 15170 | CZ57: =CY57 -> 15170 | DA57: 15149 | DB57: 15295 | DC57: 15347 | DD57: 15748 | DE57: =DD57 -> 15748 | DF57: 15638 | DG57: 15693 | DH57: 15886 | DI57: 16089 | DJ57: =DI57 -> 16089 | DK57: 16135 | DL57: 16205 | DM57: 16325
B58: Operating lease right-of-use asset | CH58: 2150 | CJ58: 1252 | CK58: =CJ58 -> 1252 | CM58: 2102 | CN58: 2027 | CO58: 1880 | CP58: =CO58 -> 1880 | CQ58: 1913 | CR58: 1900 | CS58: 1876 | CT58: 1958 | CU58: =CT58 -> 1958 | CV58: 1911 | CW58: 1866 | CX58: 1802 | CY58: 1829 | CZ58: =CY58 -> 1829 | DA58: 1844 | DB58: 1812 | DC58: 1755 | DD58: 1638 | DE58: =DD58 -> 1638 | DF58: 1639 | DG58: 1664 | DH58: 1846 | DI58: 1864 | DJ58: =DI58 -> 1864 | DK58: 1899 | DL58: 1869 | DM58: 1899
B59: Goodwill | CH59: 76652 | CJ59: 36609 | CK59: =CJ59 -> 36609 | CM59: 53269 | CN59: 53524 | CO59: 54285 | CP59: =CO59 -> 54285 | CQ59: 54265 | CR59: 54394 | CS59: 53789 | CT59: 54436 | CU59: =CT59 -> 54436 | CV59: 54316 | CW59: 53806 | CX59: 53168 | CY59: 53840 | CZ59: =CY59 -> 53840 | DA59: 53904 | DB59: 54122 | DC59: 53883 | DD59: 53699 | DE59: =DD59 -> 53699 | DF59: 53644 | DG59: 53347 | DH59: 53759 | DI59: 52789 | DJ59: =DI59 -> 52789 | DK59: 53045 | DL59: 53327 | DM59: 53311
B60: Intangible assets, net | CH60: 44184 | CJ60: 24473 | CK60: =CJ60 -> 24473 | CM60: 42003 | CN60: 41564 | CO60: 40539 | CP60: =CO60 -> 40539 | CQ60: 39999 | CR60: 39523 | CS60: 38842 | CT60: 38516 | CU60: =CT60 -> 38516 | CV60: 38118 | CW60: 37562 | CX60: 37046 | CY60: 36823 | CZ60: =CY60 -> 36823 | DA60: 36477 | DB60: 36234 | DC60: 35865 | DD60: 35399 | DE60: =DD60 -> 35399 | DF60: 34960 | DG60: 34503 | DH60: 34159 | DI60: 33443 | DJ60: =DI60 -> 33443 | DK60: 33116 | DL60: 32748 | DM60: 32260
B61: Other assets | CH61: 6799 | CJ61: 1919 | CK61: =CJ61 -> 1919 | CM61: 2969 | CN61: 3030 | CO61: 3967 | CP61: =CO61 -> 3967 | CQ61: 4058 | CR61: 4414 | CS61: 4796 | CT61: 6624 | CU61: =CT61 -> 6624 | CV61: 6678 | CW61: 6905 | CX61: 7102 | CY61: 6156 | CZ61: =CY61 -> 6156 | DA61: 6215 | DB61: 6326 | DC61: 6623 | DD61: 4576 | DE61: =DD61 -> 4576 | DF61: 3924 | DG61: 4417 | DH61: 5102 | DI61: 5297 | DJ61: =DI61 -> 5297 | DK61: 5618 | DL61: 6229 | DM61: 5688
B62: Total Assets | CH62: =SUM(CH54:CH61) -> 184678 | CJ62: =SUM(CJ54:CJ61) -> 139615 | CK62: =CJ62 -> 139615 | CM62: =SUM(CM54:CM61) -> 161517 | CN62: =SUM(CN54:CN61) -> 162399 | CO62: =SUM(CO54:CO61) -> 162153 | CP62: =CO62 -> 162153 | CQ62: =SUM(CQ54:CQ61) -> 160608 | CR62: =SUM(CR54:CR61) -> 158838 | CS62: =SUM(CS54:CS61) -> 158772 | CT62: =SUM(CT54:CT61) -> 161404 | CU62: =CT62 -> 161404 | CV62: =SUM(CV54:CV61) -> 159366 | CW62: =SUM(CW54:CW61) -> 159017 | CX62: =SUM(CX54:CX61) -> 158225 | CY62: =SUM(CY54:CY61) -> 158864 | CZ62: =CY62 -> 158864 | DA62: =SUM(DA54:DA61) -> 161636 | DB62: =SUM(DB54:DB61) -> 162161 | DC62: =SUM(DC54:DC61) -> 162443 | DD62: =SUM(DD54:DD61) -> 161869 | DE62: =DD62 -> 161869 | DF62: =SUM(DF54:DF61) -> 160187 | DG62: =SUM(DG54:DG61) -> 161169 | DH62: =SUM(DH54:DH61) -> 164822 | DI62: =SUM(DI54:DI61) -> 162861 | DJ62: =DI62 -> 162861 | DK62: =SUM(DK54:DK61) -> 164864 | DL62: =SUM(DL54:DL61) -> 167139 | DM62: =SUM(DM54:DM61) -> 168672
B63: Liabilities and shareholder's equity
B64: Short-term borrowings | CH64: 1095 | CJ64: 2293 | CK64: =CJ64 -> 2293 | CM64: 243 | CN64: 228 | CO64: 247 | CP64: =CO64 -> 247 | CQ64: 234 | CR64: 196 | CS64: 206 | CT64: 134 | CU64: =CT64 -> 134 | CV64: 140 | CW64: 113 | CX64: 2195 | CY64: 625 | CZ64: =CY64 -> 625 | DA64: 224 | DB64: 1076 | DC64: 1170 | DD64: 189 | DE64: =DD64 -> 189 | DF64: 166 | DG64: 231 | DH64: 220 | DI64: 183 | DJ64: =DI64 -> 183 | DK64: 212 | DL64: 1635 | DM64: =215 -> 215
B65: Accounts payable | CH65: 9198 | CJ65: 7816 | CK65: =CJ65 -> 7816 | CM65: 7182 | CN65: 8143 | CO65: 8639 | CP65: =CO65 -> 8639 | CQ65: 9182 | CR65: 8043 | CS65: 8667 | CT65: 8751 | CU65: =CT65 -> 8751 | CV65: 8270 | CW65: 9732 | CX65: 9017 | CY65: 9896 | CZ65: =CY65 -> 9896 | DA65: 10060 | DB65: 10128 | DC65: 10315 | DD65: 10698 | DE65: =DD65 -> 10698 | DF65: 10522 | DG65: 10939 | DH65: 11834 | DI65: 12897 | DJ65: =DI65 -> 12897 | DK65: 13444 | DL65: 13433 | DM65: 14552
B66: Accrued employee compensation | CJ66: 1353 | CK66: =CJ66 -> 1353 | CO66: 3006 | CP66: =CO66 -> 3006 | CQ66: 2511 | CR66: 2233 | CS66: 2756 | CT66: 2658 | CU66: =CT66 -> 2658 | CV66: 1880 | CW66: 2028 | CX66: 2390 | CY66: 2401 | CZ66: =CY66 -> 2401 | DA66: 1856 | DB66: 2121 | DC66: 2597 | DD66: 2491 | DE66: =DD66 -> 2491 | DF66: 1862 | DG66: 2065 | DH66: 2673 | DI66: 2620 | DJ66: =DI66 -> 2620 | DK66: 1867 | DL66: 2133 | DM66: 2937
B67: Accrued liabilities | CH67: 12451 | CJ67: 8417 | CK67: =CJ67 -> 8417 | CM67: 14253 | CN67: 13558 | CO67: =10401 -> 10401 | CP67: =CO67 -> 10401 | CQ67: 10184 | CR67: 10361 | CS67: 9685 | CT67: 10162 | CU67: =CT67 -> 10162 | CV67: 11004 | CW67: 12459 | CX67: 11210 | CY67: 10999 | CZ67: =CY67 -> 10999 | DA67: 11573 | DB67: 11719 | DC67: 14283 | DD67: 14917 | DE67: =DD67 -> 14917 | DF67: 15006 | DG67: 17048 | DH67: 15971 | DI67: 14831 | DJ67: =DI67 -> 14831 | DK67: 15219 | DL67: 15861 | DM67: 14835
B68: Contract liabilities, current | CH68: 4774 | CJ68: 9014 | CK68: =CJ68 -> 9014 | CM68: 11997 | CN68: 12208 | CO68: 12889 | CP68: =CO68 -> 12889 | CQ68: 12879 | CR68: 12591 | CS68: 12543 | CT68: 13720 | CU68: =CT68 -> 13720 | CV68: 13739 | CW68: 13430 | CX68: 13368 | CY68: 14598 | CZ68: =CY68 -> 14598 | DA68: 14870 | DB68: 15162 | DC68: 15248 | DD68: 17183 | DE68: =DD68 -> 17183 | DF68: 17119 | DG68: 17665 | DH68: 18436 | DI68: 18616 | DJ68: =DI68 -> 18616 | DK68: 19038 | DL68: 19186 | DM68: =20111 -> 20111
B69: Disco ops, other | CJ69: 14443 | CK69: =CJ69 -> 14443 | CM69: 319 | CN69: 118 | CO69: 116 | CP69: =CO69 -> 116
B70: Long-term debt currently due | CH70: 7002 | CJ70: 3258 | CK70: =CJ70 -> 3258 | CM70: 1297 | CN70: 1307 | CO70: 550 | CP70: =CO70 -> 550 | CQ70: 1369 | CR70: 1370 | CS70: 274 | CT70: 24 | CU70: =CT70 -> 24 | CV70: 24 | CW70: 26 | CX70: 193 | CY70: 595 | CZ70: =CY70 -> 595 | DA70: 1545 | DB70: 1554 | DC70: 1389 | DD70: 1283 | DE70: =DD70 -> 1283 | DF70: 344 | DG70: 1617 | DH70: 3113 | DI70: 2352 | DJ70: =DI70 -> 2352 | DK70: 2844 | DL70: 2084 | DM70: 584
B71: Total current liabilities | CH71: =SUM(CH64:CH70) -> 34520 | CJ71: =SUM(CJ64:CJ70) -> 46594 | CK71: =CJ71 -> 46594 | CM71: =SUM(CM64:CM70) -> 35291 | CN71: =SUM(CN64:CN70) -> 35562 | CO71: =SUM(CO64:CO70) -> 35848 | CP71: =CO71 -> 35848 | CQ71: =SUM(CQ64:CQ70) -> 36359 | CR71: =SUM(CR64:CR70) -> 34794 | CS71: =SUM(CS64:CS70) -> 34131 | CT71: =SUM(CT64:CT70) -> 35449 | CU71: =CT71 -> 35449 | CV71: =SUM(CV64:CV70) -> 35057 | CW71: =SUM(CW64:CW70) -> 37788 | CX71: =SUM(CX64:CX70) -> 38373 | CY71: =SUM(CY64:CY70) -> 39114 | CZ71: =CY71 -> 39114 | DA71: =SUM(DA64:DA70) -> 40128 | DB71: =SUM(DB64:DB70) -> 41760 | DC71: =SUM(DC64:DC70) -> 45002 | DD71: =SUM(DD64:DD70) -> 46761 | DE71: =DD71 -> 46761 | DF71: =SUM(DF64:DF70) -> 45019 | DG71: =SUM(DG64:DG70) -> 49565 | DH71: =SUM(DH64:DH70) -> 52247 | DI71: =SUM(DI64:DI70) -> 51499 | DJ71: =DI71 -> 51499 | DK71: =SUM(DK64:DK70) -> 52624 | DL71: =SUM(DL64:DL70) -> 54332 | DM71: =SUM(DM64:DM70) -> 53234
B72: Long-term debt | CH72: 25714 | CJ72: 37701 | CK72: =CJ72 -> 37701 | CM72: 31210 | CN72: 31246 | CO72: 31026 | CP72: =CO72 -> 31026 | CQ72: 29935 | CR72: 29916 | CS72: 30768 | CT72: 31327 | CU72: =CT72 -> 31327 | CV72: 31308 | CW72: 31274 | CX72: 31059 | CY72: 30694 | CZ72: =CY72 -> 30694 | DA72: 32717 | DB72: 32723 | DC72: 32701 | DD72: 42355 | DE72: =DD72 -> 42355 | DF72: 42334 | DG72: 40303 | DH72: 38823 | DI72: 38726 | DJ72: =DI72 -> 38726 | DK72: 38244 | DL72: 38259 | DM72: 38260
B73: Future pension and postretirement benefit obligations | CH73: 9765 | CJ73: 2487 | CK73: =CJ73 -> 2487 | CM73: 14972 | CN73: 14688 | CO73: 10342 | CP73: =CO73 -> 10342 | CQ73: 9808 | CR73: 9929 | CS73: 9742 | CT73: 7855 | CU73: =CT73 -> 7855 | CV73: 7709 | CW73: 7543 | CX73: 7362 | CY73: 4807 | CZ73: =CY73 -> 4807 | DA73: 4676 | DB73: 4579 | DC73: 4457 | DD73: 2385 | DE73: =DD73 -> 2385 | DF73: 1410 | DG73: 2264 | DH73: 2230 | DI73: 2104 | DJ73: =DI73 -> 2104 | DK73: 1646 | DL73: 2038 | DM73: 1981
B74: Operating lease liabilities | CH74: 1826 | CJ74: 1093 | CK74: =CJ74 -> 1093 | CM74: 1723 | CN74: 1651 | CO74: 1516 | CP74: =CO74 -> 1516 | CQ74: 1552 | CR74: 1563 | CS74: 1541 | CT74: 1657 | CU74: =CT74 -> 1657 | CV74: 1627 | CW74: 1593 | CX74: 1539 | CY74: 1586 | CZ74: =CY74 -> 1586 | DA74: 1624 | DB74: 1570 | DC74: 1523 | DD74: 1412 | DE74: =DD74 -> 1412 | DF74: 2320 | DG74: 1415 | DH74: 1592 | DI74: 1632 | DJ74: =DI74 -> 1632 | DK74: 2060 | DL74: 1617 | DM74: 1650
B75: Other long-term liabilities | CH75: 20627 | CJ75: 7414 | CK75: =CJ75 -> 7414 | CM75: 9394 | CN75: 9142 | CO75: 9537 | CP75: =CO75 -> 9537 | CQ75: 9612 | CR75: 9885 | CS75: 9621 | CT75: 10417 | CU75: =CT75 -> 10417 | CV75: 9643 | CW75: 8791 | CX75: 8124 | CY75: 8449 | CZ75: =CY75 -> 8449 | DA75: 8106 | DB75: 7442 | DC75: 7514 | DD75: 7511 | DE75: =DD75 -> 7511 | DF75: 6967 | DG75: 6941 | DH75: 7071 | DI75: 6942 | DJ75: =DI75 -> 6942 | DK75: 6946 | DL75: 6646 | DM75: 7154
B76: Total liabilities | CH76: =SUM(CH71:CH75) -> 92452 | CJ76: =SUM(CJ71:CJ75) -> 95289 | CK76: =CJ76 -> 95289 | CM76: =SUM(CM71:CM75) -> 92590 | CN76: =SUM(CN71:CN75) -> 92289 | CO76: =SUM(CO71:CO75) -> 88269 | CP76: =CO76 -> 88269 | CQ76: =SUM(CQ71:CQ75) -> 87266 | CR76: =SUM(CR71:CR75) -> 86087 | CS76: =SUM(CS71:CS75) -> 85803 | CT76: =SUM(CT71:CT75) -> 86705 | CU76: =CT76 -> 86705 | CV76: =SUM(CV71:CV75) -> 85344 | CW76: =SUM(CW71:CW75) -> 86989 | CX76: =SUM(CX71:CX75) -> 86457 | CY76: =SUM(CY71:CY75) -> 84650 | CZ76: =CY76 -> 84650 | DA76: =SUM(DA71:DA75) -> 87251 | DB76: =SUM(DB71:DB75) -> 88074 | DC76: =SUM(DC71:DC75) -> 91197 | DD76: =SUM(DD71:DD75) -> 100424 | DE76: =DD76 -> 100424 | DF76: =SUM(DF71:DF75) -> 98050 | DG76: =SUM(DG71:DG75) -> 100488 | DH76: =SUM(DH71:DH75) -> 101963 | DI76: =SUM(DI71:DI75) -> 100903 | DJ76: =DI76 -> 100903 | DK76: =SUM(DK71:DK75) -> 101520 | DL76: =SUM(DL71:DL75) -> 102892 | DM76: =SUM(DM71:DM75) -> 102279
B77: Redeemable noncontrolling interest, other | CH77: 435 | CJ77: 95 | CK77: =CJ77 -> 95 | CM77: 35 | CN77: 30 | CO77: 32 | CP77: =CO77 -> 32 | CQ77: 34 | CR77: 30 | CS77: 32 | CT77: 35 | CU77: =CT77 -> 35 | CV77: 36 | CW77: 38 | CX77: 33 | CY77: 36 | CZ77: =CY77 -> 36 | DA77: 38 | DB77: 31 | DC77: 33 | DD77: 35 | DE77: =DD77 -> 35 | DF77: 37 | DG77: 31 | DH77: 33 | DI77: 35 | DJ77: =DI77 -> 35 | DK77: 37 | DL77: 41 | DM77: 34
B78: Common Stock | CH78: 75501 | CJ78: 22955 | CK78: =CJ78 -> 22955 | CM78: 36679 | CN78: 36781 | CO78: 36881 | CP78: =CO78 -> 36881 | CQ78: 36951 | CR78: 37140 | CS78: 37302 | CT78: 37445 | CU78: =CT78 -> 37445 | CV78: 37468 | CW78: 37640 | CX78: 37798 | CY78: 37911 | CZ78: =CY78 -> 37911 | DA78: 38005 | DB78: 38206 | DC78: 38369 | DD78: 37040 | DE78: =DD78 -> 37040 | DF78: 37097 | DG78: 37295 | DH78: 37276 | DI78: 37434 | DJ78: =DI78 -> 37434 | DK78: 37515 | DL78: 37680 | DM78: 37869
B79: Treasury Stock | CH79: -32549 | CJ79: -32626 | CK79: =CJ79 -> -32626 | CM79: -10398 | CN79: -10407 | CO79: -10407 | CP79: =CO79 -> -10407 | CQ79: -10780 | CR79: -11424 | CS79: -12398 | CT79: -12727 | CU79: =CT79 -> -12727 | CV79: -13483 | CW79: -14539 | CX79: -15141 | CY79: -15530 | CZ79: =CY79 -> -15530 | DA79: -16112 | DB79: -16713 | DC79: -18170 | DD79: -26977 | DE79: =DD79 -> -26977 | DF79: -27029 | DG79: -27080 | DH79: -27141 | DI79: -27112 | DJ79: =DI79 -> -27112 | DK79: -27069 | DL79: -26995 | DM79: -26937
B80: Retained earnings | CH80: 54191 | CJ80: 61594 | CK80: =CJ80 -> 61594 | CM80: 49744 | CN80: 50017 | CO80: 49423 | CP80: =CO80 -> 49423 | CQ80: 49460 | CR80: 48954 | CS80: 50343 | CT80: 50265 | CU80: =CT80 -> 50265 | CV80: 50592 | CW80: 50271 | CX80: 51652 | CY80: 52269 | CZ80: =CY80 -> 52269 | DA80: 52891 | DB80: 52489 | DC80: 51513 | DD80: 52154 | DE80: =DD80 -> 52154 | DF80: 53052 | DG80: 51488 | DH80: 52948 | DI80: 53589 | DJ80: =DI80 -> 53589 | DK80: 54277 | DL80: 54104 | DM80: 56014
B81: Unearned ESOP shares | CH81: -71 | CJ81: 0 | CK81: =CJ81 -> 0 | CP81: =CO81 -> 0 | CU81: =CT81 -> 0 | CZ81: =CY81 -> 0 | DE81: =DD81 -> 0 | DJ81: =DI81 -> 0
B82: Accumulated other comprehensive loss | CH82: -6630 | CJ82: -10149 | CK82: =CJ82 -> -10149 | CM82: -8800 | CN82: -8012 | CO82: -3734 | CP82: =CO82 -> -3734 | CQ82: -3921 | CR82: -3555 | CS82: -3939 | CT82: -1915 | CU82: =CT82 -> -1915 | CV82: -2115 | CW82: -2931 | CX82: -4122 | CY82: -2018 | CZ82: =CY82 -> -2018 | DA82: -1989 | DB82: -1502 | DC82: -2116 | DD82: -2419 | DE82: =DD82 -> -2419 | DF82: -2635 | DG82: -2718 | DH82: -1969 | DI82: -3755 | DJ82: =DI82 -> -3755 | DK82: -3207 | DL82: -2391 | DM82: -2432
B83: Total shareholders' equity | CH83: =SUM(CH78:CH82) -> 90442 | CJ83: =SUM(CJ78:CJ82) -> 41774 | CK83: =CJ83 -> 41774 | CM83: =SUM(CM78:CM82) -> 67225 | CN83: =SUM(CN78:CN82) -> 68379 | CO83: =SUM(CO78:CO82) -> 72163 | CP83: =CO83 -> 72163 | CQ83: =SUM(CQ78:CQ82) -> 71710 | CR83: =SUM(CR78:CR82) -> 71115 | CS83: =SUM(CS78:CS82) -> 71308 | CT83: =SUM(CT78:CT82) -> 73068 | CU83: =CT83 -> 73068 | CV83: =SUM(CV78:CV82) -> 72462 | CW83: =SUM(CW78:CW82) -> 70441 | CX83: =SUM(CX78:CX82) -> 70187 | CY83: =SUM(CY78:CY82) -> 72632 | CZ83: =CY83 -> 72632 | DA83: =SUM(DA78:DA82) -> 72795 | DB83: =SUM(DB78:DB82) -> 72480 | DC83: =SUM(DC78:DC82) -> 69596 | DD83: =SUM(DD78:DD82) -> 59798 | DE83: =DD83 -> 59798 | DF83: =SUM(DF78:DF82) -> 60485 | DG83: =SUM(DG78:DG82) -> 58985 | DH83: =SUM(DH78:DH82) -> 61114 | DI83: =SUM(DI78:DI82) -> 60156 | DJ83: =DI83 -> 60156 | DK83: =SUM(DK78:DK82) -> 61516 | DL83: =SUM(DL78:DL82) -> 62398 | DM83: =SUM(DM78:DM82) -> 64514
B84: Noncontrolling interest | CH84: 1349 | CJ84: 2457 | CK84: =CJ84 -> 2457 | CM84: 1667 | CN84: 1701 | CO84: 1689 | CP84: =CO84 -> 1689 | CQ84: 1598 | CR84: 1606 | CS84: 1629 | CT84: 1596 | CU84: =CT84 -> 1596 | CV84: 1524 | CW84: 1549 | CX84: 1548 | CY84: 1546 | CZ84: =CY84 -> 1546 | DA84: 1552 | DB84: 1576 | DC84: 1617 | DD84: 1612 | DE84: =DD84 -> 1612 | DF84: 1615 | DG84: 1665 | DH84: 1712 | DI84: 1767 | DJ84: =DI84 -> 1767 | DK84: 1791 | DL84: 1808 | DM84: 1845
B85: Total liabilities and shareholders equity | CH85: =+CH83+CH76+CH84+CH77 -> 184678 | CJ85: =+CJ83+CJ76+CJ84+CJ77 -> 139615 | CK85: =CJ85 -> 139615 | CM85: =+CM83+CM76+CM84+CM77 -> 161517 | CN85: =+CN83+CN76+CN84+CN77 -> 162399 | CO85: =+CO83+CO76+CO84+CO77 -> 162153 | CP85: =CO85 -> 162153 | CQ85: =+CQ83+CQ76+CQ84+CQ77 -> 160608 | CR85: =+CR83+CR76+CR84+CR77 -> 158838 | CS85: =+CS83+CS76+CS84+CS77 -> 158772 | CT85: =+CT83+CT76+CT84+CT77 -> 161404 | CU85: =CT85 -> 161404 | CV85: =+CV83+CV76+CV84+CV77 -> 159366 | CW85: =+CW83+CW76+CW84+CW77 -> 159017 | CX85: =+CX83+CX76+CX84+CX77 -> 158225 | CY85: =+CY83+CY76+CY84+CY77 -> 158864 | CZ85: =CY85 -> 158864 | DA85: =+DA83+DA76+DA84+DA77 -> 161636 | DB85: =+DB83+DB76+DB84+DB77 -> 162161 | DC85: =+DC83+DC76+DC84+DC77 -> 162443 | DD85: =+DD83+DD76+DD84+DD77 -> 161869 | DE85: =DD85 -> 161869 | DF85: =+DF83+DF76+DF84+DF77 -> 160187 | DG85: =+DG83+DG76+DG84+DG77 -> 161169 | DH85: =+DH83+DH76+DH84+DH77 -> 164822 | DI85: =+DI83+DI76+DI84+DI77 -> 162861 | DJ85: =DI85 -> 162861 | DK85: =+DK83+DK76+DK84+DK77 -> 164864 | DL85: =+DL83+DL76+DL84+DL77 -> 167139 | DM85: =+DM83+DM76+DM84+DM77 -> 168672
B89: Cash Flow
B91: Operating activities | CM91: * | CQ91: Quarterly
B92: Net income from continuing operations | CK92: 3731 | CL92: =CP92-SUM(CM92:CO92) -> 492 | CM92: -3820 | CN92: 185 | CO92: 215 | CP92: -2928 | CQ92: 813 | CR92: 1088 | CS92: 1473 | CT92: 771 | CU92: =SUM(CQ92:CT92) -> 4145 | CV92: 1126 | CW92: 1338 | CX92: 1395 | CY92: 1468 | CZ92: =SUM(CV92:CY92) -> 5327 | DA92: 1481 | DB92: 1359 | DC92: -933 | DD92: 1473 | DE92: =SUM(DA92:DD92) -> 3380 | DF92: 1743 | DG92: 175 | DH92: 1535 | DI92: 1560 | DJ92: =SUM(DF92:DI92) -> 5013 | DK92: 1625 | DL92: 1725 | DM92: 2006
B93: Depreciation and amortization | CK93: 2708 | CL93: =CP93-SUM(CM93:CO93) -> 728 | CM93: 1111 | CN93: 1164 | CO93: 1153 | CP93: 4156 | CQ93: 1123 | CR93: 1132 | CS93: 1158 | CT93: 1144 | CU93: =SUM(CQ93:CT93) -> 4557 | CV93: 1014 | CW93: 999 | CX93: 1047 | CY93: 1048 | CZ93: =SUM(CV93:CY93) -> 4108 | DA93: 1034 | DB93: 1044 | DC93: 1074 | DD93: 1059 | DE93: =SUM(DA93:DD93) -> 4211 | DF93: 1059 | DG93: 1072 | DH93: 1094 | DI93: 1139 | DJ93: =SUM(DF93:DI93) -> 4364 | DK93: 1052 | DL93: 1076 | DM93: 1091
B94: Deferred income taxes | CK94: 38 | CL94: =CP94-SUM(CM94:CO94) -> 392 | CM94: -274 | CN94: -152 | CO94: -65 | CP94: -99 | CQ94: 153 | CR94: 22 | CS94: -317 | CT94: 54 | CU94: =SUM(CQ94:CT94) -> -88 | CV94: -601 | CW94: -546 | CX94: -534 | CY94: 18 | CZ94: =SUM(CV94:CY94) -> -1663 | DA94: -329 | DB94: -371 | DC94: -28 | DD94: 326 | DE94: =SUM(DA94:DD94) -> -402 | DF94: -114 | DG94: 299 | DH94: -304 | DI94: 72 | DJ94: =SUM(DF94:DI94) -> -47 | DK94: 67 | DL94: 54 | DM94: 477
B95: Stock-based compensation expense | CK95: 268 | CL95: =CP95-SUM(CM95:CO95) -> 63 | CM95: 72 | CN95: 118 | CO95: 77 | CP95: 330 | CQ95: 84 | CR95: 143 | CS95: 116 | CT95: 99 | CU95: =SUM(CQ95:CT95) -> 442 | CV95: 103 | CW95: 109 | CX95: 106 | CY95: 102 | CZ95: =SUM(CV95:CY95) -> 420 | DA95: 100 | DB95: 112 | DC95: 107 | DD95: 106 | DE95: =SUM(DA95:DD95) -> 425 | DF95: 112 | DG95: 111 | DH95: 105 | DI95: 109 | DJ95: =SUM(DF95:DI95) -> 437 | DK95: 111 | DL95: 113 | DM95: 113
B96: Net periodic pension and other PRB | CK96: -566 | CL96: =CP96-SUM(CM96:CO96) -> -130 | CM96: -93 | CN96: -102 | CO96: -88 | CP96: -413 | CQ96: -358 | CR96: -357 | CS96: -358 | CT96: -341 | CU96: =SUM(CQ96:CT96) -> -1414 | CV96: -360 | CW96: -354 | CX96: -348 | CY96: -351 | CZ96: =SUM(CV96:CY96) -> -1413 | DA96: -388 | DB96: -390 | DC96: -386 | DD96: -391 | DE96: =SUM(DA96:DD96) -> -1555 | DF96: -338 | DG96: -328 | DH96: -326 | DI96: -334 | DJ96: =SUM(DF96:DI96) -> -1326 | DK96: -324 | DL96: -312 | DM96: -320
B97: Charges & other | CK97: 0 | CL97: =CP97-SUM(CM97:CO97) -> 0 | CM97: 3183 | CP97: 3183 | CT97: 617 | CU97: =SUM(CQ97:CT97) -> 617 | CZ97: =SUM(CV97:CY97) -> 0 | DE97: =SUM(DA97:DD97) -> 0 | DF97: -415 | DJ97: =SUM(DF97:DI97) -> -415 | DK97: 0 | DL97: 140 | DM97: 128
B98: Minority interest | CL98: =CP98-SUM(CM98:CO98) -> 0
B99: Changes in operating assets and liabilities: | CH99: =SUM(CH100:CH104) -> 0 | CL99: =CP99-SUM(CM99:CO99) -> 0
B100: Accounts receivable | CK100: 88 | CL100: =CP100-SUM(CM100:CO100) -> 390 | CM100: 773 | CN100: -596 | CO100: 751 | CP100: 1318 | CQ100: -799 | CR100: 1092 | CS100: -690 | CT100: -173 | CU100: =SUM(CQ100:CT100) -> -570 | CV100: 556 | CW100: -1346 | CX100: 1111 | CY100: 116 | CZ100: =SUM(CV100:CY100) -> 437 | DA100: -962 | DB100: 263 | DC100: -214 | DD100: -892 | DE100: =SUM(DA100:DD100) -> -1805 | DF100: 431 | DG100: 156 | DH100: 349 | DI100: -1111 | DJ100: =SUM(DF100:DI100) -> -175 | DK100: -372 | DL100: -765 | DM100: -351
B101: Contract assets, current | CK101: -679 | CL101: =CP101-SUM(CM101:CO101) -> -349 | CM101: 725 | CN101: 323 | CO101: -636 | CP101: 63 | CQ101: -311 | CR101: -246 | CS101: -560 | CT101: -477 | CU101: =SUM(CQ101:CT101) -> -1594 | CV101: -219 | CW101: -306 | CX101: -474 | CY101: 765 | CZ101: =SUM(CV101:CY101) -> -234 | DA101: -1198 | DB101: -232 | DC101: 267 | DD101: 410 | DE101: =SUM(DA101:DD101) -> -753 | DF101: -978 | DG101: -479 | DH101: -996 | DI101: 39 | DJ101: =SUM(DF101:DI101) -> -2414 | DK101: -706 | DL101: -484 | DM101: -934
B102: Inventories and contracts in progress | CK102: -1267 | CL102: =CP102-SUM(CM102:CO102) -> -395 | CM102: -155 | CN102: 439 | CO102: 523 | CP102: 412 | CQ102: -113 | CR102: -20 | CS102: 76 | CT102: 220 | CU102: =SUM(CQ102:CT102) -> 163 | CV102: -587 | CW102: -446 | CX102: -401 | CY102: -141 | CZ102: =SUM(CV102:CY102) -> -1575 | DA102: -720 | DB102: -602 | DC102: -108 | DD102: 326 | DE102: =SUM(DA102:DD102) -> -1104 | DF102: -646 | DG102: -715 | DH102: -344 | DI102: 231 | DJ102: =SUM(DF102:DI102) -> -1474 | DK102: -813 | DL102: -384 | DM102: 182
B103: Other current assets / liabilities | CK103: -984 | CL103: =CP103-SUM(CM103:CO103) -> -208 | CM103: 28 | CN103: -201 | CO103: -64 | CP103: -445 | CQ103: -193 | CR103: -65 | CS103: -17 | CT103: -291 | CU103: =SUM(CQ103:CT103) -> -566 | CV103: -281 | CW103: -72 | CX103: -231 | CY103: -443 | CZ103: =SUM(CV103:CY103) -> -1027 | DA103: -526 | DB103: -108 | DC103: -244 | DD103: -283 | DE103: =SUM(DA103:DD103) -> -1161 | DF103: -225 | DG103: 442 | DH103: -459 | DI103: -160 | DJ103: =SUM(DF103:DI103) -> -402 | DK103: -125 | DL103: 25 | DM103: -879
B104: Accounts payable, accrued liabilities | CK104: 1111 | CL104: =CP104-SUM(CM104:CO104) -> 612 | CM104: -2007 | CN104: 529 | CO104: -800 | CP104: -1666 | CQ104: 538 | CR104: -1271 | CS104: 1158 | CT104: 492 | CU104: =SUM(CQ104:CT104) -> 917 | CV104: -316 | CW104: 2425 | CX104: -811 | CY104: 777 | CZ104: =SUM(CV104:CY104) -> 2075 | DA104: 490 | DB104: -639 | DC104: 3571 | DD104: 594 | DE104: =SUM(DA104:DD104) -> 4016 | DF104: -218 | DG104: 1463 | DH104: 1082 | DI104: -819 | DJ104: =SUM(DF104:DI104) -> 1508 | DK104: 397 | DL104: -538 | DM104: 2237
B105: Contract liabilities | CK105: 1234 | CL105: =CP105-SUM(CM105:CO105) -> -101 | CM105: 302 | CN105: 153 | CO105: 775 | CP105: 1129 | CQ105: -56 | CR105: 11 | CS105: 128 | CT105: 1289 | CU105: =SUM(CQ105:CT105) -> 1372 | CV105: -50 | CW105: -259 | CX105: 25 | CY105: 1130 | CZ105: =SUM(CV105:CY105) -> 846 | DA105: 223 | DB105: 32 | DC105: 174 | DD105: 1893 | DE105: =SUM(DA105:DD105) -> 2322 | DF105: -54 | DG105: 566 | DH105: 684 | DI105: 676 | DJ105: =SUM(DF105:DI105) -> 1872 | DK105: 373 | DL105: -30 | DM105: 986
B106: Global pension contributions | CK106: -55 | CL106: =CP106-SUM(CM106:CO106) -> -8 | CM106: -34 | CN106: -22 | CO106: -961 | CP106: -1025 | CQ106: -7 | CR106: -18 | CS106: -13 | CT106: -21 | CU106: =SUM(CQ106:CT106) -> -59 | CZ106: =SUM(CV106:CY106) -> 0 | DE106: =SUM(DA106:DD106) -> 0 | DJ106: =SUM(DF106:DI106) -> 0
B107: Other operating activities, net | CK107: =-38+232 -> 194 | CL107: =CP107-SUM(CM107:CO107) -> -354 | CM107: 399 | CN107: -216 | CO107: 490 | CP107: 319 | CQ107: -151 | CR107: -185 | CS107: -222 | CT107: -222 | CU107: =SUM(CQ107:CT107) -> -780 | CV107: 91 | CW107: -256 | CX107: -107 | CY107: =-28+167 -> 139 | CZ107: =SUM(CV107:CY107) -> -133 | DA107: -68 | DB107: 251 | DC107: 36 | DD107: 90 | DE107: =SUM(DA107:DD107) -> 309 | DF107: -15 | DG107: -29 | DH107: 103 | DI107: 159 | DJ107: =SUM(DF107:DI107) -> 218 | DK107: =167-147 -> 20 | DL107: -162 | DM107: -97
B108: Cash from Operations | CH108: =SUM(CH93:CH99)+CH106+CH107 -> 0 | CK108: =SUM(CK92:CK107) -> 5821 | CL108: =SUM(CL92:CL107) -> 1132 | CM108: =SUM(CM92:CM107) -> 210 | CN108: =SUM(CN92:CN107) -> 1622 | CO108: =SUM(CO92:CO107) -> 1370 | CP108: =SUM(CP92:CP107) -> 4334 | CQ108: =SUM(CQ92:CQ107) -> 723 | CR108: =SUM(CR92:CR107) -> 1326 | ... CT108: =SUM(CT92:CT107) -> 3161 | CU108: =SUM(CQ108:CT108) -> 7142 | CV108: =SUM(CV92:CV107) -> 476 | CW108: =SUM(CW92:CW107) -> 1286 | CX108: =SUM(CX92:CX107) -> 778 | CY108: =SUM(CY92:CY107) -> 4628 | CZ108: =SUM(CV108:CY108) -> 7168 | DA108: =SUM(DA92:DA107) -> -863 | DB108: =SUM(DB92:DB107) -> 719 | DC108: =SUM(DC92:DC107) -> 3316 | DD108: =SUM(DD92:DD107) -> 4711 | DE108: =SUM(DA108:DD108) -> 7883 | DF108: =SUM(DF92:DF107) -> 342 | DG108: =SUM(DG92:DG107) -> 2733 | DH108: =SUM(DH92:DH107) -> 2523 | DI108: =SUM(DI92:DI107) -> 1561 | DJ108: =SUM(DF108:DI108) -> 7159 | DK108: =SUM(DK92:DK107) -> 1305 | DL108: =SUM(DL92:DL107) -> 458 | DM108: =SUM(DM92:DM107) -> 4639
B109: Capital expenditures | CK109: -1868 | CL109: =CP109-SUM(CM109:CO109) -> -325 | CM109: -458 | CN109: -389 | CO109: -623 | CP109: -1795 | CQ109: -387 | CR109: -360 | CS109: -433 | CT109: -954 | CU109: =SUM(CQ109:CT109) -> -2134 | CV109: -439 | CW109: -479 | CX109: -515 | CY109: -855 | CZ109: =SUM(CV109:CY109) -> -2288 | DA109: -520 | DB109: -526 | DC109: -564 | DD109: -805 | DE109: =SUM(DA109:DD109) -> -2415 | DF109: -467 | DG109: -537 | DH109: -552 | DI109: -1069 | DJ109: =SUM(DF109:DI109) -> -2625 | DK109: -513 | DL109: -530 | DM109: -614
B110: Investments in businesses, net | CK110: =-9+134 -> 125 | CL110: =CP110-SUM(CM110:CO110) -> -2575 | CM110: 234 | CN110: 2341 | CO110: -419 | CP110: -419 | CQ110: -6 | CR110: 25 | CS110: 0 | CT110: =-1082+805 -> -277 | CU110: =SUM(CQ110:CT110) -> -258 | CV110: 0 | CW110: 0 | CX110: =-66+6 -> -60 | CZ110: =SUM(CV110:CY110) -> -60 | DA110: 0 | DC110: 6 | DD110: 0 | DE110: =SUM(DA110:DD110) -> 6 | DF110: 1283 | DH110: 0 | DI110: 512 | DJ110: =SUM(DF110:DI110) -> 1795 | DK110: 0 | DM110: 1188
B111: Change in customer financing assets, net | CK111: -659 | CL111: =CP111-SUM(CM111:CO111) -> -88 | CM111: -41 | CN111: -9 | CO111: 226 | CP111: 88 | CQ111: -81 | CR111: -21 | CS111: 126 | CT111: 134 | CU111: =SUM(CQ111:CT111) -> 158 | CV111: -19 | CW111: 12 | CX111: 32 | CY111: 53 | CZ111: =SUM(CV111:CY111) -> 78 | DA111: 28 | DB111: 14 | DC111: -1 | DD111: 88 | DE111: =SUM(DA111:DD111) -> 129 | DF111: 0 | DG111: 0 | DH111: 0 | DI111: 0 | DJ111: =SUM(DF111:DI111) -> 0 | DK111: 0 | DL111: 0 | DM111: 0
B112: Change in collaboration intangible assets | CK112: -351 | CL112: =CP112-SUM(CM112:CO112) -> -78 | CM112: -28 | CN112: -30 | CO112: -36 | CP112: -172 | CQ112: -32 | CR112: -28 | CS112: -78 | CT112: -50 | CU112: =SUM(CQ112:CT112) -> -188 | CV112: -50 | CW112: -41 | CX112: -78 | CY112: -49 | CZ112: =SUM(CV112:CY112) -> -218 | DA112: -154 | DB112: -160 | DC112: -222 | DD112: -34 | DE112: =SUM(DA112:DD112) -> -570 | DF112: -163 | DG112: -155 | DH112: -129 | DI112: -164 | DJ112: =SUM(DF112:DI112) -> -611 | DK112: -104 | DL112: -122 | DM112: -121
B113: Receipts (payments) from settlements of derivs contracts | CK113: 342 | CL113: =CP113-SUM(CM113:CO113) -> -524 | CM113: 238 | CN113: 171 | CO113: 83 | CP113: -32 | CQ113: 49 | CR113: 1 | CS113: -8 | CT113: -58 | CU113: =SUM(CQ113:CT113) -> -16 | CV113: -33 | CW113: -118 | CX113: -108 | CY113: -169 | CZ113: =SUM(CV113:CY113) -> -428 | DA113: -13 | DB113: 58 | DC113: -63 | DD113: -215 | DE113: =SUM(DA113:DD113) -> -233 | DF113: -1 | DG113: -28 | DH113: 32 | DI113: -145 | DJ113: =SUM(DF113:DI113) -> -142 | DK113: -47 | DL113: 192 | DM113: 42
B114: Other investing activities, net | CK114: -265 | CL114: =CP114-SUM(CM114:CO114) -> 2550 | CM114: =3208-57 -> 3151 | CN114: 12 | CO114: =-19-21 -> -40 | CP114: =3208+2556-91 -> 5673 | CQ114: =-10+1049 -> 1039 | CR114: 40 | CS114: 15 | CT114: -20 | CU114: =SUM(CQ114:CT114) -> 1074 | CV114: =35-12 -> 23 | CW114: =53-45 -> 8 | CX114: -26 | CY114: =54+28 -> 82 | CZ114: =SUM(CV114:CY114) -> 87 | DA114: 80 | DB114: -9 | DC114: -15 | DD114: =32-44 -> -12 | DE114: =SUM(DA114:DD114) -> 44 | DF114: 41 | DG114: -13 | DH114: -66 | DI114: 87 | DJ114: =SUM(DF114:DI114) -> 49 | DK114: -14 | DL114: -49 | DM114: -24
...

Sheet SEG
B3: RTX Segment Data | C3: 1997 | D3: 1998 | E3: 1999 | F3: 2000 | G3: 2001 | H3: 2002 | I3: 2003 | J3: 1Q04 | K3: 2Q04 | L3: 3Q04 | M3: 4Q04 | N3: 2004 | O3: 1Q05 | P3: 2Q05 | Q3: 3Q05 | R3: 4Q05 | S3: 2005 | T3: 1Q06 | U3: 2Q06 | V3: 3Q06 | W3: 4Q06 | X3: 2006 | Y3: 1Q07 | Z3: 2Q07 | AA3: 3Q07 | AB3: 4Q07 | AC3: 2007 | AD3: 1Q08 | AE3: 2Q08 | AF3: 3Q08 | AG3: 4Q08 | AH3: 2008 | AI3: 1Q09 | AJ3: 2Q09 | AK3: 3Q09 | AL3: 4Q09 | AM3: 2009 | AN3: 1Q10 | AO3: 2Q10 | AP3: 3Q10 | AQ3: 4Q10 | AR3: 2010 | AS3: 1Q11 | AT3: 2Q11 | AU3: 3Q11 | AV3: 4Q11 | AW3: 2011 | AX3: 1Q12 | AY3: 2Q12 | AZ3: 3Q12 | BA3: 4Q12 | BB3: 2012 | BC3: 1Q13 | BD3: 2Q13 | BE3: 3Q13 | BF3: 4Q13 | BG3: 2013 | BH3: 1Q14 | BI3: 2Q14 | BJ3: 3Q14 | BK3: 4Q14 | BL3: 2014 | BM3: 1Q15 | BN3: 2Q15 | BO3: 3Q15 | BP3: 4Q15 | BQ3: 2015 | BR3: 1Q16 | BS3: 2Q16 | BT3: 3Q16 | BU3: 4Q16 | BV3: 2016 | BW3: 1Q17 | BX3: 2Q17 | BY3: 3Q17 | BZ3: 4Q17 | CA3: 2017 | CB3: 1Q18 | CC3: 2Q18 | CD3: 3Q18 | CE3: 4Q18 | CF3: 2018 | CG3: 1Q19 | CH3: 2Q19 | CI3: 3Q19 | CJ3: 4Q19 | CK3: 2019 | CL3: 1Q20 | CM3: 2Q20 | CN3: 3Q20 | CO3: 4Q20 | CP3: 2020 | CQ3: 1Q21 | CR3: 2Q21 | CS3: 3Q21 | CT3: 4Q21 | CU3: 2021 | CV3: 1Q22 | CW3: 2Q22 | CX3: 3Q22 | CY3: 4Q22 | CZ3: 2022 | DA3: 1Q23 | DB3: 2Q23 | DC3: 3Q23 | DD3: 4Q23 | DE3: 2023 | DF3: 1Q24 | DG3: 2Q24 | DH3: 3Q24 | DI3: 4Q24 | DJ3: 2024 | DK3: 1Q25 | DL3: 2Q25 | DM3: 3Q25 | DN3: 4Q25E | DO3: 2025E | DP3: 1Q26E | DQ3: 2Q26E | DR3: 3Q26E | DS3: 4Q26E | DT3: 2026E | DU3: 2027E | DV3: 2028E
B4: ($ mn) | C4: 35795 | D4: 36160 | E4: 36525 | F4: 36891 | G4: 37256 | H4: 37621 | I4: 37986 | J4: 38076 | K4: 38168 | L4: 38260 | M4: 38352 | N4: 38352 | O4: 38441 | P4: 38533 | Q4: 38625 | R4: 38717 | S4: 38717 | T4: 38806 | U4: 38898 | V4: 38990 | W4: 39082 | X4: 39082 | Y4: 39171 | Z4: 39263 | AA4: 39355 | AB4: 39447 | AC4: 39447 | AD4: 39537 | AE4: 39629 | AF4: 39721 | AG4: 39813 | AH4: 39813 | AI4: 39902 | AJ4: 39994 | AK4: 40086 | AL4: 40178 | AM4: 40178 | AN4: 40267 | AO4: 40359 | AP4: 40451 | AQ4: 40543 | AR4: 40543 | AS4: 40632 | AT4: 40724 | AU4: 40816 | AV4: 40908 | AW4: 40908 | AX4: 40998 | AY4: 41090 | AZ4: 41182 | BA4: 41274 | BB4: 41274 | BC4: 41363 | BD4: 41455 | BE4: 41547 | BF4: 41639 | BG4: 41639 | BH4: 41728 | BI4: 41820 | BJ4: 41912 | BK4: 42004 | BL4: 42004 | BM4: 42093 | BN4: 42185 | BO4: 42277 | BP4: 42369 | BQ4: 42369 | BR4: 42459 | BS4: 42551 | BT4: 42643 | BU4: 42735 | BV4: 42735 | BW4: 42824 | BX4: 42916 | BY4: 43008 | BZ4: 43100 | CA4: 43100 | CB4: 43189 | CC4: 43281 | CD4: 43373 | CE4: 43465 | CF4: 43465 | CG4: 43554 | CH4: 43646 | CI4: 43738 | CJ4: 43830 | CK4: 43830 | CL4: 43920 | CM4: 44012 | CN4: 44104 | CO4: 44196 | CP4: 44196 | CQ4: 44285 | CR4: 44377 | CS4: 44469 | CT4: 44561 | CU4: 44561 | CV4: 44650 | CW4: 44742 | CX4: 44834 | CY4: 44926 | CZ4: 44926 | DA4: 45015 | DB4: 45107 | DC4: 45199 | DD4: 45291 | DE4: 45291 | DF4: 45381 | DG4: 45473 | DH4: 45565 | DI4: 45657 | DJ4: 45657 | DK4: 45746 | DL4: 45838 | DM4: 45930 | DN4: 46022 | DO4: 46022 | DP4: 46111 | DQ4: 46203 | DR4: 46295 | DS4: 46387 | DT4: 46387 | DU4: 46752 | DV4: 47118
B6: Revenue
B8: Acquisitions
B9: Various | AZ9: 550 | BA9: 550 | BB9: =SUM(AZ9:BA9) -> 1100 | BC9: 550 | BD9: 375 | BG9: =SUM(BC9:BF9) -> 925
B11: Divestures | BH11: -68 | BI11: 0 | BJ11: 0 | BL11: =SUM(BH11:BK11) -> -68
B12: Misc incl FX | CV12: -15 | CW12: -25 | CZ12: =SUM(CV12:CY12) -> -40 | DC12: -5401 | DE12: =SUM(DA12:DD12) -> -5401 | DJ12: =SUM(DF12:DI12) -> 0 | DO12: =SUM(DK12:DN12) -> 0
B14: Pratt & Whitney | C14: =+Data!C133 -> 7402 | D14: =+Data!D133 -> 7876 | E14: =+Data!E133 -> 7674 | F14: =+Data!F133 -> 7366 | G14: =+Data!G133 -> 7679 | H14: =+Data!H133 -> 7645 | I14: =+Data!I133 -> 7484 | J14: =+Data!J133 -> 1939 | ... CK14: =+Data!CK133 -> 20902 | CL14: =Data!CL133 -> 5353 | CM14: =Data!CM133 -> 3487 | CN14: =Data!CN133 -> 3494 | CO14: =Data!CO133 -> 4890 | CP14: =SUM(CL14:CO14) -> 17224 | CQ14: =Data!CQ133 -> 4030 | CR14: =Data!CR133 -> 4280 | CS14: =Data!CS133 -> 4725 | CT14: =Data!CT133 -> 5115 | CU14: =SUM(CQ14:CT14) -> 18150 | CV14: =Data!CV133 -> 4529 | CW14: =Data!CW133 -> 4969 | CX14: =Data!CX133 -> 5380 | CY14: =Data!CY133 -> 5652 | CZ14: =SUM(CV14:CY14) -> 20530 | DA14: =Data!DA133 -> 5230 | DB14: =Data!DB133 -> 5701 | DC14: =Data!DC133 -> 926 | DD14: =Data!DD133 -> 6439 | DE14: =SUM(DA14:DD14) -> 18296 | DF14: =Data!DF133 -> 6456 | DG14: =Data!DG133 -> 6802 | DH14: =Data!DH133 -> 7239 | DI14: =Data!DI133 -> 7569 | DJ14: =SUM(DF14:DI14) -> 28066 | DK14: =Data!DK133 -> 7366 | DL14: =Data!DL133 -> 7631 | DM14: =Data!DM133 -> 8423 | DN14: =DI14*(1+DN82)+DN65+DN73 -> 8515.125 | DO14: =SUM(DK14:DN14) -> 31935.125 | DP14: =DK14*(1+DP82)+DP65+DP73 -> 8065.77 | DQ14: =DL14*(1+DQ82)+DQ65+DQ73 -> 8333.052 | DR14: =((DM14-DM73)*(1+DR82))+DR65+DR73 -> 9189.493 | DS14: =DN14*(1+DS82)+DS65+DS73 -> 9315.5468 | DT14: =SUM(DP14:DS14) -> 34903.862 | DU14: =DT14*(1+DU82)+DU65+DU73 -> 37765.978 | DV14: =DU14*(1+DV82)+DV65+DV73 -> 40447.363
B16: Acquisitions
B17: Rockwell Collins | CB17: =2180*0.87 -> 1896.6 | CC17: =2208*0.87 -> 1920.96 | CD17: =2266*0.87 -> 1971.42 | CE17: =2113*0.87 -> 1838.31 | CF17: =SUM(CB17:CE17) -> 7627.29
B18: Goodrich | AZ18: 1300 | BA18: 1525 | BB18: =SUM(AZ18:BA18) -> 2825 | BC18: 1800 | BD18: 1800 | BE18: 500 | BF18: 500 | BG18: =SUM(BC18:BF18) -> 4600
B20: Divestures
B21: Simmonds Precision Products 10/25 | DN21: =+-87.5 -> -87.5 | DO21: =+SUM(DK21:DN21) -> -87.5 | DP21: =+-87.5 -> -87.5 | DQ21: =+-87.5 -> -87.5 | DR21: =+-87.5 -> -87.5 | DT21: =+SUM(DP21:DS21) -> -262.5
B22: Collins Actuation - July 2025 | DM22: -263 | DN22: -400 | DO22: =+SUM(DK22:DN22) -> -663 | DP22: -400 | DQ22: -400 | DT22: =+SUM(DP22:DS22) -> -800
B23: Misc incl FX | AZ23: -200 | BA23: -200 | BB23: =SUM(AZ23:BA23) -> -400 | BC23: -25 | BD23: -25 | BE23: -25 | BF23: -25 | BG23: =SUM(BC23:BF23) -> -100 | BK23: -25 | BL23: =SUM(BH23:BK23) -> -25 | CB23: -40 | CC23: -40 | CD23: -40 | CE23: -40 | CF23: =+SUM(CB23:CE23) -> -160 | CV23: -15 | CW23: -20 | CZ23: =SUM(CV23:CY23) -> -35 | DA23: -15 | DB23: -20 | DC23: 57 | DD23: 112 | DE23: =SUM(DA23:DD23) -> 134 | DH23: 30 | DJ23: =SUM(DF23:DI23) -> 30 | DO23: =SUM(DK23:DN23) -> 0
B24: CAS Military GPS | CN24: -65 | CO24: =-360/4 -> -90 | CP24: =SUM(CL24:CO24) -> -155 | CQ24: =-360/4 -> -90 | CR24: -100 | CS24: -70 | CU24: =SUM(CQ24:CT24) -> -260 | CZ24: =SUM(CV24:CY24) -> 0 | DE24: =SUM(DA24:DD24) -> 0 | DJ24: =SUM(DF24:DI24) -> 0 | DO24: =SUM(DK24:DN24) -> 0
B26: Collins Aerospace | C26: =+Data!C134 -> 2804 | D26: =+Data!D134 -> 2891 | E26: =+Data!E134 -> 3810 | F26: =+Data!F134 -> 4992 | G26: =+Data!G134 -> 5292 | H26: =+Data!H134 -> 3453 | I26: =+Data!I134 -> 3598 | J26: =+Data!J134 -> 926 | ... CK26: =+Data!CK134 -> 26028 | CL26: =Data!CL134 -> 4988.9747 | CM26: =Data!CM134 -> 4980.2956 | CN26: =Data!CN134 -> 4992.146 | CO26: =Data!CO134 -> 7027.5837 | CP26: =SUM(CL26:CO26) -> 21989 | CQ26: =Data!CQ134 -> 4991.4661 | CR26: =Data!CR134 -> 5010.5426 | CS26: =Data!CS134 -> 4998.3731 | CT26: =Data!CT134 -> 6151.6183 | CU26: =SUM(CQ26:CT26) -> 21152 | CV26: =Data!CV134 -> 5476 | CW26: =Data!CW134 -> 5627 | CX26: =Data!CX134 -> 5718 | CY26: =Data!CY134 -> 6231 | CZ26: =SUM(CV26:CY26) -> 23052 | DA26: =Data!DA134 -> 6120 | DB26: =Data!DB134 -> 6384 | DC26: =Data!DC134 -> 6629 | DD26: =Data!DD134 -> 7120 | DE26: =SUM(DA26:DD26) -> 26253 | DF26: =Data!DF134 -> 6673 | DG26: =Data!DG134 -> 6999 | DH26: =Data!DH134 -> 7075 | DI26: =Data!DI134 -> 7537 | DJ26: =SUM(DF26:DI26) -> 28284 | DK26: =Data!DK134 -> 7217 | DL26: =Data!DL134 -> 7622 | DM26: =Data!DM134 -> 7621 | DN26: =DI26*(1+DN83)+DN74+DN66 -> 7456.498 | DO26: =SUM(DK26:DN26) -> 29916.498 | DP26: =DK26*(1+DP83)+DP74+DP66 -> 7162.52 | DQ26: =DL26*(1+DQ83)+DQ74+DQ66 -> 7668.04 | DR26: =DM26*(1+DR83)+DR74+DR66 -> 7990.76 | DS26: =DN26*(1+DS83)+DS74+DS66 -> 7926.2574 | DT26: =SUM(DP26:DS26) -> 30747.577 | DU26: =DT26*(1+DU83)+DU66+DU74 -> 32530.937 | DV26: =DU26*(1+DV83)+DV66+DV74 -> 34222.546
B28: Acquisitions
B29: RGNext 02/19 | CG29: 38 | CH29: 60 | CI29: 60 | CJ29: 60 | CK29: =SUM(CG29:CJ29) -> 218 | CL29: 25 | CP29: =SUM(CL29:CO29) -> 25
B30: Collins Mission Systems | CB30: =2180*0.13 -> 283.4 | CC30: =2208*0.13 -> 287.04 | CD30: =2266*0.13 -> 294.58 | CE30: =2113*0.13 -> 274.69 | CF30: =SUM(CB30:CE30) -> 1139.71
B31: Stonesoft 1/16 | BR31: =60/4*2.5/3 -> 12.5 | BS31: =60/4 -> 15 | BT31: =60/4 -> 15 | BU31: =60/4 -> 15 | BV31: =SUM(BR31:BU31) -> 57.5 | BW31: =60/4*0.5/3 -> 2.5
B32: Websense 5/15 | BN32: =375*0.25/3 -> 31.25 | BO32: =375*0.25 -> 93.75 | BP32: =375*0.25 -> 93.75 | BQ32: =SUM(BM32:BP32) -> 218.75 | BR32: 94 | BS32: =385-BQ32-BR32 -> 72.25 | BV32: =SUM(BR32:BU32) -> 166.25
B33: Blackbird 11/14 | BK33: =200/4*2/3 -> 33.333333 | BL33: =SUM(BH33:BK33) -> 33.333333 | BM33: 50 | BN33: 50 | BO33: 50 | BP33: 50 | BQ33: =SUM(BM33:BP33) -> 200
B34: SafeNet 12/12 | BA34: 13.15 | BB34: =SUM(BA34) -> 13.15 | BC34: 65.75 | BD34: 65.75 | BE34: 65.75 | BF34: 52.6 | BG34: =SUM(BC34:BF34) -> 249.85
B35: Applied Signal - 1/11 | AS35: =61*2/3 -> 40.666667 | AT35: 62 | AU35: 67 | AV35: 58 | AW35: =SUM(AS35:AV35) -> 227.66667 | AX35: 20 | BB35: =SUM(AX35:BA35) -> 20
B37: Divestures
B38: Cyber
B39: Training & Logistics 12/21 | CT39: =-1000/12 -> -83.333333 | CU39: =SUM(CQ39:CT39) -> -83.333333 | CV39: -180 | CW39: -200 | CX39: -200 | CY39: -145 | CZ39: =SUM(CV39:CY39) -> -725 | DA39: -180 | DB39: -200 | DC39: -200 | DD39: -35
B40: Airborne Tactical Radios 5/20 | CM40: =-120/12*2 -> -20 | CN40: -25 | CO40: -30 | CP40: =SUM(CL40:CO40) -> -75 | CQ40: =-120/4 -> -30 | CR40: 0 | CU40: =SUM(CQ40:CT40) -> -30
B41: Raytheon Intelligence & Space | BB41: =Data!BB135 -> 13158 | BC41: =Data!BC135 -> 3103 | BD41: =Data!BD135 -> 3190 | BE41: =Data!BE135 -> 3052 | BF41: =Data!BF135 -> 3071 | BG41: =Data!BG135 -> 12416 | BH41: =Data!BH135 -> 2848 | BI41: =Data!BI135 -> 3023 | ... CO41: =Data!CO135 -> 3933 | CP41: =SUM(CL41:CO41) -> 14959 | CQ41: =Data!CQ135 -> 3765 | CR41: =Data!CR135 -> 3805 | CS41: =Data!CS135 -> 3740 | CT41: =Data!CT135 -> 3870 | CU41: =SUM(CQ41:CT41) -> 15180 | CV41: =Data!CV135 -> 3572 | CW41: =Data!CW135 -> 3570 | CX41: =Data!CX135 -> 3626 | CY41: =Data!CY135 -> 3544 | CZ41: =SUM(CV41:CY41) -> 14312 | DA41: =Data!DA135 -> 3565 | DB41: =Data!DB135 -> 3655 | DC41: =Data!DC135 -> 0 | DD41: =Data!DD135 -> 0 | DE41: =SUM(DA41:DD41) -> 7220 | DF41: =Data!DF135 -> 0 | DJ41: =SUM(DF41:DI41) -> 0 | DK41: =Data!DK135 -> 0 | DO41: =SUM(DK41:DN41) -> 0 | DT41: =DO41*(1+DT84)+DT75+DT67 -> 0 | DU41: =DT41*(1+DU84)+DU75+DU67 -> 0 | DV41: =DU41*(1+DV84)+DV75+DV67 -> 0
B43: Acquisitions
B44: Ktech Corp, 6/11 | AU44: =65/4 -> 16.25 | AV44: =65/4 -> 16.25 | AW44: =SUM(AS44:AV44) -> 32.5 | AX44: =65/4 -> 16.25 | AY44: =65/4 -> 16.25 | BB44: =SUM(AX44:BA44) -> 32.5
B46: Divestures
B47: Misc incl FX | CW47: -15 | CX47: -15 | CY47: -15 | CZ47: =SUM(CV47:CY47) -> -45 | DB47: -15 | DC47: -15 | DD47: -15
B48: Raytheon Missiles & Defense | BB48: =Data!BB136 -> 13131 | BC48: =Data!BC136 -> 3232 | BD48: =Data!BD136 -> 3411 | BE48: =Data!BE136 -> 3238 | BF48: =Data!BF136 -> 3207 | BG48: =Data!BG136 -> 13088 | BH48: =Data!BH136 -> 3055 | BI48: =Data!BI136 -> 3088 | ... CO48: =Data!CO136 -> 4184 | CP48: =SUM(CL48:CO48) -> 15343 | CQ48: =Data!CQ136 -> 3793 | CR48: =Data!CR136 -> 3985 | CS48: =Data!CS136 -> 3902 | CT48: =Data!CT136 -> 3859 | CU48: =SUM(CQ48:CT48) -> 15539 | CV48: =Data!CV136 -> 3527 | CW48: =Data!CW136 -> 3558 | CX48: =Data!CX136 -> 3678 | CY48: =Data!CY136 -> 4100 | CZ48: =SUM(CV48:CY48) -> 14863 | DA48: =Data!DA136 -> 3671 | DB48: =Data!DB136 -> 4000 | DC48: =Data!DC136 -> 0 | DD48: =Data!DD136 -> 0 | DE48: =SUM(DA48:DD48) -> 7671 | DF48: =Data!DF136 -> 0 | DJ48: =SUM(DF48:DI48) -> 0 | DK48: =Data!DK136 -> 0 | DO48: =SUM(DK48:DN48) -> 0 | DT48: =DO48*(1+DT85)+DT76+DT68 -> 0 | DU48: =DT48*(1+DU85)+DU76+DU68 -> 0 | DV48: =DU48*(1+DV85)+DV76+DV68 -> 0
B50: Raytheon (Defense recasted) | CL50: =Data!CL137 -> 6408.288 | CM50: =Data!CM137 -> 6318.432 | CN50: =Data!CN137 -> 6441.12 | CO50: =Data!CO137 -> 7009.16 | CP50: =Data!CP137 -> 26177 | CQ50: =Data!CQ137 -> 6545.228 | CR50: =Data!CR137 -> 6746.14 | CS50: =Data!CS137 -> 6617.972 | ... CY50: =Data!CY137 -> 6661 | CZ50: =SUM(CV50:CY50) -> 25176 | DA50: =Data!DA137 -> 6292 | DB50: =Data!DB137 -> 6700 | DC50: =Data!DC137 -> 6472 | DD50: =Data!DD137 -> 6886 | DE50: =SUM(DA50:DD50) -> 26350 | DF50: =Data!DF137 -> 6659 | DG50: =Data!DG137 -> 6581 | DH50: =Data!DH137 -> 6386 | DI50: =Data!DI137 -> 7157 | DJ50: =SUM(DF50:DI50) -> 26783 | DK50: =Data!DK137 -> 6340 | DL50: =Data!DL137 -> 7001 | DM50: =Data!DM137 -> 7045 | DN50: =DI50*(1+DN86)+DN77+DN69 -> 7328.768 | DO50: =SUM(DK50:DN50) -> 27714.768 | DP50: =DK50*(1+DP86)+DP77+DP69 -> 6783.8 | DQ50: =DL50*(1+DQ86)+DQ77+DQ69 -> 7309.044 | DR50: =DM50*(1+DR86)+DR77+DR69 -> 7404.295 | DS50: =DN50*(1+DS86)+DS77+DS69 -> 7739.179 | DT50: =SUM(DP50:DS50) -> 29236.318 | DU50: =DT50*(1+DU86)+DU77+DU69 -> 30785.843 | DV50: =DU50*(1+DV86)+DV77+DV69 -> 32355.921
B52: Acquisitions
B56: Divestitures
B57: Cyber Services Business (Mar 2024) | DG57: -360 | DH57: -390 | DI57: -350 | DJ57: =+SUM(DF57:DI57) -> -1100 | DK57: -350 | DL57: 0 | DO57: =+SUM(DK57:DN57) -> -350
B61: Eliminations & other | BB61: =Data!BB138 -> -2402 | BC61: =Data!BC138 -> -622 | BD61: =Data!BD138 -> -672 | BE61: =Data!BE138 -> -650 | BF61: =Data!BF138 -> -622 | BG61: =Data!BG138 -> -2566 | BH61: =Data!BH138 -> -596 | BI61: =Data!BI138 -> -625 | ... CO61: =Data!CO138 -> 315.25631 | CP61: =SUM(CL61:CO61) -> -790 | CQ61: =Data!CQ138 -> -315.69408 | CR61: =Data!CR138 -> -303.68257 | CS61: =Data!CS138 -> -311.34509 | CT61: =Data!CT138 -> -594.27826 | CU61: =SUM(CQ61:CT61) -> -1525 | CV61: =Data!CV138 -> -363 | CW61: =Data!CW138 -> -415 | CX61: =Data!CX138 -> -455 | CY61: =Data!CY138 -> -451 | CZ61: =SUM(CV61:CY61) -> -1684 | DA61: =Data!DA138 -> -428 | DB61: =Data!DB138 -> -470 | DC61: =Data!DC138 -> -563 | DD61: =Data!DD138 -> -518 | DE61: =SUM(DA61:DD61) -> -1979 | DF61: =Data!DF138 -> -483 | DG61: =Data!DG138 -> -591 | DH61: =Data!DH138 -> -611 | DI61: =Data!DI138 -> -640 | DJ61: =SUM(DF61:DI61) -> -2325 | DK61: =Data!DK138 -> -617 | DL61: =Data!DL138 -> -673 | DM61: =Data!DM138 -> -611 | DN61: -700 | DO61: =SUM(DK61:DN61) -> -2601 | DP61: -600 | DQ61: -650 | DR61: -700 | DS61: -750 | DT61: =SUM(DP61:DS61) -> -2700 | DU61: -2750 | DV61: -2800
B62: Total | C62: =Data!C139 -> 23357 | D62: =Data!D139 -> 29845 | E62: =Data!E139 -> 30961 | F62: =Data!F139 -> 28895 | G62: =Data!G139 -> 29531 | H62: =Data!H139 -> 27209 | I62: =Data!I139 -> 28710 | J62: =Data!J139 -> 7727 | ... BA62: =Data!BA139 -> 13319 | BB62: =BB14+BB26+BB41+BB48+BB61 -> 46185 | BC62: =BC14+BC26+BC41+BC48+BC61 -> 12378 | BD62: =BD14+BD26+BD41+BD48+BD61 -> 12874 | BE62: =BE14+BE26+BE41+BE48+BE61 -> 12338 | BF62: =BF14+BF26+BF41+BF48+BF61 -> 13196 | BG62: =BG14+BG26+BG41+BG48+BG61 -> 50786 | BH62: =BH14+BH26+BH41+BH48+BH61 -> 12086 | BI62: =BI14+BI26+BI41+BI48+BI61 -> 12714 | ... CO62: =CO14+CO26+CO41+CO48+CO61 -> 20349.84 | CP62: =SUM(CP14,CP26,CP50,CP61) -> 64600 | CQ62: =CQ14+CQ26+CQ41+CQ48+CQ61 -> 16263.772 | CR62: =CR14+CR26+CR41+CR48+CR61 -> 16776.86 | CS62: =CS14+CS26+CS41+CS48+CS61 -> 17054.028 | CT62: =CT14+CT26+CT41+CT48+CT61 -> 18401.34 | CU62: =SUM(CU14,CU26,CU50,CU61) -> 64388 | CV62: =SUM(CV14,CV26,CV50,CV61) -> 15716 | CW62: =SUM(CW14,CW26,CW50,CW61) -> 16314 | CX62: =SUM(CX14,CX26,CX50,CX61) -> 16951 | CY62: =SUM(CY14,CY26,CY50,CY61) -> 18093 | CZ62: =SUM(CZ14,CZ26,CZ50,CZ61) -> 67074 | DA62: =SUM(DA14,DA26,DA50,DA61) -> 17214 | DB62: =SUM(DB14,DB26,DB50,DB61) -> 18315 | ... DV62: =SUM(DV14,DV26,DV50,DV61) -> 104225.83
B64: Acquired Revenue
B65: Pratt & Whitney | C65: =SUM(C9:C10) -> 0 | D65: =SUM(D9:D10) -> 0 | E65: =SUM(E9:E10) -> 0 | F65: =SUM(F9:F10) -> 0 | G65: =SUM(G9:G10) -> 0 | H65: =SUM(H9:H10) -> 0 | I65: =SUM(I9:I10) -> 0 | J65: =SUM(J9:J10) -> 0 | ... AY65: =SUM(AY9:AY10) -> 0 | AZ65: =SUM(AZ$8:AZ10) -> 550 | BA65: =SUM(BA$8:BA10) -> 550 | BB65: =SUM(BB$8:BB10) -> 1100 | BC65: =SUM(BC$8:BC10) -> 550 | BD65: =SUM(BD$8:BD10) -> 375 | BE65: =SUM(BE$8:BE10) -> 0 | BF65: =SUM(BF$8:BF10) -> 0 | BG65: =SUM(BG$8:BG10) -> 925 | ... DV65: =SUM(DV$8:DV10) -> 0
B66: Collins Aerospace | C66: =SUM(C18:C19) -> 0 | D66: =SUM(D18:D19) -> 0 | E66: =SUM(E18:E19) -> 0 | F66: =SUM(F18:F19) -> 0 | G66: =SUM(G18:G19) -> 0 | H66: =SUM(H18:H19) -> 0 | I66: =SUM(I18:I19) -> 0 | J66: =SUM(J18:J19) -> 0 | ... AY66: =SUM(AY18:AY19) -> 0 | AZ66: =SUM(AZ$16:AZ19) -> 1300 | BA66: =SUM(BA$16:BA19) -> 1525 | BB66: =SUM(BB$16:BB19) -> 2825 | BC66: =SUM(BC$16:BC19) -> 1800 | BD66: =SUM(BD$16:BD19) -> 1800 | BE66: =SUM(BE$16:BE19) -> 500 | BF66: =SUM(BF$16:BF19) -> 500 | BG66: =SUM(BG$16:BG19) -> 4600 | ... DV66: =SUM(DV$16:DV19) -> 0
B67: Raytheon Intelligence & Space | AX67: =SUM(AX$28:AX36) -> 20 | AY67: =SUM(AY$28:AY36) -> 0 | AZ67: =SUM(AZ$28:AZ36) -> 0 | BA67: =SUM(BA$28:BA36) -> 13.15 | BB67: =SUM(BB$28:BB36) -> 33.15 | BC67: =SUM(BC$28:BC36) -> 65.75 | BD67: =SUM(BD$28:BD36) -> 65.75 | BE67: =SUM(BE$28:BE36) -> 65.75 | ... DV67: =SUM(DV$28:DV36) -> 0
B68: Raytheon Missiles & Defense | AX68: =SUM(AX$43:AX45) -> 16.25 | AY68: =SUM(AY$43:AY45) -> 16.25 | AZ68: =SUM(AZ$43:AZ45) -> 0 | BA68: =SUM(BA$43:BA45) -> 0 | BB68: =SUM(BB$43:BB45) -> 32.5 | BC68: =SUM(BC$43:BC45) -> 0 | BD68: =SUM(BD$43:BD45) -> 0 | BE68: =SUM(BE$43:BE45) -> 0 | ... DV68: =SUM(DV$43:DV45) -> 0
B69: Raytheon (Defense recasted) | DF69: =+SUM(DF52:DF54) -> 0 | DG69: =+SUM(DG52:DG54) -> 0 | DH69: =+SUM(DH52:DH54) -> 0 | DI69: =+SUM(DI52:DI54) -> 0 | DJ69: =+SUM(DJ52:DJ54) -> 0 | DK69: =+SUM(DK52:DK54) -> 0 | DL69: =+SUM(DL52:DL54) -> 0 | DM69: =+SUM(DM52:DM54) -> 0 | ... DV69: =+SUM(DV52:DV54) -> 0
B70: Total | C70: =SUM(C65:C66) -> 0 | D70: =SUM(D65:D66) -> 0 | E70: =SUM(E65:E66) -> 0 | F70: =SUM(F65:F66) -> 0 | G70: =SUM(G65:G66) -> 0 | H70: =SUM(H65:H66) -> 0 | I70: =SUM(I65:I66) -> 0 | J70: =SUM(J65:J66) -> 0 | ... AQ70: =SUM(AQ65:AQ66) -> 0 | AR70: 0 | AS70: =SUM(AS65:AS66) -> 0 | AT70: =SUM(AT65:AT66) -> 0 | AU70: =SUM(AU65:AU66) -> 0 | AV70: =SUM(AV65:AV66) -> 0 | AW70: =SUM(AW65:AW66) -> 0 | AX70: =SUM(AX65:AX68) -> 36.25 | AY70: =SUM(AY65:AY68) -> 16.25 | AZ70: =SUM(AZ65:AZ68) -> 1850 | BA70: =SUM(BA65:BA68) -> 2088.15 | BB70: =SUM(BB65:BB68) -> 3990.65 | BC70: =SUM(BC65:BC68) -> 2415.75 | BD70: =SUM(BD65:BD68) -> 2240.75 | BE70: =SUM(BE65:BE68) -> 565.75 | ... DE70: =SUM(DE65:DE68) -> 0 | DF70: =SUM(DF65:DF69) -> 0 | DG70: =SUM(DG65:DG69) -> 0 | DH70: =SUM(DH65:DH69) -> 0 | DI70: =SUM(DI65:DI69) -> 0 | DJ70: =SUM(DJ65:DJ69) -> 0 | DK70: =SUM(DK65:DK69) -> 0 | DL70: =SUM(DL65:DL69) -> 0 | DM70: =SUM(DM65:DM69) -> 0 | ... DV70: =SUM(DV65:DV69) -> 0
B72: Divested Revenue
B73: Pratt & Whitney | C73: =SUM(C11:C13) -> 0 | D73: =SUM(D11:D13) -> 0 | E73: =SUM(E11:E13) -> 0 | F73: =SUM(F11:F13) -> 0 | G73: =SUM(G11:G13) -> 0 | H73: =SUM(H11:H13) -> 0 | I73: =SUM(I11:I13) -> 0 | J73: =SUM(J11:J13) -> 0 | ... AY73: =SUM(AY11:AY13) -> 0 | AZ73: =SUM(AZ$11:AZ13) -> 0 | BA73: =SUM(BA$11:BA13) -> 0 | BB73: =SUM(BB$11:BB13) -> 0 | BC73: =SUM(BC$11:BC13) -> 0 | BD73: =SUM(BD$11:BD13) -> 0 | BE73: =SUM(BE$11:BE13) -> 0 | BF73: =SUM(BF$11:BF13) -> 0 | BG73: =SUM(BG$11:BG13) -> 0 | ... DV73: =SUM(DV$11:DV13) -> 0
B74: Collins Aerospace | C74: =SUM(C23:C25) -> 0 | D74: =SUM(D23:D25) -> 0 | E74: =SUM(E23:E25) -> 0 | F74: =SUM(F23:F25) -> 0 | G74: =SUM(G23:G25) -> 0 | H74: =SUM(H23:H25) -> 0 | I74: =SUM(I23:I25) -> 0 | J74: =SUM(J23:J25) -> 0 | ... AY74: =SUM(AY23:AY25) -> 0 | AZ74: =SUM(AZ$20:AZ25) -> -200 | BA74: =SUM(BA$20:BA25) -> -200 | BB74: =SUM(BB$20:BB25) -> -400 | BC74: =SUM(BC$20:BC25) -> -25 | BD74: =SUM(BD$20:BD25) -> -25 | BE74: =SUM(BE$20:BE25) -> -25 | BF74: =SUM(BF$20:BF25) -> -25 | BG74: =SUM(BG$20:BG25) -> -100 | ... DD74: =SUM(DD$20:DD25) -> 112 | DE74: =SUM(DA74:DD74) -> 134 | DF74: =SUM(DF$20:DF25) -> 0 | DG74: =SUM(DG$20:DG25) -> 0 | DH74: =SUM(DH$20:DH25) -> 30 | DI74: =SUM(DI$20:DI25) -> 0 | DJ74: =SUM(DJ$20:DJ25) -> 30 | DK74: =SUM(DK$20:DK25) -> 0 | DL74: =SUM(DL$20:DL25) -> 0 | DM74: =SUM(DM$20:DM25) -> -263 | ... DV74: =SUM(DV$20:DV25) -> 0
B75: Raytheon Intelligence & Space | AX75: =SUM(AX$37:AX40) -> 0 | AY75: =SUM(AY$37:AY40) -> 0 | AZ75: =SUM(AZ$37:AZ40) -> 0 | BA75: =SUM(BA$37:BA40) -> 0 | BB75: =SUM(BB$37:BB40) -> 0 | BC75: =SUM(BC$37:BC40) -> 0 | BD75: =SUM(BD$37:BD40) -> 0 | BE75: =SUM(BE$37:BE40) -> 0 | ... DV75: =SUM(DV$37:DV40) -> 0
B76: Raytheon Missiles & Defense | AX76: =SUM(AX$46:AX47) -> 0 | AY76: =SUM(AY$46:AY47) -> 0 | AZ76: =SUM(AZ$46:AZ47) -> 0 | BA76: =SUM(BA$46:BA47) -> 0 | BB76: =SUM(BB$46:BB47) -> 0 | BC76: =SUM(BC$46:BC47) -> 0 | BD76: =SUM(BD$46:BD47) -> 0 | BE76: =SUM(BE$46:BE47) -> 0 | ... DV76: =SUM(DV$46:DV47) -> 0
B77: Raytheon (Defense recasted) | CV77: =SUM(CV75:CV76) -> -180 | CW77: =SUM(CW75:CW76) -> -215 | CX77: =SUM(CX75:CX76) -> -215 | CY77: =SUM(CY75:CY76) -> -160 | DA77: =SUM(DA75:DA76) -> -180 | DB77: =SUM(DB75:DB76) -> -215 | DD77: =DD39 -> -35 | DE77: =SUM(DA77:DD77) -> -430 | DF77: =+SUM(DF57:DF59) -> 0 | DG77: =+SUM(DG57:DG59) -> -360 | DH77: =+SUM(DH57:DH59) -> -390 | DI77: =+SUM(DI57:DI59) -> -350 | DJ77: =SUM(DF77:DI77) -> -1100 | DK77: =+SUM(DK57:DK59) -> -350 | DL77: =+SUM(DL57:DL59) -> 0 | DM77: =+SUM(DM57:DM59) -> 0 | DN77: =+SUM(DN57:DN59) -> 0 | DO77: =SUM(DK77:DN77) -> -350 | DP77: =+SUM(DP57:DP59) -> 0 | DQ77: =+SUM(DQ57:DQ59) -> 0 | DR77: =+SUM(DR57:DR59) -> 0 | DS77: =+SUM(DS57:DS59) -> 0 | DT77: =SUM(DP77:DS77) -> 0 | DU77: =+SUM(DU57:DU59) -> 0 | DV77: =+SUM(DV57:DV59) -> 0
B78: Total | C78: =SUM(C73:C74) -> 0 | D78: =SUM(D73:D74) -> 0 | E78: =SUM(E73:E74) -> 0 | F78: =SUM(F73:F74) -> 0 | G78: =SUM(G73:G74) -> 0 | H78: =SUM(H73:H74) -> 0 | I78: =SUM(I73:I74) -> 0 | J78: =SUM(J73:J74) -> 0 | ... AW78: =SUM(AW73:AW74) -> 0 | AX78: =SUM(AX73:AX76) -> 0 | AY78: =SUM(AY73:AY76) -> 0 | AZ78: =SUM(AZ73:AZ76) -> -200 | BA78: =SUM(BA73:BA76) -> -200 | BB78: =SUM(BB73:BB76) -> -400 | BC78: =SUM(BC73:BC76) -> -25 | BD78: =SUM(BD73:BD76) -> -25 | BE78: =SUM(BE73:BE76) -> -25 | ... DD78: =SUM(DD73:DD76) -> 62 | DE78: =SUM(DE73:DE77) -> -5697 | DF78: =SUM(DF73:DF77) -> 0 | DG78: =SUM(DG73:DG77) -> -360 | DH78: =SUM(DH73:DH77) -> -360 | DI78: =SUM(DI73:DI77) -> -350 | DJ78: =SUM(DJ73:DJ77) -> -1070 | DK78: =SUM(DK73:DK77) -> -350 | DL78: =SUM(DL73:DL77) -> 0 | ... DV78: =SUM(DV73:DV77) -> 0
B81: Organic Revenue Y/Y Growth
B82: Pratt & Whitney | S82: 0.09 | X82: 0.16 | Y82: 0.074492212 | Z82: 0.13371397 | AA82: 0.091 | AB82: 0.05 | AC82: 0.09 | AD82: 0.16 | AE82: 0.05 | AF82: 0.02 | AG82: 0.115 | AH82: 0.07 | AI82: -0.05 | AJ82: -0.08 | AK82: -0.09 | AL82: -0.097 | AM82: -0.08 | AN82: -0.12 | AO82: 0.01 | AP82: 0.04 | AQ82: 0.12 | AR82: 0 | AS82: 0.1 | AT82: 0.06 | AU82: 0.01 | AV82: 0.01 | AW82: 0.04 | AX82: 0.06 | AY82: 0.05 | AZ82: -0.01 | BA82: -0.04 | BB82: =(BB14-BB65-BB73)/(AW14)-1 -> 0.012036819 | BC82: -0.02 | BD82: -0.06 | BE82: 0 | BF82: 0.13 | BG82: =(BG14-BG65-BG73)/(BB14)-1 -> -0.027785735 | BH82: 0.04 | BI82: 0.01 | BJ82: 0.05 | BK82: =(BK14-BK65-BK73)/(BF14)-1 -> -0.016140866 | BL82: =(BL14-BL65-BL73)/(BG14)-1 -> 0.0051720571 | BM82: 0 | BN82: 0.02 | BO82: -0.08 | BP82: 0 | BQ82: =(BQ14-BQ65-BQ73)/(BL14)-1 -> -0.02936311 | BR82: 0.08 | BS82: 0.04 | BT82: 0.13 | BU82: 0 | BV82: =(BV14-BV65-BV73)/(BQ14)-1 -> 0.057662264 | BW82: 0.04 | BX82: 0.06 | BY82: 0.15 | BZ82: 0.11 | CA82: =(CA14-CA65-CA73)/(BV14)-1 -> 0.11085001 | CB82: 0.09 | CC82: 0.12 | CD82: 0.13 | CE82: 0.13 | CF82: =(CF14-CF65-CF73)/(CA14)-1-CF90 -> 0.17237836 | CG82: 0.12 | CH82: 0.09 | CI82: 0.11 | CJ82: 0.02 | CK82: =(CK14-CK65-CK73)/(CF14)-1-CK90 -> 0.077589318 | CL82: =(CL14-CL65-CL73)/(CG14)-1 -> 0.11104193 | CM82: =(CM14-CM65-CM73)/(CH14)-1 -> -0.32343811 | CN82: =(CN14-CN65-CN73)/(CI14)-1 -> -0.33888363 | CO82: =(CO14-CO65-CO73)/(CJ14)-1 -> -0.13374668 | CP82: =(CP14-CP65-CP73)/(CK14)-1 -> -0.17596402 | CQ82: =(CQ14-CQ65-CQ73)/(CL14)-1 -> -0.24715113 | CR82: =(CR14-CR65-CR73)/(CM14)-1 -> 0.22741612 | CS82: =(CS14-CS65-CS73)/(CN14)-1 -> 0.35231826 | ... DG82: =(DG14-DG65-DG73)/(DB14)-1 -> 0.19312401 | DH82: =(DH14-DH65-DH73)/(DC14-DC12)-1 -> 0.14414414 | DI82: =(DI14-DI65-DI73)/(DD14)-1 -> 0.17549309 | DJ82: =(DJ14-DJ65-DJ73)/(DE14-DE12)-1 -> 0.18436933 | DK82: =(DK14-DK65-DK73)/(DF14)-1 -> 0.14095415 | DL82: =(DL14-DL65-DL73)/(DG14)-1 -> 0.12187592 | DM82: =(DM14-DM65-DM73)/(DH14)-1 -> 0.1635585 | DN82: 0.125 | DO82: =(DO14-DO65-DO73)/(DJ14-DJ12)-1 -> 0.13785808 | DP82: 0.095 | DQ82: 0.092 | DR82: 0.091 | DS82: 0.094 | DT82: =(DT14-DT65-DT73)/(DO14-DO12)-1 -> 0.092961488 | DU82: 0.082 | DV82: 0.071
B83: Collins Aerospace | S83: 0.06 | X83: 0.13 | Y83: 0.11400687 | Z83: 0.070018735 | AA83: 0.099 | AB83: 0.1 | AC83: 0.09 | AD83: 0.07 | AE83: 0.14 | AF83: 0.07 | AG83: 0.034 | AH83: 0.09 | AI83: 0 | AJ83: -0.09 | AK83: -0.09 | AL83: -0.087 | AM83: -0.07 | AN83: -0.05 | AO83: -0.01 | AP83: 0.04 | AQ83: 0.067316384 | AR83: 0.01 | AS83: 0.09 | AT83: 0.08 | AU83: 0.07 | AV83: 0.12 | AW83: 0.09 | AX83: 0.1 | AY83: 0.09 | AZ83: 0.06 | BA83: 0.04 | BB83: =(BB26-BB66+BB74)/(AW26)-1 -> 0.073319328 | BC83: 0 | BD83: 0.01 | BE83: 0.02 | BF83: 0.09 | BG83: =(BG26-BG66-BG74)/(BB26)-1 -> 0.061555076 | BH83: 0.06 | BI83: 0.09 | BJ83: 0.06 | BK83: =(BK26-BK66-BK74)/(BF26)-1 -> 0.048681542 | BL83: =(BL26-BL66-BL74)/(BG26)-1 -> 0.066906421 | BM83: 0.07 | BN83: 0.02 | BO83: 0 | BP83: 0.04 | BQ83: =(BQ26-BQ66-BQ74)/(BL26)-1 -> -0.0085121351 | BR83: -0.01 | BS83: 0.02 | BT83: 0.06 | BU83: 0 | BV83: =(BV26-BV66-BV74)/(BQ26)-1 -> 0.026323258 | BW83: 0.05 | BX83: -0.01 | BY83: 0 | BZ83: 0.05 | CA83: =(CA26-CA66-CA74)/(BV26)-1 -> 0.01562392 | CB83: 0.05 | CC83: 0.08 | CD83: 0.09 | CE83: 0.09 | CF83: =(CF26-CF66-CF74)/(CA26)-1-CF91 -> 0.14367368 | CG83: 0.1 | CH83: 0.09 | CI83: 0.07 | CJ83: 0.01 | CK83: =(CK26-CK66-CK74)/(CF26)-1-CK91 -> 0.072479295 | CL83: =(CL26-CL66-CL74)/(CG26)-1 -> -0.23399743 | CM83: =(CM26-CM66-CM74)/(CH26)-1 -> -0.24265578 | CN83: =(CN26-CN66-CN74)/(CI26)-1 -> -0.2213786 | CO83: =(CO26-CO66-CO74)/(CJ26)-1 -> 0.10452882 | CP83: =(CP26-CP66-CP74)/(CK26)-1 -> -0.14922391 | CQ83: =(CQ26-CQ66-CQ74)/(CL26)-1 -> 0.018539146 | CR83: =(CR26-CR66-CR74)/(CM26)-1 -> 0.026152462 | CS83: =(CS26-CS66-CS74)/(CN26)-1 -> 0.015269406 | ... DM83: =(DM26-DM66-DM74)/(DH26)-1 -> 0.11434629 | DN83: 0.054 | DO83: =(DO26-DO66-DO74)/(DJ26)-1 -> 0.08425251 | DP83: 0.06 | DQ83: 0.07 | DR83: 0.06 | DS83: 0.063 | DT83: =(DT26-DT66-DT74)/(DO26)-1 -> 0.063295489 | DU83: 0.058 | DV83: 0.052
B84: Raytheon Intelligence & Space | BG84: =(BG41-BG67-BG75)/BB41-1 -> -0.075379997 | BH84: =(BH41-BH67-BH75)/BC41-1 -> -0.082178537 | BI84: =(BI41-BI67-BI75)/BD41-1 -> -0.052351097 | BJ84: =(BJ41-BJ67-BJ75)/BE41-1 -> -0.030471822 | BK84: =(BK41-BK67-BK75)/BF41-1 -> 0.03050038 | BL84: =(BL41-BL67-BL75)/BG41-1 -> -0.033934708 | BM84: =(BM41-BM67-BM75)/BH41-1 -> -0.027738764 | BN84: =(BN41-BN67-BN75)/BI41-1 -> -0.031177638 | ... CF84: =(CF41-CF67-CF75)/CA41-1 -> -0.021948917 | CG84: =(3430-CG67-CG75)/CB41-1 -> 0.076825397 | CH84: =(3594-CH67-CH75)/CC41-1 -> 0.073511543 | CI84: =(3794-CI67-CI75)/CD41-1 -> 0.086412569 | CJ84: =(3760-CJ67-CJ75)/CE41-1 -> 0.030353662 | CK84: =(14578-CK67-CK75)/CF41-1 -> 0.066072754 | CL84: =(CL41-CL67-CL75)/CG41-1 -> 0.074771858 | CM84: =(CM41-CM67-CM75)/CH41-1 -> 0.01799269 | CN84: =(CN41-CN67-CN75)/CI41-1 -> 0.0034565275 | CO84: =(CO41-CO67-CO75)/CJ41-1 -> 0.062466488 | CP84: =(CP41-CP67-CP75)/CK41-1 -> 0.039044652 | CQ84: =(CQ41-CQ67-CQ75)/CL41-1 -> 0.032372144 | CR84: =(CR41-CR67-CR75)/CM41-1 -> 0.05665093 | CS84: =(CS41-CS67-CS75)/CN41-1 -> -0.0024006402 | ... DH84: =(DH41-DH67-DH75)/DC41-1 -> #DIV/0! | DI84: 0.046 | DJ84: =(DJ41-DJ67-DJ75)/DE41-1 -> -1 | DK84: 0.035
B85: Raytheon Missiles & Defense | BG85: =(BG48-BG68-BG76)/BB48-1 -> -0.0032746935 | BH85: =(BH48-BH68-BH76)/BC48-1 -> -0.054764851 | BI85: =(BI48-BI68-BI76)/BD48-1 -> -0.094693638 | BJ85: =(BJ48-BJ68-BJ76)/BE48-1 -> -0.10284126 | BK85: =(BK48-BK68-BK76)/BF48-1 -> 0.043342688 | BL85: =(BL48-BL68-BL76)/BG48-1 -> -0.053025672 | BM85: =(BM48-BM68-BM76)/BH48-1 -> -0.090016367 | BN85: =(BN48-BN68-BN76)/BI48-1 -> 0.011658031 | ... CF85: =(CF48-CF68-CF76)/CA48-1 -> 0.065263777 | CG85: =(3556-CG68-CG76)/CB48-1 -> 0.065627809 | CH85: =(3851-CH68-CH76)/CC48-1 -> 0.080224404 | CI85: =(3920-CI68-CI76)/CD48-1 -> 0.096503497 | CJ85: =(4326-CJ68-CJ76)/CE48-1 -> 0.081229693 | CK85: =(15653-CK68-CK76)/CF48-1 -> 0.081157618 | CL85: =(CL48-CL68-CL76)/CG48-1 -> 0.063086104 | CM85: =(CM48-CM68-CM76)/CH48-1 -> -0.024185068 | CN85: =(CN48-CN68-CN76)/CI48-1 -> -0.045337455 | CO85: =(CO48-CO68-CO76)/CJ48-1 -> -0.024481231 | CP85: =(CP48-CP68-CP76)/CK48-1 -> -0.009745708 | CQ85: =(CQ48-CQ68-CQ76)/CL48-1 -> 0.013900027 | CR85: =(CR48-CR68-CR76)/CM48-1 -> 0.073545259 | CS85: =(CS48-CS68-CS76)/CN48-1 -> 0.05288721 | ... DH85: =(DH48-DH68-DH76)/DC48-1 -> #DIV/0! | DI85: 0.04 | DJ85: =(DJ48-DJ68-DJ76)/DE48-1 -> -1 | DK85: 0.04
B86: Raytheon (Defense recasted) | DA86: =(DA50-DA69-DA77)/CV50-1 -> 0.065525189 | DB86: =(DB50-DB69-DB77)/CW50-1 -> 0.12750693 | DC86: =(DC50-DC69-DC77)/CX50-1 -> 0.025998732 | DD86: =(DD50-DD69-DD77)/CY50-1 -> 0.039033178 | DE86: =(DE50-DE69-DE77)/CZ50-1 -> 0.063711471 | DF86: =(DF50-DF69-DF77)/DA50-1 -> 0.058328036 | DG86: =(DG50-DG69-DG77)/DB50-1 -> 0.035970149 | DH86: =(DH50-DH69-DH77)/DC50-1 -> 0.04697157 | ... DM86: =(DM50-DM69-DM77)/DH50-1 -> 0.10319449 | DN86: 0.024 | DO86: =(DO50-DO69-DO77)/DJ50-1 -> 0.047857522 | DP86: 0.07 | DQ86: 0.044 | DR86: 0.051 | DS86: 0.056 | DT86: =(DT50-DT69-DT77)/DO50-1 -> 0.054900334 | DU86: 0.053 | DV86: 0.051
B87: Total | BC87: -0.02 | BD87: 0 | BE87: 0.01 | BF87: 0.04 | BG87: =(BG62-BG70-BG78)/(BB62)-1 -> -0.023251056 | BH87: =(BH62-BH70-BH78)/(BC62)-1 -> -0.018096623 | BI87: =(BI62-BI70-BI78)/(BD62)-1 -> -0.01242815 | BJ87: =(BJ62-BJ70-BJ78)/(BE62)-1 -> 0.00056735289 | BK87: =(BK62-BK70-BK78)/(BF62)-1 -> 0.024300293 | BL87: =(BL62-BL70-BL78)/(BG62)-1 -> -0.0016999436 | BM87: =(BM62-BM70-BM78)/(BH62)-1 -> -0.014148602 | BN87: =(BN62-BN70-BN78)/(BI62)-1 -> 0.01122778 | ... CF87: =(CF62-CF70-CF78)/(CA62)-1 -> 0.092895682 | CG87: =(CG62+70-CG70-CG78)/(CB62)-1 -> 0.10643498 | CH87: =(CH62+84-CH70-CH78)/(CC62)-1 -> 0.096917151 | CI87: =(CI62+71-CI70-CI78)/(CD62)-1 -> 0.099002797 | CJ87: =(CJ62+67-CJ70-CJ78)/(CE62)-1 -> 0.006271741 | CK87: =(CK62+292-CK70-CK78)/(CF62)-1 -> 0.074293067 | CL87: =(CL62-CL70-CL78)/(CG62)-1 -> -0.014486891 | CM87: =(CM62-CM70-CM78+400)/(CH62)-1 -> -0.14055343 | CN87: =(CN62-CN70-CN78)/(CI62)-1 -> -0.16457551 | CO87: =(CO62-CO70-CO78)/(CJ62)-1 -> 0.052596287 | CP87: =(CP62-CP70-CP78)/(CK62)-1 -> -0.12705255 | CQ87: =(CQ62-CQ70-CQ78)/(CL62)-1 -> -0.057955192 | CR87: =(CR62-CR70-CR78)/(CM62)-1 -> 0.095361708 | CS87: =(CS62-CS70-CS78)/(CN62)-1 -> 0.099393935 | CT87: =(CT62-CT70-CT78)/(CO62)-1 -> -0.091655102 | CU87: =(CU62-CU70-CU78)/(CP62)-1 -> 0.00249742 | ... DG87: =(DG62-DG70-DG78)/(DB62)-1 -> 0.1002457 | DH87: =(DH62-DH70-DH78)/(DC62-DC12)-1 -> 0.083965015 | DI87: =(DI62-DI70-DI78)/(DD62)-1 -> 0.10267476 | DJ87: =(DJ62-DJ70-DJ78)/(DE62-DC12)-1 -> 0.10168055 | DK87: =(DK62-DK70-DK78)/(DF62)-1 -> 0.06998187 | DL87: =(DL62-DL70-DL78)/(DG62)-1 -> 0.090445152 | DM87: =(DM62-DM70-DM78)/(DH62)-1 -> 0.13201254 | DN87: =(DN62-DN70-DN78)/(DI62)-1 -> 0.06774689 | DO87: =(DO62-DO70-DO78)/(DJ62-DH12)-1 -> 0.089816491 | DP87: =(DP62-DP70-DP78)/(DK62)-1 -> 0.078478775 | DQ87: =(DQ62-DQ70-DQ78)/(DL62)-1 -> 0.0725933 | DR87: =(DR62-DR70-DR78)/(DM62-DM12)-1 -> 0.066467123 | DS87: =(DS62-DS70-DS78)/(DN62)-1 -> 0.072148846 | DT87: =(DT62-DT70-DT78)/(DO62-DM12)-1 -> 0.072268589 | DU87: =(DU62-DU70-DU78)/(DT62)-1 -> 0.066657452 | DV87: =(DV62-DV70-DV78)/(DU62)-1 -> 0.059929888
B89: FX Impact
B90: Pratt & Whitney | X90: 0 | Y90: 0 | Z90: 0.003 | AA90: 0 | AB90: 0 | AC90: 0.0015226782 | AD90: 0 | AE90: 0 | AF90: 0 | AG90: 0 | AH90: 0 | AI90: 0 | AJ90: 0 | AK90: -0.02 | AL90: 0.0044435461 | AM90: -0.02 | AN90: 0.03 | AO90: 0.04 | AP90: 0.04 | AQ90: 0 | AR90: 0.04 | AS90: -0.01 | AT90: -0.01 | AU90: 0 | AV90: 0 | AW90: 0 | AX90: 0 | AY90: 0 | AZ90: 0 | BA90: 0 | BB90: 0 | BC90: 0 | BD90: 0 | BE90: 0 | BF90: 0 | BG90: 0 | BH90: 0 | BI90: -0.01 | BJ90: -0.01 | BK90: -0.01 | BL90: -0.01 | BM90: -0.01 | BN90: -0.01 | BO90: -0.01 | BP90: -0.01 | BQ90: -0.01 | BR90: 0 | BS90: 0 | BT90: 0.01 | BU90: 0.01 | BV90: 0 | BW90: 0.01 | BX90: 0.01 | BY90: 0.02 | BZ90: 0.01 | CA90: 0.01 | CB90: 0.01 | CC90: 0 | CD90: 0 | CE90: -0.01 | CF90: 0 | CG90: -0.01 | CH90: 0 | CI90: -0.01 | CJ90: 0 | CK90: 0
B91: Collins Aerospace | X91: 0 | Y91: 0.01 | Z91: 0.022 | AA91: 0.02 | AB91: 0 | AC91: 0.02 | AD91: 0.03 | AE91: 0.04 | AF91: 0.02 | AG91: -0.014174133 | AH91: 0.01 | AI91: -0.03 | AJ91: -0.03 | AK91: -0.01 | AL91: 0.016368749 | AM91: -0.01 | AN91: 0.01 | AO91: -0.01 | AP91: -0.01 | AQ91: -0.01 | AR91: 0 | AS91: 0 | AT91: 0.03 | AU91: 0.02 | AV91: 0 | AW91: 0.01 | AX91: 0 | AY91: -0.01 | AZ91: -0.02 | BA91: 0 | BB91: -0.01 | BC91: 0 | BD91: 0 | BE91: 0 | BF91: 0 | BG91: 0 | BH91: 0 | BI91: 0 | BJ91: 0.01 | BK91: -0.01 | BL91: 0.01 | BM91: -0.03 | BN91: -0.02 | BO91: -0.01 | BP91: -0.01 | BQ91: -0.02 | BR91: 0 | BS91: 0 | BT91: -0.01 | BU91: -0.01 | BV91: 0 | BW91: -0.01 | BX91: 0 | BY91: 0 | BZ91: 0.01 | CA91: 0 | CB91: 0.01 | CC91: 0.01 | CD91: 0 | CE91: 0 | CF91: 0 | CG91: 0 | CH91: 0 | CI91: -0.01 | CJ91: 0 | CK91: 0
B92: Total | T92: -0.019 | U92: -0.002 | V92: 0.014 | W92: 0.018
B94: Organic revenue with FX
B95: Pratt & Whitney | BG95: =BG82+BG90 -> -0.027785735 | BH95: =BH82+BH90 -> 0.04 | BI95: =BI82+BI90 -> 0 | BJ95: =BJ82+BJ90 -> 0.04 | BK95: =BK82+BK90 -> -0.026140866 | BL95: =BL82+BL90 -> -0.0048279429 | BM95: =BM82+BM90 -> -0.01 | BN95: =BN82+BN90 -> 0.01 | ... CK95: =CK82+CK90 -> 0.077589318
B96: Collins Aerospace | BG96: =BG83+BG91 -> 0.061555076 | BH96: =BH83+BH91 -> 0.06 | BI96: =BI83+BI91 -> 0.09 | BJ96: =BJ83+BJ91 -> 0.07 | BK96: =BK83+BK91 -> 0.038681542 | BL96: =BL83+BL91 -> 0.076906421 | BM96: =BM83+BM91 -> 0.04 | BN96: =BN83+BN91 -> 0 | ... CK96: =CK83+CK91 -> 0.072479295
B97: Total | BH97: =0.05+BH92 -> 0.05 | BI97: =0.04+BI92 -> 0.04 | BJ97: =0.04+BJ92 -> 0.04 | BK97: =BK87+BK92 -> 0.024300293
B99: Revenue Y/Y Growth
B100: Pratt & Whitney | D100: =D14/C14-1 -> 0.064036747 | E100: =E14/D14-1 -> -0.025647537 | F100: =F14/E14-1 -> -0.040135523 | G100: =G14/F14-1 -> 0.042492533 | H100: =H14/G14-1 -> -0.0044276599 | I100: =I14/H14-1 -> -0.021059516 | N100: =N14/I14-1 -> 0.10649385 | O100: =O14/J14-1 -> 0.038164002 | P100: =P14/K14-1 -> 0.092788462 | Q100: =Q14/L14-1 -> 0.14952381 | R100: =R14/M14-1 -> 0.20027752 | S100: =S14/N14-1 -> 0.12244898 | T100: =T14/O14-1 -> 0.2757079 | U100: =U14/P14-1 -> 0.19973603 | ... DG100: =DG14/DB14-1 -> 0.19312401 | DH100: =DH14/(DC14)-1 -> 6.8174946 | DI100: =DI14/DD14-1 -> 0.17549309 | DJ100: =DJ14/(DE14)-1 -> 0.5339965 | DK100: =DK14/DF14-1 -> 0.14095415 | DL100: =DL14/DG14-1 -> 0.12187592 | DM100: =DM14/(DH14)-1 -> 0.1635585 | DN100: =DN14/DI14-1 -> 0.125 | DO100: =DO14/(DJ14)-1 -> 0.13785808 | DP100: =DP14/DK14-1 -> 0.095 | DQ100: =DQ14/DL14-1 -> 0.092 | DR100: =DR14/(DM14)-1 -> 0.091 | DS100: =DS14/DN14-1 -> 0.094 | DT100: =DT14/(DO14)-1 -> 0.092961488 | DU100: =DU14/DT14-1 -> 0.082 | DV100: =DV14/DU14-1 -> 0.071
B101: Collins Aerospace | D101: =D26/C26-1 -> 0.031027104 | E101: =E26/D26-1 -> 0.31788309 | F101: =F26/E26-1 -> 0.31023622 | G101: =G26/F26-1 -> 0.060096154 | H101: =H26/G26-1 -> -0.34750567 | I101: =I26/H26-1 -> 0.04199247 | N101: =N26/I26-1 -> 0.089772096 | O101: =O26/J26-1 -> 0.11015119 | P101: =P26/K26-1 -> 0.20427807 | Q101: =Q26/L26-1 -> 0.098979592 | R101: =R26/M26-1 -> 0.065740741 | S101: =S26/N26-1 -> 0.11757205 | T101: =T26/O26-1 -> 0.13229572 | U101: =U26/P26-1 -> 0.13765542 | ... DT101: =DT26/DO26-1 -> 0.027779969 | DU101: =DU26/DT26-1 -> 0.058 | DV101: =DV26/DU26-1 -> 0.052
B102: Raytheon Intelligence & Space | BG102: =BG41/BB41-1 -> -0.056391549 | BH102: =BH41/BC41-1 -> -0.082178537 | BI102: =BI41/BD41-1 -> -0.052351097 | BJ102: =BJ41/BE41-1 -> -0.030471822 | BK102: =BK41/BF41-1 -> 0.041354608 | BL102: =BL41/BG41-1 -> -0.03125 | BM102: =BM41/BH41-1 -> -0.010182584 | BN102: =BN41/BI41-1 -> -0.0043003639 | ... DG102: =DG41/DB41-1 -> -1 | DJ102: =DJ41/DE41-1 -> -1
B103: Raytheon Missiles & Defense | BG103: =BG48/BB48-1 -> -0.0032746935 | BH103: =BH48/BC48-1 -> -0.054764851 | BI103: =BI48/BD48-1 -> -0.094693638 | BJ103: =BJ48/BE48-1 -> -0.10284126 | BK103: =BK48/BF48-1 -> 0.043342688 | BL103: =BL48/BG48-1 -> -0.053025672 | BM103: =BM48/BH48-1 -> -0.090016367 | BN103: =BN48/BI48-1 -> 0.011658031 | ... DG103: =DG48/DB48-1 -> -1 | DJ103: =DJ48/DE48-1 -> -1
B104: Raytheon (Defense recasted) | DA104: =DA50/CV50-1 -> 0.035890682 | DB104: =DB50/CW50-1 -> 0.092450677 | DC104: =DC50/CX50-1 -> 0.025998732 | DD104: =DD50/CY50-1 -> 0.033778712 | DE104: =DE50/CZ50-1 -> 0.046631713 | DF104: =DF50/DA50-1 -> 0.058328036 | DG104: =DG50/DB50-1 -> -0.017761194 | DH104: =DH50/DC50-1 -> -0.01328801 | ... DT104: =DT50/DO50-1 -> 0.054900334 | DU104: =DU50/DT50-1 -> 0.053 | DV104: =DV50/DU50-1 -> 0.051
B105: Total | D105: =D62/C62-1 -> 0.2777754 | E105: =E62/D62-1 -> 0.037393198 | F105: =F62/E62-1 -> -0.066729111 | G105: =G62/F62-1 -> 0.022010728 | H105: =H62/G62-1 -> -0.078629237 | I105: =I62/H62-1 -> 0.05516557 | J105: =J62/E62-1 -> -0.75042796 | K105: =K62/F62-1 -> -0.72278941 | L105: =L62/G62-1 -> -0.72919982 | M105: =M62/H62-1 -> -0.66871256 | N105: =N62/I62-1 -> 0.14064786 | O105: =O62/J62-1 -> 0.029506924 | P105: =P62/K62-1 -> 0.10699126 | Q105: =Q62/L62-1 -> 0.09578592 | ... BL105: =BL62/BG62-1 -> -0.002874808 | BM105: =BM62/(BH62-#REF!)-1 -> #REF! | BN105: =BN62/(BI62-#REF!)-1 -> #REF! | BO105: =BO62/(BJ62-#REF!)-1 -> #REF! | BP105: =BP62/(BK62-#REF!)-1 -> #REF! | BQ105: =BQ62/BL62-1 -> -0.0015007899 | BR105: =BR62/BM62-1 -> 0.059506895 | BS105: =BS62/BN62-1 -> 0.032076055 | BT105: =BT62/BO62-1 -> 0.057555719 | BU105: =BU62/BP62-1 -> 0.012898897 | BV105: =BV62/BQ62-1 -> 0.039652717 | BW105: =BW62/BR62-1 -> 0.034866293 | BX105: =BX62/BS62-1 -> 0.027334681 | ... DT105: =DT62/DO62-1 -> 0.060051086 | DU105: =DU62/DT62-1 -> 0.066657452 | DV105: =DV62/DU62-1 -> 0.059929888
B107: Revenue Mix
B108: =+B100 -> Pratt & Whitney | BB108: =BB14/SUM(BB$14,BB$26,BB$41,BB$48) -> 0.28740198 | BC108: =BC14/SUM(BC$14,BC$26,BC$41,BC$48) -> 0.26169231 | BD108: =BD14/SUM(BD$14,BD$26,BD$41,BD$48) -> 0.26753285 | BE108: =BE14/SUM(BE$14,BE$26,BE$41,BE$48) -> 0.26070219 | BF108: =BF14/SUM(BF$14,BF$26,BF$41,BF$48) -> 0.29591837 | BG108: =BG14/SUM(BG$14,BG$26,BG$41,BG$48) -> 0.27179862 | BH108: =BH14/SUM(BH$14,BH$26,BH$41,BH$48) -> 0.26249803 | BI108: =BI14/SUM(BI$14,BI$26,BI$41,BI$48) -> 0.26928555 | ... CU108: =CU14/SUM(CU$14,CU$26,CU$41,CU$48) -> 0.25920795 | CV108: =CV14/(SUM(CV14:CV26,CV50)) -> 0.28193476 | CW108: =CW14/(SUM(CW14:CW26,CW50)) -> 0.29738464 | CX108: =CX14/(SUM(CX14:CX26,CX50)) -> 0.30908882 | CY108: =CY14/(SUM(CY14:CY26,CY50)) -> 0.30478861 | CZ108: =CZ14/(SUM(CZ14:CZ26,CZ50)) -> 0.2987355 | DA108: =DA14/(SUM(DA14:DA26,DA50)) -> 0.29670392 | DB108: =DB14/(SUM(DB14:DB26,DB50)) -> 0.30381029 | DC108: =DC14/(SUM(DC14:DC26,DC50)) -> 0.065748367 | ... DL108: =DL14/(SUM(DL14:DL26,DL50)) -> 0.34290465 | DM108: =DM14/(SUM(DM14,DM26,DM50)) -> 0.36480575 | DN108: =DN14/(SUM(DN14,DN26,DN50)) -> 0.36544988 | DO108: =DO14/(SUM(DO14,DO26,DO50)) -> 0.35655255 | DP108: =DP14/(SUM(DP14,DP26,DP50)) -> 0.36642454 | DQ108: =DQ14/(SUM(DQ14,DQ26,DQ50)) -> 0.3574862 | DR108: =DR14/(SUM(DR14,DR26,DR50)) -> 0.37379142 | DS108: =DS14/(SUM(DS14,DS26,DS50)) -> 0.37290553 | DT108: =DT14/(SUM(DT14,DT26,DT50)) -> 0.36784368 | ... DV108: =DV14/(SUM(DV14,DV26,DV50)) -> 0.37792151
B109: =+B101 -> Collins Aerospace | BB109: =BB26/SUM(BB$14,BB$26,BB$41,BB$48) -> 0.17152736 | BC109: =BC26/SUM(BC$14,BC$26,BC$41,BC$48) -> 0.251 | BD109: =BD26/SUM(BD$14,BD$26,BD$41,BD$48) -> 0.24516462 | BE109: =BE26/SUM(BE$14,BE$26,BE$41,BE$48) -> 0.25500462 | BF109: =BF26/SUM(BF$14,BF$26,BF$41,BF$48) -> 0.24974671 | BG109: =BG26/SUM(BG$14,BG$26,BG$41,BG$48) -> 0.25016869 | BH109: =BH26/SUM(BH$14,BH$26,BH$41,BH$48) -> 0.27203911 | BI109: =BI26/SUM(BI$14,BI$26,BI$41,BI$48) -> 0.27258415 | ... CU109: =CU26/SUM(CU$14,CU$26,CU$41,CU$48) -> 0.3020808 | CV109: =CV26/(SUM(CV14:CV26,CV50)) -> 0.34088645 | CW109: =CW26/(SUM(CW14:CW26,CW50)) -> 0.33676462 | CX109: =CX26/(SUM(CX14:CX26,CX50)) -> 0.32850741 | CY109: =CY26/(SUM(CY14:CY26,CY50)) -> 0.33601165 | CZ109: =CZ26/(SUM(CZ14:CZ26,CZ50)) -> 0.33543355 | DA109: =DA26/(SUM(DA14:DA26,DA50)) -> 0.34719464 | DB109: =DB26/(SUM(DB14:DB26,DB50)) -> 0.34020783 | DC109: =DC26/(SUM(DC14:DC26,DC50)) -> 0.47067594 | ... DL109: =DL26/(SUM(DL14:DL26,DL50)) -> 0.34250022 | DM109: =DM26/(SUM(DM14,DM26,DM50)) -> 0.3300706 | DN109: =DN26/(SUM(DN14,DN26,DN50)) -> 0.320016 | DO109: =DO26/(SUM(DO14,DO26,DO50)) -> 0.33401478 | DP109: =DP26/(SUM(DP14,DP26,DP50)) -> 0.32539027 | DQ109: =DQ26/(SUM(DQ14,DQ26,DQ50)) -> 0.32895733 | DR109: =DR26/(SUM(DR14,DR26,DR50)) -> 0.3250318 | DS109: =DS26/(SUM(DS14,DS26,DS50)) -> 0.31729165 | DT109: =DT26/(SUM(DT14,DT26,DT50)) -> 0.32404157 | ... DV109: =DV26/(SUM(DV14,DV26,DV50)) -> 0.31975969
B110: Raytheon Intelligence & Space | BB110: =BB41/SUM(BB$14,BB$26,BB$41,BB$48) -> 0.27081318 | BC110: =BC41/SUM(BC$14,BC$26,BC$41,BC$48) -> 0.23869231 | BD110: =BD41/SUM(BD$14,BD$26,BD$41,BD$48) -> 0.23549387 | BE110: =BE41/SUM(BE$14,BE$26,BE$41,BE$48) -> 0.23498614 | BF110: =BF41/SUM(BF$14,BF$26,BF$41,BF$48) -> 0.22224635 | BG110: =BG41/SUM(BG$14,BG$26,BG$41,BG$48) -> 0.23271855 | BH110: =BH41/SUM(BH$14,BH$26,BH$41,BH$48) -> 0.22457026 | BI110: =BI41/SUM(BI$14,BI$26,BI$41,BI$48) -> 0.22662868 | ... DV110: =DV41/SUM(DV$14,DV$26,DV$41,DV$48) -> 0
B111: Raytheon Missiles & Defense | BB111: =BB48/SUM(BB$14,BB$26,BB$41,BB$48) -> 0.27025748 | BC111: =BC48/SUM(BC$14,BC$26,BC$41,BC$48) -> 0.24861538 | BD111: =BD48/SUM(BD$14,BD$26,BD$41,BD$48) -> 0.25180865 | BE111: =BE48/SUM(BE$14,BE$26,BE$41,BE$48) -> 0.24930705 | BF111: =BF48/SUM(BF$14,BF$26,BF$41,BF$48) -> 0.23208858 | BG111: =BG48/SUM(BG$14,BG$26,BG$41,BG$48) -> 0.24531414 | BH111: =BH48/SUM(BH$14,BH$26,BH$41,BH$48) -> 0.2408926 | BI111: =BI48/SUM(BI$14,BI$26,BI$41,BI$48) -> 0.23150161 | ... DV111: =DV48/SUM(DV$14,DV$26,DV$41,DV$48) -> 0
B112: Raytheon (Defense recasted) | CV112: =CV50/(SUM(CV14:CV26,CV50)) -> 0.37811255 | CW112: =CW50/(SUM(CW14:CW26,CW50)) -> 0.3670477 | CX112: =CX50/(SUM(CX14:CX26,CX50)) -> 0.36240377 | CY112: =CY50/(SUM(CY14:CY26,CY50)) -> 0.35919974 | CZ112: =CZ50/(SUM(CZ14:CZ26,CZ50)) -> 0.36634024 | DA112: =DA50/(SUM(DA14:DA26,DA50)) -> 0.3569524 | DB112: =DB50/(SUM(DB14:DB26,DB50)) -> 0.3570477 | DC112: =DC50/(SUM(DC14:DC26,DC50)) -> 0.45952854 | ... DL112: =DL50/(SUM(DL14:DL26,DL50)) -> 0.31459513 | DM112: =DM50/(SUM(DM14,DM26,DM50)) -> 0.30512365 | DN112: =DN50/(SUM(DN14,DN26,DN50)) -> 0.31453412 | DO112: =DO50/(SUM(DO14,DO26,DO50)) -> 0.30943268 | DP112: =DP50/(SUM(DP14,DP26,DP50)) -> 0.30818518 | DQ112: =DQ50/(SUM(DQ14,DQ26,DQ50)) -> 0.31355647 | DR112: =DR50/(SUM(DR14,DR26,DR50)) -> 0.30117678 | DS112: =DS50/(SUM(DS14,DS26,DS50)) -> 0.30980282 | DT112: =DT50/(SUM(DT14,DT26,DT50)) -> 0.30811475 | ... DV112: =DV50/(SUM(DV14,DV26,DV50)) -> 0.30231881
B113: Total | BB113: =SUM(BB108:BB111) -> 1 | BC113: =SUM(BC108:BC111) -> 1 | BD113: =SUM(BD108:BD111) -> 1 | BE113: =SUM(BE108:BE111) -> 1 | BF113: =SUM(BF108:BF111) -> 1 | BG113: =SUM(BG108:BG111) -> 1 | BH113: =SUM(BH108:BH111) -> 1 | BI113: =SUM(BI108:BI111) -> 1 | ... CU113: =SUM(CU108:CU111) -> 1 | CV113: =SUM(CV108,CV109,CV112) -> 1.0009338 | CW113: =SUM(CW108,CW109,CW112) -> 1.001197 | CX113: =SUM(CX108,CX109,CX112) -> 1 | CY113: =SUM(CY108,CY109,CY112) -> 1 | CZ113: =SUM(CZ108,CZ109,CZ112) -> 1.0005093 | DA113: =SUM(DA108,DA109,DA112) -> 1.000851 | DB113: =SUM(DB108,DB109,DB112) -> 1.0010658 | DC113: =SUM(DC108,DC109,DC112) -> 0.99595285 | ... DV113: =SUM(DV108,DV109,DV112) -> 1
B115: Revenue Q/Q growth
B116: =+B14 -> Pratt & Whitney | K116: =K14/J14-1 -> 0.072717896 | L116: =L14/K14-1 -> 0.0096153846 | M116: =M14/L14-1 -> 0.02952381 | O116: =O14/M14-1 -> -0.068917669 | P116: =P14/O14-1 -> 0.12916046 | Q116: =Q14/P14-1 -> 0.062032556 | R116: =R14/Q14-1 -> 0.074979287 | T116: =T14/R14-1 -> -0.010404624 | U116: =U14/T14-1 -> 0.061915888 | V116: =V14/U14-1 -> 0.016134947 | W116: =W14/V14-1 -> 0.099242151 | Y116: =Y14/W14-1 -> -0.091595535 | Z116: =Z14/Y14-1 -> 0.12323816 | AA116: =AA14/Z14-1 -> -0.023166023 | AB116: =AB14/AA14-1 -> 0.37516469 | AD116: =AD14/AB14-1 -> -0.1702994 | AE116: =AE14/AD14-1 -> 0.030311778 | AF116: =AF14/AE14-1 -> -0.041468198 | AG116: =AG14/AF14-1 -> -0.0076001169 | AI116: =AI14/AG14-1 -> -0.063328424 | AJ116: =AJ14/AI14-1 -> -0.021698113 | AK116: =AK14/AJ14-1 -> -0.025715204 | AL116: =AL14/AK14-1 -> 0.012867041 | AN116: =AN14/AL14-1 -> -0.074592834 | AO116: =AO14/AN14-1 -> 0.15417107 | AP116: =AP14/AO14-1 -> -0.01494358 | AQ116: =AQ14/AP14-1 -> 0.10990712 | AS116: =AS14/AQ14-1 -> -0.1986053 | AT116: =AT14/AR14-1 -> -0.74673367 | AU116: =AU14/AT14-1 -> -0.05952381 | AV116: =AV14/AU14-1 -> 0.12982798 | AX116: =AX14/AV14-1 -> -0.12324045 | AY116: =AY14/AX14-1 -> 0.12942333 | AZ116: =AZ14/AY14-1 -> 0.036843632 | BA116: =BA14/AZ14-1 -> 0.088696139 | BC116: =BC14/BA14-1 -> -0.12567463 | BD116: =BD14/BC14-1 -> 0.065255732 | BE116: =BE14/BD14-1 -> -0.065673289 | BF116: =BF14/BE14-1 -> 0.20761961 | BH116: =BH14/BF14-1 -> -0.18586451 | BI116: =BI14/BH14-1 -> 0.079002704 | BJ116: =BJ14/BI14-1 -> -0.0077951002 | BK116: =BK14/BJ14-1 -> 0.12878788 | BM116: =BM14/BK14-1 -> -0.17176237 | BN116: =BN14/BM14-1 -> 0.10354142 | BO116: =BO14/BN14-1 -> -0.12047865 | BP116: =BP14/BO14-1 -> 0.18707483 | BR116: =BR14/BP14-1 -> -0.06538161 | BS116: =BS14/BR14-1 -> 0.06270903 | BT116: =BT14/BS14-1 -> -0.081825334 | BU116: =BU14/BT14-1 -> 0.14024564 | BW116: =BW14/BU14-1 -> -0.058617234 | BX116: =BX14/BW14-1 -> 0.083022885 | BY116: =BY14/BX14-1 -> 0.045700246 | BZ116: =BZ14/BY14-1 -> 0.048167293 | CB116: =CB14/BZ14-1 -> -0.029589778 | CC116: =CC14/CB14-1 -> 0.094017094 | CD116: =CD14/CC14-1 -> 0.011190878 | CE116: =CE14/CD14-1 -> 0.15744414 | CG116: =CG14/CE14-1 -> -0.1307956 | CH116: =CH14/CG14-1 -> 0.069738481 | CI116: =CI14/CH14-1 -> 0.025417152 | CJ116: =CJ14/CI14-1 -> 0.068117313 | CL116: =CL14/CJ14-1 -> -0.051727192 | CM116: =CM14/CL14-1 -> -0.34858958 | CN116: =CN14/CM14-1 -> 0.0020074563 | CO116: =CO14/CN14-1 -> 0.39954207 | CQ116: =CQ14/CO14-1 -> -0.17586912 | CR116: =CR14/CQ14-1 -> 0.062034739 | CS116: =CS14/CR14-1 -> 0.10397196 | CT116: =CT14/CS14-1 -> 0.082539683 | CV116: =CV14/CT14-1 -> -0.114565 | CW116: =CW14/CV14-1 -> 0.097151689 | CX116: =CX14/CW14-1 -> 0.082712819 | CY116: =CY14/CX14-1 -> 0.050557621 | DA116: =DA14/CY14-1 -> -0.074663836 | DB116: =DB14/DA14-1 -> 0.090057361 | DC116: =DC14/DB14-1 -> -0.83757236 | DD116: =DD14/DC14-1 -> 5.9535637 | DF116: =DF14/DD14-1 -> 0.0026401615 | DG116: =DG14/DF14-1 -> 0.053593556 | DH116: =DH14/DG14-1 -> 0.06424581 | DI116: =DI14/DH14-1 -> 0.045586407 | DK116: =DK14/DI14-1 -> -0.026819923 | DL116: =DL14/DK14-1 -> 0.035976106 | DM116: =DM14/DL14-1 -> 0.10378718 | DN116: =DN14/DM14-1 -> 0.010937314 | DP116: =DP14/DN14-1 -> -0.052771392 | DQ116: =DQ14/DP14-1 -> 0.033137816 | DR116: =DR14/DQ14-1 -> 0.10277639 | DS116: =DS14/DR14-1 -> 0.01371716
B117: =+B26 -> Collins Aerospace | K117: =K26/J26-1 -> 0.0097192225 | L117: =L26/K26-1 -> 0.048128342 | M117: =M26/L26-1 -> 0.10204082 | O117: =O26/M26-1 -> -0.048148148 | AX117: =AX26/AV26-1 -> -0.022151899 | AY117: =AY26/AX26-1 -> 0.014563107 | AZ117: =AZ26/AY26-1 -> 1.1291866 | BA117: =BA26/AZ26-1 -> 0.18876404 | BC117: =BC26/BA26-1 -> 0.028040328 | BD117: =BD26/BC26-1 -> 0.017775054 | BE117: =BE26/BD26-1 -> -0.0027100271 | BF117: =BF26/BE26-1 -> 0.041968599 | BH117: =BH26/BF26-1 -> -0.00028977108 | BI117: =BI26/BH26-1 -> 0.053913043 | BJ117: =BJ26/BI26-1 -> -0.027777778 | BK117: =BK26/BJ26-1 -> 0.01669024 | BM117: =BM26/BK26-1 -> -0.01279911 | BN117: =BN26/BM26-1 -> 0.02367531 | BO117: =BO26/BN26-1 -> -0.048182819 | BP117: =BP26/BO26-1 -> 0 | BR117: =BR26/BP26-1 -> 0.013884871 | BS117: =BS26/BR26-1 -> 0.060199715 | BT117: =BT26/BS26-1 -> -0.01883746 | BU117: =BU26/BT26-1 -> -0.013165112 | BW117: =BW26/BU26-1 -> 0.0036131184 | BX117: =BX26/BW26-1 -> 0.0080310163 | BY117: =BY26/BX26-1 -> -0.00082417582 | BZ117: =BZ26/BY26-1 -> 0.045642013 | CB117: =CB26/BZ26-1 -> 0.50558769 | CC117: =CC26/CB26-1 -> 0.025324193 | CD117: =CD26/CC26-1 -> -0.0011923519 | CE117: =CE26/CD26-1 -> 0.16115967 | CG117: =CG26/CE26-1 -> -0.043436754 | CH117: =CH26/CG26-1 -> 0.0096729618 | CI117: =CI26/CH26-1 -> -0.012317518 | CJ117: =CJ26/CI26-1 -> -0.007852194 | CL117: =CL26/CJ26-1 -> -0.22579535 | CM117: =CM26/CL26-1 -> -0.0017396692 | CN117: =CN26/CM26-1 -> 0.0023794571 | CO117: =CO26/CN26-1 -> 0.407728 | CQ117: =CQ26/CO26-1 -> -0.28973225 | CR117: =CR26/CQ26-1 -> 0.0038218215 | CS117: =CS26/CR26-1 -> -0.0024287762 | CT117: =CT26/CS26-1 -> 0.23072411 | CV117: =CV26/CT26-1 -> -0.10982773 | CW117: =CW26/CV26-1 -> 0.027574872 | CX117: =CX26/CW26-1 -> 0.016172028 | CY117: =CY26/CX26-1 -> 0.089716684 | DA117: =DA26/CY26-1 -> -0.017814155 | DB117: =DB26/DA26-1 -> 0.043137255 | DC117: =DC26/DB26-1 -> 0.038377193 | DD117: =DD26/DC26-1 -> 0.074068487 | DF117: =DF26/DD26-1 -> -0.062780899 | DG117: =DG26/DF26-1 -> 0.048853589 | DH117: =DH26/DG26-1 -> 0.010858694 | DI117: =DI26/DH26-1 -> 0.065300353 | DK117: =DK26/DI26-1 -> -0.042457211 | DL117: =DL26/DK26-1 -> 0.0561175 | DM117: =DM26/DL26-1 -> -0.00013119916 | DN117: =DN26/DM26-1 -> -0.021585356 | DP117: =DP26/DN26-1 -> -0.039425747 | DQ117: =DQ26/DP26-1 -> 0.070578511 | DR117: =DR26/DQ26-1 -> 0.042086374 | DS117: =DS26/DR26-1 -> -0.0080721516
B118: Raytheon Intelligence & Space | BD118: =BD41/BC41-1 -> 0.028037383 | BE118: =BE41/BD41-1 -> -0.043260188 | BF118: =BF41/BE41-1 -> 0.006225426 | BH118: =BH41/BF41-1 -> -0.072614783 | BI118: =BI41/BH41-1 -> 0.061446629 | BJ118: =BJ41/BI41-1 -> -0.021171022 | BK118: =BK41/BJ41-1 -> 0.080770531 | BM118: =BM41/BK41-1 -> -0.11851157 | BN118: =BN41/BM41-1 -> 0.067754523 | BO118: =BO41/BN41-1 -> -0.014950166 | BP118: =BP41/BO41-1 -> 0.049915683 | BR118: =BR41/BP41-1 -> -0.054609701 | BS118: =BS41/BR41-1 -> 0.083588175 | BT118: =BT41/BS41-1 -> -0.01818752 | BU118: =BU41/BT41-1 -> -0.00031938678 | BW118: =BW41/BU41-1 -> -0.02172524 | BX118: =BX41/BW41-1 -> 0.032984977 | BY118: =BY41/BX41-1 -> -0.0072715776 | BZ118: =BZ41/BY41-1 -> 0.032484076 | CB118: =CB41/BZ41-1 -> -0.028377545 | CC118: =CC41/CB41-1 -> 0.045079365 | CD118: =CD41/CC41-1 -> 0.044046173 | CE118: =CE41/CD41-1 -> 0.044806517 | CG118: =CG41/CE41-1 -> -0.054023949 | CH118: =CH41/CG41-1 -> 0.047100383 | CI118: =CI41/CH41-1 -> 0.057351701 | CJ118: =CJ41/CI41-1 -> -0.0082424887 | CL118: =CL41/CJ41-1 -> -0.014477212 | CM118: =CM41/CL41-1 -> -0.020402612 | CN118: =CN41/CM41-1 -> 0.041099695 | CO118: =CO41/CN41-1 -> 0.049079755 | CQ118: =CQ41/CO41-1 -> -0.042715484 | CR118: =CR41/CQ41-1 -> 0.01062417 | CS118: =CS41/CR41-1 -> -0.017082786 | CT118: =CT41/CS41-1 -> 0.034759358 | CV118: =CV41/CT41-1 -> -0.077002584 | CW118: =CW41/CV41-1 -> -0.00055991041 | CX118: =CX41/CW41-1 -> 0.015686275 | CY118: =CY41/CX41-1 -> -0.022614451 | DA118: =DA41/CY41-1 -> 0.0059255079 | DB118: =DB41/DA41-1 -> 0.025245442 | DC118: =DC41/DB41-1 -> -1
B119: Raytheon Missiles & Defense | BD119: =BD48/BC48-1 -> 0.055383663 | BE119: =BE48/BD48-1 -> -0.050718264 | BF119: =BF48/BE48-1 -> -0.009573811 | BH119: =BH48/BF48-1 -> -0.047396321 | BI119: =BI48/BH48-1 -> 0.010801964 | BJ119: =BJ48/BI48-1 -> -0.059261658 | BK119: =BK48/BJ48-1 -> 0.15180723 | BM119: =BM48/BK48-1 -> -0.1691572 | BN119: =BN48/BM48-1 -> 0.12374101 | BO119: =BO48/BN48-1 -> -0.019846351 | BP119: =BP48/BO48-1 -> 0.12246897 | BR119: =BR48/BP48-1 -> -0.11056154 | BS119: =BS48/BR48-1 -> -0.00065423618 | BT119: =BT48/BS48-1 -> 0.025859247 | BU119: =BU48/BT48-1 -> 0.053286535 | BW119: =BW48/BU48-1 -> -0.04453196 | BX119: =BX48/BW48-1 -> 0.06626506 | BY119: =BY48/BX48-1 -> -0.0080285459 | BZ119: =BZ48/BY48-1 -> 0.1205036 | CB119: =CB48/BZ48-1 -> -0.10727662 | CC119: =CC48/CB48-1 -> 0.068324843 | CD119: =CD48/CC48-1 -> 0.0028050491 | CE119: =CE48/CD48-1 -> 0.11916084 | CG119: =CG48/CE48-1 -> -0.12046988 | CH119: =CH48/CG48-1 -> 0.080988917 | CI119: =CI48/CH48-1 -> 0.020504732 | CJ119: =CJ48/CI48-1 -> 0.10484286
B120: Raytheon (Defense recasted) | DF120: =DF50/DD50-1 -> -0.032965437 | DG120: =+DG50/DF50-1 -> -0.01171347 | DH120: =+DH50/DG50-1 -> -0.029630755 | DI120: =+DI50/DH50-1 -> 0.12073285 | DK120: =DK50/DI50-1 -> -0.11415398 | DL120: =+DL50/DK50-1 -> 0.10425868 | DM120: =+DM50/DL50-1 -> 0.0062848165 | DN120: =+DN50/DM50-1 -> 0.040279347 | DP120: =DP50/DN50-1 -> -0.074360111 | DQ120: =+DQ50/DP50-1 -> 0.077426221 | DR120: =+DR50/DQ50-1 -> 0.013031937 | DS120: =+DS50/DR50-1 -> 0.045228345
B121: Total Sales | K121: =K62/J62-1 -> 0.036624822 | L121: =L62/K62-1 -> -0.0016229713 | M121: =M62/L62-1 -> 0.12717269 | O121: =IF(ISERROR(O62/M62-1),"",(O62/M62-1)) -> -0.11748391 | P121: =P62/O62-1 -> 0.11464488 | Q121: =Q62/P62-1 -> -0.011728882 | R121: =R62/Q62-1 -> 0.1291795 | T121: =IF(ISERROR(T62/R62-1),"",(T62/R62-1)) -> -0.10146539 | U121: =U62/T62-1 -> 0.09785176 | V121: =V62/U62-1 -> -0.0088105727 | W121: =W62/V62-1 -> -0.16847545 | Y121: =IF(ISERROR(Y62/W62-1),"",(Y62/W62-1)) -> 0.13064015 | Z121: =Z62/Y62-1 -> 0.084322779 | AA121: =AA62/Z62-1 -> -0.0098347359 | AB121: =AB62/AA62-1 -> 0.14888388 | AD121: =IF(ISERROR(AD62/AB62-1),"",(AD62/AB62-1)) -> -0.088680927 | AE121: =AE62/AD62-1 -> 0.076674817 | AF121: =AF62/AE62-1 -> -0.025797075 | AG121: =AG62/AF62-1 -> 0.010815851 | AI121: =IF(ISERROR(AI62/AG62-1),"",(AI62/AG62-1)) -> -0.044276358 | AJ121: =AJ62/AI62-1 -> 0.018241482 | AK121: =AK62/AJ62-1 -> 0.0028436019 | AL121: =AL62/AK62-1 -> 0.03657845 | AN121: =IF(ISERROR(AN62/AL62-1),"",(AN62/AL62-1)) -> -0.076593417 | AO121: =AO62/AN62-1 -> 0.04048583 | AP121: =AP62/AO62-1 -> 0.029135428 | AQ121: =AQ62/AP62-1 -> 0.093876798 | AS121: =IF(ISERROR(AS62/AQ62-1),"",(AS62/AQ62-1)) -> -0.15798348 | AT121: =IF(ISERROR(AT62/AR62-1),"",(AT62/AR62-1)) -> -0.75621397 | AU121: =AU62/AT62-1 -> -0.025158422 | AV121: =AV62/AU62-1 -> 0.075676725 | AX121: =IF(ISERROR(AX62/AV62-1),"",(AX62/AV62-1)) -> -0.086948679 | AY121: =AY62/AX62-1 -> 0.042477526 | AZ121: =AZ62/AY62-1 -> 0.1472567 | BA121: =BA62/AZ62-1 -> 0.10010738 | BC121: =BC62/BB62-1 -> -0.73199091 | BD121: =BD62/BC62-1 -> 0.040071094 | BE121: =BE62/BD62-1 -> -0.041634302 | BF121: =BF62/BE62-1 -> 0.069541255 | BH121: =BH62/BF62-1 -> -0.084116399 | BI121: =BI62/BH62-1 -> 0.051960947 | BJ121: =BJ62/BI62-1 -> -0.029023124 | BK121: =BK62/BJ62-1 -> 0.095585257 | BM121: =BM62/BK62-1 -> -0.11534196 | BN121: =BN62/BM62-1 -> 0.081320518 | BO121: =BO62/BN62-1 -> -0.053253981 | BP121: =BP62/BO62-1 -> 0.094946526 | BR121: =BR62/BP62-1 -> -0.05480167 | BS121: =BS62/BR62-1 -> 0.053324919 | BT121: =BT62/BS62-1 -> -0.029880926 | BU121: =BU62/BT62-1 -> 0.048710823 | BW121: =BW62/BU62-1 -> -0.03430254 | BX121: =BX62/BW62-1 -> 0.045658968 | BY121: =BY62/BX62-1 -> 0.01231958 | BZ121: =BZ62/BY62-1 -> 0.058039893 | CB121: =CB62/BZ62-1 -> 0.085942285 | CC121: =CC62/CB62-1 -> 0.053585698 | CD121: =CD62/CC62-1 -> 0.015585265 | CE121: =CE62/CD62-1 -> 0.13237469 | CG121: =CG62/CE62-1 -> -0.088489739 | CH121: =CH62/CG62-1 -> 0.045057315 | CI121: =CI62/CH62-1 -> 0.018245004 | CJ121: =CJ62/CI62-1 -> 0.037062713 | CL121: =CL62/CJ62-1 -> -0.10568664 | CM121: =CM62/CL62-1 -> -0.11408561 | CN121: =CN62/CM62-1 -> 0.010923982 | CO121: =CO62/CN62-1 -> 0.30649697 | CQ121: =CQ62/CO62-1 -> -0.20079116 | CR121: =CR62/CQ62-1 -> 0.031547909 | CS121: =CS62/CR62-1 -> 0.016520851 | CT121: =CT62/CS62-1 -> 0.079002568 | CV121: =CV62/CT62-1 -> -0.14593176 | CW121: =CW62/CV62-1 -> 0.038050395 | CX121: =CX62/CW62-1 -> 0.039046218 | CY121: =CY62/CX62-1 -> 0.067370657 | DA121: =DA62/CY62-1 -> -0.048582325 | DB121: =DB62/DA62-1 -> 0.063959568 | DC121: =DC62/DB62-1 -> -0.26486486 | DD121: =DD62/DC62-1 -> 0.4800208 | DF121: =DF62/DD62-1 -> -0.031213931 | DG121: =DG62/DF62-1 -> 0.025174825 | DH121: =DH62/DG62-1 -> 0.015057349 | DI121: =DI62/DH62-1 -> 0.076360197 | DK121: =DK62/DI62-1 -> -0.060907367 | DL121: =DL62/DK62-1 -> 0.062789323 | DM121: =DM62/DL62-1 -> 0.041564339 | DN121: =DN62/DM62-1 -> 0.0054449239 | DP121: =DP62/DN62-1 -> -0.052578781 | DQ121: =DQ62/DP62-1 -> 0.058286977 | DR121: =DR62/DQ62-1 -> 0.054033745 | DS121: =DS62/DR62-1 -> 0.014504571
B123: Seasonality
B124: =+B116 -> Pratt & Whitney | J124: =J14/N14 -> 0.23415046 | K124: =K14/N14 -> 0.25117739 | L124: =L14/N14 -> 0.25359256 | M124: =M14/N14 -> 0.26107958 | O124: =O14/S14 -> 0.21656805 | P124: =P14/S14 -> 0.24454008 | Q124: =Q14/S14 -> 0.25970952 | R124: =R14/S14 -> 0.27918236 | T124: =T14/X14 -> 0.23110151 | U124: =U14/X14 -> 0.24541037 | V124: =V14/X14 -> 0.24937005 | W124: =W14/X14 -> 0.27411807 | Y124: =Y14/AC14 -> 0.21144735 | Z124: =Z14/AC14 -> 0.23750573 | AA124: =AA14/AC14 -> 0.23200367 | AB124: =AB14/AC14 -> 0.31904325 | AD124: =AD14/AH14 -> 0.25012636 | AE124: =AE14/AH14 -> 0.25770814 | AF124: =AF14/AH14 -> 0.24702145 | AG124: =AG14/AH14 -> 0.24514405 | AI124: =AI14/AM14 -> 0.25661717 | AJ124: =AJ14/AM14 -> 0.25104906 | AK124: =AK14/AM14 -> 0.24459329 | AL124: =AL14/AM14 -> 0.24774048 | AN124: =AN14/AR14 -> 0.21963664 | AO124: =AO14/AR14 -> 0.25349826 | AP124: =AP14/AR14 -> 0.24971009 | AQ124: =AQ14/AR14 -> 0.27715501 | AS124: =AS14/AW14 -> 0.2260247 | AT124: =AT14/AW14 -> 0.25772953 | AU124: =AU14/AW14 -> 0.24238848 | AV124: =AV14/AW14 -> 0.27385729 | AX124: =AX14/BB14 -> 0.21856202 | AY124: =AY14/BB14 -> 0.24684904 | AZ124: =AZ14/BB14 -> 0.25594386 | BA124: =BA14/BB14 -> 0.27864509 | BC124: =BC14/BG14 -> 0.23460451 | BD124: =BD14/BG14 -> 0.2499138 | BE124: =BE14/BG14 -> 0.23350114 | BF124: =BF14/BG14 -> 0.28198055 | BH124: =BH14/BL14 -> 0.22945961 | BI124: =BI14/BL14 -> 0.24758754 | BJ124: =BJ14/BL14 -> 0.24565757 | BK124: =BK14/BL14 -> 0.27729529 | BM124: =BM14/BQ14 -> 0.23661412 | BN124: =BN14/BQ14 -> 0.26111348 | BO124: =BO14/BQ14 -> 0.22965488 | BP124: =BP14/BQ14 -> 0.27261753 | BR124: =BR14/BV14 -> 0.24090238 | BS124: =BS14/BV14 -> 0.25600913 | BT124: =BT14/BV14 -> 0.2350611 | BU124: =BU14/BV14 -> 0.26802739 | BW124: =BW14/CA14 -> 0.22713811 | BX124: =BX14/CA14 -> 0.24599577 | BY124: =BY14/CA14 -> 0.25723784 | BZ124: =BZ14/CA14 -> 0.26962829 | CB124: =CB14/CF14 -> 0.22317884 | CC124: =CC14/CF14 -> 0.24416147 | CD124: =CD14/CF14 -> 0.24689385 | CE124: =CE14/CF14 -> 0.28576584 | CG124: =CG14/CK14 -> 0.23050426 | CH124: =CH14/CK14 -> 0.24657927 | CI124: =CI14/CK14 -> 0.25284662 | CJ124: =CJ14/CK14 -> 0.27006985 | CL124: =CL14/CP14 -> 0.31078727 | CM124: =CM14/CP14 -> 0.20245007 | CN124: =CN14/CP14 -> 0.20285648 | CO124: =CO14/CP14 -> 0.28390618 | CQ124: =CQ14/CU14 -> 0.22203857 | CR124: =CR14/CU14 -> 0.23581267 | CS124: =CS14/CU14 -> 0.26033058 | CT124: =CT14/CU14 -> 0.28181818 | CV124: =CV14/CZ14 -> 0.22060399 | CW124: =CW14/CZ14 -> 0.24203604 | CX124: =CX14/CZ14 -> 0.26205553 | CY124: =CY14/CZ14 -> 0.27530443 | DA124: =DA14/DE14 -> 0.28585483 | DB124: =DB14/DE14 -> 0.31159816 | DC124: =DC14/DE14 -> 0.050612156 | DD124: =DD14/DE14 -> 0.35193485 | DF124: =DF14/DJ14 -> 0.23002922 | DG124: =DG14/DJ14 -> 0.2423573 | DH124: =DH14/DJ14 -> 0.25792774 | DI124: =DI14/DJ14 -> 0.26968574 | DK124: =DK14/DO14 -> 0.23065512 | DL124: =DL14/DO14 -> 0.23895319 | DM124: =DM14/DO14 -> 0.26375347 | DN124: =DN14/DO14 -> 0.26663822 | DP124: =DP14/DT14 -> 0.23108532 | DQ124: =DQ14/DT14 -> 0.23874298 | DR124: =DR14/DT14 -> 0.26328012 | DS124: =DS14/DT14 -> 0.26689158
B125: =+B117 -> Collins Aerospace | J125: =J26/N26 -> 0.23616424 | K125: =K26/N26 -> 0.23845958 | L125: =L26/N26 -> 0.24993624 | M125: =M26/N26 -> 0.27543994 | O125: =O26/S26 -> 0.23459607 | P125: =P26/S26 -> 0.25696029 | Q125: =Q26/S26 -> 0.24577818 | R125: =R26/S26 -> 0.26266545 | T125: =T26/X26 -> 0.23303303 | U125: =U26/X26 -> 0.25645646 | V125: =V26/X26 -> 0.25085085 | W125: =W26/X26 -> 0.25965966 | Y125: =Y26/AC26 -> 0.23296664 | Z125: =Z26/AC26 -> 0.24911285 | AA125: =AA26/AC26 -> 0.25319375 | AB125: =AB26/AC26 -> 0.26472676 | AD125: =AD26/AH26 -> 0.23845275 | AE125: =AE26/AH26 -> 0.26929982 | AF125: =AF26/AH26 -> 0.2500408 | AG125: =AG26/AH26 -> 0.24220663 | AI125: =AI26/AM$26 -> 0.24838129 | AJ125: =AJ26/AM$26 -> 0.25215827 | AK125: =AK26/AM$26 -> 0.25179856 | AL125: =AM26/$AH26 -> 0.90745879 | AN125: =AN26/AR26 -> 0.23644793 | AO125: =AO26/AR26 -> 0.24589872 | AP125: =AP26/AR26 -> 0.2532097 | AQ125: =AQ26/AR26 -> 0.26444365 | AS125: =AS26/AW26 -> 0.23907563 | AT125: =AT26/AW26 -> 0.2460084 | AU125: =AU26/AW26 -> 0.24936975 | AV125: =AV26/AW26 -> 0.26554622 | AX125: =AX26/BB26 -> 0.14830814 | AY125: =AY26/BB26 -> 0.15046796 | AZ125: =AZ26/BB26 -> 0.32037437 | BA125: =BA26/BB26 -> 0.38084953 | BC125: =BC26/BG26 -> 0.24447441 | BD125: =BD26/BG26 -> 0.24881996 | BE125: =BE26/BG26 -> 0.24814565 | BF125: =BF26/BG26 -> 0.25855998 | BH125: =BH26/BL26 -> 0.24270137 | BI125: =BI26/BL26 -> 0.25578614 | BJ125: =BJ26/BL26 -> 0.24868097 | BK125: =BK26/BL26 -> 0.25283152 | BM125: =BM26/BQ26 -> 0.25173833 | BN125: =BN26/BQ26 -> 0.25769831 | BO125: =BO26/BQ26 -> 0.24528168 | BP125: =BP26/BQ26 -> 0.24528168 | BR125: =BR26/BV26 -> 0.24230902 | BS125: =BS26/BV26 -> 0.25689596 | BT125: =BT26/BV26 -> 0.25205669 | BU125: =BU26/BV26 -> 0.24873833 | BW125: =BW26/CA26 -> 0.24579675 | BX125: =BX26/CA26 -> 0.24777074 | BY125: =BY26/CA26 -> 0.24756654 | BZ125: =BZ26/CA26 -> 0.25886597 | CB125: =CB26/CF26 -> 0.23592855 | CC125: =CC26/CF26 -> 0.24190325 | CD125: =CD26/CF26 -> 0.24161482 | CE125: =CE26/CF26 -> 0.28055338 | CG125: =CG26/CK26 -> 0.25023052 | CH125: =CH26/CK26 -> 0.25265099 | CI125: =CI26/CK26 -> 0.24953896 | CJ125: =CJ26/CK26 -> 0.24757953 | CL125: =CL26/CP26 -> 0.22688502 | CM125: =CM26/CP26 -> 0.22649032 | CN125: =CN26/CP26 -> 0.22702924 | CO125: =CO26/CP26 -> 0.31959542 | CQ125: =CQ26/CU26 -> 0.23598081 | CR125: =CR26/CU26 -> 0.23688269 | CS125: =CS26/CU26 -> 0.23630735 | CT125: =CT26/CU26 -> 0.29082915 | CV125: =CV26/CZ26 -> 0.23754989 | CW125: =CW26/CZ26 -> 0.24410029 | CX125: =CX26/CZ26 -> 0.24804789 | CY125: =CY26/CZ26 -> 0.27030193 | DA125: =DA26/DE26 -> 0.23311622 | DB125: =DB26/DE26 -> 0.24317221 | DC125: =DC26/DE26 -> 0.25250448 | DD125: =DD26/DE26 -> 0.2712071 | DF125: =DF26/DJ26 -> 0.23592844 | DG125: =DG26/DJ26 -> 0.24745439 | DH125: =DH26/DJ26 -> 0.25014142 | DI125: =DI26/DJ26 -> 0.26647575 | DK125: =DK26/DO26 -> 0.24123813 | DL125: =DL26/DO26 -> 0.25477581 | DM125: =DM26/DO26 -> 0.25474238 | DN125: =DN26/DO26 -> 0.24924368 | DP125: =DP26/DT26 -> 0.23294583 | DQ125: =DQ26/DT26 -> 0.2493868 | DR125: =DR26/DT26 -> 0.25988259 | DS125: =DS26/DT26 -> 0.25778478
B126: Raytheon Intelligence & Space | BC126: =BC41/BG41 -> 0.24991946 | BD126: =BD41/BG41 -> 0.25692655 | BE126: =BE41/BG41 -> 0.24581186 | BF126: =BF41/BG41 -> 0.24734214 | BH126: =BH41/BL41 -> 0.23678084 | BI126: =BI41/BL41 -> 0.25133023 | BJ126: =BJ41/BL41 -> 0.24600931 | BK126: =BK41/BL41 -> 0.26587961 | BM126: =BM41/BQ41 -> 0.23675149 | BN126: =BN41/BQ41 -> 0.25279248 | BO126: =BO41/BQ41 -> 0.24901319 | BP126: =BP41/BQ41 -> 0.26144285 | BR126: =BR41/BV41 -> 0.23747277 | BS126: =BS41/BV41 -> 0.25732268 | BT126: =BT41/BV41 -> 0.25264262 | BU126: =BU41/BV41 -> 0.25256193 | BW126: =BW41/CA41 -> 0.24288094 | BX126: =BX41/CA41 -> 0.25089236 | BY126: =BY41/CA41 -> 0.24906798 | BZ126: =BZ41/CA41 -> 0.25715872 | CB126: =CB41/CF41 -> 0.23385301 | CC126: =CC41/CF41 -> 0.24439495 | CD126: =CD41/CF41 -> 0.25515961 | CE126: =CE41/CF41 -> 0.26659243 | CG126: =CG41/CK41 -> 0.23516788 | CH126: =CH41/CK41 -> 0.24624438 | CI126: =CI41/CK41 -> 0.26036691 | CJ126: =CJ41/CK41 -> 0.25822084 | CL126: =CL41/CP41 -> 0.24573835 | CM126: =CM41/CP41 -> 0.24072465 | CN126: =CN41/CP41 -> 0.25061836 | CO126: =CO41/CP41 -> 0.26291864 | CQ126: =CQ41/CU41 -> 0.24802372 | CR126: =CR41/CU41 -> 0.25065876 | CS126: =CS41/CU41 -> 0.24637681 | CT126: =CT41/CU41 -> 0.25494071 | CV126: =CV41/CZ41 -> 0.24958077 | CW126: =CW41/CZ41 -> 0.24944103 | CX126: =CX41/CZ41 -> 0.25335383 | CY126: =CY41/CZ41 -> 0.24762437 | DA126: =DA41/DE41 -> 0.49376731 | DB126: =DB41/DE41 -> 0.50623269 | DC126: =DC41/DE41 -> 0 | DD126: =DD41/DE41 -> 0
B127: Raytheon Missiles & Defense | BC127: =BC48/BG48 -> 0.24694377 | BD127: =BD48/BG48 -> 0.26062042 | BE127: =BE48/BG48 -> 0.2474022 | BF127: =BF48/BG48 -> 0.24503362 | BH127: =BH48/BL48 -> 0.24649024 | BI127: =BI48/BL48 -> 0.24915282 | BJ127: =BJ48/BL48 -> 0.23438761 | BK127: =BK48/BL48 -> 0.26996934 | BM127: =BM48/BQ48 -> 0.22413932 | BN127: =BN48/BQ48 -> 0.25187455 | BO127: =BO48/BQ48 -> 0.24687576 | BP127: =BP48/BQ48 -> 0.27711038 | BR127: =BR48/BV48 -> 0.2436439 | BS127: =BS48/BV48 -> 0.2434845 | BT127: =BT48/BV48 -> 0.24978082 | BU127: =BU48/BV48 -> 0.26309078 | BW127: =BW48/CA48 -> 0.23206534 | BX127: =BX48/CA48 -> 0.24744316 | BY127: =BY48/CA48 -> 0.24545655 | BZ127: =BZ48/CA48 -> 0.27503495 | CB127: =CB48/CF48 -> 0.23048764 | CC127: =CC48/CF48 -> 0.24623567 | CD127: =CD48/CF48 -> 0.24692637 | CE127: =CE48/CF48 -> 0.27635032 | CG127: =CG48/CK48 -> 0.22712018 | CH127: =CH48/CK48 -> 0.24551439 | CI127: =CI48/CK48 -> 0.2505486 | CJ127: =CJ48/CK48 -> 0.27681683 | CL127: =CL48/CP48 -> 0.24382455 | CM127: =CM48/CP48 -> 0.24193443 | CN127: =CN48/CP48 -> 0.24154337 | CO127: =CO48/CP48 -> 0.27269765 | CQ127: =CQ48/CU48 -> 0.2440955 | CR127: =CR48/CU48 -> 0.25645151 | CS127: =CS48/CU48 -> 0.25111011 | CT127: =CT48/CU48 -> 0.24834288 | CV127: =CV48/CZ48 -> 0.23730068 | CW127: =CW48/CZ48 -> 0.2393864 | CX127: =CX48/CZ48 -> 0.24746014 | CY127: =CY48/CZ48 -> 0.27585279 | DA127: =DA48/DE48 -> 0.4785556 | DB127: =DB48/DE48 -> 0.5214444 | DC127: =DC48/DE48 -> 0 | DD127: =DD48/DE48 -> 0
B128: Raytheon (Defense recasted) | DF128: =+DF50/DJ50 -> 0.24862786 | DG128: =+DG50/DJ50 -> 0.24571557 | DH128: =+DH50/DJ50 -> 0.23843483 | DI128: =+DI50/DJ50 -> 0.26722175 | DK128: =+DK50/DO50 -> 0.22875891 | DL128: =+DL50/DO50 -> 0.25260901 | DM128: =+DM50/DO50 -> 0.25419661 | DN128: =+DN50/DO50 -> 0.26443548 | DP128: =+DP50/DT50 -> 0.23203332 | DQ128: =+DQ50/DT50 -> 0.24999879 | DR128: =+DR50/DT50 -> 0.25325675 | DS128: =+DS50/DT50 -> 0.26471114
B129: Total Sales | J129: =J62/N62 -> 0.23595334 | K129: =K62/N62 -> 0.24459509 | L129: =L62/N62 -> 0.24419812 | M129: =M62/N62 -> 0.27525345 | O129: =O62/S62 -> 0.22421082 | P129: =P62/S62 -> 0.24991545 | Q129: =Q62/S62 -> 0.24698422 | R129: =R62/S62 -> 0.27888952 | T129: =T62/X62 -> 0.24444628 | U129: =U62/X62 -> 0.26836578 | V129: =V62/X62 -> 0.26600132 | W129: =W62/X62 -> 0.22118663 | Y129: =Y62/AC62 -> 0.22771311 | Z129: =Z62/AC62 -> 0.24691451 | AA129: =AA62/AC62 -> 0.24448617 | AB129: =AB62/AC62 -> 0.28088622 | AD129: =AD62/AH62 -> 0.23890187 | AE129: =AE62/AH62 -> 0.25721963 | AF129: =AF62/AH62 -> 0.25058411 | AG129: =AG62/AH62 -> 0.25329439 | AI129: =AI62/AM62 -> 0.24402939 | AJ129: =AJ62/AM62 -> 0.24848085 | AK129: =AK62/AM62 -> 0.24918743 | AL129: =AL62/AM62 -> 0.25830232 | AN129: =AN62/AR62 -> 0.23350242 | AO129: =AO62/AR62 -> 0.24295596 | AP129: =AP62/AR62 -> 0.25003459 | AQ129: =AQ62/AR62 -> 0.27350703 | AS129: =AS62/AW62 -> 0.23806459 | AT129: =AT62/AX62 -> 1.0444532 | AU129: =AU62/AW62 -> 0.24566798 | AV129: =AV62/AW62 -> 0.26425933 | AX129: =AX62/BB62 -> 0.21918372 | AY129: =AY62/BB62 -> 0.2284941 | AZ129: =AZ62/BB62 -> 0.26214139 | BA129: =BA62/BB62 -> 0.28838367 | BC129: =BC62/BG62 -> 0.24372859 | BD129: =BD62/BG62 -> 0.25349506 | BE129: =BE62/BG62 -> 0.24294097 | BF129: =BF62/BG62 -> 0.25983539 | BH129: =BH62/BL62 -> 0.23866509 | BI129: =BI62/BL62 -> 0.25106635 | BJ129: =BJ62/BL62 -> 0.24377962 | BK129: =BK62/BL62 -> 0.26708136 | BM129: =BM62/BQ62 -> 0.2366308 | BN129: =BN62/BQ62 -> 0.25587374 | BO129: =BO62/BQ62 -> 0.24224745 | BP129: =BP62/BQ62 -> 0.265248 | BR129: =BR62/BV62 -> 0.24114973 | BS129: =BS62/BV62 -> 0.25400902 | BT129: =BT62/BV62 -> 0.24641899 | BU129: =BU62/BV62 -> 0.25842226 | BW129: =BW62/CA62 -> 0.23673241 | BX129: =BX62/CA62 -> 0.24754137 | BY129: =BY62/CA62 -> 0.25059097 | BZ129: =BZ62/CA62 -> 0.26513525 | CB129: =CB62/CF62 -> 0.23066776 | CC129: =CC62/CF62 -> 0.24302825 | CD129: =CD62/CF62 -> 0.24681591 | CE129: =CE62/CF62 -> 0.27948809 | CG129: =CG62/CK62 -> 0.23737489 | CH129: =CH62/CK62 -> 0.24807037 | CI129: =CI62/CK62 -> 0.25259641 | CJ129: =CJ62/CK62 -> 0.26195832 | CL129: =CL62/CP62 -> 0.26922155 | CM129: =CM62/CP62 -> 0.23850724 | CN129: =CN62/CP62 -> 0.24111269 | CO129: =CO62/CP62 -> 0.315013 | CQ129: =CQ62/CU62 -> 0.25259011 | CR129: =CR62/CU62 -> 0.2605588 | CS129: =CS62/CU62 -> 0.26486345 | CT129: =CT62/CU62 -> 0.28578835 | CV129: =CV62/CZ62 -> 0.23430838 | CW129: =CW62/CZ62 -> 0.2432239 | CX129: =CX62/CZ62 -> 0.25272088 | CY129: =CY62/CZ62 -> 0.26974685 | DA129: =DA62/DE62 -> 0.24976785 | DB129: =DB62/DE62 -> 0.26574289 | DC129: =DC62/DE62 -> 0.19535694 | DD129: =DD62/DE62 -> 0.28913233 | DF129: =DF62/DJ62 -> 0.23889961 | DG129: =DG62/DJ62 -> 0.24491387 | DH129: =DH62/DJ62 -> 0.24860162 | DI129: =DI62/DJ62 -> 0.26758489 | DK129: =DK62/DO62 -> 0.23349518 | DL129: =DL62/DO62 -> 0.24815619 | DM129: =DM62/DO62 -> 0.25847064 | DN129: =DN62/DO62 -> 0.25987799 | DP129: =DP62/DT62 -> 0.23226609 | DQ129: =DQ62/DT62 -> 0.24580418 | DR129: =DR62/DT62 -> 0.2590859 | DS129: =DS62/DT62 -> 0.26284383
B131: Operating Income
B132: Pratt & Whitney | C132: =+Data!C164 -> 816 | D132: =+Data!D164 -> 1024 | E132: =+Data!E164 -> 634 | F132: =+Data!F164 -> 1200 | G132: =+Data!G164 -> 1308 | H132: =+Data!H164 -> 1282 | I132: =+Data!I164 -> 1063 | J132: =+Data!J164 -> 206 | ... M132: =+Data!M164 -> 280 | N132: =SUM(J132:M132) -> 1083 | O132: =+Data!O164 -> 340 | P132: =+Data!P164 -> 368 | Q132: =+Data!Q164 -> 379 | R132: =+Data!R164 -> 362 | S132: =SUM(O132:R132) -> 1449 | T132: =+Data!T164 -> 430 | U132: =+Data!U164 -> 535 | V132: =+Data!V164 -> 443 | W132: =+Data!W164 -> 409 | X132: =SUM(T132:W132) -> 1817 | Y132: =+Data!Y164 -> 490 | Z132: =+Data!Z164 -> 522 | AA132: =+Data!AA164 -> 503 | AB132: =+Data!AB164 -> 496 | AC132: =SUM(Y132:AB132) -> 2011 | AD132: =+Data!AD164 -> 526 | AE132: =+Data!AE164 -> 546 | AF132: =+Data!AF164 -> 530 | AG132: =+Data!AG164 -> 520 | AH132: =SUM(AD132:AG132) -> 2122 | AI132: =+Data!AI164 -> 436 | AJ132: =+Data!AJ164 -> 467 | AK132: =+Data!AK164 -> 444 | AL132: =+Data!AL164 -> 488 | AM132: =SUM(AI132:AL132) -> 1835 | AN132: =+Data!AN164 -> 436 | AO132: =+Data!AO164 -> 522 | AP132: =+Data!AP164 -> 547 | AQ132: =+Data!AQ164 -> 482 | AR132: =SUM(AN132:AQ132) -> 1987 | AS132: =+Data!AS164 -> 428 | AT132: =+Data!AT164 -> 424 | AU132: =+Data!AU164 -> 496 | AV132: =+Data!AV164 -> 519 | AW132: =SUM(AS132:AV132) -> 1867 | AX132: =+Data!AX164 -> 389.34229 | AY132: =+Data!AY164 -> 427.50878 | AZ132: =+Data!AZ164 -> 408.84285 | BA132: =+Data!BA164 -> 358.34895 | BB132: =SUM(AX132:BA132) -> 1584.0429 | BC132: =+Data!BC164 -> 418.55994 | BD132: =+Data!BD164 -> 574.73197 | BE132: =+Data!BE164 -> 448.72975 | BF132: =+Data!BF164 -> 467.07048 | BG132: =SUM(BC132:BF132) -> 1909.0921 | BH132: =+Data!BH164 -> 403.45661 | BI132: =+Data!BI164 -> 478.25572 | BJ132: =+Data!BJ164 -> 638.30123 | BK132: =+Data!BK164 -> 545.97492 | BL132: =SUM(BH132:BK132) -> 2065.9885 | BM132: =+Data!BM164 -> 434.40655 | BN132: =+Data!BN164 -> 489.58746 | BO132: =+Data!BO164 -> 429.57858 | BP132: =+Data!BP164 -> -515.01965 | BQ132: =SUM(BM132:BP132) -> 838.55293 | BR132: =+Data!BR164 -> 426.20491 | BS132: =+Data!BS164 -> 405.86751 | BT132: =+Data!BT164 -> 357.70324 | BU132: =+Data!BU164 -> 348.78981 | BV132: =SUM(BR132:BU132) -> 1538.5655 | BW132: =+Data!BW164 -> 365.51049 | BX132: =+Data!BX164 -> 380.6692 | BY132: =+Data!BY164 -> 212.49717 | BZ132: =+Data!BZ164 -> 386.52824 | CA132: =SUM(BW132:BZ132) -> 1345.2051 | CB132: =+Data!CB164 -> 456.71274 | CC132: =+Data!CC164 -> 427.72717 | CD132: =+Data!CD164 -> 141.39198 | CE132: =+Data!CE164 -> 390.3831 | CF132: =SUM(CB132:CE132) -> 1416.215 | CG132: =+Data!CG164 -> 478 | CH132: =+Data!CH164 -> 449 | CI132: =+Data!CI164 -> 520 | CJ132: =+Data!CJ164 -> 354 | CK132: =SUM(CG132:CJ132) -> 1801 | CL132: =Data!CL164 -> 475 | CM132: =Data!CM164 -> -457 | CN132: =Data!CN164 -> -615 | CO132: =Data!CO164 -> 33 | CP132: =SUM(CL132:CO132) -> -564 | CQ132: =Data!CQ164 -> 20 | CR132: =Data!CR164 -> 112 | CS132: =Data!CS164 -> 187 | CT132: =Data!CT164 -> 135 | CU132: =SUM(CQ132:CT132) -> 454 | CV132: =Data!CV164 -> 151 | CW132: =Data!CW164 -> 302 | CX132: =Data!CX164 -> 316 | CY132: =Data!CY164 -> 306 | CZ132: =SUM(CV132:CY132) -> 1075 | DA132: =Data!DA164 -> 415 | DB132: =Data!DB164 -> 230 | DC132: =Data!DC164 -> -2482 | DD132: =Data!DD164 -> 382 | DE132: =SUM(DA132:DD132) -> -1455 | DF132: =Data!DF164 -> 412 | DG132: =Data!DG164 -> 542 | DH132: =Data!DH164 -> 557 | DI132: =Data!DI164 -> 504 | DJ132: =SUM(DF132:DI132) -> 2015 | DK132: =Data!DK164 -> 580 | DL132: =Data!DL164 -> 492 | DM132: =Data!DM164 -> 751 | DN132: =DN168+DN156 -> 723.78563 | DO132: =SUM(DK132:DN132) -> 2546.7856 | DP132: =DP168+DP156 -> 645.2616 | DQ132: =DQ168+DQ156 -> 683.31026 | DR132: =DR168+DR156 -> 845.43336 | DS132: =DS168+DS156 -> 838.39921 | DT132: =SUM(DP132:DS132) -> 3012.4044 | DU132: =DU168+DU156 -> 3323.4061 | DV132: =DV168+DV156 -> 3640.2627
...

Sheet IS
B3: RTX Income Statement | C3: 1997 | D3: 1998 | E3: 1999 | F3: 2000 | G3: 2001 | H3: 2002 | I3: 2003 | J3: 1Q04 | K3: 2Q04 | L3: 3Q04 | M3: 4Q04 | N3: 2004 | O3: 1Q05 | P3: 2Q05 | Q3: 3Q05 | R3: 4Q05 | S3: 2005 | T3: 1Q06 | U3: 2Q06 | V3: 3Q06 | W3: 4Q06 | X3: 2006 | Y3: 1Q07 | Z3: 2Q07 | AA3: 3Q07 | AB3: 4Q07 | AC3: 2007 | AD3: 1Q08 | AE3: 2Q08 | AF3: 3Q08 | AG3: 4Q08 | AH3: 2008 | AI3: 1Q09 | AJ3: 2Q09 | AK3: 3Q09 | AL3: 4Q09 | AM3: 2009 | AN3: 1Q10 | AO3: 2Q10 | AP3: 3Q10 | AQ3: 4Q10 | AR3: 2010 | AS3: 1Q11 | AT3: 2Q11 | AU3: 3Q11 | AV3: 4Q11 | AW3: 2011 | AX3: 1Q12 | AY3: 2Q12 | AZ3: 3Q12 | BA3: 4Q12 | BB3: 2012 | BC3: 1Q13 | BD3: 2Q13 | BE3: 3Q13 | BF3: 4Q13 | BG3: 2013 | BH3: 1Q14 | BI3: 2Q14 | BJ3: 3Q14 | BK3: 4Q14 | BL3: 2014 | BM3: 1Q15 | BN3: 2Q15 | BO3: 3Q15 | BP3: 4Q15 | BQ3: 2015 | BR3: 1Q16 | BS3: 2Q16 | BT3: 3Q16 | BU3: 4Q16 | BV3: 2016 | BW3: 1Q17 | BX3: 2Q17 | BY3: 3Q17 | BZ3: 4Q17 | CA3: 2017 | CB3: 1Q18 | CC3: 2Q18 | CD3: 3Q18 | CE3: 4Q18 | CF3: 2018 | CG3: 1Q19 | CH3: 2Q19 | CI3: 3Q19 | CJ3: 4Q19 | CK3: 2019 | CL3: 1Q20E | CM3: 2Q20 | CN3: 3Q20 | CO3: 4Q20 | CP3: 2020 | CQ3: 1Q21 | CR3: 2Q21 | CS3: 3Q21 | CT3: 4Q21 | CU3: 2021 | CV3: 1Q22 | CW3: 2Q22 | CX3: 3Q22 | CY3: 4Q22 | CZ3: 2022 | DA3: 1Q23 | DB3: 2Q23 | DC3: 3Q23 | DD3: 4Q23 | DE3: 2023 | DF3: 1Q24 | DG3: 2Q24 | DH3: 3Q24 | DI3: 4Q24 | DJ3: 2024 | DK3: 1Q25 | DL3: 2Q25 | DM3: 3Q25 | DN3: 4Q25E | DO3: 2025E | DP3: 1Q26E | DQ3: 2Q26E | DR3: 3Q26E | DS3: 4Q26E | DT3: 2026E | DU3: 2027E | DV3: 2028E
B4: ($ mn, except per share data) | C4: 35795 | D4: 36160 | E4: 36525 | F4: 36891 | G4: 37256 | H4: 37621 | I4: 37986 | J4: 38077 | K4: 38168 | L4: 38260 | M4: 38352 | N4: 38352 | O4: 38442 | P4: 38533 | Q4: 38625 | R4: 38717 | S4: 38717 | T4: 38807 | U4: 38898 | V4: 38990 | W4: 39082 | X4: 39082 | Y4: 39172 | Z4: 39263 | AA4: 39355 | AB4: 39447 | AC4: 39447 | AD4: 39538 | AE4: 39629 | AF4: 39721 | AG4: 39813 | AH4: 39813 | AI4: 39903 | AJ4: 39994 | AK4: 40086 | AL4: 40178 | AM4: 40178 | AN4: 40268 | AO4: 40359 | AP4: 40451 | AQ4: 40543 | AR4: 40543 | AS4: 40633 | AT4: 40724 | AU4: 40816 | AV4: 40908 | AW4: 40908 | AX4: 40999 | AY4: 41090 | AZ4: 41182 | BA4: 41274 | BB4: 41274 | BC4: 41364 | BD4: 41455 | BE4: 41547 | BF4: 41639 | BG4: 41639 | BH4: 41729 | BI4: 41820 | BJ4: 41912 | BK4: 42004 | BL4: 42004 | BM4: 42094 | BN4: 42185 | BO4: 42277 | BP4: 42369 | BQ4: 42369 | BR4: 42460 | BS4: 42551 | BT4: 42643 | BU4: 42735 | BV4: 42735 | BW4: 42825 | BX4: 42916 | BY4: 43008 | BZ4: 43100 | CA4: 43100 | CB4: 43190 | CC4: 43281 | CD4: 43373 | CE4: 43465 | CF4: 43465 | CG4: 43555 | CH4: 43646 | CI4: 43738 | CJ4: 43830 | CK4: 43830 | CL4: 43921 | CM4: 44012 | CN4: 44104 | CO4: 44196 | CP4: 44196 | CQ4: 44286 | CR4: 44377 | CS4: 44469 | CT4: 44561 | CU4: 44561 | CV4: 44651 | CW4: 44742 | CX4: 44834 | CY4: 44926 | CZ4: 44926 | DA4: 45016 | DB4: 45107 | DC4: 45199 | DD4: 45291 | DE4: 45291 | DF4: 45382 | DG4: 45473 | DH4: 45565 | DI4: 45657 | DJ4: 45657 | DK4: 45746 | DL4: 45838 | DM4: 45930 | DN4: 46022 | DO4: 46022 | DP4: 46111 | DQ4: 46203 | DR4: 46295 | DS4: 46387 | DT4: 46387 | DU4: =SEG!DU4 -> 46752 | DV4: =SEG!DV4 -> 47118
B6: Net sales | BL6: =SEG!BL62 -> 50640 | BQ6: =SEG!BQ62 -> 50564 | BV6: =SEG!BV62 -> 52569 | CA6: =SEG!CA62 -> 55417 | CF6: =+Data!CF9 -> 69172 | CG6: =+Data!CG9 -> 17664.5 | CH6: =+Data!CH9 -> 18385.5 | CI6: =+Data!CI9 -> 18711.63 | CJ6: =+Data!CJ9 -> 19475.37 | CK6: =SUM(CG6:CJ6) -> 74237 | CL6: =Data!CL9 -> 18451 | CM6: =Data!CM9 -> 14470 | CN6: =Data!CN9 -> 14747 | CO6: =Data!CO9 -> 16419 | CP6: =SUM(CL6:CO6) -> 64087 | CQ6: =Data!CQ9 -> 15251 | CR6: =Data!CR9 -> 15880 | CS6: =Data!CS9 -> 16213 | CT6: =Data!CT9 -> 17044 | CU6: =SUM(CQ6:CT6) -> 64388 | CV6: =Data!CV9 -> 15716 | CW6: =Data!CW9 -> 16314 | CX6: =Data!CX9 -> 16951 | CY6: =Data!CY9 -> 18093 | CZ6: =SUM(CV6:CY6) -> 67074 | DA6: =Data!DA9 -> 17214 | DB6: =Data!DB9 -> 18315 | DC6: =Data!DC9 -> 13464 | DD6: =Data!DD9 -> 19927 | DE6: =SUM(DA6:DD6) -> 68920 | DF6: =Data!DF9 -> 19305 | DG6: =Data!DG9 -> 19721 | DH6: =Data!DH9 -> 20089 | DI6: =Data!DI9 -> 21623 | DJ6: =SUM(DF6:DI6) -> 80738 | DK6: =Data!DK9 -> 20306 | DL6: =Data!DL9 -> 21581 | DM6: =Data!DM9 -> 22478 | DN6: =SEG!DN62 -> 22600.391 | DO6: =SUM(DK6:DN6) -> 86965.391 | DP6: =SEG!DP62 -> 21412.09 | DQ6: =SEG!DQ62 -> 22660.136 | DR6: =SEG!DR62 -> 23884.548 | DS6: =SEG!DS62 -> 24230.983 | DT6: =SUM(DP6:DS6) -> 92187.757 | DU6: =SEG!DU62 -> 98332.758 | DV6: =SEG!DV62 -> 104225.83
B7: Cost of goods sold | CF7: =CF8-CF6 -> -51666.942 | CG7: =CG8-CG6 -> -13710.34 | CH7: =CH8-CH6 -> -13986.66 | CI7: =CI8-CI6 -> -14210.65 | CJ7: =CJ8-CJ6 -> -15298.35 | CK7: =SUM(CG7:CJ7) -> -57206 | CL7: =CL8-CL6 -> -14224.824 | CM7: =CM8-CM6 -> -15638.818 | CN7: =-Data!CN12 -> -13004 | CO7: =-Data!CO12 -> -14266 | CP7: =SUM(CL7:CO7) -> -57133.642 | CQ7: =-Data!CQ12 -> -12537 | CR7: =-Data!CR12 -> -12655 | CS7: =-Data!CS12 -> -13089 | CT7: =-Data!CT12 -> -13616 | CU7: =SUM(CQ7:CT7) -> -51897 | CV7: =-Data!CV12 -> -12560 | CW7: =-Data!CW12 -> -12856 | CX7: =-Data!CX12 -> -13464 | CY7: =-Data!CY12 -> -14526 | CZ7: =SUM(CV7:CY7) -> -53406 | DA7: =-Data!DA12 -> -13645 | DB7: =-Data!DB12 -> -14518 | DC7: =-Data!DC12 -> -12750 | DD7: =-Data!DD12 -> -15918 | DE7: =SUM(DA7:DD7) -> -56831 | DF7: =-Data!DF12 -> -15744 | DG7: =-Data!DG12 -> -16141 | DH7: =-Data!DH12 -> -16055 | DI7: =-Data!DI12 -> -17388 | DJ7: =SUM(DF7:DI7) -> -65328 | DK7: =-Data!DK12 -> -16190 | DL7: =-Data!DL12 -> -17205 | DM7: =-Data!DM12 -> -17898 | DN7: =DN8-DN6 -> -17840.714 | DO7: =SUM(DK7:DN7) -> -69133.714 | DP7: =DP8-DP6 -> -16897.817 | DQ7: =DQ8-DQ6 -> -17794.185 | DR7: =DR8-DR6 -> -18619.87 | DS7: =DS8-DS6 -> -18904.306 | DT7: =SUM(DP7:DS7) -> -72216.177 | DU7: =DU8-DU6 -> -76679.534 | DV7: =DV8-DV6 -> -80914.022
B8: Gross Income | CF8: =CF13-CF10-CF9-CF12 -> 17505.058 | CG8: =CG13-CG10-CG9-CG12 -> 3954.16 | CH8: =CH13-CH10-CH9-CH12 -> 4398.84 | CI8: =CI13-CI10-CI9-CI12 -> 4500.98 | CJ8: =CJ13-CJ10-CJ9-CJ12 -> 4177.02 | CK8: =SUM(CG8:CJ8) -> 17031 | CL8: =CL13-CL10-CL9-CL12 -> 4226.1761 | CM8: =CM13-CM10-CM9-CM12 -> -1168.8181 | CN8: =CN6+CN7 -> 1743 | CO8: =CO6+CO7 -> 2153 | CP8: =SUM(CL8:CO8) -> 6953.358 | CQ8: =CQ6+CQ7 -> 2714 | CR8: =CR6+CR7 -> 3225 | CS8: =CS6+CS7 -> 3124 | CT8: =CT6+CT7 -> 3428 | CU8: =SUM(CQ8:CT8) -> 12491 | CV8: =CV6+CV7 -> 3156 | CW8: =CW6+CW7 -> 3458 | CX8: =CX6+CX7 -> 3487 | CY8: =CY6+CY7 -> 3567 | CZ8: =SUM(CV8:CY8) -> 13668 | DA8: =DA6+DA7 -> 3569 | DB8: =DB6+DB7 -> 3797 | DC8: =DC6+DC7 -> 714 | DD8: =DD6+DD7 -> 4009 | DE8: =SUM(DA8:DD8) -> 12089 | DF8: =DF6+DF7 -> 3561 | DG8: =DG6+DG7 -> 3580 | DH8: =DH6+DH7 -> 4034 | DI8: =DI6+DI7 -> 4235 | DJ8: =SUM(DF8:DI8) -> 15410 | DK8: =DK6+DK7 -> 4116 | DL8: =DL6+DL7 -> 4376 | DM8: =DM6+DM7 -> 4580 | DN8: =DN13-DN10-DN9-DN12 -> 4759.6766 | DO8: =SUM(DK8:DN8) -> 17831.677 | DP8: =DP13-DP10-DP9-DP12 -> 4514.2729 | DQ8: =DQ13-DQ10-DQ9-DQ12 -> 4865.951 | DR8: =DR13-DR10-DR9-DR12 -> 5264.6782 | DS8: =DS13-DS10-DS9-DS12 -> 5326.6776 | DT8: =SUM(DP8:DS8) -> 19971.58 | DU8: =DU13-DU10-DU12-DU9 -> 21653.225 | DV8: =DV13-DV10-DV12-DV9 -> 23311.807
B9: =+Data!B13 -> Research and development | CF9: =-Data!CF13 -> -3252 | CG9: =-Data!CG13 -> -779.1 | CH9: =-Data!CH13 -> -810.9 | CI9: =-Data!CI13 -> -782.04 | CJ9: =-Data!CJ13 -> -813.96 | CK9: =SUM(CG9:CJ9) -> -3186 | CL9: =-CL6*CL51 -> -645.785 | CM9: =-Data!CM13 -> -695 | CN9: =-Data!CN13 -> -642 | CO9: =-Data!CO13 -> -710 | CP9: =SUM(CL9:CO9) -> -2692.785 | CQ9: =-Data!CQ13 -> -589 | CR9: =-Data!CR13 -> -657 | CS9: =-Data!CS13 -> -676 | CT9: =-Data!CT13 -> -810 | CU9: =SUM(CQ9:CT9) -> -2732 | CV9: =-Data!CV13 -> -635 | CW9: =-Data!CW13 -> -698 | CX9: =-Data!CX13 -> -662 | CY9: =-Data!CY13 -> -716 | CZ9: =SUM(CV9:CY9) -> -2711 | DA9: =-Data!DA13 -> -607 | DB9: =-Data!DB13 -> -729 | DC9: =-Data!DC13 -> -712 | DD9: =-Data!DD13 -> -757 | DE9: =SUM(DA9:DD9) -> -2805 | DF9: =-Data!DF13 -> -669 | DG9: =-Data!DG13 -> -706 | DH9: =-Data!DH13 -> -751 | DI9: =-Data!DI13 -> -808 | DJ9: =SUM(DF9:DI9) -> -2934 | DK9: =-Data!DK13 -> -637 | DL9: =-Data!DL13 -> -697 | DM9: =-Data!DM13 -> -684 | DN9: =-DN6*DN51 -> -791.01369 | DO9: =SUM(DK9:DN9) -> -2809.0137 | DP9: =-DP6*DP51 -> -749.42315 | DQ9: =-DQ6*DQ51 -> -793.10476 | DR9: =-DR6*DR51 -> -835.95918 | DS9: =-DS6*DS51 -> -848.08441 | DT9: =SUM(DP9:DS9) -> -3226.5715 | DU9: =-DU6*DU51 -> -3441.6465 | DV9: =-DV6*DV51 -> -3647.904
B10: Selling and administrative expenses | CF10: =-Data!CF14 -> -5553 | CG10: =-Data!CG14 -> -1368.08 | CH10: =-Data!CH14 -> -1423.92 | CI10: =-Data!CI14 -> -1450.89 | CJ10: =-Data!CJ14 -> -1510.11 | CK10: =SUM(CG10:CJ10) -> -5753 | CL10: =-CL6*CL50 -> -1476.08 | CM10: =-Data!CM14 -> -1811 | CN10: =-Data!CN14 -> -1401 | CO10: =-Data!CO14 -> -1351 | CP10: =SUM(CL10:CO10) -> -6039.08 | CQ10: =-Data!CQ14 -> -1220 | CR10: =-Data!CR14 -> -1368 | CS10: =-Data!CS14 -> -1229 | CT10: =-Data!CT14 -> -1407 | CU10: =SUM(CQ10:CT10) -> -5224 | CV10: =-Data!CV14 -> -1469 | CW10: =-Data!CW14 -> -1424 | CX10: =-Data!CX14 -> -1391 | CY10: =-Data!CY14 -> -1379 | CZ10: =SUM(CV10:CY10) -> -5663 | DA10: =-Data!DA14 -> -1398 | DB10: =-Data!DB14 -> -1635 | DC10: =-Data!DC14 -> -1401 | DD10: =-Data!DD14 -> -1445 | DE10: =SUM(DA10:DD10) -> -5879 | DF10: =-Data!DF14 -> -1394 | DG10: =-Data!DG14 -> -1449 | DH10: =-Data!DH14 -> -1389 | DI10: =-Data!DI14 -> -1574 | DJ10: =SUM(DF10:DI10) -> -5806 | DK10: =-Data!DK14 -> -1448 | DL10: =-Data!DL14 -> -1573 | DM10: =-Data!DM14 -> -1436 | DN10: =-DN6*DN50 -> -1695.0293 | DO10: =SUM(DK10:DN10) -> -6152.0293 | DP10: =-DP6*DP50 -> -1605.9067 | DQ10: =-DQ6*DQ50 -> -1699.5102 | DR10: =-DR6*DR50 -> -1791.3411 | DS10: =-DS6*DS50 -> -1817.3237 | DT10: =SUM(DP10:DS10) -> -6914.0818 | DU10: =-DU6*DU50 -> -7374.9569 | DV10: =-DV6*DV50 -> -7816.9372
B11: Charges & other | CL11: 0 | CM11: =Data!CM15 -> -3183 | CN11: =Data!CN15 -> 0 | CO11: =Data!CO15 -> 0 | CP11: =SUM(CL11:CO11) -> -3183 | CQ11: =Data!CQ15 -> 0 | CR11: =Data!CR15 -> 0 | CS11: =Data!CS15 -> 0 | CT11: =Data!CT15 -> -617 | CU11: =SUM(CQ11:CT11) -> -617 | CV11: =Data!CV15 -> 0 | CW11: =Data!CW15 -> 0 | CX11: =Data!CX15 -> 0 | CY11: =Data!CY15 -> 0 | CZ11: =SUM(CV11:CY11) -> 0 | DA11: 0 | DB11: =Data!DB15 -> 0 | DC11: =Data!DC15 -> 0 | DD11: =Data!DD15 -> 0 | DE11: =SUM(DA11:DD11) -> 0 | DF11: 0 | DG11: =Data!DG15 -> 0 | DH11: =Data!DH15 -> 0 | DI11: =Data!DI15 -> 0 | DJ11: =SUM(DF11:DI11) -> 0 | DK11: 0 | DL11: =Data!DL15 -> 0 | DM11: =Data!DM15 -> 0 | DN11: 0 | DO11: =SUM(DK11:DN11) -> 0 | DP11: 0 | DQ11: 0 | DR11: 0 | DS11: 0 | DT11: =SUM(DP11:DS11) -> 0 | DU11: 0 | DV11: 0
B12: Other income (expense) | CF12: =Data!CF16 -> 337 | CG12: =Data!CG16 -> 97.02 | CH12: =Data!CH16 -> 100.98 | CI12: =Data!CI16 -> 75.95 | CJ12: =Data!CJ16 -> 79.05 | CK12: =SUM(CG12:CJ12) -> 353 | CL12: 75 | CM12: =Data!CM16 -> 82 | CN12: =Data!CN16 -> 734 | CO12: =Data!CO16 -> 50 | CP12: =SUM(CL12:CO12) -> 941 | CQ12: =Data!CQ16 -> 108 | CR12: =Data!CR16 -> 82 | CS12: =Data!CS16 -> 124 | CT12: =Data!CT16 -> 109 | CU12: =SUM(CQ12:CT12) -> 423 | CV12: =Data!CV16 -> 28 | CW12: =Data!CW16 -> 17 | CX12: =Data!CX16 -> 46 | CY12: =Data!CY16 -> 29 | CZ12: =SUM(CV12:CY12) -> 120 | DA12: =Data!DA16 -> 88 | DB12: =Data!DB16 -> 25 | DC12: =Data!DC16 -> 3 | DD12: =Data!DD16 -> -30 | DE12: =SUM(DA12:DD12) -> 86 | DF12: =Data!DF16 -> 372 | DG12: =Data!DG16 -> -896 | DH12: =Data!DH16 -> 134 | DI12: =Data!DI16 -> 258 | DJ12: =SUM(DF12:DI12) -> -132 | DK12: =Data!DK16 -> 4 | DL12: =Data!DL16 -> 40 | DM12: =Data!DM16 -> 63 | DN12: 50 | DO12: =SUM(DK12:DN12) -> 157 | DP12: 50 | DQ12: 50 | DR12: 50 | DS12: 50 | DT12: =SUM(DP12:DS12) -> 200 | DU12: 200 | DV12: 200
B13: EBIT | CF13: =SEG!CF144 -> 9037.0576 | CG13: =SEG!CG144 -> 1904 | CH13: =SEG!CH144 -> 2265 | CI13: =SEG!CI144 -> 2344 | CJ13: =SEG!CJ144 -> 1932 | CK13: =SUM(CG13:CJ13) -> 8445 | CL13: =SEG!CL144 -> 2179.3111 | CM13: =SEG!CM144 -> -3592.8181 | CN13: =SUM(CN8:CN12) -> 434 | CO13: =SUM(CO8:CO12) -> 142 | CP13: =SUM(CL13:CO13) -> -837.50699 | CQ13: =SUM(CQ8:CQ12) -> 1013 | CR13: =SUM(CR8:CR12) -> 1282 | CS13: =SUM(CS8:CS12) -> 1343 | CT13: =SUM(CT8:CT12) -> 703 | CU13: =SUM(CQ13:CT13) -> 4341 | CV13: =SUM(CV8:CV12) -> 1080 | CW13: =SUM(CW8:CW12) -> 1353 | CX13: =SUM(CX8:CX12) -> 1480 | CY13: =SUM(CY8:CY12) -> 1501 | CZ13: =SUM(CV13:CY13) -> 5414 | DA13: =SUM(DA8:DA12) -> 1652 | DB13: =SUM(DB8:DB12) -> 1458 | DC13: =SUM(DC8:DC12) -> -1396 | DD13: =SUM(DD8:DD12) -> 1777 | DE13: =SUM(DA13:DD13) -> 3491 | DF13: =SUM(DF8:DF12) -> 1870 | DG13: =SUM(DG8:DG12) -> 529 | DH13: =SUM(DH8:DH12) -> 2028 | DI13: =SUM(DI8:DI12) -> 2111 | DJ13: =SUM(DF13:DI13) -> 6538 | DK13: =SUM(DK8:DK12) -> 2035 | DL13: =SUM(DL8:DL12) -> 2146 | DM13: =SUM(DM8:DM12) -> 2523 | DN13: =SEG!DN144 -> 2323.6336 | DO13: =SUM(DK13:DN13) -> 9027.6336 | DP13: =SEG!DP144 -> 2208.943 | DQ13: =SEG!DQ144 -> 2423.336 | DR13: =SEG!DR144 -> 2687.378 | DS13: =SEG!DS144 -> 2711.2695 | DT13: =SUM(DP13:DS13) -> 10030.926 | DU13: =SEG!DU144 -> 11036.621 | DV13: =SEG!DV144 -> 12046.966
B14: Non-service pension benefit (cost) | CF14: =-Data!CF18 -> 1305 | CG14: =-Data!CG18 -> 315.07 | CH14: =-Data!CH18 -> 327.93 | CI14: =-Data!CI18 -> 278.81 | CJ14: =-Data!CJ18 -> 290.19 | CK14: =SUM(CG14:CJ14) -> 1212 | CL14: =-Data!CL18 -> 276 | CM14: =-Data!CM18 -> 225 | CN14: =-Data!CN18 -> 253 | CO14: =-Data!CO18 -> 244 | CP14: =SUM(CL14:CO14) -> 998 | CQ14: =-Data!CQ18 -> 491 | CR14: =-Data!CR18 -> 490 | CS14: =-Data!CS18 -> 491 | CT14: =-Data!CT18 -> 472 | CU14: =SUM(CQ14:CT14) -> 1944 | CV14: =-Data!CV18 -> 480 | CW14: =-Data!CW18 -> 474 | CX14: =-Data!CX18 -> 468 | CY14: =-Data!CY18 -> 467 | CZ14: =SUM(CV14:CY14) -> 1889 | DA14: =-Data!DA18 -> 444 | DB14: =-Data!DB18 -> 447 | DC14: =-Data!DC18 -> 443 | DD14: =-Data!DD18 -> 446 | DE14: =SUM(DA14:DD14) -> 1780 | DF14: =-Data!DF18 -> 386 | DG14: =-Data!DG18 -> 374 | DH14: =-Data!DH18 -> 374 | DI14: =-Data!DI18 -> 384 | DJ14: =SUM(DF14:DI14) -> 1518 | DK14: =-Data!DK18 -> 366 | DL14: =-Data!DL18 -> 351 | DM14: =-Data!DM18 -> 364 | DN14: 350 | DO14: =SUM(DK14:DN14) -> 1431 | DP14: 325 | DQ14: 325 | DR14: 325 | DS14: 325 | DT14: =SUM(DP14:DS14) -> 1300 | DU14: 1200 | DV14: 1200
B15: Interest expense, net | CF15: =-Data!CF19 -> -1001 | CG15: =-Data!CG19 -> -253.82 | CH15: =-Data!CH19 -> -264.18 | CI15: =-Data!CI19 -> -274.89 | CJ15: =-Data!CJ19 -> -286.11 | CK15: =SUM(CG15:CJ15) -> -1079 | CL15: =-Data!CL19 -> -252 | CM15: =-Data!CM19 -> -337 | CN15: =-Data!CN19 -> -350 | CO15: =-Data!CO19 -> -349 | CP15: =SUM(CL15:CO15) -> -1288 | CQ15: =-Data!CQ19 -> -346 | CR15: =-Data!CR19 -> -342 | CS15: =-Data!CS19 -> -358 | CT15: =-Data!CT19 -> -308 | CU15: =SUM(CQ15:CT15) -> -1354 | CV15: =-Data!CV19 -> -318 | CW15: =-Data!CW19 -> -329 | CX15: =-Data!CX19 -> -311 | CY15: =-Data!CY19 -> -318 | CZ15: =SUM(CV15:CY15) -> -1276 | DA15: =-Data!DA19 -> -315 | DB15: =-Data!DB19 -> -333 | DC15: =-Data!DC19 -> -369 | DD15: =-Data!DD19 -> -488 | DE15: =SUM(DA15:DD15) -> -1505 | DF15: =-Data!DF19 -> -405 | DG15: =-Data!DG19 -> -475 | DH15: =-Data!DH19 -> -496 | DI15: =-Data!DI19 -> -486 | DJ15: =SUM(DF15:DI15) -> -1862 | DK15: =-Data!DK19 -> -443 | DL15: =-Data!DL19 -> -457 | DM15: =-Data!DM19 -> -449 | DN15: =(BS!DN7*0.015/4)-(BS!DN56*(0.05/4)) -> -449.48272 | DO15: =SUM(DK15:DN15) -> -1798.4827 | DP15: =(BS!DP7*0.015/4)-(BS!DP56*(0.0485/4)) -> -437.26572 | DQ15: =(BS!DQ7*0.015/4)-(BS!DQ56*(0.0485/4)) -> -438.36481 | DR15: =(BS!DR7*0.015/4)-(BS!DR56*(0.0485/4)) -> -437.46237 | DS15: =(BS!DS7*0.015/4)-(BS!DS56*(0.0485/4)) -> -430.67342 | DT15: =SUM(DP15:DS15) -> -1743.7663 | DU15: =(BS!DU7*0.015)-(BS!DU56*(0.0485)) -> -1710.2208 | DV15: =(BS!DV7*0.015)-(BS!DV56*(0.0485)) -> -1701.454
B16: EBT | CF16: =SUM(CF13:CF15) -> 9341.0576 | CG16: =SUM(CG13:CG15) -> 1965.25 | CH16: =SUM(CH13:CH15) -> 2328.75 | CI16: =SUM(CI13:CI15) -> 2347.92 | CJ16: =SUM(CJ13:CJ15) -> 1936.08 | CK16: =SUM(CG16:CJ16) -> 8578 | CL16: =SUM(CL13:CL15) -> 2203.3111 | CM16: =SUM(CM13:CM15) -> -3704.8181 | CN16: =SUM(CN13:CN15) -> 337 | CO16: =SUM(CO13:CO15) -> 37 | CP16: =SUM(CL16:CO16) -> -1127.507 | CQ16: =SUM(CQ13:CQ15) -> 1158 | CR16: =SUM(CR13:CR15) -> 1430 | CS16: =SUM(CS13:CS15) -> 1476 | CT16: =SUM(CT13:CT15) -> 867 | CU16: =SUM(CQ16:CT16) -> 4931 | CV16: =SUM(CV13:CV15) -> 1242 | CW16: =SUM(CW13:CW15) -> 1498 | CX16: =SUM(CX13:CX15) -> 1637 | CY16: =SUM(CY13:CY15) -> 1650 | CZ16: =SUM(CV16:CY16) -> 6027 | DA16: =SUM(DA13:DA15) -> 1781 | DB16: =SUM(DB13:DB15) -> 1572 | DC16: =SUM(DC13:DC15) -> -1322 | DD16: =SUM(DD13:DD15) -> 1735 | DE16: =SUM(DA16:DD16) -> 3766 | DF16: =SUM(DF13:DF15) -> 1851 | DG16: =SUM(DG13:DG15) -> 428 | DH16: =SUM(DH13:DH15) -> 1906 | DI16: =SUM(DI13:DI15) -> 2009 | DJ16: =SUM(DF16:DI16) -> 6194 | DK16: =SUM(DK13:DK15) -> 1958 | DL16: =SUM(DL13:DL15) -> 2040 | DM16: =SUM(DM13:DM15) -> 2438 | DN16: =SUM(DN13:DN15) -> 2224.1509 | DO16: =SUM(DK16:DN16) -> 8660.1509 | DP16: =SUM(DP13:DP15) -> 2096.6773 | DQ16: =SUM(DQ13:DQ15) -> 2309.9712 | DR16: =SUM(DR13:DR15) -> 2574.9156 | DS16: =SUM(DS13:DS15) -> 2605.5961 | DT16: =SUM(DP16:DS16) -> 9587.1602 | DU16: =SUM(DU13:DU15) -> 10526.4 | DV16: =SUM(DV13:DV15) -> 11545.512
B17: Income tax expense | CF17: =-Data!CF21 -> -1808 | CG17: =-Data!CG21 -> -296.94 | CH17: =-Data!CH21 -> -309.06 | CI17: =-Data!CI21 -> -299.88 | CJ17: =-Data!CJ21 -> -312.12 | CK17: =SUM(CG17:CJ17) -> -1218 | CL17: =-Data!CL21 -> -419 | CM17: =-Data!CM21 -> 23 | CN17: =-Data!CN21 -> -152 | CO17: =-Data!CO21 -> 178 | CP17: =SUM(CL17:CO17) -> -370 | CQ17: =-Data!CQ21 -> -345 | CR17: =-Data!CR21 -> -342 | CS17: =-Data!CS21 -> -3 | CT17: =-Data!CT21 -> -96 | CU17: =SUM(CQ17:CT17) -> -786 | CV17: =-Data!CV21 -> -116 | CW17: =-Data!CW21 -> -160 | CX17: =-Data!CX21 -> -242 | CY17: =-Data!CY21 -> -182 | CZ17: =SUM(CV17:CY17) -> -700 | DA17: =-Data!DA21 -> -300 | DB17: =-Data!DB21 -> -213 | DC17: =-Data!DC21 -> 389 | DD17: =-Data!DD21 -> -262 | DE17: =SUM(DA17:DD17) -> -386 | DF17: =-Data!DF21 -> -108 | DG17: =-Data!DG21 -> -253 | DH17: =-Data!DH21 -> -371 | DI17: =-Data!DI21 -> -449 | DJ17: =SUM(DF17:DI17) -> -1181 | DK17: =-Data!DK21 -> -333 | DL17: =-Data!DL21 -> -315 | DM17: =-Data!DM21 -> -432 | DN17: =-DN16*DN54 -> -533.79622 | DO17: =SUM(DK17:DN17) -> -1613.7962 | DP17: =-DP16*DP54 -> -398.36869 | DQ17: =-DQ16*DQ54 -> -438.89453 | DR17: =-DR16*DR54 -> -489.23396 | DS17: =-DS16*DS54 -> -495.06325 | DT17: =SUM(DP17:DS17) -> -1821.5604 | DU17: =-DU16*DU54 -> -2000.0161 | DV17: =-DV16*DV54 -> -2193.6472
B18: Minority Interest | CF18: =-Data!CF25 -> -163 | CG18: =-Data!CG25 -> -41.16 | CH18: =-Data!CH25 -> -42.84 | CI18: =-Data!CI25 -> -60.27 | CJ18: =-Data!CJ25 -> -62.73 | CK18: =SUM(CG18:CJ18) -> -207 | CL18: =-Data!CL25 -> -56 | CM18: =-Data!CM25 -> -24 | CN18: =-Data!CN25 -> -34 | CO18: =-Data!CO25 -> -69 | CP18: =SUM(CL18:CO18) -> -183 | CQ18: =-Data!CQ25 -> -41 | CR18: =-Data!CR25 -> -48 | CS18: =-Data!CS25 -> -73 | CT18: =-Data!CT25 -> -86 | CU18: =SUM(CQ18:CT18) -> -248 | CV18: =-Data!CV25 -> -23 | CW18: =-Data!CW25 -> -34 | CX18: =-Data!CX25 -> -8 | CY18: =-Data!CY25 -> -46 | CZ18: =SUM(CV18:CY18) -> -111 | DA18: =-Data!DA25 -> -55 | DB18: =-Data!DB25 -> -32 | DC18: =-Data!DC25 -> -51 | DD18: =-Data!DD25 -> -47 | DE18: =SUM(DA18:DD18) -> -185 | DF18: =-Data!DF25 -> -34 | DG18: =-Data!DG25 -> -64 | DH18: =-Data!DH25 -> -63 | DI18: =-Data!DI25 -> -78 | DJ18: =SUM(DF18:DI18) -> -239 | DK18: =-Data!DK25 -> -90 | DL18: =-Data!DL25 -> -68 | DM18: =-Data!DM25 -> -88 | DN18: -90 | DO18: =SUM(DK18:DN18) -> -336 | DP18: -75 | DQ18: -85 | DR18: -90 | DS18: -95 | DT18: =SUM(DP18:DS18) -> -345 | DU18: -355 | DV18: -375
B19: Net income, continuing ops. | CF19: =SUM(CF16:CF18) -> 7370.0576 | CG19: =SUM(CG16:CG18) -> 1627.15 | CH19: =SUM(CH16:CH18) -> 1976.85 | CI19: =SUM(CI16:CI18) -> 1987.77 | CJ19: =SUM(CJ16:CJ18) -> 1561.23 | CK19: =SUM(CK16:CK18) -> 7153 | CL19: =SUM(CL16:CL18) -> 1728.3111 | CM19: =SUM(CM16:CM18) -> -3705.8181 | ... DV19: =SUM(DV16:DV18) -> 8976.8645
B21: Basic EPS, continuing ops. | CF21: =CF19/CF32 -> 5.0887645 | CG21: =CG19/CG32 -> 1.0835387 | CH21: =CH19/CH32 -> 1.3164081 | CI21: =CI19/CI32 -> 1.3203388 | CJ21: =CJ19/CJ32 -> 1.0370176 | CK21: =CK19/CK32 -> 4.7572493 | CL21: =CL19/CL32 -> 1.1470838 | CM21: =CM19/CM32 -> -2.4684061 | ... DV21: =DV19/DV32 -> 6.8208073
B22: Diluted EPS, continuing ops. | CF22: =CF19/CF33 -> 5.0507522 | CG22: =CG19/CG33 -> 1.0758017 | CH22: =CH19/CH33 -> 1.3070083 | CI22: =CI19/CI33 -> 1.3085182 | CJ22: =CJ19/CJ33 -> 1.0277335 | CK22: =CK19/CK33 -> 4.7189603 | CL22: =CL19/CL33 -> 1.1386199 | CM22: =CM19/CM33 -> -2.4684061 | ... DV22: =DV19/DV33 -> 6.7424249
B24: Adjustments in EBIT | CF24: =-SEG!CF165 -> 741 | CG24: =-SEG!CG165 -> 249 | CH24: =-SEG!CH165 -> 54 | CI24: =-SEG!CI165 -> 41 | CJ24: =-SEG!CJ165 -> 203 | CK24: =SUM(CG24:CJ24) -> 547 | CL24: =-SEG!CL165 -> 132.38889 | CM24: =427+3673 -> 4100 | CN24: =245-29 -> 216 | CO24: 88 | CP24: =SUM(CL24:CO24) -> 4536.3889 | CQ24: 43 | CR24: 56 | CS24: =19 -> 19 | CT24: =-66+25 -> -41 | CU24: =SUM(CQ24:CT24) -> 77 | CV24: 44 | CW24: =12+69 -> 81 | CX24: 24 | CY24: =42+35+7 -> 84 | CZ24: =SUM(CV24:CY24) -> 233 | DA24: 30 | DB24: 68 | DC24: 104 | DD24: 44 | DE24: =SUM(DA24:DD24) -> 246 | DF24: 34 | DG24: 36 | DH24: -128 | DI24: 142 | DJ24: =SUM(DF24:DI24) -> 84 | DK24: 132 | DL24: 51 | DM24: -83 | DN24: =-SEG!DN165 -> 0 | DO24: =SUM(DK24:DN24) -> 100 | DP24: =-SEG!DP165 -> 0 | DQ24: =-SEG!DQ165 -> 0 | DR24: =-SEG!DR165 -> 0 | DS24: =-SEG!DS165 -> 0 | DT24: =SUM(DP24:DS24) -> 0 | DU24: =-SEG!DU165 -> 0 | DV24: =-SEG!DV165 -> 0
B25: Other adjustments | CL25: 0 | CM25: =25-4-88 -> -67 | CN25: =8+5-17 -> -4 | CO25: 4 | CP25: =SUM(CL25:CO25) -> -67 | CQ25: 25 | CR25: 0 | CS25: 32 | CT25: =617+29-12 -> 634 | CU25: =SUM(CQ25:CT25) -> 691 | CV25: =290-5-11 -> 274 | CW25: 0 | CX25: 0 | CY25: 0 | CZ25: =SUM(CV25:CY25) -> 274 | DA25: =-57+2 -> -55 | DB25: =193-17 -> 176 | DC25: 3003 | DD25: =-49+2-1-10-61-3 -> -122 | DE25: =SUM(DA25:DD25) -> 3002 | DF25: =-112+2-9-78-296 -> -493 | DG25: =504+1491+3+7 -> 2005 | DH25: =45+534+4+2 -> 585 | DI25: =79+520 -> 599 | DJ25: =SUM(DF25:DI25) -> 2696 | DK25: =26-43+35-26 -> -8 | DL25: =109-11-33 -> 65 | DM25: 19 | DN25: 0 | DO25: =SUM(DK25:DN25) -> 76 | DP25: 0 | DQ25: 0 | DR25: 0 | DS25: 0 | DT25: =SUM(DP25:DS25) -> 0 | DU25: 0 | DV25: 0
B26: Intangible amortization | CF26: =-SEG!CF141 -> 611.68044 | CG26: =-SEG!CG141 -> 588 | CH26: =-SEG!CH141 -> 571 | CI26: =-SEG!CI141 -> 581 | CJ26: =-SEG!CJ141 -> 594 | CK26: =SUM(CG26:CJ26) -> 2334 | CL26: =-SEG!CL141 -> 644 | CM26: =-SEG!CM141 -> 545 | CN26: =-SEG!CN141 -> 523 | CO26: =-SEG!CO141 -> 561 | CP26: =SUM(CL26:CO26) -> 2273 | CQ26: =-SEG!CQ141 -> 516 | CR26: =-SEG!CR141 -> 519 | CS26: =-SEG!CS141 -> 586 | CT26: =-SEG!CT141 -> 582 | CU26: =SUM(CQ26:CT26) -> 2203 | CV26: =-SEG!CV141 -> 484 | CW26: =-SEG!CW141 -> 448 | CX26: =-SEG!CX141 -> 482 | CY26: =-SEG!CY141 -> 479 | CZ26: =SUM(CV26:CY26) -> 1893 | DA26: =-SEG!DA141 -> 493 | DB26: 489 | DC26: =517+8 -> 525 | DD26: =499+5 -> 504 | DE26: =SUM(DA26:DD26) -> 2011 | DF26: 500 | DG26: 0 | DH26: 0 | DI26: 0 | DJ26: =SUM(DF26:DI26) -> 500 | DK26: 470 | DL26: 487 | DM26: 507 | DN26: =-SEG!DN141 -> 475 | DO26: =SUM(DK26:DN26) -> 1939 | DP26: =-SEG!DP141 -> 470 | DQ26: =-SEG!DQ141 -> 470 | DR26: =-SEG!DR141 -> 470 | DS26: =-SEG!DS141 -> 470 | DT26: =SUM(DP26:DS26) -> 1880 | DU26: =-SEG!DU141 -> 1850 | DV26: =-SEG!DV141 -> 1850
B27: Tax impact | CF27: =-(CF24+CF26)*0.215 -> -290.82629 | CG27: =-(CG24+CG26)*0.215 -> -179.955 | CH27: =-(CH24+CH26)*0.215 -> -134.375 | CI27: =-(CI24+CI26)*0.215 -> -133.73 | CJ27: =-(CJ24+CJ26)*0.215 -> -171.355 | CK27: =SUM(CG27:CJ27) -> -619.415 | CL27: =-(CL24+CL26)*0.1975 -> -153.33681 | CM27: =-321+22+60+46-31 -> -224 | CN27: =12-12-11-11-9 -> -31 | CO27: =260+55-13-2+25-5+4-1 -> 323 | CP27: =SUM(CL27:CO27) -> -85.336806 | CQ27: =-134+148 -> 14 | CR27: =-123+73 -> -50 | CS27: -141 | CT27: =-137-104-5 -> -246 | CU27: =SUM(CQ27:CT27) -> -423 | CV27: -182 | CW27: -111 | CX27: -108 | CY27: -117 | CZ27: =SUM(CV27:CY27) -> -518 | DA27: -101 | DB27: -165 | DC27: -826 | DD27: -99 | DE27: =SUM(DA27:DD27) -> -1191 | DF27: 41 | DG27: -257 | DH27: =11-148+156 -> 19 | DI27: -152 | DJ27: =SUM(DF27:DI27) -> -349 | DK27: -138 | DL27: -142 | DM27: -50 | DN27: =-(DN24+DN26)*0.22 -> -104.5 | DO27: =SUM(DK27:DN27) -> -434.5 | DP27: =-(DP24+DP26)*0.2 -> -94 | DQ27: =-(DQ24+DQ26)*0.2 -> -94 | DR27: =-(DR24+DR26)*0.2 -> -94 | DS27: =-(DS24+DS26)*0.2 -> -94 | DT27: =SUM(DP27:DS27) -> -376 | DU27: =-(DU24+DU26)*0.2 -> -370 | DV27: =-(DV24+DV26)*0.2 -> -370
B28: Adjusted net income | CF28: =CF19+SUM(CF24:CF27) -> 8431.9118 | CG28: =CG19+SUM(CG24:CG27) -> 2284.195 | CH28: =CH19+SUM(CH24:CH27) -> 2467.475 | CI28: =CI19+SUM(CI24:CI27) -> 2476.04 | CJ28: =CJ19+SUM(CJ24:CJ27) -> 2186.875 | CK28: =SUM(CG28:CJ28) -> 9414.585 | CL28: =CL19+SUM(CL24:CL27) -> 2351.3632 | CM28: =CM19+SUM(CM24:CM27) -> 648.1819 | CN28: =CN19+SUM(CN24:CN27) -> 855 | CO28: =CO19+SUM(CO24:CO27) -> 1122 | CP28: =SUM(CL28:CO28) -> 4976.5451 | CQ28: =CQ19+SUM(CQ24:CQ27) -> 1370 | CR28: =CR19+SUM(CR24:CR27) -> 1565 | CS28: =CS19+SUM(CS24:CS27) -> 1896 | CT28: =CT19+SUM(CT24:CT27) -> 1614 | CU28: =SUM(CQ28:CT28) -> 6445 | CV28: =CV19+SUM(CV24:CV27) -> 1723 | CW28: =CW19+SUM(CW24:CW27) -> 1722 | CX28: =CX19+SUM(CX24:CX27) -> 1785 | CY28: =CY19+SUM(CY24:CY27) -> 1868 | CZ28: =SUM(CV28:CY28) -> 7098 | DA28: =DA19+SUM(DA24:DA27) -> 1793 | DB28: =DB19+SUM(DB24:DB27) -> 1895 | DC28: =DC19+SUM(DC24:DC27) -> 1822 | DD28: =DD19+SUM(DD24:DD27) -> 1753 | DE28: =SUM(DA28:DD28) -> 7263 | DF28: =DF19+SUM(DF24:DF27) -> 1791 | DG28: =DG19+SUM(DG24:DG27) -> 1895 | DH28: =DH19+SUM(DH24:DH27) -> 1948 | DI28: =DI19+SUM(DI24:DI27) -> 2071 | DJ28: =SUM(DF28:DI28) -> 7705 | DK28: =DK19+SUM(DK24:DK27) -> 1991 | DL28: =DL19+SUM(DL24:DL27) -> 2118 | DM28: =DM19+SUM(DM24:DM27) -> 2311 | DN28: =DN19+SUM(DN24:DN27) -> 1970.8547 | DO28: =SUM(DK28:DN28) -> 8390.8547 | DP28: =DP19+SUM(DP24:DP27) -> 1999.3086 | DQ28: =DQ19+SUM(DQ24:DQ27) -> 2162.0767 | DR28: =DR19+SUM(DR24:DR27) -> 2371.6816 | DS28: =DS19+SUM(DS24:DS27) -> 2391.5328 | DT28: =SUM(DP28:DS28) -> 8924.5997 | DU28: =DU19+SUM(DU24:DU27) -> 9651.3843 | DV28: =DV19+SUM(DV24:DV27) -> 10456.864
B29: Adjusted EPS | CF29: =CF28/CF33 -> 5.7784483 | CG29: =CG28/CG33 -> 1.5102116 | CH29: =CH28/CH33 -> 1.6313884 | CI29: =CI28/CI33 -> 1.6299388 | CJ29: =CJ28/CJ33 -> 1.4395859 | CK29: =CK28/CK33 -> 6.2109678 | CL29: =CL28/CL33 -> 1.5490897 | CM29: =CM28/CM33 -> 0.43174709 | ... DV29: =DV28/DV33 -> 7.8540367
B31: Common shares outstanding
B32: Basic | CF32: =+Data!CF41 -> 1448.3 | CG32: =+Data!CG41 -> 1501.7 | CH32: =+Data!CH41 -> 1501.7 | CI32: =+Data!CI41 -> 1505.5 | CJ32: =+Data!CJ41 -> 1505.5 | CK32: =Data!CK41 -> 1503.6 | CL32: =Data!CL41 -> 1506.7 | CM32: =Data!CM41 -> 1501.3 | CN32: =Data!CN41 -> 1511.5 | CO32: =Data!CO41 -> 1512.3 | CP32: =Data!CP41 -> 1511.7 | CQ32: =Data!CQ41 -> 1511.1 | CR32: =Data!CR41 -> 1506.4 | ... CT32: =Data!CT41 -> 1490.5 | CU32: =AVERAGE(CQ32:CT32) -> 1501.475 | CV32: =Data!CV41 -> 1486.8 | CW32: =Data!CW41 -> 1479.2 | CX32: =Data!CX41 -> 1470.1 | CY32: =Data!CY41 -> 1465.5 | CZ32: =AVERAGE(CV32:CY32) -> 1475.4 | DA32: =Data!DA41 -> 1462.2 | DB32: =Data!DB41 -> 1457.5 | DC32: =Data!DC41 -> 1448.1 | DD32: =Data!DD41 -> 1354.9 | DE32: =AVERAGE(DA32:DD32) -> 1430.675 | DF32: =Data!DF41 -> 1329.4 | DG32: =Data!DG41 -> 1331.8 | DH32: =Data!DH41 -> 1333.2 | DI32: =Data!DI41 -> 1334.4 | DJ32: =AVERAGE(DF32:DI32) -> 1332.2 | DK32: =Data!DK41 -> 1337.1 | DL32: =Data!DL41 -> 1340.6 | DM32: =Data!DM41 -> 1343.1 | DN32: =DM32+(DN33-DM33) -> 1344.1 | DO32: =AVERAGE(DK32:DN32) -> 1341.225 | DP32: =DN32+(DP33-DN33) -> 1342.1 | DQ32: =DP32+(DQ33-DP33) -> 1339.1 | DR32: =DQ32+(DR33-DQ33) -> 1334.1 | DS32: =DR32+(DS33-DR33) -> 1329.1 | DT32: =AVERAGE(DP32:DS32) -> 1336.1 | DU32: =DT32+(DU33-DT33) -> 1326.1 | DV32: =DU32+(DV33-DU33) -> 1316.1
B33: Diluted | CF33: =+Data!CF42 -> 1459.2 | CG33: =+Data!CG42 -> 1512.5 | CH33: =+Data!CH42 -> 1512.5 | CI33: =+Data!CI42 -> 1519.1 | CJ33: =+Data!CJ42 -> 1519.1 | CK33: =Data!CK42 -> 1515.8 | CL33: =Data!CL42 -> 1517.9 | CM33: =Data!CM42 -> 1501.3 | CN33: =Data!CN42 -> 1514.2 | CO33: =Data!CO42 -> 1515.4 | CP33: =Data!CP42 -> 1511.7 | CQ33: =Data!CQ42 -> 1514.1 | CR33: =Data!CR42 -> 1513.5 | ... CT33: =Data!CT42 -> 1500.2 | CU33: =AVERAGE(CQ33:CT33) -> 1508.425 | CV33: =Data!CV42 -> 1497.9 | CW33: =Data!CW42 -> 1489.6 | CX33: =Data!CX42 -> 1479.3 | CY33: =Data!CY42 -> 1476.3 | CZ33: =AVERAGE(CV33:CY33) -> 1485.775 | DA33: =Data!DA42 -> 1474.2 | DB33: =Data!DB42 -> 1468.7 | DC33: =Data!DC42 -> 1455.7 | DD33: =Data!DD42 -> 1361.7 | DE33: =AVERAGE(DA33:DD33) -> 1440.075 | DF33: =Data!DF42 -> 1337.3 | DG33: =Data!DG42 -> 1342.1 | DH33: =Data!DH42 -> 1346.2 | DI33: =Data!DI42 -> 1348.9 | DJ33: =AVERAGE(DF33:DI33) -> 1343.625 | DK33: =Data!DK42 -> 1351.8 | DL33: =Data!DL42 -> 1354 | DM33: =Data!DM42 -> 1358.4 | DN33: =+DM33+1 -> 1359.4 | DO33: =AVERAGE(DK33:DN33) -> 1355.9 | DP33: =+DN33-2 -> 1357.4 | DQ33: =+DP33-3 -> 1354.4 | DR33: =+DQ33-5 -> 1349.4 | DS33: =+DR33-5 -> 1344.4 | DT33: =AVERAGE(DP33:DS33) -> 1351.4 | DU33: =DT33-10 -> 1341.4 | DV33: =DU33-10 -> 1331.4
B35: Cash Dividend/Share | CF35: =CK35*0.9 -> 1.71 | CG35: 0.475 | CH35: 0.475 | CI35: 0.475 | CJ35: 0.475 | CK35: =SUM(CG35:CJ35) -> 1.9 | CL35: 0.475 | CM35: 0.475 | CN35: 0.475 | CO35: 0.475 | CP35: =SUM(CL35:CO35) -> 1.9 | CQ35: 0.475 | CR35: 0.51 | CS35: =CR35 -> 0.51 | CT35: =CS35 -> 0.51 | CU35: =SUM(CQ35:CT35) -> 2.005 | CV35: =Data!CV236 -> 0.51 | CW35: =Data!CW236 -> 0.55 | CX35: =Data!CX236 -> 0.55 | CY35: =Data!CY236 -> 0.55 | CZ35: =SUM(CV35:CY35) -> 2.16 | DA35: =Data!DA236 -> 0.55 | DB35: =Data!DB236 -> 0.59 | DC35: =Data!DC236 -> 0.59 | DD35: =Data!DD236 -> 0.59 | DE35: =SUM(DA35:DD35) -> 2.32 | DF35: =Data!DF236 -> 0.59 | DG35: =Data!DG236 -> 0.63 | DH35: =Data!DH236 -> 0.63 | DI35: =Data!DI236 -> 0.63 | DJ35: =SUM(DF35:DI35) -> 2.48 | DK35: =Data!DK236 -> 0.63 | DL35: =Data!DL236 -> 0.68 | DM35: =Data!DM236 -> 0.68 | DN35: =+DM35 -> 0.68 | DO35: =SUM(DK35:DN35) -> 2.67 | DP35: 0.68 | DQ35: =+DP35*1.1 -> 0.748 | DR35: =+DQ35 -> 0.748 | DS35: =+DR35 -> 0.748 | DT35: =SUM(DP35:DS35) -> 2.924 | DU35: =DT35*1.1 -> 3.2164 | DV35: =DU35*1.1 -> 3.53804
B36: Dividend payout ratio | CF36: =CF35/CF22 -> 0.33856343 | CG36: =CG35/CG22 -> 0.4415312 | CH36: =CH35/CH22 -> 0.3634254 | CI36: =CI35/CI22 -> 0.36300603 | CJ36: =CJ35/CJ22 -> 0.46218206 | CK36: =CK35/CK22 -> 0.40263106 | CL36: =CL35/CL22 -> 0.41717171 | CM36: =CM35/CM22 -> -0.19243187 | ... DV36: =DV35/DV22 -> 0.52474296
B38: FAS/CAS expense | CF38: =SEG!CF176+CF14 -> 2733 | CK38: =SEG!CK176+CK14 -> 2627 | CP38: =SEG!CP176+CP14 -> 2390 | CU38: =SEG!CU176+CU14 -> 3598 | CZ38: =SEG!CZ176+CZ14 -> 3288 | DE38: =SEG!DE176+DE14 -> 2907 | DJ38: =SEG!DJ176+DJ14 -> 2351 | DO38: =SEG!DO176+DO14 -> 2176 | DT38: =SEG!DT176+DT14 -> 1900 | DU38: =SEG!DU176+DU14 -> 1700 | DV38: =SEG!DV176+DV14 -> 1650
B39: Pension per share | CF39: =CF38*(1-CF54)/CF33 -> 1.5104281 | CK39: =CK38*(1-CK54)/CK33 -> 1.4869965 | CP39: =CP38*(1-0.22)/CP33 -> 1.2331812 | CU39: =CU38*(1-0.22)/CU33 -> 1.8605101 | CZ39: =CZ38*(1-0.22)/CZ33 -> 1.7261295 | DE39: =DE38*(1-0.22)/DE33 -> 1.574543 | DJ39: =DJ38*(1-0.22)/DJ33 -> 1.3648004 | DO39: =DO38*(1-0.22)/DO33 -> 1.2517737 | DT39: =DT38*(1-0.22)/DT33 -> 1.0966405 | DU39: =DU38*(1-DU54)/DU33 -> 1.0265394 | DV39: =DV38*(1-DV54)/DV33 -> 1.0038306
B42: Calculation of Adjusted EBITDA
B43: Adjusted EBIT (with deal amort) | BL43: =SEG!BL178+SEG!BL141 -> 7279.7925 | BM43: =SEG!BM178+SEG!BM141 -> 1840.5605 | BN43: =SEG!BN178+SEG!BN141 -> 1606.7392 | BO43: =SEG!BO178+SEG!BO141 -> 1640.2642 | BP43: =SEG!BP178+SEG!BP141 -> 1811.7592 | BQ43: =SEG!BQ178+SEG!BQ141 -> 6899.323 | BR43: =SEG!BR178+SEG!BR141 -> 1516.6792 | BS43: =SEG!BS178+SEG!BS141 -> 1929.6282 | ... DV43: =SEG!DV178+SEG!DV141 -> 12046.966
B44: D&A | BL44: 2346 | BQ44: 2352 | BV44: 2477 | CA44: 2690 | CF44: =CFLO!CF8+CFLO!CF9-(CFLO!CF9+SEG!CF141) -> 2879.6804 | CG44: =CFLO!CG8+CFLO!CG9 -> 1095.5 | CH44: =CFLO!CH8+CFLO!CH9 -> 1078.5 | CI44: =CFLO!CI8+CFLO!CI9 -> 1088.5 | CJ44: =CFLO!CJ8+CFLO!CJ9 -> 1101.5 | CK44: =CFLO!CK8+CFLO!CK9 -> 4364 | CL44: =CFLO!CL8+CFLO!CL9 -> 728 | CM44: =CFLO!CM8+CFLO!CM9 -> 1111 | CN44: =CFLO!CN8+CFLO!CN9 -> 1164 | ... DV44: =CFLO!DV8+CFLO!DV9 -> 4350
B45: EBITDA | BL45: =BL43+BL44 -> 9625.7925 | BQ45: =BQ43+BQ44 -> 9251.323 | BV45: =BV43+BV44 -> 9560.6193 | CA45: =CA43+CA44 -> 10188.964 | CF45: =CF43+CF44 -> 12657.738 | CG45: =CG43+CG44 -> 3248.5 | CH45: =CH43+CH44 -> 3397.5 | CI45: =CI43+CI44 -> 3473.5 | CJ45: =CJ43+CJ44 -> 3236.5 | CK45: =CK43+CK44 -> 13356 | CL45: =CL43+CL44 -> 2994.6821 | CM45: =CM43+CM44 -> 1550.6381 | ... DV45: =DV43+DV44 -> 16396.966
B48: Margin analysis
B49: Gross margin | CF49: =IF(ISERROR(CF8/CF6),"",(CF8/CF6)) -> 0.25306566 | CG49: =IF(ISERROR(CG8/CG6),"",(CG8/CG6)) -> 0.22384783 | CH49: =IF(ISERROR(CH8/CH6),"",(CH8/CH6)) -> 0.23925594 | CI49: =IF(ISERROR(CI8/CI6),"",(CI8/CI6)) -> 0.24054452 | CJ49: =IF(ISERROR(CJ8/CJ6),"",(CJ8/CJ6)) -> 0.21447705 | CK49: =IF(ISERROR(CK8/CK6),"",(CK8/CK6)) -> 0.2294139 | CL49: =IF(ISERROR(CL8/CL6),"",(CL8/CL6)) -> 0.22904862 | CM49: =IF(ISERROR(CM8/CM6),"",(CM8/CM6)) -> -0.080775266 | ... DV49: =IF(ISERROR(DV8/DV6),"",(DV8/DV6)) -> 0.22366631
B50: SG&A | CF50: =IF(ISERROR(-CF10/CF6),"",(-CF10/CF6)) -> 0.080278147 | CG50: =IF(ISERROR(-CG10/CG6),"",(-CG10/CG6)) -> 0.077447989 | CH50: =IF(ISERROR(-CH10/CH6),"",(-CH10/CH6)) -> 0.077447989 | CI50: =IF(ISERROR(-CI10/CI6),"",(-CI10/CI6)) -> 0.077539477 | CJ50: =IF(ISERROR(-CJ10/CJ6),"",(-CJ10/CJ6)) -> 0.077539477 | CK50: =IF(ISERROR(-CK10/CK6),"",(-CK10/CK6)) -> 0.07749505 | CL50: 0.08 | CM50: =IF(ISERROR(-CM10/CM6),"",(-CM10/CM6)) -> 0.12515549 | CN50: =IF(ISERROR(-CN10/CN6),"",(-CN10/CN6)) -> 0.095002373 | CO50: =IF(ISERROR(-CO10/CO6),"",(-CO10/CO6)) -> 0.082282721 | CP50: =IF(ISERROR(-CP10/CP6),"",(-CP10/CP6)) -> 0.094232528 | CQ50: =IF(ISERROR(-CQ10/CQ6),"",(-CQ10/CQ6)) -> 0.079994754 | CR50: =IF(ISERROR(-CR10/CR6),"",(-CR10/CR6)) -> 0.086146096 | CS50: =IF(ISERROR(-CS10/CS6),"",(-CS10/CS6)) -> 0.075803368 | CT50: =IF(ISERROR(-CT10/CT6),"",(-CT10/CT6)) -> 0.082551044 | ... DM50: =IF(ISERROR(-DM10/DM6),"",(-DM10/DM6)) -> 0.063884687 | DN50: 0.075 | DO50: =IF(ISERROR(-DO10/DO6),"",(-DO10/DO6)) -> 0.070741122 | DP50: 0.075 | DQ50: 0.075 | DR50: 0.075 | DS50: 0.075 | DT50: =IF(ISERROR(-DT10/DT6),"",(-DT10/DT6)) -> 0.075 | DU50: 0.075 | DV50: 0.075
B51: R&D | CF51: =IF(ISERROR(-CF9/CF6),"",(-CF9/CF6)) -> 0.047013242 | CG51: =IF(ISERROR(-CG9/CG6),"",(-CG9/CG6)) -> 0.044105409 | CH51: =IF(ISERROR(-CH9/CH6),"",(-CH9/CH6)) -> 0.044105409 | CI51: =IF(ISERROR(-CI9/CI6),"",(-CI9/CI6)) -> 0.041794328 | CJ51: =IF(ISERROR(-CJ9/CJ6),"",(-CJ9/CJ6)) -> 0.041794328 | CK51: =IF(ISERROR(-CK9/CK6),"",(-CK9/CK6)) -> 0.042916605 | CL51: 0.035 | CM51: =IF(ISERROR(-CM9/CM6),"",(-CM9/CM6)) -> 0.048030408 | CN51: =IF(ISERROR(-CN9/CN6),"",(-CN9/CN6)) -> 0.043534278 | CO51: =IF(ISERROR(-CO9/CO6),"",(-CO9/CO6)) -> 0.043242585 | CP51: =IF(ISERROR(-CP9/CP6),"",(-CP9/CP6)) -> 0.042017648 | CQ51: =IF(ISERROR(-CQ9/CQ6),"",(-CQ9/CQ6)) -> 0.038620418 | CR51: =IF(ISERROR(-CR9/CR6),"",(-CR9/CR6)) -> 0.041372796 | CS51: =IF(ISERROR(-CS9/CS6),"",(-CS9/CS6)) -> 0.041694936 | CT51: =IF(ISERROR(-CT9/CT6),"",(-CT9/CT6)) -> 0.047524055 | ... DM51: =IF(ISERROR(-DM9/DM6),"",(-DM9/DM6)) -> 0.030429754 | DN51: 0.035 | DO51: =IF(ISERROR(-DO9/DO6),"",(-DO9/DO6)) -> 0.032300363 | DP51: 0.035 | DQ51: 0.035 | DR51: 0.035 | DS51: 0.035 | DT51: =IF(ISERROR(-DT9/DT6),"",(-DT9/DT6)) -> 0.035 | DU51: 0.035 | DV51: 0.035
B52: Adj EBITDA margin | BL52: =IF(ISERROR(BL45/SEG!BL62),"",(BL45/SEG!BL62)) -> 0.19008279 | BQ52: =IF(ISERROR(BQ45/SEG!BQ62),"",(BQ45/SEG!BQ62)) -> 0.18296264 | BV52: =IF(ISERROR(BV45/SEG!BV62),"",(BV45/SEG!BV62)) -> 0.18186801 | CA52: =IF(ISERROR(CA45/SEG!CA62),"",(CA45/SEG!CA62)) -> 0.18385991 | CF52: =IF(ISERROR(CF45/CF6),"",(CF45/CF6)) -> 0.18298933 | CG52: =IF(ISERROR(CG45/CG6),"",(CG45/CG6)) -> 0.18389991 | CH52: =IF(ISERROR(CH45/CH6),"",(CH45/CH6)) -> 0.18479236 | CI52: =IF(ISERROR(CI45/CI6),"",(CI45/CI6)) -> 0.18563321 | CJ52: =IF(ISERROR(CJ45/CJ6),"",(CJ45/CJ6)) -> 0.16618426 | CK52: =IF(ISERROR(CK45/CK6),"",(CK45/CK6)) -> 0.17991029 | CL52: =IF(ISERROR(CL45/CL6),"",(CL45/CL6)) -> 0.1623046 | CM52: =IF(ISERROR(CM45/CM6),"",(CM45/CM6)) -> 0.10716227 | ... DV52: =IF(ISERROR(DV45/DV6),"",(DV45/DV6)) -> 0.15732152
B53: EBIT margin | CF53: =IF(ISERROR(CF13/CF6),"",(CF13/CF6)) -> 0.13064618 | CG53: =IF(ISERROR(CG13/CG6),"",(CG13/CG6)) -> 0.1077868 | CH53: =IF(ISERROR(CH13/CH6),"",(CH13/CH6)) -> 0.12319491 | CI53: =IF(ISERROR(CI13/CI6),"",(CI13/CI6)) -> 0.12526969 | CJ53: =IF(ISERROR(CJ13/CJ6),"",(CJ13/CJ6)) -> 0.099202223 | CK53: =IF(ISERROR(CK13/CK6),"",(CK13/CK6)) -> 0.11375729 | CL53: =IF(ISERROR(CL13/CL6),"",(CL13/CL6)) -> 0.11811344 | CM53: =IF(ISERROR(CM13/CM6),"",(CM13/CM6)) -> -0.24829427 | ... DV53: =IF(ISERROR(DV13/DV6),"",(DV13/DV6)) -> 0.11558522
B54: Effective tax rate | CF54: =IF(ISERROR(-CF17/CF16),"",(-CF17/CF16)) -> 0.1935541 | CG54: =IF(ISERROR(-CG17/CG16),"",(-CG17/CG16)) -> 0.15109528 | CH54: =IF(ISERROR(-CH17/CH16),"",(-CH17/CH16)) -> 0.13271498 | CI54: =IF(ISERROR(-CI17/CI16),"",(-CI17/CI16)) -> 0.12772156 | CJ54: =IF(ISERROR(-CJ17/CJ16),"",(-CJ17/CJ16)) -> 0.16121235 | CK54: =IF(ISERROR(-CK17/CK16),"",(-CK17/CK16)) -> 0.14199114 | CL54: =IF(ISERROR(-CL17/CL16),"",(-CL17/CL16)) -> 0.19016833 | CM54: =IF(ISERROR(-CM17/CM16),"",(-CM17/CM16)) -> 0.0062081321 | ... DM54: =IF(ISERROR(-DM17/DM16),"",(-DM17/DM16)) -> 0.17719442 | DN54: 0.24 | DO54: =IF(ISERROR(-DO17/DO16),"",(-DO17/DO16)) -> 0.18634736 | DP54: 0.19 | DQ54: 0.19 | DR54: 0.19 | DS54: 0.19 | DT54: =IF(ISERROR(-DT17/DT16),"",(-DT17/DT16)) -> 0.19 | DU54: 0.19 | DV54: 0.19
B55: Adjusted tax rate | CL55: =-(CL27+CL17)/(CL28-CL27-CL17-CL18) -> 0.19207867 | CM55: =-(CM27+CM17)/(CM28-CM27-CM17-CM18) -> 0.23019259 | CN55: =-(CN27+CN17)/(CN28-CN27-CN17-CN18) -> 0.17070896 | CO55: =-(CO27+CO17)/(CO28-CO27-CO17-CO18) -> -0.72608696 | CP55: =-(CP27+CP17)/(CP28-CP27-CP17-CP18) -> 0.081094636 | CQ55: =-(CQ27+CQ17)/(CQ28-CQ27-CQ17-CQ18) -> 0.19001148 | CR55: =-(CR27+CR17)/(CR28-CR27-CR17-CR18) -> 0.19551122 | CS55: =-(CS27+CS17)/(CS28-CS27-CS17-CS18) -> 0.06814955 | ... DV55: =-(DV27+DV17)/(DV28-DV27-DV17-DV18) -> 0.19138106
B56: Net margin | CF56: =IF(ISERROR(CF19/CF6),"",(CF19/CF6)) -> 0.10654683 | CG56: =IF(ISERROR(CG19/CG6),"",(CG19/CG6)) -> 0.092114127 | CH56: =IF(ISERROR(CH19/CH6),"",(CH19/CH6)) -> 0.10752223 | CI56: =IF(ISERROR(CI19/CI6),"",(CI19/CI6)) -> 0.10623179 | CJ56: =IF(ISERROR(CJ19/CJ6),"",(CJ19/CJ6)) -> 0.080164331 | CK56: =IF(ISERROR(CK19/CK6),"",(CK19/CK6)) -> 0.09635357 | CL56: =IF(ISERROR(CL19/CL6),"",(CL19/CL6)) -> 0.093670322 | CM56: =IF(ISERROR(CM19/CM6),"",(CM19/CM6)) -> -0.25610353 | ... DV56: =IF(ISERROR(DV19/DV6),"",(DV19/DV6)) -> 0.086128981
B58: Y/Y growth
B59: Revenue | CF59: =IF(ISERROR(CF6/CA6-1),"",(CF6/CA6-1)) -> 0.24820903 | CG59: =IF(ISERROR(CG6/CB6-1),"",(CG6/CB6-1)) | CH59: =IF(ISERROR(CH6/CC6-1),"",(CH6/CC6-1)) | CI59: =IF(ISERROR(CI6/CD6-1),"",(CI6/CD6-1)) | CJ59: =IF(ISERROR(CJ6/CE6-1),"",(CJ6/CE6-1)) | CK59: =IF(ISERROR(CK6/CF6-1),"",(CK6/CF6-1)) -> 0.07322327 | CL59: =IF(ISERROR(CL6/CG6-1),"",(CL6/CG6-1)) -> 0.044524328 | CM59: =IF(ISERROR(CM6/CH6-1),"",(CM6/CH6-1)) -> -0.21296674 | ... DT59: =IF(ISERROR(DT6/DO6-1),"",(DT6/DO6-1)) -> 0.060051086 | DU59: =IF(ISERROR(DU6/DT6-1),"",(DU6/DT6-1)) -> 0.066657452 | DV59: =IF(ISERROR(DV6/DU6-1),"",(DV6/DU6-1)) -> 0.059929888
B60: EBITDA | CF60: =IF(ISERROR(CF45/CA45-1),"",(CF45/CA45-1)) -> 0.24229877 | CG60: =IF(ISERROR(CG45/CB45-1),"",(CG45/CB45-1)) | CH60: =IF(ISERROR(CH45/CC45-1),"",(CH45/CC45-1)) | CI60: =IF(ISERROR(CI45/CD45-1),"",(CI45/CD45-1)) | CJ60: =IF(ISERROR(CJ45/CE45-1),"",(CJ45/CE45-1)) | CK60: =IF(ISERROR(CK45/CF45-1),"",(CK45/CF45-1)) -> 0.055164827 | CL60: =IF(ISERROR(CL45/CG45-1),"",(CL45/CG45-1)) -> -0.078133863 | CM60: =IF(ISERROR(CM45/CH45-1),"",(CM45/CH45-1)) -> -0.54359438 | ... DT60: =IF(ISERROR(DT45/DO45-1),"",(DT45/DO45-1)) -> 0.049832095 | DU60: =IF(ISERROR(DU45/DT45-1),"",(DU45/DT45-1)) -> 0.071672139 | DV60: =IF(ISERROR(DV45/DU45-1),"",(DV45/DU45-1)) -> 0.069138081
B61: EBIT | CF61: =IF(ISERROR(CF43/CA43-1),"",(CF43/CA43-1)) -> 0.30392105 | CG61: =IF(ISERROR(CG43/CB43-1),"",(CG43/CB43-1)) -> -0.099782926 | CH61: =IF(ISERROR(CH43/CC43-1),"",(CH43/CC43-1)) -> -0.017338444 | CI61: =IF(ISERROR(CI43/CD43-1),"",(CI43/CD43-1)) -> -0.032055794 | CJ61: =IF(ISERROR(CJ43/CE43-1),"",(CJ43/CE43-1)) -> -0.16683251 | CK61: =IF(ISERROR(CK43/CF43-1),"",(CK43/CF43-1)) -> -0.080389957 | CL61: =IF(ISERROR(CL43/CG43-1),"",(CL43/CG43-1)) -> 0.05280174 | CM61: =IF(ISERROR(CM43/CH43-1),"",(CM43/CH43-1)) -> -0.8104191 | ... DT61: =IF(ISERROR(DT43/DO43-1),"",(DT43/DO43-1)) -> 0.07309795 | DU61: =IF(ISERROR(DU43/DT43-1),"",(DU43/DT43-1)) -> 0.1002594 | DV61: =IF(ISERROR(DV43/DU43-1),"",(DV43/DU43-1)) -> 0.091544735
B62: Net income | CF62: =IF(ISERROR(CF19/CA19-1),"",(CF19/CA19-1)) | CG62: =IF(ISERROR(CG19/CB19-1),"",(CG19/CB19-1)) | CH62: =IF(ISERROR(CH19/CC19-1),"",(CH19/CC19-1)) | CI62: =IF(ISERROR(CI19/CD19-1),"",(CI19/CD19-1)) | CJ62: =IF(ISERROR(CJ19/CE19-1),"",(CJ19/CE19-1)) | CK62: =IF(ISERROR(CK19/CF19-1),"",(CK19/CF19-1)) -> -0.02945128 | CL62: =IF(ISERROR(CL19/CG19-1),"",(CL19/CG19-1)) -> 0.062170735 | CM62: =IF(ISERROR(CM19/CH19-1),"",(CM19/CH19-1)) -> -2.8746076 | ... DT62: =IF(ISERROR(DT19/DO19-1),"",(DT19/DO19-1)) -> 0.10584315 | DU62: =IF(ISERROR(DU19/DT19-1),"",(DU19/DT19-1)) -> 0.10117572 | DV62: =IF(ISERROR(DV19/DU19-1),"",(DV19/DU19-1)) -> 0.098573286
B63: Diluted EPS, continuing | CF63: =IF(ISERROR(CF22/CA22-1),"",(CF22/CA22-1)) | CG63: =IF(ISERROR(CG22/CB22-1),"",(CG22/CB22-1)) | CH63: =IF(ISERROR(CH22/CC22-1),"",(CH22/CC22-1)) | CI63: =IF(ISERROR(CI22/CD22-1),"",(CI22/CD22-1)) | CJ63: =IF(ISERROR(CJ22/CE22-1),"",(CJ22/CE22-1)) | CK63: =IF(ISERROR(CK22/CF22-1),"",(CK22/CF22-1)) -> -0.065691587 | CL63: =IF(ISERROR(CL22/CG22-1),"",(CL22/CG22-1)) -> 0.058392013 | CM63: =IF(ISERROR(CM22/CH22-1),"",(CM22/CH22-1)) -> -2.8885926 | ... DT63: =IF(ISERROR(DT22/DO22-1),"",(DT22/DO22-1)) -> 0.10952547 | DU63: =IF(ISERROR(DU22/DT22-1),"",(DU22/DT22-1)) -> 0.10938488 | DV63: =IF(ISERROR(DV22/DU22-1),"",(DV22/DU22-1)) -> 0.10682455
B65: Q/Q growth
B66: Revenue | CG66: =IF(ISERROR(CG6/CE6-1),"",(CG6/CE6-1)) | CH66: =IF(ISERROR(CH6/CG6-1),"",(CH6/CG6-1)) -> 0.040816327 | CI66: =IF(ISERROR(CI6/CH6-1),"",(CI6/CH6-1)) -> 0.017738435 | CJ66: =IF(ISERROR(CJ6/CI6-1),"",(CJ6/CI6-1)) -> 0.040816327 | CL66: =IF(ISERROR(CL6/CJ6-1),"",(CL6/CJ6-1)) -> -0.05259823 | CM66: =IF(ISERROR(CM6/CL6-1),"",(CM6/CL6-1)) -> -0.21576066 | CN66: =IF(ISERROR(CN6/CM6-1),"",(CN6/CM6-1)) -> 0.019143055 | CO66: =IF(ISERROR(CO6/CN6-1),"",(CO6/CN6-1)) -> 0.11337899 | CQ66: =IF(ISERROR(CQ6/CO6-1),"",(CQ6/CO6-1)) -> -0.071137097 | CR66: =IF(ISERROR(CR6/CQ6-1),"",(CR6/CQ6-1)) -> 0.041243197 | CS66: =IF(ISERROR(CS6/CR6-1),"",(CS6/CR6-1)) -> 0.020969773 | CT66: =IF(ISERROR(CT6/CS6-1),"",(CT6/CS6-1)) -> 0.051255166 | CV66: =IF(ISERROR(CV6/CT6-1),"",(CV6/CT6-1)) -> -0.077915982 | CW66: =IF(ISERROR(CW6/CV6-1),"",(CW6/CV6-1)) -> 0.038050395 | CX66: =IF(ISERROR(CX6/CW6-1),"",(CX6/CW6-1)) -> 0.039046218 | CY66: =IF(ISERROR(CY6/CX6-1),"",(CY6/CX6-1)) -> 0.067370657 | DA66: =IF(ISERROR(DA6/CY6-1),"",(DA6/CY6-1)) -> -0.048582325 | DB66: =IF(ISERROR(DB6/DA6-1),"",(DB6/DA6-1)) -> 0.063959568 | DC66: =IF(ISERROR(DC6/DB6-1),"",(DC6/DB6-1)) -> -0.26486486 | DD66: =IF(ISERROR(DD6/DC6-1),"",(DD6/DC6-1)) -> 0.4800208 | DF66: =IF(ISERROR(DF6/DD6-1),"",(DF6/DD6-1)) -> -0.031213931 | DG66: =IF(ISERROR(DG6/DE6-1),"",(DG6/DE6-1)) -> -0.71385665 | DH66: =IF(ISERROR(DH6/DG6-1),"",(DH6/DG6-1)) -> 0.018660311 | DI66: =IF(ISERROR(DI6/DH6-1),"",(DI6/DH6-1)) -> 0.076360197 | DK66: =IF(ISERROR(DK6/DI6-1),"",(DK6/DI6-1)) -> -0.060907367 | DL66: =IF(ISERROR(DL6/DK6-1),"",(DL6/DK6-1)) -> 0.062789323 | DM66: =IF(ISERROR(DM6/DL6-1),"",(DM6/DL6-1)) -> 0.041564339 | DN66: =IF(ISERROR(DN6/DM6-1),"",(DN6/DM6-1)) -> 0.0054449239 | DP66: =IF(ISERROR(DP6/DO6-1),"",(DP6/DO6-1)) -> -0.75378608 | DQ66: =IF(ISERROR(DQ6/DP6-1),"",(DQ6/DP6-1)) -> 0.058286977 | DR66: =IF(ISERROR(DR6/DQ6-1),"",(DR6/DQ6-1)) -> 0.054033745 | DS66: =IF(ISERROR(DS6/DR6-1),"",(DS6/DR6-1)) -> 0.014504571
B67: EBITDA | CG67: =IF(ISERROR(CG45/CE45-1),"",(CG45/CE45-1)) | CH67: =IF(ISERROR(CH45/CG45-1),"",(CH45/CG45-1)) -> 0.045867323 | CI67: =IF(ISERROR(CI45/CH45-1),"",(CI45/CH45-1)) -> 0.022369389 | CJ67: =IF(ISERROR(CJ45/CI45-1),"",(CJ45/CI45-1)) -> -0.068230891 | CL67: =IF(ISERROR(CL45/CJ45-1),"",(CL45/CJ45-1)) -> -0.074715852 | CM67: =IF(ISERROR(CM45/CL45-1),"",(CM45/CL45-1)) -> -0.48220277 | CN67: =IF(ISERROR(CN45/CM45-1),"",(CN45/CM45-1)) -> 0.25067833 | CO67: =IF(ISERROR(CO45/CN45-1),"",(CO45/CN45-1)) -> -0.046417222 | CQ67: =IF(ISERROR(CQ45/CO45-1),"",(CQ45/CO45-1)) -> 0.23109449 | CR67: =IF(ISERROR(CR45/CQ45-1),"",(CR45/CQ45-1)) -> 0.096978481 | CS67: =IF(ISERROR(CS45/CR45-1),"",(CS45/CR45-1)) -> -0.011815812 | CT67: =IF(ISERROR(CT45/CS45-1),"",(CT45/CS45-1)) -> 0.034378617 | CV67: =IF(ISERROR(CV45/CT45-1),"",(CV45/CT45-1)) -> -0.040279707 | CW67: =IF(ISERROR(CW45/CV45-1),"",(CW45/CV45-1)) -> 0.0085714286 | CX67: =IF(ISERROR(CX45/CW45-1),"",(CX45/CW45-1)) -> 0.048563335 | CY67: =IF(ISERROR(CY45/CX45-1),"",(CY45/CX45-1)) -> 0.0096487843 | DA67: =IF(ISERROR(DA45/CY45-1),"",(DA45/CY45-1)) -> 0.029816514 | DB67: =IF(ISERROR(DB45/DA45-1),"",(DB45/DA45-1)) -> 0.038604306 | DC67: =IF(ISERROR(DC45/DB45-1),"",(DC45/DB45-1)) -> -0.0046461758 | DD67: =IF(ISERROR(DD45/DC45-1),"",(DD45/DC45-1)) -> 0.016517056 | DF67: =IF(ISERROR(DF45/DD45-1),"",(DF45/DD45-1)) -> 0.0070646415 | DG67: =IF(ISERROR(DG45/DE45-1),"",(DG45/DE45-1)) -> -0.67302845 | DH67: =IF(ISERROR(DH45/DG45-1),"",(DH45/DG45-1)) -> -0.016244493 | DI67: =IF(ISERROR(DI45/DH45-1),"",(DI45/DH45-1)) -> 0.11698853 | DK67: =IF(ISERROR(DK45/DI45-1),"",(DK45/DI45-1)) -> -0.18692057 | DL67: =IF(ISERROR(DL45/DK45-1),"",(DL45/DK45-1)) -> 0.042218798 | DM67: =IF(ISERROR(DM45/DL45-1),"",(DM45/DL45-1)) -> 0.049674749 | DN67: =IF(ISERROR(DN45/DM45-1),"",(DN45/DM45-1)) -> -0.045455317 | DP67: =IF(ISERROR(DP45/DO45-1),"",(DP45/DO45-1)) -> -0.75946074 | DQ67: =IF(ISERROR(DQ45/DP45-1),"",(DQ45/DP45-1)) -> 0.065384782 | DR67: =IF(ISERROR(DR45/DQ45-1),"",(DR45/DQ45-1)) -> 0.075584467 | DS67: =IF(ISERROR(DS45/DR45-1),"",(DS45/DR45-1)) -> 0.0063585606
B68: EBIT | CG68: =IF(ISERROR(CG43/CE43-1),"",(CG43/CE43-1)) -> -0.15980815 | CH68: =IF(ISERROR(CH43/CG43-1),"",(CH43/CG43-1)) -> 0.077101719 | CI68: =IF(ISERROR(CI43/CH43-1),"",(CI43/CH43-1)) -> 0.028460543 | CJ68: =IF(ISERROR(CJ43/CI43-1),"",(CJ43/CI43-1)) -> -0.1048218 | CL68: =IF(ISERROR(CL43/CJ43-1),"",(CL43/CJ43-1)) -> 0.06167782 | CM68: =IF(ISERROR(CM43/CL43-1),"",(CM43/CL43-1)) -> -0.80604333 | CN68: =IF(ISERROR(CN43/CM43-1),"",(CN43/CM43-1)) -> 0.76360843 | CO68: =IF(ISERROR(CO43/CN43-1),"",(CO43/CN43-1)) -> -0.10191432 | CQ68: =IF(ISERROR(CQ43/CO43-1),"",(CQ43/CO43-1)) -> 0.65682917 | CR68: =IF(ISERROR(CR43/CQ43-1),"",(CR43/CQ43-1)) -> 0.18357535 | CS68: =IF(ISERROR(CS43/CR43-1),"",(CS43/CR43-1)) -> -0.040651955 | CT68: =IF(ISERROR(CT43/CS43-1),"",(CT43/CS43-1)) -> 0.075455872 | CV68: =IF(ISERROR(CV43/CT43-1),"",(CV43/CT43-1)) -> 0.019287584 | CW68: =IF(ISERROR(CW43/CV43-1),"",(CW43/CV43-1)) -> 0.025069638 | CX68: =IF(ISERROR(CX43/CW43-1),"",(CX43/CW43-1)) -> 0.048913043 | CY68: =IF(ISERROR(CY43/CX43-1),"",(CY43/CX43-1)) -> 0.015544041 | DA68: =IF(ISERROR(DA43/CY43-1),"",(DA43/CY43-1)) -> 0.058673469 | DB68: =IF(ISERROR(DB43/DA43-1),"",(DB43/DA43-1)) -> 0.056626506 | DC68: =IF(ISERROR(DC43/DB43-1),"",(DC43/DB43-1)) -> -0.024515393 | DD68: =IF(ISERROR(DD43/DC43-1),"",(DD43/DC43-1)) -> 0.035651666 | DF68: =IF(ISERROR(DF43/DD43-1),"",(DF43/DD43-1)) -> 0.011286682 | DG68: =IF(ISERROR(DG43/DE43-1),"",(DG43/DE43-1)) -> -0.62882413 | DH68: =IF(ISERROR(DH43/DG43-1),"",(DH43/DG43-1)) -> -0.031640625 | DI68: =IF(ISERROR(DI43/DH43-1),"",(DI43/DH43-1)) -> 0.1504639 | DK68: =IF(ISERROR(DK43/DI43-1),"",(DK43/DI43-1)) -> -0.23106592 | DL68: =IF(ISERROR(DL43/DK43-1),"",(DL43/DK43-1)) -> 0.051527588 | DM68: =IF(ISERROR(DM43/DL43-1),"",(DM43/DL43-1)) -> 0.066348656 | DN68: =IF(ISERROR(DN43/DM43-1),"",(DN43/DM43-1)) -> -0.055049359 | DP68: =IF(ISERROR(DP43/DO43-1),"",(DP43/DO43-1)) -> -0.7636896 | DQ68: =IF(ISERROR(DQ43/DP43-1),"",(DQ43/DP43-1)) -> 0.097056815 | DR68: =IF(ISERROR(DR43/DQ43-1),"",(DR43/DQ43-1)) -> 0.10895804 | DS68: =IF(ISERROR(DS43/DR43-1),"",(DS43/DR43-1)) -> 0.00889027
B69: Net income | CG69: =IF(ISERROR(CG19/CE19-1),"",(CG19/CE19-1)) | CH69: =IF(ISERROR(CH19/CG19-1),"",(CH19/CG19-1)) -> 0.21491565 | CI69: =IF(ISERROR(CI19/CH19-1),"",(CI19/CH19-1)) -> 0.0055239396 | CJ69: =IF(ISERROR(CJ19/CI19-1),"",(CJ19/CI19-1)) -> -0.21458217 | CL69: =IF(ISERROR(CL19/CJ19-1),"",(CL19/CJ19-1)) -> 0.1070189 | CM69: =IF(ISERROR(CM19/CL19-1),"",(CM19/CL19-1)) -> -3.1441846 | CN69: =IF(ISERROR(CN19/CM19-1),"",(CN19/CM19-1)) -> -1.0407467 | CO69: =IF(ISERROR(CO19/CN19-1),"",(CO19/CN19-1)) -> -0.033112583 | CQ69: =IF(ISERROR(CQ19/CO19-1),"",(CQ19/CO19-1)) -> 4.2876712 | CR69: =IF(ISERROR(CR19/CQ19-1),"",(CR19/CQ19-1)) -> 0.34715026 | CS69: =IF(ISERROR(CS19/CR19-1),"",(CS19/CR19-1)) -> 0.34615385 | CT69: =IF(ISERROR(CT19/CS19-1),"",(CT19/CS19-1)) -> -0.51071429 | CV69: =IF(ISERROR(CV19/CT19-1),"",(CV19/CT19-1)) -> 0.61021898 | CW69: =IF(ISERROR(CW19/CV19-1),"",(CW19/CV19-1)) -> 0.18223028 | CX69: =IF(ISERROR(CX19/CW19-1),"",(CX19/CW19-1)) -> 0.063650307 | CY69: =IF(ISERROR(CY19/CX19-1),"",(CY19/CX19-1)) -> 0.025234319 | DA69: =IF(ISERROR(DA19/CY19-1),"",(DA19/CY19-1)) -> 0.0028129395 | DB69: =IF(ISERROR(DB19/DA19-1),"",(DB19/DA19-1)) -> -0.069424965 | DC69: =IF(ISERROR(DC19/DB19-1),"",(DC19/DB19-1)) -> -1.7415222 | DD69: =IF(ISERROR(DD19/DC19-1),"",(DD19/DC19-1)) -> -2.449187 | DF69: =IF(ISERROR(DF19/DD19-1),"",(DF19/DD19-1)) -> 0.19845722 | DG69: =IF(ISERROR(DG19/DE19-1),"",(DG19/DE19-1)) -> -0.96525822 | DH69: =IF(ISERROR(DH19/DG19-1),"",(DH19/DG19-1)) -> 12.261261 | DI69: =IF(ISERROR(DI19/DH19-1),"",(DI19/DH19-1)) -> 0.0067934783 | DK69: =IF(ISERROR(DK19/DI19-1),"",(DK19/DI19-1)) -> 0.035762483 | DL69: =IF(ISERROR(DL19/DK19-1),"",(DL19/DK19-1)) -> 0.079478827 | DM69: =IF(ISERROR(DM19/DL19-1),"",(DM19/DL19-1)) -> 0.15751358 | DN69: =IF(ISERROR(DN19/DM19-1),"",(DN19/DM19-1)) -> -0.16561278 | DP69: =IF(ISERROR(DP19/DO19-1),"",(DP19/DO19-1)) -> -0.758089 | DQ69: =IF(ISERROR(DQ19/DP19-1),"",(DQ19/DP19-1)) -> 0.10026932 | DR69: =IF(ISERROR(DR19/DQ19-1),"",(DR19/DQ19-1)) -> 0.11735495 | DS69: =IF(ISERROR(DS19/DR19-1),"",(DS19/DR19-1)) -> 0.0099470694
B70: Diluted EPS, continuing | CG70: =IF(ISERROR(CG22/CE22-1),"",(CG22/CE22-1)) | CH70: =IF(ISERROR(CH22/CG22-1),"",(CH22/CG22-1)) -> 0.21491565 | CI70: =IF(ISERROR(CI22/CH22-1),"",(CI22/CH22-1)) -> 0.0011552621 | CJ70: =IF(ISERROR(CJ22/CI22-1),"",(CJ22/CI22-1)) -> -0.21458217 | CL70: =IF(ISERROR(CL22/CJ22-1),"",(CL22/CJ22-1)) -> 0.10789407 | CM70: =IF(ISERROR(CM22/CL22-1),"",(CM22/CL22-1)) -> -3.167893 | CN70: =IF(ISERROR(CN22/CM22-1),"",(CN22/CM22-1)) -> -1.0403996 | CO70: =IF(ISERROR(CO22/CN22-1),"",(CO22/CN22-1)) -> -0.033878232 | CQ70: =IF(ISERROR(CQ22/CO22-1),"",(CQ22/CO22-1)) -> 4.2922112 | CR70: =IF(ISERROR(CR22/CQ22-1),"",(CR22/CQ22-1)) -> 0.34768431 | CS70: =IF(ISERROR(CS22/CR22-1),"",(CS22/CR22-1)) -> 0.35294764 | CT70: =IF(ISERROR(CT22/CS22-1),"",(CT22/CS22-1)) -> -0.50885525 | CV70: =IF(ISERROR(CV22/CT22-1),"",(CV22/CT22-1)) -> 0.61269144 | CW70: =IF(ISERROR(CW22/CV22-1),"",(CW22/CV22-1)) -> 0.18881763 | CX70: =IF(ISERROR(CX22/CW22-1),"",(CX22/CW22-1)) -> 0.071056241 | CY70: =IF(ISERROR(CY22/CX22-1),"",(CY22/CX22-1)) -> 0.027317705 | DA70: =IF(ISERROR(DA22/CY22-1),"",(DA22/CY22-1)) -> 0.004241448 | DB70: =IF(ISERROR(DB22/DA22-1),"",(DB22/DA22-1)) -> -0.06594014 | DC70: =IF(ISERROR(DC22/DB22-1),"",(DC22/DB22-1)) -> -1.7481443 | DD70: =IF(ISERROR(DD22/DC22-1),"",(DD22/DC22-1)) -> -2.5492263 | DF70: =IF(ISERROR(DF22/DD22-1),"",(DF22/DD22-1)) -> 0.22032394 | DG70: =IF(ISERROR(DG22/DE22-1),"",(DG22/DE22-1)) -> -0.96272202 | DH70: =IF(ISERROR(DH22/DG22-1),"",(DH22/DG22-1)) -> 12.220873 | DI70: =IF(ISERROR(DI22/DH22-1),"",(DI22/DH22-1)) -> 0.0047782493 | DK70: =IF(ISERROR(DK22/DI22-1),"",(DK22/DI22-1)) -> 0.033540475 | DL70: =IF(ISERROR(DL22/DK22-1),"",(DL22/DK22-1)) -> 0.077724874 | DM70: =IF(ISERROR(DM22/DL22-1),"",(DM22/DL22-1)) -> 0.15376427 | DN70: =IF(ISERROR(DN22/DM22-1),"",(DN22/DM22-1)) -> -0.16622657 | DP70: =IF(ISERROR(DP22/DO22-1),"",(DP22/DO22-1)) -> -0.75835632 | DQ70: =IF(ISERROR(DQ22/DP22-1),"",(DQ22/DP22-1)) -> 0.10270642 | DR70: =IF(ISERROR(DR22/DQ22-1),"",(DR22/DQ22-1)) -> 0.12149514 | DS70: =IF(ISERROR(DS22/DR22-1),"",(DS22/DR22-1)) -> 0.013703195

Sheet BS
B3: RTX Balance Sheet | C3: 1997 | D3: 1998 | E3: 1999 | F3: 2000 | G3: 2001 | H3: 2002 | I3: 2003 | J3: 1Q04 | K3: 2Q04 | L3: 3Q04 | M3: 4Q04 | N3: 2004 | O3: 1Q05 | P3: 2Q05 | Q3: 3Q05 | R3: 4Q05 | S3: 2005 | T3: 1Q06 | U3: 2Q06 | V3: 3Q06 | W3: 4Q06 | X3: 2006 | Y3: 1Q07 | Z3: 2Q07 | AA3: 3Q07 | AB3: 4Q07 | AC3: 2007 | AD3: 1Q08 | AE3: 2Q08 | AF3: 3Q08 | AG3: 4Q08 | AH3: 2008 | AI3: 1Q09 | AJ3: 2Q09 | AK3: 3Q09 | AL3: 4Q09 | AM3: 2009 | AN3: 1Q10 | AO3: 2Q10 | AP3: 3Q10 | AQ3: 4Q10 | AR3: 2010 | AS3: 1Q11 | AT3: 2Q11 | AU3: 3Q11 | AV3: 4Q11 | AW3: 2011 | AX3: 1Q12 | AY3: 2Q12 | AZ3: 3Q12 | BA3: 4Q12 | BB3: 2012 | BC3: 1Q13 | BD3: 2Q13 | BE3: 3Q13 | BF3: 4Q13 | BG3: 2013 | BH3: 1Q14 | BI3: 2Q14 | BJ3: 3Q14 | BK3: 4Q14 | BL3: 2014 | BM3: 1Q15 | BN3: 2Q15 | BO3: 3Q15 | BP3: 4Q15 | BQ3: 2015 | BR3: 1Q16 | BS3: 2Q16 | BT3: 3Q16 | BU3: 4Q16 | BV3: 2016 | BW3: 1Q17 | BX3: 2Q17 | BY3: 3Q17 | BZ3: 4Q17 | CA3: 2017 | CB3: 1Q18 | CC3: 2Q18 | CD3: 3Q18 | CE3: 4Q18 | CF3: 2018 | CG3: 1Q19 | CH3: 2Q19 | CI3: 3Q19 | CJ3: 4Q19 | CK3: 2019 | CL3: 1Q20E | CM3: 2Q20 | CN3: 3Q20 | CO3: 4Q20 | CP3: 2020 | CQ3: 1Q21 | CR3: 2Q21 | CS3: 3Q21 | CT3: 4Q21 | CU3: 2021 | CV3: 1Q22 | CW3: 2Q22 | CX3: 3Q22 | CY3: 4Q22 | CZ3: 2022 | DA3: 1Q23 | DB3: 2Q23 | DC3: 3Q23 | DD3: 4Q23 | DE3: 2023 | DF3: 1Q24 | DG3: 2Q24 | DH3: 3Q24 | DI3: 4Q24 | DJ3: 2024 | DK3: 1Q25 | DL3: 2Q25 | DM3: 3Q25 | DN3: 4Q25E | DO3: 2025E | DP3: 1Q26E | DQ3: 2Q26E | DR3: 3Q26E | DS3: 4Q26E | DT3: 2026E | DU3: 2027E | DV3: 2028E
B4: ($ mn) | C4: 35795 | D4: 36160 | E4: 36525 | F4: 36891 | G4: 37256 | H4: 37621 | I4: 37986 | J4: 38076 | K4: 38168 | L4: 38260 | M4: 38352 | N4: 38352 | O4: 38441 | P4: 38533 | Q4: 38625 | R4: 38717 | S4: 38717 | T4: 38806 | U4: 38898 | V4: 38990 | W4: 39082 | X4: 39082 | Y4: 39171 | Z4: 39263 | AA4: 39355 | AB4: 39447 | AC4: 39447 | AD4: 39537 | AE4: 39629 | AF4: 39721 | AG4: 39813 | AH4: 39813 | AI4: 39902 | AJ4: 39994 | AK4: 40086 | AL4: 40178 | AM4: 40178 | AN4: 40267 | AO4: 40359 | AP4: 40451 | AQ4: 40543 | AR4: 40543 | AS4: 40632 | AT4: 40724 | AU4: 40816 | AV4: 40908 | AW4: 40908 | AX4: 40998 | AY4: 41090 | AZ4: 41182 | BA4: 41274 | BB4: 41274 | BC4: 41363 | BD4: 41455 | BE4: 41547 | BF4: 41639 | BG4: 41639 | BH4: 41728 | BI4: 41820 | BJ4: 41912 | BK4: 42004 | BL4: 42004 | BM4: 42093 | BN4: 42185 | BO4: 42277 | BP4: 42369 | BQ4: 42369 | BR4: 42459 | BS4: 42551 | BT4: 42643 | BU4: 42735 | BV4: 42735 | BW4: 42824 | BX4: 42916 | BY4: 43008 | BZ4: 43100 | CA4: 43100 | CB4: 43189 | CC4: 43281 | CD4: 43373 | CE4: 43465 | CF4: 43465 | CG4: 43554 | CH4: 43646 | CI4: 43738 | CJ4: 43830 | CK4: 43830 | CL4: 43920 | CM4: 44012 | CN4: 44104 | CO4: 44196 | CP4: 44196 | CQ4: 44285 | CR4: 44377 | CS4: 44469 | CT4: 44561 | CU4: 44561 | CV4: 44650 | CW4: 44742 | CX4: 44834 | CY4: 44926 | CZ4: 44926 | DA4: 45015 | DB4: 45107 | DC4: 45199 | DD4: 45291 | DE4: 45291 | DF4: 45381 | DG4: 45473 | DH4: 45565 | DI4: 45657 | DJ4: 45657 | DK4: 45746 | DL4: 45838 | DM4: 45930 | DN4: 46022 | DO4: 46022 | DP4: 46111 | DQ4: 46203 | DR4: 46295 | DS4: 46387 | DT4: 46387 | DU4: =IS!DU4 -> 46752 | DV4: =IS!DV4 -> 47118
B6: Assets
B7: Cash and cash equivalents | CH7: =Data!CH49 -> 6480 | CI7: =+CH7+CFLO!CI41 -> 6368.1775 | CJ7: =Data!CJ49 -> 4937 | CK7: =CJ7 -> 4937 | CL7: =+CK7+CFLO!CL41 -> 6166.2628 | CM7: =Data!CM49 -> 6975 | CN7: =Data!CN49 -> 10001 | CO7: =Data!CO49 -> 8802 | CP7: =CO7 -> 8802 | CQ7: =Data!CQ49 -> 8579 | CR7: =Data!CR49 -> 8051 | CS7: =Data!CS49 -> 7476 | CT7: =Data!CT49 -> 7832 | CU7: =CT7 -> 7832 | CV7: =Data!CV49 -> 6040 | CW7: =Data!CW49 -> 4767 | CX7: =Data!CX49 -> 5381 | CY7: =Data!CY49 -> 6220 | CZ7: =CY7 -> 6220 | DA7: =Data!DA49 -> 5893 | DB7: =Data!DB49 -> 5391 | DC7: =Data!DC49 -> 5456 | DD7: =Data!DD49 -> 6587 | DE7: =DD7 -> 6587 | DF7: =Data!DF49 -> 5607 | DG7: =Data!DG49 -> 6011 | DH7: =Data!DH49 -> 6682 | DI7: =Data!DI49 -> 5578 | DJ7: =DI7 -> 5578 | DK7: =Data!DK49 -> 5157 | DL7: =Data!DL49 -> 4782 | DM7: =Data!DM49 -> 5966 | DN7: =+DM7+CFLO!DN41 -> 7834.608 | DO7: =DN7 -> 7834.608 | DP7: =+DO7+CFLO!DP41 -> 7261.576 | DQ7: =+DP7+CFLO!DQ41 -> 6968.4848 | DR7: =+DQ7+CFLO!DR41 -> 7209.1336 | DS7: =+DR7+CFLO!DS41 -> 9019.5224 | DT7: =DS7 -> 9019.5224 | DU7: =+DT7+CFLO!DU41 -> 9851.0434 | DV7: =+DU7+CFLO!DV41 -> 10435.497
B8: Accounts receivable, net | CH8: =Data!CH50 -> 9633 | CI8: =IS!CI6*BS!CI69/91 -> 9664.2485 | CJ8: =Data!CJ50 -> 8743 | CK8: =CJ8 -> 8743 | CL8: =IS!CL6*BS!CL69/91 -> 11759.978 | CM8: =Data!CM50 -> 9496 | CN8: =Data!CN50 -> 10115 | CO8: =Data!CO50 -> 9254 | CP8: =CO8 -> 9254 | CQ8: =Data!CQ50 -> 10037 | CR8: =Data!CR50 -> 8912 | CS8: =Data!CS50 -> 9538 | CT8: =Data!CT50 -> 9661 | CU8: =CT8 -> 9661 | CV8: =Data!CV50 -> 9076 | CW8: =Data!CW50 -> 10394 | CX8: =Data!CX50 -> 9233 | CY8: =Data!CY50 -> 9108 | CZ8: =CY8 -> 9108 | DA8: =Data!DA50 -> 10069 | DB8: =Data!DB50 -> 9903 | DC8: =Data!DC50 -> 10058 | DD8: =Data!DD50 -> 10838 | DE8: =DD8 -> 10838 | DF8: =Data!DF50 -> 10280 | DG8: =Data!DG50 -> 10252 | DH8: =Data!DH50 -> 10097 | DI8: =Data!DI50 -> 10976 | DJ8: =DI8 -> 10976 | DK8: =Data!DK50 -> 11426 | DL8: =Data!DL50 -> 12385 | DM8: =Data!DM50 -> 12837 | DN8: =IS!DN6*BS!DN69/91 -> 13162.865 | DO8: =DN8 -> 13162.865 | DP8: =IS!DP6*BS!DP69/91 -> 12470.778 | DQ8: =IS!DQ6*BS!DQ69/91 -> 13197.662 | DR8: =IS!DR6*BS!DR69/91 -> 13910.781 | DS8: =IS!DS6*BS!DS69/91 -> 14112.551 | DT8: =DS8 -> 14112.551 | DU8: =IS!DU6*BS!DU69/365 -> 13470.241 | DV8: =IS!DV6*BS!DV69/365 -> 14277.511
B9: Contract assets, current | CH9: =Data!CH51 -> 8969 | CI9: =-IS!CI7*365/BS!CI71/91 -> 9499.7935 | CJ9: =Data!CJ51 -> 4462 | CK9: =CJ9 -> 4462 | CL9: =-IS!CL7*365/BS!CL71/91 -> 12403.394 | CM9: =Data!CM51 -> 9943 | CN9: =Data!CN51 -> 9617 | CO9: =Data!CO51 -> 9931 | CP9: =CO9 -> 9931 | CQ9: =Data!CQ51 -> 10238 | CR9: =Data!CR51 -> 10485 | CS9: =Data!CS51 -> 10899 | CT9: =Data!CT51 -> 11361 | CU9: =CT9 -> 11361 | CV9: =Data!CV51 -> 11566 | CW9: =Data!CW51 -> 11836 | CX9: =Data!CX51 -> 12297 | CY9: =Data!CY51 -> 11534 | CZ9: =CY9 -> 11534 | DA9: =Data!DA51 -> 12729 | DB9: =Data!DB51 -> 12970 | DC9: =Data!DC51 -> 12696 | DD9: =Data!DD51 -> 12139 | DE9: =DD9 -> 12139 | DF9: =Data!DF51 -> 13104 | DG9: =Data!DG51 -> 13581 | DH9: =Data!DH51 -> 14684 | DI9: =Data!DI51 -> 14570 | DJ9: =DI9 -> 14570 | DK9: =Data!DK51 -> 15241 | DL9: =Data!DL51 -> 15686 | DM9: =Data!DM51 -> 16604 | DN9: =-IS!DN7*365/BS!DN71/91 -> 16641.607 | DO9: =DN9 -> 16641.607 | DP9: =-IS!DP7*365/BS!DP71/91 -> 15061.546 | DQ9: =-IS!DQ7*365/BS!DQ71/91 -> 15860.507 | DR9: =-IS!DR7*365/BS!DR71/91 -> 16596.465 | DS9: =-IS!DS7*365/BS!DS71/91 -> 16849.991 | DT9: =DS9 -> 16849.991 | DU9: =-IS!DU7/BS!DU71 -> 13941.733 | DV9: =-IS!DV7/BS!DV71 -> 14711.64
B10: Inventories and contracts in progress, net | CH10: =Data!CH52 -> 9554 | CI10: =-IS!CI7*BS!CI73/91 -> 9499.7935 | CJ10: =Data!CJ52 -> 9047 | CK10: =CJ10 -> 9047 | CL10: =-IS!CL7*BS!CL73/91 -> 10972.233 | CM10: =Data!CM52 -> 10256 | CN10: =Data!CN52 -> 9843 | CO10: =Data!CO52 -> 9411 | CP10: =CO10 -> 9411 | CQ10: =Data!CQ52 -> 9498 | CR10: =Data!CR52 -> 9548 | CS10: =Data!CS52 -> 9426 | CT10: =Data!CT52 -> 9178 | CU10: =CT10 -> 9178 | CV10: =Data!CV52 -> 9749 | CW10: =Data!CW52 -> 10142 | CX10: =Data!CX52 -> 10443 | CY10: =Data!CY52 -> 10617 | CZ10: =CY10 -> 10617 | DA10: =Data!DA52 -> 11327 | DB10: =Data!DB52 -> 11997 | DC10: =Data!DC52 -> 12050 | DD10: =Data!DD52 -> 11777 | DE10: =DD10 -> 11777 | DF10: =Data!DF52 -> 12386 | DG10: =Data!DG52 -> 13047 | DH10: =Data!DH52 -> 13465 | DI10: =Data!DI52 -> 12768 | DJ10: =DI10 -> 12768 | DK10: =Data!DK52 -> 13618 | DL10: =Data!DL52 -> 14012 | DM10: =Data!DM52 -> 13806 | DN10: =-IS!DN7*BS!DN73/91 -> 13501.681 | DO10: =DN10 -> 13501.681 | DP10: =-IS!DP7*BS!DP73/91 -> 12788.105 | DQ10: =-IS!DQ7*BS!DQ73/91 -> 13466.468 | DR10: =-IS!DR7*BS!DR73/91 -> 14091.338 | DS10: =-IS!DS7*BS!DS73/91 -> 14306.597 | DT10: =DS10 -> 14306.597 | DU10: =-IS!DU7*BS!DU73/365 -> 13941.733 | DV10: =-IS!DV7*BS!DV73/365 -> 14711.64
B11: Other assets, current | CH11: =Data!CH53 -> 1450 | CI11: =CH11 -> 1450 | CJ11: =Data!CJ53 -> 34388 | CK11: =CJ11 -> 34388 | CL11: =CK11 -> 34388 | CM11: =Data!CM53 -> 5604 | CN11: =Data!CN53 -> 3935 | CO11: =Data!CO53 -> 5978 | CP11: =CO11 -> 5978 | CQ11: =Data!CQ53 -> 4200 | CR11: =Data!CR53 -> 3883 | CS11: =Data!CS53 -> 4653 | CT11: =Data!CT53 -> 4018 | CU11: =CT11 -> 4018 | CV11: =Data!CV53 -> 4309 | CW11: =Data!CW53 -> 4323 | CX11: =Data!CX53 -> 4467 | CY11: =Data!CY53 -> 4964 | CZ11: =CY11 -> 4964 | DA11: =Data!DA53 -> 5486 | DB11: =Data!DB53 -> 5654 | DC11: =Data!DC53 -> 6258 | DD11: =Data!DD53 -> 7076 | DE11: =DD11 -> 7076 | DF11: =Data!DF53 -> 6646 | DG11: =Data!DG53 -> 6334 | DH11: =Data!DH53 -> 6836 | DI11: =Data!DI53 -> 7241 | DJ11: =DI11 -> 7241 | DK11: =Data!DK53 -> 7474 | DL11: =Data!DL53 -> 7792 | DM11: =Data!DM53 -> 7905 | DN11: =DM11 -> 7905 | DO11: =DN11 -> 7905 | DP11: =DO11 -> 7905 | DQ11: =DP11 -> 7905 | DR11: =DQ11 -> 7905 | DS11: =DR11 -> 7905 | DT11: =DS11 -> 7905 | DU11: =DT11 -> 7905 | DV11: =DU11 -> 7905
B12: =+Data!B54 -> Total current assets | CH12: =SUM(CH7:CH11) -> 36086 | CI12: =SUM(CI7:CI11) -> 36482.013 | CJ12: =SUM(CJ7:CJ11) -> 61577 | CK12: =CJ12 -> 61577 | CL12: =SUM(CL7:CL11) -> 75689.868 | CM12: =SUM(CM7:CM11) -> 42274 | CN12: =SUM(CN7:CN11) -> 43511 | CO12: =SUM(CO7:CO11) -> 43376 | CP12: =CO12 -> 43376 | CQ12: =SUM(CQ7:CQ11) -> 42552 | CR12: =SUM(CR7:CR11) -> 40879 | CS12: =SUM(CS7:CS11) -> 41992 | CT12: =SUM(CT7:CT11) -> 42050 | CU12: =CT12 -> 42050 | CV12: =SUM(CV7:CV11) -> 40740 | CW12: =SUM(CW7:CW11) -> 41462 | CX12: =SUM(CX7:CX11) -> 41821 | CY12: =SUM(CY7:CY11) -> 42443 | CZ12: =CY12 -> 42443 | DA12: =SUM(DA7:DA11) -> 45504 | DB12: =SUM(DB7:DB11) -> 45915 | DC12: =SUM(DC7:DC11) -> 46518 | DD12: =SUM(DD7:DD11) -> 48417 | DE12: =DD12 -> 48417 | DF12: =SUM(DF7:DF11) -> 48023 | DG12: =SUM(DG7:DG11) -> 49225 | DH12: =SUM(DH7:DH11) -> 51764 | DI12: =SUM(DI7:DI11) -> 51133 | DJ12: =DI12 -> 51133 | DK12: =SUM(DK7:DK11) -> 52916 | DL12: =SUM(DL7:DL11) -> 54657 | DM12: =SUM(DM7:DM11) -> 57118 | DN12: =SUM(DN7:DN11) -> 59045.761 | DO12: =DN12 -> 59045.761 | DP12: =SUM(DP7:DP11) -> 55487.005 | DQ12: =SUM(DQ7:DQ11) -> 57398.121 | DR12: =SUM(DR7:DR11) -> 59712.718 | DS12: =SUM(DS7:DS11) -> 62193.661 | DT12: =DS12 -> 62193.661 | DU12: =SUM(DU7:DU11) -> 59109.751 | DV12: =SUM(DV7:DV11) -> 62041.289
B13: Customer financing assets | CH13: =Data!CH55 -> 3281 | CI13: =CH13 -> 3281 | CJ13: =Data!CJ55 -> 3463 | CK13: =+CJ13 -> 3463 | CL13: =CK13 -> 3463 | CM13: =Data!CM55 -> 3363 | CN13: =Data!CN55 -> 3314 | CO13: =Data!CO55 -> 3144 | CP13: =+CO13 -> 3144 | CQ13: =Data!CQ55 -> 3079 | CR13: =Data!CR55 -> 3063 | CS13: =Data!CS55 -> 2960 | CT13: =Data!CT55 -> 2848 | CU13: =+CT13 -> 2848 | CV13: =Data!CV55 -> 2766 | CW13: =Data!CW55 -> 2675 | CX13: =Data!CX55 -> 2618 | CY13: =Data!CY55 -> 2603 | CZ13: =+CY13 -> 2603 | DA13: =Data!DA55 -> 2543 | DB13: =Data!DB55 -> 2457 | DC13: =Data!DC55 -> 2452 | DD13: =Data!DD55 -> 2392 | DE13: =+DD13 -> 2392 | DF13: =Data!DF55 -> 2359 | DG13: =Data!DG55 -> 2320 | DH13: =Data!DH55 -> 2306 | DI13: =Data!DI55 -> 2246 | DJ13: =+DI13 -> 2246 | DK13: =Data!DK55 -> 2135 | DL13: =Data!DL55 -> 2104 | DM13: =Data!DM55 -> 2071 | DN13: =DM13 -> 2071 | DO13: =DN13 -> 2071 | DP13: =DO13 -> 2071 | DQ13: =DP13 -> 2071 | DR13: =DQ13 -> 2071 | DS13: =DR13 -> 2071 | DT13: =DS13 -> 2071 | DU13: =DT13 -> 2071 | DV13: =DU13 -> 2071
B14: Future income tax benefits | CH14: =Data!CH56 -> 930 | CI14: =CH14 -> 930 | CJ14: =Data!CJ56 -> 0 | CK14: =+CJ14 -> 0 | CL14: =CK14 -> 0 | CM14: =Data!CM56 -> 732 | CN14: =Data!CN56 -> 699 | CO14: =Data!CO56 -> 0 | CP14: =+CO14 -> 0 | CQ14: =Data!CQ56 -> 0 | CR14: =Data!CR56 -> 0 | CS14: =Data!CS56 -> 0 | CT14: =Data!CT56 -> 0 | CU14: =+CT14 -> 0 | CV14: =Data!CV56 -> 0 | CW14: =Data!CW56 -> 0 | CX14: =Data!CX56 -> 0 | CY14: =Data!CY56 -> 0 | CZ14: =+CY14 -> 0 | DA14: =Data!DA56 -> 0 | DB14: =Data!DB56 -> 0 | DC14: =Data!DC56 -> 0 | DD14: =Data!DD56 -> 0 | DE14: =+DD14 -> 0 | DF14: =Data!DF56 -> 0 | DG14: =Data!DG56 -> 0 | DH14: =Data!DH56 -> 0 | DI14: =Data!DI56 -> 0 | DJ14: =+DI14 -> 0 | DK14: =Data!DK56 -> 0 | DL14: =Data!DL56 -> 0 | DM14: =Data!DM56 -> 0 | DN14: =DM14 -> 0 | DO14: =DN14 -> 0 | DP14: =DO14 -> 0 | DQ14: =DP14 -> 0 | DR14: =DQ14 -> 0 | DS14: =DR14 -> 0 | DT14: =DS14 -> 0 | DU14: =DT14 -> 0 | DV14: =DU14 -> 0
B15: Fixed assets, net | CH15: =Data!CH57 -> 14596 | CI15: =CH15-CFLO!CI24-CFLO!CI8*0.6 -> 14994.5 | CJ15: =Data!CJ57 -> 10322 | CK15: =+CJ15 -> 10322 | CL15: =CK15-CFLO!CL24-CFLO!CL8*0.6 -> 10596.6 | CM15: =Data!CM57 -> 14805 | CN15: =Data!CN57 -> 14730 | CO15: =Data!CO57 -> 14962 | CP15: =+CO15 -> 14962 | CQ15: =Data!CQ57 -> 14742 | CR15: =Data!CR57 -> 14665 | CS15: =Data!CS57 -> 14517 | CT15: =Data!CT57 -> 14972 | CU15: =+CT15 -> 14972 | CV15: =Data!CV57 -> 14837 | CW15: =Data!CW57 -> 14741 | CX15: =Data!CX57 -> 14668 | CY15: =Data!CY57 -> 15170 | CZ15: =+CY15 -> 15170 | DA15: =Data!DA57 -> 15149 | DB15: =Data!DB57 -> 15295 | DC15: =Data!DC57 -> 15347 | DD15: =Data!DD57 -> 15748 | DE15: =+DD15 -> 15748 | DF15: =Data!DF57 -> 15638 | DG15: =Data!DG57 -> 15693 | DH15: =Data!DH57 -> 15886 | DI15: =Data!DI57 -> 16089 | DJ15: =+DI15 -> 16089 | DK15: =Data!DK57 -> 16135 | DL15: =Data!DL57 -> 16205 | DM15: =Data!DM57 -> 16325 | DN15: =DM15-CFLO!DN24-CFLO!DN8*0.6 -> 16921 | DO15: =DN15 -> 16921 | DP15: =DO15-CFLO!DP24-CFLO!DP8*0.6 -> 17111 | DQ15: =DP15-CFLO!DQ24-CFLO!DQ8*0.6 -> 17331 | DR15: =DQ15-CFLO!DR24-CFLO!DR8*0.6 -> 17621 | DS15: =DR15-CFLO!DS24-CFLO!DS8*0.6 -> 18201 | DT15: =DS15 -> 18201 | DU15: =DT15-CFLO!DU24-CFLO!DU8*0.6 -> 19581 | DV15: =DU15-CFLO!DV24-CFLO!DV8*0.6 -> 20956
B16: Operating lease right-of-use asset | CH16: =Data!CH58 -> 2150 | CI16: =CH16 -> 2150 | CJ16: =Data!CJ58 -> 1252 | CK16: =+CJ16 -> 1252 | CL16: =CK16 -> 1252 | CM16: =Data!CM58 -> 2102 | CN16: =Data!CN58 -> 2027 | CO16: =Data!CO58 -> 1880 | CP16: =+CO16 -> 1880 | CQ16: =Data!CQ58 -> 1913 | CR16: =Data!CR58 -> 1900 | CS16: =Data!CS58 -> 1876 | CT16: =Data!CT58 -> 1958 | CU16: =+CT16 -> 1958 | CV16: =Data!CV58 -> 1911 | CW16: =Data!CW58 -> 1866 | CX16: =Data!CX58 -> 1802 | CY16: =Data!CY58 -> 1829 | CZ16: =+CY16 -> 1829 | DA16: =Data!DA58 -> 1844 | DB16: =Data!DB58 -> 1812 | DC16: =Data!DC58 -> 1755 | DD16: =Data!DD58 -> 1638 | DE16: =+DD16 -> 1638 | DF16: =Data!DF58 -> 1639 | DG16: =Data!DG58 -> 1664 | DH16: =Data!DH58 -> 1846 | DI16: =Data!DI58 -> 1864 | DJ16: =+DI16 -> 1864 | DK16: =Data!DK58 -> 1899 | DL16: =Data!DL58 -> 1869 | DM16: =Data!DM58 -> 1899 | DN16: =DM16 -> 1899 | DO16: =DN16 -> 1899 | DP16: =DO16 -> 1899 | DQ16: =DP16 -> 1899 | DR16: =DQ16 -> 1899 | DS16: =DR16 -> 1899 | DT16: =DS16 -> 1899 | DU16: =DT16 -> 1899 | DV16: =DU16 -> 1899
B17: Goodwill | CH17: =Data!CH59 -> 76652 | CI17: =CH17 -> 76652 | CJ17: =Data!CJ59 -> 36609 | CK17: =+CJ17 -> 36609 | CL17: =CK17 -> 36609 | CM17: =Data!CM59 -> 53269 | CN17: =Data!CN59 -> 53524 | CO17: =Data!CO59 -> 54285 | CP17: =+CO17 -> 54285 | CQ17: =Data!CQ59 -> 54265 | CR17: =Data!CR59 -> 54394 | CS17: =Data!CS59 -> 53789 | CT17: =Data!CT59 -> 54436 | CU17: =+CT17 -> 54436 | CV17: =Data!CV59 -> 54316 | CW17: =Data!CW59 -> 53806 | CX17: =Data!CX59 -> 53168 | CY17: =Data!CY59 -> 53840 | CZ17: =+CY17 -> 53840 | DA17: =Data!DA59 -> 53904 | DB17: =Data!DB59 -> 54122 | DC17: =Data!DC59 -> 53883 | DD17: =Data!DD59 -> 53699 | DE17: =+DD17 -> 53699 | DF17: =Data!DF59 -> 53644 | DG17: =Data!DG59 -> 53347 | DH17: =Data!DH59 -> 53759 | DI17: =Data!DI59 -> 52789 | DJ17: =+DI17 -> 52789 | DK17: =Data!DK59 -> 53045 | DL17: =Data!DL59 -> 53327 | DM17: =Data!DM59 -> 53311 | DN17: =DM17 -> 53311 | DO17: =DN17 -> 53311 | DP17: =DO17 -> 53311 | DQ17: =DP17 -> 53311 | DR17: =DQ17 -> 53311 | DS17: =DR17 -> 53311 | DT17: =DS17 -> 53311 | DU17: =DT17 -> 53311 | DV17: =DU17 -> 53311
B18: Intangible assets, net | CH18: =Data!CH60 -> 44184 | CI18: =+CH18-CFLO!CI8*0.4 -> 43981 | CJ18: =Data!CJ60 -> 24473 | CK18: =CJ18 -> 24473 | CL18: =+CK18-CFLO!CL8*0.4 -> 24439.4 | CM18: =Data!CM60 -> 42003 | CN18: =Data!CN60 -> 41564 | CO18: =Data!CO60 -> 40539 | CP18: =CO18 -> 40539 | CQ18: =Data!CQ60 -> 39999 | CR18: =Data!CR60 -> 39523 | CS18: =Data!CS60 -> 38842 | CT18: =Data!CT60 -> 38516 | CU18: =CT18 -> 38516 | CV18: =Data!CV60 -> 38118 | CW18: =Data!CW60 -> 37562 | CX18: =Data!CX60 -> 37046 | CY18: =Data!CY60 -> 36823 | CZ18: =CY18 -> 36823 | DA18: =Data!DA60 -> 36477 | DB18: =Data!DB60 -> 36234 | DC18: =Data!DC60 -> 35865 | DD18: =Data!DD60 -> 35399 | DE18: =DD18 -> 35399 | DF18: =Data!DF60 -> 34960 | DG18: =Data!DG60 -> 34503 | DH18: =Data!DH60 -> 34159 | DI18: =Data!DI60 -> 33443 | DJ18: =DI18 -> 33443 | DK18: =Data!DK60 -> 33116 | DL18: =Data!DL60 -> 32748 | DM18: =Data!DM60 -> 32260 | DN18: =+DM18-CFLO!DN8*0.4 -> 32024 | DO18: =DN18 -> 32024 | DP18: =+DO18-CFLO!DP8*0.4 -> 31784 | DQ18: =+DP18-CFLO!DQ8*0.4 -> 31544 | DR18: =+DQ18-CFLO!DR8*0.4 -> 31304 | DS18: =+DR18-CFLO!DS8*0.4 -> 31064 | DT18: =DS18 -> 31064 | DU18: =+DT18-CFLO!DU8*0.4 -> 30084 | DV18: =+DU18-CFLO!DV8*0.4 -> 29084
B19: =+Data!B61 -> Other assets | CH19: =Data!CH61 -> 6799 | CI19: =CH19 -> 6799 | CJ19: =Data!CJ61 -> 1919 | CK19: =+CJ19 -> 1919 | CL19: =CK19 -> 1919 | CM19: =Data!CM61 -> 2969 | CN19: =Data!CN61 -> 3030 | CO19: =Data!CO61 -> 3967 | CP19: =+CO19 -> 3967 | CQ19: =Data!CQ61 -> 4058 | CR19: =Data!CR61 -> 4414 | CS19: =Data!CS61 -> 4796 | CT19: =Data!CT61 -> 6624 | CU19: =+CT19 -> 6624 | CV19: =Data!CV61 -> 6678 | CW19: =Data!CW61 -> 6905 | CX19: =Data!CX61 -> 7102 | CY19: =Data!CY61 -> 6156 | CZ19: =+CY19 -> 6156 | DA19: =Data!DA61 -> 6215 | DB19: =Data!DB61 -> 6326 | DC19: =Data!DC61 -> 6623 | DD19: =Data!DD61 -> 4576 | DE19: =+DD19 -> 4576 | DF19: =Data!DF61 -> 3924 | DG19: =Data!DG61 -> 4417 | DH19: =Data!DH61 -> 5102 | DI19: =Data!DI61 -> 5297 | DJ19: =+DI19 -> 5297 | DK19: =Data!DK61 -> 5618 | DL19: =Data!DL61 -> 6229 | DM19: =Data!DM61 -> 5688 | DN19: =DM19 -> 5688 | DO19: =DN19 -> 5688 | DP19: =DO19 -> 5688 | DQ19: =DP19 -> 5688 | DR19: =DQ19 -> 5688 | DS19: =DR19 -> 5688 | DT19: =DS19 -> 5688 | DU19: =DT19 -> 5688 | DV19: =DU19 -> 5688
B20: Total Assets | CB20: 79886.5 | CC20: 81522.5 | CD20: 87603.5 | CE20: 98969.5 | CF20: =CE20 -> 98969.5 | CG20: 100266 | CH20: =SUM(CH12:CH19) -> 184678 | CI20: =SUM(CI12:CI19) -> 185269.51 | CJ20: =SUM(CJ12:CJ19) -> 139615 | CK20: =SUM(CK12:CK19) -> 139615 | CL20: =SUM(CL12:CL19) -> 153968.87 | CM20: =SUM(CM12:CM19) -> 161517 | CN20: =SUM(CN12:CN19) -> 162399 | CO20: =SUM(CO12:CO19) -> 162153 | ... DN20: =SUM(DN12:DN19) -> 170959.76 | DO20: =DN20 -> 170959.76 | DP20: =SUM(DP12:DP19) -> 167351.01 | DQ20: =SUM(DQ12:DQ19) -> 169242.12 | DR20: =SUM(DR12:DR19) -> 171606.72 | DS20: =SUM(DS12:DS19) -> 174427.66 | DT20: =DS20 -> 174427.66 | DU20: =SUM(DU12:DU19) -> 171743.75 | DV20: =SUM(DV12:DV19) -> 175050.29
B22: Liabilities and Shareholder's equity
B23: Short-term borrowings | CH23: =Data!CH64 -> 1095 | CI23: =CH23+CFLO!CI32 -> 1018 | CJ23: =Data!CJ64 -> 2293 | CK23: =CJ23 -> 2293 | CL23: =CK23+CFLO!CL32 -> 1630 | CM23: =Data!CM64 -> 243 | CN23: =Data!CN64 -> 228 | CO23: =Data!CO64 -> 247 | CP23: =CO23 -> 247 | CQ23: =Data!CQ64 -> 234 | CR23: =Data!CR64 -> 196 | CS23: =Data!CS64 -> 206 | CT23: =Data!CT64 -> 134 | CU23: =CT23 -> 134 | CV23: =Data!CV64 -> 140 | CW23: =Data!CW64 -> 113 | CX23: =Data!CX64 -> 2195 | CY23: =Data!CY64 -> 625 | CZ23: =CY23 -> 625 | DA23: =Data!DA64 -> 224 | DB23: =Data!DB64 -> 1076 | DC23: =Data!DC64 -> 1170 | DD23: =Data!DD64 -> 189 | DE23: =DD23 -> 189 | DF23: =Data!DF64 -> 166 | DG23: =Data!DG64 -> 231 | DH23: =Data!DH64 -> 220 | DI23: =Data!DI64 -> 183 | DJ23: =DI23 -> 183 | DK23: =Data!DK64 -> 212 | DL23: =Data!DL64 -> 1635 | DM23: =Data!DM64 -> 215 | DN23: =DM23+CFLO!DN32 -> 215 | DO23: =DN23 -> 215 | DP23: =DO23+CFLO!DP32 -> 215 | DQ23: =DP23+CFLO!DQ32 -> 215 | DR23: =DQ23+CFLO!DR32 -> 215 | DS23: =DR23+CFLO!DS32 -> 215 | DT23: =DS23 -> 215 | DU23: =DT23+CFLO!DU32 -> 215 | DV23: =DU23+CFLO!DV32 -> 215
B24: Accounts payable | CH24: =Data!CH65 -> 9198 | CI24: =-IS!CI7*BS!CI70/91 -> 9369.6593 | CJ24: =Data!CJ65 -> 7816 | CK24: =CJ24 -> 7816 | CL24: =-IS!CL7*BS!CL70/91 -> 11880.073 | CM24: =Data!CM65 -> 7182 | CN24: =Data!CN65 -> 8143 | CO24: =Data!CO65 -> 8639 | CP24: =CO24 -> 8639 | CQ24: =Data!CQ65 -> 9182 | CR24: =Data!CR65 -> 8043 | CS24: =Data!CS65 -> 8667 | CT24: =Data!CT65 -> 8751 | CU24: =CT24 -> 8751 | CV24: =Data!CV65 -> 8270 | CW24: =Data!CW65 -> 9732 | CX24: =Data!CX65 -> 9017 | CY24: =Data!CY65 -> 9896 | CZ24: =CY24 -> 9896 | DA24: =Data!DA65 -> 10060 | DB24: =Data!DB65 -> 10128 | DC24: =Data!DC65 -> 10315 | DD24: =Data!DD65 -> 10698 | DE24: =DD24 -> 10698 | DF24: =Data!DF65 -> 10522 | DG24: =Data!DG65 -> 10939 | DH24: =Data!DH65 -> 11834 | DI24: =Data!DI65 -> 12897 | DJ24: =DI24 -> 12897 | DK24: =Data!DK65 -> 13444 | DL24: =Data!DL65 -> 13433 | DM24: =Data!DM65 -> 14552 | DN24: =-IS!DN7*BS!DN70/91 -> 14507.834 | DO24: =DN24 -> 14507.834 | DP24: =-IS!DP7*BS!DP70/91 -> 12998.321 | DQ24: =-IS!DQ7*BS!DQ70/91 -> 13687.835 | DR24: =-IS!DR7*BS!DR70/91 -> 14322.977 | DS24: =-IS!DS7*BS!DS70/91 -> 14541.773 | DT24: =DS24 -> 14541.773 | DU24: =-IS!DU7*BS!DU70/365 -> 13655.259 | DV24: =-IS!DV7*BS!DV70/365 -> 14409.346
B25: Accrued employee compensation | CJ25: =Data!CJ66 -> 1353 | CK25: =CJ25 -> 1353 | CO25: =Data!CO66 -> 3006 | CP25: =CO25 -> 3006 | CQ25: =Data!CQ66 -> 2511 | CR25: =Data!CR66 -> 2233 | CS25: =Data!CS66 -> 2756 | CT25: =Data!CT66 -> 2658 | CU25: =CT25 -> 2658 | CV25: =Data!CV66 -> 1880 | CW25: =Data!CW66 -> 2028 | CX25: =Data!CX66 -> 2390 | CY25: =Data!CY66 -> 2401 | CZ25: =CY25 -> 2401 | DA25: =Data!DA66 -> 1856 | DB25: =Data!DB66 -> 2121 | DC25: =Data!DC66 -> 2597 | DD25: =Data!DD66 -> 2491 | DE25: =DD25 -> 2491 | DF25: =Data!DF66 -> 1862 | DG25: =Data!DG66 -> 2065 | DH25: =Data!DH66 -> 2673 | DI25: =Data!DI66 -> 2620 | DJ25: =DI25 -> 2620 | DK25: =Data!DK66 -> 1867 | DL25: =Data!DL66 -> 2133 | DM25: =Data!DM66 -> 2937 | DN25: =DM25 -> 2937 | DO25: =DN25 -> 2937 | DP25: =DO25 -> 2937 | DQ25: =DP25 -> 2937 | DR25: =DQ25 -> 2937 | DS25: =DR25 -> 2937 | DT25: =DS25 -> 2937 | DU25: =DT25 -> 2937 | DV25: =DU25 -> 2937
B26: Accrued liabilities | CH26: =Data!CH67 -> 12451 | CI26: =CH26 -> 12451 | CJ26: =Data!CJ67 -> 8417 | CK26: =CJ26 -> 8417 | CL26: =CK26 -> 8417 | CM26: =Data!CM67 -> 14253 | CN26: =Data!CN67 -> 13558 | CO26: =Data!CO67 -> 10401 | CP26: =CO26 -> 10401 | CQ26: =Data!CQ67 -> 10184 | CR26: =Data!CR67 -> 10361 | CS26: =Data!CS67 -> 9685 | CT26: =Data!CT67 -> 10162 | CU26: =CT26 -> 10162 | CV26: =Data!CV67 -> 11004 | CW26: =Data!CW67 -> 12459 | CX26: =Data!CX67 -> 11210 | CY26: =Data!CY67 -> 10999 | CZ26: =CY26 -> 10999 | DA26: =Data!DA67 -> 11573 | DB26: =Data!DB67 -> 11719 | DC26: =Data!DC67 -> 14283 | DD26: =Data!DD67 -> 14917 | DE26: =DD26 -> 14917 | DF26: =Data!DF67 -> 15006 | DG26: =Data!DG67 -> 17048 | DH26: =Data!DH67 -> 15971 | DI26: =Data!DI67 -> 14831 | DJ26: =DI26 -> 14831 | DK26: =Data!DK67 -> 15219 | DL26: =Data!DL67 -> 15861 | DM26: =Data!DM67 -> 14835 | DN26: =DM26 -> 14835 | DO26: =DN26 -> 14835 | DP26: =DO26 -> 14835 | DQ26: =DP26 -> 14835 | DR26: =DQ26 -> 14835 | DS26: =DR26 -> 14835 | DT26: =DS26 -> 14835 | DU26: =DT26 -> 14835 | DV26: =DU26 -> 14835
B27: Contract liabilities, current | CH27: =Data!CH68 -> 4774 | CI27: =CH27 -> 4774 | CJ27: =Data!CJ68 -> 9014 | CK27: =CJ27 -> 9014 | CL27: =CK27 -> 9014 | CM27: =Data!CM68 -> 11997 | CN27: =Data!CN68 -> 12208 | CO27: =Data!CO68 -> 12889 | CP27: =CO27 -> 12889 | CQ27: =Data!CQ68 -> 12879 | CR27: =Data!CR68 -> 12591 | CS27: =Data!CS68 -> 12543 | CT27: =Data!CT68 -> 13720 | CU27: =CT27 -> 13720 | CV27: =Data!CV68 -> 13739 | CW27: =Data!CW68 -> 13430 | CX27: =Data!CX68 -> 13368 | CY27: =Data!CY68 -> 14598 | CZ27: =CY27 -> 14598 | DA27: =Data!DA68 -> 14870 | DB27: =Data!DB68 -> 15162 | DC27: =Data!DC68 -> 15248 | DD27: =Data!DD68 -> 17183 | DE27: =DD27 -> 17183 | DF27: =Data!DF68 -> 17119 | DG27: =Data!DG68 -> 17665 | DH27: =Data!DH68 -> 18436 | DI27: =Data!DI68 -> 18616 | DJ27: =DI27 -> 18616 | DK27: =Data!DK68 -> 19038 | DL27: =Data!DL68 -> 19186 | DM27: =Data!DM68 -> 20111 | DN27: =DM27 -> 20111 | DO27: =DN27 -> 20111 | DP27: =DO27 -> 20111 | DQ27: =DP27 -> 20111 | DR27: =DQ27 -> 20111 | DS27: =DR27 -> 20111 | DT27: =DS27 -> 20111 | DU27: =DT27 -> 20111 | DV27: =DU27 -> 20111
