Workbook
Name A_ALL_BA: #REF!
Name A_ALL_BA_: #REF!
Name A_ALL_KEYWORDS_TYPE_ScalarContributed_EQTY_200000881: #REF!,#REF!,#REF!,#REF!,#REF!
Name A_ALL_KEYWORDS_TYPE_ScalarContributed_ISSR_208000201: #REF!,#REF!
Name A_ALL_KEYWORDS_TYPE_ScalarReference_EQTY_200000881: #REF!
Name A_ALL_KEYWORDS_TYPE_ScalarReference_ISSR_208000201: #REF!
Name A_ALL_KEYWORDS_TYPE_Vector_EQTY_200000881: #REF!,#REF!,#REF!,#REF!,#REF!,#REF!,#REF!
Name A_ALL_KEYWORDS_TYPE_Vector_ISSR_208000201: #REF!,#REF!,#REF!,#REF!,#REF!,#REF!,#REF!,#REF!,#REF!
Name A_ALL_SECTION_KEYWORDS_EQTY_200000881_1314: #REF!
Name A_ALL_SECTION_KEYWORDS_EQTY_200000881_1319: #REF!
Name A_ALL_SECTION_KEYWORDS_EQTY_200000881_131E: #REF!
Name A_ALL_SECTION_KEYWORDS_EQTY_200000881_131O: #REF!
Name A_ALL_SECTION_KEYWORDS_EQTY_200000881_13A: #REF!
Name A_ALL_SECTION_KEYWORDS_EQTY_200000881_13K: #REF!
Name A_ALL_SECTION_KEYWORDS_EQTY_200000881_13U: #REF!
Name A_ALL_SECTION_KEYWORDS_EQTY_200000881_13V: #REF!
Name A_ALL_SECTION_KEYWORDS_EQTY_200000881_13W: #REF!
Name A_ALL_SECTION_KEYWORDS_EQTY_200000881_Reference_Data: #REF!
Name A_ALL_SECTION_KEYWORDS_ISSR_208000201_1314: #REF!
Name A_ALL_SECTION_KEYWORDS_ISSR_208000201_13168: #REF!
Name A_ALL_SECTION_KEYWORDS_ISSR_208000201_1316S: #REF!
Name A_ALL_SECTION_KEYWORDS_ISSR_208000201_1316T: #REF!
Name A_ALL_SECTION_KEYWORDS_ISSR_208000201_1316U: #REF!
Name A_ALL_SECTION_KEYWORDS_ISSR_208000201_1319: #REF!
Name A_ALL_SECTION_KEYWORDS_ISSR_208000201_131E: #REF!
Name A_ALL_SECTION_KEYWORDS_ISSR_208000201_131J: #REF!
Name A_ALL_SECTION_KEYWORDS_ISSR_208000201_131O: #REF!
Name A_ALL_SECTION_KEYWORDS_ISSR_208000201_136E: #REF!,#REF!
Name A_ALL_SECTION_KEYWORDS_ISSR_208000201_13A: #REF!
Name A_ALL_SECTION_KEYWORDS_ISSR_208000201_13U: #REF!
Name A_ALL_SECTION_KEYWORDS_ISSR_208000201_13V: #REF!
Name A_ALL_SECTION_KEYWORDS_ISSR_208000201_Reference_Data: #REF!
Name A_ALL_SECTIONS_EQTY_200000881: #REF!,#REF!,#REF!,#REF!,#REF!,#REF!,#REF!,#REF!,#REF!,#REF!
Name A_CURRENCY_EQTY_200000881_PRI: #REF!
Name A_CURRENCY_EQTY_200000881_PUB: #REF!
Name A_CURRENCY_EQTY_200000881_REP: #REF!
Name A_CURRENCY_ISSR_208000201_REP: #REF!
Name A_KEYWORD_EQTY_200000881_AMER_CONVICTION: #REF!
Name A_KEYWORD_EQTY_200000881_AMER_LIST: #REF!
Name A_KEYWORD_EQTY_200000881_BETA_ANALYST: #REF!
Name A_KEYWORD_EQTY_200000881_BVPS: #REF!
Name A_KEYWORD_EQTY_200000881_BVPS_PUB: #REF!
Name A_KEYWORD_EQTY_200000881_CEEE_EPS: #REF!
Name A_KEYWORD_EQTY_200000881_CF_NI_PRE_PREF: #REF!
Name A_KEYWORD_EQTY_200000881_COMMON_DIV_PAID: #REF!
Name A_KEYWORD_EQTY_200000881_CURRENCY_ISO: #REF!
Name A_KEYWORD_EQTY_200000881_DILUTE_SHARES: #REF!
Name A_KEYWORD_EQTY_200000881_DPS: #REF!
Name A_KEYWORD_EQTY_200000881_DPS_PUB: #REF!
Name A_KEYWORD_EQTY_200000881_EBIT_PUB: #REF!
Name A_KEYWORD_EQTY_200000881_EBITDA_PUB: #REF!
Name A_KEYWORD_EQTY_200000881_EPS: #REF!
Name A_KEYWORD_EQTY_200000881_EPS_EX_ESO_B: #REF!
Name A_KEYWORD_EQTY_200000881_EPS_EX_ESO_D: #REF!
Name A_KEYWORD_EQTY_200000881_EPS_FUL_DIL: #REF!
Name A_KEYWORD_EQTY_200000881_EPS_POST_BASIC: #REF!
Name A_KEYWORD_EQTY_200000881_EPS_PUB: #REF!
Name A_KEYWORD_EQTY_200000881_EPS_PUB_EX_ESO: #REF!
Name A_KEYWORD_EQTY_200000881_EQ_PUB: #REF!
Name A_KEYWORD_EQTY_200000881_ESO_POST_TAX: #REF!

Sheet Cover
D7: Boeing (BA) Model
D8: 46231
B16: Noah Poponak, CFA
B17: (212) 357-0954
B18: noah.poponak@gs.com
B20: Connor Dessert
B21: (212) 357-6166
B22: connor.dessert@gs.com
B24: Nizar Mesani
B25: (212) 934-6965
B26: nizar.mesani@gs.com
B28: Amanda Fenenbock, CFA
B29: (212) 934-0385
B30: amanda.fenenbock@gs.com
... B34: tomas.russo@gs.com

Sheet Data
B3: BA Raw Data | C3: 1997 | D3: 1998 | E3: 1999 | F3: 2000 | G3: 2001 | H3: 2002 | I3: 2003 | J3: 1Q04 | K3: 2Q04 | L3: 3Q04 | M3: 4Q04 | N3: 2004 | O3: 1Q05 | P3: 2Q05 | Q3: 3Q05 | R3: 4Q05 | S3: 2005 | T3: 1Q06 | U3: 2Q06 | V3: 3Q06 | W3: 4Q06 | X3: 2006 | Y3: 1Q07 | Z3: 2Q07 | AA3: 3Q07 | AB3: 4Q07 | AC3: 2007 | AD3: 1Q08 | AE3: 2Q08 | AF3: 3Q08 | AG3: 4Q08 | AH3: 2008 | AI3: 1Q09 | AJ3: 2Q09 | AK3: 3Q09 | AL3: 4Q09 | AM3: 2009 | AN3: 1Q10 | AO3: 2Q10 | AP3: 3Q10 | AQ3: 4Q10 | AR3: 2010 | AS3: 1Q11 | AT3: 2Q11 | AU3: 3Q11 | AV3: 4Q11 | AW3: 2011 | AX3: 1Q12 | AY3: 2Q12 | AZ3: 3Q12 | BA3: 4Q12 | BB3: 2012 | BC3: 1Q13 | BD3: 2Q13 | BE3: 3Q13 | BF3: 4Q13 | BG3: 2013 | BH3: 1Q14 | BI3: 2Q14 | BJ3: 3Q14 | BK3: 4Q14 | BL3: 2014 | BM3: 1Q15 | BN3: 2Q15 | BO3: 3Q15 | BP3: 4Q15 | BQ3: 2015 | BR3: 1Q16 | BS3: 2Q16 | BT3: 3Q16 | BU3: 4Q16 | BV3: 2016 | BW3: 1Q17 | BX3: 2Q17 | BY3: 3Q17 | BZ3: 4Q17 | CA3: 2017 | CB3: 1Q18 | CC3: 2Q18 | CD3: 3Q18 | CE3: 4Q18 | CF3: 2018 | CG3: 1Q19 | CH3: 2Q19 | CI3: 3Q19 | CJ3: 4Q19 | CK3: 2019 | CL3: 1Q20 | CM3: 2Q20 | CN3: 3Q20 | CO3: 4Q20 | CP3: 2020 | CQ3: 1Q21 | CR3: 2Q21 | CS3: 3Q21 | CT3: 4Q21 | CU3: 2021 | CV3: 1Q22 | CW3: 2Q22 | CX3: 3Q22 | CY3: 4Q22 | CZ3: 2022 | DA3: 1Q23 | DB3: 2Q23 | DC3: 3Q23 | DD3: 4Q23 | DE3: 2023 | DF3: 1Q24 | DG3: 2Q24 | DH3: 3Q24 | DI3: 4Q24 | DJ3: 2024 | DK3: 1Q25 | DL3: 2Q25 | DM3: 3Q25 | DN3: 4Q25 | DO3: 2025 | DP3: 1Q26 | DQ3: 2Q26 | DR3: 3Q26 | DS3: 4Q26 | DT3: 2026 | DU3: 1Q27 | DV3: 2Q27 | DW3: 3Q27 | DX3: 4Q27 | DY3: 2027 | DZ3: 2028 | EA3: 2029 | EB3: 2030
B4: ($ mn) | C4: 35795 | D4: 36160 | E4: 36525 | F4: 36891 | G4: 37256 | H4: 37621 | I4: 37986 | J4: 38077 | K4: 38168 | L4: 38260 | M4: 38352 | N4: 38352 | O4: 38442 | P4: 38533 | Q4: 38625 | R4: 38717 | S4: 38717 | T4: 38807 | U4: 38898 | V4: 38990 | W4: 39082 | X4: 39082 | Y4: 39172 | Z4: 39263 | AA4: 39355 | AB4: 39447 | AC4: 39447 | AD4: 39538 | AE4: 39629 | AF4: 39721 | AG4: 39813 | AH4: 39813 | AI4: 39903 | AJ4: 39994 | AK4: 40086 | AL4: 40178 | AM4: 40178 | AN4: 40268 | AO4: 40359 | AP4: 40451 | AQ4: 40543 | AR4: 40543 | AS4: 40633 | AT4: 40724 | AU4: 40816 | AV4: 40908 | AW4: 40908 | AX4: 40999 | AY4: 41090 | AZ4: 41182 | BA4: 41274 | BB4: 41274 | BC4: 41364 | BD4: 41455 | BE4: 41547 | BF4: 41639 | BG4: 41639 | BH4: 41729 | BI4: 41820 | BJ4: 41912 | BK4: 42004 | BL4: 42004 | BM4: 42094 | BN4: 42185 | BO4: 42277 | BP4: 42369 | BQ4: 42369 | BR4: 42460 | BS4: 42551 | BT4: 42643 | BU4: 42735 | BV4: 42735 | BW4: 42825 | BX4: 42916 | BY4: 43008 | BZ4: 43100 | CA4: 43100 | CB4: 43190 | CC4: 43281 | CD4: 43373 | CE4: 43465 | CF4: 43465 | CG4: 43555 | CH4: 43646 | CI4: 43738 | CJ4: 43830 | CK4: 43830 | CL4: 43921 | CM4: 44012 | CN4: 44104 | CO4: 44196 | CP4: 44196 | CQ4: 44286 | CR4: 44377 | CS4: 44469 | CT4: 44561 | CU4: 44561 | CV4: 44651 | CW4: 44742 | CX4: 44834 | CY4: 44926 | CZ4: 44926 | DA4: 45016 | DB4: 45107 | DC4: 45199 | DD4: 45291 | DE4: 45291 | DF4: 45382 | DG4: 45473 | DH4: 45565 | DI4: 45657 | DJ4: 45657 | DK4: 45747 | DL4: 45838 | DM4: 45930 | DN4: 46022 | DO4: 46022 | DP4: 46112 | DQ4: 46203 | DR4: 46295 | DS4: 46387 | DT4: 46387 | DU4: 46477 | DV4: 46568 | DW4: 46660 | DX4: 46752 | DY4: 46752 | DZ4: 47118 | EA4: 47483 | EB4: 47848
B6: Income Statement
B7: Sales of products | N7: 43960 | O7: 10791 | P7: 12394 | Q7: 10334 | R7: =S7-O7-P7-Q7 -> 11879 | S7: 45398 | T7: 12202 | U7: 12848 | V7: 12388 | W7: =X7-T7-U7-V7 -> 15206 | X7: 52644 | Y7: 13229 | Z7: 14787 | AA7: 14177 | AB7: =AC7-Y7-Z7-AA7 -> 14856 | AC7: 57049 | AD7: 13688 | AE7: 14298 | AF7: 12407 | AG7: =AH7-AD7-AE7-AF7 -> 9787 | AH7: 50180 | AI7: 13835 | AJ7: 14296 | AK7: 13967 | AL7: 14934 | AM7: =SUM(AI7:AL7) -> 57032 | AN7: 12316 | AO7: 12624 | AP7: 14077 | AQ7: 13569 | AR7: =SUM(AN7:AQ7) -> 52586 | AS7: 11894 | AT7: 13640 | AU7: 14907 | AV7: =AW7-SUM(AS7:AU7) -> 16960 | AW7: 57401 | AX7: 16685 | AY7: 17341 | AZ7: 17415 | BA7: 19793 | BB7: =SUM(AX7:BA7) -> 71234 | BC7: 16318 | BD7: 19238 | BE7: 19754 | BF7: 21482.4 | BG7: =SUM(BC7:BF7) -> 76792.4 | BH7: 18015 | BI7: 19527 | BJ7: 21378 | BK7: 21768 | BL7: =SUM(BH7:BK7) -> 80688 | BM7: 19485 | BN7: 21923 | BO7: 23000 | BP7: 20847 | BQ7: =SUM(BM7:BP7) -> 85255 | BR7: 19885 | BS7: 22184 | BT7: 21494 | BU7: 20836 | BV7: =SUM(BR7:BU7) -> 84399 | BW7: 19367 | BX7: 20147 | BY7: 21825 | BZ7: 22720 | CA7: =SUM(BW7:BZ7) -> 84059 | CB7: 20820 | CC7: 21565 | CD7: 22463 | CE7: 25381 | CF7: =+SUM(CB7:CE7) -> 90229 | CG7: 20225 | CH7: 13094 | CI7: 17195 | CJ7: 15580 | CK7: =+SUM(CG7:CJ7) -> 66094 | CL7: 14191 | CM7: 9063 | CN7: 11402 | CO7: =CP7-SUM(CL7:CN7) -> 12486 | CP7: 47142 | CQ7: 12518 | CR7: 14154 | CS7: 12552 | CT7: 12162 | CU7: =+SUM(CQ7:CT7) -> 51386 | CV7: 11427 | CW7: 14009 | CX7: 13331 | CY7: 17126 | CZ7: =+SUM(CV7:CY7) -> 55893 | DA7: 14914 | DB7: 16687 | DC7: 15060 | DD7: 18920 | DE7: =+SUM(DA7:DD7) -> 65581 | DF7: 13268 | DG7: 13524 | DH7: 14534 | DI7: 11901 | DJ7: =+SUM(DF7:DI7) -> 53227 | DK7: 16147 | DL7: 19122 | DM7: 19642 | DN7: 20445 | DO7: =+SUM(DK7:DN7) -> 75356 | DP7: 18998 | DQ7: 21366
B8: Sales of services | N8: 8497 | O8: 2196 | P8: 2634 | Q8: 2295 | R8: =S8-O8-P8-Q8 -> 2322 | S8: 9447 | T8: 2062 | U8: 2138 | V8: 2351 | W8: =X8-T8-U8-V8 -> 2335 | X8: 8886 | Y8: 2136 | Z8: 2241 | AA8: 2340 | AB8: =AC8-Y8-Z8-AA8 -> 2621 | AC8: 9338 | AD8: 2302 | AE8: 2664 | AF8: 2886 | AG8: =AH8-AD8-AE8-AF8 -> 2877 | AH8: 10729 | AI8: 2667 | AJ8: 2858 | AK8: 2721 | AL8: 3003 | AM8: =SUM(AI8:AL8) -> 11249 | AN8: 2900 | AO8: 2949 | AP8: 2890 | AQ8: 2981 | AR8: =SUM(AN8:AQ8) -> 11720 | AS8: 3016 | AT8: 2903 | AU8: 2820 | AV8: =AW8-SUM(AS8:AU8) -> 2595 | AW8: 11334 | AX8: 2698 | AY8: 2664 | AZ8: 2593 | BA8: 2509 | BB8: =SUM(AX8:BA8) -> 10464 | BC8: 2575 | BD8: 2577 | BE8: 2376 | BF8: 2303 | BG8: =SUM(BC8:BF8) -> 9831 | BH8: 2450 | BI8: 2518 | BJ8: 2406 | BK8: 2700 | BL8: =SUM(BH8:BK8) -> 10074 | BM8: 2664 | BN8: 2620 | BO8: 2849 | BP8: 2726 | BQ8: =SUM(BM8:BP8) -> 10859 | BR8: 2747 | BS8: 2571 | BT8: 2404 | BU8: 2450 | BV8: =SUM(BR8:BU8) -> 10172 | BW8: 2594 | BX8: 2592 | BY8: 2484 | BZ8: 2648 | CA8: =SUM(BW8:BZ8) -> 10318 | CB8: 2562 | CC8: 2693 | CD8: 2683 | CE8: 2960 | CF8: =+SUM(CB8:CE8) -> 10898 | CG8: 2692 | CH8: 2657 | CI8: 2785 | CJ8: 2331 | CK8: =+SUM(CG8:CJ8) -> 10465 | CL8: 2717 | CM8: 2744 | CN8: 2737 | CO8: =CP8-SUM(CL8:CN8) -> 2818 | CP8: 11016 | CQ8: 2699 | CR8: 2844 | CS8: 2726 | CT8: 2631 | CU8: =+SUM(CQ8:CT8) -> 10900 | CV8: 2564 | CW8: 2672 | CX8: 2625 | CY8: 2854 | CZ8: =+SUM(CV8:CY8) -> 10715 | DA8: 3007 | DB8: 3064 | DC8: 3044 | DD8: 3098 | DE8: =+SUM(DA8:DD8) -> 12213 | DF8: 3301 | DG8: 3342 | DH8: 3306 | DI8: 3341 | DJ8: =+SUM(DF8:DI8) -> 13290 | DK8: 3349 | DL8: 3627 | DM8: 3628 | DN8: 3503 | DO8: =+SUM(DK8:DN8) -> 14107 | DP8: 3219 | DQ8: 3194
B9: Total revenues | C9: 45800 | D9: 56154 | E9: 57993 | F9: 51321 | G9: 58198 | H9: 54069 | I9: 50485 | J9: 12959 | K9: 13088 | L9: 13152 | M9: =N9-SUM(J9:L9) -> 13258 | N9: =SUM(N7:N8) -> 52457 | O9: =SUM(O7:O8) -> 12987 | P9: =SUM(P7:P8) -> 15028 | Q9: =SUM(Q7:Q8) -> 12629 | R9: =S9-O9-P9-Q9 -> 14201 | S9: =SUM(S7:S8) -> 54845 | T9: =SUM(T7:T8) -> 14264 | U9: =SUM(U7:U8) -> 14986 | V9: =SUM(V7:V8) -> 14739 | W9: =X9-T9-U9-V9 -> 17541 | X9: =SUM(X7:X8) -> 61530 | Y9: =SUM(Y7:Y8) -> 15365 | Z9: =SUM(Z7:Z8) -> 17028 | AA9: =SUM(AA7:AA8) -> 16517 | AB9: =AC9-Y9-Z9-AA9 -> 17477 | AC9: =SUM(AC7:AC8) -> 66387 | AD9: =SUM(AD7:AD8) -> 15990 | AE9: =SUM(AE7:AE8) -> 16962 | AF9: =SUM(AF7:AF8) -> 15293 | AG9: =AH9-AD9-AE9-AF9 -> 12664 | AH9: =SUM(AH7:AH8) -> 60909 | AI9: =SUM(AI7:AI8) -> 16502 | AJ9: =SUM(AJ7:AJ8) -> 17154 | AK9: =SUM(AK7:AK8) -> 16688 | AL9: =SUM(AL7:AL8) -> 17937 | AM9: =SUM(AM7:AM8) -> 68281 | AN9: =SUM(AN7:AN8) -> 15216 | AO9: =SUM(AO7:AO8) -> 15573 | ... BW9: =SUM(BW7:BW8) -> 21961 | BX9: 23051 | BY9: 24223 | BZ9: 24770 | CA9: 94005 | CB9: =SUM(CB7:CB8) -> 23382 | CC9: =SUM(CC7:CC8) -> 24258 | CD9: =SUM(CD7:CD8) -> 25146 | CE9: =SUM(CE7:CE8) -> 28341 | CF9: =+SUM(CF7:CF8) -> 101127 | CG9: =SUM(CG7:CG8) -> 22917 | CH9: =SUM(CH7:CH8) -> 15751 | CI9: =SUM(CI7:CI8) -> 19980 | CJ9: =SUM(CJ7:CJ8) -> 17911 | CK9: =+SUM(CK7:CK8) -> 76559 | CL9: =SUM(CL7:CL8) -> 16908 | CM9: =SUM(CM7:CM8) -> 11807 | CN9: =SUM(CN7:CN8) -> 14139 | CO9: =SUM(CO7:CO8) -> 15304 | CP9: =+SUM(CP7:CP8) -> 58158 | CQ9: =SUM(CQ7:CQ8) -> 15217 | CR9: =SUM(CR7:CR8) -> 16998 | CS9: =SUM(CS7:CS8) -> 15278 | CT9: =SUM(CT7:CT8) -> 14793 | CU9: =+SUM(CU7:CU8) -> 62286 | CV9: =SUM(CV7:CV8) -> 13991 | CW9: =SUM(CW7:CW8) -> 16681 | CX9: =SUM(CX7:CX8) -> 15956 | CY9: =SUM(CY7:CY8) -> 19980 | CZ9: =+SUM(CZ7:CZ8) -> 66608 | DA9: =SUM(DA7:DA8) -> 17921 | DB9: =SUM(DB7:DB8) -> 19751 | DC9: =SUM(DC7:DC8) -> 18104 | DD9: =SUM(DD7:DD8) -> 22018 | DE9: =+SUM(DE7:DE8) -> 77794 | DF9: =SUM(DF7:DF8) -> 16569 | DG9: =SUM(DG7:DG8) -> 16866 | DH9: =SUM(DH7:DH8) -> 17840 | DI9: =SUM(DI7:DI8) -> 15242 | DJ9: =+SUM(DJ7:DJ8) -> 66517 | DK9: =SUM(DK7:DK8) -> 19496 | DL9: =SUM(DL7:DL8) -> 22749 | DM9: =SUM(DM7:DM8) -> 23270 | DN9: =SUM(DN7:DN8) -> 23948 | DO9: =+SUM(DO7:DO8) -> 89463 | DP9: =SUM(DP7:DP8) -> 22217 | DQ9: =SUM(DQ7:DQ8) -> 24560
B10: Cost of products | J10: -9360.75 | K10: -9360.75 | L10: -9360.75 | M10: -9360.75 | N10: -37443 | O10: -8830 | P10: -10187 | Q10: -8706 | R10: =S10-O10-P10-Q10 -> -10359 | S10: -38082 | T10: -9618 | U10: -10821 | V10: -9789 | W10: =X10-T10-U10-V10 -> -12262 | X10: -42490 | Y10: -10431 | Z10: -11709 | AA10: -11331 | AB10: =AC10-Y10-Z10-AA10 -> -11904 | AC10: -45375 | AD10: -10788 | AE10: -11637 | AF10: -10311 | AG10: =AH10-AD10-AE10-AF10 -> -8926 | AH10: -41662 | AI10: -11579 | AJ10: -11580 | AK10: -12273 | AL10: -12207 | AM10: =SUM(AI10:AL10) -> -47639 | AN10: -9822 | AO10: -10115 | AP10: -11232 | AQ10: -11025 | AR10: =SUM(AN10:AQ10) -> -42194 | AS10: -9506 | AT10: -10823 | AU10: -12006 | AV10: =AW10-SUM(AS10:AU10) -> -14307 | AW10: -46642 | AX10: -13661 | AY10: -14759 | AZ10: -14683 | BA10: -17206 | BB10: =SUM(AX10:BA10) -> -60309 | BC10: -13728 | BD10: -16437 | BE10: -16865 | BF10: -18610 | BG10: =SUM(BC10:BF10) -> -65640 | BH10: -15258 | BI10: -16674 | BJ10: -18091 | BK10: -18528 | BL10: =SUM(BH10:BK10) -> -68551 | BM10: -16380 | BN10: -19247 | BO10: -19393 | BP10: -18426 | BQ10: =SUM(BM10:BP10) -> -73446 | BR10: -16945 | BS10: -20265 | BT10: -17907 | BU10: -17596 | BV10: =SUM(BR10:BU10) -> -72713 | BW10: -16062 | BX10: -16443 | BY10: -18050 | BZ10: -18509 | CA10: =SUM(BW10:BZ10) -> -69064 | CB10: -16816 | CC10: -17436 | CD10: -18882 | CE10: -19788 | CF10: =+SUM(CB10:CE10) -> -72922 | CG10: -16238 | CH10: -15672 | CI10: -14674 | CJ10: -16293 | CK10: =+SUM(CG10:CJ10) -> -62877 | CL10: -14713 | CM10: -10378 | CN10: -10910 | CO10: =CP10-SUM(CL10:CN10) -> -18567 | CP10: -54568 | CQ10: -11632 | CR10: -12263 | CS10: -11271 | CT10: -14788 | CU10: =+SUM(CQ10:CT10) -> -49954 | CV10: -11412 | CW10: -12284 | CX10: -14541 | CY10: -15732 | CZ10: =+SUM(CV10:CY10) -> -53969 | DA10: -13553 | DB10: -15123 | DC10: -14464 | DD10: -16724 | DE10: =+SUM(DA10:DD10) -> -59864 | DF10: -12064 | DG10: -12907 | DH10: -18413 | DI10: -14010 | DJ10: =+SUM(DF10:DI10) -> -57394 | DK10: -14379 | DL10: -17406 | DM10: -22737 | DN10: -19239 | DO10: =+SUM(DK10:DN10) -> -73761 | DP10: -17031 | DQ10: -19487
B11: Cost of services | C11: -40644 | D11: -50546 | E11: -51320 | F11: -43712 | G11: -48778 | H11: -45499 | I11: -43862 | J11: =-10728-J10 -> -1367.25 | K11: =-10875-K10 -> -1514.25 | L11: =-11164-L10 -> -1803.25 | M11: =N11-SUM(J11:L11) -> -2547.25 | N11: -7232 | O11: -1859 | P11: -2204 | Q11: -1987 | R11: =S11-O11-P11-Q11 -> -1717 | S11: -7767 | T11: -1786 | U11: -1691 | V11: -2014 | W11: =X11-T11-U11-V11 -> -2103 | X11: -7594 | Y11: -1756 | Z11: -1827 | AA11: -1803 | AB11: =AC11-Y11-Z11-AA11 -> -2346 | AC11: -7732 | AD11: -1755 | AE11: -2248 | AF11: -2176 | AG11: =AH11-AD11-AE11-AF11 -> -2288 | AH11: -8467 | AI11: -2119 | AJ11: -2184 | AK11: -2165 | AL11: -2258 | AM11: =SUM(AI11:AL11) -> -8726 | AN11: -2281 | AO11: -2384 | AP11: -2472 | AQ11: -2352 | AR11: =SUM(AN11:AQ11) -> -9489 | AS11: -2510 | AT11: -2348 | AU11: -2319 | AV11: =AW11-SUM(AS11:AU11) -> -1920 | AW11: -9097 | AX11: -2380 | AY11: -1962 | AZ11: -2089 | BA11: -1816 | BB11: =SUM(AX11:BA11) -> -8247 | BC11: -2009 | BD11: -1995 | BE11: -1791 | BF11: -1758 | BG11: =SUM(BC11:BF11) -> -7553 | BH11: -2020 | BI11: -1979 | BJ11: -1966 | BK11: -2167 | BL11: =SUM(BH11:BK11) -> -8132 | BM11: -2100 | BN11: -2086 | BO11: -2191 | BP11: -2201 | BQ11: =SUM(BM11:BP11) -> -8578 | BR11: -2136 | BS11: -2044 | BT11: -1983 | BU11: -1855 | BV11: =SUM(BR11:BU11) -> -8018 | BW11: -1998 | BX11: -1932 | BY11: -1910 | BZ11: -1901 | CA11: =SUM(BW11:BZ11) -> -7741 | CB11: -1992 | CC11: -2083 | CD11: -2140 | CE11: -2284 | CF11: =+SUM(CB11:CE11) -> -8499 | CG11: -2389 | CH11: -2122 | CI11: -2241 | CJ11: -2402 | CK11: =+SUM(CG11:CJ11) -> -9154 | CL11: -2043 | CM11: -2589 | CN11: -2185 | CO11: =CP11-SUM(CL11:CN11) -> -2415 | CP11: -9232 | CQ11: -2167 | CR11: -2316 | CS11: -2288 | CT11: -2512 | CU11: =+SUM(CQ11:CT11) -> -9283 | CV11: -2226 | CW11: -2269 | CX11: -2230 | CY11: -2384 | CZ11: =+SUM(CV11:CY11) -> -9109 | DA11: -2445 | DB11: -2689 | DC11: -2475 | DD11: -2597 | DE11: =+SUM(DA11:DD11) -> -10206 | DF11: -2629 | DG11: -2730 | DH11: -2934 | DI11: -2821 | DJ11: =+SUM(DF11:DI11) -> -11114 | DK11: -2700 | DL11: -2908 | DM11: -2908 | DN11: -2897 | DO11: =+SUM(DK11:DN11) -> -11413 | DP11: -2640 | DQ11: -2659
B12: Boeing Capital Corporation interest expense | C12: 0 | D12: 0 | E12: 0 | F12: 0 | G12: 0 | H12: 0 | I12: -442 | J12: -103 | K12: -89 | L12: -89 | M12: =N12-SUM(J12:L12) -> -69 | N12: -350 | O12: -89 | P12: -90 | Q12: -87 | R12: =S12-O12-P12-Q12 -> -93 | S12: -359 | T12: -90 | U12: -89 | V12: -88 | W12: =X12-T12-U12-V12 -> -86 | X12: -353 | Y12: -79 | Z12: -73 | AA12: -73 | AB12: =AC12-Y12-Z12-AA12 -> -70 | AC12: -295 | AD12: -62 | AE12: -57 | AF12: -54 | AG12: =AH12-AD12-AE12-AF12 -> -50 | AH12: -223 | AI12: -47 | AJ12: -43 | AK12: -42 | AL12: -43 | AM12: =SUM(AI12:AL12) -> -175 | AN12: -41 | AO12: -41 | AP12: -42 | AQ12: -36 | AR12: =SUM(AN12:AQ12) -> -160 | AS12: -33 | AT12: -29 | AU12: -32 | AV12: =AW12-SUM(AS12:AU12) -> -34 | AW12: -128 | AX12: -28 | AY12: -19 | AZ12: -22 | BA12: -19 | BB12: =SUM(AX12:BA12) -> -88 | BC12: -19 | BD12: -18 | BE12: -18 | BF12: -20 | BG12: =SUM(BC12:BF12) -> -75 | BH12: -18 | BI12: -17 | BJ12: -18 | BK12: -16 | BL12: =SUM(BH12:BK12) -> -69 | BM12: -16 | BN12: -17 | BO12: -16 | BP12: -15 | BQ12: =SUM(BM12:BP12) -> -64 | BR12: -16 | BS12: -16 | BT12: -14 | BU12: -13 | BV12: =SUM(BR12:BU12) -> -59 | BW12: -13 | BX12: -13 | BY12: -27 | BZ12: -17 | CA12: =SUM(BW12:BZ12) -> -70 | CB12: -16 | CC12: -17 | CD12: -18 | CE12: -18 | CF12: =+SUM(CB12:CE12) -> -69 | CG12: -18 | CH12: -16 | CI12: -15 | CJ12: -13 | CK12: =+SUM(CG12:CJ12) -> -62 | CL12: -12 | CM12: -11 | CN12: -10 | CO12: =CP12-SUM(CL12:CN12) -> -10 | CP12: -43 | CQ12: -9 | CR12: -9 | CS12: -7 | CT12: -7 | CU12: =+SUM(CQ12:CT12) -> -32 | CV12: -7 | CW12: -6 | CX12: -7 | CY12: -8 | CZ12: =+SUM(CV12:CY12) -> -28 | DE12: =+SUM(DA12:DD12) -> 0 | DJ12: =+SUM(DF12:DI12) -> 0 | DO12: =+SUM(DK12:DN12) -> 0
B13: Total costs and expenses | C13: =SUM(C10:C12) -> -40644 | D13: =SUM(D10:D12) -> -50546 | E13: =SUM(E10:E12) -> -51320 | F13: =SUM(F10:F12) -> -43712 | G13: =SUM(G10:G12) -> -48778 | H13: =SUM(H10:H12) -> -45499 | I13: =SUM(I10:I12) -> -44304 | J13: =SUM(J10:J12) -> -10831 | ... L13: =SUM(L10:L12) -> -11253 | M13: =N13-SUM(J13:L13) -> -11977 | N13: =SUM(N10:N12) -> -45025 | O13: =SUM(O10:O12) -> -10778 | P13: =SUM(P10:P12) -> -12481 | Q13: =SUM(Q10:Q12) -> -10780 | R13: =S13-O13-P13-Q13 -> -12169 | S13: =SUM(S10:S12) -> -46208 | T13: =SUM(T10:T12) -> -11494 | U13: =SUM(U10:U12) -> -12601 | V13: =SUM(V10:V12) -> -11891 | W13: =X13-T13-U13-V13 -> -14451 | X13: =SUM(X10:X12) -> -50437 | Y13: =SUM(Y10:Y12) -> -12266 | Z13: =SUM(Z10:Z12) -> -13609 | AA13: =SUM(AA10:AA12) -> -13207 | AB13: =AC13-Y13-Z13-AA13 -> -14320 | AC13: =SUM(AC10:AC12) -> -53402 | AD13: =SUM(AD10:AD12) -> -12605 | AE13: =SUM(AE10:AE12) -> -13942 | AF13: =SUM(AF10:AF12) -> -12541 | AG13: =AH13-AD13-AE13-AF13 -> -11264 | AH13: =SUM(AH10:AH12) -> -50352 | AI13: =SUM(AI10:AI12) -> -13745 | AJ13: =SUM(AJ10:AJ12) -> -13807 | AK13: =SUM(AK10:AK12) -> -14480 | AL13: =SUM(AL10:AL12) -> -14508 | AM13: =SUM(AM10:AM12) -> -56540 | AN13: =SUM(AN10:AN12) -> -12144 | AO13: =SUM(AO10:AO12) -> -12540 | ... BW13: =SUM(BW10:BW12) -> -18073 | BX13: -18702 | BY13: -19956 | BZ13: -19881 | CA13: -76612 | CB13: =SUM(CB10:CB12) -> -18824 | CC13: =SUM(CC10:CC12) -> -19536 | CD13: =SUM(CD10:CD12) -> -21040 | CE13: =SUM(CE10:CE12) -> -22090 | CF13: =+SUM(CB13:CE13) -> -81490 | CG13: =SUM(CG10:CG12) -> -18645 | CH13: =SUM(CH10:CH12) -> -17810 | CI13: =SUM(CI10:CI12) -> -16930 | CJ13: =SUM(CJ10:CJ12) -> -18708 | CK13: =+SUM(CG13:CJ13) -> -72093 | CL13: =SUM(CL10:CL12) -> -16768 | CM13: =SUM(CM10:CM12) -> -12978 | CN13: =SUM(CN10:CN12) -> -13105 | CO13: =SUM(CO10:CO12) -> -20992 | CP13: =+SUM(CL13:CO13) -> -63843 | CQ13: =SUM(CQ10:CQ12) -> -13808 | CR13: =SUM(CR10:CR12) -> -14588 | CS13: =SUM(CS10:CS12) -> -13566 | CT13: =SUM(CT10:CT12) -> -17307 | CU13: =+SUM(CQ13:CT13) -> -59269 | CV13: =SUM(CV10:CV12) -> -13645 | CW13: =SUM(CW10:CW12) -> -14559 | CX13: =SUM(CX10:CX12) -> -16778 | CY13: =SUM(CY10:CY12) -> -18124 | CZ13: =+SUM(CV13:CY13) -> -63106 | DA13: =SUM(DA10:DA12) -> -15998 | DB13: =SUM(DB10:DB12) -> -17812 | DC13: =SUM(DC10:DC12) -> -16939 | DD13: =SUM(DD10:DD12) -> -19321 | DE13: =+SUM(DA13:DD13) -> -70070 | DF13: =SUM(DF10:DF12) -> -14693 | DG13: =SUM(DG10:DG12) -> -15637 | DH13: =SUM(DH10:DH12) -> -21347 | DI13: =SUM(DI10:DI12) -> -16831 | DJ13: =+SUM(DF13:DI13) -> -68508 | DK13: =SUM(DK10:DK12) -> -17079 | DL13: =SUM(DL10:DL12) -> -20314 | DM13: =SUM(DM10:DM12) -> -25645 | DN13: =SUM(DN10:DN12) -> -22136 | DO13: =+SUM(DK13:DN13) -> -85174 | DP13: =SUM(DP10:DP12) -> -19671 | DQ13: =SUM(DQ10:DQ12) -> -22146
B14: Income from operating investments, net | C14: 0 | D14: 0 | E14: 4 | F14: 64 | G14: 93 | H14: -128 | I14: 28 | J14: 13 | K14: 27 | L14: 27 | M14: =N14-SUM(J14:L14) -> 24 | N14: 91 | O14: 16 | P14: 28 | Q14: 24 | R14: =S14-O14-P14-Q14 -> 20 | S14: 88 | T14: 20 | U14: 33 | V14: 42 | W14: =X14-T14-U14-V14 -> 51 | X14: 146 | Y14: 39 | Z14: 50 | AA14: 11 | AB14: =AC14-Y14-Z14-AA14 -> 88 | AC14: 188 | AD14: 58 | AE14: 65 | AF14: 72 | AG14: =AH14-AD14-AE14-AF14 -> 46 | AH14: 241 | AI14: 32 | AJ14: 70 | AK14: 84 | AL14: 63 | AM14: =SUM(AI14:AL14) -> 249 | AN14: 59 | AO14: 54 | AP14: 74 | AQ14: 80 | AR14: =SUM(AN14:AQ14) -> 267 | AS14: 62 | AT14: 88 | AU14: 52 | AV14: =AW14-SUM(AS14:AU14) -> 76 | AW14: 278 | AX14: 46 | AY14: 45 | AZ14: 120 | BA14: 57 | BB14: =SUM(AX14:BA14) -> 268 | BC14: 45 | BD14: 43 | BE14: 59 | BF14: 67 | BG14: =SUM(BC14:BF14) -> 214 | BH14: 59 | BI14: 61 | BJ14: 92 | BK14: 75 | BL14: =SUM(BH14:BK14) -> 287 | BM14: 79 | BN14: 50 | BO14: 78 | BP14: 67 | BQ14: =SUM(BM14:BP14) -> 274 | BR14: 54 | BS14: 97 | BT14: 69 | BU14: 83 | BV14: =SUM(BR14:BU14) -> 303 | BW14: 81 | BX14: 39 | BY14: 49 | BZ14: 35 | CA14: =SUM(BW14:BZ14) -> 204 | CB14: 74 | CC14: 6 | CD14: 32 | CE14: -1 | CF14: =+SUM(CB14:CE14) -> 111 | CG14: 20 | CH14: -15 | CI14: -8 | CJ14: -1 | CK14: =+SUM(CG14:CJ14) -> -4 | CL14: -2 | CM14: -45 | CN14: -14 | CO14: 70 | CP14: =+SUM(CL14:CO14) -> 9 | CQ14: 37 | CR14: 38 | CS14: 120 | CT14: 15 | CU14: =+SUM(CQ14:CT14) -> 210 | CV14: -20 | CW14: 17 | CX14: -24 | CY14: 11 | CZ14: =+SUM(CV14:CY14) -> -16 | DA14: -27 | DB14: 44 | DC14: 28 | DD14: 1 | DE14: =+SUM(DA14:DD14) -> 46 | DF14: 67 | DG14: 7 | DH14: -15 | DI14: 12 | DJ14: =+SUM(DF14:DI14) -> 71 | DK14: 3 | DL14: 25 | DM14: 14 | DN14: -17 | DO14: =+SUM(DK14:DN14) -> 25 | DP14: -10 | DQ14: 24
B15: General and administrative | C15: -2187 | D15: -1993 | E15: -2044 | F15: -2335 | G15: -2389 | H15: -2534 | I15: -2768 | J15: -710 | K15: -824 | L15: -781 | M15: =N15-SUM(J15:L15) -> -766 | N15: -3081 | O15: -1071 | P15: -1057 | Q15: -1172 | R15: =S15-O15-P15-Q15 -> -928 | S15: -4228 | T15: -1081 | U15: -1162 | V15: -834 | W15: =X15-T15-U15-V15 -> -1094 | X15: -4171 | Y15: -828 | Z15: -976 | AA15: -931 | AB15: =AC15-Y15-Z15-AA15 -> -796 | AC15: -3531 | AD15: -775 | AE15: -835 | AF15: -740 | AG15: =AH15-AD15-AE15-AF15 -> -734 | AH15: -3084 | AI15: -791 | AJ15: -925 | AK15: -868 | AL15: -780 | AM15: =SUM(AI15:AL15) -> -3364 | AN15: -953 | AO15: -778 | AP15: -936 | AQ15: -977 | AR15: =SUM(AN15:AQ15) -> -3644 | AS15: -866 | AT15: -870 | AU15: -807 | AV15: =AW15-SUM(AS15:AU15) -> -865 | AW15: -3408 | AX15: -955 | AY15: -903 | AZ15: -916.4 | BA15: -943 | BB15: =SUM(AX15:BA15) -> -3717.4 | BC15: -971 | BD15: -929 | BE15: -956 | BF15: -1100 | BG15: =SUM(BC15:BF15) -> -3956 | BH15: -877 | BI15: -918 | BJ15: -932 | BK15: -1040 | BL15: =SUM(BH15:BK15) -> -3767 | BM15: -945 | BN15: -760 | BO15: -889 | BP15: -931 | BQ15: =SUM(BM15:BP15) -> -3525 | BR15: -888 | BS15: -806 | BT15: -923 | BU15: -999 | BV15: =SUM(BR15:BU15) -> -3616 | BW15: -929 | BX15: -1043 | BY15: -918 | BZ15: -1205 | CA15: =SUM(BW15:BZ15) -> -4095 | CB15: -997 | CC15: -1194 | CD15: -1154 | CE15: -1222 | CF15: =+SUM(CB15:CE15) -> -4567 | CG15: -1184 | CH15: -672 | CI15: -1001 | CJ15: -1052 | CK15: =+SUM(CG15:CJ15) -> -3909 | CL15: -873 | CM15: -1161 | CN15: -955 | CO15: -1828 | CP15: =+SUM(CL15:CO15) -> -4817 | CQ15: -1032 | CR15: -1040 | CS15: -1097 | CT15: -988 | CU15: =+SUM(CQ15:CT15) -> -4157 | CV15: -863 | CW15: -668 | CX15: -1226 | CY15: -1430 | CZ15: =+SUM(CV15:CY15) -> -4187 | DA15: -1304 | DB15: -1286 | DC15: -1043 | DD15: -1535 | DE15: =+SUM(DA15:DD15) -> -5168 | DF15: -1161 | DG15: -1377 | DH15: -1085 | DI15: -1398 | DJ15: =+SUM(DF15:DI15) -> -5021 | DK15: -1112 | DL15: -1793 | DM15: -1522 | DN15: -1663 | DO15: =+SUM(DK15:DN15) -> -6090 | DP15: -1197 | DQ15: -1428
B16: Research and development expense, net | C16: -1924 | D16: -1895 | E16: -1341 | F16: -1441 | G16: -1936 | H16: -1639 | I16: -1651 | J16: -474 | K16: -522 | L16: -469 | M16: =N16-SUM(J16:L16) -> -414 | N16: -1879 | O16: -492 | P16: -591 | Q16: -521 | R16: =S16-O16-P16-Q16 -> -601 | S16: -2205 | T16: -748 | U16: -739 | V16: -833 | W16: =X16-T16-U16-V16 -> -937 | X16: -3257 | Y16: -999 | Z16: -989 | AA16: -869 | AB16: =AC16-Y16-Z16-AA16 -> -993 | AC16: -3850 | AD16: -869 | AE16: -1005 | AF16: -937 | AG16: =AH16-AD16-AE16-AF16 -> -957 | AH16: -3768 | AI16: -970 | AJ16: -960 | AK16: -3574 | AL16: -1002 | AM16: =SUM(AI16:AL16) -> -6506 | AN16: -1000 | AO16: -1001 | AP16: -986 | AQ16: -1134 | AR16: =SUM(AN16:AQ16) -> -4121 | AS16: -1057 | AT16: -1047 | AU16: -901 | AV16: =AW16-SUM(AS16:AU16) -> -913 | AW16: -3918 | AX16: -835 | AY16: -857 | AZ16: -853.4 | BA16: -753 | BB16: =SUM(AX16:BA16) -> -3298.4 | BC16: -705 | BD16: -763 | BE16: -755 | BF16: -848 | BG16: =SUM(BC16:BF16) -> -3071 | BH16: -809 | BI16: -733 | BJ16: -750 | BK16: -755 | BL16: =SUM(BH16:BK16) -> -3047 | BM16: -769 | BN16: -800 | BO16: -857 | BP16: -905 | BQ16: =SUM(BM16:BP16) -> -3331 | BR16: -917 | BS16: -2127 | BT16: -857 | BU16: -726 | BV16: =SUM(BR16:BU16) -> -4627 | BW16: -836 | BX16: -813 | BY16: -768 | BZ16: -762 | CA16: =SUM(BW16:BZ16) -> -3179 | CB16: -764 | CC16: -827 | CD16: -826 | CE16: -852 | CF16: =+SUM(CB16:CE16) -> -3269 | CG16: -866 | CH16: -826 | CI16: -778 | CJ16: -749 | CK16: =+SUM(CG16:CJ16) -> -3219 | CL16: -672 | CM16: -625 | CN16: -574 | CO16: -605 | CP16: =+SUM(CL16:CO16) -> -2476 | CQ16: -499 | CR16: -497 | CS16: -575 | CT16: -678 | CU16: =+SUM(CQ16:CT16) -> -2249 | CV16: -633 | CW16: -698 | CX16: -727 | CY16: -794 | CZ16: =+SUM(CV16:CY16) -> -2852 | DA16: -741 | DB16: -797 | DC16: -958 | DD16: -881 | DE16: =+SUM(DA16:DD16) -> -3377 | DF16: -868 | DG16: -954 | DH16: -1154 | DI16: -836 | DJ16: =+SUM(DF16:DI16) -> -3812 | DK16: -844 | DL16: -910 | DM16: -897 | DN16: -964 | DO16: =+SUM(DK16:DN16) -> -3615 | DP16: -903 | DQ16: -921
B17: Loss on dispositions/business shutdown, net | C17: -1400 | D17: -153 | E17: =87-209 -> -122 | F17: =-557+34-316 -> -839 | G17: =21-378-935 -> -1292 | H17: =44-447+2 -> -401 | I17: =7-456-913+21 -> -1341 | J17: -119 | K17: =6-164-3 -> -161 | L17: =1-166 -> -165 | M17: =N17-SUM(J17:L17) -> -111 | N17: =23+-576-3 -> -556 | O17: 25 | P17: -117 | Q17: 583 | R17: =S17-O17-P17-Q17 -> 29 | S17: 520 | T17: -2 | U17: 6 | V17: -272 | W17: =X17-T17-U17-V17 -> 42 | X17: -226 | Y17: -2 | Z17: 2 | AA17: -22 | AB17: =AC17-Y17-Z17-AA17 -> 60 | AC17: 38 | AE17: 2 | AG17: =AH17-AD17-AE17-AF17 -> 2 | AH17: 4 | AI17: -3 | AJ17: -3 | AK17: -1 | AL17: -17 | AM17: =SUM(AI17:AL17) -> -24 | AN17: -4 | AO17: -1 | AP17: 14 | AQ17: -3 | AR17: =SUM(AN17:AQ17) -> 6 | AS17: 0 | AT17: 20 | AU17: 0 | AV17: =AW17-SUM(AS17:AU17) -> 4 | AW17: 24 | AX17: 0 | AY17: -2 | AZ17: -1 | BA17: 7 | BB17: =SUM(AX17:BA17) -> 4 | BC17: 22 | BD17: 0 | BE17: -1 | BF17: -1 | BG17: =SUM(BC17:BF17) -> 20 | BH17: 0 | BI17: 2 | BJ17: 0 | BK17: -12 | BL17: =SUM(BH17:BK17) -> -10 | BM17: 1 | BN17: 0 | BO17: -1 | BP17: -1 | BQ17: =SUM(BM17:BP17) -> -1 | BR17: 4 | BS17: -13 | BT17: -1 | BU17: 3 | BV17: =SUM(BR17:BU17) -> -7 | BW17: 2 | BX17: -2 | BY17: 0 | BZ17: 21 | CA17: =SUM(BW17:BZ17) -> 21 | CB17: 4 | CC17: 3 | CD17: 69 | CE17: -1 | CF17: =+SUM(CB17:CE17) -> 75 | CG17: 108 | CH17: 192 | CI17: -4 | CJ17: 395 | CK17: =+SUM(CG17:CJ17) -> 691 | CL17: 54 | CM17: 38 | CN17: 108 | CO17: 2 | CP17: =+SUM(CL17:CO17) -> 202 | CQ17: 2 | CR17: 112 | CS17: 169 | CT17: -6 | CU17: =+SUM(CQ17:CT17) -> 277 | CV17: 1 | CW17: 1 | CX17: 0 | CY17: 4 | CZ17: =+SUM(CV17:CY17) -> 6 | DA17: 0 | DB17: 1 | DC17: 0 | DD17: 1 | DE17: =+SUM(DA17:DD17) -> 2 | DG17: 5 | DH17: 0 | DI17: 41 | DJ17: =+SUM(DF17:DI17) -> 46 | DK17: -3 | DL17: 67 | DM17: -1 | DN17: 9609 | DO17: =+SUM(DK17:DN17) -> 9672 | DP17: 12 | DQ17: 67
B18: Earnings from operations | C18: =SUM(C14:C17)+C9+C13 -> -355 | D18: =SUM(D14:D17)+D9+D13 -> 1567 | E18: =SUM(E14:E17)+E9+E13 -> 3170 | F18: =SUM(F14:F17)+F9+F13 -> 3058 | G18: =SUM(G14:G17)+G9+G13 -> 3896 | H18: =SUM(H14:H17)+H9+H13 -> 3868 | I18: =SUM(I14:I17)+I9+I13 -> 449 | J18: =SUM(J14:J17)+J9+J13 -> 838 | ... L18: =SUM(L14:L17)+L9+L13 -> 511 | M18: =N18-SUM(J18:L18) -> 14 | N18: =SUM(N14:N17)+N9+N13 -> 2007 | O18: =SUM(O14:O17)+O9+O13 -> 687 | P18: =SUM(P14:P17)+P9+P13 -> 810 | Q18: =SUM(Q14:Q17)+Q9+Q13 -> 763 | R18: =S18-O18-P18-Q18 -> 552 | S18: =SUM(S14:S17)+S9+S13 -> 2812 | T18: =SUM(T14:T17)+T9+T13 -> 959 | U18: =SUM(U14:U17)+U9+U13 -> 523 | V18: =SUM(V14:V17)+V9+V13 -> 951 | W18: =X18-T18-U18-V18 -> 1152 | X18: =SUM(X14:X17)+X9+X13 -> 3585 | Y18: =SUM(Y14:Y17)+Y9+Y13 -> 1309 | Z18: =SUM(Z14:Z17)+Z9+Z13 -> 1506 | AA18: =SUM(AA14:AA17)+AA9+AA13 -> 1499 | AB18: =AC18-Y18-Z18-AA18 -> 1516 | AC18: =SUM(AC14:AC17)+AC9+AC13 -> 5830 | AD18: =SUM(AD14:AD17)+AD9+AD13 -> 1799 | AE18: =SUM(AE14:AE17)+AE9+AE13 -> 1247 | AF18: =SUM(AF14:AF17)+AF9+AF13 -> 1147 | AG18: =AH18-AD18-AE18-AF18 -> -243 | AH18: =SUM(AH14:AH17)+AH9+AH13 -> 3950 | AI18: =SUM(AI14:AI17)+AI9+AI13 -> 1025 | AJ18: =SUM(AJ14:AJ17)+AJ9+AJ13 -> 1529 | AK18: =SUM(AK14:AK17)+AK9+AK13 -> -2151 | AL18: =SUM(AL14:AL17)+AL9+AL13 -> 1693 | AM18: =SUM(AM14:AM17)+AM9+AM13 -> 2096 | AN18: =SUM(AN14:AN17)+AN9+AN13 -> 1174 | AO18: =SUM(AO14:AO17)+AO9+AO13 -> 1307 | ... CC18: =SUM(CC14:CC17)+CC9+CC13 -> 2710 | CD18: 2227 | CE18: =SUM(CE14:CE17)+CE9+CE13 -> 4175 | CF18: =SUM(CF14:CF17)+CF9+CF13 -> 11987 | CG18: =SUM(CG14:CG17)+CG9+CG13 -> 2350 | CH18: =SUM(CH14:CH17)+CH9+CH13 -> -3380 | CI18: =SUM(CI14:CI17)+CI9+CI13 -> 1259 | CJ18: =SUM(CJ14:CJ17)+CJ9+CJ13 -> -2204 | CK18: =SUM(CK14:CK17)+CK9+CK13 -> -1975 | CL18: =SUM(CL14:CL17)+CL9+CL13 -> -1353 | ... DQ18: =SUM(DQ14:DQ17)+DQ9+DQ13 -> 156
B19: Other income | BW19: 22 | BX19: 27 | BY19: 45 | BZ19: 35 | CA19: =SUM(BW19:BZ19) -> 129
B20: Non-operating pension expense | BW20: 34 | BX20: 28 | BY20: 26 | BZ20: 29 | CA20: =SUM(BW20:BZ20) -> 117
B21: Non-operating postretirement expense | BW21: -30 | BX21: -30 | BY21: -31 | BZ21: -32 | CA21: =SUM(BW21:BZ21) -> -123
B22: Other (loss)/income, non-operating pension net | C22: 428 | D22: 283 | E22: 585 | F22: 386 | G22: 318 | H22: 42 | I22: 459 | J22: 159 | K22: 66 | L22: 17 | M22: =N22-SUM(J22:L22) -> 46 | N22: 288 | O22: -16 | P22: 81 | Q22: 119 | R22: =S22-O22-P22-Q22 -> 117 | S22: 301 | T22: 86 | U22: =106-571 -> -465 | V22: 104 | W22: =X22-T22-U22-V22 -> 124 | X22: =420-571 -> -151 | Y22: 91 | Z22: 125 | AA22: 139 | AB22: =AC22-Y22-Z22-AA22 -> 129 | AC22: 484 | AD22: 100 | AE22: 102 | AF22: 55 | AG22: =AH22-AD22-AE22-AF22 -> -10 | AH22: 247 | AI22: -36 | AJ22: 47 | AK22: -4 | AL22: -33 | AM22: =SUM(AI22:AL22) -> -26 | AN22: -2 | AO22: 35 | AP22: -13 | AQ22: 32 | AR22: =SUM(AN22:AQ22) -> 52 | AS22: 13 | AT22: 14 | AU22: 49 | AV22: =AW22-SUM(AS22:AU22) -> -29 | AW22: 47 | AX22: 12 | AY22: 10 | AZ22: 17 | BA22: 23 | BB22: =SUM(AX22:BA22) -> 62 | BC22: 9 | BD22: 13 | BE22: 19 | BF22: 15 | BG22: =SUM(BC22:BF22) -> 56 | BH22: 9 | BI22: 11 | BJ22: -9 | BK22: -14 | BL22: =SUM(BH22:BK22) -> -3 | BM22: -12 | BN22: 15 | BO22: -26 | BP22: 10 | BQ22: =SUM(BM22:BP22) -> -13 | BR22: 26 | BS22: 13 | BT22: 2 | BU22: -1 | BV22: =SUM(BR22:BU22) -> 40 | BW22: =SUM(BW19:BW21) -> 26 | BX22: =SUM(BX19:BX21) -> 25 | BY22: =SUM(BY19:BY21) -> 40 | BZ22: =SUM(BZ19:BZ21) -> 32 | CA22: 123 | CB22: 66 | CC22: -15 | CD22: 12 | CE22: 29 | CF22: =+SUM(CB22:CE22) -> 92 | CG22: 106 | CH22: 107 | CI22: 121 | CJ22: 104 | CK22: =+SUM(CG22:CJ22) -> 438 | CL22: 112 | CM22: 94 | CN22: 119 | CO22: 122 | CP22: =+SUM(CL22:CO22) -> 447 | CQ22: 190 | CR22: 199 | CS22: 30 | CT22: 132 | CU22: =+SUM(CQ22:CT22) -> 551 | CV22: 181 | CW22: 253 | CX22: 288 | CY22: 336 | CZ22: =+SUM(CV22:CY22) -> 1058 | DA22: 302 | DB22: 320 | DC22: 297 | DD22: 308 | DE22: =+SUM(DA22:DD22) -> 1227 | DF22: 277 | DG22: 248 | DH22: 265 | DI22: 432 | DJ22: =+SUM(DF22:DI22) -> 1222 | DK22: 323 | DL22: 325 | DM22: 276 | DN22: 201 | DO22: =+SUM(DK22:DN22) -> 1125 | DP22: 194 | DQ22: 79
B23: Interest and debt expense | C23: =-513+99 -> -414 | D23: -453 | E23: -431 | F23: -445 | G23: -650 | H23: -730 | I23: -358 | J23: -84 | K23: -85 | L23: -83 | M23: =N23-SUM(J23:L23) -> -83 | N23: -335 | O23: -87 | P23: -84 | Q23: -70 | R23: =S23-O23-P23-Q23 -> -53 | S23: -294 | T23: -69 | U23: -67 | V23: -67 | W23: =X23-T23-U23-V23 -> -37 | X23: -240 | Y23: -46 | Z23: -46 | AA23: -47 | AB23: =AC23-Y23-Z23-AA23 -> -57 | AC23: -196 | AD23: -46 | AE23: -50 | AF23: -49 | AG23: =AH23-AD23-AE23-AF23 -> -57 | AH23: -202 | AI23: -57 | AJ23: -80 | AK23: -92 | AL23: -110 | AM23: =SUM(AI23:AL23) -> -339 | AN23: -122 | AO23: -132 | AP23: -130 | AQ23: -132 | AR23: =SUM(AN23:AQ23) -> -516 | AS23: -130.2 | AT23: -123 | AU23: -121 | AV23: =AW23-SUM(AS23:AU23) -> -123.8 | AW23: -498 | AX23: -119 | AY23: -112 | AZ23: -115.4 | BA23: -117 | BB23: =SUM(AX23:BA23) -> -463.4 | BC23: -99 | BD23: -96 | BE23: -95 | BF23: -96 | BG23: =SUM(BC23:BF23) -> -386 | BH23: -92 | BI23: -81 | BJ23: -79 | BK23: -81 | BL23: =SUM(BH23:BK23) -> -333 | BM23: -61 | BN23: -75 | BO23: -67 | BP23: -72 | BQ23: =SUM(BM23:BP23) -> -275 | BR23: -73 | BS23: -73 | BT23: -81 | BU23: -79 | BV23: =SUM(BR23:BU23) -> -306 | BW23: -87 | BX23: -93 | BY23: -87 | BZ23: -93 | CA23: =SUM(BW23:BZ23) -> -360 | CB23: -102 | CC23: -109 | CD23: -106 | CE23: -158 | CF23: =+SUM(CB23:CE23) -> -475 | CG23: -123 | CH23: -154 | CI23: -203 | CJ23: -242 | CK23: =+SUM(CG23:CJ23) -> -722 | CL23: -262 | CM23: -553 | CN23: -643 | CO23: -698 | CP23: =+SUM(CL23:CO23) -> -2156 | CQ23: -679 | CR23: -673 | CS23: -669 | CT23: -661 | CU23: =+SUM(CQ23:CT23) -> -2682 | CV23: -630 | CW23: -650 | CX23: -621 | CY23: -632 | CZ23: =+SUM(CV23:CY23) -> -2533 | DA23: -649 | DB23: -621 | DC23: -589 | DD23: -600 | DE23: =+SUM(DA23:DD23) -> -2459 | DF23: -569 | DG23: -673 | DH23: -728 | DI23: -755 | DJ23: =+SUM(DF23:DI23) -> -2725 | DK23: -708 | DL23: -710 | DM23: -694 | DN23: -659 | DO23: =+SUM(DK23:DN23) -> -2771 | DP23: -616 | DQ23: -600
B24: Earnings before income taxes | C24: =C23+C22+C18 -> -341 | D24: =D23+D22+D18 -> 1397 | E24: =E23+E22+E18 -> 3324 | F24: =F23+F22+F18 -> 2999 | G24: =G23+G22+G18 -> 3564 | H24: =H23+H22+H18 -> 3180 | I24: =I23+I22+I18 -> 550 | J24: =J23+J22+J18 -> 913 | ... L24: =L23+L22+L18 -> 445 | M24: =N24-SUM(J24:L24) -> -23 | N24: =N23+N22+N18 -> 1960 | O24: =O23+O22+O18 -> 584 | P24: =P23+P22+P18 -> 807 | Q24: =Q23+Q22+Q18 -> 812 | R24: =S24-O24-P24-Q24 -> 616 | S24: =S23+S22+S18 -> 2819 | T24: =T23+T22+T18 -> 976 | U24: =U23+U22+U18 -> -9 | V24: =V23+V22+V18 -> 988 | W24: =X24-T24-U24-V24 -> 1239 | X24: =X23+X22+X18 -> 3194 | Y24: =Y23+Y22+Y18 -> 1354 | Z24: =Z23+Z22+Z18 -> 1585 | AA24: =AA23+AA22+AA18 -> 1591 | AB24: =AC24-Y24-Z24-AA24 -> 1588 | AC24: =AC23+AC22+AC18 -> 6118 | AD24: =AD23+AD22+AD18 -> 1853 | AE24: =AE23+AE22+AE18 -> 1299 | AF24: =AF23+AF22+AF18 -> 1153 | AG24: =AH24-AD24-AE24-AF24 -> -310 | AH24: =AH18+AH22+AH23 -> 3995 | AI24: =AI18+AI22+AI23 -> 932 | AJ24: =AJ18+AJ22+AJ23 -> 1496 | AK24: =AK18+AK22+AK23 -> -2247 | AL24: =AL18+AL22+AL23 -> 1550 | AM24: =AM18+AM22+AM23 -> 1731 | AN24: =AN18+AN22+AN23 -> 1050 | AO24: =AO18+AO22+AO23 -> 1210 | ... DQ24: =DQ18+DQ22+DQ23 -> -365
B25: Income tax expense | C25: 163 | D25: -277 | E25: -1015 | F25: -871 | G25: -738 | H25: -861 | I25: 168 | J25: -290 | K25: -39 | L25: -7 | M25: =N25-SUM(J25:L25) -> 196 | N25: -140 | O25: -70 | P25: -241 | Q25: 201 | R25: =S25-O25-P25-Q25 -> -147 | S25: -257 | T25: -284 | U25: -151 | V25: -294 | W25: =X25-T25-U25-V25 -> -259 | X25: -988 | Y25: -481 | Z25: -536 | AA25: -482 | AB25: =AC25-Y25-Z25-AA25 -> -561 | AC25: -2060 | AD25: -647 | AE25: -448 | AF25: -470 | AG25: =AH25-AD25-AE25-AF25 -> 224 | AH25: -1341 | AI25: -317 | AJ25: -499 | AK25: 687 | AL25: -267 | AM25: =SUM(AI25:AL25) -> -396 | AN25: -531 | AO25: -421 | AP25: -407 | AQ25: 163 | AR25: =SUM(AN25:AQ25) -> -1196 | AS25: -295 | AT25: -483 | AU25: -548 | AV25: =AW25-SUM(AS25:AU25) -> -56 | AW25: -1382 | AX25: -539 | AY25: -479 | AZ25: -432.4 | BA25: -557 | BB25: =SUM(AX25:BA25) -> -2007.4 | BC25: -332 | BD25: -546 | BE25: -567 | BF25: -201 | BG25: =SUM(BC25:BF25) -> -1646 | BH25: -494 | BI25: -64 | BJ25: -669 | BK25: -464 | BL25: =SUM(BH25:BK25) -> -1691 | BM25: -610 | BN25: -513 | BO25: -783 | BP25: -73 | BQ25: =SUM(BM25:BP25) -> -1979 | BR25: -522 | BS25: 245 | BT25: 76 | BU25: -472 | BV25: =SUM(BR25:BU25) -> -673 | BW25: -566 | BX25: -713 | BY25: -773 | BZ25: 403 | CA25: -1649 | CB25: -362 | CC25: -390 | CD25: 230 | CE25: -622 | CF25: =+SUM(CB25:CE25) -> -1144 | CG25: -184 | CH25: 485 | CI25: -10 | CJ25: 1332 | CK25: =+SUM(CG25:CJ25) -> 1623 | CL25: 862 | CM25: 1028 | CN25: 459 | CO25: 186 | CP25: =+SUM(CL25:CO25) -> 2535 | CQ25: 11 | CR25: 18 | CS25: 178 | CT25: 536 | CU25: =+SUM(CQ25:CT25) -> 743 | CV25: 376 | CW25: -217 | CX25: -176 | CY25: -14 | CZ25: =+SUM(CV25:CY25) -> -31 | DA25: 71 | DB25: 251 | DC25: -538 | DD25: -21 | DE25: =+SUM(DA25:DD25) -> -237 | DF25: 23 | DG25: 76 | DH25: 50 | DI25: 232 | DJ25: =+SUM(DF25:DI25) -> 381 | DK25: -107 | DL25: -51 | DM25: -140 | DN25: -99 | DO25: =+SUM(DK25:DN25) -> -397 | DP25: -33 | DQ25: -63
B26: NCI | CL26: 13 | CM26: 19 | CN26: 17 | CO26: 19 | CP26: =+SUM(CL26:CO26) -> 68 | CQ26: 24 | CR26: 20 | CS26: 23 | CT26: 21 | CV26: 23 | CW26: 33 | CX26: 33 | CY26: 29 | DA26: 11 | DB26: 0 | DC26: 2 | DD26: 7 | DF26: 12 | DG26: 0 | DH26: 4 | DI26: 4 | DK26: -6 | DL26: 1 | DM26: 2 | DN26: 0 | DP26: 3 | DQ26: -16
B27: Net income, continuing ops. | C27: =C24+C25 -> -178 | D27: =D24+D25 -> 1120 | E27: =E24+E25 -> 2309 | F27: =F24+F25 -> 2128 | G27: =G24+G25 -> 2826 | H27: =H24+H25 -> 2319 | I27: =I24+I25 -> 718 | J27: =J24+J25 -> 623 | ... L27: =L24+L25 -> 438 | M27: =N27-SUM(J27:L27) -> 173 | N27: =N24+N25 -> 1820 | O27: =O24+O25 -> 514 | P27: =P24+P25 -> 566 | Q27: =Q24+Q25 -> 1013 | R27: =S27-O27-P27-Q27 -> 469 | S27: =S24+S25 -> 2562 | T27: =T24+T25 -> 692 | U27: =U24+U25 -> -160 | V27: =V24+V25 -> 694 | W27: =X27-T27-U27-V27 -> 980 | X27: =X24+X25 -> 2206 | Y27: =Y24+Y25 -> 873 | Z27: =Z24+Z25 -> 1049 | AA27: =AA24+AA25 -> 1109 | AB27: =AC27-Y27-Z27-AA27 -> 1027 | AC27: =AC24+AC25 -> 4058 | AD27: =AD24+AD25 -> 1206 | AE27: =AE24+AE25 -> 851 | AF27: =AF24+AF25 -> 683 | AG27: =AH27-AD27-AE27-AF27 -> -86 | AH27: =AH24+AH25 -> 2654 | AI27: =AI24+AI25 -> 615 | AJ27: =AJ24+AJ25 -> 997 | AK27: =AK24+AK25 -> -1560 | AL27: =AL24+AL25 -> 1283 | AM27: =AM24+AM25 -> 1335 | AN27: =AN24+AN25 -> 519 | AO27: =AO24+AO25 -> 789 | ... CK27: =CK24+CK25 -> -636 | CL27: =CL24+CL25+CL26 -> -628 | CM27: =CM24+CM25+CM26 -> -2376 | CN27: =CN24+CN25+CN26 -> -449 | CO27: =CO24+CO25+CO26 -> -8420 | CP27: =CP24+CP25+CP26 -> -11873 | CQ27: =CQ24+CQ25+CQ26 -> -537 | CR27: =CR24+CR25+CR26 -> 587 | CS27: =CS24+CS25+CS26 -> -109 | CT27: =CT24+CT25+CT26 -> -4143 | CU27: =CU24+CU25 -> -4290 | CV27: =CV24+CV25+CV26 -> -1219 | CW27: =CW24+CW25+CW26 -> 193 | CX27: =CX24+CX25+CX26 -> -3275 | CY27: =CY24+CY25+CY26 -> -634 | CZ27: =CZ24+CZ25 -> -5053 | DA27: =DA24+DA25+DA26 -> -414 | DB27: =DB24+DB25+DB26 -> -149 | DC27: =DC24+DC25+DC26 -> -1636 | DD27: =DD24+DD25+DD26 -> -23 | DE27: =DE24+DE25 -> -2242 | DF27: =DF24+DF25+DF26 -> -343 | DG27: =DG24+DG25+DG26 -> -1439 | DH27: =DH24+DH25+DH26 -> -6170 | DI27: =DI24+DI25+DI26 -> -3857 | DJ27: =DJ24+DJ25 -> -11829 | DK27: =DK24+DK25+DK26 -> -37 | DL27: =DL24+DL25+DL26 -> -611 | DM27: =DM24+DM25+DM26 -> -5337 | DN27: =DN24+DN25+DN26 -> 8220 | DO27: =DO24+DO25 -> 2238 | DP27: =DP24+DP25+DP26 -> -4 | DQ27: =DQ24+DQ25+DQ26 -> -444
B28: Discontinued ops. & non recurring items | C28: 0 | D28: 0 | E28: 0 | F28: 0 | G28: 1 | H28: -1827 | I28: 0 | J28: 0 | K28: =7+14 -> 21 | L28: =-1+19 -> 18 | M28: =N28-SUM(J28:L28) -> 13 | N28: =52 -> 52 | O28: 21 | Q28: -2 | R28: =S28-O28-P28-Q28 -> -9 | S28: =-7+17 -> 10 | W28: =X28-T28-U28-V28 -> 9 | X28: 9 | Y28: 4 | Z28: 1 | AA28: 5 | AB28: =AC28-Y28-Z28-AA28 -> 6 | AC28: 16 | AD28: 5 | AE28: 1 | AF28: 12 | AG28: =AH28-AD28-AE28-AF28 -> 0 | AH28: 18 | AI28: -5 | AJ28: 1 | AK28: -4 | AL28: -15 | AM28: =SUM(AI28:AL28) -> -23 | AN28: 0 | AO28: -2 | AP28: 0 | AQ28: -2 | AR28: =SUM(AN28:AQ28) -> -4 | AS28: -2 | AT28: -1 | AU28: 4 | AV28: =AW28-SUM(AS28:AU28) -> 6 | AW28: 7 | AX28: -1 | AY28: 0 | BB28: =SUM(AX28:BA28) -> -1 | BC28: 0 | BD28: 1 | BE28: -2 | BF28: 0 | BG28: =SUM(BC28:BF28) -> -1 | BH28: 0 | BI28: 0 | BJ28: 0 | BK28: 0 | BL28: =SUM(BH28:BK28) -> 0 | BM28: 0 | BN28: 0 | BO28: 0 | BP28: 0 | BQ28: =SUM(BM28:BP28) -> 0 | BR28: 0 | BS28: 0 | BT28: 0 | BU28: 0 | BV28: =SUM(BR28:BU28) -> 0 | BW28: 0 | BX28: 0 | BY28: 0 | BZ28: 0 | CA28: =SUM(BW28:BZ28) -> 0 | CB28: 0 | CC28: 0 | CD28: 0 | CE28: 0 | CF28: =SUM(CB28:CE28) -> 0 | CG28: 0 | CK28: =SUM(CG28:CJ28) -> 0 | CP28: =SUM(CL28:CO28) -> 0 | CU28: =SUM(CQ28:CT28) -> 0 | CZ28: =SUM(CV28:CY28) -> 0 | DE28: =SUM(DA28:DD28) -> 0 | DI28: -58 | DJ28: =SUM(DF28:DI28) -> -58 | DK28: -86 | DL28: -86 | DM28: -87 | DN28: -86 | DO28: =SUM(DK28:DN28) -> -345 | DP28: -86 | DQ28: -86
B29: Net income reported | C29: =SUM(C27:C28) -> -178 | D29: =SUM(D27:D28) -> 1120 | E29: =SUM(E27:E28) -> 2309 | F29: =SUM(F27:F28) -> 2128 | G29: =SUM(G27:G28) -> 2827 | H29: =SUM(H27:H28) -> 492 | I29: =SUM(I27:I28) -> 718 | J29: =SUM(J27:J28) -> 623 | ... L29: =SUM(L27:L28) -> 456 | M29: =N29-SUM(J29:L29) -> 186 | N29: =SUM(N27:N28) -> 1872 | O29: =SUM(O27:O28) -> 535 | P29: =SUM(P27:P28) -> 566 | Q29: =SUM(Q27:Q28) -> 1011 | R29: =S29-O29-P29-Q29 -> 460 | S29: =SUM(S27:S28) -> 2572 | T29: =SUM(T27:T28) -> 692 | U29: =SUM(U27:U28) -> -160 | V29: =SUM(V27:V28) -> 694 | W29: =X29-T29-U29-V29 -> 989 | X29: =SUM(X27:X28) -> 2215 | Y29: =SUM(Y27:Y28) -> 877 | Z29: =SUM(Z27:Z28) -> 1050 | AA29: =SUM(AA27:AA28) -> 1114 | AB29: =AC29-Y29-Z29-AA29 -> 1033 | AC29: =SUM(AC27:AC28) -> 4074 | AD29: =SUM(AD27:AD28) -> 1211 | AE29: =SUM(AE27:AE28) -> 852 | AF29: =SUM(AF27:AF28) -> 695 | AG29: =AH29-AD29-AE29-AF29 -> -86 | AH29: =SUM(AH27:AH28) -> 2672 | AI29: =SUM(AI27:AI28) -> 610 | AJ29: =SUM(AJ27:AJ28) -> 998 | AK29: =SUM(AK27:AK28) -> -1564 | AL29: =SUM(AL27:AL28) -> 1268 | AM29: =SUM(AM27:AM28) -> 1312 | AN29: =SUM(AN27:AN28) -> 519 | AO29: =SUM(AO27:AO28) -> 787 | ... CE29: =SUM(CE27:CE28) -> 3424 | CF29: =+SUM(CB29:CE29) -> 10460 | CG29: =SUM(CG27:CG28) -> 2149 | CH29: =SUM(CH27:CH28) -> -2942 | CI29: =SUM(CI27:CI28) -> 1167 | CJ29: =SUM(CJ27:CJ28) -> -1010 | CK29: =+SUM(CG29:CJ29) -> -636 | CL29: =SUM(CL27:CL28) -> -628 | CM29: =SUM(CM27:CM28) -> -2376 | CN29: =SUM(CN27:CN28) -> -449 | CO29: =SUM(CO27:CO28) -> -8420 | CP29: =+SUM(CL29:CO29) -> -11873 | CQ29: =SUM(CQ27:CQ28) -> -537 | CR29: =SUM(CR27:CR28) -> 587 | CS29: =SUM(CS27:CS28) -> -109 | CT29: =SUM(CT27:CT28) -> -4143 | CU29: =+SUM(CQ29:CT29) -> -4202 | CV29: =SUM(CV27:CV28) -> -1219 | CW29: =SUM(CW27:CW28) -> 193 | CX29: =SUM(CX27:CX28) -> -3275 | CY29: =SUM(CY27:CY28) -> -634 | CZ29: =+SUM(CV29:CY29) -> -4935 | DA29: =SUM(DA27:DA28) -> -414 | DB29: =SUM(DB27:DB28) -> -149 | DC29: =SUM(DC27:DC28) -> -1636 | DD29: =SUM(DD27:DD28) -> -23 | DE29: =+SUM(DA29:DD29) -> -2222 | DF29: =SUM(DF27:DF28) -> -343 | DG29: =SUM(DG27:DG28) -> -1439 | DH29: =SUM(DH27:DH28) -> -6170 | DI29: =SUM(DI27:DI28) -> -3915 | DJ29: =+SUM(DF29:DI29) -> -11867 | DK29: =SUM(DK27:DK28) -> -123 | DL29: =SUM(DL27:DL28) -> -697 | DM29: =SUM(DM27:DM28) -> -5424 | DN29: =SUM(DN27:DN28) -> 8134 | DO29: =+SUM(DK29:DN29) -> 1890 | DP29: =SUM(DP27:DP28) -> -90 | DQ29: =SUM(DQ27:DQ28) -> -530
B31: Basic EPS, continuing ops. | C31: =C27/C40 -> -0.18348624 | D31: =D27/D40 -> 1.1467185 | E31: =E27/E40 -> 2.5177189 | F31: =F27/F40 -> 2.4758581 | G31: =G27/G40 -> 3.4623867 | H31: =H27/H40 -> 2.902378 | I31: =I27/I40 -> 0.89738783 | J31: =J27/J40 -> 0.77758362 | ... BY31: =BY27/BY40 -> 3.0252382 | CB31: =CB27/CB40 -> 4.1926202 | CC31: =CC27/CC40 -> 3.76931 | CD31: =CD27/CD40 -> 4.1109951 | CG31: =CG27/CG40 -> 3.7854501 | CH31: =CH27/CH40 -> -5.2098459 | CI31: =CI27/CI40 -> 2.0647558 | CL31: =CL27/CL40 -> -1.1097367 | CM31: =CM27/CM40 -> #DIV/0! | CN31: =CN27/CN40 -> -0.79244617 | CO31: =CO27/CO40 -> #DIV/0! | CQ31: =CQ27/CQ40 -> -0.91732149 | CR31: =CR27/CR40 -> 0.99457811 | CS31: =CS27/CS40 -> -0.18505942 | CT31: =CT27/CT40 -> -7.0184652 | CV31: =CV27/CV40 -> -2.0601656 | CW31: =CW27/CW40 -> 0.32360832 | CX31: =CX27/CX40 -> -5.4922019 | CY31: =CY27/CY40 -> -1.0586074 | DA31: =DA27/DA40 -> -0.68713693 | DB31: =DB27/DB40 -> -0.24607762 | DC31: =DC27/DC40 -> -2.6943347 | DD31: =DD27/DD40 -> -0.037947533 | DF31: =DF27/DF40 -> -0.55936073 | DG31: =DG27/DG40 -> -2.3337658 | DH31: =DH27/DH40 -> -9.9709114 | DI31: =DI27/DI40 -> -5.3711182 | DK31: =DK27/DK40 -> -0.049110698 | DL31: =DL27/DL40 -> -0.80756014 | DM31: =DM27/DM40 -> -7.0232925 | DN31: =DN27/DN40 -> 10.703125 | DP31: =DP27/DP40 -> -0.0050761421 | DQ31: =DQ27/DQ40 -> -0.56159879
B32: Discontinued ops. & non recurring items | C32: =C28/C40 -> 0 | D32: =D28/D40 -> 0 | E32: =E28/E40 -> 0 | F32: =F28/F40 -> 0 | G32: =G28/G40 -> 0.0012251899 | H32: =H28/H40 -> -2.2866083 | I32: =I28/I40 -> 0 | J32: =J28/J40 -> 0 | ... BY32: =BY28/BY40 -> 0 | CB32: =CB28/CB40 -> 0 | CC32: =CC28/CC40 -> 0 | CD32: =CD28/CD40 -> 0 | CG32: =CG28/CG40 -> 0 | CH32: =CH28/CH40 -> 0 | CI32: =CI28/CI40 -> 0 | CL32: =CL28/CL40 -> 0 | CM32: =CM28/CM40 -> #DIV/0! | CN32: =CN28/CN40 -> 0 | CO32: =CO28/CO40 -> #DIV/0! | CQ32: =CQ28/CQ40 -> 0 | CR32: =CR28/CR40 -> 0 | CS32: =CS28/CS40 -> 0 | CT32: =CT28/CT40 -> 0 | CV32: =CV28/CV40 -> 0 | CW32: =CW28/CW40 -> 0 | CX32: =CX28/CX40 -> 0 | CY32: =CY28/CY40 -> 0 | DA32: =DA28/DA40 -> 0 | DB32: =DB28/DB40 -> 0 | DC32: =DC28/DC40 -> 0 | DD32: =DD28/DD40 -> 0 | DF32: =DF28/DF40 -> 0 | DG32: =DG28/DG40 -> 0 | DH32: =DH28/DH40 -> 0 | DI32: =DI28/DI40-0.01 -> -0.090768695 | DK32: =DK28/DK40 -> -0.11414919 | DL32: =DL28/DL40 -> -0.1136664 | DM32: =DM28/DM40 -> -0.11448875 | DN32: =DN28/DN40 -> -0.11197917 | DP32: =DP28/DP40 -> -0.10913706 | DQ32: =DQ28/DQ40 -> -0.10877814
B33: Basic EPS, reported | C33: =SUM(C31:C32) -> -0.18348624 | D33: =SUM(D31:D32) -> 1.1467185 | E33: =SUM(E31:E32) -> 2.5177189 | F33: =SUM(F31:F32) -> 2.4758581 | G33: =SUM(G31:G32) -> 3.4636119 | H33: =SUM(H31:H32) -> 0.61576971 | I33: =SUM(I31:I32) -> 0.89738783 | J33: =SUM(J31:J32) -> 0.77758362 | ... BY33: =SUM(BY31:BY32) -> 3.0252382 | CB33: =SUM(CB31:CB32) -> 4.1926202 | CC33: =SUM(CC31:CC32) -> 3.76931 | CD33: =SUM(CD31:CD32) -> 4.1109951 | CG33: =SUM(CG31:CG32) -> 3.7854501 | CH33: =SUM(CH31:CH32) -> -5.2098459 | CI33: =SUM(CI31:CI32) -> 2.0647558 | CL33: =SUM(CL31:CL32) -> -1.1097367 | CM33: =SUM(CM31:CM32) -> #DIV/0! | CN33: =SUM(CN31:CN32) -> -0.79244617 | CO33: =SUM(CO31:CO32) -> #DIV/0! | CQ33: =SUM(CQ31:CQ32) -> -0.91732149 | CR33: =SUM(CR31:CR32) -> 0.99457811 | CS33: =SUM(CS31:CS32) -> -0.18505942 | CT33: =SUM(CT31:CT32) -> -7.0184652 | CV33: =SUM(CV31:CV32) -> -2.0601656 | CW33: =SUM(CW31:CW32) -> 0.32360832 | CX33: =SUM(CX31:CX32) -> -5.4922019 | CY33: =SUM(CY31:CY32) -> -1.0586074 | DA33: =SUM(DA31:DA32) -> -0.68713693 | DB33: =SUM(DB31:DB32) -> -0.24607762 | DC33: =SUM(DC31:DC32) -> -2.6943347 | DD33: =SUM(DD31:DD32) -> -0.037947533 | DF33: =SUM(DF31:DF32) -> -0.55936073 | DG33: =SUM(DG31:DG32) -> -2.3337658 | DH33: =SUM(DH31:DH32) -> -9.9709114 | DI33: =SUM(DI31:DI32) -> -5.4618869 | DK33: =SUM(DK31:DK32) -> -0.16325989 | DL33: =SUM(DL31:DL32) -> -0.92122654 | DM33: =SUM(DM31:DM32) -> -7.1377813 | DN33: =SUM(DN31:DN32) -> 10.591146 | DP33: =SUM(DP31:DP32) -> -0.1142132 | DQ33: =SUM(DQ31:DQ32) -> -0.67037693
B35: Diluted EPS | C35: =C27/C41 -> -0.18348624 | D35: =D27/D41 -> 1.1583411 | E35: =E27/E41 -> 2.4937898 | F35: =F27/F41 -> 2.4423276 | G35: =G27/G41 -> 3.4076932 | H35: =H27/H41 -> 2.8686294 | I35: =I27/I41 -> 0.88762517 | J35: =J27/J41 -> 0.76828216 | ... CY35: =CY27/CY41 -> -1.0586074 | DA35: =DA27/DA41 -> -0.68713693 | DB35: =DB27/DB41 -> -0.24607762 | DC35: =DC27/DC41 -> -2.6943347 | DD35: =DD27/DD41 -> -0.037947533 | DF35: =DF27/DF41 -> -0.55936073 | DG35: =DG27/DG41 -> -2.3337658 | DH35: =DH27/DH41 -> -9.9709114 | DI35: =DI27/DI41 -> -5.3711182 | DK35: =DK27/DK41 -> -0.049110698 | DL35: =DL27/DL41 -> -0.80756014 | DM35: =DM27/DM41 -> -7.0232925 | DN35: =DN27/DN41 -> 10.339623 | DP35: =DP27/DP41 -> -0.0050761421 | DQ35: =DQ27/DQ41 -> -0.56159879
B36: Discontinued ops. & non recurring items | C36: =C28/C41 -> 0 | D36: =D28/D41 -> 0 | E36: =E28/E41 -> 0 | F36: =F28/F41 -> 0 | G36: =G28/G41 -> 0.0012058362 | H36: =H28/H41 -> -2.2600198 | I36: =I28/I41 -> 0 | J36: =J28/J41 -> 0 | ... CY36: =CY28/CY41 -> 0 | DA36: =DA28/DA41 -> 0 | DB36: =DB28/DB41 -> 0 | DC36: =DC28/DC41 -> 0 | DD36: =DD28/DD41 -> 0 | DF36: =DF28/DF41 -> 0 | DG36: =DG28/DG41 -> 0 | DH36: =DH28/DH41 -> 0 | DI36: =DI28/DI41-0.01 -> -0.090768695 | DK36: =DK28/DK41 -> -0.11414919 | DL36: =DL28/DL41 -> -0.1136664 | DM36: =DM28/DM41 -> -0.11448875 | DN36: =DN28/DN41 -> -0.1081761 | DP36: =DP28/DP41 -> -0.10913706 | DQ36: =DQ28/DQ41 -> -0.10877814
B37: Diluted EPS, reported | C37: =SUM(C35:C36) -> -0.18348624 | D37: =SUM(D35:D36) -> 1.1583411 | E37: =SUM(E35:E36) -> 2.4937898 | F37: =SUM(F35:F36) -> 2.4423276 | G37: =SUM(G35:G36) -> 3.4088991 | H37: =SUM(H35:H36) -> 0.6086096 | I37: =SUM(I35:I36) -> 0.88762517 | J37: =SUM(J35:J36) -> 0.76828216 | ... CY37: =SUM(CY35:CY36) -> -1.0586074 | DA37: =SUM(DA35:DA36) -> -0.68713693 | DB37: =SUM(DB35:DB36) -> -0.24607762 | DC37: =SUM(DC35:DC36) -> -2.6943347 | DD37: =SUM(DD35:DD36) -> -0.037947533 | DF37: =SUM(DF35:DF36) -> -0.55936073 | DG37: =SUM(DG35:DG36) -> -2.3337658 | DH37: =SUM(DH35:DH36) -> -9.9709114 | DI37: =SUM(DI35:DI36) -> -5.4618869 | DK37: =SUM(DK35:DK36) -> -0.16325989 | DL37: =SUM(DL35:DL36) -> -0.92122654 | DM37: =SUM(DM35:DM36) -> -7.1377813 | DN37: =SUM(DN35:DN36) -> 10.231447 | DP37: =SUM(DP35:DP36) -> -0.1142132 | DQ37: =SUM(DQ35:DQ36) -> -0.67037693
B39: Common shares outstanding
B40: Basic | C40: 970.1 | D40: 976.7 | E40: 917.1 | F40: 859.5 | G40: 816.2 | H40: 799 | I40: 800.1 | J40: 801.2 | K40: 807.8 | L40: 808.2 | M40: =N40*4-J40-K40-L40 -> 810.8 | N40: 807 | O40: 798.4 | P40: 793.3 | Q40: 787.3 | R40: =S40*4-O40-P40-Q40 -> 775 | S40: 788.5 | T40: 770.5 | U40: 761.3 | V40: 773 | W40: =X40*4-T40-U40-V40 -> 779.2 | X40: 771 | Y40: 765.4 | Z40: 763.5 | AA40: 759.3 | AB40: =AC40*4-Y40-Z40-AA40 -> 749 | AC40: 759.3 | AD40: 738 | AE40: 725.5 | AF40: 717.5 | AG40: =AH40*4-AD40-AE40-AF40 -> 709.4 | AH40: 722.6 | AI40: 705.3 | AJ40: 705.2 | AK40: 701.3 | AL40: 716.661 | AM40: 709.6 | AN40: 734.8 | AO40: 737.2 | AP40: 739.1 | AQ40: 742.67516 | AR40: 738.1 | AS40: 742.9 | AT40: 745.5 | AU40: 748 | AV40: 749.83784 | AW40: 746.6 | AX40: 752.5 | AY40: 755.9 | AZ40: 756.6 | BA40: 757.8 | BB40: 755.7 | BC40: 762.8 | BD40: 763.3 | BE40: 759.4 | BF40: =BF29/1.63 -> 756.68712 | BG40: 760.8 | BH40: 745 | BI40: 731.1 | BJ40: 722.8 | BK40: 711.5 | BL40: 727.6 | BM40: 705.7 | BN40: 691.2 | BO40: 681.3 | BP40: =BO40-BO41+BP41 -> 673.5 | BQ40: 688 | BR40: 659.6 | BS40: 636.3 | BT40: 625.5 | BU40: =BT40-BT41+BU41 -> 623.1 | BV40: 636.5 | BW40: 614.4 | BX40: 602.5 | BY40: 598.3 | CB40: 590.8 | CC40: 582.6 | CD40: 574.8 | CG40: 567.7 | CH40: 564.7 | CI40: 565.2 | CL40: 565.9 | CN40: 566.6 | CP40: 568.6 | CQ40: 585.4 | CR40: 590.2 | CS40: 589 | CT40: 590.3 | CU40: 587.6 | CV40: 591.7 | CW40: 596.4 | CX40: 596.3 | CY40: 598.9 | DA40: 602.5 | DB40: 605.5 | DC40: 607.2 | DD40: 606.1 | DF40: 613.2 | DG40: 616.6 | DH40: 618.8 | DI40: 718.1 | DK40: 753.4 | DL40: 756.6 | DM40: 759.9 | DN40: 768 | DP40: 788 | DQ40: 790.6
B41: Diluted | C41: 970.1 | D41: 966.9 | E41: 925.9 | F41: 871.3 | G41: 829.3 | H41: 808.4 | I41: 808.9 | J41: 810.9 | K41: 812.3 | L41: 814.8 | M41: =N41*4-J41-K41-L41 -> 814 | N41: 813 | O41: 806.8 | P41: 807.4 | Q41: 802.8 | R41: =S41*4-O41-P41-Q41 -> 794.6 | S41: 802.9 | T41: 791.8 | U41: 761.3 | V41: 784 | W41: =X41*4-T41-U41-V41 -> 813.3 | X41: 787.6 | Y41: 777.4 | Z41: 777 | AA41: 773.4 | AB41: =AC41*4-Y41-Z41-AA41 -> 762.2 | AC41: 772.5 | AD41: 747.4 | AE41: 732.8 | AF41: 721.9 | AG41: =AH41*4-AD41-AE41-AF41 -> 713.9 | AH41: 729 | AI41: 707.4 | AJ41: 707.8 | AK41: 701.3 | AL41: 723.9 | AM41: 713.4 | AN41: 740.1 | AO41: 742.9 | AP41: 744.6 | AQ41: 747 | AR41: 744.3 | AS41: 749 | AT41: 752.6 | AU41: 753.9 | AV41: 757.1 | AW41: 753.1 | AX41: 759.6 | AY41: 762 | AZ41: 765.2 | BA41: 766.3 | BB41: 763.8 | BC41: 768.7 | BD41: 771.8 | BE41: 769.1 | BF41: 768.4 | BG41: 769.5 | BH41: 754.1 | BI41: 740.1 | BJ41: 731.9 | BK41: 724.8 | BL41: 738 | BM41: 714.2 | BN41: 698.9 | BO41: 689 | BP41: 681.2 | BQ41: 696.1 | BR41: 665.8 | BS41: 636.3 | BT41: 632.7 | BU41: 630.3 | BV41: 643.8 | BW41: 621.2 | BX41: 609.6 | BY41: 606.3 | BZ41: 605.1 | CA41: 610.7 | CB41: 597.2 | CC41: 588.7 | CD41: 580.8 | CE41: 577.5 | CF41: 586.15 | CG41: 572.4 | CH41: 565.3 | CI41: 569.2 | CJ41: 565.4 | CK41: 565.4 | CL41: 565.9 | CM41: 566.4 | CN41: 566.6 | CO41: 575.4 | CP41: 568.6 | CQ41: 585.4 | CR41: 590.2 | CS41: 589 | CT41: 590.3 | CU41: 587.6 | CV41: 591.7 | CW41: 596.4 | CX41: 596.3 | CY41: 598.9 | DA41: 602.5 | DB41: 605.5 | DC41: 607.2 | DD41: 606.1 | DF41: 613.2 | DG41: 616.6 | DH41: 618.8 | DI41: 718.1 | DK41: 753.4 | DL41: 756.6 | DM41: 759.9 | DN41: 795 | DP41: 788 | DQ41: 790.6
C43: =IF(ROUND(C35,2)=ROUND((C27/C41),2),"","check") | D43: =IF(ROUND(D35,2)=ROUND((D27/D41),2),"","check") | E43: =IF(ROUND(E35,2)=ROUND((E27/E41),2),"","check") | F43: =IF(ROUND(F35,2)=ROUND((F27/F41),2),"","check") | G43: =IF(ROUND(G35,2)=ROUND((G27/G41),2),"","check") | H43: =IF(ROUND(H35,2)=ROUND((H27/H41),2),"","check") | I43: =IF(ROUND(I35,2)=ROUND((I27/I41),2),"","check") | J43: =IF(ROUND(J35,2)=ROUND((J27/J41),2),"","check") | ... AK43: =IF(ROUND(AK35,2)=ROUND((AK27/AK41),2),"","check")
B45: Balance Sheet
B46: Assets
B47: Cash and cash equivalents | C47: 4420 | D47: 2183 | E47: 3354 | F47: 1010 | G47: 633 | H47: 2333 | I47: 4633 | J47: 3950 | K47: 6184 | L47: 4312 | M47: =N47 -> 3204 | N47: 3204 | O47: 3330 | P47: 4961 | Q47: 4547 | R47: =S47 -> 5412 | S47: 5412 | T47: 6781 | U47: 7567 | V47: 5198 | W47: =X47 -> 6118 | X47: 6118 | Y47: 4836 | Z47: 7156 | AA47: 8948 | AB47: =AC47 -> 7042 | AC47: 7042 | AD47: 7707 | AE47: 5619 | AF47: 4186 | AG47: =AH47 -> 3268 | AH47: 3268 | AI47: 4237 | AJ47: 4599 | AK47: 6095 | AL47: 9215 | AM47: =AL47 -> 9215 | AN47: 4517 | AO47: 4468 | AP47: 2864 | AQ47: 5359 | AR47: =AQ47 -> 5359 | AS47: 5670 | AT47: 5050 | AU47: 5954 | AV47: 10049 | AW47: =AV47 -> 10049 | AX47: 6718 | AY47: 6305 | AZ47: 6582 | BA47: 10341 | BB47: =BA47 -> 10341 | BC47: 8335 | BD47: 8694 | BE47: 10041 | BF47: 9088 | BG47: =BF47 -> 9088 | BH47: 6942 | BI47: 7533 | BJ47: 6655 | BK47: 11733 | BL47: =BK47 -> 11733 | BM47: 8655 | BN47: 9157 | BO47: 9383 | BP47: 11302 | BQ47: =BP47 -> 11302 | BR47: 7886 | BS47: 8605 | BT47: 8986 | BU47: 8801 | BV47: =BU47 -> 8801 | BW47: 8190 | BX47: 8737 | BY47: 8569 | BZ47: 8813 | CA47: =BZ47 -> 8813 | CB47: 9235 | CC47: 8121 | CD47: 8034 | CE47: 7637 | CF47: =CE47 -> 7637 | CG47: 6836 | CH47: 9167 | CI47: 9763 | CJ47: 9485 | CK47: =CJ47 -> 9485 | CL47: 15039 | CM47: 19992 | CN47: 10564 | CO47: 7752 | CP47: =CO47 -> 7752 | CQ47: 7059 | CR47: 8271 | CS47: 9764 | CT47: 8052 | CU47: =CT47 -> 8052 | CV47: 7409 | CW47: 10090 | CX47: 13494 | CY47: 14614 | CZ47: =CY47 -> 14614 | DA47: 10812 | DB47: 7254 | DC47: 6811 | DD47: 12691 | DE47: =DD47 -> 12691 | DF47: 6914 | DG47: 10894 | DH47: 9961 | DI47: 13801 | DJ47: =DI47 -> 13801 | DK47: 10142 | DL47: 7087 | DM47: 6173 | DN47: 10921 | DO47: =DN47 -> 10921 | DP47: 9441 | DQ47: 7239
B48: Short-term investments | C48: 729 | D48: 279 | E48: 100 | F48: 0 | G48: 0 | H48: 0 | I48: 0 | J48: 0 | K48: 0 | L48: 96 | M48: =N48 -> 319 | N48: 319 | O48: 167 | P48: 207 | Q48: 527 | R48: =S48 -> 554 | S48: 554 | T48: 576 | U48: 567 | V48: 423 | W48: =X48 -> 268 | X48: 268 | Y48: 441 | Z48: 475 | AA48: 516 | AB48: =AC48 -> 2266 | AC48: 2266 | AD48: 1881 | AE48: 1752 | AF48: 591 | AG48: =AH48 -> 11 | AH48: 11 | AI48: 213 | AJ48: 171 | AK48: 351 | AL48: 2008 | AM48: =AL48 -> 2008 | AN48: 5845 | AO48: 5558 | AP48: 7102 | AQ48: 5158 | AR48: =AQ48 -> 5158 | AS48: 2102 | AT48: 3752 | AU48: 3279 | AV48: 1223 | AW48: =AV48 -> 1223 | AX48: 3798 | AY48: 4002 | AZ48: 4590 | BA48: 3217 | BB48: =BA48 -> 3217 | BC48: 3518 | BD48: 5631 | BE48: 5870 | BF48: 6170 | BG48: =BF48 -> 6170 | BH48: 5282 | BI48: 3797 | BJ48: 3422 | BK48: 1359 | BL48: =BK48 -> 1359 | BM48: 976 | BN48: 468 | BO48: 474 | BP48: 750 | BQ48: =BP48 -> 750 | BR48: 466 | BS48: 660 | BT48: 682 | BU48: 1228 | BV48: =BU48 -> 1228 | BW48: 1015 | BX48: 1589 | BY48: 1463 | BZ48: 1179 | CA48: =BZ48 -> 1179 | CB48: 656 | CC48: 1649 | CD48: 1956 | CE48: 927 | CF48: =CE48 -> 927 | CG48: 893 | CH48: 439 | CI48: 1150 | CJ48: 545 | CK48: =CJ48 -> 545 | CL48: 488 | CM48: 12438 | CN48: 16552 | CO48: 17838 | CP48: =CO48 -> 17838 | CQ48: 14861 | CR48: 13071 | CS48: 10231 | CT48: 8192 | CU48: =CT48 -> 8192 | CV48: 4873 | CW48: 1358 | CX48: 763 | CY48: 2606 | CZ48: =CY48 -> 2606 | DA48: 3955 | DB48: 6508 | DC48: 6561 | DD48: 3274 | DE48: =DD48 -> 3274 | DF48: 615 | DG48: 1727 | DH48: 509 | DI48: 12481 | DJ48: =DI48 -> 12481 | DK48: 13532 | DL48: 15880 | DM48: 16811 | DN48: 18479 | DO48: =DN48 -> 18479 | DP48: 11464 | DQ48: 12783
B49: Accounts receivable, net | C49: 3121 | D49: 3288 | E49: 3453 | F49: 4928 | G49: 5156 | H49: 5007 | I49: 4515 | J49: 4844 | K49: 4598 | L49: 5204 | M49: =N49 -> 4653 | N49: 4653 | O49: 5316 | P49: 5066 | Q49: 4997 | R49: =S49 -> 5246 | S49: 5246 | T49: 5019 | U49: 4577 | V49: 5256 | W49: =X49 -> 5285 | X49: 5285 | Y49: 5505 | Z49: 6038 | AA49: 5634 | AB49: =AC49 -> 5740 | AC49: 5740 | AD49: 5784 | AE49: 5809 | AF49: 5814 | AG49: =AH49 -> 5602 | AH49: 5602 | AI49: 6238 | AJ49: 6588 | AK49: 6718 | AL49: 5785 | AM49: =AL49 -> 5785 | AN49: 6359 | AO49: 6565 | AP49: 6445 | AQ49: 5422 | AR49: =AQ49 -> 5422 | AS49: 6036 | AT49: 6162 | AU49: 6296 | AV49: 5793 | AW49: =AV49 -> 5793 | AX49: 6475 | AY49: 5894 | AZ49: 5437 | BA49: 5608 | BB49: =BA49 -> 5608 | BC49: 6351 | BD49: 6406 | BE49: 6652 | BF49: 6546 | BG49: =BF49 -> 6546 | BH49: 7341 | BI49: 7694 | BJ49: 7799 | BK49: 7729 | BL49: =BK49 -> 7729 | BM49: 8087 | BN49: 7927 | BO49: 8854 | BP49: 8713 | BQ49: =BP49 -> 8713 | BR49: 9711 | BS49: 9809 | BT49: 9524 | BU49: 8832 | BV49: =BU49 -> 8832 | BW49: 9335 | BX49: 9503 | BY49: 10644 | BZ49: 10516 | CA49: =BZ49 -> 10516 | CB49: 2802 | CC49: 2823 | CD49: 2893 | CE49: 3879 | CF49: =CE49 -> 3879 | CG49: 3669 | CH49: 3291 | CI49: 3564 | CJ49: 3266 | CK49: =CJ49 -> 3266 | CL49: 3211 | CM49: 2793 | CN49: 2762 | CO49: 1955 | CP49: =CO49 -> 1955 | CQ49: 2356 | CR49: 2490 | CS49: 2247 | CT49: 2641 | CU49: =CT49 -> 2641 | CV49: 2407 | CW49: 2996 | CX49: 2673 | CY49: 2517 | CZ49: =CY49 -> 2517 | DA49: 2862 | DB49: 2945 | DC49: 3032 | DD49: 2649 | DE49: =DD49 -> 2649 | DF49: 2959 | DG49: 3155 | DH49: 2894 | DI49: 2631 | DJ49: =DI49 -> 2631 | DK49: 3204 | DL49: 3190 | DM49: 3314 | DN49: 2921 | DO49: =DN49 -> 2921 | DP49: 3485 | DQ49: 3515
B50: Unbilled receivables | CB50: 9822 | CC50: 9868 | CD50: 9936 | CE50: 10025 | CF50: =+CE50 -> 10025 | CG50: 10208 | CH50: 10247 | CI50: 11078 | CJ50: 9043 | CK50: =+CJ50 -> 9043 | CL50: 9365 | CM50: 8570 | CN50: 8860 | CO50: 7995 | CP50: =+CO50 -> 7995 | CQ50: 8785 | CR50: 9203 | CS50: 10009 | CT50: 8620 | CU50: =+CT50 -> 8620 | CV50: 8991 | CW50: 9394 | CX50: 9316 | CY50: 8634 | CZ50: =+CY50 -> 8634 | DA50: 9689 | DB50: 9357 | DC50: 9184 | DD50: 8317 | DE50: =+DD50 -> 8317 | DF50: 9673 | DG50: 9660 | DH50: 9356 | DI50: 8363 | DJ50: =+DI50 -> 8363 | DK50: 9031 | DL50: 9261 | DM50: 9032 | DN50: 9158 | DO50: =+DN50 -> 9158 | DP50: 9793 | DQ50: 9660
B51: Current portion of customer financing, net | C51: 261 | D51: 781 | E51: 799 | F51: 995 | G51: 1053 | H51: 1289 | I51: 857 | J51: 847 | K51: 732 | L51: 688 | M51: =N51 -> 616 | N51: 616 | O51: 496 | P51: 464 | Q51: 454 | R51: =S51 -> 367 | S51: 367 | T51: 354 | U51: 353 | V51: 364 | W51: =X51 -> 370 | X51: 370 | Y51: 460 | Z51: 450 | AA51: 396 | AB51: =AC51 -> 328 | AC51: 328 | AD51: 226 | AE51: 198 | AF51: 193 | AG51: =AH51 -> 425 | AH51: 425 | AI51: 353 | AJ51: 463 | AK51: 341 | AL51: 368 | AM51: =AL51 -> 368 | AN51: 274 | AO51: 316 | AP51: 285 | AQ51: 285 | AR51: =AQ51 -> 285 | AS51: 252 | AT51: 260 | AU51: 294 | AV51: 476 | AW51: =AV51 -> 476 | AX51: 372 | AY51: 344 | AZ51: 318 | BA51: 364 | BB51: =BA51 -> 364 | BC51: 460 | BD51: 320 | BE51: 316 | BF51: 344 | BG51: =BF51 -> 344 | BH51: 256 | BI51: 237 | BJ51: 257 | BK51: 190 | BL51: =BK51 -> 190 | BM51: 184 | BN51: 209 | BO51: 227 | BP51: 212 | BQ51: =BP51 -> 212 | BR51: 258 | BS51: 251 | BT51: 365 | BU51: 428 | BV51: =BU51 -> 428 | BW51: 580 | BX51: 549 | BY51: 435 | BZ51: 309 | CA51: =BZ51 -> 309 | CB51: 244 | CC51: 294 | CD51: 431 | CE51: 460 | CF51: =CE51 -> 460 | CG51: 340 | CH51: 171 | CI51: 166 | CJ51: 162 | CK51: =CJ51 -> 162 | CL51: 149 | CM51: 115 | CN51: 100 | CO51: 101 | CP51: =CO51 -> 101 | CQ51: 93 | CR51: 74 | CS51: 76 | CT51: 117 | CU51: =CT51 -> 117 | CV51: 157 | CW51: 159 | CX51: 155 | CY51: 154 | CZ51: =CY51 -> 154 | DA51: 133 | DB51: 85 | DC51: 88 | DD51: 99 | DE51: =DD51 -> 99 | DF51: 57 | DG51: 60 | DH51: 457 | DI51: 207 | DJ51: =DI51 -> 207 | DK51: 202 | DL51: 16 | DM51: 0 | DN51: 0 | DO51: =DN51 -> 0 | DP51: 0 | DQ51: 0
B52: Deferred income taxes | C52: 1765 | D52: 1495 | E52: 1467 | F52: 2137 | G52: 2444 | H52: 2042 | I52: 1716 | J52: 1716 | K52: 1729 | L52: 1670 | M52: =N52 -> 1991 | N52: 1991 | O52: 1988 | P52: 2037 | Q52: 1757 | R52: =S52 -> 2449 | S52: 2449 | T52: 2406 | U52: 2545 | V52: 2962 | W52: =X52 -> 2837 | X52: 2837 | Y52: 2868 | Z52: 2924 | AA52: 2940 | AB52: =AC52 -> 2341 | AC52: 2341 | AD52: 2447 | AE52: 2414 | AF52: 2408 | AG52: =AH52 -> 1046 | AH52: 1046 | AI52: 1114 | AJ52: 1099 | AK52: 741 | AL52: 966 | AM52: =AL52 -> 966 | AN52: 1030 | AO52: 1052 | AP52: 1066 | AQ52: 31 | AR52: =AQ52 -> 31 | AS52: 37 | AT52: 35 | AU52: 31 | AV52: 29 | AW52: =AV52 -> 29 | AX52: 30 | AY52: 30 | AZ52: 34 | BA52: 28 | BB52: =BA52 -> 28 | BC52: 29 | BD52: 25 | BE52: 43 | BF52: 14 | BG52: =BF52 -> 14 | BH52: 15 | BI52: 15 | BJ52: 27 | BK52: 18 | BL52: =BK52 -> 18 | BM52: 17 | BN52: 17 | BO52: 14 | BQ52: =BP52 -> 0 | BR52: 0 | BS52: 0 | BT52: 0 | BU52: 0 | BV52: =BU52 -> 0 | BW52: 0 | CA52: =BZ52 -> 0
B53: Inventories, net of advances and progress billings | C53: 8967 | D53: 8349 | E53: 6539 | F53: 6794 | G53: 6920 | H53: 6184 | I53: =5338 -> 5338 | J53: 5324 | K53: 4255 | L53: 4280 | M53: =N53 -> 4247 | N53: 4247 | O53: 6079 | P53: 5508 | Q53: 6877 | R53: =S53 -> 7940 | S53: 7940 | T53: 7627 | U53: 7562 | V53: 8173 | W53: =X53 -> 8105 | X53: 8105 | Y53: 8400 | Z53: 8480 | AA53: 8194 | AB53: =AC53 -> 9563 | AC53: 9563 | AD53: 10156 | AE53: 10145 | AF53: 11149 | AG53: =AH53 -> 15612 | AH53: 15612 | AI53: 15649 | AJ53: 17200 | AK53: 15981 | AL53: 16933 | AM53: =AL53 -> 16933 | AN53: 18773 | AO53: 20368 | AP53: 21692 | AQ53: 24317 | AR53: =AQ53 -> 24317 | AS53: 26912 | AT53: 29094 | AU53: 30493 | AV53: 32240 | AW53: =AV53 -> 32240 | AX53: 32738 | AY53: 35033 | AZ53: 36817 | BA53: 37751 | BB53: =BA53 -> 37751 | BC53: 40797 | BD53: 40234 | BE53: 41240 | BF53: 42912 | BG53: =BF53 -> 42912 | BH53: 44941 | BI53: 46251 | BJ53: 47058 | BK53: 46756 | BL53: =BK53 -> 46756 | BM53: 48502 | BN53: 49028 | BO53: 48624 | BP53: 47257 | BQ53: =BP53 -> 47257 | BR53: 47266 | BS53: 44182 | BT53: 42680 | BU53: 43199 | BV53: =BU53 -> 43199 | BW53: 43247 | BX53: 42453 | BY53: 43031 | BZ53: 44344 | CA53: =BZ53 -> 44344 | CB53: 61303 | CC53: 61250 | CD53: 62038 | CE53: 62567 | CF53: =CE53 -> 62567 | CG53: 65369 | CH53: 68492 | CI53: 73279 | CJ53: 76622 | CK53: =CJ53 -> 76622 | CL53: 80020 | CM53: 83745 | CN53: 86961 | CO53: 81715 | CP53: =CO53 -> 81715 | CQ53: 82668 | CR53: 81799 | CS53: 81897 | CT53: 78823 | CU53: =CT53 -> 78823 | CV53: 79819 | CW53: 79917 | CX53: 79777 | CY53: 78151 | CZ53: =CY53 -> 78151 | DA53: 78503 | DB53: 78322 | DC53: 78972 | DD53: 79741 | DE53: =DD53 -> 79741 | DF53: 83471 | DG53: 85661 | DH53: 83341 | DI53: 87550 | DJ53: =DI53 -> 87550 | DK53: 89077 | DL53: 87853 | DM53: 82425 | DN53: 84679 | DO53: =DN53 -> 84679 | DP53: 87225 | DQ53: 88388
B54: Other current assets | C54: 0 | D54: 0 | E54: 0 | F54: 0 | G54: 0 | H54: 0 | I54: =199 -> 199 | J54: 0 | K54: 571 | L54: 234 | M54: =N54 -> 70 | N54: 70 | O54: 69 | Q54: 0 | R54: =S54 -> 0 | S54: 0 | T54: 0 | U54: 0 | V54: 0 | W54: =X54 -> 0 | X54: 0 | Y54: 0 | Z54: 0 | AA54: 0 | AB54: =AC54 -> 0 | AC54: 0 | AD54: 0 | AE54: 0 | AF54: 0 | AG54: =AH54 -> 0 | AH54: 0 | AI54: 0 | AJ54: 0 | AK54: 0 | AL54: 0 | AM54: =AL54 -> 0 | AN54: 0 | AO54: 0 | AP54: 0 | AQ54: 0 | AR54: =AQ54 -> 0 | AS54: 0 | AT54: 0 | AU54: 0 | AV54: 0 | AW54: =AV54 -> 0 | AX54: 0 | AY54: 0 | AZ54: 0 | BA54: 0 | BB54: =BA54 -> 0 | BC54: 0 | BD54: 0 | BE54: 0 | BF54: 0 | BG54: =BF54 -> 0 | CB54: 2481 | CC54: 2396 | CD54: 2398 | CE54: 2335 | CF54: =+CE54 -> 2335 | CG54: 2194 | CH54: 3304 | CI54: 2656 | CJ54: 3106 | CK54: =+CJ54 -> 3106 | CL54: 2739 | CM54: 2624 | CN54: 5213 | CO54: 4286 | CP54: =+CO54 -> 4286 | CQ54: 4123 | CR54: 4187 | CS54: 2664 | CT54: 2221 | CU54: =+CT54 -> 2221 | CV54: 2356 | CW54: 2086 | CX54: 3073 | CY54: 2847 | CZ54: =+CY54 -> 2847 | DA54: 2857 | DB54: 2941 | DC54: 2287 | DD54: 2504 | DE54: =+DD54 -> 2504 | DF54: 2843 | DG54: 3282 | DH54: 2918 | DI54: 2965 | DJ54: =+DI54 -> 2965 | DK54: 2474 | DL54: =2563+1451 -> 4014 | DM54: =2904+1473 -> 4377 | DN54: 2301 | DO54: =+DN54 -> 2301 | DP54: 2733 | DQ54: 3045
B55: Total current assets | C55: =SUM(C47:C54) -> 19263 | D55: =SUM(D47:D54) -> 16375 | E55: =SUM(E47:E54) -> 15712 | F55: =SUM(F47:F54) -> 15864 | G55: =SUM(G47:G54) -> 16206 | H55: =SUM(H47:H54) -> 16855 | I55: =SUM(I47:I54) -> 17258 | J55: =SUM(J47:J54) -> 16681 | ... L55: =SUM(L47:L54) -> 16484 | M55: =N55 -> 15100 | N55: =SUM(N47:N54) -> 15100 | O55: =SUM(O47:O54) -> 17445 | P55: =SUM(P47:P54) -> 18243 | Q55: =SUM(Q47:Q54) -> 19159 | R55: =S55 -> 21968 | S55: =SUM(S47:S54) -> 21968 | T55: =SUM(T47:T54) -> 22763 | U55: =SUM(U47:U54) -> 23171 | V55: =SUM(V47:V54) -> 22376 | W55: =X55 -> 22983 | X55: =SUM(X47:X54) -> 22983 | Y55: =SUM(Y47:Y54) -> 22510 | Z55: =SUM(Z47:Z54) -> 25523 | AA55: =SUM(AA47:AA54) -> 26628 | AB55: =AC55 -> 27280 | AC55: =SUM(AC47:AC54) -> 27280 | AD55: =SUM(AD47:AD54) -> 28201 | AE55: =SUM(AE47:AE54) -> 25937 | AF55: =SUM(AF47:AF54) -> 24341 | AG55: =AH55 -> 25964 | AH55: =SUM(AH47:AH54) -> 25964 | AI55: =SUM(AI47:AI54) -> 27804 | AJ55: =SUM(AJ47:AJ54) -> 30120 | AK55: =SUM(AK47:AK54) -> 30227 | AL55: =SUM(AL47:AL54) -> 35275 | AM55: =SUM(AM47:AM54) -> 35275 | AN55: =SUM(AN47:AN54) -> 36798 | AO55: =SUM(AO47:AO54) -> 38327 | ... DQ55: =SUM(DQ47:DQ54) -> 124630
B56: Customer financing, net | C56: 4339 | D56: 4930 | E56: 5205 | F56: 5964 | G56: 9345 | H56: 10922 | I56: 12094 | J56: 12588 | K56: 10823 | L56: 10710 | M56: =N56 -> 10385 | N56: 10385 | O56: 10338 | P56: 9894 | Q56: 9757 | R56: =S56 -> 9639 | S56: 9639 | T56: 9607 | U56: 9055 | V56: 8791 | W56: =X56 -> 8520 | X56: 8520 | Y56: 8255 | Z56: 7227 | AA56: 6925 | AB56: =AC56 -> 6777 | AC56: 6777 | AD56: 6699 | AE56: 6370 | AF56: 5989 | AG56: =AH56 -> 5857 | AH56: 5857 | AI56: 5854 | AJ56: 5969 | AK56: 5923 | AL56: 5466 | AM56: =AL56 -> 5466 | AN56: 5273 | AO56: 5084 | AP56: 4688 | AQ56: 4395 | AR56: =AQ56 -> 4395 | AS56: 4320 | AT56: 4217 | AU56: 4313 | AV56: 4296 | AW56: =AV56 -> 4296 | AX56: 4139 | AY56: 4068 | AZ56: 4028 | BA56: 4056 | BB56: =BA56 -> 4056 | BC56: 3910 | BD56: 3991 | BE56: 3903 | BF56: 3627 | BG56: =BF56 -> 3627 | BH56: 3280 | BI56: 3180 | BJ56: 3347 | BK56: 3371 | BL56: =BK56 -> 3371 | BM56: 3301 | BN56: 3175 | BO56: 3231 | BP56: 3358 | BQ56: =BP56 -> 3358 | BR56: 2980 | BS56: 2909 | BT56: 3401 | BU56: 3773 | BV56: =BU56 -> 3773 | BW56: 3527 | BX56: 3398 | BY56: 3039 | BZ56: 2740 | CA56: =BZ56 -> 2740 | CB56: 2753 | CC56: 2817 | CD56: 2785 | CE56: 2418 | CF56: =CE56 -> 2418 | CG56: 2236 | CH56: 2139 | CI56: 2077 | CJ56: 2136 | CK56: =CJ56 -> 2136 | CL56: 2116 | CM56: 2054 | CN56: 2010 | CO56: 1936 | CP56: =CO56 -> 1936 | CQ56: 1895 | CR56: 1865 | CS56: 1795 | CT56: 1695 | CU56: =CT56 -> 1695 | CV56: 1580 | CW56: 1542 | CX56: 1513 | CY56: 1450 | CZ56: =CY56 -> 1450 | DA56: 1372 | DB56: 1105 | DC56: 963 | DD56: 860 | DE56: =DD56 -> 860 | DF56: 833 | DG56: 785 | DH56: 321 | DI56: 314 | DJ56: =DI56 -> 314 | DK56: 308 | DL56: 318 | DM56: 245 | DN56: 241 | DO56: =DN56 -> 241 | DP56: 389 | DQ56: 365
B57: Net PP&E | C57: 8391 | D57: 8589 | E57: 8245 | F57: 8814 | G57: 8459 | H57: 8765 | I57: 8432 | J57: 8383 | K57: 8252 | L57: 8333 | M57: =N57 -> 8443 | N57: 8443 | O57: 8467 | P57: 8121 | Q57: 8268 | R57: =S57 -> 8420 | S57: 8420 | T57: 8891 | U57: 9042 | V57: 8670 | W57: =X57 -> 7675 | X57: 7675 | Y57: 7837 | Z57: 7985 | AA57: 8182 | AB57: =AC57 -> 8265 | AC57: 8265 | AD57: 8376 | AE57: 8585 | AF57: 8686 | AG57: =AH57 -> 8762 | AH57: 8762 | AI57: 8798 | AJ57: 8808 | AK57: 8912 | AL57: 8784 | AM57: =AL57 -> 8784 | AN57: 8693 | AO57: 8584 | AP57: 8671 | AQ57: 8931 | AR57: =AQ57 -> 8931 | AS57: 8973 | AT57: 9044 | AU57: 9190 | AV57: 9313 | AW57: =AV57 -> 9313 | AX57: 9399 | AY57: 9453 | AZ57: 9496 | BA57: 9660 | BB57: =BA57 -> 9660 | BC57: 9736 | BD57: 9814 | BE57: 9987 | BF57: 10224 | BG57: =BF57 -> 10224 | BH57: 10263 | BI57: 10449 | BJ57: 10707 | BK57: 11007 | BL57: =BK57 -> 11007 | BM57: 11172 | BN57: 11338 | BO57: 11614 | BP57: 12076 | BQ57: =BP57 -> 12076 | BR57: 12269 | BS57: 12533 | BT57: 12713 | BU57: 12807 | BV57: =BU57 -> 12807 | BW57: 12842 | BX57: 12820 | BY57: 12712 | BZ57: 12672 | CA57: =BZ57 -> 12672 | CB57: 12628 | CC57: 12605 | CD57: 12571 | CE57: 12645 | CF57: =CE57 -> 12645 | CG57: 12594 | CH57: 12601 | CI57: 12527 | CJ57: 12502 | CK57: =CJ57 -> 12502 | CL57: 12405 | CM57: 12182 | CN57: 11969 | CO57: 11820 | CP57: =CO57 -> 11820 | CQ57: 11643 | CR57: 11341 | CS57: 11113 | CT57: 10918 | CU57: =CT57 -> 10918 | CV57: 10755 | CW57: 10617 | CX57: 10508 | CY57: 10550 | CZ57: =CY57 -> 10550 | DA57: 10493 | DB57: 10455 | DC57: 10484 | DD57: 10661 | DE57: =DD57 -> 10661 | DF57: 10696 | DG57: 10976 | DH57: 11236 | DI57: 11412 | DJ57: =DI57 -> 11412 | DK57: 11459 | DL57: 11658 | DM57: 12078 | DN57: 15361 | DO57: =DN57 -> 15361 | DP57: 15763 | DQ57: 16321
B58: Goodwill | C58: 2395 | D58: 2312 | E58: 2233 | F58: 5214 | G58: 6443 | H58: 2760 | I58: 1913 | J58: 1915 | K58: 1923 | L58: 1947 | M58: =N58 -> 1948 | N58: 1948 | O58: 1928 | P58: 1906 | Q58: 1903 | R58: =S58 -> 1924 | S58: 1924 | T58: 1922 | U58: 2037 | V58: 3208 | W58: =X58 -> 3047 | X58: 3047 | Y58: 3091 | Z58: 3092 | AA58: 3096 | AB58: =AC58 -> 3081 | AC58: 3081 | AD58: 3135 | AE58: 3232 | AF58: 3530 | AG58: =AH58 -> 3647 | AH58: 3647 | AI58: 3654 | AJ58: 3688 | AK58: 4293 | AL58: 4319 | AM58: =AL58 -> 4319 | AN58: 4317 | AO58: 4302 | AP58: 4871 | AQ58: 4937 | AR58: =AQ58 -> 4937 | AS58: 4944 | AT58: 4949 | AU58: 4939 | AV58: 4945 | AW58: =AV58 -> 4945 | AX58: 4950 | AY58: 4955 | AZ58: 4961 | BA58: 5035 | BB58: =BA58 -> 5035 | BC58: 5049 | BD58: 5043 | BE58: 5047 | BF58: 5043 | BG58: =BF58 -> 5043 | BH58: 5046 | BI58: 5139 | BJ58: 5131 | BK58: 5119 | BL58: =BK58 -> 5119 | BM58: 5105 | BN58: 5126 | BO58: 5122 | BP58: 5126 | BQ58: =BP58 -> 5126 | BR58: 5132 | BS58: 5128 | BT58: 5128 | BU58: 5324 | BV58: =BU58 -> 5324 | BW58: 5342 | BX58: 5347 | BY58: 5344 | BZ58: 5559 | CA58: =BZ58 -> 5559 | CB58: 5558 | CC58: 5550 | CD58: 5722 | CE58: 7840 | CF58: =CE58 -> 7840 | CG58: 7967 | CH58: 8051 | CI58: 8063 | CJ58: 8060 | CK58: =CJ58 -> 8060 | CL58: 8057 | CM58: 8064 | CN58: 8071 | CO58: 8081 | CP58: =CO58 -> 8081 | CQ58: 8074 | CR58: 8076 | CS58: 8070 | CT58: 8068 | CU58: =CT58 -> 8068 | CV58: 8065 | CW58: 8055 | CX58: 8045 | CY58: 8057 | CZ58: =CY58 -> 8057 | DA58: 8063 | DB58: 8061 | DC58: 8069 | DD58: 8093 | DE58: =DD58 -> 8093 | DF58: 8089 | DG58: 8108 | DH58: 8112 | DI58: 8084 | DJ58: =DI58 -> 8084 | DK58: 8091 | DL58: 7280 | DM58: 7281 | DN58: 17275 | DO58: =DN58 -> 17275 | DP58: 17633 | DQ58: 17554
B59: Other acquired intangibles, net | C59: 0 | D59: 0 | E59: 0 | F59: 0 | G59: 0 | H59: 1128 | I59: 1035 | J59: 1012 | K59: 1006 | L59: 981 | M59: =N59 -> 955 | N59: 955 | O59: 932 | P59: 919 | Q59: 908 | R59: =S59 -> 875 | S59: 875 | T59: 850 | U59: 841 | V59: 1471 | W59: =X59 -> 1698 | X59: 1698 | Y59: 1720 | Z59: 1754 | AA59: 1750 | AB59: =AC59 -> 2093 | AC59: 2093 | AD59: 2236 | AE59: 2223 | AF59: 2208 | AG59: =AH59 -> 2685 | AH59: 2685 | AI59: 2627 | AJ59: 2727 | AK59: 2920 | AL59: 2877 | AM59: =AL59 -> 2877 | AN59: 2878 | AO59: 2821 | AP59: 3027 | AQ59: 2979 | AR59: =AQ59 -> 2979 | AS59: 2933 | AT59: 3141 | AU59: 3095 | AV59: 3044 | AW59: =AV59 -> 3044 | AX59: 2993 | AY59: 2980 | AZ59: 2930 | BA59: 3111 | BB59: =BA59 -> 3111 | BC59: 3075 | BD59: 3011 | BE59: 2962 | BF59: 3052 | BG59: =BF59 -> 3052 | BH59: 2996 | BI59: 3004 | BJ59: 2954 | BK59: 2869 | BL59: =BK59 -> 2869 | BM59: 2809 | BN59: 2763 | BO59: 2706 | BP59: 2657 | BQ59: =BP59 -> 2657 | BR59: 2594 | BS59: 2544 | BT59: 2488 | BU59: 2540 | BV59: =BU59 -> 2540 | BW59: 2496 | BX59: 2567 | BY59: 2523 | BZ59: 2573 | CA59: =BZ59 -> 2573 | CB59: 2525 | CC59: 2494 | CD59: 2530 | CE59: 3429 | CF59: =CE59 -> 3429 | CG59: 3498 | CH59: 3761 | CI59: 3587 | CJ59: 3338 | CK59: =CJ59 -> 3338 | CL59: 3256 | CM59: 3019 | CN59: 2941 | CO59: 2843 | CP59: =CO59 -> 2843 | CQ59: 2773 | CR59: 2702 | CS59: 2631 | CT59: 2562 | CU59: =CT59 -> 2562 | CV59: 2492 | CW59: 2431 | CX59: 2371 | CY59: 2311 | CZ59: =CY59 -> 2311 | DA59: 2254 | DB59: 2194 | DC59: 2143 | DD59: 2094 | DE59: =DD59 -> 2094 | DF59: 2034 | DG59: 2067 | DH59: 2011 | DI59: 1957 | DJ59: =DI59 -> 1957 | DK59: 1904 | DL59: 1542 | DM59: 1495 | DN59: 1567 | DO59: =DN59 -> 1567 | DP59: 1517 | DQ59: 1531
B60: Deferred income taxes | C60: 15 | D60: 411 | E60: 0 | F60: 0 | G60: 0 | H60: 2272 | I60: 1242 | J60: 1182 | K60: 1352 | L60: 1334 | M60: =N60 -> 154 | N60: 154 | O60: 308 | P60: 247 | Q60: 335 | R60: =S60 -> 140 | S60: 140 | T60: 161 | U60: 161 | V60: 148 | W60: =X60 -> 1051 | X60: 1051 | Y60: 980 | Z60: 918 | AA60: 823 | AB60: =AC60 -> 197 | AC60: 197 | AD60: 247 | AE60: 276 | AF60: 183 | AG60: =AH60 -> 4114 | AH60: 4114 | AI60: 3880 | AJ60: 3858 | AK60: 3835 | AL60: 3062 | AM60: =AL60 -> 3062 | AN60: 2754 | AO60: 2379 | AP60: 2223 | AQ60: 4031 | AR60: =AQ60 -> 4031 | AS60: 3862 | AT60: 3697 | AU60: 3709 | AV60: 5892 | AW60: =AV60 -> 5892 | AX60: 5791 | AY60: 5781 | AZ60: 5520 | BA60: 6753 | BB60: =BA60 -> 6753 | BC60: 6522 | BD60: 6307 | BE60: 5957 | BF60: 2939 | BG60: =BF60 -> 2939 | BH60: 2463 | BI60: 2664 | BJ60: 2546 | BK60: 6576 | BL60: =BK60 -> 6576 | BM60: 6485 | BN60: 6264 | BO60: 6146 | BP60: 265 | BQ60: =BP60 -> 265 | BR60: 267 | BS60: 267 | BT60: 265 | BU60: 332 | BV60: =BU60 -> 332 | BW60: 336 | BX60: 325 | BY60: 298 | BZ60: 341 | CA60: =BZ60 -> 341 | CB60: 325 | CC60: 325 | CD60: 323 | CE60: 284 | CF60: =CE60 -> 284 | CG60: 281 | CH60: 357 | CI60: 296 | CJ60: 683 | CK60: =CJ60 -> 683 | CL60: 678 | CM60: 729 | CN60: 704 | CO60: 86 | CP60: =CO60 -> 86 | CQ60: 79 | CR60: 84 | CS60: 74 | CT60: 77 | CU60: =CT60 -> 77 | CV60: 91 | CW60: 106 | CX60: 77 | CY60: 63 | CZ60: =CY60 -> 63 | DA60: 65 | DB60: 66 | DC60: 64 | DD60: 59 | DE60: =DD60 -> 59 | DF60: 68 | DG60: 0 | DH60: 44 | DI60: 185 | DJ60: =DI60 -> 185 | DK60: 137 | DL60: 136 | DM60: 44 | DN60: 107 | DO60: =DN60 -> 107 | DP60: 136 | DQ60: 152
B61: Investments | C61: 0 | D61: 0 | E61: 0 | F61: 0 | G61: 0 | H61: 0 | I61: 0 | J61: 0 | K61: 0 | L61: 1790 | M61: =N61 -> 3050 | N61: 3050 | O61: 3198 | P61: 3158 | Q61: 2856 | R61: =S61 -> 2852 | S61: 2852 | T61: 2754 | U61: 2743 | V61: 2864 | W61: =X61 -> 4085 | X61: 4085 | Y61: 4021 | Z61: 4104 | AA61: 4053 | AB61: =AC61 -> 4111 | AC61: 4111 | AD61: 3722 | AE61: 4017 | AF61: 3717 | AG61: =AH61 -> 1328 | AH61: 1328 | AI61: 1261 | AJ61: 1188 | AK61: 1120 | AL61: 1030 | AM61: =AL61 -> 1030 | AN61: 1030 | AO61: 1008 | AP61: 1035 | AQ61: 1111 | AR61: =AQ61 -> 1111 | AS61: 1091 | AT61: 1117 | AU61: 1109 | AV61: 1043 | AW61: =AV61 -> 1043 | AX61: 1037 | AY61: 1004 | AZ61: 1195 | BA61: 1180 | BB61: =BA61 -> 1180 | BC61: 1177 | BD61: 1166 | BE61: 1168 | BF61: 1204 | BG61: =BF61 -> 1204 | BH61: 1208 | BI61: 1196 | BJ61: 1203 | BK61: 1154 | BL61: =BK61 -> 1154 | BM61: 1154 | BN61: 1256 | BO61: 1277 | BP61: 1284 | BQ61: =BP61 -> 1284 | BR61: 1297 | BS61: 1312 | BT61: 1303 | BU61: 1317 | BV61: =BU61 -> 1317 | BW61: 1319 | BX61: 1278 | BY61: 1270 | BZ61: 1260 | CA61: =BZ61 -> 1260 | CB61: 1248 | CC61: 1203 | CD61: 1190 | CE61: 1087 | CF61: =CE61 -> 1087 | CG61: 1183 | CH61: 1142 | CI61: 1117 | CJ61: 1092 | CK61: =CJ61 -> 1092 | CL61: 1124 | CM61: 1066 | CN61: 1052 | CO61: 1016 | CP61: =CO61 -> 1016 | CQ61: 980 | CR61: 883 | CS61: 963 | CT61: 975 | CU61: =CT61 -> 975 | CV61: 992 | CW61: 981 | CX61: 979 | CY61: 983 | CZ61: =CY61 -> 983 | DA61: 969 | DB61: 1025 | DC61: 1061 | DD61: 1035 | DE61: =DD61 -> 1035 | DF61: 1042 | DG61: 1026 | DH61: 1030 | DI61: 999 | DJ61: =DI61 -> 999 | DK61: 1001 | DL61: 1036 | DM61: 1050 | DN61: 1048 | DO61: =DN61 -> 1048 | DP61: 1048 | DQ61: 1117
B62: Pension plan assets, net | C62: 3271 | D62: 3513 | E62: 3845 | F62: 4845 | G62: 5838 | H62: 6671 | I62: 8542 | J62: 9483 | K62: 10416 | L62: 11959 | M62: =N62 -> 12588 | N62: 12588 | O62: 12837 | P62: 12705 | Q62: 13687 | R62: =S62 -> 13251 | S62: 13251 | T62: 13525 | U62: =13253 -> 13253 | V62: 13031 | W62: =X62 -> 0 | X62: 0 | Y62: 0 | Z62: 0 | AA62: 0 | AB62: =AC62 -> 5924 | AC62: 5924 | AD62: 6391 | AE62: 6445 | AF62: 6497 | AG62: =AH62 -> 16 | AH62: 16 | AI62: 12 | AJ62: 21 | AK62: 20 | AL62: 16 | AM62: =AL62 -> 16 | AN62: 21 | AO62: 27 | AP62: 33 | AQ62: 6 | AR62: =AQ62 -> 6 | AS62: 4 | AT62: 5 | AU62: 6 | AV62: 0 | AW62: =AV62 -> 0 | BB62: =BA62 -> 0 | BC62: 0 | BD62: 0 | BG62: =BF62 -> 0 | BH62: 0 | BI62: 0 | BL62: =BK62 -> 0 | BQ62: =BP62 -> 0 | BV62: =BU62 -> 0 | CA62: =BZ62 -> 0
B63: Other assets, net of accumulated amortization | C63: 350 | D63: 542 | E63: 907 | F63: =60+1267 -> 1327 | G63: 2052 | H63: 2969 | I63: 2519 | J63: 2556 | K63: 2442 | L63: 1850 | M63: =N63 -> 1340 | N63: =1340 -> 1340 | O63: 1261 | P63: 1301 | Q63: 1445 | R63: =S63 -> 989 | S63: 989 | T63: 935 | U63: 966 | V63: 899 | W63: =X63 -> 2735 | X63: 2735 | Y63: 3142 | Z63: 3283 | AA63: 3330 | AB63: =AC63 -> 1258 | AC63: 1258 | AD63: 1353 | AE63: 1425 | AF63: 1368 | AG63: =AH63 -> 1406 | AH63: 1406 | AI63: 1450 | AJ63: 1333 | AK63: 1417 | AL63: 1224 | AM63: =AL63 -> 1224 | AN63: 1206 | AO63: 1223 | AP63: 1220 | AQ63: 1603 | AR63: =AQ63 -> 1603 | AS63: 1624 | AT63: 1596 | AU63: 1455 | AV63: 1643 | AW63: =AV63 -> 1643 | AX63: 1765 | AY63: 1746 | AZ63: 1746 | BA63: 1792 | BB63: =BA63 -> 1792 | BC63: 1488 | BD63: 1449 | BE63: 1447 | BF63: 1500 | BG63: =BF63 -> 1500 | BH63: 1542 | BI63: 1578 | BJ63: 1547 | BK63: 1317 | BL63: =BK63 -> 1317 | BM63: 1328 | BN63: 1374 | BO63: 1326 | BP63: 1408 | BQ63: =BP63 -> 1408 | BR63: 1421 | BS63: 1409 | BT63: 1415 | BU63: 1416 | BV63: =BU63 -> 1416 | BW63: 1444 | BX63: 1470 | BY63: 1679 | BZ63: 2027 | CA63: =BZ63 -> 2027 | CB63: 1969 | CC63: 1800 | CD63: 1852 | CE63: 1826 | CF63: =CE63 -> 1826 | CG63: 2941 | CH63: 3099 | CI63: 3275 | CJ63: 3585 | CK63: =CJ63 -> 3585 | CL63: 4428 | CM63: 5481 | CN63: 3502 | CO63: 4712 | CP63: =CO63 -> 4712 | CQ63: 4646 | CR63: 4889 | CS63: 5312 | CT63: 5591 | CU63: =CT63 -> 5591 | CV63: 5814 | CW63: 5747 | CX63: 4814 | CY63: 4163 | CZ63: =CY63 -> 4163 | DA63: 4320 | DB63: 4456 | DC63: 4562 | DD63: 4935 | DE63: =DD63 -> 4935 | DF63: 5190 | DG63: 5319 | DH63: 5505 | DI63: 5414 | DJ63: =DI63 -> 5414 | DK63: 5932 | DL63: 5849 | DM63: 5698 | DN63: 4177 | DO63: =DN63 -> 4177 | DP63: 4160 | DQ63: 4200
B64: Total assets | C64: =SUM(C55:C63) -> 38024 | D64: =SUM(D55:D63) -> 36672 | E64: =SUM(E55:E63) -> 36147 | F64: =SUM(F55:F63) -> 42028 | G64: =SUM(G55:G63) -> 48343 | H64: =SUM(H55:H63) -> 52342 | I64: =SUM(I55:I63) -> 53035 | J64: =SUM(J55:J63) -> 53800 | ... L64: =SUM(L55:L63) -> 55388 | M64: =N64 -> 53963 | N64: =SUM(N55:N63) -> 53963 | O64: =SUM(O55:O63) -> 56714 | P64: =SUM(P55:P63) -> 56494 | Q64: =SUM(Q55:Q63) -> 58318 | R64: =S64 -> 60058 | S64: =SUM(S55:S63) -> 60058 | T64: =SUM(T55:T63) -> 61408 | U64: =SUM(U55:U63) -> 61269 | V64: =SUM(V55:V63) -> 61458 | W64: =X64 -> 51794 | X64: =SUM(X55:X63) -> 51794 | Y64: =SUM(Y55:Y63) -> 51556 | Z64: =SUM(Z55:Z63) -> 53886 | AA64: =SUM(AA55:AA63) -> 54787 | AB64: =AC64 -> 58986 | AC64: =SUM(AC55:AC63) -> 58986 | AD64: =SUM(AD55:AD63) -> 60360 | AE64: =SUM(AE55:AE63) -> 58510 | AF64: =SUM(AF55:AF63) -> 56519 | AG64: =AH64 -> 53779 | AH64: =SUM(AH55:AH63) -> 53779 | AI64: =SUM(AI55:AI63) -> 55340 | AJ64: =SUM(AJ55:AJ63) -> 57712 | AK64: =SUM(AK55:AK63) -> 58667 | AL64: =SUM(AL55:AL63) -> 62053 | AM64: =SUM(AM55:AM63) -> 62053 | AN64: =SUM(AN55:AN63) -> 62970 | AO64: =SUM(AO55:AO63) -> 63755 | ... DQ64: =SUM(DQ55:DQ63) -> 165870
B66: Liabilities and shareholder's equity
B67: Accounts payable | C67: 11548 | D67: 10733 | E67: 11269 | F67: 11979 | G67: 13872 | H67: 13739 | I67: 13563 | J67: 13514 | K67: 14198 | L67: 14971 | M67: =N67 -> 14869 | N67: 14869 | O67: 15338 | P67: 15939 | Q67: 16912 | R67: =S67 -> 16513 | S67: 16513 | T67: 16719 | U67: 17847 | V67: 16741 | W67: =X67 -> 16201 | X67: 16201 | Y67: 15921 | Z67: 17174 | AA67: 16536 | AB67: =AC67 -> 16676 | AC67: 16676 | AD67: 17336 | AE67: 17431 | AF67: 16427 | AG67: =AH67 -> 17587 | AH67: 17587 | AI67: 17553 | AJ67: =6664 -> 6664 | AK67: =7053 -> 7053 | AL67: =7096 -> 7096 | AM67: =AL67 -> 7096 | AN67: =7469 -> 7469 | AO67: =6960 -> 6960 | AP67: =7563 -> 7563 | AQ67: =7715 -> 7715 | AR67: =AQ67 -> 7715 | AS67: =8304 -> 8304 | AT67: =8262 -> 8262 | AU67: =8502 -> 8502 | AV67: =8406 -> 8406 | AW67: =AV67 -> 8406 | AX67: =9041 -> 9041 | AY67: =9273 -> 9273 | AZ67: =9152 -> 9152 | BA67: =9394 -> 9394 | BB67: =BA67 -> 9394 | BC67: =9876 -> 9876 | BD67: =10437 -> 10437 | BE67: =10657 -> 10657 | BF67: =9498 -> 9498 | BG67: =BF67 -> 9498 | BH67: =10779 -> 10779 | BI67: =11060 -> 11060 | BJ67: =11136 -> 11136 | BK67: =10667 -> 10667 | BL67: =BK67 -> 10667 | BM67: =11497 -> 11497 | BN67: =11531 -> 11531 | BO67: =11777 -> 11777 | BP67: =10800 -> 10800 | BQ67: =BP67 -> 10800 | BR67: =11558 -> 11558 | BS67: =11748 -> 11748 | BT67: 11968 | BU67: 11190 | BV67: =BU67 -> 11190 | BW67: 11964 | BX67: 12093 | BY67: 12718 | BZ67: 12202 | CA67: =BZ67 -> 12202 | CB67: 12613 | CC67: 12904 | CD67: 13663 | CE67: 12916 | CF67: =CE67 -> 12916 | CG67: 14693 | CH67: 15267 | CI67: 15101 | CJ67: 15553 | CK67: =CJ67 -> 15553 | CL67: 14963 | CM67: 13700 | CN67: 14479 | CO67: 12928 | CP67: =CO67 -> 12928 | CQ67: 12410 | CR67: 11450 | CS67: 10151 | CT67: 9261 | CU67: =CT67 -> 9261 | CV67: 8779 | CW67: 9575 | CX67: 9793 | CY67: 10200 | CZ67: =CY67 -> 10200 | DA67: 10274 | DB67: 10936 | DC67: 11143 | DD67: 11964 | DE67: =DD67 -> 11964 | DF67: 11616 | DG67: 11864 | DH67: 12267 | DI67: 11364 | DJ67: =DI67 -> 11364 | DK67: 11034 | DL67: 11238 | DM67: 11732 | DN67: 13109 | DO67: =DN67 -> 13109 | DP67: 13713 | DQ67: 14346
B68: Accrued liabilities | AJ68: 11821 | AK68: 12217 | AL68: 12822 | AM68: =AL68 -> 12822 | AN68: 12267 | AO68: 12899 | AP68: 12760 | AQ68: 13802 | AR68: =AQ68 -> 13802 | AS68: 12835 | AT68: 13570 | AU68: 11213 | AV68: 12239 | AW68: =AV68 -> 12239 | AX68: 10943 | AY68: 11699 | AZ68: 11773 | BA68: 12995 | BB68: =BA68 -> 12995 | BC68: 11530 | BD68: 12412 | BE68: 12384 | BF68: 14131 | BG68: =BF68 -> 14131 | BH68: 12219 | BI68: 13222 | BJ68: 12677 | BK68: 13343 | BL68: =BK68 -> 13343 | BM68: 11958 | BN68: 13226 | BO68: 12770 | BP68: 14014 | BQ68: =BP68 -> 14014 | BR68: 12790 | BS68: 13534 | BT68: 13243 | BU68: 14691 | BV68: =BU68 -> 14691 | BW68: 13332 | BX68: 14294 | BY68: 14008 | BZ68: 15292 | CA68: =BZ68 -> 15292 | CB68: 10983 | CC68: 12240 | CD68: 12869 | CE68: 14808 | CF68: =CE68 -> 14808 | CG68: 13007 | CH68: 20042 | CI68: 19224 | CJ68: 22868 | CK68: =CJ68 -> 22868 | CL68: 21483 | CM68: 22493 | CN68: 22220 | CO68: 22171 | CP68: =CO68 -> 22171 | CQ68: 20553 | CR68: 19502 | CS68: 18974 | CT68: 18455 | CU68: =CT68 -> 18455 | CV68: 17864 | CW68: 17752 | CX68: 21217 | CY68: 21581 | CZ68: =CY68 -> 21581 | DA68: 20812 | DB68: 21221 | DC68: 21104 | DD68: 22331 | DE68: =DD68 -> 22331 | DF68: 21607 | DG68: 21850 | DH68: 22628 | DI68: 24103 | DJ68: =DI68 -> 24103 | DK68: 23576 | DL68: 23508 | DM68: 24364 | DN68: 27141 | DO68: =DN68 -> 27141 | DP68: 26388 | DQ68: 26593
B69: Advances and billings in excess of related costs | C69: 1575 | D69: 1251 | E69: 1215 | F69: 3517 | G69: 4306 | H69: 3123 | I69: 3464 | J69: 3705 | K69: 3473 | L69: 3904 | M69: =N69 -> 4123 | N69: 4123 | O69: 6471 | P69: 6875 | Q69: 7869 | R69: =S69 -> 9930 | S69: 9930 | T69: 10018 | U69: 10268 | V69: 10524 | W69: =X69 -> 11449 | X69: 11449 | Y69: 11134 | Z69: 11546 | AA69: 12226 | AB69: =AC69 -> 13847 | AC69: 13847 | AD69: 13961 | AE69: 12682 | AF69: 11793 | AG69: =AH69 -> 12737 | AH69: 12737 | AI69: 11527 | AJ69: 11717 | AK69: 11792 | AL69: 12076 | AM69: =AL69 -> 12076 | AN69: 11857 | AO69: 12009 | AP69: 11844 | AQ69: 12323 | AR69: =AQ69 -> 12323 | AS69: 12363 | AT69: 12948 | AU69: 14320 | AV69: 15496 | AW69: =AV69 -> 15496 | AX69: 15336 | AY69: 15344 | AZ69: 15619 | BA69: 16672 | BB69: =BA69 -> 16672 | BC69: 18505 | BD69: 18145 | BE69: 20216 | BF69: 20027 | BG69: =BF69 -> 20027 | BH69: 21112 | BI69: 21244 | BJ69: 21127 | BK69: 23175 | BL69: =BK69 -> 23175 | BM69: 22752 | BN69: 23373 | BO69: 23442 | BP69: 24364 | BQ69: =BP69 -> 24364 | BR69: 23926 | BS69: 23409 | BT69: 22646 | BU69: 23869 | BV69: =BU69 -> 23869 | BW69: 24118 | BX69: 25802 | BY69: 26695 | BZ69: 27440 | CA69: =BZ69 -> 27440 | CB69: 49955 | CC69: 50970 | CD69: 51496 | CE69: 50676 | CF69: =CE69 -> 50676 | CG69: 52534 | CH69: 52523 | CI69: 53167 | CJ69: 51551 | CK69: =CJ69 -> 51551 | CL69: 52883 | CM69: 53367 | CN69: 51974 | CO69: 50488 | CP69: =CO69 -> 50488 | CQ69: 50908 | CR69: 50738 | CS69: 51269 | CT69: 52980 | CU69: =CT69 -> 52980 | CV69: 52458 | CW69: 52066 | CX69: 53177 | CY69: 53081 | CZ69: =CY69 -> 53081 | DA69: 54498 | DB69: 55310 | DC69: 55924 | DD69: 56328 | DE69: =DD69 -> 56328 | DF69: 58972 | DG69: 58151 | DH69: 57931 | DI69: 60333 | DJ69: =DI69 -> 60333 | DK69: 61114 | DL69: 59407 | DM69: 57962 | DN69: 59404 | DO69: =DN69 -> 59404 | DP69: 62591 | DQ69: 64059
B70: Income tax payable | C70: 298 | D70: 569 | E70: 420 | F70: 1561 | G70: 909 | H70: 1134 | I70: 277 | J70: 437 | K70: 725 | L70: 1287 | M70: =N70 -> 522 | N70: 522 | O70: 594 | P70: 801 | Q70: 609 | R70: =S70 -> 556 | S70: 556 | T70: 684 | U70: 743 | V70: 813 | W70: =X70 -> 670 | X70: 670 | Y70: 776 | Z70: 846 | AA70: 1080 | AB70: =AC70 -> 253 | AC70: 253 | AD70: 587 | AE70: 416 | AF70: 752 | AG70: =AH70 -> 41 | AH70: 41 | AI70: 355 | AJ70: 654 | AK70: 14 | AL70: 182 | AM70: =AL70 -> 182 | AN70: 412 | AO70: 713 | AP70: 1118 | AQ70: 607 | AR70: =AQ70 -> 607 | AS70: 789 | AT70: 1286 | AU70: 1955 | AV70: 2780 | AW70: =AV70 -> 2780 | AX70: 3178 | AY70: 3668 | AZ70: 4136 | BA70: 4485 | BB70: =BA70 -> 4485 | BC70: 4838 | BD70: 5072 | BE70: 5504 | BF70: 6267 | BG70: =BF70 -> 6267 | BH70: 6732 | BI70: 6222 | BJ70: 6685 | BK70: 8603 | BL70: =BK70 -> 8603 | BM70: 8916 | BN70: 8894 | BO70: 9205 | BP70: 0 | BQ70: =BP70 -> 0 | BR70: 0 | BS70: 0 | BT70: 0 | BU70: 0 | BV70: =BU70 -> 0 | BW70: 0 | CA70: =BZ70 -> 0
B71: Short term debt and current portion of long term debt | C71: 731 | D71: 869 | E71: 752 | F71: 1232 | G71: 1399 | H71: 1814 | I71: 1144 | J71: 916 | K71: 2575 | L71: 1320 | M71: =N71 -> 1321 | N71: 1321 | O71: 998 | P71: 809 | Q71: 726 | R71: =S71 -> 1189 | S71: 1189 | T71: 1967 | U71: 1499 | V71: 1582 | W71: =X71 -> 1381 | X71: 1381 | Y71: 598 | Z71: 561 | AA71: 1025 | AB71: =AC71 -> 762 | AC71: 762 | AD71: 802 | AE71: 916 | AF71: 390 | AG71: =AH71 -> 560 | AH71: 560 | AI71: 530 | AJ71: 416 | AK71: 973 | AL71: 707 | AM71: =AL71 -> 707 | AN71: 1479 | AO71: 1507 | AP71: 953 | AQ71: 948 | AR71: =AQ71 -> 948 | AS71: 966 | AT71: 1304 | AU71: 1603 | AV71: 2353 | AW71: =AV71 -> 2353 | AX71: 2807 | AY71: 2466 | AZ71: 2172 | BA71: 1436 | BB71: =BA71 -> 1436 | BC71: 917 | BD71: 883 | BE71: 919 | BF71: 1563 | BG71: =BF71 -> 1563 | BH71: 1660 | BI71: 1591 | BJ71: 1579 | BK71: 929 | BL71: =BK71 -> 929 | BM71: 133 | BN71: 112 | BO71: 614 | BP71: 1234 | BQ71: =BP71 -> 1234 | BR71: 1243 | BS71: 1168 | BT71: 632 | BU71: 384 | BV71: =BU71 -> 384 | BW71: 367 | BX71: 720 | BY71: 988 | BZ71: 1335 | CA71: =BZ71 -> 1335 | CB71: 1981 | CC71: 1611 | CD71: 1389 | CE71: 3190 | CF71: =CE71 -> 3190 | CG71: 3381 | CH71: 4357 | CI71: 4354 | CJ71: 7340 | CK71: =CJ71 -> 7340 | CL71: 5173 | CM71: 2922 | CN71: 3634 | CO71: 1693 | CP71: =CO71 -> 1693 | CQ71: 6021 | CR71: 6534 | CS71: 5377 | CT71: 1296 | CU71: =CT71 -> 1296 | CV71: 2591 | CW71: 5406 | CX71: 5431 | CY71: 5190 | CZ71: =CY71 -> 5190 | DA71: 7926 | DB71: 4609 | DC71: 4891 | DD71: 5204 | DE71: =DD71 -> 5204 | DF71: 1063 | DG71: 4765 | DH71: 4474 | DI71: 1278 | DJ71: =DI71 -> 1278 | DK71: 7930 | DL71: 8719 | DM71: 8742 | DN71: 8461 | DO71: =DN71 -> 8461 | DP71: 2855 | DQ71: 4565
B72: Other current liabilities | C72: 0 | D72: 0 | E72: 0 | F72: 0 | G72: 0 | H72: 0 | I72: 0 | J72: 0 | K72: 0 | L72: 0 | M72: =N72 -> 0 | N72: 0 | O72: 0 | P72: 0 | Q72: 0 | R72: =S72 -> 0 | S72: 0 | T72: 0 | U72: 0 | V72: 0 | W72: =X72 -> 0 | X72: 0 | Y72: 0 | Z72: 0 | AA72: 0 | AB72: =AC72 -> 0 | AC72: 0 | AD72: 0 | AE72: 0 | AF72: 0 | AG72: =AH72 -> 0 | AH72: 0 | AI72: 0 | AJ72: 0 | AK72: 0 | AL72: 0 | AM72: =AL72 -> 0 | AN72: 0 | AO72: 0 | AP72: 0 | AQ72: 0 | AR72: =AQ72 -> 0 | AS72: 0 | AT72: 0 | AU72: 0 | AV72: 0 | AW72: =AV72 -> 0 | AX72: 0 | AY72: 0 | AZ72: 0 | BA72: 0 | BB72: =BA72 -> 0 | BC72: 0 | BD72: 0 | BE72: 0 | BF72: 0 | BG72: =BF72 -> 0 | BL72: =BK72 -> 0 | BQ72: =BP72 -> 0 | BV72: =BU72 -> 0 | CA72: =BZ72 -> 0 | DL72: 504 | DM72: 524
B73: Total current liabilities | C73: =SUM(C67:C72) -> 14152 | D73: =SUM(D67:D72) -> 13422 | E73: =SUM(E67:E72) -> 13656 | F73: =SUM(F67:F72) -> 18289 | G73: =SUM(G67:G72) -> 20486 | H73: =SUM(H67:H72) -> 19810 | I73: =SUM(I67:I72) -> 18448 | J73: =SUM(J67:J72) -> 18572 | ... L73: =SUM(L67:L72) -> 21482 | M73: =N73 -> 20835 | N73: =SUM(N67:N72) -> 20835 | O73: =SUM(O67:O72) -> 23401 | P73: =SUM(P67:P72) -> 24424 | Q73: =SUM(Q67:Q72) -> 26116 | R73: =S73 -> 28188 | S73: =SUM(S67:S72) -> 28188 | T73: =SUM(T67:T72) -> 29388 | U73: =SUM(U67:U72) -> 30357 | V73: =SUM(V67:V72) -> 29660 | W73: =X73 -> 29701 | X73: =SUM(X67:X72) -> 29701 | Y73: =SUM(Y67:Y72) -> 28429 | Z73: =SUM(Z67:Z72) -> 30127 | AA73: =SUM(AA67:AA72) -> 30867 | AB73: =AC73 -> 31538 | AC73: =SUM(AC67:AC72) -> 31538 | AD73: =SUM(AD67:AD72) -> 32686 | AE73: =SUM(AE67:AE72) -> 31445 | AF73: =SUM(AF67:AF72) -> 29362 | AG73: =AH73 -> 30925 | AH73: =SUM(AH67:AH72) -> 30925 | AI73: =SUM(AI67:AI72) -> 29965 | AJ73: =SUM(AJ67:AJ72) -> 31272 | AK73: =SUM(AK67:AK72) -> 32049 | AL73: =SUM(AL67:AL72) -> 32883 | AM73: =SUM(AM67:AM72) -> 32883 | AN73: =SUM(AN67:AN72) -> 33484 | AO73: =SUM(AO67:AO72) -> 34088 | ... DQ73: =SUM(DQ67:DQ72) -> 109563
B74: Accrued retiree health care | C74: 4796 | D74: 4831 | E74: 4877 | F74: 5152 | G74: 5367 | H74: 5434 | I74: 5745 | J74: 5802 | K74: 5847 | L74: 5911 | M74: =N74 -> 5959 | N74: 5959 | O74: 5983 | P74: 6005 | Q74: 5970 | R74: =S74 -> 5989 | S74: 5989 | T74: 6022 | U74: 6058 | V74: 6063 | W74: =X74 -> 7671 | X74: 7671 | Y74: 7674 | Z74: 7684 | AA74: 7694 | AB74: =AC74 -> 7007 | AC74: 7007 | AD74: 7123 | AE74: 7159 | AF74: 7165 | AG74: =AH74 -> 7322 | AH74: 7322 | AI74: 7336 | AJ74: 7336 | AK74: 7344 | AL74: 7049 | AM74: =AL74 -> 7049 | AN74: 7043 | AO74: 7068 | AP74: 7062 | AQ74: 8025 | AR74: =AQ74 -> 8025 | AS74: 8034 | AT74: 8036 | AU74: 8335 | AV74: 7520 | AW74: =AV74 -> 7520 | AX74: 7498 | AY74: 7478 | AZ74: 7454 | BA74: 7528 | BB74: =BA74 -> 7528 | BC74: 7447 | BD74: 7431 | BE74: 7415 | BF74: 6528 | BG74: =BF74 -> 6528 | BH74: 6515 | BI74: 6506 | BJ74: 6494 | BK74: 6802 | BL74: =BK74 -> 6802 | BM74: 6789 | BN74: 6777 | BO74: 6746 | BP74: 6616 | BQ74: =BP74 -> 6616 | BR74: 6614 | BS74: 6586 | BT74: 6544 | BU74: 5916 | BV74: =BU74 -> 5916 | BW74: 5885 | BX74: 5856 | BY74: 5826 | BZ74: 5545 | CA74: =BZ74 -> 5545 | CB74: 5494 | CC74: 5444 | CD74: 5394 | CE74: 4584 | CF74: =CE74 -> 4584 | CG74: 4535 | CH74: 4486 | CI74: 4437 | CJ74: 4540 | CK74: =CJ74 -> 4540 | CL74: 4483 | CM74: 4427 | CN74: 4429 | CO74: 4137 | CP74: =CO74 -> 4137 | CQ74: 4077 | CR74: 4017 | CS74: 3957 | CT74: 3528 | CU74: =CT74 -> 3528 | CV74: 3471 | CW74: 3413 | CX74: 3356 | CY74: 2503 | CZ74: =CY74 -> 2503 | DA74: 2466 | DB74: 2424 | DC74: 2385 | DD74: 2233 | DE74: =DD74 -> 2233 | DF74: 2196 | DG74: 2159 | DH74: 2121 | DI74: 2176 | DJ74: =DI74 -> 2176 | DK74: 2146 | DL74: 2116 | DM74: 2086 | DN74: 2091 | DO74: =DN74 -> 2091 | DP74: 2059 | DQ74: 2027
B75: Accrued pension plan liability, net | C75: 0 | D75: 0 | E75: 0 | F75: 0 | G75: 0 | H75: 6271 | I75: 6629 | J75: 6629 | K75: 6629 | L75: 6629 | M75: =N75 -> 3169 | N75: 3169 | O75: 3169 | P75: 3169 | Q75: 6012 | R75: =S75 -> 2948 | S75: 2948 | T75: 2953 | U75: 2954 | V75: 2954 | W75: =X75 -> 1135 | X75: 1135 | Y75: 985 | Z75: 992 | AA75: 980 | AB75: =AC75 -> 1155 | AC75: 1155 | AD75: 1073 | AE75: 1083 | AF75: 1102 | AG75: =AH75 -> 8383 | AH75: 8383 | AI75: 8484 | AJ75: 8553 | AK75: 8553 | AL75: 6315 | AM75: =AL75 -> 6315 | AN75: 6392 | AO75: 6466 | AP75: 6522 | AQ75: 9800 | AR75: =AQ75 -> 9800 | AS75: 9979 | AT75: 10155 | AU75: 9848 | AV75: 16537 | AW75: =AV75 -> 16537 | AX75: 16730 | AY75: 16164 | AZ75: 15586 | BA75: 19651 | BB75: =BA75 -> 19651 | BC75: 19878 | BD75: 20070 | BE75: 18559 | BF75: 10474 | BG75: =BF75 -> 10474 | BH75: 9676 | BI75: 9812 | BJ75: 9262 | BK75: 17182 | BL75: =BK75 -> 17182 | BM75: 17362 | BN75: 17537 | BO75: 17795 | BP75: 17783 | BQ75: =BP75 -> 17783 | BR75: 18196 | BS75: 18200 | BT75: 18003 | BU75: 19943 | BV75: =BU75 -> 19943 | BW75: 19796 | BX75: 19651 | BY75: 15514 | BZ75: 16471 | CA75: =BZ75 -> 16471 | CB75: 16279 | CC75: 16118 | CD75: 15927 | CE75: 15323 | CF75: =CE75 -> 15323 | CG75: 15077 | CH75: 14831 | CI75: 14590 | CJ75: 16276 | CK75: =CJ75 -> 16276 | CL75: 15962 | CM75: 15663 | CN75: 15343 | CO75: 14408 | CP75: =CO75 -> 14408 | CQ75: 13968 | CR75: 13519 | CS75: 11435 | CT75: 9104 | CU75: =CT75 -> 9104 | CV75: 8719 | CW75: 8335 | CX75: 7951 | CY75: 6141 | CZ75: =CY75 -> 6141 | DA75: 5998 | DB75: 5855 | DC75: 5713 | DD75: 6516 | DE75: =DD75 -> 6516 | DF75: 6400 | DG75: 6248 | DH75: 6097 | DI75: 5997 | DJ75: =DI75 -> 5997 | DK75: 5909 | DL75: 5803 | DM75: 5714 | DN75: 4287 | DO75: =DN75 -> 4287 | DP75: 4198 | DQ75: 4108
B76: Deferred income taxes | C76: 0 | D76: 0 | E76: 0 | F76: 0 | G76: 0 | H76: 0 | I76: 0 | J76: 0 | K76: 0 | L76: 0 | M76: =N76 -> 0 | N76: 0 | O76: 0 | P76: 0 | Q76: 0 | R76: =S76 -> 0 | S76: 0 | T76: 0 | U76: 0 | V76: 0 | W76: =X76 -> 0 | X76: 0 | Y76: 308 | Z76: 732 | AA76: 879 | AB76: =AC76 -> 1121 | AC76: 1121 | AD76: 1123 | AE76: 1148 | AF76: 1132 | AG76: =AH76 -> 1154 | AH76: 1154 | AI76: 1035 | AJ76: 1182 | AK76: 998 | AL76: 827 | AM76: =AL76 -> 827 | AN76: 896 | AO76: 860 | AP76: 838 | AQ76: 418 | AR76: =AQ76 -> 418 | AS76: 427 | AT76: 383 | AU76: 390 | AV76: 122 | AW76: =AV76 -> 122 | AX76: 192 | AY76: 226 | AZ76: 166 | BA76: 366 | BB76: =BA76 -> 366 | BC76: 241 | BD76: 275 | BE76: 299 | BF76: 156 | BG76: =BF76 -> 156 | BH76: 166 | BI76: 740 | BJ76: 709 | BK76: 358 | BL76: =BK76 -> 358 | BM76: 352 | BN76: 389 | BO76: 378 | BP76: 2392 | BQ76: =BP76 -> 2392 | BR76: 2297 | BS76: 2422 | BT76: 2211 | BU76: 1338 | BV76: =BU76 -> 1338 | BW76: 1339 | BX76: 1415 | BY76: 2884 | BZ76: 1839 | CA76: =BZ76 -> 1839 | CB76: 2001 | CC76: 1900 | CD76: 1738 | CE76: 1736 | CF76: =CE76 -> 1736 | CG76: 1656 | CH76: 0 | CI76: 1615 | CJ76: 413 | CK76: =CJ76 -> 413 | CL76: 336 | CM76: 404 | CN76: 503 | CO76: 1010 | CP76: =CO76 -> 1010 | CQ76: 908 | CR76: 1064 | CS76: 1185 | CT76: 218 | CU76: =CT76 -> 218 | CV76: 158 | CW76: 38 | CX76: 230 | CY76: 230 | CZ76: =CY76 -> 230 | DA76: 194 | DB76: 95 | DC76: 218 | DD76: 229 | DE76: =DD76 -> 229 | DF76: 223 | DG76: 291 | DH76: 249 | DI76: 122 | DJ76: =DI76 -> 122 | DK76: 162 | DL76: 193 | DM76: 191 | DN76: 216 | DO76: =DN76 -> 216 | DP76: 237 | DQ76: 260
B77: Other long term liabilities | C77: 0 | D77: 0 | E77: 172 | F77: 0 | G77: =622+177 -> 799 | H77: 542 | I77: 775 | J77: 831 | K77: 803 | L77: 774 | M77: =N77 -> 1835 | N77: =1090+745 -> 1835 | O77: =715+1186 -> 1901 | P77: =319+1222 -> 1541 | Q77: =294+367 -> 661 | R77: =S77 -> 2336 | S77: =269+2067 -> 2336 | T77: =252+2219 -> 2471 | U77: =254+2315 -> 2569 | V77: =276+2930 -> 3206 | W77: =X77 -> 391 | X77: 391 | Y77: 400 | Z77: 400 | AA77: 406 | AB77: =AC77 -> 1706 | AC77: =516+1190 -> 1706 | AD77: =391+1470 -> 1861 | AE77: =408+1433 -> 1841 | AF77: =392+1435 -> 1827 | AG77: =AH77 -> 337 | AH77: 337 | AI77: 287 | AJ77: 335 | AK77: 535 | AL77: 537 | AM77: =AL77 -> 537 | AN77: 652 | AO77: 661 | AP77: 544 | AQ77: 592 | AR77: =AQ77 -> 592 | AS77: 333 | AT77: 1027 | AU77: 1159 | AV77: 907 | AW77: =AV77 -> 907 | AX77: 543 | AY77: 650 | AZ77: 900 | BA77: 1429 | BB77: =BA77 -> 1429 | BC77: 1401 | BD77: 1039 | BE77: 936 | BF77: 950 | BG77: =BF77 -> 950 | BH77: 808 | BI77: 864 | BJ77: 1046 | BK77: 1208 | BL77: =BK77 -> 1208 | BM77: 1081 | BN77: 1052 | BO77: 1083 | BP77: 2078 | BQ77: =BP77 -> 2078 | BR77: =2096 -> 2096 | BS77: 2048 | BT77: 1729 | BU77: 2221 | BV77: =BU77 -> 2221 | BW77: 2285 | BX77: 2128 | BY77: 1449 | BZ77: 2015 | CA77: =BZ77 -> 2015 | CB77: 2474 | CC77: 2875 | CD77: 2905 | CE77: 3059 | CF77: =CE77 -> 3059 | CG77: 3731 | CH77: 4839 | CI77: 3621 | CJ77: 3422 | CK77: =CJ77 -> 3422 | CL77: 3398 | CM77: 2821 | CN77: 2907 | CO77: 1486 | CP77: =CO77 -> 1486 | CQ77: 1477 | CR77: 1571 | CS77: 1722 | CT77: 1750 | CU77: =CT77 -> 1750 | CV77: 1879 | CW77: 1891 | CX77: 2250 | CY77: 2211 | CZ77: =CY77 -> 2211 | DA77: 2198 | DB77: 2158 | DC77: 2239 | DD77: 2332 | DE77: =DD77 -> 2332 | DF77: 2546 | DG77: 2212 | DH77: 2314 | DI77: 2318 | DJ77: =DI77 -> 2318 | DK77: 2260 | DL77: 2324 | DM77: 2350 | DN77: 2432 | DO77: =DN77 -> 2432 | DP77: 2405 | DQ77: 2462
B78: Long term debt | C78: 6123 | D78: 6103 | E78: 5980 | F78: 7567 | G78: 10866 | H78: 12589 | I78: 13299 | J78: 13107 | K78: 11084 | L78: 11050 | M78: =N78 -> 10879 | N78: 10879 | O78: 10782 | P78: 10223 | Q78: 10136 | R78: =S78 -> 9538 | S78: 9538 | T78: 9057 | U78: 8962 | V78: 8549 | W78: =X78 -> 8157 | X78: 8157 | Y78: 8149 | Z78: 8094 | AA78: 7555 | AB78: =AC78 -> 7455 | AC78: 7455 | AD78: 7428 | AE78: 7240 | AF78: 7217 | AG78: =AH78 -> 6952 | AH78: 6952 | AI78: 8742 | AJ78: 8700 | AK78: 10065 | AL78: 12217 | AM78: =AL78 -> 12217 | AN78: 11464 | AO78: 11439 | AP78: 11466 | AQ78: 11473 | AR78: =AQ78 -> 11473 | AS78: 10723 | AT78: 10324 | AU78: 10777 | AV78: 10018 | AW78: =AV78 -> 10018 | AX78: 8817 | AY78: 8735 | AZ78: 9014 | BA78: 8973 | BB78: =BA78 -> 8973 | BC78: 8254 | BD78: 8695 | BE78: 8677 | BF78: 8072 | BG78: =BF78 -> 8072 | BH78: 7275 | BI78: 7292 | BJ78: 7301 | BK78: 8141 | BL78: =BK78 -> 8141 | BM78: 8905 | BN78: 8904 | BO78: 8402 | BP78: 8730 | BQ78: =BP78 -> 8730 | BR78: 8721 | BS78: 9847 | BT78: 9824 | BU78: 9568 | BV78: =BU78 -> 9568 | BW78: 10432 | BX78: 10055 | BY78: 9780 | BZ78: 9782 | CA78: =BZ78 -> 9782 | CB78: 10471 | CC78: 10507 | CD78: 10487 | CE78: 10657 | CF78: =CE78 -> 10657 | CG78: 11363 | CH78: 14859 | CI78: 20298 | CJ78: 19962 | CK78: =CJ78 -> 19962 | CL78: 33754 | CM78: 58457 | CN78: 57325 | CO78: 61890 | CP78: =CO78 -> 61890 | CQ78: 57554 | CR78: 57025 | CS78: 57042 | CT78: 56806 | CU78: =CT78 -> 56806 | CV78: 55150 | CW78: 51794 | CX78: 51788 | CY78: 51811 | CZ78: =CY78 -> 51811 | DA78: 47465 | DB78: 47659 | DC78: 47381 | DD78: 47103 | DE78: =DD78 -> 47103 | DF78: 46877 | DG78: 53162 | DH78: 53176 | DI78: 52586 | DJ78: =DI78 -> 52586 | DK78: 45688 | DL78: 44604 | DM78: 44611 | DN78: 45637 | DO78: =DN78 -> 45637 | DP78: 44354 | DQ78: 41335
B79: Total liabilities | C79: =SUM(C74:C78)+C73 -> 25071 | D79: =SUM(D74:D78)+D73 -> 24356 | E79: =SUM(E74:E78)+E73 -> 24685 | F79: =SUM(F74:F78)+F73 -> 31008 | G79: =SUM(G74:G78)+G73 -> 37518 | H79: =SUM(H74:H78)+H73 -> 44646 | I79: =SUM(I74:I78)+I73 -> 44896 | J79: =SUM(J74:J78)+J73 -> 44941 | ... L79: =SUM(L74:L78)+L73 -> 45846 | M79: =N79 -> 42677 | N79: =SUM(N74:N78)+N73 -> 42677 | O79: =SUM(O74:O78)+O73 -> 45236 | P79: =SUM(P74:P78)+P73 -> 45362 | Q79: =SUM(Q74:Q78)+Q73 -> 48895 | R79: =S79 -> 48999 | S79: =SUM(S74:S78)+S73 -> 48999 | T79: =SUM(T74:T78)+T73 -> 49891 | U79: =SUM(U74:U78)+U73 -> 50900 | V79: =SUM(V74:V78)+V73 -> 50432 | W79: =X79 -> 47055 | X79: =SUM(X74:X78)+X73 -> 47055 | Y79: =SUM(Y74:Y78)+Y73 -> 45945 | Z79: =SUM(Z74:Z78)+Z73 -> 48029 | AA79: =SUM(AA74:AA78)+AA73 -> 48381 | AB79: =AC79 -> 49982 | AC79: =SUM(AC74:AC78)+AC73 -> 49982 | AD79: =SUM(AD74:AD78)+AD73 -> 51294 | AE79: =SUM(AE74:AE78)+AE73 -> 49916 | AF79: =SUM(AF74:AF78)+AF73 -> 47805 | AG79: =AH79 -> 55073 | AH79: =SUM(AH74:AH78)+AH73 -> 55073 | AI79: =SUM(AI74:AI78)+AI73 -> 55849 | AJ79: =SUM(AJ74:AJ78)+AJ73 -> 57378 | AK79: =SUM(AK74:AK78)+AK73 -> 59544 | AL79: =SUM(AL74:AL78)+AL73 -> 59828 | AM79: =SUM(AM74:AM78)+AM73 -> 59828 | AN79: =SUM(AN74:AN78)+AN73 -> 59931 | AO79: =SUM(AO74:AO78)+AO73 -> 60582 | ... DQ79: =SUM(DQ74:DQ78)+DQ73 -> 159755
B80: Common stock | C80: 5000 | D80: 5059 | E80: 5059 | F80: 5059 | G80: 5059 | H80: 5059 | I80: 5059 | J80: 5059 | K80: 5059 | L80: 5059 | M80: =N80 -> 5059 | N80: 5059 | O80: 5059 | P80: 5059 | Q80: 5061 | R80: =S80 -> 5061 | S80: 5061 | T80: 5061 | U80: 5061 | V80: 5061 | W80: =X80 -> 5061 | X80: 5061 | Y80: 5061 | Z80: 5061 | AA80: 5061 | AB80: =AC80 -> 5061 | AC80: 5061 | AD80: 5061 | AE80: 5061 | AF80: 5061 | AG80: =AH80 -> 5061 | AH80: 5061 | AI80: 5061 | AJ80: 5061 | AK80: 5061 | AL80: 5061 | AM80: =AL80 -> 5061 | AN80: 5061 | AO80: 5061 | AP80: 5061 | AQ80: 5061 | AR80: =AQ80 -> 5061 | AS80: 5061 | AT80: 5061 | AU80: 5061 | AV80: 5061 | AW80: =AV80 -> 5061 | AX80: 5061 | AY80: 5061 | AZ80: 5061 | BA80: 5061 | BB80: =BA80 -> 5061 | BC80: 5061 | BD80: 5061 | BE80: 5061 | BF80: 5061 | BG80: =BF80 -> 5061 | BH80: 5061 | BI80: 5061 | BJ80: 5061 | BK80: 5061 | BL80: =BK80 -> 5061 | BM80: 5061 | BN80: 5061 | BO80: 5061 | BP80: 5061 | BQ80: =BP80 -> 5061 | BR80: 5061 | BS80: 5061 | BT80: 5061 | BU80: 5061 | BV80: =BU80 -> 5061 | BW80: 5061 | BX80: 5061 | BY80: 5061 | BZ80: 5061 | CA80: =BZ80 -> 5061 | CB80: 5061 | CC80: 5061 | CD80: 5061 | CE80: 5061 | CF80: =CE80 -> 5061 | CG80: 5061 | CH80: 5061 | CI80: 5061 | CJ80: 5061 | CK80: =CJ80 -> 5061 | CL80: 5061 | CM80: 5061 | CN80: 5061 | CO80: 5061 | CP80: =CO80 -> 5061 | CQ80: 5061 | CR80: 5061 | CS80: 5061 | CT80: 5061 | CU80: =CT80 -> 5061 | CV80: 5061 | CW80: 5061 | CX80: 5061 | CY80: 5061 | CZ80: =CY80 -> 5061 | DA80: 5061 | DB80: 5061 | DC80: 5061 | DD80: 5061 | DE80: =DD80 -> 5061 | DF80: 5061 | DG80: 5061 | DH80: 5061 | DI80: 5061 | DJ80: =DI80 -> 5061 | DK80: 5061 | DL80: 5061 | DM80: 5061 | DN80: 5061 | DO80: =DN80 -> 5061 | DP80: 5061 | DQ80: 5061
B81: Additional paid in capital | C81: 1090 | D81: 1147 | E81: 1684 | F81: 2693 | G81: 1975 | H81: 2141 | I81: 2880 | J81: 2846 | K81: 3212 | L81: 3272 | M81: =N81 -> 3420 | N81: 3420 | O81: 3696 | P81: 4009 | Q81: 3840 | R81: =S81 -> 4371 | S81: 4371 | T81: 4643 | U81: 4564 | V81: 4313 | W81: =X81 -> 4655 | X81: 4655 | Y81: 4691 | Z81: 4899 | AA81: 5242 | AB81: =AC81 -> 4757 | AC81: 4757 | AD81: 4357 | AE81: 4093 | AF81: 3792 | AG81: =AH81 -> 3456 | AH81: 3456 | AI81: 3289 | AJ81: 3561 | AK81: 3956 | AL81: 3724 | AM81: =AL81 -> 3724 | AN81: 4264 | AO81: 3832 | AP81: 3826 | AQ81: 3866 | AR81: =AQ81 -> 3866 | AS81: 3903 | AT81: 3945 | AU81: 3988 | AV81: 4033 | AW81: =AV81 -> 4033 | AX81: 3977 | AY81: 4018 | AZ81: 4068 | BA81: 4122 | BB81: =BA81 -> 4122 | BC81: 4079 | BD81: 4181 | BE81: 4295 | BF81: 4415 | BG81: =BF81 -> 4415 | BH81: 4441 | BI81: 4524 | BJ81: 4572 | BK81: 4625 | BL81: =BK81 -> 4625 | BM81: 4657 | BN81: 4721 | BO81: 4771 | BP81: 4834 | BQ81: =BP81 -> 4834 | BR81: 4784 | BS81: 4778 | BT81: 4808 | BU81: 4762 | BV81: =BU81 -> 4762 | BW81: 4604 | BX81: 4644 | BY81: 6754 | BZ81: 6804 | CA81: =BZ81 -> 6804 | CB81: 6624 | CC81: 6676 | CD81: 6714 | CE81: 6768 | CF81: =CE81 -> 6768 | CG81: 6573 | CH81: 6638 | CI81: 6688 | CJ81: 6745 | CK81: =CJ81 -> 6745 | CL81: 6595 | CM81: 6648 | CN81: 6687 | CO81: 7787 | CP81: =CO81 -> 7787 | CQ81: 8155 | CR81: 8481 | CS81: 8796 | CT81: 9052 | CU81: =CT81 -> 9052 | CV81: 9295 | CW81: 9475 | CX81: 9705 | CY81: 9947 | CZ81: =CY81 -> 9947 | DA81: 10298 | DB81: 10310 | DC81: 10616 | DD81: 10309 | DE81: =DD81 -> 10309 | DF81: 10539 | DG81: 10727 | DH81: 10925 | DI81: 18964 | DJ81: =DI81 -> 18964 | DK81: 19008 | DL81: 19238 | DM81: 19218 | DN81: 21441 | DO81: =DN81 -> 21441 | DP81: 21671 | DQ81: 21949
B82: Retained earnings | C82: 8147 | D82: 8706 | E82: 10487 | F82: 12090 | G82: 14340 | H82: 14262 | I82: 14407 | J82: 15030 | K82: 15300 | L82: 15756 | M82: =N82 -> 15565 | N82: 15565 | O82: 16101 | P82: 16251 | Q82: 17264 | R82: =S82 -> 17276 | S82: 17276 | T82: 17953 | U82: 17293 | V82: 17989 | W82: =X82 -> 18453 | X82: 18453 | Y82: 19319 | Z82: 19810 | AA82: 20920 | AB82: =AC82 -> 21376 | AC82: 21376 | AD82: 22409 | AE82: 22669 | AF82: 23360 | AG82: =AH82 -> 22675 | AH82: 22675 | AI82: 23284 | AJ82: 23668 | AK82: 22104 | AL82: 22746 | AM82: =AL82 -> 22746 | AN82: 23265 | AO82: 23409 | AP82: 24244 | AQ82: 24784 | AR82: =AQ82 -> 24784 | AS82: 25370 | AT82: 25681 | AU82: 26779 | AV82: 27524 | AW82: =AV82 -> 27524 | AX82: 28447 | AY82: 28743 | AZ82: 29775 | BA82: 30037 | BB82: =BA82 -> 30037 | BC82: 31143 | BD82: 31490 | BE82: 32647 | BF82: 32964 | BG82: =BF82 -> 32964 | BH82: 33929 | BI82: 34516 | BJ82: 35880 | BK82: 36180 | BL82: =BK82 -> 36180 | BM82: 37516 | BN82: 37365 | BO82: 39069 | BP82: 38756 | BQ82: =BP82 -> 38756 | BR82: 39975 | BS82: 38362 | BT82: 40641 | BU82: 40714 | BV82: =BU82 -> 40714 | BW82: 42165 | BX82: 42222 | BY82: 44052 | BZ82: 45320 | CA82: =BZ82 -> 45320 | CB82: 52095 | CC82: 52303 | CD82: 54666 | CE82: 55941 | CF82: =CE82 -> 55941 | CG82: 58090 | CH82: 52819 | CI82: 53986 | CJ82: 50644 | CK82: =CJ82 -> 50644 | CL82: 49854 | CM82: 47478 | CN82: 47029 | CO82: 38610 | CP82: =CO82 -> 38610 | CQ82: 38073 | CR82: 38660 | CS82: 38551 | CT82: 34408 | CU82: =CT82 -> 34408 | CV82: 33189 | CW82: 33382 | CX82: 30107 | CY82: 29473 | CZ82: =CY82 -> 29473 | DA82: 29059 | DB82: 28910 | DC82: 27274 | DD82: 27251 | DE82: =DD82 -> 27251 | DF82: 26908 | DG82: 25469 | DH82: 19299 | DI82: 15362 | DJ82: =DI82 -> 15362 | DK82: 15239 | DL82: 14542 | DM82: 9118 | DN82: 17252 | DO82: =DN82 -> 17252 | DP82: 17162 | DQ82: 16632
B83: Accumulated other comprehensive loss | C83: -20 | D83: =-23-17 -> -40 | E83: =6-12 -> -6 | F83: =-2-7 -> -9 | G83: =-485-3 -> -488 | H83: -4045 | I83: -4145 | J83: -4143 | K83: -4152 | L83: -4141 | M83: =N83 -> -1925 | N83: -1925 | O83: -1939 | P83: -1973 | Q83: -3713 | R83: =S83 -> -1778 | S83: -1778 | T83: -1808 | U83: -1729 | V83: -1761 | W83: =X83 -> -8217 | X83: -8217 | Y83: -8021 | Z83: -7800 | AA83: -7569 | AB83: =AC83 -> -4596 | AC83: -4596 | AD83: -4423 | AE83: -4299 | AF83: -4466 | AG83: =AH83 -> -13525 | AH83: -13525 | AI83: -13511 | AJ83: -13120 | AK83: -12821 | AL83: -11877 | AM83: =AL83 -> -11877 | AN83: -11747 | AO83: -11744 | AP83: -11375 | AQ83: -13758 | AR83: =AQ83 -> -13758 | AS83: -13401 | AT83: -13095 | AU83: -13146 | AV83: -16500 | AW83: =AV83 -> -16500 | AX83: -16364 | AY83: -15816 | AZ83: -15261 | BA83: -17416 | BB83: =BA83 -> -17416 | BC83: -17041 | BD83: -16412 | BE83: -16187 | BF83: -9894 | BG83: =BF83 -> -9894 | BH83: -8883 | BI83: -8659 | BJ83: -8653 | BK83: -13903 | BL83: =BK83 -> -13903 | BM83: -13815 | BN83: -13420 | BO83: -13263 | BP83: -12748 | BQ83: =BP83 -> -12748 | BR83: -12838 | BS83: -12795 | BT83: -12658 | BU83: -13623 | BV83: =BU83 -> -13623 | BW83: -13415 | BX83: -13234 | BY83: -13036 | BZ83: -13376 | CA83: =BZ83 -> -13376 | CB83: -16162 | CC83: -16139 | CD83: -15949 | CE83: -15083 | CF83: =CE83 -> -15083 | CG83: -14969 | CH83: -14908 | CI83: -14927 | CJ83: -16153 | CK83: =CJ83 -> -16153 | CL83: -16333 | CM83: -16025 | CN83: -15779 | CO83: -17133 | CP83: =CO83 -> -17133 | CQ83: -16952 | CR83: -16661 | CS83: -14818 | CT83: -11659 | CU83: =CT83 -> -11659 | CV83: -11370 | CW83: -11487 | CX83: -11518 | CY83: -9550 | CZ83: =CY83 -> -9550 | DA83: -9550 | DB83: -9617 | DC83: -9708 | DD83: -10305 | DE83: =DD83 -> -10305 | DF83: -10412 | DG83: -10392 | DH83: -10273 | DI83: -10915 | DJ83: =DI83 -> -10915 | DK83: -10760 | DL83: -10539 | DM83: -10544 | DN83: -10277 | DO83: =DN83 -> -10277 | DP83: -10266 | DQ83: -10132
B84: Treasury stock | C84: -9 | D84: -1321 | E84: -4161 | F84: -6221 | G84: -8509 | H84: -8397 | I84: -8322 | J84: -8244 | K84: -8359 | L84: -8411 | M84: =N84 -> -8810 | N84: -8810 | O84: -9154 | P84: -9637 | Q84: -10365 | R84: =S84 -> -11075 | S84: -11075 | T84: -11217 | U84: -11537 | V84: -12134 | W84: =X84 -> -12459 | X84: -12459 | Y84: -12667 | Z84: -13131 | AA84: -13964 | AB84: =AC84 -> -14842 | AC84: -14842 | AD84: -16006 | AE84: -16834 | AF84: -17425 | AG84: =AH84 -> -17758 | AH84: -17758 | AI84: -17756 | AJ84: -17741 | AK84: -17733 | AL84: -15911 | AM84: =AL84 -> -15911 | AN84: -15744 | AO84: -15582 | AP84: -17302 | AQ84: -17187 | AR84: =AQ84 -> -17187 | AS84: -17021 | AT84: -16859 | AU84: -16715 | AV84: -16603 | AW84: =AV84 -> -16603 | AX84: -16094 | AY84: -16202 | AZ84: -16055 | BA84: -15937 | BB84: =BA84 -> -15937 | BC84: -15780 | BD84: -16794 | BE84: -16865 | BF84: -17671 | BG84: =BF84 -> -17671 | BH84: -20028 | BI84: -21381 | BJ84: -22349 | BK84: -23298 | BL84: =BK84 -> -23298 | BM84: -25513 | BN84: -27463 | BO84: -28898 | BP84: -29568 | BQ84: =BP84 -> -29568 | BR84: -32939 | BS84: -34821 | BT84: -35763 | BU84: -36097 | BV84: =BU84 -> -36097 | BW84: -38320 | BX84: -40730 | BY84: -41745 | BZ84: -43454 | CA84: =BZ84 -> -43454 | CB84: -46396 | CC84: -49342 | CD84: -51781 | CE84: -52348 | CF84: =CE84 -> -52348 | CG84: -54630 | CH84: -54932 | CI84: -54924 | CJ84: -54914 | CK84: =CJ84 -> -54914 | CL84: -54842 | CM84: -54829 | CN84: -54819 | CO84: -52641 | CP84: =CO84 -> -52641 | CQ84: -52395 | CR84: -52223 | CS84: -52030 | CT84: -51861 | CU84: =CT84 -> -51861 | CV84: -51573 | CW84: -51319 | CX84: -51054 | CY84: -50814 | CZ84: =CY84 -> -50814 | DA84: -50376 | DB84: -50181 | DC84: -49972 | DD84: -49549 | DE84: =DD84 -> -49549 | DF84: -49105 | DG84: -48841 | DH84: -48564 | DI84: -32386 | DJ84: =DI84 -> -32386 | DK84: -31879 | DL84: -31603 | DM84: -31109 | DN84: -28029 | DO84: =DN84 -> -28029 | DP84: -27647 | DQ84: -27416
B85: Share Value Trust shares | C85: -1255 | D85: -1235 | E85: -1601 | F85: -2592 | G85: -1552 | H85: -1324 | I85: -1740 | J85: -1689 | K85: -2111 | L85: -1993 | M85: =N85 -> -2023 | N85: -2023 | O85: -2285 | P85: -2577 | Q85: -2664 | R85: =S85 -> -2796 | S85: -2796 | T85: -3115 | U85: -3283 | V85: -2442 | W85: =X85 -> -2754 | X85: -2754 | Y85: -2772 | Z85: -2982 | AA85: -3284 | AB85: =AC85 -> -2752 | AC85: -2752 | AD85: -2332 | AE85: -2096 | AF85: -1608 | AG85: =AH85 -> -1203 | AH85: -1203 | AI85: -1029 | AJ85: -1249 | AK85: -1595 | AL85: -1615 | AM85: =AL85 -> -1615 | AN85: -2157 | AO85: -1899 | AP85: 0 | AQ85: 0 | AR85: =AQ85 -> 0 | AS85: 0 | AT85: 0 | AU85: 0 | AV85: 0 | AW85: =AV85 -> 0 | AX85: 0 | AY85: 0 | AZ85: 0 | BA85: 0 | BB85: =BA85 -> 0 | BC85: 0 | BD85: 0 | BE85: 0 | BF85: 0 | BG85: =BF85 -> 0 | BL85: =BK85 -> 0 | BQ85: =BP85 -> 0 | BR85: 0 | BS85: 0 | BT85: 0 | BU85: 0 | BV85: =BU85 -> 0 | BW85: 0 | BX85: 0 | BY85: 0 | BZ85: 0 | CA85: =BZ85 -> 0 | CB85: 0 | CC85: 0 | CD85: 0 | CE85: 0 | CF85: =CE85 -> 0 | CG85: 0 | CH85: 0 | CI85: 0 | CJ85: 0 | CK85: =CJ85 -> 0 | CL85: 0 | CM85: 0 | CN85: 0 | CO85: 0 | CP85: =CO85 -> 0 | CQ85: 0 | CR85: 0 | CS85: 0 | CT85: 0 | CU85: =CT85 -> 0 | CV85: 0 | CW85: 0 | CX85: 0 | CY85: 0 | CZ85: =CY85 -> 0 | DA85: 0 | DB85: 0 | DC85: 0 | DD85: 0 | DE85: =DD85 -> 0 | DF85: 0 | DG85: 0 | DH85: 0 | DI85: 6 | DJ85: =DI85 -> 6 | DK85: 6 | DL85: 6 | DM85: 6 | DN85: 6 | DO85: =DN85 -> 6 | DP85: 6 | DQ85: 6
B86: Total Boeing's shareholder's equity | C86: =SUM(C80:C85) -> 12953 | D86: =SUM(D80:D85) -> 12316 | E86: =SUM(E80:E85) -> 11462 | F86: =SUM(F80:F85) -> 11020 | G86: =SUM(G80:G85) -> 10825 | H86: =SUM(H80:H85) -> 7696 | I86: =SUM(I80:I85) -> 8139 | J86: =SUM(J80:J85) -> 8859 | ... L86: =SUM(L80:L85) -> 9542 | M86: =N86 -> 11286 | N86: =SUM(N80:N85) -> 11286 | O86: =SUM(O80:O85) -> 11478 | P86: =SUM(P80:P85) -> 11132 | Q86: =SUM(Q80:Q85) -> 9423 | R86: =S86 -> 11059 | S86: =SUM(S80:S85) -> 11059 | T86: =SUM(T80:T85) -> 11517 | U86: =SUM(U80:U85) -> 10369 | V86: =SUM(V80:V85) -> 11026 | W86: =X86 -> 4739 | X86: =SUM(X80:X85) -> 4739 | Y86: =SUM(Y80:Y85) -> 5611 | Z86: =SUM(Z80:Z85) -> 5857 | AA86: =SUM(AA80:AA85) -> 6406 | AB86: =AC86 -> 9004 | AC86: =SUM(AC80:AC85) -> 9004 | AD86: =SUM(AD80:AD85) -> 9066 | AE86: =SUM(AE80:AE85) -> 8594 | AF86: =SUM(AF80:AF85) -> 8714 | AG86: =AH86 -> -1294 | AH86: =SUM(AH80:AH85) -> -1294 | AI86: =SUM(AI80:AI85) -> -662 | AJ86: =SUM(AJ80:AJ85) -> 180 | AK86: =SUM(AK80:AK85) -> -1028 | AL86: =SUM(AL80:AL85) -> 2128 | AM86: =SUM(AM80:AM85) -> 2128 | AN86: =SUM(AN80:AN85) -> 2942 | AO86: =SUM(AO80:AO85) -> 3077 | ... DQ86: =SUM(DQ80:DQ85) -> 6100
B87: Non controlling interest | C87: 0 | D87: 0 | E87: 0 | F87: 0 | G87: 0 | H87: 0 | I87: 0 | J87: 0 | K87: 0 | L87: 0 | M87: =N87 -> 0 | N87: 0 | O87: 0 | P87: 0 | Q87: 0 | R87: =S87 -> 0 | S87: 0 | T87: 0 | U87: 0 | V87: 0 | W87: =X87 -> 0 | X87: 0 | Y87: 0 | Z87: 0 | AA87: 0 | AB87: =AC87 -> 0 | AC87: 0 | AD87: 0 | AE87: 0 | AF87: 0 | AG87: =AH87 -> 0 | AH87: 0 | AI87: 153 | AJ87: 154 | AK87: 151 | AL87: 97 | AM87: =AL87 -> 97 | AN87: 97 | AO87: 96 | AP87: 98 | AQ87: 96 | AR87: =AQ87 -> 96 | AS87: 95 | AT87: 91 | AU87: 94 | AV87: 93 | AW87: =AV87 -> 93 | AX87: 93 | AY87: 88 | AZ87: 94 | BA87: 100 | BB87: =BA87 -> 100 | BC87: 98 | BD87: 106 | BE87: 116 | BF87: 122 | BG87: =BF87 -> 122 | BH87: 113 | BI87: 123 | BJ87: 126 | BK87: 125 | BL87: =BK87 -> 125 | BM87: 124 | BN87: 43 | BO87: 46 | BP87: 62 | BQ87: =BP87 -> 62 | BR87: 63 | BS87: 62 | BT87: 61 | BU87: 60 | BV87: =BU87 -> 60 | BW87: 60 | BX87: 59 | BY87: 59 | BZ87: 57 | CA87: =BZ87 -> 57 | CB87: 76 | CC87: 67 | CD87: 80 | CE87: 71 | CF87: =CE87 -> 71 | CG87: 107 | CH87: 379 | CI87: 307 | CJ87: 317 | CK87: =CJ87 -> 317 | CL87: 305 | CM87: 285 | CN87: 268 | CO87: 241 | CP87: =CO87 -> 241 | CQ87: 217 | CR87: 197 | CS87: 174 | CT87: 153 | CU87: =CT87 -> 153 | CV87: 130 | CW87: 97 | CX87: 64 | CY87: 35 | CZ87: =CY87 -> 35 | DA87: 24 | DB87: 24 | DC87: 12 | DD87: 5 | DE87: =DD87 -> 5 | DF87: -7 | DG87: -6 | DH87: -10 | DI87: -6 | DJ87: =DI87 -> -6 | DK87: 0 | DL87: -1 | DM87: -3 | DN87: 3 | DO87: =DN87 -> 3 | DP87: 0 | DQ87: 15
B88: Total shareholder's equity | C88: =C87+C86 -> 12953 | D88: =D87+D86 -> 12316 | E88: =E87+E86 -> 11462 | F88: =F87+F86 -> 11020 | G88: =G87+G86 -> 10825 | H88: =H87+H86 -> 7696 | I88: =I87+I86 -> 8139 | J88: =J87+J86 -> 8859 | ... L88: =L87+L86 -> 9542 | M88: =N88 -> 11286 | N88: =N87+N86 -> 11286 | O88: =O87+O86 -> 11478 | P88: =P87+P86 -> 11132 | Q88: =Q87+Q86 -> 9423 | R88: =S88 -> 11059 | S88: =S87+S86 -> 11059 | T88: =T87+T86 -> 11517 | U88: =U87+U86 -> 10369 | V88: =V87+V86 -> 11026 | W88: =X88 -> 4739 | X88: =X87+X86 -> 4739 | Y88: =Y87+Y86 -> 5611 | Z88: =Z87+Z86 -> 5857 | AA88: =AA87+AA86 -> 6406 | AB88: =AC88 -> 9004 | AC88: =AC87+AC86 -> 9004 | AD88: =AD87+AD86 -> 9066 | AE88: =AE87+AE86 -> 8594 | AF88: =AF87+AF86 -> 8714 | AG88: =AH88 -> -1294 | AH88: =AH87+AH86 -> -1294 | AI88: =AI87+AI86 -> -509 | AJ88: =AJ87+AJ86 -> 334 | AK88: =AK87+AK86 -> -877 | AL88: =AL87+AL86 -> 2225 | AM88: =AM87+AM86 -> 2225 | AN88: =AN87+AN86 -> 3039 | AO88: =AO87+AO86 -> 3173 | ... DQ88: =DQ87+DQ86 -> 6115
B89: Total liabilities and shareholder's equity | C89: =SUM(C88,C79) -> 38024 | D89: =SUM(D88,D79) -> 36672 | E89: =SUM(E88,E79) -> 36147 | F89: =SUM(F88,F79) -> 42028 | G89: =SUM(G88,G79) -> 48343 | H89: =SUM(H88,H79) -> 52342 | I89: =SUM(I88,I79) -> 53035 | J89: =SUM(J88,J79) -> 53800 | ... L89: =SUM(L88,L79) -> 55388 | M89: =N89 -> 53963 | N89: =SUM(N88,N79) -> 53963 | O89: =SUM(O88,O79) -> 56714 | P89: =SUM(P88,P79) -> 56494 | Q89: =SUM(Q88,Q79) -> 58318 | R89: =S89 -> 60058 | S89: =SUM(S88,S79) -> 60058 | T89: =SUM(T88,T79) -> 61408 | U89: =SUM(U88,U79) -> 61269 | V89: =SUM(V88,V79) -> 61458 | W89: =X89 -> 51794 | X89: =SUM(X88,X79) -> 51794 | Y89: =SUM(Y88,Y79) -> 51556 | Z89: =SUM(Z88,Z79) -> 53886 | AA89: =SUM(AA88,AA79) -> 54787 | AB89: =AC89 -> 58986 | AC89: =SUM(AC88,AC79) -> 58986 | AD89: =SUM(AD88,AD79) -> 60360 | AE89: =SUM(AE88,AE79) -> 58510 | AF89: =SUM(AF88,AF79) -> 56519 | AG89: =AH89 -> 53779 | AH89: =SUM(AH88,AH79) -> 53779 | AI89: =SUM(AI88,AI79) -> 55340 | AJ89: =SUM(AJ88,AJ79) -> 57712 | AK89: =SUM(AK88,AK79) -> 58667 | AL89: =SUM(AL88,AL79) -> 62053 | AM89: =SUM(AM88,AM79) -> 62053 | AN89: =SUM(AN88,AN79) -> 62970 | AO89: =SUM(AO88,AO79) -> 63755 | ... DQ89: =SUM(DQ88,DQ79) -> 165870
C92: =IF(ROUND(C89,2)=ROUND(C64,2),"","check") | D92: =IF(ROUND(D89,2)=ROUND(D64,2),"","check") | E92: =IF(ROUND(E89,2)=ROUND(E64,2),"","check") | F92: =IF(ROUND(F89,2)=ROUND(F64,2),"","check") | G92: =IF(ROUND(G89,2)=ROUND(G64,2),"","check") | H92: =IF(ROUND(H89,2)=ROUND(H64,2),"","check") | I92: =IF(ROUND(I89,2)=ROUND(I64,2),"","check") | J92: =IF(ROUND(J89,2)=ROUND(J64,2),"","check") | ... AK92: =IF(ROUND(AK89,2)=ROUND(AK64,2),"","check")
B94: Cash Flow YTD
B95: Operating activities
B96: Net income | C96: -178 | D96: 1120 | E96: 2309 | F96: 2128 | G96: 2827 | H96: 492 | I96: 718 | J96: 623 | K96: 1230 | L96: 1686 | M96: =N96 -> 1872 | N96: 1872 | O96: 535 | P96: 1101 | Q96: 2112 | R96: =S96 -> 2572 | S96: 2572 | T96: 692 | U96: 532 | V96: 1226 | W96: =X96 -> 2215 | X96: 2215 | Y96: 877 | Z96: 1927 | AA96: 3041 | AB96: =AC96 -> 4074 | AC96: 4074 | AD96: 1211 | AE96: 2063 | AF96: 2758 | AG96: =AH96 -> 2672 | AH96: 2672 | AI96: 610 | AJ96: 1608 | AK96: 44 | AL96: 1312 | AM96: =AL96 -> 1312 | AN96: 519 | AO96: 1306 | AP96: 2143 | AQ96: 3307 | AR96: =AQ96 -> 3307 | AS96: 586 | AT96: 1527 | AU96: 2625 | AV96: 4018 | AW96: =AV96 -> 4018 | AX96: 923 | AY96: 1890 | AZ96: 2922 | BA96: 3900 | BB96: =BA96 -> 3900 | BC96: 1106 | BD96: 2194 | BE96: 3352 | BF96: 4585 | BG96: =BF96 -> 4585 | BH96: 965 | BI96: 2618 | BJ96: 3980 | BK96: 5446 | BL96: =BK96 -> 5446 | BM96: 1336 | BN96: 2446 | BO96: 4150 | BP96: 5176 | BQ96: =BP96 -> 5176 | BR96: 1219 | BS96: 985 | BT96: 3264 | BU96: 4895 | BV96: =BU96 -> 4895 | BW96: 1451 | BX96: 3212 | BY96: 5065 | BZ96: 8197 | CA96: =BZ96 -> 8197 | CB96: 2477 | CC96: 4673 | CD96: 7036 | CE96: 10460 | CF96: =CE96 -> 10460 | CG96: 2149 | CH96: -793 | CI96: 374 | CJ96: -636 | CK96: =CJ96 -> -636 | CL96: -641 | CM96: -3036 | CN96: -3502 | CO96: -11941 | CP96: =CO96 -> -11941 | CQ96: -561 | CR96: 6 | CS96: -126 | CT96: -4290 | CU96: =CT96 -> -4290 | CV96: -1242 | CW96: -1082 | CX96: -4390 | CY96: -5053 | CZ96: =CY96 -> -5053 | DA96: -425 | DB96: -574 | DC96: -2212 | DD96: -2242 | DE96: =DD96 -> -2242 | DF96: -355 | DG96: -1794 | DH96: -7968 | DI96: -11829 | DJ96: =DI96 -> -11829 | DK96: -31 | DL96: -643 | DM96: -5982 | DN96: 2238 | DO96: =DN96 -> 2238 | DP96: -7 | DQ96: -435
B97: Share based plan expense | C97: -99 | D97: 153 | E97: 209 | F97: 316 | G97: 378 | H97: 447 | I97: 456 | J97: 119 | K97: 283 | L97: 449 | M97: =N97 -> 576 | N97: 576 | O97: 245 | P97: 446 | Q97: 692 | R97: =S97 -> 852 | S97: 852 | T97: 202 | U97: 452 | V97: 553 | W97: =X97 -> 743 | X97: 743 | Y97: 48 | Z97: 191 | AA97: 266 | AB97: =AC97 -> 287 | AC97: 287 | AD97: 45 | AE97: 98 | AF97: 159 | AG97: =AH97 -> 209 | AH97: 209 | AI97: 60 | AJ97: 121 | AK97: 180 | AL97: 238 | AM97: =AL97 -> 238 | AN97: 66 | AO97: 130 | AP97: 172 | AQ97: 215 | AR97: =AQ97 -> 215 | AS97: 51 | AT97: 96 | AU97: 141 | AV97: 186 | AW97: =AV97 -> 186 | AX97: 50 | AY97: 99 | AZ97: 148 | BA97: 193 | BB97: =BA97 -> 193 | BC97: 58 | BD97: 107 | BE97: 156 | BF97: 206 | BG97: =BF97 -> 206 | BH97: 52 | BI97: 101 | BJ97: 152 | BK97: 195 | BL97: =BK97 -> 195 | BM97: 50 | BN97: 94 | BO97: 141 | BP97: 189 | BQ97: =BP97 -> 189 | BR97: 51 | BS97: 97 | BT97: 144 | BU97: 190 | BV97: =BU97 -> 190 | BW97: 50 | BX97: 98 | BY97: 151 | BZ97: 202 | CA97: =BZ97 -> 202 | CB97: 45 | CC97: 98 | CD97: 150 | CE97: 202 | CF97: =CE97 -> 202 | CG97: 47 | CH97: 104 | CI97: 160 | CJ97: 212 | CK97: =CJ97 -> 212 | CL97: 55 | CM97: 115 | CN97: 165 | CO97: 250 | CP97: =CO97 -> 250 | CQ97: 321 | CR97: 493 | CS97: 677 | CT97: 833 | CU97: =CT97 -> 833 | CV97: 203 | CW97: 352 | CX97: 528 | CY97: 725 | CZ97: =CY97 -> 725 | DA97: 222 | DB97: 381 | DC97: 548 | DD97: 690 | DE97: =DD97 -> 690 | DF97: 119 | DG97: 208 | DH97: 310 | DI97: 407 | DJ97: =DI97 -> 407 | DK97: 135 | DL97: 254 | DM97: 343 | DN97: 426 | DO97: =DN97 -> 426 | DP97: 161 | DQ97: 264
B98: Depreciation | C98: 1354 | D98: 1517 | E98: 1538 | F98: 1317 | G98: 1448 | H98: 1409 | I98: 1356 | J98: 327 | K98: 634 | L98: 934 | M98: =N98 -> 1412 | N98: 1412 | O98: 332 | P98: 711 | Q98: 1061 | R98: =S98 -> 1412 | S98: 1412 | T98: 350 | U98: 714 | V98: 1057 | W98: =X98 -> 1445 | X98: 1445 | Y98: 319 | Z98: 676 | AA98: 975 | AB98: =AC98 -> 1334 | AC98: 1334 | AD98: 322 | AE98: 643 | AF98: 952 | AG98: =AH98 -> 1325 | AH98: 1325 | AI98: 335 | AJ98: 666 | AK98: 1047 | AL98: 1459 | AM98: =AL98 -> 1459 | AN98: 350 | AO98: 743 | AP98: 1101 | AQ98: 1510 | AR98: =AQ98 -> 1510 | AS98: 331 | AT98: 710 | AU98: 1075 | AV98: 1457 | AW98: =AV98 -> 1457 | AX98: 426 | AY98: 848 | AZ98: 1313 | BA98: 1811 | BB98: =BA98 -> 1811 | BC98: 429 | BD98: 865 | BE98: 1323 | BF98: 1844 | BG98: =BF98 -> 1844 | BH98: 448 | BI98: 900 | BJ98: 1378 | BK98: 1906 | BL98: =BK98 -> 1906 | BM98: 459 | BN98: 912 | BO98: 1349 | BP98: 1833 | BQ98: =BP98 -> 1833 | BR98: 443 | BS98: 890 | BT98: 1364 | BU98: 1910 | BV98: =BU98 -> 1910 | BW98: 471 | BX98: 965 | BY98: 1487 | BZ98: 2069 | CA98: =BZ98 -> 2069 | CB98: 501 | CC98: 1008 | CD98: 1531 | CE98: 2114 | CF98: =CE98 -> 2114 | CG98: 521 | CH98: 1067 | CI98: 1643 | CJ98: 2271 | CK98: =CJ98 -> 2271 | CL98: 556 | CM98: 1103 | CN98: 1668 | CO98: 2246 | CP98: =CO98 -> 2246 | CQ98: 536 | CR98: 1087 | CS98: 1610 | CT98: 2144 | CU98: =CT98 -> 2144 | CV98: 486 | CW98: 984 | CX98: 1477 | CY98: 1979 | CZ98: =CY98 -> 1979 | DA98: 457 | DB98: 913 | DC98: 1380 | DD98: 1861 | DE98: =DD98 -> 1861 | DF98: 442 | DG98: 883 | DH98: 1327 | DI98: 1836 | DJ98: =DI98 -> 1836 | DK98: 466 | DL98: 926 | DM98: 1417 | DN98: 1953 | DO98: =DN98 -> 1953 | DP98: 573 | DQ98: 1169
B99: Amortization of other acquired intangibles | C99: 104 | D99: 105 | E99: 107 | F99: 162 | G99: 302 | H99: 88 | I99: 94 | J99: 23 | K99: 46 | L99: 72 | M99: =N99 -> 97 | N99: 97 | O99: 23 | P99: 47 | Q99: 69 | R99: =S99 -> 91 | S99: 91 | T99: 19 | U99: 40 | V99: 66 | W99: =X99 -> 100 | X99: 100 | Y99: 37 | Z99: 77 | AA99: 116 | AB99: =AC99 -> 152 | AC99: 152 | AD99: 40 | AE99: 81 | AF99: 122 | AG99: =AH99 -> 166 | AH99: 166 | AI99: 49 | AJ99: 99 | AK99: 152 | AL99: 207 | AM99: =AL99 -> 207 | AN99: 55 | AO99: 111 | AP99: 169 | AQ99: 217 | AR99: =AQ99 -> 217 | AS99: 49 | AT99: 99 | AU99: 151 | AV99: 203 | AW99: =AV99 -> 203 | BB99: =BA99 -> 0 | BG99: =BF99 -> 0 | BL99: =BK99 -> 0 | BQ99: =BP99 -> 0 | BV99: =BU99 -> 0 | CA99: =BZ99 -> 0
B100: Amortization of debt and issuance costs | C100: 0 | D100: 0 | E100: 0 | F100: 0 | G100: 0 | H100: 12 | I100: 18 | J100: 4 | K100: 8 | L100: 12 | M100: =N100 -> 15 | N100: 15 | O100: 7 | P100: 13 | Q100: 19 | R100: =S100 -> 23 | S100: 23 | T100: 3 | U100: 10 | V100: 12 | W100: =X100 -> 14 | X100: 14 | Y100: 3 | Z100: 6 | AA100: 7 | AB100: =AC100 -> -1 | AC100: -1 | AD100: 2 | AE100: 4 | AF100: 8 | AG100: =AH100 -> 11 | AH100: 11 | AI100: 2 | AJ100: 4 | AK100: 7 | AL100: 12 | AM100: =AL100 -> 12 | AN100: 5 | AO100: 10 | AP100: 15 | AQ100: 19 | AR100: =AQ100 -> 19 | AS100: 4 | AT100: 7 | AU100: 11 | AV100: 15 | AW100: =AV100 -> 15 | BB100: =BA100 -> 0 | BG100: =BF100 -> 0 | BL100: =BK100 -> 0 | BQ100: =BP100 -> 0 | BV100: =BU100 -> 0 | CA100: =BZ100 -> 0
B101: Investment/asset impairment charges, net | C101: 0 | D101: 0 | E101: 0 | F101: 0 | G101: 0 | H101: 357 | I101: 155 | J101: 25 | K101: 60 | L101: 78 | M101: =N101 -> 122 | N101: 122 | O101: 58 | P101: 44 | Q101: 65 | R101: =S101 -> 83 | S101: 83 | T101: -2 | U101: 19 | V101: 85 | W101: =X101 -> 118 | X101: 118 | Y101: 0 | Z101: 5 | AA101: 5 | AB101: =AC101 -> 51 | AC101: 51 | AD101: 0 | AE101: 0 | AF101: 21 | AG101: =AH101 -> 50 | AH101: 50 | AI101: 21 | AJ101: 50 | AK101: 66 | AL101: 151 | AM101: =AL101 -> 151 | AN101: 15 | AO101: 20 | AP101: 127 | AQ101: 174 | AR101: =AQ101 -> 174 | AS101: 10 | AT101: 16 | AU101: 50 | AV101: 119 | AW101: =AV101 -> 119 | AX101: 36 | AY101: 45 | AZ101: 59 | BA101: 84 | BB101: =BA101 -> 84 | BC101: 26 | BD101: 26 | BE101: 38 | BF101: 96 | BG101: =BF101 -> 96 | BH101: 29 | BI101: 36 | BJ101: 140 | BK101: 229 | BL101: =BK101 -> 229 | BM101: 17 | BN101: 74 | BO101: 124 | BP101: 167 | BQ101: =BP101 -> 167 | BR101: 33 | BS101: 50 | BT101: 61 | BU101: 90 | BV101: =BU101 -> 90 | BW101: 23 | BX101: 46 | BY101: 75 | BZ101: 113 | CA101: =BZ101 -> 113 | CB101: 20 | CC101: 44 | CD101: 63 | CE101: 93 | CF101: =CE101 -> 93 | CG101: 34 | CH101: 70 | CI101: 106 | CJ101: 443 | CK101: =CJ101 -> 443 | CL101: 26 | CM101: 280 | CN101: 317 | CO101: 410 | CP101: =CO101 -> 410 | CQ101: 16 | CR101: 38 | CS101: 72 | CT101: 98 | CU101: =CT101 -> 98 | CV101: 72 | CW101: 72 | CX101: 78 | CY101: 112 | CZ101: =CY101 -> 112 | DA101: 11 | DB101: 12 | DC101: 12 | DD101: 46 | DE101: =DD101 -> 46 | DF101: 21 | DG101: 34 | DH101: 48 | DI101: 112 | DJ101: =DI101 -> 112 | DK101: 7 | DL101: 30 | DM101: 32 | DN101: 45 | DO101: =DN101 -> 45 | DP101: 9 | DQ101: 18
B102: Customer financing valuation provision/(benefit) | C102: 0 | D102: 0 | E102: 72 | F102: 13 | G102: 42 | H102: 219 | I102: 234 | J102: 44 | K102: 39 | L102: 36 | M102: =N102 -> 45 | N102: 45 | O102: 4 | P102: 14 | Q102: 47 | R102: =S102 -> 73 | S102: 73 | T102: -1 | U102: 2 | V102: 19 | W102: =X102 -> 32 | X102: 32 | Y102: -33 | Z102: -35 | AA102: -52 | AB102: =AC102 -> -60 | AC102: -60 | AD102: -6 | AE102: 80 | AF102: 73 | AG102: =AH102 -> 84 | AH102: 84 | AI102: 9 | AJ102: 12 | AK102: 31 | AL102: 45 | AM102: =AL102 -> 45 | AN102: 12 | AO102: 5 | AP102: 24 | AQ102: 51 | AR102: =AQ102 -> 51 | AS102: -15 | AT102: -65 | AU102: -220 | AV102: -269 | AW102: =AV102 -> -269 | AX102: 0 | AY102: -1 | AZ102: -4 | BA102: -10 | BB102: =BA102 -> -10 | BC102: -3 | BD102: -5 | BE102: -7 | BF102: -11 | BG102: =BF102 -> -11 | BH102: -23 | BI102: -26 | BJ102: -26 | BK102: -28 | BL102: =BK102 -> -28 | BM102: -2 | BN102: -5 | BO102: -3 | BP102: -5 | BQ102: =BP102 -> -5 | BR102: -2 | BS102: -4 | BT102: -5 | BU102: -7 | BV102: =BU102 -> -7 | BW102: 7 | BX102: 5 | BY102: 4 | BZ102: 2 | CA102: =BZ102 -> 2 | CB102: -1 | CC102: -2 | CD102: -3 | CE102: -3 | CF102: =CE102 -> -3 | CG102: 249 | CH102: 249 | CI102: 249 | CJ102: 250 | CK102: =CJ102 -> 250 | CL102: 0 | CM102: 9 | CN102: 12 | CO102: 12 | CP102: =CO102 -> 12 | CU102: =CT102 -> 0 | CZ102: =CY102 -> 0 | DE102: =DD102 -> 0 | DJ102: =DI102 -> 0 | DO102: =DN102 -> 0
B103: Loss/(gain) on disposal of disc. Ops | C103: 0 | D103: 0 | E103: 0 | F103: 0 | G103: 0 | H103: 0 | I103: 0 | J103: 0 | K103: -21 | L103: -52 | M103: =N103 -> -66 | N103: -66 | O103: 0 | P103: 0 | Q103: 12 | R103: =S103 -> 12 | S103: 12 | T103: 0 | U103: 0 | V103: 0 | W103: =X103 -> -14 | X103: -14 | Y103: -7 | Z103: -9 | AA103: -16 | AB103: =AC103 -> -25 | AC103: -25 | AD103: -8 | AE103: -10 | AF103: -28 | AG103: =AH103 -> -28 | AH103: -28 | AI103: 8 | AJ103: 7 | AK103: 13 | AL103: 36 | AM103: =AL103 -> 36 | AN103: 0 | AO103: 3 | AP103: 3 | AQ103: 6 | AR103: =AQ103 -> 6 | AS103: 3 | AT103: 4 | AU103: -1 | AV103: -11 | AW103: =AV103 -> -11 | AX103: 2 | AY103: 2 | AZ103: 5 | BA103: 5 | BB103: =BA103 -> 5 | BD103: -1 | BE103: 1 | BF103: 1 | BG103: =BF103 -> 1 | BH103: -1 | BI103: 0 | BJ103: 0 | BK103: 0 | BL103: =BK103 -> 0 | BQ103: =BP103 -> 0 | BV103: =BU103 -> 0 | CA103: =BZ103 -> 0
B104: Loss on dispositions/business shutdown net | C104: 0 | D104: 0 | E104: -87 | F104: -34 | G104: -21 | H104: -44 | I104: -7 | J104: 0 | K104: -6 | L104: -7 | M104: =N104 -> -23 | N104: -23 | O104: -25 | P104: 92 | Q104: -491 | R104: =S104 -> -520 | S104: -520 | T104: 2 | U104: -4 | V104: 268 | W104: =X104 -> 226 | X104: 226 | Y104: 2 | Z104: 0 | AA104: 22 | AB104: =AC104 -> -38 | AC104: -38 | AE104: -2 | AF104: -2 | AG104: =AH104 -> -4 | AH104: -4 | AI104: 3 | AJ104: 6 | AK104: 7 | AL104: 24 | AM104: =AL104 -> 24 | AN104: 4 | AO104: 5 | AP104: -9 | AQ104: -6 | AR104: =AQ104 -> -6 | AS104: 0 | AT104: -20 | AU104: -20 | AV104: -24 | AW104: =AV104 -> -24 | AY104: 2 | AZ104: 3 | BA104: -4 | BB104: =BA104 -> -4 | BC104: -22 | BD104: -22 | BE104: -21 | BF104: -20 | BG104: =BF104 -> -20 | BH104: 0 | BI104: -2 | BJ104: -2 | BK104: 10 | BL104: =BK104 -> 10 | BM104: -1 | BN104: -1 | BP104: 1 | BQ104: =BP104 -> 1 | BR104: -4 | BS104: 9 | BT104: 10 | BU104: 7 | BV104: =BU104 -> 7 | BW104: -2 | BX104: 0 | BZ104: -21 | CA104: =BZ104 -> -21 | CB104: -4 | CC104: -7 | CD104: -76 | CE104: -75 | CF104: =CE104 -> -75 | CG104: -108 | CH104: -300 | CI104: -296 | CJ104: -691 | CK104: =CJ104 -> -691 | CL104: -54 | CM104: -92 | CN104: -200 | CO104: -202 | CP104: =CO104 -> -202 | CQ104: -2 | CR104: -2 | CS104: -3 | CT104: -277 | CU104: =CT104 -> -277 | CV104: -1 | CW104: -2 | CX104: -2 | CZ104: =CY104 -> 0 | DA104: 0 | DB104: -1 | DC104: -1 | DD104: -2 | DE104: =DD104 -> -2 | DG104: -5 | DH104: -5 | DI104: -46 | DJ104: =DI104 -> -46 | DL104: -64 | DM104: -63 | DN104: -9672 | DO104: =DN104 -> -9672 | DP104: -12 | DQ104: -79
B105: Other charges and credits, net | C105: 1400 | D105: 0 | E105: 0 | F105: =557 -> 557 | G105: -1 | H105: =-17+1827-526 -> 1284 | I105: =63+913-147 -> 829 | J105: =-17+72 -> 55 | K105: =-5+150+3+26 -> 174 | L105: =55+214+26+3 -> 298 | M105: =N105 -> 892 | N105: =539+15+335+3 -> 892 | O105: =36+223 -> 259 | P105: =124+378 -> 502 | Q105: =92+774 -> 866 | R105: =S105 -> 1354 | S105: =129+1225 -> 1354 | T105: =43+190 -> 233 | U105: =76+317 -> 393 | V105: =112+525 -> 637 | W105: =X105 -> 828 | X105: =82+746 -> 828 | Y105: =65+252 -> 317 | Z105: =73+503 -> 576 | AA105: =120+781 -> 901 | AB105: =AC105 -> 1279 | AC105: =197+1082 -> 1279 | AD105: 56 | AE105: 78 | AF105: 83 | AG105: =AH105 -> 116 | AH105: 116 | AI105: 63 | AJ105: 78 | AK105: 170 | AL105: 214 | AM105: =AL105 -> 214 | AN105: 30 | AO105: 45 | AP105: 103 | AQ105: 512 | AR105: =AQ105 -> 512 | AS105: 113 | AT105: 223 | AU105: 358 | AV105: 500 | AW105: =AV105 -> 500 | AX105: 150 | AY105: 361 | AZ105: 559 | BA105: 694 | BB105: =BA105 -> 694 | BC105: 53 | BD105: 31 | BE105: 48 | BF105: 528 | BG105: =BF105 -> 528 | BH105: 47 | BI105: 87 | BJ105: 145 | BK105: 317 | BL105: =BK105 -> 317 | BM105: 76 | BN105: 140 | BO105: 230 | BP105: 364 | BQ105: =BP105 -> 364 | BR105: 84 | BS105: 141 | BT105: 219 | BU105: 369 | BV105: =BU105 -> 369 | BW105: 52 | BX105: 129 | BY105: 190 | BZ105: 287 | CA105: =BZ105 -> 287 | CB105: 60 | CC105: 112 | CD105: 158 | CE105: 247 | CF105: =CE105 -> 247 | CG105: 74 | CH105: 145 | CI105: 190 | CJ105: 334 | CK105: =CJ105 -> 334 | CL105: 97 | CM105: 815 | CN105: 912 | CO105: =6493+1462 -> 7955 | CP105: =CO105 -> 7955 | CQ105: =35+306 -> 341 | CR105: =628-114 -> 514 | CS105: =951-283-82 -> 586 | CT105: =1233+3460+360 -> 5053 | CU105: =CT105 -> 5053 | CV105: =329+48+175 -> 552 | CW105: =612+42+260 -> 914 | CX105: =928+39+388 -> 1355 | CY105: =1215+37-6+364 -> 1610 | CZ105: =CY105 -> 1610 | DA105: =553-1+34 -> 586 | DB105: =862-3+33 -> 892 | DC105: =1204-4-21 -> 1179 | DD105: =1515+3 -> 1518 | DE105: =DD105 -> 1518 | DF105: =606+10 -> 616 | DG105: =953-34 -> 919 | DH105: =1315+3006+270 -> 4591 | DI105: =4079+528+1601 -> 6208 | DJ105: =DI105 -> 6208 | DK105: =418+3+99 -> 520 | DL105: =793+162 -> 955 | DM105: =1173+5140+217 -> 6530 | DN105: =264+5283+1530 -> 7077 | DO105: =DN105 -> 7077 | DP105: =45+466 -> 511 | DQ105: =855+149 -> 1004
B106: Excess tax benefits from share based payments | C106: 0 | D106: 0 | E106: 0 | F106: 0 | G106: 0 | H106: 0 | I106: 0 | J106: 0 | K106: =0 -> 0 | L106: 0 | M106: =N106 -> 0 | N106: =0 -> 0 | O106: -22 | P106: -46 | Q106: -46 | R106: =S106 -> -70 | S106: -70 | T106: -41 | U106: -118 | V106: -118 | W106: =X106 -> -395 | X106: -395 | Y106: -31 | Z106: -107 | AA106: -141 | AB106: =AC106 -> -144 | AC106: -144 | AD106: -43 | AE106: -45 | AF106: -100 | AG106: =AH106 -> -100 | AH106: -100 | AI106: -5 | AJ106: -5 | AK106: -5 | AL106: -5 | AM106: =AL106 -> -5 | AN106: -8 | AO106: -15 | AP106: -17 | AQ106: -19 | AR106: =AQ106 -> -19 | AS106: -22 | AT106: -32 | AU106: -35 | AV106: -36 | AW106: =AV106 -> -36 | AX106: -40 | AY106: -39 | AZ106: -43 | BA106: -45 | BB106: =BA106 -> -45 | BC106: -23 | BD106: -47 | BE106: -86 | BF106: -128 | BG106: =BF106 -> -128 | BH106: -68 | BI106: -97 | BJ106: -104 | BK106: -114 | BL106: =BK106 -> -114 | BM106: -112 | BN106: -124 | BO106: -139 | BP106: -157 | BQ106: =BP106 -> -157 | BR106: -44 | BS106: 0 | BT106: 0 | BU106: 0 | BV106: =BU106 -> 0 | BW106: 0 | CA106: =BZ106 -> 0
B107: Changes in assets and liabilities: | C107: =SUM(C108:C120) -> -481 | D107: =SUM(D108:D120) -> -528 | E107: =SUM(E108:E120) -> 2076 | F107: =SUM(F108:F120) -> 1483 | G107: =SUM(G108:G120) -> -1161 | H107: =SUM(H108:H120) -> 111 | I107: =SUM(I108:I120) -> 28 | J107: =SUM(J108:J120) -> -1125 | ... L107: =SUM(L108:L120) -> -1287 | M107: =N107 -> -1484 | N107: =SUM(N108:N120) -> -1484 | O107: =SUM(O108:O120) -> -23 | P107: =SUM(P108:P120) -> 1126 | Q107: =SUM(Q108:Q120) -> 146 | R107: =S107 -> 1118 | S107: =SUM(S108:S120) -> 1118 | T107: =SUM(T108:T120) -> 598 | U107: =SUM(U108:U120) -> 2458 | V107: =SUM(V108:V120) -> 1253 | W107: =X107 -> 2187 | X107: =SUM(X108:X120) -> 2187 | Y107: =SUM(Y108:Y120) -> -804 | Z107: =SUM(Z108:Z120) -> 1055 | AA107: =SUM(AA108:AA120) -> 2567 | AB107: =AC107 -> 2675 | AC107: =SUM(AC108:AC120) -> 2675 | AD107: =SUM(AD108:AD120) -> 314 | AE107: =SUM(AE108:AE120) -> -1308 | AF107: =SUM(AF108:AF120) -> -2806 | AG107: =AH107 -> -4902 | AH107: =SUM(AH108:AH120) -> -4902 | AI107: =SUM(AI108:AI120) -> -962 | AJ107: =SUM(AJ108:AJ120) -> -1452 | AK107: =SUM(AK108:AK120) -> 679 | AL107: =SUM(AL108:AL120) -> 1910 | AM107: =SUM(AM108:AM120) -> 1910 | AN107: =SUM(AN108:AN120) -> -1333 | AO107: =SUM(AO108:AO120) -> -2382 | ... DQ107: =SUM(DQ108:DQ120) -> -756
B108: Accounts receivable | C108: -251 | D108: -167 | E108: -225 | F108: -768 | G108: 342 | H108: -155 | I108: 357 | J108: -378 | K108: -119 | L108: -738 | M108: =N108 -> -241 | N108: -241 | O108: -695 | P108: -510 | Q108: -346 | R108: =S108 -> -592 | S108: -592 | T108: 78 | U108: 621 | V108: 166 | W108: =X108 -> -244 | X108: -244 | Y108: -231 | Z108: -761 | AA108: -358 | AB108: =AC108 -> -392 | AC108: -392 | AD108: 197 | AE108: -129 | AF108: -145 | AG108: =AH108 -> 564 | AH108: 564 | AI108: -869 | AJ108: -1215 | AK108: -818 | AL108: -391 | AM108: =AL108 -> -391 | AN108: -572 | AO108: -827 | AP108: -701 | AQ108: 8 | AR108: =AQ108 -> 8 | AS108: -633 | AT108: -747 | AU108: -911 | AV108: -292 | AW108: =AV108 -> -292 | AX108: -729 | AY108: -310 | AZ108: 150 | BA108: -27 | BB108: =BA108 -> -27 | BC108: -437 | BD108: -550 | BE108: -1006 | BF108: -879 | BG108: =BF108 -> -879 | BH108: -792 | BI108: -1286 | BJ108: -1385 | BK108: -1328 | BL108: =BK108 -> -1328 | BM108: -389 | BN108: -313 | BO108: -1202 | BP108: -1069 | BQ108: =BP108 -> -1069 | BR108: -1002 | BS108: -503 | BT108: -517 | BU108: 112 | BV108: =BU108 -> 112 | BW108: -769 | BX108: -912 | BY108: -1983 | BZ108: -1821 | CA108: =BZ108 -> -1821 | CB108: =92 -> 92 | CC108: 62 | CD108: 10 | CE108: -795 | CF108: =CE108 -> -795 | CG108: 206 | CH108: 588 | CI108: 315 | CJ108: 603 | CK108: =CJ108 -> 603 | CL108: -54 | CM108: 143 | CN108: 125 | CO108: 909 | CP108: =CO108 -> 909 | CQ108: -394 | CR108: -523 | CS108: -280 | CT108: -713 | CU108: =CT108 -> -713 | CV108: 237 | CW108: -350 | CX108: -22 | CY108: 142 | CZ108: =CY108 -> 142 | DA108: -341 | DB108: -433 | DC108: -523 | DD108: =-128 -> -128 | DE108: =DD108 -> -128 | DF108: -328 | DG108: -522 | DH108: -275 | DI108: -37 | DJ108: =DI108 -> -37 | DK108: -570 | DL108: -683 | DM108: -836 | DN108: -95 | DO108: =DN108 -> -95 | DP108: -509 | DQ108: -553
B109: Unbilled receivables | CB109: =-1628 -> -1628 | CC109: -1675 | CD109: -1732 | CE109: -1826 | CF109: =+CE109 -> -1826 | CG109: -183 | CH109: -222 | CI109: -1053 | CJ109: 982 | CK109: =+CJ109 -> 982 | CL109: -402 | CM109: 285 | CN109: 56 | CO109: 919 | CP109: =+CO109 -> 919 | CQ109: -790 | CR109: -1207 | CS109: -2010 | CT109: -586 | CU109: =+CT109 -> -586 | CV109: -356 | CW109: -758 | CX109: -678 | CY109: 6 | CZ109: =+CY109 -> 6 | DA109: -1055 | DB109: -721 | DC109: -547 | DD109: 321 | DE109: =+DD109 -> 321 | DF109: -1357 | DG109: -1345 | DH109: -1042 | DI109: -60 | DJ109: =+DI109 -> -60 | DK109: -671 | DL109: -908 | DM109: -679 | DN109: -677 | DO109: =+DN109 -> -677 | DP109: -635 | DQ109: -504
B110: Advances and billings in excess of related costs | C110: -139 | D110: -324 | E110: -36 | F110: 1387 | G110: 789 | H110: -898 | I110: 341 | J110: 241 | K110: 9 | L110: 440 | M110: =N110 -> 659 | N110: 659 | O110: 101 | P110: 505 | Q110: 1501 | R110: =S110 -> 3562 | S110: 3562 | T110: 88 | U110: 338 | V110: 656 | W110: =X110 -> 1739 | X110: 1739 | Y110: -330 | Z110: 68 | AA110: 747 | AB110: =AC110 -> 2369 | AC110: 2369 | AD110: 113 | AE110: -1166 | AF110: -2061 | AG110: =AH110 -> -1120 | AH110: -1120 | AI110: -1210 | AJ110: -1030 | AK110: -961 | AL110: -680 | AM110: =AL110 -> -680 | AN110: -221 | AO110: -66 | AP110: -303 | AQ110: 238 | AR110: =AQ110 -> 238 | AS110: 40 | AT110: 626 | AU110: 1996 | AV110: 3173 | AW110: =AV110 -> 3173 | AX110: -160 | AY110: -152 | AZ110: 123 | BA110: 1177 | BB110: =BA110 -> 1177 | BC110: 1833 | BD110: 1472 | BE110: 3543 | BF110: 3353 | BG110: =BF110 -> 3353 | BH110: 1085 | BI110: 1217 | BJ110: 1100 | BK110: 3145 | BL110: =BK110 -> 3145 | BM110: -422 | BN110: 195 | BO110: 270 | BP110: 1192 | BQ110: =BP110 -> 1192 | BR110: -435 | BS110: -954 | BT110: -1717 | BU110: -493 | BV110: =BU110 -> -493 | BW110: 249 | BX110: 1934 | BY110: 2828 | BZ110: 3570 | CA110: =BZ110 -> 3570 | CB110: 1917 | CC110: 2931 | CD110: 3457 | CE110: 2636 | CF110: =CE110 -> 2636 | CG110: 1857 | CH110: 1842 | CI110: 2355 | CJ110: 737 | CK110: =CJ110 -> 737 | CL110: 1337 | CM110: 1822 | CN110: 428 | CO110: -1060 | CP110: =CO110 -> -1060 | CQ110: 421 | CR110: 251 | CS110: 781 | CT110: 2505 | CU110: =CT110 -> 2505 | CV110: -522 | CW110: -907 | CX110: 204 | CY110: 108 | CZ110: =CY110 -> 108 | DA110: 1417 | DB110: 2228 | DC110: 2963 | DD110: 3365 | DE110: =DD110 -> 3365 | DF110: 2718 | DG110: 1886 | DH110: 1666 | DI110: 4069 | DJ110: =DI110 -> 4069 | DK110: 781 | DL110: -616 | DM110: -2065 | DN110: -723 | DO110: =DN110 -> -723 | DP110: 3181 | DQ110: 4660
B111: Inventories, net of advances and progress billings | C111: -1008 | D111: 618 | E111: 2030 | F111: 1097 | G111: -19 | H111: 1510 | I111: 351 | J111: -512 | K111: 276 | L111: 80 | M111: =N111 -> 611 | N111: 611 | O111: 383 | P111: 454 | Q111: -1050 | R111: =S111 -> -1965 | S111: -1965 | T111: 387 | U111: 678 | V111: 520 | W111: =X111 -> 444 | X111: 444 | Y111: -298 | Z111: -380 | AA111: -100 | AB111: =AC111 -> -1558 | AC111: -1558 | AD111: -604 | AE111: -649 | AF111: -1670 | AG111: =AH111 -> -6168 | AH111: -6168 | AI111: -82 | AJ111: -1593 | AK111: -582 | AL111: -1525 | AM111: =AL111 -> -1525 | AN111: -1833 | AO111: -3425 | AP111: -4686 | AQ111: -7387 | AR111: =AQ111 -> -7387 | AS111: -2622 | AT111: -4889 | AU111: -8245 | AV111: -10012 | AW111: =AV111 -> -10012 | AX111: -497 | AY111: -2737 | AZ111: -4588 | BA111: -5681 | BB111: =BA111 -> -5681 | BC111: -3000 | BD111: -2614 | BE111: -3631 | BF111: -5562 | BG111: =BF111 -> -5562 | BH111: -2049 | BI111: -3402 | BJ111: -4425 | BK111: -4330 | BL111: =BK111 -> -4330 | BM111: -1822 | BN111: -2395 | BO111: -2186 | BP111: -1110 | BQ111: =BP111 -> -1110 | BR111: -56 | BS111: 3004 | BT111: 4334 | BU111: 3755 | BV111: =BU111 -> 3755 | BW111: -31 | BX111: 877 | BY111: 254 | BZ111: -1085 | CA111: =BZ111 -> -1085 | CB111: 283 | CC111: 408 | CD111: -173 | CE111: 568 | CF111: =CE111 -> 568 | CG111: -2725 | CH111: -5233 | CI111: -9565 | CJ111: -12391 | CK111: =CJ111 -> -12391 | CL111: -2973 | CM111: -6741 | CN111: -9653 | CO111: -11002 | CP111: =CO111 -> -11002 | CQ111: -680 | CR111: 413 | CS111: 508 | CT111: -1127 | CU111: =CT111 -> -1127 | CV111: -1203 | CW111: -1260 | CX111: -1164 | CY111: 420 | CZ111: =CY111 -> 420 | DA111: -390 | DB111: -241 | DC111: -940 | DD111: -1681 | DE111: =DD111 -> -1681 | DF111: -3778 | DG111: -5937 | DH111: -6854 | DI111: -12353 | DJ111: =DI111 -> -12353 | DK111: -1521 | DL111: -374 | DM111: -116 | DN111: -1501 | DO111: =DN111 -> -1501 | DP111: -2634 | DQ111: -3859
B112: Accounts payable | C112: 1490 | D112: -806 | E112: 217 | F112: -311 | G112: 490 | H112: -823 | I112: -147 | J112: 101 | K112: 435 | L112: 1367 | M112: =N112 -> 862 | N112: 862 | O112: 496 | P112: 782 | Q112: 1521 | R112: =S112 -> 1147 | S112: 1147 | T112: 271 | U112: 549 | V112: -682 | W112: =X112 -> -744 | X112: -744 | Y112: 98 | Z112: 842 | AA112: 470 | AB112: =AC112 -> 928 | AC112: 928 | AD112: 628 | AE112: 616 | AF112: 172 | AG112: =AH112 -> 872 | AH112: 872 | AI112: 475 | AJ112: =804 -> 804 | AK112: =1169 -> 1169 | AL112: =1141 -> 1141 | AM112: =AL112 -> 1141 | AN112: =225 -> 225 | AO112: =-129 -> -129 | AP112: =235 -> 235 | AQ112: =313 -> 313 | AR112: =AQ112 -> 313 | AS112: =969 -> 969 | AT112: =1134 -> 1134 | AU112: =1447 -> 1447 | AV112: =1164 -> 1164 | AW112: =AV112 -> 1164 | AX112: =506 -> 506 | AY112: =742 -> 742 | AZ112: 857 | BA112: =1199 -> 1199 | BB112: =BA112 -> 1199 | BC112: =654 -> 654 | BD112: =848 -> 848 | BE112: =943 -> 943 | BF112: -298 | BG112: =BF112 -> -298 | BH112: =1350 -> 1350 | BI112: =1783 -> 1783 | BJ112: =1819 -> 1819 | BK112: =1339 -> 1339 | BL112: =BK112 -> 1339 | BM112: =848 -> 848 | BN112: =888 -> 888 | BO112: =1058 -> 1058 | BP112: =-238 -> -238 | BQ112: =BP112 -> -238 | BR112: =960 -> 960 | BS112: =1221 -> 1221 | BT112: 1366 | BU112: 622 | BV112: =BU112 -> 622 | BW112: 616 | BX112: 419 | BY112: 778 | BZ112: 130 | CA112: =BZ112 -> 130 | CB112: 591 | CC112: 682 | CD112: 1181 | CE112: 2 | CF112: =CE112 -> 2 | CG112: 1624 | CH112: 2002 | CI112: 1626 | CJ112: 1600 | CK112: =CJ112 -> 1600 | CL112: -1030 | CM112: -3181 | CN112: -3303 | CO112: -5363 | CP112: =CO112 -> -5363 | CQ112: -819 | CR112: -2035 | CS112: -3565 | CT112: -3783 | CU112: =CT112 -> -3783 | CV112: -369 | CW112: 395 | CX112: 590 | CY112: 838 | CZ112: =CY112 -> 838 | DA112: 231 | DB112: 852 | DC112: 982 | DD112: 1672 | DE112: =DD112 -> 1672 | DF112: -264 | DG112: -222 | DH112: 122 | DI112: -793 | DJ112: =DI112 -> -793 | DK112: -95 | DL112: -46 | DM112: 539 | DN112: 724 | DO112: =DN112 -> 724 | DP112: 1073 | DQ112: 1381
...

Sheet BCA margin
B3: BCA Margin Analysis | C3: 1997 | D3: 1998 | E3: 1999 | F3: 2000 | G3: 2001 | H3: 2002 | I3: 2003 | J3: 1Q04 | K3: 2Q04 | L3: 3Q04 | M3: 4Q04 | N3: 2004 | O3: 1Q05 | P3: 2Q05 | Q3: 3Q05 | R3: 4Q05 | S3: 2005 | T3: 1Q06 | U3: 2Q06 | V3: 3Q06 | W3: 4Q06 | X3: 2006 | Y3: 1Q07 | Z3: 2Q07 | AA3: 3Q07 | AB3: 4Q07 | AC3: 2007 | AD3: 1Q08 | AE3: 2Q08 | AF3: 3Q08 | AG3: 4Q08 | AH3: 2008 | AI3: 1Q09 | AJ3: 2Q09 | AK3: 3Q09 | AL3: 4Q09 | AM3: 2009 | AN3: 1Q10 | AO3: 2Q10 | AP3: 3Q10 | AQ3: 4Q10 | AR3: 2010 | AS3: 1Q11 | AT3: 2Q11 | AU3: 3Q11 | AV3: 4Q11 | AW3: 2011 | AX3: 1Q12 | AY3: 2Q12 | AZ3: 3Q12 | BA3: 4Q12 | BB3: 2012 | BC3: 1Q13 | BD3: 2Q13 | BE3: 3Q13 | BF3: 4Q13 | BG3: 2013 | BH3: 1Q14 | BI3: 2Q14 | BJ3: 3Q14 | BK3: 4Q14 | BL3: 2014 | BM3: 1Q15 | BN3: 2Q15 | BO3: 3Q15 | BP3: 4Q15 | BQ3: 2015 | BR3: 1Q16 | BS3: 2Q16 | BT3: 3Q16 | BU3: 4Q16 | BV3: 2016 | BW3: 1Q17 | BX3: 2Q17 | BY3: 3Q17 | BZ3: 4Q17 | CA3: 2017 | CB3: 1Q18 | CC3: 2Q18 | CD3: 3Q18 | CE3: 4Q18 | CF3: 2018 | CG3: 1Q19 | CH3: 2Q19 | CI3: 3Q19 | CJ3: 4Q19 | CK3: 2019 | CL3: 1Q20 | CM3: 2Q20 | CN3: 3Q20 | CO3: 4Q20 | CP3: 2020 | CQ3: 1Q21 | CR3: 2Q21 | CS3: 3Q21 | CT3: 4Q21E | CU3: 2021 | CV3: 1Q22 | CW3: 2Q22 | CX3: 3Q22 | CY3: 4Q22 | CZ3: 2022 | DA3: 1Q23 | DB3: 2Q23 | DC3: 3Q23 | DD3: 4Q23 | DE3: 2023 | DF3: 1Q24 | DG3: 2Q24 | DH3: 3Q24 | DI3: 4Q24 | DJ3: 2024 | DK3: 1Q25 | DL3: 2Q25 | DM3: 3Q25 | DN3: 4Q25 | DO3: 2025 | DP3: 1Q26 | DQ3: 2Q26 | DR3: 3Q26E | DS3: 4Q26E | DT3: 2026E | DU3: 1Q27E | DV3: 2Q27E | DW3: 3Q27E | DX3: 4Q27E | DY3: 2027E | DZ3: 2028E | EA3: 2029E | EB3: 2030E
B4: ($ mn, except percentages) | C4: 35795 | D4: 36160 | E4: 36525 | F4: 36891 | G4: 37256 | H4: 37621 | I4: 37986 | J4: 38077 | K4: 38168 | L4: 38260 | M4: 38352 | N4: 38352 | O4: 38442 | P4: 38533 | Q4: 38625 | R4: 38717 | S4: 38717 | T4: 38807 | U4: 38898 | V4: 38990 | W4: 39082 | X4: 39082 | Y4: 39172 | Z4: 39263 | AA4: 39355 | AB4: 39447 | AC4: 39447 | AD4: 39538 | AE4: 39629 | AF4: 39721 | AG4: 39813 | AH4: 39813 | AI4: 39903 | AJ4: 39994 | AK4: 40086 | AL4: 40178 | AM4: 40178 | AN4: 40268 | AO4: 40359 | AP4: 40451 | AQ4: 40543 | AR4: 40543 | AS4: 40633 | AT4: 40724 | AU4: 40816 | AV4: 40908 | AW4: 40908 | AX4: 40999 | AY4: 41090 | AZ4: 41182 | BA4: 41274 | BB4: 41274 | BC4: 41364 | BD4: 41455 | BE4: 41547 | BF4: 41639 | BG4: 41639 | BH4: 41729 | BI4: 41820 | BJ4: 41912 | BK4: 42004 | BL4: 42004 | BM4: 42094 | BN4: 42185 | BO4: 42277 | BP4: 42369 | BQ4: 42369 | BR4: 42460 | BS4: 42551 | BT4: 42643 | BU4: 42735 | BV4: 42735 | BW4: 42825 | BX4: 42916 | BY4: 43008 | BZ4: 43100 | CA4: 43100 | CB4: 43190 | CC4: 43281 | CD4: 43373 | CE4: 43465 | CF4: 43465 | CG4: 43555 | CH4: 43646 | CI4: 43738 | CJ4: 43830 | CK4: 43830 | CL4: 43921 | CM4: 44012 | CN4: 44104 | CO4: 44196 | CP4: 44196 | CQ4: 44286 | CR4: 44377 | CS4: 44469 | CT4: 44561 | CU4: 44561 | CV4: 44651 | CW4: 44742 | CX4: 44834 | CY4: 44926 | CZ4: 44926 | DA4: 45016 | DB4: 45107 | DC4: 45199 | DD4: 45291 | DE4: 45291 | DF4: 45382 | DG4: 45473 | DH4: 45565 | DI4: 45657 | DJ4: 45657 | DK4: 45747 | DL4: 45838 | DM4: 45930 | DN4: 46022 | DO4: 46022 | DP4: 46112 | DQ4: 46203 | DR4: 46295 | DS4: 46387 | DT4: 46387 | DU4: 46477 | DV4: 46568 | DW4: 46660 | DX4: 46752 | DY4: 46752 | DZ4: 47118 | EA4: 47483 | EB4: 47848
B6: B-737 (units) | C6: 135 | D6: =165+116 -> 281 | E6: =278+42 -> 320 | F6: 281 | G6: 299 | H6: 223 | I6: 173 | J6: 55 | K6: 50 | L6: 49 | M6: 48 | N6: =+M6+L6+K6+J6 -> 202 | O6: 54 | P6: 59 | Q6: =47+62*0 -> 47 | R6: 52 | S6: =+R6+Q6+P6+O6 -> 212 | T6: 72 | U6: 70 | V6: 81 | W6: =+X6-V6-U6-T6 -> 79 | X6: 302 | Y6: 83 | Z6: 86 | AA6: 81 | AB6: 80 | AC6: =SUM(Y6:AB6) -> 330 | AD6: 87 | AE6: 100 | AF6: 67 | AG6: 36 | AH6: =SUM(AD6:AG6) -> 290 | AI6: 91 | AJ6: 99 | AK6: 90 | AL6: 92 | AM6: =SUM(AI6:AL6) -> 372 | AN6: 86 | AO6: 95 | AP6: =Commercial!AP32 -> 100 | AQ6: =Commercial!AQ32 -> 95 | AR6: =Commercial!AR32 -> 376 | AS6: =Commercial!AS32 -> 87 | AT6: =Commercial!AT32 -> 94 | AU6: =Commercial!AU32 -> 100 | AV6: =Commercial!AV32 -> 91 | AW6: =Commercial!AW32 -> 372 | ... EB6: =Commercial!EB32 -> 740
B7: Unit Price $ | C7: 32 | D7: 30 | E7: 29 | F7: 31 | G7: 33.5 | H7: 38.623318 | I7: 40 | J7: 41 | K7: 41 | L7: 41 | M7: 41 | N7: 41 | O7: 42 | P7: 42 | Q7: 42 | R7: 42 | S7: =+S8/S6 -> 42 | T7: 41 | U7: 41.4 | V7: 40 | W7: 40 | X7: =+X8/X6 -> 40.562914 | Y7: 40 | Z7: 40 | AA7: 40 | AB7: 40 | AC7: 40 | AD7: 41 | AE7: 41 | AF7: 41 | AG7: 41.3 | AH7: 41 | AI7: 41 | AJ7: 41 | AK7: 41 | AL7: 41 | AM7: 41 | AN7: 40 | AO7: 40 | AP7: =Commercial!AP34 -> 41 | AQ7: =Commercial!AQ34 -> 41 | AR7: =Commercial!AR34 -> 40.518617 | AS7: =Commercial!AS34 -> 42 | AT7: =Commercial!AT34 -> 43 | AU7: =Commercial!AU34 -> 43 | AV7: =Commercial!AV34 -> 43 | AW7: =Commercial!AW34 -> 42.766129 | ... CK7: =Commercial!CK34 -> 54.728961 | CL7: =IFERROR(Commercial!CL34,"--") -> 48.545 | CM7: =IFERROR(Commercial!CM34,"--") -> 48.545 | CN7: =IFERROR(Commercial!CN34,"--") -> 48.545 | CO7: =IFERROR(Commercial!CO34,"--") -> 59.368303 | CP7: =Commercial!CP34 -> 56.347846 | CQ7: =IFERROR(Commercial!CQ34,"--") -> 58.020653 | CR7: =IFERROR(Commercial!CR34,"--") -> 58.414175 | CS7: =IFERROR(Commercial!CS34,"--") -> 57.308464 | CT7: =IFERROR(Commercial!CT34,"--") -> 58.448213 | CU7: =Commercial!CU34 -> 58.053302 | CV7: =IFERROR(Commercial!CV34,"--") -> 56.671335 | CW7: =IFERROR(Commercial!CW34,"--") -> 58.030822 | CX7: =IFERROR(Commercial!CX34,"--") -> 58.098431 | CY7: =IFERROR(Commercial!CY34,"--") -> 58.488654 | CZ7: =Commercial!CZ34 -> 57.874221 | DA7: =IFERROR(Commercial!DA34,"--") -> 57.757043 | DB7: =IFERROR(Commercial!DB34,"--") -> 57.109455 | DC7: =IFERROR(Commercial!DC34,"--") -> 57.179049 | DD7: =IFERROR(Commercial!DD34,"--") -> 57.507615 | DE7: =Commercial!DE34 -> 57.417148 | DF7: =IFERROR(Commercial!DF34,"--") -> 56.597028 | DG7: =IFERROR(Commercial!DG34,"--") -> 56.598152 | DH7: =IFERROR(Commercial!DH34,"--") -> 56.126207 | DI7: =IFERROR(Commercial!DI34,"--") -> 56.838761 | DJ7: =Commercial!DJ34 -> 56.466709 | DK7: =IFERROR(Commercial!DK34,"--") -> 57.883744 | DL7: =IFERROR(Commercial!DL34,"--") -> 57.508878 | DM7: =IFERROR(Commercial!DM34,"--") -> 57.133751 | DN7: =IFERROR(Commercial!DN34,"--") -> 57.711628 | DO7: =Commercial!DO34 -> 57.548458 | DP7: =IFERROR(Commercial!DP34,"--") -> 58.077703 | DQ7: =IFERROR(Commercial!DQ34,"--") -> 58.036146 | DR7: =IFERROR(Commercial!DR34,"--") -> 57.161926 | DS7: =IFERROR(Commercial!DS34,"--") -> 56.814904 | DT7: =Commercial!DT34 -> 57.483566 | DU7: =IFERROR(Commercial!DU34,"--") -> 57.944444 | DV7: =IFERROR(Commercial!DV34,"--") -> 58.622517 | DW7: =IFERROR(Commercial!DW34,"--") -> 58.135484 | DX7: =IFERROR(Commercial!DX34,"--") -> 58.640244 | DY7: =Commercial!DY34 -> 58.345277 | DZ7: =Commercial!DZ34 -> 59.652439 | EA7: =Commercial!EA34 -> 60.91 | EB7: =Commercial!EB34 -> 61.9
B8: Program Revenue $ | C8: =C7*C6 -> 4320 | D8: =D7*D6 -> 8430 | E8: =E7*E6 -> 9280 | F8: =F7*F6 -> 8711 | G8: =G7*G6 -> 10016.5 | H8: =H7*H6 -> 8613 | I8: =I7*I6 -> 6920 | J8: =J7*J6 -> 2255 | ... M8: =M7*M6 -> 1968 | N8: =SUM(J8:M8) -> 8282 | O8: =O7*O6 -> 2268 | P8: =P7*P6 -> 2478 | Q8: =Q7*Q6 -> 1974 | R8: =R7*R6 -> 2184 | S8: =SUM(O8:R8) -> 8904 | T8: =T7*T6 -> 2952 | U8: =U7*U6 -> 2898 | V8: =V7*V6 -> 3240 | W8: =W7*W6 -> 3160 | X8: =SUM(T8:W8) -> 12250 | Y8: =Y7*Y6 -> 3320 | Z8: =Z7*Z6 -> 3440 | AA8: =AA7*AA6 -> 3240 | AB8: =AB7*AB6 -> 3200 | AC8: =SUM(Y8:AB8) -> 13200 | AD8: =AD7*AD6 -> 3567 | AE8: =AE7*AE6 -> 4100 | AF8: =AF7*AF6 -> 2747 | AG8: =AG7*AG6 -> 1486.8 | AH8: =SUM(AD8:AG8) -> 11900.8 | AI8: =AI7*AI6 -> 3731 | AJ8: =AJ7*AJ6 -> 4059 | AK8: =AK7*AK6 -> 3690 | AL8: =AL7*AL6 -> 3772 | AM8: =AM7*AM6 -> 15252 | AN8: =AN7*AN6 -> 3440 | AO8: =AO7*AO6 -> 3800 | AP8: =AP7*AP6 -> 4100 | ... CK8: =CK7*CK6 -> 6950.578 | CL8: =IFERROR(CL7*CL6,"0") -> 242.725 | CM8: =IFERROR(CM7*CM6,"0") -> 194.18 | CN8: =IFERROR(CN7*CN6,"0") -> 145.635 | CO8: =IFERROR(CO7*CO6,"0") -> 1840.4174 | CP8: =CP7*CP6 -> 2422.9574 | CQ8: =IFERROR(CQ7*CQ6,"0") -> 3655.3012 | CR8: =IFERROR(CR7*CR6,"0") -> 2920.7087 | CS8: =IFERROR(CS7*CS6,"0") -> 3782.3587 | CT8: =IFERROR(CT7*CT6,"0") -> 4909.6499 | CU8: =CU7*CU6 -> 15268.018 | CV8: =IFERROR(CV7*CV6,"0") -> 4873.7348 | CW8: =IFERROR(CW7*CW6,"0") -> 5977.1747 | CX8: =IFERROR(CX7*CX6,"0") -> 5112.6619 | CY8: =IFERROR(CY7*CY6,"0") -> 6433.7519 | CZ8: =CZ7*CZ6 -> 22397.323 | DA8: =IFERROR(DA7*DA6,"0") -> 6526.5459 | DB8: =IFERROR(DB7*DB6,"0") -> 5882.2738 | DC8: =IFERROR(DC7*DC6,"0") -> 4002.5334 | DD8: =IFERROR(DD7*DD6,"0") -> 6325.8376 | DE8: =DE7*DE6 -> 22737.191 | DF8: =IFERROR(DF7*DF6,"0") -> 3792.0009 | DG8: =IFERROR(DG7*DG6,"0") -> 3961.8706 | DH8: =IFERROR(DH7*DH6,"0") -> 5163.611 | DI8: =IFERROR(DI7*DI6,"0") -> 2046.1954 | DJ8: =DJ7*DJ6 -> 14963.678 | DK8: =IFERROR(DK7*DK6,"0") -> 6077.7931 | DL8: =IFERROR(DL7*DL6,"0") -> 5980.9233 | DM8: =IFERROR(DM7*DM6,"0") -> 6913.1838 | DN8: =IFERROR(DN7*DN6,"0") -> 6752.2605 | DO8: =DO7*DO6 -> 25724.161 | DP8: =IFERROR(DP7*DP6,"0") -> 6620.8582 | DQ8: =IFERROR(DQ7*DQ6,"0") -> 7486.6628 | DR8: =IFERROR(DR7*DR6,"0") -> 7831.1838 | DS8: =IFERROR(DS7*DS6,"0") -> 8067.7164 | DT8: =DT7*DT6 -> 30006.421 | DU8: =IFERROR(DU7*DU6,"0") -> 8344 | DV8: =IFERROR(DV7*DV6,"0") -> 8852 | DW8: =IFERROR(DW7*DW6,"0") -> 9011 | DX8: =IFERROR(DX7*DX6,"0") -> 9617 | DY8: =DY7*DY6 -> 35824 | DZ8: =DZ7*DZ6 -> 39132 | EA8: =EA7*EA6 -> 42637 | EB8: =EB7*EB6 -> 45806
B9: EBIT margin (pre-R&D) | C9: 0.09 | D9: 0.05 | E9: 0.05 | F9: 0.11 | G9: 0.1 | H9: 0.13 | I9: 0.09 | J9: 0.11 | K9: 0.11 | L9: 0.11 | M9: 0.11 | N9: 0.11 | O9: 0.152 | P9: 0.152 | Q9: 0.152 | R9: 0.152 | S9: 0.152 | T9: 0.175 | U9: 0.175 | V9: 0.175 | W9: 0.175 | X9: 0.175 | Y9: 0.19 | Z9: 0.19 | AA9: 0.19 | AB9: 0.19 | AC9: 0.19 | AD9: 0.16 | AE9: 0.16 | AF9: 0.16 | AG9: 0.16 | AH9: 0.16 | AI9: 0.14 | AJ9: 0.14 | AK9: 0.14 | AL9: 0.14 | AM9: =AM10/AM8 -> 0.14 | AN9: 0.18 | AO9: 0.185 | AP9: 0.19 | AQ9: 0.19 | AR9: =AR10/AR8 -> 0.18649491 | AS9: 0.18 | AT9: 0.18 | AU9: 0.18 | AV9: 0.18 | AW9: =AW10/AW8 -> 0.18 | BB9: 0.18 | BG9: 0.185 | BL9: 0.19 | BQ9: 0.1927 | BV9: 0.194 | CA9: 0.197 | CF9: 0.225 | CK9: 0.18 | CP9: 0.14 | CU9: 0.1 | CZ9: 0.1 | DE9: 0.1 | DJ9: 0.075 | DO9: 0.105 | DT9: 0.11 | DY9: 0.116 | DZ9: 0.132 | EA9: 0.148 | EB9: 0.17
B10: Program EBIT (pre-R&D) $ | C10: =C8*C9 -> 388.8 | D10: =D8*D9 -> 421.5 | E10: =E8*E9 -> 464 | F10: =F8*F9 -> 958.21 | G10: =G8*G9 -> 1001.65 | H10: =H8*H9 -> 1119.69 | I10: =I8*I9 -> 622.8 | J10: =J8*J9 -> 248.05 | ... AL10: =AL8*AL9 -> 528.08 | AM10: =SUM(AI10:AL10) -> 2135.28 | AN10: =AN8*AN9 -> 619.2 | AO10: =AO8*AO9 -> 703 | AP10: =AP8*AP9 -> 779 | AQ10: =AQ8*AQ9 -> 740.05 | AR10: =SUM(AN10:AQ10) -> 2841.25 | AS10: =AS8*AS9 -> 657.72 | AT10: =AT8*AT9 -> 727.56 | AU10: =AU8*AU9 -> 774 | AV10: =AV8*AV9 -> 704.34 | AW10: =SUM(AS10:AV10) -> 2863.62 | BB10: =BB8*BB9 -> 3286.8 | BG10: =BG8*BG9 -> 3663 | BL10: =BL8*BL9 -> 4281.9169 | BQ10: =BQ8*BQ9 -> 4567.2289 | BV10: =BV8*BV9 -> 4546.4598 | CA10: =CA8*CA9 -> 5209.3454 | CF10: =CF8*CF9 -> 6912.1181 | CK10: =CK8*CK9 -> 1251.104 | CP10: =CP8*CP9 -> 339.21403 | CU10: =CU8*CU9 -> 1526.8018 | CZ10: =CZ8*CZ9 -> 2239.7323 | DE10: =DE8*DE9 -> 2273.7191 | DJ10: =DJ8*DJ9 -> 1122.2758 | DO10: =DO8*DO9 -> 2701.0369 | DT10: =DT8*DT9 -> 3300.7063 | DY10: =DY8*DY9 -> 4155.584 | DZ10: =DZ8*DZ9 -> 5165.424 | EA10: =EA8*EA9 -> 6310.276 | EB10: =EB8*EB9 -> 7787.02
B12: B-747 (Units) | C12: 39 | D12: 53 | E12: 47 | F12: 25 | G12: 31 | H12: 27 | I12: 19 | J12: 5 | K12: 4 | L12: 2 | M12: 4 | N12: =+M12+L12+K12+J12 -> 15 | O12: 3 | P12: 4 | Q12: =2+3*0 -> 2 | R12: 4 | S12: =+R12+Q12+P12+O12 -> 13 | T12: 4 | U12: 4 | V12: 3 | W12: 3 | X12: 14 | Y12: 3 | Z12: 4 | AA12: 5 | AB12: 4 | AC12: =SUM(Y12:AB12) -> 16 | AD12: 4 | AE12: 5 | AF12: 4 | AG12: 1 | AH12: =SUM(AD12:AG12) -> 14 | AI12: 4 | AJ12: 2 | AK12: 0 | AL12: 2 | AM12: =SUM(AI12:AL12) -> 8 | AN12: 0 | AO12: 0 | AP12: 0 | AQ12: 0 | AR12: =SUM(AN12:AQ12) -> 0
B13: Unit Price $ | C13: 150 | D13: 150 | E13: 150 | F13: 152 | G13: 155 | H13: 162 | I13: 162 | J13: 164 | K13: 164 | L13: 164 | M13: 164 | N13: 164 | O13: 166 | P13: 166 | Q13: 166 | R13: 166 | S13: 166 | T13: 166 | U13: 166.4 | V13: 166 | W13: 166 | X13: 166 | Y13: 166 | Z13: 166 | AA13: 166 | AB13: 166 | AC13: 166 | AD13: 165 | AE13: 165 | AF13: 165 | AG13: 165 | AH13: 165 | AI13: 165 | AJ13: 165 | AK13: 165 | AL13: 165 | AM13: 165 | AN13: 165 | AO13: 165 | AP13: 165 | AQ13: 165 | AR13: 165
B14: Program Revenue $ | C14: =C13*C12 -> 5850 | D14: =D13*D12 -> 7950 | E14: =E13*E12 -> 7050 | F14: =F13*F12 -> 3800 | G14: =G13*G12 -> 4805 | H14: =H13*H12 -> 4374 | I14: =I13*I12 -> 3078 | J14: =J13*J12 -> 820 | ... M14: =M13*M12 -> 656 | N14: =SUM(J14:M14) -> 2460 | O14: =O13*O12 -> 498 | P14: =P13*P12 -> 664 | Q14: =Q13*Q12 -> 332 | R14: =R13*R12 -> 664 | S14: =SUM(O14:R14) -> 2158 | T14: =T13*T12 -> 664 | U14: =U13*U12 -> 665.6 | V14: =V13*V12 -> 498 | W14: =W13*W12 -> 498 | X14: =SUM(T14:W14) -> 2325.6 | Y14: =Y13*Y12 -> 498 | Z14: =Z13*Z12 -> 664 | AA14: =AA13*AA12 -> 830 | AB14: =AB13*AB12 -> 664 | AC14: =SUM(Y14:AB14) -> 2656 | AD14: =AD13*AD12 -> 660 | AE14: =AE13*AE12 -> 825 | AF14: =AF13*AF12 -> 660 | AG14: =AG13*AG12 -> 165 | AH14: =SUM(AD14:AG14) -> 2310 | AI14: =AI13*AI12 -> 660 | AJ14: =AJ13*AJ12 -> 330 | AK14: =AK13*AK12 -> 0 | AL14: =AL13*AL12 -> 330 | AM14: =SUM(AI14:AL14) -> 1320 | AN14: =AN13*AN12 -> 0 | AO14: =AO13*AO12 -> 0 | AP14: =AP13*AP12 -> 0 | AQ14: =AQ13*AQ12 -> 0 | AR14: =SUM(AN14:AQ14) -> 0
B15: EBIT margin (pre-R&D) | C15: 0.09 | D15: 0.07 | E15: 0.06 | F15: 0.1 | G15: 0.1 | H15: 0.12 | I15: 0.08 | J15: 0.1 | K15: 0.1 | L15: 0.1 | M15: 0.1 | N15: 0.1 | O15: 0.12 | P15: 0.12 | Q15: 0.12 | R15: 0.12 | S15: 0.12 | T15: 0.14 | U15: 0.14 | V15: 0.14 | W15: 0.14 | X15: 0.14 | Y15: 0.145 | Z15: 0.145 | AA15: 0.145 | AB15: 0.145 | AC15: 0.145 | AD15: 0.135 | AE15: 0.135 | AF15: 0.135 | AG15: 0.135 | AH15: 0.135 | AI15: 0.09 | AJ15: 0.09 | AK15: 0.09 | AL15: 0.09 | AM15: 0.09 | AN15: 0.17 | AO15: 0.17 | AP15: 0.17 | AQ15: 0.17 | AR15: 0.17
B16: Program EBIT (pre-R&D) $ | C16: =C14*C15 -> 526.5 | D16: =D14*D15 -> 556.5 | E16: =E14*E15 -> 423 | F16: =F14*F15 -> 380 | G16: =G14*G15 -> 480.5 | H16: =H14*H15 -> 524.88 | I16: =I14*I15 -> 246.24 | J16: =J14*J15 -> 82 | ... AR16: =AR14*AR15 -> 0
B18: B-747-800 (Units) | AN18: 0 | AO18: 0 | AP18: =Commercial!AP42 -> 0 | AQ18: =Commercial!AQ42 -> 0 | AR18: =Commercial!AR42 -> 0 | AS18: =Commercial!AS42 -> 0 | AT18: =Commercial!AT42 -> 0 | AU18: =Commercial!AU42 -> 0 | AV18: =Commercial!AV42 -> 9 | AW18: =Commercial!AW42 -> 9 | ... EB18: =Commercial!EB42 -> 0
B19: Unit Price $ | AN19: 188 | AO19: 188 | AP19: =Commercial!AP44 -> 0 | AQ19: =Commercial!AQ44 -> 0 | AR19: =Commercial!AR44 -> 0 | AS19: =Commercial!AS44 -> 185 | AT19: =Commercial!AT44 -> 185 | AU19: =Commercial!AU44 -> 185 | AV19: =Commercial!AV44 -> 185 | AW19: =Commercial!AW44 -> 185 | ... EB19: =Commercial!EB44 -> 0
B20: Program Revenue $ | AN20: =AN19*AN18 -> 0 | AO20: =AO19*AO18 -> 0 | AP20: =AP19*AP18 -> 0 | AQ20: =AQ19*AQ18 -> 0 | AR20: =SUM(AN20:AQ20) -> 0 | AS20: =AS19*AS18 -> 0 | AT20: =AT19*AT18 -> 0 | AU20: =AU19*AU18 -> 0 | AV20: =AV19*AV18 -> 1665 | AW20: =AW19*AW18 -> 1665 | AX20: =AX19*AX18 -> 1116 | AY20: =AY19*AY18 -> 1302 | AZ20: =AZ19*AZ18 -> 1488 | ... DD20: =DD19*DD18 -> 0 | DE20: =IFERROR(DE19*DE18,"0") -> 175 | DF20: =DF19*DF18 -> 0 | DG20: =DG19*DG18 -> 0 | DH20: =DH19*DH18 -> 0 | DI20: =DI19*DI18 -> 0 | DJ20: =IFERROR(DJ19*DJ18,0) -> 0 | DK20: =DK19*DK18 -> 0 | DL20: =DL19*DL18 -> 0 | DM20: =DM19*DM18 -> 0 | DN20: =DN19*DN18 -> 0 | DO20: =IFERROR(DO19*DO18,0) -> 0 | DP20: =DP19*DP18 -> 0 | DQ20: =DQ19*DQ18 -> 0 | DR20: =DR19*DR18 -> 0 | DS20: =DS19*DS18 -> 0 | DT20: =IFERROR(DT19*DT18,0) -> 0 | DU20: =DU19*DU18 -> 0 | DV20: =DV19*DV18 -> 0 | DW20: =DW19*DW18 -> 0 | DX20: =DX19*DX18 -> 0 | DY20: =IFERROR(DY19*DY18,0) -> 0 | DZ20: =DZ19*DZ18 -> 0 | EA20: =EA19*EA18 -> 0 | EB20: =EB19*EB18 -> 0
B21: EBIT margin (pre-R&D) | AV21: 0.01 | AW21: =AW22/AW20 -> 0.01 | BB21: 0.005 | BG21: 0.005 | BL21: 0.005 | BQ21: 0.004 | BV21: 0.005 | CA21: 0 | CF21: 0 | CK21: 0 | CP21: 0 | CU21: 0 | CZ21: 0 | DE21: 0 | DJ21: 0 | DO21: 0 | DT21: 0 | DY21: 0 | DZ21: 0 | EA21: 0 | EB21: 0
B22: Program EBIT (pre-R&D) $ | AN22: =AN20*AN21 -> 0 | AO22: =AO20*AO21 -> 0 | AP22: =AP20*AP21 -> 0 | AQ22: =AQ20*AQ21 -> 0 | AR22: =AR20*AR21 -> 0 | AS22: =AS20*AS21 -> 0 | AT22: =AT20*AT21 -> 0 | AU22: =AU20*AU21 -> 0 | AV22: =AV20*AV21 -> 16.65 | AW22: =SUM(AS22:AV22) -> 16.65 | BB22: =BB20*BB21 -> 28.83 | BG22: =BG20*BG21 -> 22.44 | BL22: =BL20*BL21 -> 17.86 | BQ22: =BQ20*BQ21 -> 13.48 | BV22: =BV20*BV21 -> 8.36 | CA22: =CA20*CA21 -> 0 | CF22: =CF20*CF21 -> 0 | CK22: =CK20*CK21 -> 0 | CP22: =CP20*CP21 -> 0 | CU22: =CU20*CU21 -> 0 | CZ22: =CZ20*CZ21 -> 0 | DE22: =DE20*DE21 -> 0 | DJ22: =DJ20*DJ21 -> 0 | DO22: =DO20*DO21 -> 0 | DT22: =DT20*DT21 -> 0 | DY22: =DY20*DY21 -> 0 | DZ22: =DZ20*DZ21 -> 0 | EA22: =EA20*EA21 -> 0 | EB22: =EB20*EB21 -> 0
B24: B-757 (Units) | C24: 46 | D24: 54 | E24: 67 | F24: 45 | G24: 45 | H24: 29 | I24: 14 | J24: 4 | K24: 4 | L24: 3 | M24: 0 | N24: =+M24+L24+K24+J24 -> 11 | O24: 1 | P24: 1 | Q24: 0 | R24: 0 | S24: =+R24+Q24+P24+O24 -> 2
B25: Unit Price $ | C25: 48 | D25: 50 | E25: 54 | F25: 54 | G25: 56 | H25: 60 | I25: 60 | J25: 60 | K25: 60 | L25: 60 | M25: 60 | N25: 60 | O25: 60 | P25: 60 | Q25: 60 | R25: 60 | S25: 60 | T25: 60 | U25: 60 | V25: 60 | W25: 60
B26: Program Revenue $ | C26: =C25*C24 -> 2208 | D26: =D25*D24 -> 2700 | E26: =E25*E24 -> 3618 | F26: =F25*F24 -> 2430 | G26: =G25*G24 -> 2520 | H26: =H25*H24 -> 1740 | I26: =I25*I24 -> 840 | J26: =J25*J24 -> 240 | ... M26: =M25*M24 -> 0 | N26: =SUM(J26:M26) -> 660 | O26: =O25*O24 -> 60 | P26: =P25*P24 -> 60 | Q26: =Q25*Q24 -> 0 | R26: =R25*R24 -> 0 | S26: =SUM(O26:R26) -> 120 | T26: =T25*T24 -> 0 | U26: =U25*U24 -> 0 | V26: =V25*V24 -> 0 | W26: =W25*W24 -> 0
B27: EBIT margin (pre-R&D) | C27: 0.09 | D27: 0.05 | E27: 0.055 | F27: 0.1 | G27: 0.09 | H27: 0.11 | I27: 0.07 | J27: 0.08 | K27: 0.08 | L27: 0.08 | M27: 0.08 | N27: 0.08 | O27: 0.09 | P27: 0.09 | Q27: 0.09 | R27: 0.09 | S27: 0.09 | T27: 0.17 | U27: 0.17 | V27: 0.17 | W27: 0.17
B28: Program EBIT (pre-R&D) $ | C28: =C26*C27 -> 198.72 | D28: =D26*D27 -> 135 | E28: =E26*E27 -> 198.99 | F28: =F26*F27 -> 243 | G28: =G26*G27 -> 226.8 | H28: =H26*H27 -> 191.4 | I28: =I26*I27 -> 58.8 | J28: =J26*J27 -> 19.2 | ... S28: =S26*S27 -> 10.8
B30: B-787 (Units) | AS30: =Commercial!AS78 -> 0 | AT30: =Commercial!AT78 -> 0 | AU30: =Commercial!AU78 -> 1 | AV30: =Commercial!AV78 -> 2 | AW30: =Commercial!AW78 -> 3 | AX30: =Commercial!AX78 -> 5 | AY30: =Commercial!AY78 -> 6 | AZ30: =Commercial!AZ78 -> 12 | ... EB30: =Commercial!EB78 -> 175
B31: Unit Price $ | AS31: =Commercial!AS80 -> 100 | AT31: =Commercial!AT80 -> 100 | AU31: =Commercial!AU80 -> 100 | AV31: =Commercial!AV80 -> 100 | AW31: =Commercial!AW80 -> 100 | AX31: =Commercial!AX80 -> 101 | AY31: =Commercial!AY80 -> 101 | AZ31: =Commercial!AZ80 -> 101 | ... EB31: =Commercial!EB80 -> 163.34286
B32: Program Revenue $ | AS32: =AS31*AS30 -> 0 | AT32: =AT31*AT30 -> 0 | AU32: =AU31*AU30 -> 100 | AV32: =AV31*AV30 -> 200 | AW32: =AW31*AW30 -> 300 | AX32: =AX31*AX30 -> 505 | AY32: =AY31*AY30 -> 606 | AZ32: =AZ31*AZ30 -> 1212 | ... CR32: =CR31*CR30 -> 1641.8638 | CU32: =CU31*CU30 -> 1931.9966 | CV32: =CV31*CV30 -> 0 | CW32: =CW31*CW30 -> 0 | CX32: =CX31*CX30 -> 1296.7796 | CY32: =CY31*CY30 -> 3048.5674 | CZ32: =CZ31*CZ30 -> 4345.347 | DA32: =DA31*DA30 -> 1567.0405 | DB32: =DB31*DB30 -> 2867.4502 | ... EB32: =EB31*EB30 -> 28585
B33: EBIT margin (pre-R&D) | AU33: 0.01 | AV33: 0.01 | AW33: =AW34/AW32 -> 0.01 | BB33: 0.005 | BG33: 0.01 | BL33: 0.01 | BQ33: 0.01 | BV33: 0.017 | CA33: 0.03 | CF33: 0.09 | CK33: 0.12 | CP33: 0.08 | CU33: 0 | CZ33: 0 | DE33: 0.01 | DJ33: 0.02 | DO33: 0.03 | DT33: 0.07 | DY33: 0.08 | DZ33: 0.1 | EA33: 0.15 | EB33: 0.2
B34: Program EBIT (pre-R&D) $ | AS34: =AS32*AS33 -> 0 | AT34: =AT32*AT33 -> 0 | AU34: =AU32*AU33 -> 1 | AV34: =AV32*AV33 -> 2 | AW34: =SUM(AS34:AV34) -> 3 | BB34: =BB32*BB33 -> 23.23 | BG34: =BG32*BG33 -> 66.3 | BL34: =BL32*BL33 -> 115.0194 | BQ34: =BQ32*BQ33 -> 156.4317 | BV34: =BV32*BV33 -> 286.20393 | CA34: =CA32*CA33 -> 522.23925 | CF34: =CF32*CF33 -> 1815.5992 | CK34: =CK32*CK33 -> 2684.9626 | CP34: =CP32*CP33 -> 604.58442 | CU34: =CU32*CU33 -> 0 | CZ34: =CZ32*CZ33 -> 0 | DE34: =DE32*DE33 -> 108.25746 | DJ34: =DJ32*DJ33 -> 155.76095 | DO34: =DO32*DO33 -> 395.89022 | DT34: =DT32*DT33 -> 1038.352 | DY34: =DY32*DY33 -> 1586.736 | DZ34: =DZ32*DZ33 -> 2264 | EA34: =EA32*EA33 -> 3988.5 | EB34: =EB32*EB33 -> 5717
B36: B-767 (Units) | C36: 41 | D36: 47 | E36: 44 | F36: 44 | G36: 40 | H36: 35 | I36: 24 | J36: 1 | K36: 3 | L36: 2 | M36: 3 | N36: =+M36+L36+K36+J36 -> 9 | O36: 1 | P36: 4 | Q36: =2+3*0 -> 2 | R36: 3 | S36: =+R36+Q36+P36+O36 -> 10 | T36: 3 | U36: 3 | V36: 3 | W36: 3 | X36: 12 | Y36: 3 | Z36: 3 | AA36: 3 | AB36: 3 | AC36: =SUM(Y36:AB36) -> 12 | AD36: 3 | AE36: 3 | AF36: 2 | AG36: 2 | AH36: =SUM(AD36:AG36) -> 10 | AI36: 3 | AJ36: 3 | AK36: 4 | AL36: 3 | AM36: =SUM(AI36:AL36) -> 13 | AN36: 3 | AO36: 3 | AP36: =Commercial!AP52 -> 3 | AQ36: =Commercial!AQ52 -> 3 | AR36: =Commercial!AR52 -> 12 | AS36: =Commercial!AS52 -> 4 | AT36: =Commercial!AT52 -> 5 | AU36: =Commercial!AU52 -> 5 | AV36: =Commercial!AV52 -> 6 | AW36: =Commercial!AW52 -> 20 | ... EB36: =Commercial!EB52 -> 30
B37: Unit Price $ | C37: 82.5 | D37: 83 | E37: 84 | F37: 85 | G37: 88 | H37: 88 | I37: 90 | J37: 92 | K37: 92 | L37: 92 | M37: 92 | N37: 92 | O37: 94 | P37: 94 | Q37: 94 | R37: 94 | S37: 94 | T37: 90 | U37: 90 | V37: 90 | W37: 90 | X37: 90 | Y37: 85 | Z37: 85 | AA37: 85 | AB37: 85 | AC37: 85 | AD37: 86 | AE37: 87 | AF37: 87 | AG37: 87 | AH37: 87 | AI37: 87 | AJ37: 87 | AK37: 87 | AL37: 87 | AM37: 87 | AN37: 86 | AO37: 86 | AP37: =Commercial!AP54 -> 87 | AQ37: =Commercial!AQ54 -> 87 | AR37: =Commercial!AR54 -> 86.5 | AS37: =Commercial!AS54 -> 88 | AT37: =Commercial!AT54 -> 88 | AU37: =Commercial!AU54 -> 89 | AV37: =Commercial!AV54 -> 89 | AW37: =Commercial!AW54 -> 88.55 | ... EB37: =Commercial!EB54 -> 92
B38: Program Revenue $ | C38: =C37*C36 -> 3382.5 | D38: =D37*D36 -> 3901 | E38: =E37*E36 -> 3696 | F38: =F37*F36 -> 3740 | G38: =G37*G36 -> 3520 | H38: =H37*H36 -> 3080 | I38: =I37*I36 -> 2160 | J38: =J37*J36 -> 92 | ... M38: =M37*M36 -> 276 | N38: =SUM(J38:M38) -> 828 | O38: =O37*O36 -> 94 | P38: =P37*P36 -> 376 | Q38: =Q37*Q36 -> 188 | R38: =R37*R36 -> 282 | S38: =SUM(O38:R38) -> 940 | T38: =T37*T36 -> 270 | U38: =U37*U36 -> 270 | V38: =V37*V36 -> 270 | W38: =W37*W36 -> 270 | X38: =SUM(T38:W38) -> 1080 | Y38: =Y37*Y36 -> 255 | Z38: =Z37*Z36 -> 255 | AA38: =AA37*AA36 -> 255 | AB38: =AB37*AB36 -> 255 | AC38: =SUM(Y38:AB38) -> 1020 | AD38: =AD37*AD36 -> 258 | AE38: =AE37*AE36 -> 261 | AF38: =AF37*AF36 -> 174 | AG38: =AG37*AG36 -> 174 | AH38: =SUM(AD38:AG38) -> 867 | AI38: =AI37*AI36 -> 261 | AJ38: =AJ37*AJ36 -> 261 | AK38: =AK37*AK36 -> 348 | AL38: =AL37*AL36 -> 261 | AM38: =SUM(AI38:AL38) -> 1131 | AN38: =AN37*AN36 -> 258 | AO38: =AO37*AO36 -> 258 | AP38: =AP37*AP36 -> 261 | AQ38: =AQ37*AQ36 -> 261 | AR38: =SUM(AN38:AQ38) -> 1038 | AS38: =AS37*AS36 -> 352 | AT38: =AT37*AT36 -> 440 | AU38: =AU37*AU36 -> 445 | AV38: =AV37*AV36 -> 534 | AW38: =AW37*AW36 -> 1771 | AX38: =AX37*AX36 -> 630 | AY38: =AY37*AY36 -> 540 | AZ38: =AZ37*AZ36 -> 630 | ... EB38: =EB37*EB36 -> 2760
B39: EBIT margin (pre-R&D) | C39: 0.08 | D39: 0.07 | E39: 0.07 | F39: 0.1 | G39: 0.07 | H39: 0.115 | I39: 0.07 | J39: 0.07 | K39: 0.07 | L39: 0.07 | M39: 0.07 | N39: 0.07 | O39: 0.1 | P39: 0.1 | Q39: 0.1 | R39: 0.1 | S39: 0.1 | T39: 0.12 | U39: 0.12 | V39: 0.12 | W39: 0.12 | X39: 0.12 | Y39: 0.115 | Z39: 0.115 | AA39: 0.115 | AB39: 0.115 | AC39: 0.115 | AD39: 0.1 | AE39: 0.1 | AF39: 0.1 | AG39: 0.1 | AH39: 0.1 | AI39: 0.1 | AJ39: 0.1 | AK39: 0.1 | AL39: 0.1 | AM39: 0.1 | AN39: 0.12 | AO39: 0.12 | AP39: 0.12 | AQ39: 0.12 | AR39: =AR40/AR38 -> 0.12 | AS39: 0.12 | AT39: 0.12 | AU39: 0.12 | AV39: 0.12 | AW39: =AW40/AW38 -> 0.12 | BB39: 0.08 | BG39: 0.07 | BL39: 0.07 | BQ39: 0.07 | BV39: 0.07 | CA39: 0.09 | CF39: 0.1 | CK39: 0.1 | CP39: 0.08 | CU39: 0.09 | CZ39: 0.09 | DE39: 0.095 | DJ39: 0.1 | DO39: 0.1 | DT39: 0.1 | DY39: 0.1 | DZ39: 0.1 | EA39: 0.1 | EB39: 0.1
B40: Program EBIT (pre-R&D) $ | C40: =C38*C39 -> 270.6 | D40: =D38*D39 -> 273.07 | E40: =E38*E39 -> 258.72 | F40: =F38*F39 -> 374 | G40: =G38*G39 -> 246.4 | H40: =H38*H39 -> 354.2 | I40: =I38*I39 -> 151.2 | J40: =J38*J39 -> 6.44 | ... AQ40: =AQ38*AQ39 -> 31.32 | AR40: =SUM(AN40:AQ40) -> 124.56 | AS40: =AS38*AS39 -> 42.24 | AT40: =AT38*AT39 -> 52.8 | AU40: =AU38*AU39 -> 53.4 | AV40: =AV38*AV39 -> 64.08 | AW40: =SUM(AS40:AV40) -> 212.52 | BB40: =BB38*BB39 -> 187.2 | BG40: =BG38*BG39 -> 133.77 | BL40: =BL38*BL39 -> 38.22 | BQ40: =BQ38*BQ39 -> 102.06 | BV40: =BV38*BV39 -> 83.72 | CA40: =CA38*CA39 -> 82.8 | CF40: =CF38*CF39 -> 248.4 | CK40: =CK38*CK39 -> 395.6 | CP40: =CP38*CP39 -> 220.8 | CU40: =CU38*CU39 -> 264.96 | CZ40: =CZ38*CZ39 -> 273.24 | DE40: =DE38*DE39 -> 279.68 | DJ40: =DJ38*DJ39 -> 165.6 | DO40: =DO38*DO39 -> 276 | DT40: =DT38*DT39 -> 257.6 | DY40: =DY38*DY39 -> 248.4 | DZ40: =DZ38*DZ39 -> 257.6 | EA40: =EA38*EA39 -> 276 | EB40: =EB38*EB39 -> 276
B42: B-777 (Units) | C42: 59 | D42: 74 | E42: 83 | F42: 55 | G42: 61 | H42: 47 | I42: 39 | J42: 8 | K42: 11 | L42: 8 | M42: 9 | N42: =+M42+L42+K42+J42 -> 36 | O42: 8 | P42: 14 | Q42: =8+12*0 -> 8 | R42: 10 | S42: =+R42+Q42+P42+O42 -> 40 | T42: 17 | U42: 17 | V42: 13 | W42: =+X42-V42-U42-T42 -> 18 | X42: 65 | Y42: 17 | Z42: 21 | AA42: 20 | AB42: 25 | AC42: =SUM(Y42:AB42) -> 83 | AD42: 21 | AE42: 18 | AF42: 11 | AG42: 11 | AH42: =SUM(AD42:AG42) -> 61 | AI42: 23 | AJ42: 21 | AK42: 19 | AL42: 25 | AM42: =SUM(AI42:AL42) -> 88 | AN42: 19 | AO42: 16 | AP42: =Commercial!AP67 -> 21 | AQ42: =Commercial!AQ67 -> 18 | AR42: =Commercial!AR67 -> 74 | AS42: =Commercial!AS67 -> 13 | AT42: =Commercial!AT67 -> 19 | AU42: =Commercial!AU67 -> 21 | AV42: =Commercial!AV67 -> 20 | AW42: =Commercial!AW67 -> 73 | ... EB42: =Commercial!EB67 -> 65
B43: Unit Price $ | C43: 112.5 | D43: 112 | E43: 118.5 | F43: 120 | G43: 126 | H43: 132 | I43: 135 | J43: 138 | K43: 138 | L43: 138 | M43: 138 | N43: 138 | O43: 141 | P43: 141 | Q43: 141 | R43: 141 | S43: 141 | T43: 141 | U43: 141.4 | V43: 141 | W43: 141 | X43: 141 | Y43: 141 | Z43: 141 | AA43: 141 | AB43: 141 | AC43: 141 | AD43: 143 | AE43: 143 | AF43: 143 | AG43: 143 | AH43: 143 | AI43: 143 | AJ43: 143 | AK43: 143 | AL43: 143 | AM43: 141 | AN43: 141 | AO43: 141 | AP43: =Commercial!AP69 -> 142 | AQ43: =Commercial!AQ69 -> 142 | AR43: =Commercial!AR69 -> 141.52703 | AS43: =Commercial!AS69 -> 144 | AT43: =Commercial!AT69 -> 144 | AU43: =Commercial!AU69 -> 144 | AV43: =Commercial!AV69 -> 144 | AW43: =Commercial!AW69 -> 144 | ... DE43: =Commercial!DE69 -> 107.0281 | DF43: 0 | DG43: =Commercial!DG69 -> 106.21297 | DH43: =Commercial!DH69 -> 106.21297 | DI43: =Commercial!DI69 -> 112.21574 | DJ43: =Commercial!DJ69 -> 107.49928 | DK43: =Commercial!DK69 -> 106.21297 | DL43: =Commercial!DL69 -> 106.21297 | DM43: =Commercial!DM69 -> 106.21297 | DN43: =Commercial!DN69 -> 106.21297 | ... EB43: =Commercial!EB69 -> 186.46154
B44: Program Revenue $ | C44: =C43*C42 -> 6637.5 | D44: =D43*D42 -> 8288 | E44: =E43*E42 -> 9835.5 | F44: =F43*F42 -> 6600 | G44: =G43*G42 -> 7686 | H44: =H43*H42 -> 6204 | I44: =I43*I42 -> 5265 | J44: =J43*J42 -> 1104 | ... M44: =M43*M42 -> 1242 | N44: =SUM(J44:M44) -> 4968 | O44: =O43*O42 -> 1128 | P44: =P43*P42 -> 1974 | Q44: =Q43*Q42 -> 1128 | R44: =R43*R42 -> 1410 | S44: =SUM(O44:R44) -> 5640 | T44: =T43*T42 -> 2397 | U44: =U43*U42 -> 2403.8 | V44: =V43*V42 -> 1833 | W44: =W43*W42 -> 2538 | X44: =SUM(T44:W44) -> 9171.8 | Y44: =Y43*Y42 -> 2397 | Z44: =Z43*Z42 -> 2961 | AA44: =AA43*AA42 -> 2820 | AB44: =AB43*AB42 -> 3525 | AC44: =SUM(Y44:AB44) -> 11703 | AD44: =AD43*AD42 -> 3003 | AE44: =AE43*AE42 -> 2574 | AF44: =AF43*AF42 -> 1573 | AG44: =AG43*AG42 -> 1573 | AH44: =SUM(AD44:AG44) -> 8723 | AI44: =AI43*AI42 -> 3289 | AJ44: =AJ43*AJ42 -> 3003 | AK44: =AK43*AK42 -> 2717 | AL44: =AL43*AL42 -> 3575 | AM44: =SUM(AI44:AL44) -> 12584 | AN44: =AN43*AN42 -> 2679 | AO44: =AO43*AO42 -> 2256 | AP44: =AP43*AP42 -> 2982 | AQ44: =AQ43*AQ42 -> 2556 | AR44: =SUM(AN44:AQ44) -> 10473 | AS44: =AS43*AS42 -> 1872 | AT44: =AT43*AT42 -> 2736 | AU44: =AU43*AU42 -> 3024 | AV44: =AV43*AV42 -> 2880 | AW44: =AW43*AW42 -> 10512 | AX44: =AX43*AX42 -> 2880 | AY44: =AY43*AY42 -> 3190 | AZ44: =AZ43*AZ42 -> 2900 | ... EB44: =EB43*EB42 -> 12120
B45: EBIT margin (pre-R&D) | C45: 0.11 | D45: 0.085 | E45: 0.09 | F45: 0.13 | G45: 0.13 | H45: 0.14 | I45: 0.085 | J45: 0.097 | K45: 0.097 | L45: 0.097 | M45: 0.097 | N45: 0.097 | O45: 0.15 | P45: 0.15 | Q45: 0.15 | R45: 0.15 | S45: 0.15 | T45: 0.19 | U45: 0.19 | V45: 0.19 | W45: 0.19 | X45: 0.215 | Y45: 0.2 | Z45: 0.2 | AA45: 0.2 | AB45: 0.2 | AC45: 0.24 | AD45: 0.2 | AE45: 0.2 | AF45: 0.2 | AG45: 0.2 | AH45: 0.2 | AI45: 0.18 | AJ45: 0.18 | AK45: 0.18 | AL45: 0.18 | AM45: 0.18 | AN45: 0.21 | AO45: 0.21 | AP45: 0.21 | AQ45: 0.21 | AR45: =AR46/AR44 -> 0.21 | AS45: 0.21 | AT45: 0.21 | AU45: 0.21 | AV45: 0.21 | AW45: =AW46/AW44 -> 0.21 | BB45: 0.2 | BG45: 0.2 | BL45: 0.2 | BQ45: 0.2 | BV45: 0.19 | CA45: 0.18 | CF45: 0.17 | CK45: 0.165 | CP45: 0.1 | CU45: 0.08 | CZ45: 0.05 | DE45: 0.055 | DJ45: 0.05 | DO45: 0 | DT45: 0.005 | DY45: 0.01 | DZ45: 0.03 | EA45: 0.06 | EB45: 0.1
B46: Program EBIT (pre-R&D) $ | C46: =C44*C45 -> 730.125 | D46: =D44*D45 -> 704.48 | E46: =E44*E45 -> 885.195 | F46: =F44*F45 -> 858 | G46: =G44*G45 -> 999.18 | H46: =H44*H45 -> 868.56 | I46: =I44*I45 -> 447.525 | J46: =J44*J45 -> 107.088 | ... AQ46: =AQ44*AQ45 -> 536.76 | AR46: =SUM(AN46:AQ46) -> 2199.33 | AS46: =AS44*AS45 -> 393.12 | AT46: =AT44*AT45 -> 574.56 | AU46: =AU44*AU45 -> 635.04 | AV46: =AV44*AV45 -> 604.8 | AW46: =SUM(AS46:AV46) -> 2207.52 | BB46: =BB44*BB45 -> 2403 | BG46: =BG44*BG45 -> 2861.6 | BL46: =BL44*BL45 -> 3152.588 | BQ46: =BQ44*BQ45 -> 3033.122 | BV46: =BV44*BV45 -> 2821.5836 | CA46: =CA44*CA45 -> 1937.0084 | CF46: =CF44*CF45 -> 1109.5424 | CK46: =CK44*CK45 -> 942.7275 | CP46: =CP44*CP45 -> 308.19262 | CU46: =CU44*CU45 -> 226.62231 | CZ46: =CZ44*CZ45 -> 131.08174 | DE46: =DE44*DE45 -> 153.05019 | DJ46: =DJ44*DJ45 -> 75.249493 | DO46: =DO44*DO45 -> 0 | DT46: =DT44*DT45 -> 9.0281023 | DY46: =DY44*DY45 -> 51.691947 | DZ46: =DZ44*DZ45 -> 246.85278 | EA46: =EA44*EA45 -> 665.64 | EB46: =EB44*EB45 -> 1212
B48: B-717 (Units) | E48: 12 | F48: 32 | G48: 49 | H48: 20 | I48: 12 | J48: 3 | K48: 3 | L48: 3 | M48: 3 | N48: =+M48+L48+K48+J48 -> 12 | O48: 3 | P48: 3 | Q48: 3 | R48: 4 | S48: =+R48+Q48+P48+O48 -> 13 | T48: 2 | U48: 3 | V48: 0 | W48: =+X48-V48-U48-T48 -> 0 | X48: 5 | Y48: 0 | Z48: 0 | AA48: 0 | AB48: 0
B49: Unit Price $ | E49: 22 | F49: 22 | G49: 23 | H49: 24 | I49: 25 | J49: 26 | K49: 26 | L49: 26 | M49: 26 | N49: 26 | O49: 27 | P49: 27 | Q49: 27 | R49: 27 | S49: 27 | T49: 27 | U49: 27.4 | V49: 27 | W49: 27 | X49: 27 | Y49: 28 | Z49: 28 | AA49: 28 | AB49: 28
B50: Program Revenue $ | E50: 264 | F50: 704 | G50: 1127 | H50: 480 | I50: 300 | J50: =J48*J49 -> 78 | K50: =K48*K49 -> 78 | L50: =L48*L49 -> 78 | M50: =M48*M49 -> 78 | N50: =SUM(J50:M50) -> 312 | O50: =O48*O49 -> 81 | P50: =P48*P49 -> 81 | Q50: =Q48*Q49 -> 81 | R50: =R48*R49 -> 108 | S50: =SUM(O50:R50) -> 351 | T50: =T48*T49 -> 54 | U50: =U48*U49 -> 82.2 | V50: =V48*V49 -> 0 | W50: =W48*W49 -> 0 | X50: =SUM(T50:W50) -> 136.2 | Y50: =Y48*Y49 -> 0 | Z50: =Z48*Z49 -> 0 | AA50: =AA48*AA49 -> 0 | AB50: =AB48*AB49 -> 0
B51: EBIT margin (pre-R&D) | E51: 0.09 | F51: 0.1 | G51: 0.1 | H51: 0.125 | I51: 0.05 | J51: 0.05 | K51: 0.05 | L51: 0.05 | M51: 0.05 | N51: 0.05 | O51: 0.1 | P51: 0.1 | Q51: 0.1 | R51: 0.1 | S51: 0.1 | T51: 0.1 | U51: 0.1 | V51: 0.1 | W51: 0.1 | X51: 0.1 | Y51: 0.12 | Z51: 0.12 | AA51: 0.12 | AB51: 0.12
B52: Program EBIT (pre-R&D) $ | E52: =E50*E51 -> 23.76 | F52: =F50*F51 -> 70.4 | G52: =G50*G51 -> 112.7 | H52: =H50*H51 -> 60 | I52: =I50*I51 -> 15 | J52: =J50*J51 -> 3.9 | K52: =K50*K51 -> 3.9 | L52: =L50*L51 -> 3.9 | ... X52: =X50*X51 -> 13.62
B54: MDs (Units) | C54: =16+26+12 -> 54 | D54: =8+34+12 -> 54 | E54: =26+13+8 -> 47 | F54: 7 | G54: 2
B55: Unit Price $ | C55: 28 | D55: 30 | E55: 30 | F55: 30 | G55: 30
B56: Program Revenue $ | C56: =C55*C54 -> 1512 | D56: =D55*D54 -> 1620 | E56: =E55*E54 -> 1410 | F56: =F55*F54 -> 210 | G56: =G55*G54 -> 60
B57: EBIT margin (pre-R&D) | C57: 0.08 | D57: 0.07 | E57: 0.07 | F57: 0.1 | G57: 0.08 | Y57: 0.12 | Z57: 0.12 | AA57: 0.12 | AB57: 0.12
B58: Program EBIT (pre-R&D) $ | C58: =C56*C57 -> 120.96 | D58: =D56*D57 -> 113.4 | E58: =E56*E57 -> 98.7 | F58: =F56*F57 -> 21 | G58: =G56*G57 -> 4.8
B60: Military eliminations | CB60: =Commercial!CB111 -> -707.5 | CC60: =Commercial!CC111 -> -529.5 | CD60: =Commercial!CD111 -> -1205 | CE60: =Commercial!CE111 -> -775 | CF60: =Commercial!CF111 -> -3217 | CG60: =Commercial!CG111 -> -800 | CH60: =Commercial!CH111 -> -700 | CI60: =Commercial!CI111 -> -800 | ... EB60: =Commercial!EB111 -> -2590
B61: Adjustment | BR61: =Commercial!BR112 -> -518 | BS61: =Commercial!BS112 -> 13 | BT61: =Commercial!BT112 -> 386 | BU61: =Commercial!BU112 -> 141 | BV61: =Commercial!BV112 -> 22 | BW61: =Commercial!BW112 -> -68 | BX61: =Commercial!BX112 -> 127 | BY61: =Commercial!BY112 -> 360 | ... EB61: =Commercial!EB112 -> -1760
B63: Total Delivery Revenue | C63: =C8+C14+C20+C26+C32+C38+C44+C50+C56 -> 23910 | D63: =D8+D14+D20+D26+D32+D38+D44+D50+D56 -> 32889 | E63: =E8+E14+E20+E26+E32+E38+E44+E50+E56 -> 35153.5 | F63: =F8+F14+F20+F26+F32+F38+F44+F50+F56 -> 26195 | G63: =G8+G14+G20+G26+G32+G38+G44+G50+G56 -> 29734.5 | H63: =H8+H14+H20+H26+H32+H38+H44+H50+H56 -> 24491 | I63: =I8+I14+I20+I26+I32+I38+I44+I50+I56 -> 18563 | J63: =J8+J14+J20+J26+J32+J38+J44+J50+J56 -> 4589 | ... EB63: =EB8+EB14+EB20+EB26+EB32+EB38+EB44+EB50+EB56 -> 89271
B65: Aviall | W65: 350 | X65: 350 | Y65: 405 | Z65: 405 | AA65: 405 | AB65: 405 | AC65: 1620 | AD65: 400 | AE65: 400 | AF65: 400 | AG65: 400 | AH65: 1600 | AI65: 380 | AJ65: 380 | AK65: 380 | AL65: 400 | AM65: =SUM(AI65:AL65) -> 1540 | AN65: 360 | AO65: 370 | AP65: 380 | AQ65: =Commercial!AQ117 -> 500 | AR65: =SUM(AN65:AQ65) -> 1610 | AS65: =Commercial!AS117 -> 400 | AT65: =Commercial!AT117 -> 420 | AU65: =Commercial!AU117 -> 480 | AV65: =Commercial!AV117 -> 550 | AW65: =SUM(AS65:AV65) -> 1850 | AX65: =Commercial!AX117 -> 410 | AY65: =Commercial!AY117 -> 440 | AZ65: =Commercial!AZ117 -> 500 | BA65: =Commercial!BA117 -> 570 | BB65: =Commercial!BB117 -> 1920 | BC65: =Commercial!BC117 -> 414.1 | BD65: =Commercial!BD117 -> 448.8 | BE65: =Commercial!BE117 -> 525 | ... BQ65: =Commercial!BQ117 -> 2248.5582
B66: EBIT margin | T66: 0.12 | U66: 0.12 | V66: 0.12 | W66: 0.12 | X66: 0.12 | Y66: 0.128 | Z66: 0.128 | AA66: 0.128 | AB66: 0.128 | AC66: 0.128 | AD66: 0.125 | AE66: 0.125 | AF66: 0.125 | AG66: 0.125 | AH66: 0.125 | AI66: 0.123 | AJ66: 0.123 | AK66: 0.123 | AL66: 0.123 | AM66: 0.123 | AN66: 0.15 | AO66: 0.15 | AP66: 0.15 | AQ66: 0.15 | AR66: =AR67/AR65 -> 0.15 | AS66: 0.15 | AT66: 0.15 | AU66: 0.15 | AV66: 0.15 | AW66: =AW67/AW65 -> 0.15 | BB66: 0.13 | BG66: 0.13 | BL66: 0.13 | BQ66: 0.13
B67: Aviall EBIT | T67: =T65*T66 -> 0 | U67: =U65*U66 -> 0 | V67: =V65*V66 -> 0 | W67: =W65*W66 -> 42 | X67: =X65*X66 -> 42 | Y67: =Y65*Y66 -> 51.84 | Z67: =Z65*Z66 -> 51.84 | AA67: =AA65*AA66 -> 51.84 | ... AQ67: =AQ65*AQ66 -> 75 | AR67: =SUM(AN67:AQ67) -> 241.5 | AS67: =AS65*AS66 -> 60 | AT67: =AT65*AT66 -> 63 | AU67: =AU65*AU66 -> 72 | AV67: =AV65*AV66 -> 82.5 | AW67: =SUM(AS67:AV67) -> 277.5 | BB67: =BB65*BB66 -> 249.6 | BG67: =BG65*BG66 -> 259.714 | BL67: =BL65*BL66 -> 277.39166 | BQ67: =BQ65*BQ66 -> 292.31257
B69: Support Service Revenue | C69: 1399 | D69: 1650 | E69: 1190 | F69: 2055 | G69: 2451 | H69: 2100 | I69: 2006 | J69: 371 | K69: 430 | L69: 380 | M69: 590 | N69: =SUM(J69:M69) -> 1771 | O69: 452 | P69: 590 | Q69: 610 | R69: 605 | S69: =SUM(O69:R69) -> 2257 | T69: 385 | U69: 438 | V69: 422 | W69: 430 | X69: =SUM(T69:W69) -> 1675 | Y69: 405 | Z69: 420 | AA69: 415 | AB69: 415 | AC69: =SUM(Y69:AB69) -> 1655 | AD69: 409.5 | AE69: 409.5 | AF69: 409.5 | AG69: 409.5 | AH69: =SUM(AD69:AG69) -> 1638 | AI69: 370 | AJ69: 370 | AK69: 370 | AL69: 390 | AM69: =SUM(AI69:AL69) -> 1500 | AN69: 370 | AO69: 380 | AP69: 390 | AQ69: =Commercial!AQ123 -> 480 | AR69: =SUM(AN69:AQ69) -> 1620 | AS69: =Commercial!AS123 -> 410 | AT69: =Commercial!AT123 -> 420 | AU69: =Commercial!AU123 -> 480 | AV69: =Commercial!AV123 -> 540 | AW69: =SUM(AS69:AV69) -> 1850 | AX69: =Commercial!AX123 -> 420 | AY69: =Commercial!AY123 -> 440 | AZ69: =Commercial!AZ123 -> 500 | BA69: =Commercial!BA123 -> 560 | BB69: =Commercial!BB123 -> 1920 | BC69: =Commercial!BC123 -> 424.2 | BD69: =Commercial!BD123 -> 448.8 | BE69: =Commercial!BE123 -> 505 | ... BQ69: =Commercial!BQ123 -> 2221.8589
B70: EBIT margin | C70: 0.11 | D70: 0.07 | E70: 0.07 | F70: 0.08 | G70: 0.08 | H70: 0.12 | I70: 0.12 | J70: 0.125 | K70: 0.125 | L70: 0.125 | M70: 0.125 | N70: 0.125 | O70: 0.15 | P70: 0.15 | Q70: 0.15 | R70: 0.15 | S70: 0.15 | T70: 0.16 | U70: 0.16 | V70: 0.16 | W70: 0.16 | X70: 0.16 | Y70: 0.165 | Z70: 0.165 | AA70: 0.165 | AB70: 0.165 | AC70: 0.16 | AD70: 0.165 | AE70: 0.165 | AF70: 0.165 | AG70: 0.165 | AH70: 0.165 | AI70: 0.16 | AJ70: 0.16 | AK70: 0.16 | AL70: 0.16 | AM70: 0.16 | AN70: 0.18 | AO70: 0.18 | AP70: 0.18 | AQ70: 0.18 | AR70: =AR71/AR69 -> 0.18 | AS70: 0.18 | AT70: 0.18 | AU70: 0.18 | AV70: 0.18 | AW70: =AW71/AW69 -> 0.18 | BB70: 0.16 | BG70: 0.16 | BL70: 0.16 | BQ70: 0.16
B71: Support EBIT | C71: =C69*C70 -> 153.89 | D71: =D69*D70 -> 115.5 | E71: =E69*E70 -> 83.3 | F71: =F69*F70 -> 164.4 | G71: =G69*G70 -> 196.08 | H71: =H69*H70 -> 252 | I71: =I69*I70 -> 240.72 | J71: =J69*J70 -> 46.375 | ... AQ71: =AQ69*AQ70 -> 86.4 | AR71: =SUM(AN71:AQ71) -> 291.6 | AS71: =AS69*AS70 -> 73.8 | AT71: =AT69*AT70 -> 75.6 | AU71: =AU69*AU70 -> 86.4 | AV71: =AV69*AV70 -> 97.2 | AW71: =SUM(AS71:AV71) -> 333 | BB71: =BB69*BB70 -> 307.2 | BG71: =BG69*BG70 -> 313.664 | BL71: =BL69*BL70 -> 337.2272 | BQ71: =BQ69*BQ70 -> 355.49742
B73: Spares Revenue | C73: 1500 | D73: 1503 | E73: 1300 | F73: 2555 | G73: 2700 | H73: 1796 | I73: 1839 | J73: 370 | K73: 423 | L73: 375 | M73: 588 | N73: =SUM(J73:M73) -> 1756 | O73: 460 | P73: 583 | Q73: 602 | R73: 636 | S73: =SUM(O73:R73) -> 2281 | T73: 336 | U73: 380 | V73: 380 | W73: 380 | X73: =SUM(T73:W73) -> 1476 | Y73: 380 | Z73: 380 | AA73: 380 | AB73: 392 | AC73: =SUM(Y73:AB73) -> 1532 | AD73: =1224/4 -> 306 | AE73: =1224/4 -> 306 | AF73: =1224/4 -> 306 | AG73: =1224/4 -> 306 | AH73: =SUM(AD73:AG73) -> 1224 | AI73: 180 | AJ73: 180 | AK73: 184 | AL73: 180 | AM73: =SUM(AI73:AL73) -> 724 | AN73: 361 | AO73: 360 | AP73: 380 | AQ73: =Commercial!AQ126 -> 480 | AR73: =SUM(AN73:AQ73) -> 1581 | AS73: =Commercial!AS126 -> 400 | AT73: =Commercial!AT126 -> 420 | AU73: =Commercial!AU126 -> 490 | AV73: =Commercial!AV126 -> 510 | AW73: =SUM(AS73:AV73) -> 1820 | AX73: =Commercial!AX126 -> 410 | AY73: =Commercial!AY126 -> 440 | AZ73: =Commercial!AZ126 -> 500 | BA73: =Commercial!BA126 -> 520 | BB73: =Commercial!BB126 -> 1870 | BC73: =Commercial!BC126 -> 414.1 | BD73: =Commercial!BD126 -> 448.8 | BE73: =Commercial!BE126 -> 515 | ... BQ73: =Commercial!BQ126 -> 2148.4213
B74: EBIT margin | C74: 0.1 | D74: 0.08 | E74: 0.07 | F74: 0.09 | G74: 0.08 | H74: 0.125 | I74: 0.11 | J74: 0.11 | K74: 0.11 | L74: 0.11 | M74: 0.11 | N74: 0.11 | O74: 0.15 | P74: 0.15 | Q74: 0.15 | R74: 0.15 | S74: 0.13 | T74: 0.16 | U74: 0.16 | V74: 0.16 | W74: 0.16 | X74: 0.16 | Y74: 0.17 | Z74: 0.17 | AA74: 0.17 | AB74: 0.17 | AC74: 0.165 | AD74: 0.165 | AE74: 0.165 | AF74: 0.165 | AG74: 0.165 | AH74: 0.165 | AI74: 0.09 | AJ74: 0.09 | AK74: 0.09 | AL74: 0.09 | AM74: 0.1 | AN74: 0.15 | AO74: 0.15 | AP74: 0.15 | AQ74: 0.15 | AR74: =AR75/AR73 -> 0.15 | AS74: 0.15 | AT74: 0.15 | AU74: 0.15 | AV74: 0.15 | AW74: =AW75/AW73 -> 0.15 | BB74: 0.127 | BG74: 0.13 | BL74: 0.13 | BQ74: 0.13
B75: Spares EBIT | C75: =C73*C74 -> 150 | D75: =D73*D74 -> 120.24 | E75: =E73*E74 -> 91 | F75: =F73*F74 -> 229.95 | G75: =G73*G74 -> 216 | H75: =H73*H74 -> 224.5 | I75: =I73*I74 -> 202.29 | J75: =J73*J74 -> 40.7 | ... AQ75: =AQ73*AQ74 -> 72 | AR75: =SUM(AN75:AQ75) -> 237.15 | AS75: =AS73*AS74 -> 60 | AT75: =AT73*AT74 -> 63 | AU75: =AU73*AU74 -> 73.5 | AV75: =AV73*AV74 -> 76.5 | AW75: =SUM(AS75:AV75) -> 273 | BB75: =BB73*BB74 -> 237.49 | BG75: =BG73*BG74 -> 250.107 | BL75: =BL73*BL74 -> 262.95529 | BQ75: =BQ73*BQ74 -> 279.29477
B77: Total BCA Revenue | C77: =C63+C65+C69+C73 -> 26809 | D77: =D63+D65+D69+D73 -> 36042 | E77: =E63+E65+E69+E73 -> 37643.5 | F77: =F63+F65+F69+F73 -> 30805 | G77: =G63+G65+G69+G73 -> 34885.5 | H77: =H63+H65+H69+H73 -> 28387 | I77: =I63+I65+I69+I73 -> 22408 | J77: =J63+J65+J69+J73 -> 5330 | ... BG77: =BG63+BG65+BG69+BG73 -> 53019.1 | BH77: =BH63+BH65+BH69+BH73+1 -> 13017.248 | BI77: =BI63+BI65+BI69+BI73 -> 14376.967 | BJ77: =BJ63+BJ65+BJ69+BJ73 -> 16054.66 | BK77: =BK63+BK65+BK69+BK73 -> 16735.595 | BL77: =BL63+BL65+BL69+BL73 -> 60183.47 | BM77: =BM63+BM65+BM69+BM73+1 -> 15399.962 | BN77: =BN63+BN65+BN69+BN73+1 -> 16998.945 | BO77: =BO63+BO65+BO69+BO73 -> 17551.579 | BP77: =BP63+BP65+BP69+BP73 -> 16008.373 | BQ77: =BQ63+BQ65+BQ69+BQ73 -> 65956.858 | BR77: =BR8+BR20+BR32+BR38+BR44+BR61 -> 12786.952 | BS77: =BS8+BS20+BS32+BS38+BS44+BS61 -> 15642.88 | BT77: =BT8+BT20+BT32+BT38+BT44+BT61 -> 15199.798 | BU77: =BU8+BU20+BU32+BU38+BU44+BU61 -> 14381.695 | BV77: =BV8+BV20+BV32+BV38+BV44+BV61 -> 58011.325 | BW77: =BW8+BW20+BW32+BW38+BW44+BW61 -> 12952.752 | BX77: =BX8+BX20+BX32+BX38+BX44+BX61 -> 14280.427 | BY77: =BY8+BY20+BY32+BY38+BY44+BY61 -> 15392.555 | ... CA77: =CA8+CA20+CA32+CA38+CA44+CA61 -> 58013.51 | CB77: =CB8+CB20+CB32+CB38+CB44+CB61+CB60 -> 12944.785 | CC77: =CC8+CC20+CC32+CC38+CC44+CC61+CC60 -> 13952.165 | CD77: =CD8+CD20+CD32+CD38+CD44+CD61+CD60 -> 14070.705 | CE77: =CE8+CE20+CE32+CE38+CE44+CE61+CE60 -> 16530.915 | CF77: =CF8+CF20+CF32+CF38+CF44+CF61+CF60 -> 57498.57 | CG77: =CG8+CG20+CG32+CG38+CG44+CG61+CG60 -> 11821.702 | CH77: =CH8+CH20+CH32+CH38+CH44+CH61+CH60 -> 4722.171 | CI77: =CI8+CI20+CI32+CI38+CI44+CI61+CI60 -> 8248.5809 | ... EB77: =EB8+EB20+EB32+EB38+EB44+EB61+EB60 -> 84921
B79: Total BCA EBIT (pre-R&D, pre-one-times) | C79: =C10+C16+C22+C28+C34+C40+C46+C52+C67+C71+C75+C58 -> 2539.595 | D79: =D10+D16+D22+D28+D34+D40+D46+D52+D67+D71+D75+D58 -> 2439.69 | E79: =E10+E16+E22+E28+E34+E40+E46+E52+E67+E71+E75+E58 -> 2526.665 | F79: =F10+F16+F22+F28+F34+F40+F46+F52+F67+F71+F75+F58 -> 3298.96 | G79: =G10+G16+G22+G28+G34+G40+G46+G52+G67+G71+G75+G58 -> 3484.11 | H79: =H10+H16+H22+H28+H34+H40+H46+H52+H67+H71+H75+H58 -> 3595.23 | I79: =I10+I16+I22+I28+I34+I40+I46+I52+I67+I71+I75+I58 -> 1984.575 | J79: =J10+J16+J22+J28+J34+J40+J46+J52+J67+J71+J75+J58 -> 553.753 | ... AW79: =AW10+AW16+AW22+AW28+AW34+AW40+AW46+AW52+AW67+AW71+AW75+AW58 -> 6186.81 | BB79: =BB10+BB16+BB22+BB28+BB34+BB40+BB46+BB52+BB67+BB71+BB75+BB58 -> 6723.35 | BG79: =BG10+BG16+BG22+BG28+BG34+BG40+BG46+BG52+BG67+BG71+BG75+BG58 -> 7570.595 | BL79: =BL10+BL16+BL22+BL28+BL34+BL40+BL46+BL52+BL67+BL71+BL75+BL58 -> 8483.1785 | BQ79: =BQ10+BQ16+BQ22+BQ28+BQ34+BQ40+BQ46+BQ52+BQ67+BQ71+BQ75+BQ58 -> 8799.4274 | BV79: =BV10+BV16+BV22+BV28+BV34+BV40+BV46+BV52+BV67+BV71+BV75+BV58 -> 7746.3274 | CA79: =CA10+CA16+CA22+CA28+CA34+CA40+CA46+CA52+CA67+CA71+CA75+CA58 -> 7751.393 | CF79: =CF10+CF16+CF22+CF28+CF34+CF40+CF46+CF52+CF67+CF71+CF75+CF58 -> 10085.66 | CK79: =CK10+CK16+CK22+CK28+CK34+CK40+CK46+CK52+CK67+CK71+CK75+CK58 -> 5274.3941 | CP79: =CP10+CP16+CP22+CP28+CP34+CP40+CP46+CP52+CP67+CP71+CP75+CP58 -> 1472.7911 | CU79: =CU10+CU16+CU22+CU28+CU34+CU40+CU46+CU52+CU67+CU71+CU75+CU58 -> 2018.3842 | CZ79: =CZ10+CZ16+CZ22+CZ28+CZ34+CZ40+CZ46+CZ52+CZ67+CZ71+CZ75+CZ58 -> 2644.0541 | DE79: =DE10+DE16+DE22+DE28+DE34+DE40+DE46+DE52+DE67+DE71+DE75+DE58 -> 2814.7067 | DJ79: =DJ10+DJ16+DJ22+DJ28+DJ34+DJ40+DJ46+DJ52+DJ67+DJ71+DJ75+DJ58 -> 1518.8863 | DO79: =DO10+DO16+DO22+DO28+DO34+DO40+DO46+DO52+DO67+DO71+DO75+DO58 -> 3372.9271 | DT79: =DT10+DT16+DT22+DT28+DT34+DT40+DT46+DT52+DT67+DT71+DT75+DT58 -> 4605.6864 | DY79: =DY10+DY16+DY22+DY28+DY34+DY40+DY46+DY52+DY67+DY71+DY75+DY58 -> 6042.4119 | DZ79: =DZ10+DZ16+DZ22+DZ28+DZ34+DZ40+DZ46+DZ52+DZ67+DZ71+DZ75+DZ58 -> 7933.8768 | EA79: =EA10+EA16+EA22+EA28+EA34+EA40+EA46+EA52+EA67+EA71+EA75+EA58 -> 11240.416 | EB79: =EB10+EB16+EB22+EB28+EB34+EB40+EB46+EB52+EB67+EB71+EB75+EB58 -> 14992.02
B80: Margin | C80: =C79/C77 -> 0.094729195 | D80: =D79/D77 -> 0.067690195 | E80: =E79/E77 -> 0.067120884 | F80: =F79/F77 -> 0.10709171 | G80: =G79/G77 -> 0.099872726 | H80: =H79/H77 -> 0.12665058 | I80: =I79/I77 -> 0.088565468 | J80: =J79/J77 -> 0.10389362 | ... AW80: =AW79/AW77 -> 0.17341172 | BB80: =BB79/BB77 -> 0.13795166 | BG80: =BG79/BG77 -> 0.14278996 | BL80: =BL79/BL77 -> 0.14095529 | BQ80: =BQ79/BQ77 -> 0.13341186 | BV80: =BV79/BV77 -> 0.1335313 | CA80: =CA79/CA77 -> 0.13361358 | CF80: =CF79/CF77 -> 0.17540714 | CK80: =CK79/CK77 -> 0.16352294 | CP80: =CP79/CP77 -> 0.091131357 | CU80: =CU79/CU77 -> 0.10355046 | CZ80: =CZ79/CZ77 -> 0.10222001 | DE80: =DE79/DE77 -> 0.083026348 | DJ80: =DJ79/DJ77 -> 0.066440716 | DO80: =DO79/DO77 -> 0.081287192 | DT80: =DT79/DT77 -> 0.10276503 | DY80: =DY79/DY77 -> 0.10232463 | DZ80: =DZ79/DZ77 -> 0.11618527 | EA80: =EA79/EA77 -> 0.14271551 | EB80: =EB79/EB77 -> 0.17654078
B81: Program incremental margin | D81: =(D79-C79)/(D77-C77) -> -0.010820427 | E81: =(E79-D79)/(E77-D77) -> 0.054308461 | F81: =(F79-E79)/(F77-E77) -> -0.11293339 | G81: =(G79-F79)/(G77-F77) -> 0.045374341 | H81: =(H79-G79)/(H77-G77) -> -0.017099331 | I81: =(I79-H79)/(I77-H77) -> 0.26938535 | N81: =(N79-I79)/(N77-I77) -> -0.14240408 | S81: =(S79-N79)/(S77-N77) -> 0.65274907 | X81: =(X79-S79)/(X77-S77) -> 0.32635596 | AC81: =(AC79-X79)/(AC77-X77) -> 0.28720059 | AH81: =(AH79-AC79)/(AH77-AC77) -> 0.35613913 | AM81: =(AM79-AH79)/(AM77-AH77) -> 0.071630559 | AR81: =(AR79-AM79)/(AR77-AM77) -> -0.32127907 | AW81: =(AW79-AR79)/(AW77-AR77) -> 0.061024272 | BB81: =(BB79-AW79)/(BB77-AW77) -> 0.041082695 | BG81: =(BG79-BB79)/(BG77-BB77) -> 0.19785736 | BL81: =(BL79-BG79)/(BL77-BG77) -> 0.12737805 | BQ81: =(BQ79-BL79)/(BQ77-BL77) -> 0.054777002 | BV81: =(BV79-BQ79)/(BV77-BQ77) -> 0.13253988 | CA81: =(CA79-BV79)/(CA77-BV77) -> 2.3183535 | CF81: =(CF79-CA79)/(CF77-CA77) -> -4.533085 | CK81: =(CK79-CF79)/(CK77-CF77) -> 0.19059194 | CP81: =(CP79-CK79)/(CP77-CK77) -> 0.23621865 | CU81: =(CU79-CP79)/(CU77-CP77) -> 0.163812 | CZ81: =(CZ79-CU79)/(CZ77-CU77) -> 0.098151827 | DE81: =(DE79-CZ79)/(DE77-CZ77) -> 0.021238497 | DJ81: =(DJ79-DE79)/(DJ77-DE77) -> 0.11736875 | DO81: =(DO79-DJ79)/(DO77-DJ77) -> 0.099502116 | DT81: =(DT79-DO79)/(DT77-DO77) -> 0.37090121 | DY81: =(DY79-DT79)/(DY77-DT77) -> 0.10093793 | DZ81: =(DZ79-DY79)/(DZ77-DY77) -> 0.20481412 | EA81: =(EA79-DZ79)/(EA77-DZ77) -> 0.3156729 | EB81: =(EB79-EA79)/(EB77-EA77) -> 0.60902662
B83: BCA R&D | C83: =Data!C294 -> 1208 | D83: =Data!D294 -> 1021 | E83: =Data!E294 -> 585 | F83: =Data!F294 -> 585 | G83: =Data!G294 -> 858 | H83: =Data!H294 -> 768 | I83: =Data!I294 -> 676 | J83: =Data!J294 -> 225 | ... BP83: =Data!BP294 -> 627 | BQ83: =SUM(BM83:BP83) -> 2340 | BR83: =Data!BR294 -> 659 | BS83: =Data!BS294-1235 -> 625 | BT83: =Data!BT294 -> 633 | BU83: =Data!BU294 -> 554 | BV83: =SUM(BR83:BU83) -> 2471 | BW83: =Data!BW294 -> 625 | BX83: =Data!BX294 -> 592 | BY83: =Data!BY294 -> 538 | BZ83: =Data!BZ294 -> 492 | CA83: =SUM(BW83:BZ83) -> 2247 | CB83: =Data!CB294 -> 549 | CC83: =Data!CC294 -> 550 | CD83: =Data!CD294 -> 517 | CE83: =Data!CE294 -> 572 | CF83: =SUM(CB83:CE83) -> 2188 | CG83: 564 | CH83: 498 | CI83: 467 | CJ83: 427 | CK83: =SUM(CG83:CJ83) -> 1956 | CL83: 425 | CM83: 361 | CN83: 321 | CO83: 278 | CP83: =SUM(CL83:CO83) -> 1385 | CQ83: =Data!CQ294 -> 269 | CR83: =Data!CR294 -> 255 | CS83: =Data!CS294 -> 293 | CT83: =Data!CT294 -> 323 | CU83: =SUM(CQ83:CT83) -> 1140 | CV83: =Data!CV294 -> 0 | CW83: =Data!CW294 -> 0 | CX83: =Data!CX294 -> 0 | CY83: 408 | CZ83: =SUM(CV83:CY83) -> 408 | DE83: 1600 | DJ83: 1597 | DO83: 1636 | DT83: 1800 | DY83: 2000 | DZ83: 2100 | EA83: 2200 | EB83: 2300
B84: BCA EBIT post-R&D | C84: =C79-C83 -> 1331.595 | D84: =D79-D83 -> 1418.69 | E84: =E79-E83 -> 1941.665 | F84: =F79-F83 -> 2713.96 | G84: =G79-G83 -> 2626.11 | H84: =H79-H83 -> 2827.23 | I84: =I79-I83 -> 1308.575 | J84: =J79-J83 -> 328.753 | ... AW84: =AW79-AW83 -> 3471.81 | BB84: =BB79-BB83 -> 4674.35 | BG84: =BG79-BG83 -> 5763.595 | BL84: =BL79-BL83 -> 6602.1785 | BQ84: =BQ79-BQ83 -> 6459.4274 | BV84: =BV79-BV83 -> 5275.3274 | CA84: =CA79-CA83 -> 5504.393 | CF84: =CF79-CF83 -> 7897.6598 | CK84: =CK79-CK83 -> 3318.3941 | CP84: =CP79-CP83 -> 87.791081 | CU84: =CU79-CU83 -> 878.38415 | CZ84: =CZ79-CZ83 -> 2236.0541 | DE84: =DE79-DE83 -> 1214.7067 | DJ84: =DJ79-DJ83 -> -78.113711 | DO84: =DO79-DO83 -> 1736.9271 | DT84: =DT79-DT83 -> 2805.6864 | DY84: =DY79-DY83 -> 4042.4119 | DZ84: =DZ79-DZ83 -> 5833.8768 | EA84: =EA79-EA83 -> 9040.416 | EB84: =EB79-EB83 -> 12692.02
B85: Margin | C85: =C84/C77 -> 0.0496697 | D85: =D84/D77 -> 0.039362133 | E85: =E84/E77 -> 0.051580353 | F85: =F84/F77 -> 0.088101282 | G85: =G84/G77 -> 0.075277981 | H85: =H84/H77 -> 0.099595942 | I85: =I84/I77 -> 0.05839767 | J85: =J84/J77 -> 0.061679737 | ... AW85: =AW84/AW77 -> 0.097312274 | BB85: =BB84/BB77 -> 0.095909678 | BG85: =BG84/BG77 -> 0.1087079 | BL85: =BL84/BL77 -> 0.10970086 | BQ85: =BQ84/BQ77 -> 0.097934128 | BV85: =BV84/BV77 -> 0.090936164 | CA85: =CA84/CA77 -> 0.094881226 | CF85: =CF84/CF77 -> 0.13735402 | CK85: =CK84/CK77 -> 0.10288074 | CP85: =CP84/CP77 -> 0.0054322167 | CU85: =CU84/CU77 -> 0.045064306 | CZ85: =CZ84/CZ77 -> 0.086446598 | DE85: =DE84/DE77 -> 0.035830612 | DJ85: =DJ84/DJ77 -> -0.0034169318 | DO85: =DO84/DO77 -> 0.041859762 | DT85: =DT84/DT77 -> 0.062602277 | DY85: =DY84/DY77 -> 0.068455825 | DZ85: =DZ84/DZ77 -> 0.085432452 | EA85: =EA84/EA77 -> 0.1147829 | EB85: =EB84/EB77 -> 0.14945679
B87: One-time items, abnormal cost | C87: =SEG!C189 -> 3150 | D87: =SEG!D189 -> 1350 | E87: =SEG!E189 -> 0 | F87: =SEG!F189 -> 0 | G87: =SEG!G189 -> 0 | H87: =SEG!H189 -> 0 | I87: =SEG!I189 -> 600 | J87: =SEG!J189 -> 0 | ... AW87: =SEG!AW189 -> 0 | BB87: =SEG!BB189 -> 0 | BG87: =SEG!BG189 -> 0 | BI87: 238 | BL87: =SUM(BH87:BK87) -> 238 | BN87: 513 | BP87: 885 | BQ87: =SUM(BM87:BP87) -> 1398 | BR87: 232 | BS87: =1235+1188+354 -> 2777 | BT87: 0 | BU87: 243 | BV87: =SUM(BR87:BU87) -> 3252 | BW87: 120 | BX87: 0 | BY87: 256 | BZ87: -278 | CA87: =SUM(BW87:BZ87) -> 98 | CC87: 307 | CD87: 112 | CF87: =-300+SUM(CB87:CE87) -> 119 | CH87: 5600 | CJ87: 2600 | CK87: =SUM(CG87:CJ87) -> 8200 | CL87: =SEG!CL189 -> 1270 | CM87: =SEG!CM189 -> 1864 | CN87: =SEG!CN189 -> 590 | CO87: =SEG!CO189 -> 6500 | CP87: =SUM(CL87:CO87) -> 10224 | CQ87: =SEG!CQ189 -> 568 | CR87: =SEG!CR189 -> 515 | CS87: =SEG!CS189 -> 601 | CT87: =SEG!CT189 -> 4131 | CU87: =SUM(CQ87:CT87) -> 5815 | CV87: =SEG!CV189 -> 500 | CW87: =283+102 -> 385 | CX87: =330+111 -> 441 | CY87: 1560 | CZ87: =SUM(CV87:CY87) -> 2886 | DA87: =379+126 -> 505 | DB87: 450 | DC87: 424 | DD87: 400 | DE87: =SUM(DA87:DD87) -> 1779 | DF87: 1500 | DG87: 450 | DH87: 4000 | DI87: 1941 | DJ87: =SUM(DF87:DI87) -> 7891 | DK87: 1500 | DL87: 650 | DM87: 5600 | DN87: 1066 | DO87: =SUM(DK87:DN87) -> 8816 | DP87: 1500 | DQ87: 1000 | DR87: 1000 | DS87: 500 | DT87: =SUM(DP87:DS87) -> 4000 | DU87: 1000 | DV87: 500 | DW87: 500 | DX87: 400 | DY87: =SUM(DU87:DX87) -> 2400 | DZ87: 1000 | EA87: 800 | EB87: 500
B88: Unabsorbed overhead | CK88: -1775 | CP88: -3711 | CU88: -1530 | CZ88: -1720 | DE88: -1071
B90: Total Reported BCA EBIT | C90: =C79-C83-C87 -> -1818.405 | D90: =D79-D83-D87 -> 68.69 | E90: =E79-E83-E87 -> 1941.665 | F90: =F79-F83-F87 -> 2713.96 | G90: =G79-G83-G87 -> 2626.11 | H90: =H79-H83-H87 -> 2827.23 | I90: =I79-I83-I87 -> 708.575 | N90: =N79-N83-N87 -> 763.811 | S90: =S79-S83-S87 -> 1431.348 | X90: =X79-X83-X87 -> 2740.651 | AC90: =AC79-AC83-AC87 -> 3582.08 | AH90: =AH79-AH83-AH87 -> 1196.508 | AM90: =AM79-AM83-AM87 -> -595.88 | AR90: =AR79-AR83-AR87 -> 2960.39 | AW90: =AW79-AW83-AW87 -> 3471.81 | BB90: =BB79-BB83-BB87 -> 4674.35 | BG90: =BG79-BG83-BG87 -> 5763.595 | BL90: =BL79-BL83-BL87 -> 6364.1785 | BQ90: =BQ79-BQ83-BQ87 -> 5061.4274 | BV90: =BV79-BV83-BV87 -> 2023.3274 | CA90: =CA79-CA83-CA87 -> 5406.393 | CF90: =CF79-CF83-CF87 -> 7778.6598 | CK90: =CK79-CK83-CK87+CK88 -> -6656.6059 | CP90: =CP79-CP83-CP87+CP88 -> -13847.209 | CU90: =CU79-CU83-CU87+CU88 -> -6466.6158 | CZ90: =CZ79-CZ83-CZ87+CZ88 -> -2369.9459 | DE90: =DE79-DE83-DE87+DE88 -> -1635.2933 | DJ90: =DJ79-DJ83-DJ87+DJ88 -> -7969.1137 | DO90: =DO79-DO83-DO87+DO88 -> -7079.0729 | DT90: =DT79-DT83-DT87+DT88 -> -1194.3136 | DY90: =DY79-DY83-DY87+DY88 -> 1642.4119 | DZ90: =DZ79-DZ83-DZ87+DZ88 -> 4833.8768 | EA90: =EA79-EA83-EA87+EA88 -> 8240.416 | EB90: =EB79-EB83-EB87+EB88 -> 12192.02
B91: BCA EBIT margin | C91: =C90/C77 -> -0.067828155 | D91: =D90/D77 -> 0.0019058321 | E91: =E90/E77 -> 0.051580353 | F91: =F90/F77 -> 0.088101282 | G91: =G90/G77 -> 0.075277981 | H91: =H90/H77 -> 0.099595942 | I91: =I90/I77 -> 0.031621519 | N91: =N90/N77 -> 0.036307981 | S91: =S90/S77 -> 0.063191382 | X91: =X90/X77 -> 0.096282786 | AC91: =AC90/AC77 -> 0.10729288 | AH91: =AH90/AH77 -> 0.042335084 | AM91: =AM90/AM77 -> -0.017499633 | AR91: =AR90/AR77 -> 0.093810882 | AW91: =AW90/AW77 -> 0.097312274 | BB91: =BB90/BB77 -> 0.095909678 | BG91: =BG90/BG77 -> 0.1087079 | BL91: =BL90/BL77 -> 0.10574629 | BQ91: =BQ90/BQ77 -> 0.076738455 | BV91: =BV90/BV77 -> 0.034878144 | CA91: =CA90/CA77 -> 0.093191965 | CF91: =CF90/CF77 -> 0.1352844 | CK91: =CK90/CK77 -> -0.20637588 | CP91: =CP90/CP77 -> -0.8568187 | CU91: =CU90/CU77 -> -0.33176094 | CZ91: =CZ90/CZ77 -> -0.091622902 | DE91: =DE90/DE77 -> -0.048236794 | DJ91: =DJ90/DJ77 -> -0.34859332 | DO91: =DO90/DO77 -> -0.17060492 | DT91: =DT90/DT77 -> -0.026648291 | DY91: =DY90/DY77 -> 0.027813263 | DZ91: =DZ90/DZ77 -> 0.070788253 | EA91: =EA90/EA77 -> 0.10462559 | EB91: =EB90/EB77 -> 0.14356896

Sheet Commercial
B3: BA BCA Build | C3: 1997 | D3: 1998 | E3: 1999 | F3: 2000 | G3: 2001 | H3: 2002 | I3: 2003 | J3: 1Q04 | K3: 2Q04 | L3: 3Q04 | M3: 4Q04 | N3: 2004 | O3: 1Q05 | P3: 2Q05 | Q3: 3Q05 | R3: 4Q05 | S3: 2005 | T3: 1Q06 | U3: 2Q06 | V3: 3Q06 | W3: 4Q06 | X3: 2006 | Y3: 1Q07 | Z3: 2Q07 | AA3: 3Q07 | AB3: 4Q07 | AC3: 2007 | AD3: 1Q08 | AE3: 2Q08 | AF3: 3Q08 | AG3: 4Q08 | AH3: 2008 | AI3: 1Q09 | AJ3: 2Q09 | AK3: 3Q09 | AL3: 4Q09 | AM3: 2009 | AN3: 1Q10 | AO3: 2Q10 | AP3: 3Q10 | AQ3: 4Q10 | AR3: 2010 | AS3: 1Q11 | AT3: 2Q11 | AU3: 3Q11 | AV3: 4Q11 | AW3: 2011 | AX3: 1Q12 | AY3: 2Q12 | AZ3: 3Q12 | BA3: 4Q12 | BB3: 2012 | BC3: 1Q13 | BD3: 2Q13 | BE3: 3Q13 | BF3: 4Q13 | BG3: 2013 | BH3: 1Q14 | BI3: 2Q14 | BJ3: 3Q14 | BK3: 4Q14 | BL3: 2014 | BM3: 1Q15 | BN3: 2Q15 | BO3: 3Q15 | BP3: 4Q15 | BQ3: 2015 | BR3: 1Q16 | BS3: 2Q16 | BT3: 3Q16 | BU3: 4Q16 | BV3: 2016 | BW3: 1Q17 | BX3: 2Q17 | BY3: 3Q17 | BZ3: 4Q17 | CA3: 2017 | CB3: 1Q18 | CC3: 2Q18 | CD3: 3Q18 | CE3: 4Q18 | CF3: 2018 | CG3: 1Q19 | CH3: 2Q19 | CI3: 3Q19 | CJ3: 4Q19 | CK3: 2019 | CL3: 1Q20 | CM3: 2Q20 | CN3: 3Q20 | CO3: 4Q20 | CP3: 2020 | CQ3: 1Q21 | CR3: 2Q21 | CS3: 3Q21 | CT3: 4Q21 | CU3: 2021 | CV3: 1Q22 | CW3: 2Q22 | CX3: 3Q22 | CY3: 4Q22 | CZ3: 2022 | DA3: 1Q23 | DB3: 2Q23 | DC3: 3Q23 | DD3: 4Q23 | DE3: 2023 | DF3: 1Q24 | DG3: 2Q24 | DH3: 3Q24 | DI3: 4Q24 | DJ3: 2024 | DK3: 1Q25 | DL3: 2Q25 | DM3: 3Q25 | DN3: 4Q25 | DO3: 2025 | DP3: 1Q26 | DQ3: 2Q26 | DR3: 3Q26E | DS3: 4Q26E | DT3: 2026E | DU3: 1Q27E | DV3: 2Q27E | DW3: 3Q27E | DX3: 4Q27E | DY3: 2027E | DZ3: 2028E | EA3: 2029E | EB3: 2030E
