Workbook
Name africa: 0.01
Name africaCountries: #REF!
Name allRegions: #REF!
Name americaRegion: #REF!
Name americas: 0.55
Name americasStates: #REF!
Name AppVersion: "GEG-1.0"
Name asiaPacific: 0.22
Name asiaPacificExJapan: 0.11
Name asiaPacificExJapanCountries: #REF!
Name asiaPacificRegion: #REF!
Name asiaPacificStates: #REF!
Name australasia: 0.02
Name BRICS: 0.1
Name centralEasternEurope: 0.03
Name centralEasternEuropeCountries: #REF!
Name china: 0.07
Name consumerDemandExposure: #REF!
Name consumersExposure: 0
Name countryList: "Country Mapping"
Name developedEuropeExUK: 0.07
Name developedEuropeExUKCountries: #REF!
Name domesticAndForeignExposure: #REF!
Name domesticCostExposure: #REF!
Name EEMEA: 0.15
Name endDemandExposure: #REF!
Name europe: 0.11
Name europeRegion: #REF!
Name europeStates: #REF!
Name india: 0.02
Name instructions: #REF!
Name IQ_CH: 110000
Name IQ_CQ: 5000
Name IQ_CY: 10000
Name IQ_DAILY: 500000
Name IQ_FH: 100000
Name IQ_FQ: 500
Name IQ_FY: 1000
Name IQ_LTM: 2000
Name IQ_MONTH: 15000
Name IQ_NTM: 6000
Name IQ_WEEK: 50000
Name IQ_YTD: 3000
Name italy: 0.01
Name japan: 0.02
Name latinAmerica: 0.03
Name latinAmericaCountries: #REF!
Name Linking_1: #REF!
Name Linking_2: BCA_Model_Annual!$AW$38:$AY$51
Name middleEast: 0.11
Name middleEastAfrica: 0.12
Name middleEastAfricaRegion: #REF!
Name middleEastAfricaStates: #REF!
Name northAmerica: 0.52
Name northAmericaCountries: #REF!
Name otherAfrica: 0.01
Name otherAsiaPacific: 0.06
Name otherCentralEasternEurope: 0.02
Name otherDevelopedEurope: 0.03
Name otherLATAM: 0.03

Sheet CircularReferenceAlert
B2: This workbook contains formulas which intentionally use circular reference calculation. These calculations can be resolved as intended by the originating analyst by applying the following settings in the File >> Options >> Formulas:
B5: 1) Select the Enable iterative calculation check box
B6: 2) Set Maximum Iterations = 100
B7: 3) Set Maximum Change = 0.001
B9: Failure to apply these settings can result in incorrect calculation or unexpected termination of your Microsoft Excel session.

Sheet ImportantDisclosures
A2: 1585 Broadway
A3: New York, NY 10036-8293
A4: United States
A5: Tel: +1 (1)212 761 4000
A7: Authors: Kristine Liwag
A8: Date: 28 Jan 2026
A10: Ticker: BA.N
A11: Stock Rating: Equal-weight
A12: Industry: Aerospace
A13: Industry View: Attractive
A14: Price as of 28 Jan 2026: 245.30
A15: Target Price: 245.00
... A128: Equal-weight and Not-Rated to hold and Underweight to sell recommendations, respectively.
B130: Coverage Universe | D130: Investment Banking Clients (IBC) | G130: Other Material Investment Services Clients (MISC)
A131: Stock Rating Category | B131: Count | C131: % of Total | D131: Count | E131: % of Total IBC | F131: % of Rating Category | G131: Count | H131: % of Total Other MISC
A132: Overweight/Buy | B132: 1519 | C132: 0.41 | D132: 415 | E132: 0.48 | F132: 0.27 | G132: 674 | H132: 0.42
A133: Equal-weight/Hold | B133: 1583 | C133: 0.43 | D133: 362 | E133: 0.42 | F133: 0.23 | G133: 720 | H133: 0.45
A134: Not-Rated/Hold | B134: 4 | C134: 0 | D134: 1 | E134: 0 | F134: 0.25 | G134: 1 | H134: 0
A135: Underweight/Sell | B135: 564 | C135: 0.15 | D135: 87 | E135: 0.1 | F135: 0.15 | G135: 216 | H135: 0.13
A136: Total | B136: 3670 | D136: 865 | G136: 1611
A138: Data include common stock and ADRs currently assigned ratings. Investment Banking Clients are companies
A139: from whom Morgan Stanley received investment banking compensation in the last 12 months. Due to rounding
A140: off of decimals, the percentages provided in the "% of total" column may not add up to exactly 100
A141: percent.
A143: Analyst Stock Ratings
A145: Overweight (O). The stock's total return is expected to exceed the average total return of the analyst's
A146: industry (or industry team's) coverage universe, on a risk-adjusted basis, over the next 12-18 months.
A148: Equal-weight (E). The stock's total return is expected to be in line with the average total return of
A149: the analyst's industry (or industry team's) coverage universe, on a risk-adjusted basis, over the next
A150: 12-18 months.
A152: Not-Rated (NR). Currently the analyst does not have adequate conviction about the stock's total return
A153: relative to the average total return of the analyst's industry (or industry team's) coverage universe,
... A427: © Copyright 2026 Morgan Stanley

Sheet Financial Summary
A1: Financial Summary
B2: =Income_Statement_Annual!B2 -> CY2000A | C2: =Income_Statement_Annual!C2 -> CY2001A | D2: =Income_Statement_Annual!D2 -> CY2002A | E2: =Income_Statement_Annual!E2 -> CY2003A | F2: =Income_Statement_Annual!F2 -> CY2004A | G2: =Income_Statement_Annual!G2 -> CY2005A | H2: =Income_Statement_Annual!H2 -> CY2006A | I2: =Income_Statement_Annual!I2 -> CY2007A | ... AB2: =Income_Statement_Annual!AB2 -> CY2026E
A3: Income Statement
A4: Revenue | B4: =Income_Statement_Annual!B10 -> 51321 | C4: =Income_Statement_Annual!C10 -> 58198 | D4: =Income_Statement_Annual!D10 -> 54061 | E4: =Income_Statement_Annual!E10 -> 50256 | F4: =Income_Statement_Annual!F10 -> 52457 | G4: =Income_Statement_Annual!G10 -> 53621 | H4: =Income_Statement_Annual!H10 -> 61530 | I4: =Income_Statement_Annual!I10 -> 66387 | ... AB4: =Income_Statement_Annual!AB10 -> 99714.978
A5: Revenue Growth | B5: =Income_Statement_Annual!B11 -> -0.11504837 | C5: =Income_Statement_Annual!C11 -> 0.13399973 | D5: =Income_Statement_Annual!D11 -> -0.071084917 | E5: =Income_Statement_Annual!E11 -> -0.070383456 | F5: =Income_Statement_Annual!F11 -> 0.043795766 | G5: =Income_Statement_Annual!G11 -> 0.022189603 | H5: =Income_Statement_Annual!H11 -> 0.14749818 | I5: =Income_Statement_Annual!I11 -> 0.078937104 | ... AB5: =Income_Statement_Annual!AB11 -> 0.11459462
A6: EBITDA | B6: =Income_Statement_Annual!B97 -> 4537 | C6: =Income_Statement_Annual!C97 -> 5639 | D6: =Income_Statement_Annual!D97 -> 4947 | E6: =Income_Statement_Annual!E97 -> 2711 | F6: =Income_Statement_Annual!F97 -> 4071 | G6: =Income_Statement_Annual!G97 -> 4315 | H6: =Income_Statement_Annual!H97 -> 5465 | I6: =Income_Statement_Annual!I97 -> 7316 | ... AB6: =Income_Statement_Annual!AB97 -> 4185.7288
A7: EBITDA Margin | B7: =Income_Statement_Annual!B98 -> 0.088404357 | C7: =Income_Statement_Annual!C98 -> 0.096893364 | D7: =Income_Statement_Annual!D98 -> 0.091507741 | E7: =Income_Statement_Annual!E98 -> 0.053943808 | F7: =Income_Statement_Annual!F98 -> 0.07760642 | G7: =Income_Statement_Annual!G98 -> 0.080472203 | H7: =Income_Statement_Annual!H98 -> 0.088818463 | I7: =Income_Statement_Annual!I98 -> 0.1102023 | ... AB7: =Income_Statement_Annual!AB98 -> 0.041976931
A8: EBIT | B8: =Income_Statement_Annual!B34 -> 3058 | C8: =Income_Statement_Annual!C34 -> 3896 | D8: =Income_Statement_Annual!D34 -> 3450 | E8: =Income_Statement_Annual!E34 -> 1311 | F8: =Income_Statement_Annual!F34 -> 2562 | G8: =Income_Statement_Annual!G34 -> 2812 | H8: =Income_Statement_Annual!H34 -> 3920 | I8: =Income_Statement_Annual!I34 -> 5830 | ... AB8: =Income_Statement_Annual!AB34 -> 2111.9938
A9: EBIT Margin | B9: =Income_Statement_Annual!B35 -> 0.059585745 | C9: =Income_Statement_Annual!C35 -> 0.066943881 | D9: =Income_Statement_Annual!D35 -> 0.0638168 | E9: =Income_Statement_Annual!E35 -> 0.026086437 | F9: =Income_Statement_Annual!F35 -> 0.048840002 | G9: =Income_Statement_Annual!G35 -> 0.05244214 | H9: =Income_Statement_Annual!H35 -> 0.06370876 | I9: =Income_Statement_Annual!I35 -> 0.087818398 | ... AB9: =Income_Statement_Annual!AB35 -> 0.021180306
A10: Pre-Tax Income | B10: =Income_Statement_Annual!B40 -> 2999 | C10: =Income_Statement_Annual!C40 -> 3564 | D10: =Income_Statement_Annual!D40 -> 3180 | E10: =Income_Statement_Annual!E40 -> 1413 | F10: =Income_Statement_Annual!F40 -> 2296 | G10: =Income_Statement_Annual!G40 -> 2755 | H10: =Income_Statement_Annual!H40 -> 4100 | I10: =Income_Statement_Annual!I40 -> 6118 | ... AB10: =Income_Statement_Annual!AB40 -> 527.84551
A11: Tax Rate | B11: =Income_Statement_Annual!B44 -> 0.29043014 | C11: =Income_Statement_Annual!C44 -> 0.20707071 | D11: =Income_Statement_Annual!D44 -> 0.27075472 | E11: =Income_Statement_Annual!E44 -> NM | F11: =Income_Statement_Annual!F44 -> 0.27155488 | G11: =Income_Statement_Annual!G44 -> 0.29152269 | H11: =Income_Statement_Annual!H44 -> 0.27267707 | I11: =Income_Statement_Annual!I44 -> 0.33671134 | ... AB11: =Income_Statement_Annual!AB44 -> 0.1
A12: Net Income Attributable to Boeing Shareholder | B12: =Income_Statement_Annual!B56 -> 2128 | C12: =Income_Statement_Annual!C56 -> 2827 | D12: =Income_Statement_Annual!D56 -> 492 | E12: =Income_Statement_Annual!E56 -> 718 | F12: =Income_Statement_Annual!F56 -> 1872 | G12: =Income_Statement_Annual!G56 -> 2572 | H12: =Income_Statement_Annual!H56 -> 2215 | I12: =Income_Statement_Annual!I56 -> 4074 | ... AB12: =Income_Statement_Annual!AB56 -> 475.06095
A13: EPS | B13: =Income_Statement_Annual!B70 -> 2.4423276 | C13: =Income_Statement_Annual!C70 -> 3.4076932 | D13: =Income_Statement_Annual!D70 -> 2.8686294 | E13: =Income_Statement_Annual!E70 -> 1.856829 | F13: =Income_Statement_Annual!F70 -> 2.0572079 | G13: =Income_Statement_Annual!G70 -> 2.4310064 | H13: =Income_Statement_Annual!H70 -> 3.8204977 | I13: =Income_Statement_Annual!I70 -> 5.2530744 | ... AB13: =Income_Statement_Annual!AB70 -> 0.16056352
A14: Diluted Shares Outstanding (mn) | B14: =Income_Statement_Annual!B79 -> 871.3 | C14: =Income_Statement_Annual!C79 -> 829.3 | D14: =Income_Statement_Annual!D79 -> 808.4 | E14: =Income_Statement_Annual!E79 -> 808.9 | F14: =Income_Statement_Annual!F79 -> 813 | G14: =Income_Statement_Annual!G79 -> 802.9 | H14: =Income_Statement_Annual!H79 -> 787.6 | I14: =Income_Statement_Annual!I79 -> 772.5 | ... AB14: =Income_Statement_Annual!AB79 -> 803.8
A15: Total Book to Bill | B15: 0 | C15: 0.69399292 | D15: 1.0881967 | E15: 1.3277221 | F15: 1.0413863 | G15: 1.8902669 | H15: 1.7318381 | I15: 2.1556028 | J15: 1.4094961 | K15: 0.46737745 | L15: 1.0819208 | M15: 1.5034698 | N15: 1.4259101 | O15: 1.5852949 | P15: 1.6771887 | Q15: 0.86378675 | R15: 0.83285574 | S15: 1.0122121 | T15: 1.1566446 | U15: 0.64631199 | V15: -0.40613261 | W15: 1.2262948 | X15: 1.4035852 | Y15: 2.4887266 | Z15: 0 | AA15: 0 | AB15: 0
A17: Cash Flow Statement
A18: Operating Cash Flow | B18: =Cash_Flow_Annual!B29 -> 5942 | C18: =Cash_Flow_Annual!C29 -> 3894 | D18: =Cash_Flow_Annual!D29 -> 4236 | E18: =Cash_Flow_Annual!E29 -> 2709 | F18: =Cash_Flow_Annual!F29 -> 3504 | G18: =Cash_Flow_Annual!G29 -> 7000 | H18: =Cash_Flow_Annual!H29 -> 7499 | I18: =Cash_Flow_Annual!I29 -> 9584 | ... AB18: =Cash_Flow_Annual!AB29 -> 6229.8022
A19: Capex | B19: =Cash_Flow_Annual!B33 -> -932 | C19: =Cash_Flow_Annual!C33 -> -1189 | D19: =Cash_Flow_Annual!D33 -> -1001 | E19: =Cash_Flow_Annual!E33 -> -741 | F19: =Cash_Flow_Annual!F33 -> -1246 | G19: =Cash_Flow_Annual!G33 -> -1547 | H19: =Cash_Flow_Annual!H33 -> -1681 | I19: =Cash_Flow_Annual!I33 -> -1731 | ... AB19: =Cash_Flow_Annual!AB33 -> -4058.3996
A20: Free Cash Flow | B20: =Cash_Flow_Annual!B77 -> 5010 | C20: =Cash_Flow_Annual!C77 -> 2705 | D20: =Cash_Flow_Annual!D77 -> 3235 | E20: =Cash_Flow_Annual!E77 -> 1968 | F20: =Cash_Flow_Annual!F77 -> 2258 | G20: =Cash_Flow_Annual!G77 -> 5453 | H20: =Cash_Flow_Annual!H77 -> 5818 | I20: =Cash_Flow_Annual!I77 -> 7853 | ... AB20: =Cash_Flow_Annual!AB77 -> 2171.4025
A21: FCF Conversion | B21: =Cash_Flow_Annual!B78 -> 2.3543233 | C21: =Cash_Flow_Annual!C78 -> 0.95684471 | D21: =Cash_Flow_Annual!D78 -> 6.5752033 | E21: =Cash_Flow_Annual!E78 -> 2.7409471 | F21: =Cash_Flow_Annual!F78 -> 1.2061966 | G21: =Cash_Flow_Annual!G78 -> 2.12014 | H21: =Cash_Flow_Annual!H78 -> 2.6266366 | I21: =Cash_Flow_Annual!I78 -> 1.9275896 | ... AB21: =Cash_Flow_Annual!AB78 -> 2.6446301
A22: FCF Returned to Shareholders | B22: =Cash_Flow_Annual!B81 -> 2861 | C22: =Cash_Flow_Annual!C81 -> 2999 | D22: =Cash_Flow_Annual!D81 -> 571 | E22: =Cash_Flow_Annual!E81 -> 572 | F22: =Cash_Flow_Annual!F81 -> 1400 | G22: =Cash_Flow_Annual!G81 -> 3697 | H22: =Cash_Flow_Annual!H81 -> 2654 | I22: =Cash_Flow_Annual!I81 -> 3871 | ... AB22: =Cash_Flow_Annual!AB81 -> 346
A23: % of FCF Returned to Shareholders | B23: =Cash_Flow_Annual!B82 -> 0.57105788 | C23: =Cash_Flow_Annual!C82 -> 1.1086876 | D23: =Cash_Flow_Annual!D82 -> 0.17650696 | E23: =Cash_Flow_Annual!E82 -> 0.29065041 | F23: =Cash_Flow_Annual!F82 -> 0.62001771 | G23: =Cash_Flow_Annual!G82 -> 0.67797543 | H23: =Cash_Flow_Annual!H82 -> 0.45617051 | I23: =Cash_Flow_Annual!I82 -> 0.49293264 | ... AB23: =Cash_Flow_Annual!AB82 -> 0.15934401
A25: Balance Sheet
A26: Total Cash | B26: =Balance_Sheet_Annual!B5 -> 1010 | C26: =Balance_Sheet_Annual!C5 -> 633 | D26: =Balance_Sheet_Annual!D5 -> 2333 | E26: =Balance_Sheet_Annual!E5 -> 4633 | F26: =Balance_Sheet_Annual!F5 -> 3204 | G26: =Balance_Sheet_Annual!G5 -> 5412 | H26: =Balance_Sheet_Annual!H5 -> 6118 | I26: =Balance_Sheet_Annual!I5 -> 7042 | ... AB26: =Balance_Sheet_Annual!AB5 -> 8329.4025
A27: Total Debt | B27: =Balance_Sheet_Annual!B82 -> 8799 | C27: =Balance_Sheet_Annual!C82 -> 12265 | D27: =Balance_Sheet_Annual!D82 -> 14403 | E27: =Balance_Sheet_Annual!E82 -> 14443 | F27: =Balance_Sheet_Annual!F82 -> 12200 | G27: =Balance_Sheet_Annual!G82 -> 10727 | H27: =Balance_Sheet_Annual!H82 -> 9538 | I27: =Balance_Sheet_Annual!I82 -> 8217 | ... AB27: =Balance_Sheet_Annual!AB82 -> 49648
A28: Net Debt | B28: =Balance_Sheet_Annual!B83 -> 7789 | C28: =Balance_Sheet_Annual!C83 -> 11632 | D28: =Balance_Sheet_Annual!D83 -> 12070 | E28: =Balance_Sheet_Annual!E83 -> 9810 | F28: =Balance_Sheet_Annual!F83 -> 8996 | G28: =Balance_Sheet_Annual!G83 -> 5315 | H28: =Balance_Sheet_Annual!H83 -> 3420 | I28: =Balance_Sheet_Annual!I83 -> 1175 | ... AB28: =Balance_Sheet_Annual!AB83 -> 22839.597
A29: Net Debt to EBITDA | B29: =Balance_Sheet_Annual!B85 -> 1.7167732 | C29: =Balance_Sheet_Annual!C85 -> 2.0627771 | D29: =Balance_Sheet_Annual!D85 -> 2.4398625 | E29: =Balance_Sheet_Annual!E85 -> 3.6185909 | F29: =Balance_Sheet_Annual!F85 -> 2.2097765 | G29: =Balance_Sheet_Annual!G85 -> 1.2317497 | H29: =Balance_Sheet_Annual!H85 -> 0.62580055 | I29: =Balance_Sheet_Annual!I85 -> 0.16060689 | ... AB29: =Balance_Sheet_Annual!AB85 -> 5.4565403
A31: Capital Deployment
A32: Dry Powder for M&A | B32: =Balance_Sheet_Annual!B91 -> 0 | C32: =Balance_Sheet_Annual!C91 -> 0 | D32: =Balance_Sheet_Annual!D91 -> 0 | E32: =Balance_Sheet_Annual!E91 -> 0 | F32: =Balance_Sheet_Annual!F91 -> 0 | G32: =Balance_Sheet_Annual!G91 -> 0 | H32: =Balance_Sheet_Annual!H91 -> 0 | I32: =Balance_Sheet_Annual!I91 -> 0 | ... AB32: =Balance_Sheet_Annual!AB91 -> -38348.548
A33: Target EV/EBITDA | B33: =Balance_Sheet_Annual!B92 -> 0 | C33: =Balance_Sheet_Annual!C92 -> 0 | D33: =Balance_Sheet_Annual!D92 -> 0 | E33: =Balance_Sheet_Annual!E92 -> 0 | F33: =Balance_Sheet_Annual!F92 -> 0 | G33: =Balance_Sheet_Annual!G92 -> 0 | H33: =Balance_Sheet_Annual!H92 -> 0 | I33: =Balance_Sheet_Annual!I92 -> 0 | ... AB33: =Balance_Sheet_Annual!AB92 -> 3
A34: EPS Accretion | B34: =Balance_Sheet_Annual!B106 -> 0 | C34: =Balance_Sheet_Annual!C106 -> 0 | D34: =Balance_Sheet_Annual!D106 -> 0 | E34: =Balance_Sheet_Annual!E106 -> 0 | F34: =Balance_Sheet_Annual!F106 -> 0 | G34: =Balance_Sheet_Annual!G106 -> 0 | H34: =Balance_Sheet_Annual!H106 -> 0 | I34: =Balance_Sheet_Annual!I106 -> 0 | ... AB34: =Balance_Sheet_Annual!AB106 -> -0.87943714
A35: Annualized EPS Accretion | B35: =Balance_Sheet_Annual!B107 -> 0 | C35: =Balance_Sheet_Annual!C107 -> 0 | D35: =Balance_Sheet_Annual!D107 -> 0 | E35: =Balance_Sheet_Annual!E107 -> 0 | F35: =Balance_Sheet_Annual!F107 -> 0 | G35: =Balance_Sheet_Annual!G107 -> 0 | H35: =Balance_Sheet_Annual!H107 -> 0 | I35: =Balance_Sheet_Annual!I107 -> 0 | ... AB35: =Balance_Sheet_Annual!AB107 -> -5.4771916
A37: Dry Powder for Incremental Buybacks | B37: =Balance_Sheet_Annual!B111 -> 0 | C37: =Balance_Sheet_Annual!C111 -> 0 | D37: =Balance_Sheet_Annual!D111 -> 0 | E37: =Balance_Sheet_Annual!E111 -> 0 | F37: =Balance_Sheet_Annual!F111 -> 0 | G37: =Balance_Sheet_Annual!G111 -> 0 | H37: =Balance_Sheet_Annual!H111 -> 0 | I37: =Balance_Sheet_Annual!I111 -> 0 | ... AB37: =Balance_Sheet_Annual!AB111 -> -28761.411
A38: Target EV/EBITDA | B38: =Balance_Sheet_Annual!B113 -> 0 | C38: =Balance_Sheet_Annual!C113 -> 0 | D38: =Balance_Sheet_Annual!D113 -> 0 | E38: =Balance_Sheet_Annual!E113 -> 0 | F38: =Balance_Sheet_Annual!F113 -> 0 | G38: =Balance_Sheet_Annual!G113 -> 0 | H38: =Balance_Sheet_Annual!H113 -> 0 | I38: =Balance_Sheet_Annual!I113 -> 0 | ... AB38: =Balance_Sheet_Annual!AB113 -> 3
A39: EPS Accretion | B39: =Balance_Sheet_Annual!B121 -> 0 | C39: =Balance_Sheet_Annual!C121 -> 0 | D39: =Balance_Sheet_Annual!D121 -> 0 | E39: =Balance_Sheet_Annual!E121 -> 0 | F39: =Balance_Sheet_Annual!F121 -> 0 | G39: =Balance_Sheet_Annual!G121 -> 0 | H39: =Balance_Sheet_Annual!H121 -> 0 | I39: =Balance_Sheet_Annual!I121 -> 0 | ... AB39: =Balance_Sheet_Annual!AB121 -> 1.5400309
A40: Annualized EPS Accretion | B40: =Balance_Sheet_Annual!B122 -> 0 | C40: =Balance_Sheet_Annual!C122 -> 0 | D40: =Balance_Sheet_Annual!D122 -> 0 | E40: =Balance_Sheet_Annual!E122 -> 0 | F40: =Balance_Sheet_Annual!F122 -> 0 | G40: =Balance_Sheet_Annual!G122 -> 0 | H40: =Balance_Sheet_Annual!H122 -> 0 | I40: =Balance_Sheet_Annual!I122 -> 0 | ... AB40: =Balance_Sheet_Annual!AB122 -> 9.5914121
A42: Reporting Segment Metrics
A43: Commercial Airplanes (BCA)
A44: Revenue | R44: =BCA_Annual!R3 -> 58012 | S44: =BCA_Annual!S3 -> 58014 | T44: =BCA_Annual!T3 -> 57499 | U44: =BCA_Annual!U3 -> 32255 | V44: =BCA_Annual!V3 -> 16162 | W44: =BCA_Annual!W3 -> 19493 | X44: =BCA_Annual!X3 -> 25867 | Y44: =BCA_Annual!Y3 -> 33901 | ... AB44: =BCA_Annual!AB3 -> 50763.127
A45: Revenue Growth | R45: =BCA_Annual!R4 -> 0 | S45: =BCA_Annual!S4 -> 3.4475626e-05 | T45: =BCA_Annual!T4 -> -0.0088771676 | U45: =BCA_Annual!U4 -> -0.43903372 | V45: =BCA_Annual!V4 -> -0.4989304 | W45: =BCA_Annual!W4 -> 0.20610073 | X45: =BCA_Annual!X4 -> 0.32698918 | Y45: =BCA_Annual!Y4 -> 0.31058878 | ... AB45: =BCA_Annual!AB4 -> 0.22338475
A46: Segment Adjusted Profit | R46: =BCA_Annual!R19 -> 1995 | S46: =BCA_Annual!S19 -> 5452 | T46: =BCA_Annual!T19 -> 7830 | U46: =BCA_Annual!U19 -> -6657 | V46: =BCA_Annual!V19 -> -13847 | W46: =BCA_Annual!W19 -> -6475 | X46: =BCA_Annual!X19 -> -2370 | Y46: =BCA_Annual!Y19 -> -1635 | ... AB46: =BCA_Annual!AB19 -> -994.54108
A47: Segment Adjusted Profit Margin | R47: =BCA_Annual!R22 -> 0.034389437 | S47: =BCA_Annual!S22 -> 0.093977316 | T47: =BCA_Annual!T22 -> 0.13617628 | U47: =BCA_Annual!U22 -> -0.20638661 | V47: =BCA_Annual!V22 -> -0.85676278 | W47: =BCA_Annual!W22 -> -0.33217052 | X47: =BCA_Annual!X22 -> -0.091622531 | Y47: =BCA_Annual!Y22 -> -0.048228666 | ... AB47: =BCA_Annual!AB22 -> -0.019591801
A48: Book to Bill | R48: NM | S48: 0.9646637 | T48: 0.95050349 | U48: 0.021950085 | V48: -4.8782948 | W48: 1.7845893 | X48: 2.2735145 | Y48: 4.2648889 | Z48: 0 | AA48: 0 | AB48: 0
A50: Defense, Space & Security (BDS)
A51: Revenue | R51: =BDS_Annual!R3 -> 22563 | S51: =BDS_Annual!S3 -> 20561 | T51: =BDS_Annual!T3 -> 26392 | U51: =BDS_Annual!U3 -> 26227 | V51: =BDS_Annual!V3 -> 26257 | W51: =BDS_Annual!W3 -> 26540 | X51: =BDS_Annual!X3 -> 23162 | Y51: =BDS_Annual!Y3 -> 24933 | ... AB51: =BDS_Annual!AB3 -> 28228.851
A52: Revenue Growth | R52: =BDS_Annual!R4 -> 0 | S52: =BDS_Annual!S4 -> -0.088729336 | T52: =BDS_Annual!T4 -> 0.28359516 | U52: =BDS_Annual!U4 -> -0.0062518945 | V52: =BDS_Annual!V4 -> 0.0011438594 | W52: =BDS_Annual!W4 -> 0.010778078 | X52: =BDS_Annual!X4 -> -0.12727958 | Y52: =BDS_Annual!Y4 -> 0.076461445 | ... AB52: =BDS_Annual!AB4 -> 0.036529756
A53: Segment Adjusted Profit | R53: =BDS_Annual!R19 -> 1966 | S53: =BDS_Annual!S19 -> 2193 | T53: =BDS_Annual!T19 -> 1657 | U53: =BDS_Annual!U19 -> 2608 | V53: =BDS_Annual!V19 -> 1539 | W53: =BDS_Annual!W19 -> 1544 | X53: =BDS_Annual!X19 -> -3544 | Y53: =BDS_Annual!Y19 -> -1764 | ... AB53: =BDS_Annual!AB19 -> 796.81656
A54: Segment Adjusted Profit Margin | R54: =BDS_Annual!R22 -> 0.087133803 | S54: =BDS_Annual!S22 -> 0.10665824 | T54: =BDS_Annual!T22 -> 0.062784177 | U54: =BDS_Annual!U22 -> 0.099439509 | V54: =BDS_Annual!V22 -> 0.058612941 | W54: =BDS_Annual!W22 -> 0.058176338 | X54: =BDS_Annual!X22 -> -0.15300924 | Y54: =BDS_Annual!Y22 -> -0.070749609 | ... AB54: =BDS_Annual!AB22 -> 0.028227028
A55: Book to Bill | R55: NM | S55: 0.96225865 | T55: 1.6527736 | U55: 1.0920426 | V55: 0.89168603 | W55: 0.96160512 | X55: 0.76448493 | Y55: 1.1860586 | Z55: 0 | AA55: 0 | AB55: 0
A57: Global Services (BGS)
A58: Revenue | R58: =BGS_Annual!R3 -> 13925 | S58: =BGS_Annual!S3 -> 14581 | T58: =BGS_Annual!T3 -> 17056 | U58: =BGS_Annual!U3 -> 18468 | V58: =BGS_Annual!V3 -> 15543 | W58: =BGS_Annual!W3 -> 16328 | X58: =BGS_Annual!X3 -> 17611 | Y58: =BGS_Annual!Y3 -> 19127 | ... AB58: =BGS_Annual!AB3 -> 20923
A59: Revenue Growth | R59: =BGS_Annual!R4 -> 0 | S59: =BGS_Annual!S4 -> 0.047109515 | T59: =BGS_Annual!T4 -> 0.16974144 | U59: =BGS_Annual!U4 -> 0.082786116 | V59: =BGS_Annual!V4 -> -0.15838207 | W59: =BGS_Annual!W4 -> 0.050505051 | X59: =BGS_Annual!X4 -> 0.078576678 | Y59: =BGS_Annual!Y4 -> 0.086082562 | ... AB59: =BGS_Annual!AB4 -> 0
A60: Segment Adjusted Profit | R60: =BGS_Annual!R19 -> 2177 | S60: =BGS_Annual!S19 -> 2246 | T60: =BGS_Annual!T19 -> 2536 | U60: =BGS_Annual!U19 -> 2697 | V60: =BGS_Annual!V19 -> 450 | W60: =BGS_Annual!W19 -> 2017 | X60: =BGS_Annual!X19 -> 2727 | Y60: =BGS_Annual!Y19 -> 3329 | ... AB60: =BGS_Annual!AB19 -> 3818.4475
A61: Segment Adjusted Profit Margin | R61: =BGS_Annual!R22 -> 0.15633752 | S61: =BGS_Annual!S22 -> 0.15403607 | T61: =BGS_Annual!T22 -> 0.14868668 | U61: =BGS_Annual!U22 -> 0.14603639 | V61: =BGS_Annual!V22 -> 0.02895194 | W61: =BGS_Annual!W22 -> 0.12353013 | X61: =BGS_Annual!X22 -> 0.1548464 | Y61: =BGS_Annual!Y22 -> 0.17404716 | ... AB61: =BGS_Annual!AB22 -> 0.1825
A62: Book to Bill | R62: NM | S62: 1.2725465 | T62: 1.0855417 | U62: 1.0995235 | V62: 0.85395355 | W62: 0.99167075 | X62: 0.93424564 | Y62: 1.0277618 | Z62: 0 | AA62: 0 | AB62: 0
A64: Boeing Capital (BCC)
A65: Revenue | B65: 728 | C65: 815 | D65: 994 | E65: 991 | F65: 959 | G65: 966 | H65: 1025 | I65: 815 | J65: 703 | K65: 660 | L65: 639 | M65: 520 | N65: 468 | O65: 408 | P65: 416 | Q65: 413 | R65: 298 | S65: 307 | T65: 274 | U65: 244 | V65: 261 | W65: 272 | X65: 199 | Y65: 200.99 | Z65: 202.9999 | AA65: 205.0299 | AB65: 207.0802
A66: Revenue Growth | B66: -0.055771725 | C66: 0.11950549 | D66: 0.2196319 | E66: -0.0030181087 | F66: -0.032290616 | G66: 0.0072992701 | H66: 0.061076605 | I66: -0.20487805 | J66: -0.13742331 | K66: -0.06116643 | L66: -0.031818182 | M66: -0.18622848 | N66: -0.1 | O66: -0.12820513 | P66: 0.019607843 | Q66: -0.0072115385 | R66: -0.27845036 | S66: 0.030201342 | T66: -0.10749186 | U66: -0.10948905 | V66: 0.069672131 | W66: 0.042145594 | X66: -0.26838235 | Y66: 0.01 | Z66: 0.01 | AA66: 0.01 | AB66: 0.01
A67: Segment Adjusted Profit | B67: 516 | C67: 562 | D67: 72 | E67: 91 | F67: 183 | G67: 232 | H67: 291 | I67: 234 | J67: 162 | K67: 126 | L67: 152 | M67: 113 | N67: 88 | O67: 107 | P67: 92 | Q67: 50 | R67: 59 | S67: 114 | T67: 79 | U67: 28 | V67: 63 | W67: 106 | X67: 29 | Y67: 24.1188 | Z67: 24.359988 | AA67: 24.603588 | AB67: 24.849624
A68: Segment Adjusted Profit Margin | B68: 0.70879121 | C68: 0.68957055 | D68: 0.072434608 | E68: 0.091826438 | F68: 0.19082377 | G68: 0.24016563 | H68: 0.28390244 | I68: 0.28711656 | J68: 0.23044097 | K68: 0.19090909 | L68: 0.23787167 | M68: 0.21730769 | N68: 0.18803419 | O68: 0.2622549 | P68: 0.22115385 | Q68: 0.12106538 | R68: 0.19798658 | S68: 0.3713355 | T68: 0.28832117 | U68: 0.1147541 | V68: 0.24137931 | W68: 0.38970588 | X68: 0.14572864 | Y68: 0.12 | Z68: 0.12 | AA68: 0.12 | AB68: 0.12
A69: Book to Bill | B69: ND | C69: ND | D69: ND | E69: ND | F69: ND | G69: ND | H69: ND | I69: ND | J69: ND | K69: ND | L69: ND | M69: ND | N69: ND | O69: ND | P69: ND | Q69: ND | R69: ND | S69: ND | T69: ND | U69: ND | V69: ND | W69: ND | X69: ND | Y69: ND | Z69: ND | AA69: ND | AB69: ND
A71: Commercial Airplanes (BCA) (Old)
A72: Revenue | B72: 31171 | C72: 35056 | D72: 28387 | E72: 22408 | F72: 21037 | G72: 21365 | H72: 28465 | I72: 33386 | J72: 28263 | K72: 34051 | L72: 31834 | M72: 36171 | N72: 49127 | O72: 52981 | P72: 59990 | Q72: 66048
A73: Revenue Growth | B73: -0.18983756 | C73: 0.12463508 | D73: -0.19023848 | E73: -0.21062458 | F73: -0.061183506 | G73: 0.015591577 | H73: 0.33231921 | I73: 0.17287897 | J73: -0.15344755 | K73: 0.20479072 | L73: -0.06510822 | M73: 0.13623798 | N73: 0.3581875 | O73: 0.078449732 | P73: 0.13229271 | Q73: 0.1009835
A74: Segment Adjusted Profit | B74: 2736 | C74: 2632 | D74: 2017 | E74: 1048 | F74: 1308 | G74: 1431 | H74: 2733 | I74: 3584 | J74: 3809.1385 | K74: 3462 | L74: 3006 | M74: 3495 | N74: 4711 | O74: 5795 | P74: 6411 | Q74: 5157
A75: Segment Adjusted Profit Margin | B75: 0.087773892 | C75: 0.075079872 | D75: 0.071053651 | E75: 0.046769011 | F75: 0.062176166 | G75: 0.066978703 | H75: 0.096012647 | I75: 0.10735039 | J75: 0.13477474 | K75: 0.10167102 | L75: 0.094427342 | M75: 0.096624368 | N75: 0.095894315 | O75: 0.10937883 | P75: 0.10686781 | Q75: 0.078079578
A76: Book to Bill | B76: 0 | C76: NM | D76: NM | E76: 0.81122813 | F76: 1.3398774 | G76: 3.5108823 | H76: 2.7505006 | I76: 3.4240999 | J76: 1.8293175 | K76: 0.17174239 | L76: 1.1545832 | M76: 2.0989743 | N76: 1.475543 | O76: 2.0359752 | P76: 2.1141524 | Q76: 0.86594598
A78: Defense Space & Security (BDS) (Old)
A79: Revenue | B79: 19963 | C79: 22815 | D79: 24957 | E79: 27361 | F79: 30465 | G79: 31106 | H79: 32439 | I79: 32052 | J79: 32047 | K79: 33661 | L79: 31943 | M79: 31976 | N79: 32607 | O79: 33197 | P79: 30881 | Q79: 30388
A80: Revenue Growth | B80: 0.047871503 | C80: 0.1428643 | D80: 0.093885602 | E80: 0.09632568 | F80: 0.11344615 | G80: 0.021040538 | H80: 0.042853469 | I80: -0.011930084 | J80: -0.00015599651 | K80: 0.050363529 | L80: -0.051038294 | M80: 0.0010330902 | N80: 0.01973355 | O80: 0.018094274 | P80: -0.06976534 | Q80: -0.49344891
A81: Segment Adjusted Profit | B81: 1002 | C81: 1965 | D81: 2009 | E81: 1338 | F81: 2925 | G81: 3919 | H81: 3032 | I81: 3440 | J81: 3480 | K81: 3299 | L81: 2875 | M81: 3158 | N81: 3068 | O81: 3235 | P81: 3133 | Q81: 3274
A82: Segment Adjusted Profit Margin | B82: 0.050192857 | C82: 0.086127548 | D82: 0.080498457 | E82: 0.048901721 | F82: 0.096011817 | G82: 0.12598856 | H82: 0.093467739 | I82: 0.1073256 | J82: 0.10859051 | K82: 0.098006595 | L82: 0.09000407 | M82: 0.098761571 | N82: 0.094090226 | O82: 0.097448565 | P82: 0.10145397 | Q82: 0.1077399
A83: Book to Bill | B83: 0 | C83: NM | D83: NM | E83: 1.7565513 | F83: 0.83656655 | G83: 0.8100688 | H83: 0.85209162 | I83: 0.86852615 | J83: 1.0468999 | K83: 0.75743442 | L83: 1.0108631 | M83: 0.83909807 | N83: 1.3506609 | O83: 0.87387415 | P83: 0.82594476 | Q83: 0.86053705

Sheet Income_Statement_Annual
A1: Income Statement Annual
B2: CY2000A | C2: CY2001A | D2: CY2002A | E2: CY2003A | F2: CY2004A | G2: CY2005A | H2: CY2006A | I2: CY2007A | J2: CY2008A | K2: CY2009A | L2: CY2010A | M2: CY2011A | N2: CY2012A | O2: CY2013A | P2: CY2014A | Q2: CY2015A | R2: CY2016A | S2: CY2017A | T2: CY2018A | U2: CY2019A | V2: CY2020A | W2: CY2021A | X2: CY2022A | Y2: CY2023A | Z2: CY2024A | AA2: CY2025A | AB2: CY2026E | AC2: CY2027E | AD2: CY2028E | AE2: CY2029E | AF2: CY2030E
A3: =Income_Statement_Qtr!A3 -> Commercial Airplanes (BCA) | B3: =BCA_Annual!B3 -> 0 | C3: =BCA_Annual!C3 -> 0 | D3: =BCA_Annual!D3 -> 0 | E3: =BCA_Annual!E3 -> 0 | F3: =BCA_Annual!F3 -> 0 | G3: =BCA_Annual!G3 -> 0 | H3: =BCA_Annual!H3 -> 0 | I3: =BCA_Annual!I3 -> 0 | ... P3: =BCA_Annual!P3 -> 0 | Q3: =+Income_Statement_Qtr!F3 -> 0 | R3: =+Income_Statement_Qtr!K3 -> 58012 | S3: =+Income_Statement_Qtr!P3 -> 58014 | T3: =+Income_Statement_Qtr!U3 -> 57499 | U3: =+Income_Statement_Qtr!Z3 -> 32255 | V3: =+Income_Statement_Qtr!AE3 -> 16162 | W3: =+Income_Statement_Qtr!AJ3 -> 19493 | X3: =+Income_Statement_Qtr!AO3 -> 25867 | Y3: =+Income_Statement_Qtr!AT3 -> 33901 | Z3: =+Income_Statement_Qtr!AY3 -> 22861 | AA3: =+Income_Statement_Qtr!BD3 -> 41494 | AB3: =+Income_Statement_Qtr!BI3 -> 50763.127 | AC3: =BCA_Annual!AC3 -> 57203.394 | AD3: =BCA_Annual!AD3 -> 59684.099 | AE3: =BCA_Annual!AE3 -> 61238.072 | AF3: =BCA_Annual!AF3 -> 62838.664
A4: =Income_Statement_Qtr!A4 -> Defense, Space & Security (BDS) | B4: =BDS_Annual!B3 -> 0 | C4: =BDS_Annual!C3 -> 0 | D4: =BDS_Annual!D3 -> 0 | E4: =BDS_Annual!E3 -> 0 | F4: =BDS_Annual!F3 -> 0 | G4: =BDS_Annual!G3 -> 0 | H4: =BDS_Annual!H3 -> 0 | I4: =BDS_Annual!I3 -> 0 | ... P4: =BDS_Annual!P3 -> 0 | Q4: =+Income_Statement_Qtr!F4 -> 0 | R4: =+Income_Statement_Qtr!K4 -> 22563 | S4: =+Income_Statement_Qtr!P4 -> 20561 | T4: =+Income_Statement_Qtr!U4 -> 26392 | U4: =+Income_Statement_Qtr!Z4 -> 26227 | V4: =+Income_Statement_Qtr!AE4 -> 26257 | W4: =+Income_Statement_Qtr!AJ4 -> 26540 | X4: =+Income_Statement_Qtr!AO4 -> 23162 | Y4: =+Income_Statement_Qtr!AT4 -> 24933 | Z4: =+Income_Statement_Qtr!AY4 -> 23918 | AA4: =+Income_Statement_Qtr!BD4 -> 27234 | AB4: =+Income_Statement_Qtr!BI4 -> 28228.851 | AC4: =BDS_Annual!AC3 -> 29196.688 | AD4: =BDS_Annual!AD3 -> 30119.099 | AE4: =BDS_Annual!AE3 -> 31087.585 | AF4: =BDS_Annual!AF3 -> 31291.727
A5: =Income_Statement_Qtr!A5 -> Global Services (BGS) | B5: =BGS_Annual!B3 -> 0 | C5: =BGS_Annual!C3 -> 0 | D5: =BGS_Annual!D3 -> 0 | E5: =BGS_Annual!E3 -> 0 | F5: =BGS_Annual!F3 -> 0 | G5: =BGS_Annual!G3 -> 0 | H5: =BGS_Annual!H3 -> 0 | I5: =BGS_Annual!I3 -> 0 | ... P5: =BGS_Annual!P3 -> 0 | Q5: =+Income_Statement_Qtr!F5 -> 0 | R5: =+Income_Statement_Qtr!K5 -> 13925 | S5: =+Income_Statement_Qtr!P5 -> 14581 | T5: =+Income_Statement_Qtr!U5 -> 17056 | U5: =+Income_Statement_Qtr!Z5 -> 18468 | V5: =+Income_Statement_Qtr!AE5 -> 15543 | W5: =+Income_Statement_Qtr!AJ5 -> 16328 | X5: =+Income_Statement_Qtr!AO5 -> 17611 | Y5: =+Income_Statement_Qtr!AT5 -> 19127 | Z5: =+Income_Statement_Qtr!AY5 -> 19954 | AA5: =+Income_Statement_Qtr!BD5 -> 20923 | AB5: =+Income_Statement_Qtr!BI5 -> 20923 | AC5: =BGS_Annual!AC3 -> 22178.38 | AD5: =BGS_Annual!AD3 -> 23509.083 | AE5: =BGS_Annual!AE3 -> 24919.628 | AF5: =BGS_Annual!AF3 -> 26414.805
A6: =Income_Statement_Qtr!A6 -> Boeing Capital (BCC) (Old | B6: 728 | C6: 815 | D6: 994 | E6: 991 | F6: 959 | G6: 966 | H6: 1025 | I6: 815 | J6: 703 | K6: 660 | L6: 639 | M6: 520 | N6: 468 | O6: 408 | P6: 416 | Q6: =+Income_Statement_Qtr!F6 -> 413 | R6: =+Income_Statement_Qtr!K6 -> 298 | S6: =+Income_Statement_Qtr!P6 -> 307 | T6: =+Income_Statement_Qtr!U6 -> 274 | U6: =+Income_Statement_Qtr!Z6 -> 244 | V6: =+Income_Statement_Qtr!AE6 -> 261 | W6: =+Income_Statement_Qtr!AJ6 -> 272 | X6: =+Income_Statement_Qtr!AO6 -> 199 | Y6: =+Income_Statement_Qtr!AT6 -> 0 | Z6: =+Income_Statement_Qtr!AY6 -> 0 | AA6: =+Income_Statement_Qtr!BD6 -> 0 | AB6: =+Income_Statement_Qtr!BI6 -> 0 | AC6: 0 | AD6: 0 | AE6: 0 | AF6: 0
A7: =Income_Statement_Qtr!A7 -> Commercial Airplanes (BCA) (Old) | B7: 31171 | C7: 35056 | D7: 28387 | E7: 22408 | F7: 21037 | G7: 21365 | H7: 28465 | I7: 33386 | J7: 28263 | K7: 34051 | L7: 31834 | M7: 36171 | N7: 49127 | O7: 52981 | P7: 59990 | Q7: =+Income_Statement_Qtr!F7 -> 66048 | R7: =+Income_Statement_Qtr!K7 -> 0 | S7: =+Income_Statement_Qtr!P7 -> 0 | T7: =+Income_Statement_Qtr!U7 -> 0 | U7: =+Income_Statement_Qtr!Z7 -> 0 | V7: =+Income_Statement_Qtr!AE7 -> 0 | W7: =+Income_Statement_Qtr!AJ7 -> 0 | X7: =+Income_Statement_Qtr!AO7 -> 0 | Y7: =+Income_Statement_Qtr!AT7 -> 0 | Z7: =+Income_Statement_Qtr!AY7 -> 0 | AA7: =+Income_Statement_Qtr!BD7 -> 0 | AB7: =+Income_Statement_Qtr!BI7 -> 0 | AC7: 0 | AD7: 0 | AE7: 0 | AF7: 0
A8: =Income_Statement_Qtr!A8 -> Defense, Space & Security (BDS) (Old) | B8: 19963 | C8: 22815 | D8: 24957 | E8: 27361 | F8: 30465 | G8: 31106 | H8: 32439 | I8: 32052 | J8: 32047 | K8: 33661 | L8: 31943 | M8: 31976 | N8: 32607 | O8: 33197 | P8: 30881 | Q8: =+Income_Statement_Qtr!F8 -> 30388 | R8: =+Income_Statement_Qtr!K8 -> 0 | S8: =+Income_Statement_Qtr!P8 -> 0 | T8: =+Income_Statement_Qtr!U8 -> 0 | U8: =+Income_Statement_Qtr!Z8 -> 0 | V8: =+Income_Statement_Qtr!AE8 -> 0 | W8: =+Income_Statement_Qtr!AJ8 -> 0 | X8: =+Income_Statement_Qtr!AO8 -> 0 | Y8: =+Income_Statement_Qtr!AT8 -> 0 | Z8: =+Income_Statement_Qtr!AY8 -> 0 | AA8: =+Income_Statement_Qtr!BD8 -> 0 | AB8: =+Income_Statement_Qtr!BI8 -> 0 | AC8: 0 | AD8: 0 | AE8: 0 | AF8: 0
A9: =Income_Statement_Qtr!A9 -> Unallocated Items, Eliminations and Other | B9: =303-844 -> -541 | C9: =413-901 -> -488 | D9: =536-813 -> -277 | E9: =871-1375 -> -504 | F9: =549-553 -> -4 | G9: =657-473 -> 184 | H9: =299-698 -> -399 | I9: =308-174 -> 134 | J9: =567-671 -> -104 | K9: =165-256 -> -91 | L9: =-248+138 -> -110 | M9: =150-82 -> 68 | N9: =106-610 -> -504 | O9: 37 | P9: -525 | Q9: =+Income_Statement_Qtr!F9 -> -735 | R9: =+Income_Statement_Qtr!K9 -> -227 | S9: =+Income_Statement_Qtr!P9 -> 542 | T9: =+Income_Statement_Qtr!U9 -> -94 | U9: =+Income_Statement_Qtr!Z9 -> -635 | V9: =+Income_Statement_Qtr!AE9 -> -65 | W9: =+Income_Statement_Qtr!AJ9 -> -347 | X9: =+Income_Statement_Qtr!AO9 -> -231 | Y9: =+Income_Statement_Qtr!AT9 -> -167 | Z9: =+Income_Statement_Qtr!AY9 -> -216 | AA9: =+Income_Statement_Qtr!BD9 -> -188 | AB9: =+Income_Statement_Qtr!BI9 -> -200 | AC9: -200 | AD9: -200 | AE9: -200 | AF9: -200
A10: =Income_Statement_Qtr!A10 -> Total Net Sales | B10: =SUM(B3:B9) -> 51321 | C10: =SUM(C3:C9) -> 58198 | D10: =SUM(D3:D9) -> 54061 | E10: =SUM(E3:E9) -> 50256 | F10: =SUM(F3:F9) -> 52457 | G10: =SUM(G3:G9) -> 53621 | H10: =SUM(H3:H9) -> 61530 | I10: =SUM(I3:I9) -> 66387 | ... AF10: =SUM(AF3:AF9) -> 120345.2
A11: =Income_Statement_Qtr!A11 -> YoY | B11: =B10/57993-1 -> -0.11504837 | C11: =C10/B10-1 -> 0.13399973 | D11: =D10/C10-1 -> -0.071084917 | E11: =E10/D10-1 -> -0.070383456 | F11: =F10/E10-1 -> 0.043795766 | G11: =G10/F10-1 -> 0.022189603 | H11: =H10/G10-1 -> 0.14749818 | I11: =I10/H10-1 -> 0.078937104 | J11: =J10/I10-1 -> -0.082516155 | ... P11: =P10/O10-1 -> 0.047781767 | Q11: =+Income_Statement_Qtr!F11 -> 0.058967409 | R11: =+Income_Statement_Qtr!K11 -> -0.016053853 | S11: =+Income_Statement_Qtr!P11 -> -0.0059849214 | T11: =+Income_Statement_Qtr!U11 -> 0.075761928 | U11: =+Income_Statement_Qtr!Z11 -> -0.24294204 | V11: =+Income_Statement_Qtr!AE11 -> -0.24035058 | W11: =+Income_Statement_Qtr!AJ11 -> 0.070979057 | X11: =+Income_Statement_Qtr!AO11 -> 0.06938959 | Y11: =+Income_Statement_Qtr!AT11 -> 0.16793779 | Z11: =+Income_Statement_Qtr!AY11 -> -0.14495977 | AA11: =+Income_Statement_Qtr!BD11 -> 0.34496445 | AB11: =+Income_Statement_Qtr!BI11 -> 0.11459462 | AC11: =AC10/AB10-1 -> 0.086882475 | AD11: =AD10/AC10-1 -> 0.04367859 | AE11: =AE10/AD10-1 -> 0.03477079 | AF11: =AF10/AE10-1 -> 0.028193462
A13: =Income_Statement_Qtr!A13 -> Commercial Airplanes (BCA) | B13: =BCA_Annual!B19 -> 0 | C13: =BCA_Annual!C19 -> 0 | D13: =BCA_Annual!D19 -> 0 | E13: =BCA_Annual!E19 -> 0 | F13: =BCA_Annual!F19 -> 0 | G13: =BCA_Annual!G19 -> 0 | H13: =BCA_Annual!H19 -> 0 | I13: =BCA_Annual!I19 -> 0 | ... P13: =BCA_Annual!P19 -> 0 | Q13: =+Income_Statement_Qtr!F13 -> 0 | R13: =+Income_Statement_Qtr!K13 -> 1995 | S13: =+Income_Statement_Qtr!P13 -> 5452 | T13: =+Income_Statement_Qtr!U13 -> 7830 | U13: =+Income_Statement_Qtr!Z13 -> -6657 | V13: =+Income_Statement_Qtr!AE13 -> -13847 | W13: =+Income_Statement_Qtr!AJ13 -> -6475 | X13: =+Income_Statement_Qtr!AO13 -> -2370 | Y13: =+Income_Statement_Qtr!AT13 -> -1635 | Z13: =+Income_Statement_Qtr!AY13 -> -7969 | AA13: =+Income_Statement_Qtr!BD13 -> -7079 | AB13: =+Income_Statement_Qtr!BI13 -> -994.54108 | AC13: =BCA_Annual!AC19 -> 4404.3018 | AD13: =BCA_Annual!AD19 -> 5872.9449 | AE13: =BCA_Annual!AE19 -> 6048.3803 | AF13: =BCA_Annual!AF19 -> 6229.0787
A14: =Income_Statement_Qtr!A14 -> Defense, Space & Security (BDS) | B14: =BDS_Annual!B19 -> 0 | C14: =BDS_Annual!C19 -> 0 | D14: =BDS_Annual!D19 -> 0 | E14: =BDS_Annual!E19 -> 0 | F14: =BDS_Annual!F19 -> 0 | G14: =BDS_Annual!G19 -> 0 | H14: =BDS_Annual!H19 -> 0 | I14: =BDS_Annual!I19 -> 0 | ... P14: =BDS_Annual!P19 -> 0 | Q14: =+Income_Statement_Qtr!F14 -> 0 | R14: =+Income_Statement_Qtr!K14 -> 1966 | S14: =+Income_Statement_Qtr!P14 -> 2193 | T14: =+Income_Statement_Qtr!U14 -> 1657 | U14: =+Income_Statement_Qtr!Z14 -> 2608 | V14: =+Income_Statement_Qtr!AE14 -> 1539 | W14: =+Income_Statement_Qtr!AJ14 -> 1544 | X14: =+Income_Statement_Qtr!AO14 -> -3544 | Y14: =+Income_Statement_Qtr!AT14 -> -1764 | Z14: =+Income_Statement_Qtr!AY14 -> -5413 | AA14: =+Income_Statement_Qtr!BD14 -> -128 | AB14: =+Income_Statement_Qtr!BI14 -> 796.81656 | AC14: =BDS_Annual!AC19 -> 1490.5286 | AD14: =BDS_Annual!AD19 -> 1971.7166 | AE14: =BDS_Annual!AE19 -> 2043.429 | AF14: =BDS_Annual!AF19 -> 2058.5266
A15: =Income_Statement_Qtr!A15 -> Global Services (BGS) | B15: =BGS_Annual!B19 -> 0 | C15: =BGS_Annual!C19 -> 0 | D15: =BGS_Annual!D19 -> 0 | E15: =BGS_Annual!E19 -> 0 | F15: =BGS_Annual!F19 -> 0 | G15: =BGS_Annual!G19 -> 0 | H15: =BGS_Annual!H19 -> 0 | I15: =BGS_Annual!I19 -> 0 | ... P15: =BGS_Annual!P19 -> 0 | Q15: =+Income_Statement_Qtr!F15 -> 0 | R15: =+Income_Statement_Qtr!K15 -> 2177 | S15: =+Income_Statement_Qtr!P15 -> 2246 | T15: =+Income_Statement_Qtr!U15 -> 2536 | U15: =+Income_Statement_Qtr!Z15 -> 2697 | V15: =+Income_Statement_Qtr!AE15 -> 450 | W15: =+Income_Statement_Qtr!AJ15 -> 2017 | X15: =+Income_Statement_Qtr!AO15 -> 2727 | Y15: =+Income_Statement_Qtr!AT15 -> 3329 | Z15: =+Income_Statement_Qtr!AY15 -> 3618 | AA15: =+Income_Statement_Qtr!BD15 -> 13474 | AB15: =+Income_Statement_Qtr!BI15 -> 3818.4475 | AC15: =BGS_Annual!AC19 -> 3881.2165 | AD15: =BGS_Annual!AD19 -> 4114.0895 | AE15: =BGS_Annual!AE19 -> 4360.9349 | AF15: =BGS_Annual!AF19 -> 4622.591
A16: =Income_Statement_Qtr!A16 -> Boeing Capital (BCC) | B16: 516 | C16: 562 | D16: 72 | E16: 91 | F16: 183 | G16: 232 | H16: 291 | I16: 234 | J16: 162 | K16: 126 | L16: 152 | M16: 113 | N16: 88 | O16: 107 | P16: 92 | Q16: =+Income_Statement_Qtr!F16 -> 50 | R16: =+Income_Statement_Qtr!K16 -> 59 | S16: =+Income_Statement_Qtr!P16 -> 114 | T16: =+Income_Statement_Qtr!U16 -> 79 | U16: =+Income_Statement_Qtr!Z16 -> 28 | V16: =+Income_Statement_Qtr!AE16 -> 63 | W16: =+Income_Statement_Qtr!AJ16 -> 106 | X16: =+Income_Statement_Qtr!AO16 -> 29 | Y16: =+Income_Statement_Qtr!AT16 -> 0 | Z16: =+Income_Statement_Qtr!AY16 -> 0 | AA16: =+Income_Statement_Qtr!BD16 -> 0 | AB16: =+Income_Statement_Qtr!BI16 -> 0 | AC16: 0 | AD16: 0 | AE16: 0 | AF16: 0
A17: =Income_Statement_Qtr!A17 -> Commercial Airplanes (BCA) (Old) | B17: 2736 | C17: 2632 | D17: 2017 | E17: 1048 | F17: 1308 | G17: 1431 | H17: 2733 | I17: 3584 | J17: 3809.1385 | K17: 3462 | L17: 3006 | M17: 3495 | N17: 4711 | O17: 5795 | P17: 6411 | Q17: =+Income_Statement_Qtr!F17 -> 5157 | R17: =+Income_Statement_Qtr!K17 -> 0 | S17: =+Income_Statement_Qtr!P17 -> 0 | T17: =+Income_Statement_Qtr!U17 -> 0 | U17: =+Income_Statement_Qtr!Z17 -> 0 | V17: =+Income_Statement_Qtr!AE17 -> 0 | W17: =+Income_Statement_Qtr!AJ17 -> 0 | X17: =+Income_Statement_Qtr!AO17 -> 0 | Y17: =+Income_Statement_Qtr!AT17 -> 0 | Z17: =+Income_Statement_Qtr!AY17 -> 0 | AA17: =+Income_Statement_Qtr!BD17 -> 0 | AB17: =+Income_Statement_Qtr!BI17 -> 0 | AC17: 0 | AD17: 0 | AE17: 0 | AF17: 0
A18: =Income_Statement_Qtr!A18 -> Defense, Space & Security (BDS) (Old) | B18: 1002 | C18: 1965 | D18: 2009 | E18: 1338 | F18: 2925 | G18: 3919 | H18: 3032 | I18: 3440 | J18: 3480 | K18: 3299 | L18: 2875 | M18: 3158 | N18: 3068 | O18: 3235 | P18: 3133 | Q18: =+Income_Statement_Qtr!F18 -> 3274 | R18: =+Income_Statement_Qtr!K18 -> 0 | S18: =+Income_Statement_Qtr!P18 -> 0 | T18: =+Income_Statement_Qtr!U18 -> 0 | U18: =+Income_Statement_Qtr!Z18 -> 0 | V18: =+Income_Statement_Qtr!AE18 -> 0 | W18: =+Income_Statement_Qtr!AJ18 -> 0 | X18: =+Income_Statement_Qtr!AO18 -> 0 | Y18: =+Income_Statement_Qtr!AT18 -> 0 | Z18: =+Income_Statement_Qtr!AY18 -> 0 | AA18: =+Income_Statement_Qtr!BD18 -> 0 | AB18: =+Income_Statement_Qtr!BI18 -> 0 | AC18: 0 | AD18: 0 | AE18: 0 | AF18: 0
A19: =Income_Statement_Qtr!A19 -> Unallocated Items, Eliminations and Other | B19: -76 | C19: -354 | D19: -432 | E19: -379 | F19: -535 | G19: -363 | H19: -738 | I19: -331 | J19: -307 | K19: -152 | L19: -327 | M19: 66 | N19: -186 | O19: 0 | P19: 0 | Q19: =+Income_Statement_Qtr!F19 -> 0 | R19: =+Income_Statement_Qtr!K19 -> 0 | S19: =+Income_Statement_Qtr!P19 -> 0 | T19: =+Income_Statement_Qtr!U19 -> 0 | U19: =+Income_Statement_Qtr!Z19 -> 0 | V19: =+Income_Statement_Qtr!AE19 -> 0 | W19: =+Income_Statement_Qtr!AJ19 -> 0 | X19: =+Income_Statement_Qtr!AO19 -> 0 | Y19: =+Income_Statement_Qtr!AT19 -> 0 | Z19: =+Income_Statement_Qtr!AY19 -> 0 | AA19: =+Income_Statement_Qtr!BD19 -> 0 | AB19: =+Income_Statement_Qtr!BI19 -> 0 | AC19: 0 | AD19: 0 | AE19: 0 | AF19: 0
A20: =Income_Statement_Qtr!A20 -> Business Segment Operating Profit | B20: =SUM(B13:B19) -> 4178 | C20: =SUM(C13:C19) -> 4805 | D20: =SUM(D13:D19) -> 3666 | E20: =SUM(E13:E19) -> 2098 | F20: =SUM(F13:F19) -> 3881 | G20: =SUM(G13:G19) -> 5219 | H20: =SUM(H13:H19) -> 5318 | I20: =SUM(I13:I19) -> 6927 | ... AF20: =SUM(AF13:AF19) -> 12910.196
A22: =Income_Statement_Qtr!A22 -> Pension FAS/CAS Service Cost Adjustment | B22: ND | C22: ND | D22: ND | E22: 463 | F22: 27 | G22: -846 | H22: -369 | I22: -561 | J22: -208 | K22: 110 | L22: 54 | M22: -269 | N22: -787 | O22: -1374 | P22: -1469 | Q22: =Income_Statement_Qtr!F22 -> -421 | R22: =Income_Statement_Qtr!K22 -> 217 | S22: =Income_Statement_Qtr!P22 -> 1127 | T22: =Income_Statement_Qtr!U22 -> 1005 | U22: =Income_Statement_Qtr!Z22 -> 1071 | V22: =Income_Statement_Qtr!AE22 -> 1024 | W22: =Income_Statement_Qtr!AJ22 -> 882 | X22: =Income_Statement_Qtr!AO22 -> 849 | Y22: =Income_Statement_Qtr!AT22 -> 799 | Z22: =Income_Statement_Qtr!AY22 -> 811 | AA22: =Income_Statement_Qtr!BD22 -> 784 | AB22: =Income_Statement_Qtr!BI22 -> 850 | AC22: 850 | AD22: 850 | AE22: 850 | AF22: 850
A23: =Income_Statement_Qtr!A23 -> Postretirement FAS/CAS Service Cost Adjustment | B23: ND | C23: ND | D23: ND | E23: -257 | F23: -285 | G23: -5 | H23: -103 | I23: -125 | J23: -79 | K23: -93 | L23: -59 | M23: -248 | N23: -112 | O23: 60 | P23: 82 | Q23: =Income_Statement_Qtr!F23 -> 123 | R23: =Income_Statement_Qtr!K23 -> 153 | S23: =Income_Statement_Qtr!P23 -> 311 | T23: =Income_Statement_Qtr!U23 -> 322 | U23: =Income_Statement_Qtr!Z23 -> 344 | V23: =Income_Statement_Qtr!AE23 -> 359 | W23: =Income_Statement_Qtr!AJ23 -> 291 | X23: =Income_Statement_Qtr!AO23 -> 294 | Y23: =Income_Statement_Qtr!AT23 -> 257 | Z23: =Income_Statement_Qtr!AY23 -> 293 | AA23: =Income_Statement_Qtr!BD23 -> 261 | AB23: =Income_Statement_Qtr!BI23 -> 260 | AC23: 260 | AD23: 260 | AE23: 260 | AF23: 260
A24: =Income_Statement_Qtr!A24 -> FAS/CAS Operating Adjustment | B24: =SUM(B22:B23) -> 0 | C24: =SUM(C22:C23) -> 0 | D24: =SUM(D22:D23) -> 0 | E24: =SUM(E22:E23) -> 206 | F24: =SUM(F22:F23) -> -258 | G24: =SUM(G22:G23) -> -851 | H24: =SUM(H22:H23) -> -472 | I24: =SUM(I22:I23) -> -686 | ... AF24: =SUM(AF22:AF23) -> 1110
A25: =Income_Statement_Qtr!A25 -> Share-Based Plans | B25: -316 | C25: -378 | D25: -447 | E25: -456 | F25: -576 | G25: =-999 -> -999 | H25: -680 | I25: -233 | J25: -149 | K25: -189 | L25: -136 | M25: -83 | N25: -81 | O25: -95 | P25: -67 | Q25: =Income_Statement_Qtr!F25 -> -76 | R25: =Income_Statement_Qtr!K25 -> -66 | S25: =Income_Statement_Qtr!P25 -> -77 | T25: =Income_Statement_Qtr!U25 -> -76 | U25: =Income_Statement_Qtr!Z25 -> -65 | V25: =Income_Statement_Qtr!AE25 -> -120 | W25: =Income_Statement_Qtr!AJ25 -> -174 | X25: =Income_Statement_Qtr!AO25 -> -114 | Y25: =Income_Statement_Qtr!AT25 -> 62 | Z25: =Income_Statement_Qtr!AY25 -> 171 | AA25: =Income_Statement_Qtr!BD25 -> -49 | AB25: =Income_Statement_Qtr!BI25 -> 50.5 | AC25: 51.005 | AD25: 51.51505 | AE25: 52.0302 | AF25: 52.0302
A26: =Income_Statement_Qtr!A26 -> Deferred Compensation | B26: 0 | C26: 0 | D26: 0 | E26: 0 | F26: 0 | G26: -186 | H26: -211 | I26: -51 | J26: 223 | K26: -158 | L26: -112 | M26: -61 | N26: -75 | O26: -238 | P26: -44 | Q26: =Income_Statement_Qtr!F26 -> -63 | R26: =Income_Statement_Qtr!K26 -> -46 | S26: =Income_Statement_Qtr!P26 -> -240 | T26: =Income_Statement_Qtr!U26 -> -19 | U26: =Income_Statement_Qtr!Z26 -> -174 | V26: =Income_Statement_Qtr!AE26 -> -93 | W26: =Income_Statement_Qtr!AJ26 -> -126 | X26: =Income_Statement_Qtr!AO26 -> 117 | Y26: =Income_Statement_Qtr!AT26 -> -188 | Z26: =Income_Statement_Qtr!AY26 -> -114 | AA26: =Income_Statement_Qtr!BD26 -> -182 | AB26: =Income_Statement_Qtr!BI26 -> -130 | AC26: -130 | AD26: -130 | AE26: -130 | AF26: -130
A27: =Income_Statement_Qtr!A27 -> Amortization of Previously Capitalized Interest | B27: 0 | C27: 0 | D27: 0 | E27: -53 | F27: -48 | G27: -47 | H27: -48 | I27: -53 | J27: -44 | K27: -53 | L27: -54 | M27: -51 | N27: -70 | O27: -69 | P27: -72 | Q27: =Income_Statement_Qtr!F27 -> -90 | R27: =Income_Statement_Qtr!K27 -> -94 | S27: =Income_Statement_Qtr!P27 -> -96 | T27: =Income_Statement_Qtr!U27 -> -92 | U27: =Income_Statement_Qtr!Z27 -> -89 | V27: =Income_Statement_Qtr!AE27 -> -95 | W27: =Income_Statement_Qtr!AJ27 -> -107 | X27: =Income_Statement_Qtr!AO27 -> -95 | Y27: =Income_Statement_Qtr!AT27 -> -95 | Z27: =Income_Statement_Qtr!AY27 -> -93 | AA27: =Income_Statement_Qtr!BD27 -> -92 | AB27: =Income_Statement_Qtr!BI27 -> -100 | AC27: -100 | AD27: -100 | AE27: -100 | AF27: -100
A28: =Income_Statement_Qtr!A28 -> Customer Financing Impairment | B28: 0 | C28: 0 | D28: 0 | E28: 0 | F28: 0 | G28: 0 | H28: 0 | I28: 0 | J28: 0 | K28: 0 | L28: 0 | M28: 0 | N28: 0 | O28: 0 | P28: 0 | Q28: =Income_Statement_Qtr!F28 -> 0 | R28: =Income_Statement_Qtr!K28 -> 0 | S28: =Income_Statement_Qtr!P28 -> 0 | T28: =Income_Statement_Qtr!U28 -> 0 | U28: =Income_Statement_Qtr!Z28 -> -250 | V28: =Income_Statement_Qtr!AE28 -> 0 | W28: =Income_Statement_Qtr!AJ28 -> 0 | X28: =Income_Statement_Qtr!AO28 -> 0 | Y28: =Income_Statement_Qtr!AT28 -> 0 | Z28: =Income_Statement_Qtr!AY28 -> 0 | AA28: =Income_Statement_Qtr!BD28 -> 0 | AB28: =Income_Statement_Qtr!BI28 -> 0 | AC28: 0 | AD28: 0 | AE28: 0 | AF28: 0
A29: =Income_Statement_Qtr!A29 -> Research and Development Expense, net | B29: 0 | C29: 0 | D29: 0 | E29: 0 | F29: 0 | G29: 0 | H29: 0 | I29: 0 | J29: 0 | K29: 0 | L29: 0 | M29: 0 | N29: 0 | O29: 0 | P29: 0 | Q29: =Income_Statement_Qtr!F29 -> 0 | R29: =Income_Statement_Qtr!K29 -> 0 | S29: =Income_Statement_Qtr!P29 -> 0 | T29: =Income_Statement_Qtr!U29 -> -132 | U29: =Income_Statement_Qtr!Z29 -> -384 | V29: =Income_Statement_Qtr!AE29 -> -240 | W29: =Income_Statement_Qtr!AJ29 -> -184 | X29: =Income_Statement_Qtr!AO29 -> -278 | Y29: =Income_Statement_Qtr!AT29 -> -315 | Z29: =Income_Statement_Qtr!AY29 -> -377 | AA29: =Income_Statement_Qtr!BD29 -> -411 | AB29: =Income_Statement_Qtr!BI29 -> -375 | AC29: -375 | AD29: -375 | AE29: -375 | AF29: -375
A30: =Income_Statement_Qtr!A30 -> Eliminations and Other Unallocated Items | B30: =-442-362 -> -804 | C30: =-368-163 -> -531 | D30: =424-193 -> 231 | E30: =-128-36-320 -> -484 | F30: =15-112-340 -> -437 | G30: =-324 -> -324 | H30: =-322+320+15 -> 13 | I30: -74 | J30: -66 | K30: -211 | L30: -428 | M30: -276 | N30: -266 | O30: =-859+406 -> -453 | P30: -593 | Q30: =Income_Statement_Qtr!F30 -> -511 | R30: =Income_Statement_Qtr!K30 -> -527 | S30: =Income_Statement_Qtr!P30 -> -686 | T30: =Income_Statement_Qtr!U30 -> -1123 | U30: =Income_Statement_Qtr!Z30 -> -1104 | V30: =Income_Statement_Qtr!AE30 -> -1807 | W30: =Income_Statement_Qtr!AJ30 -> -676 | X30: =Income_Statement_Qtr!AO30 -> -1162 | Y30: =Income_Statement_Qtr!AT30 -> -1223 | Z30: =Income_Statement_Qtr!AY30 -> -1634 | AA30: =Income_Statement_Qtr!BD30 -> -2297 | AB30: =Income_Statement_Qtr!BI30 -> -2064.2292 | AC30: -1650.34 | AD30: -1650.34 | AE30: -1650.34 | AF30: -1650.34
A31: =Income_Statement_Qtr!A31 -> Total Unallocated Items | B31: =SUM(B24:B30) -> -1120 | C31: =SUM(C24:C30) -> -909 | D31: =SUM(D24:D30) -> -216 | E31: =SUM(E24:E30) -> -787 | F31: =SUM(F24:F30) -> -1319 | G31: =SUM(G24:G30) -> -2407 | H31: =SUM(H24:H30) -> -1398 | I31: =SUM(I24:I30) -> -1097 | ... AF31: =SUM(AF24:AF30) -> -1093.3098
A32: =Income_Statement_Qtr!A32 -> Settlement With U.S. Department of Justice, net of Accruals | B32: 0 | C32: 0 | D32: 0 | E32: 0 | F32: 0 | G32: 0 | H32: =-571+571 -> 0 | I32: 0 | J32: 0 | K32: 0 | L32: 0 | M32: 0 | N32: 0 | O32: 0 | P32: 0 | Q32: =Income_Statement_Qtr!F32 -> 0 | R32: =Income_Statement_Qtr!K32 -> 0 | S32: =Income_Statement_Qtr!P32 -> 0 | T32: =Income_Statement_Qtr!U32 -> 0 | U32: =Income_Statement_Qtr!Z32 -> 0 | V32: =Income_Statement_Qtr!AE32 -> 0 | W32: =Income_Statement_Qtr!AJ32 -> 0 | X32: =Income_Statement_Qtr!AO32 -> 0 | Y32: =Income_Statement_Qtr!AT32 -> 0 | Z32: =Income_Statement_Qtr!AY32 -> 0 | AA32: =Income_Statement_Qtr!BD32 -> 0 | AB32: =Income_Statement_Qtr!BI32 -> 0 | AC32: 0 | AD32: 0 | AE32: 0 | AF32: 0
A34: =Income_Statement_Qtr!A34 -> Operating Profit | B34: =B20+B31+B32 -> 3058 | C34: =C20+C31+C32 -> 3896 | D34: =D20+D31+D32 -> 3450 | E34: =E20+E31+E32 -> 1311 | F34: =F20+F31+F32 -> 2562 | G34: =G20+G31+G32 -> 2812 | H34: =H20+H31+H32 -> 3920 | I34: =I20+I31+I32 -> 5830 | ... AF34: =AF20+AF31+AF32 -> 11816.886
A35: =Income_Statement_Qtr!A35 -> Operating Margin | B35: =B34/B10 -> 0.059585745 | C35: =C34/C10 -> 0.066943881 | D35: =D34/D10 -> 0.0638168 | E35: =E34/E10 -> 0.026086437 | F35: =F34/F10 -> 0.048840002 | G35: =G34/G10 -> 0.05244214 | H35: =H34/H10 -> 0.06370876 | I35: =I34/I10 -> 0.087818398 | ... P35: =P34/P10 -> 0.08233622 | Q35: =+Income_Statement_Qtr!F35 -> 0.077439291 | R35: =+Income_Statement_Qtr!K35 -> 0.061689101 | S35: =+Income_Statement_Qtr!P35 -> 0.1100367 | T35: =+Income_Statement_Qtr!U35 -> 0.11853412 | U35: =+Income_Statement_Qtr!Z35 -> -0.025797098 | V35: =+Income_Statement_Qtr!AE35 -> -0.21952268 | W35: =+Income_Statement_Qtr!AJ35 -> -0.046591529 | X35: =+Income_Statement_Qtr!AO35 -> -0.053251862 | Y35: =+Income_Statement_Qtr!AT35 -> -0.009936499 | Z35: =+Income_Statement_Qtr!AY35 -> -0.16096637 | AA35: =+Income_Statement_Qtr!BD35 -> 0.047852185 | AB35: =+Income_Statement_Qtr!BI35 -> 0.021180306 | AC35: =AC34/AC10 -> 0.080105509 | AD35: =AD34/AD10 -> 0.096054345 | AE35: =AE34/AE10 -> 0.097051619 | AF35: =AF34/AF10 -> 0.098191593
A37: =Income_Statement_Qtr!A37 -> Interest and Debt Expense | B37: -445 | C37: -650 | D37: -320 | E37: -358 | F37: -335 | G37: -294 | H37: -240 | I37: -196 | J37: -202 | K37: -339 | L37: -516 | M37: -498 | N37: -442 | O37: -386 | P37: -333 | Q37: =+Income_Statement_Qtr!F37 -> -275 | R37: =+Income_Statement_Qtr!K37 -> -306 | S37: =+Income_Statement_Qtr!P37 -> -360 | T37: =+Income_Statement_Qtr!U37 -> -475 | U37: =+Income_Statement_Qtr!Z37 -> -722 | V37: =+Income_Statement_Qtr!AE37 -> -2156 | W37: =+Income_Statement_Qtr!AJ37 -> -2682 | X37: =+Income_Statement_Qtr!AO37 -> -2533 | Y37: =+Income_Statement_Qtr!AT37 -> -2459 | Z37: =+Income_Statement_Qtr!AY37 -> -2725 | AA37: =+Income_Statement_Qtr!BD37 -> -2771 | AB37: =+Income_Statement_Qtr!BI37 -> -2709.1483 | AC37: =-Debt_Annual!AC202 -> -2479.2937 | AD37: =-Debt_Annual!AD202 -> -2263.4693 | AE37: =-Debt_Annual!AE202 -> -2132.2887 | AF37: =-Debt_Annual!AF202 -> -2132.0712
A38: =Income_Statement_Qtr!A38 -> Non-Operating FAS Pension Cost | B38: 0 | C38: 0 | D38: 0 | E38: 0 | F38: 0 | G38: 0 | H38: 0 | I38: 0 | J38: 0 | K38: 0 | L38: 0 | M38: 0 | N38: 0 | O38: 0 | P38: 0 | Q38: =Income_Statement_Qtr!F38 -> 0 | R38: =Income_Statement_Qtr!K38 -> 0 | S38: =Income_Statement_Qtr!P38 -> 0 | T38: =Income_Statement_Qtr!U38 -> 0 | U38: =Income_Statement_Qtr!$Z$38 -> 0 | V38: =Income_Statement_Qtr!AE$38 -> 0 | W38: =Income_Statement_Qtr!AJ$38 -> 0 | X38: =Income_Statement_Qtr!AO$38 -> 0 | Y38: =Income_Statement_Qtr!AT$38 -> 0 | Z38: =Income_Statement_Qtr!AY$38 -> 0 | AA38: =Income_Statement_Qtr!BD$38 -> 0 | AB38: =Income_Statement_Qtr!BI$38 -> 0 | AC38: =AB38 -> 0 | AD38: =AC38 -> 0 | AE38: =AD38 -> 0 | AF38: =AE38 -> 0
A39: =Income_Statement_Qtr!A39 -> Other Non-Operating Expense/ Income, Net | B39: 386 | C39: 318 | D39: 50 | E39: 460 | F39: =288-219 -> 69 | G39: =301-64 -> 237 | H39: 420 | I39: 484 | J39: 247 | K39: -26 | L39: 52 | M39: 47 | N39: 62 | O39: 56 | P39: -3 | Q39: =+Income_Statement_Qtr!F39 -> -13 | R39: =+Income_Statement_Qtr!K39 -> 40 | S39: =+Income_Statement_Qtr!P39 -> 123 | T39: =+Income_Statement_Qtr!U39 -> 92 | U39: =+Income_Statement_Qtr!Z39 -> 438 | V39: =+Income_Statement_Qtr!AE39 -> 447 | W39: =+Income_Statement_Qtr!AJ39 -> 551 | X39: =+Income_Statement_Qtr!AO39 -> 1058 | Y39: =+Income_Statement_Qtr!AT39 -> 1227 | Z39: =+Income_Statement_Qtr!AY39 -> 1222 | AA39: =+Income_Statement_Qtr!BD39 -> 1125 | AB39: =+Income_Statement_Qtr!BI39 -> 1125 | AC39: =AB39 -> 1125 | AD39: =AC39 -> 1125 | AE39: =AD39 -> 1125 | AF39: =AE39 -> 1125
A40: =Income_Statement_Qtr!A40 -> Pre-Tax Income | B40: =SUM(B34,B37:B39) -> 2999 | C40: =SUM(C34,C37:C39) -> 3564 | D40: =SUM(D34,D37:D39) -> 3180 | E40: =SUM(E34,E37:E39) -> 1413 | F40: =SUM(F34,F37:F39) -> 2296 | G40: =SUM(G34,G37:G39) -> 2755 | H40: =SUM(H34,H37:H39) -> 4100 | I40: =SUM(I34,I37:I39) -> 6118 | ... AF40: =SUM(AF34,AF37:AF39) -> 10809.815
A41: =Income_Statement_Qtr!A41 -> YoY | B41: =B40/3324-1 -> -0.097773767 | C41: =C40/B40-1 -> 0.18839613 | D41: =D40/C40-1 -> -0.10774411 | E41: =E40/D40-1 -> -0.55566038 | F41: =F40/E40-1 -> 0.62491154 | G41: =G40/F40-1 -> 0.19991289 | H41: =H40/G40-1 -> 0.48820327 | I41: =I40/H40-1 -> 0.49219512 | J41: =J40/I40-1 -> 0.12228481 | ... P41: =P40/O40-1 -> 0.075173245 | Q41: =+Income_Statement_Qtr!F41 -> 0.0025220681 | R41: =+Income_Statement_Qtr!K41 -> -0.22180294 | S41: =+Income_Statement_Qtr!P41 -> 0.81519397 | T41: =+Income_Statement_Qtr!U41 -> 0.14811517 | U41: =+Income_Statement_Qtr!Z41 -> -1.1946743 | V41: =+Income_Statement_Qtr!AE41 -> 5.4081452 | W41: =+Income_Statement_Qtr!AJ41 -> -0.65232108 | X41: =+Income_Statement_Qtr!AO41 -> -0.0021855752 | Y41: =+Income_Statement_Qtr!AT41 -> -0.60075667 | Z41: =+Income_Statement_Qtr!AY41 -> 5.0897756 | AA41: =+Income_Statement_Qtr!BD41 -> -1.2158067 | AB41: =+Income_Statement_Qtr!BI41 -> -0.79967913 | AC41: =AC40/AB40-1 -> 12.881748 | AD41: =AD40/AC40-1 -> 0.32740573 | AE41: =AE40/AD40-1 -> 0.064328541 | AF41: =AF40/AE40-1 -> 0.044210125
A43: =Income_Statement_Qtr!A43 -> Income Tax Benefit/ (Expense) | B43: -871 | C43: -738 | D43: -861 | E43: =185-(913-(1.01*808.9)) -> 88.989 | F43: =-140-((280+275)-0.44*813)+(219-(0.17*813))-367 -> -623.49 | G43: =-257-570+(64-(0.05*802.9)) -> -803.145 | H43: =-988-((320+15)-(0.24*787.6))+16 -> -1117.976 | I43: -2060 | J43: =-1341-(((2.56*729)/(1-35%))-(2.56*729)) -> -2345.8985 | K43: =-396-((2693+1352)-(3.58*713.4)) -> -1887.028 | L43: =-1196-0.5*744.3+0.2*744.3 -> -1419.29 | M43: =-1382-0.53*750.6 -> -1779.818 | N43: -2007 | O43: =-1646-(406-0.34*767.6) -> -1791.016 | P43: -1691 | Q43: =+Income_Statement_Qtr!F43 -> -1979 | R43: =+Income_Statement_Qtr!K43 -> -673 | S43: =+Income_Statement_Qtr!P43 -> -1649 | T43: =+Income_Statement_Qtr!U43 -> -1144 | U43: =+Income_Statement_Qtr!Z43 -> 1623 | V43: =+Income_Statement_Qtr!AE43 -> 2535 | W43: =+Income_Statement_Qtr!AJ43 -> 743 | X43: =+Income_Statement_Qtr!AO43 -> -31 | Y43: =+Income_Statement_Qtr!AT43 -> -237 | Z43: =+Income_Statement_Qtr!AY43 -> 381 | AA43: =+Income_Statement_Qtr!BD43 -> -397 | AB43: =+Income_Statement_Qtr!BI43 -> -52.784551 | AC43: =IF(AC40<0,0,-AC40*AC44) -> -1450.8288 | AD43: =IF(AD40<0,0,-AD40*AD44) -> -1989.0604 | AE43: =IF(AE40<0,0,-AE40*AE44) -> -2122.1898 | AF43: =IF(AF40<0,0,-AF40*AF44) -> -2216.0121
A44: =Income_Statement_Qtr!A44 -> Tax Rate | B44: =IF(B43>0,"NM",-B43/B40) -> 0.29043014 | C44: =IF(C43>0,"NM",-C43/C40) -> 0.20707071 | D44: =IF(D43>0,"NM",-D43/D40) -> 0.27075472 | E44: =IF(E43>0,"NM",-E43/E40) -> NM | F44: =IF(F43>0,"NM",-F43/F40) -> 0.27155488 | G44: =IF(G43>0,"NM",-G43/G40) -> 0.29152269 | H44: =IF(H43>0,"NM",-H43/H40) -> 0.27267707 | I44: =IF(I43>0,"NM",-I43/I40) -> 0.33671134 | ... P44: =IF(P43>0,"NM",-P43/P40) -> 0.23693429 | Q44: =+Income_Statement_Qtr!F44 -> 0.2765898 | R44: =+Income_Statement_Qtr!K44 -> 0.12086925 | S44: =+Income_Statement_Qtr!P44 -> 0.16315425 | T44: =+Income_Statement_Qtr!U44 -> 0.098586694 | U44: =+Income_Statement_Qtr!Z44 -> NM | V44: =+Income_Statement_Qtr!AE44 -> NM | W44: =+Income_Statement_Qtr!AJ44 -> NM | X44: =+Income_Statement_Qtr!AO44 -> -0.0061728395 | Y44: =+Income_Statement_Qtr!AT44 -> -0.11820449 | Z44: =+Income_Statement_Qtr!AY44 -> NM | AA44: =+Income_Statement_Qtr!BD44 -> -0.05915 | AB44: =+Income_Statement_Qtr!BI44 -> 0.1 | AC44: 0.198 | AD44: 0.2045 | AE44: 0.205 | AF44: 0.205
A46: =Income_Statement_Qtr!A46 -> Net earnings | B46: =B43+B40 -> 2128 | C46: =C43+C40 -> 2826 | D46: =D43+D40 -> 2319 | E46: =E43+E40 -> 1501.989 | F46: =F43+F40 -> 1672.51 | G46: =G43+G40 -> 1951.855 | H46: =H43+H40 -> 2982.024 | I46: =I43+I40 -> 4058 | ... AF46: =AF43+AF40 -> 8593.8031
A48: =Income_Statement_Qtr!A48 -> Net Loss Attributable to Noncontrolling Interest | B48: 0 | C48: 0 | D48: 0 | E48: 0 | F48: 0 | G48: 0 | H48: 0 | I48: 0 | J48: 0 | K48: 0 | L48: 0 | M48: 0 | N48: 0 | O48: 0 | P48: 0 | Q48: =+Income_Statement_Qtr!F48 -> 0 | R48: =+Income_Statement_Qtr!K48 -> 0 | S48: =+Income_Statement_Qtr!P48 -> 0 | T48: =+Income_Statement_Qtr!U48 -> 0 | U48: =+Income_Statement_Qtr!Z48 -> 0 | V48: =+Income_Statement_Qtr!AE48 -> 68 | W48: =+Income_Statement_Qtr!AJ48 -> 88 | X48: =+Income_Statement_Qtr!AO48 -> 118 | Y48: =+Income_Statement_Qtr!AT48 -> 19.8 | Z48: =+Income_Statement_Qtr!AY48 -> 12 | AA48: =+Income_Statement_Qtr!BD48 -> -3 | AB48: =+Income_Statement_Qtr!BI48 -> 0 | AC48: 20 | AD48: 20 | AE48: 20 | AF48: 20
A49: =Income_Statement_Qtr!A49 -> Preferred Stock Dividends | Z49: =+Income_Statement_Qtr!AY49 -> -58 | AA49: =+Income_Statement_Qtr!BD49 -> -345 | AB49: =+Income_Statement_Qtr!BI49 -> -346 | AC49: =AB49 -> -346 | AD49: 0 | AE49: 0 | AF49: 0
A50: =Income_Statement_Qtr!A50 -> Net Earnings Attributable to Boeing Shareholders | B50: =B46+B48 -> 2128 | C50: =C46+C48 -> 2826 | D50: =D46+D48 -> 2319 | E50: =E46+E48 -> 1501.989 | F50: =F46+F48 -> 1672.51 | G50: =G46+G48 -> 1951.855 | H50: =H46+H48 -> 2982.024 | I50: =I46+I48 -> 4058 | ... Y50: =Y46+Y48 -> -2222.2 | Z50: =Z46+Z48+Z49 -> -11875 | AA50: =AA46+AA48+AA49 -> 1890 | AB50: =AB46+AB48+AB49 -> 129.06095 | AC50: =AC46+AC48+AC49 -> 5550.5894 | AD50: =AD46+AD48+AD49 -> 7757.3964 | AE50: =AE46+AE48+AE49 -> 8249.9557 | AF50: =AF46+AF48+AF49 -> 8613.8031
A51: =Income_Statement_Qtr!A51 -> YoY | B51: =B50/2309-1 -> -0.078388913 | C51: =C50/B50-1 -> 0.32800752 | D51: =D50/C50-1 -> -0.17940552 | E51: =E50/D50-1 -> -0.35231177 | F51: =F50/E50-1 -> 0.11353013 | G51: =G50/F50-1 -> 0.16702142 | H51: =H50/G50-1 -> 0.52778972 | I51: =I50/H50-1 -> 0.3608207 | J51: =J50/I50-1 -> 0.11390833 | ... P51: =P50/O50-1 -> 0.12358531 | Q51: =+Income_Statement_Qtr!F51 -> -0.049577672 | R51: =+Income_Statement_Qtr!K51 -> -0.054289026 | S51: =+Income_Statement_Qtr!P51 -> 0.7278856 | T51: =+Income_Statement_Qtr!U51 -> 0.23669898 | U51: =+Income_Statement_Qtr!Z51 -> -1.0608031 | V51: =+Income_Statement_Qtr!AE51 -> 17.668239 | W51: =+Income_Statement_Qtr!AJ51 -> -0.64608776 | X51: =+Income_Statement_Qtr!AO51 -> 0.17444074 | Y51: =+Income_Statement_Qtr!AT51 -> -0.54970618 | Z51: =+Income_Statement_Qtr!AY51 -> 4.3438034 | AA51: =+Income_Statement_Qtr!BD51 -> -1.1591579 | AB51: =+Income_Statement_Qtr!BI51 -> -0.93171378 | AC51: =AC50/AB50-1 -> 42.007503 | AD51: =AD50/AC50-1 -> 0.39758067 | AE51: =AE50/AD50-1 -> 0.063495447 | AF51: =AF50/AE50-1 -> 0.044102949
A53: =Income_Statement_Qtr!A53 -> Non-Recurring Charges | B53: 0 | C53: 0 | D53: 0 | E53: =-1.01*808.9 -> -816.989 | F53: =-0.44*813+0.17*813+367 -> 147.49 | G53: =570+(0.05*802.9) -> 610.145 | H53: =-0.24*787.6-571-16 -> -776.024 | I53: 0 | J53: =-(2.56*729) -> -1866.24 | K53: =-(3.58*713.4) -> -2553.972 | L53: =0.5*744.3-0.2*744.3 -> 223.29 | M53: =0.53*750.6 -> 397.818 | N53: 0 | O53: =-0.34*767.6 -> -260.984 | P53: 0 | Q53: =+Income_Statement_Qtr!F53 -> 0 | R53: =+Income_Statement_Qtr!K53 -> 0 | S53: =+Income_Statement_Qtr!P53 -> 0 | T53: =+Income_Statement_Qtr!U53 -> 0 | U53: =+Income_Statement_Qtr!Z53 -> 0 | V53: =+Income_Statement_Qtr!AE53 -> 0 | W53: =+Income_Statement_Qtr!AJ53 -> 0 | X53: =+Income_Statement_Qtr!AO53 -> 0 | Y53: =+Income_Statement_Qtr!AT53 -> 0 | Z53: =+Income_Statement_Qtr!AY53 -> 0 | AA53: =+Income_Statement_Qtr!BD53 -> 0 | AB53: =+Income_Statement_Qtr!BI53 -> 0 | AC53: 0 | AD53: 0 | AE53: 0 | AF53: 0
A54: =Income_Statement_Qtr!A54 -> Discontinued Operations | B54: 0 | C54: 0 | D54: 0 | E54: 33 | F54: =42+10 -> 52 | G54: -7 | H54: 9 | I54: 16 | J54: 18 | K54: -23 | L54: -4 | M54: 7 | N54: -3 | O54: -1 | P54: 0 | Q54: =+Income_Statement_Qtr!F54 -> 0 | R54: =+Income_Statement_Qtr!K54 -> 0 | S54: =+Income_Statement_Qtr!P54 -> 0 | T54: =+Income_Statement_Qtr!U54 -> 0 | U54: =+Income_Statement_Qtr!Z54 -> 0 | V54: =+Income_Statement_Qtr!AE54 -> 0 | W54: =+Income_Statement_Qtr!AJ54 -> 0 | X54: =+Income_Statement_Qtr!AO54 -> 0 | Y54: =+Income_Statement_Qtr!AT54 -> 0 | Z54: =+Income_Statement_Qtr!AY54 -> 0 | AA54: =+Income_Statement_Qtr!BD54 -> 0 | AB54: =+Income_Statement_Qtr!BI54 -> 0 | AC54: 0 | AD54: 0 | AE54: 0 | AF54: 0
A55: =Income_Statement_Qtr!A55 -> Cumulative Effect of Accounting Change | B55: 0 | C55: 1 | D55: -1827 | E55: 0 | F55: 0 | G55: 17 | H55: 0 | I55: 0 | J55: 0 | K55: 0 | L55: 0 | M55: 0 | N55: 0 | O55: 0 | P55: 0 | Q55: =+Income_Statement_Qtr!F55 -> 0 | R55: =+Income_Statement_Qtr!K55 -> 0 | S55: =+Income_Statement_Qtr!P55 -> 0 | T55: =+Income_Statement_Qtr!U55 -> 0 | U55: =+Income_Statement_Qtr!Z55 -> 0 | V55: =+Income_Statement_Qtr!AE55 -> 0 | W55: =+Income_Statement_Qtr!AJ55 -> 0 | X55: =+Income_Statement_Qtr!AO55 -> 0 | Y55: =+Income_Statement_Qtr!AT55 -> 0 | Z55: =+Income_Statement_Qtr!AY55 -> 0 | AA55: =+Income_Statement_Qtr!BD55 -> 0 | AB55: =+Income_Statement_Qtr!BI55 -> 0 | AC55: 0 | AD55: 0 | AE55: 0 | AF55: 0
A56: =Income_Statement_Qtr!A56 -> GAAP Net Earnings | B56: =B46+B53+B54+B55 -> 2128 | C56: =C46+C53+C54+C55 -> 2827 | D56: =D46+D53+D54+D55 -> 492 | E56: =E46+E53+E54+E55 -> 718 | F56: =F46+F53+F54+F55 -> 1872 | G56: =G46+G53+G54+G55 -> 2572 | H56: =H46+H53+H54+H55 -> 2215 | I56: =I46+I53+I54+I55 -> 4074 | ... AF56: =AF46+AF53+AF54+AF55 -> 8593.8031
A57: =Income_Statement_Qtr!A57 -> YoY | B57: =B56/2309-1 -> -0.078388913 | C57: =C56/B56-1 -> 0.32847744 | D57: =D56/C56-1 -> -0.82596392 | E57: =E56/D56-1 -> 0.45934959 | F57: =F56/E56-1 -> 1.6072423 | G57: =G56/F56-1 -> 0.37393162 | H57: =H56/G56-1 -> -0.13880249 | I57: =I56/H56-1 -> 0.83927765 | J57: =J56/I56-1 -> -0.34413353 | ... P57: =P56/O56-1 -> 0.18778626 | Q57: =+Income_Statement_Qtr!F57 -> -0.049577672 | R57: =+Income_Statement_Qtr!K57 -> -0.054289026 | S57: =+Income_Statement_Qtr!P57 -> 0.7278856 | T57: =+Income_Statement_Qtr!U57 -> 0.23669898 | U57: =+Income_Statement_Qtr!Z57 -> -1.0608031 | V57: =+Income_Statement_Qtr!AE57 -> 17.775157 | W57: =+Income_Statement_Qtr!AJ57 -> -0.64073361 | X57: =+Income_Statement_Qtr!AO57 -> 0.17785548 | Y57: =+Income_Statement_Qtr!AT57 -> -0.55630319 | Z57: =+Income_Statement_Qtr!AY57 -> 4.2760928 | AA57: =+Income_Statement_Qtr!BD57 -> -1.189196 | AB57: =+Income_Statement_Qtr!BI57 -> -0.78772969 | AC57: =AC56/AB56-1 -> 11.37018 | AD57: =AD56/AC56-1 -> 0.31664745 | AE57: =AE56/AD56-1 -> 0.063659573 | AF57: =AF56/AE56-1 -> 0.044210125
A59: Net Loss Attributable to Noncontrolling Interest | B59: =B48 -> 0 | C59: =C48 -> 0 | D59: =D48 -> 0 | E59: =E48 -> 0 | F59: =F48 -> 0 | G59: =G48 -> 0 | H59: =H48 -> 0 | I59: =I48 -> 0 | ... AF59: =AF48 -> 20
A60: GAAP Net Earnings Attributable to Boeing Shareholder | B60: =B56+B59 -> 2128 | C60: =C56+C59 -> 2827 | D60: =D56+D59 -> 492 | E60: =E56+E59 -> 718 | F60: =F56+F59 -> 1872 | G60: =G56+G59 -> 2572 | H60: =H56+H59 -> 2215 | I60: =I56+I59 -> 4074 | ... AF60: =AF56+AF59 -> 8613.8031
A62: =Income_Statement_Qtr!A62 -> Adjustments for Core Earnings | B62: =B130 -> 0 | C62: =C130 -> 0 | D62: =D130 -> 0 | E62: =E130 -> 0 | F62: =F130 -> 0 | G62: =G130 -> -32.116 | H62: =H130 -> 0 | I62: =I130 -> 0 | ... P62: =P130 -> 898.774 | Q62: =+Income_Statement_Qtr!F62 -> 193.75 | R62: =+Income_Statement_Qtr!K62 -> -241.44 | S62: =+Income_Statement_Qtr!P62 -> -931 | T62: =+Income_Statement_Qtr!U62 -> -1082 | U62: =+Income_Statement_Qtr!Z62 -> -1329 | V62: =+Income_Statement_Qtr!AE62 -> -1348 | W62: =+Income_Statement_Qtr!AJ62 -> -1345 | X62: =+Income_Statement_Qtr!AO62 -> -1645 | Y62: =+Income_Statement_Qtr!AT62 -> -1299 | Z62: =+Income_Statement_Qtr!AY62 -> -1306 | AA62: =+Income_Statement_Qtr!BD62 -> -979.8 | AB62: =+Income_Statement_Qtr!BI62 -> -1066.5 | AC62: =AC130 -> -1066.5 | AD62: =AD130 -> -1066.5 | AE62: =AE130 -> -1066.5 | AF62: =AF130 -> -1066.5
A63: =Income_Statement_Qtr!A63 -> Core Net Earnings from Continuing Operations | B63: =B50+B62 -> 2128 | C63: =C50+C62 -> 2826 | D63: =D50+D62 -> 2319 | E63: =E50+E62 -> 1501.989 | F63: =F50+F62 -> 1672.51 | G63: =G50+G62 -> 1919.739 | H63: =H50+H62 -> 2982.024 | I63: =I50+I62 -> 4058 | ... AF63: =AF50+AF62 -> 7547.3031
A64: =Income_Statement_Qtr!A64 -> YoY | B64: =B63/2309-1 -> -0.078388913 | C64: =C63/B63-1 -> 0.32800752 | D64: =D63/C63-1 -> -0.17940552 | E64: =E63/D63-1 -> -0.35231177 | F64: =F63/E63-1 -> 0.11353013 | G64: =G63/F63-1 -> 0.14781915 | H64: =H63/G63-1 -> 0.55334866 | I64: =I63/H63-1 -> 0.3608207 | J64: =J63/I63-1 -> 0.11390833 | ... P64: =P63/O63-1 -> 0.16673998 | Q64: =+Income_Statement_Qtr!F64 -> -0.15367356 | R64: =+Income_Statement_Qtr!K64 -> -0.13337492 | S64: =+Income_Statement_Qtr!P64 -> 0.61747136 | T64: =+Income_Statement_Qtr!U64 -> 0.24591471 | U64: =+Income_Statement_Qtr!Z64 -> -1.2095329 | V64: =+Income_Statement_Qtr!AE64 -> 5.7282443 | W64: =+Income_Statement_Qtr!AJ64 -> -0.58044021 | X64: =+Income_Statement_Qtr!AO64 -> 0.18622679 | Y64: =+Income_Statement_Qtr!AT64 -> -0.46486322 | Z64: =+Income_Statement_Qtr!AY64 -> 2.7433261 | AA64: =+Income_Statement_Qtr!BD64 -> -1.0690539 | AB64: =+Income_Statement_Qtr!BI64 -> -2.0299264 | AC64: =AC63/AB63-1 -> -5.7833396 | AD64: =AD63/AC63-1 -> 0.49214163 | AE64: =AE63/AD63-1 -> 0.073616347 | AF64: =AF63/AE63-1 -> 0.050650744
A66: =Income_Statement_Qtr!A66 -> Less: Earnings Available to Participating Securities | B66: 0 | C66: 0 | D66: 0 | E66: 0 | F66: 0 | G66: 0 | H66: 0 | I66: 0 | J66: 0 | K66: 0 | L66: 0 | M66: -9 | N66: -8 | O66: -7 | P66: -6 | Q66: =+Income_Statement_Qtr!F66 -> -4 | R66: =+Income_Statement_Qtr!K66 -> -3 | S66: =+Income_Statement_Qtr!P66 -> -6 | T66: =+Income_Statement_Qtr!U66 -> -7 | U66: =+Income_Statement_Qtr!Z66 -> 0 | V66: =+Income_Statement_Qtr!AE66 -> 0 | W66: =+Income_Statement_Qtr!AJ66 -> 0 | X66: =+Income_Statement_Qtr!AO66 -> 0 | Y66: =+Income_Statement_Qtr!AT66 -> 0 | Z66: =+Income_Statement_Qtr!AY66 -> 0 | AA66: =+Income_Statement_Qtr!BD66 -> 0 | AB66: =+Income_Statement_Qtr!BI66 -> 0 | AC66: 0 | AD66: 0 | AE66: 0 | AF66: 0
A67: =Income_Statement_Qtr!A67 -> Expense related to diluted shares | B67: 0 | C67: 0 | D67: 0 | E67: 0 | F67: 0 | G67: 0 | H67: 27 | I67: 0 | J67: 0 | K67: 0 | L67: 0 | M67: 0 | N67: 0 | O67: 0 | P67: 0 | Q67: =+Income_Statement_Qtr!F67 -> 0 | R67: =+Income_Statement_Qtr!K67 -> 0 | S67: =+Income_Statement_Qtr!P67 -> 0 | T67: =+Income_Statement_Qtr!U67 -> 0 | U67: =+Income_Statement_Qtr!Z67 -> 0 | V67: =+Income_Statement_Qtr!AE67 -> 0 | W67: =+Income_Statement_Qtr!AJ67 -> 0 | X67: =+Income_Statement_Qtr!AO67 -> 0 | Y67: =+Income_Statement_Qtr!AT67 -> 0 | Z67: =+Income_Statement_Qtr!AY67 -> 0 | AA67: =+Income_Statement_Qtr!BD67 -> 0 | AB67: =+Income_Statement_Qtr!BI67 -> 0 | AC67: 0 | AD67: 0 | AE67: 0 | AF67: 0
A69: =Income_Statement_Qtr!A69 -> Core EPS from Continuing Operations - Diluted | B69: =(B63+B66+B67)/B79 -> 2.4423276 | C69: =(C63+C66+C67)/C79 -> 3.4076932 | D69: =(D63+D66+D67)/D79 -> 2.8686294 | E69: =(E63+E66+E67)/E79 -> 1.856829 | F69: =(F63+F66+F67)/F79 -> 2.0572079 | G69: =(G63+G66+G67)/G79 -> 2.3910064 | H69: =(H63+H66+H67)/H79 -> 3.8204977 | I69: =(I63+I66+I67)/I79 -> 5.2530744 | ... AF69: =(AF63+AF66+AF67)/AF79 -> 9.0137394
A70: =Income_Statement_Qtr!A70 -> EPS from Continuing Operations - Diluted | B70: =(B50+B66+B67)/B79 -> 2.4423276 | C70: =(C50+C66+C67)/C79 -> 3.4076932 | D70: =(D50+D66+D67)/D79 -> 2.8686294 | E70: =(E50+E66+E67)/E79 -> 1.856829 | F70: =(F50+F66+F67)/F79 -> 2.0572079 | G70: =(G50+G66+G67)/G79 -> 2.4310064 | H70: =(H50+H66+H67)/H79 -> 3.8204977 | I70: =(I50+I66+I67)/I79 -> 5.2530744 | ... P70: =(P50+P66+P67)/P79 -> 7.3842813 | Q70: =IF((Q50+Q66+Q67)/Q79=Income_Statement_Qtr!F70,(Q50+Q66+Q67)/Q79,"error") -> 7.4417266 | R70: =IF((R50+R66+R67)/R79=Income_Statement_Qtr!K70,(R50+R66+R67)/R79,"error") -> 7.6104543 | S70: =IF((S50+S66+S67)/S79=Income_Statement_Qtr!P70,(S50+S66+S67)/S79,"error") -> 13.855738 | T70: =IF((T50+T66+T67)/T79=Income_Statement_Qtr!U70,(T50+T66+T67)/T79,"error") -> 17.853117 | U70: =IF((U50+U66+U67)/U79=Income_Statement_Qtr!Z70,(U50+U66+U67)/U79,"error") -> -1.1248674 | V70: =IF((V50+V66+V67)/V79=Income_Statement_Qtr!AE70,(V50+V66+V67)/V79,"error") -> -20.896731 | W70: =IF((W50+W66+W67)/W79=Income_Statement_Qtr!AJ70,(W50+W66+W67)/W79,"error") -> -7.1398836 | X70: =IF((X50+X66+X67)/X79=Income_Statement_Qtr!AO70,(X50+X66+X67)/X79,"error") -> -8.2824943 | Y70: =IF((Y50+Y66+Y67)/Y79=Income_Statement_Qtr!AT70,(Y50+Y66+Y67)/Y79,"error") -> -3.6659381 | Z70: =IF((Z50+Z66+Z67)/Z79=Income_Statement_Qtr!AY70,(Z50+Z66+Z67)/Z79,"error") -> -18.348269 | AA70: =IF((AA50+AA66+AA67)/AA79=Income_Statement_Qtr!BD70,(AA50+AA66+AA67)/AA79,"error") -> 2.4793388 | AB70: =IF((AB50+AB66+AB67)/AB79=Income_Statement_Qtr!BI70,(AB50+AB66+AB67)/AB79,"error") -> 0.16056352 | AC70: =(AC50+AC66+AC67)/AC79 -> 6.6290654 | AD70: =(AD50+AD66+AD67)/AD79 -> 9.2646536 | AE70: =(AE50+AE66+AE67)/AE79 -> 9.8529169 | AF70: =(AF50+AF66+AF67)/AF79 -> 10.28746
A71: =Income_Statement_Qtr!A71 -> GAAP EPS - Diluted | B71: =(B56+B66+B67)/B79 -> 2.4423276 | C71: =(C56+C66+C67)/C79 -> 3.4088991 | D71: =(D56+D66+D67)/D79 -> 0.6086096 | E71: =(E56+E66+E67)/E79 -> 0.88762517 | F71: =(F56+F66+F67)/F79 -> 2.302583 | G71: =(G56+G66+G67)/G79 -> 3.2033877 | H71: =(H56+H66+H67)/H79 -> 2.8466227 | I71: =(I56+I66+I67)/I79 -> 5.2737864 | ... AF71: =(AF56+AF66+AF67)/AF79 -> 10.263574
A73: =Income_Statement_Qtr!A73 -> EPS from Continuing Operations - Basic | B73: =(B50+B66)/B76 -> 2.4758581 | C73: =(C50+C66)/C76 -> 3.4623867 | D73: =(D50+D66)/D76 -> 2.8998374 | E73: =(E50+E66)/E76 -> 1.8648982 | F73: =(F50+F66)/F76 -> 2.0725031 | G73: =(G50+G66)/G76 -> 2.4754027 | H73: =(H50+H66)/H76 -> 3.9211361 | I73: =(I50+I66)/I76 -> 5.3443962 | ... AF73: =(AF50+AF66)/AF76 -> 10.28746
A74: =Income_Statement_Qtr!A74 -> GAAP EPS - Basic | B74: =(B56+B66)/B76 -> 2.4758581 | C74: =(C56+C66)/C76 -> 3.4636119 | D74: =(D56+D66)/D76 -> 0.61523071 | E74: =(E56+E66)/E76 -> 0.89148249 | F74: =(F56+F66)/F76 -> 2.3197026 | G74: =(G56+G66)/G76 -> 3.2618897 | H74: =(H56+H66)/H76 -> 2.9125575 | I74: =(I56+I66)/I76 -> 5.3654682 | ... AF74: =(AF56+AF66)/AF76 -> 10.263574
A76: =Income_Statement_Qtr!A76 -> Weighted Average Common Shares - Basic | B76: 859.5 | C76: 816.2 | D76: 799.7 | E76: 805.4 | F76: 807 | G76: 788.5 | H76: 760.5 | I76: 759.3 | J76: 722.8 | K76: 709.6 | L76: 738.1 | M76: 744.1 | N76: 755.7 | O76: 758.9 | P76: 727.6 | Q76: =+Income_Statement_Qtr!F76 -> 686.9 | R76: =+Income_Statement_Qtr!K76 -> 635.5 | S76: =+Income_Statement_Qtr!P76 -> 602.5 | T76: =+Income_Statement_Qtr!U76 -> 579.2 | U76: =+Income_Statement_Qtr!Z76 -> 565.4 | V76: =+Income_Statement_Qtr!AE76 -> 568.175 | W76: =+Income_Statement_Qtr!AJ76 -> 587.85 | X76: =+Income_Statement_Qtr!AO76 -> 595.075 | Y76: =+Income_Statement_Qtr!AT76 -> 606.1 | Z76: =+Income_Statement_Qtr!AY76 -> 647.2 | AA76: =+Income_Statement_Qtr!BD76 -> 759.03614 | AB76: =+Income_Statement_Qtr!BI76 -> 759.03614 | AC76: =AVERAGE(AC82,AB82) -> 820.5555 | AD76: =AVERAGE(AD82,AC82) -> 837.311 | AE76: =AVERAGE(AE82,AD82) -> 837.311 | AF76: =AVERAGE(AF82,AE82) -> 837.311
A77: =Income_Statement_Qtr!A77 -> YoY | B77: =B76/917.1-1 -> -0.062806673 | C77: =C76/B76-1 -> -0.050378127 | D77: =D76/C76-1 -> -0.020215633 | E77: =E76/D76-1 -> 0.0071276729 | F77: =F76/E76-1 -> 0.0019865905 | G77: =G76/F76-1 -> -0.022924411 | H77: =H76/G76-1 -> -0.035510463 | I77: =I76/H76-1 -> -0.0015779093 | J77: =J76/I76-1 -> -0.048070591 | ... P77: =P76/O76-1 -> -0.041243906 | Q77: =+Income_Statement_Qtr!F77 -> -0.055937328 | R77: =+Income_Statement_Qtr!K77 -> -0.074828942 | S77: =+Income_Statement_Qtr!P77 -> -0.051927616 | T77: =+Income_Statement_Qtr!U77 -> -0.038672199 | U77: =+Income_Statement_Qtr!Z77 -> -0.023825967 | V77: =+Income_Statement_Qtr!AE77 -> 0.0049080297 | W77: =+Income_Statement_Qtr!AJ77 -> 0.034628416 | X77: =+Income_Statement_Qtr!AO77 -> 0.01229055 | Y77: =+Income_Statement_Qtr!AT77 -> 0.018527076 | Z77: =+Income_Statement_Qtr!AY77 -> 0.067810592 | AA77: =+Income_Statement_Qtr!BD77 -> 0.17279998 | AB77: =+Income_Statement_Qtr!BI77 -> 0 | AC77: =AC76/AB76-1 -> 0.08104931 | AD77: =AD76/AC76-1 -> 0.020419703 | AE77: =AE76/AD76-1 -> 0 | AF77: =AF76/AE76-1 -> 0
A79: =Income_Statement_Qtr!A79 -> Weighted Average Common Shares - Diluted | B79: 871.3 | C79: 829.3 | D79: 808.4 | E79: 808.9 | F79: 813 | G79: 802.9 | H79: 787.6 | I79: 772.5 | J79: 729 | K79: 713.4 | L79: 744.3 | M79: 750.6 | N79: 761.5 | O79: 767.6 | P79: 736.7 | Q79: =+Income_Statement_Qtr!F79 -> 695 | R79: =+Income_Statement_Qtr!K79 -> 642.8 | S79: =+Income_Statement_Qtr!P79 -> 610 | T79: =+Income_Statement_Qtr!U79 -> 585.5 | U79: =+Income_Statement_Qtr!Z79 -> 565.4 | V79: =+Income_Statement_Qtr!AE79 -> 568.175 | W79: =+Income_Statement_Qtr!AJ79 -> 588.525 | X79: =+Income_Statement_Qtr!AO79 -> 595.835 | Y79: =+Income_Statement_Qtr!AT79 -> 606.175 | Z79: =+Income_Statement_Qtr!AY79 -> 647.2 | AA79: =+Income_Statement_Qtr!BD79 -> 762.3 | AB79: =+Income_Statement_Qtr!BI79 -> 803.8 | AC79: =AC82 -> 837.311 | AD79: =AD82 -> 837.311 | AE79: =AE82 -> 837.311 | AF79: =AF82 -> 837.311 | AG79: =AA79/Z79-1 -> 0.17784302
A80: =Income_Statement_Qtr!A80 -> YoY | B80: =B79/925.9-1 -> -0.058969651 | C80: =C79/B79-1 -> -0.048203833 | D80: =D79/C79-1 -> -0.025201978 | E80: =E79/D79-1 -> 0.00061850569 | F80: =F79/E79-1 -> 0.0050686117 | G80: =G79/F79-1 -> -0.012423124 | H80: =H79/G79-1 -> -0.019055922 | I80: =I79/H79-1 -> -0.019172169 | J80: =J79/I79-1 -> -0.05631068 | ... P80: =P79/O79-1 -> -0.040255341 | Q80: =+Income_Statement_Qtr!F80 -> -0.056603774 | R80: =+Income_Statement_Qtr!K80 -> -0.075107914 | S80: =+Income_Statement_Qtr!P80 -> -0.051026758 | T80: =+Income_Statement_Qtr!U80 -> -0.040163934 | U80: =+Income_Statement_Qtr!Z80 -> -0.034329633 | V80: =+Income_Statement_Qtr!AE80 -> 0.0049080297 | W80: =+Income_Statement_Qtr!AJ80 -> 0.03581643 | X80: =+Income_Statement_Qtr!AO80 -> 0.012420883 | Y80: =+Income_Statement_Qtr!AT80 -> 0.017353798 | Z80: =+Income_Statement_Qtr!AY80 -> 0.067678476 | AA80: =+Income_Statement_Qtr!BD80 -> 0.17784302 | AB80: =+Income_Statement_Qtr!BI80 -> 0.054440509 | AC80: =AC79/AB79-1 -> 0.041690719 | AD80: =AD79/AC79-1 -> 0 | AE80: =AE79/AD79-1 -> 0 | AF80: =AF79/AE79-1 -> 0
A82: =Income_Statement_Qtr!A82 -> Shares Outstanding at the End of the Period - Diluted | B82: 875.48494 | C82: 837.58044 | D82: 840.03521 | E82: 841.48711 | F82: 832.18393 | G82: 800.17018 | H82: 788.73898 | I82: 768.04399 | J82: 726.59921 | K82: 755.85445 | L82: 735.2591 | M82: 744.70477 | N82: 755.63053 | O82: 747.3787 | P82: 706.72755 | Q82: =+Income_Statement_Qtr!F82 -> 666.6238 | R82: =+Income_Statement_Qtr!K82 -> 617.15159 | S82: =+Income_Statement_Qtr!P82 -> 591.03883 | T82: =+Income_Statement_Qtr!U82 -> 567.64119 | U82: =+Income_Statement_Qtr!Z82 -> 562.90875 | V82: =+Income_Statement_Qtr!AE82 -> 582.32509 | W82: =+Income_Statement_Qtr!AJ82 -> 582.99977 | X82: =+Income_Statement_Qtr!AO82 -> 598.23959 | Y82: =+Income_Statement_Qtr!AT82 -> 610.13521 | Z82: =+Income_Statement_Qtr!AY82 -> 750.07441 | AA82: =+Income_Statement_Qtr!BD82 -> 803.8 | AB82: =+Income_Statement_Qtr!BI82 -> 803.8 | AC82: =AB82+((Cash_Flow_Annual!AC51+Cash_Flow_Annual!AC48)/Income_Statement_Annual!AC89)+AC85 -> 837.311 | AD82: =AC82+((Cash_Flow_Annual!AD51+Cash_Flow_Annual!AD48)/Income_Statement_Annual!AD89)+AD85 -> 837.311 | AE82: =AD82+((Cash_Flow_Annual!AE51+Cash_Flow_Annual!AE48)/Income_Statement_Annual!AE89)+AE85 -> 837.311 | AF82: =AE82+((Cash_Flow_Annual!AF51+Cash_Flow_Annual!AF48)/Income_Statement_Annual!AF89)+AF85 -> 837.311
A83: =Income_Statement_Qtr!A83 -> YoY | B83: =B82/(1011.870159-102.356897)-1 -> -0.037413776 | C83: =C82/B82-1 -> -0.043295431 | D83: =D82/C82-1 -> 0.0029307872 | E83: =E82/D82-1 -> 0.0017283764 | F83: =F82/E82-1 -> -0.011055639 | G83: =G82/F82-1 -> -0.038469557 | H83: =H82/G82-1 -> -0.014285959 | I83: =I82/H82-1 -> -0.026238077 | J83: =J82/I82-1 -> -0.053961459 | ... P83: =P82/O82-1 -> -0.054391629 | Q83: =+Income_Statement_Qtr!F83 -> -0.056745698 | R83: =+Income_Statement_Qtr!K83 -> -0.074213092 | S83: =+Income_Statement_Qtr!P83 -> -0.042311741 | T83: =+Income_Statement_Qtr!U83 -> -0.039587321 | U83: =+Income_Statement_Qtr!Z83 -> -0.0083370183 | V83: =+Income_Statement_Qtr!AE83 -> 0.034492874 | W83: =+Income_Statement_Qtr!AJ83 -> 0.0011585798 | X83: =+Income_Statement_Qtr!AO83 -> 0.026140354 | Y83: =+Income_Statement_Qtr!AT83 -> 0.019884375 | Z83: =+Income_Statement_Qtr!AY83 -> 0.2293577 | AA83: =+Income_Statement_Qtr!BD83 -> 0.071627012 | AB83: =+Income_Statement_Qtr!BI83 -> 0 | AC83: =AC82/AB82-1 -> 0.041690719 | AD83: =AD82/AC82-1 -> 0 | AE83: =AE82/AD82-1 -> 0 | AF83: =AF82/AE82-1 -> 0
A85: Impact of Dilutive Instruments | C85: =(C82+C88-B82) -> 2.795502 | D85: =(D82+D88-C82) -> 2.45477 | E85: =(E82+E88-D82) -> 1.451897 | F85: =(F82+F88-E82) -> 5.405678 | G85: =(G82+G88-F82) -> 13.203553 | H85: =(H82+H88-G82) -> 9.753004 | I85: =(I82+I88-H82) -> 8.300605 | J85: =(J82+J88-I82) -> 0.629111 | ... AB85: =(AB82+AB88-AA82) -> 0 | AC85: =5.75*5.828 -> 33.511 | AD85: 0 | AE85: 0 | AF85: 0
A86: YoY | D86: =D85/C85-1 -> -0.1218858 | E86: =E85/D85-1 -> -0.40854051 | F86: =F85/E85-1 -> 2.7231828 | G86: =G85/F85-1 -> 1.4425341 | H86: =H85/G85-1 -> -0.26133488 | I86: =I85/H85-1 -> -0.14891812 | J86: =J85/I85-1 -> -0.92420902 | K86: =K85/J85-1 -> 47.367279 | ... AF86: =AF85/AE85-1 -> #DIV/0!
A88: =Income_Statement_Qtr!A88 -> Shares Repurchased/(Issued) | B88: 41.8 | C88: 40.7 | D88: 0 | E88: 0 | F88: 14.708856 | G88: 45.2173 | H88: 21.184202 | I88: 28.995599 | J88: 42.073885 | K88: 1.173152 | L88: 0 | M88: 0 | N88: 0 | O88: 25.4 | P88: 46.6 | Q88: =Income_Statement_Qtr!F88 -> 46.730728 | R88: =Income_Statement_Qtr!K88 -> 55.104871 | S88: =Income_Statement_Qtr!P88 -> 46.136166 | T88: =Income_Statement_Qtr!U88 -> 26.058304 | U88: =Income_Statement_Qtr!Z88 -> 6.908645 | V88: =Income_Statement_Qtr!AE88 -> 0 | W88: =Income_Statement_Qtr!AJ88 -> 0 | X88: =Income_Statement_Qtr!AO88 -> 0.288162 | Y88: =Income_Statement_Qtr!AT88 -> 0.277726 | Z88: =Income_Statement_Qtr!AY88 -> 0.135853 | AA88: =Income_Statement_Qtr!BD88 -> 0.10981 | AB88: =Income_Statement_Qtr!BI88 -> 0 | AC88: =-Cash_Flow_Annual!AC51/AC89 -> 0 | AD88: =-Cash_Flow_Annual!AD51/AD89 -> 0 | AE88: =-Cash_Flow_Annual!AE51/AE89 -> 0 | AF88: =-Cash_Flow_Annual!AF51/AF89 -> 0
A89: =Income_Statement_Qtr!A89 -> Average Stock Price | B89: 56.38756 | C89: 59.385749 | D89: NM | E89: NM | F89: 51.125662 | G89: 63.6 | H89: 80.18 | I89: 95.68 | J89: 69.79 | K89: 42.94 | L89: NM | M89: NM | N89: NM | O89: 110.27559 | P89: 128.77682 | Q89: =Income_Statement_Qtr!F89 -> 143.5125 | R89: =Income_Statement_Qtr!K89 -> 130.505 | S89: =Income_Statement_Qtr!P89 -> 210.075 | T89: =Income_Statement_Qtr!U89 -> 351.51 | U89: =Income_Statement_Qtr!Z89 -> 391.30435 | V89: =Income_Statement_Qtr!AE89 -> 391.30435 | W89: =Income_Statement_Qtr!AJ89 -> 391.30435 | X89: =Income_Statement_Qtr!AO89 -> 175.5425 | Y89: =Income_Statement_Qtr!AT89 -> 205.68516 | Z89: =Income_Statement_Qtr!AY89 -> 182.2875 | AA89: =Income_Statement_Qtr!BD89 -> 208.3375 | AB89: =Income_Statement_Qtr!BI89 -> 229.25976 | AC89: =AB89*(1+AC90) -> 252.18573 | AD89: =AC89*(1+AD90) -> 277.40431 | AE89: =AD89*(1+AE90) -> 305.14474 | AF89: =AE89*(1+AF90) -> 335.65921
A90: Sequential Share Price Growth | C90: =IFERROR(C89/B89-1,"NM") -> 0.053171118 | D90: =IFERROR(D89/C89-1,"NM") -> NM | E90: =IFERROR(E89/D89-1,"NM") -> NM | F90: =IFERROR(F89/E89-1,"NM") -> NM | G90: =IFERROR(G89/F89-1,"NM") -> 0.24399367 | H90: =IFERROR(H89/G89-1,"NM") -> 0.26069182 | I90: =IFERROR(I89/H89-1,"NM") -> 0.19331504 | J90: =IFERROR(J89/I89-1,"NM") -> -0.27058946 | ... AB90: =IFERROR(AB89/AA89-1,"NM") -> 0.10042483 | AC90: 0.1 | AD90: 0.1 | AE90: 0.1 | AF90: 0.1
A92: =Income_Statement_Qtr!A92 -> Dividend Per Share | B92: =Cash_Flow_Annual!B84 -> 0.56 | C92: =Cash_Flow_Annual!C84 -> 0.68 | D92: =Cash_Flow_Annual!D84 -> 0.68 | E92: =Cash_Flow_Annual!E84 -> 0.68 | F92: =Cash_Flow_Annual!F84 -> 0.85 | G92: =Cash_Flow_Annual!G84 -> 1.05 | H92: =Cash_Flow_Annual!H84 -> 1.25 | I92: =Cash_Flow_Annual!I84 -> 1.45 | ... P92: =Cash_Flow_Annual!P84 -> 3.1 | Q92: =Income_Statement_Qtr!F92 -> 3.82 | R92: =Income_Statement_Qtr!K92 -> 4.69 | S92: =Income_Statement_Qtr!P92 -> 5.97 | T92: =Income_Statement_Qtr!U92 -> 7.185 | U92: =Income_Statement_Qtr!Z92 -> 8.22 | V92: =Income_Statement_Qtr!AE92 -> 0 | W92: =Income_Statement_Qtr!AJ92 -> 0 | X92: =Income_Statement_Qtr!AO92 -> 0 | Y92: =Income_Statement_Qtr!AT92 -> 0 | Z92: =Income_Statement_Qtr!AY92 -> 0 | AA92: =Income_Statement_Qtr!BD92 -> 0 | AB92: =Income_Statement_Qtr!BI92 -> 0 | AC92: =Cash_Flow_Annual!AC84 -> 0 | AD92: =Cash_Flow_Annual!AD84 -> 0.25 | AE92: =Cash_Flow_Annual!AE84 -> 0.25 | AF92: =Cash_Flow_Annual!AF84 -> 0.25
A93: =Income_Statement_Qtr!A93 -> YoY | B93: =Cash_Flow_Annual!B85 -> 0 | C93: =Cash_Flow_Annual!C85 -> 0.21428571 | D93: =Cash_Flow_Annual!D85 -> 0 | E93: =Cash_Flow_Annual!E85 -> 0 | F93: =Cash_Flow_Annual!F85 -> 0.25 | G93: =Cash_Flow_Annual!G85 -> 0.23529412 | H93: =Cash_Flow_Annual!H85 -> 0.19047619 | I93: =Cash_Flow_Annual!I85 -> 0.16 | ... P93: =Cash_Flow_Annual!P85 -> 0.4187643 | Q93: =Income_Statement_Qtr!F93 -> 0.23225806 | R93: =Income_Statement_Qtr!K93 -> 0.22774869 | S93: =Income_Statement_Qtr!P93 -> 0.27292111 | T93: =Income_Statement_Qtr!U93 -> 0.20351759 | U93: =Income_Statement_Qtr!Z93 -> 0.1440501 | V93: =Income_Statement_Qtr!AE93 -> -1 | W93: =Income_Statement_Qtr!AJ93 -> NM | X93: =Income_Statement_Qtr!AO93 -> NM | Y93: =Income_Statement_Qtr!AT93 -> NM | Z93: =Income_Statement_Qtr!AY93 -> NM | AA93: =Income_Statement_Qtr!BD93 -> 0 | AB93: =Income_Statement_Qtr!BI93 -> 0 | AC93: =Cash_Flow_Annual!AC85 -> NM | AD93: =Cash_Flow_Annual!AD85 -> NM | AE93: =Cash_Flow_Annual!AE85 -> 0 | AF93: =Cash_Flow_Annual!AF85 -> 0
A95: =Income_Statement_Qtr!A95 -> Financial Metrics
A96: =Income_Statement_Qtr!A96 -> Depreciation & Amortization | B96: =Cash_Flow_Annual!B5 -> 1479 | C96: =Cash_Flow_Annual!C5 -> 1743 | D96: =Cash_Flow_Annual!D5 -> 1497 | E96: =Cash_Flow_Annual!E5 -> 1400 | F96: =Cash_Flow_Annual!F5 -> 1509 | G96: =Cash_Flow_Annual!G5 -> 1503 | H96: =Cash_Flow_Annual!H5 -> 1545 | I96: =Cash_Flow_Annual!I5 -> 1486 | ... P96: =Cash_Flow_Annual!P5 -> 1906 | Q96: =Income_Statement_Qtr!$F$96 -> 1833 | R96: =Income_Statement_Qtr!$K$96 -> 1910 | S96: =Income_Statement_Qtr!$P$96 -> 2047 | T96: =Income_Statement_Qtr!$U$96 -> 2114 | U96: =Income_Statement_Qtr!$Z$96 -> 2271 | V96: =Cash_Flow_Annual!V5 -> 2246 | W96: =Cash_Flow_Annual!W5 -> 2144 | X96: =Cash_Flow_Annual!X5 -> 1979 | Y96: =Cash_Flow_Annual!Y5 -> 1861 | Z96: =Cash_Flow_Annual!Z5 -> 1836 | AA96: =Cash_Flow_Annual!AA5 -> 1953 | AB96: =Cash_Flow_Annual!AB5 -> 2073.735 | AC96: =Cash_Flow_Annual!AC5 -> 2827.3433 | ... AF96: =Cash_Flow_Annual!AF5 -> 3064.4801
A97: =Income_Statement_Qtr!A97 -> EBITDA | B97: =B34+B96 -> 4537 | C97: =C34+C96 -> 5639 | D97: =D34+D96 -> 4947 | E97: =E34+E96 -> 2711 | F97: =F34+F96 -> 4071 | G97: =G34+G96 -> 4315 | H97: =H34+H96 -> 5465 | I97: =I34+I96 -> 7316 | ... AF97: =AF34+AF96 -> 14881.367
A98: =Income_Statement_Qtr!A98 -> EBITDA Margin | B98: =B97/B10 -> 0.088404357 | C98: =C97/C10 -> 0.096893364 | D98: =D97/D10 -> 0.091507741 | E98: =E97/E10 -> 0.053943808 | F98: =F97/F10 -> 0.07760642 | G98: =G97/G10 -> 0.080472203 | H98: =H97/H10 -> 0.088818463 | I98: =I97/I10 -> 0.1102023 | ... AF98: =AF97/AF10 -> 0.12365568
A100: =Income_Statement_Qtr!A100 -> Total Cost of Sales | B100: -43712 | C100: -48778 | D100: -45578 | E100: -43792 | F100: =-37759-6916 -> -44675 | G100: =-36858-7767 -> -44625 | H100: =-42490-7594 -> -50084 | I100: =-45375-7732 -> -53107 | J100: =-41662-8467 -> -50129 | K100: =-47639-8726 -> -56365 | L100: =-42194-9489 -> -51683 | M100: =-46642-9097 -> -55739 | N100: =-60309-8247 -> -68556 | O100: =-65640-7553 -> -73193 | P100: =-68551-8132 -> -76683 | Q100: =Income_Statement_Qtr!F100 -> -82024 | R100: =Income_Statement_Qtr!K100 -> -80731 | S100: =Income_Statement_Qtr!P100 -> -76542 | T100: =Income_Statement_Qtr!U100 -> -81421 | U100: =Income_Statement_Qtr!Z100 -> -72031 | V100: =Income_Statement_Qtr!AE100 -> -55913 | W100: =Income_Statement_Qtr!AJ100 -> -59237 | X100: =Income_Statement_Qtr!AO100 -> -63078 | Y100: =Income_Statement_Qtr!AT100 -> -71993 | Z100: =Income_Statement_Qtr!AY100 -> -68508 | AA100: =Income_Statement_Qtr!BD100 -> -85174 | AB100: =Income_Statement_Qtr!BI100 -> -82264.857 | AC100: =AC105-AC10 -> -89412.231 | AD100: =AD105-AD10 -> -93317.632 | AE100: =AE105-AE10 -> -96562.359 | AF100: =AF105-AF10 -> -99284.787
A101: =Income_Statement_Qtr!A101 -> Boeing Capital Interest Expense | B101: ND | C101: -324 | D101: -410 | E101: -358 | F101: -350 | G101: -359 | H101: -353 | I101: -295 | J101: -223 | K101: -175 | L101: -160 | M101: -128 | N101: -109 | O101: -75 | P101: -69 | Q101: =Income_Statement_Qtr!F101 -> -64 | R101: =Income_Statement_Qtr!K101 -> -59 | S101: =Income_Statement_Qtr!P101 -> -70 | T101: =Income_Statement_Qtr!U101 -> -69 | U101: =Income_Statement_Qtr!Z101 -> -62 | V101: =Income_Statement_Qtr!AE101 -> -43 | W101: =Income_Statement_Qtr!AJ101 -> -32 | X101: =Income_Statement_Qtr!AO101 -> -28 | Y101: =Income_Statement_Qtr!AT101 -> 0 | Z101: =Income_Statement_Qtr!AY101 -> 0 | AA101: =Income_Statement_Qtr!BD101 -> 0 | AB101: =Income_Statement_Qtr!BI101 -> 0 | AC101: 0 | AD101: 0 | AE101: 0 | AF101: 0
A102: =Income_Statement_Qtr!A102 -> Operating Expenses | B102: =SUM(B100:B101) -> -43712 | C102: =SUM(C100:C101) -> -49102 | D102: =SUM(D100:D101) -> -45988 | E102: =SUM(E100:E101) -> -44150 | F102: =SUM(F100:F101) -> -45025 | G102: =SUM(G100:G101) -> -44984 | H102: =SUM(H100:H101) -> -50437 | I102: =SUM(I100:I101) -> -53402 | ... AF102: =SUM(AF100:AF101) -> -99284.787
A103: =Income_Statement_Qtr!A103 -> YoY | B103: =B102/-51320-1 -> -0.1482463 | C103: =C102/B102-1 -> 0.1233071 | D103: =D102/C102-1 -> -0.063419005 | E103: =E102/D102-1 -> -0.039966948 | F103: =F102/E102-1 -> 0.0198188 | G103: =G102/F102-1 -> -0.00091060522 | H103: =H102/G102-1 -> 0.12122088 | I103: =I102/H102-1 -> 0.058786209 | J103: =J102/I102-1 -> -0.057113966 | ... P103: =P102/O102-1 -> 0.047551455 | Q103: =Income_Statement_Qtr!F103 -> 0.069522618 | R103: =Income_Statement_Qtr!K103 -> -0.015812299 | S103: =Income_Statement_Qtr!P103 -> -0.051714321 | T103: =Income_Statement_Qtr!U103 -> 0.063671487 | U103: =Income_Statement_Qtr!Z103 -> -0.11531476 | V103: =Income_Statement_Qtr!AE103 -> -0.22383588 | W103: =Income_Statement_Qtr!AJ103 -> 0.059207234 | X103: =Income_Statement_Qtr!AO103 -> 0.064738734 | Y103: =Income_Statement_Qtr!AT103 -> 0.14082655 | Z103: =Income_Statement_Qtr!AY103 -> -0.048407484 | AA103: =Income_Statement_Qtr!BD103 -> 0.24327086 | AB103: =Income_Statement_Qtr!BI103 -> -0.034155294 | AC103: =AC102/AB102-1 -> 0.086882475 | AD103: =AD102/AC102-1 -> 0.04367859 | AE103: =AE102/AD102-1 -> 0.03477079 | AF103: =AF102/AE102-1 -> 0.028193462
A105: =Income_Statement_Qtr!A105 -> Gross Profit | B105: =B10+B100 -> 7609 | C105: =C10+C100 -> 9420 | D105: =D10+D100 -> 8483 | E105: =E10+E100 -> 6464 | F105: =F10+F100 -> 7782 | G105: =G10+G100 -> 8996 | H105: =H10+H100 -> 11446 | I105: =I10+I100 -> 13280 | ... AB105: =AB10+AB100 -> 17450.121 | AC105: =AC106*AC10 -> 18966.231 | AD105: =AD106*AD10 -> 19794.649 | AE105: =AE106*AE10 -> 20482.925 | AF105: =AF106*AF10 -> 21060.409
A106: =Income_Statement_Qtr!A106 -> Gross Margin | B106: =B105/B$10 -> 0.14826289 | C106: =C105/C$10 -> 0.16186123 | D106: =D105/D$10 -> 0.15691534 | E106: =E105/E$10 -> 0.12862146 | F106: =F105/F$10 -> 0.14835008 | G106: =G105/G$10 -> 0.16777009 | H106: =H105/H$10 -> 0.18602308 | I106: =I105/I$10 -> 0.20003916 | ... AB106: =AB105/AB$10 -> 0.175 | AC106: 0.175 | AD106: 0.175 | AE106: 0.175 | AF106: 0.175
A108: =Income_Statement_Qtr!A108 -> Research and Development Expense, net
A109: =Income_Statement_Qtr!A109 -> Commercial Airplanes | B109: =BCA_Annual!B6 -> 0 | C109: =BCA_Annual!C6 -> 0 | D109: =BCA_Annual!D6 -> 0 | E109: =BCA_Annual!E6 -> 0 | F109: =BCA_Annual!F6 -> 0 | G109: =BCA_Annual!G6 -> 0 | H109: =BCA_Annual!H6 -> 0 | I109: =BCA_Annual!I6 -> 0 | ... P109: =BCA_Annual!P6 -> 0 | Q109: =Income_Statement_Qtr!F109 -> 0 | R109: =Income_Statement_Qtr!K109 -> 3706 | S109: =Income_Statement_Qtr!P109 -> 2247 | T109: =Income_Statement_Qtr!U109 -> 2188 | U109: =Income_Statement_Qtr!Z109 -> 1956 | V109: =Income_Statement_Qtr!AE109 -> 1385 | W109: =Income_Statement_Qtr!AJ109 -> 1140 | X109: =Income_Statement_Qtr!AO109 -> 1510 | Y109: =Income_Statement_Qtr!AT109 -> 2036 | Z109: =Income_Statement_Qtr!AY109 -> 2386 | AA109: =Income_Statement_Qtr!BD109 -> 2202 | AB109: =Income_Statement_Qtr!BI109 -> 2422.2 | AC109: =BCA_Annual!AC6 -> 2664.42 | AD109: =BCA_Annual!AD6 -> 2930.862 | AE109: =BCA_Annual!AE6 -> 3223.9482 | AF109: =BCA_Annual!AF6 -> 3546.343
A110: =Income_Statement_Qtr!A110 -> Defense, Space & Security | B110: =BDS_Annual!B6 -> 0 | C110: =BDS_Annual!C6 -> 0 | D110: =BDS_Annual!D6 -> 0 | E110: =BDS_Annual!E6 -> 0 | F110: =BDS_Annual!F6 -> 0 | G110: =BDS_Annual!G6 -> 0 | H110: =BDS_Annual!H6 -> 0 | I110: =BDS_Annual!I6 -> 0 | ... P110: =BDS_Annual!P6 -> 0 | Q110: =Income_Statement_Qtr!F110 -> 0 | R110: =Income_Statement_Qtr!K110 -> 815 | S110: =Income_Statement_Qtr!P110 -> 834 | T110: =Income_Statement_Qtr!U110 -> 788 | U110: =Income_Statement_Qtr!Z110 -> 758 | V110: =Income_Statement_Qtr!AE110 -> 713 | W110: =Income_Statement_Qtr!AJ110 -> 818 | X110: =Income_Statement_Qtr!AO110 -> 945 | Y110: =Income_Statement_Qtr!AT110 -> 919 | Z110: =Income_Statement_Qtr!AY110 -> 917 | AA110: =Income_Statement_Qtr!BD110 -> 877 | AB110: =Income_Statement_Qtr!BI110 -> 903.31 | AC110: =BDS_Annual!AC6 -> 930.4093 | AD110: =BDS_Annual!AD6 -> 958.32158 | AE110: =BDS_Annual!AE6 -> 987.07123 | AF110: =BDS_Annual!AF6 -> 1016.6834
A111: =Income_Statement_Qtr!A111 -> Global Services | B111: =BGS_Annual!B6 -> 0 | C111: =BGS_Annual!C6 -> 0 | D111: =BGS_Annual!D6 -> 0 | E111: =BGS_Annual!E6 -> 0 | F111: =BGS_Annual!F6 -> 0 | G111: =BGS_Annual!G6 -> 0 | H111: =BGS_Annual!H6 -> 0 | I111: =BGS_Annual!I6 -> 0 | ... P111: =BGS_Annual!P6 -> 0 | Q111: =Income_Statement_Qtr!F111 -> 0 | R111: =Income_Statement_Qtr!K111 -> 153 | S111: =Income_Statement_Qtr!P111 -> 140 | T111: =Income_Statement_Qtr!U111 -> 161 | U111: =Income_Statement_Qtr!Z111 -> 121 | V111: =Income_Statement_Qtr!AE111 -> 138 | W111: =Income_Statement_Qtr!AJ111 -> 107 | X111: =Income_Statement_Qtr!AO111 -> 119 | Y111: =Income_Statement_Qtr!AT111 -> 107 | Z111: =Income_Statement_Qtr!AY111 -> 132 | AA111: =Income_Statement_Qtr!BD111 -> 125 | AB111: =Income_Statement_Qtr!BI111 -> 127.5 | AC111: =BGS_Annual!AC6 -> 130.05 | AD111: =BGS_Annual!AD6 -> 132.651 | AE111: =BGS_Annual!AE6 -> 135.30402 | AF111: =BGS_Annual!AF6 -> 138.0101
A112: =Income_Statement_Qtr!A112 -> Commercial Airplanes (Old) | B112: 574 | C112: 858 | D112: 768 | E112: 676 | F112: 941 | G112: 1302 | H112: 2390 | I112: 2962 | J112: 2838 | K112: 5383 | L112: 2975 | M112: 2715 | N112: 2049 | O112: 1807 | P112: 1881 | Q112: =Income_Statement_Qtr!F112 -> 2340 | R112: =Income_Statement_Qtr!K112 -> 0 | S112: =Income_Statement_Qtr!P112 -> 0 | T112: =Income_Statement_Qtr!U112 -> 0 | U112: =Income_Statement_Qtr!Z112 -> 0 | V112: =Income_Statement_Qtr!AE112 -> 0 | W112: =Income_Statement_Qtr!AJ112 -> 0 | X112: =Income_Statement_Qtr!AO112 -> 0 | Y112: =Income_Statement_Qtr!AT112 -> 0 | Z112: =Income_Statement_Qtr!AY112 -> 0 | AA112: =Income_Statement_Qtr!BD112 -> 0 | AB112: =Income_Statement_Qtr!BI112 -> 0 | AC112: 0 | AD112: 0 | AE112: 0 | AF112: 0
A113: =Income_Statement_Qtr!A113 -> Defense, Space & Security (Old) | B113: 783 | C113: 784 | D113: 742 | E113: 846 | F113: 834 | G113: 855 | H113: 791 | I113: 848 | J113: 933 | K113: 1101 | L113: 1136 | M113: 1138 | N113: 1189 | O113: 1215 | P113: 1158 | Q113: =Income_Statement_Qtr!F113 -> 986 | R113: =Income_Statement_Qtr!K113 -> 0 | S113: =Income_Statement_Qtr!P113 -> 0 | T113: =Income_Statement_Qtr!U113 -> 0 | U113: =Income_Statement_Qtr!Z113 -> 0 | V113: =Income_Statement_Qtr!AE113 -> 0 | W113: =Income_Statement_Qtr!AJ113 -> 0 | X113: =Income_Statement_Qtr!AO113 -> 0 | Y113: =Income_Statement_Qtr!AT113 -> 0 | Z113: =Income_Statement_Qtr!AY113 -> 0 | AA113: =Income_Statement_Qtr!BD113 -> 0 | AB113: =Income_Statement_Qtr!BI113 -> 0 | AC113: 0 | AD113: 0 | AE113: 0 | AF113: 0
A114: =Income_Statement_Qtr!A114 -> Other | B114: 84 | C114: =1936-C112-C113 -> 294 | D114: 129 | E114: 129 | F114: 104 | G114: 48 | H114: 76 | I114: 40 | J114: -3 | K114: 22 | L114: 10 | M114: 65 | N114: 60 | O114: 49 | P114: 8 | Q114: =Income_Statement_Qtr!F114 -> 5 | R114: =Income_Statement_Qtr!K114 -> -47 | S114: =Income_Statement_Qtr!P114 -> -42 | T114: =Income_Statement_Qtr!U114 -> 132 | U114: =Income_Statement_Qtr!Z114 -> 384 | V114: =Income_Statement_Qtr!AE114 -> 240 | W114: =Income_Statement_Qtr!AJ114 -> 184 | X114: =Income_Statement_Qtr!AO114 -> 278 | Y114: =Income_Statement_Qtr!AT114 -> 315 | Z114: =Income_Statement_Qtr!AY114 -> 377 | AA114: =Income_Statement_Qtr!BD114 -> 411 | AB114: =Income_Statement_Qtr!BI114 -> 316.09516 | AC114: =AB114*1.03 -> 325.57801 | AD114: =AC114*1.03 -> 335.34535 | AE114: =AD114*1.03 -> 345.40571 | AF114: =AE114*1.03 -> 355.76788
A115: =Income_Statement_Qtr!A115 -> Total R&D Expense | B115: =SUM(B109:B114) -> 1441 | C115: =SUM(C109:C114) -> 1936 | D115: =SUM(D109:D114) -> 1639 | E115: =SUM(E109:E114) -> 1651 | F115: =SUM(F109:F114) -> 1879 | G115: =SUM(G109:G114) -> 2205 | H115: =SUM(H109:H114) -> 3257 | I115: =SUM(I109:I114) -> 3850 | ... AF115: =SUM(AF109:AF114) -> 5056.8044
A117: =Income_Statement_Qtr!A117 -> Non-Recurring Charges
A118: =Income_Statement_Qtr!A118 -> Operating Profit (GAAP) | B118: =B34 -> 3058 | C118: =C34 -> 3896 | D118: =D34 -> 3450 | E118: =E34 -> 1311 | F118: =F34 -> 2562 | G118: =G34 -> 2812 | H118: =H34 -> 3920 | I118: =I34 -> 5830 | ... P118: =P34 -> 7473 | Q118: =Income_Statement_Qtr!F118 -> 7443 | R118: =Income_Statement_Qtr!K118 -> 5834 | S118: =Income_Statement_Qtr!P118 -> 10344 | T118: =Income_Statement_Qtr!U118 -> 11987 | U118: =Income_Statement_Qtr!Z118 -> -1975 | V118: =Income_Statement_Qtr!AE118 -> -12767 | W118: =Income_Statement_Qtr!AJ118 -> -2902 | X118: =Income_Statement_Qtr!AO118 -> -3547 | Y118: =Income_Statement_Qtr!AT118 -> -773 | Z118: =Income_Statement_Qtr!AY118 -> -10707 | AA118: =Income_Statement_Qtr!BD118 -> 4281 | AB118: =Income_Statement_Qtr!BI118 -> 2111.9938 | AC118: =AC34 -> 8681.7119 | AD118: =AD34 -> 10864.926 | AE118: =AE34 -> 11359.434 | AF118: =AF34 -> 11816.886
A119: =Income_Statement_Qtr!A119 -> Pension FAS/CAS Service Cost Adjustment | B119: 0 | C119: 0 | D119: 0 | E119: 0 | F119: 0 | G119: =-0.04*802.9/(1-37.8%) -> -51.633441 | H119: 0 | I119: 0 | J119: 0 | K119: 0 | L119: 0 | M119: 269 | N119: 787 | O119: 1374 | P119: 1469 | Q119: =Income_Statement_Qtr!F119 -> 421 | R119: =Income_Statement_Qtr!K119 -> -217 | S119: =Income_Statement_Qtr!P119 -> -1127 | T119: =Income_Statement_Qtr!U119 -> -1005 | U119: =Income_Statement_Qtr!Z119 -> -1071 | V119: =Income_Statement_Qtr!AE119 -> -1024 | W119: =Income_Statement_Qtr!AJ119 -> -882 | X119: =Income_Statement_Qtr!AO119 -> -849 | Y119: =Income_Statement_Qtr!AT119 -> -799 | Z119: =Income_Statement_Qtr!AY119 -> -811 | AA119: =Income_Statement_Qtr!BD119 -> -784 | AB119: =Income_Statement_Qtr!BI119 -> -850 | AC119: =AB119 -> -850 | AD119: =AC119 -> -850 | AE119: =AD119 -> -850 | AF119: =AE119 -> -850
A120: =Income_Statement_Qtr!A120 -> Postretirement FAS/CAS Service Cost Adjustment | B120: 0 | C120: 0 | D120: 0 | E120: 0 | F120: 0 | G120: 0 | H120: 0 | I120: 0 | J120: 0 | K120: 0 | L120: 0 | M120: 248 | N120: 112 | O120: -60 | P120: -82 | Q120: =Income_Statement_Qtr!F120 -> -123 | R120: =Income_Statement_Qtr!K120 -> -153 | S120: =Income_Statement_Qtr!P120 -> -311 | T120: =Income_Statement_Qtr!U120 -> -322 | U120: =Income_Statement_Qtr!Z120 -> -344 | V120: =Income_Statement_Qtr!AE120 -> -359 | W120: =Income_Statement_Qtr!AJ120 -> -291 | X120: =Income_Statement_Qtr!AO120 -> -294 | Y120: =Income_Statement_Qtr!AT120 -> -257 | Z120: =Income_Statement_Qtr!AY120 -> -293 | AA120: =Income_Statement_Qtr!BD120 -> -261 | AB120: =Income_Statement_Qtr!BI120 -> -260 | AC120: =AB120 -> -260 | AD120: =AC120 -> -260 | AE120: =AD120 -> -260 | AF120: =AE120 -> -260
A121: =Income_Statement_Qtr!A121 -> Core Operating Profit (Incl. Others) | B121: =B118+B119+B120 -> 3058 | C121: =C118+C119+C120 -> 3896 | D121: =D118+D119+D120 -> 3450 | E121: =E118+E119+E120 -> 1311 | F121: =F118+F119+F120 -> 2562 | G121: =G118+G119+G120 -> 2760.3666 | H121: =H118+H119+H120 -> 3920 | I121: =I118+I119+I120 -> 5830 | ... P121: =P118+P119+P120 -> 8860 | Q121: =Income_Statement_Qtr!F121 -> 7741 | R121: =Income_Statement_Qtr!K121 -> 5464 | S121: =Income_Statement_Qtr!P121 -> 8906 | T121: =Income_Statement_Qtr!U121 -> 10660 | U121: =Income_Statement_Qtr!Z121 -> -3390 | V121: =Income_Statement_Qtr!AE121 -> -14150 | W121: =Income_Statement_Qtr!AJ121 -> -4075 | X121: =Income_Statement_Qtr!AO121 -> -4690 | Y121: =Income_Statement_Qtr!AT121 -> -1829 | Z121: =Income_Statement_Qtr!AY121 -> -11811 | AA121: =Income_Statement_Qtr!BD121 -> 3236 | AB121: =Income_Statement_Qtr!BI121 -> 1001.9938 | AC121: =AC118+AC119+AC120 -> 7571.7119 | AD121: =AD118+AD119+AD120 -> 9754.9261 | AE121: =AE118+AE119+AE120 -> 10249.434 | AF121: =AF118+AF119+AF120 -> 10706.886
A122: =Income_Statement_Qtr!A122 -> Other | B122: 0 | C122: 0 | D122: 0 | E122: 0 | F122: 0 | G122: 0 | H122: 0 | I122: 0 | J122: 0 | K122: 0 | L122: 0 | M122: 0 | N122: 0 | O122: -406 | P122: 0 | Q122: =Income_Statement_Qtr!F122 -> 0 | R122: =Income_Statement_Qtr!K122 -> 0 | S122: =Income_Statement_Qtr!P122 -> 0 | T122: =Income_Statement_Qtr!U122 -> 0 | U122: =Income_Statement_Qtr!Z122 -> 0 | V122: =Income_Statement_Qtr!AE122 -> 0 | W122: =Income_Statement_Qtr!AJ122 -> 0 | X122: =Income_Statement_Qtr!AO122 -> 0 | Y122: =Income_Statement_Qtr!AT122 -> 0 | Z122: =Income_Statement_Qtr!AY122 -> 0 | AA122: =Income_Statement_Qtr!BD122 -> 0 | AB122: =Income_Statement_Qtr!BI122 -> 0 | AC122: 0 | AD122: 0 | AE122: 0 | AF122: 0
A123: =Income_Statement_Qtr!A123 -> Core Operating Profit (Excl. Pension) | B123: =B118+B119+B120 -> 3058 | C123: =C118+C119+C120 -> 3896 | D123: =D118+D119+D120 -> 3450 | E123: =E118+E119+E120 -> 1311 | F123: =F118+F119+F120 -> 2562 | G123: =G118+G119+G120 -> 2760.3666 | H123: =H118+H119+H120 -> 3920 | I123: =I118+I119+I120 -> 5830 | ... N123: =N118+N119+N120 -> 7189 | O123: =O121+O122 -> 7876 | P123: =P118+P119+P120 -> 8860 | Q123: =Q118+Q119+Q120 -> 7741 | R123: =R118+R119+R120 -> 5464 | S123: =S118+S119+S120 -> 8906 | T123: =T118+T119+T120 -> 10660 | U123: =U118+U119+U120 -> -3390 | V123: =V118+V119+V120 -> -14150 | W123: =W118+W119+W120 -> -4075 | ... AB123: =AB118+AB119+AB120 -> 1001.9938 | AC123: =AC121+AC122 -> 7571.7119 | AD123: =AD121+AD122 -> 9754.9261 | AE123: =AE121+AE122 -> 10249.434 | AF123: =AF121+AF122 -> 10706.886
A125: =Income_Statement_Qtr!A125 -> Non-Operating Adjustments
...

Sheet Income_Statement_Qtr
A1: Income Statement Quarter
B2: 1Q15A | C2: 2Q15A | D2: 3Q15A | E2: 4Q15A | F2: CY2015A | G2: 1Q16A | H2: 2Q16A | I2: 3Q16A | J2: 4Q16A | K2: CY2016A | L2: 1Q17A | M2: 2Q17A | N2: 3Q17A | O2: 4Q17A | P2: CY2017A | Q2: 1Q18A | R2: 2Q18A | S2: 3Q18A | T2: 4Q18A | U2: CY2018A | V2: 1Q19A | W2: 2Q19A | X2: 3Q19A | Y2: 4Q19A | Z2: CY2019A | AA2: 1Q20A | AB2: 2Q20A | AC2: 3Q20A | AD2: 4Q20A | AE2: CY2020E | AF2: 1Q21A | AG2: 2Q21A | AH2: 3Q21A | AI2: 4Q21A | AJ2: CY2021A | AK2: 1Q22A | AL2: 2Q22A | AM2: 3Q22A | AN2: 4Q22A | AO2: CY2022A | AP2: 1Q23A | AQ2: 2Q23A | AR2: 3Q23A | AS2: 4Q23A | AT2: CY2023A | AU2: 1Q24A | AV2: 2Q24A | AW2: 3Q24A | AX2: 4Q24A | AY2: CY2024A | AZ2: 1Q25A | BA2: 2Q25A | BB2: 3Q25A | BC2: 4Q25A | BD2: CY2025A | BE2: 1Q26E | BF2: 2Q26E | BG2: 3Q26E | BH2: 4Q26E | BI2: CY2026E
A3: Commercial Airplanes (BCA) | B3: =BCA_Qtr!B3 -> 0 | C3: =BCA_Qtr!C3 -> 0 | D3: =BCA_Qtr!D3 -> 0 | E3: =BCA_Qtr!E3 -> 0 | F3: =BCA_Qtr!F3 -> 0 | G3: =BCA_Qtr!G3 -> 12787 | H3: =BCA_Qtr!H3 -> 15643 | I3: =BCA_Qtr!I3 -> 15200 | ... BI3: =BCA_Qtr!BI3 -> 50763.127
A4: Defense, Space & Security (BDS) | B4: =BDS_Qtr!B3 -> 0 | C4: =BDS_Qtr!C3 -> 0 | D4: =BDS_Qtr!D3 -> 0 | E4: =BDS_Qtr!E3 -> 0 | F4: =BDS_Qtr!F3 -> 0 | G4: =BDS_Qtr!G3 -> 6136 | H4: =BDS_Qtr!H3 -> 5394 | I4: =BDS_Qtr!I3 -> 5751 | ... BI4: =BDS_Qtr!BI3 -> 28228.851
A5: Global Services (BGS) | B5: =BGS_Qtr!B3 -> 0 | C5: =BGS_Qtr!C3 -> 0 | D5: =BGS_Qtr!D3 -> 0 | E5: =BGS_Qtr!E3 -> 0 | F5: =BGS_Qtr!F3 -> 0 | G5: =BGS_Qtr!G3 -> 3421 | H5: =BGS_Qtr!H3 -> 3581 | I5: =BGS_Qtr!I3 -> 3506 | ... BI5: =BGS_Qtr!BI3 -> 20923
A6: Boeing Capital (BCC) (Old | B6: 86 | C6: 115 | D6: 114 | E6: 98 | F6: 413 | G6: 64 | H6: 84 | I6: 63 | J6: 87 | K6: 298 | L6: 92 | M6: 72 | N6: 70 | O6: 73 | P6: 307 | Q6: 65 | R6: 72 | S6: 77 | T6: 60 | U6: 274 | V6: 66 | W6: 75 | X6: 66 | Y6: 37 | Z6: 244 | AA6: 65 | AB6: 69 | AC6: 71 | AD6: 56 | AE6: 261 | AF6: 60 | AG6: 78 | AH6: 71 | AI6: 63 | AJ6: 272 | AK6: 46 | AL6: 52 | AM6: 52 | AN6: 49 | AO6: 199 | AU6: 0 | AV6: 0 | AZ6: 0 | BA6: 0 | BB6: 0 | BC6: 0 | BD6: =SUM(AZ6:BC6) -> 0 | BE6: 0 | BF6: 0 | BG6: 0 | BH6: 0 | BI6: =SUM(BE6:BH6) -> 0
A7: Commercial Airplanes (BCA) (Old) | B7: 15381 | C7: 16877 | D7: 17692 | E7: 16098 | F7: 66048 | G7: 0 | H7: 0 | I7: 0 | J7: =K7-SUM(G7,H7,I7) -> 0 | K7: 0 | L7: 0 | M7: 0 | N7: 0 | O7: =P7-SUM(L7,M7,N7) -> 0 | P7: 0 | Q7: 0 | R7: 0 | S7: 0 | T7: =U7-SUM(Q7,R7,S7) -> 0 | U7: 0 | V7: 0 | W7: 0 | X7: 0 | Y7: =Z7-SUM(V7,W7,X7) -> 0 | Z7: 0 | AA7: 0 | AB7: 0 | AC7: 0 | AD7: 0 | AE7: =SUM(AA7:AD7) -> 0 | AF7: 0 | AG7: 0 | AH7: 0 | AI7: 0 | AJ7: =SUM(AF7:AI7) -> 0 | AK7: 0 | AL7: 0 | AM7: 0 | AN7: 0 | AO7: =SUM(AK7:AN7) -> 0 | AT7: =SUM(AP7:AS7) -> 0 | AU7: 0 | AV7: 0 | AY7: =SUM(AU7:AX7) -> 0 | AZ7: 0 | BA7: 0 | BB7: 0 | BC7: 0 | BD7: =SUM(AZ7:BC7) -> 0 | BE7: 0 | BF7: 0 | BG7: 0 | BH7: 0 | BI7: =SUM(BE7:BH7) -> 0
A8: Defense, Space & Security (BDS) (Old) | B8: 6709 | C8: 7544 | D8: 8350 | E8: 7785 | F8: 30388 | G8: 0 | H8: 0 | I8: 0 | J8: =K8-SUM(G8,H8,I8) -> 0 | K8: 0 | L8: 0 | M8: 0 | N8: 0 | O8: =P8-SUM(L8,M8,N8) -> 0 | P8: 0 | Q8: 0 | R8: 0 | S8: 0 | T8: =U8-SUM(Q8,R8,S8) -> 0 | U8: 0 | V8: 0 | W8: 0 | X8: 0 | Y8: =Z8-SUM(V8,W8,X8) -> 0 | Z8: 0 | AA8: 0 | AB8: 0 | AC8: 0 | AD8: 0 | AE8: =SUM(AA8:AD8) -> 0 | AF8: 0 | AG8: 0 | AH8: 0 | AI8: 0 | AJ8: =SUM(AF8:AI8) -> 0 | AK8: 0 | AL8: 0 | AM8: 0 | AN8: 0 | AO8: =SUM(AK8:AN8) -> 0 | AT8: =SUM(AP8:AS8) -> 0 | AU8: 0 | AV8: 0 | AY8: =SUM(AU8:AX8) -> 0 | AZ8: 0 | BA8: 0 | BB8: 0 | BC8: 0 | BD8: =SUM(AZ8:BC8) -> 0 | BE8: 0 | BF8: 0 | BG8: 0 | BH8: 0 | BI8: =SUM(BE8:BH8) -> 0
A9: Unallocated Items, Eliminations and Other | B9: -27 | C9: 7 | D9: -307 | E9: =F9-SUM(B9,C9,D9) -> -408 | F9: -735 | G9: 224 | H9: 53 | I9: -622 | J9: =K9-SUM(G9,H9,I9) -> 118 | K9: -227 | L9: 151 | M9: 5 | N9: 131 | O9: =P9-SUM(L9,M9,N9) -> 255 | P9: 542 | Q9: -59 | R9: 37 | S9: -40 | T9: =U9-SUM(Q9,R9,S9) -> -32 | U9: -94 | V9: -177 | W9: -201 | X9: -35 | Y9: =Z9-SUM(V9,W9,X9) -> -222 | Z9: -635 | AA9: -32 | AB9: 29 | AC9: -70 | AD9: 8 | AE9: =SUM(AA9:AD9) -> -65 | AF9: -46 | AG9: -38 | AH9: -90 | AI9: -173 | AJ9: =SUM(AF9:AI9) -> -347 | AK9: -13 | AL9: -79 | AM9: -98 | AN9: =AO9-SUM(AK9:AM9) -> -41 | AO9: -231 | AP9: -42 | AQ9: -2 | AR9: -65 | AS9: =AT9-SUM(AP9:AR9) -> -58 | AT9: -167 | AU9: -79 | AV9: -47 | AW9: -40 | AX9: =AY9-SUM(AU9:AW9) -> -50 | AY9: -216 | AZ9: -12 | BA9: -23 | BB9: -96 | BC9: =BD9-SUM(AZ9:BB9) -> -57 | BD9: -188 | BE9: =$BI9/4 -> -50 | BF9: =$BI9/4 -> -50 | BG9: =$BI9/4 -> -50 | BH9: =BI9-SUM(BE9:BG9) -> -50 | BI9: -200
A10: Total Net Sales | B10: =SUM(B3:B9) -> 22149 | C10: =SUM(C3:C9) -> 24543 | D10: =SUM(D3:D9) -> 25849 | E10: =SUM(E3:E9) -> 23573 | F10: =SUM(F3:F9) -> 96114 | G10: =SUM(G3:G9) -> 22632 | H10: =SUM(H3:H9) -> 24755 | I10: =SUM(I3:I9) -> 23898 | ... BI10: =SUM(BI3:BI9) -> 99714.978
A11: YoY | F11: =F10/Income_Statement_Annual!P10-1 -> 0.058967409 | G11: =G10/B10-1 -> 0.021806854 | H11: =H10/C10-1 -> 0.0086379008 | I11: =I10/D10-1 -> -0.075476808 | J11: =J10/E10-1 -> -0.012174946 | K11: =K10/F10-1 -> -0.016053853 | L11: =L10/G10-1 -> -0.029648286 | M11: =M10/H10-1 -> -0.068834579 | N11: =N10/I10-1 -> 0.013599464 | ... BI11: =BI10/BD10-1 -> 0.11459462
A13: Commercial Airplanes (BCA) | B13: =+BCA_Qtr!B19 -> 0 | C13: =+BCA_Qtr!C19 -> 0 | D13: =+BCA_Qtr!D19 -> 0 | E13: =+BCA_Qtr!E19 -> 0 | F13: =+BCA_Qtr!F19 -> 0 | G13: =+BCA_Qtr!G19 -> 792 | H13: =+BCA_Qtr!H19 -> -1281 | I13: =+BCA_Qtr!I19 -> 1293 | ... BI13: =+BCA_Qtr!BI19 -> -994.54108
A14: Defense, Space & Security (BDS) | B14: =+BDS_Qtr!B19 -> 0 | C14: =+BDS_Qtr!C19 -> 0 | D14: =+BDS_Qtr!D19 -> 0 | E14: =+BDS_Qtr!E19 -> 0 | F14: =+BDS_Qtr!F19 -> 0 | G14: =+BDS_Qtr!G19 -> 517 | H14: =+BDS_Qtr!H19 -> 362 | I14: =+BDS_Qtr!I19 -> 564 | ... BI14: =+BDS_Qtr!BI19 -> 796.81656
A15: Global Services (BGS) | B15: =+BGS_Qtr!B19 -> 0 | C15: =+BGS_Qtr!C19 -> 0 | D15: =+BGS_Qtr!D19 -> 0 | E15: =+BGS_Qtr!E19 -> 0 | F15: =+BGS_Qtr!F19 -> 0 | G15: =+BGS_Qtr!G19 -> 546 | H15: =+BGS_Qtr!H19 -> 539 | I15: =+BGS_Qtr!I19 -> 524 | ... BI15: =+BGS_Qtr!BI19 -> 3818.4475
A16: Boeing Capital (BCC) | B16: 20 | C16: 11 | D16: 10 | E16: 9 | F16: 50 | G16: 5 | H16: 18 | I16: 13 | J16: 23 | K16: 59 | L16: 39 | M16: 25 | N16: 23 | O16: 27 | P16: 114 | Q16: 20 | R16: 24 | S16: 27 | T16: 8 | U16: 79 | V16: 20 | W16: 37 | X16: 29 | Y16: -58 | Z16: 28 | AA16: 24 | AB16: -7 | AC16: 30 | AD16: 16 | AE16: 63 | AF16: 21 | AG16: 36 | AH16: 42 | AI16: 7 | AJ16: 106 | AK16: -36 | AL16: 27 | AM16: 23 | AN16: 15 | AO16: 29 | AU16: 0 | AV16: 0 | AZ16: 0 | BA16: 0 | BB16: 0 | BC16: 0 | BD16: =SUM(AZ16:BC16) -> 0 | BE16: 0 | BF16: 0 | BG16: 0 | BH16: 0 | BI16: =SUM(BE16:BH16) -> 0
A17: Commercial Airplanes (BCA) (Old) | B17: 1617 | C17: 1206 | D17: 1768 | E17: 566 | F17: 5157 | G17: 0 | H17: 0 | I17: 0 | J17: =K17-SUM(G17,H17,I17) -> 0 | K17: 0 | L17: 0 | M17: 0 | N17: 0 | O17: =P17-SUM(L17,M17,N17) -> 0 | P17: 0 | Q17: 0 | R17: 0 | S17: 0 | T17: =U17-SUM(Q17,R17,S17) -> 0 | U17: 0 | V17: 0 | W17: 0 | X17: 0 | Y17: =Z17-SUM(V17,W17,X17) -> 0 | Z17: 0 | AA17: 0 | AB17: 0 | AC17: 0 | AD17: 0 | AE17: =SUM(AA17:AD17) -> 0 | AF17: 0 | AG17: 0 | AH17: 0 | AI17: 0 | AJ17: =SUM(AF17:AI17) -> 0 | AK17: 0 | AL17: 0 | AM17: 0 | AN17: 0 | AO17: =SUM(AK17:AN17) -> 0 | AT17: =SUM(AP17:AS17) -> 0 | AU17: 0 | AV17: 0 | AY17: =SUM(AU17:AX17) -> 0 | AZ17: 0 | BA17: 0 | BB17: 0 | BC17: 0 | BD17: =SUM(AZ17:BC17) -> 0 | BE17: 0 | BF17: 0 | BG17: 0 | BH17: 0 | BI17: =SUM(BE17:BH17) -> 0
A18: Defense, Space & Security (BDS) (Old) | B18: 743 | C18: 546 | D18: 1022 | E18: 963 | F18: 3274 | G18: 0 | H18: 0 | I18: 0 | J18: =K18-SUM(G18,H18,I18) -> 0 | K18: 0 | L18: 0 | M18: 0 | N18: 0 | O18: =P18-SUM(L18,M18,N18) -> 0 | P18: 0 | Q18: 0 | R18: 0 | S18: 0 | T18: =U18-SUM(Q18,R18,S18) -> 0 | U18: 0 | V18: 0 | W18: 0 | X18: 0 | Y18: =Z18-SUM(V18,W18,X18) -> 0 | Z18: 0 | AA18: 0 | AB18: 0 | AC18: 0 | AD18: 0 | AE18: =SUM(AA18:AD18) -> 0 | AF18: 0 | AG18: 0 | AH18: 0 | AI18: 0 | AJ18: =SUM(AF18:AI18) -> 0 | AK18: 0 | AL18: 0 | AM18: 0 | AN18: 0 | AO18: =SUM(AK18:AN18) -> 0 | AT18: =SUM(AP18:AS18) -> 0 | AU18: 0 | AV18: 0 | AY18: =SUM(AU18:AX18) -> 0 | AZ18: 0 | BA18: 0 | BB18: 0 | BC18: 0 | BD18: =SUM(AZ18:BC18) -> 0 | BE18: 0 | BF18: 0 | BG18: 0 | BH18: 0 | BI18: =SUM(BE18:BH18) -> 0
A19: Unallocated Items, Eliminations and Other | B19: 0 | C19: 0 | D19: 0 | E19: =F19-SUM(B19,C19,D19) -> 0 | F19: 0 | G19: 0 | H19: 0 | I19: 0 | J19: =K19-SUM(G19,H19,I19) -> 0 | K19: 0 | L19: 0 | M19: 0 | N19: 0 | O19: =P19-SUM(L19,M19,N19) -> 0 | P19: 0 | Q19: 0 | R19: 0 | S19: 0 | T19: =U19-SUM(Q19,R19,S19) -> 0 | U19: 0 | V19: 0 | W19: 0 | X19: 0 | Y19: =Z19-SUM(V19,W19,X19) -> 0 | Z19: 0 | AA19: 0 | AB19: 0 | AC19: 0 | AD19: 0 | AE19: =SUM(AA19:AD19) -> 0 | AF19: 0 | AG19: 0 | AH19: 0 | AI19: 0 | AJ19: =SUM(AF19:AI19) -> 0 | AK19: 0 | AL19: 0 | AM19: 0 | AN19: =AO19-SUM(AK19:AM19) -> 0 | AO19: 0 | AP19: 0 | AQ19: 0 | AR19: 0 | AS19: =AT19-SUM(AP19:AR19) -> 0 | AT19: 0 | AU19: 0 | AV19: 0 | AW19: 0 | AX19: =AY19-SUM(AU19:AW19) -> 0 | AY19: 0 | AZ19: 0 | BA19: 0 | BB19: 0 | BC19: =BD19-SUM(AZ19:BB19) -> 0 | BD19: 0 | BE19: 0 | BF19: 0 | BG19: 0 | BH19: =BI19-SUM(BE19:BG19) -> 0 | BI19: 0
A20: Business Segment Operating Profit | B20: =SUM(B13:B19) -> 2380 | C20: =SUM(C13:C19) -> 1763 | D20: =SUM(D13:D19) -> 2800 | E20: =SUM(E13:E19) -> 1538 | F20: =SUM(F13:F19) -> 8481 | G20: =SUM(G13:G19) -> 1860 | H20: =SUM(H13:H19) -> -362 | I20: =SUM(I13:I19) -> 2394 | ... BI20: =SUM(BI13:BI19) -> 3620.723
A22: Pension FAS/CAS Service Cost Adjustment | B22: -152 | C22: -57 | D22: -84 | E22: =+F22-SUM(B22:D22) -> -128 | F22: -421 | G22: 45 | H22: 34 | I22: 50 | J22: =+K22-SUM(G22:I22) -> 88 | K22: 217 | L22: 262 | M22: 278 | N22: 271 | O22: =+P22-SUM(L22:N22) -> 316 | P22: 1127 | Q22: 283 | R22: 237 | S22: 260 | T22: =+U22-SUM(Q22:S22) -> 225 | U22: 1005 | V22: 274 | W22: 275 | X22: 274 | Y22: =+Z22-SUM(V22:X22) -> 248 | Z22: 1071 | AA22: =255 -> 255 | AB22: 258 | AC22: 260 | AD22: 251 | AE22: =SUM(AA22:AD22) -> 1024 | AF22: 193 | AG22: 191 | AH22: 192 | AI22: 306 | AJ22: =SUM(AF22:AI22) -> 882 | AK22: 208 | AL22: 205 | AM22: 208 | AN22: 228 | AO22: =SUM(AK22:AN22) -> 849 | AP22: 223 | AQ22: 222 | AR22: 218 | AS22: 136 | AT22: =SUM(AP22:AS22) -> 799 | AU22: 230 | AV22: 230 | AW22: 148 | AX22: 203 | AY22: =SUM(AU22:AX22) -> 811 | AZ22: 193 | BA22: 197 | BB22: 198 | BC22: 196 | BD22: =SUM(AZ22:BC22) -> 784 | BE22: =$BI22/4 -> 212.5 | BF22: =$BI22/4 -> 212.5 | BG22: =$BI22/4 -> 212.5 | BH22: =BI22-SUM(BE22:BG22) -> 212.5 | BI22: 850
A23: Postretirement FAS/CAS Service Cost Adjustment | B23: 39 | C23: 27 | D23: 27 | E23: =+F23-SUM(B23:D23) -> 30 | F23: 123 | G23: 49 | H23: 35 | I23: 38 | J23: =+K23-SUM(G23:I23) -> 31 | K23: 153 | L23: 84 | M23: 79 | N23: 75 | O23: =+P23-SUM(L23:N23) -> 73 | P23: 311 | Q23: 82 | R23: 80 | S23: 77 | T23: =+U23-SUM(Q23:S23) -> 83 | U23: 322 | V23: 90 | W23: 90 | X23: 90 | Y23: =+Z23-SUM(V23:X23) -> 74 | Z23: 344 | AA23: =92 -> 92 | AB23: 97 | AC23: 93 | AD23: 77 | AE23: =SUM(AA23:AD23) -> 359 | AF23: 77 | AG23: 77 | AH23: 78 | AI23: 59 | AJ23: =SUM(AF23:AI23) -> 291 | AK23: 75 | AL23: 79 | AM23: 71 | AN23: 69 | AO23: =SUM(AK23:AN23) -> 294 | AP23: 68 | AQ23: 69 | AR23: 63 | AS23: 57 | AT23: =SUM(AP23:AS23) -> 257 | AU23: 72 | AV23: 72 | AW23: 80 | AX23: 69 | AY23: =SUM(AU23:AX23) -> 293 | AZ23: 69 | BA23: 60 | BB23: 70 | BC23: 62 | BD23: =SUM(AZ23:BC23) -> 261 | BE23: =$BI23/4 -> 65 | BF23: =$BI23/4 -> 65 | BG23: =$BI23/4 -> 65 | BH23: =BI23-SUM(BE23:BG23) -> 65 | BI23: 260
A24: FAS/CAS Operating Adjustment | B24: =+SUM(B22:B23) -> -113 | C24: =+SUM(C22:C23) -> -30 | D24: =+SUM(D22:D23) -> -57 | E24: =+F24-SUM(B24:D24) -> -98 | F24: =+SUM(F22:F23) -> -298 | G24: =+SUM(G22:G23) -> 94 | H24: =+SUM(H22:H23) -> 69 | I24: =+SUM(I22:I23) -> 88 | J24: =+K24-SUM(G24:I24) -> 119 | K24: =+SUM(K22:K23) -> 370 | L24: =+SUM(L22:L23) -> 346 | M24: =+SUM(M22:M23) -> 357 | N24: =+SUM(N22:N23) -> 346 | O24: =+P24-SUM(L24:N24) -> 389 | P24: =+SUM(P22:P23) -> 1438 | Q24: =+SUM(Q22:Q23) -> 365 | R24: =+SUM(R22:R23) -> 317 | S24: =+SUM(S22:S23) -> 337 | T24: =+U24-SUM(Q24:S24) -> 308 | U24: =+SUM(U22:U23) -> 1327 | V24: =+SUM(V22:V23) -> 364 | W24: =+SUM(W22:W23) -> 365 | X24: =+SUM(X22:X23) -> 364 | Y24: =+Z24-SUM(V24:X24) -> 322 | Z24: =+SUM(Z22:Z23) -> 1415 | AA24: =+SUM(AA22:AA23) -> 347 | AB24: =+SUM(AB22:AB23) -> 355 | AC24: =+SUM(AC22:AC23) -> 353 | AD24: =+AE24-SUM(AA24:AC24) -> 328 | AE24: =+SUM(AE22:AE23) -> 1383 | AF24: =+SUM(AF22:AF23) -> 270 | AG24: =+SUM(AG22:AG23) -> 268 | AH24: =+SUM(AH22:AH23) -> 270 | AI24: =+AJ24-SUM(AF24:AH24) -> 365 | AJ24: =+SUM(AJ22:AJ23) -> 1173 | AK24: =+SUM(AK22:AK23) -> 283 | AL24: =+SUM(AL22:AL23) -> 284 | AM24: =+SUM(AM22:AM23) -> 279 | AN24: =+AO24-SUM(AK24:AM24) -> 297 | AO24: =+SUM(AO22:AO23) -> 1143 | AP24: =+SUM(AP22:AP23) -> 291 | AQ24: =+SUM(AQ22:AQ23) -> 291 | AR24: =+SUM(AR22:AR23) -> 281 | AS24: =+AT24-SUM(AP24:AR24) -> 193 | AT24: =+SUM(AT22:AT23) -> 1056 | AU24: =+SUM(AU22:AU23) -> 302 | AV24: =+SUM(AV22:AV23) -> 302 | AW24: =+SUM(AW22:AW23) -> 228 | AX24: =+AY24-SUM(AU24:AW24) -> 272 | AY24: =+SUM(AY22:AY23) -> 1104 | AZ24: =+SUM(AZ22:AZ23) -> 262 | BA24: =+SUM(BA22:BA23) -> 257 | BB24: =+SUM(BB22:BB23) -> 268 | BC24: =+BD24-SUM(AZ24:BB24) -> 258 | BD24: =+SUM(BD22:BD23) -> 1045 | BE24: =+SUM(BE22:BE23) -> 277.5 | BF24: =+SUM(BF22:BF23) -> 277.5 | BG24: =+SUM(BG22:BG23) -> 277.5 | BH24: =+SUM(BH22:BH23) -> 277.5 | BI24: =+SUM(BI22:BI23) -> 1110
A25: Share-Based Plans | B25: -21 | C25: -16 | D25: -20 | E25: =+F25-SUM(B25:D25) -> -19 | F25: -76 | G25: -23 | H25: -18 | I25: -9 | J25: =+K25-SUM(G25:I25) -> -16 | K25: -66 | L25: -21 | M25: -25 | N25: -21 | O25: =+P25-SUM(L25:N25) -> -10 | P25: -77 | Q25: -18 | R25: -18 | S25: -24 | T25: =+U25-SUM(Q25:S25) -> -16 | U25: -76 | V25: -14 | W25: -22 | X25: -21 | Y25: =+Z25-SUM(V25:X25) -> -8 | Z25: -65 | AA25: -18 | AB25: -25 | AC25: -37 | AD25: -40 | AE25: =SUM(AA25:AD25) -> -120 | AF25: -128 | AG25: -14 | AH25: -29 | AI25: -3 | AJ25: =SUM(AF25:AI25) -> -174 | AK25: -83 | AL25: -25 | AM25: 44 | AN25: -50 | AO25: =SUM(AK25:AN25) -> -114 | AP25: -52 | AQ25: 14 | AR25: 5 | AS25: 95 | AT25: =SUM(AP25:AS25) -> 62 | AU25: 10 | AV25: 43 | AW25: 65 | AX25: 53 | AY25: =SUM(AU25:AX25) -> 171 | AZ25: -30 | BA25: -21 | BB25: 11 | BC25: -9 | BD25: =SUM(AZ25:BC25) -> -49 | BE25: =$BI25/4 -> 12.625 | BF25: =$BI25/4 -> 12.625 | BG25: =$BI25/4 -> 12.625 | BH25: =BI25-SUM(BE25:BG25) -> 12.625 | BI25: 50.5
A26: Deferred Compensation | B26: -58 | C26: 10 | D26: 38 | E26: =+F26-SUM(B26:D26) -> -53 | F26: -63 | G26: 16 | H26: -21 | I26: -33 | J26: =+K26-SUM(G26:I26) -> -8 | K26: -46 | L26: -50 | M26: -46 | N26: -78 | O26: =+P26-SUM(L26:N26) -> -66 | P26: -240 | Q26: -29 | R26: -27 | S26: -56 | T26: =+U26-SUM(Q26:S26) -> 93 | U26: -19 | V26: -102 | W26: -27 | X26: -25 | Y26: =+Z26-SUM(V26:X26) -> -20 | Z26: -174 | AA26: 193 | AB26: -120 | AC26: -39 | AD26: -127 | AE26: =SUM(AA26:AD26) -> -93 | AF26: -52 | AG26: -42 | AH26: 8 | AI26: -40 | AJ26: =SUM(AF26:AI26) -> -126 | AK26: 42 | AL26: 124 | AM26: 38 | AN26: -87 | AO26: =SUM(AK26:AN26) -> 117 | AP26: -54 | AQ26: -42 | AR26: 25 | AS26: -117 | AT26: =SUM(AP26:AS26) -> -188 | AU26: -30 | AV26: -19 | AW26: -51 | AX26: -14 | AY26: =SUM(AU26:AX26) -> -114 | AZ26: 5 | BA26: -85 | BB26: -70 | BC26: -32 | BD26: =SUM(AZ26:BC26) -> -182 | BE26: =$BI26/4 -> -32.5 | BF26: =$BI26/4 -> -32.5 | BG26: =$BI26/4 -> -32.5 | BH26: =BI26-SUM(BE26:BG26) -> -32.5 | BI26: -130
A27: Amortization of Previously Capitalized Interest | B27: -29 | C27: -20 | D27: -21 | E27: =+F27-SUM(B27:D27) -> -20 | F27: -90 | G27: -30 | H27: -18 | I27: -23 | J27: =+K27-SUM(G27:I27) -> -23 | K27: -94 | L27: -24 | M27: -22 | N27: -22 | O27: =+P27-SUM(L27:N27) -> -28 | P27: -96 | Q27: -25 | R27: -23 | S27: -19 | T27: =+U27-SUM(Q27:S27) -> -25 | U27: -92 | V27: -24 | W27: -21 | X27: -23 | Y27: =+Z27-SUM(V27:X27) -> -21 | Z27: -89 | AA27: -23 | AB27: -27 | AC27: -19 | AD27: -26 | AE27: =SUM(AA27:AD27) -> -95 | AF27: -22 | AG27: -22 | AH27: -22 | AI27: -41 | AJ27: =SUM(AF27:AI27) -> -107 | AK27: -23 | AL27: -24 | AM27: -24 | AN27: -24 | AO27: =SUM(AK27:AN27) -> -95 | AP27: -23 | AQ27: -24 | AR27: -24 | AS27: -24 | AT27: =SUM(AP27:AS27) -> -95 | AU27: -23 | AV27: -23 | AW27: -24 | AX27: -23 | AY27: =SUM(AU27:AX27) -> -93 | AZ27: -21 | BA27: -21 | BB27: -22 | BC27: -28 | BD27: =SUM(AZ27:BC27) -> -92 | BE27: =$BI27/4 -> -25 | BF27: =$BI27/4 -> -25 | BG27: =$BI27/4 -> -25 | BH27: =BI27-SUM(BE27:BG27) -> -25 | BI27: -100
A28: Customer Financing Impairment | B28: 0 | C28: 0 | D28: 0 | E28: =+F28-SUM(B28:D28) -> 0 | F28: 0 | G28: 0 | H28: 0 | I28: 0 | J28: =+K28-SUM(G28:I28) -> 0 | K28: 0 | L28: 0 | M28: 0 | N28: 0 | O28: =+P28-SUM(L28:N28) -> 0 | P28: 0 | Q28: 0 | R28: 0 | S28: 0 | T28: =+U28-SUM(Q28:S28) -> 0 | U28: 0 | V28: -250 | W28: 0 | X28: 0 | Y28: =+Z28-SUM(V28:X28) -> 0 | Z28: -250 | AA28: 0 | AB28: =AA28 -> 0 | AC28: =AB28 -> 0 | AD28: =AC28 -> 0 | AE28: =SUM(AA28:AD28) -> 0 | AF28: 0 | AG28: 0 | AH28: 0 | AI28: 0 | AJ28: =SUM(AF28:AI28) -> 0 | AK28: 0 | AL28: 0 | AM28: 0 | AN28: 0 | AO28: =SUM(AK28:AN28) -> 0 | AP28: 0 | AQ28: 0 | AR28: 0 | AS28: 0 | AT28: =SUM(AP28:AS28) -> 0 | AU28: 0 | AV28: 0 | AW28: 0 | AX28: 0 | AY28: =SUM(AU28:AX28) -> 0 | AZ28: 0 | BA28: 0 | BB28: 0 | BC28: 0 | BD28: =SUM(AZ28:BC28) -> 0 | BE28: =$BI28/4 -> 0 | BF28: =$BI28/4 -> 0 | BG28: =$BI28/4 -> 0 | BH28: =BI28-SUM(BE28:BG28) -> 0 | BI28: 0
A29: Research and Development Expense, net | B29: 0 | C29: 0 | D29: 0 | E29: =+F29-SUM(B29:D29) -> 0 | F29: 0 | G29: 0 | H29: 0 | I29: 0 | J29: =+K29-SUM(G29:I29) -> 0 | K29: 0 | L29: 0 | M29: 0 | N29: 0 | O29: =+P29-SUM(L29:N29) -> 0 | P29: 0 | Q29: 2 | R29: -21 | S29: -50 | T29: =+U29-SUM(Q29:S29) -> -63 | U29: -132 | V29: -78 | W29: -99 | X29: -97 | Y29: =+Z29-SUM(V29:X29) -> -110 | Z29: -384 | AA29: -54 | AB29: -62 | AC29: -44 | AD29: -80 | AE29: =SUM(AA29:AD29) -> -240 | AF29: -42 | AG29: -43 | AH29: -59 | AI29: -40 | AJ29: =SUM(AF29:AI29) -> -184 | AK29: -52 | AL29: -66 | AM29: -43 | AN29: -117 | AO29: =SUM(AK29:AN29) -> -278 | AP29: -76 | AQ29: -73 | AR29: -73 | AS29: -93 | AT29: =SUM(AP29:AS29) -> -315 | AU29: -89 | AV29: -99 | AW29: -105 | AX29: -84 | AY29: =SUM(AU29:AX29) -> -377 | AZ29: -82 | BA29: -101 | BB29: -102 | BC29: -126 | BD29: =SUM(AZ29:BC29) -> -411 | BE29: =$BI29/4 -> -93.75 | BF29: =$BI29/4 -> -93.75 | BG29: =$BI29/4 -> -93.75 | BH29: =BI29-SUM(BE29:BG29) -> -93.75 | BI29: -375
A30: Eliminations and Other Unallocated Items | B30: -140 | C30: -24 | D30: -160 | E30: =+F30-SUM(B30:D30) -> -187 | F30: -511 | G30: -129 | H30: -69 | I30: -135 | J30: =+K30-SUM(G30:I30) -> -194 | K30: -527 | L30: -126 | M30: -224 | N30: -112 | O30: =+P30-SUM(L30:N30) -> -224 | P30: -686 | Q30: -256 | R30: -307 | S30: =+-322 -> -322 | T30: =+U30-SUM(Q30:S30) -> -238 | U30: -1123 | V30: -244 | W30: -329 | X30: -356 | Y30: =+Z30-SUM(V30:X30) -> -175 | Z30: -1104 | AA30: -271 | AB30: -244 | AC30: -175 | AD30: -1117 | AE30: =SUM(AA30:AD30) -> -1807 | AF30: -120 | AG30: -177 | AH30: -268 | AI30: -111 | AJ30: =SUM(AF30:AI30) -> -676 | AK30: -144 | AL30: -103 | AM30: -408 | AN30: -507 | AO30: =SUM(AK30:AN30) -> -1162 | AP30: -255 | AQ30: -211 | AR30: -204 | AS30: -553 | AT30: =SUM(AP30:AS30) -> -1223 | AU30: -180 | AV30: -536 | AW30: -303 | AX30: -615 | AY30: =SUM(AU30:AX30) -> -1634 | AZ30: -234 | BA30: -807 | BB30: -565 | BC30: -691 | BD30: =SUM(AZ30:BC30) -> -2297 | BE30: =$BI30/4 -> -516.05731 | BF30: =$BI30/4 -> -516.05731 | BG30: =$BI30/4 -> -516.05731 | BH30: =BI30-SUM(BE30:BG30) -> -516.05731 | BI30: =(BD30+445)*(1+BI11) -> -2064.2292
A31: Total Unallocated Items | B31: =SUM(B24:B30) -> -361 | C31: =SUM(C24:C30) -> -80 | D31: =SUM(D24:D30) -> -220 | E31: =+F31-SUM(B31:D31) -> -377 | F31: =SUM(F24:F30) -> -1038 | G31: =SUM(G24:G30) -> -72 | H31: =SUM(H24:H30) -> -57 | I31: =SUM(I24:I30) -> -112 | J31: =+K31-SUM(G31:I31) -> -122 | K31: =SUM(K24:K30) -> -363 | L31: =SUM(L24:L30) -> 125 | M31: =SUM(M24:M30) -> 40 | N31: =SUM(N24:N30) -> 113 | O31: =+P31-SUM(L31:N31) -> 61 | P31: =SUM(P24:P30) -> 339 | Q31: =SUM(Q24:Q30) -> 39 | R31: =SUM(R24:R30) -> -79 | S31: =SUM(S24:S30) -> -134 | T31: =+U31-SUM(Q31:S31) -> 59 | U31: =SUM(U24:U30) -> -115 | V31: =SUM(V24:V30) -> -348 | W31: =SUM(W24:W30) -> -133 | X31: =SUM(X24:X30) -> -158 | Y31: =+Z31-SUM(V31:X31) -> -12 | Z31: =SUM(Z24:Z30) -> -651 | AA31: =SUM(AA24:AA30) -> 174 | AB31: =SUM(AB24:AB30) -> -123 | AC31: =SUM(AC24:AC30) -> 39 | AD31: =+AE31-SUM(AA31:AC31) -> -1062 | AE31: =SUM(AE24:AE30) -> -972 | AF31: =SUM(AF24:AF30) -> -94 | AG31: =SUM(AG24:AG30) -> -30 | AH31: =SUM(AH24:AH30) -> -100 | AI31: =+AJ31-SUM(AF31:AH31) -> 130 | AJ31: =SUM(AJ24:AJ30) -> -94 | AK31: =SUM(AK24:AK30) -> 23 | AL31: =SUM(AL24:AL30) -> 190 | AM31: =SUM(AM24:AM30) -> -114 | AN31: =+AO31-SUM(AK31:AM31) -> -488 | AO31: =SUM(AO24:AO30) -> -389 | AP31: =SUM(AP24:AP30) -> -169 | AQ31: =SUM(AQ24:AQ30) -> -45 | AR31: =SUM(AR24:AR30) -> 10 | AS31: =+AT31-SUM(AP31:AR31) -> -499 | AT31: =SUM(AT24:AT30) -> -703 | AU31: =SUM(AU24:AU30) -> -10 | AV31: =SUM(AV24:AV30) -> -332 | AW31: =SUM(AW24:AW30) -> -190 | AX31: =+AY31-SUM(AU31:AW31) -> -411 | AY31: =SUM(AY24:AY30) -> -943 | AZ31: =SUM(AZ24:AZ30) -> -100 | BA31: =SUM(BA24:BA30) -> -778 | BB31: =SUM(BB24:BB30) -> -480 | BC31: =SUM(BC24:BC30) -> -628 | BD31: =SUM(BD24:BD30) -> -1986 | BE31: =SUM(BE24:BE30) -> -377.18231 | BF31: =SUM(BF24:BF30) -> -377.18231 | ... BI31: =SUM(BI24:BI30) -> -1508.7292
A32: Settlement With U.S. Department of Justice, net of Accruals | B32: 0 | C32: 0 | D32: 0 | E32: =+F32-SUM(B32:D32) -> 0 | F32: 0 | G32: 0 | H32: 0 | I32: 0 | J32: =+K32-SUM(G32:I32) -> 0 | K32: 0 | L32: 0 | M32: 0 | N32: 0 | O32: =+P32-SUM(L32:N32) -> 0 | P32: 0 | Q32: 0 | R32: 0 | S32: 0 | T32: =+U32-SUM(Q32:S32) -> 0 | U32: 0 | V32: 0 | W32: 0 | X32: 0 | Y32: =+Z32-SUM(V32:X32) -> 0 | Z32: 0 | AA32: 0 | AB32: 0 | AC32: 0 | AD32: 0 | AE32: =SUM(AA32:AD32) -> 0 | AF32: 0 | AG32: 0 | AH32: 0 | AI32: 0 | AJ32: =SUM(AF32:AI32) -> 0 | AK32: 0 | AL32: 0 | AM32: 0 | AN32: 0 | AO32: =SUM(AK32:AN32) -> 0 | AP32: 0 | AQ32: 0 | AR32: 0 | AS32: 0 | AT32: =SUM(AP32:AS32) -> 0 | AU32: 0 | AW32: 0 | AX32: 0 | AY32: =SUM(AU32:AX32) -> 0 | AZ32: 0 | BA32: 0 | BB32: 0 | BC32: 0 | BD32: =SUM(AZ32:BC32) -> 0 | BE32: 0 | BF32: 0 | BG32: 0 | BH32: 0 | BI32: =SUM(BE32:BH32) -> 0
A34: Operating Profit | B34: =+B20+B31+B32 -> 2019 | C34: =+C20+C31+C32 -> 1683 | D34: =+D20+D31+D32 -> 2580 | E34: =+E20+E31+E32 -> 1161 | F34: =+F20+F31+F32 -> 7443 | G34: =+G20+G31+G32 -> 1788 | H34: =+H20+H31+H32 -> -419 | I34: =+I20+I31+I32 -> 2282 | ... BI34: =+BI20+BI31+BI32 -> 2111.9938
A35: Operating Margin | B35: =B34/B10 -> 0.091155357 | C35: =C34/C10 -> 0.068573524 | D35: =D34/D10 -> 0.099810438 | E35: =E34/E10 -> 0.049251262 | F35: =F34/F10 -> 0.077439291 | G35: =G34/G10 -> 0.079003181 | H35: =H34/H10 -> -0.016925874 | I35: =I34/I10 -> 0.095489162 | ... BI35: =BI34/BI10 -> 0.021180306
A37: Interest and Debt Expense | B37: -61 | C37: -75 | D37: -67 | E37: =F37-SUM(B37:D37) -> -72 | F37: -275 | G37: -73 | H37: -73 | I37: -81 | J37: =K37-SUM(G37:I37) -> -79 | K37: -306 | L37: -87 | M37: -93 | N37: -87 | O37: =P37-SUM(L37:N37) -> -93 | P37: -360 | Q37: -102 | R37: -109 | S37: -106 | T37: =U37-SUM(Q37:S37) -> -158 | U37: -475 | V37: -123 | W37: -154 | X37: -203 | Y37: =Z37-SUM(V37:X37) -> -242 | Z37: -722 | AA37: -262 | AB37: -553 | AC37: -643 | AD37: -698 | AE37: =SUM(AA37:AD37) -> -2156 | AF37: -679 | AG37: -673 | AH37: -669 | AI37: -661 | AJ37: =SUM(AF37:AI37) -> -2682 | AK37: -630 | AL37: -650 | AM37: -621 | AN37: -632 | AO37: =SUM(AK37:AN37) -> -2533 | AP37: -649 | AQ37: -621 | AR37: -589 | AS37: -600 | AT37: =SUM(AP37:AS37) -> -2459 | AU37: -569 | AV37: -673 | AW37: -728 | AX37: -755 | AY37: =SUM(AU37:AX37) -> -2725 | AZ37: -708 | BA37: -710 | BB37: -694 | BC37: -659 | BD37: =SUM(AZ37:BC37) -> -2771 | BE37: =-'Debt_Qtr '!BE202 -> -691.95753 | BF37: =-'Debt_Qtr '!BF202 -> -683.06428 | BG37: =-'Debt_Qtr '!BG202 -> -670.01791 | BH37: =-'Debt_Qtr '!BH202 -> -664.10853 | BI37: =SUM(BE37:BH37) -> -2709.1483
A38: Non-Operating FAS Pension Cost | B38: 0 | C38: 0 | D38: 0 | E38: =+F38-SUM(B38:D38) -> 0 | F38: 0 | G38: 0 | H38: 0 | I38: 0 | J38: =+K38-SUM(G38:I38) -> 0 | K38: 0 | L38: 0 | M38: 0 | N38: 0 | O38: =+P38-SUM(L38:N38) -> 0 | P38: 0 | Q38: 0 | R38: 0 | S38: 0 | T38: =+U38-SUM(Q38:S38) -> 0 | U38: 0 | V38: 0 | W38: 0 | X38: 0 | Y38: =+Z38-SUM(V38:X38) -> 0 | Z38: 0 | AA38: 0 | AB38: 0 | AC38: 0 | AD38: =AC38 -> 0 | AE38: =SUM(AA38:AD38) -> 0 | AF38: 0 | AG38: 0 | AH38: 0 | AI38: =AH38 -> 0 | AJ38: =SUM(AF38:AI38) -> 0 | AK38: 0 | AL38: 0 | AM38: 0 | AN38: =AM38 -> 0 | AO38: =SUM(AK38:AN38) -> 0 | AP38: 0 | AQ38: 0 | AR38: 0 | AS38: 0 | AT38: =SUM(AP38:AS38) -> 0 | AU38: 0 | AV38: 0 | AW38: 0 | AX38: 0 | AY38: =SUM(AU38:AX38) -> 0 | AZ38: 0 | BA38: 0 | BB38: 0 | BC38: 0 | BD38: =SUM(AZ38:BC38) -> 0 | BE38: 0 | BF38: 0 | BG38: 0 | BH38: 0 | BI38: =SUM(BE38:BH38) -> 0
A39: Other Non-Operating Expense/ Income, Net | B39: -12 | C39: 15 | D39: -26 | E39: =+F39-SUM(B39:D39) -> 10 | F39: -13 | G39: 26 | H39: 13 | I39: 2 | J39: =+K39-SUM(G39:I39) -> -1 | K39: 40 | L39: 26 | M39: 25 | N39: 40 | O39: =+P39-SUM(L39:N39) -> 32 | P39: 123 | Q39: 66 | R39: -15 | S39: 12 | T39: =+U39-SUM(Q39:S39) -> 29 | U39: 92 | V39: 106 | W39: 107 | X39: 121 | Y39: =+Z39-SUM(V39:X39) -> 104 | Z39: 438 | AA39: =112 -> 112 | AB39: 94 | AC39: 119 | AD39: 122 | AE39: =SUM(AA39:AD39) -> 447 | AF39: 190 | AG39: 199 | AH39: 30 | AI39: 132 | AJ39: =SUM(AF39:AI39) -> 551 | AK39: 181 | AL39: 253 | AM39: 288 | AN39: 336 | AO39: =SUM(AK39:AN39) -> 1058 | AP39: 302 | AQ39: 320 | AR39: 297 | AS39: 308 | AT39: =SUM(AP39:AS39) -> 1227 | AU39: 277 | AV39: 248 | AW39: 265 | AX39: 432 | AY39: =SUM(AU39:AX39) -> 1222 | AZ39: 323 | BA39: 325 | BB39: 276 | BC39: 201 | BD39: =SUM(AZ39:BC39) -> 1125 | BE39: 250 | BF39: 250 | BG39: 250 | BH39: =BI39-SUM(BE39:BG39) -> 375 | BI39: 1125
A40: Pre-Tax Income | B40: =B34+B37+B38+B39 -> 1946 | C40: =C34+C37+C38+C39 -> 1623 | D40: =D34+D37+D38+D39 -> 2487 | E40: =F40-SUM(B40:D40) -> 1099 | F40: =F34+F37+F38+F39 -> 7155 | G40: =G34+G37+G38+G39 -> 1741 | H40: =H34+H37+H38+H39 -> -479 | I40: =I34+I37+I38+I39 -> 2203 | J40: =K40-SUM(G40:I40) -> 2103 | K40: =K34+K37+K38+K39 -> 5568 | L40: =L34+L37+L38+L39 -> 2145 | M40: =M34+M37+M38+M39 -> 2462 | N40: =N34+N37+N38+N39 -> 2583 | O40: =P40-SUM(L40:N40) -> 2917 | P40: =P34+P37+P38+P39 -> 10107 | Q40: =Q34+Q37+Q38+Q39 -> 2839 | R40: =R34+R37+R38+R39 -> 2586 | S40: =S34+S37+S38+S39 -> 2133 | T40: =U40-SUM(Q40:S40) -> 4046 | U40: =U34+U37+U38+U39 -> 11604 | V40: =V34+V37+V38+V39 -> 2333 | W40: =W34+W37+W38+W39 -> -3427 | X40: =X34+X37+X38+X39 -> 1177 | Y40: =Z40-SUM(V40:X40) -> -2342 | Z40: =Z34+Z37+Z38+Z39 -> -2259 | AA40: =AA34+AA37+AA38+AA39 -> -1503 | AB40: =AB34+AB37+AB38+AB39 -> -3423 | AC40: =AC34+AC37+AC38+AC39 -> -925 | AD40: =AD34+AD37+AD38+AD39 -> -8625 | AE40: =AE34+AE37+AE38+AE39 -> -14476 | AF40: =AF34+AF37+AF38+AF39 -> -572 | AG40: =AG34+AG37+AG38+AG39 -> 549 | ... BI40: =BI34+BI37+BI38+BI39 -> 527.84551
A41: YoY | F41: =F40/Income_Statement_Annual!P40-1 -> 0.0025220681 | G41: =G40/B40-1 -> -0.1053443 | H41: =H40/C40-1 -> -1.2951325 | I41: =I40/D40-1 -> -0.11419381 | J41: =J40/E40-1 -> 0.91355778 | K41: =K40/F40-1 -> -0.22180294 | L41: =L40/G40-1 -> 0.23205055 | M41: =M40/H40-1 -> -6.1398747 | N41: =N40/I40-1 -> 0.17249206 | ... BI41: =BI40/BD40-1 -> -0.79967913
A43: Income Tax Benefit/ (Expense) | B43: -610 | C43: -513 | D43: -783 | E43: =+F43-SUM(B43:D43) -> -73 | F43: -1979 | G43: -522 | H43: 245 | I43: 76 | J43: =+K43-SUM(G43:I43) -> -472 | K43: -673 | L43: -566 | M43: -713 | N43: -773 | O43: =+P43-SUM(L43:N43) -> 403 | P43: -1649 | Q43: -362 | R43: -390 | S43: 230 | T43: =+U43-SUM(Q43:S43) -> -622 | U43: -1144 | V43: -184 | W43: 485 | X43: -10 | Y43: =+Z43-SUM(V43:X43) -> 1332 | Z43: 1623 | AA43: =862 -> 862 | AB43: 1028 | AC43: 459 | AD43: 186 | AE43: =SUM(AA43:AD43) -> 2535 | AF43: 11 | AG43: 18 | AH43: 178 | AI43: 536 | AJ43: =SUM(AF43:AI43) -> 743 | AK43: 376 | AL43: -217 | AM43: -176 | AN43: -14 | AO43: =SUM(AK43:AN43) -> -31 | AP43: 71 | AQ43: 251 | AR43: -538 | AS43: -21 | AT43: =SUM(AP43:AS43) -> -237 | AU43: 23 | AV43: 76 | AW43: 50 | AX43: 232 | AY43: =SUM(AU43:AX43) -> 381 | AZ43: -107 | BA43: -51 | BB43: -140 | BC43: -99 | BD43: =SUM(AZ43:BC43) -> -397 | BE43: =-BE40*BE44 -> 26.162935 | BF43: =-BF40*BF44 -> -4.7982755 | BG43: =-BG40*BG44 -> -26.763335 | BH43: =BI43-SUM(BE43:BG43) -> -47.385874 | BI43: =-BI40*BI44 -> -52.784551
A44: Tax Rate | B44: =IF(B43>0,"NM",-B43/B40) -> 0.31346351 | C44: =IF(C43>0,"NM",-C43/C40) -> 0.31608133 | D44: =IF(D43>0,"NM",-D43/D40) -> 0.31483715 | E44: =IF(E43>0,"NM",-E43/E40) -> 0.066424022 | F44: =IF(F43>0,"NM",-F43/F40) -> 0.2765898 | G44: =IF(G43>0,"NM",-G43/G40) -> 0.29982769 | H44: =IF(H43>0,"NM",-H43/H40) -> NM | I44: =IF(I43>0,"NM",-I43/I40) -> NM | ... AH44: =IF(AH43>0,"NM",-AH43/AH40) -> NM | AI44: =-AI43/AI40 -> 0.11404255 | AJ44: =IF(AJ43>0,"NM",-AJ43/AJ40) -> NM | AK44: =IF(AK43>0,"NM",-AK43/AK40) -> NM | AL44: =IF(AL43>0,"NM",-AL43/AL40) -> 0.57559682 | AM44: =IF(AM43>0,"NM",-AM43/AM40) -> -0.056194125 | AN44: =-AN43/AN40 -> -0.021571649 | AO44: =IF(AO43>0,"NM",-AO43/AO40) -> -0.0061728395 | AP44: =IF(AP43>0,"NM",-AP43/AP40) -> NM | AQ44: =IF(AQ43>0,"NM",-AQ43/AQ40) -> NM | AR44: =IF(AR43>0,"NM",-AR43/AR40) -> -0.48909091 | AS44: =-AS43/AS40 -> -2.3333333 | AT44: =IF(AT43>0,"NM",-AT43/AT40) -> -0.11820449 | AU44: =IF(AU43>0,"NM",-AU43/AU40) -> NM | AV44: =IF(AV43>0,"NM",-AV43/AV40) -> NM | AW44: =IF(AW43>0,"NM",-AW43/AW40) -> NM | AX44: =-AX43/AX40 -> 0.05668214 | AY44: =IF(AY43>0,"NM",-AY43/AY40) -> NM | AZ44: =IF(AZ43>0,"NM",-AZ43/AZ40) -> 1.4078947 | BA44: =IF(BA43>0,"NM",-BA43/BA40) -> -0.090909091 | BB44: =IF(BB43>0,"NM",-BB43/BB40) -> -0.026928255 | BC44: =IF(BC43>0,"NM",-BC43/BC40) -> 0.011900469 | BD44: -0.05915 | BE44: =$BI44 -> 0.1 | BF44: =$BI44 -> 0.1 | BG44: =$BI44 -> 0.1 | BH44: =IF(BH43>0,"NM",-BH43/BH40) -> 0.1 | BI44: 0.1
A46: Net earnings | B46: =B40+B43 -> 1336 | C46: =C40+C43 -> 1110 | D46: =D40+D43 -> 1704 | E46: =E40+E43 -> 1026 | F46: =F40+F43 -> 5176 | G46: =G40+G43 -> 1219 | H46: =H40+H43 -> -234 | I46: =I40+I43 -> 2279 | ... BI46: =BI40+BI43 -> 475.06095
A48: Net Loss Attributable to Noncontrolling Interest | B48: 0 | C48: 0 | D48: 0 | E48: =+F48-SUM(B48:D48) -> 0 | F48: 0 | G48: 0 | H48: 0 | I48: 0 | J48: =+K48-SUM(G48:I48) -> 0 | K48: 0 | L48: 0 | M48: 0 | N48: 0 | O48: =+P48-SUM(L48:N48) -> 0 | P48: 0 | Q48: 0 | R48: 0 | S48: 0 | T48: =+U48-SUM(Q48:S48) -> 0 | U48: 0 | V48: 0 | W48: 0 | X48: 0 | Y48: =+Z48-SUM(V48:X48) -> 0 | Z48: 0 | AA48: 13 | AB48: 19 | AC48: 17 | AD48: 19 | AE48: =SUM(AA48:AD48) -> 68 | AF48: 24 | AG48: 20 | AH48: 23 | AI48: 21 | AJ48: =SUM(AF48:AI48) -> 88 | AK48: 23 | AL48: 33 | AM48: 33 | AN48: 29 | AO48: =SUM(AK48:AN48) -> 118 | AP48: 10.8 | AQ48: 0 | AR48: 2 | AS48: 7 | AT48: =SUM(AP48:AS48) -> 19.8 | AU48: 12 | AV48: 0 | AW48: 4 | AX48: -4 | AY48: =SUM(AU48:AX48) -> 12 | AZ48: -6 | BA48: 1 | BB48: 2 | BC48: 0 | BD48: =SUM(AZ48:BC48) -> -3 | BE48: 0 | BF48: 0 | BG48: 0 | BH48: 0 | BI48: =SUM(BE48:BH48) -> 0
A49: Preferred Stock Dividends | AX49: -58 | AY49: =SUM(AU49:AX49) -> -58 | AZ49: -86 | BA49: -86 | BB49: -87 | BC49: -86 | BD49: =SUM(AZ49:BC49) -> -345 | BE49: -86.5 | BF49: -86.5 | BG49: -86.5 | BH49: -86.5 | BI49: =SUM(BE49:BH49) -> -346
A50: Net Earnings Attributable to Boeing Shareholders | B50: =B46+B48 -> 1336 | C50: =C46+C48 -> 1110 | D50: =D46+D48 -> 1704 | E50: =E46+E48 -> 1026 | F50: =F46+F48 -> 5176 | G50: =G46+G48 -> 1219 | H50: =H46+H48 -> -234 | I50: =I46+I48 -> 2279 | ... AT50: =AT46+AT48 -> -2222.2 | AU50: =AU46+AU48+AU49 -> -343 | AV50: =AV46+AV48+AV49 -> -1439 | AW50: =AW46+AW48+AW49 -> -6170 | AX50: =AX46+AX48+AX49 -> -3923 | AY50: =AY46+AY48+AY49 -> -11875 | AZ50: =AZ46+AZ48+AZ49 -> -123 | BA50: =BA46+BA48+BA49 -> -697 | BB50: =BB46+BB48+BB49 -> -5424 | ... BI50: =BI46+BI48+BI49 -> 129.06095
A51: YoY | F51: =F50/Income_Statement_Annual!P50-1 -> -0.049577672 | G51: =G50/B50-1 -> -0.08757485 | H51: =H50/C50-1 -> -1.2108108 | I51: =I50/D50-1 -> 0.33744131 | J51: =J50/E50-1 -> 0.58966862 | K51: =K50/F50-1 -> -0.054289026 | L51: =L50/G50-1 -> 0.29532404 | M51: =M50/H50-1 -> -8.474359 | N51: =N50/I50-1 -> -0.20579201 | ... BD51: =BD50/AY50-1 -> -1.1591579 | BH51: =BH50/BC50-1 -> -0.95820348 | BI51: =BI50/BD50-1 -> -0.93171378
A53: Non-Recurring Charges | B53: 0 | C53: 0 | D53: 0 | E53: =+F53-SUM(B53:D53) -> 0 | F53: 0 | G53: 0 | H53: 0 | I53: 0 | J53: =+K53-SUM(G53:I53) -> 0 | K53: 0 | L53: 0 | M53: 0 | N53: 0 | O53: =+P53-SUM(L53:N53) -> 0 | P53: 0 | Q53: 0 | R53: 0 | S53: 0 | T53: =+U53-SUM(Q53:S53) -> 0 | U53: 0 | V53: 0 | W53: 0 | X53: 0 | Y53: =+Z53-SUM(V53:X53) -> 0 | Z53: 0 | AA53: 0 | AB53: 0 | AC53: =AB53 -> 0 | AD53: =AC53 -> 0 | AE53: =SUM(AA53:AD53) -> 0 | AF53: =AD53 -> 0 | AG53: 0 | AH53: =AG53 -> 0 | AI53: =AH53 -> 0 | AJ53: =SUM(AF53:AI53) -> 0 | AK53: =AI53 -> 0 | AL53: 0 | AM53: =AL53 -> 0 | AN53: =AM53 -> 0 | AO53: =SUM(AK53:AN53) -> 0 | AP53: =AN53 -> 0 | AQ53: 0 | AR53: =AQ53 -> 0 | AS53: 0 | AT53: =SUM(AP53:AS53) -> 0 | AU53: 0 | AV53: 0 | AW53: 0 | AX53: 0 | AY53: =SUM(AU53:AX53) -> 0 | AZ53: 0 | BA53: 0 | BB53: 0 | BC53: 0 | BD53: =SUM(AZ53:BC53) -> 0 | BE53: 0 | BF53: 0 | BG53: 0 | BH53: =BI53-SUM(BE53:BG53) -> 0 | BI53: 0 | BN53: =55/4 -> 13.75
A54: Discontinued Operations | B54: 0 | C54: 0 | D54: 0 | E54: =+F54-SUM(B54:D54) -> 0 | F54: 0 | G54: 0 | H54: 0 | I54: 0 | J54: =+K54-SUM(G54:I54) -> 0 | K54: 0 | L54: 0 | M54: 0 | N54: 0 | O54: =+P54-SUM(L54:N54) -> 0 | P54: 0 | Q54: 0 | R54: 0 | S54: 0 | T54: =+U54-SUM(Q54:S54) -> 0 | U54: 0 | V54: 0 | W54: 0 | X54: 0 | Y54: =+Z54-SUM(V54:X54) -> 0 | Z54: 0 | AA54: 0 | AB54: 0 | AC54: =AB54 -> 0 | AD54: =AC54 -> 0 | AE54: =SUM(AA54:AD54) -> 0 | AF54: =AD54 -> 0 | AG54: 0 | AH54: =AG54 -> 0 | AI54: =AH54 -> 0 | AJ54: =SUM(AF54:AI54) -> 0 | AK54: =AI54 -> 0 | AL54: 0 | AM54: =AL54 -> 0 | AN54: =AM54 -> 0 | AO54: =SUM(AK54:AN54) -> 0 | AP54: =AN54 -> 0 | AQ54: 0 | AR54: =AQ54 -> 0 | AS54: 0 | AT54: =SUM(AP54:AS54) -> 0 | AU54: 0 | AV54: 0 | AW54: 0 | AX54: 0 | AY54: =SUM(AU54:AX54) -> 0 | AZ54: 0 | BA54: 0 | BB54: 0 | BC54: 0 | BD54: =SUM(AZ54:BC54) -> 0 | BE54: =BD54 -> 0 | BF54: =BE54 -> 0 | BG54: =BF54 -> 0 | BH54: =BI54-SUM(BE54:BG54) -> 0 | BI54: 0
A55: Cumulative Effect of Accounting Change | B55: 0 | C55: 0 | D55: 0 | E55: =+F55-SUM(B55:D55) -> 0 | F55: 0 | G55: 0 | H55: 0 | I55: 0 | J55: =+K55-SUM(G55:I55) -> 0 | K55: 0 | L55: 0 | M55: 0 | N55: 0 | O55: =+P55-SUM(L55:N55) -> 0 | P55: 0 | Q55: 0 | R55: 0 | S55: 0 | T55: =+U55-SUM(Q55:S55) -> 0 | U55: 0 | V55: 0 | W55: 0 | X55: 0 | Y55: =+Z55-SUM(V55:X55) -> 0 | Z55: 0 | AA55: 0 | AB55: 0 | AC55: 0 | AD55: =AC55 -> 0 | AE55: =SUM(AA55:AD55) -> 0 | AF55: 0 | AG55: 0 | AH55: 0 | AI55: =AH55 -> 0 | AJ55: =SUM(AF55:AI55) -> 0 | AK55: 0 | AL55: 0 | AM55: 0 | AN55: =AM55 -> 0 | AO55: =SUM(AK55:AN55) -> 0 | AP55: 0 | AQ55: 0 | AR55: 0 | AS55: 0 | AT55: =SUM(AP55:AS55) -> 0 | AU55: 0 | AV55: 0 | AW55: 0 | AX55: 0 | AY55: =SUM(AU55:AX55) -> 0 | AZ55: 0 | BA55: 0 | BB55: 0 | BC55: 0 | BD55: =SUM(AZ55:BC55) -> 0 | BE55: 0 | BF55: 0 | BG55: 0 | BH55: =BI55-SUM(BE55:BG55) -> 0 | BI55: 0
A56: GAAP Net Earnings | B56: =B46+B53+B54+B55 -> 1336 | C56: =C46+C53+C54+C55 -> 1110 | D56: =D46+D53+D54+D55 -> 1704 | E56: =E46+E53+E54+E55 -> 1026 | F56: =F46+F53+F54+F55 -> 5176 | G56: =G46+G53+G54+G55 -> 1219 | H56: =H46+H53+H54+H55 -> -234 | I56: =I46+I53+I54+I55 -> 2279 | ... AY56: =AY46+AY53+AY54+AY55 -> -11829 | AZ56: =AZ50+AZ53+AZ54+AZ55 -> -123 | BA56: =BA46+BA53+BA54+BA55 -> -612 | BB56: =BB46+BB53+BB54+BB55 -> -5339 | BC56: =BC46+BC53+BC54+BC55 -> 8220 | BD56: =BD46+BD53+BD54+BD55 -> 2238 | BE56: =BE46-SUM(BE53:BE55) -> -235.46641 | BF56: =BF46-SUM(BF53:BF55) -> 43.184479 | BG56: =BG46-SUM(BG53:BG55) -> 240.87002 | BH56: =BH46-SUM(BH53:BH55) -> 426.47287 | BI56: =BI46-SUM(BI53:BI55) -> 475.06095
A57: YoY | F57: =F56/Income_Statement_Annual!P56-1 -> -0.049577672 | G57: =G56/B56-1 -> -0.08757485 | H57: =H56/C56-1 -> -1.2108108 | I57: =I56/D56-1 -> 0.33744131 | J57: =J56/E56-1 -> 0.58966862 | K57: =K56/F56-1 -> -0.054289026 | L57: =L56/G56-1 -> 0.29532404 | M57: =M56/H56-1 -> -8.474359 | N57: =N56/I56-1 -> -0.20579201 | ... BI57: =BI56/BD56-1 -> -0.78772969
A59: Net Loss Attributable to Noncontrolling Interest | B59: =B48 -> 0 | C59: =C48 -> 0 | D59: =D48 -> 0 | E59: =E48 -> 0 | F59: =F48 -> 0 | G59: =G48 -> 0 | H59: =H48 -> 0 | I59: =I48 -> 0 | ... BI59: =BI48 -> 0
A60: GAAP Net Earnings Attributable to Boeing Shareholder | B60: =B56+B59 -> 1336 | C60: =C56+C59 -> 1110 | D60: =D56+D59 -> 1704 | E60: =E56+E59 -> 1026 | F60: =F56+F59 -> 5176 | G60: =G56+G59 -> 1219 | H60: =H56+H59 -> -234 | I60: =I56+I59 -> 2279 | ... BI60: =BI56+BI59 -> 475.06095
A62: Adjustments for Core Earnings | B62: =B130 -> 71.31 | C62: =C130 -> 16.044 | D62: =D130 -> 36.366 | E62: =E130 -> 70.03 | F62: =F130 -> 193.75 | G62: =G130 -> -60.76 | H62: =H130 -> -43.588 | I62: =I130 -> -56.41 | ... BI62: =BI130 -> -1066.5
A63: Core Net Earnings from Continuing Operations | B63: =B50+B62 -> 1407.31 | C63: =C50+C62 -> 1126.044 | D63: =D50+D62 -> 1740.366 | E63: =E50+E62 -> 1096.03 | F63: =F50+F62 -> 5369.75 | G63: =G50+G62 -> 1158.24 | H63: =H50+H62 -> -277.588 | I63: =I50+I62 -> 2222.59 | ... BI63: =BI50+BI62 -> -937.43905
A64: YoY | F64: =F63/Income_Statement_Annual!P63-1 -> -0.15367356 | G64: =G63/B63-1 -> -0.17698304 | H64: =H63/C63-1 -> -1.2465161 | I64: =I63/D63-1 -> 0.27708195 | J64: =J63/E63-1 -> 0.414485 | K64: =K63/F63-1 -> -0.13337492 | L64: =L63/G63-1 -> 0.16642492 | M64: =M63/H63-1 -> -6.4721386 | N64: =N63/I63-1 -> -0.28551825 | ... BI64: =BI63/BD63-1 -> -2.0299264
A66: Less: Earnings Available to Participating Securities | B66: -2 | C66: 0 | D66: -3 | E66: =+F66-SUM(B66:D66) -> 1 | F66: -4 | G66: -2 | H66: 0 | I66: -3 | J66: =+K66-SUM(G66:I66) -> 2 | K66: -3 | L66: -2 | M66: 0 | N66: -2 | O66: =+P66-SUM(L66:N66) -> -2 | P66: -6 | Q66: -3 | R66: 0 | S66: -2 | T66: =+U66-SUM(Q66:S66) -> -2 | U66: -7 | V66: -2 | W66: 0 | X66: -1 | Y66: =+Z66-SUM(V66:X66) -> 3 | Z66: 0 | AA66: 0 | AB66: 0 | AC66: 0 | AD66: =AC66 -> 0 | AE66: =SUM(AA66:AD66) -> 0 | AF66: 0 | AG66: 0 | AH66: 0 | AI66: =AH66 -> 0 | AJ66: =SUM(AF66:AI66) -> 0 | AK66: 0 | AL66: 0 | AM66: 0 | AN66: =AM66 -> 0 | AO66: =SUM(AK66:AN66) -> 0 | AP66: 0 | AQ66: 0 | AR66: 0 | AS66: 0 | AT66: =SUM(AP66:AS66) -> 0 | AU66: 0 | AV66: 0 | AW66: 0 | AX66: 0 | AY66: =SUM(AU66:AX66) -> 0 | AZ66: 0 | BA66: 0 | BB66: 0 | BC66: 0 | BD66: =SUM(AZ66:BC66) -> 0 | BE66: 0 | BF66: 0 | BG66: 0 | BH66: =BI66-SUM(BE66:BG66) -> 0 | BI66: 0
A67: Expense related to diluted shares | B67: 0 | C67: 0 | D67: 0 | E67: =+F67-SUM(B67:D67) -> 0 | F67: 0 | G67: 0 | H67: 0 | I67: 0 | J67: =+K67-SUM(G67:I67) -> 0 | K67: 0 | L67: 0 | M67: 0 | N67: 0 | O67: =+P67-SUM(L67:N67) -> 0 | P67: 0 | Q67: 0 | R67: 0 | S67: 0 | T67: =+U67-SUM(Q67:S67) -> 0 | U67: 0 | V67: 0 | W67: 0 | X67: 0 | Y67: =+Z67-SUM(V67:X67) -> 0 | Z67: 0 | AA67: 0 | AB67: 0 | AC67: 0 | AD67: =AC67 -> 0 | AE67: =SUM(AA67:AD67) -> 0 | AF67: 0 | AG67: 0 | AH67: 0 | AI67: =AH67 -> 0 | AJ67: =SUM(AF67:AI67) -> 0 | AK67: 0 | AL67: 0 | AM67: 0 | AN67: =AM67 -> 0 | AO67: =SUM(AK67:AN67) -> 0 | AP67: 0 | AQ67: 0 | AR67: 0 | AS67: 0 | AT67: =SUM(AP67:AS67) -> 0 | AU67: 0 | AV67: 0 | AW67: 0 | AX67: 0 | AY67: =SUM(AU67:AX67) -> 0 | AZ67: 0 | BA67: 0 | BB67: 0 | BC67: 0 | BD67: =SUM(AZ67:BC67) -> 0 | BE67: 0 | BF67: 0 | BG67: 0 | BH67: =BI67-SUM(BE67:BG67) -> 0 | BI67: 0
A69: Core EPS from Continuing Operations - Diluted | B69: =(B63+B66+B67)/B79 -> 1.9707054 | C69: =(C63+C66+C67)/C79 -> 1.6137059 | D69: =(D63+D66+D67)/D79 -> 2.5259756 | E69: =(E63+E66+E67)/E79 -> 1.6145373 | F69: =(F63+F66+F67)/F79 -> 7.7205036 | G69: =(G63+G66+G67)/G79 -> 1.7392298 | H69: =(H63+H66+H67)/H79 -> -0.43694003 | I69: =(I63+I66+I67)/I79 -> 3.5131212 | ... AK69: =(AK63+AK66+AK67)/AK79 -> -2.7513943 | AL69: =(AL63+AL66+AL67)/AL76 -> -0.36550446 | AM69: =(AM63+AM66+AM67)/AM79 -> -6.1797753 | AN69: =(AN63+AN66+AN67)/AN79 -> -1.7532142 | AO69: =(AO63+AO66+AO67)/AO79 -> -11.043326 | AP69: =(AP63+AP66+AP67)/AP79 -> -1.2650622 | AQ69: =(AQ63+AQ66+AQ67)/AQ76 -> -0.81915772 | AR69: =(AR63+AR66+AR67)/AR79 -> -3.2542819 | AS69: =(AS63+AS66+AS67)/AS79 -> -0.47087777 | AT69: =(AT63+AT66+AT67)/AT79 -> -5.8088836 | AU69: =(AU63+AU66+AU67)/AU79 -> -1.130137 | AV69: =(AV63+AV66+AV67)/AV79 -> -2.9013947 | AW69: =(AW63+AW66+AW67)/AW79 -> -10.442793 | AX69: =(AX63+AX66+AX67)/AX79 -> -5.9002924 | AY69: =(AY63+AY66+AY67)/AY79 -> -20.366193 | ... BI69: =(BI63+BI66+BI67)/BI79 -> -1.1662591
A70: EPS from Continuing Operations - Diluted | B70: =(B50+B66+B67)/B79 -> 1.8707054 | C70: =(C50+C66+C67)/C79 -> 1.5907137 | D70: =(D50+D66+D67)/D79 -> 2.4731026 | E70: =(E50+E66+E67)/E79 -> 1.5114717 | F70: =(F50+F66+F67)/F79 -> 7.4417266 | G70: =(G50+G66+G67)/G79 -> 1.8306258 | H70: =(H50+H66+H67)/H79 -> -0.36832992 | I70: =(I50+I66+I67)/I79 -> 3.6024058 | ... BI70: =(BI50+BI66+BI67)/BI79 -> 0.16056352
A71: GAAP EPS - Diluted | B71: =(B56+B66+B67)/B79 -> 1.8707054 | C71: =(C56+C66+C67)/C79 -> 1.5907137 | D71: =(D56+D66+D67)/D79 -> 2.4731026 | E71: =(E56+E66+E67)/E79 -> 1.5114717 | F71: =(F56+F66+F67)/F79 -> 7.4417266 | G71: =(G56+G66+G67)/G79 -> 1.8306258 | H71: =(H56+H66+H67)/H79 -> -0.36832992 | I71: =(I56+I66+I67)/I79 -> 3.6024058 | ... BI71: =(BI56+BI66+BI67)/BI79 -> 0.59101885
A73: EPS from Continuing Operations - Basic | B73: =(B50+B66)/B76 -> 1.8932728 | C73: =(C50+C66)/C76 -> 1.6084625 | D73: =(D50+D66)/D76 -> 2.5011028 | E73: =(E50+E66)/E76 -> 1.5214815 | F73: =(F50+F66)/F76 -> 7.5294803 | G73: =(G50+G66)/G76 -> 1.8478591 | H73: =(H50+H66)/H76 -> -0.36832992 | I73: =(I50+I66)/I76 -> 3.6439321 | ... BI73: =(BI50+BI66)/BI76 -> 0.17003269
A74: GAAP EPS - Basic | B74: =(B56+B66)/B76 -> 1.8932728 | C74: =(C56+C66)/C76 -> 1.6084625 | D74: =(D56+D66)/D76 -> 2.5011028 | E74: =(E56+E66)/E76 -> 1.5214815 | F74: =(F56+F66)/F76 -> 7.5294803 | G74: =(G56+G66)/G76 -> 1.8478591 | H74: =(H56+H66)/H76 -> -0.36832992 | I74: =(I56+I66)/I76 -> 3.6439321 | ... BI74: =(BI56+BI66)/BI76 -> 0.62587396
A76: Weighted Average Common Shares - Basic | B76: 704.6 | C76: 690.1 | D76: 680.1 | E76: =1026/1.52 -> 675 | F76: 686.9 | G76: 658.6 | H76: 635.3 | I76: 624.6 | J76: =1631/2.63 -> 620.15209 | K76: 635.5 | L76: 613.6 | M76: 601.8 | N76: 597.6 | O76: =3320/5.57 -> 596.05027 | P76: 602.5 | Q76: 590.1 | R76: 581.9 | S76: 574.2 | T76: =3424/6 -> 570.66667 | U76: 579.2 | V76: 567.1 | W76: 564.7 | X76: 564.6 | Y76: =1010/1.79 -> 564.24581 | Z76: 565.4 | AA76: 565.4 | AB76: 565.9 | AC76: 566.6 | AD76: =AD79 -> 574.8 | AE76: =AVERAGE(AA76:AD76) -> 568.175 | AF76: 585 | AG76: 587.1 | AH76: 589 | AI76: =AI79 -> 590.3 | AJ76: =AVERAGE(AF76:AI76) -> 587.85 | AK76: 591.4 | AL76: 593.7 | AM76: 596.3 | AN76: 598.9 | AO76: =AVERAGE(AK76:AN76) -> 595.075 | AP76: 602.2 | AQ76: 605.5 | AR76: 607.2 | AS76: 609.5 | AT76: =AVERAGE(AP76:AS76) -> 606.1 | AU76: 613.2 | AV76: 616.6 | AW76: 618.8 | AX76: 718.1 | AY76: 647.2 | AZ76: 753.4 | BA76: 756.6 | BB76: 759.9 | BC76: =8134/10.59 -> 768.0831 | BD76: =1890/2.49 -> 759.03614 | BE76: =BD76/BD82*BE82 -> 759.03614 | BF76: =BE76/BE82*BF82 -> 759.03614 | BG76: =BF76/BF82*BG82 -> 759.03614 | BH76: =BG76/BG82*BH82 -> 759.03614 | BI76: =AVERAGE(BE76:BH76) -> 759.03614
A77: YoY | F77: =F76/Income_Statement_Annual!P76-1 -> -0.055937328 | G77: =G76/B76-1 -> -0.065285268 | H77: =H76/C76-1 -> -0.079408781 | I77: =I76/D76-1 -> -0.081605646 | J77: =J76/E76-1 -> -0.081256161 | K77: =K76/F76-1 -> -0.074828942 | L77: =L76/G76-1 -> -0.068326754 | M77: =M76/H76-1 -> -0.052730993 | N77: =N76/I76-1 -> -0.043227666 | ... BI77: =BI76/BD76-1 -> 0
A79: Weighted Average Common Shares - Diluted | B79: 713.1 | C79: 697.8 | D79: 687.8 | E79: =1026/1.51 -> 679.4702 | F79: 695 | G79: 664.8 | H79: 635.3 | I79: 631.8 | J79: =1631/2.59 -> 629.72973 | K79: 642.8 | L79: 620.4 | M79: 608.9 | N79: 605.6 | O79: =3320/5.49 -> 604.73588 | P79: 610 | Q79: 596.5 | R79: 588 | S79: 580.2 | T79: =3424/5.93 -> 577.40304 | U79: 585.5 | V79: 571.8 | W79: 564.7 | X79: 568.6 | Y79: =1010/1.79 -> 564.24581 | Z79: 565.4 | AA79: 565.4 | AB79: 565.9 | AC79: 566.6 | AD79: =575.4-0.6 -> 574.8 | AE79: =AVERAGE(AA79:AD79) -> 568.175 | AF79: 585.4 | AG79: 589.8 | AH79: 588.6 | AI79: 590.3 | AJ79: =AVERAGE(AF79:AI79) -> 588.525 | AK79: 591.7 | AL79: 596.44 | AM79: 596.3 | AN79: 598.9 | AO79: =AVERAGE(AK79:AN79) -> 595.835 | AP79: 602.5 | AQ79: 605.5 | AR79: 607.2 | AS79: 609.5 | AT79: =AVERAGE(AP79:AS79) -> 606.175 | AU79: 613.2 | AV79: 616.6 | AW79: 618.8 | AX79: 718.1 | AY79: 647.2 | AZ79: 753.4 | BA79: 756.6 | BB79: 759.9 | BC79: 803.8 | BD79: 762.3 | BE79: =BC79 -> 803.8 | BF79: =BE79/BE76*BF76 -> 803.8 | BG79: =BF79/BF76*BG76 -> 803.8 | BH79: =BG79/BG76*BH76 -> 803.8 | BI79: =AVERAGE(BE79:BH79) -> 803.8
A80: YoY | F80: =F79/Income_Statement_Annual!P79-1 -> -0.056603774 | G80: =G79/B79-1 -> -0.067732436 | H80: =H79/C79-1 -> -0.089567211 | I80: =I79/D79-1 -> -0.081419017 | J80: =J79/E79-1 -> -0.073204784 | K80: =K79/F79-1 -> -0.075107914 | L80: =L79/G79-1 -> -0.066787004 | M80: =M79/H79-1 -> -0.041555171 | N80: =N79/I79-1 -> -0.041468819 | ... BI80: =BI79/BD79-1 -> 0.054440509
A82: Shares Outstanding at the End of the Period - Diluted | B82: 694.00362 | C82: 681.06719 | D82: 670.96095 | E82: 666.6238 | F82: =E82 -> 666.6238 | G82: 639.815 | H82: 625.85837 | I82: 618.95951 | J82: 617.15159 | K82: =J82 -> 617.15159 | L82: 605.79236 | M82: 593.19855 | N82: 597.35094 | O82: 591.03883 | P82: =O82 -> 591.03883 | Q82: 584.22217 | R82: 575.88368 | S82: 568.99903 | T82: 567.64119 | U82: =T82 -> 567.64119 | V82: 563.41139 | W82: 562.70261 | X82: 562.78876 | Y82: 562.90875 | Z82: =Y82 -> 562.90875 | AA82: 564.31335 | AB82: 564.42022 | AC82: 564.52122 | AD82: 582.32509 | AE82: =AD82 -> 582.32509 | AF82: 584.81007 | AG82: 586.1519 | AH82: 587.69922 | AI82: 582.99977 | AJ82: =AI82 -> 582.99977 | AK82: 591.63583 | AL82: 593.81117 | AM82: 595.98319 | AN82: 598.23959 | AO82: =AN82 -> 598.23959 | AP82: 601.59351 | AQ82: 603.20355 | AR82: 604.9768 | AS82: 610.13521 | AT82: =AS82 -> 610.13521 | AU82: 613.88422 | AV82: 616.16716 | AW82: 618.20091 | AX82: 750.07441 | AY82: =AX82 -> 750.07441 | AZ82: 754.00547 | BA82: 756.15769 | BB82: 760.09547 | BC82: 803.8 | BD82: =BC82 -> 803.8 | BE82: =BD82-BE88+BE85 -> 803.8 | BF82: =BE82-BF88+BF85 -> 803.8 | BG82: =BF82-BG88+BG85 -> 803.8 | BH82: =BG82-BH88+BH85 -> 803.8 | BI82: =BH82 -> 803.8
A83: YoY | F83: =F82/Income_Statement_Annual!P82-1 -> -0.056745698 | G83: =G82/B82-1 -> -0.078081174 | H83: =H82/C82-1 -> -0.08106223 | I83: =I82/D82-1 -> -0.077502933 | J83: =J82/E82-1 -> -0.074213092 | K83: =K82/F82-1 -> -0.074213092 | L83: =L82/G82-1 -> -0.053175752 | M83: =M82/H82-1 -> -0.052184034 | N83: =N82/I82-1 -> -0.034911122 | ... BI83: =BI82/BD82-1 -> 0
A85: Impact of Dilutive Instruments | C85: =(C82+C88-B82) -> 0.634068 | D85: =(D82+D88-C82) -> 0.79683 | E85: =(E82+E88-D82) -> 0.95521 | G85: =(G82+G88-F82) -> 1.76694 | H85: =(H82+H88-G82) -> 1.341897 | I85: =(I82+I88-H82) -> 0.659151 | J85: =(J82+J88-I82) -> 1.864669 | K85: =(K82+K88-F82) -> 5.632657 | L85: =(L82+L88-K82) -> 3.551835 | M85: =(M82+M88-L82) -> 0.972842 | N85: =(N82+N88-M82) -> 15.153908 | O85: =(O82+O88-N82) -> 0.344823 | P85: =(P82+P88-K82) -> 20.023408 | Q85: =(Q82+Q88-P82) -> 2.058433 | R85: =(R82+R88-Q82) -> 0.23511 | S85: =(S82+S88-R82) -> 0.164107 | T85: =(T82+T88-S82) -> 0.20301 | U85: =(U82+U88-P82) -> 2.66066 | V85: =(V82+V88-U82) -> 1.878209 | W85: =(W82+W88-V82) -> 0.091853 | X85: =(X82+X88-W82) -> 0.08615 | Y85: =(Y82+Y88-X82) -> 0.119998 | Z85: =(Z82+Z88-U82) -> 2.17621 | AA85: =(AA82+AA88-Z82) -> 1.404598 | AB85: =(AB82+AB88-AA82) -> 0.106869 | AC85: =(AC82+AC88-AB82) -> 0.1009989 | AD85: =(AD82+AD88-AC82) -> 17.803875 | AE85: =(AE82+AE88-Z82) -> 19.416341 | AF85: =(AF82+AF88-AE82) -> 2.4849731 | AG85: =(AG82+AG88-AF82) -> 1.341836 | AH85: =(AH82+AH88-AG82) -> 1.54732 | AI85: =(AI82+AI88-AH82) -> -4.699459 | AJ85: =(AJ82+AJ88-AE82) -> 0.6746701 | AK85: =(AK82+AK88-AJ82) -> 8.798878 | AL85: =(AL82+AL88-AK82) -> 2.185886 | AM85: =(AM82+AM88-AL82) -> 2.261083 | AN85: =(AN82+AN88-AM82) -> 2.282135 | AO85: =(AO82+AO88-AJ82) -> 15.527982 | AP85: =(AP82+AP88-AO82) -> 3.582214 | AQ85: =(AQ82+AQ88-AP82) -> 1.638288 | AR85: =(AR82+AR88-AQ82) -> 1.794436 | AS85: =(AS82+AS88-AR82) -> 5.158408 | AT85: =(AT82+AT88-AO82) -> 12.173346 | AU85: =(AU82+AU88-AT82) -> 3.749019 | AV85: =(AV82+AV88-AU82) -> 2.320885 | AW85: =(AW82+AW88-AV82) -> 2.065658 | AX85: =(AX82+AX88-AW82) -> 131.9395 | AY85: =(AY82+AY88-AT82) -> 140.07506 | AZ85: =(AZ82+AZ88-AY82) -> 4.019363 | BA85: =(BA82+BA88-AZ82) -> 2.173731 | BB85: =(BB82+BB88-BA82) -> 3.937773 | BC85: =BD85-SUM(AZ85:BB85) -> -6.130867 | BD85: 4 | BE85: =$BI85/4 -> 0 | BF85: =$BI85/4 -> 0 | BG85: =$BI85/4 -> 0 | BH85: =BI85-SUM(BE85:BG85) -> 0 | BI85: 0
A86: YoY | C86: =IFERROR(C85/#REF!-1,"nm") -> nm | D86: =IFERROR(D85/#REF!-1,"nm") -> nm | E86: =IFERROR(E85/#REF!-1,"nm") -> nm | G86: =IFERROR(G85/B85-1,"nm") -> nm | H86: =IFERROR(H85/C85-1,"nm") -> 1.1163298 | I86: =IFERROR(I85/D85-1,"nm") -> -0.1727834 | J86: =IFERROR(J85/E85-1,"nm") -> 0.95210373 | K86: =IFERROR(K85/F85-1,"nm") -> nm | L86: =IFERROR(L85/G85-1,"nm") -> 1.0101616 | M86: =IFERROR(M85/H85-1,"nm") -> -0.27502483 | N86: =IFERROR(N85/I85-1,"nm") -> 21.99004 | ... BI86: =IFERROR(BI85/BD85-1,"nm") -> -1
A88: Shares Repurchased/(Issued) | B88: 16.964807 | C88: 13.570495 | D88: 10.903068 | E88: 5.292358 | F88: =SUM(B88:E88) -> 46.730728 | G88: 28.575744 | H88: 15.298532 | I88: 7.558006 | J88: 3.672589 | K88: =SUM(G88:J88) -> 55.104871 | L88: 14.911069 | M88: 13.566647 | N88: 11.00152 | O88: 6.65693 | P88: =SUM(L88:O88) -> 46.136166 | Q88: 8.875094 | R88: 8.573602 | S88: 7.048754 | T88: 1.560854 | U88: =SUM(Q88:T88) -> 26.058304 | V88: 6.108004 | W88: 0.800641 | X88: 0 | Y88: 0 | Z88: =SUM(V88:Y88) -> 6.908645 | AA88: 0 | AB88: 0 | AC88: 0 | AD88: 0 | AE88: =SUM(AA88:AD88) -> 0 | AF88: 0 | AG88: 0 | AH88: =-Cash_Flow_Qtr!AH51/AH89 -> 0 | AI88: 0 | AJ88: =SUM(AF88:AI88) -> 0 | AK88: 0.16281 | AL88: 0.01055 | AM88: 0.08906 | AN88: 0.025742 | AO88: =SUM(AK88:AN88) -> 0.288162 | AP88: 0.228292 | AQ88: 0.028241 | AR88: 0.021193 | AS88: 0 | AT88: =SUM(AP88:AS88) -> 0.277726 | AU88: 0 | AV88: 0.037944 | AW88: 0.031912 | AX88: 0.065997 | AY88: =SUM(AU88:AX88) -> 0.135853 | AZ88: 0.0883 | BA88: 0.02151 | BB88: 0 | BC88: =-Cash_Flow_Qtr!BC51/Income_Statement_Qtr!BC89 -> 0 | BD88: =SUM(AZ88:BC88) -> 0.10981 | BE88: =-Cash_Flow_Qtr!BE51/Income_Statement_Qtr!BE89 -> 0 | BF88: =-Cash_Flow_Qtr!BF51/Income_Statement_Qtr!BF89 -> 0 | BG88: =-Cash_Flow_Qtr!BG51/Income_Statement_Qtr!BG89 -> 0 | BH88: =-Cash_Flow_Qtr!BH51/Income_Statement_Qtr!BH89 -> 0 | BI88: =SUM(BE88:BH88) -> 0
A89: Average Stock Price | B89: 147.32 | C89: 147.39 | D89: 137.6 | E89: 141.74 | F89: 143.5125 | G89: 122.49 | H89: 130.75 | I89: 132.32 | J89: 136.46 | K89: 130.505 | L89: 167.89 | M89: 184.27 | N89: 227.25 | O89: 260.89 | P89: 210.075 | Q89: 338.46 | R89: 345.77 | S89: 347.57 | T89: 374.24 | U89: 351.51 | V89: 384.93 | W89: 387.48 | X89: 0 | Y89: 0 | Z89: 391.30435 | AA89: 140 | AB89: 180 | AC89: 180 | AD89: 190 | AE89: 391.30435 | AF89: 222.26656 | AG89: 180 | AH89: =AG89*(1+AH90) -> 185.4 | AI89: 190 | AJ89: 391.30435 | AK89: 201.44 | AL89: 179.72 | AM89: 151.07 | AN89: 169.94 | AO89: 175.5425 | AP89: 185.29 | AQ89: 204.78 | AR89: 219.15 | AS89: 213.52062 | AT89: 205.68516 | AU89: 213.6 | AV89: 177.47 | AW89: 180.07 | AX89: 158.01 | AY89: =AVERAGE(AU89:AX89) -> 182.2875 | AZ89: 178.26 | BA89: 186.66 | BB89: 220 | BC89: 248.43 | BD89: =AVERAGE(AZ89:BC89) -> 208.3375 | BE89: =BD89*(1+BE90) -> 216.671 | BF89: =BE89*(1+BF90) -> 225.33784 | BG89: =BF89*(1+BG90) -> 234.35135 | BH89: =BG89*(1+BH90) -> 240.67884 | BI89: =AVERAGE(BE89:BH89) -> 229.25976
A90: Sequential Share Price Growth | C90: =IFERROR(C89/B89-1,"NM") -> 0.00047515612 | D90: =IFERROR(D89/C89-1,"NM") -> -0.066422417 | E90: =IFERROR(E89/D89-1,"NM") -> 0.030087209 | G90: =IFERROR(G89/E89-1,"NM") -> -0.13581205 | H90: =IFERROR(H89/G89-1,"NM") -> 0.067434076 | I90: =IFERROR(I89/H89-1,"NM") -> 0.012007648 | J90: =IFERROR(J89/I89-1,"NM") -> 0.031287787 | K90: =IFERROR(K89/F89-1,"NM") -> -0.090636704 | L90: =IFERROR(L89/J89-1,"NM") -> 0.2303239 | M90: =IFERROR(M89/L89-1,"NM") -> 0.097563881 | N90: =IFERROR(N89/M89-1,"NM") -> 0.2332447 | O90: =IFERROR(O89/N89-1,"NM") -> 0.1480308 | P90: =IFERROR(P89/K89-1,"NM") -> 0.60970844 | Q90: =IFERROR(Q89/O89-1,"NM") -> 0.29732838 | R90: =IFERROR(R89/Q89-1,"NM") -> 0.021597825 | S90: =IFERROR(S89/R89-1,"NM") -> 0.0052057726 | T90: =IFERROR(T89/S89-1,"NM") -> 0.076732744 | U90: =IFERROR(U89/P89-1,"NM") -> 0.67325955 | V90: =IFERROR(V89/T89-1,"NM") -> 0.028564558 | W90: =IFERROR(W89/V89-1,"NM") -> 0.0066245811 | X90: =IFERROR(X89/W89-1,"NM") -> -1 | Y90: =IFERROR(Y89/X89-1,"NM") -> NM | Z90: =IFERROR(Z89/U89-1,"NM") -> 0.11320972 | AA90: =IFERROR(AA89/Y89-1,"NM") -> NM | AB90: =IFERROR(AB89/AA89-1,"NM") -> 0.28571429 | AC90: =IFERROR(AC89/AB89-1,"NM") -> 0 | AD90: =IFERROR(AD89/AC89-1,"NM") -> 0.055555556 | AE90: =IFERROR(AE89/Z89-1,"NM") -> 0 | AF90: =IFERROR(AF89/AD89-1,"NM") -> 0.16982399 | AG90: =IFERROR(AG89/AF89-1,"NM") -> -0.19016157 | AH90: 0.03 | AI90: =IFERROR(AI89/AH89-1,"NM") -> 0.024811219 | AJ90: =IFERROR(AJ89/AE89-1,"NM") -> 0 | AK90: =IFERROR(AK89/AI89-1,"NM") -> 0.060210526 | AL90: =IFERROR(AL89/AK89-1,"NM") -> -0.10782367 | AM90: =IFERROR(AM89/AL89-1,"NM") -> -0.15941465 | AN90: =IFERROR(AN89/AM89-1,"NM") -> 0.12490898 | AO90: =IFERROR(AO89/AJ89-1,"NM") -> -0.55139139 | AP90: =IFERROR(AP89/AN89-1,"NM") -> 0.090325997 | AQ90: =IFERROR(AQ89/AP89-1,"NM") -> 0.10518646 | AR90: =IFERROR(AR89/AQ89-1,"NM") -> 0.070172868 | AS90: =IFERROR(AS89/AR89-1,"NM") -> -0.025687315 | AT90: =IFERROR(AT89/AO89-1,"NM") -> 0.17171144 | AU90: =IFERROR(AU89/AS89-1,"NM") -> 0.00037174395 | AV90: =IFERROR(AV89/AU89-1,"NM") -> -0.16914794 | AW90: =IFERROR(AW89/AV89-1,"NM") -> 0.014650363 | AX90: =IFERROR(AX89/AW89-1,"NM") -> -0.12250791 | AY90: =IFERROR(AY89/AT89-1,"NM") -> -0.11375471 | AZ90: =IFERROR(AZ89/AX89-1,"NM") -> 0.12815645 | BA90: =IFERROR(BA89/AZ89-1,"NM") -> 0.047122181 | BB90: =IFERROR(BB89/BA89-1,"NM") -> 0.17861352 | BC90: =IFERROR(BC89/BB89-1,"NM") -> 0.12922727 | BD90: =IFERROR(BD89/AY89-1,"NM") -> 0.14290612 | BE90: 0.04 | BF90: 0.04 | BG90: 0.04 | BH90: 0.027 | BI90: =IFERROR(BI89/BD89-1,"NM") -> 0.10042483
A92: Dividend Per Share | B92: =Cash_Flow_Qtr!B84 -> 0.91 | C92: =Cash_Flow_Qtr!C84 -> 0.91 | D92: =Cash_Flow_Qtr!D84 -> 0.91 | E92: =Cash_Flow_Qtr!E84 -> 1.09 | F92: =Cash_Flow_Qtr!F84 -> 3.82 | G92: =Cash_Flow_Qtr!G84 -> 1.09 | H92: =Cash_Flow_Qtr!H84 -> 1.09 | I92: =Cash_Flow_Qtr!I84 -> 1.09 | ... BB92: =Cash_Flow_Qtr!BB84 -> 0 | BC92: =Cash_Flow_Qtr!BM84 -> 0 | BD92: =Cash_Flow_Qtr!BN84 -> 0 | BE92: =Cash_Flow_Qtr!BE84 -> 0 | BF92: =Cash_Flow_Qtr!BF84 -> 0 | BG92: =Cash_Flow_Qtr!BG84 -> 0 | BH92: =Cash_Flow_Qtr!BH84 -> 0 | BI92: =Cash_Flow_Qtr!BI84 -> 0
A93: YoY | F93: =Cash_Flow_Qtr!F85 -> 0.23225806 | G93: =Cash_Flow_Qtr!G85 -> 0.1978022 | H93: =Cash_Flow_Qtr!H85 -> 0.1978022 | I93: =Cash_Flow_Qtr!I85 -> 0.1978022 | J93: =Cash_Flow_Qtr!J85 -> 0.30275229 | K93: =Cash_Flow_Qtr!K85 -> 0.22774869 | L93: =Cash_Flow_Qtr!L85 -> 0.30275229 | M93: =Cash_Flow_Qtr!M85 -> 0.30275229 | ... BB93: =Cash_Flow_Qtr!BB85 -> NM | BC93: =Cash_Flow_Qtr!BM85 -> 0 | BD93: =Cash_Flow_Qtr!BN85 -> 0 | BE93: =Cash_Flow_Qtr!BE85 -> NM | BF93: =Cash_Flow_Qtr!BF85 -> NM | BG93: =Cash_Flow_Qtr!BG85 -> NM | BH93: =Cash_Flow_Qtr!BR85 -> 0 | BI93: =Cash_Flow_Qtr!BS85 -> 0
A95: Financial Metrics
A96: Depreciation & Amortization | B96: =Cash_Flow_Qtr!B5 -> 459 | C96: =Cash_Flow_Qtr!C5 -> 453 | D96: =Cash_Flow_Qtr!D5 -> 437 | E96: =Cash_Flow_Qtr!E5 -> 484 | F96: =Cash_Flow_Qtr!F5 -> 1833 | G96: =Cash_Flow_Qtr!G5 -> 443 | H96: =Cash_Flow_Qtr!H5 -> 447 | I96: =Cash_Flow_Qtr!I5 -> 474 | ... BI96: =Cash_Flow_Qtr!BI5 -> 2073.735
A97: EBITDA | B97: =B34+B96 -> 2478 | C97: =C34+C96 -> 2136 | D97: =D34+D96 -> 3017 | E97: =F97-SUM(B97:D97) -> 1645 | F97: =F34+F96 -> 9276 | G97: =G34+G96 -> 2231 | H97: =H34+H96 -> 28 | I97: =I34+I96 -> 2756 | J97: =K97-SUM(G97:I97) -> 2729 | K97: =K34+K96 -> 7744 | L97: =L34+L96 -> 2674 | M97: =M34+M96 -> 3018 | N97: =N34+N96 -> 3144 | O97: =P97-SUM(L97:N97) -> 3555 | P97: =P34+P96 -> 12391 | Q97: =Q34+Q96 -> 3376 | R97: =R34+R96 -> 3217 | S97: =S34+S96 -> 2750 | T97: =U97-SUM(Q97:S97) -> 4758 | U97: =U34+U96 -> 14101 | V97: =V34+V96 -> 2871 | W97: =W34+W96 -> -2834 | X97: =X34+X96 -> 1835 | Y97: =Z97-SUM(V97:X97) -> -1576 | Z97: =Z34+Z96 -> 296 | AA97: =AA34+AA96 -> -797 | AB97: =AB34+AB96 -> -2417 | AC97: =AC34+AC96 -> 164 | AD97: =AE97-SUM(AA97:AC97) -> -7471 | AE97: =AE34+AE96 -> -10521 | AF97: =AF34+AF96 -> 453 | AG97: =AG34+AG96 -> 1574 | AH97: =AH34+AH96 -> 852 | AI97: =AJ97-SUM(AF97:AH97) -> -3637 | AJ97: =AJ34+AJ96 -> -758 | AK97: =AK34+AK96 -> -683 | AL97: =AL34+AL96 -> 1272 | AM97: =AM34+AM96 -> -2306 | AN97: =AO97-SUM(AK97:AM97) -> 149 | AO97: =AO34+AO96 -> -1568 | AP97: =AP34+AP96 -> 308 | AQ97: =AQ34+AQ96 -> 357 | AR97: =AR34+AR96 -> -341 | AS97: =AT97-SUM(AP97:AR97) -> 764 | AT97: =AT34+AT96 -> 1088 | AU97: =AU34+AU96 -> 356 | AV97: =AV34+AV96 -> -649 | AW97: =AW34+AW96 -> -5317 | AX97: =AY97-SUM(AU97:AW97) -> -3261 | AY97: =AY34+AY96 -> -8871 | AZ97: =AZ34+AZ96 -> 927 | BA97: =BA34+BA96 -> 284 | BB97: =BB34+BB96 -> -4290 | BC97: =BC34+BC96 -> 9313 | BD97: =BD34+BD96 -> 6234 | BE97: =BE34+BE96 -> 698.76193 | BF97: =BF34+BF96 -> 1015.996 | ... BI97: =BI34+BI96 -> 4185.7288
A98: EBITDA Margin | B98: =B97/B10 -> 0.11187864 | C98: =C97/C10 -> 0.087030925 | D98: =D97/D10 -> 0.11671631 | E98: =E97/E10 -> 0.069783227 | F98: =F97/F10 -> 0.096510394 | G98: =G97/G10 -> 0.098577236 | H98: =H97/H10 -> 0.0011310846 | I98: =I97/I10 -> 0.11532346 | ... BD98: =BD97/BD10 -> 0.069682439 | BE98: =BE97/BE11 -> 2587.479 | BF98: =BF97/BF11 -> 10364.551 | BG98: =BG97/BG11 -> 16033.537 | BH98: =BH97/BH10 -> 0.049468571 | BI98: =BI97/BI10 -> 0.041976931
A100: Total Cost of Sales | B100: =-16380-2100 -> -18480 | C100: =-19247-2086 -> -21333 | D100: =-19393-2191 -> -21584 | E100: =F100-SUM(B100:D100) -> -20627 | F100: =-73446-8578 -> -82024 | G100: =-16945-2136 -> -19081 | H100: =-20265-2044 -> -22309 | I100: =-17907-1983 -> -19890 | J100: =K100-SUM(G100:I100) -> -19451 | K100: =-72713-8018 -> -80731 | L100: =-16062-1998 -> -18060 | M100: =-16824-1865 -> -18689 | N100: =-18050-1879 -> -19929 | O100: =P100-SUM(L100:N100) -> -19864 | P100: =-68879-7663 -> -76542 | Q100: =-16816-1992 -> -18808 | R100: =-17436-2083 -> -19519 | S100: =-18882-2140 -> -21022 | T100: =U100-SUM(Q100:S100) -> -22072 | U100: =-72922-8499 -> -81421 | V100: =-16238-2389 -> -18627 | W100: =-15672-2122 -> -17794 | X100: =-14674-2241 -> -16915 | Y100: =Z100-SUM(V100:X100) -> -18695 | Z100: =-62877-9154 -> -72031 | AA100: =-14713-2043 -> -16756 | AB100: =-10378-2589 -> -12967 | AC100: =-10910-2185 -> -13095 | AD100: =-10910-2185 -> -13095 | AE100: =SUM(AA100:AD100) -> -55913 | AF100: =-11632-2167 -> -13799 | AG100: =-12263-2316 -> -14579 | AH100: =-11271-2288 -> -13559 | AI100: =-14788-2512 -> -17300 | AJ100: =SUM(AF100:AI100) -> -59237 | AK100: =-11412-2226 -> -13638 | AL100: =-12284-2269 -> -14553 | AM100: =-14541-2230 -> -16771 | AN100: =-15732-2384 -> -18116 | AO100: =SUM(AK100:AN100) -> -63078 | AP100: =-14914-3007 -> -17921 | AQ100: =-15123-2689 -> -17812 | AR100: =-(14464+2475) -> -16939 | AS100: =-16724-2597 -> -19321 | AT100: =SUM(AP100:AS100) -> -71993 | AU100: =-12064-2629 -> -14693 | AV100: =-12907-2730 -> -15637 | AW100: =-18413-2934 -> -21347 | AX100: =-14010-2821 -> -16831 | AY100: =SUM(AU100:AX100) -> -68508 | AZ100: =-14379-2700 -> -17079 | BA100: =-17406-2908 -> -20314 | BB100: =-22737-2908 -> -25645 | BC100: -22136 | BD100: =SUM(AZ100:BC100) -> -85174 | BE100: =-BE10*(1-BE106) -> -20427.82 | BF100: =-BF10*(1-BF106) -> -20607.67 | BG100: =-BG10*(1-BG106) -> -20681.095 | BH100: =-BH10*(1-BH106) -> -20548.27 | BI100: =SUM(BE100:BH100) -> -82264.857
A101: Boeing Capital Interest Expense | B101: -16 | C101: -17 | D101: -16 | E101: =F101-SUM(B101:D101) -> -15 | F101: -64 | G101: -16 | H101: -16 | I101: -14 | J101: =K101-SUM(G101:I101) -> -13 | K101: -59 | L101: -13 | M101: -13 | N101: -27 | O101: =P101-SUM(L101:N101) -> -17 | P101: -70 | Q101: -16 | R101: -17 | S101: -18 | T101: =U101-SUM(Q101:S101) -> -18 | U101: -69 | V101: -18 | W101: -16 | X101: -15 | Y101: =Z101-SUM(V101:X101) -> -13 | Z101: -62 | AA101: -12 | AB101: -11 | AC101: -10 | AD101: -10 | AE101: =SUM(AA101:AD101) -> -43 | AF101: -9 | AG101: -9 | AH101: -7 | AI101: -7 | AJ101: =SUM(AF101:AI101) -> -32 | AK101: -7 | AL101: -6 | AM101: -7 | AN101: -8 | AO101: =SUM(AK101:AN101) -> -28 | AP101: 0 | AQ101: 0 | AT101: =SUM(AP101:AS101) -> 0 | AU101: 0 | AV101: 0 | AW101: 0 | AY101: =SUM(AU101:AX101) -> 0 | AZ101: 0 | BA101: 0 | BB101: 0 | BC101: 0 | BD101: =SUM(AZ101:BC101) -> 0 | BE101: 0 | BF101: 0 | BG101: 0 | BH101: =BI101-SUM(BE101:BG101) -> 0 | BI101: 0
A102: Operating Expenses | B102: =+B100+B101 -> -18496 | C102: =+C100+C101 -> -21350 | D102: =+D100+D101 -> -21600 | E102: =F102-SUM(B102:D102) -> -20642 | F102: =+F100+F101 -> -82088 | G102: =+G100+G101 -> -19097 | H102: =+H100+H101 -> -22325 | I102: =+I100+I101 -> -19904 | J102: =K102-SUM(G102:I102) -> -19464 | K102: =+K100+K101 -> -80790 | L102: =+L100+L101 -> -18073 | M102: =+M100+M101 -> -18702 | N102: =+N100+N101 -> -19956 | O102: =P102-SUM(L102:N102) -> -19881 | P102: =+P100+P101 -> -76612 | Q102: =+Q100+Q101 -> -18824 | R102: =+R100+R101 -> -19536 | S102: =+S100+S101 -> -21040 | T102: =U102-SUM(Q102:S102) -> -22090 | U102: =+U100+U101 -> -81490 | V102: =+V100+V101 -> -18645 | W102: =+W100+W101 -> -17810 | X102: =+X100+X101 -> -16930 | Y102: =Z102-SUM(V102:X102) -> -18708 | Z102: =+Z100+Z101 -> -72093 | AA102: =+AA100+AA101 -> -16768 | AB102: =+AB100+AB101 -> -12978 | AC102: =+AC100+AC101 -> -13105 | AD102: =AE102-SUM(AA102:AC102) -> -13105 | AE102: =+AE100+AE101 -> -55956 | AF102: =+AF100+AF101 -> -13808 | AG102: =+AG100+AG101 -> -14588 | AH102: =+AH100+AH101 -> -13566 | AI102: =AJ102-SUM(AF102:AH102) -> -17307 | AJ102: =+AJ100+AJ101 -> -59269 | AK102: =+AK100+AK101 -> -13645 | AL102: =+AL100+AL101 -> -14559 | AM102: =+AM100+AM101 -> -16778 | AN102: =AO102-SUM(AK102:AM102) -> -18124 | AO102: =+AO100+AO101 -> -63106 | AP102: =+AP100+AP101 -> -17921 | AQ102: =+AQ100+AQ101 -> -17812 | AR102: =+AR100+AR101 -> -16939 | AS102: =AT102-SUM(AP102:AR102) -> -19321 | AT102: =+AT100+AT101 -> -71993 | AU102: =+AU100+AU101 -> -14693 | AV102: =+AV100+AV101 -> -15637 | AW102: =+AW100+AW101 -> -21347 | AX102: =AY102-SUM(AU102:AW102) -> -16831 | AY102: =+AY100+AY101 -> -68508 | AZ102: =+AZ100+AZ101 -> -17079 | BA102: =+BA100+BA101 -> -20314 | BB102: =+BB100+BB101 -> -25645 | BC102: =+BC100+BC101 -> -22136 | BD102: =+BD100+BD101 -> -85174 | BE102: =+BE100+BE101 -> -20427.82 | BF102: =+BF100+BF101 -> -20607.67 | ... BI102: =+BI100+BI101 -> -82264.857
A103: YoY | F103: =F102/Income_Statement_Annual!P102-1 -> 0.069522618 | G103: =G102/B102-1 -> 0.032493512 | H103: =H102/C102-1 -> 0.045667447 | I103: =I102/D102-1 -> -0.078518519 | J103: =J102/E102-1 -> -0.057068114 | K103: =K102/F102-1 -> -0.015812299 | L103: =L102/G102-1 -> -0.053620988 | M103: =M102/H102-1 -> -0.16228443 | N103: =N102/I102-1 -> 0.0026125402 | ... BI103: =BI102/BD102-1 -> -0.034155294
A105: Gross Profit | B105: =B10+B100 -> 3669 | C105: =C10+C100 -> 3210 | D105: =D10+D100 -> 4265 | E105: =+F105-SUM(B105:D105) -> 2946 | F105: =F10+F100 -> 14090 | G105: =G10+G100 -> 3551 | H105: =H10+H100 -> 2446 | I105: =I10+I100 -> 4008 | J105: =+K105-SUM(G105:I105) -> 3835 | K105: =K10+K100 -> 13840 | L105: =L10+L100 -> 3901 | M105: =M10+M100 -> 4362 | N105: =N10+N100 -> 4294 | O105: =+P105-SUM(L105:N105) -> 4906 | P105: =P10+P100 -> 17463 | Q105: =Q10+Q100 -> 4574 | R105: =R10+R100 -> 4739 | S105: =S10+S100 -> 4124 | T105: =+U105-SUM(Q105:S105) -> 6269 | U105: =U10+U100 -> 19706 | V105: =V10+V100 -> 4290 | W105: =W10+W100 -> -2043 | X105: =X10+X100 -> 3065 | Y105: =+Z105-SUM(V105:X105) -> -784 | Z105: =Z10+Z100 -> 4528 | AA105: =AA10+AA100 -> 152 | AB105: =AB10+AB100 -> -1160 | AC105: =AC10+AC100 -> 1044 | AD105: =AD10+AD100 -> 2209 | AE105: =AE10+AE100 -> 2245 | AF105: =AF10+AF100 -> 1418 | AG105: =AG10+AG100 -> 2419 | ... BB105: =BB10+BB100 -> -2375 | BC105: =BD105-SUM(AZ105:BB105) -> 1812 | BD105: =BD10+BD100 -> 4289 | BE105: =BE10*BE106 -> 4333.174 | BF105: =BF10*BF106 -> 4371.324 | BG105: =BG10*BG106 -> 4386.899 | BH105: =BI105-SUM(BE105:BG105) -> 4358.724 | BI105: =BI10*BI106 -> 17450.121
A106: Gross Margin | B106: =B105/B10 -> 0.16565082 | C106: =C105/C10 -> 0.13079086 | D106: =D105/D10 -> 0.16499671 | E106: =E105/E10 -> 0.12497349 | F106: =F105/F10 -> 0.14659675 | G106: =G105/G10 -> 0.15690173 | H106: =H105/H10 -> 0.098808322 | I106: =I105/I10 -> 0.16771278 | ... BD106: =BD105/BD10 -> 0.047941607 | BE106: =$BI106 -> 0.175 | BF106: =$BI106 -> 0.175 | BG106: =$BI106 -> 0.175 | BH106: =BH105/BH10 -> 0.175 | BI106: 0.175
A108: Research and Development Expense, net
A109: Commercial Airplanes | B109: =BCA_Qtr!B6 -> 0 | C109: =BCA_Qtr!C6 -> 0 | D109: =BCA_Qtr!D6 -> 0 | E109: =BCA_Qtr!E6 -> 0 | F109: =BCA_Qtr!F6 -> 0 | G109: =BCA_Qtr!G6 -> 659 | H109: =BCA_Qtr!H6 -> 1860 | I109: =BCA_Qtr!I6 -> 633 | ... BI109: =BCA_Qtr!BI6 -> 2422.2
A110: Defense, Space & Security | B110: =BDS_Qtr!B6 -> 0 | C110: =BDS_Qtr!C6 -> 0 | D110: =BDS_Qtr!D6 -> 0 | E110: =BDS_Qtr!E6 -> 0 | F110: =BDS_Qtr!F6 -> 0 | G110: =BDS_Qtr!G6 -> 232 | H110: =BDS_Qtr!H6 -> 233 | I110: =BDS_Qtr!I6 -> 201 | ... BI110: =BDS_Qtr!BI6 -> 903.31
A111: Global Services | B111: =BGS_Qtr!B6 -> 0 | C111: =BGS_Qtr!C6 -> 0 | D111: =BGS_Qtr!D6 -> 0 | E111: =BGS_Qtr!E6 -> 0 | F111: =BGS_Qtr!F6 -> 0 | G111: =BGS_Qtr!G6 -> 38 | H111: =BGS_Qtr!H6 -> 47 | I111: =BGS_Qtr!I6 -> 41 | ... P111: =BGS_Qtr!P6 -> 140 | Q111: 34 | R111: =BGS_Qtr!R6 -> 37 | S111: =BGS_Qtr!S6 -> 48 | T111: =BGS_Qtr!T6 -> 42 | U111: =BGS_Qtr!U6 -> 161 | V111: =BGS_Qtr!V6 -> 40 | W111: =BGS_Qtr!W6 -> 33 | X111: =BGS_Qtr!X6 -> 29 | Y111: =BGS_Qtr!Y6 -> 19 | ... BI111: =BGS_Qtr!BI6 -> 127.5
A112: Commercial Airplanes (Old) | B112: 543 | C112: 554 | D112: 616 | E112: 627 | F112: 2340 | G112: 0 | H112: 0 | I112: 0 | J112: =K112-SUM(G112:I112) -> 0 | K112: 0 | L112: 0 | M112: 0 | N112: 0 | O112: =P112-SUM(L112:N112) -> 0 | P112: 0 | Q112: 0 | R112: 0 | S112: 0 | T112: =U112-SUM(Q112:S112) -> 0 | U112: 0 | V112: 0 | W112: 0 | X112: 0 | Y112: =Z112-SUM(V112:X112) -> 0 | Z112: 0 | AA112: 0 | AB112: 0 | AC112: 0 | AD112: 0 | AE112: =SUM(AA112:AD112) -> 0 | AF112: 0 | AG112: 0 | AH112: 0 | AI112: 0 | AJ112: =SUM(AF112:AI112) -> 0 | AK112: 0 | AL112: 0 | AM112: 0 | AN112: 0 | AO112: =SUM(AK112:AN112) -> 0 | AP112: 0 | AQ112: 0 | AR112: 0 | AS112: 0 | AT112: =SUM(AP112:AS112) -> 0 | AU112: 0 | AV112: 0 | AW112: 0 | AX112: 0 | AY112: =SUM(AU112:AX112) -> 0 | AZ112: 0 | BA112: 0 | BB112: 0 | BC112: =BD112-SUM(AZ112:BB112) -> 0 | BD112: 0 | BE112: 0 | BF112: 0 | BG112: 0 | BH112: =BI112-SUM(BE112:BG112) -> 0 | BI112: 0
A113: Defense, Space & Security (Old) | B113: 224 | C113: 250 | D113: 241 | E113: 271 | F113: 986 | G113: 0 | H113: 0 | I113: 0 | J113: =K113-SUM(G113:I113) -> 0 | K113: 0 | L113: 0 | M113: 0 | N113: 0 | O113: =P113-SUM(L113:N113) -> 0 | P113: 0 | Q113: 0 | R113: 0 | S113: 0 | T113: =U113-SUM(Q113:S113) -> 0 | U113: 0 | V113: 0 | W113: 0 | X113: 0 | Y113: =Z113-SUM(V113:X113) -> 0 | Z113: 0 | AA113: 0 | AB113: 0 | AC113: 0 | AD113: 0 | AE113: =SUM(AA113:AD113) -> 0 | AF113: 0 | AG113: 0 | AH113: 0 | AI113: 0 | AJ113: =SUM(AF113:AI113) -> 0 | AK113: 0 | AL113: 0 | AM113: 0 | AN113: 0 | AO113: =SUM(AK113:AN113) -> 0 | AP113: 0 | AQ113: 0 | AR113: 0 | AS113: 0 | AT113: =SUM(AP113:AS113) -> 0 | AU113: 0 | AV113: 0 | AW113: 0 | AX113: 0 | AY113: =SUM(AU113:AX113) -> 0 | AZ113: 0 | BA113: 0 | BB113: 0 | BC113: =BD113-SUM(AZ113:BB113) -> 0 | BD113: 0 | BE113: 0 | BF113: 0 | BG113: 0 | BH113: =BI113-SUM(BE113:BG113) -> 0 | BI113: 0
A114: Other | B114: 2 | C114: -4 | D114: 0 | E114: =F114-SUM(B114:D114) -> 7 | F114: 5 | G114: -12 | H114: -13 | I114: -18 | J114: =K114-SUM(G114:I114) -> -4 | K114: -47 | L114: -13 | M114: -10 | N114: -15 | O114: =P114-SUM(L114:N114) -> -4 | P114: -42 | Q114: -2 | R114: 21 | S114: 50 | T114: =U114-SUM(Q114:S114) -> 63 | U114: 132 | V114: 78 | W114: 99 | X114: 97 | Y114: =Z114-SUM(V114:X114) -> 110 | Z114: 384 | AA114: 54 | AB114: 62 | AC114: 44 | AD114: 80 | AE114: =SUM(AA114:AD114) -> 240 | AF114: 42 | AG114: 43 | AH114: 59 | AI114: =80-40 -> 40 | AJ114: =SUM(AF114:AI114) -> 184 | AK114: 52 | AL114: 66 | AM114: 43 | AN114: 117 | AO114: =SUM(AK114:AN114) -> 278 | AP114: 76 | AQ114: 73 | AR114: 73 | AS114: 93 | AT114: =SUM(AP114:AS114) -> 315 | AU114: 89 | AV114: 99 | AW114: 105 | AX114: 84 | AY114: =SUM(AU114:AX114) -> 377 | AZ114: 82 | BA114: 101 | BB114: 102 | BC114: 126 | BD114: =SUM(AZ114:BC114) -> 411 | BE114: =$BI114/4 -> 79.023789 | BF114: =$BI114/4 -> 79.023789 | BG114: =$BI114/4 -> 79.023789 | BH114: =BI114-SUM(BE114:BG114) -> 79.023789 | BI114: 316.09516
A115: Total R&D Expense | B115: =SUM(B109:B114) -> 769 | C115: =SUM(C109:C114) -> 800 | D115: =SUM(D109:D114) -> 857 | E115: =SUM(E109:E114) -> 905 | F115: =SUM(F109:F114) -> 3331 | G115: =SUM(G109:G114) -> 917 | H115: =SUM(H109:H114) -> 2127 | I115: =SUM(I109:I114) -> 857 | ... BI115: =SUM(BI109:BI114) -> 3769.1052 | BJ115: 3.4bn
A117: Non-Recurring Charges
A118: Operating Profit (GAAP) | B118: =B34 -> 2019 | C118: =C34 -> 1683 | D118: =D34 -> 2580 | E118: =E34 -> 1161 | F118: =F34 -> 7443 | G118: =G34 -> 1788 | H118: =H34 -> -419 | I118: =I34 -> 2282 | ... AZ118: =AZ34 -> 461 | BA118: =BA35 -> -0.0077366038 | BB118: =BB34 -> -4781 | BC118: =BC34 -> 8777 | BD118: =BD34 -> 4281 | BE118: =BE35 -> 0.007282752 | BF118: =BF35 -> 0.019258062 | BG118: =BG35 -> 0.027431443 | BH118: =BH34 -> 762.96728 | BI118: =BI34 -> 2111.9938
A119: Pension FAS/CAS Service Cost Adjustment | B119: 152 | C119: 57 | D119: 84 | E119: =+F119-SUM(B119:D119) -> 128 | F119: 421 | G119: -45 | H119: -34 | I119: -50 | J119: =+K119-SUM(G119:I119) -> -88 | K119: -217 | L119: -262 | M119: -278 | N119: -271 | O119: =+P119-SUM(L119:N119) -> -316 | P119: =-1127 -> -1127 | Q119: -283 | R119: -237 | S119: -260 | T119: =+U119-SUM(Q119:S119) -> -225 | U119: -1005 | V119: -274 | W119: -275 | X119: -274 | Y119: =+Z119-SUM(V119:X119) -> -248 | Z119: -1071 | AA119: -255 | AB119: -258 | AC119: -260 | AD119: -251 | AE119: =SUM(AA119:AD119) -> -1024 | AF119: =-AF22 -> -193 | AG119: =-AG22 -> -191 | AH119: =-AH22 -> -192 | AI119: -306 | AJ119: =SUM(AF119:AI119) -> -882 | AK119: =-AK22 -> -208 | AL119: =-AL22 -> -205 | AM119: =-AM22 -> -208 | AN119: -228 | AO119: =SUM(AK119:AN119) -> -849 | AP119: =-AP22 -> -223 | AQ119: =-AQ22 -> -222 | AR119: =-AR22 -> -218 | AS119: -136 | AT119: =SUM(AP119:AS119) -> -799 | AU119: =-AU22 -> -230 | AV119: =-AV22 -> -230 | AW119: =-AW22 -> -148 | AX119: -203 | AY119: =SUM(AU119:AX119) -> -811 | AZ119: =-AZ22 -> -193 | BA119: =-BA22 -> -197 | BB119: =-BB22 -> -198 | BC119: =-BC22 -> -196 | BD119: =SUM(AZ119:BC119) -> -784 | BE119: =-BE22 -> -212.5 | BF119: =-BF22 -> -212.5 | BG119: =-BG22 -> -212.5 | BH119: =-BH22 -> -212.5 | BI119: =SUM(BE119:BH119) -> -850
A120: Postretirement FAS/CAS Service Cost Adjustment | B120: -39 | C120: -27 | D120: -27 | E120: =+F120-SUM(B120:D120) -> -30 | F120: -123 | G120: -49 | H120: -35 | I120: -38 | J120: =+K120-SUM(G120:I120) -> -31 | K120: -153 | L120: -84 | M120: -79 | N120: -75 | O120: =+P120-SUM(L120:N120) -> -73 | P120: -311 | Q120: -82 | R120: -80 | S120: -77 | T120: =+U120-SUM(Q120:S120) -> -83 | U120: -322 | V120: -90 | W120: -90 | X120: -90 | Y120: =+Z120-SUM(V120:X120) -> -74 | Z120: -344 | AA120: -92 | AB120: -97 | AC120: -93 | AD120: -77 | AE120: =SUM(AA120:AD120) -> -359 | AF120: =-AF23 -> -77 | AG120: =-AG23 -> -77 | AH120: =-AH23 -> -78 | AI120: -59 | AJ120: =SUM(AF120:AI120) -> -291 | AK120: =-AK23 -> -75 | AL120: =-AL23 -> -79 | AM120: =-AM23 -> -71 | AN120: -69 | AO120: =SUM(AK120:AN120) -> -294 | AP120: =-AP23 -> -68 | AQ120: =-AQ23 -> -69 | AR120: =-AR23 -> -63 | AS120: -57 | AT120: =SUM(AP120:AS120) -> -257 | AU120: =-AU23 -> -72 | AV120: =-AV23 -> -72 | AW120: =-AW23 -> -80 | AX120: -69 | AY120: =SUM(AU120:AX120) -> -293 | AZ120: =-AZ23 -> -69 | BA120: =-BA23 -> -60 | BB120: =-BB23 -> -70 | BC120: =-BC23 -> -62 | BD120: =SUM(AZ120:BC120) -> -261 | BE120: =-BE23 -> -65 | BF120: =-BF23 -> -65 | BG120: =-BG23 -> -65 | BH120: =-BH23 -> -65 | BI120: =SUM(BE120:BH120) -> -260
A121: Core Operating Profit (Incl. Others) | B121: =B118+B119+B120 -> 2132 | C121: =C118+C119+C120 -> 1713 | D121: =D118+D119+D120 -> 2637 | E121: =E118+E119+E120 -> 1259 | F121: =F118+F119+F120 -> 7741 | G121: =G118+G119+G120 -> 1694 | H121: =H118+H119+H120 -> -488 | I121: =I118+I119+I120 -> 2194 | ... BI121: =BI118+BI119+BI120 -> 1001.9938
A122: Other | B122: 0 | C122: 0 | D122: 0 | E122: =+F122-SUM(B122:D122) -> 0 | F122: 0 | G122: 0 | H122: 0 | I122: 0 | J122: =+K122-SUM(G122:I122) -> 0 | K122: 0 | L122: 0 | M122: 0 | N122: 0 | O122: =+P122-SUM(L122:N122) -> 0 | P122: 0 | Q122: 0 | R122: 0 | S122: 0 | T122: =+U122-SUM(Q122:S122) -> 0 | U122: 0 | V122: 0 | W122: 0 | X122: 0 | Y122: =+Z122-SUM(V122:X122) -> 0 | Z122: 0 | AA122: 0 | AB122: 0 | AC122: 0 | AD122: 0 | AE122: =SUM(AA122:AD122) -> 0 | AF122: 0 | AG122: 0 | AH122: 0 | AI122: 0 | AJ122: =SUM(AF122:AI122) -> 0 | AK122: 0 | AL122: 0 | AM122: 0 | AN122: 0 | AO122: =SUM(AK122:AN122) -> 0 | AP122: 0 | AQ122: 0 | AR122: 0 | AS122: 0 | AT122: =SUM(AP122:AS122) -> 0 | AU122: 0 | AV122: 0 | AW122: 0 | AX122: 0 | AY122: =SUM(AU122:AX122) -> 0 | AZ122: 0 | BA122: 0 | BB122: 0 | BC122: 0 | BD122: =SUM(AZ122:BC122) -> 0 | BE122: 0 | BF122: 0 | BG122: 0 | BH122: 0 | BI122: =SUM(BE122:BH122) -> 0
A123: Core Operating Profit (Excl. Pension) | B123: =B121+B122 -> 2132 | C123: =C121+C122 -> 1713 | D123: =D121+D122 -> 2637 | E123: =E121+E122 -> 1259 | F123: =F121+F122 -> 7741 | G123: =G121+G122 -> 1694 | H123: =H121+H122 -> -488 | I123: =I121+I122 -> 2194 | ... BI123: =BI121+BI122 -> 1001.9938
A125: Non-Operating Adjustments
...

Sheet Balance_Sheet_Annual
A1: Balance Sheet Annual
B2: =Income_Statement_Annual!B2 -> CY2000A | C2: =Income_Statement_Annual!C2 -> CY2001A | D2: =Income_Statement_Annual!D2 -> CY2002A | E2: =Income_Statement_Annual!E2 -> CY2003A | F2: =Income_Statement_Annual!F2 -> CY2004A | G2: =Income_Statement_Annual!G2 -> CY2005A | H2: =Income_Statement_Annual!H2 -> CY2006A | I2: =Income_Statement_Annual!I2 -> CY2007A | ... AF2: =Income_Statement_Annual!AF2 -> CY2030E
A3: =Balance_Sheet_Qtr!A3 -> Assets
A4: =Balance_Sheet_Qtr!A4 -> Current Assets
A5: =Balance_Sheet_Qtr!A5 -> Cash and Cash Equivalents | B5: 1010 | C5: 633 | D5: 2333 | E5: 4633 | F5: 3204 | G5: 5412 | H5: 6118 | I5: 7042 | J5: 3268 | K5: 9215 | L5: 5359 | M5: 10049 | N5: 10341 | O5: 9088 | P5: 11733 | Q5: =Balance_Sheet_Qtr!F5 -> 11302 | R5: =Balance_Sheet_Qtr!K5 -> 8801 | S5: =Balance_Sheet_Qtr!P5 -> 8813 | T5: =Balance_Sheet_Qtr!U5 -> 7637 | U5: =Balance_Sheet_Qtr!Z5 -> 9485 | V5: =Balance_Sheet_Qtr!AE5 -> 7752 | W5: =Balance_Sheet_Qtr!AJ5 -> 8052 | X5: =Balance_Sheet_Qtr!AO5 -> 14614 | Y5: =Balance_Sheet_Qtr!AT5 -> 12691 | Z5: =Balance_Sheet_Qtr!AY5 -> 13801 | AA5: =Balance_Sheet_Qtr!BD5 -> 10921 | AB5: =Balance_Sheet_Qtr!BI5 -> 8329.4025 | AC5: =Cash_Flow_Annual!AC64 -> 6992.4568 | AD5: =Cash_Flow_Annual!AD64 -> 15270.023 | AE5: =Cash_Flow_Annual!AE64 -> 25856.7 | AF5: =Cash_Flow_Annual!AF64 -> 38337.089
A6: =Balance_Sheet_Qtr!A6 -> Restricted Cash | B6: 0 | C6: 0 | D6: 0 | E6: 0 | F6: 0 | G6: 0 | H6: 0 | I6: 0 | J6: 0 | K6: 0 | L6: 0 | M6: 0 | N6: 0 | O6: 0 | P6: 0 | Q6: =Balance_Sheet_Qtr!F6 -> 0 | R6: =Balance_Sheet_Qtr!K6 -> 0 | S6: =Balance_Sheet_Qtr!P6 -> 74 | T6: =Balance_Sheet_Qtr!U6 -> 176 | U6: =Balance_Sheet_Qtr!Z6 -> 86 | V6: =Balance_Sheet_Qtr!AE6 -> 83 | W6: =Balance_Sheet_Qtr!AJ6 -> 52 | X6: =Balance_Sheet_Qtr!AO6 -> 33 | Y6: =Balance_Sheet_Qtr!AT6 -> 22 | Z6: =Balance_Sheet_Qtr!AY6 -> 21 | AA6: =Balance_Sheet_Qtr!BD6 -> 742 | AB6: =Balance_Sheet_Qtr!BI6 -> 709 | AC6: =Cash_Flow_Annual!AC63 -> 709 | AD6: =Cash_Flow_Annual!AD63 -> 709 | AE6: =Cash_Flow_Annual!AE63 -> 709 | AF6: =Cash_Flow_Annual!AF63 -> 709
A7: =Balance_Sheet_Qtr!A7 -> Short-Term and Other Investments | B7: 0 | C7: 0 | D7: 0 | E7: 0 | F7: 319 | G7: 554 | H7: 268 | I7: 2266 | J7: 11 | K7: 2008 | L7: 5158 | M7: 1223 | N7: 3217 | O7: 6170 | P7: 1359 | Q7: =Balance_Sheet_Qtr!F7 -> 750 | R7: =Balance_Sheet_Qtr!K7 -> 1228 | S7: =Balance_Sheet_Qtr!P7 -> 1105 | T7: =Balance_Sheet_Qtr!U7 -> 751 | U7: =Balance_Sheet_Qtr!Z7 -> 459 | V7: =Balance_Sheet_Qtr!AE7 -> 17755 | W7: =Balance_Sheet_Qtr!AJ7 -> 8140 | X7: =Balance_Sheet_Qtr!AO7 -> 2606 | Y7: =Balance_Sheet_Qtr!AT7 -> 3274 | Z7: =Balance_Sheet_Qtr!AY7 -> 12481 | AA7: =Balance_Sheet_Qtr!BD7 -> 18479 | AB7: =Balance_Sheet_Qtr!BI7 -> 18479 | AC7: =AB7 -> 18479 | AD7: =AC7 -> 18479 | AE7: =AD7 -> 18479 | AF7: =AE7 -> 18479
A8: =Balance_Sheet_Qtr!A8 -> Accounts Receivables, Net | B8: 4928 | C8: 5156 | D8: 5007 | E8: 4515 | F8: 4653 | G8: 5246 | H8: 5285 | I8: 5740 | J8: 5602 | K8: 5785 | L8: 5422 | M8: 5793 | N8: 5608 | O8: 6546 | P8: 7729 | Q8: =Balance_Sheet_Qtr!F8 -> 8713 | R8: =Balance_Sheet_Qtr!K8 -> 8832 | S8: =Balance_Sheet_Qtr!P8 -> 10516 | T8: =Balance_Sheet_Qtr!U8 -> 3879 | U8: =Balance_Sheet_Qtr!Z8 -> 3266 | V8: =Balance_Sheet_Qtr!AE8 -> 1955 | W8: =Balance_Sheet_Qtr!AJ8 -> 2641 | X8: =Balance_Sheet_Qtr!AO8 -> 2517 | Y8: =Balance_Sheet_Qtr!AT8 -> 2649 | Z8: =Balance_Sheet_Qtr!AY8 -> 2631 | AA8: =Balance_Sheet_Qtr!BD8 -> 2921 | AB8: =Balance_Sheet_Qtr!BI8 -> 2868.5131 | AC8: =AC$68*(Income_Statement_Annual!AC$10/(365)) -> 2969.2729 | AD8: =AD$68*(Income_Statement_Annual!AD$10/(365)) -> 3005.9976 | AE8: =AE$68*(Income_Statement_Annual!AE$10/(365)) -> 2963.0094 | AF8: =AF$68*(Income_Statement_Annual!AF$10/(365)) -> 2637.7029
A9: =Balance_Sheet_Qtr!A9 -> Unbilled Receivables, Net | B9: 0 | C9: 0 | D9: 0 | E9: 0 | F9: 0 | G9: 0 | H9: 0 | I9: 0 | J9: 0 | K9: 0 | L9: 0 | M9: 0 | N9: 0 | O9: 0 | P9: 0 | Q9: =Balance_Sheet_Qtr!F9 -> 0 | R9: =Balance_Sheet_Qtr!K9 -> 0 | S9: =Balance_Sheet_Qtr!P9 -> 0 | T9: =Balance_Sheet_Qtr!U9 -> 10025 | U9: =Balance_Sheet_Qtr!Z9 -> 9043 | V9: =Balance_Sheet_Qtr!AE9 -> 7995 | W9: =Balance_Sheet_Qtr!AJ9 -> 8620 | X9: =Balance_Sheet_Qtr!AO9 -> 8634 | Y9: =Balance_Sheet_Qtr!AT9 -> 8317 | Z9: =Balance_Sheet_Qtr!AY9 -> 8363 | AA9: =Balance_Sheet_Qtr!BD9 -> 9158 | AB9: =Balance_Sheet_Qtr!BI9 -> 8810.433 | AC9: =AC$69*(Income_Statement_Annual!AC$10/(365)) -> 9056.2825 | AD9: =AD$69*(Income_Statement_Annual!AD$10/(365)) -> 9175.4203 | AE9: =AE$69*(Income_Statement_Annual!AE$10/(365)) -> 9244.9741 | AF9: =AF$69*(Income_Statement_Annual!AF$10/(365)) -> 8572.5345
A10: =Balance_Sheet_Qtr!A10 -> Current Portion of Customer Financing, Net | B10: 995 | C10: 1053 | D10: 1289 | E10: 857 | F10: 616 | G10: 367 | H10: 370 | I10: 328 | J10: 425 | K10: 368 | L10: 285 | M10: 476 | N10: 364 | O10: 344 | P10: 190 | Q10: =Balance_Sheet_Qtr!F10 -> 212 | R10: =Balance_Sheet_Qtr!K10 -> 428 | S10: =Balance_Sheet_Qtr!P10 -> 309 | T10: =Balance_Sheet_Qtr!U10 -> 460 | U10: =Balance_Sheet_Qtr!Z10 -> 162 | V10: =Balance_Sheet_Qtr!AE10 -> 101 | W10: =Balance_Sheet_Qtr!AJ10 -> 117 | X10: =Balance_Sheet_Qtr!AO10 -> 154 | Y10: =Balance_Sheet_Qtr!AT10 -> 99 | Z10: =Balance_Sheet_Qtr!AY10 -> 207 | AA10: =Balance_Sheet_Qtr!BD10 -> 0 | AB10: =Balance_Sheet_Qtr!BI10 -> 0 | AC10: =AB10 -> 0 | AD10: =AC10 -> 0 | AE10: =AD10 -> 0 | AF10: =AE10 -> 0
A11: =Balance_Sheet_Qtr!A11 -> Deferred Income Taxes | B11: 2137 | C11: 2444 | D11: 2042 | E11: 1716 | F11: 1991 | G11: 2449 | H11: 2837 | I11: 2341 | J11: 1046 | K11: 966 | L11: 31 | M11: 29 | N11: 28 | O11: 14 | P11: 18 | Q11: =Balance_Sheet_Qtr!F11 -> 0 | R11: =Balance_Sheet_Qtr!K11 -> 0 | S11: =Balance_Sheet_Qtr!P11 -> 0 | T11: =Balance_Sheet_Qtr!U11 -> 0 | U11: =Balance_Sheet_Qtr!Z11 -> 0 | V11: =Balance_Sheet_Qtr!AE11 -> 0 | W11: =Balance_Sheet_Qtr!AJ11 -> 0 | X11: =Balance_Sheet_Qtr!AO11 -> 0 | Y11: =Balance_Sheet_Qtr!AT11 -> 0 | Z11: =Balance_Sheet_Qtr!AY11 -> 0 | AA11: =Balance_Sheet_Qtr!BD11 -> 0 | AB11: =Balance_Sheet_Qtr!BI11 -> 0 | AC11: =AB11 -> 0 | AD11: =AC11 -> 0 | AE11: =AD11 -> 0 | AF11: =AE11 -> 0
A12: =Balance_Sheet_Qtr!A12 -> Inventories | B12: 6794 | C12: 6920 | D12: 6184 | E12: 5338 | F12: 4247 | G12: 7940 | H12: 8105 | I12: 9563 | J12: 15612 | K12: 16933 | L12: 24317 | M12: 32240 | N12: 37751 | O12: 42912 | P12: 46756 | Q12: =Balance_Sheet_Qtr!F12 -> 47257 | R12: =Balance_Sheet_Qtr!K12 -> 43199 | S12: =Balance_Sheet_Qtr!P12 -> 44344 | T12: =Balance_Sheet_Qtr!U12 -> 62567 | U12: =Balance_Sheet_Qtr!Z12 -> 76622 | V12: =Balance_Sheet_Qtr!AE12 -> 81715 | W12: =Balance_Sheet_Qtr!AJ12 -> 78823 | X12: =Balance_Sheet_Qtr!AO12 -> 78151 | Y12: =Balance_Sheet_Qtr!AT12 -> 79741 | Z12: =Balance_Sheet_Qtr!AY12 -> 87550 | AA12: =Balance_Sheet_Qtr!BD12 -> 84679 | AB12: =Balance_Sheet_Qtr!BI12 -> 82768.25 | AC12: =Inventory!S124 -> 81858.25 | AD12: =Inventory!T124 -> 80198.25 | AE12: =Inventory!U124 -> 78538.25 | AF12: =Inventory!V124 -> 76878.25
A13: =Balance_Sheet_Qtr!A13 -> Assets of Discontinued Operations | B13: 0 | C13: 0 | D13: 0 | E13: 0 | F13: 70 | G13: 0 | H13: 0 | I13: 0 | J13: 0 | K13: 0 | L13: 0 | M13: 0 | N13: 0 | O13: 0 | P13: 0 | Q13: =Balance_Sheet_Qtr!F13 -> 0 | R13: =Balance_Sheet_Qtr!K13 -> 0 | S13: =Balance_Sheet_Qtr!P13 -> 0 | T13: =Balance_Sheet_Qtr!U13 -> 0 | U13: =Balance_Sheet_Qtr!Z13 -> 0 | V13: =Balance_Sheet_Qtr!AE13 -> 0 | W13: =Balance_Sheet_Qtr!AJ13 -> 0 | X13: =Balance_Sheet_Qtr!AO13 -> 0 | Y13: =Balance_Sheet_Qtr!AT13 -> 0 | Z13: =Balance_Sheet_Qtr!AY13 -> 0 | AA13: =Balance_Sheet_Qtr!BD13 -> 0 | AB13: =Balance_Sheet_Qtr!BI13 -> 0 | AC13: =AB13 -> 0 | AD13: =AC13 -> 0 | AE13: =AD13 -> 0 | AF13: =AE13 -> 0
A14: =Balance_Sheet_Qtr!A14 -> Other Current Assets | B14: 0 | C14: 0 | D14: 0 | E14: 199 | F14: 0 | G14: 0 | H14: 0 | I14: 0 | J14: 0 | K14: 0 | L14: 0 | M14: 0 | N14: 0 | O14: 0 | P14: 0 | Q14: =Balance_Sheet_Qtr!F14 -> 0 | R14: =Balance_Sheet_Qtr!K14 -> 0 | S14: =Balance_Sheet_Qtr!P14 -> 0 | T14: =Balance_Sheet_Qtr!U14 -> 2335 | U14: =Balance_Sheet_Qtr!Z14 -> 3106 | V14: =Balance_Sheet_Qtr!AE14 -> 4286 | W14: =Balance_Sheet_Qtr!AJ14 -> 2221 | X14: =Balance_Sheet_Qtr!AO14 -> 2814 | Y14: =Balance_Sheet_Qtr!AT14 -> 2482 | Z14: =Balance_Sheet_Qtr!AY14 -> 2944 | AA14: =Balance_Sheet_Qtr!BD14 -> 1559 | AB14: =Balance_Sheet_Qtr!BI14 -> 1495.7247 | AC14: =AC75*Income_Statement_Annual!AC$10 -> 1625.6769 | AD14: =AD75*Income_Statement_Annual!AD$10 -> 1696.6842 | AE14: =AE75*Income_Statement_Annual!AE$10 -> 1755.6793 | AF14: =AF75*Income_Statement_Annual!AF$10 -> 1805.1779
A15: =Balance_Sheet_Qtr!A15 -> Total Current Assets | B15: =+SUM(B5:B14) -> 15864 | C15: =+SUM(C5:C14) -> 16206 | D15: =+SUM(D5:D14) -> 16855 | E15: =+SUM(E5:E14) -> 17258 | F15: =+SUM(F5:F14) -> 15100 | G15: =+SUM(G5:G14) -> 21968 | H15: =+SUM(H5:H14) -> 22983 | I15: =+SUM(I5:I14) -> 27280 | ... P15: =+SUM(P5:P14) -> 67785 | Q15: =Balance_Sheet_Qtr!F15 -> 68234 | R15: =Balance_Sheet_Qtr!K15 -> 62488 | S15: =Balance_Sheet_Qtr!P15 -> 65161 | T15: =Balance_Sheet_Qtr!U15 -> 87830 | U15: =Balance_Sheet_Qtr!Z15 -> 102229 | V15: =Balance_Sheet_Qtr!AE15 -> 121642 | W15: =Balance_Sheet_Qtr!AJ15 -> 108666 | X15: =Balance_Sheet_Qtr!AO15 -> 109523 | Y15: =Balance_Sheet_Qtr!AT15 -> 109275 | Z15: =Balance_Sheet_Qtr!AY15 -> 127998 | AA15: =Balance_Sheet_Qtr!BD15 -> 128459 | AB15: =Balance_Sheet_Qtr!BI15 -> 123460.32 | AC15: =+SUM(AC5:AC14) -> 121689.94 | AD15: =+SUM(AD5:AD14) -> 128534.37 | AE15: =+SUM(AE5:AE14) -> 137546.61 | AF15: =+SUM(AF5:AF14) -> 147418.75
A17: =Balance_Sheet_Qtr!A17 -> Noncurrent Assets
A18: =Balance_Sheet_Qtr!A18 -> Customer Financing, Net | B18: 5964 | C18: 9345 | D18: 10922 | E18: 12094 | F18: 10385 | G18: 9639 | H18: 8520 | I18: 6777 | J18: 5857 | K18: 5466 | L18: 4395 | M18: 4296 | N18: 4056 | O18: 3627 | P18: 3371 | Q18: =Balance_Sheet_Qtr!F18 -> 3358 | R18: =Balance_Sheet_Qtr!K18 -> 3773 | S18: =Balance_Sheet_Qtr!P18 -> 2740 | T18: =Balance_Sheet_Qtr!U18 -> 2418 | U18: =Balance_Sheet_Qtr!Z18 -> 2136 | V18: =Balance_Sheet_Qtr!AE18 -> 1936 | W18: =Balance_Sheet_Qtr!AJ18 -> 1695 | X18: =Balance_Sheet_Qtr!AO18 -> 1450 | Y18: =Balance_Sheet_Qtr!AT18 -> 860 | Z18: =Balance_Sheet_Qtr!AY18 -> 314 | AA18: =Balance_Sheet_Qtr!BD18 -> 241 | AB18: =Balance_Sheet_Qtr!BI18 -> 241 | AC18: =AB18 -> 241 | AD18: =AC18 -> 241 | AE18: =AD18 -> 241 | AF18: =AE18 -> 241
A19: =Balance_Sheet_Qtr!A19 -> Property, Plant and Equipment, Net | B19: 8814 | C19: 8459 | D19: 8765 | E19: 8432 | F19: 8443 | G19: 8420 | H19: 7675 | I19: 8265 | J19: 8762 | K19: 8784 | L19: 8931 | M19: 9313 | N19: 9660 | O19: 10224 | P19: 11007 | Q19: =Balance_Sheet_Qtr!F19 -> 12076 | R19: =Balance_Sheet_Qtr!K19 -> 12807 | S19: =Balance_Sheet_Qtr!P19 -> 12672 | T19: =Balance_Sheet_Qtr!U19 -> 12645 | U19: =Balance_Sheet_Qtr!Z19 -> 12502 | V19: =Balance_Sheet_Qtr!AE19 -> 11820 | W19: =Balance_Sheet_Qtr!AJ19 -> 10918 | X19: =Balance_Sheet_Qtr!AO19 -> 10550 | Y19: =Balance_Sheet_Qtr!AT19 -> 10661 | Z19: =Balance_Sheet_Qtr!AY19 -> 11412 | AA19: =Balance_Sheet_Qtr!BD19 -> 15361 | AB19: =Balance_Sheet_Qtr!BI19 -> 17345.665 | AC19: =AB19-Cash_Flow_Annual!AC68-Cash_Flow_Annual!AC71-Cash_Flow_Annual!AC33-Cash_Flow_Annual!AC34-Cash_Flow_Annual!AC11 -> 17769.675 | AD19: =AC19-Cash_Flow_Annual!AD68-Cash_Flow_Annual!AD71-Cash_Flow_Annual!AD33-Cash_Flow_Annual!AD34-Cash_Flow_Annual!AD11 -> 18266.587 | AE19: =AD19-Cash_Flow_Annual!AE68-Cash_Flow_Annual!AE71-Cash_Flow_Annual!AE33-Cash_Flow_Annual!AE34-Cash_Flow_Annual!AE11 -> 18800.491 | AF19: =AE19-Cash_Flow_Annual!AF68-Cash_Flow_Annual!AF71-Cash_Flow_Annual!AF33-Cash_Flow_Annual!AF34-Cash_Flow_Annual!AF11 -> 19346.367
A20: =Balance_Sheet_Qtr!A20 -> Goodwill | B20: 4189 | C20: 5666 | D20: 2760 | E20: 1913 | F20: 1948 | G20: 1924 | H20: 3047 | I20: 3081 | J20: 3647 | K20: 4319 | L20: 4937 | M20: 4945 | N20: 5035 | O20: 5043 | P20: 5119 | Q20: =Balance_Sheet_Qtr!F20 -> 5126 | R20: =Balance_Sheet_Qtr!K20 -> 5324 | S20: =Balance_Sheet_Qtr!P20 -> 5559 | T20: =Balance_Sheet_Qtr!U20 -> 7840 | U20: =Balance_Sheet_Qtr!Z20 -> 8060 | V20: =Balance_Sheet_Qtr!AE20 -> 8081 | W20: =Balance_Sheet_Qtr!AJ20 -> 8068 | X20: =Balance_Sheet_Qtr!AO20 -> 8057 | Y20: =Balance_Sheet_Qtr!AT20 -> 8093 | Z20: =Balance_Sheet_Qtr!AY20 -> 8084 | AA20: =Balance_Sheet_Qtr!BD20 -> 17275 | AB20: =Balance_Sheet_Qtr!BI20 -> 17275 | AC20: =AB20-Cash_Flow_Annual!AC35-Cash_Flow_Annual!AC36 -> 17275 | AD20: =AC20-Cash_Flow_Annual!AD35-Cash_Flow_Annual!AD36 -> 17275 | AE20: =AD20-Cash_Flow_Annual!AE35-Cash_Flow_Annual!AE36 -> 17275 | AF20: =AE20-Cash_Flow_Annual!AF35-Cash_Flow_Annual!AF36 -> 17275
A21: =Balance_Sheet_Qtr!A21 -> Acquired Intangible Assets, Net | B21: =1415-390 -> 1025 | C21: =1449-672 -> 777 | D21: 1128 | E21: 1035 | F21: 955 | G21: 875 | H21: 1698 | I21: 2093 | J21: 2685 | K21: 2877 | L21: 2979 | M21: 3044 | N21: 3111 | O21: 3052 | P21: 2869 | Q21: =Balance_Sheet_Qtr!F21 -> 2657 | R21: =Balance_Sheet_Qtr!K21 -> 2540 | S21: =Balance_Sheet_Qtr!P21 -> 2573 | T21: =Balance_Sheet_Qtr!U21 -> 3429 | U21: =Balance_Sheet_Qtr!Z21 -> 3338 | V21: =Balance_Sheet_Qtr!AE21 -> 2843 | W21: =Balance_Sheet_Qtr!AJ21 -> 2562 | X21: =Balance_Sheet_Qtr!AO21 -> 2311 | Y21: =Balance_Sheet_Qtr!AT21 -> 2094 | Z21: =Balance_Sheet_Qtr!AY21 -> 1957 | AA21: =Balance_Sheet_Qtr!BD21 -> 1567 | AB21: =Balance_Sheet_Qtr!BI21 -> 1567 | AC21: =AB21-Cash_Flow_Annual!AC70-Cash_Flow_Annual!AC39-Cash_Flow_Annual!AC46 -> 1567 | AD21: =AC21-Cash_Flow_Annual!AD70-Cash_Flow_Annual!AD39-Cash_Flow_Annual!AD46 -> 1567 | AE21: =AD21-Cash_Flow_Annual!AE70-Cash_Flow_Annual!AE39-Cash_Flow_Annual!AE46 -> 1567 | AF21: =AE21-Cash_Flow_Annual!AF70-Cash_Flow_Annual!AF39-Cash_Flow_Annual!AF46 -> 1567
A22: =Balance_Sheet_Qtr!A22 -> Deferred Income Taxes | B22: 60 | C22: 0 | D22: 2272 | E22: 1242 | F22: 154 | G22: 140 | H22: 1051 | I22: 197 | J22: 4114 | K22: 3062 | L22: 4031 | M22: 5892 | N22: 6753 | O22: 2939 | P22: 6576 | Q22: =Balance_Sheet_Qtr!F22 -> 265 | R22: =Balance_Sheet_Qtr!K22 -> 332 | S22: =Balance_Sheet_Qtr!P22 -> 341 | T22: =Balance_Sheet_Qtr!U22 -> 284 | U22: =Balance_Sheet_Qtr!Z22 -> 683 | V22: =Balance_Sheet_Qtr!AE22 -> 86 | W22: =Balance_Sheet_Qtr!AJ22 -> 77 | X22: =Balance_Sheet_Qtr!AO22 -> 63 | Y22: =Balance_Sheet_Qtr!AT22 -> 59 | Z22: =Balance_Sheet_Qtr!AY22 -> 185 | AA22: =Balance_Sheet_Qtr!BD22 -> 107 | AB22: =Balance_Sheet_Qtr!BI22 -> 107 | AC22: =AB22 -> 107 | AD22: =AC22 -> 107 | AE22: =AD22 -> 107 | AF22: =AE22 -> 107
A23: =Balance_Sheet_Qtr!A23 -> Investments | B23: 0 | C23: 0 | D23: 0 | E23: 0 | F23: 3050 | G23: 2852 | H23: 4085 | I23: 4111 | J23: 1328 | K23: 1030 | L23: 1111 | M23: 1043 | N23: 1180 | O23: 1204 | P23: 1154 | Q23: =Balance_Sheet_Qtr!F23 -> 1284 | R23: =Balance_Sheet_Qtr!K23 -> 1317 | S23: =Balance_Sheet_Qtr!P23 -> 1260 | T23: =Balance_Sheet_Qtr!U23 -> 1087 | U23: =Balance_Sheet_Qtr!Z23 -> 1092 | V23: =Balance_Sheet_Qtr!AE23 -> 1016 | W23: =Balance_Sheet_Qtr!AJ23 -> 975 | X23: =Balance_Sheet_Qtr!AO23 -> 983 | Y23: =Balance_Sheet_Qtr!AT23 -> 1035 | Z23: =Balance_Sheet_Qtr!AY23 -> 999 | AA23: =Balance_Sheet_Qtr!BD23 -> 1048 | AB23: =Balance_Sheet_Qtr!BI23 -> 1048 | AC23: =AB23 -> 1048 | AD23: =AC23 -> 1048 | AE23: =AD23 -> 1048 | AF23: =AE23 -> 1048
A24: =Balance_Sheet_Qtr!A24 -> Other Assets | B24: =1267+4845 -> 6112 | C24: =2052+5838 -> 7890 | D24: =2969+6671 -> 9640 | E24: =2519+8542 -> 11061 | F24: =1340+12588 -> 13928 | G24: =989+13251 -> 14240 | H24: 2735 | I24: =1258+5924 -> 7182 | J24: =1406+16 -> 1422 | K24: =1224+16 -> 1240 | L24: =1603+6 -> 1609 | M24: 1643 | N24: 1792 | O24: 1500 | P24: 1317 | Q24: =Balance_Sheet_Qtr!F24 -> 1408 | R24: =Balance_Sheet_Qtr!K24 -> 1416 | S24: =Balance_Sheet_Qtr!P24 -> 2027 | T24: =Balance_Sheet_Qtr!U24 -> 1826 | U24: =Balance_Sheet_Qtr!Z24 -> 3585 | V24: =Balance_Sheet_Qtr!AE24 -> 4712 | W24: =Balance_Sheet_Qtr!AJ24 -> 5591 | X24: =Balance_Sheet_Qtr!AO24 -> 4163 | Y24: =Balance_Sheet_Qtr!AT24 -> 4935 | Z24: =Balance_Sheet_Qtr!AY24 -> 5414 | AA24: =Balance_Sheet_Qtr!BD24 -> 4177 | AB24: =Balance_Sheet_Qtr!BI24 -> 4177 | AC24: =AB24 -> 4177 | AD24: =AC24 -> 4177 | AE24: =AD24 -> 4177 | AF24: =AE24 -> 4177
A25: =Balance_Sheet_Qtr!A25 -> Total Noncurrent Assets | B25: =SUM(B18:B24) -> 26164 | C25: =SUM(C18:C24) -> 32137 | D25: =SUM(D18:D24) -> 35487 | E25: =SUM(E18:E24) -> 35777 | F25: =SUM(F18:F24) -> 38863 | G25: =SUM(G18:G24) -> 38090 | H25: =SUM(H18:H24) -> 28811 | I25: =SUM(I18:I24) -> 31706 | ... P25: =SUM(P18:P24) -> 31413 | Q25: =Balance_Sheet_Qtr!F25 -> 26174 | R25: =Balance_Sheet_Qtr!K25 -> 27509 | S25: =Balance_Sheet_Qtr!P25 -> 27172 | T25: =Balance_Sheet_Qtr!U25 -> 29529 | U25: =Balance_Sheet_Qtr!Z25 -> 31396 | V25: =Balance_Sheet_Qtr!AE25 -> 30494 | W25: =Balance_Sheet_Qtr!AJ25 -> 29886 | X25: =Balance_Sheet_Qtr!AO25 -> 27577 | Y25: =Balance_Sheet_Qtr!AT25 -> 27737 | Z25: =Balance_Sheet_Qtr!AY25 -> 28365 | AA25: =Balance_Sheet_Qtr!BD25 -> 39776 | AB25: =Balance_Sheet_Qtr!BI25 -> 41760.665 | AC25: =SUM(AC18:AC24) -> 42184.675 | AD25: =SUM(AD18:AD24) -> 42681.587 | AE25: =SUM(AE18:AE24) -> 43215.491 | AF25: =SUM(AF18:AF24) -> 43761.367
A27: =Balance_Sheet_Qtr!A27 -> Total Assets | B27: =+B25+B15 -> 42028 | C27: =+C25+C15 -> 48343 | D27: =+D25+D15 -> 52342 | E27: =+E25+E15 -> 53035 | F27: =+F25+F15 -> 53963 | G27: =+G25+G15 -> 60058 | H27: =+H25+H15 -> 51794 | I27: =+I25+I15 -> 58986 | ... P27: =+P25+P15 -> 99198 | Q27: =Balance_Sheet_Qtr!F27 -> 94408 | R27: =Balance_Sheet_Qtr!K27 -> 89997 | S27: =Balance_Sheet_Qtr!P27 -> 92333 | T27: =Balance_Sheet_Qtr!U27 -> 117359 | U27: =Balance_Sheet_Qtr!Z27 -> 133625 | V27: =Balance_Sheet_Qtr!AE27 -> 152136 | W27: =Balance_Sheet_Qtr!AJ27 -> 138552 | X27: =Balance_Sheet_Qtr!AO27 -> 137100 | Y27: =Balance_Sheet_Qtr!AT27 -> 137012 | Z27: =Balance_Sheet_Qtr!AY27 -> 156363 | AA27: =Balance_Sheet_Qtr!BD27 -> 168235 | AB27: =Balance_Sheet_Qtr!BI27 -> 165220.99 | AC27: =+AC25+AC15 -> 163874.61 | AD27: =+AD25+AD15 -> 171215.96 | AE27: =+AE25+AE15 -> 180762.1 | AF27: =+AF25+AF15 -> 191180.12
A29: =Balance_Sheet_Qtr!A29 -> Liabilities
A30: =Balance_Sheet_Qtr!A30 -> Current Liabilities
A31: =Balance_Sheet_Qtr!A31 -> Accounts Payable | B31: 11979 | C31: 13872 | D31: 13739 | E31: 13563 | F31: 14869 | G31: 16513 | H31: 16201 | I31: 16676 | J31: 17587 | K31: 7096 | L31: 7715 | M31: 8406 | N31: 9394 | O31: 9498 | P31: 10667 | Q31: =Balance_Sheet_Qtr!F31 -> 10800 | R31: =Balance_Sheet_Qtr!K31 -> 11190 | S31: =Balance_Sheet_Qtr!P31 -> 12202 | T31: =Balance_Sheet_Qtr!U31 -> 12916 | U31: =Balance_Sheet_Qtr!Z31 -> 15553 | V31: =Balance_Sheet_Qtr!AE31 -> 12928 | W31: =Balance_Sheet_Qtr!AJ31 -> 9261 | X31: =Balance_Sheet_Qtr!AO31 -> 10200 | Y31: =Balance_Sheet_Qtr!AT31 -> 11964 | Z31: =Balance_Sheet_Qtr!AY31 -> 11364 | AA31: =Balance_Sheet_Qtr!BD31 -> 13109 | AB31: =Balance_Sheet_Qtr!BI31 -> 13522.99 | AC31: =AC70*(-Income_Statement_Annual!AC100/(365)) -> 13733.719 | AD31: =AD70*(-Income_Statement_Annual!AD100/(365)) -> 14026.279 | AE31: =AE70*(-Income_Statement_Annual!AE100/(365)) -> 14021.384 | AF31: =AF70*(-Income_Statement_Annual!AF100/(365)) -> 14854.636
A32: =Balance_Sheet_Qtr!A32 -> Accrued Liabilities | B32: 0 | C32: 0 | D32: 0 | E32: 0 | F32: 0 | G32: 0 | H32: 0 | I32: 0 | J32: 0 | K32: 12822 | L32: 13802 | M32: 12239 | N32: 12995 | O32: 14131 | P32: 13343 | Q32: =Balance_Sheet_Qtr!F32 -> 14014 | R32: =Balance_Sheet_Qtr!K32 -> 14691 | S32: =Balance_Sheet_Qtr!P32 -> 15292 | T32: =Balance_Sheet_Qtr!U32 -> 14808 | U32: =Balance_Sheet_Qtr!Z32 -> 22868 | V32: =Balance_Sheet_Qtr!AE32 -> 22171 | W32: =Balance_Sheet_Qtr!AJ32 -> 18455 | X32: =Balance_Sheet_Qtr!AO32 -> 21581 | Y32: =Balance_Sheet_Qtr!AT32 -> 22331 | Z32: =Balance_Sheet_Qtr!AY32 -> 24103 | AA32: =Balance_Sheet_Qtr!BD32 -> 27141 | AB32: =Balance_Sheet_Qtr!BI32 -> 25472 | AC32: =AB32-500-(((2600+700)*0.79)/3)-200 -> 23903 | AD32: =AC32-200-200 -> 23503 | AE32: =AD32-200-200 -> 23103 | AF32: =AE32-200-200 -> 22703
A33: =Balance_Sheet_Qtr!A33 -> Advances and Progress Billings | B33: 3517 | C33: 4306 | D33: 3123 | E33: 3464 | F33: 4123 | G33: 9930 | H33: 11449 | I33: 13847 | J33: 12737 | K33: 12076 | L33: 12323 | M33: 15496 | N33: 16672 | O33: 20027 | P33: 23175 | Q33: =Balance_Sheet_Qtr!F33 -> 24364 | R33: =Balance_Sheet_Qtr!K33 -> 23869 | S33: =Balance_Sheet_Qtr!P33 -> 27440 | T33: =Balance_Sheet_Qtr!U33 -> 50676 | U33: =Balance_Sheet_Qtr!Z33 -> 51551 | V33: =Balance_Sheet_Qtr!AE33 -> 50488 | W33: =Balance_Sheet_Qtr!AJ33 -> 52980 | X33: =Balance_Sheet_Qtr!AO33 -> 53081 | Y33: =Balance_Sheet_Qtr!AT33 -> 56328 | Z33: =Balance_Sheet_Qtr!AY33 -> 60333 | AA33: =Balance_Sheet_Qtr!BD33 -> 59404 | AB33: =Balance_Sheet_Qtr!BI33 -> 59214.937 | AC33: ='Customer Advances'!S61 -> 59244.245 | AD33: ='Customer Advances'!T61 -> 59558.963 | AE33: ='Customer Advances'!U61 -> 60083.373 | AF33: ='Customer Advances'!V61 -> 60277.663
A34: =Balance_Sheet_Qtr!A34 -> Short-Term Debt and Current Portion of Long-Term Debt | B34: 1232 | C34: 1399 | D34: 1814 | E34: 1144 | F34: 1321 | G34: 1189 | H34: 1381 | I34: 762 | J34: 560 | K34: 707 | L34: 948 | M34: 2353 | N34: 1436 | O34: 1563 | P34: 929 | Q34: =Balance_Sheet_Qtr!F34 -> 1234 | R34: =Balance_Sheet_Qtr!K34 -> 384 | S34: =Balance_Sheet_Qtr!P34 -> 1335 | T34: =Balance_Sheet_Qtr!U34 -> 3190 | U34: =Balance_Sheet_Qtr!Z34 -> 7340 | V34: =Balance_Sheet_Qtr!AE34 -> 1693 | W34: =Balance_Sheet_Qtr!AJ34 -> 1296 | X34: =Balance_Sheet_Qtr!AO34 -> 5190 | Y34: =Balance_Sheet_Qtr!AT34 -> 5204 | Z34: =Balance_Sheet_Qtr!AY34 -> 1278 | AA34: =Balance_Sheet_Qtr!BD34 -> 8461 | AB34: =Balance_Sheet_Qtr!BI34 -> 1300 | AC34: =Debt_Annual!AC67 -> 1300 | AD34: =Debt_Annual!AD67 -> 1300 | AE34: =Debt_Annual!AE67 -> 1300 | AF34: =Debt_Annual!AF67 -> 1300
A35: =Balance_Sheet_Qtr!A35 -> Deferred Income Taxes and Income Taxes Payable | B35: 1561 | C35: 909 | D35: 1134 | E35: 277 | F35: 522 | G35: 556 | H35: 670 | I35: 253 | J35: 41 | K35: 182 | L35: 607 | M35: 2780 | N35: 4485 | O35: 6267 | P35: 8603 | Q35: =Balance_Sheet_Qtr!F35 -> 0 | R35: =Balance_Sheet_Qtr!K35 -> 0 | S35: =Balance_Sheet_Qtr!P35 -> 0 | T35: =Balance_Sheet_Qtr!U35 -> 0 | U35: =Balance_Sheet_Qtr!Z35 -> 0 | V35: =Balance_Sheet_Qtr!AE35 -> 0 | W35: =Balance_Sheet_Qtr!AJ35 -> 0 | X35: =Balance_Sheet_Qtr!AO35 -> 0 | Y35: =Balance_Sheet_Qtr!AT35 -> 0 | Z35: =Balance_Sheet_Qtr!AY35 -> 0 | AA35: =Balance_Sheet_Qtr!BD35 -> 0 | AB35: =Balance_Sheet_Qtr!BI35 -> 0 | AC35: =AB35 -> 0 | AD35: =AC35 -> 0 | AE35: =AD35 -> 0 | AF35: =AE35 -> 0
A36: =Balance_Sheet_Qtr!A36 -> Other Current Liabilities | B36: 0 | C36: 0 | D36: 0 | E36: 0 | F36: 0 | G36: 0 | H36: 0 | I36: 0 | J36: 0 | K36: 0 | L36: 0 | M36: 0 | N36: 0 | O36: 0 | P36: 0 | Q36: =Balance_Sheet_Qtr!F36 -> 0 | R36: =Balance_Sheet_Qtr!K36 -> 0 | S36: =Balance_Sheet_Qtr!P36 -> 0 | T36: =Balance_Sheet_Qtr!U36 -> 0 | U36: =Balance_Sheet_Qtr!Z36 -> 0 | V36: =Balance_Sheet_Qtr!AE36 -> 0 | W36: =Balance_Sheet_Qtr!AJ36 -> 0 | X36: =Balance_Sheet_Qtr!AO36 -> 0 | Y36: =Balance_Sheet_Qtr!AT36 -> 0 | Z36: =Balance_Sheet_Qtr!AY36 -> 0 | AA36: =Balance_Sheet_Qtr!BD36 -> 0 | AB36: =Balance_Sheet_Qtr!BI36 -> 0 | AC36: =AB36 -> 0 | AD36: =AC36 -> 0 | AE36: =AD36 -> 0 | AF36: =AE36 -> 0
A37: =Balance_Sheet_Qtr!A37 -> Total Current Liabilities | B37: =SUM(B31:B36) -> 18289 | C37: =SUM(C31:C36) -> 20486 | D37: =SUM(D31:D36) -> 19810 | E37: =SUM(E31:E36) -> 18448 | F37: =SUM(F31:F36) -> 20835 | G37: =SUM(G31:G36) -> 28188 | H37: =SUM(H31:H36) -> 29701 | I37: =SUM(I31:I36) -> 31538 | ... P37: =SUM(P31:P36) -> 56717 | Q37: =Balance_Sheet_Qtr!F37 -> 50412 | R37: =Balance_Sheet_Qtr!K37 -> 50134 | S37: =Balance_Sheet_Qtr!P37 -> 56269 | T37: =Balance_Sheet_Qtr!U37 -> 81590 | U37: =Balance_Sheet_Qtr!Z37 -> 97312 | V37: =Balance_Sheet_Qtr!AE37 -> 87280 | W37: =Balance_Sheet_Qtr!AJ37 -> 81992 | X37: =Balance_Sheet_Qtr!AO37 -> 90052 | Y37: =Balance_Sheet_Qtr!AT37 -> 95827 | Z37: =Balance_Sheet_Qtr!AY37 -> 97078 | AA37: =Balance_Sheet_Qtr!BD37 -> 108115 | AB37: =Balance_Sheet_Qtr!BI37 -> 99509.927 | AC37: =SUM(AC31:AC36) -> 98180.964 | AD37: =SUM(AD31:AD36) -> 98388.242 | AE37: =SUM(AE31:AE36) -> 98507.757 | AF37: =SUM(AF31:AF36) -> 99135.299
A39: =Balance_Sheet_Qtr!A39 -> Noncurrent Liabilities
A40: =Balance_Sheet_Qtr!A40 -> Deferred Income Taxes | B40: 0 | C40: 177 | D40: 0 | E40: 0 | F40: 1090 | G40: 2067 | H40: 0 | I40: 1190 | J40: 0 | K40: 0 | L40: 0 | M40: 0 | N40: 0 | O40: 0 | P40: 0 | Q40: =Balance_Sheet_Qtr!F40 -> 2392 | R40: =Balance_Sheet_Qtr!K40 -> 1338 | S40: =Balance_Sheet_Qtr!P40 -> 1839 | T40: =Balance_Sheet_Qtr!U40 -> 1736 | U40: =Balance_Sheet_Qtr!Z40 -> 413 | V40: =Balance_Sheet_Qtr!AE40 -> 1010 | W40: =Balance_Sheet_Qtr!AJ40 -> 218 | X40: =Balance_Sheet_Qtr!AO40 -> 230 | Y40: =Balance_Sheet_Qtr!AT40 -> 229 | Z40: =Balance_Sheet_Qtr!AY40 -> 122 | AA40: =Balance_Sheet_Qtr!BD40 -> 216 | AB40: =Balance_Sheet_Qtr!BI40 -> 216 | AC40: =AB40 -> 216 | AD40: =AC40 -> 216 | AE40: =AD40 -> 216 | AF40: =AE40 -> 216
A41: =Balance_Sheet_Qtr!A41 -> Accrued Retiree Health Care | B41: 5152 | C41: 5367 | D41: 5434 | E41: 5745 | F41: 5959 | G41: 5989 | H41: 7671 | I41: 7007 | J41: 7322 | K41: 7049 | L41: 8025 | M41: 7520 | N41: 7528 | O41: 6528 | P41: 6802 | Q41: =Balance_Sheet_Qtr!F41 -> 6616 | R41: =Balance_Sheet_Qtr!K41 -> 5916 | S41: =Balance_Sheet_Qtr!P41 -> 5545 | T41: =Balance_Sheet_Qtr!U41 -> 4584 | U41: =Balance_Sheet_Qtr!Z41 -> 4540 | V41: =Balance_Sheet_Qtr!AE41 -> 4137 | W41: =Balance_Sheet_Qtr!AJ41 -> 3528 | X41: =Balance_Sheet_Qtr!AO41 -> 2503 | Y41: =Balance_Sheet_Qtr!AT41 -> 2233 | Z41: =Balance_Sheet_Qtr!AY41 -> 2176 | AA41: =Balance_Sheet_Qtr!BD41 -> 2091 | AB41: =Balance_Sheet_Qtr!BI41 -> 2071 | AC41: =AB41-Cash_Flow_Annual!AC89 -> 2051 | AD41: =AC41-Cash_Flow_Annual!AD89 -> 2031 | AE41: =AD41-Cash_Flow_Annual!AE89 -> 2011 | AF41: =AE41-Cash_Flow_Annual!AF89 -> 1991
